{
  "type": "Feature",
  "properties": {
    "gn:admin1_code":"39.0",
    "gn:asciiname":"Coc Cong",
    "gn:country_code":"VN",
    "gn:dem":324,
    "gn:feature_class":"P",
    "gn:feature_code":"PPL",
    "gn:name":"C\u00f3c C\u00f4ng",
    "gn:population":0,
    "gn:timezone":"Asia/Ho_Chi_Minh",
    "iso:country":"VN",
    "wof:name":"Coc Cong",
    "wof:placetype":"locality"
},
  "geometry": {"coordinates":[106.53333000000001,21.98333],"type":"Point"}
}