{
  "type": "Feature",
  "properties": {
    "iso:country":"VN",
    "name:und_x_variant":[
        "Cho Ben Tranh"
    ],
    "qs:gn_country":"VN",
    "qs:gn_fcode":"PPL",
    "qs:gn_pop":0,
    "qs:name":"B\u1ebfn Tranh",
    "qs:name_adm0":"Vietnam",
    "qs:name_adm1":"Tien Giang",
    "qs:photos":201,
    "qs:photos_1k":41,
    "qs:photos_9k":1,
    "qs:photos_9r":4,
    "qs:photos_all":201,
    "qs:photos_sr":4,
    "qs:placetype":"Town",
    "qs:pop_sr":"5",
    "qs:woe_adm0":23424984,
    "wof:name":"B\u1ebfn Tranh",
    "wof:placetype":"locality"
},
  "geometry": {"coordinates":[106.34999999999999,10.41667],"type":"Point"}
}