{
  "type": "Feature",
  "properties": {
    "gn:admin1_code":"2.0",
    "gn:asciiname":"Coue Zueuil",
    "gn:country_code":"VN",
    "gn:dem":288,
    "gn:feature_class":"P",
    "gn:feature_code":"PPL",
    "gn:name":"Coue Zueuil",
    "gn:population":0,
    "gn:timezone":"Asia/Ho_Chi_Minh",
    "iso:country":"VN",
    "wof:name":"Coue Zueuil",
    "wof:placetype":"locality"
},
  "geometry": {"coordinates":[105.83333,22.43333],"type":"Point"}
}