{
  "type": "Feature",
  "properties": {
    "gn:admin1_code":"52.0",
    "gn:asciiname":"Xom Sau",
    "gn:country_code":"VN",
    "gn:dem":9,
    "gn:feature_class":"P",
    "gn:feature_code":"PPL",
    "gn:name":"X\u00f3m S\u00e1u",
    "gn:population":0,
    "gn:timezone":"Asia/Ho_Chi_Minh",
    "iso:country":"VN",
    "name:vie_x_preferred":[
        "X\u00f3m S\u00e1u"
    ],
    "name:vie_x_variant":[
        "X\u00f3m 6"
    ],
    "wof:name":"Xom Sau",
    "wof:placetype":"locality"
},
  "geometry": {"coordinates":[105.65483,18.49478],"type":"Point"}
}