{
  "type": "Feature",
  "properties": {
    "gn:admin1_code":"89.0",
    "gn:asciiname":"Nam Cum",
    "gn:country_code":"VN",
    "gn:dem":314,
    "gn:feature_class":"P",
    "gn:feature_code":"PPL",
    "gn:name":"N\u1eadm C\u1ee7m",
    "gn:population":0,
    "gn:timezone":"Asia/Ho_Chi_Minh",
    "iso:country":"VN",
    "name:vie_x_preferred":[
        "N\u1eadm C\u1ee7m"
    ],
    "wof:name":"Nam Cum",
    "wof:placetype":"locality"
},
  "geometry": {"coordinates":[102.61444,22.48486],"type":"Point"}
}