{
  "type": "Feature",
  "properties": {
    "gn:admin1_code":"66.0",
    "gn:asciiname":"Vien Trinh",
    "gn:country_code":"VN",
    "gn:dem":4,
    "gn:feature_class":"P",
    "gn:feature_code":"PPL",
    "gn:name":"Vi\u1ec5n Trinh",
    "gn:population":0,
    "gn:timezone":"Asia/Ho_Chi_Minh",
    "iso:country":"VN",
    "name:vie_x_preferred":[
        "Vi\u1ec5n Trinh"
    ],
    "wof:name":"Vien Trinh",
    "wof:placetype":"locality"
},
  "geometry": {"coordinates":[107.73738,16.45594],"type":"Point"}
}