{
  "type": "Feature",
  "properties": {
    "gn:admin1_code":"33.0",
    "gn:asciiname":"Tan Lam",
    "gn:country_code":"VN",
    "gn:dem":44,
    "gn:feature_class":"P",
    "gn:feature_code":"PPL",
    "gn:name":"T\u00e2n L\u00e2m",
    "gn:population":0,
    "gn:timezone":"Asia/Ho_Chi_Minh",
    "iso:country":"VN",
    "name:vie_x_preferred":[
        "T\u00e2n L\u00e2m"
    ],
    "wof:name":"Tan Lam",
    "wof:placetype":"locality"
},
  "geometry": {"coordinates":[106.11274,11.70351],"type":"Point"}
}