{
  "type": "Feature",
  "properties": {
    "gn:admin1_code":"47.0",
    "gn:asciiname":"Thon Hai",
    "gn:country_code":"VN",
    "gn:dem":27,
    "gn:feature_class":"P",
    "gn:feature_code":"PPL",
    "gn:name":"Th\u00f4n Hai",
    "gn:population":0,
    "gn:timezone":"Asia/Ho_Chi_Minh",
    "iso:country":"VN",
    "name:vie_x_preferred":[
        "Th\u00f4n Hai"
    ],
    "name:vie_x_variant":[
        "Th\u00f4n 2"
    ],
    "wof:name":"Thon Hai",
    "wof:placetype":"locality"
},
  "geometry": {"coordinates":[107.72524,10.71729],"type":"Point"}
}