{
  "type": "Feature",
  "properties": {
    "gn:admin1_code":"71.0",
    "gn:asciiname":"Xom Nguon",
    "gn:country_code":"VN",
    "gn:dem":17,
    "gn:feature_class":"P",
    "gn:feature_code":"PPL",
    "gn:name":"X\u00f3m Ngu\u1ed9n",
    "gn:population":0,
    "gn:timezone":"Asia/Ho_Chi_Minh",
    "iso:country":"VN",
    "name:vie_x_preferred":[
        "X\u00f3m Ngu\u1ed9n"
    ],
    "wof:name":"Xom Nguon",
    "wof:placetype":"locality"
},
  "geometry": {"coordinates":[106.24678,21.41895],"type":"Point"}
}