{
  "type": "Feature",
  "properties": {
    "gn:admin1_code":"88.0",
    "gn:asciiname":"Thien An",
    "gn:country_code":"VN",
    "gn:dem":670,
    "gn:feature_class":"P",
    "gn:feature_code":"PPL",
    "gn:name":"Thi\u1ec7n An",
    "gn:population":0,
    "gn:timezone":"Asia/Ho_Chi_Minh",
    "iso:country":"VN",
    "name:vie_x_preferred":[
        "Thi\u1ec7n An"
    ],
    "wof:name":"Thien An",
    "wof:placetype":"locality"
},
  "geometry": {"coordinates":[108.26548,12.8976],"type":"Point"}
}