{
  "type": "Feature",
  "properties": {
    "gn:admin1_code":"63.0",
    "gn:asciiname":"Trang Dien",
    "gn:country_code":"VN",
    "gn:dem":88,
    "gn:feature_class":"P",
    "gn:feature_code":"PPL",
    "gn:name":"Trang \u0110i\u1ec1n",
    "gn:population":0,
    "gn:timezone":"Asia/Ho_Chi_Minh",
    "iso:country":"VN",
    "wof:name":"Trang Dien",
    "wof:placetype":"locality"
},
  "geometry": {"coordinates":[108.66667,14.86667],"type":"Point"}
}