{
  "type": "Feature",
  "properties": {
    "gn:admin1_code":"24.0",
    "gn:asciiname":"Ap Long Khot",
    "gn:cc2":"VN",
    "gn:country_code":"VN",
    "gn:dem":6,
    "gn:feature_class":"P",
    "gn:feature_code":"PPL",
    "gn:name":"\u1ea4p Long Kh\u1ed1t",
    "gn:population":0,
    "gn:timezone":"Asia/Ho_Chi_Minh",
    "iso:country":"VN",
    "name:und_x_variant":[
        "Tuyen Binh",
        "Long Khot",
        "Long Khoi",
        "\u1ea4p Long Kh\u1ed1t"
    ],
    "wof:name":"Ap Long Khot",
    "wof:placetype":"locality"
},
  "geometry": {"coordinates":[105.84999999999999,10.91667],"type":"Point"}
}