{
  "type": "Feature",
  "properties": {
    "gn:admin1_code":"68.0",
    "gn:asciiname":"Hong Thai",
    "gn:country_code":"VN",
    "gn:dem":31,
    "gn:feature_class":"P",
    "gn:feature_code":"PPL",
    "gn:name":"H\u1ed3ng Th\u00e1i",
    "gn:population":0,
    "gn:timezone":"Asia/Ho_Chi_Minh",
    "iso:country":"VN",
    "name:nld_x_preferred":[
        "H\u1ed3ng Th\u00e1i"
    ],
    "name:vie_x_preferred":[
        "H\u1ed3ng Th\u00e1i"
    ],
    "wof:name":"Hong Thai",
    "wof:placetype":"locality"
},
  "geometry": {"coordinates":[105.18092,21.89771],"type":"Point"}
}