{
  "type": "Feature",
  "properties": {
    "gn:admin1_code":"49.0",
    "gn:asciiname":"Ma Lin Mot",
    "gn:country_code":"VN",
    "gn:dem":171,
    "gn:feature_class":"P",
    "gn:feature_code":"PPL",
    "gn:name":"Ma Lin M\u1ed9t",
    "gn:population":0,
    "gn:timezone":"Asia/Ho_Chi_Minh",
    "iso:country":"VN",
    "name:vie_x_preferred":[
        "Ma Lin M\u1ed9t"
    ],
    "name:vie_x_variant":[
        "Ma Lin 1"
    ],
    "wof:name":"Ma Lin Mot",
    "wof:placetype":"locality"
},
  "geometry": {"coordinates":[108.45090999999999,13.49476],"type":"Point"}
}