{
  "type": "Feature",
  "properties": {
    "gn:admin1_code":"34.0",
    "gn:asciiname":"Bach Bao",
    "gn:cc2":"VN",
    "gn:country_code":"VN",
    "gn:dem":11,
    "gn:feature_class":"P",
    "gn:feature_code":"PPL",
    "gn:name":"B\u1ea1ch B\u00e0o",
    "gn:population":0,
    "gn:timezone":"Asia/Ho_Chi_Minh",
    "iso:country":"VN",
    "name:und_x_variant":[
        "Bach Bae",
        "B\u1ea1ch B\u00e0o"
    ],
    "wof:name":"Bach Bao",
    "wof:placetype":"locality"
},
  "geometry": {"coordinates":[105.61667,19.63333],"type":"Point"}
}