{
  "type": "Feature",
  "properties": {
    "gn:admin1_code":"52.0",
    "gn:asciiname":"Dong Bui",
    "gn:country_code":"VN",
    "gn:dem":24,
    "gn:feature_class":"P",
    "gn:feature_code":"PPL",
    "gn:name":"\u0110\u1ed3ng B\u1ee5i",
    "gn:population":0,
    "gn:timezone":"Asia/Ho_Chi_Minh",
    "iso:country":"VN",
    "name:vie_x_preferred":[
        "\u0110\u1ed3ng B\u1ee5i"
    ],
    "wof:name":"Dong Bui",
    "wof:placetype":"locality"
},
  "geometry": {"coordinates":[105.80072,18.09561],"type":"Point"}
}