{
  "type": "Feature",
  "properties": {
    "gn:admin1_code":"44.0",
    "gn:asciiname":"Gia Trung",
    "gn:country_code":"VN",
    "gn:dem":14,
    "gn:feature_class":"P",
    "gn:feature_code":"PPL",
    "gn:name":"Gia Trung",
    "gn:population":0,
    "gn:timezone":"Asia/Ho_Chi_Minh",
    "iso:country":"VN",
    "name:vie_x_preferred":[
        "Gia Trung"
    ],
    "wof:name":"Gia Trung",
    "wof:placetype":"locality"
},
  "geometry": {"coordinates":[105.76832,21.20101],"type":"Point"}
}