{
  "type": "Feature",
  "properties": {
    "gn:admin1_code":"58.0",
    "gn:asciiname":"Binh Thuan",
    "gn:country_code":"VN",
    "gn:dem":8,
    "gn:feature_class":"P",
    "gn:feature_code":"PPL",
    "gn:name":"B\u00ecnh Thu\u1eadn",
    "gn:population":0,
    "gn:timezone":"Asia/Ho_Chi_Minh",
    "iso:country":"VN",
    "name:vie_x_preferred":[
        "B\u00ecnh Thu\u1eadn"
    ],
    "wof:name":"Binh Thuan",
    "wof:placetype":"locality"
},
  "geometry": {"coordinates":[105.63981,18.82377],"type":"Point"}
}