{
  "type": "Feature",
  "properties": {
    "gn:admin1_code":"60.0",
    "gn:asciiname":"Thon Phu Tho",
    "gn:country_code":"VN",
    "gn:dem":-9999,
    "gn:feature_class":"P",
    "gn:feature_code":"PPL",
    "gn:name":"Th\u00f4n Ph\u00fa Th\u1ecd",
    "gn:population":0,
    "gn:timezone":"Asia/Ho_Chi_Minh",
    "iso:country":"VN",
    "name:und_x_variant":[
        "Phu Tho",
        "Th\u00f4n Ph\u00fa Th\u1ecd"
    ],
    "wof:name":"Thon Phu Tho",
    "wof:placetype":"locality"
},
  "geometry": {"coordinates":[109.03333000000001,11.53333],"type":"Point"}
}