{
  "type": "Feature",
  "properties": {
    "gn:admin1_code":"16.0",
    "gn:asciiname":"Dong Tranh",
    "gn:country_code":"VN",
    "gn:dem":73,
    "gn:feature_class":"P",
    "gn:feature_code":"PPL",
    "gn:name":"D\u1ed3ng Tranh",
    "gn:population":0,
    "gn:timezone":"Asia/Ho_Chi_Minh",
    "iso:country":"VN",
    "wof:name":"Dong Tranh",
    "wof:placetype":"locality"
},
  "geometry": {"coordinates":[105.71666999999999,20.58333],"type":"Point"}
}