{
  "type": "Feature",
  "properties": {
    "gn:admin1_code":"49.0",
    "gn:asciiname":"Ban To Khe",
    "gn:country_code":"VN",
    "gn:dem":162,
    "gn:feature_class":"P",
    "gn:feature_code":"PPL",
    "gn:name":"B\u1ea3n T\u01a1 Kh\u1ebf",
    "gn:population":0,
    "gn:timezone":"Asia/Ho_Chi_Minh",
    "iso:country":"VN",
    "name:vie_x_preferred":[
        "B\u1ea3n T\u01a1 Kh\u1ebf"
    ],
    "wof:name":"Ban To Khe",
    "wof:placetype":"locality"
},
  "geometry": {"coordinates":[108.49250000000001,13.40821],"type":"Point"}
}