{
  "type": "Feature",
  "properties": {
    "gn:admin1_code":"34.0",
    "gn:asciiname":"Muong Ly",
    "gn:country_code":"VN",
    "gn:dem":388,
    "gn:feature_class":"P",
    "gn:feature_code":"PPL",
    "gn:name":"Muong Ly",
    "gn:population":0,
    "gn:timezone":"Asia/Ho_Chi_Minh",
    "iso:country":"VN",
    "name:und_x_variant":[
        "Auc Poh",
        "Muang Ly",
        "Muong Ly"
    ],
    "wof:name":"Muong Ly",
    "wof:placetype":"locality"
},
  "geometry": {"coordinates":[104.78333000000001,20.55],"type":"Point"}
}