{
  "type": "Feature",
  "properties": {
    "gn:admin1_code":"52.0",
    "gn:asciiname":"Tan Dua",
    "gn:country_code":"VN",
    "gn:dem":23,
    "gn:feature_class":"P",
    "gn:feature_code":"PPL",
    "gn:name":"T\u00e2n D\u1eeba",
    "gn:population":0,
    "gn:timezone":"Asia/Ho_Chi_Minh",
    "iso:country":"VN",
    "name:und_x_variant":[
        "Tnai Dua",
        "Tr\u1ea1i \u0110\u1eeba"
    ],
    "name:vie_x_preferred":[
        "T\u00e2n D\u1eeba"
    ],
    "wof:name":"Tan Dua",
    "wof:placetype":"locality"
},
  "geometry": {"coordinates":[105.78815,18.10591],"type":"Point"}
}