{
  "type": "Feature",
  "properties": {
    "gn:admin1_code":"3.0",
    "gn:asciiname":"Giong Ngai",
    "gn:cc2":"VN",
    "gn:country_code":"VN",
    "gn:dem":0,
    "gn:feature_class":"P",
    "gn:feature_code":"PPL",
    "gn:name":"Gi\u1ed3ng Ng\u1ea3i",
    "gn:population":0,
    "gn:timezone":"Asia/Ho_Chi_Minh",
    "iso:country":"VN",
    "name:und_x_variant":[
        "Ng\u1ea3i",
        "Gi\u1ed3ng Ng\u1ea3i"
    ],
    "wof:name":"Giong Ngai",
    "wof:placetype":"locality"
},
  "geometry": {"coordinates":[106.54833000000001,9.93306],"type":"Point"}
}