{
  "type": "Feature",
  "properties": {
    "gn:admin1_code":"45.0",
    "gn:asciiname":"Lien Loc",
    "gn:country_code":"VN",
    "gn:dem":209,
    "gn:feature_class":"P",
    "gn:feature_code":"PPL",
    "gn:name":"Li\u00ean L\u1ed9c",
    "gn:population":0,
    "gn:timezone":"Asia/Ho_Chi_Minh",
    "iso:country":"VN",
    "name:vie_x_preferred":[
        "Li\u00ean L\u1ed9c"
    ],
    "wof:name":"Lien Loc",
    "wof:placetype":"locality"
},
  "geometry": {"coordinates":[107.24266,10.74493],"type":"Point"}
}