{
  "type": "Feature",
  "properties": {
    "gn:admin1_code":"72.0",
    "gn:asciiname":"Tong Neng",
    "gn:country_code":"VN",
    "gn:dem":138,
    "gn:feature_class":"P",
    "gn:feature_code":"PPL",
    "gn:name":"T\u1ed5ng N\u1ebbng",
    "gn:population":0,
    "gn:timezone":"Asia/Ho_Chi_Minh",
    "iso:country":"VN",
    "name:vie_x_preferred":[
        "T\u1ed5ng N\u1ebbng"
    ],
    "wof:name":"Tong Neng",
    "wof:placetype":"locality"
},
  "geometry": {"coordinates":[105.8664,22.15366],"type":"Point"}
}