{
  "type": "Feature",
  "properties": {
    "gn:admin1_code":"64.0",
    "gn:asciiname":"Ba Ngay",
    "gn:country_code":"VN",
    "gn:dem":214,
    "gn:feature_class":"P",
    "gn:feature_code":"PPL",
    "gn:name":"Ba Ng\u00e1y",
    "gn:population":0,
    "gn:timezone":"Asia/Ho_Chi_Minh",
    "iso:country":"VN",
    "name:und_x_variant":[
        "Ba Noai"
    ],
    "name:vie_x_preferred":[
        "Ba Ng\u00e1y"
    ],
    "wof:name":"Ba Ngay",
    "wof:placetype":"locality"
},
  "geometry": {"coordinates":[106.92285,16.50697000000001],"type":"Point"}
}