{
  "type": "Feature",
  "properties": {
    "gn:admin1_code":"66.0",
    "gn:asciiname":"Thon Vinh Ve",
    "gn:country_code":"VN",
    "gn:dem":3,
    "gn:feature_class":"P",
    "gn:feature_code":"PPL",
    "gn:name":"Th\u00f4n V\u0129nh V\u1ec7",
    "gn:population":0,
    "gn:timezone":"Asia/Ho_Chi_Minh",
    "iso:country":"VN",
    "name:und_x_variant":[
        "Vinh Ve",
        "Th\u00f4n V\u0129nh V\u1ec7"
    ],
    "wof:name":"Thon Vinh Ve",
    "wof:placetype":"locality"
},
  "geometry": {"coordinates":[107.63333,16.48333],"type":"Point"}
}