{
  "type": "Feature",
  "properties": {
    "gn:admin1_code":"69.0",
    "gn:asciiname":"Tan Thanh",
    "gn:country_code":"VN",
    "gn:dem":2,
    "gn:feature_class":"P",
    "gn:feature_code":"PPL",
    "gn:name":"T\u00e2n Th\u1ea1nh",
    "gn:population":0,
    "gn:timezone":"Asia/Ho_Chi_Minh",
    "iso:country":"VN",
    "name:nld_x_preferred":[
        "Tan Thanh"
    ],
    "name:und_x_variant":[
        "\u1ea4p T\u00e2n Th\u1ea1nh"
    ],
    "name:vie_x_preferred":[
        "T\u00e2n Th\u1ea1nh"
    ],
    "wof:name":"Tan Thanh",
    "wof:placetype":"locality"
},
  "geometry": {"coordinates":[105.92693,10.21692],"type":"Point"}
}