{
  "type": "Feature",
  "properties": {
    "gn:admin1_code":"90.0",
    "gn:asciiname":"Goc Diep",
    "gn:country_code":"VN",
    "gn:dem":159,
    "gn:feature_class":"P",
    "gn:feature_code":"PPL",
    "gn:name":"G\u1ed1c \u0110i\u1ec7p",
    "gn:population":0,
    "gn:timezone":"Asia/Ho_Chi_Minh",
    "iso:country":"VN",
    "name:und_x_variant":[
        "G\u00f4c Di\u1ec7p"
    ],
    "name:vie_x_preferred":[
        "G\u1ed1c \u0110i\u1ec7p"
    ],
    "wof:name":"Goc Diep",
    "wof:placetype":"locality"
},
  "geometry": {"coordinates":[104.51357,22.31951],"type":"Point"}
}