{
  "type": "Feature",
  "properties": {
    "gn:admin1_code":"75.0",
    "gn:asciiname":"Binh Phuoc Ba Khu",
    "gn:country_code":"VN",
    "gn:dem":34,
    "gn:feature_class":"P",
    "gn:feature_code":"PPL",
    "gn:name":"B\u00ecnh Ph\u01b0\u1edbc Ba Khu",
    "gn:population":0,
    "gn:timezone":"Asia/Ho_Chi_Minh",
    "iso:country":"VN",
    "name:vie_x_preferred":[
        "B\u00ecnh Ph\u01b0\u1edbc Ba Khu"
    ],
    "wof:name":"Binh Phuoc Ba Khu",
    "wof:placetype":"locality"
},
  "geometry": {"coordinates":[106.71723,10.97465],"type":"Point"}
}