{
  "type": "Feature",
  "properties": {
    "gn:admin1_code":"88.0",
    "gn:asciiname":"Dang Rit",
    "gn:country_code":"VN",
    "gn:dem":1466,
    "gn:feature_class":"P",
    "gn:feature_code":"PPL",
    "gn:name":"\u0110\u0103ng R\u00edt",
    "gn:population":0,
    "gn:timezone":"Asia/Ho_Chi_Minh",
    "iso:country":"VN",
    "name:vie_x_preferred":[
        "\u0110\u0103ng R\u00edt"
    ],
    "wof:name":"Dang Rit",
    "wof:placetype":"locality"
},
  "geometry": {"coordinates":[108.3908,12.02407],"type":"Point"}
}