{
  "type": "Feature",
  "properties": {
    "gn:admin1_code":"87.0",
    "gn:asciiname":"Binh Yen B",
    "gn:country_code":"VN",
    "gn:dem":2,
    "gn:feature_class":"P",
    "gn:feature_code":"PPL",
    "gn:name":"B\u00ecnh Y\u00ean B",
    "gn:population":0,
    "gn:timezone":"Asia/Ho_Chi_Minh",
    "iso:country":"VN",
    "name:vie_x_preferred":[
        "B\u00ecnh Y\u00ean B"
    ],
    "wof:name":"Binh Yen B",
    "wof:placetype":"locality"
},
  "geometry": {"coordinates":[105.71536,10.07148],"type":"Point"}
}