{
  "type": "Feature",
  "properties": {
    "gn:admin1_code":"68.0",
    "gn:asciiname":"Ngoi Ne",
    "gn:country_code":"VN",
    "gn:dem":63,
    "gn:feature_class":"P",
    "gn:feature_code":"PPL",
    "gn:name":"Ng\u00f2i N\u00e9",
    "gn:population":0,
    "gn:timezone":"Asia/Ho_Chi_Minh",
    "iso:country":"VN",
    "name:vie_x_preferred":[
        "Ng\u00f2i N\u00e9"
    ],
    "wof:name":"Ngoi Ne",
    "wof:placetype":"locality"
},
  "geometry": {"coordinates":[105.38245999999999,22.32236],"type":"Point"}
}