{
  "type": "Feature",
  "properties": {
    "gn:admin1_code":"39.0",
    "gn:asciiname":"Dong",
    "gn:country_code":"VN",
    "gn:dem":277,
    "gn:feature_class":"P",
    "gn:feature_code":"PPL",
    "gn:name":"Dong",
    "gn:population":0,
    "gn:timezone":"Asia/Ho_Chi_Minh",
    "iso:country":"VN",
    "name:ara_x_preferred":[
        "\u062f\u0648\u0646\u063a"
    ],
    "name:ben_x_preferred":[
        "\u09a1\u0982"
    ],
    "name:ceb_x_preferred":[
        "Dong"
    ],
    "name:dan_x_preferred":[
        "Dong"
    ],
    "name:deu_x_preferred":[
        "Dong"
    ],
    "name:ell_x_preferred":[
        "\u039d\u03c4\u03bf\u03bd\u03b3\u03ba"
    ],
    "name:fas_x_preferred":[
        "\u062f\u0648\u0646\u06af"
    ],
    "name:fin_x_preferred":[
        "Dong"
    ],
    "name:fra_x_preferred":[
        "Dong"
    ],
    "name:heb_x_preferred":[
        "\u05d3\u05d5\u05e0\u05d2"
    ],
    "name:hun_x_preferred":[
        "Dong"
    ],
    "name:ido_x_preferred":[
        "Dong"
    ],
    "name:ind_x_preferred":[
        "Dong"
    ],
    "name:ita_x_preferred":[
        "Dong"
    ],
    "name:nld_x_preferred":[
        "Dong"
    ],
    "name:nor_x_preferred":[
        "Dong"
    ],
    "name:pol_x_preferred":[
        "Dong"
    ],
    "name:por_x_preferred":[
        "Dong"
    ],
    "name:spa_x_preferred":[
        "Dong"
    ],
    "name:swe_x_preferred":[
        "Dong"
    ],
    "name:tur_x_preferred":[
        "Dong"
    ],
    "name:ukr_x_preferred":[
        "\u0414\u043e\u043d\u0433"
    ],
    "name:und_x_variant":[
        "\u0110\u1ed3ng Vi"
    ],
    "name:urd_x_preferred":[
        "\u0688\u0627\u0646\u06af"
    ],
    "name:uzb_x_preferred":[
        "Dong"
    ],
    "name:vie_x_preferred":[
        "Dong"
    ],
    "wof:name":"Dong",
    "wof:placetype":"locality"
},
  "geometry": {"coordinates":[106.76667,21.86667],"type":"Point"}
}