{
  "type": "Feature",
  "properties": {
    "gn:admin1_code":"39.0",
    "gn:asciiname":"Dong",
    "gn:country_code":"VN",
    "gn:dem":277,
    "gn:feature_class":"P",
    "gn:feature_code":"PPL",
    "gn:name":"Dong",
    "gn:population":0,
    "gn:timezone":"Asia/Ho_Chi_Minh",
    "iso:country":"VN",
    "name:ceb_x_preferred":[
        "Dong"
    ],
    "name:dan_x_preferred":[
        "Dong"
    ],
    "name:deu_x_preferred":[
        "Dong"
    ],
    "name:fin_x_preferred":[
        "Dong"
    ],
    "name:fra_x_preferred":[
        "Dong"
    ],
    "name:heb_x_preferred":[
        "\u05d3\u05d5\u05e0\u05d2"
    ],
    "name:ido_x_preferred":[
        "Dong"
    ],
    "name:ita_x_preferred":[
        "Dong"
    ],
    "name:nld_x_preferred":[
        "Dong"
    ],
    "name:nor_x_preferred":[
        "Dong"
    ],
    "name:pol_x_preferred":[
        "Dong"
    ],
    "name:por_x_preferred":[
        "Dong"
    ],
    "name:spa_x_preferred":[
        "Dong"
    ],
    "name:swe_x_preferred":[
        "Dong"
    ],
    "name:tur_x_preferred":[
        "Dong"
    ],
    "name:und_x_variant":[
        "\u0110\u1ed3ng Vi"
    ],
    "name:uzb_x_preferred":[
        "Dong"
    ],
    "name:vie_x_preferred":[
        "Dong"
    ],
    "wof:name":"Dong",
    "wof:placetype":"locality"
},
  "geometry": {"coordinates":[106.76667,21.86667000000001],"type":"Point"}
}