{
  "type": "Feature",
  "properties": {
    "gn:admin1_code":"39.0",
    "gn:asciiname":"Dong",
    "gn:country_code":"VN",
    "gn:dem":277,
    "gn:feature_class":"P",
    "gn:feature_code":"PPL",
    "gn:name":"Dong",
    "gn:population":0,
    "gn:timezone":"Asia/Ho_Chi_Minh",
    "iso:country":"VN",
    "name:und_x_variant":[
        "\u0110\u1ed3ng Vi"
    ],
    "wof:name":"Dong",
    "wof:placetype":"locality"
},
  "geometry": {"coordinates":[106.76667,21.86667000000001],"type":"Point"}
}