{
  "type": "Feature",
  "properties": {
    "gn:admin1_code":"88.0",
    "gn:asciiname":"Ban Yun Roue",
    "gn:cc2":"VN",
    "gn:country_code":"VN",
    "gn:dem":747,
    "gn:feature_class":"P",
    "gn:feature_code":"PPL",
    "gn:name":"Ban Yun Rou\u00e9",
    "gn:population":0,
    "gn:timezone":"Asia/Ho_Chi_Minh",
    "iso:country":"VN",
    "name:und_x_variant":[
        "Buon Yun Roue",
        "Ban Yun Rou\u00e9"
    ],
    "wof:name":"Ban Yun Roue",
    "wof:placetype":"locality"
},
  "geometry": {"coordinates":[108.34999999999999,13.03333],"type":"Point"}
}