{
  "type": "Feature",
  "properties": {
    "gn:admin1_code":"49.0",
    "gn:asciiname":"Yen Lac",
    "gn:country_code":"VN",
    "gn:dem":184,
    "gn:feature_class":"P",
    "gn:feature_code":"PPL",
    "gn:name":"Y\u00ean L\u1ea1c",
    "gn:population":0,
    "gn:timezone":"Asia/Ho_Chi_Minh",
    "iso:country":"VN",
    "name:vie_x_preferred":[
        "Y\u00ean L\u1ea1c"
    ],
    "wof:name":"Yen Lac",
    "wof:placetype":"locality"
},
  "geometry": {"coordinates":[108.37048,13.45622],"type":"Point"}
}