{
  "type": "Feature",
  "properties": {
    "gn:admin1_code":"24.0",
    "gn:asciiname":"Ap Dao",
    "gn:country_code":"VN",
    "gn:dem":5,
    "gn:feature_class":"P",
    "gn:feature_code":"PPL",
    "gn:name":"\u1ea4p \u0110\u1ea1o",
    "gn:population":0,
    "gn:timezone":"Asia/Ho_Chi_Minh",
    "iso:country":"VN",
    "name:und_x_variant":[
        "X\u00f3m \u0110\u1ea1o"
    ],
    "name:vie_x_preferred":[
        "\u1ea4p \u0110\u1ea1o"
    ],
    "wof:name":"Ap Dao",
    "wof:placetype":"locality"
},
  "geometry": {"coordinates":[106.42161000000002,10.62227],"type":"Point"}
}