{
  "type": "Feature",
  "properties": {
    "gn:admin1_code":"52.0",
    "gn:asciiname":"Quyet Thang",
    "gn:country_code":"VN",
    "gn:dem":7,
    "gn:feature_class":"P",
    "gn:feature_code":"PPL",
    "gn:name":"Quy\u1ebft Th\u1eafng",
    "gn:population":0,
    "gn:timezone":"Asia/Ho_Chi_Minh",
    "iso:country":"VN",
    "name:vie_x_preferred":[
        "Quy\u1ebft Th\u1eafng"
    ],
    "wof:name":"Quyet Thang",
    "wof:placetype":"locality"
},
  "geometry": {"coordinates":[105.76882000000001,18.48066],"type":"Point"}
}