{
  "type": "Feature",
  "properties": {
    "gn:admin1_code":"86.0",
    "gn:asciiname":"Thanh Cong",
    "gn:country_code":"VN",
    "gn:dem":56,
    "gn:feature_class":"P",
    "gn:feature_code":"PPL",
    "gn:name":"Th\u00e0nh C\u00f4ng",
    "gn:population":0,
    "gn:timezone":"Asia/Ho_Chi_Minh",
    "iso:country":"VN",
    "name:vie_x_preferred":[
        "Th\u00e0nh C\u00f4ng"
    ],
    "wof:name":"Thanh Cong",
    "wof:placetype":"locality"
},
  "geometry": {"coordinates":[105.39232,21.49091],"type":"Point"}
}