{
  "type": "Feature",
  "properties": {
    "gn:admin1_code":"43.0",
    "gn:asciiname":"Bau Dien",
    "gn:country_code":"VN",
    "gn:dem":72,
    "gn:feature_class":"P",
    "gn:feature_code":"PPL",
    "gn:name":"B\u00e0u \u0110i\u1ec1n",
    "gn:population":0,
    "gn:timezone":"Asia/Ho_Chi_Minh",
    "iso:country":"VN",
    "name:vie_x_preferred":[
        "B\u00e0u \u0110i\u1ec1n"
    ],
    "wof:name":"Bau Dien",
    "wof:placetype":"locality"
},
  "geometry": {"coordinates":[107.12203999999998,11.32686],"type":"Point"}
}