{
  "type": "Feature",
  "properties": {
    "gn:admin1_code":"81.0",
    "gn:asciiname":"Dong Thien",
    "gn:country_code":"VN",
    "gn:dem":4,
    "gn:feature_class":"P",
    "gn:feature_code":"PPL",
    "gn:name":"\u0110\u00f4ng Thi\u1ec7n",
    "gn:population":0,
    "gn:timezone":"Asia/Ho_Chi_Minh",
    "iso:country":"VN",
    "name:vie_x_preferred":[
        "\u0110\u00f4ng Thi\u1ec7n"
    ],
    "wof:name":"Dong Thien",
    "wof:placetype":"locality"
},
  "geometry": {"coordinates":[106.10198,20.64817],"type":"Point"}
}