{
  "type": "Feature",
  "properties": {
    "gn:admin1_code":"1.0",
    "gn:asciiname":"To Binh",
    "gn:country_code":"VN",
    "gn:dem":12,
    "gn:feature_class":"P",
    "gn:feature_code":"PPL",
    "gn:name":"T\u00f4 B\u00ecnh",
    "gn:population":0,
    "gn:timezone":"Asia/Ho_Chi_Minh",
    "iso:country":"VN",
    "name:vie_x_preferred":[
        "T\u00f4 B\u00ecnh"
    ],
    "wof:name":"To Binh",
    "wof:placetype":"locality"
},
  "geometry": {"coordinates":[105.01502000000001,10.36336],"type":"Point"}
}