{
  "type": "Feature",
  "properties": {
    "gn:admin1_code":"34.0",
    "gn:asciiname":"Trung Xa",
    "gn:country_code":"VN",
    "gn:dem":7,
    "gn:feature_class":"P",
    "gn:feature_code":"PPL",
    "gn:name":"Trung X\u00e3",
    "gn:population":0,
    "gn:timezone":"Asia/Ho_Chi_Minh",
    "iso:country":"VN",
    "wof:name":"Trung Xa",
    "wof:placetype":"locality"
},
  "geometry": {"coordinates":[105.93333,19.85],"type":"Point"}
}