{
  "type": "Feature",
  "properties": {
    "gn:admin1_code":"77.0",
    "gn:asciiname":"Ngoc Hien",
    "gn:country_code":"VN",
    "gn:dem":0,
    "gn:feature_class":"P",
    "gn:feature_code":"PPLA2",
    "gn:name":"Ng\u1ecdc Hi\u1ec3n",
    "gn:population":0,
    "gn:timezone":"Asia/Ho_Chi_Minh",
    "iso:country":"VN",
    "name:vie_x_preferred":[
        "Ng\u1ecdc Hi\u1ec3n"
    ],
    "wof:name":"Ngoc Hien",
    "wof:placetype":"locality"
},
  "geometry": {"coordinates":[105.06021,8.65724],"type":"Point"}
}