{
  "type": "Feature",
  "properties": {
    "gn:admin1_code":"39.0",
    "gn:asciiname":"Dong Huong",
    "gn:country_code":"VN",
    "gn:dem":315,
    "gn:feature_class":"P",
    "gn:feature_code":"PPL",
    "gn:name":"\u0110\u1ed3ng H\u01b0\u1eddng",
    "gn:population":0,
    "gn:timezone":"Asia/Ho_Chi_Minh",
    "iso:country":"VN",
    "name:vie_x_preferred":[
        "\u0110\u1ed3ng H\u01b0\u1eddng"
    ],
    "wof:name":"Dong Huong",
    "wof:placetype":"locality"
},
  "geometry": {"coordinates":[106.30122,21.98139],"type":"Point"}
}