{
  "type": "Feature",
  "properties": {
    "gn:admin1_code":"76.0",
    "gn:asciiname":"Tek Xong",
    "gn:country_code":"VN",
    "gn:dem":148,
    "gn:feature_class":"P",
    "gn:feature_code":"PPL",
    "gn:name":"Tek Xong",
    "gn:population":0,
    "gn:timezone":"Asia/Ho_Chi_Minh",
    "iso:country":"VN",
    "name:und_x_variant":[
        "Bu Tek Xong"
    ],
    "wof:name":"Tek Xong",
    "wof:placetype":"locality"
},
  "geometry": {"coordinates":[107.02439,11.47371],"type":"Point"}
}