{
  "type": "Feature",
  "properties": {
    "gn:admin1_code":"52.0",
    "gn:asciiname":"Bac Thi",
    "gn:country_code":"VN",
    "gn:dem":7,
    "gn:feature_class":"P",
    "gn:feature_code":"PPL",
    "gn:name":"B\u1eafc Th\u1ecb",
    "gn:population":0,
    "gn:timezone":"Asia/Ho_Chi_Minh",
    "iso:country":"VN",
    "name:vie_x_preferred":[
        "B\u1eafc Th\u1ecb"
    ],
    "wof:name":"Bac Thi",
    "wof:placetype":"locality"
},
  "geometry": {"coordinates":[105.99445,18.25916],"type":"Point"}
}