{
  "type": "Feature",
  "properties": {
    "gn:admin1_code":"63.0",
    "gn:asciiname":"Lang Chai",
    "gn:country_code":"VN",
    "gn:dem":110,
    "gn:feature_class":"P",
    "gn:feature_code":"PPL",
    "gn:name":"L\u00e0ng Chai",
    "gn:population":0,
    "gn:timezone":"Asia/Ho_Chi_Minh",
    "iso:country":"VN",
    "name:und_x_variant":[
        "Li Bilem",
        "Ong Chai",
        "Li Blem",
        "\u00d4 Chai"
    ],
    "name:vie_x_preferred":[
        "L\u00e0ng Chai"
    ],
    "wof:name":"Lang Chai",
    "wof:placetype":"locality"
},
  "geometry": {"coordinates":[108.55595,14.81676],"type":"Point"}
}