{
  "type": "Feature",
  "properties": {
    "gn:admin1_code":"70.0",
    "gn:asciiname":"Cao Khanh",
    "gn:country_code":"VN",
    "gn:dem":225,
    "gn:feature_class":"P",
    "gn:feature_code":"PPL",
    "gn:name":"Cao Kh\u00e1nh",
    "gn:population":0,
    "gn:timezone":"Asia/Ho_Chi_Minh",
    "iso:country":"VN",
    "name:vie_x_preferred":[
        "Cao Kh\u00e1nh"
    ],
    "wof:name":"Cao Khanh",
    "wof:placetype":"locality"
},
  "geometry": {"coordinates":[104.84721,22.01002],"type":"Point"}
}