{
  "type": "Feature",
  "properties": {
    "gn:admin1_code":"32.0",
    "gn:asciiname":"Ban Bai Bong",
    "gn:country_code":"VN",
    "gn:dem":447,
    "gn:feature_class":"P",
    "gn:feature_code":"PPL",
    "gn:name":"B\u1ea3n B\u00e3i B\u00f4ng",
    "gn:population":0,
    "gn:timezone":"Asia/Ho_Chi_Minh",
    "iso:country":"VN",
    "name:vie_x_preferred":[
        "B\u1ea3n B\u00e3i B\u00f4ng"
    ],
    "wof:name":"Ban Bai Bong",
    "wof:placetype":"locality"
},
  "geometry": {"coordinates":[104.74254000000001,21.22706],"type":"Point"}
}