{
  "type": "Feature",
  "properties": {
    "gn:admin1_code":"68.0",
    "gn:asciiname":"Quy Mo",
    "gn:country_code":"VN",
    "gn:dem":35,
    "gn:feature_class":"P",
    "gn:feature_code":"PPL",
    "gn:name":"Quy M\u00f4",
    "gn:population":0,
    "gn:timezone":"Asia/Ho_Chi_Minh",
    "iso:country":"VN",
    "name:vie_x_preferred":[
        "Quy M\u00f4"
    ],
    "wof:name":"Quy Mo",
    "wof:placetype":"locality"
},
  "geometry": {"coordinates":[105.15913,21.93093],"type":"Point"}
}