{
  "type": "Feature",
  "properties": {
    "gn:admin1_code":"46.0",
    "gn:asciiname":"Trai Ong Cuoi",
    "gn:country_code":"VN",
    "gn:dem":417,
    "gn:feature_class":"P",
    "gn:feature_code":"PPL",
    "gn:name":"Tr\u1ea1i \u00d4ng Cu\u1ed9i",
    "gn:population":0,
    "gn:timezone":"Asia/Ho_Chi_Minh",
    "iso:country":"VN",
    "wof:name":"Trai Ong Cuoi",
    "wof:placetype":"locality"
},
  "geometry": {"coordinates":[108.96666999999999,14.53333],"type":"Point"}
}