{
  "type": "Feature",
  "properties": {
    "gn:admin1_code":"83.0",
    "gn:asciiname":"Quang Trung",
    "gn:country_code":"VN",
    "gn:dem":34,
    "gn:feature_class":"P",
    "gn:feature_code":"PPL",
    "gn:name":"Quang Trung",
    "gn:population":0,
    "gn:timezone":"Asia/Ho_Chi_Minh",
    "iso:country":"VN",
    "name:vie_x_preferred":[
        "Quang Trung"
    ],
    "wof:name":"Quang Trung",
    "wof:placetype":"locality"
},
  "geometry": {"coordinates":[105.1045,21.44183],"type":"Point"}
}