{
  "type": "Feature",
  "properties": {
    "gn:admin1_code":"21.0",
    "gn:asciiname":"Xom Hoc Hoa",
    "gn:cc2":"VN",
    "gn:country_code":"VN",
    "gn:dem":2,
    "gn:feature_class":"P",
    "gn:feature_code":"PPL",
    "gn:name":"X\u00f3m H\u1ed1c H\u00f2a",
    "gn:population":0,
    "gn:timezone":"Asia/Ho_Chi_Minh",
    "iso:country":"VN",
    "name:und_x_variant":[
        "H\u1ed1c H\u00f2a",
        "X\u00f3m H\u1ed1c H\u00f2a"
    ],
    "wof:name":"Xom Hoc Hoa",
    "wof:placetype":"locality"
},
  "geometry": {"coordinates":[105.14778,9.74944],"type":"Point"}
}