{
  "type": "Feature",
  "properties": {
    "gn:admin1_code":"82.0",
    "gn:asciiname":"Ninh Cuong Trai",
    "gn:country_code":"VN",
    "gn:dem":2,
    "gn:feature_class":"P",
    "gn:feature_code":"PPL",
    "gn:name":"Ninh C\u01b0\u1eddng Trai",
    "gn:population":0,
    "gn:timezone":"Asia/Ho_Chi_Minh",
    "iso:country":"VN",
    "wof:name":"Ninh Cuong Trai",
    "wof:placetype":"locality"
},
  "geometry": {"coordinates":[106.21666999999999,20.11667000000001],"type":"Point"}
}