{
  "type": "Feature",
  "properties": {
    "gn:admin1_code":"89.0",
    "gn:asciiname":"Ban Phieng Ly",
    "gn:country_code":"VN",
    "gn:dem":486,
    "gn:feature_class":"P",
    "gn:feature_code":"PPL",
    "gn:name":"B\u1ea3n Phi\u00eang Ly",
    "gn:population":0,
    "gn:timezone":"Asia/Ho_Chi_Minh",
    "iso:country":"VN",
    "name:vie_x_preferred":[
        "B\u1ea3n Phi\u00eang Ly"
    ],
    "wof:name":"Ban Phieng Ly",
    "wof:placetype":"locality"
},
  "geometry": {"coordinates":[103.7174,22.13605],"type":"Point"}
}