{
  "type": "Feature",
  "properties": {
    "gn:admin1_code":"69.0",
    "gn:asciiname":"Quang Binh",
    "gn:country_code":"VN",
    "gn:dem":5,
    "gn:feature_class":"P",
    "gn:feature_code":"PPL",
    "gn:name":"Quang B\u00ecnh",
    "gn:population":0,
    "gn:timezone":"Asia/Ho_Chi_Minh",
    "iso:country":"VN",
    "name:und_x_variant":[
        "\u1ea4p Quang B\u00ecnh"
    ],
    "name:vie_x_preferred":[
        "Quang B\u00ecnh"
    ],
    "wof:name":"Quang Binh",
    "wof:placetype":"locality"
},
  "geometry": {"coordinates":[106.15898,10.12824],"type":"Point"}
}