{
  "type": "Feature",
  "properties": {
    "gn:admin1_code":"72.0",
    "gn:asciiname":"Coc Nao",
    "gn:country_code":"VN",
    "gn:dem":231,
    "gn:feature_class":"P",
    "gn:feature_code":"PPL",
    "gn:name":"C\u1ed1c Nao",
    "gn:population":0,
    "gn:timezone":"Asia/Ho_Chi_Minh",
    "iso:country":"VN",
    "wof:name":"Coc Nao",
    "wof:placetype":"locality"
},
  "geometry": {"coordinates":[105.83638999999999,22.26708],"type":"Point"}
}