{
  "type": "Feature",
  "properties": {
    "gn:admin1_code":"88.0",
    "gn:asciiname":"Ban Khua",
    "gn:cc2":"VN",
    "gn:country_code":"VN",
    "gn:dem":559,
    "gn:feature_class":"P",
    "gn:feature_code":"PPL",
    "gn:name":"Ban Khua",
    "gn:population":0,
    "gn:timezone":"Asia/Ho_Chi_Minh",
    "iso:country":"VN",
    "name:und_x_variant":[
        "Buon Khua",
        "Ban Khua"
    ],
    "wof:name":"Ban Khua",
    "wof:placetype":"locality"
},
  "geometry": {"coordinates":[108.56667,12.51667],"type":"Point"}
}