{
  "type": "Feature",
  "properties": {
    "gn:admin1_code":"61.0",
    "gn:asciiname":"My Hoa",
    "gn:country_code":"VN",
    "gn:dem":7,
    "gn:feature_class":"P",
    "gn:feature_code":"PPL",
    "gn:name":"M\u1ef9 H\u00f3a",
    "gn:population":0,
    "gn:timezone":"Asia/Ho_Chi_Minh",
    "iso:country":"VN",
    "wof:name":"My Hoa",
    "wof:placetype":"locality"
},
  "geometry": {"coordinates":[109.25,12.93333],"type":"Point"}
}