{
  "type": "Feature",
  "properties": {
    "gn:admin1_code":"49.0",
    "gn:asciiname":"Plei Mrong Yo",
    "gn:country_code":"VN",
    "gn:dem":635,
    "gn:feature_class":"P",
    "gn:feature_code":"PPL",
    "gn:name":"Plei Mrong Y\u1ed1",
    "gn:population":0,
    "gn:timezone":"Asia/Ho_Chi_Minh",
    "iso:country":"VN",
    "name:und_x_variant":[
        "Plei Mrong"
    ],
    "name:vie_x_preferred":[
        "Plei Mrong Y\u1ed1"
    ],
    "wof:name":"Plei Mrong Yo",
    "wof:placetype":"locality"
},
  "geometry": {"coordinates":[107.88043999999999,14.16233],"type":"Point"}
}