{
  "type": "Feature",
  "properties": {
    "gn:admin1_code":"85.0",
    "gn:asciiname":"Na Zenh",
    "gn:country_code":"VN",
    "gn:dem":115,
    "gn:feature_class":"P",
    "gn:feature_code":"PPL",
    "gn:name":"Na Zenh",
    "gn:population":0,
    "gn:timezone":"Asia/Ho_Chi_Minh",
    "iso:country":"VN",
    "wof:name":"Na Zenh",
    "wof:placetype":"locality"
},
  "geometry": {"coordinates":[105.65000000000001,21.95],"type":"Point"}
}