{
  "type": "Feature",
  "properties": {
    "gn:admin1_code":"53.0",
    "gn:asciiname":"Lang Bua",
    "gn:country_code":"VN",
    "gn:dem":587,
    "gn:feature_class":"P",
    "gn:feature_code":"PPL",
    "gn:name":"L\u00e0ng Bua",
    "gn:population":0,
    "gn:timezone":"Asia/Ho_Chi_Minh",
    "iso:country":"VN",
    "wof:name":"Lang Bua",
    "wof:placetype":"locality"
},
  "geometry": {"coordinates":[105.09999999999999,20.86667000000001],"type":"Point"}
}