{
  "type": "Feature",
  "properties": {
    "gn:admin1_code":"30.0",
    "gn:asciiname":"Thon Coi",
    "gn:country_code":"VN",
    "gn:dem":60,
    "gn:feature_class":"P",
    "gn:feature_code":"PPL",
    "gn:name":"Th\u00f4n C\u01a1i",
    "gn:population":0,
    "gn:timezone":"Asia/Ho_Chi_Minh",
    "iso:country":"VN",
    "name:vie_x_preferred":[
        "Th\u00f4n C\u01a1i"
    ],
    "wof:name":"Thon Coi",
    "wof:placetype":"locality"
},
  "geometry": {"coordinates":[106.97111,21.10533],"type":"Point"}
}