{
  "type": "Feature",
  "properties": {
    "gn:admin1_code":"39.0",
    "gn:asciiname":"Ban Muong",
    "gn:country_code":"VN",
    "gn:dem":324,
    "gn:feature_class":"P",
    "gn:feature_code":"PPL",
    "gn:name":"B\u1ea3n Mu\u1ed1ng",
    "gn:population":0,
    "gn:timezone":"Asia/Ho_Chi_Minh",
    "iso:country":"VN",
    "name:vie_x_preferred":[
        "B\u1ea3n Mu\u1ed1ng"
    ],
    "wof:name":"Ban Muong",
    "wof:placetype":"locality"
},
  "geometry": {"coordinates":[106.31189000000001,21.97507],"type":"Point"}
}