{
  "type": "Feature",
  "properties": {
    "gn:admin1_code":"33.0",
    "gn:asciiname":"Bhum Ba Diet",
    "gn:country_code":"VN",
    "gn:dem":6,
    "gn:feature_class":"P",
    "gn:feature_code":"PPL",
    "gn:name":"Bhum Ba Diet",
    "gn:population":0,
    "gn:timezone":"Asia/Ho_Chi_Minh",
    "iso:country":"VN",
    "name:und_x_variant":[
        "B\u00e0 \u0110\u00e9t"
    ],
    "wof:name":"Bhum Ba Diet",
    "wof:placetype":"locality"
},
  "geometry": {"coordinates":[105.95,11.41667],"type":"Point"}
}