{
  "type": "Feature",
  "properties": {
    "gn:admin1_code":"32.0",
    "gn:asciiname":"Phieng Don",
    "gn:country_code":"VN",
    "gn:dem":350,
    "gn:feature_class":"P",
    "gn:feature_code":"PPL",
    "gn:name":"Phi\u00eang \u0110\u1ed3n",
    "gn:population":0,
    "gn:timezone":"Asia/Ho_Chi_Minh",
    "iso:country":"VN",
    "name:vie_x_preferred":[
        "Phi\u00eang \u0110\u1ed3n"
    ],
    "wof:name":"Phieng Don",
    "wof:placetype":"locality"
},
  "geometry": {"coordinates":[103.62341000000001,21.14829],"type":"Point"}
}