{
  "type": "Feature",
  "properties": {
    "gn:admin1_code":"43.0",
    "gn:asciiname":"Suoi Duc",
    "gn:country_code":"VN",
    "gn:dem":64,
    "gn:feature_class":"P",
    "gn:feature_code":"PPL",
    "gn:name":"Su\u1ed1i \u0110\u1ee5c",
    "gn:population":0,
    "gn:timezone":"Asia/Ho_Chi_Minh",
    "iso:country":"VN",
    "name:vie_x_preferred":[
        "Su\u1ed1i \u0110\u1ee5c"
    ],
    "wof:name":"Suoi Duc",
    "wof:placetype":"locality"
},
  "geometry": {"coordinates":[107.19504000000001,11.27379],"type":"Point"}
}