{
  "type": "Feature",
  "properties": {
    "gn:admin1_code":"50.0",
    "gn:asciiname":"Nam Kia",
    "gn:country_code":"VN",
    "gn:dem":769,
    "gn:feature_class":"P",
    "gn:feature_code":"PPL",
    "gn:name":"Nam Kia",
    "gn:population":0,
    "gn:timezone":"Asia/Ho_Chi_Minh",
    "iso:country":"VN",
    "wof:name":"Nam Kia",
    "wof:placetype":"locality"
},
  "geometry": {"coordinates":[104.48333,22.66667],"type":"Point"}
}