{
  "type": "Feature",
  "properties": {
    "gn:admin1_code":"52.0",
    "gn:asciiname":"Can Hoi",
    "gn:country_code":"VN",
    "gn:dem":20,
    "gn:feature_class":"P",
    "gn:feature_code":"PPL",
    "gn:name":"C\u1ea7n H\u1ecfi",
    "gn:population":0,
    "gn:timezone":"Asia/Ho_Chi_Minh",
    "iso:country":"VN",
    "name:und_x_variant":[
        "C\u1ea7n H\u01a1i Th\u00f4n"
    ],
    "name:vie_x_preferred":[
        "C\u1ea7n H\u1ecfi"
    ],
    "wof:name":"Can Hoi",
    "wof:placetype":"locality"
},
  "geometry": {"coordinates":[105.75597,18.13146],"type":"Point"}
}