{
  "type": "Feature",
  "properties": {
    "gn:admin1_code":"47.0",
    "gn:asciiname":"Xa Song Trao",
    "gn:country_code":"VN",
    "gn:dem":48,
    "gn:feature_class":"P",
    "gn:feature_code":"PPL",
    "gn:name":"X\u00e3 S\u00f4ng Trao",
    "gn:population":0,
    "gn:timezone":"Asia/Ho_Chi_Minh",
    "iso:country":"VN",
    "name:und_x_variant":[
        "S\u00f4ng Trao",
        "X\u00e3 S\u00f4ng Trao"
    ],
    "wof:name":"Xa Song Trao",
    "wof:placetype":"locality"
},
  "geometry": {"coordinates":[108.05,11.08333],"type":"Point"}
}