{
  "type": "Feature",
  "properties": {
    "gn:admin1_code":"89.0",
    "gn:asciiname":"Xa Trai",
    "gn:country_code":"VN",
    "gn:dem":459,
    "gn:feature_class":"P",
    "gn:feature_code":"PPL",
    "gn:name":"Xa Tr\u1ea3i",
    "gn:population":0,
    "gn:timezone":"Asia/Ho_Chi_Minh",
    "iso:country":"VN",
    "name:und_x_variant":[
        "S\u1ea3 Ch\u1ea3i"
    ],
    "name:vie_x_preferred":[
        "Xa Tr\u1ea3i"
    ],
    "wof:name":"Xa Trai",
    "wof:placetype":"locality"
},
  "geometry": {"coordinates":[103.28344,22.39959],"type":"Point"}
}