{
  "type": "Feature",
  "properties": {
    "gn:admin1_code":"32.0",
    "gn:asciiname":"Tin Toc",
    "gn:country_code":"VN",
    "gn:dem":788,
    "gn:feature_class":"P",
    "gn:feature_code":"PPL",
    "gn:name":"Tin T\u1ed1c",
    "gn:population":0,
    "gn:timezone":"Asia/Ho_Chi_Minh",
    "iso:country":"VN",
    "name:vie_x_preferred":[
        "Tin T\u1ed1c"
    ],
    "wof:name":"Tin Toc",
    "wof:placetype":"locality"
},
  "geometry": {"coordinates":[103.94401000000001,21.23664],"type":"Point"}
}