{
  "type": "Feature",
  "properties": {
    "gn:admin1_code":"52.0",
    "gn:asciiname":"Trai Trong",
    "gn:country_code":"VN",
    "gn:dem":20,
    "gn:feature_class":"P",
    "gn:feature_code":"PPL",
    "gn:name":"Tr\u1ea1i Trong",
    "gn:population":0,
    "gn:timezone":"Asia/Ho_Chi_Minh",
    "iso:country":"VN",
    "name:und_x_variant":[
        "Tr\u1ea1i N\u00e1i Trong"
    ],
    "name:vie_x_preferred":[
        "Tr\u1ea1i Trong"
    ],
    "wof:name":"Trai Trong",
    "wof:placetype":"locality"
},
  "geometry": {"coordinates":[105.7636,18.1775],"type":"Point"}
}