{
  "type": "Feature",
  "properties": {
    "gn:admin1_code":"84.0",
    "gn:asciiname":"Phu Qui",
    "gn:country_code":"VN",
    "gn:dem":3,
    "gn:feature_class":"P",
    "gn:feature_code":"PPL",
    "gn:name":"Ph\u00fa Qu\u00ed",
    "gn:population":0,
    "gn:timezone":"Asia/Ho_Chi_Minh",
    "iso:country":"VN",
    "name:und_x_variant":[
        "Tam Qui",
        "Phu Qui Ha",
        "Ph\u00fa Qu\u00ed"
    ],
    "wof:name":"Phu Qui",
    "wof:placetype":"locality"
},
  "geometry": {"coordinates":[108.55,15.58333],"type":"Point"}
}