{
  "type": "Feature",
  "properties": {
    "gn:admin1_code":"78.0",
    "gn:asciiname":"Cau Sap",
    "gn:country_code":"VN",
    "gn:dem":27,
    "gn:feature_class":"P",
    "gn:feature_code":"PPL",
    "gn:name":"C\u1ea7u S\u1eadp",
    "gn:population":0,
    "gn:timezone":"Asia/Ho_Chi_Minh",
    "iso:country":"VN",
    "name:vie_x_preferred":[
        "C\u1ea7u S\u1eadp"
    ],
    "wof:name":"Cau Sap",
    "wof:placetype":"locality"
},
  "geometry": {"coordinates":[107.98707,16.12008],"type":"Point"}
}