{
  "type": "Feature",
  "properties": {
    "gn:admin1_code":"44.0",
    "gn:asciiname":"Dong Bang",
    "gn:country_code":"VN",
    "gn:dem":19,
    "gn:feature_class":"P",
    "gn:feature_code":"PPL",
    "gn:name":"\u0110\u1ed3ng B\u1ea3ng",
    "gn:population":0,
    "gn:timezone":"Asia/Ho_Chi_Minh",
    "iso:country":"VN",
    "name:vie_x_preferred":[
        "\u0110\u1ed3ng B\u1ea3ng"
    ],
    "wof:name":"Dong Bang",
    "wof:placetype":"locality"
},
  "geometry": {"coordinates":[105.40752999999999,21.21983],"type":"Point"}
}