{
  "type": "Feature",
  "properties": {
    "gn:admin1_code":"64.0",
    "gn:asciiname":"Cam Phu",
    "gn:country_code":"VN",
    "gn:dem":55,
    "gn:feature_class":"P",
    "gn:feature_code":"PPL",
    "gn:name":"Cam Ph\u00fa",
    "gn:population":0,
    "gn:timezone":"Asia/Ho_Chi_Minh",
    "iso:country":"VN",
    "name:vie_x_preferred":[
        "Cam Ph\u00fa"
    ],
    "wof:name":"Cam Phu",
    "wof:placetype":"locality"
},
  "geometry": {"coordinates":[106.90515000000001,16.78225],"type":"Point"}
}