{
  "type": "Feature",
  "properties": {
    "gn:admin1_code":"90.0",
    "gn:asciiname":"Na Ham",
    "gn:country_code":"VN",
    "gn:dem":570,
    "gn:feature_class":"P",
    "gn:feature_code":"PPL",
    "gn:name":"N\u00e1 Ham",
    "gn:population":0,
    "gn:timezone":"Asia/Ho_Chi_Minh",
    "iso:country":"VN",
    "wof:name":"Na Ham",
    "wof:placetype":"locality"
},
  "geometry": {"coordinates":[104.06667,21.98333],"type":"Point"}
}