{
  "type": "Feature",
  "properties": {
    "gn:admin1_code":"74.0",
    "gn:asciiname":"Phuong La Doai",
    "gn:country_code":"VN",
    "gn:dem":12,
    "gn:feature_class":"P",
    "gn:feature_code":"PPL",
    "gn:name":"Ph\u01b0\u01a1ng La \u0110o\u00e0i",
    "gn:population":0,
    "gn:timezone":"Asia/Ho_Chi_Minh",
    "iso:country":"VN",
    "name:vie_x_preferred":[
        "Ph\u01b0\u01a1ng La \u0110o\u00e0i"
    ],
    "wof:name":"Phuong La Doai",
    "wof:placetype":"locality"
},
  "geometry": {"coordinates":[105.93415,21.23292],"type":"Point"}
}