{
  "type": "Feature",
  "properties": {
    "gn:admin1_code":"32.0",
    "gn:asciiname":"Ky Ninh",
    "gn:country_code":"VN",
    "gn:dem":1158,
    "gn:feature_class":"P",
    "gn:feature_code":"PPL",
    "gn:name":"K\u1ef3 N\u00ecnh",
    "gn:population":0,
    "gn:timezone":"Asia/Ho_Chi_Minh",
    "iso:country":"VN",
    "wof:name":"Ky Ninh",
    "wof:placetype":"locality"
},
  "geometry": {"coordinates":[103.95,21.05],"type":"Point"}
}