{
  "type": "Feature",
  "properties": {
    "gn:admin1_code":"62.0",
    "gn:asciiname":"Sen Phuong",
    "gn:country_code":"VN",
    "gn:dem":15,
    "gn:feature_class":"P",
    "gn:feature_code":"PPL",
    "gn:name":"Sen Ph\u01b0\u01a1ng",
    "gn:population":0,
    "gn:timezone":"Asia/Ho_Chi_Minh",
    "iso:country":"VN",
    "name:und_x_variant":[
        "Sao Sa",
        "Sen Ph\u01b0\u01a1ng"
    ],
    "wof:name":"Sen Phuong",
    "wof:placetype":"locality"
},
  "geometry": {"coordinates":[106.53333000000001,17.51667],"type":"Point"}
}