{
  "type": "Feature",
  "properties": {
    "gn:admin1_code":"80.0",
    "gn:asciiname":"Dien Xa",
    "gn:country_code":"VN",
    "gn:dem":7,
    "gn:feature_class":"P",
    "gn:feature_code":"PPL",
    "gn:name":"\u0110i\u1ec1n X\u00e1",
    "gn:population":0,
    "gn:timezone":"Asia/Ho_Chi_Minh",
    "iso:country":"VN",
    "name:vie_x_preferred":[
        "\u0110i\u1ec1n X\u00e1"
    ],
    "wof:name":"Dien Xa",
    "wof:placetype":"locality"
},
  "geometry": {"coordinates":[105.90088,20.60099],"type":"Point"}
}