{
  "type": "Feature",
  "properties": {
    "gn:admin1_code":"62.0",
    "gn:asciiname":"Ron",
    "gn:cc2":"VN",
    "gn:country_code":"VN",
    "gn:dem":3,
    "gn:feature_class":"P",
    "gn:feature_code":"PPL",
    "gn:name":"R\u00f2n",
    "gn:population":0,
    "gn:timezone":"Asia/Ho_Chi_Minh",
    "iso:country":"VN",
    "name:ceb_x_preferred":[
        "Ron"
    ],
    "name:ces_x_preferred":[
        "Ron"
    ],
    "name:deu_x_preferred":[
        "Ron"
    ],
    "name:hye_x_preferred":[
        "\u054c\u0578\u0576"
    ],
    "name:rus_x_preferred":[
        "\u0420\u043e\u043d"
    ],
    "name:spa_x_preferred":[
        "Ron"
    ],
    "name:swe_x_preferred":[
        "Ron"
    ],
    "name:und_x_variant":[
        "Roon",
        "Rone",
        "R\u00f2n"
    ],
    "wof:name":"Ron",
    "wof:placetype":"locality"
},
  "geometry": {"coordinates":[106.45,17.88332999999999],"type":"Point"}
}