{
  "type": "Feature",
  "properties": {
    "gn:admin1_code":"52.0",
    "gn:asciiname":"Kha Vuong",
    "gn:country_code":"VN",
    "gn:dem":84,
    "gn:feature_class":"P",
    "gn:feature_code":"PPL",
    "gn:name":"Kh\u1ea3 V\u01b0\u1ee3ng",
    "gn:population":0,
    "gn:timezone":"Asia/Ho_Chi_Minh",
    "iso:country":"VN",
    "name:vie_x_preferred":[
        "Kh\u1ea3 V\u01b0\u1ee3ng"
    ],
    "wof:name":"Kha Vuong",
    "wof:placetype":"locality"
},
  "geometry": {"coordinates":[105.74072,18.06992],"type":"Point"}
}