{
  "type": "Feature",
  "properties": {
    "gn:admin1_code":"85.0",
    "gn:asciiname":"Lang Ke",
    "gn:country_code":"VN",
    "gn:dem":73,
    "gn:feature_class":"P",
    "gn:feature_code":"PPL",
    "gn:name":"L\u00e0ng Ke",
    "gn:population":0,
    "gn:timezone":"Asia/Ho_Chi_Minh",
    "iso:country":"VN",
    "wof:name":"Lang Ke",
    "wof:placetype":"locality"
},
  "geometry": {"coordinates":[105.59999999999999,21.68333],"type":"Point"}
}