{
  "type": "Feature",
  "properties": {
    "gn:admin1_code":"37.0",
    "gn:asciiname":"Long Thanh",
    "gn:country_code":"VN",
    "gn:dem":5,
    "gn:feature_class":"P",
    "gn:feature_code":"PPL",
    "gn:name":"Long Th\u00e0nh",
    "gn:population":0,
    "gn:timezone":"Asia/Ho_Chi_Minh",
    "iso:country":"VN",
    "name:und_x_variant":[
        "Long Th\u00e0nh B",
        "Long Th\u00e0nh"
    ],
    "wof:name":"Long Thanh",
    "wof:placetype":"locality"
},
  "geometry": {"coordinates":[106.23333,10.35],"type":"Point"}
}