{
  "type": "Feature",
  "properties": {
    "gn:admin1_code":"79.0",
    "gn:asciiname":"An Doi",
    "gn:country_code":"VN",
    "gn:dem":7,
    "gn:feature_class":"P",
    "gn:feature_code":"PPL",
    "gn:name":"An Doi",
    "gn:population":0,
    "gn:timezone":"Asia/Ho_Chi_Minh",
    "iso:country":"VN",
    "name:und_x_variant":[
        "An \u0110o\u00e0i"
    ],
    "wof:name":"An Doi",
    "wof:placetype":"locality"
},
  "geometry": {"coordinates":[106.36667,21.03333],"type":"Point"}
}