{
  "type": "Feature",
  "properties": {
    "gn:admin1_code":"60.0",
    "gn:asciiname":"Ninh Binh",
    "gn:country_code":"VN",
    "gn:dem":108,
    "gn:feature_class":"P",
    "gn:feature_code":"PPL",
    "gn:name":"Ninh B\u00ecnh",
    "gn:population":0,
    "gn:timezone":"Asia/Ho_Chi_Minh",
    "iso:country":"VN",
    "name:vie_x_preferred":[
        "Ninh B\u00ecnh"
    ],
    "wof:name":"Ninh Binh",
    "wof:placetype":"locality"
},
  "geometry": {"coordinates":[108.789,11.77257],"type":"Point"}
}