{
  "type": "Feature",
  "properties": {
    "gn:admin1_code":"33.0",
    "gn:asciiname":"Loc Hiep",
    "gn:country_code":"VN",
    "gn:dem":16,
    "gn:feature_class":"P",
    "gn:feature_code":"PPL",
    "gn:name":"L\u1ed9c Hi\u1ec7p",
    "gn:population":0,
    "gn:timezone":"Asia/Ho_Chi_Minh",
    "iso:country":"VN",
    "name:vie_x_preferred":[
        "L\u1ed9c Hi\u1ec7p"
    ],
    "wof:name":"Loc Hiep",
    "wof:placetype":"locality"
},
  "geometry": {"coordinates":[106.30762,11.26213],"type":"Point"}
}