{
  "type": "Feature",
  "properties": {
    "gn:admin1_code":"67.0",
    "gn:asciiname":"Ap Lo O",
    "gn:cc2":"VN",
    "gn:country_code":"VN",
    "gn:dem":1,
    "gn:feature_class":"P",
    "gn:feature_code":"PPL",
    "gn:name":"\u1ea4p L\u1ed3 \u1ed2",
    "gn:population":0,
    "gn:timezone":"Asia/Ho_Chi_Minh",
    "iso:country":"VN",
    "name:und_x_variant":[
        "L\u1ed3 \u1ed2",
        "\u1ea4p L\u1ed3 \u1ed2"
    ],
    "wof:name":"Ap Lo O",
    "wof:placetype":"locality"
},
  "geometry": {"coordinates":[106.47389,9.73694],"type":"Point"}
}