{
  "type": "Feature",
  "properties": {
    "gn:admin1_code":"34.0",
    "gn:asciiname":"My Xuyen",
    "gn:country_code":"VN",
    "gn:dem":12,
    "gn:feature_class":"P",
    "gn:feature_code":"PPL",
    "gn:name":"M\u1ef7 Xuy\u00ean",
    "gn:population":0,
    "gn:timezone":"Asia/Ho_Chi_Minh",
    "iso:country":"VN",
    "wof:name":"My Xuyen",
    "wof:placetype":"locality"
},
  "geometry": {"coordinates":[105.59999999999999,20.08333],"type":"Point"}
}