{
  "type": "Feature",
  "properties": {
    "gn:admin1_code":"23.0",
    "gn:asciiname":"Tan Repo",
    "gn:country_code":"VN",
    "gn:dem":746,
    "gn:feature_class":"P",
    "gn:feature_code":"PPL",
    "gn:name":"Tan Repo",
    "gn:population":0,
    "gn:timezone":"Asia/Ho_Chi_Minh",
    "iso:country":"VN",
    "wof:name":"Tan Repo",
    "wof:placetype":"locality"
},
  "geometry": {"coordinates":[108.05,11.35],"type":"Point"}
}