{
  "type": "Feature",
  "properties": {
    "gn:admin1_code":"32.0",
    "gn:asciiname":"Pac Hom",
    "gn:country_code":"VN",
    "gn:dem":362,
    "gn:feature_class":"P",
    "gn:feature_code":"PPL",
    "gn:name":"Pac Hom",
    "gn:population":0,
    "gn:timezone":"Asia/Ho_Chi_Minh",
    "iso:country":"VN",
    "wof:name":"Pac Hom",
    "wof:placetype":"locality"
},
  "geometry": {"coordinates":[104.41667,20.95],"type":"Point"}
}