{
  "type": "Feature",
  "properties": {
    "gn:admin1_code":"68.0",
    "gn:asciiname":"Ba Thuong",
    "gn:country_code":"VN",
    "gn:dem":36,
    "gn:feature_class":"P",
    "gn:feature_code":"PPL",
    "gn:name":"Ba Th\u01b0\u1ee3ng",
    "gn:population":0,
    "gn:timezone":"Asia/Ho_Chi_Minh",
    "iso:country":"VN",
    "name:vie_x_preferred":[
        "Ba Th\u01b0\u1ee3ng"
    ],
    "wof:name":"Ba Thuong",
    "wof:placetype":"locality"
},
  "geometry": {"coordinates":[105.3039,21.73666],"type":"Point"}
}