{
  "type": "Feature",
  "properties": {
    "gn:admin1_code":"50.0",
    "gn:asciiname":"Ban Tien Xuan",
    "gn:country_code":"VN",
    "gn:dem":329,
    "gn:feature_class":"P",
    "gn:feature_code":"PPL",
    "gn:name":"B\u1ea3n Ti\u1ebfn Xu\u00e2n",
    "gn:population":0,
    "gn:timezone":"Asia/Ho_Chi_Minh",
    "iso:country":"VN",
    "name:vie_x_preferred":[
        "B\u1ea3n Ti\u1ebfn Xu\u00e2n"
    ],
    "wof:name":"Ban Tien Xuan",
    "wof:placetype":"locality"
},
  "geometry": {"coordinates":[105.3506,22.71746],"type":"Point"}
}