{
  "type": "Feature",
  "properties": {
    "gn:admin1_code":"52.0",
    "gn:asciiname":"Dong Phuc",
    "gn:country_code":"VN",
    "gn:dem":6,
    "gn:feature_class":"P",
    "gn:feature_code":"PPL",
    "gn:name":"\u0110\u00f4ng Ph\u00fac",
    "gn:population":0,
    "gn:timezone":"Asia/Ho_Chi_Minh",
    "iso:country":"VN",
    "name:vie_x_preferred":[
        "\u0110\u00f4ng Ph\u00fac"
    ],
    "wof:name":"Dong Phuc",
    "wof:placetype":"locality"
},
  "geometry": {"coordinates":[105.94937,18.38503],"type":"Point"}
}