{
  "type": "Feature",
  "properties": {
    "gn:admin1_code":"55.0",
    "gn:asciiname":"Polei Dak Tur Nak",
    "gn:country_code":"VN",
    "gn:dem":1104,
    "gn:feature_class":"P",
    "gn:feature_code":"PPL",
    "gn:name":"P\u01a1lei Dak Tur Nak",
    "gn:population":0,
    "gn:timezone":"Asia/Ho_Chi_Minh",
    "iso:country":"VN",
    "name:und_x_variant":[
        "Pele Dak Tour Nak",
        "P\u01a1lei Dak Tur Nak"
    ],
    "wof:name":"Polei Dak Tur Nak",
    "wof:placetype":"locality"
},
  "geometry": {"coordinates":[107.75,14.81667],"type":"Point"}
}