{
  "type": "Feature",
  "properties": {
    "gn:admin1_code":"23.0",
    "gn:asciiname":"Ap Phuoc Thanh",
    "gn:cc2":"VN",
    "gn:country_code":"VN",
    "gn:dem":1539,
    "gn:feature_class":"P",
    "gn:feature_code":"PPL",
    "gn:name":"\u1ea4p Ph\u01b0\u1edbc Th\u00e1nh",
    "gn:population":0,
    "gn:timezone":"Asia/Ho_Chi_Minh",
    "iso:country":"VN",
    "name:und_x_variant":[
        "Phuoc Thanh",
        "\u1ea4p Ph\u01b0\u1edbc Th\u00e1nh"
    ],
    "wof:name":"Ap Phuoc Thanh",
    "wof:placetype":"locality"
},
  "geometry": {"coordinates":[108.43333,11.98333],"type":"Point"}
}