{
  "type": "Feature",
  "properties": {
    "gn:admin1_code":"47.0",
    "gn:asciiname":"Cay Gang",
    "gn:country_code":"VN",
    "gn:dem":5,
    "gn:feature_class":"P",
    "gn:feature_code":"PPL",
    "gn:name":"C\u00e2y G\u0103ng",
    "gn:population":0,
    "gn:timezone":"Asia/Ho_Chi_Minh",
    "iso:country":"VN",
    "name:und_x_variant":[
        "X\u00f3m Chum G\u0103ng"
    ],
    "name:vie_x_preferred":[
        "C\u00e2y G\u0103ng"
    ],
    "wof:name":"Cay Gang",
    "wof:placetype":"locality"
},
  "geometry": {"coordinates":[107.941,10.7211],"type":"Point"}
}