{
  "type": "Feature",
  "properties": {
    "gn:admin1_code":"9.0",
    "gn:asciiname":"Hoa Que",
    "gn:country_code":"VN",
    "gn:dem":3,
    "gn:feature_class":"P",
    "gn:feature_code":"PPL",
    "gn:name":"H\u00f2a Qu\u1ebf",
    "gn:population":0,
    "gn:timezone":"Asia/Ho_Chi_Minh",
    "iso:country":"VN",
    "name:und_x_variant":[
        "H\u00f2a Q\u1ee9i"
    ],
    "name:vie_x_preferred":[
        "H\u00f2a Qu\u1ebf"
    ],
    "wof:name":"Hoa Que",
    "wof:placetype":"locality"
},
  "geometry": {"coordinates":[105.83398,10.17514],"type":"Point"}
}