{
  "type": "Feature",
  "properties": {
    "gn:admin1_code":"32.0",
    "gn:asciiname":"Loong Lau",
    "gn:country_code":"VN",
    "gn:dem":803,
    "gn:feature_class":"P",
    "gn:feature_code":"PPL",
    "gn:name":"Loong L\u1ea7u",
    "gn:population":0,
    "gn:timezone":"Asia/Ho_Chi_Minh",
    "iso:country":"VN",
    "name:vie_x_preferred":[
        "Loong L\u1ea7u"
    ],
    "wof:name":"Loong Lau",
    "wof:placetype":"locality"
},
  "geometry": {"coordinates":[103.73564,21.34672],"type":"Point"}
}