{
  "type": "Feature",
  "properties": {
    "gn:admin1_code":"68.0",
    "gn:asciiname":"Cau Mot Dong",
    "gn:country_code":"VN",
    "gn:dem":41,
    "gn:feature_class":"P",
    "gn:feature_code":"PPL",
    "gn:name":"C\u1ea7u M\u1ed9t \u0110\u00f4ng",
    "gn:population":0,
    "gn:timezone":"Asia/Ho_Chi_Minh",
    "iso:country":"VN",
    "name:und_x_variant":[
        "C\u1ea7u M\u00f4t \u0110\u00f4ng"
    ],
    "name:vie_x_preferred":[
        "C\u1ea7u M\u1ed9t \u0110\u00f4ng"
    ],
    "wof:name":"Cau Mot Dong",
    "wof:placetype":"locality"
},
  "geometry": {"coordinates":[105.15524000000001,22.03386],"type":"Point"}
}