{
  "type": "Feature",
  "properties": {
    "gn:admin1_code":"49.0",
    "gn:asciiname":"Phu Tuc",
    "gn:country_code":"VN",
    "gn:dem":135,
    "gn:feature_class":"P",
    "gn:feature_code":"PPLA2",
    "gn:name":"Ph\u00fa T\u00fac",
    "gn:population":0,
    "gn:timezone":"Asia/Ho_Chi_Minh",
    "iso:country":"VN",
    "name:und_x_variant":[
        "Ban Ba M\u2019La",
        "Ph\u00fa T\u00fac"
    ],
    "wof:name":"Phu Tuc",
    "wof:placetype":"locality"
},
  "geometry": {"coordinates":[108.69043000000001,13.19682],"type":"Point"}
}