{
  "type": "Feature",
  "properties": {
    "gn:admin1_code":"61.0",
    "gn:asciiname":"Nguyen An",
    "gn:country_code":"VN",
    "gn:dem":39,
    "gn:feature_class":"P",
    "gn:feature_code":"PPL",
    "gn:name":"Nguy\u00ean An",
    "gn:population":0,
    "gn:timezone":"Asia/Ho_Chi_Minh",
    "iso:country":"VN",
    "name:vie_x_preferred":[
        "Nguy\u00ean An"
    ],
    "wof:name":"Nguyen An",
    "wof:placetype":"locality"
},
  "geometry": {"coordinates":[109.03757,13.07722],"type":"Point"}
}