{
  "type": "Feature",
  "properties": {
    "gn:admin1_code":"52.0",
    "gn:asciiname":"Tho Hoang",
    "gn:country_code":"VN",
    "gn:dem":59,
    "gn:feature_class":"P",
    "gn:feature_code":"PPL",
    "gn:name":"Th\u1ed5 Ho\u00e0ng",
    "gn:population":0,
    "gn:timezone":"Asia/Ho_Chi_Minh",
    "iso:country":"VN",
    "wof:name":"Tho Hoang",
    "wof:placetype":"locality"
},
  "geometry": {"coordinates":[105.61667,18.31667],"type":"Point"}
}