{
  "type": "Feature",
  "properties": {
    "gn:admin1_code":"66.0",
    "gn:asciiname":"Ap Lai Thanh",
    "gn:country_code":"VN",
    "gn:dem":5,
    "gn:feature_class":"P",
    "gn:feature_code":"PPL",
    "gn:name":"\u1ea4p Lai Th\u00e1nh",
    "gn:population":0,
    "gn:timezone":"Asia/Ho_Chi_Minh",
    "iso:country":"VN",
    "name:und_x_variant":[
        "Lai Thanh",
        "\u1ea4p Lai Th\u00e1nh"
    ],
    "wof:name":"Ap Lai Thanh",
    "wof:placetype":"locality"
},
  "geometry": {"coordinates":[107.45,16.53333],"type":"Point"}
}