{
  "type": "Feature",
  "properties": {
    "gn:admin1_code":"67.0",
    "gn:asciiname":"At Ech",
    "gn:cc2":"VN",
    "gn:country_code":"VN",
    "gn:dem":4,
    "gn:feature_class":"P",
    "gn:feature_code":"PPL",
    "gn:name":"\u1ea4t \u1ebech",
    "gn:population":0,
    "gn:timezone":"Asia/Ho_Chi_Minh",
    "iso:country":"VN",
    "name:und_x_variant":[
        "\u1ebech",
        "\u1ea4t \u1ebech"
    ],
    "wof:name":"At Ech",
    "wof:placetype":"locality"
},
  "geometry": {"coordinates":[106.235,9.92222],"type":"Point"}
}