{
  "type": "Feature",
  "properties": {
    "gn:admin1_code":"61.0",
    "gn:asciiname":"Trieu Son",
    "gn:country_code":"VN",
    "gn:dem":11,
    "gn:feature_class":"P",
    "gn:feature_code":"PPL",
    "gn:name":"Tri\u1ec1u S\u01a1n",
    "gn:population":0,
    "gn:timezone":"Asia/Ho_Chi_Minh",
    "iso:country":"VN",
    "name:und_x_variant":[
        "Tri\u00eau S\u01a1n"
    ],
    "name:vie_x_preferred":[
        "Tri\u1ec1u S\u01a1n"
    ],
    "wof:name":"Trieu Son",
    "wof:placetype":"locality"
},
  "geometry": {"coordinates":[109.19677,13.39365],"type":"Point"}
}