{
  "type": "Feature",
  "properties": {
    "gn:admin1_code":"72.0",
    "gn:asciiname":"Bang Lang",
    "gn:country_code":"VN",
    "gn:dem":543,
    "gn:feature_class":"P",
    "gn:feature_code":"PPL",
    "gn:name":"B\u1eb1ng L\u1eb7ng",
    "gn:population":0,
    "gn:timezone":"Asia/Ho_Chi_Minh",
    "iso:country":"VN",
    "name:vie_x_preferred":[
        "B\u1eb1ng L\u1eb7ng"
    ],
    "wof:name":"Bang Lang",
    "wof:placetype":"locality"
},
  "geometry": {"coordinates":[106.00272,22.41145],"type":"Point"}
}