{
  "type": "Feature",
  "properties": {
    "gn:admin1_code":"65.0",
    "gn:asciiname":"An Thuong",
    "gn:country_code":"VN",
    "gn:dem":2,
    "gn:feature_class":"P",
    "gn:feature_code":"PPL",
    "gn:name":"An Th\u01b0\u1eddng",
    "gn:population":0,
    "gn:timezone":"Asia/Ho_Chi_Minh",
    "iso:country":"VN",
    "name:vie_x_preferred":[
        "An Th\u01b0\u1eddng"
    ],
    "wof:name":"An Thuong",
    "wof:placetype":"locality"
},
  "geometry": {"coordinates":[106.09446,9.74518],"type":"Point"}
}