{
  "type": "Feature",
  "properties": {
    "gn:admin1_code":"65.0",
    "gn:asciiname":"Ap Tan",
    "gn:country_code":"VN",
    "gn:dem":2,
    "gn:feature_class":"P",
    "gn:feature_code":"PPL",
    "gn:name":"\u1ea4p T\u00e2n",
    "gn:population":0,
    "gn:timezone":"Asia/Ho_Chi_Minh",
    "iso:country":"VN",
    "wof:name":"Ap Tan",
    "wof:placetype":"locality"
},
  "geometry": {"coordinates":[106.01667,9.38333],"type":"Point"}
}