{
  "type": "Feature",
  "properties": {
    "gn:admin1_code":"61.0",
    "gn:asciiname":"Buon Tong Trach",
    "gn:country_code":"VN",
    "gn:dem":185,
    "gn:feature_class":"P",
    "gn:feature_code":"PPL",
    "gn:name":"Bu\u00f4n T\u1ed5ng Tr\u00e1ch",
    "gn:population":0,
    "gn:timezone":"Asia/Ho_Chi_Minh",
    "iso:country":"VN",
    "name:vie_x_preferred":[
        "Bu\u00f4n T\u1ed5ng Tr\u00e1ch"
    ],
    "wof:name":"Buon Tong Trach",
    "wof:placetype":"locality"
},
  "geometry": {"coordinates":[108.92281,12.94375],"type":"Point"}
}