{
  "type": "Feature",
  "properties": {
    "gn:admin1_code":"33.0",
    "gn:asciiname":"Ap Gia Loc",
    "gn:cc2":"VN",
    "gn:country_code":"VN",
    "gn:dem":12,
    "gn:feature_class":"P",
    "gn:feature_code":"PPL",
    "gn:name":"\u1ea4p Gia L\u1ed9c",
    "gn:population":0,
    "gn:timezone":"Asia/Ho_Chi_Minh",
    "iso:country":"VN",
    "name:und_x_variant":[
        "Gia Loc",
        "\u1ea4p Gia L\u1ed9c"
    ],
    "wof:name":"Ap Gia Loc",
    "wof:placetype":"locality"
},
  "geometry": {"coordinates":[106.34999999999999,11.05],"type":"Point"}
}