{
  "type": "Feature",
  "properties": {
    "gn:admin1_code":"61.0",
    "gn:asciiname":"Ma Then",
    "gn:country_code":"VN",
    "gn:dem":620,
    "gn:feature_class":"P",
    "gn:feature_code":"PPL",
    "gn:name":"Ma Then",
    "gn:population":0,
    "gn:timezone":"Asia/Ho_Chi_Minh",
    "iso:country":"VN",
    "name:und_x_variant":[
        "Buon Ma Then",
        "Ban Ma Then"
    ],
    "name:vie_x_preferred":[
        "Ma Then"
    ],
    "wof:name":"Ma Then",
    "wof:placetype":"locality"
},
  "geometry": {"coordinates":[108.84788,13.34993],"type":"Point"}
}