{
  "type": "Feature",
  "properties": {
    "gn:admin1_code":"89.0",
    "gn:asciiname":"Ban Pa Khoang Duoi",
    "gn:country_code":"VN",
    "gn:dem":510,
    "gn:feature_class":"P",
    "gn:feature_code":"PPL",
    "gn:name":"B\u1ea3n P\u00e1 Khoang D\u01b0\u1edbi",
    "gn:population":0,
    "gn:timezone":"Asia/Ho_Chi_Minh",
    "iso:country":"VN",
    "name:vie_x_preferred":[
        "B\u1ea3n P\u00e1 Khoang D\u01b0\u1edbi"
    ],
    "wof:name":"Ban Pa Khoang Duoi",
    "wof:placetype":"locality"
},
  "geometry": {"coordinates":[103.74393000000001,21.89581],"type":"Point"}
}