{
  "type": "Feature",
  "properties": {
    "gn:admin1_code":"52.0",
    "gn:asciiname":"Huong Hoa",
    "gn:country_code":"VN",
    "gn:dem":4,
    "gn:feature_class":"P",
    "gn:feature_code":"PPL",
    "gn:name":"H\u01b0\u01a1ng Hoa",
    "gn:population":0,
    "gn:timezone":"Asia/Ho_Chi_Minh",
    "iso:country":"VN",
    "name:vie_x_preferred":[
        "H\u01b0\u01a1ng Hoa"
    ],
    "wof:name":"Huong Hoa",
    "wof:placetype":"locality"
},
  "geometry": {"coordinates":[106.07622000000001,18.26102],"type":"Point"}
}