{
  "type": "Feature",
  "properties": {
    "gn:admin1_code":"68.0",
    "gn:asciiname":"Cay Tre",
    "gn:country_code":"VN",
    "gn:dem":88,
    "gn:feature_class":"P",
    "gn:feature_code":"PPL",
    "gn:name":"C\u00e2y Tre",
    "gn:population":0,
    "gn:timezone":"Asia/Ho_Chi_Minh",
    "iso:country":"VN",
    "name:vie_x_preferred":[
        "C\u00e2y Tre"
    ],
    "wof:name":"Cay Tre",
    "wof:placetype":"locality"
},
  "geometry": {"coordinates":[105.0078,21.91398],"type":"Point"}
}