{
  "type": "Feature",
  "properties": {
    "gn:admin1_code":"43.0",
    "gn:asciiname":"La Nga",
    "gn:country_code":"VN",
    "gn:dem":60,
    "gn:feature_class":"P",
    "gn:feature_code":"PPL",
    "gn:name":"L\u00e0 Ng\u00e0",
    "gn:population":0,
    "gn:timezone":"Asia/Ho_Chi_Minh",
    "iso:country":"VN",
    "wof:name":"La Nga",
    "wof:placetype":"locality"
},
  "geometry": {"coordinates":[107.28333000000001,11.15],"type":"Point"}
}