{
  "type": "Feature",
  "properties": {
    "gn:admin1_code":"32.0",
    "gn:asciiname":"Ban Sang",
    "gn:country_code":"VN",
    "gn:dem":647,
    "gn:feature_class":"P",
    "gn:feature_code":"PPL",
    "gn:name":"B\u1ea3n S\u00e0ng",
    "gn:population":0,
    "gn:timezone":"Asia/Ho_Chi_Minh",
    "iso:country":"VN",
    "name:und_x_variant":[
        "Ban Seng",
        "B\u1ea3n Sang"
    ],
    "name:vie_x_preferred":[
        "B\u1ea3n S\u00e0ng"
    ],
    "wof:name":"Ban Sang",
    "wof:placetype":"locality"
},
  "geometry": {"coordinates":[104.14198,21.09219],"type":"Point"}
}