{
  "type": "Feature",
  "properties": {
    "gn:admin1_code":"58.0",
    "gn:asciiname":"Con Queo",
    "gn:country_code":"VN",
    "gn:dem":18,
    "gn:feature_class":"P",
    "gn:feature_code":"PPL",
    "gn:name":"C\u1ed3n Queo",
    "gn:population":0,
    "gn:timezone":"Asia/Ho_Chi_Minh",
    "iso:country":"VN",
    "name:vie_x_preferred":[
        "C\u1ed3n Queo"
    ],
    "wof:name":"Con Queo",
    "wof:placetype":"locality"
},
  "geometry": {"coordinates":[105.6626,19.19611],"type":"Point"}
}