{
  "type": "Feature",
  "properties": {
    "gn:admin1_code":"58.0",
    "gn:asciiname":"Hong Son",
    "gn:country_code":"VN",
    "gn:dem":6,
    "gn:feature_class":"P",
    "gn:feature_code":"PPL",
    "gn:name":"H\u1ed3ng S\u01a1n",
    "gn:population":0,
    "gn:timezone":"Asia/Ho_Chi_Minh",
    "iso:country":"VN",
    "name:vie_x_preferred":[
        "H\u1ed3ng S\u01a1n"
    ],
    "wof:name":"Hong Son",
    "wof:placetype":"locality"
},
  "geometry": {"coordinates":[105.55500000000001,19.09147],"type":"Point"}
}