{
  "type": "Feature",
  "properties": {
    "gn:admin1_code":"44.0",
    "gn:asciiname":"Phung Nghia",
    "gn:country_code":"VN",
    "gn:dem":12,
    "gn:feature_class":"P",
    "gn:feature_code":"PPL",
    "gn:name":"Ph\u1ee5ng Nghia",
    "gn:population":0,
    "gn:timezone":"Asia/Ho_Chi_Minh",
    "iso:country":"VN",
    "name:und_x_variant":[
        "Ph\u01b0\u01a1ng Nghia",
        "Ph\u1ee5ng Nghia"
    ],
    "wof:name":"Phung Nghia",
    "wof:placetype":"locality"
},
  "geometry": {"coordinates":[105.71666999999999,20.95],"type":"Point"}
}