{
  "type": "Feature",
  "properties": {
    "gn:admin1_code":"68.0",
    "gn:asciiname":"Khuon Ma",
    "gn:country_code":"VN",
    "gn:dem":134,
    "gn:feature_class":"P",
    "gn:feature_code":"PPL",
    "gn:name":"Khu\u00f4n M\u1ea1",
    "gn:population":0,
    "gn:timezone":"Asia/Ho_Chi_Minh",
    "iso:country":"VN",
    "name:und_x_variant":[
        "Khu\u00f4n Ma",
        "Khouen Ma"
    ],
    "name:vie_x_preferred":[
        "Khu\u00f4n M\u1ea1"
    ],
    "wof:name":"Khuon Ma",
    "wof:placetype":"locality"
},
  "geometry": {"coordinates":[105.41669,22.1085],"type":"Point"}
}