{
  "type": "Feature",
  "properties": {
    "gn:admin1_code":"58.0",
    "gn:asciiname":"Ban Dung",
    "gn:country_code":"VN",
    "gn:dem":69,
    "gn:feature_class":"P",
    "gn:feature_code":"PPL",
    "gn:name":"B\u1ea3n \u0110ung",
    "gn:population":0,
    "gn:timezone":"Asia/Ho_Chi_Minh",
    "iso:country":"VN",
    "name:vie_x_preferred":[
        "B\u1ea3n \u0110ung"
    ],
    "wof:name":"Ban Dung",
    "wof:placetype":"locality"
},
  "geometry": {"coordinates":[105.25744,19.4624],"type":"Point"}
}