{
  "type": "Feature",
  "properties": {
    "gn:admin1_code":"85.0",
    "gn:asciiname":"Luong Thai",
    "gn:country_code":"VN",
    "gn:dem":16,
    "gn:feature_class":"P",
    "gn:feature_code":"PPL",
    "gn:name":"L\u01b0\u01a1ng Th\u00e1i",
    "gn:population":0,
    "gn:timezone":"Asia/Ho_Chi_Minh",
    "iso:country":"VN",
    "name:vie_x_preferred":[
        "L\u01b0\u01a1ng Th\u00e1i"
    ],
    "wof:name":"Luong Thai",
    "wof:placetype":"locality"
},
  "geometry": {"coordinates":[106.00311000000001,21.4324],"type":"Point"}
}