{
  "type": "Feature",
  "properties": {
    "gn:admin1_code":"89.0",
    "gn:asciiname":"Kho Bon",
    "gn:country_code":"VN",
    "gn:dem":1220,
    "gn:feature_class":"P",
    "gn:feature_code":"PPL",
    "gn:name":"Kho Bon",
    "gn:population":0,
    "gn:timezone":"Asia/Ho_Chi_Minh",
    "iso:country":"VN",
    "wof:name":"Kho Bon",
    "wof:placetype":"locality"
},
  "geometry": {"coordinates":[103.93333,21.95],"type":"Point"}
}