{
  "type": "Feature",
  "properties": {
    "gn:admin1_code":"50.0",
    "gn:asciiname":"Ban Khau Tau",
    "gn:country_code":"VN",
    "gn:dem":376,
    "gn:feature_class":"P",
    "gn:feature_code":"PPL",
    "gn:name":"B\u1ea3n Khau T\u1ea7u",
    "gn:population":0,
    "gn:timezone":"Asia/Ho_Chi_Minh",
    "iso:country":"VN",
    "name:vie_x_preferred":[
        "B\u1ea3n Khau T\u1ea7u"
    ],
    "wof:name":"Ban Khau Tau",
    "wof:placetype":"locality"
},
  "geometry": {"coordinates":[105.47002999999999,22.74136],"type":"Point"}
}