{
  "type": "Feature",
  "properties": {
    "gn:admin1_code":"50.0",
    "gn:asciiname":"Bac Quang",
    "gn:cc2":"VN",
    "gn:country_code":"VN",
    "gn:dem":70,
    "gn:feature_class":"P",
    "gn:feature_code":"PPL",
    "gn:name":"B\u1eafc Quang",
    "gn:population":0,
    "gn:timezone":"Asia/Ho_Chi_Minh",
    "iso:country":"VN",
    "name:fas_x_preferred":[
        "\u062a\u0627\u0646 \u0642\u0648\u0627\u0646\u06af"
    ],
    "name:nld_x_preferred":[
        "T\u00e2n Quang"
    ],
    "name:und_x_variant":[
        "Ban Quong",
        "Bac Kwang",
        "T\u00e2n Quang",
        "Bac Quong",
        "Bak Kang",
        "Ban Kwang",
        "B\u1eafc Quang"
    ],
    "name:vie_x_preferred":[
        "T\u00e2n Quang"
    ],
    "wof:name":"Bac Quang",
    "wof:placetype":"locality"
},
  "geometry": {"coordinates":[104.86667,22.48333],"type":"Point"}
}