{
  "type": "Feature",
  "properties": {
    "gn:admin1_code":"68.0",
    "gn:asciiname":"Hiep Khai",
    "gn:country_code":"VN",
    "gn:dem":83,
    "gn:feature_class":"P",
    "gn:feature_code":"PPL",
    "gn:name":"Hi\u1ec7p Khai",
    "gn:population":0,
    "gn:timezone":"Asia/Ho_Chi_Minh",
    "iso:country":"VN",
    "name:vie_x_preferred":[
        "Hi\u1ec7p Khai"
    ],
    "wof:name":"Hiep Khai",
    "wof:placetype":"locality"
},
  "geometry": {"coordinates":[105.19548,22.10481],"type":"Point"}
}