{
  "type": "Feature",
  "properties": {
    "gn:admin1_code":"46.0",
    "gn:asciiname":"An Quang",
    "gn:country_code":"VN",
    "gn:dem":7,
    "gn:feature_class":"P",
    "gn:feature_code":"PPL",
    "gn:name":"An Quang",
    "gn:population":0,
    "gn:timezone":"Asia/Ho_Chi_Minh",
    "iso:country":"VN",
    "name:und_x_variant":[
        "\u0110\u1ebfgi"
    ],
    "wof:name":"An Quang",
    "wof:placetype":"locality"
},
  "geometry": {"coordinates":[109.20153000000001,14.12382],"type":"Point"}
}