{
  "type": "Feature",
  "properties": {
    "gn:admin1_code":"71.0",
    "gn:asciiname":"Nui Dua",
    "gn:country_code":"VN",
    "gn:dem":16,
    "gn:feature_class":"P",
    "gn:feature_code":"PPL",
    "gn:name":"N\u00fai D\u1ee9a",
    "gn:population":0,
    "gn:timezone":"Asia/Ho_Chi_Minh",
    "iso:country":"VN",
    "name:vie_x_preferred":[
        "N\u00fai D\u1ee9a"
    ],
    "wof:name":"Nui Dua",
    "wof:placetype":"locality"
},
  "geometry": {"coordinates":[106.01418,21.38215],"type":"Point"}
}