{
  "type": "Feature",
  "properties": {
    "gn:admin1_code":"32.0",
    "gn:asciiname":"Ban Co Do",
    "gn:country_code":"VN",
    "gn:dem":167,
    "gn:feature_class":"P",
    "gn:feature_code":"PPL",
    "gn:name":"B\u1ea3n Co \u0110\u1edb",
    "gn:population":0,
    "gn:timezone":"Asia/Ho_Chi_Minh",
    "iso:country":"VN",
    "name:vie_x_preferred":[
        "B\u1ea3n Co \u0110\u1edb"
    ],
    "wof:name":"Ban Co Do",
    "wof:placetype":"locality"
},
  "geometry": {"coordinates":[103.56583999999999,21.82264],"type":"Point"}
}