{
  "type": "Feature",
  "properties": {
    "iso:country":"VN",
    "name:unk_x_variant":[
        "Pho Cho"
    ],
    "qs:gn_country":"VN",
    "qs:gn_fcode":"PPL",
    "qs:gn_pop":0,
    "qs:name":"Suvui",
    "qs:name_adm0":"Vietnam",
    "qs:name_adm1":"Hoa Binh",
    "qs:photos":61,
    "qs:photos_1k":12,
    "qs:photos_9k":1,
    "qs:photos_9r":2,
    "qs:photos_all":61,
    "qs:photos_sr":2,
    "qs:placetype":"Town",
    "qs:pop_sr":"0",
    "qs:woe_adm0":23424984,
    "wof:name":"Suvui",
    "wof:placetype":"locality"
},
  "geometry": {"coordinates":[105.08333,20.76667],"type":"Point"}
}