{
  "type": "Feature",
  "properties": {
    "gn:admin1_code":"74.0",
    "gn:asciiname":"Lac Trung",
    "gn:country_code":"VN",
    "gn:dem":7,
    "gn:feature_class":"P",
    "gn:feature_code":"PPL",
    "gn:name":"L\u1ea1c Trung",
    "gn:population":0,
    "gn:timezone":"Asia/Ho_Chi_Minh",
    "iso:country":"VN",
    "name:und_x_variant":[
        "Choa B\u00ean",
        "L\u1ea1c Trung"
    ],
    "wof:name":"Lac Trung",
    "wof:placetype":"locality"
},
  "geometry": {"coordinates":[105.99387,21.24289],"type":"Point"}
}