{
  "type": "Feature",
  "properties": {
    "gn:admin1_code":"5.0",
    "gn:asciiname":"Knau Gat",
    "gn:cc2":"VN",
    "gn:country_code":"VN",
    "gn:dem":580,
    "gn:feature_class":"P",
    "gn:feature_code":"PPL",
    "gn:name":"Knau Gat",
    "gn:population":0,
    "gn:timezone":"Asia/Ho_Chi_Minh",
    "iso:country":"VN",
    "name:und_x_variant":[
        "Khau Gat",
        "Knau Gat"
    ],
    "wof:name":"Knau Gat",
    "wof:placetype":"locality"
},
  "geometry": {"coordinates":[106.56667,22.81667],"type":"Point"}
}