{
  "type": "Feature",
  "properties": {
    "gn:admin1_code":"55.0",
    "gn:asciiname":"Mang But",
    "gn:country_code":"VN",
    "gn:dem":1183,
    "gn:feature_class":"P",
    "gn:feature_code":"PPL",
    "gn:name":"M\u0103ng B\u00fat",
    "gn:population":0,
    "gn:timezone":"Asia/Ho_Chi_Minh",
    "iso:country":"VN",
    "name:und_x_variant":[
        "Nang Buk",
        "Mang Buk",
        "Mang B\u00fac"
    ],
    "name:vie_x_preferred":[
        "M\u0103ng B\u00fat"
    ],
    "wof:name":"Mang But",
    "wof:placetype":"locality"
},
  "geometry": {"coordinates":[108.19661000000001,14.85008],"type":"Point"}
}