{
  "type": "Feature",
  "properties": {
    "gn:admin1_code":"50.0",
    "gn:asciiname":"Pac Mieng",
    "gn:country_code":"VN",
    "gn:dem":92,
    "gn:feature_class":"P",
    "gn:feature_code":"PPL",
    "gn:name":"P\u00e1c Mi\u1ec1ng",
    "gn:population":0,
    "gn:timezone":"Asia/Ho_Chi_Minh",
    "iso:country":"VN",
    "name:vie_x_preferred":[
        "P\u00e1c Mi\u1ec1ng"
    ],
    "wof:name":"Pac Mieng",
    "wof:placetype":"locality"
},
  "geometry": {"coordinates":[105.01232,22.6407],"type":"Point"}
}