{
  "type": "Feature",
  "properties": {
    "gn:admin1_code":"67.0",
    "gn:asciiname":"Xom O Bap",
    "gn:cc2":"VN",
    "gn:country_code":"VN",
    "gn:dem":5,
    "gn:feature_class":"P",
    "gn:feature_code":"PPL",
    "gn:name":"X\u00f3m \u00d4 B\u1ea5p",
    "gn:population":0,
    "gn:timezone":"Asia/Ho_Chi_Minh",
    "iso:country":"VN",
    "name:und_x_variant":[
        "\u00d4 B\u1ea5p",
        "X\u00f3m \u00d4 B\u1ea5p"
    ],
    "wof:name":"Xom O Bap",
    "wof:placetype":"locality"
},
  "geometry": {"coordinates":[106.28,9.85111],"type":"Point"}
}