{
  "type": "Feature",
  "properties": {
    "gn:admin1_code":"72.0",
    "gn:asciiname":"Cum Nhuong",
    "gn:country_code":"VN",
    "gn:dem":702,
    "gn:feature_class":"P",
    "gn:feature_code":"PPL",
    "gn:name":"C\u1ee7m Nh\u01b0\u01a1ng",
    "gn:population":0,
    "gn:timezone":"Asia/Ho_Chi_Minh",
    "iso:country":"VN",
    "wof:name":"Cum Nhuong",
    "wof:placetype":"locality"
},
  "geometry": {"coordinates":[105.95999999999999,22.35696],"type":"Point"}
}