{
  "type": "Feature",
  "properties": {
    "gn:admin1_code":"58.0",
    "gn:asciiname":"Truong Son",
    "gn:country_code":"VN",
    "gn:dem":10,
    "gn:feature_class":"P",
    "gn:feature_code":"PPL",
    "gn:name":"Tr\u01b0\u1eddng S\u01a1n",
    "gn:population":0,
    "gn:timezone":"Asia/Ho_Chi_Minh",
    "iso:country":"VN",
    "name:vie_x_preferred":[
        "Tr\u01b0\u1eddng S\u01a1n"
    ],
    "wof:name":"Truong Son",
    "wof:placetype":"locality"
},
  "geometry": {"coordinates":[105.69119999999999,18.77319],"type":"Point"}
}