{
  "type": "Feature",
  "properties": {
    "gn:admin1_code":"71.0",
    "gn:asciiname":"Van Cam",
    "gn:country_code":"VN",
    "gn:dem":12,
    "gn:feature_class":"P",
    "gn:feature_code":"PPL",
    "gn:name":"V\u00e2n C\u1ea9m",
    "gn:population":0,
    "gn:timezone":"Asia/Ho_Chi_Minh",
    "iso:country":"VN",
    "name:und_x_variant":[
        "V\u00e2n C\u00e2m"
    ],
    "name:vie_x_preferred":[
        "V\u00e2n C\u1ea9m"
    ],
    "wof:name":"Van Cam",
    "wof:placetype":"locality"
},
  "geometry": {"coordinates":[106.01421999999999,21.28964],"type":"Point"}
}