{
  "type": "Feature",
  "properties": {
    "gn:admin1_code":"44.0",
    "gn:asciiname":"Dong Da",
    "gn:country_code":"VN",
    "gn:dem":16,
    "gn:feature_class":"P",
    "gn:feature_code":"PPLA2",
    "gn:name":"\u0110\u1ed1ng \u0110a",
    "gn:population":0,
    "gn:timezone":"Asia/Ho_Chi_Minh",
    "iso:country":"VN",
    "name:vie_x_preferred":[
        "\u0110\u1ed1ng \u0110a"
    ],
    "wof:name":"Dong Da",
    "wof:placetype":"locality"
},
  "geometry": {"coordinates":[105.83096999999999,21.02009],"type":"Point"}
}