{
  "type": "Feature",
  "properties": {
    "gn:admin1_code":"59.0",
    "gn:asciiname":"Xom Men",
    "gn:country_code":"VN",
    "gn:dem":281,
    "gn:feature_class":"P",
    "gn:feature_code":"PPL",
    "gn:name":"X\u00f3m M\u1ec5n",
    "gn:population":0,
    "gn:timezone":"Asia/Ho_Chi_Minh",
    "iso:country":"VN",
    "name:vie_x_preferred":[
        "X\u00f3m M\u1ec5n"
    ],
    "wof:name":"Xom Men",
    "wof:placetype":"locality"
},
  "geometry": {"coordinates":[105.61622,20.33118],"type":"Point"}
}