{
  "type": "Feature",
  "properties": {
    "gn:admin1_code":"32.0",
    "gn:asciiname":"Na Nghe",
    "gn:country_code":"VN",
    "gn:dem":618,
    "gn:feature_class":"P",
    "gn:feature_code":"PPL",
    "gn:name":"N\u00e0 Ngh\u00e8",
    "gn:population":0,
    "gn:timezone":"Asia/Ho_Chi_Minh",
    "iso:country":"VN",
    "name:und_x_variant":[
        "B\u1ea3n Nh\u00ea"
    ],
    "name:vie_x_preferred":[
        "N\u00e0 Ngh\u00e8"
    ],
    "wof:name":"Na Nghe",
    "wof:placetype":"locality"
},
  "geometry": {"coordinates":[104.04434999999999,21.18901],"type":"Point"}
}