{
  "type": "Feature",
  "properties": {
    "gn:admin1_code":"75.0",
    "gn:asciiname":"Ben Tranh",
    "gn:country_code":"VN",
    "gn:dem":18,
    "gn:feature_class":"P",
    "gn:feature_code":"PPL",
    "gn:name":"B\u1ebfn Tranh",
    "gn:population":0,
    "gn:timezone":"Asia/Ho_Chi_Minh",
    "iso:country":"VN",
    "name:und_x_variant":[
        "X\u00f3m B\u1ebfn Tranh"
    ],
    "name:vie_x_preferred":[
        "B\u1ebfn Tranh"
    ],
    "wof:name":"Ben Tranh",
    "wof:placetype":"locality"
},
  "geometry": {"coordinates":[106.38961,11.22964],"type":"Point"}
}