{
  "type": "Feature",
  "properties": {
    "gn:admin1_code":"2.0",
    "gn:asciiname":"Kouei Y",
    "gn:country_code":"VN",
    "gn:dem":296,
    "gn:feature_class":"P",
    "gn:feature_code":"PPL",
    "gn:name":"Kouei Y",
    "gn:population":0,
    "gn:timezone":"Asia/Ho_Chi_Minh",
    "iso:country":"VN",
    "wof:name":"Kouei Y",
    "wof:placetype":"locality"
},
  "geometry": {"coordinates":[106.58333,22.55],"type":"Point"}
}