{
  "type": "Feature",
  "properties": {
    "gn:admin1_code":"90.0",
    "gn:asciiname":"Thai Giang Tchai",
    "gn:country_code":"VN",
    "gn:dem":629,
    "gn:feature_class":"P",
    "gn:feature_code":"PPL",
    "gn:name":"Thai Giang Tchai",
    "gn:population":0,
    "gn:timezone":"Asia/Ho_Chi_Minh",
    "iso:country":"VN",
    "wof:name":"Thai Giang Tchai",
    "wof:placetype":"locality"
},
  "geometry": {"coordinates":[104.18333,22.68333],"type":"Point"}
}