{
  "type": "Feature",
  "properties": {
    "gn:admin1_code":"19.0",
    "gn:asciiname":"Na Luong",
    "gn:cc2":"VN",
    "gn:country_code":"VN",
    "gn:dem":112,
    "gn:feature_class":"P",
    "gn:feature_code":"PPL",
    "gn:name":"N\u00e0 Lu\u00f4ng",
    "gn:population":0,
    "gn:timezone":"Asia/Ho_Chi_Minh",
    "iso:country":"VN",
    "name:und_x_variant":[
        "Na Long",
        "N\u00e0 Lu\u00f4ng"
    ],
    "wof:name":"Na Luong",
    "wof:placetype":"locality"
},
  "geometry": {"coordinates":[104.73333,22.25],"type":"Point"}
}