{
  "type": "Feature",
  "properties": {
    "gn:admin1_code":"23.0",
    "gn:asciiname":"Conion Pill",
    "gn:country_code":"VN",
    "gn:dem":876,
    "gn:feature_class":"P",
    "gn:feature_code":"PPL",
    "gn:name":"Conion Pill",
    "gn:population":0,
    "gn:timezone":"Asia/Ho_Chi_Minh",
    "iso:country":"VN",
    "wof:name":"Conion Pill",
    "wof:placetype":"locality"
},
  "geometry": {"coordinates":[107.98333,11.61667],"type":"Point"}
}