{
  "type": "Feature",
  "properties": {
    "gn:admin1_code":"65.0",
    "gn:asciiname":"Ap Thoi Thanh",
    "gn:cc2":"VN",
    "gn:country_code":"VN",
    "gn:dem":1,
    "gn:feature_class":"P",
    "gn:feature_code":"PPL",
    "gn:name":"\u1ea4p Th\u1edbi Thanh",
    "gn:population":0,
    "gn:timezone":"Asia/Ho_Chi_Minh",
    "iso:country":"VN",
    "name:und_x_variant":[
        "Th\u1edbi Thanh",
        "\u1ea4p Thanh Q\u1ee9i",
        "\u1ea4p Thanh Q\u01b0\u1edbi",
        "\u1ea4p Th\u1edbi Thanh"
    ],
    "wof:name":"Ap Thoi Thanh",
    "wof:placetype":"locality"
},
  "geometry": {"coordinates":[106.03528,9.46917],"type":"Point"}
}