{
  "type": "Feature",
  "properties": {
    "gn:admin1_code":"50.0",
    "gn:asciiname":"Coc Pou",
    "gn:country_code":"VN",
    "gn:dem":564,
    "gn:feature_class":"P",
    "gn:feature_code":"PPL",
    "gn:name":"Coc Pou",
    "gn:population":0,
    "gn:timezone":"Asia/Ho_Chi_Minh",
    "iso:country":"VN",
    "wof:name":"Coc Pou",
    "wof:placetype":"locality"
},
  "geometry": {"coordinates":[104.55,22.71667],"type":"Point"}
}