{
  "type": "Feature",
  "properties": {
    "gn:admin1_code":"79.0",
    "gn:asciiname":"Tru Ha",
    "gn:country_code":"VN",
    "gn:dem":7,
    "gn:feature_class":"P",
    "gn:feature_code":"PPL",
    "gn:name":"Tr\u1ee5 H\u1ea1",
    "gn:population":0,
    "gn:timezone":"Asia/Ho_Chi_Minh",
    "iso:country":"VN",
    "name:vie_x_preferred":[
        "Tr\u1ee5 H\u1ea1"
    ],
    "wof:name":"Tru Ha",
    "wof:placetype":"locality"
},
  "geometry": {"coordinates":[106.37286,21.04793],"type":"Point"}
}