{
  "type": "Feature",
  "properties": {
    "gn:admin1_code":"52.0",
    "gn:asciiname":"Thuong Noi",
    "gn:country_code":"VN",
    "gn:dem":5,
    "gn:feature_class":"P",
    "gn:feature_code":"PPL",
    "gn:name":"Th\u01b0\u1ee3ng N\u1ed9i",
    "gn:population":0,
    "gn:timezone":"Asia/Ho_Chi_Minh",
    "iso:country":"VN",
    "name:und_x_variant":[
        "Thuong Nai",
        "Th\u01b0\u1ee3ng N\u1ed9i"
    ],
    "wof:name":"Thuong Noi",
    "wof:placetype":"locality"
},
  "geometry": {"coordinates":[105.90000000000001,18.28333],"type":"Point"}
}