{
  "type": "Feature",
  "properties": {
    "gn:admin1_code":"92.0",
    "gn:asciiname":"Ho Dom",
    "gn:country_code":"VN",
    "gn:dem":1002,
    "gn:feature_class":"P",
    "gn:feature_code":"PPL",
    "gn:name":"H\u1ed1 D\u1ed1m",
    "gn:population":0,
    "gn:timezone":"Asia/Ho_Chi_Minh",
    "iso:country":"VN",
    "name:und_x_variant":[
        "B\u1ea3n Hua Gi\u00f4m"
    ],
    "name:vie_x_preferred":[
        "H\u1ed1 D\u1ed1m"
    ],
    "wof:name":"Ho Dom",
    "wof:placetype":"locality"
},
  "geometry": {"coordinates":[103.12913,21.54819],"type":"Point"}
}