{
  "type": "Feature",
  "properties": {
    "gn:admin1_code":"52.0",
    "gn:asciiname":"Vinh Ai",
    "gn:country_code":"VN",
    "gn:dem":6,
    "gn:feature_class":"P",
    "gn:feature_code":"PPL",
    "gn:name":"V\u0129nh \u00c1i",
    "gn:population":0,
    "gn:timezone":"Asia/Ho_Chi_Minh",
    "iso:country":"VN",
    "name:und_x_variant":[
        "Xom Vinh Ai",
        "V\u0129nh \u00c1i"
    ],
    "wof:name":"Vinh Ai",
    "wof:placetype":"locality"
},
  "geometry": {"coordinates":[106.26667,18.15],"type":"Point"}
}