{
  "type": "Feature",
  "properties": {
    "gn:admin1_code":"32.0",
    "gn:asciiname":"Ban Phu Luong",
    "gn:country_code":"VN",
    "gn:dem":668,
    "gn:feature_class":"P",
    "gn:feature_code":"PPL",
    "gn:name":"B\u1ea3n Ph\u00fa L\u01b0\u01a1ng",
    "gn:population":0,
    "gn:timezone":"Asia/Ho_Chi_Minh",
    "iso:country":"VN",
    "name:vie_x_preferred":[
        "B\u1ea3n Ph\u00fa L\u01b0\u01a1ng"
    ],
    "wof:name":"Ban Phu Luong",
    "wof:placetype":"locality"
},
  "geometry": {"coordinates":[104.18409,21.06466],"type":"Point"}
}