{
  "type": "Feature",
  "properties": {
    "gn:admin1_code":"40.0",
    "gn:asciiname":"La Canh Dom",
    "gn:cc2":"VN",
    "gn:country_code":"VN",
    "gn:dem":136,
    "gn:feature_class":"P",
    "gn:feature_code":"PPL",
    "gn:name":"La Canh Dom",
    "gn:population":0,
    "gn:timezone":"Asia/Ho_Chi_Minh",
    "iso:country":"VN",
    "name:und_x_variant":[
        "Canh Dom",
        "La Cahn Dom",
        "La Cahm Dom",
        "La Canh Dong",
        "La Canh Dom"
    ],
    "wof:name":"La Canh Dom",
    "wof:placetype":"locality"
},
  "geometry": {"coordinates":[107.36667,11.55],"type":"Point"}
}