{
  "type": "Feature",
  "properties": {
    "gn:admin1_code":"89.0",
    "gn:asciiname":"Hua Sao Chai",
    "gn:country_code":"VN",
    "gn:dem":776,
    "gn:feature_class":"P",
    "gn:feature_code":"PPL",
    "gn:name":"Hua Sao Ch\u1ea3i",
    "gn:population":0,
    "gn:timezone":"Asia/Ho_Chi_Minh",
    "iso:country":"VN",
    "name:und_x_variant":[
        "Ho Sao Ch\u1ea3i"
    ],
    "name:vie_x_preferred":[
        "Hua Sao Ch\u1ea3i"
    ],
    "wof:name":"Hua Sao Chai",
    "wof:placetype":"locality"
},
  "geometry": {"coordinates":[103.34533999999999,22.58485],"type":"Point"}
}