{
  "type": "Feature",
  "properties": {
    "gn:admin1_code":"39.0",
    "gn:asciiname":"Tham Giam",
    "gn:country_code":"VN",
    "gn:dem":200,
    "gn:feature_class":"P",
    "gn:feature_code":"PPL",
    "gn:name":"Th\u00e2m Gi\u1ea7m",
    "gn:population":0,
    "gn:timezone":"Asia/Ho_Chi_Minh",
    "iso:country":"VN",
    "wof:name":"Tham Giam",
    "wof:placetype":"locality"
},
  "geometry": {"coordinates":[106.66667,22.11667000000001],"type":"Point"}
}