{
  "type": "Feature",
  "properties": {
    "gn:admin1_code":"58.0",
    "gn:asciiname":"Doi Muoi Ba",
    "gn:country_code":"VN",
    "gn:dem":12,
    "gn:feature_class":"P",
    "gn:feature_code":"PPL",
    "gn:name":"\u0110\u1ed9i M\u01b0\u1eddi Ba",
    "gn:population":0,
    "gn:timezone":"Asia/Ho_Chi_Minh",
    "iso:country":"VN",
    "name:vie_x_preferred":[
        "\u0110\u1ed9i M\u01b0\u1eddi Ba"
    ],
    "name:vie_x_variant":[
        "\u0110\u1ed9i 13"
    ],
    "wof:name":"Doi Muoi Ba",
    "wof:placetype":"locality"
},
  "geometry": {"coordinates":[105.62854,18.86756],"type":"Point"}
}