{
  "type": "Feature",
  "properties": {
    "gn:admin1_code":"1.0",
    "gn:asciiname":"Vinh Hiep",
    "gn:country_code":"VN",
    "gn:dem":2,
    "gn:feature_class":"P",
    "gn:feature_code":"PPL",
    "gn:name":"V\u0129nh Hi\u1ec7p",
    "gn:population":0,
    "gn:timezone":"Asia/Ho_Chi_Minh",
    "iso:country":"VN",
    "name:vie_x_preferred":[
        "V\u0129nh Hi\u1ec7p"
    ],
    "wof:name":"Vinh Hiep",
    "wof:placetype":"locality"
},
  "geometry": {"coordinates":[105.26061,10.36968],"type":"Point"}
}