{
  "type": "Feature",
  "properties": {
    "gn:admin1_code":"32.0",
    "gn:asciiname":"Huong Can",
    "gn:country_code":"VN",
    "gn:dem":261,
    "gn:feature_class":"P",
    "gn:feature_code":"PPL",
    "gn:name":"H\u01b0\u01a1ng C\u00e2n",
    "gn:population":0,
    "gn:timezone":"Asia/Ho_Chi_Minh",
    "iso:country":"VN",
    "wof:name":"Huong Can",
    "wof:placetype":"locality"
},
  "geometry": {"coordinates":[104.71666999999999,20.95],"type":"Point"}
}