{
  "type": "Feature",
  "properties": {
    "gn:admin1_code":"58.0",
    "gn:asciiname":"Kim Lien",
    "gn:country_code":"VN",
    "gn:dem":6,
    "gn:feature_class":"P",
    "gn:feature_code":"PPL",
    "gn:name":"Kim Li\u00ean",
    "gn:population":0,
    "gn:timezone":"Asia/Ho_Chi_Minh",
    "iso:country":"VN",
    "name:vie_x_preferred":[
        "Kim Li\u00ean"
    ],
    "wof:name":"Kim Lien",
    "wof:placetype":"locality"
},
  "geometry": {"coordinates":[105.61583,19.02493],"type":"Point"}
}