{
  "type": "Feature",
  "properties": {
    "gn:admin1_code":"89.0",
    "gn:asciiname":"Ban Muong Moi",
    "gn:country_code":"VN",
    "gn:dem":635,
    "gn:feature_class":"P",
    "gn:feature_code":"PPL",
    "gn:name":"B\u1ea3n M\u01b0\u01a1ng M\u1edbi",
    "gn:population":0,
    "gn:timezone":"Asia/Ho_Chi_Minh",
    "iso:country":"VN",
    "name:vie_x_preferred":[
        "B\u1ea3n M\u01b0\u01a1ng M\u1edbi"
    ],
    "wof:name":"Ban Muong Moi",
    "wof:placetype":"locality"
},
  "geometry": {"coordinates":[103.62697,22.31627000000001],"type":"Point"}
}