{
  "type": "Feature",
  "properties": {
    "gn:admin1_code":"43.0",
    "gn:asciiname":"Loi Ha",
    "gn:country_code":"VN",
    "gn:dem":68,
    "gn:feature_class":"P",
    "gn:feature_code":"PPL",
    "gn:name":"L\u1ee3i H\u00e0",
    "gn:population":0,
    "gn:timezone":"Asia/Ho_Chi_Minh",
    "iso:country":"VN",
    "name:vie_x_preferred":[
        "L\u1ee3i H\u00e0"
    ],
    "wof:name":"Loi Ha",
    "wof:placetype":"locality"
},
  "geometry": {"coordinates":[107.08091,11.07882],"type":"Point"}
}