{
  "type": "Feature",
  "properties": {
    "gn:admin1_code":"55.0",
    "gn:asciiname":"Rolaap",
    "gn:country_code":"VN",
    "gn:dem":737,
    "gn:feature_class":"P",
    "gn:feature_code":"PPL",
    "gn:name":"R\u00f4laap",
    "gn:population":0,
    "gn:timezone":"Asia/Ho_Chi_Minh",
    "iso:country":"VN",
    "name:und_x_variant":[
        "Dak Relaap",
        "Dak R\u01a1laap",
        "R\u00f4laap"
    ],
    "wof:name":"Rolaap",
    "wof:placetype":"locality"
},
  "geometry": {"coordinates":[107.94726,14.72727],"type":"Point"}
}