{
  "type": "Feature",
  "properties": {
    "gn:admin1_code":"23.0",
    "gn:asciiname":"Buon Deun Djiri",
    "gn:country_code":"VN",
    "gn:dem":514,
    "gn:feature_class":"P",
    "gn:feature_code":"PPL",
    "gn:name":"Bu\u00f4n Deun Djiri",
    "gn:population":0,
    "gn:timezone":"Asia/Ho_Chi_Minh",
    "iso:country":"VN",
    "wof:name":"Buon Deun Djiri",
    "wof:placetype":"locality"
},
  "geometry": {"coordinates":[108.21666999999999,12.16667],"type":"Point"}
}