{
  "type": "Feature",
  "properties": {
    "gn:admin1_code":"79.0",
    "gn:asciiname":"Gia Coc",
    "gn:country_code":"VN",
    "gn:dem":4,
    "gn:feature_class":"P",
    "gn:feature_code":"PPL",
    "gn:name":"Gia C\u1ed1c",
    "gn:population":0,
    "gn:timezone":"Asia/Ho_Chi_Minh",
    "iso:country":"VN",
    "wof:name":"Gia Coc",
    "wof:placetype":"locality"
},
  "geometry": {"coordinates":[106.23333,20.76667],"type":"Point"}
}