{
  "type": "Feature",
  "properties": {
    "gn:admin1_code":"72.0",
    "gn:asciiname":"Yen Nhuan",
    "gn:country_code":"VN",
    "gn:dem":251,
    "gn:feature_class":"P",
    "gn:feature_code":"PPL",
    "gn:name":"Y\u00ean Nhu\u1eadn",
    "gn:population":0,
    "gn:timezone":"Asia/Ho_Chi_Minh",
    "iso:country":"VN",
    "name:und_x_variant":[
        "Y\u00ean Nhu\u1eadn"
    ],
    "wof:name":"Yen Nhuan",
    "wof:placetype":"locality"
},
  "geometry": {"coordinates":[105.61667,22.05],"type":"Point"}
}