{
  "type": "Feature",
  "properties": {
    "gn:admin1_code":"87.0",
    "gn:asciiname":"Thoi Hoa A",
    "gn:country_code":"VN",
    "gn:dem":4,
    "gn:feature_class":"P",
    "gn:feature_code":"PPL",
    "gn:name":"Th\u1edbi H\u00f2a A",
    "gn:population":0,
    "gn:timezone":"Asia/Ho_Chi_Minh",
    "iso:country":"VN",
    "name:vie_x_preferred":[
        "Th\u1edbi H\u00f2a A"
    ],
    "wof:name":"Thoi Hoa A",
    "wof:placetype":"locality"
},
  "geometry": {"coordinates":[105.62273,10.13124],"type":"Point"}
}