{
  "type": "Feature",
  "properties": {
    "gn:admin1_code":"58.0",
    "gn:asciiname":"Trang Mao",
    "gn:country_code":"VN",
    "gn:dem":13,
    "gn:feature_class":"P",
    "gn:feature_code":"PPL",
    "gn:name":"Trang Mao",
    "gn:population":0,
    "gn:timezone":"Asia/Ho_Chi_Minh",
    "iso:country":"VN",
    "name:und_x_variant":[
        "Trang Den",
        "Trang Der",
        "Trang Mao"
    ],
    "wof:name":"Trang Mao",
    "wof:placetype":"locality"
},
  "geometry": {"coordinates":[105.43333,18.75],"type":"Point"}
}