{
  "type": "Feature",
  "properties": {
    "gn:admin1_code":"34.0",
    "gn:asciiname":"Lang Di",
    "gn:country_code":"VN",
    "gn:dem":353,
    "gn:feature_class":"P",
    "gn:feature_code":"PPL",
    "gn:name":"L\u00e0ng Di",
    "gn:population":0,
    "gn:timezone":"Asia/Ho_Chi_Minh",
    "iso:country":"VN",
    "name:und_x_variant":[
        "X\u00f3m Dy"
    ],
    "name:vie_x_preferred":[
        "L\u00e0ng Di"
    ],
    "wof:name":"Lang Di",
    "wof:placetype":"locality"
},
  "geometry": {"coordinates":[105.34754,20.36613],"type":"Point"}
}