{
  "type": "Feature",
  "properties": {
    "gn:admin1_code":"34.0",
    "gn:asciiname":"Sam Son",
    "gn:country_code":"VN",
    "gn:dem":10,
    "gn:feature_class":"P",
    "gn:feature_code":"PPL",
    "gn:name":"S\u1ea7m S\u01a1n",
    "gn:population":0,
    "gn:timezone":"Asia/Ho_Chi_Minh",
    "iso:country":"VN",
    "name:und_x_variant":[
        "S\u1ea7m S\u01a1n"
    ],
    "wof:name":"Sam Son",
    "wof:placetype":"locality"
},
  "geometry": {"coordinates":[105.90000000000001,19.73333],"type":"Point"}
}