{
  "type": "Feature",
  "properties": {
    "iso:country":"VN",
    "name:nld_x_preferred":[
        "C\u00e1t Ti\u00ean"
    ],
    "name:vie_x_preferred":[
        "C\u00e1t Ti\u00ean"
    ],
    "qs:gn_pop":0,
    "qs:name":"Ninh Ph\u01b0\u1edbc (1)",
    "qs:name_adm0":"Vietnam",
    "qs:name_adm1":"Khanh Hoa",
    "qs:photos":37,
    "qs:photos_1k":7,
    "qs:photos_9k":1,
    "qs:photos_9r":2,
    "qs:photos_all":37,
    "qs:photos_sr":2,
    "qs:placetype":"Town",
    "qs:pop_sr":"0",
    "qs:woe_adm0":23424984,
    "wof:name":"Ninh Ph\u01b0\u1edbc (1)",
    "wof:placetype":"locality"
},
  "geometry": {"coordinates":[109.286402,12.431517],"type":"Point"}
}