{
  "type": "Feature",
  "properties": {
    "gn:admin1_code":"72.0",
    "gn:asciiname":"Khuoi Dum",
    "gn:country_code":"VN",
    "gn:dem":177,
    "gn:feature_class":"P",
    "gn:feature_code":"PPL",
    "gn:name":"Khu\u1ed5i D\u0169m",
    "gn:population":0,
    "gn:timezone":"Asia/Ho_Chi_Minh",
    "iso:country":"VN",
    "name:vie_x_preferred":[
        "Khu\u1ed5i D\u0169m"
    ],
    "wof:name":"Khuoi Dum",
    "wof:placetype":"locality"
},
  "geometry": {"coordinates":[105.84007,22.17878],"type":"Point"}
}