{
  "type": "Feature",
  "properties": {
    "gn:admin1_code":"73.0",
    "gn:asciiname":"Vinh Loi",
    "gn:country_code":"VN",
    "gn:dem":2,
    "gn:feature_class":"P",
    "gn:feature_code":"PPL",
    "gn:name":"V\u0129nh L\u1ee3i",
    "gn:population":0,
    "gn:timezone":"Asia/Ho_Chi_Minh",
    "iso:country":"VN",
    "name:vie_x_preferred":[
        "V\u0129nh L\u1ee3i"
    ],
    "wof:name":"Vinh Loi",
    "wof:placetype":"locality"
},
  "geometry": {"coordinates":[105.71532000000001,9.22016],"type":"Point"}
}