{
  "type": "Feature",
  "properties": {
    "gn:admin1_code":"47.0",
    "gn:asciiname":"Gia Huynh",
    "gn:country_code":"VN",
    "gn:dem":116,
    "gn:feature_class":"P",
    "gn:feature_code":"PPL",
    "gn:name":"Gia Huynh",
    "gn:population":0,
    "gn:timezone":"Asia/Ho_Chi_Minh",
    "iso:country":"VN",
    "name:und_x_variant":[
        "\u1ea4p Gia Hu\u1ef3nh"
    ],
    "name:vie_x_preferred":[
        "Gia Huynh"
    ],
    "wof:name":"Gia Huynh",
    "wof:placetype":"locality"
},
  "geometry": {"coordinates":[107.54141,10.98581],"type":"Point"}
}