{
  "type": "Feature",
  "properties": {
    "gn:admin1_code":"58.0",
    "gn:asciiname":"Hong Phong",
    "gn:country_code":"VN",
    "gn:dem":23,
    "gn:feature_class":"P",
    "gn:feature_code":"PPL",
    "gn:name":"H\u1ed3ng Phong",
    "gn:population":0,
    "gn:timezone":"Asia/Ho_Chi_Minh",
    "iso:country":"VN",
    "name:vie_x_preferred":[
        "H\u1ed3ng Phong"
    ],
    "wof:name":"Hong Phong",
    "wof:placetype":"locality"
},
  "geometry": {"coordinates":[105.27294999999999,18.89854],"type":"Point"}
}