{
  "type": "Feature",
  "properties": {
    "gn:admin1_code":"27.0",
    "gn:asciiname":"Trung An",
    "gn:country_code":"VN",
    "gn:dem":8,
    "gn:feature_class":"P",
    "gn:feature_code":"PPL",
    "gn:name":"Trung An",
    "gn:population":0,
    "gn:timezone":"Asia/Ho_Chi_Minh",
    "iso:country":"VN",
    "name:und_x_variant":[
        "Trung Yen",
        "Trung An"
    ],
    "wof:name":"Trung An",
    "wof:placetype":"locality"
},
  "geometry": {"coordinates":[108.73333,15.36667],"type":"Point"}
}