{
  "type": "Feature",
  "properties": {
    "gn:admin1_code":"81.0",
    "gn:asciiname":"Le Chi",
    "gn:country_code":"VN",
    "gn:dem":5,
    "gn:feature_class":"P",
    "gn:feature_code":"PPL",
    "gn:name":"L\u1ec7 Chi",
    "gn:population":0,
    "gn:timezone":"Asia/Ho_Chi_Minh",
    "iso:country":"VN",
    "name:vie_x_preferred":[
        "L\u1ec7 Chi"
    ],
    "wof:name":"Le Chi",
    "wof:placetype":"locality"
},
  "geometry": {"coordinates":[106.15234,20.66219],"type":"Point"}
}