{
  "type": "Feature",
  "properties": {
    "gn:admin1_code":"39.0",
    "gn:asciiname":"Dien Phong",
    "gn:country_code":"VN",
    "gn:dem":259,
    "gn:feature_class":"P",
    "gn:feature_code":"PPL",
    "gn:name":"Di\u1ec1n Phong",
    "gn:population":0,
    "gn:timezone":"Asia/Ho_Chi_Minh",
    "iso:country":"VN",
    "wof:name":"Dien Phong",
    "wof:placetype":"locality"
},
  "geometry": {"coordinates":[106.61667,21.98333],"type":"Point"}
}