{
  "type": "Feature",
  "properties": {
    "gn:admin1_code":"68.0",
    "gn:asciiname":"Ban Na Muong",
    "gn:country_code":"VN",
    "gn:dem":289,
    "gn:feature_class":"P",
    "gn:feature_code":"PPLL",
    "gn:name":"B\u1ea3n N\u00e0 Mu\u1ed5ng",
    "gn:population":0,
    "gn:timezone":"Asia/Ho_Chi_Minh",
    "iso:country":"VN",
    "name:vie_x_preferred":[
        "B\u1ea3n N\u00e0 Mu\u1ed5ng"
    ],
    "wof:name":"Ban Na Muong",
    "wof:placetype":"locality"
},
  "geometry": {"coordinates":[105.29136,22.50771],"type":"Point"}
}