{
  "type": "Feature",
  "properties": {
    "gn:admin1_code":"32.0",
    "gn:asciiname":"Ban Bua Thuong",
    "gn:country_code":"VN",
    "gn:dem":180,
    "gn:feature_class":"P",
    "gn:feature_code":"PPL",
    "gn:name":"B\u1ea3n B\u00f9a Th\u01b0\u1ee3ng",
    "gn:population":0,
    "gn:timezone":"Asia/Ho_Chi_Minh",
    "iso:country":"VN",
    "name:vie_x_preferred":[
        "B\u1ea3n B\u00f9a Th\u01b0\u1ee3ng"
    ],
    "wof:name":"Ban Bua Thuong",
    "wof:placetype":"locality"
},
  "geometry": {"coordinates":[104.61229,21.20716],"type":"Point"}
}