{
  "type": "Feature",
  "properties": {
    "gn:admin1_code":"79.0",
    "gn:asciiname":"Bang Lan",
    "gn:country_code":"VN",
    "gn:dem":6,
    "gn:feature_class":"P",
    "gn:feature_code":"PPL",
    "gn:name":"B\u1eb1ng Lan",
    "gn:population":0,
    "gn:timezone":"Asia/Ho_Chi_Minh",
    "iso:country":"VN",
    "name:vie_x_preferred":[
        "B\u1eb1ng Lan"
    ],
    "wof:name":"Bang Lan",
    "wof:placetype":"locality"
},
  "geometry": {"coordinates":[106.49097,20.94185],"type":"Point"}
}