{
  "type": "Feature",
  "properties": {
    "gn:admin1_code":"88.0",
    "gn:asciiname":"Ban Don",
    "gn:country_code":"VN",
    "gn:dem":181,
    "gn:feature_class":"P",
    "gn:feature_code":"PPL",
    "gn:name":"B\u1ea3n \u0110\u00f4n",
    "gn:population":0,
    "gn:timezone":"Asia/Ho_Chi_Minh",
    "iso:country":"VN",
    "name:vie_x_preferred":[
        "B\u1ea3n \u0110\u00f4n"
    ],
    "wof:name":"Ban Don",
    "wof:placetype":"locality"
},
  "geometry": {"coordinates":[107.78272,12.88762],"type":"Point"}
}