{
  "type": "Feature",
  "properties": {
    "gn:admin1_code":"88.0",
    "gn:asciiname":"Ban Toi",
    "gn:country_code":"VN",
    "gn:dem":107,
    "gn:feature_class":"P",
    "gn:feature_code":"PPL",
    "gn:name":"Ban T\u00f4i",
    "gn:population":0,
    "gn:timezone":"Asia/Ho_Chi_Minh",
    "iso:country":"VN",
    "wof:name":"Ban Toi",
    "wof:placetype":"locality"
},
  "geometry": {"coordinates":[108.73333,13.06667],"type":"Point"}
}