{
  "type": "Feature",
  "properties": {
    "gn:admin1_code":"68.0",
    "gn:asciiname":"Bac Hop",
    "gn:country_code":"VN",
    "gn:dem":114,
    "gn:feature_class":"P",
    "gn:feature_code":"PPL",
    "gn:name":"B\u1eafc H\u1ee3p",
    "gn:population":0,
    "gn:timezone":"Asia/Ho_Chi_Minh",
    "iso:country":"VN",
    "name:vie_x_preferred":[
        "B\u1eafc H\u1ee3p"
    ],
    "wof:name":"Bac Hop",
    "wof:placetype":"locality"
},
  "geometry": {"coordinates":[105.35212,21.96147],"type":"Point"}
}