{
  "type": "Feature",
  "properties": {
    "gn:admin1_code":"32.0",
    "gn:asciiname":"Ban Co Muong",
    "gn:country_code":"VN",
    "gn:dem":1030,
    "gn:feature_class":"P",
    "gn:feature_code":"PPL",
    "gn:name":"B\u1ea3n Co Mu\u00f4ng",
    "gn:population":0,
    "gn:timezone":"Asia/Ho_Chi_Minh",
    "iso:country":"VN",
    "name:vie_x_preferred":[
        "B\u1ea3n Co Mu\u00f4ng"
    ],
    "wof:name":"Ban Co Muong",
    "wof:placetype":"locality"
},
  "geometry": {"coordinates":[103.94365000000001,21.11275],"type":"Point"}
}