{
  "type": "Feature",
  "properties": {
    "gn:admin1_code":"86.0",
    "gn:asciiname":"Hoang Tan",
    "gn:country_code":"VN",
    "gn:dem":16,
    "gn:feature_class":"P",
    "gn:feature_code":"PPL",
    "gn:name":"Ho\u00e0ng T\u00e2n",
    "gn:population":0,
    "gn:timezone":"Asia/Ho_Chi_Minh",
    "iso:country":"VN",
    "name:vie_x_preferred":[
        "Ho\u00e0ng T\u00e2n"
    ],
    "wof:name":"Hoang Tan",
    "wof:placetype":"locality"
},
  "geometry": {"coordinates":[105.49445,21.32239],"type":"Point"}
}