{
  "type": "Feature",
  "properties": {
    "gn:admin1_code":"49.0",
    "gn:asciiname":"Plei Bia Tih",
    "gn:country_code":"VN",
    "gn:dem":723,
    "gn:feature_class":"P",
    "gn:feature_code":"PPL",
    "gn:name":"Plei Bia Tih",
    "gn:population":0,
    "gn:timezone":"Asia/Ho_Chi_Minh",
    "iso:country":"VN",
    "name:und_x_variant":[
        "Plei Bia",
        "Plei Bia Tih"
    ],
    "wof:name":"Plei Bia Tih",
    "wof:placetype":"locality"
},
  "geometry": {"coordinates":[108.08333,13.93333],"type":"Point"}
}