{
  "type": "Feature",
  "properties": {
    "gn:admin1_code":"88.0",
    "gn:asciiname":"Buon Krai",
    "gn:country_code":"VN",
    "gn:dem":426,
    "gn:feature_class":"P",
    "gn:feature_code":"PPL",
    "gn:name":"Bu\u00f4n Krai",
    "gn:population":0,
    "gn:timezone":"Asia/Ho_Chi_Minh",
    "iso:country":"VN",
    "name:vie_x_preferred":[
        "Bu\u00f4n Krai"
    ],
    "wof:name":"Buon Krai",
    "wof:placetype":"locality"
},
  "geometry": {"coordinates":[108.2195,12.42189],"type":"Point"}
}