{
  "type": "Feature",
  "properties": {
    "gn:admin1_code":"90.0",
    "gn:asciiname":"Nam Tsin",
    "gn:country_code":"VN",
    "gn:dem":987,
    "gn:feature_class":"P",
    "gn:feature_code":"PPL",
    "gn:name":"Nam Tsin",
    "gn:population":0,
    "gn:timezone":"Asia/Ho_Chi_Minh",
    "iso:country":"VN",
    "wof:name":"Nam Tsin",
    "wof:placetype":"locality"
},
  "geometry": {"coordinates":[104.21666999999999,22.61667000000001],"type":"Point"}
}