{
  "type": "Feature",
  "properties": {
    "gn:admin1_code":"89.0",
    "gn:asciiname":"Ban Nam It",
    "gn:country_code":"VN",
    "gn:dem":565,
    "gn:feature_class":"P",
    "gn:feature_code":"PPL",
    "gn:name":"B\u1ea3n N\u1eadm \u00cdt",
    "gn:population":0,
    "gn:timezone":"Asia/Ho_Chi_Minh",
    "iso:country":"VN",
    "name:vie_x_preferred":[
        "B\u1ea3n N\u1eadm \u00cdt"
    ],
    "wof:name":"Ban Nam It",
    "wof:placetype":"locality"
},
  "geometry": {"coordinates":[103.69313,22.24102],"type":"Point"}
}