{
  "type": "Feature",
  "properties": {
    "gn:admin1_code":"30.0",
    "gn:asciiname":"Dong Lam",
    "gn:country_code":"VN",
    "gn:dem":4,
    "gn:feature_class":"P",
    "gn:feature_code":"PPL",
    "gn:name":"\u0110\u00f4ng L\u00e2m",
    "gn:population":0,
    "gn:timezone":"Asia/Ho_Chi_Minh",
    "iso:country":"VN",
    "name:und_x_variant":[
        "Dong L\u00f4m",
        "\u0110\u00f4ng L\u00e2m"
    ],
    "wof:name":"Dong Lam",
    "wof:placetype":"locality"
},
  "geometry": {"coordinates":[106.43333,21.11667000000001],"type":"Point"}
}