{
  "type": "Feature",
  "properties": {
    "gn:admin1_code":"34.0",
    "gn:asciiname":"Yen Binh",
    "gn:country_code":"VN",
    "gn:dem":23,
    "gn:feature_class":"P",
    "gn:feature_code":"PPL",
    "gn:name":"Y\u00ean B\u00ecnh",
    "gn:population":0,
    "gn:timezone":"Asia/Ho_Chi_Minh",
    "iso:country":"VN",
    "name:vie_x_preferred":[
        "Y\u00ean B\u00ecnh"
    ],
    "wof:name":"Yen Binh",
    "wof:placetype":"locality"
},
  "geometry": {"coordinates":[105.65297,19.4957],"type":"Point"}
}