{
  "type": "Feature",
  "properties": {
    "gn:admin1_code":"58.0",
    "gn:asciiname":"Xom Muoi Sau",
    "gn:country_code":"VN",
    "gn:dem":9,
    "gn:feature_class":"P",
    "gn:feature_code":"PPL",
    "gn:name":"X\u00f3m M\u01b0\u1eddi S\u00e1u",
    "gn:population":0,
    "gn:timezone":"Asia/Ho_Chi_Minh",
    "iso:country":"VN",
    "name:vie_x_preferred":[
        "X\u00f3m M\u01b0\u1eddi S\u00e1u"
    ],
    "name:vie_x_variant":[
        "X\u00f3m 16"
    ],
    "wof:name":"Xom Muoi Sau",
    "wof:placetype":"locality"
},
  "geometry": {"coordinates":[105.64731999999999,18.80174],"type":"Point"}
}