{
  "type": "Feature",
  "properties": {
    "gn:admin1_code":"68.0",
    "gn:asciiname":"Lang Dinh",
    "gn:country_code":"VN",
    "gn:dem":213,
    "gn:feature_class":"P",
    "gn:feature_code":"PPL",
    "gn:name":"L\u00e0ng \u0110inh",
    "gn:population":0,
    "gn:timezone":"Asia/Ho_Chi_Minh",
    "iso:country":"VN",
    "wof:name":"Lang Dinh",
    "wof:placetype":"locality"
},
  "geometry": {"coordinates":[105.38522,22.04977],"type":"Point"}
}