{
  "type": "Feature",
  "properties": {
    "gn:admin1_code":"50.0",
    "gn:asciiname":"Ban Roai",
    "gn:country_code":"VN",
    "gn:dem":320,
    "gn:feature_class":"P",
    "gn:feature_code":"PPL",
    "gn:name":"B\u1ea3n Ro\u00e0i",
    "gn:population":0,
    "gn:timezone":"Asia/Ho_Chi_Minh",
    "iso:country":"VN",
    "name:vie_x_preferred":[
        "B\u1ea3n Ro\u00e0i"
    ],
    "wof:name":"Ban Roai",
    "wof:placetype":"locality"
},
  "geometry": {"coordinates":[105.29031999999999,22.9905],"type":"Point"}
}