{
  "type": "Feature",
  "properties": {
    "gn:admin1_code":"33.0",
    "gn:asciiname":"Ka Tum",
    "gn:country_code":"VN",
    "gn:dem":36,
    "gn:feature_class":"P",
    "gn:feature_code":"PPL",
    "gn:name":"K\u00e0 Tum",
    "gn:population":0,
    "gn:timezone":"Asia/Ho_Chi_Minh",
    "iso:country":"VN",
    "name:und_x_variant":[
        "Katum",
        "C\u00e0 Tum",
        "K\u00e0 Tum"
    ],
    "wof:name":"Ka Tum",
    "wof:placetype":"locality"
},
  "geometry": {"coordinates":[106.21904000000001,11.66772],"type":"Point"}
}