{
  "type": "Feature",
  "properties": {
    "gn:admin1_code":"46.0",
    "gn:asciiname":"Vinh Phu",
    "gn:country_code":"VN",
    "gn:dem":5,
    "gn:feature_class":"P",
    "gn:feature_code":"PPL",
    "gn:name":"V\u0129nh Ph\u00fa",
    "gn:population":0,
    "gn:timezone":"Asia/Ho_Chi_Minh",
    "iso:country":"VN",
    "name:und_x_variant":[
        "Phu Oc",
        "V\u0129nh Ph\u00fa"
    ],
    "wof:name":"Vinh Phu",
    "wof:placetype":"locality"
},
  "geometry": {"coordinates":[109.18333,13.96667],"type":"Point"}
}