{
  "type": "Feature",
  "properties": {
    "gn:admin1_code":"88.0",
    "gn:asciiname":"Buon E Gui",
    "gn:country_code":"VN",
    "gn:dem":473,
    "gn:feature_class":"P",
    "gn:feature_code":"PPL",
    "gn:name":"Bu\u00f4n \u00ca Gui",
    "gn:population":0,
    "gn:timezone":"Asia/Ho_Chi_Minh",
    "iso:country":"VN",
    "wof:name":"Buon E Gui",
    "wof:placetype":"locality"
},
  "geometry": {"coordinates":[108.58333,12.46667],"type":"Point"}
}