{
  "type": "Feature",
  "properties": {
    "gn:admin1_code":"76.0",
    "gn:asciiname":"Srok Penang",
    "gn:country_code":"VN",
    "gn:dem":168,
    "gn:feature_class":"P",
    "gn:feature_code":"PPL",
    "gn:name":"Srok P\u00e9nang",
    "gn:population":0,
    "gn:timezone":"Asia/Ho_Chi_Minh",
    "iso:country":"VN",
    "wof:name":"Srok Penang",
    "wof:placetype":"locality"
},
  "geometry": {"coordinates":[106.61667,11.91667],"type":"Point"}
}