{
  "type": "Feature",
  "properties": {
    "gn:admin1_code":"58.0",
    "gn:asciiname":"Ban Canh",
    "gn:country_code":"VN",
    "gn:dem":556,
    "gn:feature_class":"P",
    "gn:feature_code":"PPL",
    "gn:name":"B\u1ea3n C\u00e0nh",
    "gn:population":0,
    "gn:timezone":"Asia/Ho_Chi_Minh",
    "iso:country":"VN",
    "name:und_x_variant":[
        "Ban Ganh",
        "B\u1ea3n C\u00e0nh"
    ],
    "wof:name":"Ban Canh",
    "wof:placetype":"locality"
},
  "geometry": {"coordinates":[104.73333,19.06667],"type":"Point"}
}