{
  "type": "Feature",
  "properties": {
    "gn:admin1_code":"20.0",
    "gn:asciiname":"Quan Muoi Mot",
    "gn:country_code":"VN",
    "gn:dem":8,
    "gn:feature_class":"P",
    "gn:feature_code":"PPLA2",
    "gn:name":"Qu\u1eadn M\u01b0\u1eddi M\u1ed9t",
    "gn:population":0,
    "gn:timezone":"Asia/Ho_Chi_Minh",
    "iso:country":"VN",
    "name:und_x_variant":[
        "Qu\u1eadn M\u01b0\u1eddi M\u1ed9t",
        "Qu\u1eadn 11"
    ],
    "wof:name":"Quan Muoi Mot",
    "wof:placetype":"locality"
},
  "geometry": {"coordinates":[106.64355,10.76383],"type":"Point"}
}