{
  "type": "Feature",
  "properties": {
    "gn:admin1_code":"65.0",
    "gn:asciiname":"Ap Vinh Thanh",
    "gn:country_code":"VN",
    "gn:dem":3,
    "gn:feature_class":"P",
    "gn:feature_code":"PPL",
    "gn:name":"\u1ea4p V\u0129nh Thanh",
    "gn:population":0,
    "gn:timezone":"Asia/Ho_Chi_Minh",
    "iso:country":"VN",
    "name:und_x_variant":[
        "Vinh Thanh",
        "\u1ea4p V\u0129nh Thanh"
    ],
    "wof:name":"Ap Vinh Thanh",
    "wof:placetype":"locality"
},
  "geometry": {"coordinates":[105.65722,9.52972],"type":"Point"}
}