{
  "type": "Feature",
  "properties": {
    "gn:admin1_code":"86.0",
    "gn:asciiname":"Hai Luu",
    "gn:country_code":"VN",
    "gn:dem":24,
    "gn:feature_class":"P",
    "gn:feature_code":"PPL",
    "gn:name":"H\u1ea3i L\u01b0u",
    "gn:population":0,
    "gn:timezone":"Asia/Ho_Chi_Minh",
    "iso:country":"VN",
    "name:vie_x_preferred":[
        "H\u1ea3i L\u01b0u"
    ],
    "wof:name":"Hai Luu",
    "wof:placetype":"locality"
},
  "geometry": {"coordinates":[105.36506,21.47442],"type":"Point"}
}