{
  "type": "Feature",
  "properties": {
    "gn:admin1_code":"28.0",
    "gn:asciiname":"Buon Thach Bay",
    "gn:cc2":"VN",
    "gn:country_code":"VN",
    "gn:dem":192,
    "gn:feature_class":"P",
    "gn:feature_code":"PPL",
    "gn:name":"Bu\u00f4n Th\u1ea1ch Bay",
    "gn:population":0,
    "gn:timezone":"Asia/Ho_Chi_Minh",
    "iso:country":"VN",
    "name:und_x_variant":[
        "Ban Thach Bay",
        "Bu\u00f4n Th\u1ea1ch Bay"
    ],
    "wof:name":"Buon Thach Bay",
    "wof:placetype":"locality"
},
  "geometry": {"coordinates":[108.88333,12.46667],"type":"Point"}
}