{
  "type": "Feature",
  "properties": {
    "gn:admin1_code":"58.0",
    "gn:asciiname":"Ban Nong Mot",
    "gn:country_code":"VN",
    "gn:dem":662,
    "gn:feature_class":"P",
    "gn:feature_code":"PPL",
    "gn:name":"B\u1ea3n Nong M\u1ed9t",
    "gn:population":0,
    "gn:timezone":"Asia/Ho_Chi_Minh",
    "iso:country":"VN",
    "name:vie_x_preferred":[
        "B\u1ea3n Nong M\u1ed9t"
    ],
    "name:vie_x_variant":[
        "B\u1ea3n Nong 1"
    ],
    "wof:name":"Ban Nong Mot",
    "wof:placetype":"locality"
},
  "geometry": {"coordinates":[104.6884,19.60404],"type":"Point"}
}