{
  "type": "Feature",
  "properties": {
    "gn:admin1_code":"46.0",
    "gn:asciiname":"Canh Lanh",
    "gn:country_code":"VN",
    "gn:dem":89,
    "gn:feature_class":"P",
    "gn:feature_code":"PPL",
    "gn:name":"Canh L\u00e3nh",
    "gn:population":0,
    "gn:timezone":"Asia/Ho_Chi_Minh",
    "iso:country":"VN",
    "name:und_x_variant":[
        "Lang Trich",
        "Canh L\u00e3nh"
    ],
    "wof:name":"Canh Lanh",
    "wof:placetype":"locality"
},
  "geometry": {"coordinates":[108.98333,13.56667],"type":"Point"}
}