{
  "type": "Feature",
  "properties": {
    "gn:admin1_code":"89.0",
    "gn:asciiname":"Ban Chan Nuoi",
    "gn:country_code":"VN",
    "gn:dem":730,
    "gn:feature_class":"P",
    "gn:feature_code":"PPL",
    "gn:name":"B\u1ea3n Ch\u0103n Nu\u00f4i",
    "gn:population":0,
    "gn:timezone":"Asia/Ho_Chi_Minh",
    "iso:country":"VN",
    "name:vie_x_preferred":[
        "B\u1ea3n Ch\u0103n Nu\u00f4i"
    ],
    "wof:name":"Ban Chan Nuoi",
    "wof:placetype":"locality"
},
  "geometry": {"coordinates":[103.59369,22.29299],"type":"Point"}
}