{
  "type": "Feature",
  "properties": {
    "gn:admin1_code":"82.0",
    "gn:asciiname":"Trang Nghiem Thuong",
    "gn:country_code":"VN",
    "gn:dem":35,
    "gn:feature_class":"P",
    "gn:feature_code":"PPL",
    "gn:name":"Trang Nghi\u00eam Th\u01b0\u1ee3ng",
    "gn:population":0,
    "gn:timezone":"Asia/Ho_Chi_Minh",
    "iso:country":"VN",
    "wof:name":"Trang Nghiem Thuong",
    "wof:placetype":"locality"
},
  "geometry": {"coordinates":[106.06667,20.36667000000001],"type":"Point"}
}