{
  "type": "Feature",
  "properties": {
    "gn:admin1_code":"47.0",
    "gn:asciiname":"Hai Xuan",
    "gn:country_code":"VN",
    "gn:dem":17,
    "gn:feature_class":"P",
    "gn:feature_code":"PPL",
    "gn:name":"H\u1ea3i Xu\u00e2n",
    "gn:population":0,
    "gn:timezone":"Asia/Ho_Chi_Minh",
    "iso:country":"VN",
    "name:vie_x_preferred":[
        "H\u1ea3i Xu\u00e2n"
    ],
    "wof:name":"Hai Xuan",
    "wof:placetype":"locality"
},
  "geometry": {"coordinates":[108.50543999999999,11.25278],"type":"Point"}
}