{
  "type": "Feature",
  "properties": {
    "gn:admin1_code":"34.0",
    "gn:asciiname":"Na Men",
    "gn:country_code":"VN",
    "gn:dem":68,
    "gn:feature_class":"P",
    "gn:feature_code":"PPL",
    "gn:name":"N\u00e1 M\u00e9n",
    "gn:population":0,
    "gn:timezone":"Asia/Ho_Chi_Minh",
    "iso:country":"VN",
    "name:und_x_variant":[
        "L\u00e0ng Men"
    ],
    "name:vie_x_preferred":[
        "N\u00e1 M\u00e9n"
    ],
    "wof:name":"Na Men",
    "wof:placetype":"locality"
},
  "geometry": {"coordinates":[105.24782999999999,19.82043],"type":"Point"}
}