{
  "type": "Feature",
  "properties": {
    "gn:admin1_code":"81.0",
    "gn:asciiname":"Vuong",
    "gn:country_code":"VN",
    "gn:dem":4,
    "gn:feature_class":"P",
    "gn:feature_code":"PPLA2",
    "gn:name":"V\u01b0\u01a1ng",
    "gn:population":0,
    "gn:timezone":"Asia/Ho_Chi_Minh",
    "iso:country":"VN",
    "name:ukr_x_preferred":[
        "\u0412\u0438\u043e\u043d\u0433"
    ],
    "name:vie_x_preferred":[
        "V\u01b0\u01a1ng"
    ],
    "wof:name":"Vuong",
    "wof:placetype":"locality"
},
  "geometry": {"coordinates":[106.11751,20.7011],"type":"Point"}
}