{
  "type": "Feature",
  "properties": {
    "gn:admin1_code":"52.0",
    "gn:asciiname":"Quang Trung",
    "gn:country_code":"VN",
    "gn:dem":7,
    "gn:feature_class":"P",
    "gn:feature_code":"PPL",
    "gn:name":"Quang Trung",
    "gn:population":0,
    "gn:timezone":"Asia/Ho_Chi_Minh",
    "iso:country":"VN",
    "name:vie_x_preferred":[
        "Quang Trung"
    ],
    "wof:name":"Quang Trung",
    "wof:placetype":"locality"
},
  "geometry": {"coordinates":[105.96297,18.26539],"type":"Point"}
}