{
  "type": "Feature",
  "properties": {
    "gn:admin1_code":"52.0",
    "gn:asciiname":"Dong Gian",
    "gn:country_code":"VN",
    "gn:dem":-9999,
    "gn:feature_class":"P",
    "gn:feature_code":"PPL",
    "gn:name":"\u0110\u1ed9ng Gian",
    "gn:population":0,
    "gn:timezone":"Asia/Ho_Chi_Minh",
    "iso:country":"VN",
    "name:und_x_variant":[
        "Dong Ken",
        "\u0110\u1ed9ng Gian"
    ],
    "wof:name":"Dong Gian",
    "wof:placetype":"locality"
},
  "geometry": {"coordinates":[105.86667,18.55],"type":"Point"}
}