{
  "type": "Feature",
  "properties": {
    "gn:admin1_code":"76.0",
    "gn:asciiname":"Phuoc Binh",
    "gn:country_code":"VN",
    "gn:dem":169,
    "gn:feature_class":"P",
    "gn:feature_code":"PPL",
    "gn:name":"Ph\u01b0\u1edbc B\u00ecnh",
    "gn:population":0,
    "gn:timezone":"Asia/Ho_Chi_Minh",
    "iso:country":"VN",
    "name:und_x_variant":[
        "S\u00f4ng-B\u00e9",
        "Ph\u01b0\u1edbc B\u00ecnh"
    ],
    "wof:name":"Phuoc Binh",
    "wof:placetype":"locality"
},
  "geometry": {"coordinates":[106.98333,11.81667],"type":"Point"}
}