{
  "type": "Feature",
  "properties": {
    "gn:admin1_code":"86.0",
    "gn:asciiname":"Vinh Ninh",
    "gn:country_code":"VN",
    "gn:dem":61,
    "gn:feature_class":"P",
    "gn:feature_code":"PPL",
    "gn:name":"V\u0129nh Ninh",
    "gn:population":0,
    "gn:timezone":"Asia/Ho_Chi_Minh",
    "iso:country":"VN",
    "name:vie_x_preferred":[
        "V\u0129nh Ninh"
    ],
    "wof:name":"Vinh Ninh",
    "wof:placetype":"locality"
},
  "geometry": {"coordinates":[105.51940999999999,21.52156],"type":"Point"}
}