{
  "type": "Feature",
  "properties": {
    "gn:admin1_code":"63.0",
    "gn:asciiname":"Phu Hau",
    "gn:country_code":"VN",
    "gn:dem":29,
    "gn:feature_class":"P",
    "gn:feature_code":"PPL",
    "gn:name":"Ph\u00fa H\u1eadu",
    "gn:population":0,
    "gn:timezone":"Asia/Ho_Chi_Minh",
    "iso:country":"VN",
    "name:vie_x_preferred":[
        "Ph\u00fa H\u1eadu"
    ],
    "wof:name":"Phu Hau",
    "wof:placetype":"locality"
},
  "geometry": {"coordinates":[108.74775,15.24325],"type":"Point"}
}