{
  "type": "Feature",
  "properties": {
    "gn:admin1_code":"58.0",
    "gn:asciiname":"Xep Khay",
    "gn:country_code":"VN",
    "gn:dem":686,
    "gn:feature_class":"P",
    "gn:feature_code":"PPL",
    "gn:name":"X\u00e9p Khay",
    "gn:population":0,
    "gn:timezone":"Asia/Ho_Chi_Minh",
    "iso:country":"VN",
    "name:vie_x_preferred":[
        "X\u00e9p Khay"
    ],
    "wof:name":"Xep Khay",
    "wof:placetype":"locality"
},
  "geometry": {"coordinates":[104.21989000000001,19.54345],"type":"Point"}
}