{
  "type": "Feature",
  "properties": {
    "gn:admin1_code":"84.0",
    "gn:asciiname":"Khuong Trung",
    "gn:country_code":"VN",
    "gn:dem":25,
    "gn:feature_class":"P",
    "gn:feature_code":"PPL",
    "gn:name":"Kh\u01b0\u01a1ng Trung",
    "gn:population":0,
    "gn:timezone":"Asia/Ho_Chi_Minh",
    "iso:country":"VN",
    "name:und_x_variant":[
        "Trung Phuoc",
        "Kh\u01b0\u01a1ng Trung"
    ],
    "wof:name":"Khuong Trung",
    "wof:placetype":"locality"
},
  "geometry": {"coordinates":[108.06667,15.71667],"type":"Point"}
}