{
  "type": "Feature",
  "properties": {
    "gn:admin1_code":"47.0",
    "gn:asciiname":"Karai",
    "gn:country_code":"VN",
    "gn:dem":94,
    "gn:feature_class":"P",
    "gn:feature_code":"PPL",
    "gn:name":"Karai",
    "gn:population":0,
    "gn:timezone":"Asia/Ho_Chi_Minh",
    "iso:country":"VN",
    "name:ceb_x_preferred":[
        "Karai"
    ],
    "name:deu_x_preferred":[
        "Karai"
    ],
    "name:fra_x_preferred":[
        "Karai"
    ],
    "wof:name":"Karai",
    "wof:placetype":"locality"
},
  "geometry": {"coordinates":[108.45,11.36667],"type":"Point"}
}