{
  "type": "Feature",
  "properties": {
    "gn:admin1_code":"88.0",
    "gn:asciiname":"Lien Ket Hai",
    "gn:country_code":"VN",
    "gn:dem":419,
    "gn:feature_class":"P",
    "gn:feature_code":"PPL",
    "gn:name":"Li\u00ean K\u1ebft Hai",
    "gn:population":0,
    "gn:timezone":"Asia/Ho_Chi_Minh",
    "iso:country":"VN",
    "name:vie_x_preferred":[
        "Li\u00ean K\u1ebft Hai"
    ],
    "name:vie_x_variant":[
        "Li\u00ean K\u1ebft 2"
    ],
    "wof:name":"Lien Ket Hai",
    "wof:placetype":"locality"
},
  "geometry": {"coordinates":[108.12526,12.40154],"type":"Point"}
}