{
  "type": "Feature",
  "properties": {
    "gn:admin1_code":"90.0",
    "gn:asciiname":"Niu Co San Chai",
    "gn:country_code":"VN",
    "gn:dem":1709,
    "gn:feature_class":"P",
    "gn:feature_code":"PPL",
    "gn:name":"N\u00ecu C\u00f2 San Chai",
    "gn:population":0,
    "gn:timezone":"Asia/Ho_Chi_Minh",
    "iso:country":"VN",
    "wof:name":"Niu Co San Chai",
    "wof:placetype":"locality"
},
  "geometry": {"coordinates":[103.58333,22.61667000000001],"type":"Point"}
}