{
  "type": "Feature",
  "properties": {
    "gn:admin1_code":"88.0",
    "gn:asciiname":"Ban M'o",
    "gn:country_code":"VN",
    "gn:dem":498,
    "gn:feature_class":"P",
    "gn:feature_code":"PPL",
    "gn:name":"Ban M\u2019o",
    "gn:population":0,
    "gn:timezone":"Asia/Ho_Chi_Minh",
    "iso:country":"VN",
    "name:und_x_variant":[
        "Buon Mo",
        "Ban M\u2019o"
    ],
    "wof:name":"Ban M'o",
    "wof:placetype":"locality"
},
  "geometry": {"coordinates":[108.81667,12.66667],"type":"Point"}
}