{
  "type": "Feature",
  "properties": {
    "gn:admin1_code":"72.0",
    "gn:asciiname":"Na Nen",
    "gn:country_code":"VN",
    "gn:dem":308,
    "gn:feature_class":"P",
    "gn:feature_code":"PPL",
    "gn:name":"N\u00e0 Nen",
    "gn:population":0,
    "gn:timezone":"Asia/Ho_Chi_Minh",
    "iso:country":"VN",
    "name:vie_x_preferred":[
        "N\u00e0 Nen"
    ],
    "wof:name":"Na Nen",
    "wof:placetype":"locality"
},
  "geometry": {"coordinates":[106.03695999999999,22.05702],"type":"Point"}
}