{
  "type": "Feature",
  "properties": {
    "gn:admin1_code":"89.0",
    "gn:asciiname":"Loung Tap",
    "gn:country_code":"VN",
    "gn:dem":855,
    "gn:feature_class":"P",
    "gn:feature_code":"PPL",
    "gn:name":"Loung Tap",
    "gn:population":0,
    "gn:timezone":"Asia/Ho_Chi_Minh",
    "iso:country":"VN",
    "wof:name":"Loung Tap",
    "wof:placetype":"locality"
},
  "geometry": {"coordinates":[103.78333000000001,22.18333],"type":"Point"}
}