{
  "type": "Feature",
  "properties": {
    "gn:admin1_code":"62.0",
    "gn:asciiname":"Phu Vinh",
    "gn:country_code":"VN",
    "gn:dem":15,
    "gn:feature_class":"P",
    "gn:feature_code":"PPL",
    "gn:name":"Phu Vinh",
    "gn:population":0,
    "gn:timezone":"Asia/Ho_Chi_Minh",
    "iso:country":"VN",
    "wof:name":"Phu Vinh",
    "wof:placetype":"locality"
},
  "geometry": {"coordinates":[106.56667,17.45],"type":"Point"}
}