{
  "type": "Feature",
  "properties": {
    "gn:admin1_code":"58.0",
    "gn:asciiname":"Phu Quac Hai",
    "gn:country_code":"VN",
    "gn:dem":836,
    "gn:feature_class":"P",
    "gn:feature_code":"PPL",
    "gn:name":"Phu Qu\u1eafc Hai",
    "gn:population":0,
    "gn:timezone":"Asia/Ho_Chi_Minh",
    "iso:country":"VN",
    "name:vie_x_preferred":[
        "Phu Qu\u1eafc Hai"
    ],
    "name:vie_x_variant":[
        "Phu Qu\u1eafc 2"
    ],
    "wof:name":"Phu Quac Hai",
    "wof:placetype":"locality"
},
  "geometry": {"coordinates":[104.26206000000001,19.26851],"type":"Point"}
}