{
  "type": "Feature",
  "properties": {
    "gn:admin1_code":"35.0",
    "gn:asciiname":"Xuan Hoa",
    "gn:country_code":"VN",
    "gn:dem":3,
    "gn:feature_class":"P",
    "gn:feature_code":"PPL",
    "gn:name":"Xu\u00e2n H\u00f2a",
    "gn:population":0,
    "gn:timezone":"Asia/Ho_Chi_Minh",
    "iso:country":"VN",
    "name:und_x_variant":[
        "Xu\u00e2n H\u00f2a Gi\u00e1o"
    ],
    "name:vie_x_preferred":[
        "Xu\u00e2n H\u00f2a"
    ],
    "wof:name":"Xuan Hoa",
    "wof:placetype":"locality"
},
  "geometry": {"coordinates":[106.53478,20.46485],"type":"Point"}
}