{
  "type": "Feature",
  "properties": {
    "gn:admin1_code":"24.0",
    "gn:asciiname":"Ap Bac",
    "gn:cc2":"VN",
    "gn:country_code":"VN",
    "gn:dem":2,
    "gn:feature_class":"P",
    "gn:feature_code":"PPL",
    "gn:name":"\u1ea4p B\u1eafc",
    "gn:population":0,
    "gn:timezone":"Asia/Ho_Chi_Minh",
    "iso:country":"VN",
    "name:und_x_variant":[
        "Ki\u1ebfn Binh",
        "\u1ea4p B\u1eafc"
    ],
    "wof:name":"Ap Bac",
    "wof:placetype":"locality"
},
  "geometry": {"coordinates":[106.05,10.61667],"type":"Point"}
}