{
  "type": "Feature",
  "properties": {
    "gn:admin1_code":"90.0",
    "gn:asciiname":"Phung Man",
    "gn:country_code":"VN",
    "gn:dem":928,
    "gn:feature_class":"P",
    "gn:feature_code":"PPL",
    "gn:name":"Ph\u00f9ng Man",
    "gn:population":0,
    "gn:timezone":"Asia/Ho_Chi_Minh",
    "iso:country":"VN",
    "name:und_x_variant":[
        "Ph\u00f9ng M\u00e1n"
    ],
    "name:vie_x_preferred":[
        "Ph\u00f9ng Man"
    ],
    "wof:name":"Phung Man",
    "wof:placetype":"locality"
},
  "geometry": {"coordinates":[103.98011,22.32575],"type":"Point"}
}