{
  "type": "Feature",
  "properties": {
    "gn:admin1_code":"63.0",
    "gn:asciiname":"Lac Ha",
    "gn:country_code":"VN",
    "gn:dem":48,
    "gn:feature_class":"P",
    "gn:feature_code":"PPL",
    "gn:name":"L\u1ea1c H\u1ea1",
    "gn:population":0,
    "gn:timezone":"Asia/Ho_Chi_Minh",
    "iso:country":"VN",
    "name:vie_x_preferred":[
        "L\u1ea1c H\u1ea1"
    ],
    "wof:name":"Lac Ha",
    "wof:placetype":"locality"
},
  "geometry": {"coordinates":[108.71132,14.98677],"type":"Point"}
}