{
  "type": "Feature",
  "properties": {
    "gn:admin1_code":"33.0",
    "gn:asciiname":"Tra Xim",
    "gn:country_code":"VN",
    "gn:dem":7,
    "gn:feature_class":"P",
    "gn:feature_code":"PPL",
    "gn:name":"Tr\u00e0 Xim",
    "gn:population":0,
    "gn:timezone":"Asia/Ho_Chi_Minh",
    "iso:country":"VN",
    "name:und_x_variant":[
        "Tra Sim"
    ],
    "name:vie_x_preferred":[
        "Tr\u00e0 Xim"
    ],
    "wof:name":"Tra Xim",
    "wof:placetype":"locality"
},
  "geometry": {"coordinates":[106.05568,11.22061],"type":"Point"}
}