{
  "type": "Feature",
  "properties": {
    "gn:admin1_code":"39.0",
    "gn:asciiname":"Na Dua",
    "gn:country_code":"VN",
    "gn:dem":331,
    "gn:feature_class":"P",
    "gn:feature_code":"PPL",
    "gn:name":"N\u00e0 D\u1eeba",
    "gn:population":0,
    "gn:timezone":"Asia/Ho_Chi_Minh",
    "iso:country":"VN",
    "name:und_x_variant":[
        "N\u00e0 Dua"
    ],
    "name:vie_x_preferred":[
        "N\u00e0 D\u1eeba"
    ],
    "wof:name":"Na Dua",
    "wof:placetype":"locality"
},
  "geometry": {"coordinates":[107.06113000000001,21.74453],"type":"Point"}
}