{
  "type": "Feature",
  "properties": {
    "gn:admin1_code":"13.0",
    "gn:asciiname":"Dong Tao",
    "gn:country_code":"VN",
    "gn:dem":3,
    "gn:feature_class":"P",
    "gn:feature_code":"PPL",
    "gn:name":"Dong Tao",
    "gn:population":0,
    "gn:timezone":"Asia/Ho_Chi_Minh",
    "iso:country":"VN",
    "name:und_x_variant":[
        "\u0110\u00f4ng T\u00e2n"
    ],
    "wof:name":"Dong Tao",
    "wof:placetype":"locality"
},
  "geometry": {"coordinates":[106.55,20.78333],"type":"Point"}
}