{
  "type": "Feature",
  "properties": {
    "gn:admin1_code":"34.0",
    "gn:asciiname":"Lang Lieu",
    "gn:country_code":"VN",
    "gn:dem":76,
    "gn:feature_class":"P",
    "gn:feature_code":"PPL",
    "gn:name":"L\u00e0ng Li\u1ebfu",
    "gn:population":0,
    "gn:timezone":"Asia/Ho_Chi_Minh",
    "iso:country":"VN",
    "name:vie_x_preferred":[
        "L\u00e0ng Li\u1ebfu"
    ],
    "wof:name":"Lang Lieu",
    "wof:placetype":"locality"
},
  "geometry": {"coordinates":[105.31587,20.04724],"type":"Point"}
}