{
  "type": "Feature",
  "properties": {
    "gn:admin1_code":"64.0",
    "gn:asciiname":"Khu C",
    "gn:country_code":"VN",
    "gn:dem":15,
    "gn:feature_class":"P",
    "gn:feature_code":"PPL",
    "gn:name":"Khu C",
    "gn:population":0,
    "gn:timezone":"Asia/Ho_Chi_Minh",
    "iso:country":"VN",
    "name:vie_x_preferred":[
        "Khu C"
    ],
    "wof:name":"Khu C",
    "wof:placetype":"locality"
},
  "geometry": {"coordinates":[107.00606999999999,17.07295],"type":"Point"}
}