{
  "type": "Feature",
  "properties": {
    "gn:admin1_code":"58.0",
    "gn:asciiname":"Trang Giang",
    "gn:country_code":"VN",
    "gn:dem":36,
    "gn:feature_class":"P",
    "gn:feature_code":"PPL",
    "gn:name":"Tr\u00e0ng Giang",
    "gn:population":0,
    "gn:timezone":"Asia/Ho_Chi_Minh",
    "iso:country":"VN",
    "name:vie_x_preferred":[
        "Tr\u00e0ng Giang"
    ],
    "wof:name":"Trang Giang",
    "wof:placetype":"locality"
},
  "geometry": {"coordinates":[105.26667999999999,18.98482000000001],"type":"Point"}
}