{
  "type": "Feature",
  "properties": {
    "gn:admin1_code":"37.0",
    "gn:asciiname":"Binh Hoa",
    "gn:country_code":"VN",
    "gn:dem":3,
    "gn:feature_class":"P",
    "gn:feature_code":"PPL",
    "gn:name":"B\u00ecnh H\u00f2a",
    "gn:population":0,
    "gn:timezone":"Asia/Ho_Chi_Minh",
    "iso:country":"VN",
    "wof:name":"Binh Hoa",
    "wof:placetype":"locality"
},
  "geometry": {"coordinates":[106.18333,10.31667],"type":"Point"}
}