{
  "type": "Feature",
  "properties": {
    "gn:admin1_code":"84.0",
    "gn:asciiname":"Pimah",
    "gn:country_code":"VN",
    "gn:dem":1006,
    "gn:feature_class":"P",
    "gn:feature_code":"PPL",
    "gn:name":"Pimah",
    "gn:population":0,
    "gn:timezone":"Asia/Ho_Chi_Minh",
    "iso:country":"VN",
    "wof:name":"Pimah",
    "wof:placetype":"locality"
},
  "geometry": {"coordinates":[107.31667,15.66667],"type":"Point"}
}