{
  "type": "Feature",
  "properties": {
    "gn:admin1_code":"85.0",
    "gn:asciiname":"Coc Ngan",
    "gn:country_code":"VN",
    "gn:dem":106,
    "gn:feature_class":"P",
    "gn:feature_code":"PPL",
    "gn:name":"C\u1ed1c Ng\u00e2n",
    "gn:population":0,
    "gn:timezone":"Asia/Ho_Chi_Minh",
    "iso:country":"VN",
    "name:vie_x_preferred":[
        "C\u1ed1c Ng\u00e2n"
    ],
    "wof:name":"Coc Ngan",
    "wof:placetype":"locality"
},
  "geometry": {"coordinates":[105.67719,21.97238],"type":"Point"}
}