{
  "type": "Feature",
  "properties": {
    "gn:admin1_code":"66.0",
    "gn:asciiname":"Thon Thai Duong Thuong",
    "gn:country_code":"VN",
    "gn:dem":-9999,
    "gn:feature_class":"P",
    "gn:feature_code":"PPL",
    "gn:name":"Th\u00f4n Th\u00e1i D\u01b0\u01a1ng Th\u01b0\u1ee3ng",
    "gn:population":0,
    "gn:timezone":"Asia/Ho_Chi_Minh",
    "iso:country":"VN",
    "name:und_x_variant":[
        "Thai Duong Thuong",
        "Th\u00f4n Th\u00e1i D\u01b0\u01a1ng Th\u01b0\u1ee3ng"
    ],
    "wof:name":"Thon Thai Duong Thuong",
    "wof:placetype":"locality"
},
  "geometry": {"coordinates":[107.61667,16.58333],"type":"Point"}
}