{
  "type": "Feature",
  "properties": {
    "gn:admin1_code":"68.0",
    "gn:asciiname":"Cay Thi",
    "gn:country_code":"VN",
    "gn:dem":158,
    "gn:feature_class":"P",
    "gn:feature_code":"PPL",
    "gn:name":"C\u00e2y Th\u1ecb",
    "gn:population":0,
    "gn:timezone":"Asia/Ho_Chi_Minh",
    "iso:country":"VN",
    "name:vie_x_preferred":[
        "C\u00e2y Th\u1ecb"
    ],
    "wof:name":"Cay Thi",
    "wof:placetype":"locality"
},
  "geometry": {"coordinates":[105.36253000000001,21.85588],"type":"Point"}
}