{
  "type": "Feature",
  "properties": {
    "gn:admin1_code":"60.0",
    "gn:asciiname":"Ma O",
    "gn:country_code":"VN",
    "gn:dem":72,
    "gn:feature_class":"P",
    "gn:feature_code":"PPL",
    "gn:name":"Ma \u00d3",
    "gn:population":0,
    "gn:timezone":"Asia/Ho_Chi_Minh",
    "iso:country":"VN",
    "wof:name":"Ma O",
    "wof:placetype":"locality"
},
  "geometry": {"coordinates":[109.08333,11.76667],"type":"Point"}
}