{
  "type": "Feature",
  "properties": {
    "gn:admin1_code":"17.0",
    "gn:asciiname":"Van Vai",
    "gn:country_code":"VN",
    "gn:dem":208,
    "gn:feature_class":"P",
    "gn:feature_code":"PPL",
    "gn:name":"Van Vai",
    "gn:population":0,
    "gn:timezone":"Asia/Ho_Chi_Minh",
    "iso:country":"VN",
    "wof:name":"Van Vai",
    "wof:placetype":"locality"
},
  "geometry": {"coordinates":[105.51667,23.08333],"type":"Point"}
}