{
  "type": "Feature",
  "properties": {
    "gn:admin1_code":"32.0",
    "gn:asciiname":"Suoi Cai",
    "gn:country_code":"VN",
    "gn:dem":431,
    "gn:feature_class":"P",
    "gn:feature_code":"PPL",
    "gn:name":"Su\u1ed1i Cai",
    "gn:population":0,
    "gn:timezone":"Asia/Ho_Chi_Minh",
    "iso:country":"VN",
    "wof:name":"Suoi Cai",
    "wof:placetype":"locality"
},
  "geometry": {"coordinates":[104.36667,21.25],"type":"Point"}
}