{
  "type": "Feature",
  "properties": {
    "gn:admin1_code":"71.0",
    "gn:asciiname":"Vi Loai",
    "gn:country_code":"VN",
    "gn:dem":151,
    "gn:feature_class":"P",
    "gn:feature_code":"PPL",
    "gn:name":"Vi Lo\u1ea1i",
    "gn:population":0,
    "gn:timezone":"Asia/Ho_Chi_Minh",
    "iso:country":"VN",
    "wof:name":"Vi Loai",
    "wof:placetype":"locality"
},
  "geometry": {"coordinates":[106.88333,21.21667],"type":"Point"}
}