{
  "type": "Feature",
  "properties": {
    "gn:admin1_code":"32.0",
    "gn:asciiname":"Ban Na Luong",
    "gn:country_code":"VN",
    "gn:dem":184,
    "gn:feature_class":"P",
    "gn:feature_code":"PPL",
    "gn:name":"B\u1ea3n N\u00e0 L\u01b0\u1eddng",
    "gn:population":0,
    "gn:timezone":"Asia/Ho_Chi_Minh",
    "iso:country":"VN",
    "name:vie_x_preferred":[
        "B\u1ea3n N\u00e0 L\u01b0\u1eddng"
    ],
    "wof:name":"Ban Na Luong",
    "wof:placetype":"locality"
},
  "geometry": {"coordinates":[104.64727000000001,21.2161],"type":"Point"}
}