{
  "type": "Feature",
  "properties": {
    "gn:admin1_code":"34.0",
    "gn:asciiname":"Hai Lam",
    "gn:country_code":"VN",
    "gn:dem":16,
    "gn:feature_class":"P",
    "gn:feature_code":"PPL",
    "gn:name":"H\u1ea3i L\u00e2m",
    "gn:population":0,
    "gn:timezone":"Asia/Ho_Chi_Minh",
    "iso:country":"VN",
    "name:vie_x_preferred":[
        "H\u1ea3i L\u00e2m"
    ],
    "wof:name":"Hai Lam",
    "wof:placetype":"locality"
},
  "geometry": {"coordinates":[105.73412999999999,19.36161],"type":"Point"}
}