{
  "type": "Feature",
  "properties": {
    "gn:admin1_code":"20.0",
    "gn:asciiname":"Thanh My Loi",
    "gn:country_code":"VN",
    "gn:dem":1,
    "gn:feature_class":"P",
    "gn:feature_code":"PPL",
    "gn:name":"Th\u1ea1nh My L\u1ee3i",
    "gn:population":0,
    "gn:timezone":"Asia/Ho_Chi_Minh",
    "iso:country":"VN",
    "wof:name":"Thanh My Loi",
    "wof:placetype":"locality"
},
  "geometry": {"coordinates":[106.78333000000001,10.76667],"type":"Point"}
}