{
  "type": "Feature",
  "properties": {
    "gn:admin1_code":"5.0",
    "gn:asciiname":"Ban Lung Ria",
    "gn:country_code":"VN",
    "gn:dem":638,
    "gn:feature_class":"P",
    "gn:feature_code":"PPL",
    "gn:name":"B\u1ea3n L\u0169ng Ria",
    "gn:population":0,
    "gn:timezone":"Asia/Ho_Chi_Minh",
    "iso:country":"VN",
    "name:vie_x_preferred":[
        "B\u1ea3n L\u0169ng Ria"
    ],
    "wof:name":"Ban Lung Ria",
    "wof:placetype":"locality"
},
  "geometry": {"coordinates":[105.35498,22.87163],"type":"Point"}
}