{
  "type": "Feature",
  "properties": {
    "gn:admin1_code":"90.0",
    "gn:asciiname":"Xuan Dau",
    "gn:country_code":"VN",
    "gn:dem":147,
    "gn:feature_class":"P",
    "gn:feature_code":"PPL",
    "gn:name":"Xu\u00e2n \u0110\u00e1u",
    "gn:population":0,
    "gn:timezone":"Asia/Ho_Chi_Minh",
    "iso:country":"VN",
    "wof:name":"Xuan Dau",
    "wof:placetype":"locality"
},
  "geometry": {"coordinates":[104.23333,22.38333],"type":"Point"}
}