{
  "type": "Feature",
  "properties": {
    "gn:admin1_code":"89.0",
    "gn:asciiname":"Ban Bo",
    "gn:country_code":"VN",
    "gn:dem":691,
    "gn:feature_class":"P",
    "gn:feature_code":"PPL",
    "gn:name":"B\u1ea3n B\u00f3",
    "gn:population":0,
    "gn:timezone":"Asia/Ho_Chi_Minh",
    "iso:country":"VN",
    "name:und_x_variant":[
        "Na Bo"
    ],
    "name:vie_x_preferred":[
        "B\u1ea3n B\u00f3"
    ],
    "wof:name":"Ban Bo",
    "wof:placetype":"locality"
},
  "geometry": {"coordinates":[103.52194,22.34414],"type":"Point"}
}