{
  "type": "Feature",
  "properties": {
    "gn:admin1_code":"13.0",
    "gn:asciiname":"Da Nghi",
    "gn:country_code":"VN",
    "gn:dem":6,
    "gn:feature_class":"P",
    "gn:feature_code":"PPL",
    "gn:name":"\u0110a Nghi",
    "gn:population":0,
    "gn:timezone":"Asia/Ho_Chi_Minh",
    "iso:country":"VN",
    "name:vie_x_preferred":[
        "\u0110a Nghi"
    ],
    "wof:name":"Da Nghi",
    "wof:placetype":"locality"
},
  "geometry": {"coordinates":[106.75582,20.93441],"type":"Point"}
}