{
  "type": "Feature",
  "properties": {
    "gn:admin1_code":"65.0",
    "gn:asciiname":"Huynh Huu Nghia",
    "gn:country_code":"VN",
    "gn:dem":2,
    "gn:feature_class":"P",
    "gn:feature_code":"PPLA2",
    "gn:name":"Hu\u1ef3nh H\u1eefu Ngh\u0129a",
    "gn:population":0,
    "gn:timezone":"Asia/Ho_Chi_Minh",
    "iso:country":"VN",
    "name:vie_x_preferred":[
        "Hu\u1ef3nh H\u1eefu Ngh\u0129a"
    ],
    "wof:name":"Huynh Huu Nghia",
    "wof:placetype":"locality"
},
  "geometry": {"coordinates":[105.81165,9.63537],"type":"Point"}
}