{
  "type": "Feature",
  "properties": {
    "gn:admin1_code":"5.0",
    "gn:asciiname":"Loung Rang",
    "gn:country_code":"VN",
    "gn:dem":1415,
    "gn:feature_class":"P",
    "gn:feature_code":"PPL",
    "gn:name":"Loung Rang",
    "gn:population":0,
    "gn:timezone":"Asia/Ho_Chi_Minh",
    "iso:country":"VN",
    "wof:name":"Loung Rang",
    "wof:placetype":"locality"
},
  "geometry": {"coordinates":[105.81667,22.95],"type":"Point"}
}