{
  "type": "Feature",
  "properties": {
    "gn:admin1_code":"73.0",
    "gn:asciiname":"Hoang Minh",
    "gn:country_code":"VN",
    "gn:dem":2,
    "gn:feature_class":"P",
    "gn:feature_code":"PPL",
    "gn:name":"Ho\u00e0ng Minh",
    "gn:population":0,
    "gn:timezone":"Asia/Ho_Chi_Minh",
    "iso:country":"VN",
    "name:vie_x_preferred":[
        "Ho\u00e0ng Minh"
    ],
    "wof:name":"Hoang Minh",
    "wof:placetype":"locality"
},
  "geometry": {"coordinates":[105.32151,9.17553],"type":"Point"}
}