{
  "type": "Feature",
  "properties": {
    "gn:admin1_code":"58.0",
    "gn:asciiname":"Thanh Gia",
    "gn:country_code":"VN",
    "gn:dem":6,
    "gn:feature_class":"P",
    "gn:feature_code":"PPL",
    "gn:name":"Thanh G\u0129a",
    "gn:population":0,
    "gn:timezone":"Asia/Ho_Chi_Minh",
    "iso:country":"VN",
    "name:und_x_variant":[
        "Than Gia"
    ],
    "name:vie_x_preferred":[
        "Thanh G\u0129a"
    ],
    "wof:name":"Thanh Gia",
    "wof:placetype":"locality"
},
  "geometry": {"coordinates":[105.68391,19.16855],"type":"Point"}
}