{
  "type": "Feature",
  "properties": {
    "gn:admin1_code":"34.0",
    "gn:asciiname":"Lang Chanh",
    "gn:country_code":"VN",
    "gn:dem":56,
    "gn:feature_class":"P",
    "gn:feature_code":"PPLA2",
    "gn:name":"Lang Ch\u00e1nh",
    "gn:population":0,
    "gn:timezone":"Asia/Ho_Chi_Minh",
    "iso:country":"VN",
    "name:und_x_variant":[
        "L\u00e0ng Chi\u00eang Trai",
        "Lang Ch\u00e1nh",
        "H\u01b0\u01a1ng Lang Ch\u00e1nh"
    ],
    "wof:name":"Lang Chanh",
    "wof:placetype":"locality"
},
  "geometry": {"coordinates":[105.24223000000001,20.15611],"type":"Point"}
}