{
  "type": "Feature",
  "properties": {
    "gn:admin1_code":"72.0",
    "gn:asciiname":"Tat Dai",
    "gn:country_code":"VN",
    "gn:dem":184,
    "gn:feature_class":"P",
    "gn:feature_code":"PPL",
    "gn:name":"T\u00e1t D\u00e0i",
    "gn:population":0,
    "gn:timezone":"Asia/Ho_Chi_Minh",
    "iso:country":"VN",
    "wof:name":"Tat Dai",
    "wof:placetype":"locality"
},
  "geometry": {"coordinates":[105.75507,22.43649],"type":"Point"}
}