{
  "type": "Feature",
  "properties": {
    "gn:admin1_code":"71.0",
    "gn:asciiname":"Van Coc",
    "gn:country_code":"VN",
    "gn:dem":7,
    "gn:feature_class":"P",
    "gn:feature_code":"PPL",
    "gn:name":"V\u00e2n C\u1ed1c",
    "gn:population":0,
    "gn:timezone":"Asia/Ho_Chi_Minh",
    "iso:country":"VN",
    "name:und_x_variant":[
        "Lang Bai",
        "V\u00e2n C\u1ed1c"
    ],
    "wof:name":"Van Coc",
    "wof:placetype":"locality"
},
  "geometry": {"coordinates":[106.12869999999999,21.23778],"type":"Point"}
}