{
  "type": "Feature",
  "properties": {
    "gn:admin1_code":"92.0",
    "gn:asciiname":"Phi Cong",
    "gn:country_code":"VN",
    "gn:dem":998,
    "gn:feature_class":"P",
    "gn:feature_code":"PPL",
    "gn:name":"Phi C\u00f4ng",
    "gn:population":0,
    "gn:timezone":"Asia/Ho_Chi_Minh",
    "iso:country":"VN",
    "name:vie_x_preferred":[
        "Phi C\u00f4ng"
    ],
    "wof:name":"Phi Cong",
    "wof:placetype":"locality"
},
  "geometry": {"coordinates":[103.18319,21.956],"type":"Point"}
}