{
  "type": "Feature",
  "properties": {
    "gn:admin1_code":"66.0",
    "gn:asciiname":"Thon Hung Thai",
    "gn:country_code":"VN",
    "gn:dem":15,
    "gn:feature_class":"P",
    "gn:feature_code":"PPL",
    "gn:name":"Th\u00f4n H\u01b0ng Th\u00e1i",
    "gn:population":0,
    "gn:timezone":"Asia/Ho_Chi_Minh",
    "iso:country":"VN",
    "name:und_x_variant":[
        "My Xuyen",
        "Th\u00f4n H\u01b0ng Th\u00e1i"
    ],
    "wof:name":"Thon Hung Thai",
    "wof:placetype":"locality"
},
  "geometry": {"coordinates":[107.31667,16.55],"type":"Point"}
}