{
  "type": "Feature",
  "properties": {
    "gn:admin1_code":"9.0",
    "gn:asciiname":"Ap Mot",
    "gn:country_code":"VN",
    "gn:dem":5,
    "gn:feature_class":"P",
    "gn:feature_code":"PPL",
    "gn:name":"\u1ea4p M\u1ed9t",
    "gn:population":0,
    "gn:timezone":"Asia/Ho_Chi_Minh",
    "iso:country":"VN",
    "name:vie_x_preferred":[
        "\u1ea4p M\u1ed9t"
    ],
    "name:vie_x_variant":[
        "\u1ea4p 1"
    ],
    "wof:name":"Ap Mot",
    "wof:placetype":"locality"
},
  "geometry": {"coordinates":[105.22066,10.84865],"type":"Point"}
}