{
  "type": "Feature",
  "properties": {
    "gn:admin1_code":"32.0",
    "gn:asciiname":"Ban Ta Kom",
    "gn:country_code":"VN",
    "gn:dem":1346,
    "gn:feature_class":"P",
    "gn:feature_code":"PPL",
    "gn:name":"B\u1ea3n Ta Kom",
    "gn:population":0,
    "gn:timezone":"Asia/Ho_Chi_Minh",
    "iso:country":"VN",
    "wof:name":"Ban Ta Kom",
    "wof:placetype":"locality"
},
  "geometry": {"coordinates":[103.45,21.41667],"type":"Point"}
}