{
  "type": "Feature",
  "properties": {
    "gn:admin1_code":"63.0",
    "gn:asciiname":"Yen Ngua",
    "gn:country_code":"VN",
    "gn:dem":85,
    "gn:feature_class":"P",
    "gn:feature_code":"PPL",
    "gn:name":"Y\u00ean Ng\u1ef1a",
    "gn:population":0,
    "gn:timezone":"Asia/Ho_Chi_Minh",
    "iso:country":"VN",
    "name:vie_x_preferred":[
        "Y\u00ean Ng\u1ef1a"
    ],
    "wof:name":"Yen Ngua",
    "wof:placetype":"locality"
},
  "geometry": {"coordinates":[108.68939,15.03017],"type":"Point"}
}