{
  "type": "Feature",
  "properties": {
    "gn:admin1_code":"70.0",
    "gn:asciiname":"Ban Nam Khat",
    "gn:country_code":"VN",
    "gn:dem":1406,
    "gn:feature_class":"P",
    "gn:feature_code":"PPL",
    "gn:name":"B\u1ea3n N\u1eadm Kh\u1eaft",
    "gn:population":0,
    "gn:timezone":"Asia/Ho_Chi_Minh",
    "iso:country":"VN",
    "name:vie_x_preferred":[
        "N\u1eadm Kh\u1eaft"
    ],
    "name:vie_x_variant":[
        "B\u1ea3n N\u1eadm Kh\u1eaft"
    ],
    "wof:name":"Ban Nam Khat",
    "wof:placetype":"locality"
},
  "geometry": {"coordinates":[104.22105000000001,21.7076],"type":"Point"}
}