{
  "type": "Feature",
  "properties": {
    "gn:admin1_code":"39.0",
    "gn:asciiname":"Na Yeu",
    "gn:country_code":"VN",
    "gn:dem":462,
    "gn:feature_class":"P",
    "gn:feature_code":"PPL",
    "gn:name":"N\u00e0 Y\u00eau",
    "gn:population":0,
    "gn:timezone":"Asia/Ho_Chi_Minh",
    "iso:country":"VN",
    "name:vie_x_preferred":[
        "N\u00e0 Y\u00eau"
    ],
    "wof:name":"Na Yeu",
    "wof:placetype":"locality"
},
  "geometry": {"coordinates":[106.28639,21.87942],"type":"Point"}
}