{
  "type": "Feature",
  "properties": {
    "gn:admin1_code":"50.0",
    "gn:asciiname":"Ban Na Sai",
    "gn:country_code":"VN",
    "gn:dem":966,
    "gn:feature_class":"P",
    "gn:feature_code":"PPL",
    "gn:name":"B\u1ea3n Na Sai",
    "gn:population":0,
    "gn:timezone":"Asia/Ho_Chi_Minh",
    "iso:country":"VN",
    "name:vie_x_preferred":[
        "B\u1ea3n Na Sai"
    ],
    "wof:name":"Ban Na Sai",
    "wof:placetype":"locality"
},
  "geometry": {"coordinates":[104.50047000000001,22.72036],"type":"Point"}
}