{
  "type": "Feature",
  "properties": {
    "gn:admin1_code":"89.0",
    "gn:asciiname":"Ban Phieng Giang",
    "gn:country_code":"VN",
    "gn:dem":591,
    "gn:feature_class":"P",
    "gn:feature_code":"PPL",
    "gn:name":"B\u1ea3n Phi\u00eang Gi\u0103ng",
    "gn:population":0,
    "gn:timezone":"Asia/Ho_Chi_Minh",
    "iso:country":"VN",
    "name:und_x_variant":[
        "Pin Yang"
    ],
    "name:vie_x_preferred":[
        "B\u1ea3n Phi\u00eang Gi\u0103ng"
    ],
    "wof:name":"Ban Phieng Giang",
    "wof:placetype":"locality"
},
  "geometry": {"coordinates":[103.64717,22.27363],"type":"Point"}
}