{
  "type": "Feature",
  "properties": {
    "gn:admin1_code":"68.0",
    "gn:asciiname":"Khuon Sum",
    "gn:country_code":"VN",
    "gn:dem":149,
    "gn:feature_class":"P",
    "gn:feature_code":"PPL",
    "gn:name":"Khu\u00f4n S\u00fam",
    "gn:population":0,
    "gn:timezone":"Asia/Ho_Chi_Minh",
    "iso:country":"VN",
    "name:vie_x_preferred":[
        "Khu\u00f4n S\u00fam"
    ],
    "wof:name":"Khuon Sum",
    "wof:placetype":"locality"
},
  "geometry": {"coordinates":[105.25829,22.26884],"type":"Point"}
}