{
  "type": "Feature",
  "properties": {
    "gn:admin1_code":"46.0",
    "gn:asciiname":"Hoi Tinh",
    "gn:country_code":"VN",
    "gn:dem":20,
    "gn:feature_class":"P",
    "gn:feature_code":"PPL",
    "gn:name":"Hoi Tinh",
    "gn:population":0,
    "gn:timezone":"Asia/Ho_Chi_Minh",
    "iso:country":"VN",
    "name:und_x_variant":[
        "H\u1ed9i \u0110\u01b0c"
    ],
    "wof:name":"Hoi Tinh",
    "wof:placetype":"locality"
},
  "geometry": {"coordinates":[109.01667,14.48333],"type":"Point"}
}