{
  "type": "Feature",
  "properties": {
    "gn:admin1_code":"72.0",
    "gn:asciiname":"Thach Ngoa Hai",
    "gn:country_code":"VN",
    "gn:dem":287,
    "gn:feature_class":"P",
    "gn:feature_code":"PPL",
    "gn:name":"Th\u1ea1ch Ngo\u00e3 Hai",
    "gn:population":0,
    "gn:timezone":"Asia/Ho_Chi_Minh",
    "iso:country":"VN",
    "name:und_x_variant":[
        "Th\u1ea1ch Ngo\u00e3 Hai",
        "Ta Ngoa"
    ],
    "wof:name":"Thach Ngoa Hai",
    "wof:placetype":"locality"
},
  "geometry": {"coordinates":[105.83958,22.32015],"type":"Point"}
}