{
  "type": "Feature",
  "properties": {
    "gn:admin1_code":"50.0",
    "gn:asciiname":"Lung Quoc",
    "gn:country_code":"VN",
    "gn:dem":717,
    "gn:feature_class":"P",
    "gn:feature_code":"PPL",
    "gn:name":"L\u0169ng Qu\u1ed1c",
    "gn:population":0,
    "gn:timezone":"Asia/Ho_Chi_Minh",
    "iso:country":"VN",
    "name:vie_x_preferred":[
        "L\u00f9ng Qu\u1ed1c"
    ],
    "name:vie_x_variant":[
        "L\u0169ng Qu\u1ed1c"
    ],
    "wof:name":"Lung Quoc",
    "wof:placetype":"locality"
},
  "geometry": {"coordinates":[105.249,22.8712],"type":"Point"}
}