{
  "type": "Feature",
  "properties": {
    "gn:admin1_code":"61.0",
    "gn:asciiname":"Xuan Cay Xoai",
    "gn:country_code":"VN",
    "gn:dem":52,
    "gn:feature_class":"P",
    "gn:feature_code":"PPL",
    "gn:name":"Xu\u1eadn C\u00e2y Xo\u00e0i",
    "gn:population":0,
    "gn:timezone":"Asia/Ho_Chi_Minh",
    "iso:country":"VN",
    "name:und_x_variant":[
        "Xom Cay Xoai",
        "Xu\u1eadn C\u00e2y Xo\u00e0i"
    ],
    "wof:name":"Xuan Cay Xoai",
    "wof:placetype":"locality"
},
  "geometry": {"coordinates":[109.06667,13.26667],"type":"Point"}
}