{
  "type": "Feature",
  "properties": {
    "gn:admin1_code":"89.0",
    "gn:asciiname":"San Di",
    "gn:country_code":"VN",
    "gn:dem":862,
    "gn:feature_class":"P",
    "gn:feature_code":"PPL",
    "gn:name":"San Di",
    "gn:population":0,
    "gn:timezone":"Asia/Ho_Chi_Minh",
    "iso:country":"VN",
    "name:und_x_variant":[
        "San G\u00ec"
    ],
    "name:vie_x_preferred":[
        "San Di"
    ],
    "wof:name":"San Di",
    "wof:placetype":"locality"
},
  "geometry": {"coordinates":[103.39610999999999,22.55371],"type":"Point"}
}