{
  "type": "Feature",
  "properties": {
    "gn:admin1_code":"89.0",
    "gn:asciiname":"Ban Nam Co",
    "gn:country_code":"VN",
    "gn:dem":885,
    "gn:feature_class":"P",
    "gn:feature_code":"PPL",
    "gn:name":"B\u1ea3n N\u1eadm C\u1ecd",
    "gn:population":0,
    "gn:timezone":"Asia/Ho_Chi_Minh",
    "iso:country":"VN",
    "name:und_x_variant":[
        "B\u1ea3n Nam C\u1ea7i M\u1ebfo"
    ],
    "name:vie_x_preferred":[
        "B\u1ea3n N\u1eadm C\u1ecd"
    ],
    "wof:name":"Ban Nam Co",
    "wof:placetype":"locality"
},
  "geometry": {"coordinates":[103.53818,22.14919],"type":"Point"}
}