{
  "type": "Feature",
  "properties": {
    "gn:admin1_code":"34.0",
    "gn:asciiname":"Thon Tam",
    "gn:country_code":"VN",
    "gn:dem":16,
    "gn:feature_class":"P",
    "gn:feature_code":"PPL",
    "gn:name":"Th\u00f4n T\u00e1m",
    "gn:population":0,
    "gn:timezone":"Asia/Ho_Chi_Minh",
    "iso:country":"VN",
    "name:vie_x_preferred":[
        "Th\u00f4n T\u00e1m"
    ],
    "name:vie_x_variant":[
        "Th\u00f4n 8"
    ],
    "wof:name":"Thon Tam",
    "wof:placetype":"locality"
},
  "geometry": {"coordinates":[105.74583,19.49364],"type":"Point"}
}