{
  "type": "Feature",
  "properties": {
    "gn:admin1_code":"26.0",
    "gn:asciiname":"Yen Vuc",
    "gn:country_code":"VN",
    "gn:dem":47,
    "gn:feature_class":"P",
    "gn:feature_code":"PPL",
    "gn:name":"Y\u00ean V\u01b0c",
    "gn:population":0,
    "gn:timezone":"Asia/Ho_Chi_Minh",
    "iso:country":"VN",
    "wof:name":"Yen Vuc",
    "wof:placetype":"locality"
},
  "geometry": {"coordinates":[105.55,18.56667],"type":"Point"}
}