{
  "type": "Feature",
  "properties": {
    "gn:admin1_code":"68.0",
    "gn:asciiname":"Khuon Giang",
    "gn:country_code":"VN",
    "gn:dem":67,
    "gn:feature_class":"P",
    "gn:feature_code":"PPL",
    "gn:name":"Khu\u00f4n Giang",
    "gn:population":0,
    "gn:timezone":"Asia/Ho_Chi_Minh",
    "iso:country":"VN",
    "name:vie_x_preferred":[
        "Khu\u00f4n Giang"
    ],
    "wof:name":"Khuon Giang",
    "wof:placetype":"locality"
},
  "geometry": {"coordinates":[105.37528,21.64409],"type":"Point"}
}