{
  "type": "Feature",
  "properties": {
    "gn:admin1_code":"58.0",
    "gn:asciiname":"Xom Hai Muoi Hai",
    "gn:country_code":"VN",
    "gn:dem":9,
    "gn:feature_class":"P",
    "gn:feature_code":"PPL",
    "gn:name":"X\u00f3m Hai M\u01b0\u01a1i Hai",
    "gn:population":0,
    "gn:timezone":"Asia/Ho_Chi_Minh",
    "iso:country":"VN",
    "name:vie_x_preferred":[
        "X\u00f3m Hai M\u01b0\u01a1i Hai"
    ],
    "name:vie_x_variant":[
        "X\u00f3m 22"
    ],
    "wof:name":"Xom Hai Muoi Hai",
    "wof:placetype":"locality"
},
  "geometry": {"coordinates":[105.64963,18.76582],"type":"Point"}
}