{
  "type": "Feature",
  "properties": {
    "gn:admin1_code":"89.0",
    "gn:asciiname":"Ban Pa Cam",
    "gn:country_code":"VN",
    "gn:dem":334,
    "gn:feature_class":"P",
    "gn:feature_code":"PPL",
    "gn:name":"B\u1ea3n Pa Cam",
    "gn:population":0,
    "gn:timezone":"Asia/Ho_Chi_Minh",
    "iso:country":"VN",
    "wof:name":"Ban Pa Cam",
    "wof:placetype":"locality"
},
  "geometry": {"coordinates":[102.61667,22.48333],"type":"Point"}
}