{
  "type": "Feature",
  "properties": {
    "gn:admin1_code":"68.0",
    "gn:asciiname":"Lang Di",
    "gn:country_code":"VN",
    "gn:dem":94,
    "gn:feature_class":"P",
    "gn:feature_code":"PPL",
    "gn:name":"L\u00e0ng D\u0129",
    "gn:population":0,
    "gn:timezone":"Asia/Ho_Chi_Minh",
    "iso:country":"VN",
    "name:und_x_variant":[
        "L\u00e0ng Gi"
    ],
    "name:vie_x_preferred":[
        "L\u00e0ng D\u0129"
    ],
    "wof:name":"Lang Di",
    "wof:placetype":"locality"
},
  "geometry": {"coordinates":[105.16795999999999,22.20906],"type":"Point"}
}