{
  "type": "Feature",
  "properties": {
    "gn:admin1_code":"49.0",
    "gn:asciiname":"Plei Gol",
    "gn:country_code":"VN",
    "gn:dem":687,
    "gn:feature_class":"P",
    "gn:feature_code":"PPL",
    "gn:name":"Plei G\u01a1l",
    "gn:population":0,
    "gn:timezone":"Asia/Ho_Chi_Minh",
    "iso:country":"VN",
    "wof:name":"Plei Gol",
    "wof:placetype":"locality"
},
  "geometry": {"coordinates":[108.23333,13.98333],"type":"Point"}
}