{
  "type": "Feature",
  "properties": {
    "gn:admin1_code":"74.0",
    "gn:asciiname":"Man Xa Tay",
    "gn:country_code":"VN",
    "gn:dem":7,
    "gn:feature_class":"P",
    "gn:feature_code":"PPL",
    "gn:name":"M\u00e3n X\u00e1 T\u00e2y",
    "gn:population":0,
    "gn:timezone":"Asia/Ho_Chi_Minh",
    "iso:country":"VN",
    "name:vie_x_preferred":[
        "M\u00e3n X\u00e1 T\u00e2y"
    ],
    "wof:name":"Man Xa Tay",
    "wof:placetype":"locality"
},
  "geometry": {"coordinates":[106.02789,21.0217],"type":"Point"}
}