{
  "type": "Feature",
  "properties": {
    "gn:admin1_code":"88.0",
    "gn:asciiname":"Dat Hieu",
    "gn:country_code":"VN",
    "gn:dem":707,
    "gn:feature_class":"P",
    "gn:feature_code":"PPL",
    "gn:name":"\u0110\u1ea1t Hi\u1ebfu",
    "gn:population":0,
    "gn:timezone":"Asia/Ho_Chi_Minh",
    "iso:country":"VN",
    "name:vie_x_preferred":[
        "\u0110\u1ea1t Hi\u1ebfu"
    ],
    "wof:name":"Dat Hieu",
    "wof:placetype":"locality"
},
  "geometry": {"coordinates":[108.25608,12.93224],"type":"Point"}
}