{
  "type": "Feature",
  "properties": {
    "gn:admin1_code":"72.0",
    "gn:asciiname":"Khuoi Heo",
    "gn:country_code":"VN",
    "gn:dem":755,
    "gn:feature_class":"P",
    "gn:feature_code":"PPL",
    "gn:name":"Khu\u1ed5i H\u1ebbo",
    "gn:population":0,
    "gn:timezone":"Asia/Ho_Chi_Minh",
    "iso:country":"VN",
    "wof:name":"Khuoi Heo",
    "wof:placetype":"locality"
},
  "geometry": {"coordinates":[105.91739,22.4696],"type":"Point"}
}