{
  "type": "Feature",
  "properties": {
    "gn:admin1_code":"77.0",
    "gn:asciiname":"Xom Cay Me",
    "gn:country_code":"VN",
    "gn:dem":3,
    "gn:feature_class":"P",
    "gn:feature_code":"PPL",
    "gn:name":"X\u00f3m C\u00e2y Me",
    "gn:population":0,
    "gn:timezone":"Asia/Ho_Chi_Minh",
    "iso:country":"VN",
    "name:und_x_variant":[
        "Cay Me",
        "X\u00f3m C\u00e2y Me"
    ],
    "wof:name":"Xom Cay Me",
    "wof:placetype":"locality"
},
  "geometry": {"coordinates":[104.91667,8.68333],"type":"Point"}
}