{
  "type": "Feature",
  "properties": {
    "gn:admin1_code":"89.0",
    "gn:asciiname":"Le Ma",
    "gn:country_code":"VN",
    "gn:dem":387,
    "gn:feature_class":"P",
    "gn:feature_code":"PPL",
    "gn:name":"Le Ma",
    "gn:population":0,
    "gn:timezone":"Asia/Ho_Chi_Minh",
    "iso:country":"VN",
    "name:vie_x_preferred":[
        "Le Ma"
    ],
    "wof:name":"Le Ma",
    "wof:placetype":"locality"
},
  "geometry": {"coordinates":[102.51394000000001,22.57485],"type":"Point"}
}