{
  "type": "Feature",
  "properties": {
    "gn:admin1_code":"83.0",
    "gn:asciiname":"Dao Thon",
    "gn:country_code":"VN",
    "gn:dem":33,
    "gn:feature_class":"P",
    "gn:feature_code":"PPL",
    "gn:name":"\u0110\u00e0o Th\u00f4n",
    "gn:population":0,
    "gn:timezone":"Asia/Ho_Chi_Minh",
    "iso:country":"VN",
    "name:vie_x_preferred":[
        "\u0110\u00e0o Th\u00f4n"
    ],
    "wof:name":"Dao Thon",
    "wof:placetype":"locality"
},
  "geometry": {"coordinates":[105.30016000000001,21.22468],"type":"Point"}
}