{
  "type": "Feature",
  "properties": {
    "gn:admin1_code":"64.0",
    "gn:asciiname":"Thuy Can",
    "gn:country_code":"VN",
    "gn:dem":-9999,
    "gn:feature_class":"P",
    "gn:feature_code":"PPL",
    "gn:name":"Th\u1ee7y C\u1ea7n",
    "gn:population":0,
    "gn:timezone":"Asia/Ho_Chi_Minh",
    "iso:country":"VN",
    "wof:name":"Thuy Can",
    "wof:placetype":"locality"
},
  "geometry": {"coordinates":[107.11667,17.08333],"type":"Point"}
}