{
  "type": "Feature",
  "properties": {
    "gn:admin1_code":"82.0",
    "gn:asciiname":"Cuong Hai",
    "gn:country_code":"VN",
    "gn:dem":1,
    "gn:feature_class":"P",
    "gn:feature_code":"PPL",
    "gn:name":"C\u01b0\u1eddng H\u1ea3i",
    "gn:population":0,
    "gn:timezone":"Asia/Ho_Chi_Minh",
    "iso:country":"VN",
    "name:vie_x_preferred":[
        "C\u01b0\u1eddng H\u1ea3i"
    ],
    "wof:name":"Cuong Hai",
    "wof:placetype":"locality"
},
  "geometry": {"coordinates":[106.2358,20.2263],"type":"Point"}
}