{
  "type": "Feature",
  "properties": {
    "gn:admin1_code":"37.0",
    "gn:asciiname":"An Thi",
    "gn:country_code":"VN",
    "gn:dem":1,
    "gn:feature_class":"P",
    "gn:feature_code":"PPL",
    "gn:name":"An Th\u1ecb",
    "gn:population":0,
    "gn:timezone":"Asia/Ho_Chi_Minh",
    "iso:country":"VN",
    "name:vie_x_preferred":[
        "An Th\u1ecb"
    ],
    "wof:name":"An Thi",
    "wof:placetype":"locality"
},
  "geometry": {"coordinates":[106.38176,10.45788],"type":"Point"}
}