{
  "type": "Feature",
  "properties": {
    "gn:admin1_code":"58.0",
    "gn:asciiname":"Dau Vinh",
    "gn:country_code":"VN",
    "gn:dem":5,
    "gn:feature_class":"P",
    "gn:feature_code":"PPL",
    "gn:name":"\u0110\u1eadu Vinh",
    "gn:population":0,
    "gn:timezone":"Asia/Ho_Chi_Minh",
    "iso:country":"VN",
    "name:vie_x_preferred":[
        "\u0110\u1eadu Vinh"
    ],
    "wof:name":"Dau Vinh",
    "wof:placetype":"locality"
},
  "geometry": {"coordinates":[105.59741,19.04569],"type":"Point"}
}