{
  "type": "Feature",
  "properties": {
    "gn:admin1_code":"72.0",
    "gn:asciiname":"Phia Khao",
    "gn:country_code":"VN",
    "gn:dem":636,
    "gn:feature_class":"P",
    "gn:feature_code":"PPLL",
    "gn:name":"Phia Khao",
    "gn:population":0,
    "gn:timezone":"Asia/Ho_Chi_Minh",
    "iso:country":"VN",
    "wof:name":"Phia Khao",
    "wof:placetype":"locality"
},
  "geometry": {"coordinates":[105.97477000000001,22.43563],"type":"Point"}
}