{
  "type": "Feature",
  "properties": {
    "gn:admin1_code":"67.0",
    "gn:asciiname":"Ngai Hiep",
    "gn:country_code":"VN",
    "gn:dem":3,
    "gn:feature_class":"P",
    "gn:feature_code":"PPL",
    "gn:name":"Ng\u00e0i Hi\u1ec7p",
    "gn:population":0,
    "gn:timezone":"Asia/Ho_Chi_Minh",
    "iso:country":"VN",
    "name:vie_x_preferred":[
        "Ng\u00e0i Hi\u1ec7p"
    ],
    "wof:name":"Ngai Hiep",
    "wof:placetype":"locality"
},
  "geometry": {"coordinates":[106.40873000000001,9.89849],"type":"Point"}
}