{
  "type": "Feature",
  "properties": {
    "gn:admin1_code":"63.0",
    "gn:asciiname":"Nuoc Gia",
    "gn:country_code":"VN",
    "gn:dem":55,
    "gn:feature_class":"P",
    "gn:feature_code":"PPL",
    "gn:name":"N\u01b0\u1edbc Gia",
    "gn:population":0,
    "gn:timezone":"Asia/Ho_Chi_Minh",
    "iso:country":"VN",
    "name:vie_x_preferred":[
        "N\u01b0\u1edbc Gia"
    ],
    "wof:name":"Nuoc Gia",
    "wof:placetype":"locality"
},
  "geometry": {"coordinates":[108.70132,14.82111],"type":"Point"}
}