{
  "type": "Feature",
  "properties": {
    "gn:admin1_code":"82.0",
    "gn:asciiname":"Tuan Chu",
    "gn:country_code":"VN",
    "gn:dem":5,
    "gn:feature_class":"P",
    "gn:feature_code":"PPL",
    "gn:name":"Tu\u00e2n Ch\u01b0",
    "gn:population":0,
    "gn:timezone":"Asia/Ho_Chi_Minh",
    "iso:country":"VN",
    "wof:name":"Tuan Chu",
    "wof:placetype":"locality"
},
  "geometry": {"coordinates":[106.21666999999999,20.16667],"type":"Point"}
}