{
  "type": "Feature",
  "properties": {
    "gn:admin1_code":"83.0",
    "gn:asciiname":"Go Che",
    "gn:country_code":"VN",
    "gn:dem":31,
    "gn:feature_class":"P",
    "gn:feature_code":"PPL",
    "gn:name":"G\u00f2 Ch\u00e8",
    "gn:population":0,
    "gn:timezone":"Asia/Ho_Chi_Minh",
    "iso:country":"VN",
    "name:vie_x_preferred":[
        "G\u00f2 Ch\u00e8"
    ],
    "wof:name":"Go Che",
    "wof:placetype":"locality"
},
  "geometry": {"coordinates":[105.04138,21.42297],"type":"Point"}
}