{
  "type": "Feature",
  "properties": {
    "gn:admin1_code":"91.0",
    "gn:asciiname":"Bu Jeng Gle",
    "gn:country_code":"VN",
    "gn:dem":590,
    "gn:feature_class":"P",
    "gn:feature_code":"PPL",
    "gn:name":"Bu Jeng Gl\u00e9",
    "gn:population":0,
    "gn:timezone":"Asia/Ho_Chi_Minh",
    "iso:country":"VN",
    "wof:name":"Bu Jeng Gle",
    "wof:placetype":"locality"
},
  "geometry": {"coordinates":[107.48333,12.01667],"type":"Point"}
}