{
  "type": "Feature",
  "properties": {
    "gn:admin1_code":"89.0",
    "gn:asciiname":"Ban Cay Gao",
    "gn:country_code":"VN",
    "gn:dem":619,
    "gn:feature_class":"P",
    "gn:feature_code":"PPL",
    "gn:name":"B\u1ea3n C\u00e2y G\u1ea1o",
    "gn:population":0,
    "gn:timezone":"Asia/Ho_Chi_Minh",
    "iso:country":"VN",
    "name:vie_x_preferred":[
        "B\u1ea3n C\u00e2y G\u1ea1o"
    ],
    "wof:name":"Ban Cay Gao",
    "wof:placetype":"locality"
},
  "geometry": {"coordinates":[103.79196,22.13093],"type":"Point"}
}