{
  "type": "Feature",
  "properties": {
    "gn:admin1_code":"61.0",
    "gn:asciiname":"Nguyen Xuan",
    "gn:country_code":"VN",
    "gn:dem":48,
    "gn:feature_class":"P",
    "gn:feature_code":"PPL",
    "gn:name":"Nguy\u00ean Xu\u00e2n",
    "gn:population":0,
    "gn:timezone":"Asia/Ho_Chi_Minh",
    "iso:country":"VN",
    "name:vie_x_preferred":[
        "Nguy\u00ean Xu\u00e2n"
    ],
    "wof:name":"Nguyen Xuan",
    "wof:placetype":"locality"
},
  "geometry": {"coordinates":[109.04572,13.11154],"type":"Point"}
}