{
  "type": "Feature",
  "properties": {
    "gn:admin1_code":"90.0",
    "gn:asciiname":"O Qui Ho",
    "gn:country_code":"VN",
    "gn:dem":1704,
    "gn:feature_class":"P",
    "gn:feature_code":"PPL",
    "gn:name":"\u00d4 Qu\u00ed H\u1ed3",
    "gn:population":0,
    "gn:timezone":"Asia/Ho_Chi_Minh",
    "iso:country":"VN",
    "name:und_x_variant":[
        "\u00d4 Quy H\u1ed3"
    ],
    "name:vie_x_preferred":[
        "\u00d4 Qu\u00ed H\u1ed3"
    ],
    "wof:name":"O Qui Ho",
    "wof:placetype":"locality"
},
  "geometry": {"coordinates":[103.79456999999999,22.37072],"type":"Point"}
}