{
  "type": "Feature",
  "properties": {
    "gn:admin1_code":"58.0",
    "gn:asciiname":"Ban Nam Bo",
    "gn:country_code":"VN",
    "gn:dem":112,
    "gn:feature_class":"P",
    "gn:feature_code":"PPL",
    "gn:name":"B\u1ea3n N\u00e2m B\u1ed1",
    "gn:population":0,
    "gn:timezone":"Asia/Ho_Chi_Minh",
    "iso:country":"VN",
    "name:und_x_variant":[
        "Ban Nam",
        "B\u1ea3n N\u00e2m B\u1ed1"
    ],
    "wof:name":"Ban Nam Bo",
    "wof:placetype":"locality"
},
  "geometry": {"coordinates":[104.95,18.93333],"type":"Point"}
}