{
  "type": "Feature",
  "properties": {
    "gn:admin1_code":"88.0",
    "gn:asciiname":"Minh Ha",
    "gn:country_code":"VN",
    "gn:dem":572,
    "gn:feature_class":"P",
    "gn:feature_code":"PPL",
    "gn:name":"Minh H\u00e0",
    "gn:population":0,
    "gn:timezone":"Asia/Ho_Chi_Minh",
    "iso:country":"VN",
    "name:vie_x_preferred":[
        "Minh H\u00e0"
    ],
    "wof:name":"Minh Ha",
    "wof:placetype":"locality"
},
  "geometry": {"coordinates":[108.40863,12.92271],"type":"Point"}
}