{
  "type": "Feature",
  "properties": {
    "gn:admin1_code":"58.0",
    "gn:asciiname":"Truyen Thon",
    "gn:country_code":"VN",
    "gn:dem":4,
    "gn:feature_class":"P",
    "gn:feature_code":"PPL",
    "gn:name":"Truy\u00ean Th\u00f4n",
    "gn:population":0,
    "gn:timezone":"Asia/Ho_Chi_Minh",
    "iso:country":"VN",
    "name:und_x_variant":[
        "Truy\u00ean Th\u00f4n"
    ],
    "name:vie_x_preferred":[
        "Truyen Thon"
    ],
    "wof:name":"Truyen Thon",
    "wof:placetype":"locality"
},
  "geometry": {"coordinates":[105.56667,18.78333],"type":"Point"}
}