{
  "type": "Feature",
  "properties": {
    "gn:admin1_code":"83.0",
    "gn:asciiname":"Lang Nhe Mot",
    "gn:country_code":"VN",
    "gn:dem":163,
    "gn:feature_class":"P",
    "gn:feature_code":"PPL",
    "gn:name":"L\u00e0ng Nh\u00e9 M\u1ed9t",
    "gn:population":0,
    "gn:timezone":"Asia/Ho_Chi_Minh",
    "iso:country":"VN",
    "name:und_x_variant":[
        "L\u00e0ng Nh\u00e9",
        "L\u00e0ng Nh\u00e9 1"
    ],
    "name:vie_x_preferred":[
        "L\u00e0ng Nh\u00e9 M\u1ed9t"
    ],
    "wof:name":"Lang Nhe Mot",
    "wof:placetype":"locality"
},
  "geometry": {"coordinates":[104.88242,21.22317],"type":"Point"}
}