{
  "type": "Feature",
  "properties": {
    "gn:admin1_code":"44.0",
    "gn:asciiname":"Tong Thai",
    "gn:country_code":"VN",
    "gn:dem":21,
    "gn:feature_class":"P",
    "gn:feature_code":"PPL",
    "gn:name":"T\u00f2ng Th\u00e1i",
    "gn:population":0,
    "gn:timezone":"Asia/Ho_Chi_Minh",
    "iso:country":"VN",
    "name:vie_x_preferred":[
        "T\u00f2ng Th\u00e1i"
    ],
    "wof:name":"Tong Thai",
    "wof:placetype":"locality"
},
  "geometry": {"coordinates":[105.33322,21.19507],"type":"Point"}
}