{
  "type": "Feature",
  "properties": {
    "gn:admin1_code":"71.0",
    "gn:asciiname":"Xuan Tan",
    "gn:country_code":"VN",
    "gn:dem":12,
    "gn:feature_class":"P",
    "gn:feature_code":"PPL",
    "gn:name":"Xu\u00e2n T\u00e2n",
    "gn:population":0,
    "gn:timezone":"Asia/Ho_Chi_Minh",
    "iso:country":"VN",
    "name:vie_x_preferred":[
        "Xu\u00e2n T\u00e2n"
    ],
    "wof:name":"Xuan Tan",
    "wof:placetype":"locality"
},
  "geometry": {"coordinates":[106.09207000000001,21.39434],"type":"Point"}
}