{
  "type": "Feature",
  "properties": {
    "gn:admin1_code":"5.0",
    "gn:asciiname":"Na Lai",
    "gn:country_code":"VN",
    "gn:dem":467,
    "gn:feature_class":"P",
    "gn:feature_code":"PPL",
    "gn:name":"N\u00e0 Lai",
    "gn:population":0,
    "gn:timezone":"Asia/Ho_Chi_Minh",
    "iso:country":"VN",
    "name:und_x_variant":[
        "Ma Lot",
        "Na Lot"
    ],
    "name:vie_x_preferred":[
        "N\u00e0 Lai"
    ],
    "wof:name":"Na Lai",
    "wof:placetype":"locality"
},
  "geometry": {"coordinates":[105.71455,22.95343],"type":"Point"}
}