{
  "type": "Feature",
  "properties": {
    "gn:admin1_code":"89.0",
    "gn:asciiname":"Nam Tien Hai",
    "gn:country_code":"VN",
    "gn:dem":448,
    "gn:feature_class":"P",
    "gn:feature_code":"PPL",
    "gn:name":"N\u1eadm Ti\u1ebfn Hai",
    "gn:population":0,
    "gn:timezone":"Asia/Ho_Chi_Minh",
    "iso:country":"VN",
    "name:vie_x_preferred":[
        "N\u1eadm Ti\u1ebfn Hai"
    ],
    "name:vie_x_variant":[
        "N\u1eadm Ti\u1ebfn 2"
    ],
    "wof:name":"Nam Tien Hai",
    "wof:placetype":"locality"
},
  "geometry": {"coordinates":[103.15169,22.48915],"type":"Point"}
}