{
  "type": "Feature",
  "properties": {
    "gn:admin1_code":"53.0",
    "gn:asciiname":"Bac Son",
    "gn:country_code":"VN",
    "gn:dem":214,
    "gn:feature_class":"P",
    "gn:feature_code":"PPL",
    "gn:name":"B\u1eafc S\u01a1n",
    "gn:population":0,
    "gn:timezone":"Asia/Ho_Chi_Minh",
    "iso:country":"VN",
    "name:vie_x_preferred":[
        "B\u1eafc S\u01a1n"
    ],
    "wof:name":"Bac Son",
    "wof:placetype":"locality"
},
  "geometry": {"coordinates":[105.31983,20.74203],"type":"Point"}
}