{
  "type": "Feature",
  "properties": {
    "gn:admin1_code":"58.0",
    "gn:asciiname":"Tan Thu",
    "gn:country_code":"VN",
    "gn:dem":7,
    "gn:feature_class":"P",
    "gn:feature_code":"PPL",
    "gn:name":"T\u00e2n Th\u01b0",
    "gn:population":0,
    "gn:timezone":"Asia/Ho_Chi_Minh",
    "iso:country":"VN",
    "name:vie_x_preferred":[
        "T\u00e2n Th\u01b0"
    ],
    "wof:name":"Tan Thu",
    "wof:placetype":"locality"
},
  "geometry": {"coordinates":[105.5244,19.00678],"type":"Point"}
}