{
  "type": "Feature",
  "properties": {
    "gn:admin1_code":"53.0",
    "gn:asciiname":"Xom Cang",
    "gn:country_code":"VN",
    "gn:dem":681,
    "gn:feature_class":"P",
    "gn:feature_code":"PPL",
    "gn:name":"X\u00f3m Cang",
    "gn:population":0,
    "gn:timezone":"Asia/Ho_Chi_Minh",
    "iso:country":"VN",
    "name:vie_x_preferred":[
        "X\u00f3m Cang"
    ],
    "wof:name":"Xom Cang",
    "wof:placetype":"locality"
},
  "geometry": {"coordinates":[105.06627,20.90737],"type":"Point"}
}