{
  "type": "Feature",
  "properties": {
    "gn:admin1_code":"23.0",
    "gn:asciiname":"Da M'Ri",
    "gn:country_code":"VN",
    "gn:dem":257,
    "gn:feature_class":"P",
    "gn:feature_code":"PPL",
    "gn:name":"\u0110\u1ea1 M\u2019Ri",
    "gn:population":0,
    "gn:timezone":"Asia/Ho_Chi_Minh",
    "iso:country":"VN",
    "name:vie_x_preferred":[
        "\u0110\u1ea1 M\u2019Ri"
    ],
    "wof:name":"Da M'Ri",
    "wof:placetype":"locality"
},
  "geometry": {"coordinates":[107.65893,11.41029],"type":"Point"}
}