{
  "type": "Feature",
  "properties": {
    "gn:admin1_code":"90.0",
    "gn:asciiname":"Ngai Thau Hai",
    "gn:country_code":"VN",
    "gn:dem":1117,
    "gn:feature_class":"P",
    "gn:feature_code":"PPL",
    "gn:name":"Ng\u1ea3i Th\u1ea7u Hai",
    "gn:population":0,
    "gn:timezone":"Asia/Ho_Chi_Minh",
    "iso:country":"VN",
    "name:vie_x_preferred":[
        "Ng\u1ea3i Th\u1ea7u Hai"
    ],
    "name:vie_x_variant":[
        "Ng\u1ea3i Th\u1ea7u 2"
    ],
    "wof:name":"Ngai Thau Hai",
    "wof:placetype":"locality"
},
  "geometry": {"coordinates":[104.26476,22.52324],"type":"Point"}
}