{
  "type": "Feature",
  "properties": {
    "gn:admin1_code":"32.0",
    "gn:asciiname":"Nuoi Lac",
    "gn:country_code":"VN",
    "gn:dem":346,
    "gn:feature_class":"P",
    "gn:feature_code":"PPL",
    "gn:name":"Nu\u00f4i Lac",
    "gn:population":0,
    "gn:timezone":"Asia/Ho_Chi_Minh",
    "iso:country":"VN",
    "wof:name":"Nuoi Lac",
    "wof:placetype":"locality"
},
  "geometry": {"coordinates":[104.68333,21.18333],"type":"Point"}
}