{
  "type": "Feature",
  "properties": {
    "gn:admin1_code":"71.0",
    "gn:asciiname":"Nam Son",
    "gn:country_code":"VN",
    "gn:dem":17,
    "gn:feature_class":"P",
    "gn:feature_code":"PPL",
    "gn:name":"Nam S\u01a1n",
    "gn:population":0,
    "gn:timezone":"Asia/Ho_Chi_Minh",
    "iso:country":"VN",
    "name:vie_x_preferred":[
        "Nam S\u01a1n"
    ],
    "wof:name":"Nam Son",
    "wof:placetype":"locality"
},
  "geometry": {"coordinates":[106.03176000000001,21.39656],"type":"Point"}
}