{
  "type": "Feature",
  "properties": {
    "gn:admin1_code":"70.0",
    "gn:asciiname":"Khe Cam",
    "gn:country_code":"VN",
    "gn:dem":279,
    "gn:feature_class":"P",
    "gn:feature_code":"PPL",
    "gn:name":"Kh\u1ec1 Cam",
    "gn:population":0,
    "gn:timezone":"Asia/Ho_Chi_Minh",
    "iso:country":"VN",
    "name:und_x_variant":[
        "Khe Can",
        "Kh\u1ec1 Cam"
    ],
    "wof:name":"Khe Cam",
    "wof:placetype":"locality"
},
  "geometry": {"coordinates":[104.76667,21.58333],"type":"Point"}
}