{
  "type": "Feature",
  "properties": {
    "gn:admin1_code":"24.0",
    "gn:asciiname":"Ap Ben Tram",
    "gn:country_code":"VN",
    "gn:dem":3,
    "gn:feature_class":"P",
    "gn:feature_code":"PPL",
    "gn:name":"\u1ea4p B\u00ean Tr\u00e0m",
    "gn:population":0,
    "gn:timezone":"Asia/Ho_Chi_Minh",
    "iso:country":"VN",
    "wof:name":"Ap Ben Tram",
    "wof:placetype":"locality"
},
  "geometry": {"coordinates":[105.84999999999999,10.85],"type":"Point"}
}