{
  "type": "Feature",
  "properties": {
    "gn:admin1_code":"37.0",
    "gn:asciiname":"Ap Muoi",
    "gn:country_code":"VN",
    "gn:dem":6,
    "gn:feature_class":"P",
    "gn:feature_code":"PPL",
    "gn:name":"\u1ea4p M\u01b0\u1eddi",
    "gn:population":0,
    "gn:timezone":"Asia/Ho_Chi_Minh",
    "iso:country":"VN",
    "name:vie_x_preferred":[
        "\u1ea4p M\u01b0\u1eddi"
    ],
    "name:vie_x_variant":[
        "\u1ea4p 10"
    ],
    "wof:name":"Ap Muoi",
    "wof:placetype":"locality"
},
  "geometry": {"coordinates":[106.04801999999999,10.40444],"type":"Point"}
}