{
  "type": "Feature",
  "properties": {
    "gn:admin1_code":"39.0",
    "gn:asciiname":"Ba Ha",
    "gn:country_code":"VN",
    "gn:dem":398,
    "gn:feature_class":"P",
    "gn:feature_code":"PPL",
    "gn:name":"B\u00e1 H\u00e0",
    "gn:population":0,
    "gn:timezone":"Asia/Ho_Chi_Minh",
    "iso:country":"VN",
    "name:vie_x_preferred":[
        "B\u00e1 H\u00e0"
    ],
    "wof:name":"Ba Ha",
    "wof:placetype":"locality"
},
  "geometry": {"coordinates":[106.42229,21.80923],"type":"Point"}
}