{
  "type": "Feature",
  "properties": {
    "gn:admin1_code":"50.0",
    "gn:asciiname":"Khau Thue",
    "gn:country_code":"VN",
    "gn:dem":322,
    "gn:feature_class":"P",
    "gn:feature_code":"PPL",
    "gn:name":"Khau Thu\u00ea",
    "gn:population":0,
    "gn:timezone":"Asia/Ho_Chi_Minh",
    "iso:country":"VN",
    "name:vie_x_preferred":[
        "Kh\u00e2u Thi\u00eac"
    ],
    "name:vie_x_variant":[
        "B\u1ea3n Khau Thi\u1ebft",
        "Khau Thu\u00ea"
    ],
    "wof:name":"Khau Thue",
    "wof:placetype":"locality"
},
  "geometry": {"coordinates":[105.361,22.72531],"type":"Point"}
}