{
  "type": "Feature",
  "properties": {
    "gn:admin1_code":"32.0",
    "gn:asciiname":"Ban Nong Giang",
    "gn:country_code":"VN",
    "gn:dem":602,
    "gn:feature_class":"P",
    "gn:feature_code":"PPL",
    "gn:name":"B\u1ea3n N\u00f4ng Gi\u1eb1ng",
    "gn:population":0,
    "gn:timezone":"Asia/Ho_Chi_Minh",
    "iso:country":"VN",
    "wof:name":"Ban Nong Giang",
    "wof:placetype":"locality"
},
  "geometry": {"coordinates":[103.73333,21.48333],"type":"Point"}
}