{
  "type": "Feature",
  "properties": {
    "gn:admin1_code":"39.0",
    "gn:asciiname":"Ban Ghe",
    "gn:country_code":"VN",
    "gn:dem":429,
    "gn:feature_class":"P",
    "gn:feature_code":"PPL",
    "gn:name":"B\u1ea3n Gh\u1ec1",
    "gn:population":0,
    "gn:timezone":"Asia/Ho_Chi_Minh",
    "iso:country":"VN",
    "name:vie_x_preferred":[
        "B\u1ea3n Gh\u1ec1"
    ],
    "wof:name":"Ban Ghe",
    "wof:placetype":"locality"
},
  "geometry": {"coordinates":[106.32156000000001,21.85248],"type":"Point"}
}