{
  "type": "Feature",
  "properties": {
    "gn:admin1_code":"68.0",
    "gn:asciiname":"Khuon Chau",
    "gn:country_code":"VN",
    "gn:dem":122,
    "gn:feature_class":"P",
    "gn:feature_code":"PPL",
    "gn:name":"Khu\u00f4n Ch\u00e2u",
    "gn:population":0,
    "gn:timezone":"Asia/Ho_Chi_Minh",
    "iso:country":"VN",
    "name:vie_x_preferred":[
        "Khu\u00f4n Ch\u00e2u"
    ],
    "wof:name":"Khuon Chau",
    "wof:placetype":"locality"
},
  "geometry": {"coordinates":[105.43704,21.66807],"type":"Point"}
}