{
  "type": "Feature",
  "properties": {
    "gn:admin1_code":"52.0",
    "gn:asciiname":"Xom Muoi Bon",
    "gn:country_code":"VN",
    "gn:dem":9,
    "gn:feature_class":"P",
    "gn:feature_code":"PPL",
    "gn:name":"X\u00f3m M\u01b0\u1eddi B\u1ed1n",
    "gn:population":0,
    "gn:timezone":"Asia/Ho_Chi_Minh",
    "iso:country":"VN",
    "name:vie_x_preferred":[
        "X\u00f3m M\u01b0\u1eddi B\u1ed1n"
    ],
    "name:vie_x_variant":[
        "X\u00f3m 14"
    ],
    "wof:name":"Xom Muoi Bon",
    "wof:placetype":"locality"
},
  "geometry": {"coordinates":[105.87285,18.47123],"type":"Point"}
}