{
  "type": "Feature",
  "properties": {
    "gn:admin1_code":"61.0",
    "gn:asciiname":"Ha Giang",
    "gn:country_code":"VN",
    "gn:dem":36,
    "gn:feature_class":"P",
    "gn:feature_code":"PPL",
    "gn:name":"H\u00e0 Giang",
    "gn:population":0,
    "gn:timezone":"Asia/Ho_Chi_Minh",
    "iso:country":"VN",
    "name:heb_x_preferred":[
        "\u05d4\u05d0 \u05d2'\u05d9\u05d0\u05e0\u05d2"
    ],
    "name:hun_x_preferred":[
        "Ha Giang"
    ],
    "name:por_x_preferred":[
        "H\u00e0 Giang"
    ],
    "name:spa_x_preferred":[
        "Ha Giang"
    ],
    "name:und_x_variant":[
        "Dieu Giang",
        "Nhi\u1ec5u Giang"
    ],
    "name:vie_x_preferred":[
        "H\u00e0 Giang"
    ],
    "wof:name":"Ha Giang",
    "wof:placetype":"locality"
},
  "geometry": {"coordinates":[109.03598,13.01774],"type":"Point"}
}