{
  "type": "Feature",
  "properties": {
    "gn:admin1_code":"88.0",
    "gn:asciiname":"Buon Blang",
    "gn:cc2":"VN",
    "gn:country_code":"VN",
    "gn:dem":441,
    "gn:feature_class":"P",
    "gn:feature_code":"PPL",
    "gn:name":"Bu\u00f4n Blang",
    "gn:population":0,
    "gn:timezone":"Asia/Ho_Chi_Minh",
    "iso:country":"VN",
    "name:und_x_variant":[
        "Ban Blang",
        "Bu\u00f4n Blang"
    ],
    "wof:name":"Buon Blang",
    "wof:placetype":"locality"
},
  "geometry": {"coordinates":[108.08333,12.53333],"type":"Point"}
}