{
  "type": "Feature",
  "properties": {
    "gn:admin1_code":"66.0",
    "gn:asciiname":"Phu Vang",
    "gn:country_code":"VN",
    "gn:dem":8,
    "gn:feature_class":"P",
    "gn:feature_code":"PPLA2",
    "gn:name":"Ph\u00fa Vang",
    "gn:population":0,
    "gn:timezone":"Asia/Ho_Chi_Minh",
    "iso:country":"VN",
    "name:vie_x_preferred":[
        "Ph\u00fa Vang"
    ],
    "wof:name":"Phu Vang",
    "wof:placetype":"locality"
},
  "geometry": {"coordinates":[107.71438000000001,16.43911],"type":"Point"}
}