{
  "type": "Feature",
  "properties": {
    "gn:admin1_code":"68.0",
    "gn:asciiname":"Khuon Phuon",
    "gn:country_code":"VN",
    "gn:dem":98,
    "gn:feature_class":"P",
    "gn:feature_code":"PPL",
    "gn:name":"Khu\u00f4n Ph\u01b0\u01a1n",
    "gn:population":0,
    "gn:timezone":"Asia/Ho_Chi_Minh",
    "iso:country":"VN",
    "name:vie_x_preferred":[
        "Khu\u00f4n Ph\u01b0\u01a1n"
    ],
    "wof:name":"Khuon Phuon",
    "wof:placetype":"locality"
},
  "geometry": {"coordinates":[105.36781999999999,22.36794],"type":"Point"}
}