{
  "type": "Feature",
  "properties": {
    "gn:admin1_code":"32.0",
    "gn:asciiname":"Ban Han B",
    "gn:country_code":"VN",
    "gn:dem":292,
    "gn:feature_class":"P",
    "gn:feature_code":"PPL",
    "gn:name":"B\u1ea3n H\u00e1n B",
    "gn:population":0,
    "gn:timezone":"Asia/Ho_Chi_Minh",
    "iso:country":"VN",
    "name:vie_x_preferred":[
        "B\u1ea3n H\u00e1n B"
    ],
    "wof:name":"Ban Han B",
    "wof:placetype":"locality"
},
  "geometry": {"coordinates":[103.70018,21.56285],"type":"Point"}
}