{
  "type": "Feature",
  "properties": {
    "gn:admin1_code":"71.0",
    "gn:asciiname":"Bo Cho",
    "gn:country_code":"VN",
    "gn:dem":15,
    "gn:feature_class":"P",
    "gn:feature_code":"PPL",
    "gn:name":"Bo Ch\u1ee3",
    "gn:population":0,
    "gn:timezone":"Asia/Ho_Chi_Minh",
    "iso:country":"VN",
    "name:vie_x_preferred":[
        "Bo Ch\u1ee3"
    ],
    "wof:name":"Bo Cho",
    "wof:placetype":"locality"
},
  "geometry": {"coordinates":[106.20851999999999,21.45307],"type":"Point"}
}