{
  "type": "Feature",
  "properties": {
    "gn:admin1_code":"34.0",
    "gn:asciiname":"Cam Ram",
    "gn:cc2":"VN",
    "gn:country_code":"VN",
    "gn:dem":82,
    "gn:feature_class":"P",
    "gn:feature_code":"PPL",
    "gn:name":"Cam R\u00e0m",
    "gn:population":0,
    "gn:timezone":"Asia/Ho_Chi_Minh",
    "iso:country":"VN",
    "name:und_x_variant":[
        "Chom Ram",
        "Cam R\u00e0m"
    ],
    "wof:name":"Cam Ram",
    "wof:placetype":"locality"
},
  "geometry": {"coordinates":[105.45,20.11667000000001],"type":"Point"}
}