{
  "type": "Feature",
  "properties": {
    "gn:admin1_code":"53.0",
    "gn:asciiname":"Hom Hao",
    "gn:country_code":"VN",
    "gn:dem":755,
    "gn:feature_class":"P",
    "gn:feature_code":"PPL",
    "gn:name":"Hom Hao",
    "gn:population":0,
    "gn:timezone":"Asia/Ho_Chi_Minh",
    "iso:country":"VN",
    "wof:name":"Hom Hao",
    "wof:placetype":"locality"
},
  "geometry": {"coordinates":[105.06667,20.85],"type":"Point"}
}