{
  "type": "Feature",
  "properties": {
    "gn:admin1_code":"43.0",
    "gn:asciiname":"Cam My",
    "gn:country_code":"VN",
    "gn:dem":135,
    "gn:feature_class":"P",
    "gn:feature_code":"PPL",
    "gn:name":"C\u1ea9m M\u1ef9",
    "gn:population":0,
    "gn:timezone":"Asia/Ho_Chi_Minh",
    "iso:country":"VN",
    "name:und_x_variant":[
        "Gam My",
        "C\u1ea9m M\u1ef9"
    ],
    "wof:name":"Cam My",
    "wof:placetype":"locality"
},
  "geometry": {"coordinates":[107.31667,10.76667],"type":"Point"}
}