{
  "type": "Feature",
  "properties": {
    "gn:admin1_code":"32.0",
    "gn:asciiname":"Ban Cang",
    "gn:country_code":"VN",
    "gn:dem":331,
    "gn:feature_class":"P",
    "gn:feature_code":"PPL",
    "gn:name":"B\u1ea3n Cang",
    "gn:population":0,
    "gn:timezone":"Asia/Ho_Chi_Minh",
    "iso:country":"VN",
    "name:vie_x_preferred":[
        "B\u1ea3n Cang"
    ],
    "wof:name":"Ban Cang",
    "wof:placetype":"locality"
},
  "geometry": {"coordinates":[103.79155,21.02146],"type":"Point"}
}