{
  "type": "Feature",
  "properties": {
    "gn:admin1_code":"71.0",
    "gn:asciiname":"Ngoc Trai",
    "gn:country_code":"VN",
    "gn:dem":14,
    "gn:feature_class":"P",
    "gn:feature_code":"PPL",
    "gn:name":"Ng\u1ecdc Tr\u1ea1i",
    "gn:population":0,
    "gn:timezone":"Asia/Ho_Chi_Minh",
    "iso:country":"VN",
    "name:vie_x_preferred":[
        "Ng\u1ecdc Tr\u1ea1i"
    ],
    "wof:name":"Ngoc Trai",
    "wof:placetype":"locality"
},
  "geometry": {"coordinates":[106.14637999999999,21.33603],"type":"Point"}
}