{
  "type": "Feature",
  "properties": {
    "gn:admin1_code":"49.0",
    "gn:asciiname":"A Yun Pa",
    "gn:country_code":"VN",
    "gn:dem":165,
    "gn:feature_class":"P",
    "gn:feature_code":"PPLA2",
    "gn:name":"A Yun Pa",
    "gn:population":0,
    "gn:timezone":"Asia/Ho_Chi_Minh",
    "iso:country":"VN",
    "name:vie_x_preferred":[
        "A Yun Pa"
    ],
    "wof:name":"A Yun Pa",
    "wof:placetype":"locality"
},
  "geometry": {"coordinates":[108.43503,13.40025],"type":"Point"}
}