{
  "type": "Feature",
  "properties": {
    "gn:admin1_code":"21.0",
    "gn:asciiname":"Vinh Hoa Hiep",
    "gn:cc2":"VN",
    "gn:country_code":"VN",
    "gn:dem":3,
    "gn:feature_class":"P",
    "gn:feature_code":"PPL",
    "gn:name":"V\u0129nh H\u00f2a Hi\u1ec7p",
    "gn:population":0,
    "gn:timezone":"Asia/Ho_Chi_Minh",
    "iso:country":"VN",
    "name:und_x_variant":[
        "Vinh Hoa Dong",
        "V\u0129nh H\u00f2a Hi\u1ec7p"
    ],
    "wof:name":"Vinh Hoa Hiep",
    "wof:placetype":"locality"
},
  "geometry": {"coordinates":[105.11667,9.91667],"type":"Point"}
}