{
  "type": "Feature",
  "properties": {
    "gn:admin1_code":"69.0",
    "gn:asciiname":"Phuoc Loi",
    "gn:country_code":"VN",
    "gn:dem":3,
    "gn:feature_class":"P",
    "gn:feature_code":"PPL",
    "gn:name":"Ph\u01b0\u1edbc L\u1ee3i",
    "gn:population":0,
    "gn:timezone":"Asia/Ho_Chi_Minh",
    "iso:country":"VN",
    "name:vie_x_preferred":[
        "Ph\u01b0\u1edbc L\u1ee3i"
    ],
    "wof:name":"Phuoc Loi",
    "wof:placetype":"locality"
},
  "geometry": {"coordinates":[105.98362,10.18238],"type":"Point"}
}