{
  "type": "Feature",
  "properties": {
    "gn:admin1_code":"74.0",
    "gn:asciiname":"Nghia Huong",
    "gn:country_code":"VN",
    "gn:dem":5,
    "gn:feature_class":"P",
    "gn:feature_code":"PPL",
    "gn:name":"Ngh\u0129a H\u01b0\u01a1ng",
    "gn:population":0,
    "gn:timezone":"Asia/Ho_Chi_Minh",
    "iso:country":"VN",
    "name:vie_x_preferred":[
        "Ngh\u0129a H\u01b0\u01a1ng"
    ],
    "wof:name":"Nghia Huong",
    "wof:placetype":"locality"
},
  "geometry": {"coordinates":[106.26021,21.03727],"type":"Point"}
}