{
  "type": "Feature",
  "properties": {
    "gn:admin1_code":"71.0",
    "gn:asciiname":"Xom Truoc",
    "gn:country_code":"VN",
    "gn:dem":7,
    "gn:feature_class":"P",
    "gn:feature_code":"PPL",
    "gn:name":"X\u00f3m Tr\u01b0\u1edbc",
    "gn:population":0,
    "gn:timezone":"Asia/Ho_Chi_Minh",
    "iso:country":"VN",
    "name:vie_x_preferred":[
        "X\u00f3m Tr\u01b0\u1edbc"
    ],
    "wof:name":"Xom Truoc",
    "wof:placetype":"locality"
},
  "geometry": {"coordinates":[106.21101000000002,21.25642],"type":"Point"}
}