{
  "type": "Feature",
  "properties": {
    "gn:admin1_code":"90.0",
    "gn:asciiname":"Y Ti",
    "gn:country_code":"VN",
    "gn:dem":938,
    "gn:feature_class":"P",
    "gn:feature_code":"PPL",
    "gn:name":"\u00dd T\u00ed",
    "gn:population":0,
    "gn:timezone":"Asia/Ho_Chi_Minh",
    "iso:country":"VN",
    "wof:name":"Y Ti",
    "wof:placetype":"locality"
},
  "geometry": {"coordinates":[103.58333,22.66667],"type":"Point"}
}