{
  "type": "Feature",
  "properties": {
    "gn:admin1_code":"32.0",
    "gn:asciiname":"Huoi My",
    "gn:country_code":"VN",
    "gn:dem":794,
    "gn:feature_class":"P",
    "gn:feature_code":"PPL",
    "gn:name":"Hu\u1ed5i My",
    "gn:population":0,
    "gn:timezone":"Asia/Ho_Chi_Minh",
    "iso:country":"VN",
    "name:vie_x_preferred":[
        "Hu\u1ed5i My"
    ],
    "wof:name":"Huoi My",
    "wof:placetype":"locality"
},
  "geometry": {"coordinates":[103.96871,21.23022000000001],"type":"Point"}
}