{
  "type": "Feature",
  "properties": {
    "gn:admin1_code":"32.0",
    "gn:asciiname":"Ban Ham",
    "gn:country_code":"VN",
    "gn:dem":801,
    "gn:feature_class":"P",
    "gn:feature_code":"PPL",
    "gn:name":"B\u1ea3n H\u1ea1m",
    "gn:population":0,
    "gn:timezone":"Asia/Ho_Chi_Minh",
    "iso:country":"VN",
    "name:und_x_variant":[
        "B\u1ea3n H\u00e0m"
    ],
    "name:vie_x_preferred":[
        "B\u1ea3n H\u1ea1m"
    ],
    "wof:name":"Ban Ham",
    "wof:placetype":"locality"
},
  "geometry": {"coordinates":[103.89772000000001,21.22438],"type":"Point"}
}