{
  "type": "Feature",
  "properties": {
    "gn:admin1_code":"83.0",
    "gn:asciiname":"Van Coc",
    "gn:country_code":"VN",
    "gn:dem":41,
    "gn:feature_class":"P",
    "gn:feature_code":"PPL",
    "gn:name":"V\u00e2n C\u1ed1c",
    "gn:population":0,
    "gn:timezone":"Asia/Ho_Chi_Minh",
    "iso:country":"VN",
    "name:vie_x_preferred":[
        "V\u00e2n C\u1ed1c"
    ],
    "wof:name":"Van Coc",
    "wof:placetype":"locality"
},
  "geometry": {"coordinates":[105.21979,21.58129],"type":"Point"}
}