{
  "type": "Feature",
  "properties": {
    "gn:admin1_code":"88.0",
    "gn:asciiname":"Khoi Hai",
    "gn:country_code":"VN",
    "gn:dem":513,
    "gn:feature_class":"P",
    "gn:feature_code":"PPL",
    "gn:name":"Kh\u1ed1i Hai",
    "gn:population":0,
    "gn:timezone":"Asia/Ho_Chi_Minh",
    "iso:country":"VN",
    "name:vie_x_preferred":[
        "Kh\u1ed1i Hai"
    ],
    "name:vie_x_variant":[
        "Kh\u1ed1i 2"
    ],
    "wof:name":"Khoi Hai",
    "wof:placetype":"locality"
},
  "geometry": {"coordinates":[108.05800000000001,12.69519],"type":"Point"}
}