{
  "type": "Feature",
  "properties": {
    "gn:admin1_code":"53.0",
    "gn:asciiname":"Som Jo",
    "gn:country_code":"VN",
    "gn:dem":510,
    "gn:feature_class":"P",
    "gn:feature_code":"PPL",
    "gn:name":"Som J\u00f4",
    "gn:population":0,
    "gn:timezone":"Asia/Ho_Chi_Minh",
    "iso:country":"VN",
    "wof:name":"Som Jo",
    "wof:placetype":"locality"
},
  "geometry": {"coordinates":[105.11667,20.71667],"type":"Point"}
}