{
  "type": "Feature",
  "properties": {
    "gn:admin1_code":"3.0",
    "gn:asciiname":"Ap Thanh Hoa",
    "gn:country_code":"VN",
    "gn:dem":1,
    "gn:feature_class":"P",
    "gn:feature_code":"PPL",
    "gn:name":"\u1ea4p Th\u1ea1nh H\u00f2a",
    "gn:population":0,
    "gn:timezone":"Asia/Ho_Chi_Minh",
    "iso:country":"VN",
    "name:und_x_variant":[
        "Th\u1ea1nh H\u00f2a",
        "\u1ea4p Th\u1ea1nh H\u00f2a"
    ],
    "wof:name":"Ap Thanh Hoa",
    "wof:placetype":"locality"
},
  "geometry": {"coordinates":[106.51472,9.95528],"type":"Point"}
}