{
  "type": "Feature",
  "properties": {
    "gn:admin1_code":"89.0",
    "gn:asciiname":"Ta Tu Hai",
    "gn:country_code":"VN",
    "gn:dem":240,
    "gn:feature_class":"P",
    "gn:feature_code":"PPL",
    "gn:name":"T\u1ea3 T\u1eed Hai",
    "gn:population":0,
    "gn:timezone":"Asia/Ho_Chi_Minh",
    "iso:country":"VN",
    "name:vie_x_preferred":[
        "T\u1ea3 T\u1eed Hai"
    ],
    "name:vie_x_variant":[
        "T\u1ea3 T\u1eed 2"
    ],
    "wof:name":"Ta Tu Hai",
    "wof:placetype":"locality"
},
  "geometry": {"coordinates":[103.37203,22.30199],"type":"Point"}
}