{
  "type": "Feature",
  "properties": {
    "gn:admin1_code":"3.0",
    "gn:asciiname":"Xom Giong Rung",
    "gn:cc2":"VN",
    "gn:country_code":"VN",
    "gn:dem":5,
    "gn:feature_class":"P",
    "gn:feature_code":"PPL",
    "gn:name":"X\u00f3m Gi\u1ed3ng R\u1eebng",
    "gn:population":0,
    "gn:timezone":"Asia/Ho_Chi_Minh",
    "iso:country":"VN",
    "name:und_x_variant":[
        "Giong Rung",
        "X\u00f3m Gi\u1ed3ng R\u1eebng"
    ],
    "wof:name":"Xom Giong Rung",
    "wof:placetype":"locality"
},
  "geometry": {"coordinates":[106.63333,10.18333],"type":"Point"}
}