{
  "type": "Feature",
  "properties": {
    "gn:admin1_code":"89.0",
    "gn:asciiname":"Ban Pa Sap",
    "gn:country_code":"VN",
    "gn:dem":517,
    "gn:feature_class":"P",
    "gn:feature_code":"PPL",
    "gn:name":"B\u1ea3n P\u00e1 S\u1eadp",
    "gn:population":0,
    "gn:timezone":"Asia/Ho_Chi_Minh",
    "iso:country":"VN",
    "name:vie_x_preferred":[
        "B\u1ea3n P\u00e1 S\u1eadp"
    ],
    "wof:name":"Ban Pa Sap",
    "wof:placetype":"locality"
},
  "geometry": {"coordinates":[103.11189,22.27592000000001],"type":"Point"}
}