{
  "type": "Feature",
  "properties": {
    "gn:admin1_code":"88.0",
    "gn:asciiname":"Buon Ea Huk",
    "gn:country_code":"VN",
    "gn:dem":555,
    "gn:feature_class":"P",
    "gn:feature_code":"PPL",
    "gn:name":"Bu\u00f4n Ea Huk",
    "gn:population":0,
    "gn:timezone":"Asia/Ho_Chi_Minh",
    "iso:country":"VN",
    "name:und_x_variant":[
        "Buon Ne Molh",
        "Bu\u00f4n Ea Huk"
    ],
    "wof:name":"Buon Ea Huk",
    "wof:placetype":"locality"
},
  "geometry": {"coordinates":[108.13333,12.86667],"type":"Point"}
}