{
  "type": "Feature",
  "properties": {
    "gn:admin1_code":"32.0",
    "gn:asciiname":"Ban Bo Mot",
    "gn:country_code":"VN",
    "gn:dem":160,
    "gn:feature_class":"P",
    "gn:feature_code":"PPL",
    "gn:name":"B\u1ea3n B\u00f3 M\u1ed9t",
    "gn:population":0,
    "gn:timezone":"Asia/Ho_Chi_Minh",
    "iso:country":"VN",
    "name:vie_x_preferred":[
        "B\u1ea3n B\u00f3 M\u1ed9t"
    ],
    "name:vie_x_variant":[
        "B\u1ea3n B\u00f3 1"
    ],
    "wof:name":"Ban Bo Mot",
    "wof:placetype":"locality"
},
  "geometry": {"coordinates":[104.63018,21.23684],"type":"Point"}
}