{
  "type": "Feature",
  "properties": {
    "gn:admin1_code":"90.0",
    "gn:asciiname":"Bo Lay",
    "gn:country_code":"VN",
    "gn:dem":376,
    "gn:feature_class":"P",
    "gn:feature_code":"PPL",
    "gn:name":"B\u00f2 L\u00e2y",
    "gn:population":0,
    "gn:timezone":"Asia/Ho_Chi_Minh",
    "iso:country":"VN",
    "name:und_x_variant":[
        "Bo Loy",
        "B\u00f2 L\u00e2y"
    ],
    "wof:name":"Bo Lay",
    "wof:placetype":"locality"
},
  "geometry": {"coordinates":[103.98333,22.38333],"type":"Point"}
}