{
  "type": "Feature",
  "properties": {
    "gn:admin1_code":"71.0",
    "gn:asciiname":"Tan Thanh",
    "gn:country_code":"VN",
    "gn:dem":73,
    "gn:feature_class":"P",
    "gn:feature_code":"PPL",
    "gn:name":"T\u00e2n Th\u00e0nh",
    "gn:population":0,
    "gn:timezone":"Asia/Ho_Chi_Minh",
    "iso:country":"VN",
    "name:nld_x_preferred":[
        "Tan Thanh"
    ],
    "name:vie_x_preferred":[
        "T\u00e2n Th\u00e0nh"
    ],
    "wof:name":"Tan Thanh",
    "wof:placetype":"locality"
},
  "geometry": {"coordinates":[106.72987000000001,21.42968],"type":"Point"}
}