{
  "type": "Feature",
  "properties": {
    "gn:admin1_code":"34.0",
    "gn:asciiname":"Hoi Xuan",
    "gn:cc2":"VN",
    "gn:country_code":"VN",
    "gn:dem":68,
    "gn:feature_class":"P",
    "gn:feature_code":"PPL",
    "gn:name":"H\u1ed3i Xu\u00e2n",
    "gn:population":0,
    "gn:timezone":"Asia/Ho_Chi_Minh",
    "iso:country":"VN",
    "name:und_x_variant":[
        "Hoai Xuan",
        "H\u1ed3i Xu\u00e2n"
    ],
    "wof:name":"Hoi Xuan",
    "wof:placetype":"locality"
},
  "geometry": {"coordinates":[105.11667,20.36667000000001],"type":"Point"}
}