{
  "type": "Feature",
  "properties": {
    "gn:admin1_code":"69.0",
    "gn:asciiname":"My Trung Mot",
    "gn:country_code":"VN",
    "gn:dem":4,
    "gn:feature_class":"P",
    "gn:feature_code":"PPL",
    "gn:name":"M\u1ef9 Trung M\u1ed9t",
    "gn:population":0,
    "gn:timezone":"Asia/Ho_Chi_Minh",
    "iso:country":"VN",
    "name:vie_x_preferred":[
        "M\u1ef9 Trung M\u1ed9t"
    ],
    "name:vie_x_variant":[
        "M\u1ef9 Trung 1"
    ],
    "wof:name":"My Trung Mot",
    "wof:placetype":"locality"
},
  "geometry": {"coordinates":[105.98577,10.07158],"type":"Point"}
}