{
  "type": "Feature",
  "properties": {
    "gn:admin1_code":"71.0",
    "gn:asciiname":"Nam Xuong",
    "gn:country_code":"VN",
    "gn:dem":3,
    "gn:feature_class":"P",
    "gn:feature_code":"PPL",
    "gn:name":"Nam X\u01b0\u01a1ng",
    "gn:population":0,
    "gn:timezone":"Asia/Ho_Chi_Minh",
    "iso:country":"VN",
    "wof:name":"Nam Xuong",
    "wof:placetype":"locality"
},
  "geometry": {"coordinates":[106.18333,21.28333],"type":"Point"}
}