{
  "type": "Feature",
  "properties": {
    "gn:admin1_code":"30.0",
    "gn:asciiname":"Luu Khe",
    "gn:cc2":"VN",
    "gn:country_code":"VN",
    "gn:dem":2,
    "gn:feature_class":"P",
    "gn:feature_code":"PPL",
    "gn:name":"L\u01b0u Kh\u00ea",
    "gn:population":0,
    "gn:timezone":"Asia/Ho_Chi_Minh",
    "iso:country":"VN",
    "name:und_x_variant":[
        "Lunkhe",
        "L\u01b0u Kh\u00ea"
    ],
    "wof:name":"Luu Khe",
    "wof:placetype":"locality"
},
  "geometry": {"coordinates":[106.83333,20.88333],"type":"Point"}
}