{
  "type": "Feature",
  "properties": {
    "gn:admin1_code":"32.0",
    "gn:asciiname":"Ban Bom Khoang",
    "gn:country_code":"VN",
    "gn:dem":851,
    "gn:feature_class":"P",
    "gn:feature_code":"PPL",
    "gn:name":"B\u1ea3n B\u00f4m Khoang",
    "gn:population":0,
    "gn:timezone":"Asia/Ho_Chi_Minh",
    "iso:country":"VN",
    "name:vie_x_preferred":[
        "B\u1ea3n B\u00f4m Khoang"
    ],
    "wof:name":"Ban Bom Khoang",
    "wof:placetype":"locality"
},
  "geometry": {"coordinates":[104.15063000000001,21.04764],"type":"Point"}
}