{
  "type": "Feature",
  "properties": {
    "gn:admin1_code":"35.0",
    "gn:asciiname":"Hung Ha",
    "gn:country_code":"VN",
    "gn:dem":4,
    "gn:feature_class":"P",
    "gn:feature_code":"PPLA2",
    "gn:name":"H\u01b0ng H\u00e0",
    "gn:population":0,
    "gn:timezone":"Asia/Ho_Chi_Minh",
    "iso:country":"VN",
    "name:vie_x_preferred":[
        "H\u01b0ng H\u00e0"
    ],
    "wof:name":"Hung Ha",
    "wof:placetype":"locality"
},
  "geometry": {"coordinates":[106.22445,20.5904],"type":"Point"}
}