{
  "type": "Feature",
  "properties": {
    "gn:admin1_code":"54.0",
    "gn:asciiname":"Ap Van Khe",
    "gn:country_code":"VN",
    "gn:dem":8,
    "gn:feature_class":"P",
    "gn:feature_code":"PPL",
    "gn:name":"\u1ea4p V\u1ea1n Kh\u00ea",
    "gn:population":0,
    "gn:timezone":"Asia/Ho_Chi_Minh",
    "iso:country":"VN",
    "wof:name":"Ap Van Khe",
    "wof:placetype":"locality"
},
  "geometry": {"coordinates":[109.11667,12.43333],"type":"Point"}
}