{
  "type": "Feature",
  "properties": {
    "gn:admin1_code":"89.0",
    "gn:asciiname":"Ban Le Rang",
    "gn:country_code":"VN",
    "gn:dem":1362,
    "gn:feature_class":"P",
    "gn:feature_code":"PPL",
    "gn:name":"B\u1ea3n L\u00e8 R\u1eb1ng",
    "gn:population":0,
    "gn:timezone":"Asia/Ho_Chi_Minh",
    "iso:country":"VN",
    "wof:name":"Ban Le Rang",
    "wof:placetype":"locality"
},
  "geometry": {"coordinates":[102.51667,22.66667],"type":"Point"}
}