{
  "type": "Feature",
  "properties": {
    "gn:admin1_code":"58.0",
    "gn:asciiname":"Trung Son",
    "gn:country_code":"VN",
    "gn:dem":30,
    "gn:feature_class":"P",
    "gn:feature_code":"PPL",
    "gn:name":"Trung S\u01a1n",
    "gn:population":0,
    "gn:timezone":"Asia/Ho_Chi_Minh",
    "iso:country":"VN",
    "name:vie_x_preferred":[
        "Trung S\u01a1n"
    ],
    "wof:name":"Trung Son",
    "wof:placetype":"locality"
},
  "geometry": {"coordinates":[105.11624999999999,19.03142],"type":"Point"}
}