{
  "type": "Feature",
  "properties": {
    "gn:admin1_code":"65.0",
    "gn:asciiname":"Cai Trau",
    "gn:country_code":"VN",
    "gn:dem":4,
    "gn:feature_class":"P",
    "gn:feature_code":"PPL",
    "gn:name":"C\u00e1i Tr\u1ea7u",
    "gn:population":0,
    "gn:timezone":"Asia/Ho_Chi_Minh",
    "iso:country":"VN",
    "wof:name":"Cai Trau",
    "wof:placetype":"locality"
},
  "geometry": {"coordinates":[105.68832999999999,9.52944],"type":"Point"}
}