{
  "type": "Feature",
  "properties": {
    "gn:admin1_code":"53.0",
    "gn:asciiname":"Tuong Doi",
    "gn:country_code":"VN",
    "gn:dem":539,
    "gn:feature_class":"P",
    "gn:feature_code":"PPL",
    "gn:name":"Tu\u1ed5ng \u0110\u1ed3i",
    "gn:population":0,
    "gn:timezone":"Asia/Ho_Chi_Minh",
    "iso:country":"VN",
    "name:vie_x_preferred":[
        "Tu\u1ed5ng \u0110\u1ed3i"
    ],
    "wof:name":"Tuong Doi",
    "wof:placetype":"locality"
},
  "geometry": {"coordinates":[104.90633,21.00819],"type":"Point"}
}