{
  "type": "Feature",
  "properties": {
    "gn:admin1_code":"23.0",
    "gn:asciiname":"Pampe Da R'ging",
    "gn:country_code":"VN",
    "gn:dem":532,
    "gn:feature_class":"P",
    "gn:feature_code":"PPL",
    "gn:name":"Pamp\u00e9 Da R\u2019ging",
    "gn:population":0,
    "gn:timezone":"Asia/Ho_Chi_Minh",
    "iso:country":"VN",
    "name:und_x_variant":[
        "Pang Phey Dak R\u2019Guinn",
        "Pamp\u00e9 Da R\u2019ging"
    ],
    "wof:name":"Pampe Da R'ging",
    "wof:placetype":"locality"
},
  "geometry": {"coordinates":[108.09999999999999,12.13333],"type":"Point"}
}