{
  "type": "Feature",
  "properties": {
    "gn:admin1_code":"20.0",
    "gn:asciiname":"Phu Xuan Hoi",
    "gn:cc2":"VN",
    "gn:country_code":"VN",
    "gn:dem":3,
    "gn:feature_class":"P",
    "gn:feature_code":"PPL",
    "gn:name":"Ph\u00fa Xu\u00e2n H\u1ed9i",
    "gn:population":0,
    "gn:timezone":"Asia/Ho_Chi_Minh",
    "iso:country":"VN",
    "name:und_x_variant":[
        "X\u00f3m Phu Xuan",
        "Ph\u00fa Xu\u00e2n H\u1ed9i"
    ],
    "wof:name":"Phu Xuan Hoi",
    "wof:placetype":"locality"
},
  "geometry": {"coordinates":[106.72611000000001,10.70583],"type":"Point"}
}