{
  "type": "Feature",
  "properties": {
    "gn:admin1_code":"90.0",
    "gn:asciiname":"Ban Sang Chai",
    "gn:country_code":"VN",
    "gn:dem":1343,
    "gn:feature_class":"P",
    "gn:feature_code":"PPL",
    "gn:name":"B\u1ea3n S\u1ea3ng Ch\u1ea3i",
    "gn:population":0,
    "gn:timezone":"Asia/Ho_Chi_Minh",
    "iso:country":"VN",
    "name:vie_x_preferred":[
        "B\u1ea3n S\u1ea3ng Ch\u1ea3i"
    ],
    "wof:name":"Ban Sang Chai",
    "wof:placetype":"locality"
},
  "geometry": {"coordinates":[104.30186,22.67936],"type":"Point"}
}