{
  "type": "Feature",
  "properties": {
    "gn:admin1_code":"46.0",
    "gn:asciiname":"An Thien",
    "gn:country_code":"VN",
    "gn:dem":27,
    "gn:feature_class":"P",
    "gn:feature_code":"PPL",
    "gn:name":"An Thi\u00ean",
    "gn:population":0,
    "gn:timezone":"Asia/Ho_Chi_Minh",
    "iso:country":"VN",
    "name:und_x_variant":[
        "\u00c2n Thi\u1ec7n"
    ],
    "name:vie_x_preferred":[
        "An Thi\u00ean"
    ],
    "wof:name":"An Thien",
    "wof:placetype":"locality"
},
  "geometry": {"coordinates":[109.00538,14.34978],"type":"Point"}
}