{
  "type": "Feature",
  "properties": {
    "gn:admin1_code":"92.0",
    "gn:asciiname":"Ban Som",
    "gn:country_code":"VN",
    "gn:dem":636,
    "gn:feature_class":"P",
    "gn:feature_code":"PPL",
    "gn:name":"B\u1ea3n S\u00f4m",
    "gn:population":0,
    "gn:timezone":"Asia/Ho_Chi_Minh",
    "iso:country":"VN",
    "name:vie_x_preferred":[
        "B\u1ea3n S\u00f4m"
    ],
    "wof:name":"Ban Som",
    "wof:placetype":"locality"
},
  "geometry": {"coordinates":[103.17628000000001,21.56097],"type":"Point"}
}