{
  "type": "Feature",
  "properties": {
    "gn:admin1_code":"70.0",
    "gn:asciiname":"Ban Thai",
    "gn:country_code":"VN",
    "gn:dem":824,
    "gn:feature_class":"P",
    "gn:feature_code":"PPL",
    "gn:name":"B\u1ea3n Th\u00e1i",
    "gn:population":0,
    "gn:timezone":"Asia/Ho_Chi_Minh",
    "iso:country":"VN",
    "name:vie_x_preferred":[
        "B\u1ea3n Th\u00e1i"
    ],
    "wof:name":"Ban Thai",
    "wof:placetype":"locality"
},
  "geometry": {"coordinates":[104.01027999999999,21.86862],"type":"Point"}
}