{
  "type": "Feature",
  "properties": {
    "gn:admin1_code":"92.0",
    "gn:asciiname":"Nam Na",
    "gn:country_code":"VN",
    "gn:dem":587,
    "gn:feature_class":"P",
    "gn:feature_code":"PPL",
    "gn:name":"N\u1eadm N\u00e3",
    "gn:population":0,
    "gn:timezone":"Asia/Ho_Chi_Minh",
    "iso:country":"VN",
    "name:vie_x_preferred":[
        "N\u1eadm N\u00e3"
    ],
    "wof:name":"Nam Na",
    "wof:placetype":"locality"
},
  "geometry": {"coordinates":[103.28506,21.08347],"type":"Point"}
}