{
  "type": "Feature",
  "properties": {
    "gn:admin1_code":"32.0",
    "gn:asciiname":"Ban Lom",
    "gn:country_code":"VN",
    "gn:dem":273,
    "gn:feature_class":"P",
    "gn:feature_code":"PPL",
    "gn:name":"B\u1ea3n L\u1ed1m",
    "gn:population":0,
    "gn:timezone":"Asia/Ho_Chi_Minh",
    "iso:country":"VN",
    "name:und_x_variant":[
        "B\u1ea3n L\u00f4m"
    ],
    "name:vie_x_preferred":[
        "B\u1ea3n L\u1ed1m"
    ],
    "wof:name":"Ban Lom",
    "wof:placetype":"locality"
},
  "geometry": {"coordinates":[104.70958,21.13332],"type":"Point"}
}