{
  "type": "Feature",
  "properties": {
    "gn:admin1_code":"72.0",
    "gn:asciiname":"Na Kha",
    "gn:country_code":"VN",
    "gn:dem":207,
    "gn:feature_class":"P",
    "gn:feature_code":"PPL",
    "gn:name":"N\u00e0 Kha",
    "gn:population":0,
    "gn:timezone":"Asia/Ho_Chi_Minh",
    "iso:country":"VN",
    "name:vie_x_preferred":[
        "N\u00e0 Kha"
    ],
    "wof:name":"Na Kha",
    "wof:placetype":"locality"
},
  "geometry": {"coordinates":[105.77302,22.12117000000001],"type":"Point"}
}