{
  "type": "Feature",
  "properties": {
    "gn:admin1_code":"32.0",
    "gn:asciiname":"Ban Lung Tang",
    "gn:country_code":"VN",
    "gn:dem":766,
    "gn:feature_class":"P",
    "gn:feature_code":"PPL",
    "gn:name":"B\u1ea3n Lung Tang",
    "gn:population":0,
    "gn:timezone":"Asia/Ho_Chi_Minh",
    "iso:country":"VN",
    "name:vie_x_preferred":[
        "B\u1ea3n Lung Tang"
    ],
    "wof:name":"Ban Lung Tang",
    "wof:placetype":"locality"
},
  "geometry": {"coordinates":[104.51163,21.1264],"type":"Point"}
}