{
  "type": "Feature",
  "properties": {
    "gn:admin1_code":"88.0",
    "gn:asciiname":"Ban Dang Tchieng Kao",
    "gn:country_code":"VN",
    "gn:dem":822,
    "gn:feature_class":"P",
    "gn:feature_code":"PPL",
    "gn:name":"Ban Dang Tchieng Kao",
    "gn:population":0,
    "gn:timezone":"Asia/Ho_Chi_Minh",
    "iso:country":"VN",
    "wof:name":"Ban Dang Tchieng Kao",
    "wof:placetype":"locality"
},
  "geometry": {"coordinates":[108.36667,12.28333],"type":"Point"}
}