{
  "type": "Feature",
  "properties": {
    "gn:admin1_code":"58.0",
    "gn:asciiname":"Na Ken",
    "gn:country_code":"VN",
    "gn:dem":179,
    "gn:feature_class":"P",
    "gn:feature_code":"PPL",
    "gn:name":"N\u00e0 K\u00e9n",
    "gn:population":0,
    "gn:timezone":"Asia/Ho_Chi_Minh",
    "iso:country":"VN",
    "name:vie_x_preferred":[
        "N\u00e0 K\u00e9n"
    ],
    "wof:name":"Na Ken",
    "wof:placetype":"locality"
},
  "geometry": {"coordinates":[105.08144,19.53621],"type":"Point"}
}