{
  "type": "Feature",
  "properties": {
    "gn:admin1_code":"49.0",
    "gn:asciiname":"Plei Tong Hotte",
    "gn:country_code":"VN",
    "gn:dem":385,
    "gn:feature_class":"P",
    "gn:feature_code":"PPL",
    "gn:name":"Plei Tong H\u00f4tte",
    "gn:population":0,
    "gn:timezone":"Asia/Ho_Chi_Minh",
    "iso:country":"VN",
    "wof:name":"Plei Tong Hotte",
    "wof:placetype":"locality"
},
  "geometry": {"coordinates":[108.09999999999999,13.58333],"type":"Point"}
}