{
  "type": "Feature",
  "properties": {
    "gn:admin1_code":"58.0",
    "gn:asciiname":"Na Sanh",
    "gn:country_code":"VN",
    "gn:dem":202,
    "gn:feature_class":"P",
    "gn:feature_code":"PPL",
    "gn:name":"Na S\u00e0nh",
    "gn:population":0,
    "gn:timezone":"Asia/Ho_Chi_Minh",
    "iso:country":"VN",
    "name:vie_x_preferred":[
        "Na S\u00e0nh"
    ],
    "wof:name":"Na Sanh",
    "wof:placetype":"locality"
},
  "geometry": {"coordinates":[105.01638,19.73558],"type":"Point"}
}