{
  "type": "Feature",
  "properties": {
    "gn:admin1_code":"63.0",
    "gn:asciiname":"Lang Bao",
    "gn:country_code":"VN",
    "gn:dem":101,
    "gn:feature_class":"P",
    "gn:feature_code":"PPL",
    "gn:name":"Lang Bao",
    "gn:population":0,
    "gn:timezone":"Asia/Ho_Chi_Minh",
    "iso:country":"VN",
    "wof:name":"Lang Bao",
    "wof:placetype":"locality"
},
  "geometry": {"coordinates":[108.61667,15.11667],"type":"Point"}
}