{
  "type": "Feature",
  "properties": {
    "gn:admin1_code":"49.0",
    "gn:asciiname":"Phu Hoa",
    "gn:country_code":"VN",
    "gn:dem":751,
    "gn:feature_class":"P",
    "gn:feature_code":"PPLA2",
    "gn:name":"Ph\u00fa H\u00f2a",
    "gn:population":0,
    "gn:timezone":"Asia/Ho_Chi_Minh",
    "iso:country":"VN",
    "name:vie_x_preferred":[
        "Ph\u00fa H\u00f2a"
    ],
    "wof:name":"Phu Hoa",
    "wof:placetype":"locality"
},
  "geometry": {"coordinates":[107.96896,14.10005],"type":"Point"}
}