{
  "type": "Feature",
  "properties": {
    "gn:admin1_code":"71.0",
    "gn:asciiname":"Thang Dai Ha",
    "gn:country_code":"VN",
    "gn:dem":4,
    "gn:feature_class":"P",
    "gn:feature_code":"PPL",
    "gn:name":"Th\u1eafng \u0110\u1ea1i H\u1ea1",
    "gn:population":0,
    "gn:timezone":"Asia/Ho_Chi_Minh",
    "iso:country":"VN",
    "name:vie_x_preferred":[
        "Th\u1eafng \u0110\u1ea1i H\u1ea1"
    ],
    "wof:name":"Thang Dai Ha",
    "wof:placetype":"locality"
},
  "geometry": {"coordinates":[106.21259999999999,21.15818],"type":"Point"}
}