{
  "type": "Feature",
  "properties": {
    "gn:admin1_code":"58.0",
    "gn:asciiname":"Dong Kha",
    "gn:country_code":"VN",
    "gn:dem":58,
    "gn:feature_class":"P",
    "gn:feature_code":"PPL",
    "gn:name":"\u0110\u1ed3ng Kha",
    "gn:population":0,
    "gn:timezone":"Asia/Ho_Chi_Minh",
    "iso:country":"VN",
    "name:vie_x_preferred":[
        "\u0110\u1ed3ng Kha"
    ],
    "wof:name":"Dong Kha",
    "wof:placetype":"locality"
},
  "geometry": {"coordinates":[105.15772,19.12279],"type":"Point"}
}