{
  "type": "Feature",
  "properties": {
    "gn:admin1_code":"67.0",
    "gn:asciiname":"Lo Ngo",
    "gn:country_code":"VN",
    "gn:dem":8,
    "gn:feature_class":"P",
    "gn:feature_code":"PPL",
    "gn:name":"L\u00f2 Ng\u1edd",
    "gn:population":0,
    "gn:timezone":"Asia/Ho_Chi_Minh",
    "iso:country":"VN",
    "name:und_x_variant":[
        "B\u00e0 Ng\u00f4 Nh\u1ecf",
        "Gi\u1ed3ng Lo Ng\u00f3 Nh\u1ecf",
        "Gi\u1ed3ng B\u00e0 Ng\u00f4 Nh\u1ecf"
    ],
    "name:vie_x_preferred":[
        "L\u00f2 Ng\u1edd"
    ],
    "wof:name":"Lo Ngo",
    "wof:placetype":"locality"
},
  "geometry": {"coordinates":[106.21943,9.87369],"type":"Point"}
}