{
  "type": "Feature",
  "properties": {
    "gn:admin1_code":"69.0",
    "gn:asciiname":"Dong Thanh A",
    "gn:country_code":"VN",
    "gn:dem":-2,
    "gn:feature_class":"P",
    "gn:feature_code":"PPL",
    "gn:name":"\u0110\u00f4ng Th\u1ea1nh A",
    "gn:population":0,
    "gn:timezone":"Asia/Ho_Chi_Minh",
    "iso:country":"VN",
    "name:vie_x_preferred":[
        "\u0110\u00f4ng Th\u1ea1nh A"
    ],
    "wof:name":"Dong Thanh A",
    "wof:placetype":"locality"
},
  "geometry": {"coordinates":[105.83920999999999,10.07159],"type":"Point"}
}