{
  "type": "Feature",
  "properties": {
    "gn:admin1_code":"39.0",
    "gn:asciiname":"Ban Coc Muong",
    "gn:country_code":"VN",
    "gn:dem":176,
    "gn:feature_class":"P",
    "gn:feature_code":"PPL",
    "gn:name":"B\u1ea3n C\u1ed1c Mu\u1ed1ng",
    "gn:population":0,
    "gn:timezone":"Asia/Ho_Chi_Minh",
    "iso:country":"VN",
    "wof:name":"Ban Coc Muong",
    "wof:placetype":"locality"
},
  "geometry": {"coordinates":[106.60195,22.1752],"type":"Point"}
}