{
  "type": "Feature",
  "properties": {
    "gn:admin1_code":"78.0",
    "gn:asciiname":"Hoa Khue Dong",
    "gn:country_code":"VN",
    "gn:dem":7,
    "gn:feature_class":"P",
    "gn:feature_code":"PPL",
    "gn:name":"H\u00f2a Khu\u00ea \u0110\u00f4ng",
    "gn:population":0,
    "gn:timezone":"Asia/Ho_Chi_Minh",
    "iso:country":"VN",
    "name:und_x_variant":[
        "H\u00f2a Khu\u00ea"
    ],
    "name:vie_x_preferred":[
        "H\u00f2a Khu\u00ea \u0110\u00f4ng"
    ],
    "wof:name":"Hoa Khue Dong",
    "wof:placetype":"locality"
},
  "geometry": {"coordinates":[108.24005,16.0393],"type":"Point"}
}