{
  "type": "Feature",
  "properties": {
    "gn:admin1_code":"73.0",
    "gn:asciiname":"Xom Dao",
    "gn:country_code":"VN",
    "gn:dem":3,
    "gn:feature_class":"P",
    "gn:feature_code":"PPL",
    "gn:name":"X\u00f3m \u0110\u1ea1o",
    "gn:population":0,
    "gn:timezone":"Asia/Ho_Chi_Minh",
    "iso:country":"VN",
    "name:und_x_variant":[
        "\u1ea4p X\u00f3m \u0110\u1ea1o"
    ],
    "name:vie_x_preferred":[
        "X\u00f3m \u0110\u1ea1o"
    ],
    "wof:name":"Xom Dao",
    "wof:placetype":"locality"
},
  "geometry": {"coordinates":[105.59975,9.25591],"type":"Point"}
}