{
  "type": "Feature",
  "properties": {
    "gn:admin1_code":"32.0",
    "gn:asciiname":"Ta Niet",
    "gn:country_code":"VN",
    "gn:dem":515,
    "gn:feature_class":"P",
    "gn:feature_code":"PPL",
    "gn:name":"T\u00e0 Ni\u1ebft",
    "gn:population":0,
    "gn:timezone":"Asia/Ho_Chi_Minh",
    "iso:country":"VN",
    "name:vie_x_preferred":[
        "T\u00e0 Ni\u1ebft"
    ],
    "wof:name":"Ta Niet",
    "wof:placetype":"locality"
},
  "geometry": {"coordinates":[104.52184,20.89759],"type":"Point"}
}