{
  "type": "Feature",
  "properties": {
    "gn:admin1_code":"23.0",
    "gn:asciiname":"Ban Da Chay",
    "gn:country_code":"VN",
    "gn:dem":1456,
    "gn:feature_class":"P",
    "gn:feature_code":"PPL",
    "gn:name":"B\u1ea3n \u0110a Chay",
    "gn:population":0,
    "gn:timezone":"Asia/Ho_Chi_Minh",
    "iso:country":"VN",
    "name:vie_x_preferred":[
        "\u0110\u1ea1 Chay"
    ],
    "name:vie_x_variant":[
        "B\u1ea3n \u0110a Chay"
    ],
    "wof:name":"Ban Da Chay",
    "wof:placetype":"locality"
},
  "geometry": {"coordinates":[108.56292999999999,12.10542],"type":"Point"}
}