{
  "type": "Feature",
  "properties": {
    "gn:admin1_code":"70.0",
    "gn:asciiname":"Khe Mang Mot",
    "gn:country_code":"VN",
    "gn:dem":280,
    "gn:feature_class":"P",
    "gn:feature_code":"PPL",
    "gn:name":"Khe Mang M\u1ed9t",
    "gn:population":0,
    "gn:timezone":"Asia/Ho_Chi_Minh",
    "iso:country":"VN",
    "name:und_x_variant":[
        "Kh\u00ea M\u1ea3ng",
        "Khe Mang 1"
    ],
    "name:vie_x_preferred":[
        "Khe Mang M\u1ed9t"
    ],
    "wof:name":"Khe Mang Mot",
    "wof:placetype":"locality"
},
  "geometry": {"coordinates":[104.4255,21.84849],"type":"Point"}
}