{
  "type": "Feature",
  "properties": {
    "gn:admin1_code":"88.0",
    "gn:asciiname":"Hang Ja",
    "gn:country_code":"VN",
    "gn:dem":428,
    "gn:feature_class":"P",
    "gn:feature_code":"PPL",
    "gn:name":"Hang Ja",
    "gn:population":0,
    "gn:timezone":"Asia/Ho_Chi_Minh",
    "iso:country":"VN",
    "name:vie_x_preferred":[
        "Hang Ja"
    ],
    "wof:name":"Hang Ja",
    "wof:placetype":"locality"
},
  "geometry": {"coordinates":[108.22112,12.4078],"type":"Point"}
}