{
  "type": "Feature",
  "properties": {
    "gn:admin1_code":"70.0",
    "gn:asciiname":"Ban Thiu",
    "gn:country_code":"VN",
    "gn:dem":86,
    "gn:feature_class":"P",
    "gn:feature_code":"PPL",
    "gn:name":"B\u1ea3n Th\u00ecu",
    "gn:population":0,
    "gn:timezone":"Asia/Ho_Chi_Minh",
    "iso:country":"VN",
    "name:vie_x_preferred":[
        "B\u1ea3n Th\u00ecu"
    ],
    "wof:name":"Ban Thiu",
    "wof:placetype":"locality"
},
  "geometry": {"coordinates":[104.75923,21.98639],"type":"Point"}
}