{
  "type": "Feature",
  "properties": {
    "gn:admin1_code":"52.0",
    "gn:asciiname":"Song Linh",
    "gn:country_code":"VN",
    "gn:dem":11,
    "gn:feature_class":"P",
    "gn:feature_code":"PPL",
    "gn:name":"Song Linh",
    "gn:population":0,
    "gn:timezone":"Asia/Ho_Chi_Minh",
    "iso:country":"VN",
    "name:vie_x_preferred":[
        "Song Linh"
    ],
    "wof:name":"Song Linh",
    "wof:placetype":"locality"
},
  "geometry": {"coordinates":[105.673,18.29958],"type":"Point"}
}