{
  "type": "Feature",
  "properties": {
    "gn:admin1_code":"49.0",
    "gn:asciiname":"Kon Jot",
    "gn:country_code":"VN",
    "gn:dem":738,
    "gn:feature_class":"P",
    "gn:feature_code":"PPL",
    "gn:name":"Kon J\u00f4t",
    "gn:population":0,
    "gn:timezone":"Asia/Ho_Chi_Minh",
    "iso:country":"VN",
    "name:und_x_variant":[
        "Kon Djot",
        "Kon J\u00f4t"
    ],
    "wof:name":"Kon Jot",
    "wof:placetype":"locality"
},
  "geometry": {"coordinates":[108.26842000000001,14.29674],"type":"Point"}
}