{
  "type": "Feature",
  "properties": {
    "gn:admin1_code":"34.0",
    "gn:asciiname":"Van Lung",
    "gn:cc2":"VN",
    "gn:country_code":"VN",
    "gn:dem":17,
    "gn:feature_class":"P",
    "gn:feature_code":"PPL",
    "gn:name":"V\u00e2n Lung",
    "gn:population":0,
    "gn:timezone":"Asia/Ho_Chi_Minh",
    "iso:country":"VN",
    "name:und_x_variant":[
        "Van Son",
        "V\u00e2n Lung"
    ],
    "wof:name":"Van Lung",
    "wof:placetype":"locality"
},
  "geometry": {"coordinates":[105.68333,20.08333],"type":"Point"}
}