{
  "type": "Feature",
  "properties": {
    "gn:admin1_code":"68.0",
    "gn:asciiname":"Tan Long",
    "gn:country_code":"VN",
    "gn:dem":35,
    "gn:feature_class":"P",
    "gn:feature_code":"PPL",
    "gn:name":"T\u00e2n Long",
    "gn:population":0,
    "gn:timezone":"Asia/Ho_Chi_Minh",
    "iso:country":"VN",
    "name:vie_x_preferred":[
        "T\u00e2n Long"
    ],
    "wof:name":"Tan Long",
    "wof:placetype":"locality"
},
  "geometry": {"coordinates":[105.16473000000001,21.91065],"type":"Point"}
}