{
  "type": "Feature",
  "properties": {
    "gn:admin1_code":"1.0",
    "gn:asciiname":"Ap My Thuan",
    "gn:country_code":"VN",
    "gn:dem":5,
    "gn:feature_class":"P",
    "gn:feature_code":"PPL",
    "gn:name":"\u1ea4p M\u1ef9 Thu\u1eadn",
    "gn:population":0,
    "gn:timezone":"Asia/Ho_Chi_Minh",
    "iso:country":"VN",
    "wof:name":"Ap My Thuan",
    "wof:placetype":"locality"
},
  "geometry": {"coordinates":[105.34999999999999,10.53333],"type":"Point"}
}