{
  "type": "Feature",
  "properties": {
    "gn:admin1_code":"89.0",
    "gn:asciiname":"Ban Houei Co",
    "gn:country_code":"VN",
    "gn:dem":826,
    "gn:feature_class":"P",
    "gn:feature_code":"PPL",
    "gn:name":"B\u1ea3n Houei Co",
    "gn:population":0,
    "gn:timezone":"Asia/Ho_Chi_Minh",
    "iso:country":"VN",
    "wof:name":"Ban Houei Co",
    "wof:placetype":"locality"
},
  "geometry": {"coordinates":[103.25,21.18333],"type":"Point"}
}