{
  "type": "Feature",
  "properties": {
    "gn:admin1_code":"68.0",
    "gn:asciiname":"Thon Thung",
    "gn:country_code":"VN",
    "gn:dem":28,
    "gn:feature_class":"P",
    "gn:feature_code":"PPL",
    "gn:name":"Th\u00f4n Thung",
    "gn:population":0,
    "gn:timezone":"Asia/Ho_Chi_Minh",
    "iso:country":"VN",
    "name:vie_x_preferred":[
        "Th\u00f4n Thung"
    ],
    "wof:name":"Thon Thung",
    "wof:placetype":"locality"
},
  "geometry": {"coordinates":[105.30698,21.52625],"type":"Point"}
}