{
  "type": "Feature",
  "properties": {
    "gn:admin1_code":"64.0",
    "gn:asciiname":"Thon Tam Lang",
    "gn:country_code":"VN",
    "gn:dem":7,
    "gn:feature_class":"P",
    "gn:feature_code":"PPL",
    "gn:name":"Th\u00f4n Tam Lang",
    "gn:population":0,
    "gn:timezone":"Asia/Ho_Chi_Minh",
    "iso:country":"VN",
    "name:und_x_variant":[
        "Lam Lang",
        "Th\u00f4n Tam Lang"
    ],
    "wof:name":"Thon Tam Lang",
    "wof:placetype":"locality"
},
  "geometry": {"coordinates":[107.05,16.81667],"type":"Point"}
}