{
  "type": "Feature",
  "properties": {
    "gn:admin1_code":"73.0",
    "gn:asciiname":"Vinh Moi",
    "gn:country_code":"VN",
    "gn:dem":2,
    "gn:feature_class":"P",
    "gn:feature_code":"PPL",
    "gn:name":"V\u0129nh M\u1edbi",
    "gn:population":0,
    "gn:timezone":"Asia/Ho_Chi_Minh",
    "iso:country":"VN",
    "name:vie_x_preferred":[
        "V\u0129nh M\u1edbi"
    ],
    "wof:name":"Vinh Moi",
    "wof:placetype":"locality"
},
  "geometry": {"coordinates":[105.57568000000001,9.1606],"type":"Point"}
}