{
  "type": "Feature",
  "properties": {
    "gn:admin1_code":"53.0",
    "gn:asciiname":"Lang Bay",
    "gn:country_code":"VN",
    "gn:dem":92,
    "gn:feature_class":"P",
    "gn:feature_code":"PPL",
    "gn:name":"L\u00e0ng Bay",
    "gn:population":0,
    "gn:timezone":"Asia/Ho_Chi_Minh",
    "iso:country":"VN",
    "name:vie_x_preferred":[
        "L\u00e0ng Bay"
    ],
    "wof:name":"Lang Bay",
    "wof:placetype":"locality"
},
  "geometry": {"coordinates":[105.52093000000001,20.3836],"type":"Point"}
}