{
  "type": "Feature",
  "properties": {
    "gn:admin1_code":"35.0",
    "gn:asciiname":"Quynh Ngoc",
    "gn:country_code":"VN",
    "gn:dem":-1,
    "gn:feature_class":"P",
    "gn:feature_code":"PPL",
    "gn:name":"Qu\u1ef3nh Ng\u1ecdc",
    "gn:population":0,
    "gn:timezone":"Asia/Ho_Chi_Minh",
    "iso:country":"VN",
    "wof:name":"Quynh Ngoc",
    "wof:placetype":"locality"
},
  "geometry": {"coordinates":[106.33333,20.66667],"type":"Point"}
}