{
  "type": "Feature",
  "properties": {
    "gn:admin1_code":"45.0",
    "gn:asciiname":"Xa Long Dien",
    "gn:country_code":"VN",
    "gn:dem":17,
    "gn:feature_class":"P",
    "gn:feature_code":"PPL",
    "gn:name":"X\u00e3 Long Di\u1ec1n",
    "gn:population":0,
    "gn:timezone":"Asia/Ho_Chi_Minh",
    "iso:country":"VN",
    "name:und_x_variant":[
        "Long Dien",
        "X\u00e3 Long Di\u1ec1n"
    ],
    "wof:name":"Xa Long Dien",
    "wof:placetype":"locality"
},
  "geometry": {"coordinates":[107.21666999999999,10.48333],"type":"Point"}
}