{
  "type": "Feature",
  "properties": {
    "gn:admin1_code":"89.0",
    "gn:asciiname":"Ho Pien",
    "gn:country_code":"VN",
    "gn:dem":1359,
    "gn:feature_class":"P",
    "gn:feature_code":"PPL",
    "gn:name":"H\u1ed3 Pi\u1ec1n",
    "gn:population":0,
    "gn:timezone":"Asia/Ho_Chi_Minh",
    "iso:country":"VN",
    "name:vie_x_preferred":[
        "H\u1ed3 Pi\u1ec1n"
    ],
    "wof:name":"Ho Pien",
    "wof:placetype":"locality"
},
  "geometry": {"coordinates":[103.54011,22.40879],"type":"Point"}
}