{
  "type": "Feature",
  "properties": {
    "gn:admin1_code":"90.0",
    "gn:asciiname":"Ban Bau Bang",
    "gn:country_code":"VN",
    "gn:dem":139,
    "gn:feature_class":"P",
    "gn:feature_code":"PPL",
    "gn:name":"B\u1ea3n B\u1ea7u B\u00e0ng",
    "gn:population":0,
    "gn:timezone":"Asia/Ho_Chi_Minh",
    "iso:country":"VN",
    "name:vie_x_preferred":[
        "B\u1ea3n B\u1ea7u B\u00e0ng"
    ],
    "wof:name":"Ban Bau Bang",
    "wof:placetype":"locality"
},
  "geometry": {"coordinates":[103.7863,22.64103],"type":"Point"}
}