{
  "type": "Feature",
  "properties": {
    "gn:admin1_code":"88.0",
    "gn:asciiname":"Mewal",
    "gn:country_code":"VN",
    "gn:dem":511,
    "gn:feature_class":"P",
    "gn:feature_code":"PPL",
    "gn:name":"Mewal",
    "gn:population":0,
    "gn:timezone":"Asia/Ho_Chi_Minh",
    "iso:country":"VN",
    "wof:name":"Mewal",
    "wof:placetype":"locality"
},
  "geometry": {"coordinates":[108.11667,12.85],"type":"Point"}
}