{
  "type": "Feature",
  "properties": {
    "gn:admin1_code":"32.0",
    "gn:asciiname":"Ban Dong Tau",
    "gn:country_code":"VN",
    "gn:dem":404,
    "gn:feature_class":"P",
    "gn:feature_code":"PPL",
    "gn:name":"B\u1ea3n \u0110\u00f4ng T\u1ea5u",
    "gn:population":0,
    "gn:timezone":"Asia/Ho_Chi_Minh",
    "iso:country":"VN",
    "name:vie_x_preferred":[
        "B\u1ea3n \u0110\u00f4ng T\u1ea5u"
    ],
    "wof:name":"Ban Dong Tau",
    "wof:placetype":"locality"
},
  "geometry": {"coordinates":[104.23421,21.1101],"type":"Point"}
}