{
  "type": "Feature",
  "properties": {
    "gn:admin1_code":"74.0",
    "gn:asciiname":"Bong Lai",
    "gn:country_code":"VN",
    "gn:dem":5,
    "gn:feature_class":"P",
    "gn:feature_code":"PPL",
    "gn:name":"B\u1ed3ng Lai",
    "gn:population":0,
    "gn:timezone":"Asia/Ho_Chi_Minh",
    "iso:country":"VN",
    "name:vie_x_preferred":[
        "B\u1ed3ng Lai"
    ],
    "wof:name":"Bong Lai",
    "wof:placetype":"locality"
},
  "geometry": {"coordinates":[106.27875,21.02521],"type":"Point"}
}