{
  "type": "Feature",
  "properties": {
    "gn:admin1_code":"71.0",
    "gn:asciiname":"Trai Moun",
    "gn:country_code":"VN",
    "gn:dem":23,
    "gn:feature_class":"P",
    "gn:feature_code":"PPL",
    "gn:name":"Tr\u1ea1i Moun",
    "gn:population":0,
    "gn:timezone":"Asia/Ho_Chi_Minh",
    "iso:country":"VN",
    "wof:name":"Trai Moun",
    "wof:placetype":"locality"
},
  "geometry": {"coordinates":[106.68333,21.36667000000001],"type":"Point"}
}