{
  "type": "Feature",
  "properties": {
    "gn:admin1_code":"88.0",
    "gn:asciiname":"Buon Pok",
    "gn:country_code":"VN",
    "gn:dem":600,
    "gn:feature_class":"P",
    "gn:feature_code":"PPL",
    "gn:name":"Bu\u00f4n P\u00f3k",
    "gn:population":0,
    "gn:timezone":"Asia/Ho_Chi_Minh",
    "iso:country":"VN",
    "name:und_x_variant":[
        "Ban Pok Kenh",
        "Buon Pok Kenh",
        "Buon Pok Penh",
        "Bu\u00f4n Pok"
    ],
    "name:vie_x_preferred":[
        "Bu\u00f4n P\u00f3k"
    ],
    "wof:name":"Buon Pok",
    "wof:placetype":"locality"
},
  "geometry": {"coordinates":[108.23551999999999,12.72656],"type":"Point"}
}