{
  "type": "Feature",
  "properties": {
    "gn:admin1_code":"58.0",
    "gn:asciiname":"Trung My",
    "gn:country_code":"VN",
    "gn:dem":6,
    "gn:feature_class":"P",
    "gn:feature_code":"PPL",
    "gn:name":"Trung M\u1ef9",
    "gn:population":0,
    "gn:timezone":"Asia/Ho_Chi_Minh",
    "iso:country":"VN",
    "name:vie_x_preferred":[
        "Trung M\u1ef9"
    ],
    "wof:name":"Trung My",
    "wof:placetype":"locality"
},
  "geometry": {"coordinates":[105.62403999999999,19.04216],"type":"Point"}
}