{
  "type": "Feature",
  "properties": {
    "gn:admin1_code":"71.0",
    "gn:asciiname":"Tam Tang",
    "gn:country_code":"VN",
    "gn:dem":17,
    "gn:feature_class":"P",
    "gn:feature_code":"PPL",
    "gn:name":"Tam T\u1ea7ng",
    "gn:population":0,
    "gn:timezone":"Asia/Ho_Chi_Minh",
    "iso:country":"VN",
    "name:vie_x_preferred":[
        "Tam T\u1ea7ng"
    ],
    "wof:name":"Tam Tang",
    "wof:placetype":"locality"
},
  "geometry": {"coordinates":[106.09931,21.22156],"type":"Point"}
}