{
  "type": "Feature",
  "properties": {
    "gn:admin1_code":"88.0",
    "gn:asciiname":"Thong Nhat",
    "gn:country_code":"VN",
    "gn:dem":451,
    "gn:feature_class":"P",
    "gn:feature_code":"PPL",
    "gn:name":"Th\u1ed1ng Nh\u1ea5t",
    "gn:population":0,
    "gn:timezone":"Asia/Ho_Chi_Minh",
    "iso:country":"VN",
    "name:vie_x_preferred":[
        "Th\u1ed1ng Nh\u1ea5t"
    ],
    "wof:name":"Thong Nhat",
    "wof:placetype":"locality"
},
  "geometry": {"coordinates":[108.20609,12.57567],"type":"Point"}
}