{
  "type": "Feature",
  "properties": {
    "gn:admin1_code":"54.0",
    "gn:asciiname":"Thon Phung Can",
    "gn:country_code":"VN",
    "gn:dem":1,
    "gn:feature_class":"P",
    "gn:feature_code":"PPL",
    "gn:name":"Th\u00f4n Ph\u1ee5ng Can",
    "gn:population":0,
    "gn:timezone":"Asia/Ho_Chi_Minh",
    "iso:country":"VN",
    "name:und_x_variant":[
        "Phung Cang",
        "Th\u00f4n Ph\u1ee5ng Can"
    ],
    "wof:name":"Thon Phung Can",
    "wof:placetype":"locality"
},
  "geometry": {"coordinates":[109.11667,12.45],"type":"Point"}
}