{
  "type": "Feature",
  "properties": {
    "gn:admin1_code":"93.0",
    "gn:asciiname":"Phung Son B",
    "gn:country_code":"VN",
    "gn:dem":5,
    "gn:feature_class":"P",
    "gn:feature_code":"PPL",
    "gn:name":"Ph\u1ee5ng S\u01a1n B",
    "gn:population":0,
    "gn:timezone":"Asia/Ho_Chi_Minh",
    "iso:country":"VN",
    "name:vie_x_preferred":[
        "Ph\u1ee5ng S\u01a1n B"
    ],
    "wof:name":"Phung Son B",
    "wof:placetype":"locality"
},
  "geometry": {"coordinates":[105.75193,9.85336],"type":"Point"}
}