{
  "type": "Feature",
  "properties": {
    "gn:admin1_code":"70.0",
    "gn:asciiname":"Ta Don",
    "gn:country_code":"VN",
    "gn:dem":1249,
    "gn:feature_class":"P",
    "gn:feature_code":"PPL",
    "gn:name":"Ta Don",
    "gn:population":0,
    "gn:timezone":"Asia/Ho_Chi_Minh",
    "iso:country":"VN",
    "wof:name":"Ta Don",
    "wof:placetype":"locality"
},
  "geometry": {"coordinates":[104.08333,21.71667],"type":"Point"}
}