{
  "type": "Feature",
  "properties": {
    "gn:admin1_code":"58.0",
    "gn:asciiname":"Ban Na Tin",
    "gn:country_code":"VN",
    "gn:dem":321,
    "gn:feature_class":"P",
    "gn:feature_code":"PPL",
    "gn:name":"B\u1ea3n Na Tin",
    "gn:population":0,
    "gn:timezone":"Asia/Ho_Chi_Minh",
    "iso:country":"VN",
    "wof:name":"Ban Na Tin",
    "wof:placetype":"locality"
},
  "geometry": {"coordinates":[104.28333000000001,19.38333],"type":"Point"}
}