{
  "type": "Feature",
  "properties": {
    "gn:admin1_code":"72.0",
    "gn:asciiname":"Tie Co",
    "gn:country_code":"VN",
    "gn:dem":367,
    "gn:feature_class":"P",
    "gn:feature_code":"PPL",
    "gn:name":"Ti\u00e9 Co",
    "gn:population":0,
    "gn:timezone":"Asia/Ho_Chi_Minh",
    "iso:country":"VN",
    "wof:name":"Tie Co",
    "wof:placetype":"locality"
},
  "geometry": {"coordinates":[106.03333000000001,22.13333],"type":"Point"}
}