{
  "type": "Feature",
  "properties": {
    "gn:admin1_code":"67.0",
    "gn:asciiname":"Tra Sot",
    "gn:country_code":"VN",
    "gn:dem":6,
    "gn:feature_class":"P",
    "gn:feature_code":"PPL",
    "gn:name":"Tr\u00e0 S\u1ed1t",
    "gn:population":0,
    "gn:timezone":"Asia/Ho_Chi_Minh",
    "iso:country":"VN",
    "name:und_x_variant":[
        "Tr\u00e0 S\u1ea7t",
        "Gi\u1ed3ng Tr\u00e0 S\u1ea7t"
    ],
    "name:vie_x_preferred":[
        "Tr\u00e0 S\u1ed1t"
    ],
    "wof:name":"Tra Sot",
    "wof:placetype":"locality"
},
  "geometry": {"coordinates":[106.31873,9.69831],"type":"Point"}
}