{
  "type": "Feature",
  "properties": {
    "gn:admin1_code":"68.0",
    "gn:asciiname":"Khe Xuyen",
    "gn:country_code":"VN",
    "gn:dem":30,
    "gn:feature_class":"P",
    "gn:feature_code":"PPL",
    "gn:name":"Khe Xuy\u00ean",
    "gn:population":0,
    "gn:timezone":"Asia/Ho_Chi_Minh",
    "iso:country":"VN",
    "name:und_x_variant":[
        "Kh\u00ea Xuy\u00ean"
    ],
    "name:vie_x_preferred":[
        "Khe Xuy\u00ean"
    ],
    "wof:name":"Khe Xuyen",
    "wof:placetype":"locality"
},
  "geometry": {"coordinates":[105.29581,21.60349],"type":"Point"}
}