{
  "type": "Feature",
  "properties": {
    "gn:admin1_code":"34.0",
    "gn:asciiname":"Xuan Thinh",
    "gn:country_code":"VN",
    "gn:dem":62,
    "gn:feature_class":"P",
    "gn:feature_code":"PPL",
    "gn:name":"Xu\u00e2n Th\u1ecbnh",
    "gn:population":0,
    "gn:timezone":"Asia/Ho_Chi_Minh",
    "iso:country":"VN",
    "name:vie_x_preferred":[
        "Xu\u00e2n Th\u1ecbnh"
    ],
    "wof:name":"Xuan Thinh",
    "wof:placetype":"locality"
},
  "geometry": {"coordinates":[105.41625999999999,19.73692],"type":"Point"}
}