{
  "type": "Feature",
  "properties": {
    "gn:admin1_code":"88.0",
    "gn:asciiname":"Ban Ea Pal",
    "gn:country_code":"VN",
    "gn:dem":468,
    "gn:feature_class":"P",
    "gn:feature_code":"PPL",
    "gn:name":"Ban Ea Pal",
    "gn:population":0,
    "gn:timezone":"Asia/Ho_Chi_Minh",
    "iso:country":"VN",
    "name:und_x_variant":[
        "Buon Ea Pal",
        "Ban Ea Pal"
    ],
    "wof:name":"Ban Ea Pal",
    "wof:placetype":"locality"
},
  "geometry": {"coordinates":[108.56667,12.76667],"type":"Point"}
}