{
  "type": "Feature",
  "properties": {
    "gn:admin1_code":"70.0",
    "gn:asciiname":"Co Thai",
    "gn:country_code":"VN",
    "gn:dem":749,
    "gn:feature_class":"P",
    "gn:feature_code":"PPL",
    "gn:name":"C\u00f2 Th\u00e1i",
    "gn:population":0,
    "gn:timezone":"Asia/Ho_Chi_Minh",
    "iso:country":"VN",
    "name:vie_x_preferred":[
        "C\u00f2 Th\u00e1i"
    ],
    "wof:name":"Co Thai",
    "wof:placetype":"locality"
},
  "geometry": {"coordinates":[104.29154,21.8136],"type":"Point"}
}