{
  "type": "Feature",
  "properties": {
    "gn:admin1_code":"39.0",
    "gn:asciiname":"Gia Leou",
    "gn:country_code":"VN",
    "gn:dem":502,
    "gn:feature_class":"P",
    "gn:feature_code":"PPL",
    "gn:name":"Gia L\u00e9ou",
    "gn:population":0,
    "gn:timezone":"Asia/Ho_Chi_Minh",
    "iso:country":"VN",
    "wof:name":"Gia Leou",
    "wof:placetype":"locality"
},
  "geometry": {"coordinates":[106.41667,21.93333],"type":"Point"}
}