{
  "type": "Feature",
  "properties": {
    "gn:admin1_code":"43.0",
    "gn:asciiname":"Xom Thien Quan",
    "gn:country_code":"VN",
    "gn:dem":15,
    "gn:feature_class":"P",
    "gn:feature_code":"PPL",
    "gn:name":"X\u00f3m Thi\u1ec7n Qu\u00e2n",
    "gn:population":0,
    "gn:timezone":"Asia/Ho_Chi_Minh",
    "iso:country":"VN",
    "name:und_x_variant":[
        "Thien Quan",
        "X\u00f3m Thi\u1ec7n Qu\u00e2n"
    ],
    "wof:name":"Xom Thien Quan",
    "wof:placetype":"locality"
},
  "geometry": {"coordinates":[106.93333,10.98333],"type":"Point"}
}