{
  "type": "Feature",
  "properties": {
    "gn:admin1_code":"76.0",
    "gn:asciiname":"Tang Hach",
    "gn:country_code":"VN",
    "gn:dem":64,
    "gn:feature_class":"P",
    "gn:feature_code":"PPL",
    "gn:name":"T\u1eb1ng H\u00e1ch",
    "gn:population":0,
    "gn:timezone":"Asia/Ho_Chi_Minh",
    "iso:country":"VN",
    "name:vie_x_preferred":[
        "T\u1eb1ng H\u00e1ch"
    ],
    "wof:name":"Tang Hach",
    "wof:placetype":"locality"
},
  "geometry": {"coordinates":[106.53346000000001,11.68989],"type":"Point"}
}