{
  "type": "Feature",
  "properties": {
    "gn:admin1_code":"63.0",
    "gn:asciiname":"Phuoc Thuan",
    "gn:country_code":"VN",
    "gn:dem":14,
    "gn:feature_class":"P",
    "gn:feature_code":"PPL",
    "gn:name":"Ph\u01b0\u1edbc Thu\u1eadn",
    "gn:population":0,
    "gn:timezone":"Asia/Ho_Chi_Minh",
    "iso:country":"VN",
    "name:und_x_variant":[
        "Phuoc Thien",
        "Ph\u01b0\u1edbc Thu\u1eadn"
    ],
    "wof:name":"Phuoc Thuan",
    "wof:placetype":"locality"
},
  "geometry": {"coordinates":[108.86667,15.35],"type":"Point"}
}