{
  "type": "Feature",
  "properties": {
    "gn:admin1_code":"43.0",
    "gn:asciiname":"Ap Sau Muoi Bay",
    "gn:country_code":"VN",
    "gn:dem":11,
    "gn:feature_class":"P",
    "gn:feature_code":"PPL",
    "gn:name":"\u1ea4p S\u00e1u M\u01b0\u01a1i B\u1ea3y",
    "gn:population":0,
    "gn:timezone":"Asia/Ho_Chi_Minh",
    "iso:country":"VN",
    "name:vie_x_preferred":[
        "\u1ea4p S\u00e1u M\u01b0\u01a1i B\u1ea3y"
    ],
    "name:vie_x_variant":[
        "\u1ea4p 67"
    ],
    "wof:name":"Ap Sau Muoi Bay",
    "wof:placetype":"locality"
},
  "geometry": {"coordinates":[106.89635,11.02206],"type":"Point"}
}