{
  "type": "Feature",
  "properties": {
    "gn:admin1_code":"74.0",
    "gn:asciiname":"Thong Thuong",
    "gn:country_code":"VN",
    "gn:dem":8,
    "gn:feature_class":"P",
    "gn:feature_code":"PPL",
    "gn:name":"Th\u00f4ng Th\u01b0\u1ee3ng",
    "gn:population":0,
    "gn:timezone":"Asia/Ho_Chi_Minh",
    "iso:country":"VN",
    "name:vie_x_preferred":[
        "Th\u00f4ng Th\u01b0\u1ee3ng"
    ],
    "wof:name":"Thong Thuong",
    "wof:placetype":"locality"
},
  "geometry": {"coordinates":[106.1284,21.20788],"type":"Point"}
}