{
  "type": "Feature",
  "properties": {
    "gn:admin1_code":"10.0",
    "gn:asciiname":"Kon Kotu",
    "gn:country_code":"VN",
    "gn:dem":539,
    "gn:feature_class":"P",
    "gn:feature_code":"PPL",
    "gn:name":"Kon K\u01a1tu",
    "gn:population":0,
    "gn:timezone":"Asia/Ho_Chi_Minh",
    "iso:country":"VN",
    "wof:name":"Kon Kotu",
    "wof:placetype":"locality"
},
  "geometry": {"coordinates":[108.08333,14.31667],"type":"Point"}
}