{
  "type": "Feature",
  "properties": {
    "gn:admin1_code":"23.0",
    "gn:asciiname":"Blac Dang R'mit",
    "gn:country_code":"VN",
    "gn:dem":416,
    "gn:feature_class":"P",
    "gn:feature_code":"PPL",
    "gn:name":"Blac Dang R\u2019mit",
    "gn:population":0,
    "gn:timezone":"Asia/Ho_Chi_Minh",
    "iso:country":"VN",
    "wof:name":"Blac Dang R'mit",
    "wof:placetype":"locality"
},
  "geometry": {"coordinates":[107.55,11.48333],"type":"Point"}
}