{
  "type": "Feature",
  "properties": {
    "gn:admin1_code":"52.0",
    "gn:asciiname":"Xom Muoi Lam",
    "gn:country_code":"VN",
    "gn:dem":8,
    "gn:feature_class":"P",
    "gn:feature_code":"PPL",
    "gn:name":"X\u00f3m M\u01b0\u1eddi L\u0103m",
    "gn:population":0,
    "gn:timezone":"Asia/Ho_Chi_Minh",
    "iso:country":"VN",
    "name:vie_x_preferred":[
        "X\u00f3m M\u01b0\u1eddi L\u0103m"
    ],
    "name:vie_x_variant":[
        "X\u00f3m 15"
    ],
    "wof:name":"Xom Muoi Lam",
    "wof:placetype":"locality"
},
  "geometry": {"coordinates":[105.86857999999999,18.38441],"type":"Point"}
}