{
  "type": "Feature",
  "properties": {
    "gn:admin1_code":"46.0",
    "gn:asciiname":"Ca Loc",
    "gn:country_code":"VN",
    "gn:dem":501,
    "gn:feature_class":"P",
    "gn:feature_code":"PPL",
    "gn:name":"Ca L\u00f4c",
    "gn:population":0,
    "gn:timezone":"Asia/Ho_Chi_Minh",
    "iso:country":"VN",
    "name:und_x_variant":[
        "Ca L\u00f4c"
    ],
    "wof:name":"Ca Loc",
    "wof:placetype":"locality"
},
  "geometry": {"coordinates":[108.91667,13.63333],"type":"Point"}
}