{
  "type": "Feature",
  "properties": {
    "gn:admin1_code":"64.0",
    "gn:asciiname":"Thuy Trung",
    "gn:country_code":"VN",
    "gn:dem":62,
    "gn:feature_class":"P",
    "gn:feature_code":"PPL",
    "gn:name":"Th\u1ee7y Trung",
    "gn:population":0,
    "gn:timezone":"Asia/Ho_Chi_Minh",
    "iso:country":"VN",
    "name:vie_x_preferred":[
        "Th\u1ee7y Trung"
    ],
    "wof:name":"Thuy Trung",
    "wof:placetype":"locality"
},
  "geometry": {"coordinates":[107.09256999999999,17.07213],"type":"Point"}
}