{
  "type": "Feature",
  "properties": {
    "gn:admin1_code":"31.0",
    "gn:asciiname":"Xom Bo",
    "gn:country_code":"VN",
    "gn:dem":70,
    "gn:feature_class":"P",
    "gn:feature_code":"PPL",
    "gn:name":"X\u00f3m B\u00f2",
    "gn:population":0,
    "gn:timezone":"Asia/Ho_Chi_Minh",
    "iso:country":"VN",
    "wof:name":"Xom Bo",
    "wof:placetype":"locality"
},
  "geometry": {"coordinates":[106.78333000000001,11.46667],"type":"Point"}
}