{
  "type": "Feature",
  "properties": {
    "gn:admin1_code":"92.0",
    "gn:asciiname":"Ban Hin Mot",
    "gn:country_code":"VN",
    "gn:dem":376,
    "gn:feature_class":"P",
    "gn:feature_code":"PPL",
    "gn:name":"B\u1ea3n Hin M\u1ed9t",
    "gn:population":0,
    "gn:timezone":"Asia/Ho_Chi_Minh",
    "iso:country":"VN",
    "name:vie_x_preferred":[
        "B\u1ea3n Hin M\u1ed9t"
    ],
    "name:vie_x_variant":[
        "B\u1ea3n Hin 1"
    ],
    "wof:name":"Ban Hin Mot",
    "wof:placetype":"locality"
},
  "geometry": {"coordinates":[103.08873,21.69798],"type":"Point"}
}