{
  "type": "Feature",
  "properties": {
    "gn:admin1_code":"32.0",
    "gn:asciiname":"Ban Suoi He",
    "gn:country_code":"VN",
    "gn:dem":542,
    "gn:feature_class":"P",
    "gn:feature_code":"PPL",
    "gn:name":"B\u1ea3n Su\u1ed1i H\u00ea",
    "gn:population":0,
    "gn:timezone":"Asia/Ho_Chi_Minh",
    "iso:country":"VN",
    "wof:name":"Ban Suoi He",
    "wof:placetype":"locality"
},
  "geometry": {"coordinates":[104.95,20.78333],"type":"Point"}
}