{
  "type": "Feature",
  "properties": {
    "gn:admin1_code":"82.0",
    "gn:asciiname":"Thu Loc",
    "gn:country_code":"VN",
    "gn:dem":5,
    "gn:feature_class":"P",
    "gn:feature_code":"PPL",
    "gn:name":"Th\u1ee5 L\u1ed9c",
    "gn:population":0,
    "gn:timezone":"Asia/Ho_Chi_Minh",
    "iso:country":"VN",
    "name:vie_x_preferred":[
        "Th\u1ee5 L\u1ed9c"
    ],
    "wof:name":"Thu Loc",
    "wof:placetype":"locality"
},
  "geometry": {"coordinates":[106.15996,20.21839],"type":"Point"}
}