{
  "type": "Feature",
  "properties": {
    "gn:admin1_code":"32.0",
    "gn:asciiname":"Ban Nhom",
    "gn:country_code":"VN",
    "gn:dem":458,
    "gn:feature_class":"P",
    "gn:feature_code":"PPL",
    "gn:name":"B\u1ea3n Nh\u00f4m",
    "gn:population":0,
    "gn:timezone":"Asia/Ho_Chi_Minh",
    "iso:country":"VN",
    "name:und_x_variant":[
        "B\u1ea3n Nh\u00f2m"
    ],
    "name:vie_x_preferred":[
        "B\u1ea3n Nh\u00f4m"
    ],
    "wof:name":"Ban Nhom",
    "wof:placetype":"locality"
},
  "geometry": {"coordinates":[104.21863999999999,21.13231],"type":"Point"}
}