{
  "type": "Feature",
  "properties": {
    "gn:admin1_code":"53.0",
    "gn:asciiname":"Xom Xat",
    "gn:country_code":"VN",
    "gn:dem":144,
    "gn:feature_class":"P",
    "gn:feature_code":"PPL",
    "gn:name":"X\u00f3m X\u00e1t",
    "gn:population":0,
    "gn:timezone":"Asia/Ho_Chi_Minh",
    "iso:country":"VN",
    "name:vie_x_preferred":[
        "X\u00f3m X\u00e1t"
    ],
    "wof:name":"Xom Xat",
    "wof:placetype":"locality"
},
  "geometry": {"coordinates":[105.38234,20.39224],"type":"Point"}
}