{
  "type": "Feature",
  "properties": {
    "gn:admin1_code":"85.0",
    "gn:asciiname":"Quang Ha",
    "gn:country_code":"VN",
    "gn:dem":132,
    "gn:feature_class":"P",
    "gn:feature_code":"PPL",
    "gn:name":"Quang Ha",
    "gn:population":0,
    "gn:timezone":"Asia/Ho_Chi_Minh",
    "iso:country":"VN",
    "wof:name":"Quang Ha",
    "wof:placetype":"locality"
},
  "geometry": {"coordinates":[105.56667,21.78333],"type":"Point"}
}