{
  "type": "Feature",
  "properties": {
    "gn:admin1_code":"65.0",
    "gn:asciiname":"Can Duoc",
    "gn:country_code":"VN",
    "gn:dem":6,
    "gn:feature_class":"P",
    "gn:feature_code":"PPL",
    "gn:name":"C\u1ea7n \u0110\u01b0\u1edbc",
    "gn:population":0,
    "gn:timezone":"Asia/Ho_Chi_Minh",
    "iso:country":"VN",
    "name:vie_x_preferred":[
        "C\u1ea7n \u0110\u01b0\u1edbc"
    ],
    "wof:name":"Can Duoc",
    "wof:placetype":"locality"
},
  "geometry": {"coordinates":[105.86321,9.50739],"type":"Point"}
}