{
  "type": "Feature",
  "properties": {
    "gn:admin1_code":"52.0",
    "gn:asciiname":"Binh Nguyen",
    "gn:country_code":"VN",
    "gn:dem":5,
    "gn:feature_class":"P",
    "gn:feature_code":"PPL",
    "gn:name":"Binh Nguy\u00ean",
    "gn:population":0,
    "gn:timezone":"Asia/Ho_Chi_Minh",
    "iso:country":"VN",
    "name:und_x_variant":[
        "Bing Nguyen",
        "Binh Nguy\u00ean"
    ],
    "wof:name":"Binh Nguyen",
    "wof:placetype":"locality"
},
  "geometry": {"coordinates":[105.86667,18.46667],"type":"Point"}
}