{
  "type": "Feature",
  "properties": {
    "gn:admin1_code":"32.0",
    "gn:asciiname":"Tieng Sang",
    "gn:cc2":"VN",
    "gn:country_code":"VN",
    "gn:dem":964,
    "gn:feature_class":"P",
    "gn:feature_code":"PPL",
    "gn:name":"Tieng Sang",
    "gn:population":0,
    "gn:timezone":"Asia/Ho_Chi_Minh",
    "iso:country":"VN",
    "name:und_x_variant":[
        "Tieng Seng",
        "Tieng Sang"
    ],
    "wof:name":"Tieng Sang",
    "wof:placetype":"locality"
},
  "geometry": {"coordinates":[104.71666999999999,20.86667000000001],"type":"Point"}
}