{
  "type": "Feature",
  "properties": {
    "gn:admin1_code":"72.0",
    "gn:asciiname":"Pieng Lan",
    "gn:country_code":"VN",
    "gn:dem":1407,
    "gn:feature_class":"P",
    "gn:feature_code":"PPL",
    "gn:name":"Pieng Lan",
    "gn:population":0,
    "gn:timezone":"Asia/Ho_Chi_Minh",
    "iso:country":"VN",
    "wof:name":"Pieng Lan",
    "wof:placetype":"locality"
},
  "geometry": {"coordinates":[105.57512,22.65992],"type":"Point"}
}