{
  "type": "Feature",
  "properties": {
    "gn:admin1_code":"88.0",
    "gn:asciiname":"Buon Ea Bong",
    "gn:country_code":"VN",
    "gn:dem":432,
    "gn:feature_class":"P",
    "gn:feature_code":"PPL",
    "gn:name":"Bu\u00f4n Ea B\u014fng",
    "gn:population":0,
    "gn:timezone":"Asia/Ho_Chi_Minh",
    "iso:country":"VN",
    "wof:name":"Buon Ea Bong",
    "wof:placetype":"locality"
},
  "geometry": {"coordinates":[108.03333000000001,12.71667],"type":"Point"}
}