{
  "type": "Feature",
  "properties": {
    "gn:admin1_code":"32.0",
    "gn:asciiname":"Ban Nha Sang",
    "gn:country_code":"VN",
    "gn:dem":502,
    "gn:feature_class":"P",
    "gn:feature_code":"PPL",
    "gn:name":"B\u1ea3n Nh\u00e0 S\u00e0ng",
    "gn:population":0,
    "gn:timezone":"Asia/Ho_Chi_Minh",
    "iso:country":"VN",
    "name:vie_x_preferred":[
        "B\u1ea3n Nh\u00e0 S\u00e0ng"
    ],
    "wof:name":"Ban Nha Sang",
    "wof:placetype":"locality"
},
  "geometry": {"coordinates":[103.69781999999999,21.6045],"type":"Point"}
}