{
  "type": "Feature",
  "properties": {
    "gn:admin1_code":"63.0",
    "gn:asciiname":"Xom Peo",
    "gn:country_code":"VN",
    "gn:dem":55,
    "gn:feature_class":"P",
    "gn:feature_code":"PPL",
    "gn:name":"X\u00f3m Peo",
    "gn:population":0,
    "gn:timezone":"Asia/Ho_Chi_Minh",
    "iso:country":"VN",
    "name:vie_x_preferred":[
        "X\u00f3m Peo"
    ],
    "wof:name":"Xom Peo",
    "wof:placetype":"locality"
},
  "geometry": {"coordinates":[108.54241,15.01812],"type":"Point"}
}