{
  "type": "Feature",
  "properties": {
    "gn:admin1_code":"90.0",
    "gn:asciiname":"Ban Chong Chai",
    "gn:country_code":"VN",
    "gn:dem":706,
    "gn:feature_class":"P",
    "gn:feature_code":"PPL",
    "gn:name":"B\u1ea3n Ch\u1ed1ng Ch\u1ea3i",
    "gn:population":0,
    "gn:timezone":"Asia/Ho_Chi_Minh",
    "iso:country":"VN",
    "name:vie_x_preferred":[
        "B\u1ea3n Ch\u1ed1ng Ch\u1ea3i"
    ],
    "wof:name":"Ban Chong Chai",
    "wof:placetype":"locality"
},
  "geometry": {"coordinates":[104.38112,22.66479],"type":"Point"}
}