{
  "type": "Feature",
  "properties": {
    "gn:admin1_code":"79.0",
    "gn:asciiname":"Xom Lam",
    "gn:country_code":"VN",
    "gn:dem":13,
    "gn:feature_class":"P",
    "gn:feature_code":"PPL",
    "gn:name":"X\u00f3m L\u1eabm",
    "gn:population":0,
    "gn:timezone":"Asia/Ho_Chi_Minh",
    "iso:country":"VN",
    "name:vie_x_preferred":[
        "X\u00f3m L\u1eabm"
    ],
    "wof:name":"Xom Lam",
    "wof:placetype":"locality"
},
  "geometry": {"coordinates":[106.32656,21.16484],"type":"Point"}
}