{
  "type": "Feature",
  "properties": {
    "gn:admin1_code":"33.0",
    "gn:asciiname":"Ro Ban",
    "gn:cc2":"VN",
    "gn:country_code":"VN",
    "gn:dem":6,
    "gn:feature_class":"P",
    "gn:feature_code":"PPL",
    "gn:name":"R\u00f4 B\u00e2n",
    "gn:population":0,
    "gn:timezone":"Asia/Ho_Chi_Minh",
    "iso:country":"VN",
    "name:und_x_variant":[
        "Tapang Robon",
        "R\u00f4 B\u00e2n"
    ],
    "wof:name":"Ro Ban",
    "wof:placetype":"locality"
},
  "geometry": {"coordinates":[105.93333,11.25],"type":"Point"}
}