{
  "type": "Feature",
  "properties": {
    "gn:admin1_code":"46.0",
    "gn:asciiname":"Vinh Thuan",
    "gn:country_code":"VN",
    "gn:dem":22,
    "gn:feature_class":"P",
    "gn:feature_code":"PPL",
    "gn:name":"V\u0129nh Thu\u1eadn",
    "gn:population":0,
    "gn:timezone":"Asia/Ho_Chi_Minh",
    "iso:country":"VN",
    "name:vie_x_preferred":[
        "V\u0129nh Thu\u1eadn"
    ],
    "wof:name":"Vinh Thuan",
    "wof:placetype":"locality"
},
  "geometry": {"coordinates":[109.05141,14.29183],"type":"Point"}
}