{
  "type": "Feature",
  "properties": {
    "gn:admin1_code":"89.0",
    "gn:asciiname":"Ban Hua Uy Dao",
    "gn:country_code":"VN",
    "gn:dem":874,
    "gn:feature_class":"P",
    "gn:feature_code":"PPL",
    "gn:name":"B\u1ea3n Hua Uy D\u1ea1o",
    "gn:population":0,
    "gn:timezone":"Asia/Ho_Chi_Minh",
    "iso:country":"VN",
    "name:vie_x_preferred":[
        "B\u1ea3n Hua Uy D\u1ea1o"
    ],
    "wof:name":"Ban Hua Uy Dao",
    "wof:placetype":"locality"
},
  "geometry": {"coordinates":[103.60135,22.10188],"type":"Point"}
}