{
  "type": "Feature",
  "properties": {
    "gn:admin1_code":"90.0",
    "gn:asciiname":"Nam Si",
    "gn:country_code":"VN",
    "gn:dem":954,
    "gn:feature_class":"P",
    "gn:feature_code":"PPL",
    "gn:name":"N\u1eadm Si",
    "gn:population":0,
    "gn:timezone":"Asia/Ho_Chi_Minh",
    "iso:country":"VN",
    "name:vie_x_preferred":[
        "N\u1eadm Si"
    ],
    "wof:name":"Nam Si",
    "wof:placetype":"locality"
},
  "geometry": {"coordinates":[103.99379999999999,22.32862],"type":"Point"}
}