{
  "type": "Feature",
  "properties": {
    "gn:admin1_code":"68.0",
    "gn:asciiname":"Ban Vit",
    "gn:country_code":"VN",
    "gn:dem":429,
    "gn:feature_class":"P",
    "gn:feature_code":"PPL",
    "gn:name":"B\u1ea3n V\u1ecbt",
    "gn:population":0,
    "gn:timezone":"Asia/Ho_Chi_Minh",
    "iso:country":"VN",
    "name:vie_x_preferred":[
        "B\u1ea3n V\u1ecbt"
    ],
    "wof:name":"Ban Vit",
    "wof:placetype":"locality"
},
  "geometry": {"coordinates":[105.49471,22.62074],"type":"Point"}
}