{
  "type": "Feature",
  "properties": {
    "gn:admin1_code":"70.0",
    "gn:asciiname":"Khe Chung Ba",
    "gn:country_code":"VN",
    "gn:dem":298,
    "gn:feature_class":"P",
    "gn:feature_code":"PPL",
    "gn:name":"Khe Chung Ba",
    "gn:population":0,
    "gn:timezone":"Asia/Ho_Chi_Minh",
    "iso:country":"VN",
    "name:vie_x_preferred":[
        "Khe Chung Ba"
    ],
    "name:vie_x_variant":[
        "Khe Chung 3"
    ],
    "wof:name":"Khe Chung Ba",
    "wof:placetype":"locality"
},
  "geometry": {"coordinates":[104.48448999999999,21.91333],"type":"Point"}
}