{
  "type": "Feature",
  "properties": {
    "gn:admin1_code":"58.0",
    "gn:asciiname":"Lang Bai",
    "gn:country_code":"VN",
    "gn:dem":71,
    "gn:feature_class":"P",
    "gn:feature_code":"PPL",
    "gn:name":"L\u00e0ng Bai",
    "gn:population":0,
    "gn:timezone":"Asia/Ho_Chi_Minh",
    "iso:country":"VN",
    "name:vie_x_preferred":[
        "L\u00e0ng Bai"
    ],
    "wof:name":"Lang Bai",
    "wof:placetype":"locality"
},
  "geometry": {"coordinates":[105.26061,19.36544],"type":"Point"}
}