{
  "type": "Feature",
  "properties": {
    "gn:admin1_code":"39.0",
    "gn:asciiname":"Khuay Rat",
    "gn:country_code":"VN",
    "gn:dem":351,
    "gn:feature_class":"P",
    "gn:feature_code":"PPL",
    "gn:name":"Khu\u1ea9y R\u1eadt",
    "gn:population":0,
    "gn:timezone":"Asia/Ho_Chi_Minh",
    "iso:country":"VN",
    "name:vie_x_preferred":[
        "Khu\u1ea9y R\u1eadt"
    ],
    "wof:name":"Khuay Rat",
    "wof:placetype":"locality"
},
  "geometry": {"coordinates":[106.26873999999999,21.94792],"type":"Point"}
}