{
  "type": "Feature",
  "properties": {
    "gn:admin1_code":"53.0",
    "gn:asciiname":"Mai Ha",
    "gn:country_code":"VN",
    "gn:dem":355,
    "gn:feature_class":"P",
    "gn:feature_code":"PPL",
    "gn:name":"Mai H\u1ea1",
    "gn:population":0,
    "gn:timezone":"Asia/Ho_Chi_Minh",
    "iso:country":"VN",
    "name:und_x_variant":[
        "Mai Hai",
        "Mai H\u1ea1"
    ],
    "wof:name":"Mai Ha",
    "wof:placetype":"locality"
},
  "geometry": {"coordinates":[105.01667,20.61667000000001],"type":"Point"}
}