{
  "type": "Feature",
  "properties": {
    "gn:admin1_code":"23.0",
    "gn:asciiname":"Vinh Ninh",
    "gn:country_code":"VN",
    "gn:dem":173,
    "gn:feature_class":"P",
    "gn:feature_code":"PPL",
    "gn:name":"V\u0129nh Ninh",
    "gn:population":0,
    "gn:timezone":"Asia/Ho_Chi_Minh",
    "iso:country":"VN",
    "name:vie_x_preferred":[
        "V\u0129nh Ninh"
    ],
    "wof:name":"Vinh Ninh",
    "wof:placetype":"locality"
},
  "geometry": {"coordinates":[107.27591,11.64015],"type":"Point"}
}