{
  "type": "Feature",
  "properties": {
    "gn:admin1_code":"44.0",
    "gn:asciiname":"Tuong Phieu",
    "gn:country_code":"VN",
    "gn:dem":16,
    "gn:feature_class":"P",
    "gn:feature_code":"PPL",
    "gn:name":"T\u01b0\u1eddng Phi\u00eau",
    "gn:population":0,
    "gn:timezone":"Asia/Ho_Chi_Minh",
    "iso:country":"VN",
    "wof:name":"Tuong Phieu",
    "wof:placetype":"locality"
},
  "geometry": {"coordinates":[105.51667,21.08333],"type":"Point"}
}