{
  "type": "Feature",
  "properties": {
    "gn:admin1_code":"89.0",
    "gn:asciiname":"Ban Mit No Thai",
    "gn:country_code":"VN",
    "gn:dem":709,
    "gn:feature_class":"P",
    "gn:feature_code":"PPL",
    "gn:name":"B\u1ea3n M\u00edt N\u1ecd Th\u00e1i",
    "gn:population":0,
    "gn:timezone":"Asia/Ho_Chi_Minh",
    "iso:country":"VN",
    "name:vie_x_preferred":[
        "B\u1ea3n M\u00edt N\u1ecd Th\u00e1i"
    ],
    "wof:name":"Ban Mit No Thai",
    "wof:placetype":"locality"
},
  "geometry": {"coordinates":[103.89039,22.06858],"type":"Point"}
}