{
  "type": "Feature",
  "properties": {
    "gn:admin1_code":"37.0",
    "gn:asciiname":"My Hoi",
    "gn:cc2":"VN",
    "gn:country_code":"VN",
    "gn:dem":3,
    "gn:feature_class":"P",
    "gn:feature_code":"PPL",
    "gn:name":"M\u1ef9 H\u1ed9i",
    "gn:population":0,
    "gn:timezone":"Asia/Ho_Chi_Minh",
    "iso:country":"VN",
    "name:und_x_variant":[
        "M\u1ef9 Q\u00fai",
        "M\u1ef9 H\u1ed9i"
    ],
    "wof:name":"My Hoi",
    "wof:placetype":"locality"
},
  "geometry": {"coordinates":[106.18333,10.38333],"type":"Point"}
}