{
  "type": "Feature",
  "properties": {
    "gn:admin1_code":"70.0",
    "gn:asciiname":"Lang Noi",
    "gn:country_code":"VN",
    "gn:dem":73,
    "gn:feature_class":"P",
    "gn:feature_code":"PPL",
    "gn:name":"L\u00e0ng N\u00f4i",
    "gn:population":0,
    "gn:timezone":"Asia/Ho_Chi_Minh",
    "iso:country":"VN",
    "name:vie_x_preferred":[
        "L\u00e0ng N\u00f4i"
    ],
    "wof:name":"Lang Noi",
    "wof:placetype":"locality"
},
  "geometry": {"coordinates":[104.9175,21.93066],"type":"Point"}
}