{
  "type": "Feature",
  "properties": {
    "gn:admin1_code":"23.0",
    "gn:asciiname":"Bo Kocil",
    "gn:country_code":"VN",
    "gn:dem":260,
    "gn:feature_class":"P",
    "gn:feature_code":"PPL",
    "gn:name":"Bo Kocil",
    "gn:population":0,
    "gn:timezone":"Asia/Ho_Chi_Minh",
    "iso:country":"VN",
    "wof:name":"Bo Kocil",
    "wof:placetype":"locality"
},
  "geometry": {"coordinates":[107.55,11.43333],"type":"Point"}
}