{
  "type": "Feature",
  "properties": {
    "gn:admin1_code":"58.0",
    "gn:asciiname":"Ke Te",
    "gn:country_code":"VN",
    "gn:dem":165,
    "gn:feature_class":"P",
    "gn:feature_code":"PPL",
    "gn:name":"K\u1ebb Te",
    "gn:population":0,
    "gn:timezone":"Asia/Ho_Chi_Minh",
    "iso:country":"VN",
    "wof:name":"Ke Te",
    "wof:placetype":"locality"
},
  "geometry": {"coordinates":[104.96666999999999,19.08333],"type":"Point"}
}