{
  "type": "Feature",
  "properties": {
    "gn:admin1_code":"58.0",
    "gn:asciiname":"Xom Nam",
    "gn:country_code":"VN",
    "gn:dem":9,
    "gn:feature_class":"P",
    "gn:feature_code":"PPL",
    "gn:name":"X\u00f3m N\u0103m",
    "gn:population":0,
    "gn:timezone":"Asia/Ho_Chi_Minh",
    "iso:country":"VN",
    "name:vie_x_preferred":[
        "X\u00f3m N\u0103m"
    ],
    "name:vie_x_variant":[
        "X\u00f3m 5"
    ],
    "wof:name":"Xom Nam",
    "wof:placetype":"locality"
},
  "geometry": {"coordinates":[105.64776999999999,18.75885],"type":"Point"}
}