{
  "type": "Feature",
  "properties": {
    "gn:admin1_code":"39.0",
    "gn:asciiname":"Na Puoc",
    "gn:country_code":"VN",
    "gn:dem":172,
    "gn:feature_class":"P",
    "gn:feature_code":"PPL",
    "gn:name":"N\u00e0 Pu\u1ed9c",
    "gn:population":0,
    "gn:timezone":"Asia/Ho_Chi_Minh",
    "iso:country":"VN",
    "name:vie_x_preferred":[
        "N\u00e0 Pu\u1ed9c"
    ],
    "wof:name":"Na Puoc",
    "wof:placetype":"locality"
},
  "geometry": {"coordinates":[106.46477,22.26954],"type":"Point"}
}