{
  "type": "Feature",
  "properties": {
    "gn:admin1_code":"85.0",
    "gn:asciiname":"Yen Thai",
    "gn:country_code":"VN",
    "gn:dem":67,
    "gn:feature_class":"P",
    "gn:feature_code":"PPL",
    "gn:name":"Y\u00ean Th\u00e1i",
    "gn:population":0,
    "gn:timezone":"Asia/Ho_Chi_Minh",
    "iso:country":"VN",
    "name:und_x_variant":[
        "Y\u00ean Tai"
    ],
    "name:vie_x_preferred":[
        "Y\u00ean Th\u00e1i"
    ],
    "wof:name":"Yen Thai",
    "wof:placetype":"locality"
},
  "geometry": {"coordinates":[105.67556,21.60984],"type":"Point"}
}