{
  "type": "Feature",
  "properties": {
    "gn:admin1_code":"63.0",
    "gn:asciiname":"Phu Hoa",
    "gn:country_code":"VN",
    "gn:dem":26,
    "gn:feature_class":"P",
    "gn:feature_code":"PPL",
    "gn:name":"Ph\u00fa H\u00f2a",
    "gn:population":0,
    "gn:timezone":"Asia/Ho_Chi_Minh",
    "iso:country":"VN",
    "name:und_x_variant":[
        "Nh\u00e2n H\u00f2a"
    ],
    "name:vie_x_preferred":[
        "Ph\u00fa H\u00f2a"
    ],
    "wof:name":"Phu Hoa",
    "wof:placetype":"locality"
},
  "geometry": {"coordinates":[108.56612,15.25302],"type":"Point"}
}