{
  "type": "Feature",
  "properties": {
    "gn:admin1_code":"13.0",
    "gn:asciiname":"Minh Hung",
    "gn:country_code":"VN",
    "gn:dem":1,
    "gn:feature_class":"P",
    "gn:feature_code":"PPL",
    "gn:name":"Minh H\u01b0ng",
    "gn:population":0,
    "gn:timezone":"Asia/Ho_Chi_Minh",
    "iso:country":"VN",
    "name:vie_x_preferred":[
        "Minh H\u01b0ng"
    ],
    "wof:name":"Minh Hung",
    "wof:placetype":"locality"
},
  "geometry": {"coordinates":[106.61911000000001,20.64208],"type":"Point"}
}