{
  "type": "Feature",
  "properties": {
    "gn:admin1_code":"43.0",
    "gn:asciiname":"Xom Mieu",
    "gn:country_code":"VN",
    "gn:dem":20,
    "gn:feature_class":"P",
    "gn:feature_code":"PPL",
    "gn:name":"X\u00f3m Mi\u1ebfu",
    "gn:population":0,
    "gn:timezone":"Asia/Ho_Chi_Minh",
    "iso:country":"VN",
    "wof:name":"Xom Mieu",
    "wof:placetype":"locality"
},
  "geometry": {"coordinates":[106.93333,10.81667],"type":"Point"}
}