{
  "type": "Feature",
  "properties": {
    "gn:admin1_code":"92.0",
    "gn:asciiname":"Nam Po",
    "gn:country_code":"VN",
    "gn:dem":982,
    "gn:feature_class":"P",
    "gn:feature_code":"PPL",
    "gn:name":"N\u1eadm P\u00f3",
    "gn:population":0,
    "gn:timezone":"Asia/Ho_Chi_Minh",
    "iso:country":"VN",
    "name:vie_x_preferred":[
        "N\u1eadm P\u00f3"
    ],
    "wof:name":"Nam Po",
    "wof:placetype":"locality"
},
  "geometry": {"coordinates":[103.04783,21.71066],"type":"Point"}
}