{
  "type": "Feature",
  "properties": {
    "gn:admin1_code":"58.0",
    "gn:asciiname":"Hoang Tru",
    "gn:country_code":"VN",
    "gn:dem":11,
    "gn:feature_class":"P",
    "gn:feature_code":"PPL",
    "gn:name":"Ho\u00e0ng Tr\u00f9",
    "gn:population":0,
    "gn:timezone":"Asia/Ho_Chi_Minh",
    "iso:country":"VN",
    "wof:name":"Hoang Tru",
    "wof:placetype":"locality"
},
  "geometry": {"coordinates":[105.56667,18.68333],"type":"Point"}
}