{
  "type": "Feature",
  "properties": {
    "gn:admin1_code":"31.0",
    "gn:asciiname":"Ap Duong Dap",
    "gn:country_code":"VN",
    "gn:dem":8,
    "gn:feature_class":"P",
    "gn:feature_code":"PPL",
    "gn:name":"\u1ea4p D\u01b0\u1eddng D\u1eafp",
    "gn:population":0,
    "gn:timezone":"Asia/Ho_Chi_Minh",
    "iso:country":"VN",
    "wof:name":"Ap Duong Dap",
    "wof:placetype":"locality"
},
  "geometry": {"coordinates":[106.78333000000001,11.03333],"type":"Point"}
}