{
  "type": "Feature",
  "properties": {
    "gn:admin1_code":"16.0",
    "gn:asciiname":"Hai Nhan",
    "gn:country_code":"VN",
    "gn:dem":369,
    "gn:feature_class":"P",
    "gn:feature_code":"PPL",
    "gn:name":"Hai Nhan",
    "gn:population":0,
    "gn:timezone":"Asia/Ho_Chi_Minh",
    "iso:country":"VN",
    "wof:name":"Hai Nhan",
    "wof:placetype":"locality"
},
  "geometry": {"coordinates":[105.31667,20.91667],"type":"Point"}
}