{
  "type": "Feature",
  "properties": {
    "gn:admin1_code":"30.0",
    "gn:asciiname":"Na Ech",
    "gn:country_code":"VN",
    "gn:dem":268,
    "gn:feature_class":"P",
    "gn:feature_code":"PPL",
    "gn:name":"N\u00e0 \u1ebech",
    "gn:population":0,
    "gn:timezone":"Asia/Ho_Chi_Minh",
    "iso:country":"VN",
    "name:vie_x_preferred":[
        "N\u00e0 \u1ebech"
    ],
    "wof:name":"Na Ech",
    "wof:placetype":"locality"
},
  "geometry": {"coordinates":[107.44807,21.48004],"type":"Point"}
}