{
  "type": "Feature",
  "properties": {
    "gn:admin1_code":"68.0",
    "gn:asciiname":"Khoang Lu",
    "gn:country_code":"VN",
    "gn:dem":62,
    "gn:feature_class":"P",
    "gn:feature_code":"PPL",
    "gn:name":"Khoang L\u01b0",
    "gn:population":0,
    "gn:timezone":"Asia/Ho_Chi_Minh",
    "iso:country":"VN",
    "name:und_x_variant":[
        "Khoan L\u01b0"
    ],
    "name:vie_x_preferred":[
        "Khoang L\u01b0"
    ],
    "wof:name":"Khoang Lu",
    "wof:placetype":"locality"
},
  "geometry": {"coordinates":[105.4552,21.55413],"type":"Point"}
}