{
  "type": "Feature",
  "properties": {
    "gn:admin1_code":"80.0",
    "gn:asciiname":"Quang Am",
    "gn:country_code":"VN",
    "gn:dem":5,
    "gn:feature_class":"P",
    "gn:feature_code":"PPL",
    "gn:name":"Quang \u00c3m",
    "gn:population":0,
    "gn:timezone":"Asia/Ho_Chi_Minh",
    "iso:country":"VN",
    "name:und_x_variant":[
        "Quang An",
        "Quang \u00c3m"
    ],
    "wof:name":"Quang Am",
    "wof:placetype":"locality"
},
  "geometry": {"coordinates":[105.93333,20.56667],"type":"Point"}
}