{
  "type": "Feature",
  "properties": {
    "gn:admin1_code":"68.0",
    "gn:asciiname":"Ban Na Hao",
    "gn:country_code":"VN",
    "gn:dem":145,
    "gn:feature_class":"P",
    "gn:feature_code":"PPL",
    "gn:name":"B\u1ea3n N\u00e0 H\u00e1o",
    "gn:population":0,
    "gn:timezone":"Asia/Ho_Chi_Minh",
    "iso:country":"VN",
    "name:vie_x_preferred":[
        "N\u00e0 R\u00e1o"
    ],
    "name:vie_x_variant":[
        "B\u1ea3n N\u00e0 H\u00e1o"
    ],
    "wof:name":"Ban Na Hao",
    "wof:placetype":"locality"
},
  "geometry": {"coordinates":[105.25933999999999,22.52045],"type":"Point"}
}