{
  "type": "Feature",
  "properties": {
    "gn:admin1_code":"39.0",
    "gn:asciiname":"Ban Na Han",
    "gn:country_code":"VN",
    "gn:dem":343,
    "gn:feature_class":"P",
    "gn:feature_code":"PPL",
    "gn:name":"B\u1ea3n N\u00e0 Han",
    "gn:population":0,
    "gn:timezone":"Asia/Ho_Chi_Minh",
    "iso:country":"VN",
    "name:und_x_variant":[
        "B\u1ea3n N\u00e0 Han",
        "Na H\u00e0n"
    ],
    "wof:name":"Ban Na Han",
    "wof:placetype":"locality"
},
  "geometry": {"coordinates":[106.6816,22.02039],"type":"Point"}
}