{
  "type": "Feature",
  "properties": {
    "gn:admin1_code":"83.0",
    "gn:asciiname":"Kien Thiet",
    "gn:country_code":"VN",
    "gn:dem":38,
    "gn:feature_class":"P",
    "gn:feature_code":"PPL",
    "gn:name":"Ki\u00ean Thi\u1ebft",
    "gn:population":0,
    "gn:timezone":"Asia/Ho_Chi_Minh",
    "iso:country":"VN",
    "name:vie_x_preferred":[
        "Ki\u00ean Thi\u1ebft"
    ],
    "wof:name":"Kien Thiet",
    "wof:placetype":"locality"
},
  "geometry": {"coordinates":[105.37456,21.41364],"type":"Point"}
}