{
  "type": "Feature",
  "properties": {
    "gn:admin1_code":"86.0",
    "gn:asciiname":"Phan Du",
    "gn:country_code":"VN",
    "gn:dem":42,
    "gn:feature_class":"P",
    "gn:feature_code":"PPL",
    "gn:name":"Phan D\u01b0",
    "gn:population":0,
    "gn:timezone":"Asia/Ho_Chi_Minh",
    "iso:country":"VN",
    "name:vie_x_preferred":[
        "Phan D\u01b0"
    ],
    "wof:name":"Phan Du",
    "wof:placetype":"locality"
},
  "geometry": {"coordinates":[105.43347,21.35456],"type":"Point"}
}