{
  "type": "Feature",
  "properties": {
    "gn:admin1_code":"34.0",
    "gn:asciiname":"Tan Hiep",
    "gn:country_code":"VN",
    "gn:dem":104,
    "gn:feature_class":"P",
    "gn:feature_code":"PPL",
    "gn:name":"T\u00e2n Hi\u1ec7p",
    "gn:population":0,
    "gn:timezone":"Asia/Ho_Chi_Minh",
    "iso:country":"VN",
    "name:vie_x_preferred":[
        "T\u00e2n Hi\u1ec7p"
    ],
    "wof:name":"Tan Hiep",
    "wof:placetype":"locality"
},
  "geometry": {"coordinates":[105.31074,19.62444],"type":"Point"}
}