{
  "type": "Feature",
  "properties": {
    "gn:admin1_code":"63.0",
    "gn:asciiname":"Hai Chau",
    "gn:country_code":"VN",
    "gn:dem":6,
    "gn:feature_class":"P",
    "gn:feature_code":"PPL",
    "gn:name":"H\u1ea3i Ch\u00e2u",
    "gn:population":0,
    "gn:timezone":"Asia/Ho_Chi_Minh",
    "iso:country":"VN",
    "name:und_x_variant":[
        "Phu-Chau",
        "Phuchali",
        "H\u1ea3i Ch\u00e2u"
    ],
    "wof:name":"Hai Chau",
    "wof:placetype":"locality"
},
  "geometry": {"coordinates":[108.88333,15.05],"type":"Point"}
}