{
  "type": "Feature",
  "properties": {
    "gn:admin1_code":"77.0",
    "gn:asciiname":"Ong Do",
    "gn:country_code":"VN",
    "gn:dem":3,
    "gn:feature_class":"P",
    "gn:feature_code":"PPL",
    "gn:name":"\u00d4ng Do",
    "gn:population":0,
    "gn:timezone":"Asia/Ho_Chi_Minh",
    "iso:country":"VN",
    "name:und_x_variant":[
        "Hang Vinh",
        "X\u00f3m \u00d4ng \u0110\u1ed3"
    ],
    "name:vie_x_preferred":[
        "\u00d4ng Do"
    ],
    "name:vie_x_variant":[
        "H\u00e0ng V\u1ecbnh"
    ],
    "wof:name":"Ong Do",
    "wof:placetype":"locality"
},
  "geometry": {"coordinates":[105.00874,8.82432],"type":"Point"}
}