{
  "type": "Feature",
  "properties": {
    "gn:admin1_code":"91.0",
    "gn:asciiname":"Thuan Hanh",
    "gn:country_code":"VN",
    "gn:dem":775,
    "gn:feature_class":"P",
    "gn:feature_code":"PPL",
    "gn:name":"Thu\u1eadn H\u1ea1nh",
    "gn:population":0,
    "gn:timezone":"Asia/Ho_Chi_Minh",
    "iso:country":"VN",
    "name:vie_x_preferred":[
        "Thu\u1eadn H\u1ea1nh"
    ],
    "wof:name":"Thuan Hanh",
    "wof:placetype":"locality"
},
  "geometry": {"coordinates":[107.58078999999999,12.4121],"type":"Point"}
}