{
  "type": "Feature",
  "properties": {
    "gn:admin1_code":"90.0",
    "gn:asciiname":"Phan Kong Su",
    "gn:country_code":"VN",
    "gn:dem":1661,
    "gn:feature_class":"P",
    "gn:feature_code":"PPL",
    "gn:name":"Phan K\u01a1ng Su",
    "gn:population":0,
    "gn:timezone":"Asia/Ho_Chi_Minh",
    "iso:country":"VN",
    "wof:name":"Phan Kong Su",
    "wof:placetype":"locality"
},
  "geometry": {"coordinates":[103.61667,22.65],"type":"Point"}
}