{
  "type": "Feature",
  "properties": {
    "gn:admin1_code":"32.0",
    "gn:asciiname":"Huoi Duong",
    "gn:cc2":"VN",
    "gn:country_code":"VN",
    "gn:dem":309,
    "gn:feature_class":"P",
    "gn:feature_code":"PPL",
    "gn:name":"Hu\u00f4i Duong",
    "gn:population":0,
    "gn:timezone":"Asia/Ho_Chi_Minh",
    "iso:country":"VN",
    "name:und_x_variant":[
        "Houei Duong",
        "Hu\u00f4i Duong"
    ],
    "wof:name":"Huoi Duong",
    "wof:placetype":"locality"
},
  "geometry": {"coordinates":[104.15000000000001,21.43333],"type":"Point"}
}