{
  "type": "Feature",
  "properties": {
    "gn:admin1_code":"83.0",
    "gn:asciiname":"Yen Lap",
    "gn:country_code":"VN",
    "gn:dem":70,
    "gn:feature_class":"P",
    "gn:feature_code":"PPLA2",
    "gn:name":"Y\u00ean L\u1eadp",
    "gn:population":0,
    "gn:timezone":"Asia/Ho_Chi_Minh",
    "iso:country":"VN",
    "name:vie_x_preferred":[
        "Huy\u1ec7n Y\u00ean L\u1eadp"
    ],
    "name:vie_x_variant":[
        "Y\u00ean L\u1eadp"
    ],
    "wof:name":"Yen Lap",
    "wof:placetype":"locality"
},
  "geometry": {"coordinates":[105.05738999999998,21.34705],"type":"Point"}
}