{
  "type": "Feature",
  "properties": {
    "gn:admin1_code":"1.0",
    "gn:asciiname":"Binh Duc Bon",
    "gn:country_code":"VN",
    "gn:dem":5,
    "gn:feature_class":"P",
    "gn:feature_code":"PPL",
    "gn:name":"B\u00ecnh \u0110\u1ee9c B\u1ed1n",
    "gn:population":0,
    "gn:timezone":"Asia/Ho_Chi_Minh",
    "iso:country":"VN",
    "name:vie_x_preferred":[
        "B\u00ecnh \u0110\u1ee9c B\u1ed1n"
    ],
    "name:vie_x_variant":[
        "B\u00ecnh \u0110\u1ee9c 4"
    ],
    "wof:name":"Binh Duc Bon",
    "wof:placetype":"locality"
},
  "geometry": {"coordinates":[105.40993,10.41757],"type":"Point"}
}