{
  "type": "Feature",
  "properties": {
    "gn:admin1_code":"52.0",
    "gn:asciiname":"Hai Khau",
    "gn:country_code":"VN",
    "gn:dem":7,
    "gn:feature_class":"P",
    "gn:feature_code":"PPL",
    "gn:name":"H\u1ea3i Kh\u1ea9u",
    "gn:population":0,
    "gn:timezone":"Asia/Ho_Chi_Minh",
    "iso:country":"VN",
    "wof:name":"Hai Khau",
    "wof:placetype":"locality"
},
  "geometry": {"coordinates":[106.34999999999999,18.11667000000001],"type":"Point"}
}