{
  "type": "Feature",
  "properties": {
    "gn:admin1_code":"64.0",
    "gn:asciiname":"Binh An",
    "gn:country_code":"VN",
    "gn:dem":9,
    "gn:feature_class":"P",
    "gn:feature_code":"PPL",
    "gn:name":"B\u00ecnh An",
    "gn:population":0,
    "gn:timezone":"Asia/Ho_Chi_Minh",
    "iso:country":"VN",
    "name:und_x_variant":[
        "Linh An",
        "Th\u00f4n Linh An"
    ],
    "name:vie_x_preferred":[
        "B\u00ecnh An"
    ],
    "wof:name":"Binh An",
    "wof:placetype":"locality"
},
  "geometry": {"coordinates":[107.22775,16.81292],"type":"Point"}
}