{
  "type": "Feature",
  "properties": {
    "gn:admin1_code":"39.0",
    "gn:asciiname":"Ban Xam Kha",
    "gn:country_code":"VN",
    "gn:dem":295,
    "gn:feature_class":"P",
    "gn:feature_code":"PPL",
    "gn:name":"B\u1ea3n Xam Kha",
    "gn:population":0,
    "gn:timezone":"Asia/Ho_Chi_Minh",
    "iso:country":"VN",
    "wof:name":"Ban Xam Kha",
    "wof:placetype":"locality"
},
  "geometry": {"coordinates":[106.65262,22.07169],"type":"Point"}
}