{
  "type": "Feature",
  "properties": {
    "gn:admin1_code":"32.0",
    "gn:asciiname":"Phieng Lap",
    "gn:country_code":"VN",
    "gn:dem":572,
    "gn:feature_class":"P",
    "gn:feature_code":"PPL",
    "gn:name":"Phi\u00eang L\u1eb7p",
    "gn:population":0,
    "gn:timezone":"Asia/Ho_Chi_Minh",
    "iso:country":"VN",
    "name:und_x_variant":[
        "Phiang Lap",
        "Phi\u00eang L\u1eadp"
    ],
    "name:vie_x_preferred":[
        "Phi\u00eang L\u1eb7p"
    ],
    "wof:name":"Phieng Lap",
    "wof:placetype":"locality"
},
  "geometry": {"coordinates":[104.0814,21.16435],"type":"Point"}
}