{
  "type": "Feature",
  "properties": {
    "gn:admin1_code":"68.0",
    "gn:asciiname":"Na Len",
    "gn:country_code":"VN",
    "gn:dem":75,
    "gn:feature_class":"P",
    "gn:feature_code":"PPL",
    "gn:name":"N\u00e0 Len",
    "gn:population":0,
    "gn:timezone":"Asia/Ho_Chi_Minh",
    "iso:country":"VN",
    "name:vie_x_preferred":[
        "N\u00e0 Len"
    ],
    "wof:name":"Na Len",
    "wof:placetype":"locality"
},
  "geometry": {"coordinates":[105.40526,22.31059],"type":"Point"}
}