{
  "type": "Feature",
  "properties": {
    "gn:admin1_code":"71.0",
    "gn:asciiname":"Dong Loan",
    "gn:country_code":"VN",
    "gn:dem":5,
    "gn:feature_class":"P",
    "gn:feature_code":"PPL",
    "gn:name":"\u0110\u00f4ng Loan",
    "gn:population":0,
    "gn:timezone":"Asia/Ho_Chi_Minh",
    "iso:country":"VN",
    "wof:name":"Dong Loan",
    "wof:placetype":"locality"
},
  "geometry": {"coordinates":[106.26667,21.21667],"type":"Point"}
}