{
  "type": "Feature",
  "properties": {
    "gn:admin1_code":"52.0",
    "gn:asciiname":"Bac Doai",
    "gn:country_code":"VN",
    "gn:dem":11,
    "gn:feature_class":"P",
    "gn:feature_code":"PPL",
    "gn:name":"B\u1eafc \u0110o\u00e0i",
    "gn:population":0,
    "gn:timezone":"Asia/Ho_Chi_Minh",
    "iso:country":"VN",
    "name:vie_x_preferred":[
        "B\u1eafc \u0110o\u00e0i"
    ],
    "wof:name":"Bac Doai",
    "wof:placetype":"locality"
},
  "geometry": {"coordinates":[105.74677,18.49793],"type":"Point"}
}