{
  "type": "Feature",
  "properties": {
    "gn:admin1_code":"24.0",
    "gn:asciiname":"Tan Chanh",
    "gn:country_code":"VN",
    "gn:dem":5,
    "gn:feature_class":"P",
    "gn:feature_code":"PPL",
    "gn:name":"T\u00e2n Ch\u00e1nh",
    "gn:population":0,
    "gn:timezone":"Asia/Ho_Chi_Minh",
    "iso:country":"VN",
    "name:und_x_variant":[
        "\u1ea4p T\u00e2n Ch\u00e1nh"
    ],
    "name:vie_x_preferred":[
        "T\u00e2n Ch\u00e1nh"
    ],
    "wof:name":"Tan Chanh",
    "wof:placetype":"locality"
},
  "geometry": {"coordinates":[105.98052,10.57635],"type":"Point"}
}