{
  "type": "Feature",
  "properties": {
    "gn:admin1_code":"32.0",
    "gn:asciiname":"Ma Luoi",
    "gn:country_code":"VN",
    "gn:dem":336,
    "gn:feature_class":"P",
    "gn:feature_code":"PPL",
    "gn:name":"M\u00e1 L\u01b0\u01a1i",
    "gn:population":0,
    "gn:timezone":"Asia/Ho_Chi_Minh",
    "iso:country":"VN",
    "name:vie_x_preferred":[
        "M\u00e1 L\u01b0\u01a1i"
    ],
    "wof:name":"Ma Luoi",
    "wof:placetype":"locality"
},
  "geometry": {"coordinates":[103.77876999999999,21.02589],"type":"Point"}
}