{
  "type": "Feature",
  "properties": {
    "gn:admin1_code":"79.0",
    "gn:asciiname":"Mac Binh",
    "gn:country_code":"VN",
    "gn:dem":4,
    "gn:feature_class":"P",
    "gn:feature_code":"PPL",
    "gn:name":"M\u1eb7c B\u00ecnh",
    "gn:population":0,
    "gn:timezone":"Asia/Ho_Chi_Minh",
    "iso:country":"VN",
    "name:und_x_variant":[
        "M\u1eb7c C\u1ea7u"
    ],
    "name:vie_x_preferred":[
        "M\u1eb7c B\u00ecnh"
    ],
    "wof:name":"Mac Binh",
    "wof:placetype":"locality"
},
  "geometry": {"coordinates":[106.28707,21.00718],"type":"Point"}
}