{
  "type": "Feature",
  "properties": {
    "gn:admin1_code":"52.0",
    "gn:asciiname":"Xom Mot",
    "gn:country_code":"VN",
    "gn:dem":6,
    "gn:feature_class":"P",
    "gn:feature_code":"PPL",
    "gn:name":"X\u00f3m M\u1ed9t",
    "gn:population":0,
    "gn:timezone":"Asia/Ho_Chi_Minh",
    "iso:country":"VN",
    "name:vie_x_preferred":[
        "X\u00f3m M\u1ed9t"
    ],
    "name:vie_x_variant":[
        "X\u00f3m 1"
    ],
    "wof:name":"Xom Mot",
    "wof:placetype":"locality"
},
  "geometry": {"coordinates":[105.9404,18.34788],"type":"Point"}
}