{
  "type": "Feature",
  "properties": {
    "gn:admin1_code":"1.0",
    "gn:asciiname":"Vinh Hung",
    "gn:country_code":"VN",
    "gn:dem":8,
    "gn:feature_class":"P",
    "gn:feature_code":"PPL",
    "gn:name":"V\u0129nh H\u01b0ng",
    "gn:population":0,
    "gn:timezone":"Asia/Ho_Chi_Minh",
    "iso:country":"VN",
    "name:und_x_variant":[
        "\u1ea4p V\u0129nh H\u01b0ng"
    ],
    "name:vie_x_preferred":[
        "V\u0129nh H\u01b0ng"
    ],
    "wof:name":"Vinh Hung",
    "wof:placetype":"locality"
},
  "geometry": {"coordinates":[105.22948999999998,10.58671],"type":"Point"}
}