{
  "type": "Feature",
  "properties": {
    "gn:admin1_code":"50.0",
    "gn:asciiname":"Yen Binh",
    "gn:country_code":"VN",
    "gn:dem":112,
    "gn:feature_class":"P",
    "gn:feature_code":"PPLA2",
    "gn:name":"Y\u00ean B\u00ecnh",
    "gn:population":0,
    "gn:timezone":"Asia/Ho_Chi_Minh",
    "iso:country":"VN",
    "name:vie_x_preferred":[
        "Y\u00ean B\u00ecnh"
    ],
    "wof:name":"Yen Binh",
    "wof:placetype":"locality"
},
  "geometry": {"coordinates":[104.57949000000001,22.40989],"type":"Point"}
}