{
  "type": "Feature",
  "properties": {
    "gn:admin1_code":"53.0",
    "gn:asciiname":"Ban Am",
    "gn:country_code":"VN",
    "gn:dem":165,
    "gn:feature_class":"P",
    "gn:feature_code":"PPL",
    "gn:name":"B\u1ea3n \u1ea4m",
    "gn:population":0,
    "gn:timezone":"Asia/Ho_Chi_Minh",
    "iso:country":"VN",
    "name:und_x_variant":[
        "B\u1ea3n Om"
    ],
    "name:vie_x_preferred":[
        "B\u1ea3n \u1ea4m"
    ],
    "wof:name":"Ban Am",
    "wof:placetype":"locality"
},
  "geometry": {"coordinates":[104.85598,21.06973],"type":"Point"}
}