{
  "type": "Feature",
  "properties": {
    "gn:admin1_code":"74.0",
    "gn:asciiname":"Huong Vinh",
    "gn:country_code":"VN",
    "gn:dem":8,
    "gn:feature_class":"P",
    "gn:feature_code":"PPL",
    "gn:name":"H\u01b0\u01a1ng Vinh",
    "gn:population":0,
    "gn:timezone":"Asia/Ho_Chi_Minh",
    "iso:country":"VN",
    "name:vie_x_preferred":[
        "H\u01b0\u01a1ng Vinh"
    ],
    "wof:name":"Huong Vinh",
    "wof:placetype":"locality"
},
  "geometry": {"coordinates":[106.17587,21.06001],"type":"Point"}
}