{
  "type": "Feature",
  "properties": {
    "gn:admin1_code":"52.0",
    "gn:asciiname":"Tay Nguyen",
    "gn:country_code":"VN",
    "gn:dem":4,
    "gn:feature_class":"P",
    "gn:feature_code":"PPL",
    "gn:name":"T\u00e2y Nguy\u00ean",
    "gn:population":0,
    "gn:timezone":"Asia/Ho_Chi_Minh",
    "iso:country":"VN",
    "name:vie_x_preferred":[
        "T\u00e2y Nguy\u00ean"
    ],
    "wof:name":"Tay Nguyen",
    "wof:placetype":"locality"
},
  "geometry": {"coordinates":[106.02418,18.29398],"type":"Point"}
}