{
  "type": "Feature",
  "properties": {
    "gn:admin1_code":"81.0",
    "gn:asciiname":"Cuu Thuy",
    "gn:country_code":"VN",
    "gn:dem":6,
    "gn:feature_class":"P",
    "gn:feature_code":"PPL",
    "gn:name":"C\u1ef1u Th\u1ee5y",
    "gn:population":0,
    "gn:timezone":"Asia/Ho_Chi_Minh",
    "iso:country":"VN",
    "name:vie_x_preferred":[
        "C\u1ef1u Th\u1ee5y"
    ],
    "wof:name":"Cuu Thuy",
    "wof:placetype":"locality"
},
  "geometry": {"coordinates":[106.14085,20.79154],"type":"Point"}
}