{
  "type": "Feature",
  "properties": {
    "gn:admin1_code":"38.0",
    "gn:asciiname":"Am Ha (2)",
    "gn:country_code":"VN",
    "gn:dem":78,
    "gn:feature_class":"P",
    "gn:feature_code":"PPL",
    "gn:name":"\u1ea4m H\u1ea1 (2)",
    "gn:population":0,
    "gn:timezone":"Asia/Ho_Chi_Minh",
    "iso:country":"VN",
    "wof:name":"Am Ha (2)",
    "wof:placetype":"locality"
},
  "geometry": {"coordinates":[105.03333000000001,21.56667],"type":"Point"}
}