{
  "type": "Feature",
  "properties": {
    "gn:admin1_code":"39.0",
    "gn:asciiname":"Bac Ban",
    "gn:country_code":"VN",
    "gn:dem":298,
    "gn:feature_class":"P",
    "gn:feature_code":"PPL",
    "gn:name":"B\u00e1c Ban",
    "gn:population":0,
    "gn:timezone":"Asia/Ho_Chi_Minh",
    "iso:country":"VN",
    "wof:name":"Bac Ban",
    "wof:placetype":"locality"
},
  "geometry": {"coordinates":[106.91667,21.75],"type":"Point"}
}