{
  "type": "Feature",
  "properties": {
    "gn:admin1_code":"47.0",
    "gn:asciiname":"Kolova Koglai",
    "gn:country_code":"VN",
    "gn:dem":410,
    "gn:feature_class":"P",
    "gn:feature_code":"PPL",
    "gn:name":"Kolova Kogla\u00ef",
    "gn:population":0,
    "gn:timezone":"Asia/Ho_Chi_Minh",
    "iso:country":"VN",
    "wof:name":"Kolova Koglai",
    "wof:placetype":"locality"
},
  "geometry": {"coordinates":[108.51667,11.45],"type":"Point"}
}