{
  "type": "Feature",
  "properties": {
    "gn:admin1_code":"32.0",
    "gn:asciiname":"Ban Keo Bo A",
    "gn:country_code":"VN",
    "gn:dem":978,
    "gn:feature_class":"P",
    "gn:feature_code":"PPL",
    "gn:name":"B\u1ea3n K\u00e9o B\u00f3 A",
    "gn:population":0,
    "gn:timezone":"Asia/Ho_Chi_Minh",
    "iso:country":"VN",
    "name:vie_x_preferred":[
        "B\u1ea3n K\u00e9o B\u00f3 A"
    ],
    "wof:name":"Ban Keo Bo A",
    "wof:placetype":"locality"
},
  "geometry": {"coordinates":[104.22335,21.19348],"type":"Point"}
}