{
  "type": "Feature",
  "properties": {
    "gn:admin1_code":"32.0",
    "gn:asciiname":"Ban Suoi Let",
    "gn:country_code":"VN",
    "gn:dem":553,
    "gn:feature_class":"P",
    "gn:feature_code":"PPL",
    "gn:name":"B\u1ea3n Su\u1ed1i L\u1eb9t",
    "gn:population":0,
    "gn:timezone":"Asia/Ho_Chi_Minh",
    "iso:country":"VN",
    "name:vie_x_preferred":[
        "B\u1ea3n Su\u1ed1i L\u1eb9t"
    ],
    "wof:name":"Ban Suoi Let",
    "wof:placetype":"locality"
},
  "geometry": {"coordinates":[104.56931,21.11767],"type":"Point"}
}