{
  "type": "Feature",
  "properties": {
    "gn:admin1_code":"90.0",
    "gn:asciiname":"Ta Ho Ti",
    "gn:country_code":"VN",
    "gn:dem":1811,
    "gn:feature_class":"P",
    "gn:feature_code":"PPL",
    "gn:name":"Ta Ho Ti",
    "gn:population":0,
    "gn:timezone":"Asia/Ho_Chi_Minh",
    "iso:country":"VN",
    "wof:name":"Ta Ho Ti",
    "wof:placetype":"locality"
},
  "geometry": {"coordinates":[103.65000000000001,22.65],"type":"Point"}
}