{
  "type": "Feature",
  "properties": {
    "gn:admin1_code":"44.0",
    "gn:asciiname":"Thanh Sam",
    "gn:country_code":"VN",
    "gn:dem":7,
    "gn:feature_class":"P",
    "gn:feature_code":"PPL",
    "gn:name":"Thanh Sam",
    "gn:population":0,
    "gn:timezone":"Asia/Ho_Chi_Minh",
    "iso:country":"VN",
    "name:und_x_variant":[
        "Sam Thanh",
        "Thanh Sam"
    ],
    "wof:name":"Thanh Sam",
    "wof:placetype":"locality"
},
  "geometry": {"coordinates":[105.76667,20.76667],"type":"Point"}
}