{
  "type": "Feature",
  "properties": {
    "gn:admin1_code":"32.0",
    "gn:asciiname":"Ban Nguoc Ngoi",
    "gn:cc2":"VN",
    "gn:country_code":"VN",
    "gn:dem":1262,
    "gn:feature_class":"P",
    "gn:feature_code":"PPL",
    "gn:name":"B\u1ea3n Ng\u01b0\u1ee3c Ng\u01a1i",
    "gn:population":0,
    "gn:timezone":"Asia/Ho_Chi_Minh",
    "iso:country":"VN",
    "name:und_x_variant":[
        "Ban Nuoc Ngo",
        "B\u1ea3n Ng\u01b0\u1ee3c Ng\u01a1i"
    ],
    "wof:name":"Ban Nguoc Ngoi",
    "wof:placetype":"locality"
},
  "geometry": {"coordinates":[104.11667,21.05],"type":"Point"}
}