{
  "type": "Feature",
  "properties": {
    "gn:admin1_code":"63.0",
    "gn:asciiname":"Tay Tra",
    "gn:country_code":"VN",
    "gn:dem":222,
    "gn:feature_class":"P",
    "gn:feature_code":"PPLA2",
    "gn:name":"T\u00e2y Tr\u00e0",
    "gn:population":0,
    "gn:timezone":"Asia/Ho_Chi_Minh",
    "iso:country":"VN",
    "name:vie_x_preferred":[
        "T\u00e2y Tr\u00e0"
    ],
    "wof:name":"Tay Tra",
    "wof:placetype":"locality"
},
  "geometry": {"coordinates":[108.35997999999999,15.16948],"type":"Point"}
}