{
  "type": "Feature",
  "properties": {
    "gn:admin1_code":"40.0",
    "gn:asciiname":"Xa Thien Tan",
    "gn:country_code":"VN",
    "gn:dem":11,
    "gn:feature_class":"P",
    "gn:feature_code":"PPL",
    "gn:name":"X\u00e3 Thi\u00ean T\u00e2n",
    "gn:population":0,
    "gn:timezone":"Asia/Ho_Chi_Minh",
    "iso:country":"VN",
    "name:und_x_variant":[
        "Thi\u1ec7n T\u00e2n",
        "X\u00e3 Thi\u00ean T\u00e2n"
    ],
    "wof:name":"Xa Thien Tan",
    "wof:placetype":"locality"
},
  "geometry": {"coordinates":[106.90000000000001,11.01667],"type":"Point"}
}