{
  "type": "Feature",
  "properties": {
    "gn:admin1_code":"87.0",
    "gn:asciiname":"Phung Quoi",
    "gn:country_code":"VN",
    "gn:dem":2,
    "gn:feature_class":"P",
    "gn:feature_code":"PPL",
    "gn:name":"Ph\u1ee5ng Qu\u1edbi",
    "gn:population":0,
    "gn:timezone":"Asia/Ho_Chi_Minh",
    "iso:country":"VN",
    "name:vie_x_preferred":[
        "Ph\u1ee5ng Qu\u1edbi"
    ],
    "wof:name":"Phung Quoi",
    "wof:placetype":"locality"
},
  "geometry": {"coordinates":[105.33569,10.16058],"type":"Point"}
}