{
  "type": "Feature",
  "properties": {
    "gn:admin1_code":"92.0",
    "gn:asciiname":"Na O",
    "gn:country_code":"VN",
    "gn:dem":563,
    "gn:feature_class":"P",
    "gn:feature_code":"PPL",
    "gn:name":"Na \u1ed0",
    "gn:population":0,
    "gn:timezone":"Asia/Ho_Chi_Minh",
    "iso:country":"VN",
    "wof:name":"Na O",
    "wof:placetype":"locality"
},
  "geometry": {"coordinates":[103.08869,21.14049],"type":"Point"}
}