{
  "type": "Feature",
  "properties": {
    "gn:admin1_code":"55.0",
    "gn:asciiname":"Lang Xop",
    "gn:country_code":"VN",
    "gn:dem":251,
    "gn:feature_class":"P",
    "gn:feature_code":"PPL",
    "gn:name":"L\u00e0ng X\u1ed9p",
    "gn:population":0,
    "gn:timezone":"Asia/Ho_Chi_Minh",
    "iso:country":"VN",
    "name:vie_x_preferred":[
        "L\u00e0ng X\u1ed9p"
    ],
    "wof:name":"Lang Xop",
    "wof:placetype":"locality"
},
  "geometry": {"coordinates":[107.52003999999999,14.39056],"type":"Point"}
}