{
  "type": "Feature",
  "properties": {
    "gn:admin1_code":"2.0",
    "gn:asciiname":"Luong Khouong",
    "gn:country_code":"VN",
    "gn:dem":457,
    "gn:feature_class":"P",
    "gn:feature_code":"PPL",
    "gn:name":"Luong Khouong",
    "gn:population":0,
    "gn:timezone":"Asia/Ho_Chi_Minh",
    "iso:country":"VN",
    "wof:name":"Luong Khouong",
    "wof:placetype":"locality"
},
  "geometry": {"coordinates":[105.68333,22.05],"type":"Point"}
}