{
  "type": "Feature",
  "properties": {
    "gn:admin1_code":"71.0",
    "gn:asciiname":"Xom Cam",
    "gn:country_code":"VN",
    "gn:dem":25,
    "gn:feature_class":"P",
    "gn:feature_code":"PPL",
    "gn:name":"X\u00f3m C\u00e1m",
    "gn:population":0,
    "gn:timezone":"Asia/Ho_Chi_Minh",
    "iso:country":"VN",
    "name:vie_x_preferred":[
        "X\u00f3m C\u00e1m"
    ],
    "wof:name":"Xom Cam",
    "wof:placetype":"locality"
},
  "geometry": {"coordinates":[106.00393,21.34341],"type":"Point"}
}