{
  "type": "Feature",
  "properties": {
    "gn:admin1_code":"1.0",
    "gn:asciiname":"Cai Tau Thuong",
    "gn:cc2":"VN",
    "gn:country_code":"VN",
    "gn:dem":8,
    "gn:feature_class":"P",
    "gn:feature_code":"PPL",
    "gn:name":"C\u00e1i T\u1ea7u Th\u01b0\u1ee3ng",
    "gn:population":0,
    "gn:timezone":"Asia/Ho_Chi_Minh",
    "iso:country":"VN",
    "name:und_x_variant":[
        "Hoi An",
        "C\u00e1i T\u1ea7u Th\u01b0\u1ee3ng"
    ],
    "wof:name":"Cai Tau Thuong",
    "wof:placetype":"locality"
},
  "geometry": {"coordinates":[105.55,10.43333],"type":"Point"}
}