{
  "type": "Feature",
  "properties": {
    "gn:admin1_code":"30.0",
    "gn:asciiname":"Ma Lao Coc",
    "gn:country_code":"VN",
    "gn:dem":39,
    "gn:feature_class":"P",
    "gn:feature_code":"PPL",
    "gn:name":"Ma Lao Coc",
    "gn:population":0,
    "gn:timezone":"Asia/Ho_Chi_Minh",
    "iso:country":"VN",
    "wof:name":"Ma Lao Coc",
    "wof:placetype":"locality"
},
  "geometry": {"coordinates":[107.63333,21.38333],"type":"Point"}
}