{
  "type": "Feature",
  "properties": {
    "gn:admin1_code":"62.0",
    "gn:asciiname":"Cu Nam",
    "gn:country_code":"VN",
    "gn:dem":10,
    "gn:feature_class":"P",
    "gn:feature_code":"PPL",
    "gn:name":"C\u1eeb Nam",
    "gn:population":0,
    "gn:timezone":"Asia/Ho_Chi_Minh",
    "iso:country":"VN",
    "name:und_x_variant":[
        "Dun Nam",
        "C\u1eeb Nam"
    ],
    "wof:name":"Cu Nam",
    "wof:placetype":"locality"
},
  "geometry": {"coordinates":[106.41667,17.63332999999999],"type":"Point"}
}