{
  "type": "Feature",
  "properties": {
    "gn:admin1_code":"46.0",
    "gn:asciiname":"Quang Hien",
    "gn:country_code":"VN",
    "gn:dem":29,
    "gn:feature_class":"P",
    "gn:feature_code":"PPL",
    "gn:name":"Quang Hi\u1ec3n",
    "gn:population":0,
    "gn:timezone":"Asia/Ho_Chi_Minh",
    "iso:country":"VN",
    "name:und_x_variant":[
        "Quan Hien",
        "Quang Hi\u1ec3n"
    ],
    "wof:name":"Quang Hien",
    "wof:placetype":"locality"
},
  "geometry": {"coordinates":[109.05,13.68333],"type":"Point"}
}