{
  "type": "Feature",
  "properties": {
    "gn:admin1_code":"17.0",
    "gn:asciiname":"Na Ri",
    "gn:country_code":"VN",
    "gn:dem":395,
    "gn:feature_class":"P",
    "gn:feature_code":"PPL",
    "gn:name":"Na Ri",
    "gn:population":0,
    "gn:timezone":"Asia/Ho_Chi_Minh",
    "iso:country":"VN",
    "wof:name":"Na Ri",
    "wof:placetype":"locality"
},
  "geometry": {"coordinates":[105.41667,22.76667],"type":"Point"}
}