{
  "type": "Feature",
  "properties": {
    "gn:admin1_code":"83.0",
    "gn:asciiname":"Xom Mo",
    "gn:country_code":"VN",
    "gn:dem":77,
    "gn:feature_class":"P",
    "gn:feature_code":"PPL",
    "gn:name":"X\u00f3m M\u01a1",
    "gn:population":0,
    "gn:timezone":"Asia/Ho_Chi_Minh",
    "iso:country":"VN",
    "name:und_x_variant":[
        "X\u00f3m Mu"
    ],
    "name:vie_x_preferred":[
        "X\u00f3m M\u01a1"
    ],
    "wof:name":"Xom Mo",
    "wof:placetype":"locality"
},
  "geometry": {"coordinates":[105.05388000000001,21.36553],"type":"Point"}
}