{
  "type": "Feature",
  "properties": {
    "gn:admin1_code":"88.0",
    "gn:asciiname":"Doi Muoi Sau",
    "gn:country_code":"VN",
    "gn:dem":581,
    "gn:feature_class":"P",
    "gn:feature_code":"PPL",
    "gn:name":"\u0110\u1ed9i M\u01b0\u1eddi S\u00e1u",
    "gn:population":0,
    "gn:timezone":"Asia/Ho_Chi_Minh",
    "iso:country":"VN",
    "name:vie_x_preferred":[
        "\u0110\u1ed9i M\u01b0\u1eddi S\u00e1u"
    ],
    "name:vie_x_variant":[
        "\u0110\u1ed9i 16"
    ],
    "wof:name":"Doi Muoi Sau",
    "wof:placetype":"locality"
},
  "geometry": {"coordinates":[108.18359,12.70086],"type":"Point"}
}