{
  "type": "Feature",
  "properties": {
    "gn:admin1_code":"66.0",
    "gn:asciiname":"Thon An Thon",
    "gn:country_code":"VN",
    "gn:dem":11,
    "gn:feature_class":"P",
    "gn:feature_code":"PPL",
    "gn:name":"Th\u00f4n An Th\u00f4n",
    "gn:population":0,
    "gn:timezone":"Asia/Ho_Chi_Minh",
    "iso:country":"VN",
    "name:und_x_variant":[
        "T\u00e2n L\u1ed9c",
        "Th\u00f4n An Th\u00f4n"
    ],
    "wof:name":"Thon An Thon",
    "wof:placetype":"locality"
},
  "geometry": {"coordinates":[107.33333,16.56667],"type":"Point"}
}