{
  "type": "Feature",
  "properties": {
    "gn:admin1_code":"44.0",
    "gn:asciiname":"Thang Tri",
    "gn:country_code":"VN",
    "gn:dem":22,
    "gn:feature_class":"P",
    "gn:feature_code":"PPL",
    "gn:name":"Th\u1eafng Tr\u00ed",
    "gn:population":0,
    "gn:timezone":"Asia/Ho_Chi_Minh",
    "iso:country":"VN",
    "name:und_x_variant":[
        "Th\u0103ng Tri"
    ],
    "name:vie_x_preferred":[
        "Th\u1eafng Tr\u00ed"
    ],
    "wof:name":"Thang Tri",
    "wof:placetype":"locality"
},
  "geometry": {"coordinates":[105.74972,21.26116],"type":"Point"}
}