{
  "type": "Feature",
  "properties": {
    "gn:admin1_code":"68.0",
    "gn:asciiname":"Thuong Chinh",
    "gn:country_code":"VN",
    "gn:dem":71,
    "gn:feature_class":"P",
    "gn:feature_code":"PPL",
    "gn:name":"Th\u01b0\u1ee3ng Ch\u00ednh",
    "gn:population":0,
    "gn:timezone":"Asia/Ho_Chi_Minh",
    "iso:country":"VN",
    "name:vie_x_preferred":[
        "Th\u01b0\u1ee3ng Ch\u00ednh"
    ],
    "wof:name":"Thuong Chinh",
    "wof:placetype":"locality"
},
  "geometry": {"coordinates":[105.19743,22.25571],"type":"Point"}
}