{
  "type": "Feature",
  "properties": {
    "gn:admin1_code":"90.0",
    "gn:asciiname":"Hai Khe",
    "gn:country_code":"VN",
    "gn:dem":99,
    "gn:feature_class":"P",
    "gn:feature_code":"PPL",
    "gn:name":"H\u1ea3i Kh\u00ea",
    "gn:population":0,
    "gn:timezone":"Asia/Ho_Chi_Minh",
    "iso:country":"VN",
    "name:vie_x_preferred":[
        "H\u1ea3i Kh\u00ea"
    ],
    "wof:name":"Hai Khe",
    "wof:placetype":"locality"
},
  "geometry": {"coordinates":[103.85903999999999,22.58132],"type":"Point"}
}