{
  "type": "Feature",
  "properties": {
    "gn:admin1_code":"46.0",
    "gn:asciiname":"Duong Lieu",
    "gn:country_code":"VN",
    "gn:dem":20,
    "gn:feature_class":"P",
    "gn:feature_code":"PPL",
    "gn:name":"D\u01b0\u01a1ng Li\u1ec5u",
    "gn:population":0,
    "gn:timezone":"Asia/Ho_Chi_Minh",
    "iso:country":"VN",
    "name:vie_x_preferred":[
        "D\u01b0\u01a1ng Li\u1ec5u"
    ],
    "wof:name":"Duong Lieu",
    "wof:placetype":"locality"
},
  "geometry": {"coordinates":[109.07853,14.28842],"type":"Point"}
}