{
  "type": "Feature",
  "properties": {
    "gn:admin1_code":"89.0",
    "gn:asciiname":"Ban Bang Mai",
    "gn:country_code":"VN",
    "gn:dem":462,
    "gn:feature_class":"P",
    "gn:feature_code":"PPL",
    "gn:name":"B\u1ea3n B\u1eb1ng Mai",
    "gn:population":0,
    "gn:timezone":"Asia/Ho_Chi_Minh",
    "iso:country":"VN",
    "name:vie_x_preferred":[
        "B\u1ea3n B\u1eb1ng Mai"
    ],
    "wof:name":"Ban Bang Mai",
    "wof:placetype":"locality"
},
  "geometry": {"coordinates":[103.72293000000001,22.08828],"type":"Point"}
}