{
  "type": "Feature",
  "properties": {
    "gn:admin1_code":"54.0",
    "gn:asciiname":"Xom Cau Hin",
    "gn:country_code":"VN",
    "gn:dem":3,
    "gn:feature_class":"P",
    "gn:feature_code":"PPL",
    "gn:name":"X\u00f3m C\u1ea7u Hin",
    "gn:population":0,
    "gn:timezone":"Asia/Ho_Chi_Minh",
    "iso:country":"VN",
    "name:und_x_variant":[
        "Cau Hin",
        "Cao Hin",
        "X\u00f3m C\u1ea7u Hin"
    ],
    "wof:name":"Xom Cau Hin",
    "wof:placetype":"locality"
},
  "geometry": {"coordinates":[109.18333,12.11667],"type":"Point"}
}