{
  "type": "Feature",
  "properties": {
    "gn:admin1_code":"58.0",
    "gn:asciiname":"Thuan Ly",
    "gn:country_code":"VN",
    "gn:dem":21,
    "gn:feature_class":"P",
    "gn:feature_code":"PPL",
    "gn:name":"Thu\u1eadn L\u00fd",
    "gn:population":0,
    "gn:timezone":"Asia/Ho_Chi_Minh",
    "iso:country":"VN",
    "name:vie_x_preferred":[
        "Thu\u1eadn L\u00fd"
    ],
    "wof:name":"Thuan Ly",
    "wof:placetype":"locality"
},
  "geometry": {"coordinates":[105.28064999999999,18.84513],"type":"Point"}
}