{
  "type": "Feature",
  "properties": {
    "gn:admin1_code":"32.0",
    "gn:asciiname":"Ban Suoi Giang",
    "gn:country_code":"VN",
    "gn:dem":1104,
    "gn:feature_class":"P",
    "gn:feature_code":"PPL",
    "gn:name":"B\u1ea3n Su\u1ed1i Giang",
    "gn:population":0,
    "gn:timezone":"Asia/Ho_Chi_Minh",
    "iso:country":"VN",
    "wof:name":"Ban Suoi Giang",
    "wof:placetype":"locality"
},
  "geometry": {"coordinates":[104.93333,20.75],"type":"Point"}
}