{
  "type": "Feature",
  "properties": {
    "gn:admin1_code":"23.0",
    "gn:asciiname":"Tien Yen",
    "gn:country_code":"VN",
    "gn:dem":814,
    "gn:feature_class":"P",
    "gn:feature_code":"PPL",
    "gn:name":"Ti\u00ean Y\u00ean",
    "gn:population":0,
    "gn:timezone":"Asia/Ho_Chi_Minh",
    "iso:country":"VN",
    "name:vie_x_preferred":[
        "Ti\u00ean Y\u00ean"
    ],
    "wof:name":"Tien Yen",
    "wof:placetype":"locality"
},
  "geometry": {"coordinates":[107.89158,11.62916],"type":"Point"}
}