{
  "type": "Feature",
  "properties": {
    "gn:admin1_code":"32.0",
    "gn:asciiname":"Ban Pa Cha",
    "gn:country_code":"VN",
    "gn:dem":906,
    "gn:feature_class":"P",
    "gn:feature_code":"PPL",
    "gn:name":"B\u1ea3n P\u00e1 Ch\u1ea3",
    "gn:population":0,
    "gn:timezone":"Asia/Ho_Chi_Minh",
    "iso:country":"VN",
    "name:vie_x_preferred":[
        "B\u1ea3n P\u00e1 Ch\u1ea3"
    ],
    "wof:name":"Ban Pa Cha",
    "wof:placetype":"locality"
},
  "geometry": {"coordinates":[104.03246,21.04687],"type":"Point"}
}