{
  "type": "Feature",
  "properties": {
    "gn:admin1_code":"5.0",
    "gn:asciiname":"Lung Phuc",
    "gn:country_code":"VN",
    "gn:dem":509,
    "gn:feature_class":"P",
    "gn:feature_code":"PPL",
    "gn:name":"L\u0169ng Ph\u1ee5c",
    "gn:population":0,
    "gn:timezone":"Asia/Ho_Chi_Minh",
    "iso:country":"VN",
    "wof:name":"Lung Phuc",
    "wof:placetype":"locality"
},
  "geometry": {"coordinates":[106.68333,22.71667],"type":"Point"}
}