{
  "type": "Feature",
  "properties": {
    "gn:admin1_code":"32.0",
    "gn:asciiname":"Ban Beo",
    "gn:country_code":"VN",
    "gn:dem":138,
    "gn:feature_class":"P",
    "gn:feature_code":"PPL",
    "gn:name":"B\u1ea3n B\u00e8o",
    "gn:population":0,
    "gn:timezone":"Asia/Ho_Chi_Minh",
    "iso:country":"VN",
    "name:und_x_variant":[
        "B\u1ea3n P\u00e8o"
    ],
    "name:vie_x_preferred":[
        "B\u1ea3n B\u00e8o"
    ],
    "wof:name":"Ban Beo",
    "wof:placetype":"locality"
},
  "geometry": {"coordinates":[104.69645,21.106],"type":"Point"}
}