{
  "type": "Feature",
  "properties": {
    "gn:admin1_code":"34.0",
    "gn:asciiname":"Ke Quan",
    "gn:country_code":"VN",
    "gn:dem":167,
    "gn:feature_class":"P",
    "gn:feature_code":"PPL",
    "gn:name":"K\u1ebb Qu\u00e2n",
    "gn:population":0,
    "gn:timezone":"Asia/Ho_Chi_Minh",
    "iso:country":"VN",
    "wof:name":"Ke Quan",
    "wof:placetype":"locality"
},
  "geometry": {"coordinates":[105.25,19.66667],"type":"Point"}
}