{
  "type": "Feature",
  "properties": {
    "gn:admin1_code":"43.0",
    "gn:asciiname":"Phan Tuong Hai",
    "gn:country_code":"VN",
    "gn:dem":71,
    "gn:feature_class":"P",
    "gn:feature_code":"PPL",
    "gn:name":"Ph\u00e2n T\u01b0\u1eddng Hai",
    "gn:population":0,
    "gn:timezone":"Asia/Ho_Chi_Minh",
    "iso:country":"VN",
    "name:vie_x_preferred":[
        "Ph\u00e2n T\u01b0\u1eddng Hai"
    ],
    "name:vie_x_variant":[
        "Ph\u00e2n T\u01b0\u1eddng 2"
    ],
    "wof:name":"Phan Tuong Hai",
    "wof:placetype":"locality"
},
  "geometry": {"coordinates":[107.09734,11.1799],"type":"Point"}
}