{
  "type": "Feature",
  "properties": {
    "gn:admin1_code":"23.0",
    "gn:asciiname":"Tho Meria",
    "gn:country_code":"VN",
    "gn:dem":1029,
    "gn:feature_class":"P",
    "gn:feature_code":"PPL",
    "gn:name":"Tho M\u00e9ria",
    "gn:population":0,
    "gn:timezone":"Asia/Ho_Chi_Minh",
    "iso:country":"VN",
    "wof:name":"Tho Meria",
    "wof:placetype":"locality"
},
  "geometry": {"coordinates":[108.46666999999999,11.68333],"type":"Point"}
}