{
  "type": "Feature",
  "properties": {
    "gn:admin1_code":"91.0",
    "gn:asciiname":"Bon Leng",
    "gn:country_code":"VN",
    "gn:dem":494,
    "gn:feature_class":"P",
    "gn:feature_code":"PPL",
    "gn:name":"Bon Leng",
    "gn:population":0,
    "gn:timezone":"Asia/Ho_Chi_Minh",
    "iso:country":"VN",
    "wof:name":"Bon Leng",
    "wof:placetype":"locality"
},
  "geometry": {"coordinates":[107.83333,12.45],"type":"Point"}
}