{
  "type": "Feature",
  "properties": {
    "gn:admin1_code":"70.0",
    "gn:asciiname":"Lang Pang",
    "gn:country_code":"VN",
    "gn:dem":1511,
    "gn:feature_class":"P",
    "gn:feature_code":"PPL",
    "gn:name":"L\u00e0ng Pang",
    "gn:population":0,
    "gn:timezone":"Asia/Ho_Chi_Minh",
    "iso:country":"VN",
    "wof:name":"Lang Pang",
    "wof:placetype":"locality"
},
  "geometry": {"coordinates":[104.33333,21.83333],"type":"Point"}
}