{
  "type": "Feature",
  "properties": {
    "gn:admin1_code":"44.0",
    "gn:asciiname":"Van Dinh",
    "gn:country_code":"VN",
    "gn:dem":11,
    "gn:feature_class":"P",
    "gn:feature_code":"PPLA2",
    "gn:name":"V\u00e2n \u0110\u00ecnh",
    "gn:population":0,
    "gn:timezone":"Asia/Ho_Chi_Minh",
    "iso:country":"VN",
    "name:vie_x_preferred":[
        "V\u00e2n \u0110\u00ecnh"
    ],
    "wof:name":"Van Dinh",
    "wof:placetype":"locality"
},
  "geometry": {"coordinates":[105.77236000000001,20.73514],"type":"Point"}
}