{
  "type": "Feature",
  "properties": {
    "gn:admin1_code":"44.0",
    "gn:asciiname":"Phung",
    "gn:country_code":"VN",
    "gn:dem":16,
    "gn:feature_class":"P",
    "gn:feature_code":"PPLA2",
    "gn:name":"Ph\u00f9ng",
    "gn:population":0,
    "gn:timezone":"Asia/Ho_Chi_Minh",
    "iso:country":"VN",
    "name:vie_x_preferred":[
        "Ph\u00f9ng"
    ],
    "wof:name":"Phung",
    "wof:placetype":"locality"
},
  "geometry": {"coordinates":[105.65900999999999,21.08902],"type":"Point"}
}