{
  "type": "Feature",
  "properties": {
    "iso:country":"VN",
    "name:ceb_x_preferred":[
        "Na-San Airport"
    ],
    "name:eng_x_preferred":[
        "N\u00e0 S\u1ea3n Airport"
    ],
    "name:fas_x_preferred":[
        "\u0641\u0631\u0648\u062f\u06af\u0627\u0647 \u0646\u0627\u0633\u0627\u0646"
    ],
    "name:ind_x_preferred":[
        "Bandar Udara N\u00e0 S\u1ea3n"
    ],
    "name:jpn_x_preferred":[
        "\u30ca\u30fc\u30b5\u30f3\u7a7a\u6e2f"
    ],
    "name:msa_x_preferred":[
        "Lapangan Terbang Nasan"
    ],
    "name:nld_x_preferred":[
        "Luchthaven N\u00e0 S\u1ea3n"
    ],
    "name:pol_x_preferred":[
        "Port lotniczy N\u00e0 S\u1ea3n"
    ],
    "name:ron_x_preferred":[
        "Aeroportul N\u00e0 S\u1ea3n"
    ],
    "name:rus_x_preferred":[
        "\u0428\u043e\u043d\u043b\u0430"
    ],
    "name:tgk_x_preferred":[
        "\u0424\u0443\u0440\u0443\u0434\u0433\u043e\u04b3\u0438 \u041c\u0430\u04b3\u0430\u043b\u04e3 \u043c\u043e\u0432\u043d\u0442 \u0432\u043e\u0448\u0435\u043d\u0433\u0442\u0443\u043d"
    ],
    "name:ukr_x_preferred":[
        "\u0428\u043e\u043d\u043b\u0430"
    ],
    "name:vie_x_preferred":[
        "S\u00e2n bay N\u00e0 S\u1ea3n"
    ],
    "name:zho_x_preferred":[
        "\u90a3\u7522\u6a5f\u5834"
    ],
    "oa:elevation_ft":"2133",
    "oa:type":"small_airport",
    "wd:wordcount":50,
    "woe:hierarchy":{
        "country_id":23424984,
        "planet_id":1,
        "state_id":2347713
    },
    "wof:name":"Na San Airport",
    "wof:placetype":"campus"
},
  "geometry": {"coordinates":[104.03527777778,21.214722222222],"type":"Point"}
}