{
  "type": "Feature",
  "properties": {
    "gn:admin1_code":"32.0",
    "gn:asciiname":"Ban To Van",
    "gn:country_code":"VN",
    "gn:dem":843,
    "gn:feature_class":"P",
    "gn:feature_code":"PPL",
    "gn:name":"B\u1ea3n T\u00f4 V\u0103n",
    "gn:population":0,
    "gn:timezone":"Asia/Ho_Chi_Minh",
    "iso:country":"VN",
    "name:vie_x_preferred":[
        "B\u1ea3n T\u00f4 V\u0103n"
    ],
    "wof:name":"Ban To Van",
    "wof:placetype":"locality"
},
  "geometry": {"coordinates":[103.97839,21.15466],"type":"Point"}
}