{
  "type": "Feature",
  "properties": {
    "gn:admin1_code":"91.0",
    "gn:asciiname":"Giang Du",
    "gn:country_code":"VN",
    "gn:dem":692,
    "gn:feature_class":"P",
    "gn:feature_code":"PPL",
    "gn:name":"Gi\u0103ng D\u01b0",
    "gn:population":0,
    "gn:timezone":"Asia/Ho_Chi_Minh",
    "iso:country":"VN",
    "name:vie_x_preferred":[
        "Gi\u0103ng D\u01b0"
    ],
    "wof:name":"Giang Du",
    "wof:placetype":"locality"
},
  "geometry": {"coordinates":[107.64512000000001,12.39487],"type":"Point"}
}