{
  "type": "Feature",
  "properties": {
    "gn:admin1_code":"47.0",
    "gn:asciiname":"Phu Nhien",
    "gn:country_code":"VN",
    "gn:dem":219,
    "gn:feature_class":"P",
    "gn:feature_code":"PPL",
    "gn:name":"Ph\u00fa Nhi\u00ean",
    "gn:population":0,
    "gn:timezone":"Asia/Ho_Chi_Minh",
    "iso:country":"VN",
    "name:und_x_variant":[
        "X\u00e3 Ph\u00fa Nhi\u00eau",
        "Phu Nhieu",
        "Ph\u00fa Nhi\u00ean"
    ],
    "wof:name":"Phu Nhien",
    "wof:placetype":"locality"
},
  "geometry": {"coordinates":[108.66667,11.38333],"type":"Point"}
}