{
  "type": "Feature",
  "properties": {
    "gn:admin1_code":"32.0",
    "gn:asciiname":"Ban Cha",
    "gn:country_code":"VN",
    "gn:dem":142,
    "gn:feature_class":"P",
    "gn:feature_code":"PPL",
    "gn:name":"B\u1ea3n Cha",
    "gn:population":0,
    "gn:timezone":"Asia/Ho_Chi_Minh",
    "iso:country":"VN",
    "name:vie_x_preferred":[
        "B\u1ea3n Cha"
    ],
    "wof:name":"Ban Cha",
    "wof:placetype":"locality"
},
  "geometry": {"coordinates":[104.63958,21.17893],"type":"Point"}
}