{
  "type": "Feature",
  "properties": {
    "gn:admin1_code":"60.0",
    "gn:asciiname":"Thon Luong Giang",
    "gn:country_code":"VN",
    "gn:dem":45,
    "gn:feature_class":"P",
    "gn:feature_code":"PPL",
    "gn:name":"Th\u00f4n L\u01b0\u01a1ng Giang",
    "gn:population":0,
    "gn:timezone":"Asia/Ho_Chi_Minh",
    "iso:country":"VN",
    "name:und_x_variant":[
        "L\u01b0\u01a1ng Giang",
        "Th\u00f4n L\u01b0\u01a1ng Giang"
    ],
    "wof:name":"Thon Luong Giang",
    "wof:placetype":"locality"
},
  "geometry": {"coordinates":[108.81667,11.71667],"type":"Point"}
}