{
  "type": "Feature",
  "properties": {
    "gn:admin1_code":"52.0",
    "gn:asciiname":"Vinh Khanh",
    "gn:country_code":"VN",
    "gn:dem":7,
    "gn:feature_class":"P",
    "gn:feature_code":"PPL",
    "gn:name":"Vinh Khanh",
    "gn:population":0,
    "gn:timezone":"Asia/Ho_Chi_Minh",
    "iso:country":"VN",
    "name:vie_x_preferred":[
        "Vinh Khanh"
    ],
    "wof:name":"Vinh Khanh",
    "wof:placetype":"locality"
},
  "geometry": {"coordinates":[105.97208000000001,18.34611],"type":"Point"}
}