{
  "type": "Feature",
  "properties": {
    "gn:admin1_code":"39.0",
    "gn:asciiname":"Na Bo",
    "gn:country_code":"VN",
    "gn:dem":341,
    "gn:feature_class":"P",
    "gn:feature_code":"PPL",
    "gn:name":"Na B\u00f3",
    "gn:population":0,
    "gn:timezone":"Asia/Ho_Chi_Minh",
    "iso:country":"VN",
    "name:vie_x_preferred":[
        "N\u00e0 B\u00f3"
    ],
    "name:vie_x_variant":[
        "Na B\u00f3"
    ],
    "wof:name":"Na Bo",
    "wof:placetype":"locality"
},
  "geometry": {"coordinates":[106.4263,21.78425],"type":"Point"}
}