{
  "type": "Feature",
  "properties": {
    "gn:admin1_code":"23.0",
    "gn:asciiname":"Thon Nam A",
    "gn:country_code":"VN",
    "gn:dem":429,
    "gn:feature_class":"P",
    "gn:feature_code":"PPL",
    "gn:name":"Th\u00f4n N\u0103m A",
    "gn:population":0,
    "gn:timezone":"Asia/Ho_Chi_Minh",
    "iso:country":"VN",
    "name:vie_x_preferred":[
        "Th\u00f4n N\u0103m A"
    ],
    "name:vie_x_variant":[
        "Th\u00f4n 5A"
    ],
    "wof:name":"Thon Nam A",
    "wof:placetype":"locality"
},
  "geometry": {"coordinates":[107.46283,11.73816],"type":"Point"}
}