{
  "type": "Feature",
  "properties": {
    "gn:admin1_code":"74.0",
    "gn:asciiname":"Tam A",
    "gn:country_code":"VN",
    "gn:dem":8,
    "gn:feature_class":"P",
    "gn:feature_code":"PPL",
    "gn:name":"Tam \u00c1",
    "gn:population":0,
    "gn:timezone":"Asia/Ho_Chi_Minh",
    "iso:country":"VN",
    "name:vie_x_preferred":[
        "Tam \u00c1"
    ],
    "wof:name":"Tam A",
    "wof:placetype":"locality"
},
  "geometry": {"coordinates":[106.06865999999999,21.03095],"type":"Point"}
}