{
  "type": "Feature",
  "properties": {
    "gn:admin1_code":"55.0",
    "gn:asciiname":"Vi Koa",
    "gn:country_code":"VN",
    "gn:dem":912,
    "gn:feature_class":"P",
    "gn:feature_code":"PPL",
    "gn:name":"Vi Koa",
    "gn:population":0,
    "gn:timezone":"Asia/Ho_Chi_Minh",
    "iso:country":"VN",
    "name:und_x_variant":[
        "Vioic",
        "Vikoa",
        "Vi Koa"
    ],
    "wof:name":"Vi Koa",
    "wof:placetype":"locality"
},
  "geometry": {"coordinates":[108.49229,14.7597],"type":"Point"}
}