{
  "type": "Feature",
  "properties": {
    "gn:admin1_code":"90.0",
    "gn:asciiname":"Keu Tang Tchai",
    "gn:country_code":"VN",
    "gn:dem":483,
    "gn:feature_class":"P",
    "gn:feature_code":"PPL",
    "gn:name":"Keu Tang Tchai",
    "gn:population":0,
    "gn:timezone":"Asia/Ho_Chi_Minh",
    "iso:country":"VN",
    "wof:name":"Keu Tang Tchai",
    "wof:placetype":"locality"
},
  "geometry": {"coordinates":[104.18333,22.53333],"type":"Point"}
}