{
  "type": "Feature",
  "properties": {
    "gn:admin1_code":"58.0",
    "gn:asciiname":"Dong Nhan",
    "gn:country_code":"VN",
    "gn:dem":79,
    "gn:feature_class":"P",
    "gn:feature_code":"PPL",
    "gn:name":"\u0110\u1ed3ng Nh\u00e2n",
    "gn:population":0,
    "gn:timezone":"Asia/Ho_Chi_Minh",
    "iso:country":"VN",
    "name:vie_x_preferred":[
        "\u0110\u1ed3ng Nh\u00e2n"
    ],
    "wof:name":"Dong Nhan",
    "wof:placetype":"locality"
},
  "geometry": {"coordinates":[105.51779999999999,19.06545],"type":"Point"}
}