{
  "type": "Feature",
  "properties": {
    "gn:admin1_code":"76.0",
    "gn:asciiname":"Bu Bitt",
    "gn:country_code":"VN",
    "gn:dem":299,
    "gn:feature_class":"P",
    "gn:feature_code":"PPL",
    "gn:name":"Bu Bitt",
    "gn:population":0,
    "gn:timezone":"Asia/Ho_Chi_Minh",
    "iso:country":"VN",
    "wof:name":"Bu Bitt",
    "wof:placetype":"locality"
},
  "geometry": {"coordinates":[107.21666999999999,11.65],"type":"Point"}
}