{
  "type": "Feature",
  "properties": {
    "gn:admin1_code":"71.0",
    "gn:asciiname":"Am Bai",
    "gn:country_code":"VN",
    "gn:dem":17,
    "gn:feature_class":"P",
    "gn:feature_code":"PPL",
    "gn:name":"Am B\u00e1i",
    "gn:population":0,
    "gn:timezone":"Asia/Ho_Chi_Minh",
    "iso:country":"VN",
    "name:vie_x_preferred":[
        "Am B\u00e1i"
    ],
    "wof:name":"Am Bai",
    "wof:placetype":"locality"
},
  "geometry": {"coordinates":[106.19861000000002,21.46551],"type":"Point"}
}