{
  "type": "Feature",
  "properties": {
    "gn:admin1_code":"83.0",
    "gn:asciiname":"La Hao",
    "gn:country_code":"VN",
    "gn:dem":21,
    "gn:feature_class":"P",
    "gn:feature_code":"PPL",
    "gn:name":"La H\u00e0o",
    "gn:population":0,
    "gn:timezone":"Asia/Ho_Chi_Minh",
    "iso:country":"VN",
    "name:vie_x_preferred":[
        "La H\u00e0o"
    ],
    "wof:name":"La Hao",
    "wof:placetype":"locality"
},
  "geometry": {"coordinates":[105.34172,21.22558],"type":"Point"}
}