{
  "type": "Feature",
  "properties": {
    "gn:admin1_code":"39.0",
    "gn:asciiname":"Ban Tat",
    "gn:country_code":"VN",
    "gn:dem":217,
    "gn:feature_class":"P",
    "gn:feature_code":"PPL",
    "gn:name":"B\u1ea3n T\u00e1t",
    "gn:population":0,
    "gn:timezone":"Asia/Ho_Chi_Minh",
    "iso:country":"VN",
    "name:und_x_variant":[
        "B\u1ea3n T\u00e1t",
        "B\u00e1n Tat"
    ],
    "wof:name":"Ban Tat",
    "wof:placetype":"locality"
},
  "geometry": {"coordinates":[106.66658,22.1028],"type":"Point"}
}