{
  "type": "Feature",
  "properties": {
    "gn:admin1_code":"50.0",
    "gn:asciiname":"Na Dinh",
    "gn:country_code":"VN",
    "gn:dem":775,
    "gn:feature_class":"P",
    "gn:feature_code":"PPL",
    "gn:name":"N\u00e0 D\u00ecnh",
    "gn:population":0,
    "gn:timezone":"Asia/Ho_Chi_Minh",
    "iso:country":"VN",
    "name:vie_x_preferred":[
        "N\u00e0 D\u00ecnh"
    ],
    "wof:name":"Na Dinh",
    "wof:placetype":"locality"
},
  "geometry": {"coordinates":[105.47693999999998,23.0321],"type":"Point"}
}