{
  "type": "Feature",
  "properties": {
    "gn:admin1_code":"46.0",
    "gn:asciiname":"To Bon",
    "gn:country_code":"VN",
    "gn:dem":44,
    "gn:feature_class":"P",
    "gn:feature_code":"PPL",
    "gn:name":"T\u1ed5 B\u1ed1n",
    "gn:population":0,
    "gn:timezone":"Asia/Ho_Chi_Minh",
    "iso:country":"VN",
    "name:vie_x_preferred":[
        "T\u1ed5 B\u1ed1n"
    ],
    "name:vie_x_variant":[
        "T\u1ed5 4"
    ],
    "wof:name":"To Bon",
    "wof:placetype":"locality"
},
  "geometry": {"coordinates":[108.90455,14.61647],"type":"Point"}
}