{
  "type": "Feature",
  "properties": {
    "gn:admin1_code":"88.0",
    "gn:asciiname":"Ea Sup",
    "gn:country_code":"VN",
    "gn:dem":208,
    "gn:feature_class":"P",
    "gn:feature_code":"PPLA2",
    "gn:name":"Ea S\u00fap",
    "gn:population":0,
    "gn:timezone":"Asia/Ho_Chi_Minh",
    "iso:country":"VN",
    "name:vie_x_preferred":[
        "Ea S\u00fap"
    ],
    "wof:name":"Ea Sup",
    "wof:placetype":"locality"
},
  "geometry": {"coordinates":[107.88545999999999,13.06616],"type":"Point"}
}