{
  "type": "Feature",
  "properties": {
    "gn:admin1_code":"32.0",
    "gn:asciiname":"Mon Ua",
    "gn:country_code":"VN",
    "gn:dem":542,
    "gn:feature_class":"P",
    "gn:feature_code":"PPL",
    "gn:name":"Mon Ua",
    "gn:population":0,
    "gn:timezone":"Asia/Ho_Chi_Minh",
    "iso:country":"VN",
    "wof:name":"Mon Ua",
    "wof:placetype":"locality"
},
  "geometry": {"coordinates":[104.63333,20.98333],"type":"Point"}
}