{
  "type": "Feature",
  "properties": {
    "gn:admin1_code":"72.0",
    "gn:asciiname":"Na Luu",
    "gn:country_code":"VN",
    "gn:dem":179,
    "gn:feature_class":"P",
    "gn:feature_code":"PPL",
    "gn:name":"N\u00e0 L\u1eebu",
    "gn:population":0,
    "gn:timezone":"Asia/Ho_Chi_Minh",
    "iso:country":"VN",
    "name:vie_x_preferred":[
        "N\u00e0 L\u1eebu"
    ],
    "wof:name":"Na Luu",
    "wof:placetype":"locality"
},
  "geometry": {"coordinates":[105.78073999999999,22.14188],"type":"Point"}
}