{
  "type": "Feature",
  "properties": {
    "gn:admin1_code":"68.0",
    "gn:asciiname":"Bac Vang",
    "gn:country_code":"VN",
    "gn:dem":69,
    "gn:feature_class":"P",
    "gn:feature_code":"PPL",
    "gn:name":"B\u1eafc V\u00e3ng",
    "gn:population":0,
    "gn:timezone":"Asia/Ho_Chi_Minh",
    "iso:country":"VN",
    "name:vie_x_preferred":[
        "B\u1eafc V\u00e3ng"
    ],
    "wof:name":"Bac Vang",
    "wof:placetype":"locality"
},
  "geometry": {"coordinates":[105.38746999999999,22.45562],"type":"Point"}
}