{
  "type": "Feature",
  "properties": {
    "gn:admin1_code":"70.0",
    "gn:asciiname":"Dam Phung",
    "gn:country_code":"VN",
    "gn:dem":61,
    "gn:feature_class":"P",
    "gn:feature_code":"PPL",
    "gn:name":"\u0110am Phung",
    "gn:population":0,
    "gn:timezone":"Asia/Ho_Chi_Minh",
    "iso:country":"VN",
    "name:und_x_variant":[
        "\u0110\u1ea7m Ph\u00f9ng"
    ],
    "name:vie_x_preferred":[
        "\u0110am Phung"
    ],
    "wof:name":"Dam Phung",
    "wof:placetype":"locality"
},
  "geometry": {"coordinates":[104.85279,21.75446],"type":"Point"}
}