{
  "type": "Feature",
  "properties": {
    "gn:admin1_code":"39.0",
    "gn:asciiname":"Ni Mou",
    "gn:country_code":"VN",
    "gn:dem":340,
    "gn:feature_class":"P",
    "gn:feature_code":"PPL",
    "gn:name":"Ni Mou",
    "gn:population":0,
    "gn:timezone":"Asia/Ho_Chi_Minh",
    "iso:country":"VN",
    "wof:name":"Ni Mou",
    "wof:placetype":"locality"
},
  "geometry": {"coordinates":[106.18333,21.95],"type":"Point"}
}