{
  "type": "Feature",
  "properties": {
    "gn:admin1_code":"55.0",
    "gn:asciiname":"Kong Gua",
    "gn:country_code":"VN",
    "gn:dem":644,
    "gn:feature_class":"P",
    "gn:feature_code":"PPL",
    "gn:name":"Kong Gua",
    "gn:population":0,
    "gn:timezone":"Asia/Ho_Chi_Minh",
    "iso:country":"VN",
    "wof:name":"Kong Gua",
    "wof:placetype":"locality"
},
  "geometry": {"coordinates":[108.05,14.45],"type":"Point"}
}