{
  "type": "Feature",
  "properties": {
    "gn:admin1_code":"53.0",
    "gn:asciiname":"Muong Boi",
    "gn:country_code":"VN",
    "gn:dem":554,
    "gn:feature_class":"P",
    "gn:feature_code":"PPL",
    "gn:name":"M\u01b0\u01a1ng B\u00f4i",
    "gn:population":0,
    "gn:timezone":"Asia/Ho_Chi_Minh",
    "iso:country":"VN",
    "wof:name":"Muong Boi",
    "wof:placetype":"locality"
},
  "geometry": {"coordinates":[105.38333,20.66667],"type":"Point"}
}