{
  "type": "Feature",
  "properties": {
    "gn:admin1_code":"83.0",
    "gn:asciiname":"Mao Pho",
    "gn:country_code":"VN",
    "gn:dem":22,
    "gn:feature_class":"P",
    "gn:feature_code":"PPL",
    "gn:name":"M\u1ea1o Ph\u00f4",
    "gn:population":0,
    "gn:timezone":"Asia/Ho_Chi_Minh",
    "iso:country":"VN",
    "name:vie_x_preferred":[
        "M\u1ea1o Ph\u00f4"
    ],
    "wof:name":"Mao Pho",
    "wof:placetype":"locality"
},
  "geometry": {"coordinates":[105.2085,21.35726],"type":"Point"}
}