{
  "type": "Feature",
  "properties": {
    "gn:admin1_code":"88.0",
    "gn:asciiname":"Ea Tieu",
    "gn:country_code":"VN",
    "gn:dem":470,
    "gn:feature_class":"P",
    "gn:feature_code":"PPL",
    "gn:name":"Ea Ti\u00eau",
    "gn:population":0,
    "gn:timezone":"Asia/Ho_Chi_Minh",
    "iso:country":"VN",
    "name:und_x_variant":[
        "Buon Ea Tiu",
        "Bu\u00f4n Ea Ti\u1ebfu"
    ],
    "name:vie_x_preferred":[
        "Ea Ti\u00eau"
    ],
    "wof:name":"Ea Tieu",
    "wof:placetype":"locality"
},
  "geometry": {"coordinates":[108.09548999999998,12.60335],"type":"Point"}
}