{
  "type": "Feature",
  "properties": {
    "gn:admin1_code":"23.0",
    "gn:asciiname":"Sre Boh",
    "gn:cc2":"VN",
    "gn:country_code":"VN",
    "gn:dem":1085,
    "gn:feature_class":"P",
    "gn:feature_code":"PPL",
    "gn:name":"Sr\u00ea B\u00f3h",
    "gn:population":0,
    "gn:timezone":"Asia/Ho_Chi_Minh",
    "iso:country":"VN",
    "name:und_x_variant":[
        "Sre Bo",
        "Sr\u00ea B\u00f3h"
    ],
    "wof:name":"Sre Boh",
    "wof:placetype":"locality"
},
  "geometry": {"coordinates":[108.03333000000001,11.48333],"type":"Point"}
}