{
  "type": "Feature",
  "properties": {
    "gn:admin1_code":"92.0",
    "gn:asciiname":"La Ca",
    "gn:country_code":"VN",
    "gn:dem":468,
    "gn:feature_class":"P",
    "gn:feature_code":"PPL",
    "gn:name":"La Ca",
    "gn:population":0,
    "gn:timezone":"Asia/Ho_Chi_Minh",
    "iso:country":"VN",
    "name:vie_x_preferred":[
        "La Ca"
    ],
    "wof:name":"La Ca",
    "wof:placetype":"locality"
},
  "geometry": {"coordinates":[103.34311,21.24493],"type":"Point"}
}