{
  "type": "Feature",
  "properties": {
    "gn:admin1_code":"58.0",
    "gn:asciiname":"Ban Kem Hai",
    "gn:country_code":"VN",
    "gn:dem":690,
    "gn:feature_class":"P",
    "gn:feature_code":"PPL",
    "gn:name":"B\u1ea3n K\u1ebdm Hai",
    "gn:population":0,
    "gn:timezone":"Asia/Ho_Chi_Minh",
    "iso:country":"VN",
    "name:vie_x_preferred":[
        "B\u1ea3n K\u1ebdm Hai"
    ],
    "name:vie_x_variant":[
        "B\u1ea3n K\u1ebdm 2"
    ],
    "wof:name":"Ban Kem Hai",
    "wof:placetype":"locality"
},
  "geometry": {"coordinates":[104.69175,19.6246],"type":"Point"}
}