{
  "type": "Feature",
  "properties": {
    "gn:admin1_code":"50.0",
    "gn:asciiname":"Ta Loung",
    "gn:country_code":"VN",
    "gn:dem":587,
    "gn:feature_class":"P",
    "gn:feature_code":"PPL",
    "gn:name":"Ta Loung",
    "gn:population":0,
    "gn:timezone":"Asia/Ho_Chi_Minh",
    "iso:country":"VN",
    "name:und_x_variant":[
        "Da Loung",
        "Ta Loung"
    ],
    "wof:name":"Ta Loung",
    "wof:placetype":"locality"
},
  "geometry": {"coordinates":[105.25,23.03333],"type":"Point"}
}