{
  "type": "Feature",
  "properties": {
    "gn:admin1_code":"32.0",
    "gn:asciiname":"Ban Coi",
    "gn:country_code":"VN",
    "gn:dem":263,
    "gn:feature_class":"P",
    "gn:feature_code":"PPL",
    "gn:name":"B\u1ea3n Coi",
    "gn:population":0,
    "gn:timezone":"Asia/Ho_Chi_Minh",
    "iso:country":"VN",
    "name:vie_x_preferred":[
        "B\u1ea3n Coi"
    ],
    "wof:name":"Ban Coi",
    "wof:placetype":"locality"
},
  "geometry": {"coordinates":[103.6887,21.61865],"type":"Point"}
}