{
  "type": "Feature",
  "properties": {
    "gn:admin1_code":"71.0",
    "gn:asciiname":"Xom Quyen",
    "gn:country_code":"VN",
    "gn:dem":23,
    "gn:feature_class":"P",
    "gn:feature_code":"PPL",
    "gn:name":"X\u00f3m Quy\u1ec1n",
    "gn:population":0,
    "gn:timezone":"Asia/Ho_Chi_Minh",
    "iso:country":"VN",
    "name:vie_x_preferred":[
        "X\u00f3m Quy\u1ec1n"
    ],
    "wof:name":"Xom Quyen",
    "wof:placetype":"locality"
},
  "geometry": {"coordinates":[106.00418000000001,21.3507],"type":"Point"}
}