{
  "type": "Feature",
  "properties": {
    "gn:admin1_code":"68.0",
    "gn:asciiname":"Lang Luong",
    "gn:country_code":"VN",
    "gn:dem":56,
    "gn:feature_class":"P",
    "gn:feature_code":"PPL",
    "gn:name":"L\u00e0ng Lu\u00f4ng",
    "gn:population":0,
    "gn:timezone":"Asia/Ho_Chi_Minh",
    "iso:country":"VN",
    "name:vie_x_preferred":[
        "L\u00e0ng Lu\u00f4ng"
    ],
    "wof:name":"Lang Luong",
    "wof:placetype":"locality"
},
  "geometry": {"coordinates":[105.31923,22.21684],"type":"Point"}
}