{
  "type": "Feature",
  "properties": {
    "gn:admin1_code":"49.0",
    "gn:asciiname":"Thanh Trang",
    "gn:country_code":"VN",
    "gn:dem":169,
    "gn:feature_class":"P",
    "gn:feature_code":"PPL",
    "gn:name":"Thanh Trang",
    "gn:population":0,
    "gn:timezone":"Asia/Ho_Chi_Minh",
    "iso:country":"VN",
    "name:vie_x_preferred":[
        "Thanh Trang"
    ],
    "wof:name":"Thanh Trang",
    "wof:placetype":"locality"
},
  "geometry": {"coordinates":[108.36837,13.49352],"type":"Point"}
}