{
  "type": "Feature",
  "properties": {
    "gn:admin1_code":"53.0",
    "gn:asciiname":"Sang Nua",
    "gn:country_code":"VN",
    "gn:dem":179,
    "gn:feature_class":"P",
    "gn:feature_code":"PPL",
    "gn:name":"S\u1eb3ng N\u01b0a",
    "gn:population":0,
    "gn:timezone":"Asia/Ho_Chi_Minh",
    "iso:country":"VN",
    "name:vie_x_preferred":[
        "S\u1eb3ng N\u01b0a"
    ],
    "wof:name":"Sang Nua",
    "wof:placetype":"locality"
},
  "geometry": {"coordinates":[105.3959,20.82574],"type":"Point"}
}