{
  "type": "Feature",
  "properties": {
    "gn:admin1_code":"87.0",
    "gn:asciiname":"Thoi Thanh B",
    "gn:country_code":"VN",
    "gn:dem":1,
    "gn:feature_class":"P",
    "gn:feature_code":"PPL",
    "gn:name":"Th\u1edbi Th\u00e0nh B",
    "gn:population":0,
    "gn:timezone":"Asia/Ho_Chi_Minh",
    "iso:country":"VN",
    "name:vie_x_preferred":[
        "Th\u1edbi Th\u00e0nh B"
    ],
    "wof:name":"Thoi Thanh B",
    "wof:placetype":"locality"
},
  "geometry": {"coordinates":[105.48193000000001,9.97363],"type":"Point"}
}