{
  "type": "Feature",
  "properties": {
    "gn:admin1_code":"32.0",
    "gn:asciiname":"Si Li",
    "gn:country_code":"VN",
    "gn:dem":933,
    "gn:feature_class":"P",
    "gn:feature_code":"PPL",
    "gn:name":"Si Li",
    "gn:population":0,
    "gn:timezone":"Asia/Ho_Chi_Minh",
    "iso:country":"VN",
    "wof:name":"Si Li",
    "wof:placetype":"locality"
},
  "geometry": {"coordinates":[104.75,20.96667],"type":"Point"}
}