{
  "type": "Feature",
  "properties": {
    "gn:admin1_code":"32.0",
    "gn:asciiname":"Ban Na Muong",
    "gn:country_code":"VN",
    "gn:dem":397,
    "gn:feature_class":"P",
    "gn:feature_code":"PPL",
    "gn:name":"B\u1ea3n N\u00e0 M\u01b0\u1eddng",
    "gn:population":0,
    "gn:timezone":"Asia/Ho_Chi_Minh",
    "iso:country":"VN",
    "name:vie_x_preferred":[
        "N\u00e0 M\u01b0\u1eddng"
    ],
    "name:vie_x_variant":[
        "B\u1ea3n N\u00e0 M\u01b0\u1eddng"
    ],
    "wof:name":"Ban Na Muong",
    "wof:placetype":"locality"
},
  "geometry": {"coordinates":[104.61490999999999,21.00181],"type":"Point"}
}