{
  "type": "Feature",
  "properties": {
    "gn:admin1_code":"23.0",
    "gn:asciiname":"Tan Da Nghich",
    "gn:country_code":"VN",
    "gn:dem":461,
    "gn:feature_class":"P",
    "gn:feature_code":"PPL",
    "gn:name":"T\u00e2n Da Nghich",
    "gn:population":0,
    "gn:timezone":"Asia/Ho_Chi_Minh",
    "iso:country":"VN",
    "wof:name":"Tan Da Nghich",
    "wof:placetype":"locality"
},
  "geometry": {"coordinates":[108.06667,11.26667],"type":"Point"}
}