{
  "type": "Feature",
  "properties": {
    "gn:admin1_code":"39.0",
    "gn:asciiname":"Hang Na",
    "gn:country_code":"VN",
    "gn:dem":275,
    "gn:feature_class":"P",
    "gn:feature_code":"PPL",
    "gn:name":"Hang N\u00e0",
    "gn:population":0,
    "gn:timezone":"Asia/Ho_Chi_Minh",
    "iso:country":"VN",
    "name:vie_x_preferred":[
        "Hang N\u00e0"
    ],
    "wof:name":"Hang Na",
    "wof:placetype":"locality"
},
  "geometry": {"coordinates":[106.49030999999999,21.83939],"type":"Point"}
}