{
  "type": "Feature",
  "properties": {
    "gn:admin1_code":"58.0",
    "gn:asciiname":"Phuc Due",
    "gn:country_code":"VN",
    "gn:dem":10,
    "gn:feature_class":"P",
    "gn:feature_code":"PPL",
    "gn:name":"Ph\u00fac Du\u1ec7",
    "gn:population":0,
    "gn:timezone":"Asia/Ho_Chi_Minh",
    "iso:country":"VN",
    "name:und_x_variant":[
        "Ph\u00fac D\u00fac",
        "Ph\u00fac Du\u1ec7"
    ],
    "wof:name":"Phuc Due",
    "wof:placetype":"locality"
},
  "geometry": {"coordinates":[105.42928999999999,18.94288],"type":"Point"}
}