{
  "type": "Feature",
  "properties": {
    "gn:admin1_code":"77.0",
    "gn:asciiname":"Nha May",
    "gn:country_code":"VN",
    "gn:dem":1,
    "gn:feature_class":"P",
    "gn:feature_code":"PPL",
    "gn:name":"Nh\u00e0 M\u00e1y",
    "gn:population":0,
    "gn:timezone":"Asia/Ho_Chi_Minh",
    "iso:country":"VN",
    "name:und_x_variant":[
        "Xom Nha May",
        "\u1ea4p Nh\u00e0 M\u00e1y"
    ],
    "name:vie_x_preferred":[
        "Nh\u00e0 M\u00e1y"
    ],
    "wof:name":"Nha May",
    "wof:placetype":"locality"
},
  "geometry": {"coordinates":[104.91728999999999,9.13731],"type":"Point"}
}