{
  "type": "Feature",
  "properties": {
    "gn:admin1_code":"69.0",
    "gn:asciiname":"Hoa Hiep",
    "gn:country_code":"VN",
    "gn:dem":2,
    "gn:feature_class":"P",
    "gn:feature_code":"PPL",
    "gn:name":"H\u00f2a Hi\u1ec7p",
    "gn:population":0,
    "gn:timezone":"Asia/Ho_Chi_Minh",
    "iso:country":"VN",
    "name:vie_x_preferred":[
        "H\u00f2a Hi\u1ec7p"
    ],
    "wof:name":"Hoa Hiep",
    "wof:placetype":"locality"
},
  "geometry": {"coordinates":[106.15297,10.11734],"type":"Point"}
}