{
  "type": "Feature",
  "properties": {
    "iso:country":"VN",
    "name:ara_x_preferred":[
        "\u0633\u0627 \u0628\u0627"
    ],
    "name:ceb_x_preferred":[
        "Sa P\u00e1"
    ],
    "name:ceb_x_variant":[
        "Sa Pa"
    ],
    "name:dan_x_preferred":[
        "Sapa"
    ],
    "name:deu_x_preferred":[
        "Sa Pa"
    ],
    "name:eng_x_preferred":[
        "Sa Pa"
    ],
    "name:epo_x_preferred":[
        "Sa Pa"
    ],
    "name:fas_x_preferred":[
        "\u0633\u0627 \u067e\u0627"
    ],
    "name:fra_x_preferred":[
        "Sa Pa"
    ],
    "name:ind_x_preferred":[
        "Sa Pa"
    ],
    "name:jpn_x_preferred":[
        "\u30b5\u30d1"
    ],
    "name:kor_x_preferred":[
        "\uc0ac\ube60"
    ],
    "name:nld_x_preferred":[
        "Sa Pa"
    ],
    "name:nob_x_preferred":[
        "Sa Pa"
    ],
    "name:nor_x_preferred":[
        "Sa Pa"
    ],
    "name:pol_x_preferred":[
        "Sa Pa"
    ],
    "name:por_x_preferred":[
        "Sa Pa"
    ],
    "name:rus_x_preferred":[
        "\u0428\u0430\u043f\u0430"
    ],
    "name:rus_x_variant":[
        "\u0421\u0430\u043f\u0430"
    ],
    "name:slk_x_preferred":[
        "Sa Pa"
    ],
    "name:spa_x_preferred":[
        "Sa Pa"
    ],
    "name:swe_x_preferred":[
        "Sa Pa"
    ],
    "name:tha_x_preferred":[
        "\u0e0b\u0e32\u0e1b\u0e32"
    ],
    "name:und_x_variant":[
        "Chapa"
    ],
    "name:urd_x_preferred":[
        "\u0633\u0627 \u067e\u0627"
    ],
    "name:vie_x_preferred":[
        "Sa Pa"
    ],
    "name:zho_x_preferred":[
        "\u6c99\u575d\u9547"
    ],
    "name:zho_x_variant":[
        "\u6c99\u575d\u5e02\u9547",
        "\u6c99\u575d\u574a"
    ],
    "qs:gn_country":"VN",
    "qs:gn_fcode":"PPL",
    "qs:gn_pop":138622,
    "qs:name":"Sa P\u00e1",
    "qs:name_adm0":"Vietnam",
    "qs:name_adm1":"Lao Cai",
    "qs:photos":4999,
    "qs:photos_1k":1000,
    "qs:photos_9k":22,
    "qs:photos_9r":14,
    "qs:photos_all":4999,
    "qs:photos_sr":24,
    "qs:placetype":"Town",
    "qs:pop_sr":"9",
    "qs:woe_adm0":23424984,
    "wd:wordcount":2941,
    "wof:name":"Sa P\u00e1",
    "wof:placetype":"locality",
    "wof:population":138622
},
  "geometry": {"coordinates":[103.84415,22.34023],"type":"Point"}
}