{
  "type": "Feature",
  "properties": {
    "gn:admin1_code":"53.0",
    "gn:asciiname":"Yen Lac",
    "gn:country_code":"VN",
    "gn:dem":151,
    "gn:feature_class":"P",
    "gn:feature_code":"PPL",
    "gn:name":"Y\u00ean L\u1ea1c",
    "gn:population":0,
    "gn:timezone":"Asia/Ho_Chi_Minh",
    "iso:country":"VN",
    "wof:name":"Yen Lac",
    "wof:placetype":"locality"
},
  "geometry": {"coordinates":[105.59999999999999,20.38333],"type":"Point"}
}