{
  "type": "Feature",
  "properties": {
    "gn:admin1_code":"89.0",
    "gn:asciiname":"Vang Ma Chai",
    "gn:country_code":"VN",
    "gn:dem":1439,
    "gn:feature_class":"P",
    "gn:feature_code":"PPL",
    "gn:name":"Vang Ma Ch\u00e0i",
    "gn:population":0,
    "gn:timezone":"Asia/Ho_Chi_Minh",
    "iso:country":"VN",
    "wof:name":"Vang Ma Chai",
    "wof:placetype":"locality"
},
  "geometry": {"coordinates":[103.34999999999999,22.71667],"type":"Point"}
}