{
  "type": "Feature",
  "properties": {
    "gn:admin1_code":"71.0",
    "gn:asciiname":"Tien Ly",
    "gn:country_code":"VN",
    "gn:dem":154,
    "gn:feature_class":"P",
    "gn:feature_code":"PPL",
    "gn:name":"Ti\u00ean L\u00fd",
    "gn:population":0,
    "gn:timezone":"Asia/Ho_Chi_Minh",
    "iso:country":"VN",
    "name:vie_x_preferred":[
        "Ti\u00ean L\u00fd"
    ],
    "wof:name":"Tien Ly",
    "wof:placetype":"locality"
},
  "geometry": {"coordinates":[106.81182,21.35412],"type":"Point"}
}