{
  "type": "Feature",
  "properties": {
    "gn:admin1_code":"65.0",
    "gn:asciiname":"Ap Nuoc Man Ngoai",
    "gn:cc2":"VN",
    "gn:country_code":"VN",
    "gn:dem":2,
    "gn:feature_class":"P",
    "gn:feature_code":"PPL",
    "gn:name":"\u1ea4p N\u01b0\u1edbc M\u1eb7n Ngo\u00e0i",
    "gn:population":0,
    "gn:timezone":"Asia/Ho_Chi_Minh",
    "iso:country":"VN",
    "name:und_x_variant":[
        "N\u01b0\u1edbc M\u1eb7n Ngo\u00e0i",
        "\u1ea4p N\u01b0\u1edbc M\u1eb7n Ngo\u00e0i"
    ],
    "wof:name":"Ap Nuoc Man Ngoai",
    "wof:placetype":"locality"
},
  "geometry": {"coordinates":[106.13916999999999,9.59417],"type":"Point"}
}