{
  "type": "Feature",
  "properties": {
    "gn:admin1_code":"62.0",
    "gn:asciiname":"Dai Hoa Phuong",
    "gn:country_code":"VN",
    "gn:dem":53,
    "gn:feature_class":"P",
    "gn:feature_code":"PPL",
    "gn:name":"\u0110\u1ea1i H\u00f2a Ph\u01b0\u1eddng",
    "gn:population":0,
    "gn:timezone":"Asia/Ho_Chi_Minh",
    "iso:country":"VN",
    "wof:name":"Dai Hoa Phuong",
    "wof:placetype":"locality"
},
  "geometry": {"coordinates":[106.08333,17.88332999999999],"type":"Point"}
}