{
  "type": "Feature",
  "properties": {
    "gn:admin1_code":"37.0",
    "gn:asciiname":"Ninh Binh",
    "gn:country_code":"VN",
    "gn:dem":-2,
    "gn:feature_class":"P",
    "gn:feature_code":"PPL",
    "gn:name":"Ninh B\u00ecnh",
    "gn:population":0,
    "gn:timezone":"Asia/Ho_Chi_Minh",
    "iso:country":"VN",
    "name:vie_x_preferred":[
        "Ninh B\u00ecnh"
    ],
    "wof:name":"Ninh Binh",
    "wof:placetype":"locality"
},
  "geometry": {"coordinates":[106.37711000000002,10.46784],"type":"Point"}
}