{
  "type": "Feature",
  "properties": {
    "gn:admin1_code":"88.0",
    "gn:asciiname":"Buon Phoke",
    "gn:country_code":"VN",
    "gn:dem":428,
    "gn:feature_class":"P",
    "gn:feature_code":"PPL",
    "gn:name":"Bu\u00f4n Phoke",
    "gn:population":0,
    "gn:timezone":"Asia/Ho_Chi_Minh",
    "iso:country":"VN",
    "wof:name":"Buon Phoke",
    "wof:placetype":"locality"
},
  "geometry": {"coordinates":[107.95,12.33333],"type":"Point"}
}