{
  "type": "Feature",
  "properties": {
    "gn:admin1_code":"13.0",
    "gn:asciiname":"Mai Thu",
    "gn:cc2":"VN",
    "gn:country_code":"VN",
    "gn:dem":3,
    "gn:feature_class":"P",
    "gn:feature_code":"PPL",
    "gn:name":"Mai Thu",
    "gn:population":0,
    "gn:timezone":"Asia/Ho_Chi_Minh",
    "iso:country":"VN",
    "name:und_x_variant":[
        "Mai Tru",
        "Mai Tou",
        "Mai Thu"
    ],
    "wof:name":"Mai Thu",
    "wof:placetype":"locality"
},
  "geometry": {"coordinates":[106.59999999999999,20.91667],"type":"Point"}
}