{
  "type": "Feature",
  "properties": {
    "gn:admin1_code":"33.0",
    "gn:asciiname":"Ba Chiem",
    "gn:country_code":"VN",
    "gn:dem":21,
    "gn:feature_class":"P",
    "gn:feature_code":"PPL",
    "gn:name":"B\u00e0 Chi\u00eam",
    "gn:population":0,
    "gn:timezone":"Asia/Ho_Chi_Minh",
    "iso:country":"VN",
    "name:vie_x_preferred":[
        "B\u00e0 Chi\u00eam"
    ],
    "wof:name":"Ba Chiem",
    "wof:placetype":"locality"
},
  "geometry": {"coordinates":[106.3321,11.45185],"type":"Point"}
}