{
  "type": "Feature",
  "properties": {
    "gn:admin1_code":"50.0",
    "gn:asciiname":"Phuc Ha",
    "gn:country_code":"VN",
    "gn:dem":177,
    "gn:feature_class":"P",
    "gn:feature_code":"PPL",
    "gn:name":"Ph\u00fac H\u1ea1",
    "gn:population":0,
    "gn:timezone":"Asia/Ho_Chi_Minh",
    "iso:country":"VN",
    "name:vie_x_preferred":[
        "Ph\u00fac H\u1ea1"
    ],
    "wof:name":"Phuc Ha",
    "wof:placetype":"locality"
},
  "geometry": {"coordinates":[105.08183,22.88057],"type":"Point"}
}