{
  "type": "Feature",
  "properties": {
    "gn:admin1_code":"88.0",
    "gn:asciiname":"Quang Nhieu",
    "gn:country_code":"VN",
    "gn:dem":458,
    "gn:feature_class":"P",
    "gn:feature_code":"PPL",
    "gn:name":"Qu\u1ea3ng Nhi\u00eau",
    "gn:population":0,
    "gn:timezone":"Asia/Ho_Chi_Minh",
    "iso:country":"VN",
    "wof:name":"Quang Nhieu",
    "wof:placetype":"locality"
},
  "geometry": {"coordinates":[108.09999999999999,12.81667],"type":"Point"}
}