{
  "type": "Feature",
  "properties": {
    "gn:admin1_code":"88.0",
    "gn:asciiname":"Tang Mai",
    "gn:country_code":"VN",
    "gn:dem":679,
    "gn:feature_class":"P",
    "gn:feature_code":"PPL",
    "gn:name":"T\u0103ng Mai",
    "gn:population":0,
    "gn:timezone":"Asia/Ho_Chi_Minh",
    "iso:country":"VN",
    "name:und_x_variant":[
        "Ban Tang May",
        "Buon Tang May",
        "Ban Tang",
        "Bu\u00f4n T\u00e2ng Mai"
    ],
    "name:vie_x_preferred":[
        "T\u0103ng Mai"
    ],
    "wof:name":"Tang Mai",
    "wof:placetype":"locality"
},
  "geometry": {"coordinates":[108.22181,12.93562],"type":"Point"}
}