{
  "type": "Feature",
  "properties": {
    "gn:admin1_code":"68.0",
    "gn:asciiname":"Dieu Thuong",
    "gn:country_code":"VN",
    "gn:dem":83,
    "gn:feature_class":"P",
    "gn:feature_code":"PPL",
    "gn:name":"Di\u00eau Th\u01b0\u1ee3ng",
    "gn:population":0,
    "gn:timezone":"Asia/Ho_Chi_Minh",
    "iso:country":"VN",
    "name:vie_x_preferred":[
        "Di\u00eau Th\u01b0\u1ee3ng"
    ],
    "wof:name":"Dieu Thuong",
    "wof:placetype":"locality"
},
  "geometry": {"coordinates":[105.31485000000001,21.99802],"type":"Point"}
}