{
  "type": "Feature",
  "properties": {
    "gn:admin1_code":"1.0",
    "gn:asciiname":"Binh Thoi",
    "gn:country_code":"VN",
    "gn:dem":7,
    "gn:feature_class":"P",
    "gn:feature_code":"PPL",
    "gn:name":"B\u00ecnh Th\u1edbi",
    "gn:population":0,
    "gn:timezone":"Asia/Ho_Chi_Minh",
    "iso:country":"VN",
    "name:und_x_variant":[
        "\u1ea4p B\u00ecnh Th\u1edbi"
    ],
    "name:vie_x_preferred":[
        "B\u00ecnh Th\u1edbi"
    ],
    "wof:name":"Binh Thoi",
    "wof:placetype":"locality"
},
  "geometry": {"coordinates":[105.42308,10.39484],"type":"Point"}
}