{
  "type": "Feature",
  "properties": {
    "gn:admin1_code":"65.0",
    "gn:asciiname":"My Thanh",
    "gn:country_code":"VN",
    "gn:dem":1,
    "gn:feature_class":"P",
    "gn:feature_code":"PPL",
    "gn:name":"M\u1ef9 Th\u1ea1nh",
    "gn:population":0,
    "gn:timezone":"Asia/Ho_Chi_Minh",
    "iso:country":"VN",
    "name:und_x_variant":[
        "M\u1ef9 Th\u1ea1nh",
        "X\u00f3m M\u1ef9 Th\u1ea1nh"
    ],
    "wof:name":"My Thanh",
    "wof:placetype":"locality"
},
  "geometry": {"coordinates":[106.1614,9.41291],"type":"Point"}
}