{
  "type": "Feature",
  "properties": {
    "gn:admin1_code":"52.0",
    "gn:asciiname":"Thanh Hoa",
    "gn:country_code":"VN",
    "gn:dem":13,
    "gn:feature_class":"P",
    "gn:feature_code":"PPL",
    "gn:name":"Thanh H\u00f2a",
    "gn:population":0,
    "gn:timezone":"Asia/Ho_Chi_Minh",
    "iso:country":"VN",
    "name:vie_x_preferred":[
        "Thanh H\u00f2a"
    ],
    "wof:name":"Thanh Hoa",
    "wof:placetype":"locality"
},
  "geometry": {"coordinates":[105.98927,18.23608],"type":"Point"}
}