{
  "type": "Feature",
  "properties": {
    "gn:admin1_code":"45.0",
    "gn:asciiname":"Xa Long My",
    "gn:country_code":"VN",
    "gn:dem":5,
    "gn:feature_class":"P",
    "gn:feature_code":"PPL",
    "gn:name":"X\u00e3 Long M\u1ef9",
    "gn:population":0,
    "gn:timezone":"Asia/Ho_Chi_Minh",
    "iso:country":"VN",
    "name:und_x_variant":[
        "Long My",
        "X\u00e3 Long M\u1ef9"
    ],
    "wof:name":"Xa Long My",
    "wof:placetype":"locality"
},
  "geometry": {"coordinates":[107.26667,10.45],"type":"Point"}
}