{
  "type": "Feature",
  "properties": {
    "gn:admin1_code":"39.0",
    "gn:asciiname":"Tien Mung",
    "gn:cc2":"VN",
    "gn:country_code":"VN",
    "gn:dem":312,
    "gn:feature_class":"P",
    "gn:feature_code":"PPL",
    "gn:name":"Ti\u00ean Mung",
    "gn:population":0,
    "gn:timezone":"Asia/Ho_Chi_Minh",
    "iso:country":"VN",
    "name:und_x_variant":[
        "Ten Mung",
        "Ti\u00ean Mung"
    ],
    "wof:name":"Tien Mung",
    "wof:placetype":"locality"
},
  "geometry": {"coordinates":[106.48333,22.05],"type":"Point"}
}