{
  "type": "Feature",
  "properties": {
    "gn:admin1_code":"87.0",
    "gn:asciiname":"Nhon Hung",
    "gn:country_code":"VN",
    "gn:dem":6,
    "gn:feature_class":"P",
    "gn:feature_code":"PPL",
    "gn:name":"Nh\u01a1n H\u01b0ng",
    "gn:population":0,
    "gn:timezone":"Asia/Ho_Chi_Minh",
    "iso:country":"VN",
    "name:vie_x_preferred":[
        "Nh\u01a1n H\u01b0ng"
    ],
    "wof:name":"Nhon Hung",
    "wof:placetype":"locality"
},
  "geometry": {"coordinates":[105.72214,9.99287],"type":"Point"}
}