{
  "type": "Feature",
  "properties": {
    "gn:admin1_code":"64.0",
    "gn:asciiname":"Ho Xa",
    "gn:country_code":"VN",
    "gn:dem":11,
    "gn:feature_class":"P",
    "gn:feature_code":"PPLA2",
    "gn:name":"H\u1ed3 X\u00e1",
    "gn:population":0,
    "gn:timezone":"Asia/Ho_Chi_Minh",
    "iso:country":"VN",
    "name:und_x_variant":[
        "V\u0129nh Linh",
        "H\u1ed3 X\u00e1"
    ],
    "name:vie_x_preferred":[
        "H\u1ed3 X\u00e1"
    ],
    "wof:name":"Ho Xa",
    "wof:placetype":"locality"
},
  "geometry": {"coordinates":[107.0052,17.06836],"type":"Point"}
}