{
  "type": "Feature",
  "properties": {
    "gn:admin1_code":"83.0",
    "gn:asciiname":"Go Que",
    "gn:country_code":"VN",
    "gn:dem":30,
    "gn:feature_class":"P",
    "gn:feature_code":"PPL",
    "gn:name":"G\u00f2 Que",
    "gn:population":0,
    "gn:timezone":"Asia/Ho_Chi_Minh",
    "iso:country":"VN",
    "name:vie_x_preferred":[
        "G\u00f2 Que"
    ],
    "wof:name":"Go Que",
    "wof:placetype":"locality"
},
  "geometry": {"coordinates":[105.24236999999999,21.2579],"type":"Point"}
}