{
  "type": "Feature",
  "properties": {
    "gn:admin1_code":"61.0",
    "gn:asciiname":"Luong Phuoc",
    "gn:country_code":"VN",
    "gn:dem":19,
    "gn:feature_class":"P",
    "gn:feature_code":"PPL",
    "gn:name":"L\u01b0\u01a1ng Ph\u01b0\u1edbc",
    "gn:population":0,
    "gn:timezone":"Asia/Ho_Chi_Minh",
    "iso:country":"VN",
    "name:und_x_variant":[
        "Long Ph\u01b0\u1edbc",
        "L\u01b0\u01a1ng Ph\u01b0\u1edbc"
    ],
    "wof:name":"Luong Phuoc",
    "wof:placetype":"locality"
},
  "geometry": {"coordinates":[109.16667,12.98333],"type":"Point"}
}