{
  "type": "Feature",
  "properties": {
    "gn:admin1_code":"55.0",
    "gn:asciiname":"Kon Ko Tu Peng",
    "gn:country_code":"VN",
    "gn:dem":588,
    "gn:feature_class":"P",
    "gn:feature_code":"PPL",
    "gn:name":"Kon Ko Tu Peng",
    "gn:population":0,
    "gn:timezone":"Asia/Ho_Chi_Minh",
    "iso:country":"VN",
    "name:und_x_variant":[
        "Kon Ketou Peng",
        "Kon K\u01a1tu Peng",
        "Kon Ko Tu Peng"
    ],
    "wof:name":"Kon Ko Tu Peng",
    "wof:placetype":"locality"
},
  "geometry": {"coordinates":[107.83407,14.60504],"type":"Point"}
}