{
  "type": "Feature",
  "properties": {
    "gn:admin1_code":"74.0",
    "gn:asciiname":"Ha Lieu",
    "gn:country_code":"VN",
    "gn:dem":10,
    "gn:feature_class":"P",
    "gn:feature_code":"PPL",
    "gn:name":"H\u00e0 Li\u1ec5u",
    "gn:population":0,
    "gn:timezone":"Asia/Ho_Chi_Minh",
    "iso:country":"VN",
    "name:und_x_variant":[
        "K\u00e9 H\u00e0",
        "H\u00e0 Li\u1ec5u"
    ],
    "wof:name":"Ha Lieu",
    "wof:placetype":"locality"
},
  "geometry": {"coordinates":[106.13706999999999,21.16608],"type":"Point"}
}