{
  "type": "Feature",
  "properties": {
    "gn:admin1_code":"84.0",
    "gn:asciiname":"Muong Ron",
    "gn:country_code":"VN",
    "gn:dem":683,
    "gn:feature_class":"P",
    "gn:feature_code":"PPL",
    "gn:name":"Muong Ron",
    "gn:population":0,
    "gn:timezone":"Asia/Ho_Chi_Minh",
    "iso:country":"VN",
    "wof:name":"Muong Ron",
    "wof:placetype":"locality"
},
  "geometry": {"coordinates":[108.06667,15.25],"type":"Point"}
}