{
  "type": "Feature",
  "properties": {
    "gn:admin1_code":"66.0",
    "gn:asciiname":"Thon Huynh An",
    "gn:country_code":"VN",
    "gn:dem":9,
    "gn:feature_class":"P",
    "gn:feature_code":"PPL",
    "gn:name":"Th\u00f4n H\u00f9ynh An",
    "gn:population":0,
    "gn:timezone":"Asia/Ho_Chi_Minh",
    "iso:country":"VN",
    "name:und_x_variant":[
        "Huynh An",
        "Th\u00f4n H\u00f9ynh An"
    ],
    "wof:name":"Thon Huynh An",
    "wof:placetype":"locality"
},
  "geometry": {"coordinates":[107.68333,16.41667],"type":"Point"}
}