{
  "type": "Feature",
  "properties": {
    "gn:admin1_code":"92.0",
    "gn:asciiname":"Huoi Tong",
    "gn:country_code":"VN",
    "gn:dem":707,
    "gn:feature_class":"P",
    "gn:feature_code":"PPL",
    "gn:name":"Hu\u1ed5i T\u00f3ng",
    "gn:population":0,
    "gn:timezone":"Asia/Ho_Chi_Minh",
    "iso:country":"VN",
    "name:vie_x_preferred":[
        "Hu\u1ed5i T\u00f3ng"
    ],
    "wof:name":"Huoi Tong",
    "wof:placetype":"locality"
},
  "geometry": {"coordinates":[103.12981000000001,21.87277000000001],"type":"Point"}
}