{
  "type": "Feature",
  "properties": {
    "gn:admin1_code":"70.0",
    "gn:asciiname":"Xoi Hoa",
    "gn:country_code":"VN",
    "gn:dem":52,
    "gn:feature_class":"P",
    "gn:feature_code":"PPL",
    "gn:name":"Xoi H\u1ecfa",
    "gn:population":0,
    "gn:timezone":"Asia/Ho_Chi_Minh",
    "iso:country":"VN",
    "name:vie_x_preferred":[
        "Xoi H\u1ecfa"
    ],
    "wof:name":"Xoi Hoa",
    "wof:placetype":"locality"
},
  "geometry": {"coordinates":[104.63068,21.91932000000001],"type":"Point"}
}