{
  "type": "Feature",
  "properties": {
    "gn:admin1_code":"91.0",
    "gn:asciiname":"Buon Pe Gour",
    "gn:country_code":"VN",
    "gn:dem":481,
    "gn:feature_class":"P",
    "gn:feature_code":"PPL",
    "gn:name":"Bu\u00f4n P\u00e9 Gour",
    "gn:population":0,
    "gn:timezone":"Asia/Ho_Chi_Minh",
    "iso:country":"VN",
    "name:vie_x_preferred":[
        "Pegour"
    ],
    "name:vie_x_variant":[
        "Bu\u00f4n P\u00e9 Gour"
    ],
    "wof:name":"Buon Pe Gour",
    "wof:placetype":"locality"
},
  "geometry": {"coordinates":[108.03554,12.26934],"type":"Point"}
}