{
  "type": "Feature",
  "properties": {
    "gn:admin1_code":"83.0",
    "gn:asciiname":"Mai O",
    "gn:country_code":"VN",
    "gn:dem":32,
    "gn:feature_class":"P",
    "gn:feature_code":"PPL",
    "gn:name":"Mai O",
    "gn:population":0,
    "gn:timezone":"Asia/Ho_Chi_Minh",
    "iso:country":"VN",
    "name:vie_x_preferred":[
        "Mai O"
    ],
    "wof:name":"Mai O",
    "wof:placetype":"locality"
},
  "geometry": {"coordinates":[105.05544,21.50856],"type":"Point"}
}