{
  "type": "Feature",
  "properties": {
    "gn:admin1_code":"92.0",
    "gn:asciiname":"Xa Phinh Hai",
    "gn:country_code":"VN",
    "gn:dem":922,
    "gn:feature_class":"P",
    "gn:feature_code":"PPL",
    "gn:name":"X\u00e0 Ph\u00ecnh Hai",
    "gn:population":0,
    "gn:timezone":"Asia/Ho_Chi_Minh",
    "iso:country":"VN",
    "name:vie_x_preferred":[
        "X\u00e0 Ph\u00ecnh Hai"
    ],
    "name:vie_x_variant":[
        "X\u00e0 Ph\u00ecnh 2"
    ],
    "wof:name":"Xa Phinh Hai",
    "wof:placetype":"locality"
},
  "geometry": {"coordinates":[103.21256,21.99205],"type":"Point"}
}