{
  "type": "Feature",
  "properties": {
    "gn:admin1_code":"1.0",
    "gn:asciiname":"Soc Ta Ngao",
    "gn:country_code":"VN",
    "gn:dem":18,
    "gn:feature_class":"P",
    "gn:feature_code":"PPL",
    "gn:name":"S\u00f3c T\u00e0 Ng\u00e1o",
    "gn:population":0,
    "gn:timezone":"Asia/Ho_Chi_Minh",
    "iso:country":"VN",
    "name:und_x_variant":[
        "S\u00f3c T\u00e0 Ngao"
    ],
    "name:vie_x_preferred":[
        "S\u00f3c T\u00e0 Ng\u00e1o"
    ],
    "wof:name":"Soc Ta Ngao",
    "wof:placetype":"locality"
},
  "geometry": {"coordinates":[104.96306,10.61587],"type":"Point"}
}