{
  "type": "Feature",
  "properties": {
    "gn:admin1_code":"32.0",
    "gn:asciiname":"Ban Suoi On",
    "gn:country_code":"VN",
    "gn:dem":927,
    "gn:feature_class":"P",
    "gn:feature_code":"PPL",
    "gn:name":"B\u1ea3n Su\u1ed1i On",
    "gn:population":0,
    "gn:timezone":"Asia/Ho_Chi_Minh",
    "iso:country":"VN",
    "name:vie_x_preferred":[
        "B\u1ea3n Su\u1ed1i On"
    ],
    "wof:name":"Ban Suoi On",
    "wof:placetype":"locality"
},
  "geometry": {"coordinates":[104.58474,21.14207],"type":"Point"}
}