{
  "type": "Feature",
  "properties": {
    "gn:admin1_code":"50.0",
    "gn:asciiname":"Na Chien",
    "gn:country_code":"VN",
    "gn:dem":244,
    "gn:feature_class":"P",
    "gn:feature_code":"PPL",
    "gn:name":"Na Chi\u00ean",
    "gn:population":0,
    "gn:timezone":"Asia/Ho_Chi_Minh",
    "iso:country":"VN",
    "wof:name":"Na Chien",
    "wof:placetype":"locality"
},
  "geometry": {"coordinates":[104.59999999999999,22.36667000000001],"type":"Point"}
}