{
  "type": "Feature",
  "properties": {
    "gn:admin1_code":"10.0",
    "gn:asciiname":"Dak Pokai",
    "gn:country_code":"VN",
    "gn:dem":393,
    "gn:feature_class":"P",
    "gn:feature_code":"PPL",
    "gn:name":"Dak Pokai",
    "gn:population":0,
    "gn:timezone":"Asia/Ho_Chi_Minh",
    "iso:country":"VN",
    "wof:name":"Dak Pokai",
    "wof:placetype":"locality"
},
  "geometry": {"coordinates":[108.31667,14.93333],"type":"Point"}
}