{
  "type": "Feature",
  "properties": {
    "gn:admin1_code":"90.0",
    "gn:asciiname":"Nam Yang",
    "gn:country_code":"VN",
    "gn:dem":818,
    "gn:feature_class":"P",
    "gn:feature_code":"PPL",
    "gn:name":"Nam Yang",
    "gn:population":0,
    "gn:timezone":"Asia/Ho_Chi_Minh",
    "iso:country":"VN",
    "name:und_x_variant":[
        "Nam Tang",
        "Nam Yang"
    ],
    "wof:name":"Nam Yang",
    "wof:placetype":"locality"
},
  "geometry": {"coordinates":[103.68333,22.56667],"type":"Point"}
}