{
  "type": "Feature",
  "properties": {
    "gn:admin1_code":"89.0",
    "gn:asciiname":"Ban Yang",
    "gn:country_code":"VN",
    "gn:dem":716,
    "gn:feature_class":"P",
    "gn:feature_code":"PPL",
    "gn:name":"B\u1ea3n Yang",
    "gn:population":0,
    "gn:timezone":"Asia/Ho_Chi_Minh",
    "iso:country":"VN",
    "name:ceb_x_preferred":[
        "Ban Yang"
    ],
    "wof:name":"Ban Yang",
    "wof:placetype":"locality"
},
  "geometry": {"coordinates":[103.53333000000001,22.31667],"type":"Point"}
}