{
  "type": "Feature",
  "properties": {
    "gn:admin1_code":"58.0",
    "gn:asciiname":"Khu Pho Tam",
    "gn:country_code":"VN",
    "gn:dem":5,
    "gn:feature_class":"P",
    "gn:feature_code":"PPL",
    "gn:name":"Khu Ph\u1ed1 T\u00e1m",
    "gn:population":0,
    "gn:timezone":"Asia/Ho_Chi_Minh",
    "iso:country":"VN",
    "name:vie_x_preferred":[
        "Khu Ph\u1ed1 T\u00e1m"
    ],
    "name:vie_x_variant":[
        "Khu Ph\u1ed1 8"
    ],
    "wof:name":"Khu Pho Tam",
    "wof:placetype":"locality"
},
  "geometry": {"coordinates":[105.62581000000002,19.13653],"type":"Point"}
}