{
  "type": "Feature",
  "properties": {
    "gn:admin1_code":"53.0",
    "gn:asciiname":"Chan Mien",
    "gn:country_code":"VN",
    "gn:dem":245,
    "gn:feature_class":"P",
    "gn:feature_code":"PPL",
    "gn:name":"Ch\u00e2n Mi\u00ean",
    "gn:population":0,
    "gn:timezone":"Asia/Ho_Chi_Minh",
    "iso:country":"VN",
    "name:und_x_variant":[
        "Ch\u00e2h Mi\u00ean",
        "Ch\u00e2n Mi\u00ean"
    ],
    "wof:name":"Chan Mien",
    "wof:placetype":"locality"
},
  "geometry": {"coordinates":[105.51667,20.81667],"type":"Point"}
}