{
  "type": "Feature",
  "properties": {
    "gn:admin1_code":"30.0",
    "gn:asciiname":"Ngan Gam",
    "gn:country_code":"VN",
    "gn:dem":757,
    "gn:feature_class":"P",
    "gn:feature_code":"PPL",
    "gn:name":"Ng\u00e0n G\u1eb7m",
    "gn:population":0,
    "gn:timezone":"Asia/Ho_Chi_Minh",
    "iso:country":"VN",
    "name:vie_x_preferred":[
        "Ng\u00e0n G\u1eb7m"
    ],
    "wof:name":"Ngan Gam",
    "wof:placetype":"locality"
},
  "geometry": {"coordinates":[107.52852,21.54023],"type":"Point"}
}