{
  "type": "Feature",
  "properties": {
    "gn:admin1_code":"32.0",
    "gn:asciiname":"Ban Keo Pia",
    "gn:country_code":"VN",
    "gn:dem":203,
    "gn:feature_class":"P",
    "gn:feature_code":"PPL",
    "gn:name":"B\u1ea3n K\u00e9o P\u1ecba",
    "gn:population":0,
    "gn:timezone":"Asia/Ho_Chi_Minh",
    "iso:country":"VN",
    "name:vie_x_preferred":[
        "K\u00e9o Pia"
    ],
    "name:vie_x_variant":[
        "B\u1ea3n K\u00e9o P\u1ecba"
    ],
    "wof:name":"Ban Keo Pia",
    "wof:placetype":"locality"
},
  "geometry": {"coordinates":[103.62846,21.69673],"type":"Point"}
}