{
  "type": "Feature",
  "properties": {
    "gn:admin1_code":"49.0",
    "gn:asciiname":"Plei Ko Dut",
    "gn:country_code":"VN",
    "gn:dem":729,
    "gn:feature_class":"P",
    "gn:feature_code":"PPL",
    "gn:name":"Plei K\u01a1 Dut",
    "gn:population":0,
    "gn:timezone":"Asia/Ho_Chi_Minh",
    "iso:country":"VN",
    "wof:name":"Plei Ko Dut",
    "wof:placetype":"locality"
},
  "geometry": {"coordinates":[107.96666999999999,14.06667],"type":"Point"}
}