{
  "type": "Feature",
  "properties": {
    "gn:admin1_code":"35.0",
    "gn:asciiname":"Vien Ngoai Khu",
    "gn:country_code":"VN",
    "gn:dem":4,
    "gn:feature_class":"P",
    "gn:feature_code":"PPL",
    "gn:name":"Vi\u00ean Ngoai Khu",
    "gn:population":0,
    "gn:timezone":"Asia/Ho_Chi_Minh",
    "iso:country":"VN",
    "wof:name":"Vien Ngoai Khu",
    "wof:placetype":"locality"
},
  "geometry": {"coordinates":[106.53333000000001,20.31667],"type":"Point"}
}