{
  "type": "Feature",
  "properties": {
    "gn:admin1_code":"71.0",
    "gn:asciiname":"Ngoc Yen",
    "gn:country_code":"VN",
    "gn:dem":17,
    "gn:feature_class":"P",
    "gn:feature_code":"PPL",
    "gn:name":"Ng\u1ecdc Y\u00ean",
    "gn:population":0,
    "gn:timezone":"Asia/Ho_Chi_Minh",
    "iso:country":"VN",
    "name:vie_x_preferred":[
        "Ng\u1ecdc Y\u00ean"
    ],
    "wof:name":"Ngoc Yen",
    "wof:placetype":"locality"
},
  "geometry": {"coordinates":[106.11083000000001,21.36579],"type":"Point"}
}