{
  "type": "Feature",
  "properties": {
    "gn:admin1_code":"23.0",
    "gn:asciiname":"Xieng Tiaran",
    "gn:country_code":"VN",
    "gn:dem":944,
    "gn:feature_class":"P",
    "gn:feature_code":"PPL",
    "gn:name":"Xieng Tiaran",
    "gn:population":0,
    "gn:timezone":"Asia/Ho_Chi_Minh",
    "iso:country":"VN",
    "wof:name":"Xieng Tiaran",
    "wof:placetype":"locality"
},
  "geometry": {"coordinates":[108.53333000000001,11.53333],"type":"Point"}
}