{
  "type": "Feature",
  "properties": {
    "gn:admin1_code":"72.0",
    "gn:asciiname":"Khuoi Coi",
    "gn:country_code":"VN",
    "gn:dem":745,
    "gn:feature_class":"P",
    "gn:feature_code":"PPL",
    "gn:name":"Khu\u1ed5i C\u00f2i",
    "gn:population":0,
    "gn:timezone":"Asia/Ho_Chi_Minh",
    "iso:country":"VN",
    "name:vie_x_preferred":[
        "Khu\u1ed5i C\u00f2i"
    ],
    "wof:name":"Khuoi Coi",
    "wof:placetype":"locality"
},
  "geometry": {"coordinates":[105.98681000000001,22.29324],"type":"Point"}
}