{
  "type": "Feature",
  "properties": {
    "gn:admin1_code":"84.0",
    "gn:asciiname":"Phu Thanh",
    "gn:country_code":"VN",
    "gn:dem":114,
    "gn:feature_class":"P",
    "gn:feature_code":"PPL",
    "gn:name":"Ph\u00fa Thanh",
    "gn:population":0,
    "gn:timezone":"Asia/Ho_Chi_Minh",
    "iso:country":"VN",
    "wof:name":"Phu Thanh",
    "wof:placetype":"locality"
},
  "geometry": {"coordinates":[108.25,15.36667],"type":"Point"}
}