{
  "type": "Feature",
  "properties": {
    "gn:admin1_code":"87.0",
    "gn:asciiname":"Cau Nhiem",
    "gn:country_code":"VN",
    "gn:dem":2,
    "gn:feature_class":"P",
    "gn:feature_code":"PPL",
    "gn:name":"C\u1ea7u Nhi\u1ebfm",
    "gn:population":0,
    "gn:timezone":"Asia/Ho_Chi_Minh",
    "iso:country":"VN",
    "wof:name":"Cau Nhiem",
    "wof:placetype":"locality"
},
  "geometry": {"coordinates":[105.65000000000001,10.01667],"type":"Point"}
}