{
  "type": "Feature",
  "properties": {
    "gn:admin1_code":"39.0",
    "gn:asciiname":"Keo Pai",
    "gn:country_code":"VN",
    "gn:dem":301,
    "gn:feature_class":"P",
    "gn:feature_code":"PPL",
    "gn:name":"K\u00e9o P\u00e0i",
    "gn:population":0,
    "gn:timezone":"Asia/Ho_Chi_Minh",
    "iso:country":"VN",
    "name:vie_x_preferred":[
        "K\u00e9o P\u00e0i"
    ],
    "wof:name":"Keo Pai",
    "wof:placetype":"locality"
},
  "geometry": {"coordinates":[106.98869999999999,21.65944],"type":"Point"}
}