{
  "type": "Feature",
  "properties": {
    "gn:admin1_code":"1.0",
    "gn:asciiname":"Tay Binh",
    "gn:country_code":"VN",
    "gn:dem":10,
    "gn:feature_class":"P",
    "gn:feature_code":"PPL",
    "gn:name":"T\u00e2y B\u00ecnh",
    "gn:population":0,
    "gn:timezone":"Asia/Ho_Chi_Minh",
    "iso:country":"VN",
    "name:vie_x_preferred":[
        "T\u00e2y B\u00ecnh A"
    ],
    "name:vie_x_variant":[
        "T\u00e2y B\u00ecnh"
    ],
    "wof:name":"Tay Binh",
    "wof:placetype":"locality"
},
  "geometry": {"coordinates":[105.37818,10.35029],"type":"Point"}
}