{
  "type": "Feature",
  "properties": {
    "gn:admin1_code":"63.0",
    "gn:asciiname":"Plei Ya Yac",
    "gn:country_code":"VN",
    "gn:dem":279,
    "gn:feature_class":"P",
    "gn:feature_code":"PPL",
    "gn:name":"Plei Ya Yac",
    "gn:population":0,
    "gn:timezone":"Asia/Ho_Chi_Minh",
    "iso:country":"VN",
    "wof:name":"Plei Ya Yac",
    "wof:placetype":"locality"
},
  "geometry": {"coordinates":[108.56667,14.71667],"type":"Point"}
}