{
  "type": "Feature",
  "properties": {
    "gn:admin1_code":"67.0",
    "gn:asciiname":"Ap Giong Dai",
    "gn:cc2":"VN",
    "gn:country_code":"VN",
    "gn:dem":0,
    "gn:feature_class":"P",
    "gn:feature_code":"PPL",
    "gn:name":"\u1ea4p Gi\u1ed3ng D\u00e0i",
    "gn:population":0,
    "gn:timezone":"Asia/Ho_Chi_Minh",
    "iso:country":"VN",
    "name:und_x_variant":[
        "Gi\u1ed3ng D\u00e0i",
        "\u1ea4p Gi\u1ed3ng D\u00e0i"
    ],
    "wof:name":"Ap Giong Dai",
    "wof:placetype":"locality"
},
  "geometry": {"coordinates":[106.50917,9.71722],"type":"Point"}
}