{
  "type": "Feature",
  "properties": {
    "gn:admin1_code":"72.0",
    "gn:asciiname":"Hoang Phai",
    "gn:country_code":"VN",
    "gn:dem":488,
    "gn:feature_class":"P",
    "gn:feature_code":"PPL",
    "gn:name":"Ho\u00e0ng Ph\u1ea3i",
    "gn:population":0,
    "gn:timezone":"Asia/Ho_Chi_Minh",
    "iso:country":"VN",
    "name:und_x_variant":[
        "Ho\u00e0ng Phai",
        "Van Phai"
    ],
    "name:vie_x_preferred":[
        "Ho\u00e0ng Ph\u1ea3i"
    ],
    "wof:name":"Hoang Phai",
    "wof:placetype":"locality"
},
  "geometry": {"coordinates":[105.97636,22.50008],"type":"Point"}
}