{
  "type": "Feature",
  "properties": {
    "gn:admin1_code":"70.0",
    "gn:asciiname":"Khau Thon",
    "gn:country_code":"VN",
    "gn:dem":1047,
    "gn:feature_class":"P",
    "gn:feature_code":"PPL",
    "gn:name":"Khau Th\u00f3n",
    "gn:population":0,
    "gn:timezone":"Asia/Ho_Chi_Minh",
    "iso:country":"VN",
    "name:vie_x_preferred":[
        "Khau Th\u00f3n"
    ],
    "wof:name":"Khau Thon",
    "wof:placetype":"locality"
},
  "geometry": {"coordinates":[104.31559,21.76566],"type":"Point"}
}