{
  "type": "Feature",
  "properties": {
    "gn:admin1_code":"49.0",
    "gn:asciiname":"Lang Klan",
    "gn:country_code":"VN",
    "gn:dem":539,
    "gn:feature_class":"P",
    "gn:feature_code":"PPL",
    "gn:name":"L\u00e0ng Klan",
    "gn:population":0,
    "gn:timezone":"Asia/Ho_Chi_Minh",
    "iso:country":"VN",
    "name:vie_x_preferred":[
        "L\u00e0ng Klan"
    ],
    "wof:name":"Lang Klan",
    "wof:placetype":"locality"
},
  "geometry": {"coordinates":[108.12245,13.74212],"type":"Point"}
}