{
  "type": "Feature",
  "properties": {
    "gn:admin1_code":"88.0",
    "gn:asciiname":"Buon Mo Rong A",
    "gn:country_code":"VN",
    "gn:dem":500,
    "gn:feature_class":"P",
    "gn:feature_code":"PPL",
    "gn:name":"Bu\u00f4n M\u01a1 R\u00f4ng A",
    "gn:population":0,
    "gn:timezone":"Asia/Ho_Chi_Minh",
    "iso:country":"VN",
    "name:vie_x_preferred":[
        "Bu\u00f4n M\u01a1 R\u00f4ng A"
    ],
    "wof:name":"Buon Mo Rong A",
    "wof:placetype":"locality"
},
  "geometry": {"coordinates":[108.44676,12.82209],"type":"Point"}
}