{
  "type": "Feature",
  "properties": {
    "gn:admin1_code":"55.0",
    "gn:asciiname":"Peng Sial Tonot",
    "gn:country_code":"VN",
    "gn:dem":1113,
    "gn:feature_class":"P",
    "gn:feature_code":"PPL",
    "gn:name":"Peng Sial Ton\u00f4t",
    "gn:population":0,
    "gn:timezone":"Asia/Ho_Chi_Minh",
    "iso:country":"VN",
    "name:und_x_variant":[
        "Plei Sial Tenot",
        "Plei Sial Tonot",
        "Peng Sial Ton\u00f4t"
    ],
    "wof:name":"Peng Sial Tonot",
    "wof:placetype":"locality"
},
  "geometry": {"coordinates":[107.68333,15.08333],"type":"Point"}
}