{
  "type": "Feature",
  "properties": {
    "gn:admin1_code":"82.0",
    "gn:asciiname":"Tan Coc",
    "gn:country_code":"VN",
    "gn:dem":5,
    "gn:feature_class":"P",
    "gn:feature_code":"PPL",
    "gn:name":"T\u00e2n C\u1ed1c",
    "gn:population":0,
    "gn:timezone":"Asia/Ho_Chi_Minh",
    "iso:country":"VN",
    "name:und_x_variant":[
        "Tieu Coc",
        "Tien Loc",
        "T\u00e2n C\u1ed1c"
    ],
    "wof:name":"Tan Coc",
    "wof:placetype":"locality"
},
  "geometry": {"coordinates":[106.16667,20.38333],"type":"Point"}
}