{
  "type": "Feature",
  "properties": {
    "gn:admin1_code":"32.0",
    "gn:asciiname":"Xen Cheo",
    "gn:country_code":"VN",
    "gn:dem":525,
    "gn:feature_class":"P",
    "gn:feature_code":"PPL",
    "gn:name":"Xen Ch\u00e8o",
    "gn:population":0,
    "gn:timezone":"Asia/Ho_Chi_Minh",
    "iso:country":"VN",
    "wof:name":"Xen Cheo",
    "wof:placetype":"locality"
},
  "geometry": {"coordinates":[103.71666999999999,21.23333],"type":"Point"}
}