{
  "type": "Feature",
  "properties": {
    "gn:admin1_code":"21.0",
    "gn:asciiname":"Dong Yer",
    "gn:country_code":"VN",
    "gn:dem":1,
    "gn:feature_class":"P",
    "gn:feature_code":"PPL",
    "gn:name":"Dong Yer",
    "gn:population":0,
    "gn:timezone":"Asia/Ho_Chi_Minh",
    "iso:country":"VN",
    "name:und_x_variant":[
        "\u0110\u00f4ng Y\u00ean"
    ],
    "wof:name":"Dong Yer",
    "wof:placetype":"locality"
},
  "geometry": {"coordinates":[105.06667,9.93333],"type":"Point"}
}