{
  "type": "Feature",
  "properties": {
    "gn:admin1_code":"53.0",
    "gn:asciiname":"Chi Gao",
    "gn:country_code":"VN",
    "gn:dem":724,
    "gn:feature_class":"P",
    "gn:feature_code":"PPL",
    "gn:name":"Ch\u00ed Gao",
    "gn:population":0,
    "gn:timezone":"Asia/Ho_Chi_Minh",
    "iso:country":"VN",
    "wof:name":"Chi Gao",
    "wof:placetype":"locality"
},
  "geometry": {"coordinates":[105.31667,20.43333],"type":"Point"}
}