{
  "type": "Feature",
  "properties": {
    "gn:admin1_code":"32.0",
    "gn:asciiname":"Ban Hat Lay",
    "gn:country_code":"VN",
    "gn:dem":209,
    "gn:feature_class":"P",
    "gn:feature_code":"PPL",
    "gn:name":"B\u1ea3n H\u00e1t L\u00e2y",
    "gn:population":0,
    "gn:timezone":"Asia/Ho_Chi_Minh",
    "iso:country":"VN",
    "name:vie_x_preferred":[
        "B\u1ea3n H\u00e1t L\u00e2y"
    ],
    "wof:name":"Ban Hat Lay",
    "wof:placetype":"locality"
},
  "geometry": {"coordinates":[103.61673,21.69829],"type":"Point"}
}