{
  "type": "Feature",
  "properties": {
    "gn:admin1_code":"30.0",
    "gn:asciiname":"Pac Linh",
    "gn:country_code":"VN",
    "gn:dem":229,
    "gn:feature_class":"P",
    "gn:feature_code":"PPL",
    "gn:name":"Pac Linh",
    "gn:population":0,
    "gn:timezone":"Asia/Ho_Chi_Minh",
    "iso:country":"VN",
    "wof:name":"Pac Linh",
    "wof:placetype":"locality"
},
  "geometry": {"coordinates":[107.43333,21.48333],"type":"Point"}
}