{
  "type": "Feature",
  "properties": {
    "gn:admin1_code":"32.0",
    "gn:asciiname":"Ban Pum",
    "gn:country_code":"VN",
    "gn:dem":283,
    "gn:feature_class":"P",
    "gn:feature_code":"PPL",
    "gn:name":"B\u1ea3n P\u00fam",
    "gn:population":0,
    "gn:timezone":"Asia/Ho_Chi_Minh",
    "iso:country":"VN",
    "name:vie_x_preferred":[
        "B\u1ea3n P\u00fam"
    ],
    "wof:name":"Ban Pum",
    "wof:placetype":"locality"
},
  "geometry": {"coordinates":[103.58063,21.81254],"type":"Point"}
}