{
  "type": "Feature",
  "properties": {
    "gn:admin1_code":"75.0",
    "gn:asciiname":"Phu Hoa",
    "gn:country_code":"VN",
    "gn:dem":38,
    "gn:feature_class":"P",
    "gn:feature_code":"PPL",
    "gn:name":"Ph\u00fa H\u00f2a",
    "gn:population":0,
    "gn:timezone":"Asia/Ho_Chi_Minh",
    "iso:country":"VN",
    "name:und_x_variant":[
        "Ph\u00fa H\u00f2a",
        "H\u00f2a L\u1ee3i"
    ],
    "wof:name":"Phu Hoa",
    "wof:placetype":"locality"
},
  "geometry": {"coordinates":[106.65680999999999,11.06578],"type":"Point"}
}