{
  "type": "Feature",
  "properties": {
    "gn:admin1_code":"71.0",
    "gn:asciiname":"My Nuong",
    "gn:country_code":"VN",
    "gn:dem":12,
    "gn:feature_class":"P",
    "gn:feature_code":"PPL",
    "gn:name":"M\u1ef9 N\u01b0\u01a1ng",
    "gn:population":0,
    "gn:timezone":"Asia/Ho_Chi_Minh",
    "iso:country":"VN",
    "name:und_x_variant":[
        "Mi Nuong",
        "M\u1ef9 N\u01b0\u01a1ng"
    ],
    "wof:name":"My Nuong",
    "wof:placetype":"locality"
},
  "geometry": {"coordinates":[106.51667,21.33333],"type":"Point"}
}