{
  "type": "Feature",
  "properties": {
    "gn:admin1_code":"13.0",
    "gn:asciiname":"Truc Cat",
    "gn:country_code":"VN",
    "gn:dem":5,
    "gn:feature_class":"P",
    "gn:feature_code":"PPL",
    "gn:name":"Tr\u1ef1c C\u00e1t",
    "gn:population":0,
    "gn:timezone":"Asia/Ho_Chi_Minh",
    "iso:country":"VN",
    "wof:name":"Truc Cat",
    "wof:placetype":"locality"
},
  "geometry": {"coordinates":[106.73333,20.81667],"type":"Point"}
}