{
  "type": "Feature",
  "properties": {
    "gn:admin1_code":"89.0",
    "gn:asciiname":"Ban Na Hin",
    "gn:cc2":"VN",
    "gn:country_code":"VN",
    "gn:dem":331,
    "gn:feature_class":"P",
    "gn:feature_code":"PPL",
    "gn:name":"B\u1ea3n Na Hin",
    "gn:population":0,
    "gn:timezone":"Asia/Ho_Chi_Minh",
    "iso:country":"VN",
    "name:und_x_variant":[
        "B\u1ea3n Na Min",
        "B\u1ea3n Na Hin"
    ],
    "wof:name":"Ban Na Hin",
    "wof:placetype":"locality"
},
  "geometry": {"coordinates":[102.93333,22.21667],"type":"Point"}
}