{
  "type": "Feature",
  "properties": {
    "gn:admin1_code":"39.0",
    "gn:asciiname":"My Let",
    "gn:country_code":"VN",
    "gn:dem":200,
    "gn:feature_class":"P",
    "gn:feature_code":"PPL",
    "gn:name":"M\u1ef9 L\u00e9t",
    "gn:population":0,
    "gn:timezone":"Asia/Ho_Chi_Minh",
    "iso:country":"VN",
    "wof:name":"My Let",
    "wof:placetype":"locality"
},
  "geometry": {"coordinates":[106.56667,21.98333],"type":"Point"}
}