{
  "type": "Feature",
  "properties": {
    "gn:admin1_code":"93.0",
    "gn:asciiname":"Son Phu Hai",
    "gn:country_code":"VN",
    "gn:dem":6,
    "gn:feature_class":"P",
    "gn:feature_code":"PPL",
    "gn:name":"S\u01a1n Ph\u00fa Hai",
    "gn:population":0,
    "gn:timezone":"Asia/Ho_Chi_Minh",
    "iso:country":"VN",
    "name:vie_x_preferred":[
        "S\u01a1n Ph\u00fa Hai"
    ],
    "name:vie_x_variant":[
        "S\u01a1n Ph\u00fa 2"
    ],
    "wof:name":"Son Phu Hai",
    "wof:placetype":"locality"
},
  "geometry": {"coordinates":[105.83778999999998,9.87119],"type":"Point"}
}