{
  "type": "Feature",
  "properties": {
    "gn:admin1_code":"88.0",
    "gn:asciiname":"Buon Bhoa",
    "gn:country_code":"VN",
    "gn:dem":455,
    "gn:feature_class":"P",
    "gn:feature_code":"PPL",
    "gn:name":"Bu\u00f4n Bhoa",
    "gn:population":0,
    "gn:timezone":"Asia/Ho_Chi_Minh",
    "iso:country":"VN",
    "name:vie_x_preferred":[
        "Bu\u00f4n Bhoa"
    ],
    "wof:name":"Buon Bhoa",
    "wof:placetype":"locality"
},
  "geometry": {"coordinates":[108.18353,12.58459],"type":"Point"}
}