{
  "type": "Feature",
  "properties": {
    "gn:admin1_code":"90.0",
    "gn:asciiname":"Thon Kim",
    "gn:country_code":"VN",
    "gn:dem":216,
    "gn:feature_class":"P",
    "gn:feature_code":"PPL",
    "gn:name":"Th\u00f4n Kim",
    "gn:population":0,
    "gn:timezone":"Asia/Ho_Chi_Minh",
    "iso:country":"VN",
    "name:vie_x_preferred":[
        "Th\u00f4n Kim"
    ],
    "wof:name":"Thon Kim",
    "wof:placetype":"locality"
},
  "geometry": {"coordinates":[103.89219,22.49402000000001],"type":"Point"}
}