{
  "type": "Feature",
  "properties": {
    "gn:admin1_code":"62.0",
    "gn:asciiname":"Hop Trung",
    "gn:country_code":"VN",
    "gn:dem":27,
    "gn:feature_class":"P",
    "gn:feature_code":"PPL",
    "gn:name":"H\u1ee3p Trung",
    "gn:population":0,
    "gn:timezone":"Asia/Ho_Chi_Minh",
    "iso:country":"VN",
    "name:vie_x_preferred":[
        "H\u1ee3p Trung"
    ],
    "wof:name":"Hop Trung",
    "wof:placetype":"locality"
},
  "geometry": {"coordinates":[106.346,17.9245],"type":"Point"}
}