{
  "type": "Feature",
  "properties": {
    "gn:admin1_code":"66.0",
    "gn:asciiname":"Cat Thuong",
    "gn:country_code":"VN",
    "gn:dem":9,
    "gn:feature_class":"P",
    "gn:feature_code":"PPL",
    "gn:name":"C\u00e1t Th\u01b0\u1ee3ng",
    "gn:population":0,
    "gn:timezone":"Asia/Ho_Chi_Minh",
    "iso:country":"VN",
    "name:und_x_variant":[
        "X\u00f3m C\u00e1t Th\u01b0\u1ee3ng"
    ],
    "name:vie_x_preferred":[
        "C\u00e1t Th\u01b0\u1ee3ng"
    ],
    "wof:name":"Cat Thuong",
    "wof:placetype":"locality"
},
  "geometry": {"coordinates":[107.72552,16.34672],"type":"Point"}
}