{
  "type": "Feature",
  "properties": {
    "gn:admin1_code":"72.0",
    "gn:asciiname":"Ban Chang",
    "gn:country_code":"VN",
    "gn:dem":139,
    "gn:feature_class":"P",
    "gn:feature_code":"PPL",
    "gn:name":"B\u1ea3n Ch\u00e2ng",
    "gn:population":0,
    "gn:timezone":"Asia/Ho_Chi_Minh",
    "iso:country":"VN",
    "name:vie_x_preferred":[
        "B\u1ea3n Ch\u00e2ng"
    ],
    "wof:name":"Ban Chang",
    "wof:placetype":"locality"
},
  "geometry": {"coordinates":[105.9194,22.16088],"type":"Point"}
}