{
  "type": "Feature",
  "properties": {
    "gn:admin1_code":"68.0",
    "gn:asciiname":"Khoun Nieou",
    "gn:country_code":"VN",
    "gn:dem":285,
    "gn:feature_class":"P",
    "gn:feature_code":"PPL",
    "gn:name":"Khoun Nieou",
    "gn:population":0,
    "gn:timezone":"Asia/Ho_Chi_Minh",
    "iso:country":"VN",
    "name:und_x_variant":[
        "Khoun Nieo",
        "Khoun Nieou"
    ],
    "wof:name":"Khoun Nieou",
    "wof:placetype":"locality"
},
  "geometry": {"coordinates":[105.13333,22.13333],"type":"Point"}
}