{
  "type": "Feature",
  "properties": {
    "gn:admin1_code":"32.0",
    "gn:asciiname":"Ban Buom",
    "gn:country_code":"VN",
    "gn:dem":282,
    "gn:feature_class":"P",
    "gn:feature_code":"PPL",
    "gn:name":"B\u1ea3n B\u01b0\u1edbm",
    "gn:population":0,
    "gn:timezone":"Asia/Ho_Chi_Minh",
    "iso:country":"VN",
    "name:vie_x_preferred":[
        "B\u1ea3n B\u01b0\u1edbm"
    ],
    "wof:name":"Ban Buom",
    "wof:placetype":"locality"
},
  "geometry": {"coordinates":[104.0027,21.55087],"type":"Point"}
}