{
  "type": "Feature",
  "properties": {
    "gn:admin1_code":"58.0",
    "gn:asciiname":"Yen My",
    "gn:country_code":"VN",
    "gn:dem":26,
    "gn:feature_class":"P",
    "gn:feature_code":"PPL",
    "gn:name":"Y\u00ean M\u1ef9",
    "gn:population":0,
    "gn:timezone":"Asia/Ho_Chi_Minh",
    "iso:country":"VN",
    "name:und_x_variant":[
        "Y\u00ean M\u1ef9"
    ],
    "name:vie_x_preferred":[
        "Yen My"
    ],
    "wof:name":"Yen My",
    "wof:placetype":"locality"
},
  "geometry": {"coordinates":[105.34392,18.95119],"type":"Point"}
}