{
  "type": "Feature",
  "properties": {
    "gn:admin1_code":"30.0",
    "gn:asciiname":"Quang Yen",
    "gn:country_code":"VN",
    "gn:dem":9,
    "gn:feature_class":"P",
    "gn:feature_code":"PPLA2",
    "gn:name":"Qu\u1ea3ng Y\u00ean",
    "gn:population":0,
    "gn:timezone":"Asia/Ho_Chi_Minh",
    "iso:country":"VN",
    "name:jpn_x_preferred":[
        "\u30af\u30a2\u30f3\u30a4\u30a8\u30f3"
    ],
    "name:und_x_variant":[
        "Kang Yen",
        "Kwang Yen",
        "Qu\u1ea3ng Y\u00ean"
    ],
    "name:vie_x_preferred":[
        "Qu\u1ea3ng Y\u00ean"
    ],
    "name:zho_x_preferred":[
        "\u5ee3\u5b89\u5e02\u793e"
    ],
    "wof:name":"Quang Yen",
    "wof:placetype":"locality"
},
  "geometry": {"coordinates":[106.8027,20.9421],"type":"Point"}
}