{
  "type": "Feature",
  "properties": {
    "gn:admin1_code":"33.0",
    "gn:asciiname":"Con Tran",
    "gn:country_code":"VN",
    "gn:dem":64,
    "gn:feature_class":"P",
    "gn:feature_code":"PPL",
    "gn:name":"Con Tr\u0103n",
    "gn:population":0,
    "gn:timezone":"Asia/Ho_Chi_Minh",
    "iso:country":"VN",
    "name:und_x_variant":[
        "Sroo Con Trang",
        "Srok Can Trang",
        "Sr\u1ed1c Con Tr\u0103ng",
        "Con Tr\u0103n"
    ],
    "wof:name":"Con Tran",
    "wof:placetype":"locality"
},
  "geometry": {"coordinates":[106.43001,11.61808],"type":"Point"}
}