{
  "type": "Feature",
  "properties": {
    "gn:admin1_code":"84.0",
    "gn:asciiname":"Beneang Ko",
    "gn:country_code":"VN",
    "gn:dem":1170,
    "gn:feature_class":"P",
    "gn:feature_code":"PPL",
    "gn:name":"B\u00e9n\u00eaang Ko",
    "gn:population":0,
    "gn:timezone":"Asia/Ho_Chi_Minh",
    "iso:country":"VN",
    "wof:name":"Beneang Ko",
    "wof:placetype":"locality"
},
  "geometry": {"coordinates":[107.83333,15.25],"type":"Point"}
}