{
  "type": "Feature",
  "properties": {
    "gn:admin1_code":"38.0",
    "gn:asciiname":"Ha Gia",
    "gn:cc2":"VN",
    "gn:country_code":"VN",
    "gn:dem":14,
    "gn:feature_class":"P",
    "gn:feature_code":"PPL",
    "gn:name":"H\u1ea1 Gia",
    "gn:population":0,
    "gn:timezone":"Asia/Ho_Chi_Minh",
    "iso:country":"VN",
    "name:und_x_variant":[
        "Da Phuc",
        "Ho Oia",
        "H\u1ea1 Gia"
    ],
    "wof:name":"Ha Gia",
    "wof:placetype":"locality"
},
  "geometry": {"coordinates":[105.86667,21.33333],"type":"Point"}
}