{
  "type": "Feature",
  "properties": {
    "gn:admin1_code":"46.0",
    "gn:asciiname":"Tuy Phuoc",
    "gn:country_code":"VN",
    "gn:dem":8,
    "gn:feature_class":"P",
    "gn:feature_code":"PPLA2",
    "gn:name":"Tuy Ph\u01b0\u1edbc",
    "gn:population":0,
    "gn:timezone":"Asia/Ho_Chi_Minh",
    "iso:country":"VN",
    "name:und_x_variant":[
        "Trung T\u00edn",
        "Tuy Ph\u01b0\u01a1c"
    ],
    "name:vie_x_preferred":[
        "Tuy Ph\u01b0\u1edbc"
    ],
    "wof:name":"Tuy Phuoc",
    "wof:placetype":"locality"
},
  "geometry": {"coordinates":[109.16651,13.82738],"type":"Point"}
}