{
  "type": "Feature",
  "properties": {
    "gn:admin1_code":"34.0",
    "gn:asciiname":"Yen Hoa Thuong",
    "gn:cc2":"VN",
    "gn:country_code":"VN",
    "gn:dem":167,
    "gn:feature_class":"P",
    "gn:feature_code":"PPL",
    "gn:name":"Y\u00ean Hoa Th\u01b0\u01a1ng",
    "gn:population":0,
    "gn:timezone":"Asia/Ho_Chi_Minh",
    "iso:country":"VN",
    "name:und_x_variant":[
        "Yen Hoa",
        "Y\u00ean Hoa Th\u01b0\u01a1ng"
    ],
    "wof:name":"Yen Hoa Thuong",
    "wof:placetype":"locality"
},
  "geometry": {"coordinates":[105.78333000000001,19.31667],"type":"Point"}
}