{
  "type": "Feature",
  "properties": {
    "gn:admin1_code":"81.0",
    "gn:asciiname":"Kha Duy",
    "gn:country_code":"VN",
    "gn:dem":6,
    "gn:feature_class":"P",
    "gn:feature_code":"PPL",
    "gn:name":"Kh\u1ea3 Duy",
    "gn:population":0,
    "gn:timezone":"Asia/Ho_Chi_Minh",
    "iso:country":"VN",
    "name:vie_x_preferred":[
        "Kh\u1ea3 Duy"
    ],
    "wof:name":"Kha Duy",
    "wof:placetype":"locality"
},
  "geometry": {"coordinates":[106.15340999999999,20.71635],"type":"Point"}
}