{
  "type": "Feature",
  "properties": {
    "gn:admin1_code":"90.0",
    "gn:asciiname":"Tang",
    "gn:country_code":"VN",
    "gn:dem":1345,
    "gn:feature_class":"P",
    "gn:feature_code":"PPL",
    "gn:name":"Tang",
    "gn:population":0,
    "gn:timezone":"Asia/Ho_Chi_Minh",
    "iso:country":"VN",
    "name:ceb_x_preferred":[
        "Tang"
    ],
    "name:dan_x_preferred":[
        "Tang"
    ],
    "name:deu_x_preferred":[
        "Tang"
    ],
    "name:est_x_preferred":[
        "Tang"
    ],
    "name:fin_x_preferred":[
        "Tang"
    ],
    "name:fra_x_preferred":[
        "Tang"
    ],
    "name:hun_x_preferred":[
        "Tang"
    ],
    "name:nld_x_preferred":[
        "Tang"
    ],
    "name:nor_x_preferred":[
        "Tang"
    ],
    "name:pol_x_preferred":[
        "Tang"
    ],
    "name:rus_x_preferred":[
        "\u0422\u0430\u043d\u0433"
    ],
    "name:spa_x_preferred":[
        "Tang"
    ],
    "name:swe_x_preferred":[
        "Tang"
    ],
    "name:ukr_x_preferred":[
        "\u0422\u0430\u043d\u0433"
    ],
    "wof:name":"Tang",
    "wof:placetype":"locality"
},
  "geometry": {"coordinates":[104.16667,22.61667000000001],"type":"Point"}
}