{
  "type": "Feature",
  "properties": {
    "gn:admin1_code":"68.0",
    "gn:asciiname":"Mo Tom",
    "gn:country_code":"VN",
    "gn:dem":31,
    "gn:feature_class":"P",
    "gn:feature_code":"PPL",
    "gn:name":"M\u00f4 T\u00f4m",
    "gn:population":0,
    "gn:timezone":"Asia/Ho_Chi_Minh",
    "iso:country":"VN",
    "name:vie_x_preferred":[
        "M\u00f4 T\u00f4m"
    ],
    "wof:name":"Mo Tom",
    "wof:placetype":"locality"
},
  "geometry": {"coordinates":[105.23299,21.73553],"type":"Point"}
}