{
  "type": "Feature",
  "properties": {
    "gn:admin1_code":"43.0",
    "gn:asciiname":"Da Kai",
    "gn:country_code":"VN",
    "gn:dem":114,
    "gn:feature_class":"P",
    "gn:feature_code":"PPL",
    "gn:name":"\u0110a Kai",
    "gn:population":0,
    "gn:timezone":"Asia/Ho_Chi_Minh",
    "iso:country":"VN",
    "name:und_x_variant":[
        "Ba Xe",
        "Da Kai"
    ],
    "name:vie_x_preferred":[
        "\u0110a Kai"
    ],
    "wof:name":"Da Kai",
    "wof:placetype":"locality"
},
  "geometry": {"coordinates":[107.52261,11.26415],"type":"Point"}
}