{
  "type": "Feature",
  "properties": {
    "gn:admin1_code":"52.0",
    "gn:asciiname":"Thuong Hai",
    "gn:country_code":"VN",
    "gn:dem":13,
    "gn:feature_class":"P",
    "gn:feature_code":"PPL",
    "gn:name":"Th\u01b0\u1ee3ng H\u1ea3i",
    "gn:population":0,
    "gn:timezone":"Asia/Ho_Chi_Minh",
    "iso:country":"VN",
    "name:vie_x_preferred":[
        "Th\u01b0\u1ee3ng H\u1ea3i"
    ],
    "wof:name":"Thuong Hai",
    "wof:placetype":"locality"
},
  "geometry": {"coordinates":[105.96678,18.41172000000001],"type":"Point"}
}