{
  "type": "Feature",
  "properties": {
    "gn:admin1_code":"54.0",
    "gn:asciiname":"Thon Phu Dang",
    "gn:country_code":"VN",
    "gn:dem":3,
    "gn:feature_class":"P",
    "gn:feature_code":"PPL",
    "gn:name":"Th\u00f4n Ph\u00fa \u0110\u0103ng",
    "gn:population":0,
    "gn:timezone":"Asia/Ho_Chi_Minh",
    "iso:country":"VN",
    "name:und_x_variant":[
        "Phu Da",
        "Th\u00f4n Ph\u00fa \u0110\u0103ng"
    ],
    "wof:name":"Thon Phu Dang",
    "wof:placetype":"locality"
},
  "geometry": {"coordinates":[109.11667,12.48333],"type":"Point"}
}