{
  "type": "Feature",
  "properties": {
    "gn:admin1_code":"88.0",
    "gn:asciiname":"Khoi Nam",
    "gn:country_code":"VN",
    "gn:dem":526,
    "gn:feature_class":"P",
    "gn:feature_code":"PPL",
    "gn:name":"Kh\u1ed1i N\u0103m",
    "gn:population":0,
    "gn:timezone":"Asia/Ho_Chi_Minh",
    "iso:country":"VN",
    "name:vie_x_preferred":[
        "Kh\u1ed1i N\u0103m"
    ],
    "name:vie_x_variant":[
        "Kh\u1ed1i 5"
    ],
    "wof:name":"Khoi Nam",
    "wof:placetype":"locality"
},
  "geometry": {"coordinates":[108.05992999999999,12.70025],"type":"Point"}
}