{
  "type": "Feature",
  "properties": {
    "gn:admin1_code":"68.0",
    "gn:asciiname":"Khang Ha",
    "gn:country_code":"VN",
    "gn:dem":64,
    "gn:feature_class":"P",
    "gn:feature_code":"PPL",
    "gn:name":"Khang Ha",
    "gn:population":0,
    "gn:timezone":"Asia/Ho_Chi_Minh",
    "iso:country":"VN",
    "name:und_x_variant":[
        "Kh\u00e0ng Ha"
    ],
    "name:vie_x_preferred":[
        "Khang Ha"
    ],
    "wof:name":"Khang Ha",
    "wof:placetype":"locality"
},
  "geometry": {"coordinates":[105.01893,22.1767],"type":"Point"}
}