{
  "type": "Feature",
  "properties": {
    "gn:admin1_code":"58.0",
    "gn:asciiname":"Ban Dai",
    "gn:country_code":"VN",
    "gn:dem":496,
    "gn:feature_class":"P",
    "gn:feature_code":"PPL",
    "gn:name":"B\u1ea3n Dai",
    "gn:population":0,
    "gn:timezone":"Asia/Ho_Chi_Minh",
    "iso:country":"VN",
    "name:nld_x_preferred":[
        "Ban Dai"
    ],
    "wof:name":"Ban Dai",
    "wof:placetype":"locality"
},
  "geometry": {"coordinates":[104.98333,19.55],"type":"Point"}
}