{
  "type": "Feature",
  "properties": {
    "gn:admin1_code":"46.0",
    "gn:asciiname":"Ngai An",
    "gn:country_code":"VN",
    "gn:dem":229,
    "gn:feature_class":"P",
    "gn:feature_code":"PPL",
    "gn:name":"Ng\u00e0i An",
    "gn:population":0,
    "gn:timezone":"Asia/Ho_Chi_Minh",
    "iso:country":"VN",
    "name:und_x_variant":[
        "Phu Ngai",
        "Ng\u00e0i An"
    ],
    "wof:name":"Ngai An",
    "wof:placetype":"locality"
},
  "geometry": {"coordinates":[109.16667,14.11667],"type":"Point"}
}