{
  "type": "Feature",
  "properties": {
    "gn:admin1_code":"40.0",
    "gn:asciiname":"Luong Thien",
    "gn:country_code":"VN",
    "gn:dem":4,
    "gn:feature_class":"P",
    "gn:feature_code":"PPL",
    "gn:name":"L\u01b0\u01a1ng Thi\u1ec7n",
    "gn:population":0,
    "gn:timezone":"Asia/Ho_Chi_Minh",
    "iso:country":"VN",
    "wof:name":"Luong Thien",
    "wof:placetype":"locality"
},
  "geometry": {"coordinates":[106.75888999999999,10.71611],"type":"Point"}
}