{
  "type": "Feature",
  "properties": {
    "gn:admin1_code":"55.0",
    "gn:asciiname":"Kon Kokotu",
    "gn:country_code":"VN",
    "gn:dem":921,
    "gn:feature_class":"P",
    "gn:feature_code":"PPL",
    "gn:name":"Kon Kok\u01a1tu",
    "gn:population":0,
    "gn:timezone":"Asia/Ho_Chi_Minh",
    "iso:country":"VN",
    "name:und_x_variant":[
        "Konko Tou",
        "Kon Kok\u01a1tu"
    ],
    "wof:name":"Kon Kokotu",
    "wof:placetype":"locality"
},
  "geometry": {"coordinates":[108.06667,14.53333],"type":"Point"}
}