{
  "type": "Feature",
  "properties": {
    "gn:admin1_code":"88.0",
    "gn:asciiname":"Ea Nao B",
    "gn:country_code":"VN",
    "gn:dem":520,
    "gn:feature_class":"P",
    "gn:feature_code":"PPL",
    "gn:name":"Ea Nao B",
    "gn:population":0,
    "gn:timezone":"Asia/Ho_Chi_Minh",
    "iso:country":"VN",
    "name:vie_x_preferred":[
        "Ea Nao B"
    ],
    "wof:name":"Ea Nao B",
    "wof:placetype":"locality"
},
  "geometry": {"coordinates":[108.09869,12.70165],"type":"Point"}
}