{
  "type": "Feature",
  "properties": {
    "gn:admin1_code":"89.0",
    "gn:asciiname":"Ban Nam Han",
    "gn:country_code":"VN",
    "gn:dem":433,
    "gn:feature_class":"P",
    "gn:feature_code":"PPL",
    "gn:name":"B\u1ea3n N\u1eb1m H\u1ea3n",
    "gn:population":0,
    "gn:timezone":"Asia/Ho_Chi_Minh",
    "iso:country":"VN",
    "wof:name":"Ban Nam Han",
    "wof:placetype":"locality"
},
  "geometry": {"coordinates":[102.65000000000001,22.46667],"type":"Point"}
}