{
  "type": "Feature",
  "properties": {
    "gn:admin1_code":"23.0",
    "gn:asciiname":"Ap Dai Nga",
    "gn:country_code":"VN",
    "gn:dem":776,
    "gn:feature_class":"P",
    "gn:feature_code":"PPL",
    "gn:name":"\u1ea4p \u0110\u1ea1i Nga",
    "gn:population":0,
    "gn:timezone":"Asia/Ho_Chi_Minh",
    "iso:country":"VN",
    "name:und_x_variant":[
        "\u0110ai Nga",
        "\u1ea4p \u0110\u1ea1i Nga"
    ],
    "wof:name":"Ap Dai Nga",
    "wof:placetype":"locality"
},
  "geometry": {"coordinates":[107.86667,11.53333],"type":"Point"}
}