{
  "type": "Feature",
  "properties": {
    "gn:admin1_code":"68.0",
    "gn:asciiname":"Lang Phat",
    "gn:country_code":"VN",
    "gn:dem":124,
    "gn:feature_class":"P",
    "gn:feature_code":"PPL",
    "gn:name":"L\u00e0ng Phat",
    "gn:population":0,
    "gn:timezone":"Asia/Ho_Chi_Minh",
    "iso:country":"VN",
    "name:und_x_variant":[
        "L\u00e0ng \u0110at"
    ],
    "name:vie_x_preferred":[
        "L\u00e0ng Phat"
    ],
    "wof:name":"Lang Phat",
    "wof:placetype":"locality"
},
  "geometry": {"coordinates":[105.19927,22.38518],"type":"Point"}
}