{
  "type": "Feature",
  "properties": {
    "gn:admin1_code":"32.0",
    "gn:asciiname":"Ban Pou Ha",
    "gn:cc2":"VN",
    "gn:country_code":"VN",
    "gn:dem":940,
    "gn:feature_class":"P",
    "gn:feature_code":"PPL",
    "gn:name":"B\u1ea3n Pou Ha",
    "gn:population":0,
    "gn:timezone":"Asia/Ho_Chi_Minh",
    "iso:country":"VN",
    "name:und_x_variant":[
        "Ban Pau Ha",
        "B\u1ea3n Pou Ha"
    ],
    "wof:name":"Ban Pou Ha",
    "wof:placetype":"locality"
},
  "geometry": {"coordinates":[103.45,21.28333],"type":"Point"}
}