{
  "type": "Feature",
  "properties": {
    "gn:admin1_code":"81.0",
    "gn:asciiname":"Hoa Dam",
    "gn:country_code":"VN",
    "gn:dem":7,
    "gn:feature_class":"P",
    "gn:feature_code":"PPL",
    "gn:name":"H\u00f2a \u0110am",
    "gn:population":0,
    "gn:timezone":"Asia/Ho_Chi_Minh",
    "iso:country":"VN",
    "name:vie_x_preferred":[
        "H\u00f2a \u0110am"
    ],
    "wof:name":"Hoa Dam",
    "wof:placetype":"locality"
},
  "geometry": {"coordinates":[106.14243,20.95278],"type":"Point"}
}