{
  "type": "Feature",
  "properties": {
    "gn:admin1_code":"83.0",
    "gn:asciiname":"Xom Ham",
    "gn:country_code":"VN",
    "gn:dem":89,
    "gn:feature_class":"P",
    "gn:feature_code":"PPL",
    "gn:name":"X\u00f3m H\u1ea5m",
    "gn:population":0,
    "gn:timezone":"Asia/Ho_Chi_Minh",
    "iso:country":"VN",
    "name:vie_x_preferred":[
        "X\u00f3m H\u1ea5m"
    ],
    "wof:name":"Xom Ham",
    "wof:placetype":"locality"
},
  "geometry": {"coordinates":[105.13727,21.02682],"type":"Point"}
}