{
  "type": "Feature",
  "properties": {
    "gn:admin1_code":"64.0",
    "gn:asciiname":"Lang Ho",
    "gn:country_code":"VN",
    "gn:dem":601,
    "gn:feature_class":"P",
    "gn:feature_code":"PPL",
    "gn:name":"L\u00e0ng H\u1ed3",
    "gn:population":0,
    "gn:timezone":"Asia/Ho_Chi_Minh",
    "iso:country":"VN",
    "name:und_x_variant":[
        "L\u00e0ng H\u00f4"
    ],
    "name:vie_x_preferred":[
        "L\u00e0ng H\u1ed3"
    ],
    "wof:name":"Lang Ho",
    "wof:placetype":"locality"
},
  "geometry": {"coordinates":[106.66278,16.81574],"type":"Point"}
}