{
  "type": "Feature",
  "properties": {
    "gn:admin1_code":"46.0",
    "gn:asciiname":"Xom Dong Le",
    "gn:country_code":"VN",
    "gn:dem":85,
    "gn:feature_class":"P",
    "gn:feature_code":"PPL",
    "gn:name":"Xom Dong Le",
    "gn:population":0,
    "gn:timezone":"Asia/Ho_Chi_Minh",
    "iso:country":"VN",
    "name:und_x_variant":[
        "\u0110\u1ed3ng La",
        "\u0110\u1ed3ng Le"
    ],
    "wof:name":"Xom Dong Le",
    "wof:placetype":"locality"
},
  "geometry": {"coordinates":[108.84999999999999,13.86667],"type":"Point"}
}