{
  "type": "Feature",
  "properties": {
    "gn:admin1_code":"89.0",
    "gn:asciiname":"Nam Tau",
    "gn:country_code":"VN",
    "gn:dem":517,
    "gn:feature_class":"P",
    "gn:feature_code":"PPL",
    "gn:name":"N\u1eadm T\u1ea5u",
    "gn:population":0,
    "gn:timezone":"Asia/Ho_Chi_Minh",
    "iso:country":"VN",
    "name:vie_x_preferred":[
        "N\u1eadm T\u1ea5u"
    ],
    "wof:name":"Nam Tau",
    "wof:placetype":"locality"
},
  "geometry": {"coordinates":[103.7158,21.91694],"type":"Point"}
}