{
  "type": "Feature",
  "properties": {
    "gn:admin1_code":"3.0",
    "gn:asciiname":"An Hoa",
    "gn:country_code":"VN",
    "gn:dem":2,
    "gn:feature_class":"P",
    "gn:feature_code":"PPL",
    "gn:name":"An H\u00f2a",
    "gn:population":0,
    "gn:timezone":"Asia/Ho_Chi_Minh",
    "iso:country":"VN",
    "name:vie_x_preferred":[
        "An H\u00f2a"
    ],
    "wof:name":"An Hoa",
    "wof:placetype":"locality"
},
  "geometry": {"coordinates":[106.18966,10.23217],"type":"Point"}
}