{
  "type": "Feature",
  "properties": {
    "gn:admin1_code":"83.0",
    "gn:asciiname":"Co Tiet Rung",
    "gn:country_code":"VN",
    "gn:dem":34,
    "gn:feature_class":"P",
    "gn:feature_code":"PPL",
    "gn:name":"C\u1ed5 Ti\u1ebft R\u01b0ng",
    "gn:population":0,
    "gn:timezone":"Asia/Ho_Chi_Minh",
    "iso:country":"VN",
    "name:und_x_variant":[
        "C\u1ecf Ti\u1ebft"
    ],
    "name:vie_x_preferred":[
        "C\u1ed5 Ti\u1ebft R\u01b0ng"
    ],
    "wof:name":"Co Tiet Rung",
    "wof:placetype":"locality"
},
  "geometry": {"coordinates":[105.24164,21.29885],"type":"Point"}
}