{
  "type": "Feature",
  "properties": {
    "gn:admin1_code":"39.0",
    "gn:asciiname":"Na Chau",
    "gn:country_code":"VN",
    "gn:dem":308,
    "gn:feature_class":"P",
    "gn:feature_code":"PPL",
    "gn:name":"N\u00e0 Ch\u1ea7u",
    "gn:population":0,
    "gn:timezone":"Asia/Ho_Chi_Minh",
    "iso:country":"VN",
    "name:vie_x_preferred":[
        "N\u00e0 Ch\u1ea7u"
    ],
    "wof:name":"Na Chau",
    "wof:placetype":"locality"
},
  "geometry": {"coordinates":[106.42795,21.77183],"type":"Point"}
}