{
  "type": "Feature",
  "properties": {
    "gn:admin1_code":"75.0",
    "gn:asciiname":"Hoa Loi",
    "gn:country_code":"VN",
    "gn:dem":34,
    "gn:feature_class":"P",
    "gn:feature_code":"PPL",
    "gn:name":"H\u00f2a L\u1ee3i",
    "gn:population":0,
    "gn:timezone":"Asia/Ho_Chi_Minh",
    "iso:country":"VN",
    "name:und_x_variant":[
        "Phu Hoa",
        "H\u00f2a L\u1ee3i"
    ],
    "wof:name":"Hoa Loi",
    "wof:placetype":"locality"
},
  "geometry": {"coordinates":[106.66667,11.08333],"type":"Point"}
}