{
  "type": "Feature",
  "properties": {
    "gn:admin1_code":"89.0",
    "gn:asciiname":"Na Sang",
    "gn:cc2":"VN",
    "gn:country_code":"VN",
    "gn:dem":873,
    "gn:feature_class":"P",
    "gn:feature_code":"PPL",
    "gn:name":"Na Sang",
    "gn:population":0,
    "gn:timezone":"Asia/Ho_Chi_Minh",
    "iso:country":"VN",
    "name:und_x_variant":[
        "Ban Na Sang",
        "Na Sang"
    ],
    "wof:name":"Na Sang",
    "wof:placetype":"locality"
},
  "geometry": {"coordinates":[103.08333,21.23333],"type":"Point"}
}