{
  "type": "Feature",
  "properties": {
    "gn:admin1_code":"58.0",
    "gn:asciiname":"Ban Co Mi",
    "gn:country_code":"VN",
    "gn:dem":357,
    "gn:feature_class":"P",
    "gn:feature_code":"PPL",
    "gn:name":"B\u1ea3n Co Mi",
    "gn:population":0,
    "gn:timezone":"Asia/Ho_Chi_Minh",
    "iso:country":"VN",
    "wof:name":"Ban Co Mi",
    "wof:placetype":"locality"
},
  "geometry": {"coordinates":[104.34999999999999,19.36667000000001],"type":"Point"}
}