{
  "type": "Feature",
  "properties": {
    "gn:admin1_code":"37.0",
    "gn:asciiname":"Tan Thuan",
    "gn:country_code":"VN",
    "gn:dem":2,
    "gn:feature_class":"P",
    "gn:feature_code":"PPL",
    "gn:name":"T\u00e2n Thu\u1eadn",
    "gn:population":0,
    "gn:timezone":"Asia/Ho_Chi_Minh",
    "iso:country":"VN",
    "name:vie_x_preferred":[
        "T\u00e2n Thu\u1eadn"
    ],
    "wof:name":"Tan Thuan",
    "wof:placetype":"locality"
},
  "geometry": {"coordinates":[106.43573000000001,10.33882],"type":"Point"}
}