{
  "type": "Feature",
  "properties": {
    "gn:admin1_code":"34.0",
    "gn:asciiname":"Lang Ac",
    "gn:country_code":"VN",
    "gn:dem":110,
    "gn:feature_class":"P",
    "gn:feature_code":"PPL",
    "gn:name":"L\u00e0ng \u1ea0c",
    "gn:population":0,
    "gn:timezone":"Asia/Ho_Chi_Minh",
    "iso:country":"VN",
    "wof:name":"Lang Ac",
    "wof:placetype":"locality"
},
  "geometry": {"coordinates":[105.22629999999999,19.75479],"type":"Point"}
}