{
  "type": "Feature",
  "properties": {
    "gn:admin1_code":"39.0",
    "gn:asciiname":"Ban Duoc",
    "gn:country_code":"VN",
    "gn:dem":255,
    "gn:feature_class":"P",
    "gn:feature_code":"PPL",
    "gn:name":"B\u1ea3n \u0110u\u1ed1c",
    "gn:population":0,
    "gn:timezone":"Asia/Ho_Chi_Minh",
    "iso:country":"VN",
    "name:und_x_variant":[
        "B\u1ea3n \u0110u\u1ed1c",
        "B\u1ea3n \u0110u\u1ed3c"
    ],
    "wof:name":"Ban Duoc",
    "wof:placetype":"locality"
},
  "geometry": {"coordinates":[106.66016999999999,22.0287],"type":"Point"}
}