{
  "type": "Feature",
  "properties": {
    "gn:admin1_code":"5.0",
    "gn:asciiname":"Tchiem Thang",
    "gn:country_code":"VN",
    "gn:dem":889,
    "gn:feature_class":"P",
    "gn:feature_code":"PPL",
    "gn:name":"Tchiem Thang",
    "gn:population":0,
    "gn:timezone":"Asia/Ho_Chi_Minh",
    "iso:country":"VN",
    "wof:name":"Tchiem Thang",
    "wof:placetype":"locality"
},
  "geometry": {"coordinates":[105.86667,22.55],"type":"Point"}
}