{
  "type": "Feature",
  "properties": {
    "gn:admin1_code":"65.0",
    "gn:asciiname":"Hoa Quoi",
    "gn:country_code":"VN",
    "gn:dem":5,
    "gn:feature_class":"P",
    "gn:feature_code":"PPL",
    "gn:name":"H\u00f2a Qu\u1edbi",
    "gn:population":0,
    "gn:timezone":"Asia/Ho_Chi_Minh",
    "iso:country":"VN",
    "name:vie_x_preferred":[
        "H\u00f2a Qu\u1edbi"
    ],
    "wof:name":"Hoa Quoi",
    "wof:placetype":"locality"
},
  "geometry": {"coordinates":[105.89179,9.6174],"type":"Point"}
}