{
  "type": "Feature",
  "properties": {
    "gn:admin1_code":"53.0",
    "gn:asciiname":"Mong Luong",
    "gn:country_code":"VN",
    "gn:dem":629,
    "gn:feature_class":"P",
    "gn:feature_code":"PPL",
    "gn:name":"Mong Lu\u00f4ng",
    "gn:population":0,
    "gn:timezone":"Asia/Ho_Chi_Minh",
    "iso:country":"VN",
    "name:und_x_variant":[
        "Mang Lu\u00f4ng",
        "Mong Lu\u00f4ng"
    ],
    "wof:name":"Mong Luong",
    "wof:placetype":"locality"
},
  "geometry": {"coordinates":[105.25,20.51667],"type":"Point"}
}