{
  "type": "Feature",
  "properties": {
    "gn:admin1_code":"91.0",
    "gn:asciiname":"Tu Minh",
    "gn:country_code":"VN",
    "gn:dem":723,
    "gn:feature_class":"P",
    "gn:feature_code":"PPL",
    "gn:name":"T\u01b0 Minh",
    "gn:population":0,
    "gn:timezone":"Asia/Ho_Chi_Minh",
    "iso:country":"VN",
    "wof:name":"Tu Minh",
    "wof:placetype":"locality"
},
  "geometry": {"coordinates":[107.66667,12.45],"type":"Point"}
}