{
  "type": "Feature",
  "properties": {
    "gn:admin1_code":"52.0",
    "gn:asciiname":"Trai Xoi",
    "gn:country_code":"VN",
    "gn:dem":8,
    "gn:feature_class":"P",
    "gn:feature_code":"PPL",
    "gn:name":"Trai Xoi",
    "gn:population":0,
    "gn:timezone":"Asia/Ho_Chi_Minh",
    "iso:country":"VN",
    "name:und_x_variant":[
        "Trai Xai",
        "Trai Xoi"
    ],
    "wof:name":"Trai Xoi",
    "wof:placetype":"locality"
},
  "geometry": {"coordinates":[105.76667,18.36667000000001],"type":"Point"}
}