{
  "type": "Feature",
  "properties": {
    "gn:admin1_code":"78.0",
    "gn:asciiname":"Cam Hoa",
    "gn:country_code":"VN",
    "gn:dem":38,
    "gn:feature_class":"P",
    "gn:feature_code":"PPL",
    "gn:name":"C\u1ea9m H\u00f2a",
    "gn:population":0,
    "gn:timezone":"Asia/Ho_Chi_Minh",
    "iso:country":"VN",
    "name:vie_x_preferred":[
        "C\u1ea9m H\u00f2a"
    ],
    "wof:name":"Cam Hoa",
    "wof:placetype":"locality"
},
  "geometry": {"coordinates":[108.16903000000001,16.00916],"type":"Point"}
}