{
  "type": "Feature",
  "properties": {
    "gn:admin1_code":"49.0",
    "gn:asciiname":"Plei Ya Kavn",
    "gn:country_code":"VN",
    "gn:dem":422,
    "gn:feature_class":"P",
    "gn:feature_code":"PPL",
    "gn:name":"Plei Ya Kavn",
    "gn:population":0,
    "gn:timezone":"Asia/Ho_Chi_Minh",
    "iso:country":"VN",
    "wof:name":"Plei Ya Kavn",
    "wof:placetype":"locality"
},
  "geometry": {"coordinates":[107.68333,13.86667],"type":"Point"}
}