{
  "type": "Feature",
  "properties": {
    "gn:admin1_code":"32.0",
    "gn:asciiname":"Ban Me",
    "gn:country_code":"VN",
    "gn:dem":791,
    "gn:feature_class":"P",
    "gn:feature_code":"PPL",
    "gn:name":"B\u1ea3n M\u00e9",
    "gn:population":0,
    "gn:timezone":"Asia/Ho_Chi_Minh",
    "iso:country":"VN",
    "name:vie_x_preferred":[
        "B\u1ea3n M\u00e9"
    ],
    "wof:name":"Ban Me",
    "wof:placetype":"locality"
},
  "geometry": {"coordinates":[103.88018,21.22556],"type":"Point"}
}