{
  "type": "Feature",
  "properties": {
    "gn:admin1_code":"20.0",
    "gn:asciiname":"Thong Tay Hoi",
    "gn:cc2":"VN",
    "gn:country_code":"VN",
    "gn:dem":9,
    "gn:feature_class":"P",
    "gn:feature_code":"PPL",
    "gn:name":"Th\u00f4ng T\u00e2y H\u1ed9i",
    "gn:population":0,
    "gn:timezone":"Asia/Ho_Chi_Minh",
    "iso:country":"VN",
    "name:und_x_variant":[
        "Hanh Thong Tay",
        "Th\u00f4ng T\u00e2y H\u1ed9i"
    ],
    "wof:name":"Thong Tay Hoi",
    "wof:placetype":"locality"
},
  "geometry": {"coordinates":[106.65000000000001,10.83333],"type":"Point"}
}