{
  "type": "Feature",
  "properties": {
    "gn:admin1_code":"75.0",
    "gn:asciiname":"Binh Quoi",
    "gn:country_code":"VN",
    "gn:dem":31,
    "gn:feature_class":"P",
    "gn:feature_code":"PPL",
    "gn:name":"B\u00ecnh Q\u01b0\u1edbi",
    "gn:population":0,
    "gn:timezone":"Asia/Ho_Chi_Minh",
    "iso:country":"VN",
    "name:vie_x_preferred":[
        "B\u00ecnh Q\u01b0\u1edbi"
    ],
    "wof:name":"Binh Quoi",
    "wof:placetype":"locality"
},
  "geometry": {"coordinates":[106.73361,10.98154],"type":"Point"}
}