{
  "type": "Feature",
  "properties": {
    "gn:admin1_code":"46.0",
    "gn:asciiname":"Lang Ba Lanh",
    "gn:country_code":"VN",
    "gn:dem":542,
    "gn:feature_class":"P",
    "gn:feature_code":"PPL",
    "gn:name":"Lang Ba Lanh",
    "gn:population":0,
    "gn:timezone":"Asia/Ho_Chi_Minh",
    "iso:country":"VN",
    "wof:name":"Lang Ba Lanh",
    "wof:placetype":"locality"
},
  "geometry": {"coordinates":[108.86667,14.48333],"type":"Point"}
}