{
  "type": "Feature",
  "properties": {
    "gn:admin1_code":"89.0",
    "gn:asciiname":"Ban Ip Chom",
    "gn:country_code":"VN",
    "gn:dem":465,
    "gn:feature_class":"P",
    "gn:feature_code":"PPL",
    "gn:name":"B\u1ea3n Ip Chom",
    "gn:population":0,
    "gn:timezone":"Asia/Ho_Chi_Minh",
    "iso:country":"VN",
    "name:vie_x_preferred":[
        "B\u1ea3n Ip Chom"
    ],
    "wof:name":"Ban Ip Chom",
    "wof:placetype":"locality"
},
  "geometry": {"coordinates":[103.67467000000001,22.01665],"type":"Point"}
}