{
  "type": "Feature",
  "properties": {
    "gn:admin1_code":"90.0",
    "gn:asciiname":"Thi Tran Muong Khuong",
    "gn:country_code":"VN",
    "gn:dem":771,
    "gn:feature_class":"P",
    "gn:feature_code":"PPLA2",
    "gn:name":"Th\u1ecb Tr\u1ea5n M\u01b0\u1eddng Kh\u01b0\u01a1ng",
    "gn:population":0,
    "gn:timezone":"Asia/Ho_Chi_Minh",
    "iso:country":"VN",
    "name:und_x_variant":[
        "M\u01b0\u1eddng Kh\u01b0\u01a1ng"
    ],
    "name:vie_x_preferred":[
        "Th\u1ecb Tr\u1ea5n M\u01b0\u1eddng Kh\u01b0\u01a1ng"
    ],
    "wof:name":"Thi Tran Muong Khuong",
    "wof:placetype":"locality"
},
  "geometry": {"coordinates":[104.12156,22.76141],"type":"Point"}
}