{
  "type": "Feature",
  "properties": {
    "gn:admin1_code":"34.0",
    "gn:asciiname":"Yen Trung",
    "gn:country_code":"VN",
    "gn:dem":10,
    "gn:feature_class":"P",
    "gn:feature_code":"PPL",
    "gn:name":"Yen Trung",
    "gn:population":0,
    "gn:timezone":"Asia/Ho_Chi_Minh",
    "iso:country":"VN",
    "name:und_x_variant":[
        "Thuong",
        "Yen Trung"
    ],
    "wof:name":"Yen Trung",
    "wof:placetype":"locality"
},
  "geometry": {"coordinates":[105.63333,19.93333],"type":"Point"}
}