{
  "type": "Feature",
  "properties": {
    "gn:admin1_code":"84.0",
    "gn:asciiname":"Phuoc Hoa",
    "gn:country_code":"VN",
    "gn:dem":86,
    "gn:feature_class":"P",
    "gn:feature_code":"PPL",
    "gn:name":"Ph\u01b0\u1edbc H\u00f2a",
    "gn:population":0,
    "gn:timezone":"Asia/Ho_Chi_Minh",
    "iso:country":"VN",
    "wof:name":"Phuoc Hoa",
    "wof:placetype":"locality"
},
  "geometry": {"coordinates":[108.16667,15.58333],"type":"Point"}
}