{
  "type": "Feature",
  "properties": {
    "gn:admin1_code":"52.0",
    "gn:asciiname":"Xom Muoi",
    "gn:country_code":"VN",
    "gn:dem":8,
    "gn:feature_class":"P",
    "gn:feature_code":"PPL",
    "gn:name":"X\u00f3m M\u01b0\u1eddi",
    "gn:population":0,
    "gn:timezone":"Asia/Ho_Chi_Minh",
    "iso:country":"VN",
    "name:vie_x_preferred":[
        "X\u00f3m M\u01b0\u1eddi"
    ],
    "name:vie_x_variant":[
        "X\u00f3m 10"
    ],
    "wof:name":"Xom Muoi",
    "wof:placetype":"locality"
},
  "geometry": {"coordinates":[105.86425,18.37298],"type":"Point"}
}