{
  "type": "Feature",
  "properties": {
    "gn:admin1_code":"24.0",
    "gn:asciiname":"Long Truong",
    "gn:country_code":"VN",
    "gn:dem":-1,
    "gn:feature_class":"P",
    "gn:feature_code":"PPL",
    "gn:name":"Long Tr\u01b0\u1eddng",
    "gn:population":0,
    "gn:timezone":"Asia/Ho_Chi_Minh",
    "iso:country":"VN",
    "name:und_x_variant":[
        "X\u00f3m Long Tr\u01b0\u01a1ng"
    ],
    "name:vie_x_preferred":[
        "Long Tr\u01b0\u1eddng"
    ],
    "wof:name":"Long Truong",
    "wof:placetype":"locality"
},
  "geometry": {"coordinates":[106.45332000000001,10.42267],"type":"Point"}
}