{
  "type": "Feature",
  "properties": {
    "gn:admin1_code":"89.0",
    "gn:asciiname":"Hong Ngai",
    "gn:country_code":"VN",
    "gn:dem":774,
    "gn:feature_class":"P",
    "gn:feature_code":"PPL",
    "gn:name":"H\u1ed3ng Ng\u00e0i",
    "gn:population":0,
    "gn:timezone":"Asia/Ho_Chi_Minh",
    "iso:country":"VN",
    "name:und_x_variant":[
        "H\u00f4ng Ng\u00e0i Chay"
    ],
    "name:vie_x_preferred":[
        "H\u1ed3ng Ng\u00e0i"
    ],
    "wof:name":"Hong Ngai",
    "wof:placetype":"locality"
},
  "geometry": {"coordinates":[103.16104,22.13793],"type":"Point"}
}