{
  "type": "Feature",
  "properties": {
    "gn:admin1_code":"63.0",
    "gn:asciiname":"Calok",
    "gn:country_code":"VN",
    "gn:dem":252,
    "gn:feature_class":"P",
    "gn:feature_code":"PPL",
    "gn:name":"Calok",
    "gn:population":0,
    "gn:timezone":"Asia/Ho_Chi_Minh",
    "iso:country":"VN",
    "wof:name":"Calok",
    "wof:placetype":"locality"
},
  "geometry": {"coordinates":[108.41667,15.01667],"type":"Point"}
}