{
  "type": "Feature",
  "properties": {
    "gn:admin1_code":"64.0",
    "gn:asciiname":"Dong Luat",
    "gn:country_code":"VN",
    "gn:dem":9,
    "gn:feature_class":"P",
    "gn:feature_code":"PPL",
    "gn:name":"\u0110\u1ed3ng Lu\u1eadt",
    "gn:population":0,
    "gn:timezone":"Asia/Ho_Chi_Minh",
    "iso:country":"VN",
    "name:vie_x_preferred":[
        "\u0110\u1ed3ng Lu\u1eadt"
    ],
    "wof:name":"Dong Luat",
    "wof:placetype":"locality"
},
  "geometry": {"coordinates":[107.0543,17.11943],"type":"Point"}
}