{
  "type": "Feature",
  "properties": {
    "gn:admin1_code":"69.0",
    "gn:asciiname":"An Phu",
    "gn:country_code":"VN",
    "gn:dem":5,
    "gn:feature_class":"P",
    "gn:feature_code":"PPL",
    "gn:name":"An Ph\u00fa",
    "gn:population":0,
    "gn:timezone":"Asia/Ho_Chi_Minh",
    "iso:country":"VN",
    "name:vie_x_preferred":[
        "An Ph\u00fa"
    ],
    "wof:name":"An Phu",
    "wof:placetype":"locality"
},
  "geometry": {"coordinates":[105.92624000000001,10.00328],"type":"Point"}
}