{
  "type": "Feature",
  "properties": {
    "gn:admin1_code":"63.0",
    "gn:asciiname":"Ong Thang",
    "gn:country_code":"VN",
    "gn:dem":373,
    "gn:feature_class":"P",
    "gn:feature_code":"PPL",
    "gn:name":"\u00d4ng Thang",
    "gn:population":0,
    "gn:timezone":"Asia/Ho_Chi_Minh",
    "iso:country":"VN",
    "name:vie_x_preferred":[
        "\u00d4ng Thang"
    ],
    "wof:name":"Ong Thang",
    "wof:placetype":"locality"
},
  "geometry": {"coordinates":[108.33871000000001,14.99401],"type":"Point"}
}