{
  "type": "Feature",
  "properties": {
    "gn:admin1_code":"58.0",
    "gn:asciiname":"Van Hoi Tay",
    "gn:country_code":"VN",
    "gn:dem":6,
    "gn:feature_class":"P",
    "gn:feature_code":"PPL",
    "gn:name":"V\u0103n H\u1ed9i T\u00e2y",
    "gn:population":0,
    "gn:timezone":"Asia/Ho_Chi_Minh",
    "iso:country":"VN",
    "name:vie_x_preferred":[
        "V\u0103n H\u1ed9i T\u00e2y"
    ],
    "wof:name":"Van Hoi Tay",
    "wof:placetype":"locality"
},
  "geometry": {"coordinates":[105.50915000000001,18.97307],"type":"Point"}
}