{
  "type": "Feature",
  "properties": {
    "iso:country":"VN",
    "name:ara_x_preferred":[
        "\u062a\u0648\u064a \u0647\u0648\u0627"
    ],
    "name:ben_x_preferred":[
        "\u09a4\u09c1\u09af\u09bc \u09b9\u09cb\u09af\u09bc\u09be"
    ],
    "name:ceb_x_preferred":[
        "Tuy H\u00f2a"
    ],
    "name:dan_x_preferred":[
        "Tuy Hoa"
    ],
    "name:deu_x_preferred":[
        "Tuy H\u00f2a"
    ],
    "name:ell_x_preferred":[
        "\u03a4\u03bf\u03cd\u03b9 \u03a7\u03cc\u03b1"
    ],
    "name:eng_x_preferred":[
        "Tuy H\u00f2a"
    ],
    "name:fas_x_preferred":[
        "\u062a\u0648\u06cc \u0647\u0648\u0626\u0627"
    ],
    "name:fin_x_preferred":[
        "Tuy H\u00f2a"
    ],
    "name:fra_x_preferred":[
        "Tuy H\u00f2a"
    ],
    "name:guj_x_preferred":[
        "\u0a9f\u0ac1\u0aaf \u0ab9\u0acb\u0a86"
    ],
    "name:hin_x_preferred":[
        "\u0924\u0941\u092f \u0939\u094b\u0906"
    ],
    "name:ind_x_preferred":[
        "Tuy H\u00f2a"
    ],
    "name:ita_x_preferred":[
        "Tuy Hoa"
    ],
    "name:jpn_x_preferred":[
        "\u30c8\u30a5\u30a4\u30db\u30a2"
    ],
    "name:kan_x_preferred":[
        "\u0ca4\u0cc1\u0caf\u0ccd \u0cb9\u0cca"
    ],
    "name:kor_x_preferred":[
        "\ub69c\uc774\ud638\uc544"
    ],
    "name:lav_x_preferred":[
        "Tujhoa"
    ],
    "name:lit_x_preferred":[
        "Tui Hoa"
    ],
    "name:mar_x_preferred":[
        "\u091f\u094d\u092f\u0942 \u0939\u094b"
    ],
    "name:msa_x_preferred":[
        "Tuy Hoa"
    ],
    "name:nld_x_preferred":[
        "Tuy H\u00f2a"
    ],
    "name:nob_x_preferred":[
        "Tuy Hoa"
    ],
    "name:pol_x_preferred":[
        "Tuy H\u00f2a"
    ],
    "name:por_x_preferred":[
        "Tuy Hoa"
    ],
    "name:rus_x_preferred":[
        "\u0422\u0443\u0438\u0445\u043e\u0430"
    ],
    "name:sin_x_preferred":[
        "\u0da7\u0dd4\u0dba\u0dd2 \u0dc4\u0ddd\u0d86"
    ],
    "name:spa_x_preferred":[
        "Tuy H\u00f2a"
    ],
    "name:srp_x_preferred":[
        "\u0422\u0443\u0438 \u0425\u043e\u0430"
    ],
    "name:swe_x_preferred":[
        "Tuy Hoa"
    ],
    "name:tam_x_preferred":[
        "\u0b9f\u0bbe\u0baf\u0bcd \u0bb9\u0bc2"
    ],
    "name:tel_x_preferred":[
        "\u0c1f\u0c41\u0c2f\u0c4d \u0c39\u0c4b\u0c35\u0c3e"
    ],
    "name:tha_x_preferred":[
        "\u0e15\u0e27\u0e35\u0e2e\u0e2b\u0e27\u0e48\u0e32"
    ],
    "name:tur_x_preferred":[
        "Tuy H\u00f2a"
    ],
    "name:ukr_x_preferred":[
        "\u0422\u0443\u0439\u0445\u043e\u0430"
    ],
    "name:urd_x_preferred":[
        "\u062a\u0648\u0626\u06d2 \u06c1\u0648\u0627"
    ],
    "name:vie_x_preferred":[
        "Tuy H\u00f2a"
    ],
    "name:war_x_preferred":[
        "Tuy Hoa"
    ],
    "name:zho_x_preferred":[
        "\u7d8f\u548c\u5e02"
    ],
    "qs:gn_country":"VN",
    "qs:gn_fcode":"PPL",
    "qs:gn_pop":0,
    "qs:name":"Tuy H\u00f2a",
    "qs:name_adm0":"Vietnam",
    "qs:name_adm1":"Phu Yen",
    "qs:photos":441,
    "qs:photos_1k":89,
    "qs:photos_9k":2,
    "qs:photos_9r":5,
    "qs:photos_all":441,
    "qs:photos_sr":6,
    "qs:placetype":"Town",
    "qs:pop_sr":"0",
    "qs:woe_adm0":23424984,
    "wd:wordcount":96,
    "wof:name":"Tuy H\u00f2a",
    "wof:placetype":"locality"
},
  "geometry": {"coordinates":[109.08333,13.95],"type":"Point"}
}