{
  "type": "Feature",
  "properties": {
    "iso:country":"VN",
    "name:fas_x_preferred":[
        "\u062a\u0648\u06cc \u0647\u0648\u0626\u0627"
    ],
    "name:fra_x_preferred":[
        "Tuy H\u00f2a"
    ],
    "name:ind_x_preferred":[
        "Tuy H\u00f2a"
    ],
    "name:ita_x_preferred":[
        "Tuy Hoa"
    ],
    "name:jpn_x_preferred":[
        "\u30c8\u30a5\u30a4\u30db\u30a2"
    ],
    "name:kor_x_preferred":[
        "\ub69c\uc774\ud638\uc544"
    ],
    "name:nld_x_preferred":[
        "Tuy H\u00f2a"
    ],
    "name:pol_x_preferred":[
        "Tuy H\u00f2a"
    ],
    "name:por_x_preferred":[
        "Tuy Hoa"
    ],
    "name:spa_x_preferred":[
        "Tuy H\u00f2a"
    ],
    "qs:gn_country":"VN",
    "qs:gn_fcode":"PPL",
    "qs:gn_pop":0,
    "qs:name":"Tuy H\u00f2a",
    "qs:name_adm0":"Vietnam",
    "qs:name_adm1":"Phu Yen",
    "qs:photos":441,
    "qs:photos_1k":89,
    "qs:photos_9k":2,
    "qs:photos_9r":5,
    "qs:photos_all":441,
    "qs:photos_sr":6,
    "qs:placetype":"Town",
    "qs:pop_sr":"0",
    "qs:woe_adm0":23424984,
    "wd:wordcount":96,
    "wof:name":"Tuy H\u00f2a",
    "wof:placetype":"locality"
},
  "geometry": {"coordinates":[109.08333,13.95],"type":"Point"}
}