{
  "type": "Feature",
  "properties": {
    "gn:admin1_code":"37.0",
    "gn:asciiname":"Hoa Lac Trung",
    "gn:country_code":"VN",
    "gn:dem":1,
    "gn:feature_class":"P",
    "gn:feature_code":"PPL",
    "gn:name":"H\u00f2a L\u1ea1c Trung",
    "gn:population":0,
    "gn:timezone":"Asia/Ho_Chi_Minh",
    "iso:country":"VN",
    "name:vie_x_preferred":[
        "H\u00f2a L\u1ea1c Trung"
    ],
    "wof:name":"Hoa Lac Trung",
    "wof:placetype":"locality"
},
  "geometry": {"coordinates":[106.46392,10.32554],"type":"Point"}
}