{
  "type": "Feature",
  "properties": {
    "gn:admin1_code":"52.0",
    "gn:asciiname":"Trung Ra",
    "gn:country_code":"VN",
    "gn:dem":7,
    "gn:feature_class":"P",
    "gn:feature_code":"PPL",
    "gn:name":"Trung R\u00e1",
    "gn:population":0,
    "gn:timezone":"Asia/Ho_Chi_Minh",
    "iso:country":"VN",
    "name:vie_x_preferred":[
        "Trung R\u00e1"
    ],
    "wof:name":"Trung Ra",
    "wof:placetype":"locality"
},
  "geometry": {"coordinates":[106.04787,18.27458],"type":"Point"}
}