{
  "type": "Feature",
  "properties": {
    "gn:admin1_code":"85.0",
    "gn:asciiname":"Chan Mam",
    "gn:country_code":"VN",
    "gn:dem":32,
    "gn:feature_class":"P",
    "gn:feature_code":"PPL",
    "gn:name":"Ch\u00e2n M\u1ea5m",
    "gn:population":0,
    "gn:timezone":"Asia/Ho_Chi_Minh",
    "iso:country":"VN",
    "name:vie_x_preferred":[
        "Ch\u00e2n M\u1ea5m"
    ],
    "wof:name":"Chan Mam",
    "wof:placetype":"locality"
},
  "geometry": {"coordinates":[106.01064,21.45399],"type":"Point"}
}