{
  "type": "Feature",
  "properties": {
    "gn:admin1_code":"72.0",
    "gn:asciiname":"Pac Cuong",
    "gn:country_code":"VN",
    "gn:dem":184,
    "gn:feature_class":"P",
    "gn:feature_code":"PPL",
    "gn:name":"P\u00e1c Cu\u00f4ng",
    "gn:population":0,
    "gn:timezone":"Asia/Ho_Chi_Minh",
    "iso:country":"VN",
    "name:vie_x_preferred":[
        "P\u00e1c Cu\u00f4ng"
    ],
    "wof:name":"Pac Cuong",
    "wof:placetype":"locality"
},
  "geometry": {"coordinates":[105.49629,22.18769],"type":"Point"}
}