{
  "type": "Feature",
  "properties": {
    "gn:admin1_code":"71.0",
    "gn:asciiname":"Dang Dang",
    "gn:country_code":"VN",
    "gn:dem":10,
    "gn:feature_class":"P",
    "gn:feature_code":"PPL",
    "gn:name":"D\u00e0ng D\u00e0ng",
    "gn:population":0,
    "gn:timezone":"Asia/Ho_Chi_Minh",
    "iso:country":"VN",
    "name:vie_x_preferred":[
        "D\u00e0ng D\u00e0ng"
    ],
    "wof:name":"Dang Dang",
    "wof:placetype":"locality"
},
  "geometry": {"coordinates":[106.11832,21.33031],"type":"Point"}
}