{
  "type": "Feature",
  "properties": {
    "gn:admin1_code":"5.0",
    "gn:asciiname":"Ban Phieng Dan",
    "gn:country_code":"VN",
    "gn:dem":671,
    "gn:feature_class":"P",
    "gn:feature_code":"PPL",
    "gn:name":"B\u1ea3n Phi\u00eang \u0110\u0103n",
    "gn:population":0,
    "gn:timezone":"Asia/Ho_Chi_Minh",
    "iso:country":"VN",
    "name:vie_x_preferred":[
        "Pi\u00eang \u0110\u0103m"
    ],
    "name:vie_x_variant":[
        "B\u1ea3n Phi\u00eang \u0110\u0103n"
    ],
    "wof:name":"Ban Phieng Dan",
    "wof:placetype":"locality"
},
  "geometry": {"coordinates":[105.48173,22.95622],"type":"Point"}
}