{
  "type": "Feature",
  "properties": {
    "gn:admin1_code":"90.0",
    "gn:asciiname":"Sin Cho",
    "gn:country_code":"VN",
    "gn:dem":1413,
    "gn:feature_class":"P",
    "gn:feature_code":"PPL",
    "gn:name":"S\u1ec9n Ch\u1ed3",
    "gn:population":0,
    "gn:timezone":"Asia/Ho_Chi_Minh",
    "iso:country":"VN",
    "name:vie_x_preferred":[
        "S\u1ec9n Ch\u1ed3"
    ],
    "wof:name":"Sin Cho",
    "wof:placetype":"locality"
},
  "geometry": {"coordinates":[104.23412,22.62425],"type":"Point"}
}