{
  "type": "Feature",
  "properties": {
    "gn:admin1_code":"32.0",
    "gn:asciiname":"Ban Dom",
    "gn:country_code":"VN",
    "gn:dem":752,
    "gn:feature_class":"P",
    "gn:feature_code":"PPL",
    "gn:name":"B\u1ea3n \u0110\u1ed1m",
    "gn:population":0,
    "gn:timezone":"Asia/Ho_Chi_Minh",
    "iso:country":"VN",
    "name:vie_x_preferred":[
        "B\u1ea3n \u0110\u1ed1m"
    ],
    "wof:name":"Ban Dom",
    "wof:placetype":"locality"
},
  "geometry": {"coordinates":[103.56228,20.95032],"type":"Point"}
}