{
  "type": "Feature",
  "properties": {
    "gn:admin1_code":"50.0",
    "gn:asciiname":"Ngai La Teou",
    "gn:country_code":"VN",
    "gn:dem":1199,
    "gn:feature_class":"P",
    "gn:feature_code":"PPL",
    "gn:name":"Ngai La Teou",
    "gn:population":0,
    "gn:timezone":"Asia/Ho_Chi_Minh",
    "iso:country":"VN",
    "name:und_x_variant":[
        "Ngai La Teoa",
        "Ngai La Teou"
    ],
    "wof:name":"Ngai La Teou",
    "wof:placetype":"locality"
},
  "geometry": {"coordinates":[104.56667,22.66667],"type":"Point"}
}