{
  "type": "Feature",
  "properties": {
    "gn:admin1_code":"50.0",
    "gn:asciiname":"Lang Dap",
    "gn:country_code":"VN",
    "gn:dem":86,
    "gn:feature_class":"P",
    "gn:feature_code":"PPL",
    "gn:name":"L\u00e0ng D\u00e1p",
    "gn:population":0,
    "gn:timezone":"Asia/Ho_Chi_Minh",
    "iso:country":"VN",
    "wof:name":"Lang Dap",
    "wof:placetype":"locality"
},
  "geometry": {"coordinates":[104.90000000000001,22.38333],"type":"Point"}
}