{
  "type": "Feature",
  "properties": {
    "iso:country":"VN",
    "name:eng_x_preferred":[
        "Duong Dong"
    ],
    "name:rus_x_preferred":[
        "\u0414\u0443\u043e\u043d\u0433-\u0414\u043e\u043d\u0433"
    ],
    "name:unk_x_variant":[
        "D\u01b0\u01a1ng D\u00f4ng"
    ],
    "name:vie_x_preferred":[
        "D\u01b0\u01a1ng \u0110\u00f4ng"
    ],
    "qs:gn_country":"VN",
    "qs:gn_fcode":"PPL",
    "qs:gn_pop":15000,
    "qs:name":"Duong Dong",
    "qs:name_adm0":"Vietnam",
    "qs:name_adm1":"Kien Giang",
    "qs:photos":1061,
    "qs:photos_1k":215,
    "qs:photos_9k":5,
    "qs:photos_9r":7,
    "qs:photos_all":1061,
    "qs:photos_sr":11,
    "qs:placetype":"Town",
    "qs:pop_sr":"6",
    "qs:woe_adm0":23424984,
    "wof:name":"Duong Dong",
    "wof:placetype":"locality",
    "wof:population":15000
},
  "geometry": {"coordinates":[103.96666999999999,10.21667],"type":"Point"}
}