{
  "type": "Feature",
  "properties": {
    "gn:admin1_code":"74.0",
    "gn:asciiname":"Giang Lieu",
    "gn:country_code":"VN",
    "gn:dem":9,
    "gn:feature_class":"P",
    "gn:feature_code":"PPL",
    "gn:name":"Giang Li\u1ec5u",
    "gn:population":0,
    "gn:timezone":"Asia/Ho_Chi_Minh",
    "iso:country":"VN",
    "name:vie_x_preferred":[
        "Giang Li\u1ec5u"
    ],
    "wof:name":"Giang Lieu",
    "wof:placetype":"locality"
},
  "geometry": {"coordinates":[106.12842000000001,21.16274],"type":"Point"}
}