{
  "type": "Feature",
  "properties": {
    "gn:admin1_code":"67.0",
    "gn:asciiname":"Ap Phuoc Hoi",
    "gn:cc2":"VN",
    "gn:country_code":"VN",
    "gn:dem":1,
    "gn:feature_class":"P",
    "gn:feature_code":"PPL",
    "gn:name":"\u1ea4p Ph\u01b0\u1edbc H\u1ed9i",
    "gn:population":0,
    "gn:timezone":"Asia/Ho_Chi_Minh",
    "iso:country":"VN",
    "name:nld_x_preferred":[
        "Ph\u01b0\u1edbc H\u1ed9i"
    ],
    "name:und_x_variant":[
        "\u1ea4p Ph\u01b0\u1edbc H\u1ed9i"
    ],
    "name:vie_x_preferred":[
        "Ph\u01b0\u1edbc H\u1ed9i"
    ],
    "wof:name":"Ap Phuoc Hoi",
    "wof:placetype":"locality"
},
  "geometry": {"coordinates":[106.42306000000001,9.62528],"type":"Point"}
}