{
  "type": "Feature",
  "properties": {
    "gn:admin1_code":"70.0",
    "gn:asciiname":"Ban Tong Cang",
    "gn:country_code":"VN",
    "gn:dem":398,
    "gn:feature_class":"P",
    "gn:feature_code":"PPL",
    "gn:name":"B\u1ea3n T\u00f4ng C\u00e1ng",
    "gn:population":0,
    "gn:timezone":"Asia/Ho_Chi_Minh",
    "iso:country":"VN",
    "wof:name":"Ban Tong Cang",
    "wof:placetype":"locality"
},
  "geometry": {"coordinates":[104.55,21.58333],"type":"Point"}
}