{
  "type": "Feature",
  "properties": {
    "gn:admin1_code":"30.0",
    "gn:asciiname":"Khe Co",
    "gn:country_code":"VN",
    "gn:dem":296,
    "gn:feature_class":"P",
    "gn:feature_code":"PPL",
    "gn:name":"Kh\u00ea C\u1ed1",
    "gn:population":0,
    "gn:timezone":"Asia/Ho_Chi_Minh",
    "iso:country":"VN",
    "wof:name":"Khe Co",
    "wof:placetype":"locality"
},
  "geometry": {"coordinates":[107.34999999999999,21.53333],"type":"Point"}
}