{
  "type": "Feature",
  "properties": {
    "gn:admin1_code":"88.0",
    "gn:asciiname":"To Long",
    "gn:country_code":"VN",
    "gn:dem":475,
    "gn:feature_class":"P",
    "gn:feature_code":"PPL",
    "gn:name":"T\u01a1 L\u00f4ng",
    "gn:population":0,
    "gn:timezone":"Asia/Ho_Chi_Minh",
    "iso:country":"VN",
    "name:vie_x_preferred":[
        "T\u01a1 L\u00f4ng"
    ],
    "wof:name":"To Long",
    "wof:placetype":"locality"
},
  "geometry": {"coordinates":[108.20733,12.35546],"type":"Point"}
}