{
  "type": "Feature",
  "properties": {
    "gn:admin1_code":"90.0",
    "gn:asciiname":"Xa Heu",
    "gn:country_code":"VN",
    "gn:dem":1077,
    "gn:feature_class":"P",
    "gn:feature_code":"PPL",
    "gn:name":"Xa Heu",
    "gn:population":0,
    "gn:timezone":"Asia/Ho_Chi_Minh",
    "iso:country":"VN",
    "wof:name":"Xa Heu",
    "wof:placetype":"locality"
},
  "geometry": {"coordinates":[104.31667,22.71667],"type":"Point"}
}