{
  "type": "Feature",
  "properties": {
    "gn:admin1_code":"39.0",
    "gn:asciiname":"Ban Du",
    "gn:country_code":"VN",
    "gn:dem":363,
    "gn:feature_class":"P",
    "gn:feature_code":"PPL",
    "gn:name":"Ban Du",
    "gn:population":0,
    "gn:timezone":"Asia/Ho_Chi_Minh",
    "iso:country":"VN",
    "name:und_x_variant":[
        "N\u00f4 L\u1ef1c"
    ],
    "name:vie_x_preferred":[
        "B\u1ea3n \u0110\u00fa"
    ],
    "wof:name":"Ban Du",
    "wof:placetype":"locality"
},
  "geometry": {"coordinates":[106.44047999999999,21.86801],"type":"Point"}
}