{
  "type": "Feature",
  "properties": {
    "gn:admin1_code":"74.0",
    "gn:asciiname":"Dinh Cuong",
    "gn:country_code":"VN",
    "gn:dem":6,
    "gn:feature_class":"P",
    "gn:feature_code":"PPL",
    "gn:name":"\u0110\u00ecnh C\u01b0\u01a1ng",
    "gn:population":0,
    "gn:timezone":"Asia/Ho_Chi_Minh",
    "iso:country":"VN",
    "name:und_x_variant":[
        "\u0110\u1ec9nh D\u01b0\u01a1ng"
    ],
    "name:vie_x_preferred":[
        "\u0110\u00ecnh C\u01b0\u01a1ng"
    ],
    "wof:name":"Dinh Cuong",
    "wof:placetype":"locality"
},
  "geometry": {"coordinates":[106.24378,21.01571],"type":"Point"}
}