{
  "type": "Feature",
  "properties": {
    "gn:admin1_code":"34.0",
    "gn:asciiname":"Luong Muc",
    "gn:country_code":"VN",
    "gn:dem":10,
    "gn:feature_class":"P",
    "gn:feature_code":"PPL",
    "gn:name":"L\u01b0\u01a1ng M\u1ee5c",
    "gn:population":0,
    "gn:timezone":"Asia/Ho_Chi_Minh",
    "iso:country":"VN",
    "name:vie_x_preferred":[
        "L\u01b0\u01a1ng M\u1ee5c"
    ],
    "wof:name":"Luong Muc",
    "wof:placetype":"locality"
},
  "geometry": {"coordinates":[105.70480000000001,19.37392],"type":"Point"}
}