{
  "type": "Feature",
  "properties": {
    "gn:admin1_code":"33.0",
    "gn:asciiname":"Gia Tan",
    "gn:country_code":"VN",
    "gn:dem":14,
    "gn:feature_class":"P",
    "gn:feature_code":"PPL",
    "gn:name":"Gia T\u00e2n",
    "gn:population":0,
    "gn:timezone":"Asia/Ho_Chi_Minh",
    "iso:country":"VN",
    "name:vie_x_preferred":[
        "Gia T\u00e2n"
    ],
    "wof:name":"Gia Tan",
    "wof:placetype":"locality"
},
  "geometry": {"coordinates":[106.36006,11.05296],"type":"Point"}
}