{
  "type": "Feature",
  "properties": {
    "gn:admin1_code":"84.0",
    "gn:asciiname":"Thanh Duc",
    "gn:country_code":"VN",
    "gn:dem":22,
    "gn:feature_class":"P",
    "gn:feature_code":"PPL",
    "gn:name":"Thanh \u0110\u01b0c",
    "gn:population":0,
    "gn:timezone":"Asia/Ho_Chi_Minh",
    "iso:country":"VN",
    "wof:name":"Thanh Duc",
    "wof:placetype":"locality"
},
  "geometry": {"coordinates":[108.40000000000001,15.55],"type":"Point"}
}