{
  "type": "Feature",
  "properties": {
    "gn:admin1_code":"52.0",
    "gn:asciiname":"Phuc Cuu",
    "gn:country_code":"VN",
    "gn:dem":9,
    "gn:feature_class":"P",
    "gn:feature_code":"PPL",
    "gn:name":"Ph\u00fac C\u1eebu",
    "gn:population":0,
    "gn:timezone":"Asia/Ho_Chi_Minh",
    "iso:country":"VN",
    "name:vie_x_preferred":[
        "Ph\u00fac C\u1eebu"
    ],
    "wof:name":"Phuc Cuu",
    "wof:placetype":"locality"
},
  "geometry": {"coordinates":[105.52477,18.42724],"type":"Point"}
}