{
  "type": "Feature",
  "properties": {
    "gn:admin1_code":"59.0",
    "gn:asciiname":"Mat Nhu",
    "gn:country_code":"VN",
    "gn:dem":4,
    "gn:feature_class":"P",
    "gn:feature_code":"PPL",
    "gn:name":"M\u1eadt Nh\u01b0",
    "gn:population":0,
    "gn:timezone":"Asia/Ho_Chi_Minh",
    "iso:country":"VN",
    "wof:name":"Mat Nhu",
    "wof:placetype":"locality"
},
  "geometry": {"coordinates":[106.08333,20.15],"type":"Point"}
}