{
  "type": "Feature",
  "properties": {
    "gn:admin1_code":"20.0",
    "gn:asciiname":"Ap Trum Tri",
    "gn:cc2":"VN",
    "gn:country_code":"VN",
    "gn:dem":13,
    "gn:feature_class":"P",
    "gn:feature_code":"PPL",
    "gn:name":"\u1ea4p Tr\u00f9m Tri",
    "gn:population":0,
    "gn:timezone":"Asia/Ho_Chi_Minh",
    "iso:country":"VN",
    "name:und_x_variant":[
        "Ap Trum Toi",
        "\u1ea4p Tr\u00f9m Tri"
    ],
    "wof:name":"Ap Trum Tri",
    "wof:placetype":"locality"
},
  "geometry": {"coordinates":[106.51667,10.98333],"type":"Point"}
}