{
  "type": "Feature",
  "properties": {
    "gn:admin1_code":"43.0",
    "gn:asciiname":"Long Khanh Mot",
    "gn:country_code":"VN",
    "gn:dem":38,
    "gn:feature_class":"P",
    "gn:feature_code":"PPL",
    "gn:name":"Long Kh\u00e1nh M\u1ed9t",
    "gn:population":0,
    "gn:timezone":"Asia/Ho_Chi_Minh",
    "iso:country":"VN",
    "name:und_x_variant":[
        "Long Khanh",
        "\u1ea4p Long Kh\u00e1nh"
    ],
    "name:vie_x_preferred":[
        "Long Kh\u00e1nh M\u1ed9t"
    ],
    "name:vie_x_variant":[
        "Long Kh\u00e1nh 1"
    ],
    "wof:name":"Long Khanh Mot",
    "wof:placetype":"locality"
},
  "geometry": {"coordinates":[106.92701,10.8559],"type":"Point"}
}