{
  "type": "Feature",
  "properties": {
    "gn:admin1_code":"91.0",
    "gn:asciiname":"Quang Duc",
    "gn:country_code":"VN",
    "gn:dem":732,
    "gn:feature_class":"P",
    "gn:feature_code":"PPL",
    "gn:name":"Quang Duc",
    "gn:population":0,
    "gn:timezone":"Asia/Ho_Chi_Minh",
    "iso:country":"VN",
    "name:eng_x_preferred":[
        "Quang Duc"
    ],
    "name:und_x_variant":[
        "Bu M\u2019Bre",
        "Bu Xach"
    ],
    "name:vie_x_preferred":[
        "Ki\u1ebfn \u0110\u1ee9c"
    ],
    "wof:name":"Quang Duc",
    "wof:placetype":"locality"
},
  "geometry": {"coordinates":[107.51118,11.99598],"type":"Point"}
}