{
  "type": "Feature",
  "properties": {
    "gn:admin1_code":"66.0",
    "gn:asciiname":"Tay Nam Son",
    "gn:country_code":"VN",
    "gn:dem":664,
    "gn:feature_class":"P",
    "gn:feature_code":"PPL",
    "gn:name":"T\u00e2y Nam S\u01a1n",
    "gn:population":0,
    "gn:timezone":"Asia/Ho_Chi_Minh",
    "iso:country":"VN",
    "name:vie_x_preferred":[
        "T\u00e2y Nam S\u01a1n"
    ],
    "wof:name":"Tay Nam Son",
    "wof:placetype":"locality"
},
  "geometry": {"coordinates":[107.15228,16.3636],"type":"Point"}
}