{
  "type": "Feature",
  "properties": {
    "gn:admin1_code":"24.0",
    "gn:asciiname":"Vinh Hung",
    "gn:country_code":"VN",
    "gn:dem":6,
    "gn:feature_class":"P",
    "gn:feature_code":"PPLA2",
    "gn:name":"V\u0129nh H\u01b0ng",
    "gn:population":0,
    "gn:timezone":"Asia/Ho_Chi_Minh",
    "iso:country":"VN",
    "name:vie_x_preferred":[
        "V\u0129nh H\u01b0ng"
    ],
    "wof:name":"Vinh Hung",
    "wof:placetype":"locality"
},
  "geometry": {"coordinates":[105.78494999999999,10.89067],"type":"Point"}
}