{
  "type": "Feature",
  "properties": {
    "gn:admin1_code":"46.0",
    "gn:asciiname":"Son Lai Su",
    "gn:country_code":"VN",
    "gn:dem":333,
    "gn:feature_class":"P",
    "gn:feature_code":"PPL",
    "gn:name":"S\u01a1n L\u1ea1i S\u1ee9",
    "gn:population":0,
    "gn:timezone":"Asia/Ho_Chi_Minh",
    "iso:country":"VN",
    "wof:name":"Son Lai Su",
    "wof:placetype":"locality"
},
  "geometry": {"coordinates":[109.16667,14.03333],"type":"Point"}
}