{
  "type": "Feature",
  "properties": {
    "gn:admin1_code":"68.0",
    "gn:asciiname":"Hai Mo",
    "gn:country_code":"VN",
    "gn:dem":66,
    "gn:feature_class":"P",
    "gn:feature_code":"PPL",
    "gn:name":"Hai M\u00f4",
    "gn:population":0,
    "gn:timezone":"Asia/Ho_Chi_Minh",
    "iso:country":"VN",
    "name:vie_x_preferred":[
        "Hai M\u00f4"
    ],
    "wof:name":"Hai Mo",
    "wof:placetype":"locality"
},
  "geometry": {"coordinates":[105.43998999999999,21.51922],"type":"Point"}
}