{
  "type": "Feature",
  "properties": {
    "gn:admin1_code":"81.0",
    "gn:asciiname":"Vinh Hau",
    "gn:country_code":"VN",
    "gn:dem":7,
    "gn:feature_class":"P",
    "gn:feature_code":"PPL",
    "gn:name":"V\u0129nh H\u1eadu",
    "gn:population":0,
    "gn:timezone":"Asia/Ho_Chi_Minh",
    "iso:country":"VN",
    "name:und_x_variant":[
        "Vinh H\u1eadu"
    ],
    "name:vie_x_preferred":[
        "V\u0129nh H\u1eadu"
    ],
    "wof:name":"Vinh Hau",
    "wof:placetype":"locality"
},
  "geometry": {"coordinates":[106.02379000000001,20.76935],"type":"Point"}
}