{
  "type": "Feature",
  "properties": {
    "gn:admin1_code":"88.0",
    "gn:asciiname":"Buon Kao",
    "gn:country_code":"VN",
    "gn:dem":417,
    "gn:feature_class":"P",
    "gn:feature_code":"PPL",
    "gn:name":"Bu\u00f4n Kao",
    "gn:population":0,
    "gn:timezone":"Asia/Ho_Chi_Minh",
    "iso:country":"VN",
    "name:vie_x_preferred":[
        "Bu\u00f4n Kao"
    ],
    "wof:name":"Buon Kao",
    "wof:placetype":"locality"
},
  "geometry": {"coordinates":[108.03525,12.62111],"type":"Point"}
}