{
  "type": "Feature",
  "properties": {
    "gn:admin1_code":"24.0",
    "gn:asciiname":"Giong Tho Dia",
    "gn:country_code":"VN",
    "gn:dem":2,
    "gn:feature_class":"P",
    "gn:feature_code":"PPL",
    "gn:name":"Gi\u1ed3ng Th\u00f4 \u0110\u1ecba",
    "gn:population":0,
    "gn:timezone":"Asia/Ho_Chi_Minh",
    "iso:country":"VN",
    "wof:name":"Giong Tho Dia",
    "wof:placetype":"locality"
},
  "geometry": {"coordinates":[106.25,10.93333],"type":"Point"}
}