{
  "type": "Feature",
  "properties": {
    "gn:admin1_code":"88.0",
    "gn:asciiname":"Thon Sau",
    "gn:country_code":"VN",
    "gn:dem":447,
    "gn:feature_class":"P",
    "gn:feature_code":"PPL",
    "gn:name":"Th\u00f4n S\u00e1u",
    "gn:population":0,
    "gn:timezone":"Asia/Ho_Chi_Minh",
    "iso:country":"VN",
    "name:vie_x_preferred":[
        "Th\u00f4n S\u00e1u"
    ],
    "name:vie_x_variant":[
        "Th\u00f4n 6"
    ],
    "wof:name":"Thon Sau",
    "wof:placetype":"locality"
},
  "geometry": {"coordinates":[108.03619999999999,12.30417],"type":"Point"}
}