{
  "type": "Feature",
  "properties": {
    "gn:admin1_code":"89.0",
    "gn:asciiname":"Tan Sao Pin",
    "gn:country_code":"VN",
    "gn:dem":1236,
    "gn:feature_class":"P",
    "gn:feature_code":"PPL",
    "gn:name":"Tan Sao Pin",
    "gn:population":0,
    "gn:timezone":"Asia/Ho_Chi_Minh",
    "iso:country":"VN",
    "wof:name":"Tan Sao Pin",
    "wof:placetype":"locality"
},
  "geometry": {"coordinates":[103.41667,22.45],"type":"Point"}
}