{
  "type": "Feature",
  "properties": {
    "gn:admin1_code":"43.0",
    "gn:asciiname":"Trang Bom",
    "gn:country_code":"VN",
    "gn:dem":61,
    "gn:feature_class":"P",
    "gn:feature_code":"PPLA2",
    "gn:name":"Tr\u1ea3ng Bom",
    "gn:population":0,
    "gn:timezone":"Asia/Ho_Chi_Minh",
    "iso:country":"VN",
    "name:und_x_variant":[
        "X\u00e3 Tr\u1ea3ng B\u00f4m"
    ],
    "name:vie_x_preferred":[
        "Tr\u1ea3ng Bom"
    ],
    "wof:name":"Trang Bom",
    "wof:placetype":"locality"
},
  "geometry": {"coordinates":[107.00588999999999,10.95358],"type":"Point"}
}