{
  "type": "Feature",
  "properties": {
    "gn:admin1_code":"87.0",
    "gn:asciiname":"Dong Hoa",
    "gn:country_code":"VN",
    "gn:dem":3,
    "gn:feature_class":"P",
    "gn:feature_code":"PPL",
    "gn:name":"\u0110\u00f4ng H\u00f2a",
    "gn:population":0,
    "gn:timezone":"Asia/Ho_Chi_Minh",
    "iso:country":"VN",
    "name:vie_x_preferred":[
        "\u0110\u00f4ng H\u00f2a"
    ],
    "wof:name":"Dong Hoa",
    "wof:placetype":"locality"
},
  "geometry": {"coordinates":[105.50106,10.07966],"type":"Point"}
}