{
  "type": "Feature",
  "properties": {
    "gn:admin1_code":"1.0",
    "gn:asciiname":"Phum Krang Chai",
    "gn:country_code":"VN",
    "gn:dem":9,
    "gn:feature_class":"P",
    "gn:feature_code":"PPL",
    "gn:name":"Phum Krang Chai",
    "gn:population":0,
    "gn:timezone":"Asia/Ho_Chi_Minh",
    "iso:country":"VN",
    "wof:name":"Phum Krang Chai",
    "wof:placetype":"locality"
},
  "geometry": {"coordinates":[105.03333000000001,10.48333],"type":"Point"}
}