{
  "type": "Feature",
  "properties": {
    "gn:admin1_code":"70.0",
    "gn:asciiname":"Pang De",
    "gn:country_code":"VN",
    "gn:dem":1244,
    "gn:feature_class":"P",
    "gn:feature_code":"PPL",
    "gn:name":"P\u0103ng D\u00ea",
    "gn:population":0,
    "gn:timezone":"Asia/Ho_Chi_Minh",
    "iso:country":"VN",
    "name:cat_x_preferred":[
        "Pang De"
    ],
    "name:deu_x_preferred":[
        "Pang De"
    ],
    "name:fra_x_preferred":[
        "Pang De"
    ],
    "name:ind_x_preferred":[
        "Pang De"
    ],
    "name:ita_x_preferred":[
        "Pang De"
    ],
    "name:jpn_x_preferred":[
        "\u30db\u30a6\u5fb3"
    ],
    "name:por_x_preferred":[
        "Pang De"
    ],
    "name:tha_x_preferred":[
        "\u0e1a\u0e31\u0e07\u0e40\u0e15\u0e4a\u0e01"
    ],
    "name:vie_x_preferred":[
        "P\u0103ng D\u00ea"
    ],
    "name:vie_x_variant":[
        "B\u00e0ng \u0110\u1ee9c"
    ],
    "wof:name":"Pang De",
    "wof:placetype":"locality"
},
  "geometry": {"coordinates":[104.41202,21.45904],"type":"Point"}
}