{
  "type": "Feature",
  "properties": {
    "gn:admin1_code":"70.0",
    "gn:asciiname":"Pang De",
    "gn:country_code":"VN",
    "gn:dem":1244,
    "gn:feature_class":"P",
    "gn:feature_code":"PPL",
    "gn:name":"P\u0103ng D\u00ea",
    "gn:population":0,
    "gn:timezone":"Asia/Ho_Chi_Minh",
    "iso:country":"VN",
    "name:vie_x_preferred":[
        "P\u0103ng D\u00ea"
    ],
    "wof:name":"Pang De",
    "wof:placetype":"locality"
},
  "geometry": {"coordinates":[104.41202,21.45904],"type":"Point"}
}