{
  "type": "Feature",
  "properties": {
    "gn:admin1_code":"52.0",
    "gn:asciiname":"Tay Hoa",
    "gn:country_code":"VN",
    "gn:dem":9,
    "gn:feature_class":"P",
    "gn:feature_code":"PPL",
    "gn:name":"T\u00e2y H\u00f2a",
    "gn:population":0,
    "gn:timezone":"Asia/Ho_Chi_Minh",
    "iso:country":"VN",
    "name:vie_x_preferred":[
        "T\u00e2y H\u00f2a"
    ],
    "wof:name":"Tay Hoa",
    "wof:placetype":"locality"
},
  "geometry": {"coordinates":[106.00321,18.32996],"type":"Point"}
}