{
  "type": "Feature",
  "properties": {
    "gn:admin1_code":"39.0",
    "gn:asciiname":"Chi Quan Ha",
    "gn:country_code":"VN",
    "gn:dem":129,
    "gn:feature_class":"P",
    "gn:feature_code":"PPL",
    "gn:name":"Chi Quan H\u1ea1",
    "gn:population":0,
    "gn:timezone":"Asia/Ho_Chi_Minh",
    "iso:country":"VN",
    "wof:name":"Chi Quan Ha",
    "wof:placetype":"locality"
},
  "geometry": {"coordinates":[106.45,21.53333],"type":"Point"}
}