{
  "type": "Feature",
  "properties": {
    "gn:admin1_code":"69.0",
    "gn:asciiname":"Tra Con Mot",
    "gn:country_code":"VN",
    "gn:dem":4,
    "gn:feature_class":"P",
    "gn:feature_code":"PPL",
    "gn:name":"Tr\u00e0 C\u00f4n M\u1ed9t",
    "gn:population":0,
    "gn:timezone":"Asia/Ho_Chi_Minh",
    "iso:country":"VN",
    "name:und_x_variant":[
        "Tr\u00e0 Lu\u1ed9c"
    ],
    "name:vie_x_preferred":[
        "Tr\u00e0 C\u00f4n M\u1ed9t"
    ],
    "name:vie_x_variant":[
        "Tr\u00e0 C\u00f4n 1"
    ],
    "wof:name":"Tra Con Mot",
    "wof:placetype":"locality"
},
  "geometry": {"coordinates":[105.99478999999999,10.00239],"type":"Point"}
}