{
  "type": "Feature",
  "properties": {
    "gn:admin1_code":"49.0",
    "gn:asciiname":"Ban Bat",
    "gn:country_code":"VN",
    "gn:dem":105,
    "gn:feature_class":"P",
    "gn:feature_code":"PPL",
    "gn:name":"Ban Bat",
    "gn:population":0,
    "gn:timezone":"Asia/Ho_Chi_Minh",
    "iso:country":"VN",
    "name:und_x_variant":[
        "Buon Bat",
        "Ban Bat"
    ],
    "wof:name":"Ban Bat",
    "wof:placetype":"locality"
},
  "geometry": {"coordinates":[108.65000000000001,13.21667],"type":"Point"}
}