{
  "type": "Feature",
  "properties": {
    "gn:admin1_code":"80.0",
    "gn:asciiname":"Thinh Dai",
    "gn:country_code":"VN",
    "gn:dem":7,
    "gn:feature_class":"P",
    "gn:feature_code":"PPL",
    "gn:name":"Th\u1ec9nh \u0110\u1ea1i",
    "gn:population":0,
    "gn:timezone":"Asia/Ho_Chi_Minh",
    "iso:country":"VN",
    "name:vie_x_preferred":[
        "Th\u1ec9nh \u0110\u1ea1i"
    ],
    "wof:name":"Thinh Dai",
    "wof:placetype":"locality"
},
  "geometry": {"coordinates":[105.88461,20.64205],"type":"Point"}
}