{
  "type": "Feature",
  "properties": {
    "gn:admin1_code":"89.0",
    "gn:asciiname":"Po Cha",
    "gn:country_code":"VN",
    "gn:dem":782,
    "gn:feature_class":"P",
    "gn:feature_code":"PPL",
    "gn:name":"Po Ch\u00e0",
    "gn:population":0,
    "gn:timezone":"Asia/Ho_Chi_Minh",
    "iso:country":"VN",
    "name:vie_x_preferred":[
        "Po Ch\u00e0"
    ],
    "wof:name":"Po Cha",
    "wof:placetype":"locality"
},
  "geometry": {"coordinates":[103.44208,22.54293],"type":"Point"}
}