{
  "type": "Feature",
  "properties": {
    "gn:admin1_code":"58.0",
    "gn:asciiname":"Trang Ho",
    "gn:country_code":"VN",
    "gn:dem":22,
    "gn:feature_class":"P",
    "gn:feature_code":"PPL",
    "gn:name":"Trang H\u1ed9",
    "gn:population":0,
    "gn:timezone":"Asia/Ho_Chi_Minh",
    "iso:country":"VN",
    "name:und_x_variant":[
        "Trang Hoi",
        "Tr\u00e0ng H\u1ed9"
    ],
    "name:vie_x_preferred":[
        "Trang H\u1ed9"
    ],
    "wof:name":"Trang Ho",
    "wof:placetype":"locality"
},
  "geometry": {"coordinates":[105.65179000000001,19.24166],"type":"Point"}
}