{
  "type": "Feature",
  "properties": {
    "gn:admin1_code":"63.0",
    "gn:asciiname":"My Trang",
    "gn:country_code":"VN",
    "gn:dem":13,
    "gn:feature_class":"P",
    "gn:feature_code":"PPL",
    "gn:name":"M\u1ef9 Trang",
    "gn:population":0,
    "gn:timezone":"Asia/Ho_Chi_Minh",
    "iso:country":"VN",
    "name:vie_x_preferred":[
        "M\u1ef9 Trang"
    ],
    "wof:name":"My Trang",
    "wof:placetype":"locality"
},
  "geometry": {"coordinates":[108.97906,14.77149],"type":"Point"}
}