{
  "type": "Feature",
  "properties": {
    "gn:admin1_code":"68.0",
    "gn:asciiname":"Ngoi Thang",
    "gn:country_code":"VN",
    "gn:dem":79,
    "gn:feature_class":"P",
    "gn:feature_code":"PPL",
    "gn:name":"Ng\u00f2i Th\u1eafng",
    "gn:population":0,
    "gn:timezone":"Asia/Ho_Chi_Minh",
    "iso:country":"VN",
    "name:vie_x_preferred":[
        "Ng\u00f2i Th\u1eafng"
    ],
    "wof:name":"Ngoi Thang",
    "wof:placetype":"locality"
},
  "geometry": {"coordinates":[105.36045,21.72234],"type":"Point"}
}