{
  "type": "Feature",
  "properties": {
    "gn:admin1_code":"72.0",
    "gn:asciiname":"Na Pet",
    "gn:country_code":"VN",
    "gn:dem":624,
    "gn:feature_class":"P",
    "gn:feature_code":"PPL",
    "gn:name":"N\u00e0 P\u00e9t",
    "gn:population":0,
    "gn:timezone":"Asia/Ho_Chi_Minh",
    "iso:country":"VN",
    "name:vie_x_preferred":[
        "N\u00e0 P\u00e9t"
    ],
    "wof:name":"Na Pet",
    "wof:placetype":"locality"
},
  "geometry": {"coordinates":[105.97346,22.22349],"type":"Point"}
}