{
  "type": "Feature",
  "properties": {
    "gn:admin1_code":"88.0",
    "gn:asciiname":"Dong Giang Hai",
    "gn:country_code":"VN",
    "gn:dem":432,
    "gn:feature_class":"P",
    "gn:feature_code":"PPL",
    "gn:name":"\u0110\u00f4ng Giang Hai",
    "gn:population":0,
    "gn:timezone":"Asia/Ho_Chi_Minh",
    "iso:country":"VN",
    "name:vie_x_preferred":[
        "\u0110\u00f4ng Giang Hai"
    ],
    "name:vie_x_variant":[
        "\u0110\u00f4ng Giang 2"
    ],
    "wof:name":"Dong Giang Hai",
    "wof:placetype":"locality"
},
  "geometry": {"coordinates":[108.10796999999999,12.39029],"type":"Point"}
}