{
  "type": "Feature",
  "properties": {
    "gn:admin1_code":"64.0",
    "gn:asciiname":"Ha Loi Thuong",
    "gn:country_code":"VN",
    "gn:dem":8,
    "gn:feature_class":"P",
    "gn:feature_code":"PPL",
    "gn:name":"H\u00e0 L\u1ee3i Th\u01b0\u1ee3ng",
    "gn:population":0,
    "gn:timezone":"Asia/Ho_Chi_Minh",
    "iso:country":"VN",
    "name:vie_x_preferred":[
        "H\u00e0 L\u1ee3i Th\u01b0\u1ee3ng"
    ],
    "wof:name":"Ha Loi Thuong",
    "wof:placetype":"locality"
},
  "geometry": {"coordinates":[107.16052000000001,16.9318],"type":"Point"}
}