{
  "type": "Feature",
  "properties": {
    "gn:admin1_code":"72.0",
    "gn:asciiname":"Na Cuom",
    "gn:country_code":"VN",
    "gn:dem":156,
    "gn:feature_class":"P",
    "gn:feature_code":"PPL",
    "gn:name":"N\u00e0 C\u01b0\u1edfm",
    "gn:population":0,
    "gn:timezone":"Asia/Ho_Chi_Minh",
    "iso:country":"VN",
    "name:vie_x_preferred":[
        "N\u00e0 C\u01b0\u1edfm"
    ],
    "wof:name":"Na Cuom",
    "wof:placetype":"locality"
},
  "geometry": {"coordinates":[105.81411,22.15178],"type":"Point"}
}