{
  "type": "Feature",
  "properties": {
    "gn:admin1_code":"63.0",
    "gn:asciiname":"Ong Don",
    "gn:country_code":"VN",
    "gn:dem":669,
    "gn:feature_class":"P",
    "gn:feature_code":"PPL",
    "gn:name":"\u00d4ng \u0110\u00f4n",
    "gn:population":0,
    "gn:timezone":"Asia/Ho_Chi_Minh",
    "iso:country":"VN",
    "name:vie_x_preferred":[
        "\u00d4ng \u0110\u00f4n"
    ],
    "wof:name":"Ong Don",
    "wof:placetype":"locality"
},
  "geometry": {"coordinates":[108.36181000000001,14.88602],"type":"Point"}
}