{
  "type": "Feature",
  "properties": {
    "gn:admin1_code":"34.0",
    "gn:asciiname":"Lang Lua",
    "gn:country_code":"VN",
    "gn:dem":187,
    "gn:feature_class":"P",
    "gn:feature_code":"PPL",
    "gn:name":"L\u00e0ng L\u00faa",
    "gn:population":0,
    "gn:timezone":"Asia/Ho_Chi_Minh",
    "iso:country":"VN",
    "name:vie_x_preferred":[
        "L\u00e0ng L\u00faa"
    ],
    "wof:name":"Lang Lua",
    "wof:placetype":"locality"
},
  "geometry": {"coordinates":[105.13573,20.0121],"type":"Point"}
}