{
  "type": "Feature",
  "properties": {
    "gn:admin1_code":"58.0",
    "gn:asciiname":"Cu Dai",
    "gn:country_code":"VN",
    "gn:dem":24,
    "gn:feature_class":"P",
    "gn:feature_code":"PPL",
    "gn:name":"C\u01b0 \u0110\u1ea1i",
    "gn:population":0,
    "gn:timezone":"Asia/Ho_Chi_Minh",
    "iso:country":"VN",
    "wof:name":"Cu Dai",
    "wof:placetype":"locality"
},
  "geometry": {"coordinates":[105.46666999999999,18.81667],"type":"Point"}
}