{
  "type": "Feature",
  "properties": {
    "gn:admin1_code":"44.0",
    "gn:asciiname":"Trai Khoai",
    "gn:country_code":"VN",
    "gn:dem":45,
    "gn:feature_class":"P",
    "gn:feature_code":"PPL",
    "gn:name":"Tr\u1ea1i Khoai",
    "gn:population":0,
    "gn:timezone":"Asia/Ho_Chi_Minh",
    "iso:country":"VN",
    "name:und_x_variant":[
        "Xom Trai Khoang",
        "X\u00f3m Tr\u1ea1i Khoai"
    ],
    "name:vie_x_preferred":[
        "Tr\u1ea1i Khoai"
    ],
    "wof:name":"Trai Khoai",
    "wof:placetype":"locality"
},
  "geometry": {"coordinates":[105.34479,21.13174],"type":"Point"}
}