{
  "type": "Feature",
  "properties": {
    "gn:admin1_code":"70.0",
    "gn:asciiname":"Vu Son",
    "gn:country_code":"VN",
    "gn:dem":58,
    "gn:feature_class":"P",
    "gn:feature_code":"PPL",
    "gn:name":"V\u0169 S\u01a1n",
    "gn:population":0,
    "gn:timezone":"Asia/Ho_Chi_Minh",
    "iso:country":"VN",
    "name:vie_x_preferred":[
        "V\u0169 S\u01a1n"
    ],
    "wof:name":"Vu Son",
    "wof:placetype":"locality"
},
  "geometry": {"coordinates":[105.03513,21.80677],"type":"Point"}
}