{
  "type": "Feature",
  "properties": {
    "gn:admin1_code":"52.0",
    "gn:asciiname":"Nam Lien",
    "gn:country_code":"VN",
    "gn:dem":5,
    "gn:feature_class":"P",
    "gn:feature_code":"PPL",
    "gn:name":"Nam Li\u00ean",
    "gn:population":0,
    "gn:timezone":"Asia/Ho_Chi_Minh",
    "iso:country":"VN",
    "name:vie_x_preferred":[
        "Nam Li\u00ean"
    ],
    "wof:name":"Nam Lien",
    "wof:placetype":"locality"
},
  "geometry": {"coordinates":[105.95368999999999,18.26039],"type":"Point"}
}