{
  "type": "Feature",
  "properties": {
    "gn:admin1_code":"92.0",
    "gn:asciiname":"Na Cang",
    "gn:country_code":"VN",
    "gn:dem":571,
    "gn:feature_class":"P",
    "gn:feature_code":"PPL",
    "gn:name":"N\u00e0 Cang",
    "gn:population":0,
    "gn:timezone":"Asia/Ho_Chi_Minh",
    "iso:country":"VN",
    "name:vie_x_preferred":[
        "N\u00e0 Cang"
    ],
    "wof:name":"Na Cang",
    "wof:placetype":"locality"
},
  "geometry": {"coordinates":[102.90361,21.88739],"type":"Point"}
}