{
  "type": "Feature",
  "properties": {
    "gn:admin1_code":"31.0",
    "gn:asciiname":"Binh My",
    "gn:cc2":"VN",
    "gn:country_code":"VN",
    "gn:dem":1,
    "gn:feature_class":"P",
    "gn:feature_code":"PPL",
    "gn:name":"B\u00ecnh M\u1ef9",
    "gn:population":0,
    "gn:timezone":"Asia/Ho_Chi_Minh",
    "iso:country":"VN",
    "name:und_x_variant":[
        "My Binh",
        "B\u00ecnh M\u1ef9"
    ],
    "wof:name":"Binh My",
    "wof:placetype":"locality"
},
  "geometry": {"coordinates":[106.65000000000001,10.96667],"type":"Point"}
}