{
  "type": "Feature",
  "properties": {
    "gn:admin1_code":"83.0",
    "gn:asciiname":"Xom Xe",
    "gn:country_code":"VN",
    "gn:dem":96,
    "gn:feature_class":"P",
    "gn:feature_code":"PPL",
    "gn:name":"X\u00f3m Xe",
    "gn:population":0,
    "gn:timezone":"Asia/Ho_Chi_Minh",
    "iso:country":"VN",
    "name:und_x_variant":[
        "X\u00f3m X\u00ea"
    ],
    "name:vie_x_preferred":[
        "X\u00f3m Xe"
    ],
    "wof:name":"Xom Xe",
    "wof:placetype":"locality"
},
  "geometry": {"coordinates":[105.1504,21.09577],"type":"Point"}
}