{
  "type": "Feature",
  "properties": {
    "gn:admin1_code":"39.0",
    "gn:asciiname":"Bac Lang",
    "gn:country_code":"VN",
    "gn:dem":210,
    "gn:feature_class":"P",
    "gn:feature_code":"PPL",
    "gn:name":"B\u00e1c Lang",
    "gn:population":0,
    "gn:timezone":"Asia/Ho_Chi_Minh",
    "iso:country":"VN",
    "wof:name":"Bac Lang",
    "wof:placetype":"locality"
},
  "geometry": {"coordinates":[106.58333,21.91667],"type":"Point"}
}