{
  "type": "Feature",
  "properties": {
    "gn:admin1_code":"70.0",
    "gn:asciiname":"Thi Tran Mau A",
    "gn:country_code":"VN",
    "gn:dem":52,
    "gn:feature_class":"P",
    "gn:feature_code":"PPL",
    "gn:name":"Th\u1ecb Tr\u1ea5n M\u1eadu A",
    "gn:population":0,
    "gn:timezone":"Asia/Ho_Chi_Minh",
    "iso:country":"VN",
    "name:und_x_variant":[
        "M\u1eadu A"
    ],
    "name:vie_x_preferred":[
        "Th\u1ecb Tr\u1ea5n M\u1eadu A"
    ],
    "wof:name":"Thi Tran Mau A",
    "wof:placetype":"locality"
},
  "geometry": {"coordinates":[104.69029999999999,21.8771],"type":"Point"}
}