{
  "type": "Feature",
  "properties": {
    "gn:admin1_code":"30.0",
    "gn:asciiname":"Keo Tien",
    "gn:country_code":"VN",
    "gn:dem":347,
    "gn:feature_class":"P",
    "gn:feature_code":"PPL",
    "gn:name":"Keo Ti\u00ean",
    "gn:population":0,
    "gn:timezone":"Asia/Ho_Chi_Minh",
    "iso:country":"VN",
    "name:vie_x_preferred":[
        "Keo Ti\u00ean"
    ],
    "wof:name":"Keo Tien",
    "wof:placetype":"locality"
},
  "geometry": {"coordinates":[107.54839,21.50865],"type":"Point"}
}