{
  "type": "Feature",
  "properties": {
    "gn:admin1_code":"68.0",
    "gn:asciiname":"Dong Tan",
    "gn:country_code":"VN",
    "gn:dem":241,
    "gn:feature_class":"P",
    "gn:feature_code":"PPL",
    "gn:name":"Dong Tan",
    "gn:population":0,
    "gn:timezone":"Asia/Ho_Chi_Minh",
    "iso:country":"VN",
    "name:und_x_variant":[
        "Khoun Deo",
        "Dong Tan"
    ],
    "wof:name":"Dong Tan",
    "wof:placetype":"locality"
},
  "geometry": {"coordinates":[105.11667,22.08333],"type":"Point"}
}