{
  "type": "Feature",
  "properties": {
    "gn:admin1_code":"39.0",
    "gn:asciiname":"Tien Hoi",
    "gn:country_code":"VN",
    "gn:dem":420,
    "gn:feature_class":"P",
    "gn:feature_code":"PPL",
    "gn:name":"Ti\u00ean H\u1ed3i",
    "gn:population":0,
    "gn:timezone":"Asia/Ho_Chi_Minh",
    "iso:country":"VN",
    "name:vie_x_preferred":[
        "Ti\u00ean H\u1ed3i"
    ],
    "wof:name":"Tien Hoi",
    "wof:placetype":"locality"
},
  "geometry": {"coordinates":[106.35229,21.85447000000001],"type":"Point"}
}