{
  "type": "Feature",
  "properties": {
    "gn:admin1_code":"61.0",
    "gn:asciiname":"Ngo Chau",
    "gn:country_code":"VN",
    "gn:dem":55,
    "gn:feature_class":"P",
    "gn:feature_code":"PPL",
    "gn:name":"Ng\u00f4 Ch\u00e2u",
    "gn:population":0,
    "gn:timezone":"Asia/Ho_Chi_Minh",
    "iso:country":"VN",
    "wof:name":"Ngo Chau",
    "wof:placetype":"locality"
},
  "geometry": {"coordinates":[109.09999999999999,13.45],"type":"Point"}
}