{
  "type": "Feature",
  "properties": {
    "gn:admin1_code":"34.0",
    "gn:asciiname":"Chom Co Gieu",
    "gn:country_code":"VN",
    "gn:dem":30,
    "gn:feature_class":"P",
    "gn:feature_code":"PPL",
    "gn:name":"Ch\u00f2m Co Gi\u1ec1u",
    "gn:population":0,
    "gn:timezone":"Asia/Ho_Chi_Minh",
    "iso:country":"VN",
    "wof:name":"Chom Co Gieu",
    "wof:placetype":"locality"
},
  "geometry": {"coordinates":[105.51667,20.08333],"type":"Point"}
}