{
  "type": "Feature",
  "properties": {
    "gn:admin1_code":"24.0",
    "gn:asciiname":"Cau Duc",
    "gn:country_code":"VN",
    "gn:dem":0,
    "gn:feature_class":"P",
    "gn:feature_code":"PPL",
    "gn:name":"C\u1ea7u \u0110\u00fac",
    "gn:population":0,
    "gn:timezone":"Asia/Ho_Chi_Minh",
    "iso:country":"VN",
    "name:vie_x_preferred":[
        "C\u1ea7u \u0110\u00fac"
    ],
    "wof:name":"Cau Duc",
    "wof:placetype":"locality"
},
  "geometry": {"coordinates":[106.45677999999999,10.41571],"type":"Point"}
}