{
  "type": "Feature",
  "properties": {
    "gn:admin1_code":"43.0",
    "gn:asciiname":"Ap Tam",
    "gn:country_code":"VN",
    "gn:dem":142,
    "gn:feature_class":"P",
    "gn:feature_code":"PPL",
    "gn:name":"\u1ea4p T\u00e1m",
    "gn:population":0,
    "gn:timezone":"Asia/Ho_Chi_Minh",
    "iso:country":"VN",
    "name:vie_x_preferred":[
        "\u1ea4p T\u00e1m"
    ],
    "name:vie_x_variant":[
        "\u1ea4p 8"
    ],
    "wof:name":"Ap Tam",
    "wof:placetype":"locality"
},
  "geometry": {"coordinates":[107.40666,10.96045],"type":"Point"}
}