{
  "type": "Feature",
  "properties": {
    "gn:admin1_code":"71.0",
    "gn:asciiname":"Dong Bui",
    "gn:country_code":"VN",
    "gn:dem":11,
    "gn:feature_class":"P",
    "gn:feature_code":"PPL",
    "gn:name":"\u0110\u1ed3ng B\u00f9i",
    "gn:population":0,
    "gn:timezone":"Asia/Ho_Chi_Minh",
    "iso:country":"VN",
    "name:vie_x_preferred":[
        "\u0110\u1ed3ng B\u00f9i"
    ],
    "wof:name":"Dong Bui",
    "wof:placetype":"locality"
},
  "geometry": {"coordinates":[106.18876000000002,21.31182],"type":"Point"}
}