{
  "type": "Feature",
  "properties": {
    "gn:admin1_code":"49.0",
    "gn:asciiname":"Plei Deu Ngol",
    "gn:country_code":"VN",
    "gn:dem":503,
    "gn:feature_class":"P",
    "gn:feature_code":"PPL",
    "gn:name":"Plei Deu Ngol",
    "gn:population":0,
    "gn:timezone":"Asia/Ho_Chi_Minh",
    "iso:country":"VN",
    "wof:name":"Plei Deu Ngol",
    "wof:placetype":"locality"
},
  "geometry": {"coordinates":[107.98333,13.68333],"type":"Point"}
}