{
  "type": "Feature",
  "properties": {
    "gn:admin1_code":"39.0",
    "gn:asciiname":"Ban Pieng",
    "gn:country_code":"VN",
    "gn:dem":174,
    "gn:feature_class":"P",
    "gn:feature_code":"PPL",
    "gn:name":"B\u1ea3n Pi\u1ec1ng",
    "gn:population":0,
    "gn:timezone":"Asia/Ho_Chi_Minh",
    "iso:country":"VN",
    "name:vie_x_preferred":[
        "B\u1ea3n Pi\u1ec1ng"
    ],
    "wof:name":"Ban Pieng",
    "wof:placetype":"locality"
},
  "geometry": {"coordinates":[106.97620999999999,21.48981],"type":"Point"}
}