{
  "type": "Feature",
  "properties": {
    "gn:admin1_code":"58.0",
    "gn:asciiname":"Ban Huoi Heo",
    "gn:country_code":"VN",
    "gn:dem":683,
    "gn:feature_class":"P",
    "gn:feature_code":"PPL",
    "gn:name":"B\u1ea3n Hu\u00f4i H\u1eb9o",
    "gn:population":0,
    "gn:timezone":"Asia/Ho_Chi_Minh",
    "iso:country":"VN",
    "name:und_x_variant":[
        "Ban Houei Heo",
        "B\u1ea3n Hu\u00f4i H\u1eb9o"
    ],
    "wof:name":"Ban Huoi Heo",
    "wof:placetype":"locality"
},
  "geometry": {"coordinates":[104.13333,19.46667],"type":"Point"}
}