{
  "type": "Feature",
  "properties": {
    "gn:admin1_code":"72.0",
    "gn:asciiname":"Khuoi Giac",
    "gn:country_code":"VN",
    "gn:dem":124,
    "gn:feature_class":"P",
    "gn:feature_code":"PPL",
    "gn:name":"Khu\u1ed5i Gi\u00e1c",
    "gn:population":0,
    "gn:timezone":"Asia/Ho_Chi_Minh",
    "iso:country":"VN",
    "name:vie_x_preferred":[
        "Khu\u1ed5i Gi\u00e1c"
    ],
    "wof:name":"Khuoi Giac",
    "wof:placetype":"locality"
},
  "geometry": {"coordinates":[105.87715,22.04296],"type":"Point"}
}