{
  "type": "Feature",
  "properties": {
    "gn:admin1_code":"61.0",
    "gn:asciiname":"An Nghiep",
    "gn:country_code":"VN",
    "gn:dem":4,
    "gn:feature_class":"P",
    "gn:feature_code":"PPL",
    "gn:name":"An Nghi\u1ec7p",
    "gn:population":0,
    "gn:timezone":"Asia/Ho_Chi_Minh",
    "iso:country":"VN",
    "name:und_x_variant":[
        "An Nghi\u00ean",
        "An Nghi\u1ec7p",
        "An Nghien"
    ],
    "wof:name":"An Nghiep",
    "wof:placetype":"locality"
},
  "geometry": {"coordinates":[109.21666999999999,13.01667],"type":"Point"}
}