{
  "type": "Feature",
  "properties": {
    "gn:admin1_code":"34.0",
    "gn:asciiname":"Dong Quac",
    "gn:country_code":"VN",
    "gn:dem":103,
    "gn:feature_class":"P",
    "gn:feature_code":"PPL",
    "gn:name":"Dong Quac",
    "gn:population":0,
    "gn:timezone":"Asia/Ho_Chi_Minh",
    "iso:country":"VN",
    "name:und_x_variant":[
        "\u0110\u1ed3ng Qu\u1ed1c"
    ],
    "wof:name":"Dong Quac",
    "wof:placetype":"locality"
},
  "geometry": {"coordinates":[105.56667,19.58333],"type":"Point"}
}