{
  "type": "Feature",
  "properties": {
    "gn:admin1_code":"32.0",
    "gn:asciiname":"Ban Bai Vang A",
    "gn:country_code":"VN",
    "gn:dem":142,
    "gn:feature_class":"P",
    "gn:feature_code":"PPL",
    "gn:name":"B\u1ea3n B\u00e3i V\u00e0ng A",
    "gn:population":0,
    "gn:timezone":"Asia/Ho_Chi_Minh",
    "iso:country":"VN",
    "name:vie_x_preferred":[
        "B\u1ea3n B\u00e3i V\u00e0ng A"
    ],
    "wof:name":"Ban Bai Vang A",
    "wof:placetype":"locality"
},
  "geometry": {"coordinates":[104.54331999999999,21.07857000000001],"type":"Point"}
}