{
  "type": "Feature",
  "properties": {
    "gn:admin1_code":"58.0",
    "gn:asciiname":"Ban Nguon",
    "gn:country_code":"VN",
    "gn:dem":53,
    "gn:feature_class":"P",
    "gn:feature_code":"PPL",
    "gn:name":"B\u1ea3n Ngu\u00f2n",
    "gn:population":0,
    "gn:timezone":"Asia/Ho_Chi_Minh",
    "iso:country":"VN",
    "wof:name":"Ban Nguon",
    "wof:placetype":"locality"
},
  "geometry": {"coordinates":[104.83333,19.08333],"type":"Point"}
}