{
  "type": "Feature",
  "properties": {
    "gn:admin1_code":"61.0",
    "gn:asciiname":"Thanh An",
    "gn:country_code":"VN",
    "gn:dem":21,
    "gn:feature_class":"P",
    "gn:feature_code":"PPL",
    "gn:name":"Th\u1ea1nh An",
    "gn:population":0,
    "gn:timezone":"Asia/Ho_Chi_Minh",
    "iso:country":"VN",
    "name:vie_x_preferred":[
        "Th\u1ea1nh An"
    ],
    "name:vie_x_variant":[
        "Th\u00e0nh An"
    ],
    "wof:name":"Thanh An",
    "wof:placetype":"locality"
},
  "geometry": {"coordinates":[109.09406,13.02307],"type":"Point"}
}