{
  "type": "Feature",
  "properties": {
    "gn:admin1_code":"63.0",
    "gn:asciiname":"Tra Bung",
    "gn:country_code":"VN",
    "gn:dem":687,
    "gn:feature_class":"P",
    "gn:feature_code":"PPL",
    "gn:name":"Tr\u00e0 Bung",
    "gn:population":0,
    "gn:timezone":"Asia/Ho_Chi_Minh",
    "iso:country":"VN",
    "name:vie_x_preferred":[
        "Tr\u00e0 Bung"
    ],
    "wof:name":"Tra Bung",
    "wof:placetype":"locality"
},
  "geometry": {"coordinates":[108.39194999999999,15.20092],"type":"Point"}
}