{
  "type": "Feature",
  "properties": {
    "gn:admin1_code":"84.0",
    "gn:asciiname":"Nong Lam",
    "gn:country_code":"VN",
    "gn:dem":8,
    "gn:feature_class":"P",
    "gn:feature_code":"PPL",
    "gn:name":"N\u00f4ng L\u00e2m",
    "gn:population":0,
    "gn:timezone":"Asia/Ho_Chi_Minh",
    "iso:country":"VN",
    "name:und_x_variant":[
        "Dai Phuoc An",
        "N\u00f4ng L\u00e2m"
    ],
    "wof:name":"Nong Lam",
    "wof:placetype":"locality"
},
  "geometry": {"coordinates":[108.05,15.86667],"type":"Point"}
}