{
  "type": "Feature",
  "properties": {
    "gn:admin1_code":"90.0",
    "gn:asciiname":"Ban Seo Khai Hoa",
    "gn:country_code":"VN",
    "gn:dem":1156,
    "gn:feature_class":"P",
    "gn:feature_code":"PPL",
    "gn:name":"B\u1ea3n Seo Khai Hoa",
    "gn:population":0,
    "gn:timezone":"Asia/Ho_Chi_Minh",
    "iso:country":"VN",
    "name:und_x_variant":[
        "Giao Khai Hoa"
    ],
    "name:vie_x_preferred":[
        "B\u1ea3n Seo Khai Hoa"
    ],
    "wof:name":"Ban Seo Khai Hoa",
    "wof:placetype":"locality"
},
  "geometry": {"coordinates":[104.31034,22.70227],"type":"Point"}
}