{
  "type": "Feature",
  "properties": {
    "gn:admin1_code":"88.0",
    "gn:asciiname":"Ban Dle Ya",
    "gn:cc2":"VN",
    "gn:country_code":"VN",
    "gn:dem":858,
    "gn:feature_class":"P",
    "gn:feature_code":"PPL",
    "gn:name":"Ban Dl\u00e9 Ya",
    "gn:population":0,
    "gn:timezone":"Asia/Ho_Chi_Minh",
    "iso:country":"VN",
    "name:und_x_variant":[
        "Buon Dle Ya",
        "Ban Dl\u00e9 Ya"
    ],
    "wof:name":"Ban Dle Ya",
    "wof:placetype":"locality"
},
  "geometry": {"coordinates":[108.38333,13.16667],"type":"Point"}
}