{
  "type": "Feature",
  "properties": {
    "gn:admin1_code":"72.0",
    "gn:asciiname":"Na Muong",
    "gn:country_code":"VN",
    "gn:dem":157,
    "gn:feature_class":"P",
    "gn:feature_code":"PPL",
    "gn:name":"N\u00e0 Mu\u1ed3ng",
    "gn:population":0,
    "gn:timezone":"Asia/Ho_Chi_Minh",
    "iso:country":"VN",
    "name:und_x_variant":[
        "Na Mouong"
    ],
    "name:vie_x_preferred":[
        "N\u00e0 Mu\u1ed3ng"
    ],
    "wof:name":"Na Muong",
    "wof:placetype":"locality"
},
  "geometry": {"coordinates":[105.92155,22.18121],"type":"Point"}
}