{
  "type": "Feature",
  "properties": {
    "gn:admin1_code":"49.0",
    "gn:asciiname":"Plei Bak",
    "gn:country_code":"VN",
    "gn:dem":574,
    "gn:feature_class":"P",
    "gn:feature_code":"PPL",
    "gn:name":"Plei Bak",
    "gn:population":0,
    "gn:timezone":"Asia/Ho_Chi_Minh",
    "iso:country":"VN",
    "wof:name":"Plei Bak",
    "wof:placetype":"locality"
},
  "geometry": {"coordinates":[107.93333,13.76667],"type":"Point"}
}