{
  "type": "Feature",
  "properties": {
    "gn:admin1_code":"93.0",
    "gn:asciiname":"Ap Dong Binh",
    "gn:country_code":"VN",
    "gn:dem":-1,
    "gn:feature_class":"P",
    "gn:feature_code":"PPL",
    "gn:name":"\u1ea4p \u0110\u00f4ng B\u00ecnh",
    "gn:population":0,
    "gn:timezone":"Asia/Ho_Chi_Minh",
    "iso:country":"VN",
    "wof:name":"Ap Dong Binh",
    "wof:placetype":"locality"
},
  "geometry": {"coordinates":[105.82805999999999,9.86806],"type":"Point"}
}