{
  "type": "Feature",
  "properties": {
    "gn:admin1_code":"62.0",
    "gn:asciiname":"Ba Don",
    "gn:country_code":"VN",
    "gn:dem":8,
    "gn:feature_class":"P",
    "gn:feature_code":"PPLA2",
    "gn:name":"Ba \u0110\u1ed3n",
    "gn:population":0,
    "gn:timezone":"Asia/Ho_Chi_Minh",
    "iso:country":"VN",
    "name:und_x_variant":[
        "Ba \u0110\u1ed3n",
        "Qu\u1ea3ng Trach"
    ],
    "wof:name":"Ba Don",
    "wof:placetype":"locality"
},
  "geometry": {"coordinates":[106.42355000000001,17.75352999999999],"type":"Point"}
}