{
  "type": "Feature",
  "properties": {
    "gn:admin1_code":"44.0",
    "gn:asciiname":"Vi Thuy",
    "gn:country_code":"VN",
    "gn:dem":24,
    "gn:feature_class":"P",
    "gn:feature_code":"PPL",
    "gn:name":"V\u1ecb Th\u1ee7y",
    "gn:population":0,
    "gn:timezone":"Asia/Ho_Chi_Minh",
    "iso:country":"VN",
    "name:vie_x_preferred":[
        "V\u1ecb Th\u1ee7y"
    ],
    "wof:name":"Vi Thuy",
    "wof:placetype":"locality"
},
  "geometry": {"coordinates":[105.47502,21.12017],"type":"Point"}
}