{
  "type": "Feature",
  "properties": {
    "gn:admin1_code":"88.0",
    "gn:asciiname":"Loc Ha",
    "gn:country_code":"VN",
    "gn:dem":733,
    "gn:feature_class":"P",
    "gn:feature_code":"PPL",
    "gn:name":"L\u1ed9c H\u00e0",
    "gn:population":0,
    "gn:timezone":"Asia/Ho_Chi_Minh",
    "iso:country":"VN",
    "name:vie_x_preferred":[
        "L\u1ed9c H\u00e0"
    ],
    "wof:name":"Loc Ha",
    "wof:placetype":"locality"
},
  "geometry": {"coordinates":[108.32368,12.98722],"type":"Point"}
}