{
  "type": "Feature",
  "properties": {
    "gn:admin1_code":"89.0",
    "gn:asciiname":"Tien Po",
    "gn:country_code":"VN",
    "gn:dem":951,
    "gn:feature_class":"P",
    "gn:feature_code":"PPL",
    "gn:name":"Tien Po",
    "gn:population":0,
    "gn:timezone":"Asia/Ho_Chi_Minh",
    "iso:country":"VN",
    "wof:name":"Tien Po",
    "wof:placetype":"locality"
},
  "geometry": {"coordinates":[103.38333,22.45],"type":"Point"}
}