{
  "type": "Feature",
  "properties": {
    "gn:admin1_code":"52.0",
    "gn:asciiname":"Xom Do",
    "gn:country_code":"VN",
    "gn:dem":3,
    "gn:feature_class":"P",
    "gn:feature_code":"PPL",
    "gn:name":"Xom Do",
    "gn:population":0,
    "gn:timezone":"Asia/Ho_Chi_Minh",
    "iso:country":"VN",
    "name:und_x_variant":[
        "C\u1ea7u \u0110\u00e1"
    ],
    "wof:name":"Xom Do",
    "wof:placetype":"locality"
},
  "geometry": {"coordinates":[106.09999999999999,18.23333],"type":"Point"}
}