{
  "type": "Feature",
  "properties": {
    "gn:admin1_code":"60.0",
    "gn:asciiname":"Phuoc Thien",
    "gn:country_code":"VN",
    "gn:dem":17,
    "gn:feature_class":"P",
    "gn:feature_code":"PPL",
    "gn:name":"Ph\u01b0\u1edbc Thi\u1ec7n",
    "gn:population":0,
    "gn:timezone":"Asia/Ho_Chi_Minh",
    "iso:country":"VN",
    "name:und_x_variant":[
        "Th\u00f4n Ph\u01b0\u1edbc Thi\u1ec7n"
    ],
    "name:vie_x_preferred":[
        "Ph\u01b0\u1edbc Thi\u1ec7n"
    ],
    "wof:name":"Phuoc Thien",
    "wof:placetype":"locality"
},
  "geometry": {"coordinates":[108.89767000000001,11.6142],"type":"Point"}
}