{
  "type": "Feature",
  "properties": {
    "gn:admin1_code":"1.0",
    "gn:asciiname":"Can Thoi",
    "gn:country_code":"VN",
    "gn:dem":7,
    "gn:feature_class":"P",
    "gn:feature_code":"PPL",
    "gn:name":"C\u1ea7n Th\u1edbi",
    "gn:population":0,
    "gn:timezone":"Asia/Ho_Chi_Minh",
    "iso:country":"VN",
    "name:und_x_variant":[
        "\u1ea4p C\u1ea7n Th\u1edbi"
    ],
    "name:vie_x_preferred":[
        "C\u1ea7n Th\u1edbi"
    ],
    "wof:name":"Can Thoi",
    "wof:placetype":"locality"
},
  "geometry": {"coordinates":[105.2878,10.47778],"type":"Point"}
}