{
  "type": "Feature",
  "properties": {
    "gn:admin1_code":"89.0",
    "gn:asciiname":"Hin Lap",
    "gn:country_code":"VN",
    "gn:dem":777,
    "gn:feature_class":"P",
    "gn:feature_code":"PPL",
    "gn:name":"Hin Lap",
    "gn:population":0,
    "gn:timezone":"Asia/Ho_Chi_Minh",
    "iso:country":"VN",
    "name:und_x_variant":[
        "Hin Lao",
        "Hin Lap"
    ],
    "wof:name":"Hin Lap",
    "wof:placetype":"locality"
},
  "geometry": {"coordinates":[103.86667,21.95],"type":"Point"}
}