{
  "type": "Feature",
  "properties": {
    "gn:admin1_code":"5.0",
    "gn:asciiname":"Na Loat",
    "gn:country_code":"VN",
    "gn:dem":143,
    "gn:feature_class":"P",
    "gn:feature_code":"PPL",
    "gn:name":"N\u00e0 Lo\u1ea1t",
    "gn:population":0,
    "gn:timezone":"Asia/Ho_Chi_Minh",
    "iso:country":"VN",
    "name:vie_x_preferred":[
        "N\u00e0 Lo\u1ea1t"
    ],
    "wof:name":"Na Loat",
    "wof:placetype":"locality"
},
  "geometry": {"coordinates":[105.43425000000001,22.80684],"type":"Point"}
}