{
  "type": "Feature",
  "properties": {
    "gn:admin1_code":"23.0",
    "gn:asciiname":"Bu Gor",
    "gn:cc2":"VN",
    "gn:country_code":"VN",
    "gn:dem":137,
    "gn:feature_class":"P",
    "gn:feature_code":"PPL",
    "gn:name":"Bu Gor",
    "gn:population":0,
    "gn:timezone":"Asia/Ho_Chi_Minh",
    "iso:country":"VN",
    "name:und_x_variant":[
        "Ban Gor",
        "Bu Gor"
    ],
    "wof:name":"Bu Gor",
    "wof:placetype":"locality"
},
  "geometry": {"coordinates":[107.36667,11.58333],"type":"Point"}
}