{
  "type": "Feature",
  "properties": {
    "gn:admin1_code":"74.0",
    "gn:asciiname":"Trac But",
    "gn:country_code":"VN",
    "gn:dem":9,
    "gn:feature_class":"P",
    "gn:feature_code":"PPL",
    "gn:name":"Tr\u00e1c B\u00fat",
    "gn:population":0,
    "gn:timezone":"Asia/Ho_Chi_Minh",
    "iso:country":"VN",
    "name:vie_x_preferred":[
        "Tr\u00e1c B\u00fat"
    ],
    "wof:name":"Trac But",
    "wof:placetype":"locality"
},
  "geometry": {"coordinates":[105.9486,21.20954],"type":"Point"}
}