{
  "type": "Feature",
  "properties": {
    "gn:admin1_code":"76.0",
    "gn:asciiname":"Tap Doan Ba",
    "gn:country_code":"VN",
    "gn:dem":324,
    "gn:feature_class":"P",
    "gn:feature_code":"PPL",
    "gn:name":"T\u1eadp \u0110o\u00e0n Ba",
    "gn:population":0,
    "gn:timezone":"Asia/Ho_Chi_Minh",
    "iso:country":"VN",
    "name:vie_x_preferred":[
        "T\u1eadp \u0110o\u00e0n Ba"
    ],
    "name:vie_x_variant":[
        "T\u1eadp \u0110o\u00e0n 3"
    ],
    "wof:name":"Tap Doan Ba",
    "wof:placetype":"locality"
},
  "geometry": {"coordinates":[107.17545,11.63715],"type":"Point"}
}