{
  "type": "Feature",
  "properties": {
    "gn:admin1_code":"52.0",
    "gn:asciiname":"Hong Nguyet",
    "gn:country_code":"VN",
    "gn:dem":7,
    "gn:feature_class":"P",
    "gn:feature_code":"PPL",
    "gn:name":"H\u1ed3ng Nguy\u1ec7t",
    "gn:population":0,
    "gn:timezone":"Asia/Ho_Chi_Minh",
    "iso:country":"VN",
    "name:vie_x_preferred":[
        "H\u1ed3ng Nguy\u1ec7t"
    ],
    "wof:name":"Hong Nguyet",
    "wof:placetype":"locality"
},
  "geometry": {"coordinates":[105.69484,18.4954],"type":"Point"}
}