{
  "type": "Feature",
  "properties": {
    "gn:admin1_code":"91.0",
    "gn:asciiname":"Thon Bay",
    "gn:country_code":"VN",
    "gn:dem":515,
    "gn:feature_class":"P",
    "gn:feature_code":"PPL",
    "gn:name":"Th\u00f4n B\u1ea3y",
    "gn:population":0,
    "gn:timezone":"Asia/Ho_Chi_Minh",
    "iso:country":"VN",
    "name:vie_x_preferred":[
        "Th\u00f4n B\u1ea3y"
    ],
    "name:vie_x_variant":[
        "Th\u00f4n 7"
    ],
    "wof:name":"Thon Bay",
    "wof:placetype":"locality"
},
  "geometry": {"coordinates":[107.75792,12.5199],"type":"Point"}
}