{
  "type": "Feature",
  "properties": {
    "gn:admin1_code":"32.0",
    "gn:asciiname":"Ban Men",
    "gn:country_code":"VN",
    "gn:dem":846,
    "gn:feature_class":"P",
    "gn:feature_code":"PPL",
    "gn:name":"B\u1ea3n Men",
    "gn:population":0,
    "gn:timezone":"Asia/Ho_Chi_Minh",
    "iso:country":"VN",
    "name:vie_x_preferred":[
        "B\u1ea3n Men"
    ],
    "wof:name":"Ban Men",
    "wof:placetype":"locality"
},
  "geometry": {"coordinates":[103.91024,21.20487],"type":"Point"}
}