{
  "type": "Feature",
  "properties": {
    "gn:admin1_code":"32.0",
    "gn:asciiname":"Tat Ban",
    "gn:country_code":"VN",
    "gn:dem":779,
    "gn:feature_class":"P",
    "gn:feature_code":"PPL",
    "gn:name":"T\u00e1t Ban",
    "gn:population":0,
    "gn:timezone":"Asia/Ho_Chi_Minh",
    "iso:country":"VN",
    "name:vie_x_preferred":[
        "T\u00e1t Ban"
    ],
    "wof:name":"Tat Ban",
    "wof:placetype":"locality"
},
  "geometry": {"coordinates":[103.98452,21.21326],"type":"Point"}
}