{
  "type": "Feature",
  "properties": {
    "gn:admin1_code":"72.0",
    "gn:asciiname":"Ban Cau",
    "gn:country_code":"VN",
    "gn:dem":484,
    "gn:feature_class":"P",
    "gn:feature_code":"PPL",
    "gn:name":"B\u1ea3n C\u1ea5u",
    "gn:population":0,
    "gn:timezone":"Asia/Ho_Chi_Minh",
    "iso:country":"VN",
    "wof:name":"Ban Cau",
    "wof:placetype":"locality"
},
  "geometry": {"coordinates":[105.95421,22.30657],"type":"Point"}
}