{
  "type": "Feature",
  "properties": {
    "gn:admin1_code":"92.0",
    "gn:asciiname":"La Puc Hai",
    "gn:country_code":"VN",
    "gn:dem":495,
    "gn:feature_class":"P",
    "gn:feature_code":"PPL",
    "gn:name":"L\u00e0 P\u00fac Hai",
    "gn:population":0,
    "gn:timezone":"Asia/Ho_Chi_Minh",
    "iso:country":"VN",
    "name:vie_x_preferred":[
        "L\u00e0 P\u00fac Hai"
    ],
    "name:vie_x_variant":[
        "L\u00e0 P\u00fac 2"
    ],
    "wof:name":"La Puc Hai",
    "wof:placetype":"locality"
},
  "geometry": {"coordinates":[103.31367,21.24021],"type":"Point"}
}