{
  "type": "Feature",
  "properties": {
    "gn:admin1_code":"70.0",
    "gn:asciiname":"Pa Chiu Phing",
    "gn:country_code":"VN",
    "gn:dem":1285,
    "gn:feature_class":"P",
    "gn:feature_code":"PPL",
    "gn:name":"Pa Chiu Phing",
    "gn:population":0,
    "gn:timezone":"Asia/Ho_Chi_Minh",
    "iso:country":"VN",
    "wof:name":"Pa Chiu Phing",
    "wof:placetype":"locality"
},
  "geometry": {"coordinates":[104.11667,21.81667],"type":"Point"}
}