{
  "type": "Feature",
  "properties": {
    "gn:admin1_code":"88.0",
    "gn:asciiname":"Bu Ur",
    "gn:country_code":"VN",
    "gn:dem":646,
    "gn:feature_class":"P",
    "gn:feature_code":"PPL",
    "gn:name":"Bu Ur",
    "gn:population":0,
    "gn:timezone":"Asia/Ho_Chi_Minh",
    "iso:country":"VN",
    "name:vie_x_preferred":[
        "Bu Ur"
    ],
    "wof:name":"Bu Ur",
    "wof:placetype":"locality"
},
  "geometry": {"coordinates":[108.35473,12.93193],"type":"Point"}
}