{
  "type": "Feature",
  "properties": {
    "gn:admin1_code":"75.0",
    "gn:asciiname":"Ap Nam",
    "gn:country_code":"VN",
    "gn:dem":8,
    "gn:feature_class":"P",
    "gn:feature_code":"PPL",
    "gn:name":"\u1ea4p N\u0103m",
    "gn:population":0,
    "gn:timezone":"Asia/Ho_Chi_Minh",
    "iso:country":"VN",
    "name:vie_x_preferred":[
        "\u1ea4p N\u0103m"
    ],
    "name:vie_x_variant":[
        "\u1ea4p 5"
    ],
    "wof:name":"Ap Nam",
    "wof:placetype":"locality"
},
  "geometry": {"coordinates":[106.60307,11.08345],"type":"Point"}
}