{
  "type": "Feature",
  "properties": {
    "gn:admin1_code":"59.0",
    "gn:asciiname":"Ao Luon",
    "gn:country_code":"VN",
    "gn:dem":135,
    "gn:feature_class":"P",
    "gn:feature_code":"PPL",
    "gn:name":"Ao L\u01b0\u01a1n",
    "gn:population":0,
    "gn:timezone":"Asia/Ho_Chi_Minh",
    "iso:country":"VN",
    "name:vie_x_preferred":[
        "Ao L\u01b0\u01a1n"
    ],
    "wof:name":"Ao Luon",
    "wof:placetype":"locality"
},
  "geometry": {"coordinates":[105.71229,20.22044],"type":"Point"}
}