{
  "type": "Feature",
  "properties": {
    "gn:admin1_code":"21.0",
    "gn:asciiname":"Xom Co Kheu",
    "gn:cc2":"VN",
    "gn:country_code":"VN",
    "gn:dem":3,
    "gn:feature_class":"P",
    "gn:feature_code":"PPL",
    "gn:name":"X\u00f3m C\u1ecf Kh\u00eau",
    "gn:population":0,
    "gn:timezone":"Asia/Ho_Chi_Minh",
    "iso:country":"VN",
    "name:und_x_variant":[
        "Co Kheu",
        "X\u00f3m C\u1ecf Kh\u00eau"
    ],
    "wof:name":"Xom Co Kheu",
    "wof:placetype":"locality"
},
  "geometry": {"coordinates":[105.23333,9.98333],"type":"Point"}
}