{
  "type": "Feature",
  "properties": {
    "gn:admin1_code":"68.0",
    "gn:asciiname":"Khuoi Khuong",
    "gn:country_code":"VN",
    "gn:dem":224,
    "gn:feature_class":"P",
    "gn:feature_code":"PPL",
    "gn:name":"Khu\u1ed5i Kh\u01b0\u01a1ng",
    "gn:population":0,
    "gn:timezone":"Asia/Ho_Chi_Minh",
    "iso:country":"VN",
    "name:vie_x_preferred":[
        "Khu\u1ed5i Kh\u01b0\u01a1ng"
    ],
    "wof:name":"Khuoi Khuong",
    "wof:placetype":"locality"
},
  "geometry": {"coordinates":[105.25279,22.53757],"type":"Point"}
}