{
  "type": "Feature",
  "properties": {
    "gn:admin1_code":"39.0",
    "gn:asciiname":"Po Mane",
    "gn:country_code":"VN",
    "gn:dem":272,
    "gn:feature_class":"P",
    "gn:feature_code":"PPL",
    "gn:name":"Po Mane",
    "gn:population":0,
    "gn:timezone":"Asia/Ho_Chi_Minh",
    "iso:country":"VN",
    "wof:name":"Po Mane",
    "wof:placetype":"locality"
},
  "geometry": {"coordinates":[106.28333000000001,22.08333],"type":"Point"}
}