{
  "type": "Feature",
  "properties": {
    "gn:admin1_code":"92.0",
    "gn:asciiname":"Quang Han",
    "gn:country_code":"VN",
    "gn:dem":667,
    "gn:feature_class":"P",
    "gn:feature_code":"PPL",
    "gn:name":"Quang Han",
    "gn:population":0,
    "gn:timezone":"Asia/Ho_Chi_Minh",
    "iso:country":"VN",
    "wof:name":"Quang Han",
    "wof:placetype":"locality"
},
  "geometry": {"coordinates":[102.76667,22.01667],"type":"Point"}
}