{
  "type": "Feature",
  "properties": {
    "gn:admin1_code":"70.0",
    "gn:asciiname":"Dong Buoi",
    "gn:country_code":"VN",
    "gn:dem":41,
    "gn:feature_class":"P",
    "gn:feature_code":"PPL",
    "gn:name":"\u0110\u00f4ng B\u01b0\u1edfi",
    "gn:population":0,
    "gn:timezone":"Asia/Ho_Chi_Minh",
    "iso:country":"VN",
    "name:vie_x_preferred":[
        "\u0110\u00f4ng B\u01b0\u1edfi"
    ],
    "wof:name":"Dong Buoi",
    "wof:placetype":"locality"
},
  "geometry": {"coordinates":[104.77489,21.82433],"type":"Point"}
}