{
  "type": "Feature",
  "properties": {
    "gn:admin1_code":"66.0",
    "gn:asciiname":"Mang Ca",
    "gn:country_code":"VN",
    "gn:dem":346,
    "gn:feature_class":"P",
    "gn:feature_code":"PPL",
    "gn:name":"Mang C\u00e0",
    "gn:population":0,
    "gn:timezone":"Asia/Ho_Chi_Minh",
    "iso:country":"VN",
    "wof:name":"Mang Ca",
    "wof:placetype":"locality"
},
  "geometry": {"coordinates":[107.53333000000001,16.23333],"type":"Point"}
}