{
  "type": "Feature",
  "properties": {
    "gn:admin1_code":"87.0",
    "gn:asciiname":"Dinh Yen",
    "gn:country_code":"VN",
    "gn:dem":7,
    "gn:feature_class":"P",
    "gn:feature_code":"PPL",
    "gn:name":"\u0110\u1ecbnh Y\u00ean",
    "gn:population":0,
    "gn:timezone":"Asia/Ho_Chi_Minh",
    "iso:country":"VN",
    "name:vie_x_preferred":[
        "\u0110\u1ecbnh Y\u00ean"
    ],
    "wof:name":"Dinh Yen",
    "wof:placetype":"locality"
},
  "geometry": {"coordinates":[105.61224,10.05407],"type":"Point"}
}