{
  "type": "Feature",
  "properties": {
    "gn:admin1_code":"17.0",
    "gn:asciiname":"Ban Man",
    "gn:country_code":"VN",
    "gn:dem":148,
    "gn:feature_class":"P",
    "gn:feature_code":"PPL",
    "gn:name":"B\u00e1n Man",
    "gn:population":0,
    "gn:timezone":"Asia/Ho_Chi_Minh",
    "iso:country":"VN",
    "name:und_x_variant":[
        "B\u00e1n Man",
        "B\u1ea3n Man"
    ],
    "wof:name":"Ban Man",
    "wof:placetype":"locality"
},
  "geometry": {"coordinates":[105.43934,22.18896],"type":"Point"}
}