{
  "type": "Feature",
  "properties": {
    "gn:admin1_code":"58.0",
    "gn:asciiname":"Ban Quang",
    "gn:country_code":"VN",
    "gn:dem":242,
    "gn:feature_class":"P",
    "gn:feature_code":"PPL",
    "gn:name":"B\u1ea3n Qu\u1ea3ng",
    "gn:population":0,
    "gn:timezone":"Asia/Ho_Chi_Minh",
    "iso:country":"VN",
    "name:vie_x_preferred":[
        "B\u1ea3n Qu\u1ea3ng"
    ],
    "wof:name":"Ban Quang",
    "wof:placetype":"locality"
},
  "geometry": {"coordinates":[105.01738,19.23926],"type":"Point"}
}