{
  "type": "Feature",
  "properties": {
    "gn:admin1_code":"54.0",
    "gn:asciiname":"Ap Lac Ninh",
    "gn:country_code":"VN",
    "gn:dem":15,
    "gn:feature_class":"P",
    "gn:feature_code":"PPL",
    "gn:name":"\u1ea4p L\u1ea1c Ninh",
    "gn:population":0,
    "gn:timezone":"Asia/Ho_Chi_Minh",
    "iso:country":"VN",
    "name:und_x_variant":[
        "L\u1ea1c Ninh",
        "Hoa Huynh",
        "\u1ea4p L\u1ea1c Ninh"
    ],
    "wof:name":"Ap Lac Ninh",
    "wof:placetype":"locality"
},
  "geometry": {"coordinates":[109.16667,12.56667],"type":"Point"}
}