{
  "type": "Feature",
  "properties": {
    "gn:admin1_code":"72.0",
    "gn:asciiname":"Kouan Lan",
    "gn:country_code":"VN",
    "gn:dem":501,
    "gn:feature_class":"P",
    "gn:feature_code":"PPL",
    "gn:name":"Kouan Lan",
    "gn:population":0,
    "gn:timezone":"Asia/Ho_Chi_Minh",
    "iso:country":"VN",
    "name:und_x_variant":[
        "Kouau Lan",
        "Kouan Lan"
    ],
    "wof:name":"Kouan Lan",
    "wof:placetype":"locality"
},
  "geometry": {"coordinates":[106.05,22.46667],"type":"Point"}
}