{
  "type": "Feature",
  "properties": {
    "gn:admin1_code":"90.0",
    "gn:asciiname":"Suoi Thau Mot",
    "gn:country_code":"VN",
    "gn:dem":1164,
    "gn:feature_class":"P",
    "gn:feature_code":"PPL",
    "gn:name":"Su\u1ed1i Th\u1ea7u M\u1ed9t",
    "gn:population":0,
    "gn:timezone":"Asia/Ho_Chi_Minh",
    "iso:country":"VN",
    "name:vie_x_preferred":[
        "Su\u1ed1i Th\u1ea7u M\u1ed9t"
    ],
    "name:vie_x_variant":[
        "Su\u1ed1i Th\u1ea7u 1"
    ],
    "wof:name":"Suoi Thau Mot",
    "wof:placetype":"locality"
},
  "geometry": {"coordinates":[103.80905,22.44502],"type":"Point"}
}