{
  "type": "Feature",
  "properties": {
    "gn:admin1_code":"89.0",
    "gn:asciiname":"Binh Lu",
    "gn:country_code":"VN",
    "gn:dem":639,
    "gn:feature_class":"P",
    "gn:feature_code":"PPL",
    "gn:name":"B\u00ecnh L\u01b0",
    "gn:population":0,
    "gn:timezone":"Asia/Ho_Chi_Minh",
    "iso:country":"VN",
    "wof:name":"Binh Lu",
    "wof:placetype":"locality"
},
  "geometry": {"coordinates":[103.61667,22.31667],"type":"Point"}
}