{
  "type": "Feature",
  "properties": {
    "gn:admin1_code":"79.0",
    "gn:asciiname":"An Cuong",
    "gn:country_code":"VN",
    "gn:dem":6,
    "gn:feature_class":"P",
    "gn:feature_code":"PPL",
    "gn:name":"An C\u01b0\u1eddng",
    "gn:population":0,
    "gn:timezone":"Asia/Ho_Chi_Minh",
    "iso:country":"VN",
    "name:und_x_variant":[
        "Y\u00ean C\u01b0\u01a1ng"
    ],
    "name:vie_x_preferred":[
        "An C\u01b0\u1eddng"
    ],
    "wof:name":"An Cuong",
    "wof:placetype":"locality"
},
  "geometry": {"coordinates":[106.5355,21.00324],"type":"Point"}
}