{
  "type": "Feature",
  "properties": {
    "gn:admin1_code":"50.0",
    "gn:asciiname":"Ban Day",
    "gn:country_code":"VN",
    "gn:dem":123,
    "gn:feature_class":"P",
    "gn:feature_code":"PPL",
    "gn:name":"B\u1ea3n \u0110\u00e1y",
    "gn:population":0,
    "gn:timezone":"Asia/Ho_Chi_Minh",
    "iso:country":"VN",
    "name:vie_x_preferred":[
        "B\u1ea3n \u0110\u00e1y"
    ],
    "wof:name":"Ban Day",
    "wof:placetype":"locality"
},
  "geometry": {"coordinates":[105.29472,22.73744],"type":"Point"}
}