{
  "type": "Feature",
  "properties": {
    "gn:admin1_code":"71.0",
    "gn:asciiname":"Kim Vien",
    "gn:country_code":"VN",
    "gn:dem":11,
    "gn:feature_class":"P",
    "gn:feature_code":"PPL",
    "gn:name":"Kim Vi\u00ean",
    "gn:population":0,
    "gn:timezone":"Asia/Ho_Chi_Minh",
    "iso:country":"VN",
    "name:vie_x_preferred":[
        "Kim Vi\u00ean"
    ],
    "wof:name":"Kim Vien",
    "wof:placetype":"locality"
},
  "geometry": {"coordinates":[106.02637,21.26354],"type":"Point"}
}