{
  "type": "Feature",
  "properties": {
    "gn:admin1_code":"39.0",
    "gn:asciiname":"Bac Son",
    "gn:country_code":"VN",
    "gn:dem":396,
    "gn:feature_class":"P",
    "gn:feature_code":"PPLA2",
    "gn:name":"B\u1eafc S\u01a1n",
    "gn:population":0,
    "gn:timezone":"Asia/Ho_Chi_Minh",
    "iso:country":"VN",
    "name:und_x_variant":[
        "B\u1eafc S\u01a1n"
    ],
    "wof:name":"Bac Son",
    "wof:placetype":"locality"
},
  "geometry": {"coordinates":[106.32077,21.89999],"type":"Point"}
}