{
  "type": "Feature",
  "properties": {
    "gn:admin1_code":"54.0",
    "gn:asciiname":"Thon Vinh Diem Trung",
    "gn:country_code":"VN",
    "gn:dem":3,
    "gn:feature_class":"P",
    "gn:feature_code":"PPL",
    "gn:name":"Th\u00f4n V\u0129nh \u0110i\u1ec1m Trung",
    "gn:population":0,
    "gn:timezone":"Asia/Ho_Chi_Minh",
    "iso:country":"VN",
    "wof:name":"Thon Vinh Diem Trung",
    "wof:placetype":"locality"
},
  "geometry": {"coordinates":[109.16667,12.25],"type":"Point"}
}