{
  "type": "Feature",
  "properties": {
    "gn:admin1_code":"76.0",
    "gn:asciiname":"Srok Trao",
    "gn:country_code":"VN",
    "gn:dem":178,
    "gn:feature_class":"P",
    "gn:feature_code":"PPL",
    "gn:name":"Srok Tr\u00e0o",
    "gn:population":0,
    "gn:timezone":"Asia/Ho_Chi_Minh",
    "iso:country":"VN",
    "wof:name":"Srok Trao",
    "wof:placetype":"locality"
},
  "geometry": {"coordinates":[106.65000000000001,11.86667],"type":"Point"}
}