{
  "type": "Feature",
  "properties": {
    "gn:admin1_code":"35.0",
    "gn:asciiname":"Quynh Coi",
    "gn:country_code":"VN",
    "gn:dem":6,
    "gn:feature_class":"P",
    "gn:feature_code":"PPLA2",
    "gn:name":"Qu\u1ef3nh C\u00f4i",
    "gn:population":0,
    "gn:timezone":"Asia/Ho_Chi_Minh",
    "iso:country":"VN",
    "name:und_x_variant":[
        "Qu\u1ef3nh C\u00f4i"
    ],
    "wof:name":"Quynh Coi",
    "wof:placetype":"locality"
},
  "geometry": {"coordinates":[106.32744,20.66192],"type":"Point"}
}