{
  "type": "Feature",
  "properties": {
    "gn:admin1_code":"58.0",
    "gn:asciiname":"Con Moi",
    "gn:country_code":"VN",
    "gn:dem":52,
    "gn:feature_class":"P",
    "gn:feature_code":"PPL",
    "gn:name":"C\u1ed3n M\u1ed1i",
    "gn:population":0,
    "gn:timezone":"Asia/Ho_Chi_Minh",
    "iso:country":"VN",
    "wof:name":"Con Moi",
    "wof:placetype":"locality"
},
  "geometry": {"coordinates":[105.34999999999999,19.16667],"type":"Point"}
}