{
  "type": "Feature",
  "properties": {
    "gn:admin1_code":"83.0",
    "gn:asciiname":"Xom Doc",
    "gn:country_code":"VN",
    "gn:dem":124,
    "gn:feature_class":"P",
    "gn:feature_code":"PPL",
    "gn:name":"X\u00f3m D\u1ed9c",
    "gn:population":0,
    "gn:timezone":"Asia/Ho_Chi_Minh",
    "iso:country":"VN",
    "name:vie_x_preferred":[
        "X\u00f3m D\u1ed9c"
    ],
    "wof:name":"Xom Doc",
    "wof:placetype":"locality"
},
  "geometry": {"coordinates":[104.93066,21.21978],"type":"Point"}
}