{
  "type": "Feature",
  "properties": {
    "gn:admin1_code":"47.0",
    "gn:asciiname":"Ap Long Hiep",
    "gn:country_code":"VN",
    "gn:dem":26,
    "gn:feature_class":"P",
    "gn:feature_code":"PPL",
    "gn:name":"\u1ea4p Long Hi\u1ec7p",
    "gn:population":0,
    "gn:timezone":"Asia/Ho_Chi_Minh",
    "iso:country":"VN",
    "name:und_x_variant":[
        "Xom Giua",
        "\u1ea4p Long Hi\u1ec7p"
    ],
    "wof:name":"Ap Long Hiep",
    "wof:placetype":"locality"
},
  "geometry": {"coordinates":[108.18333,11.06667],"type":"Point"}
}