{
  "type": "Feature",
  "properties": {
    "gn:admin1_code":"92.0",
    "gn:asciiname":"Ban Chong Ban",
    "gn:country_code":"VN",
    "gn:dem":596,
    "gn:feature_class":"P",
    "gn:feature_code":"PPL",
    "gn:name":"B\u1ea3n Chong Ban",
    "gn:population":0,
    "gn:timezone":"Asia/Ho_Chi_Minh",
    "iso:country":"VN",
    "wof:name":"Ban Chong Ban",
    "wof:placetype":"locality"
},
  "geometry": {"coordinates":[103.38333,21.73333],"type":"Point"}
}