{
  "type": "Feature",
  "properties": {
    "gn:admin1_code":"52.0",
    "gn:asciiname":"Xom Trai",
    "gn:country_code":"VN",
    "gn:dem":7,
    "gn:feature_class":"P",
    "gn:feature_code":"PPL",
    "gn:name":"X\u00f3m Trai",
    "gn:population":0,
    "gn:timezone":"Asia/Ho_Chi_Minh",
    "iso:country":"VN",
    "name:und_x_variant":[
        "Xom Tra",
        "Xam Trai",
        "X\u00f3m Trai"
    ],
    "wof:name":"Xom Trai",
    "wof:placetype":"locality"
},
  "geometry": {"coordinates":[105.96666999999999,18.38333],"type":"Point"}
}