{
  "type": "Feature",
  "properties": {
    "gn:admin1_code":"39.0",
    "gn:asciiname":"Sao Thong",
    "gn:country_code":"VN",
    "gn:dem":343,
    "gn:feature_class":"P",
    "gn:feature_code":"PPL",
    "gn:name":"Sao Th\u00f4ng",
    "gn:population":0,
    "gn:timezone":"Asia/Ho_Chi_Minh",
    "iso:country":"VN",
    "wof:name":"Sao Thong",
    "wof:placetype":"locality"
},
  "geometry": {"coordinates":[106.48333,21.88333],"type":"Point"}
}