{
  "type": "Feature",
  "properties": {
    "gn:admin1_code":"73.0",
    "gn:asciiname":"Nha May Gao",
    "gn:country_code":"VN",
    "gn:dem":1,
    "gn:feature_class":"P",
    "gn:feature_code":"PPL",
    "gn:name":"Nh\u00e0 M\u00e1y Gao",
    "gn:population":0,
    "gn:timezone":"Asia/Ho_Chi_Minh",
    "iso:country":"VN",
    "wof:name":"Nha May Gao",
    "wof:placetype":"locality"
},
  "geometry": {"coordinates":[105.64278,9.34583],"type":"Point"}
}