{
  "type": "Feature",
  "properties": {
    "gn:admin1_code":"58.0",
    "gn:asciiname":"Ban Sop Kun",
    "gn:country_code":"VN",
    "gn:dem":448,
    "gn:feature_class":"P",
    "gn:feature_code":"PPL",
    "gn:name":"B\u1ea3n Sop Kun",
    "gn:population":0,
    "gn:timezone":"Asia/Ho_Chi_Minh",
    "iso:country":"VN",
    "wof:name":"Ban Sop Kun",
    "wof:placetype":"locality"
},
  "geometry": {"coordinates":[104.98333,19.86667000000001],"type":"Point"}
}