{
  "type": "Feature",
  "properties": {
    "gn:admin1_code":"33.0",
    "gn:asciiname":"Xom Ho Don",
    "gn:cc2":"VN",
    "gn:country_code":"VN",
    "gn:dem":10,
    "gn:feature_class":"P",
    "gn:feature_code":"PPL",
    "gn:name":"X\u00f3m Ho D\u1ed3n",
    "gn:population":0,
    "gn:timezone":"Asia/Ho_Chi_Minh",
    "iso:country":"VN",
    "name:und_x_variant":[
        "Ho Don",
        "X\u00f3m Ho D\u1ed3n"
    ],
    "wof:name":"Xom Ho Don",
    "wof:placetype":"locality"
},
  "geometry": {"coordinates":[106.11667,11.21667],"type":"Point"}
}