{
  "type": "Feature",
  "properties": {
    "gn:admin1_code":"34.0",
    "gn:asciiname":"Sop Sim",
    "gn:country_code":"VN",
    "gn:dem":272,
    "gn:feature_class":"P",
    "gn:feature_code":"PPL",
    "gn:name":"S\u1ed1p Sim",
    "gn:population":0,
    "gn:timezone":"Asia/Ho_Chi_Minh",
    "iso:country":"VN",
    "name:und_x_variant":[
        "Xom Sop Xiem",
        "Sop Sim"
    ],
    "name:vie_x_preferred":[
        "S\u1ed1p Sim"
    ],
    "wof:name":"Sop Sim",
    "wof:placetype":"locality"
},
  "geometry": {"coordinates":[104.5059,20.51562],"type":"Point"}
}