{
  "type": "Feature",
  "properties": {
    "gn:admin1_code":"83.0",
    "gn:asciiname":"Bep Gao",
    "gn:country_code":"VN",
    "gn:dem":66,
    "gn:feature_class":"P",
    "gn:feature_code":"PPL",
    "gn:name":"B\u1ebfp Gao",
    "gn:population":0,
    "gn:timezone":"Asia/Ho_Chi_Minh",
    "iso:country":"VN",
    "name:vie_x_preferred":[
        "B\u1ebfp Gao"
    ],
    "wof:name":"Bep Gao",
    "wof:placetype":"locality"
},
  "geometry": {"coordinates":[105.0941,21.16376],"type":"Point"}
}