{
  "type": "Feature",
  "properties": {
    "gn:admin1_code":"69.0",
    "gn:asciiname":"Rach Muc",
    "gn:country_code":"VN",
    "gn:dem":3,
    "gn:feature_class":"P",
    "gn:feature_code":"PPL",
    "gn:name":"R\u1ea1ch M\u00fac",
    "gn:population":0,
    "gn:timezone":"Asia/Ho_Chi_Minh",
    "iso:country":"VN",
    "name:vie_x_preferred":[
        "R\u1ea1ch M\u00fac"
    ],
    "wof:name":"Rach Muc",
    "wof:placetype":"locality"
},
  "geometry": {"coordinates":[105.83886,10.08101],"type":"Point"}
}