{
  "type": "Feature",
  "properties": {
    "gn:admin1_code":"32.0",
    "gn:asciiname":"Phieng Pen",
    "gn:country_code":"VN",
    "gn:dem":763,
    "gn:feature_class":"P",
    "gn:feature_code":"PPL",
    "gn:name":"Phi\u1ec1ng Pen",
    "gn:population":0,
    "gn:timezone":"Asia/Ho_Chi_Minh",
    "iso:country":"VN",
    "name:vie_x_preferred":[
        "Phi\u1ec1ng Pen"
    ],
    "wof:name":"Phieng Pen",
    "wof:placetype":"locality"
},
  "geometry": {"coordinates":[103.71729000000001,20.81489],"type":"Point"}
}