{
  "type": "Feature",
  "properties": {
    "gn:admin1_code":"88.0",
    "gn:asciiname":"Khoi Muoi Mot",
    "gn:country_code":"VN",
    "gn:dem":426,
    "gn:feature_class":"P",
    "gn:feature_code":"PPL",
    "gn:name":"Kh\u1ed1i M\u01b0\u1eddi M\u1ed9t",
    "gn:population":0,
    "gn:timezone":"Asia/Ho_Chi_Minh",
    "iso:country":"VN",
    "name:vie_x_preferred":[
        "Kh\u1ed1i M\u01b0\u1eddi M\u1ed9t"
    ],
    "name:vie_x_variant":[
        "Kh\u1ed1i 11"
    ],
    "wof:name":"Khoi Muoi Mot",
    "wof:placetype":"locality"
},
  "geometry": {"coordinates":[108.52657000000001,12.81347],"type":"Point"}
}