{
  "type": "Feature",
  "properties": {
    "gn:admin1_code":"84.0",
    "gn:asciiname":"Thanh Xuyen",
    "gn:country_code":"VN",
    "gn:dem":24,
    "gn:feature_class":"P",
    "gn:feature_code":"PPL",
    "gn:name":"Thanh Xuy\u00ean",
    "gn:population":0,
    "gn:timezone":"Asia/Ho_Chi_Minh",
    "iso:country":"VN",
    "name:und_x_variant":[
        "Thinh My",
        "Thanh Xuy\u00ean"
    ],
    "wof:name":"Thanh Xuyen",
    "wof:placetype":"locality"
},
  "geometry": {"coordinates":[108.06667,15.78333],"type":"Point"}
}