{
  "type": "Feature",
  "properties": {
    "gn:admin1_code":"70.0",
    "gn:asciiname":"Ngoi Quan",
    "gn:country_code":"VN",
    "gn:dem":62,
    "gn:feature_class":"P",
    "gn:feature_code":"PPL",
    "gn:name":"Ng\u00f2i Quan",
    "gn:population":0,
    "gn:timezone":"Asia/Ho_Chi_Minh",
    "iso:country":"VN",
    "wof:name":"Ngoi Quan",
    "wof:placetype":"locality"
},
  "geometry": {"coordinates":[104.96666999999999,21.88333],"type":"Point"}
}