{
  "type": "Feature",
  "properties": {
    "gn:admin1_code":"68.0",
    "gn:asciiname":"Ban Bo",
    "gn:country_code":"VN",
    "gn:dem":246,
    "gn:feature_class":"P",
    "gn:feature_code":"PPL",
    "gn:name":"B\u00e1n B\u00f3",
    "gn:population":0,
    "gn:timezone":"Asia/Ho_Chi_Minh",
    "iso:country":"VN",
    "name:und_x_variant":[
        "B\u00e1n B\u00f3",
        "B\u1ea3n Bo"
    ],
    "wof:name":"Ban Bo",
    "wof:placetype":"locality"
},
  "geometry": {"coordinates":[105.29868,22.45527],"type":"Point"}
}