{
  "type": "Feature",
  "properties": {
    "gn:admin1_code":"80.0",
    "gn:asciiname":"Nhan Gia",
    "gn:country_code":"VN",
    "gn:dem":7,
    "gn:feature_class":"P",
    "gn:feature_code":"PPL",
    "gn:name":"Nh\u00e2n Gia",
    "gn:population":0,
    "gn:timezone":"Asia/Ho_Chi_Minh",
    "iso:country":"VN",
    "name:und_x_variant":[
        "Nh\u00e2n G\u1ec9a"
    ],
    "name:vie_x_preferred":[
        "Nh\u00e2n Gia"
    ],
    "wof:name":"Nhan Gia",
    "wof:placetype":"locality"
},
  "geometry": {"coordinates":[106.03494999999999,20.54537],"type":"Point"}
}