{
  "type": "Feature",
  "properties": {
    "gn:admin1_code":"52.0",
    "gn:asciiname":"Xom Bon",
    "gn:country_code":"VN",
    "gn:dem":14,
    "gn:feature_class":"P",
    "gn:feature_code":"PPL",
    "gn:name":"X\u00f3m B\u1ed1n",
    "gn:population":0,
    "gn:timezone":"Asia/Ho_Chi_Minh",
    "iso:country":"VN",
    "name:vie_x_preferred":[
        "X\u00f3m B\u1ed1n"
    ],
    "name:vie_x_variant":[
        "X\u00f3m 4"
    ],
    "wof:name":"Xom Bon",
    "wof:placetype":"locality"
},
  "geometry": {"coordinates":[105.78892,18.35128],"type":"Point"}
}