{
  "type": "Feature",
  "properties": {
    "gn:admin1_code":"68.0",
    "gn:asciiname":"Lung Phat",
    "gn:country_code":"VN",
    "gn:dem":197,
    "gn:feature_class":"P",
    "gn:feature_code":"PPL",
    "gn:name":"L\u00f9ng Ph\u1ea1t",
    "gn:population":0,
    "gn:timezone":"Asia/Ho_Chi_Minh",
    "iso:country":"VN",
    "name:vie_x_preferred":[
        "L\u00f9ng Ph\u1ea1t"
    ],
    "wof:name":"Lung Phat",
    "wof:placetype":"locality"
},
  "geometry": {"coordinates":[105.16094,22.38435],"type":"Point"}
}