{
  "type": "Feature",
  "properties": {
    "gn:admin1_code":"59.0",
    "gn:asciiname":"Phu Huu",
    "gn:country_code":"VN",
    "gn:dem":103,
    "gn:feature_class":"P",
    "gn:feature_code":"PPL",
    "gn:name":"Ph\u00fa H\u1eefu",
    "gn:population":0,
    "gn:timezone":"Asia/Ho_Chi_Minh",
    "iso:country":"VN",
    "name:vie_x_preferred":[
        "Ph\u00fa H\u1eefu"
    ],
    "wof:name":"Phu Huu",
    "wof:placetype":"locality"
},
  "geometry": {"coordinates":[105.81667,20.18333],"type":"Point"}
}