{
  "type": "Feature",
  "properties": {
    "gn:admin1_code":"49.0",
    "gn:asciiname":"Ma Lin Hai",
    "gn:country_code":"VN",
    "gn:dem":169,
    "gn:feature_class":"P",
    "gn:feature_code":"PPL",
    "gn:name":"Ma Lin Hai",
    "gn:population":0,
    "gn:timezone":"Asia/Ho_Chi_Minh",
    "iso:country":"VN",
    "name:vie_x_preferred":[
        "Ma Lin Hai"
    ],
    "name:vie_x_variant":[
        "Ma Lin 2"
    ],
    "wof:name":"Ma Lin Hai",
    "wof:placetype":"locality"
},
  "geometry": {"coordinates":[108.45439,13.48892],"type":"Point"}
}