{
  "type": "Feature",
  "properties": {
    "gn:admin1_code":"65.0",
    "gn:asciiname":"Bo Lien",
    "gn:country_code":"VN",
    "gn:dem":6,
    "gn:feature_class":"P",
    "gn:feature_code":"PPL",
    "gn:name":"B\u1ed1 Li\u00ean",
    "gn:population":0,
    "gn:timezone":"Asia/Ho_Chi_Minh",
    "iso:country":"VN",
    "name:vie_x_preferred":[
        "B\u1ed1 Li\u00ean"
    ],
    "wof:name":"Bo Lien",
    "wof:placetype":"locality"
},
  "geometry": {"coordinates":[105.85638,9.57045],"type":"Point"}
}