{
  "type": "Feature",
  "properties": {
    "gn:admin1_code":"32.0",
    "gn:asciiname":"Ban Non",
    "gn:cc2":"VN",
    "gn:country_code":"VN",
    "gn:dem":700,
    "gn:feature_class":"P",
    "gn:feature_code":"PPL",
    "gn:name":"B\u1ea3n Non",
    "gn:population":0,
    "gn:timezone":"Asia/Ho_Chi_Minh",
    "iso:country":"VN",
    "name:und_x_variant":[
        "Ban Bon",
        "B\u1ea3n Non"
    ],
    "wof:name":"Ban Non",
    "wof:placetype":"locality"
},
  "geometry": {"coordinates":[104.86667,20.98333],"type":"Point"}
}