{
  "type": "Feature",
  "properties": {
    "gn:admin1_code":"37.0",
    "gn:asciiname":"Ca Thu",
    "gn:country_code":"VN",
    "gn:dem":0,
    "gn:feature_class":"P",
    "gn:feature_code":"PPL",
    "gn:name":"C\u00e1 Thu",
    "gn:population":0,
    "gn:timezone":"Asia/Ho_Chi_Minh",
    "iso:country":"VN",
    "name:vie_x_preferred":[
        "C\u00e1 Thu"
    ],
    "wof:name":"Ca Thu",
    "wof:placetype":"locality"
},
  "geometry": {"coordinates":[106.67358,10.2583],"type":"Point"}
}