{
  "type": "Feature",
  "properties": {
    "gn:admin1_code":"32.0",
    "gn:asciiname":"Ban Cheo A",
    "gn:country_code":"VN",
    "gn:dem":764,
    "gn:feature_class":"P",
    "gn:feature_code":"PPL",
    "gn:name":"B\u1ea3n Ch\u00e8o A",
    "gn:population":0,
    "gn:timezone":"Asia/Ho_Chi_Minh",
    "iso:country":"VN",
    "name:vie_x_preferred":[
        "B\u1ea3n Ch\u00e8o A"
    ],
    "wof:name":"Ban Cheo A",
    "wof:placetype":"locality"
},
  "geometry": {"coordinates":[104.56937000000001,21.18483],"type":"Point"}
}