{
  "type": "Feature",
  "properties": {
    "gn:admin1_code":"60.0",
    "gn:asciiname":"Quan The Mot",
    "gn:country_code":"VN",
    "gn:dem":34,
    "gn:feature_class":"P",
    "gn:feature_code":"PPL",
    "gn:name":"Qu\u00e1n Th\u1ebb M\u1ed9t",
    "gn:population":0,
    "gn:timezone":"Asia/Ho_Chi_Minh",
    "iso:country":"VN",
    "name:vie_x_preferred":[
        "Qu\u00e1n Th\u1ebb M\u1ed9t"
    ],
    "name:vie_x_variant":[
        "Qu\u00e1n Th\u1ebb 1"
    ],
    "wof:name":"Quan The Mot",
    "wof:placetype":"locality"
},
  "geometry": {"coordinates":[108.89479,11.42765],"type":"Point"}
}