{
  "type": "Feature",
  "properties": {
    "gn:admin1_code":"82.0",
    "gn:asciiname":"Quang Cat",
    "gn:country_code":"VN",
    "gn:dem":4,
    "gn:feature_class":"P",
    "gn:feature_code":"PPL",
    "gn:name":"Quang C\u00e1t",
    "gn:population":0,
    "gn:timezone":"Asia/Ho_Chi_Minh",
    "iso:country":"VN",
    "name:vie_x_preferred":[
        "Quang C\u00e1t"
    ],
    "wof:name":"Quang Cat",
    "wof:placetype":"locality"
},
  "geometry": {"coordinates":[106.23779,20.20396],"type":"Point"}
}