{
  "type": "Feature",
  "properties": {
    "gn:admin1_code":"66.0",
    "gn:asciiname":"Ke Mon",
    "gn:country_code":"VN",
    "gn:dem":8,
    "gn:feature_class":"P",
    "gn:feature_code":"PPL",
    "gn:name":"K\u1ebf M\u00f4n",
    "gn:population":0,
    "gn:timezone":"Asia/Ho_Chi_Minh",
    "iso:country":"VN",
    "name:und_x_variant":[
        "Th\u00f4n K\u1ebf M\u00f4n"
    ],
    "name:vie_x_preferred":[
        "K\u1ebf M\u00f4n"
    ],
    "wof:name":"Ke Mon",
    "wof:placetype":"locality"
},
  "geometry": {"coordinates":[107.3982,16.69338],"type":"Point"}
}