{
  "type": "Feature",
  "properties": {
    "gn:admin1_code":"80.0",
    "gn:asciiname":"Ngoc Tan",
    "gn:country_code":"VN",
    "gn:dem":6,
    "gn:feature_class":"P",
    "gn:feature_code":"PPL",
    "gn:name":"Ng\u1ecdc T\u00e2n",
    "gn:population":0,
    "gn:timezone":"Asia/Ho_Chi_Minh",
    "iso:country":"VN",
    "name:vie_x_preferred":[
        "Ng\u1ecdc T\u00e2n"
    ],
    "wof:name":"Ngoc Tan",
    "wof:placetype":"locality"
},
  "geometry": {"coordinates":[106.08937,20.51828],"type":"Point"}
}