{
  "type": "Feature",
  "properties": {
    "gn:admin1_code":"87.0",
    "gn:asciiname":"Thanh Quoi Mot",
    "gn:country_code":"VN",
    "gn:dem":5,
    "gn:feature_class":"P",
    "gn:feature_code":"PPL",
    "gn:name":"Th\u1ea1nh Qu\u1edbi M\u1ed9t",
    "gn:population":0,
    "gn:timezone":"Asia/Ho_Chi_Minh",
    "iso:country":"VN",
    "name:vie_x_preferred":[
        "Th\u1ea1nh Qu\u1edbi M\u1ed9t"
    ],
    "name:vie_x_variant":[
        "Th\u1ea1nh Qu\u1edbi 1"
    ],
    "wof:name":"Thanh Quoi Mot",
    "wof:placetype":"locality"
},
  "geometry": {"coordinates":[105.47769,10.18203],"type":"Point"}
}