{
  "type": "Feature",
  "properties": {
    "gn:admin1_code":"84.0",
    "gn:asciiname":"Pa Lua",
    "gn:country_code":"VN",
    "gn:dem":369,
    "gn:feature_class":"P",
    "gn:feature_code":"PPL",
    "gn:name":"P\u00e0 L\u1eeba",
    "gn:population":0,
    "gn:timezone":"Asia/Ho_Chi_Minh",
    "iso:country":"VN",
    "name:vie_x_preferred":[
        "P\u00e0 L\u1eeba"
    ],
    "wof:name":"Pa Lua",
    "wof:placetype":"locality"
},
  "geometry": {"coordinates":[107.65554,15.6692],"type":"Point"}
}