{
  "type": "Feature",
  "properties": {
    "gn:admin1_code":"89.0",
    "gn:asciiname":"Ban Na Cai",
    "gn:country_code":"VN",
    "gn:dem":517,
    "gn:feature_class":"P",
    "gn:feature_code":"PPL",
    "gn:name":"B\u1ea3n N\u00e0 Cai",
    "gn:population":0,
    "gn:timezone":"Asia/Ho_Chi_Minh",
    "iso:country":"VN",
    "name:und_x_variant":[
        "Na Kai"
    ],
    "name:vie_x_preferred":[
        "B\u1ea3n N\u00e0 Cai"
    ],
    "wof:name":"Ban Na Cai",
    "wof:placetype":"locality"
},
  "geometry": {"coordinates":[103.70856000000001,22.19092],"type":"Point"}
}