{
  "type": "Feature",
  "properties": {
    "gn:admin1_code":"66.0",
    "gn:asciiname":"Tan Hoi",
    "gn:country_code":"VN",
    "gn:dem":8,
    "gn:feature_class":"P",
    "gn:feature_code":"PPL",
    "gn:name":"T\u00e2n H\u1ed9i",
    "gn:population":0,
    "gn:timezone":"Asia/Ho_Chi_Minh",
    "iso:country":"VN",
    "name:und_x_variant":[
        "Th\u00f4n T\u00e2n H\u00f4i"
    ],
    "name:vie_x_preferred":[
        "T\u00e2n H\u1ed9i"
    ],
    "wof:name":"Tan Hoi",
    "wof:placetype":"locality"
},
  "geometry": {"coordinates":[107.43333,16.7039],"type":"Point"}
}