{
  "type": "Feature",
  "properties": {
    "gn:admin1_code":"32.0",
    "gn:asciiname":"Ban Han",
    "gn:country_code":"VN",
    "gn:dem":663,
    "gn:feature_class":"P",
    "gn:feature_code":"PPL",
    "gn:name":"B\u1ea3n H\u00e1n",
    "gn:population":0,
    "gn:timezone":"Asia/Ho_Chi_Minh",
    "iso:country":"VN",
    "name:vie_x_preferred":[
        "B\u1ea3n H\u00e1n"
    ],
    "wof:name":"Ban Han",
    "wof:placetype":"locality"
},
  "geometry": {"coordinates":[103.66153,21.53064],"type":"Point"}
}