{
  "type": "Feature",
  "properties": {
    "gn:admin1_code":"20.0",
    "gn:asciiname":"Long Truong",
    "gn:cc2":"VN",
    "gn:country_code":"VN",
    "gn:dem":-1,
    "gn:feature_class":"P",
    "gn:feature_code":"PPL",
    "gn:name":"Long Tr\u01b0\u1eddng",
    "gn:population":0,
    "gn:timezone":"Asia/Ho_Chi_Minh",
    "iso:country":"VN",
    "name:und_x_variant":[
        "Phuoc Truong",
        "Long Tr\u01b0\u1eddng"
    ],
    "wof:name":"Long Truong",
    "wof:placetype":"locality"
},
  "geometry": {"coordinates":[106.81667,10.81667],"type":"Point"}
}