{
  "type": "Feature",
  "properties": {
    "gn:admin1_code":"23.0",
    "gn:asciiname":"Ap Man Ling",
    "gn:cc2":"VN",
    "gn:country_code":"VN",
    "gn:dem":1483,
    "gn:feature_class":"P",
    "gn:feature_code":"PPL",
    "gn:name":"\u1ea4p Man Ling",
    "gn:population":0,
    "gn:timezone":"Asia/Ho_Chi_Minh",
    "iso:country":"VN",
    "name:und_x_variant":[
        "Man Linh",
        "\u1ea4p Man Ling"
    ],
    "wof:name":"Ap Man Ling",
    "wof:placetype":"locality"
},
  "geometry": {"coordinates":[108.40000000000001,11.98333],"type":"Point"}
}