{
  "type": "Feature",
  "properties": {
    "gn:admin1_code":"81.0",
    "gn:asciiname":"Tam Trach",
    "gn:country_code":"VN",
    "gn:dem":6,
    "gn:feature_class":"P",
    "gn:feature_code":"PPL",
    "gn:name":"Tam Tr\u1ea1ch",
    "gn:population":0,
    "gn:timezone":"Asia/Ho_Chi_Minh",
    "iso:country":"VN",
    "name:vie_x_preferred":[
        "Tam Tr\u1ea1ch"
    ],
    "wof:name":"Tam Trach",
    "wof:placetype":"locality"
},
  "geometry": {"coordinates":[106.07043,20.88581],"type":"Point"}
}