{
  "type": "Feature",
  "properties": {
    "gn:admin1_code":"58.0",
    "gn:asciiname":"Van Tap",
    "gn:country_code":"VN",
    "gn:dem":8,
    "gn:feature_class":"P",
    "gn:feature_code":"PPL",
    "gn:name":"V\u0103n T\u1eadp",
    "gn:population":0,
    "gn:timezone":"Asia/Ho_Chi_Minh",
    "iso:country":"VN",
    "name:vie_x_preferred":[
        "V\u0103n T\u1eadp"
    ],
    "wof:name":"Van Tap",
    "wof:placetype":"locality"
},
  "geometry": {"coordinates":[105.53829,18.96675],"type":"Point"}
}