{
  "type": "Feature",
  "properties": {
    "gn:admin1_code":"32.0",
    "gn:asciiname":"Ban Day",
    "gn:country_code":"VN",
    "gn:dem":1000,
    "gn:feature_class":"P",
    "gn:feature_code":"PPL",
    "gn:name":"B\u1ea3n \u0110\u1ea9y",
    "gn:population":0,
    "gn:timezone":"Asia/Ho_Chi_Minh",
    "iso:country":"VN",
    "wof:name":"Ban Day",
    "wof:placetype":"locality"
},
  "geometry": {"coordinates":[103.75,21.35],"type":"Point"}
}