{
  "type": "Feature",
  "properties": {
    "gn:admin1_code":"32.0",
    "gn:asciiname":"Den Din",
    "gn:country_code":"VN",
    "gn:dem":665,
    "gn:feature_class":"P",
    "gn:feature_code":"PPL",
    "gn:name":"\u0110en \u0110in",
    "gn:population":0,
    "gn:timezone":"Asia/Ho_Chi_Minh",
    "iso:country":"VN",
    "name:vie_x_preferred":[
        "\u0110en \u0110in"
    ],
    "wof:name":"Den Din",
    "wof:placetype":"locality"
},
  "geometry": {"coordinates":[103.88146,21.58185],"type":"Point"}
}