{
  "type": "Feature",
  "properties": {
    "gn:admin1_code":"23.0",
    "gn:asciiname":"Thon Bon",
    "gn:country_code":"VN",
    "gn:dem":1477,
    "gn:feature_class":"P",
    "gn:feature_code":"PPL",
    "gn:name":"Th\u00f4n B\u1ed1n",
    "gn:population":0,
    "gn:timezone":"Asia/Ho_Chi_Minh",
    "iso:country":"VN",
    "name:vie_x_preferred":[
        "Th\u00f4n B\u1ed1n"
    ],
    "name:vie_x_variant":[
        "Th\u00f4n 4"
    ],
    "wof:name":"Thon Bon",
    "wof:placetype":"locality"
},
  "geometry": {"coordinates":[108.50286,12.05252],"type":"Point"}
}