{
  "type": "Feature",
  "properties": {
    "gn:admin1_code":"64.0",
    "gn:asciiname":"Luan Ly",
    "gn:country_code":"VN",
    "gn:dem":21,
    "gn:feature_class":"P",
    "gn:feature_code":"PPL",
    "gn:name":"Luan Ly",
    "gn:population":0,
    "gn:timezone":"Asia/Ho_Chi_Minh",
    "iso:country":"VN",
    "name:und_x_variant":[
        "Luam Ly",
        "Luan Ly"
    ],
    "wof:name":"Luan Ly",
    "wof:placetype":"locality"
},
  "geometry": {"coordinates":[107.09999999999999,17.01667],"type":"Point"}
}