{
  "type": "Feature",
  "properties": {
    "gn:admin1_code":"82.0",
    "gn:asciiname":"Diem Dien",
    "gn:country_code":"VN",
    "gn:dem":3,
    "gn:feature_class":"P",
    "gn:feature_code":"PPL",
    "gn:name":"Di\u00eam \u0110i\u1ec1n",
    "gn:population":0,
    "gn:timezone":"Asia/Ho_Chi_Minh",
    "iso:country":"VN",
    "name:vie_x_preferred":[
        "Di\u00eam \u0110i\u1ec1n"
    ],
    "wof:name":"Diem Dien",
    "wof:placetype":"locality"
},
  "geometry": {"coordinates":[106.46799,20.25211],"type":"Point"}
}