{
  "type": "Feature",
  "properties": {
    "gn:admin1_code":"32.0",
    "gn:asciiname":"Ban Dan A",
    "gn:country_code":"VN",
    "gn:dem":917,
    "gn:feature_class":"P",
    "gn:feature_code":"PPL",
    "gn:name":"B\u1ea3n D\u1eb1n A",
    "gn:population":0,
    "gn:timezone":"Asia/Ho_Chi_Minh",
    "iso:country":"VN",
    "name:vie_x_preferred":[
        "B\u1ea3n D\u1eb1n A"
    ],
    "wof:name":"Ban Dan A",
    "wof:placetype":"locality"
},
  "geometry": {"coordinates":[104.59429,21.14795],"type":"Point"}
}