{
  "type": "Feature",
  "properties": {
    "gn:admin1_code":"32.0",
    "gn:asciiname":"Ban Co Chai",
    "gn:country_code":"VN",
    "gn:dem":771,
    "gn:feature_class":"P",
    "gn:feature_code":"PPL",
    "gn:name":"B\u1ea3n Co Chai",
    "gn:population":0,
    "gn:timezone":"Asia/Ho_Chi_Minh",
    "iso:country":"VN",
    "name:und_x_variant":[
        "B\u1ea3n C\u00f4 Chai"
    ],
    "name:vie_x_preferred":[
        "B\u1ea3n Co Chai"
    ],
    "name:vie_x_variant":[
        "Co Chai"
    ],
    "wof:name":"Ban Co Chai",
    "wof:placetype":"locality"
},
  "geometry": {"coordinates":[104.08806,21.1407],"type":"Point"}
}