{
  "type": "Feature",
  "properties": {
    "gn:admin1_code":"88.0",
    "gn:asciiname":"Buon Le",
    "gn:cc2":"VN",
    "gn:country_code":"VN",
    "gn:dem":416,
    "gn:feature_class":"P",
    "gn:feature_code":"PPL",
    "gn:name":"Bu\u00f4n Le",
    "gn:population":0,
    "gn:timezone":"Asia/Ho_Chi_Minh",
    "iso:country":"VN",
    "name:und_x_variant":[
        "Ban Le",
        "Bu\u00f4n Le"
    ],
    "wof:name":"Buon Le",
    "wof:placetype":"locality"
},
  "geometry": {"coordinates":[108.18333,12.41667],"type":"Point"}
}