{
  "type": "Feature",
  "properties": {
    "gn:admin1_code":"49.0",
    "gn:asciiname":"Plei Bong",
    "gn:country_code":"VN",
    "gn:dem":707,
    "gn:feature_class":"P",
    "gn:feature_code":"PPL",
    "gn:name":"Plei B\u00f4ng",
    "gn:population":0,
    "gn:timezone":"Asia/Ho_Chi_Minh",
    "iso:country":"VN",
    "name:vie_x_preferred":[
        "Plei B\u00f4ng"
    ],
    "wof:name":"Plei Bong",
    "wof:placetype":"locality"
},
  "geometry": {"coordinates":[108.05436,13.82385],"type":"Point"}
}