{
  "type": "Feature",
  "properties": {
    "gn:admin1_code":"71.0",
    "gn:asciiname":"Bo Man",
    "gn:country_code":"VN",
    "gn:dem":12,
    "gn:feature_class":"P",
    "gn:feature_code":"PPL",
    "gn:name":"B\u1edd M\u1eadn",
    "gn:population":0,
    "gn:timezone":"Asia/Ho_Chi_Minh",
    "iso:country":"VN",
    "name:vie_x_preferred":[
        "B\u1edd M\u1eadn"
    ],
    "wof:name":"Bo Man",
    "wof:placetype":"locality"
},
  "geometry": {"coordinates":[106.19556,21.45578],"type":"Point"}
}