{
  "type": "Feature",
  "properties": {
    "gn:admin1_code":"59.0",
    "gn:asciiname":"Me",
    "gn:country_code":"VN",
    "gn:dem":10,
    "gn:feature_class":"P",
    "gn:feature_code":"PPLA2",
    "gn:name":"Me",
    "gn:population":0,
    "gn:timezone":"Asia/Ho_Chi_Minh",
    "iso:country":"VN",
    "name:hun_x_preferred":[
        "Me"
    ],
    "name:ind_x_preferred":[
        "Me"
    ],
    "name:vie_x_preferred":[
        "Me"
    ],
    "wof:name":"Me",
    "wof:placetype":"locality"
},
  "geometry": {"coordinates":[105.83615,20.34697],"type":"Point"}
}