{
  "type": "Feature",
  "properties": {
    "gn:admin1_code":"50.0",
    "gn:asciiname":"Khau Cua",
    "gn:country_code":"VN",
    "gn:dem":373,
    "gn:feature_class":"P",
    "gn:feature_code":"PPL",
    "gn:name":"Khau Cua",
    "gn:population":0,
    "gn:timezone":"Asia/Ho_Chi_Minh",
    "iso:country":"VN",
    "name:vie_x_preferred":[
        "Khau C\u00f9a"
    ],
    "name:vie_x_variant":[
        "Khau Cua"
    ],
    "wof:name":"Khau Cua",
    "wof:placetype":"locality"
},
  "geometry": {"coordinates":[105.27675000000001,22.98066],"type":"Point"}
}