{
  "type": "Feature",
  "properties": {
    "gn:admin1_code":"66.0",
    "gn:asciiname":"Ap An Lo",
    "gn:country_code":"VN",
    "gn:dem":7,
    "gn:feature_class":"P",
    "gn:feature_code":"PPL",
    "gn:name":"\u1ea4p An L\u1ed7",
    "gn:population":0,
    "gn:timezone":"Asia/Ho_Chi_Minh",
    "iso:country":"VN",
    "name:und_x_variant":[
        "An Lo",
        "\u1ea4p An L\u1ed7"
    ],
    "wof:name":"Ap An Lo",
    "wof:placetype":"locality"
},
  "geometry": {"coordinates":[107.46666999999999,16.55],"type":"Point"}
}