{
  "type": "Feature",
  "properties": {
    "gn:admin1_code":"35.0",
    "gn:asciiname":"Tien Hai",
    "gn:country_code":"VN",
    "gn:dem":5,
    "gn:feature_class":"P",
    "gn:feature_code":"PPLA2",
    "gn:name":"Ti\u1ec1n H\u1ea3i",
    "gn:population":0,
    "gn:timezone":"Asia/Ho_Chi_Minh",
    "iso:country":"VN",
    "name:und_x_variant":[
        "Ti\u1ec1n H\u1ea3i",
        "Ngo\u1ea1i \u0110\u00ea"
    ],
    "wof:name":"Tien Hai",
    "wof:placetype":"locality"
},
  "geometry": {"coordinates":[106.50364999999999,20.40557],"type":"Point"}
}