{
  "type": "Feature",
  "properties": {
    "gn:admin1_code":"81.0",
    "gn:asciiname":"Vong Phan",
    "gn:country_code":"VN",
    "gn:dem":9,
    "gn:feature_class":"P",
    "gn:feature_code":"PPL",
    "gn:name":"V\u00f5ng Phan",
    "gn:population":0,
    "gn:timezone":"Asia/Ho_Chi_Minh",
    "iso:country":"VN",
    "name:und_x_variant":[
        "V\u00f5ng Ph\u00e0n"
    ],
    "name:vie_x_preferred":[
        "V\u00f5ng Phan"
    ],
    "wof:name":"Vong Phan",
    "wof:placetype":"locality"
},
  "geometry": {"coordinates":[106.19589000000001,20.65171],"type":"Point"}
}