{
  "type": "Feature",
  "properties": {
    "gn:admin1_code":"88.0",
    "gn:asciiname":"Buon Hang",
    "gn:country_code":"VN",
    "gn:dem":437,
    "gn:feature_class":"P",
    "gn:feature_code":"PPL",
    "gn:name":"Bu\u00f4n Hang",
    "gn:population":0,
    "gn:timezone":"Asia/Ho_Chi_Minh",
    "iso:country":"VN",
    "wof:name":"Buon Hang",
    "wof:placetype":"locality"
},
  "geometry": {"coordinates":[108.40000000000001,12.61667],"type":"Point"}
}