{
  "type": "Feature",
  "properties": {
    "gn:admin1_code":"78.0",
    "gn:asciiname":"Khu Pho Nam Tho",
    "gn:country_code":"VN",
    "gn:dem":7,
    "gn:feature_class":"P",
    "gn:feature_code":"PPL",
    "gn:name":"Khu Ph\u1ed1 Nam Th\u1ecd",
    "gn:population":0,
    "gn:timezone":"Asia/Ho_Chi_Minh",
    "iso:country":"VN",
    "name:und_x_variant":[
        "Nam Tho",
        "Phong Nam Th\u1ecd",
        "Khu Ph\u1ed1 Nam Th\u1ecd"
    ],
    "wof:name":"Khu Pho Nam Tho",
    "wof:placetype":"locality"
},
  "geometry": {"coordinates":[108.2593,16.1054],"type":"Point"}
}