{
  "type": "Feature",
  "properties": {
    "gn:admin1_code":"32.0",
    "gn:asciiname":"Ban Khau Pum",
    "gn:country_code":"VN",
    "gn:dem":1301,
    "gn:feature_class":"P",
    "gn:feature_code":"PPL",
    "gn:name":"B\u1ea3n Khau P\u00f9m",
    "gn:population":0,
    "gn:timezone":"Asia/Ho_Chi_Minh",
    "iso:country":"VN",
    "name:vie_x_preferred":[
        "B\u1ea3n Khau P\u00f9m"
    ],
    "wof:name":"Ban Khau Pum",
    "wof:placetype":"locality"
},
  "geometry": {"coordinates":[103.68317999999999,21.83279],"type":"Point"}
}