{
  "type": "Feature",
  "properties": {
    "gn:admin1_code":"72.0",
    "gn:asciiname":"Khuoi Vien",
    "gn:country_code":"VN",
    "gn:dem":631,
    "gn:feature_class":"P",
    "gn:feature_code":"PPL",
    "gn:name":"Khu\u1ed5i Vi\u1ec1n",
    "gn:population":0,
    "gn:timezone":"Asia/Ho_Chi_Minh",
    "iso:country":"VN",
    "name:und_x_variant":[
        "Khu\u1ed5i Vi\u1ec1n",
        "Loung Vien"
    ],
    "wof:name":"Khuoi Vien",
    "wof:placetype":"locality"
},
  "geometry": {"coordinates":[105.90846000000001,22.48078],"type":"Point"}
}