{
  "type": "Feature",
  "properties": {
    "gn:admin1_code":"39.0",
    "gn:asciiname":"Ban Pe",
    "gn:country_code":"VN",
    "gn:dem":158,
    "gn:feature_class":"P",
    "gn:feature_code":"PPL",
    "gn:name":"B\u1ea3n Pe",
    "gn:population":0,
    "gn:timezone":"Asia/Ho_Chi_Minh",
    "iso:country":"VN",
    "name:vie_x_preferred":[
        "B\u1ea3n Pe"
    ],
    "wof:name":"Ban Pe",
    "wof:placetype":"locality"
},
  "geometry": {"coordinates":[107.08434,21.47483],"type":"Point"}
}