{
  "type": "Feature",
  "properties": {
    "gn:admin1_code":"44.0",
    "gn:asciiname":"Xom Quan",
    "gn:country_code":"VN",
    "gn:dem":96,
    "gn:feature_class":"P",
    "gn:feature_code":"PPL",
    "gn:name":"X\u00f3m Qu\u00e1n",
    "gn:population":0,
    "gn:timezone":"Asia/Ho_Chi_Minh",
    "iso:country":"VN",
    "name:vie_x_preferred":[
        "X\u00f3m Qu\u00e1n"
    ],
    "wof:name":"Xom Quan",
    "wof:placetype":"locality"
},
  "geometry": {"coordinates":[105.35372,21.02736],"type":"Point"}
}