{
  "type": "Feature",
  "properties": {
    "gn:admin1_code":"46.0",
    "gn:asciiname":"Xom Tho Lam Ha",
    "gn:country_code":"VN",
    "gn:dem":22,
    "gn:feature_class":"P",
    "gn:feature_code":"PPL",
    "gn:name":"X\u00f3m Th\u1ecd L\u00e2m H\u1ea1",
    "gn:population":0,
    "gn:timezone":"Asia/Ho_Chi_Minh",
    "iso:country":"VN",
    "wof:name":"Xom Tho Lam Ha",
    "wof:placetype":"locality"
},
  "geometry": {"coordinates":[109.01667,13.81667],"type":"Point"}
}