{
  "type": "Feature",
  "properties": {
    "gn:admin1_code":"74.0",
    "gn:asciiname":"Thon Che",
    "gn:country_code":"VN",
    "gn:dem":5,
    "gn:feature_class":"P",
    "gn:feature_code":"PPL",
    "gn:name":"Th\u00f4n Ch\u00e8",
    "gn:population":0,
    "gn:timezone":"Asia/Ho_Chi_Minh",
    "iso:country":"VN",
    "name:vie_x_preferred":[
        "Th\u00f4n Ch\u00e8"
    ],
    "wof:name":"Thon Che",
    "wof:placetype":"locality"
},
  "geometry": {"coordinates":[106.09383,21.01337],"type":"Point"}
}