{
  "type": "Feature",
  "properties": {
    "gn:admin1_code":"5.0",
    "gn:asciiname":"Ban Pac Ken",
    "gn:country_code":"VN",
    "gn:dem":472,
    "gn:feature_class":"P",
    "gn:feature_code":"PPL",
    "gn:name":"B\u1ea3n P\u00e1c K\u00e9n",
    "gn:population":0,
    "gn:timezone":"Asia/Ho_Chi_Minh",
    "iso:country":"VN",
    "name:vie_x_preferred":[
        "P\u00e1o K\u00e9n"
    ],
    "name:vie_x_variant":[
        "B\u1ea3n P\u00e1c K\u00e9n"
    ],
    "wof:name":"Ban Pac Ken",
    "wof:placetype":"locality"
},
  "geometry": {"coordinates":[105.41173999999999,22.95897],"type":"Point"}
}