{
  "type": "Feature",
  "properties": {
    "gn:admin1_code":"23.0",
    "gn:asciiname":"Dan Kia",
    "gn:country_code":"VN",
    "gn:dem":1456,
    "gn:feature_class":"P",
    "gn:feature_code":"PPL",
    "gn:name":"Dan Kia",
    "gn:population":0,
    "gn:timezone":"Asia/Ho_Chi_Minh",
    "iso:country":"VN",
    "name:und_x_variant":[
        "\u1ea4p Dan Kia",
        "Dang Gia",
        "\u0110an Kia",
        "Doukia",
        "Dankia"
    ],
    "name:vie_x_preferred":[
        "Dan Kia"
    ],
    "wof:name":"Dan Kia",
    "wof:placetype":"locality"
},
  "geometry": {"coordinates":[108.39328999999999,12.01619],"type":"Point"}
}