{
  "type": "Feature",
  "properties": {
    "gn:admin1_code":"41.0",
    "gn:asciiname":"Ap Nhon Phu",
    "gn:cc2":"VN",
    "gn:country_code":"VN",
    "gn:dem":1,
    "gn:feature_class":"P",
    "gn:feature_code":"PPL",
    "gn:name":"\u1ea4p Nh\u01a1n Ph\u00fa",
    "gn:population":0,
    "gn:timezone":"Asia/Ho_Chi_Minh",
    "iso:country":"VN",
    "name:und_x_variant":[
        "\u1ea4p Nh\u00e2n Ph\u00fa",
        "\u1ea4p Nh\u01a1n Ph\u00fa"
    ],
    "wof:name":"Ap Nhon Phu",
    "wof:placetype":"locality"
},
  "geometry": {"coordinates":[105.66667,9.95],"type":"Point"}
}