{
  "type": "Feature",
  "properties": {
    "gn:admin1_code":"23.0",
    "gn:asciiname":"Brui Hang Liang",
    "gn:cc2":"VN",
    "gn:country_code":"VN",
    "gn:dem":968,
    "gn:feature_class":"P",
    "gn:feature_code":"PPL",
    "gn:name":"Brui Hang Liang",
    "gn:population":0,
    "gn:timezone":"Asia/Ho_Chi_Minh",
    "iso:country":"VN",
    "name:und_x_variant":[
        "Broui Han Lian",
        "Brui Hang Liang"
    ],
    "wof:name":"Brui Hang Liang",
    "wof:placetype":"locality"
},
  "geometry": {"coordinates":[108.01667,11.51667],"type":"Point"}
}