{
  "type": "Feature",
  "properties": {
    "gn:admin1_code":"52.0",
    "gn:asciiname":"Xom Ba",
    "gn:country_code":"VN",
    "gn:dem":8,
    "gn:feature_class":"P",
    "gn:feature_code":"PPL",
    "gn:name":"X\u00f3m Ba",
    "gn:population":0,
    "gn:timezone":"Asia/Ho_Chi_Minh",
    "iso:country":"VN",
    "name:vie_x_preferred":[
        "X\u00f3m Ba"
    ],
    "name:vie_x_variant":[
        "X\u00f3m 3"
    ],
    "wof:name":"Xom Ba",
    "wof:placetype":"locality"
},
  "geometry": {"coordinates":[105.95117,18.31846],"type":"Point"}
}