{
  "type": "Feature",
  "properties": {
    "gn:admin1_code":"72.0",
    "gn:asciiname":"Keo Tat",
    "gn:country_code":"VN",
    "gn:dem":761,
    "gn:feature_class":"P",
    "gn:feature_code":"PPL",
    "gn:name":"Keo Tat",
    "gn:population":0,
    "gn:timezone":"Asia/Ho_Chi_Minh",
    "iso:country":"VN",
    "wof:name":"Keo Tat",
    "wof:placetype":"locality"
},
  "geometry": {"coordinates":[105.55,22.21667],"type":"Point"}
}