{
  "type": "Feature",
  "properties": {
    "gn:admin1_code":"52.0",
    "gn:asciiname":"Xom Trang",
    "gn:country_code":"VN",
    "gn:dem":56,
    "gn:feature_class":"P",
    "gn:feature_code":"PPL",
    "gn:name":"X\u00f3m Tr\u00e1ng",
    "gn:population":0,
    "gn:timezone":"Asia/Ho_Chi_Minh",
    "iso:country":"VN",
    "name:und_x_variant":[
        "Xom Tiang",
        "X\u00f3m Tr\u00e1ng"
    ],
    "wof:name":"Xom Trang",
    "wof:placetype":"locality"
},
  "geometry": {"coordinates":[106.15000000000001,18.01667],"type":"Point"}
}