{
  "type": "Feature",
  "properties": {
    "gn:admin1_code":"70.0",
    "gn:asciiname":"Hong Phong",
    "gn:country_code":"VN",
    "gn:dem":49,
    "gn:feature_class":"P",
    "gn:feature_code":"PPL",
    "gn:name":"H\u1ed3ng Phong",
    "gn:population":0,
    "gn:timezone":"Asia/Ho_Chi_Minh",
    "iso:country":"VN",
    "name:vie_x_preferred":[
        "H\u1ed3ng Phong"
    ],
    "wof:name":"Hong Phong",
    "wof:placetype":"locality"
},
  "geometry": {"coordinates":[104.68188000000001,21.88045],"type":"Point"}
}