{
  "type": "Feature",
  "properties": {
    "gn:admin1_code":"88.0",
    "gn:asciiname":"Loc Thanh",
    "gn:country_code":"VN",
    "gn:dem":699,
    "gn:feature_class":"P",
    "gn:feature_code":"PPL",
    "gn:name":"L\u1ed9c Th\u1ea1nh",
    "gn:population":0,
    "gn:timezone":"Asia/Ho_Chi_Minh",
    "iso:country":"VN",
    "name:vie_x_preferred":[
        "L\u1ed9c Th\u1ea1nh"
    ],
    "wof:name":"Loc Thanh",
    "wof:placetype":"locality"
},
  "geometry": {"coordinates":[108.3447,12.97888],"type":"Point"}
}