{
  "type": "Feature",
  "properties": {
    "gn:admin1_code":"5.0",
    "gn:asciiname":"Lang Tchen",
    "gn:cc2":"VN",
    "gn:country_code":"VN",
    "gn:dem":715,
    "gn:feature_class":"P",
    "gn:feature_code":"PPL",
    "gn:name":"L\u00e0ng Tchen",
    "gn:population":0,
    "gn:timezone":"Asia/Ho_Chi_Minh",
    "iso:country":"VN",
    "name:und_x_variant":[
        "Lang Tchem",
        "L\u00e0ng Tchen"
    ],
    "wof:name":"Lang Tchen",
    "wof:placetype":"locality"
},
  "geometry": {"coordinates":[105.91667,22.71667],"type":"Point"}
}