{
  "type": "Feature",
  "properties": {
    "gn:admin1_code":"62.0",
    "gn:asciiname":"Phuc Loc",
    "gn:country_code":"VN",
    "gn:dem":8,
    "gn:feature_class":"P",
    "gn:feature_code":"PPL",
    "gn:name":"Ph\u00fac L\u1ed9c",
    "gn:population":0,
    "gn:timezone":"Asia/Ho_Chi_Minh",
    "iso:country":"VN",
    "name:und_x_variant":[
        "Ph\u00fac L\u1ed9c Ph\u01b0\u01a1ng",
        "Ph\u00fac L\u1ed9c"
    ],
    "wof:name":"Phuc Loc",
    "wof:placetype":"locality"
},
  "geometry": {"coordinates":[106.53333000000001,17.56667],"type":"Point"}
}