{
  "type": "Feature",
  "properties": {
    "gn:admin1_code":"50.0",
    "gn:asciiname":"Lung Thang",
    "gn:country_code":"VN",
    "gn:dem":964,
    "gn:feature_class":"P",
    "gn:feature_code":"PPL",
    "gn:name":"L\u00fang Th\u00e0ng",
    "gn:population":0,
    "gn:timezone":"Asia/Ho_Chi_Minh",
    "iso:country":"VN",
    "name:vie_x_preferred":[
        "L\u00fang Th\u00e0ng"
    ],
    "wof:name":"Lung Thang",
    "wof:placetype":"locality"
},
  "geometry": {"coordinates":[105.22472999999999,23.00085],"type":"Point"}
}