{
  "type": "Feature",
  "properties": {
    "gn:admin1_code":"62.0",
    "gn:asciiname":"Dong Thanh",
    "gn:country_code":"VN",
    "gn:dem":21,
    "gn:feature_class":"P",
    "gn:feature_code":"PPL",
    "gn:name":"\u0110\u00f4ng Th\u00e0nh",
    "gn:population":0,
    "gn:timezone":"Asia/Ho_Chi_Minh",
    "iso:country":"VN",
    "name:und_x_variant":[
        "Ba \u0110\u00f4ng",
        "\u0110\u00f4ng Th\u00e0ng",
        "\u0110\u00f4ng Th\u00e0nh"
    ],
    "wof:name":"Dong Thanh",
    "wof:placetype":"locality"
},
  "geometry": {"coordinates":[106.51667,17.51667],"type":"Point"}
}