{
  "type": "Feature",
  "properties": {
    "gn:admin1_code":"72.0",
    "gn:asciiname":"Na Bua",
    "gn:country_code":"VN",
    "gn:dem":430,
    "gn:feature_class":"P",
    "gn:feature_code":"PPL",
    "gn:name":"Na Bua",
    "gn:population":0,
    "gn:timezone":"Asia/Ho_Chi_Minh",
    "iso:country":"VN",
    "wof:name":"Na Bua",
    "wof:placetype":"locality"
},
  "geometry": {"coordinates":[105.56667,22.16667],"type":"Point"}
}