{
  "type": "Feature",
  "properties": {
    "gn:admin1_code":"72.0",
    "gn:asciiname":"Van Tung",
    "gn:country_code":"VN",
    "gn:dem":491,
    "gn:feature_class":"P",
    "gn:feature_code":"PPLA2",
    "gn:name":"V\u00e2n T\u00f9ng",
    "gn:population":0,
    "gn:timezone":"Asia/Ho_Chi_Minh",
    "iso:country":"VN",
    "name:und_x_variant":[
        "Ng\u00e2n S\u01a1n"
    ],
    "name:vie_x_preferred":[
        "V\u00e2n T\u00f9ng"
    ],
    "wof:name":"Van Tung",
    "wof:placetype":"locality"
},
  "geometry": {"coordinates":[105.99687,22.43082],"type":"Point"}
}