{
  "type": "Feature",
  "properties": {
    "gn:admin1_code":"67.0",
    "gn:asciiname":"Bai Sao Sat",
    "gn:country_code":"VN",
    "gn:dem":7,
    "gn:feature_class":"P",
    "gn:feature_code":"PPL",
    "gn:name":"B\u00e3i S\u00e0o S\u1eaft",
    "gn:population":0,
    "gn:timezone":"Asia/Ho_Chi_Minh",
    "iso:country":"VN",
    "name:vie_x_preferred":[
        "B\u00e3i S\u00e0o S\u1eaft"
    ],
    "wof:name":"Bai Sao Sat",
    "wof:placetype":"locality"
},
  "geometry": {"coordinates":[106.21657,9.66946],"type":"Point"}
}