{
  "type": "Feature",
  "properties": {
    "gn:admin1_code":"39.0",
    "gn:asciiname":"Hoan Ha",
    "gn:country_code":"VN",
    "gn:dem":316,
    "gn:feature_class":"P",
    "gn:feature_code":"PPL",
    "gn:name":"Hoan Ha",
    "gn:population":0,
    "gn:timezone":"Asia/Ho_Chi_Minh",
    "iso:country":"VN",
    "wof:name":"Hoan Ha",
    "wof:placetype":"locality"
},
  "geometry": {"coordinates":[106.16667,21.78333],"type":"Point"}
}