{
  "type": "Feature",
  "properties": {
    "gn:admin1_code":"49.0",
    "gn:asciiname":"H'Loi",
    "gn:country_code":"VN",
    "gn:dem":115,
    "gn:feature_class":"P",
    "gn:feature_code":"PPL",
    "gn:name":"H\u2019L\u1ed1i",
    "gn:population":0,
    "gn:timezone":"Asia/Ho_Chi_Minh",
    "iso:country":"VN",
    "name:und_x_variant":[
        "Buon Loi",
        "Ban Ling",
        "H\u2019L\u1ed1i"
    ],
    "wof:name":"H'Loi",
    "wof:placetype":"locality"
},
  "geometry": {"coordinates":[108.71751,13.07132],"type":"Point"}
}