{
  "type": "Feature",
  "properties": {
    "gn:admin1_code":"90.0",
    "gn:asciiname":"Li Thang",
    "gn:country_code":"VN",
    "gn:dem":896,
    "gn:feature_class":"P",
    "gn:feature_code":"PPL",
    "gn:name":"Li Thang",
    "gn:population":0,
    "gn:timezone":"Asia/Ho_Chi_Minh",
    "iso:country":"VN",
    "wof:name":"Li Thang",
    "wof:placetype":"locality"
},
  "geometry": {"coordinates":[104.16667,22.78333],"type":"Point"}
}