{
  "type": "Feature",
  "properties": {
    "gn:admin1_code":"92.0",
    "gn:asciiname":"Nam Vi",
    "gn:country_code":"VN",
    "gn:dem":651,
    "gn:feature_class":"P",
    "gn:feature_code":"PPL",
    "gn:name":"N\u1eb1m Vi",
    "gn:population":0,
    "gn:timezone":"Asia/Ho_Chi_Minh",
    "iso:country":"VN",
    "name:und_x_variant":[
        "N\u1eb1m Vi"
    ],
    "name:vie_x_preferred":[
        "N\u1eadm V\u00ec"
    ],
    "wof:name":"Nam Vi",
    "wof:placetype":"locality"
},
  "geometry": {"coordinates":[102.51667,22.21667],"type":"Point"}
}