{
  "type": "Feature",
  "properties": {
    "gn:admin1_code":"89.0",
    "gn:asciiname":"Ban Na Hum",
    "gn:country_code":"VN",
    "gn:dem":614,
    "gn:feature_class":"P",
    "gn:feature_code":"PPL",
    "gn:name":"B\u1ea3n Na Hum",
    "gn:population":0,
    "gn:timezone":"Asia/Ho_Chi_Minh",
    "iso:country":"VN",
    "name:und_x_variant":[
        "No Hum",
        "Na Hum"
    ],
    "name:vie_x_preferred":[
        "B\u1ea3n Na Hum"
    ],
    "wof:name":"Ban Na Hum",
    "wof:placetype":"locality"
},
  "geometry": {"coordinates":[103.61606999999999,22.29247],"type":"Point"}
}