{
  "type": "Feature",
  "properties": {
    "gn:admin1_code":"70.0",
    "gn:asciiname":"Dat Rua",
    "gn:country_code":"VN",
    "gn:dem":60,
    "gn:feature_class":"P",
    "gn:feature_code":"PPL",
    "gn:name":"\u0110\u00e1t R\u00f9a",
    "gn:population":0,
    "gn:timezone":"Asia/Ho_Chi_Minh",
    "iso:country":"VN",
    "name:vie_x_preferred":[
        "\u0110\u00e1t R\u00f9a"
    ],
    "wof:name":"Dat Rua",
    "wof:placetype":"locality"
},
  "geometry": {"coordinates":[105.02303999999999,21.79285],"type":"Point"}
}