{
  "type": "Feature",
  "properties": {
    "gn:admin1_code":"39.0",
    "gn:asciiname":"Ban Pac Cu",
    "gn:country_code":"VN",
    "gn:dem":242,
    "gn:feature_class":"P",
    "gn:feature_code":"PPL",
    "gn:name":"B\u1ea3n P\u1eafc C\u00fa",
    "gn:population":0,
    "gn:timezone":"Asia/Ho_Chi_Minh",
    "iso:country":"VN",
    "name:und_x_variant":[
        "B\u1ea3n P\u1eafc C\u00fa",
        "Pac Cu"
    ],
    "wof:name":"Ban Pac Cu",
    "wof:placetype":"locality"
},
  "geometry": {"coordinates":[106.68022000000001,22.09163],"type":"Point"}
}