{
  "type": "Feature",
  "properties": {
    "gn:admin1_code":"58.0",
    "gn:asciiname":"Duc Lien",
    "gn:country_code":"VN",
    "gn:dem":8,
    "gn:feature_class":"P",
    "gn:feature_code":"PPL",
    "gn:name":"\u0110\u1ee9c Li\u00ean",
    "gn:population":0,
    "gn:timezone":"Asia/Ho_Chi_Minh",
    "iso:country":"VN",
    "name:vie_x_preferred":[
        "\u0110\u1ee9c Li\u00ean"
    ],
    "wof:name":"Duc Lien",
    "wof:placetype":"locality"
},
  "geometry": {"coordinates":[105.55728999999999,19.09614],"type":"Point"}
}