{
  "type": "Feature",
  "properties": {
    "gn:admin1_code":"89.0",
    "gn:asciiname":"Huoi Na",
    "gn:country_code":"VN",
    "gn:dem":366,
    "gn:feature_class":"P",
    "gn:feature_code":"PPL",
    "gn:name":"Hu\u1ed5i N\u1ea3",
    "gn:population":0,
    "gn:timezone":"Asia/Ho_Chi_Minh",
    "iso:country":"VN",
    "name:vie_x_preferred":[
        "Hu\u1ed5i N\u1ea3"
    ],
    "wof:name":"Huoi Na",
    "wof:placetype":"locality"
},
  "geometry": {"coordinates":[103.34233,22.55019],"type":"Point"}
}