{
  "type": "Feature",
  "properties": {
    "gn:admin1_code":"58.0",
    "gn:asciiname":"Lien Chung",
    "gn:country_code":"VN",
    "gn:dem":28,
    "gn:feature_class":"P",
    "gn:feature_code":"PPL",
    "gn:name":"Li\u00ean Chung",
    "gn:population":0,
    "gn:timezone":"Asia/Ho_Chi_Minh",
    "iso:country":"VN",
    "name:vie_x_preferred":[
        "Li\u00ean Chung"
    ],
    "wof:name":"Lien Chung",
    "wof:placetype":"locality"
},
  "geometry": {"coordinates":[105.26264,18.84036],"type":"Point"}
}