{
  "type": "Feature",
  "properties": {
    "gn:admin1_code":"34.0",
    "gn:asciiname":"Thon Eo",
    "gn:country_code":"VN",
    "gn:dem":103,
    "gn:feature_class":"P",
    "gn:feature_code":"PPL",
    "gn:name":"Th\u00f4n \u00c9o",
    "gn:population":0,
    "gn:timezone":"Asia/Ho_Chi_Minh",
    "iso:country":"VN",
    "name:vie_x_preferred":[
        "Th\u00f4n \u00c9o"
    ],
    "wof:name":"Thon Eo",
    "wof:placetype":"locality"
},
  "geometry": {"coordinates":[105.03863,20.46481],"type":"Point"}
}