{
  "type": "Feature",
  "properties": {
    "gn:admin1_code":"20.0",
    "gn:asciiname":"Cau Muong Chuoi",
    "gn:country_code":"VN",
    "gn:dem":0,
    "gn:feature_class":"P",
    "gn:feature_code":"PPL",
    "gn:name":"C\u1ea7u M\u01b0\u01a1ng Chu\u00f4i",
    "gn:population":0,
    "gn:timezone":"Asia/Ho_Chi_Minh",
    "iso:country":"VN",
    "wof:name":"Cau Muong Chuoi",
    "wof:placetype":"locality"
},
  "geometry": {"coordinates":[106.73333,10.66667],"type":"Point"}
}