{
  "type": "Feature",
  "properties": {
    "gn:admin1_code":"39.0",
    "gn:asciiname":"Song Hoa",
    "gn:country_code":"VN",
    "gn:dem":406,
    "gn:feature_class":"P",
    "gn:feature_code":"PPL",
    "gn:name":"S\u00f4ng H\u00f3a",
    "gn:population":0,
    "gn:timezone":"Asia/Ho_Chi_Minh",
    "iso:country":"VN",
    "name:vie_x_preferred":[
        "S\u00f4ng H\u00f3a"
    ],
    "wof:name":"Song Hoa",
    "wof:placetype":"locality"
},
  "geometry": {"coordinates":[106.30468,21.83704],"type":"Point"}
}