{
  "type": "Feature",
  "properties": {
    "gn:admin1_code":"70.0",
    "gn:asciiname":"Co Ge Phong",
    "gn:country_code":"VN",
    "gn:dem":1446,
    "gn:feature_class":"P",
    "gn:feature_code":"PPL",
    "gn:name":"Co Ge Phong",
    "gn:population":0,
    "gn:timezone":"Asia/Ho_Chi_Minh",
    "iso:country":"VN",
    "wof:name":"Co Ge Phong",
    "wof:placetype":"locality"
},
  "geometry": {"coordinates":[104.15000000000001,21.76667],"type":"Point"}
}