{
  "type": "Feature",
  "properties": {
    "gn:admin1_code":"87.0",
    "gn:asciiname":"Nhon Khanh",
    "gn:country_code":"VN",
    "gn:dem":5,
    "gn:feature_class":"P",
    "gn:feature_code":"PPL",
    "gn:name":"Nh\u01a1n Kh\u00e1nh",
    "gn:population":0,
    "gn:timezone":"Asia/Ho_Chi_Minh",
    "iso:country":"VN",
    "name:und_x_variant":[
        "\u1ea4p Nh\u01a1n Kh\u00e1nh"
    ],
    "name:vie_x_preferred":[
        "Nh\u01a1n Kh\u00e1nh"
    ],
    "wof:name":"Nhon Khanh",
    "wof:placetype":"locality"
},
  "geometry": {"coordinates":[105.70918,9.98449],"type":"Point"}
}