{
  "type": "Feature",
  "properties": {
    "gn:admin1_code":"44.0",
    "gn:asciiname":"Noi Xom",
    "gn:country_code":"VN",
    "gn:dem":9,
    "gn:feature_class":"P",
    "gn:feature_code":"PPL",
    "gn:name":"N\u1ed9i X\u00f3m",
    "gn:population":0,
    "gn:timezone":"Asia/Ho_Chi_Minh",
    "iso:country":"VN",
    "wof:name":"Noi Xom",
    "wof:placetype":"locality"
},
  "geometry": {"coordinates":[105.71666999999999,20.91667],"type":"Point"}
}