{
  "type": "Feature",
  "properties": {
    "gn:admin1_code":"71.0",
    "gn:asciiname":"Lang Ten",
    "gn:country_code":"VN",
    "gn:dem":93,
    "gn:feature_class":"P",
    "gn:feature_code":"PPL",
    "gn:name":"L\u00e0ng T\u00ean",
    "gn:population":0,
    "gn:timezone":"Asia/Ho_Chi_Minh",
    "iso:country":"VN",
    "name:und_x_variant":[
        "Lang Tan",
        "L\u00e0ng T\u00ean"
    ],
    "wof:name":"Lang Ten",
    "wof:placetype":"locality"
},
  "geometry": {"coordinates":[106.81667,21.41667],"type":"Point"}
}