{
  "type": "Feature",
  "properties": {
    "gn:admin1_code":"58.0",
    "gn:asciiname":"Ba Ra",
    "gn:country_code":"VN",
    "gn:dem":20,
    "gn:feature_class":"P",
    "gn:feature_code":"PPL",
    "gn:name":"B\u00e0 R\u00e1",
    "gn:population":0,
    "gn:timezone":"Asia/Ho_Chi_Minh",
    "iso:country":"VN",
    "name:vie_x_preferred":[
        "B\u00e0 R\u00e1"
    ],
    "wof:name":"Ba Ra",
    "wof:placetype":"locality"
},
  "geometry": {"coordinates":[105.65783999999999,19.23007],"type":"Point"}
}