{
  "type": "Feature",
  "properties": {
    "gn:admin1_code":"85.0",
    "gn:asciiname":"Kouei Meo",
    "gn:country_code":"VN",
    "gn:dem":321,
    "gn:feature_class":"P",
    "gn:feature_code":"PPL",
    "gn:name":"Kouei Meo",
    "gn:population":0,
    "gn:timezone":"Asia/Ho_Chi_Minh",
    "iso:country":"VN",
    "wof:name":"Kouei Meo",
    "wof:placetype":"locality"
},
  "geometry": {"coordinates":[105.95,21.86667000000001],"type":"Point"}
}