{
  "type": "Feature",
  "properties": {
    "gn:admin1_code":"34.0",
    "gn:asciiname":"Lang Bua",
    "gn:country_code":"VN",
    "gn:dem":81,
    "gn:feature_class":"P",
    "gn:feature_code":"PPL",
    "gn:name":"L\u00e0ng B\u1ee9a",
    "gn:population":0,
    "gn:timezone":"Asia/Ho_Chi_Minh",
    "iso:country":"VN",
    "name:vie_x_preferred":[
        "L\u00e0ng B\u1ee9a"
    ],
    "wof:name":"Lang Bua",
    "wof:placetype":"locality"
},
  "geometry": {"coordinates":[105.34183,20.11991],"type":"Point"}
}