{
  "type": "Feature",
  "properties": {
    "gn:admin1_code":"89.0",
    "gn:asciiname":"Ban Nam Coong",
    "gn:country_code":"VN",
    "gn:dem":683,
    "gn:feature_class":"P",
    "gn:feature_code":"PPL",
    "gn:name":"B\u1ea3n N\u1eadm Co\u00f3ng",
    "gn:population":0,
    "gn:timezone":"Asia/Ho_Chi_Minh",
    "iso:country":"VN",
    "name:und_x_variant":[
        "Nam Coung",
        "Nam Cong"
    ],
    "name:vie_x_preferred":[
        "N\u1eadm Co\u00f3ng"
    ],
    "name:vie_x_variant":[
        "B\u1ea3n N\u1eadm Co\u00f3ng"
    ],
    "wof:name":"Ban Nam Coong",
    "wof:placetype":"locality"
},
  "geometry": {"coordinates":[103.51488000000001,22.16056],"type":"Point"}
}