{
  "type": "Feature",
  "properties": {
    "gn:admin1_code":"68.0",
    "gn:asciiname":"Leng Bai",
    "gn:country_code":"VN",
    "gn:dem":132,
    "gn:feature_class":"P",
    "gn:feature_code":"PPL",
    "gn:name":"Leng Bai",
    "gn:population":0,
    "gn:timezone":"Asia/Ho_Chi_Minh",
    "iso:country":"VN",
    "name:und_x_variant":[
        "Lang Bai",
        "Leng Bai"
    ],
    "wof:name":"Leng Bai",
    "wof:placetype":"locality"
},
  "geometry": {"coordinates":[105.16667,22.33333],"type":"Point"}
}