{
  "type": "Feature",
  "properties": {
    "gn:admin1_code":"58.0",
    "gn:asciiname":"Xom Hai",
    "gn:country_code":"VN",
    "gn:dem":9,
    "gn:feature_class":"P",
    "gn:feature_code":"PPL",
    "gn:name":"X\u00f3m Hai",
    "gn:population":0,
    "gn:timezone":"Asia/Ho_Chi_Minh",
    "iso:country":"VN",
    "name:vie_x_preferred":[
        "X\u00f3m Hai"
    ],
    "name:vie_x_variant":[
        "X\u00f3m 2"
    ],
    "wof:name":"Xom Hai",
    "wof:placetype":"locality"
},
  "geometry": {"coordinates":[105.69998,18.78654],"type":"Point"}
}