{
  "type": "Feature",
  "properties": {
    "gn:admin1_code":"32.0",
    "gn:asciiname":"Tieu Khu Mot",
    "gn:country_code":"VN",
    "gn:dem":575,
    "gn:feature_class":"P",
    "gn:feature_code":"PPL",
    "gn:name":"Ti\u1ec3u Khu M\u1ed9t",
    "gn:population":0,
    "gn:timezone":"Asia/Ho_Chi_Minh",
    "iso:country":"VN",
    "name:vie_x_preferred":[
        "Ti\u1ec3u Khu M\u1ed9t"
    ],
    "name:vie_x_variant":[
        "Ti\u1ec3u Khu 1"
    ],
    "wof:name":"Tieu Khu Mot",
    "wof:placetype":"locality"
},
  "geometry": {"coordinates":[104.11548999999999,21.18462],"type":"Point"}
}