{
  "type": "Feature",
  "properties": {
    "gn:admin1_code":"68.0",
    "gn:asciiname":"Linh Thuan",
    "gn:country_code":"VN",
    "gn:dem":49,
    "gn:feature_class":"P",
    "gn:feature_code":"PPL",
    "gn:name":"Linh Thu\u1eadn",
    "gn:population":0,
    "gn:timezone":"Asia/Ho_Chi_Minh",
    "iso:country":"VN",
    "name:vie_x_preferred":[
        "Linh Thu\u1eadn"
    ],
    "wof:name":"Linh Thuan",
    "wof:placetype":"locality"
},
  "geometry": {"coordinates":[105.15871,21.8091],"type":"Point"}
}