{
  "type": "Feature",
  "properties": {
    "gn:admin1_code":"58.0",
    "gn:asciiname":"Lien Duc",
    "gn:country_code":"VN",
    "gn:dem":20,
    "gn:feature_class":"P",
    "gn:feature_code":"PPL",
    "gn:name":"Li\u00ean \u0110\u1ee9c",
    "gn:population":0,
    "gn:timezone":"Asia/Ho_Chi_Minh",
    "iso:country":"VN",
    "name:vie_x_preferred":[
        "Li\u00ean \u0110\u1ee9c"
    ],
    "wof:name":"Lien Duc",
    "wof:placetype":"locality"
},
  "geometry": {"coordinates":[105.26042,18.80893],"type":"Point"}
}