{
  "type": "Feature",
  "properties": {
    "gn:admin1_code":"65.0",
    "gn:asciiname":"Ap Phu Ninh",
    "gn:country_code":"VN",
    "gn:dem":3,
    "gn:feature_class":"P",
    "gn:feature_code":"PPL",
    "gn:name":"\u1ea4p Ph\u00fa Ninh",
    "gn:population":0,
    "gn:timezone":"Asia/Ho_Chi_Minh",
    "iso:country":"VN",
    "name:und_x_variant":[
        "Phu Ninh",
        "\u1ea4p Ph\u00fa Ninh"
    ],
    "wof:name":"Ap Phu Ninh",
    "wof:placetype":"locality"
},
  "geometry": {"coordinates":[105.95,9.61667],"type":"Point"}
}