{
  "type": "Feature",
  "properties": {
    "gn:admin1_code":"6.0",
    "gn:asciiname":"Giong Dinh",
    "gn:country_code":"VN",
    "gn:dem":2,
    "gn:feature_class":"P",
    "gn:feature_code":"PPL",
    "gn:name":"Gi\u1ed3ng \u0110inh",
    "gn:population":0,
    "gn:timezone":"Asia/Ho_Chi_Minh",
    "iso:country":"VN",
    "name:und_x_variant":[
        "An Thoi",
        "Gi\u1ed3ng \u0110inh"
    ],
    "wof:name":"Giong Dinh",
    "wof:placetype":"locality"
},
  "geometry": {"coordinates":[106.26667,9.63333],"type":"Point"}
}