{
  "type": "Feature",
  "properties": {
    "gn:admin1_code":"67.0",
    "gn:asciiname":"Soc Pna",
    "gn:cc2":"VN",
    "gn:country_code":"VN",
    "gn:dem":4,
    "gn:feature_class":"P",
    "gn:feature_code":"PPL",
    "gn:name":"S\u1ed1c Pna",
    "gn:population":0,
    "gn:timezone":"Asia/Ho_Chi_Minh",
    "iso:country":"VN",
    "name:und_x_variant":[
        "Pna",
        "S\u1ed1c Pna"
    ],
    "wof:name":"Soc Pna",
    "wof:placetype":"locality"
},
  "geometry": {"coordinates":[106.35861,9.84361],"type":"Point"}
}