{
  "type": "Feature",
  "properties": {
    "gn:admin1_code":"58.0",
    "gn:asciiname":"Xom Phuc Tho",
    "gn:country_code":"VN",
    "gn:dem":5,
    "gn:feature_class":"P",
    "gn:feature_code":"PPL",
    "gn:name":"X\u00f3m Phuc Th\u1ecd",
    "gn:population":0,
    "gn:timezone":"Asia/Ho_Chi_Minh",
    "iso:country":"VN",
    "name:und_x_variant":[
        "Phuc Tho",
        "X\u00f3m Phuc Th\u1ecd"
    ],
    "wof:name":"Xom Phuc Tho",
    "wof:placetype":"locality"
},
  "geometry": {"coordinates":[105.61667,18.75],"type":"Point"}
}