{
  "type": "Feature",
  "properties": {
    "gn:admin1_code":"79.0",
    "gn:asciiname":"Thon Ngo",
    "gn:country_code":"VN",
    "gn:dem":5,
    "gn:feature_class":"P",
    "gn:feature_code":"PPL",
    "gn:name":"Th\u00f4n Ng\u1ecd",
    "gn:population":0,
    "gn:timezone":"Asia/Ho_Chi_Minh",
    "iso:country":"VN",
    "name:vie_x_preferred":[
        "Th\u00f4n Ng\u1ecd"
    ],
    "wof:name":"Thon Ngo",
    "wof:placetype":"locality"
},
  "geometry": {"coordinates":[106.24863000000001,20.93002000000001],"type":"Point"}
}