{
  "type": "Feature",
  "properties": {
    "gn:admin1_code":"32.0",
    "gn:asciiname":"Na Hieng",
    "gn:country_code":"VN",
    "gn:dem":317,
    "gn:feature_class":"P",
    "gn:feature_code":"PPL",
    "gn:name":"N\u00e0 Hi\u1ec1ng",
    "gn:population":0,
    "gn:timezone":"Asia/Ho_Chi_Minh",
    "iso:country":"VN",
    "name:vie_x_preferred":[
        "N\u00e0 Hi\u1ec1ng"
    ],
    "wof:name":"Na Hieng",
    "wof:placetype":"locality"
},
  "geometry": {"coordinates":[104.76712999999999,20.70536],"type":"Point"}
}