{
  "type": "Feature",
  "properties": {
    "gn:admin1_code":"1.0",
    "gn:asciiname":"Nui Sap",
    "gn:country_code":"VN",
    "gn:dem":7,
    "gn:feature_class":"P",
    "gn:feature_code":"PPLA2",
    "gn:name":"N\u00fai S\u1eadp",
    "gn:population":0,
    "gn:timezone":"Asia/Ho_Chi_Minh",
    "iso:country":"VN",
    "name:vie_x_preferred":[
        "N\u00fai S\u1eadp"
    ],
    "wof:name":"Nui Sap",
    "wof:placetype":"locality"
},
  "geometry": {"coordinates":[105.26676,10.26478],"type":"Point"}
}