{
  "type": "Feature",
  "properties": {
    "gn:admin1_code":"71.0",
    "gn:asciiname":"Binh Noi",
    "gn:country_code":"VN",
    "gn:dem":16,
    "gn:feature_class":"P",
    "gn:feature_code":"PPL",
    "gn:name":"Binh N\u1ed9i",
    "gn:population":0,
    "gn:timezone":"Asia/Ho_Chi_Minh",
    "iso:country":"VN",
    "name:und_x_variant":[
        "Lang Noi",
        "Binh N\u1ed9i"
    ],
    "wof:name":"Binh Noi",
    "wof:placetype":"locality"
},
  "geometry": {"coordinates":[106.55,21.38333],"type":"Point"}
}