{
  "type": "Feature",
  "properties": {
    "gn:admin1_code":"39.0",
    "gn:asciiname":"Kinh Lan",
    "gn:country_code":"VN",
    "gn:dem":425,
    "gn:feature_class":"P",
    "gn:feature_code":"PPL",
    "gn:name":"Kinh Lan",
    "gn:population":0,
    "gn:timezone":"Asia/Ho_Chi_Minh",
    "iso:country":"VN",
    "wof:name":"Kinh Lan",
    "wof:placetype":"locality"
},
  "geometry": {"coordinates":[106.66667,22.28333],"type":"Point"}
}