{
  "type": "Feature",
  "properties": {
    "gn:admin1_code":"32.0",
    "gn:asciiname":"Nong Nua",
    "gn:country_code":"VN",
    "gn:dem":834,
    "gn:feature_class":"P",
    "gn:feature_code":"PPL",
    "gn:name":"Nong N\u01b0a",
    "gn:population":0,
    "gn:timezone":"Asia/Ho_Chi_Minh",
    "iso:country":"VN",
    "name:vie_x_preferred":[
        "Nong N\u01b0a"
    ],
    "wof:name":"Nong Nua",
    "wof:placetype":"locality"
},
  "geometry": {"coordinates":[103.92283,21.24952],"type":"Point"}
}