{
  "type": "Feature",
  "properties": {
    "gn:admin1_code":"5.0",
    "gn:asciiname":"Khau Lua",
    "gn:country_code":"VN",
    "gn:dem":411,
    "gn:feature_class":"P",
    "gn:feature_code":"PPL",
    "gn:name":"Khau L\u01b0a",
    "gn:population":0,
    "gn:timezone":"Asia/Ho_Chi_Minh",
    "iso:country":"VN",
    "wof:name":"Khau Lua",
    "wof:placetype":"locality"
},
  "geometry": {"coordinates":[106.63333,22.65],"type":"Point"}
}