{
  "type": "Feature",
  "properties": {
    "gn:admin1_code":"70.0",
    "gn:asciiname":"Chieng Cong",
    "gn:country_code":"VN",
    "gn:dem":280,
    "gn:feature_class":"P",
    "gn:feature_code":"PPL",
    "gn:name":"Chi\u00eang C\u00f4ng",
    "gn:population":0,
    "gn:timezone":"Asia/Ho_Chi_Minh",
    "iso:country":"VN",
    "wof:name":"Chieng Cong",
    "wof:placetype":"locality"
},
  "geometry": {"coordinates":[104.51667,21.56667],"type":"Point"}
}