{
  "type": "Feature",
  "properties": {
    "gn:admin1_code":"34.0",
    "gn:asciiname":"Lim Coc",
    "gn:country_code":"VN",
    "gn:dem":145,
    "gn:feature_class":"P",
    "gn:feature_code":"PPL",
    "gn:name":"Lim C\u1ed1c",
    "gn:population":0,
    "gn:timezone":"Asia/Ho_Chi_Minh",
    "iso:country":"VN",
    "wof:name":"Lim Coc",
    "wof:placetype":"locality"
},
  "geometry": {"coordinates":[105.53333000000001,19.46667],"type":"Point"}
}