{
  "type": "Feature",
  "properties": {
    "gn:admin1_code":"67.0",
    "gn:asciiname":"Xom Dua",
    "gn:cc2":"VN",
    "gn:country_code":"VN",
    "gn:dem":1,
    "gn:feature_class":"P",
    "gn:feature_code":"PPL",
    "gn:name":"X\u00f3m D\u1eefa",
    "gn:population":0,
    "gn:timezone":"Asia/Ho_Chi_Minh",
    "iso:country":"VN",
    "name:und_x_variant":[
        "D\u1eefa",
        "X\u00f3m Gi\u01b0a",
        "X\u00f3m D\u1eefa"
    ],
    "wof:name":"Xom Dua",
    "wof:placetype":"locality"
},
  "geometry": {"coordinates":[106.14943999999998,9.85278],"type":"Point"}
}