{
  "type": "Feature",
  "properties": {
    "gn:admin1_code":"68.0",
    "gn:asciiname":"Khanh hoa",
    "gn:country_code":"VN",
    "gn:dem":35,
    "gn:feature_class":"P",
    "gn:feature_code":"PPL",
    "gn:name":"Kh\u00e1nh h\u00f2a",
    "gn:population":0,
    "gn:timezone":"Asia/Ho_Chi_Minh",
    "iso:country":"VN",
    "name:vie_x_preferred":[
        "Kh\u00e1nh h\u00f2a"
    ],
    "wof:name":"Khanh hoa",
    "wof:placetype":"locality"
},
  "geometry": {"coordinates":[105.12703999999999,21.96428],"type":"Point"}
}