{
  "type": "Feature",
  "properties": {
    "gn:admin1_code":"26.0",
    "gn:asciiname":"Lang Trot",
    "gn:country_code":"VN",
    "gn:dem":140,
    "gn:feature_class":"P",
    "gn:feature_code":"PPL",
    "gn:name":"L\u00e0ng Tr\u00f3t",
    "gn:population":0,
    "gn:timezone":"Asia/Ho_Chi_Minh",
    "iso:country":"VN",
    "wof:name":"Lang Trot",
    "wof:placetype":"locality"
},
  "geometry": {"coordinates":[105.41667,19.45],"type":"Point"}
}