{
  "type": "Feature",
  "properties": {
    "gn:admin1_code":"71.0",
    "gn:asciiname":"Xom Cho",
    "gn:country_code":"VN",
    "gn:dem":10,
    "gn:feature_class":"P",
    "gn:feature_code":"PPL",
    "gn:name":"X\u00f3m Ch\u1ee3",
    "gn:population":0,
    "gn:timezone":"Asia/Ho_Chi_Minh",
    "iso:country":"VN",
    "name:vie_x_preferred":[
        "X\u00f3m Ch\u1ee3"
    ],
    "wof:name":"Xom Cho",
    "wof:placetype":"locality"
},
  "geometry": {"coordinates":[106.21983,21.2845],"type":"Point"}
}