{
  "type": "Feature",
  "properties": {
    "gn:admin1_code":"30.0",
    "gn:asciiname":"Thi tran Mao Khe",
    "gn:country_code":"VN",
    "gn:dem":7,
    "gn:feature_class":"P",
    "gn:feature_code":"PPL",
    "gn:name":"Th\u1ecb tr\u1ea5n M\u1ea1o Kh\u00ea",
    "gn:population":0,
    "gn:timezone":"Asia/Ho_Chi_Minh",
    "iso:country":"VN",
    "name:und_x_variant":[
        "M\u1ea1o Kh\u00ea"
    ],
    "name:vie_x_preferred":[
        "Th\u1ecb tr\u1ea5n M\u1ea1o Kh\u00ea"
    ],
    "wof:name":"Thi tran Mao Khe",
    "wof:placetype":"locality"
},
  "geometry": {"coordinates":[106.59255,21.05858],"type":"Point"}
}