{
  "type": "Feature",
  "properties": {
    "gn:admin1_code":"50.0",
    "gn:asciiname":"Ban Nam Xom",
    "gn:country_code":"VN",
    "gn:dem":578,
    "gn:feature_class":"P",
    "gn:feature_code":"PPL",
    "gn:name":"B\u1ea3n N\u1eadm X\u1ecfm",
    "gn:population":0,
    "gn:timezone":"Asia/Ho_Chi_Minh",
    "iso:country":"VN",
    "name:vie_x_preferred":[
        "B\u1ea3n N\u1eadm X\u1ecfm"
    ],
    "wof:name":"Ban Nam Xom",
    "wof:placetype":"locality"
},
  "geometry": {"coordinates":[104.42910000000001,22.62867],"type":"Point"}
}