{
  "type": "Feature",
  "properties": {
    "gn:admin1_code":"33.0",
    "gn:asciiname":"Ap Rung Dan",
    "gn:country_code":"VN",
    "gn:dem":11,
    "gn:feature_class":"P",
    "gn:feature_code":"PPL",
    "gn:name":"\u1ea4p R\u1eebng \u0110an",
    "gn:population":0,
    "gn:timezone":"Asia/Ho_Chi_Minh",
    "iso:country":"VN",
    "name:und_x_variant":[
        "T\u00e2n-L\u00e2p Li\u00ean \u1ea4p R\u00f9ng \u0110an",
        "Xom R\u00f9ng D\u1ea5u",
        "Li\u00ean \u1ea4p R\u00f9ng \u0110an",
        "\u1ea4p R\u1eebng \u0110an"
    ],
    "wof:name":"Ap Rung Dan",
    "wof:placetype":"locality"
},
  "geometry": {"coordinates":[106.15000000000001,11.11667],"type":"Point"}
}