{
  "type": "Feature",
  "properties": {
    "gn:admin1_code":"62.0",
    "gn:asciiname":"Cay Lim",
    "gn:country_code":"VN",
    "gn:dem":61,
    "gn:feature_class":"P",
    "gn:feature_code":"PPL",
    "gn:name":"C\u00e2y Lim",
    "gn:population":0,
    "gn:timezone":"Asia/Ho_Chi_Minh",
    "iso:country":"VN",
    "wof:name":"Cay Lim",
    "wof:placetype":"locality"
},
  "geometry": {"coordinates":[106.28333000000001,17.68332999999999],"type":"Point"}
}