{
  "type": "Feature",
  "properties": {
    "gn:admin1_code":"32.0",
    "gn:asciiname":"To Lang",
    "gn:country_code":"VN",
    "gn:dem":797,
    "gn:feature_class":"P",
    "gn:feature_code":"PPL",
    "gn:name":"To Lang",
    "gn:population":0,
    "gn:timezone":"Asia/Ho_Chi_Minh",
    "iso:country":"VN",
    "wof:name":"To Lang",
    "wof:placetype":"locality"
},
  "geometry": {"coordinates":[104.56667,20.76667],"type":"Point"}
}