{
  "type": "Feature",
  "properties": {
    "gn:admin1_code":"70.0",
    "gn:asciiname":"Thanh Qui",
    "gn:country_code":"VN",
    "gn:dem":1231,
    "gn:feature_class":"P",
    "gn:feature_code":"PPL",
    "gn:name":"Thanh Qu\u00ec",
    "gn:population":0,
    "gn:timezone":"Asia/Ho_Chi_Minh",
    "iso:country":"VN",
    "name:und_x_variant":[
        "Muong Kim",
        "Thanh Qu\u00ec"
    ],
    "wof:name":"Thanh Qui",
    "wof:placetype":"locality"
},
  "geometry": {"coordinates":[104.16667,21.78333],"type":"Point"}
}