{
  "type": "Feature",
  "properties": {
    "gn:admin1_code":"64.0",
    "gn:asciiname":"Thon Ha Xa",
    "gn:country_code":"VN",
    "gn:dem":112,
    "gn:feature_class":"P",
    "gn:feature_code":"PPL",
    "gn:name":"Th\u00f4n H\u00e0 X\u00e1",
    "gn:population":0,
    "gn:timezone":"Asia/Ho_Chi_Minh",
    "iso:country":"VN",
    "name:und_x_variant":[
        "Ha Xa",
        "Th\u00f4n H\u00e0 X\u00e1"
    ],
    "wof:name":"Thon Ha Xa",
    "wof:placetype":"locality"
},
  "geometry": {"coordinates":[106.96666999999999,16.73333],"type":"Point"}
}