{
  "type": "Feature",
  "properties": {
    "gn:admin1_code":"32.0",
    "gn:asciiname":"Lang Ke Re",
    "gn:country_code":"VN",
    "gn:dem":901,
    "gn:feature_class":"P",
    "gn:feature_code":"PPL",
    "gn:name":"L\u00e0ng Ke Re",
    "gn:population":0,
    "gn:timezone":"Asia/Ho_Chi_Minh",
    "iso:country":"VN",
    "wof:name":"Lang Ke Re",
    "wof:placetype":"locality"
},
  "geometry": {"coordinates":[104.45,20.83333],"type":"Point"}
}