{
  "type": "Feature",
  "properties": {
    "gn:admin1_code":"50.0",
    "gn:asciiname":"Lang Kiem",
    "gn:country_code":"VN",
    "gn:dem":343,
    "gn:feature_class":"P",
    "gn:feature_code":"PPL",
    "gn:name":"L\u00e0ng Ki\u00eam",
    "gn:population":0,
    "gn:timezone":"Asia/Ho_Chi_Minh",
    "iso:country":"VN",
    "wof:name":"Lang Kiem",
    "wof:placetype":"locality"
},
  "geometry": {"coordinates":[104.73333,22.28333],"type":"Point"}
}