{
  "type": "Feature",
  "properties": {
    "gn:admin1_code":"83.0",
    "gn:asciiname":"Xom Nuong",
    "gn:country_code":"VN",
    "gn:dem":33,
    "gn:feature_class":"P",
    "gn:feature_code":"PPL",
    "gn:name":"X\u00f3m N\u01b0\u01a1ng",
    "gn:population":0,
    "gn:timezone":"Asia/Ho_Chi_Minh",
    "iso:country":"VN",
    "name:vie_x_preferred":[
        "X\u00f3m N\u01b0\u01a1ng"
    ],
    "wof:name":"Xom Nuong",
    "wof:placetype":"locality"
},
  "geometry": {"coordinates":[105.24535,21.11845],"type":"Point"}
}