{
  "type": "Feature",
  "properties": {
    "gn:admin1_code":"90.0",
    "gn:asciiname":"Chin Chu Lin",
    "gn:country_code":"VN",
    "gn:dem":1530,
    "gn:feature_class":"P",
    "gn:feature_code":"PPL",
    "gn:name":"Chin Ch\u01b0 Lin",
    "gn:population":0,
    "gn:timezone":"Asia/Ho_Chi_Minh",
    "iso:country":"VN",
    "wof:name":"Chin Chu Lin",
    "wof:placetype":"locality"
},
  "geometry": {"coordinates":[103.58333,22.68333],"type":"Point"}
}