{
  "type": "Feature",
  "properties": {
    "gn:admin1_code":"32.0",
    "gn:asciiname":"Suoi Han Mot",
    "gn:country_code":"VN",
    "gn:dem":765,
    "gn:feature_class":"P",
    "gn:feature_code":"PPL",
    "gn:name":"Su\u1ed1i Han M\u1ed9t",
    "gn:population":0,
    "gn:timezone":"Asia/Ho_Chi_Minh",
    "iso:country":"VN",
    "name:vie_x_preferred":[
        "Su\u1ed1i Han M\u1ed9t"
    ],
    "name:vie_x_variant":[
        "Su\u1ed1i Han 1"
    ],
    "wof:name":"Suoi Han Mot",
    "wof:placetype":"locality"
},
  "geometry": {"coordinates":[104.78471,21.2014],"type":"Point"}
}