{
  "type": "Feature",
  "properties": {
    "gn:admin1_code":"1.0",
    "gn:asciiname":"My Hoa",
    "gn:country_code":"VN",
    "gn:dem":1,
    "gn:feature_class":"P",
    "gn:feature_code":"PPL",
    "gn:name":"M\u1ef9 H\u00f2a",
    "gn:population":0,
    "gn:timezone":"Asia/Ho_Chi_Minh",
    "iso:country":"VN",
    "name:vie_x_preferred":[
        "M\u1ef9 H\u00f2a"
    ],
    "wof:name":"My Hoa",
    "wof:placetype":"locality"
},
  "geometry": {"coordinates":[105.38038,10.47235],"type":"Point"}
}