{
  "type": "Feature",
  "properties": {
    "gn:admin1_code":"58.0",
    "gn:asciiname":"Trung Phuong",
    "gn:country_code":"VN",
    "gn:dem":7,
    "gn:feature_class":"P",
    "gn:feature_code":"PPL",
    "gn:name":"Trung Ph\u01b0\u01a1ng",
    "gn:population":0,
    "gn:timezone":"Asia/Ho_Chi_Minh",
    "iso:country":"VN",
    "name:vie_x_preferred":[
        "Trung Ph\u01b0\u01a1ng"
    ],
    "wof:name":"Trung Phuong",
    "wof:placetype":"locality"
},
  "geometry": {"coordinates":[105.52524,18.95567],"type":"Point"}
}