{
  "type": "Feature",
  "properties": {
    "gn:admin1_code":"68.0",
    "gn:asciiname":"Lang Toat",
    "gn:country_code":"VN",
    "gn:dem":429,
    "gn:feature_class":"P",
    "gn:feature_code":"PPL",
    "gn:name":"L\u00e0ng To\u1ea1t",
    "gn:population":0,
    "gn:timezone":"Asia/Ho_Chi_Minh",
    "iso:country":"VN",
    "name:und_x_variant":[
        "L\u00e0ng Tho\u00e1t"
    ],
    "name:vie_x_preferred":[
        "L\u00e0ng To\u1ea1t"
    ],
    "wof:name":"Lang Toat",
    "wof:placetype":"locality"
},
  "geometry": {"coordinates":[105.43158,21.95491],"type":"Point"}
}