{
  "type": "Feature",
  "properties": {
    "gn:admin1_code":"64.0",
    "gn:asciiname":"Lang Tenouo",
    "gn:country_code":"VN",
    "gn:dem":224,
    "gn:feature_class":"P",
    "gn:feature_code":"PPL",
    "gn:name":"L\u00e0ng T\u00e9nouo",
    "gn:population":0,
    "gn:timezone":"Asia/Ho_Chi_Minh",
    "iso:country":"VN",
    "wof:name":"Lang Tenouo",
    "wof:placetype":"locality"
},
  "geometry": {"coordinates":[106.66388999999999,16.49028],"type":"Point"}
}