{
  "type": "Feature",
  "properties": {
    "gn:admin1_code":"90.0",
    "gn:asciiname":"Ban Sin Chai",
    "gn:country_code":"VN",
    "gn:dem":1373,
    "gn:feature_class":"P",
    "gn:feature_code":"PPL",
    "gn:name":"B\u1ea3n S\u00edn Ch\u1ea3i",
    "gn:population":0,
    "gn:timezone":"Asia/Ho_Chi_Minh",
    "iso:country":"VN",
    "name:vie_x_preferred":[
        "B\u1ea3n S\u00edn Ch\u1ea3i"
    ],
    "wof:name":"Ban Sin Chai",
    "wof:placetype":"locality"
},
  "geometry": {"coordinates":[104.29669,22.58776],"type":"Point"}
}