{
  "type": "Feature",
  "properties": {
    "gn:admin1_code":"70.0",
    "gn:asciiname":"Khe Xuan",
    "gn:country_code":"VN",
    "gn:dem":111,
    "gn:feature_class":"P",
    "gn:feature_code":"PPL",
    "gn:name":"Kh\u00ea Xu\u00e2n",
    "gn:population":0,
    "gn:timezone":"Asia/Ho_Chi_Minh",
    "iso:country":"VN",
    "wof:name":"Khe Xuan",
    "wof:placetype":"locality"
},
  "geometry": {"coordinates":[104.55,21.95],"type":"Point"}
}