{
  "type": "Feature",
  "properties": {
    "gn:admin1_code":"58.0",
    "gn:asciiname":"Ban Cha Hia",
    "gn:country_code":"VN",
    "gn:dem":183,
    "gn:feature_class":"P",
    "gn:feature_code":"PPL",
    "gn:name":"B\u1ea3n Ch\u00e0 H\u1ecba",
    "gn:population":0,
    "gn:timezone":"Asia/Ho_Chi_Minh",
    "iso:country":"VN",
    "wof:name":"Ban Cha Hia",
    "wof:placetype":"locality"
},
  "geometry": {"coordinates":[104.81667,19.23333],"type":"Point"}
}