{
  "type": "Feature",
  "properties": {
    "gn:admin1_code":"65.0",
    "gn:asciiname":"Can Gio",
    "gn:country_code":"VN",
    "gn:dem":5,
    "gn:feature_class":"P",
    "gn:feature_code":"PPL",
    "gn:name":"C\u1ea7n Gi\u1edd",
    "gn:population":0,
    "gn:timezone":"Asia/Ho_Chi_Minh",
    "iso:country":"VN",
    "name:vie_x_preferred":[
        "C\u1ea7n Gi\u1edd"
    ],
    "wof:name":"Can Gio",
    "wof:placetype":"locality"
},
  "geometry": {"coordinates":[105.96434000000001,9.54673],"type":"Point"}
}