{
  "type": "Feature",
  "properties": {
    "gn:admin1_code":"83.0",
    "gn:asciiname":"Minh Duc",
    "gn:country_code":"VN",
    "gn:dem":59,
    "gn:feature_class":"P",
    "gn:feature_code":"PPL",
    "gn:name":"Minh \u0110\u1ee9c",
    "gn:population":0,
    "gn:timezone":"Asia/Ho_Chi_Minh",
    "iso:country":"VN",
    "name:vie_x_preferred":[
        "Minh \u0110\u1ee9c"
    ],
    "wof:name":"Minh Duc",
    "wof:placetype":"locality"
},
  "geometry": {"coordinates":[105.12717000000001,21.29067],"type":"Point"}
}