{
  "type": "Feature",
  "properties": {
    "gn:admin1_code":"5.0",
    "gn:asciiname":"Ban Chang",
    "gn:country_code":"VN",
    "gn:dem":543,
    "gn:feature_class":"P",
    "gn:feature_code":"PPL",
    "gn:name":"B\u1ea3n Chang",
    "gn:population":0,
    "gn:timezone":"Asia/Ho_Chi_Minh",
    "iso:country":"VN",
    "name:ceb_x_preferred":[
        "Ban Chang"
    ],
    "wof:name":"Ban Chang",
    "wof:placetype":"locality"
},
  "geometry": {"coordinates":[106.38333,22.66667],"type":"Point"}
}