{
  "type": "Feature",
  "properties": {
    "gn:admin1_code":"71.0",
    "gn:asciiname":"Lang Non",
    "gn:country_code":"VN",
    "gn:dem":69,
    "gn:feature_class":"P",
    "gn:feature_code":"PPL",
    "gn:name":"L\u00e0ng N\u00f2n",
    "gn:population":0,
    "gn:timezone":"Asia/Ho_Chi_Minh",
    "iso:country":"VN",
    "name:und_x_variant":[
        "Lang Nang",
        "An No\u00f3ng",
        "L\u00e0ng Nong",
        "An N\u01b0\u01a1ng"
    ],
    "name:vie_x_preferred":[
        "L\u00e0ng N\u00f2n"
    ],
    "wof:name":"Lang Non",
    "wof:placetype":"locality"
},
  "geometry": {"coordinates":[106.76631999999999,21.21452],"type":"Point"}
}