{
  "type": "Feature",
  "properties": {
    "gn:admin1_code":"70.0",
    "gn:asciiname":"Khe Chung",
    "gn:country_code":"VN",
    "gn:dem":554,
    "gn:feature_class":"P",
    "gn:feature_code":"PPL",
    "gn:name":"Kh\u00ea Chung",
    "gn:population":0,
    "gn:timezone":"Asia/Ho_Chi_Minh",
    "iso:country":"VN",
    "name:vie_x_preferred":[
        "Kh\u00ea Chung"
    ],
    "wof:name":"Khe Chung",
    "wof:placetype":"locality"
},
  "geometry": {"coordinates":[104.73081999999999,21.96776],"type":"Point"}
}