{
  "type": "Feature",
  "properties": {
    "gn:admin1_code":"53.0",
    "gn:asciiname":"Douy Bouy",
    "gn:country_code":"VN",
    "gn:dem":51,
    "gn:feature_class":"P",
    "gn:feature_code":"PPL",
    "gn:name":"Douy Bouy",
    "gn:population":0,
    "gn:timezone":"Asia/Ho_Chi_Minh",
    "iso:country":"VN",
    "wof:name":"Douy Bouy",
    "wof:placetype":"locality"
},
  "geometry": {"coordinates":[105.61667,20.58333],"type":"Point"}
}