{
  "type": "Feature",
  "properties": {
    "gn:admin1_code":"73.0",
    "gn:asciiname":"Ap Muoi Bay",
    "gn:country_code":"VN",
    "gn:dem":0,
    "gn:feature_class":"P",
    "gn:feature_code":"PPL",
    "gn:name":"\u1ea4p M\u01b0\u1eddi B\u1ea3y",
    "gn:population":0,
    "gn:timezone":"Asia/Ho_Chi_Minh",
    "iso:country":"VN",
    "name:vie_x_preferred":[
        "\u1ea4p M\u01b0\u1eddi B\u1ea3y"
    ],
    "name:vie_x_variant":[
        "\u1ea4p 17"
    ],
    "wof:name":"Ap Muoi Bay",
    "wof:placetype":"locality"
},
  "geometry": {"coordinates":[105.54836,9.31454],"type":"Point"}
}