{
  "type": "Feature",
  "properties": {
    "gn:admin1_code":"85.0",
    "gn:asciiname":"Na Nuong",
    "gn:country_code":"VN",
    "gn:dem":134,
    "gn:feature_class":"P",
    "gn:feature_code":"PPL",
    "gn:name":"Na N\u01b0\u01a1ng",
    "gn:population":0,
    "gn:timezone":"Asia/Ho_Chi_Minh",
    "iso:country":"VN",
    "name:vie_x_preferred":[
        "Na N\u01b0\u01a1ng"
    ],
    "wof:name":"Na Nuong",
    "wof:placetype":"locality"
},
  "geometry": {"coordinates":[105.57677,21.63387],"type":"Point"}
}