{
  "type": "Feature",
  "properties": {
    "gn:admin1_code":"58.0",
    "gn:asciiname":"Xom Tam",
    "gn:country_code":"VN",
    "gn:dem":29,
    "gn:feature_class":"P",
    "gn:feature_code":"PPL",
    "gn:name":"X\u00f3m T\u00e1m",
    "gn:population":0,
    "gn:timezone":"Asia/Ho_Chi_Minh",
    "iso:country":"VN",
    "name:vie_x_preferred":[
        "X\u00f3m T\u00e1m"
    ],
    "name:vie_x_variant":[
        "X\u00f3m 8"
    ],
    "wof:name":"Xom Tam",
    "wof:placetype":"locality"
},
  "geometry": {"coordinates":[105.28691000000001,18.97143],"type":"Point"}
}