{
  "type": "Feature",
  "properties": {
    "gn:admin1_code":"50.0",
    "gn:asciiname":"Nam Nic",
    "gn:country_code":"VN",
    "gn:dem":1127,
    "gn:feature_class":"P",
    "gn:feature_code":"PPL",
    "gn:name":"Nam Nic",
    "gn:population":0,
    "gn:timezone":"Asia/Ho_Chi_Minh",
    "iso:country":"VN",
    "wof:name":"Nam Nic",
    "wof:placetype":"locality"
},
  "geometry": {"coordinates":[104.78333000000001,22.88333],"type":"Point"}
}