{
  "type": "Feature",
  "properties": {
    "gn:admin1_code":"74.0",
    "gn:asciiname":"Thon Den",
    "gn:country_code":"VN",
    "gn:dem":11,
    "gn:feature_class":"P",
    "gn:feature_code":"PPL",
    "gn:name":"Th\u00f4n D\u1ec1n",
    "gn:population":0,
    "gn:timezone":"Asia/Ho_Chi_Minh",
    "iso:country":"VN",
    "name:vie_x_preferred":[
        "Th\u00f4n D\u1ec1n"
    ],
    "wof:name":"Thon Den",
    "wof:placetype":"locality"
},
  "geometry": {"coordinates":[106.0291,21.07637],"type":"Point"}
}