{
  "type": "Feature",
  "properties": {
    "gn:admin1_code":"67.0",
    "gn:asciiname":"Ap Ngai Thuan",
    "gn:cc2":"VN",
    "gn:country_code":"VN",
    "gn:dem":2,
    "gn:feature_class":"P",
    "gn:feature_code":"PPL",
    "gn:name":"\u1ea4p Ng\u00e3i Thu\u1eadn",
    "gn:population":0,
    "gn:timezone":"Asia/Ho_Chi_Minh",
    "iso:country":"VN",
    "name:und_x_variant":[
        "Ng\u00e3i Thu\u1eadn",
        "\u1ea4p Ng\u00e3i Thu\u1eadn"
    ],
    "wof:name":"Ap Ngai Thuan",
    "wof:placetype":"locality"
},
  "geometry": {"coordinates":[106.24611000000002,9.79222],"type":"Point"}
}