{
  "type": "Feature",
  "properties": {
    "gn:admin1_code":"16.0",
    "gn:asciiname":"Yen Ve",
    "gn:country_code":"VN",
    "gn:dem":41,
    "gn:feature_class":"P",
    "gn:feature_code":"PPL",
    "gn:name":"Y\u00ean V\u1ec7",
    "gn:population":0,
    "gn:timezone":"Asia/Ho_Chi_Minh",
    "iso:country":"VN",
    "wof:name":"Yen Ve",
    "wof:placetype":"locality"
},
  "geometry": {"coordinates":[105.75,20.38333],"type":"Point"}
}