{
  "type": "Feature",
  "properties": {
    "gn:admin1_code":"50.0",
    "gn:asciiname":"Man Phung",
    "gn:country_code":"VN",
    "gn:dem":933,
    "gn:feature_class":"P",
    "gn:feature_code":"PPL",
    "gn:name":"Man Phung",
    "gn:population":0,
    "gn:timezone":"Asia/Ho_Chi_Minh",
    "iso:country":"VN",
    "wof:name":"Man Phung",
    "wof:placetype":"locality"
},
  "geometry": {"coordinates":[104.58333,22.78333],"type":"Point"}
}