{
  "type": "Feature",
  "properties": {
    "gn:admin1_code":"53.0",
    "gn:asciiname":"Ban Tao",
    "gn:country_code":"VN",
    "gn:dem":615,
    "gn:feature_class":"P",
    "gn:feature_code":"PPL",
    "gn:name":"B\u1ea3n Tao",
    "gn:population":0,
    "gn:timezone":"Asia/Ho_Chi_Minh",
    "iso:country":"VN",
    "wof:name":"Ban Tao",
    "wof:placetype":"locality"
},
  "geometry": {"coordinates":[105.09999999999999,20.68333],"type":"Point"}
}