{
  "type": "Feature",
  "properties": {
    "gn:admin1_code":"89.0",
    "gn:asciiname":"Ban Na Khuong",
    "gn:country_code":"VN",
    "gn:dem":556,
    "gn:feature_class":"P",
    "gn:feature_code":"PPL",
    "gn:name":"B\u1ea3n N\u00e0 Kh\u01b0\u01a1ng",
    "gn:population":0,
    "gn:timezone":"Asia/Ho_Chi_Minh",
    "iso:country":"VN",
    "name:und_x_variant":[
        "Na Ku\u00f4ng"
    ],
    "name:vie_x_preferred":[
        "B\u1ea3n N\u00e0 Kh\u01b0\u01a1ng"
    ],
    "wof:name":"Ban Na Khuong",
    "wof:placetype":"locality"
},
  "geometry": {"coordinates":[103.67552999999999,22.23697],"type":"Point"}
}