{
  "type": "Feature",
  "properties": {
    "gn:admin1_code":"72.0",
    "gn:asciiname":"Na Moi",
    "gn:country_code":"VN",
    "gn:dem":173,
    "gn:feature_class":"P",
    "gn:feature_code":"PPL",
    "gn:name":"N\u00e0 M\u1edbi",
    "gn:population":0,
    "gn:timezone":"Asia/Ho_Chi_Minh",
    "iso:country":"VN",
    "wof:name":"Na Moi",
    "wof:placetype":"locality"
},
  "geometry": {"coordinates":[105.8734,22.25357],"type":"Point"}
}