{
  "type": "Feature",
  "properties": {
    "gn:admin1_code":"90.0",
    "gn:asciiname":"Nam Tieu",
    "gn:country_code":"VN",
    "gn:dem":139,
    "gn:feature_class":"P",
    "gn:feature_code":"PPL",
    "gn:name":"Nam Tieu",
    "gn:population":0,
    "gn:timezone":"Asia/Ho_Chi_Minh",
    "iso:country":"VN",
    "name:und_x_variant":[
        "Nun Nam Tieu",
        "Nam Tieu"
    ],
    "wof:name":"Nam Tieu",
    "wof:placetype":"locality"
},
  "geometry": {"coordinates":[104.06667,22.51667],"type":"Point"}
}