{
  "type": "Feature",
  "properties": {
    "gn:admin1_code":"71.0",
    "gn:asciiname":"Cau Dam",
    "gn:country_code":"VN",
    "gn:dem":12,
    "gn:feature_class":"P",
    "gn:feature_code":"PPL",
    "gn:name":"C\u1ea7u \u0110\u1ea7m",
    "gn:population":0,
    "gn:timezone":"Asia/Ho_Chi_Minh",
    "iso:country":"VN",
    "name:vie_x_preferred":[
        "C\u1ea7u \u0110\u1ea7m"
    ],
    "wof:name":"Cau Dam",
    "wof:placetype":"locality"
},
  "geometry": {"coordinates":[106.19121,21.379],"type":"Point"}
}