{
  "type": "Feature",
  "properties": {
    "gn:admin1_code":"50.0",
    "gn:asciiname":"Coc Pang",
    "gn:country_code":"VN",
    "gn:dem":527,
    "gn:feature_class":"P",
    "gn:feature_code":"PPL",
    "gn:name":"C\u1ed1c P\u00e0ng",
    "gn:population":0,
    "gn:timezone":"Asia/Ho_Chi_Minh",
    "iso:country":"VN",
    "name:vie_x_preferred":[
        "C\u1ed1c P\u00e0ng"
    ],
    "wof:name":"Coc Pang",
    "wof:placetype":"locality"
},
  "geometry": {"coordinates":[105.22606,22.92252],"type":"Point"}
}