{
  "type": "Feature",
  "properties": {
    "gn:admin1_code":"92.0",
    "gn:asciiname":"Na Xam",
    "gn:country_code":"VN",
    "gn:dem":580,
    "gn:feature_class":"P",
    "gn:feature_code":"PPL",
    "gn:name":"Na Xam",
    "gn:population":0,
    "gn:timezone":"Asia/Ho_Chi_Minh",
    "iso:country":"VN",
    "wof:name":"Na Xam",
    "wof:placetype":"locality"
},
  "geometry": {"coordinates":[103.08333,21.68333],"type":"Point"}
}