{
  "type": "Feature",
  "properties": {
    "gn:admin1_code":"77.0",
    "gn:asciiname":"Ap Hoa Tach",
    "gn:cc2":"VN",
    "gn:country_code":"VN",
    "gn:dem":0,
    "gn:feature_class":"P",
    "gn:feature_code":"PPL",
    "gn:name":"\u1ea4p H\u00f3a T\u00e1ch",
    "gn:population":0,
    "gn:timezone":"Asia/Ho_Chi_Minh",
    "iso:country":"VN",
    "name:und_x_variant":[
        "H\u00f3a T\u00e1ch",
        "Ap Hoa Thanh",
        "\u1ea4p H\u00f3a T\u00e1ch"
    ],
    "wof:name":"Ap Hoa Tach",
    "wof:placetype":"locality"
},
  "geometry": {"coordinates":[105.15139000000001,9.10333],"type":"Point"}
}