{
  "type": "Feature",
  "properties": {
    "gn:admin1_code":"53.0",
    "gn:asciiname":"Na De",
    "gn:country_code":"VN",
    "gn:dem":433,
    "gn:feature_class":"P",
    "gn:feature_code":"PPL",
    "gn:name":"Na \u0110\u00ea",
    "gn:population":0,
    "gn:timezone":"Asia/Ho_Chi_Minh",
    "iso:country":"VN",
    "wof:name":"Na De",
    "wof:placetype":"locality"
},
  "geometry": {"coordinates":[105.21666999999999,20.86667000000001],"type":"Point"}
}