{
  "type": "Feature",
  "properties": {
    "gn:admin1_code":"43.0",
    "gn:asciiname":"Quan Keang",
    "gn:country_code":"VN",
    "gn:dem":222,
    "gn:feature_class":"P",
    "gn:feature_code":"PPL",
    "gn:name":"Quan Keang",
    "gn:population":0,
    "gn:timezone":"Asia/Ho_Chi_Minh",
    "iso:country":"VN",
    "name:und_x_variant":[
        "Quan Keong",
        "Quan Keang"
    ],
    "wof:name":"Quan Keang",
    "wof:placetype":"locality"
},
  "geometry": {"coordinates":[107.34999999999999,11.35],"type":"Point"}
}