{
  "type": "Feature",
  "properties": {
    "gn:admin1_code":"83.0",
    "gn:asciiname":"Nhuong Bo",
    "gn:country_code":"VN",
    "gn:dem":16,
    "gn:feature_class":"P",
    "gn:feature_code":"PPL",
    "gn:name":"Nh\u01b0\u01a1ng Bo",
    "gn:population":0,
    "gn:timezone":"Asia/Ho_Chi_Minh",
    "iso:country":"VN",
    "name:vie_x_preferred":[
        "Nh\u01b0\u01a1ng Bo"
    ],
    "wof:name":"Nhuong Bo",
    "wof:placetype":"locality"
},
  "geometry": {"coordinates":[105.37633,21.38109],"type":"Point"}
}