{
  "type": "Feature",
  "properties": {
    "gn:admin1_code":"64.0",
    "gn:asciiname":"Thon Nhan Bieu",
    "gn:country_code":"VN",
    "gn:dem":2,
    "gn:feature_class":"P",
    "gn:feature_code":"PPL",
    "gn:name":"Th\u00f4n Nhan Bi\u1ec1u",
    "gn:population":0,
    "gn:timezone":"Asia/Ho_Chi_Minh",
    "iso:country":"VN",
    "name:und_x_variant":[
        "Nhan Bieu",
        "Th\u00f4n Nhan Bi\u1ec1u"
    ],
    "wof:name":"Thon Nhan Bieu",
    "wof:placetype":"locality"
},
  "geometry": {"coordinates":[107.18333,16.75],"type":"Point"}
}