{
  "type": "Feature",
  "properties": {
    "gn:admin1_code":"75.0",
    "gn:asciiname":"Suoi Dia",
    "gn:country_code":"VN",
    "gn:dem":55,
    "gn:feature_class":"P",
    "gn:feature_code":"PPL",
    "gn:name":"Suoi Dia",
    "gn:population":0,
    "gn:timezone":"Asia/Ho_Chi_Minh",
    "iso:country":"VN",
    "name:und_x_variant":[
        "X\u00f3m Su\u1ed1i \u0110\u1ec9a"
    ],
    "wof:name":"Suoi Dia",
    "wof:placetype":"locality"
},
  "geometry": {"coordinates":[106.81667,11.16667],"type":"Point"}
}