{
  "type": "Feature",
  "properties": {
    "gn:admin1_code":"49.0",
    "gn:asciiname":"De Groi",
    "gn:country_code":"VN",
    "gn:dem":646,
    "gn:feature_class":"P",
    "gn:feature_code":"PPL",
    "gn:name":"De Groi",
    "gn:population":0,
    "gn:timezone":"Asia/Ho_Chi_Minh",
    "iso:country":"VN",
    "name:und_x_variant":[
        "De Krouk",
        "De Groi"
    ],
    "wof:name":"De Groi",
    "wof:placetype":"locality"
},
  "geometry": {"coordinates":[108.25,13.88333],"type":"Point"}
}