{
  "type": "Feature",
  "properties": {
    "gn:admin1_code":"52.0",
    "gn:asciiname":"Giap Trong",
    "gn:country_code":"VN",
    "gn:dem":117,
    "gn:feature_class":"P",
    "gn:feature_code":"PPL",
    "gn:name":"Gi\u00e1p Trong",
    "gn:population":0,
    "gn:timezone":"Asia/Ho_Chi_Minh",
    "iso:country":"VN",
    "name:und_x_variant":[
        "Gia Phou Trong",
        "Gi\u00e1p Trong"
    ],
    "wof:name":"Giap Trong",
    "wof:placetype":"locality"
},
  "geometry": {"coordinates":[106.16667,18.06667],"type":"Point"}
}