{
  "type": "Feature",
  "properties": {
    "gn:admin1_code":"72.0",
    "gn:asciiname":"Tan Minh",
    "gn:country_code":"VN",
    "gn:dem":137,
    "gn:feature_class":"P",
    "gn:feature_code":"PPL",
    "gn:name":"T\u00e2n Minh",
    "gn:population":0,
    "gn:timezone":"Asia/Ho_Chi_Minh",
    "iso:country":"VN",
    "name:vie_x_preferred":[
        "T\u00e2n Minh"
    ],
    "wof:name":"Tan Minh",
    "wof:placetype":"locality"
},
  "geometry": {"coordinates":[105.81823,22.02204],"type":"Point"}
}