{
  "type": "Feature",
  "properties": {
    "gn:admin1_code":"34.0",
    "gn:asciiname":"Boi Trach",
    "gn:cc2":"VN",
    "gn:country_code":"VN",
    "gn:dem":13,
    "gn:feature_class":"P",
    "gn:feature_code":"PPL",
    "gn:name":"Boi Trach",
    "gn:population":0,
    "gn:timezone":"Asia/Ho_Chi_Minh",
    "iso:country":"VN",
    "name:und_x_variant":[
        "Ban Thach",
        "Boi Trach"
    ],
    "wof:name":"Boi Trach",
    "wof:placetype":"locality"
},
  "geometry": {"coordinates":[105.53333000000001,19.91667],"type":"Point"}
}