{
  "type": "Feature",
  "properties": {
    "gn:admin1_code":"83.0",
    "gn:asciiname":"Minh Kha",
    "gn:country_code":"VN",
    "gn:dem":105,
    "gn:feature_class":"P",
    "gn:feature_code":"PPL",
    "gn:name":"Minh Kha",
    "gn:population":0,
    "gn:timezone":"Asia/Ho_Chi_Minh",
    "iso:country":"VN",
    "wof:name":"Minh Kha",
    "wof:placetype":"locality"
},
  "geometry": {"coordinates":[105.18333,21.55],"type":"Point"}
}