{
  "type": "Feature",
  "properties": {
    "gn:admin1_code":"4.0",
    "gn:asciiname":"Thon My Hoa",
    "gn:cc2":"VN",
    "gn:country_code":"VN",
    "gn:dem":-9999,
    "gn:feature_class":"P",
    "gn:feature_code":"PPL",
    "gn:name":"Th\u00f4n M\u1ef9 H\u00f2a",
    "gn:population":0,
    "gn:timezone":"Asia/Ho_Chi_Minh",
    "iso:country":"VN",
    "name:und_x_variant":[
        "M\u1ef9 H\u00f2a",
        "Th\u00f4n M\u1ef9 H\u00f2a"
    ],
    "wof:name":"Thon My Hoa",
    "wof:placetype":"locality"
},
  "geometry": {"coordinates":[107.45,16.78333],"type":"Point"}
}