{
  "type": "Feature",
  "properties": {
    "gn:admin1_code":"92.0",
    "gn:asciiname":"Nam Tin Ba",
    "gn:country_code":"VN",
    "gn:dem":998,
    "gn:feature_class":"P",
    "gn:feature_code":"PPL",
    "gn:name":"N\u1eadm Tin Ba",
    "gn:population":0,
    "gn:timezone":"Asia/Ho_Chi_Minh",
    "iso:country":"VN",
    "name:vie_x_preferred":[
        "N\u1eadm Tin Ba"
    ],
    "name:vie_x_variant":[
        "N\u1eadm Tin 3"
    ],
    "wof:name":"Nam Tin Ba",
    "wof:placetype":"locality"
},
  "geometry": {"coordinates":[102.79653999999999,21.88726],"type":"Point"}
}