{
  "type": "Feature",
  "properties": {
    "gn:admin1_code":"20.0",
    "gn:asciiname":"Cho Cu",
    "gn:country_code":"VN",
    "gn:dem":22,
    "gn:feature_class":"P",
    "gn:feature_code":"PPL",
    "gn:name":"Ch\u1ee3 C\u0169",
    "gn:population":0,
    "gn:timezone":"Asia/Ho_Chi_Minh",
    "iso:country":"VN",
    "name:vie_x_preferred":[
        "Ch\u1ee3 C\u0169"
    ],
    "wof:name":"Cho Cu",
    "wof:placetype":"locality"
},
  "geometry": {"coordinates":[106.51416999999999,11.08871],"type":"Point"}
}