{
  "type": "Feature",
  "properties": {
    "gn:admin1_code":"20.0",
    "gn:asciiname":"Binh Hung",
    "gn:country_code":"VN",
    "gn:dem":2,
    "gn:feature_class":"P",
    "gn:feature_code":"PPL",
    "gn:name":"B\u00ecnh H\u01b0ng",
    "gn:population":0,
    "gn:timezone":"Asia/Ho_Chi_Minh",
    "iso:country":"VN",
    "wof:name":"Binh Hung",
    "wof:placetype":"locality"
},
  "geometry": {"coordinates":[106.65722,10.72167],"type":"Point"}
}