{
  "type": "Feature",
  "properties": {
    "gn:admin1_code":"39.0",
    "gn:asciiname":"Ban Tich",
    "gn:country_code":"VN",
    "gn:dem":196,
    "gn:feature_class":"P",
    "gn:feature_code":"PPL",
    "gn:name":"B\u1ea3n T\u00edch",
    "gn:population":0,
    "gn:timezone":"Asia/Ho_Chi_Minh",
    "iso:country":"VN",
    "name:und_x_variant":[
        "B\u1ea3n T\u00edch",
        "B\u1ea3n Tich"
    ],
    "wof:name":"Ban Tich",
    "wof:placetype":"locality"
},
  "geometry": {"coordinates":[106.61659,22.05993],"type":"Point"}
}