{
  "type": "Feature",
  "properties": {
    "gn:admin1_code":"72.0",
    "gn:asciiname":"Khuoi Man",
    "gn:country_code":"VN",
    "gn:dem":239,
    "gn:feature_class":"P",
    "gn:feature_code":"PPL",
    "gn:name":"Khu\u1ed5i M\u1ea3n",
    "gn:population":0,
    "gn:timezone":"Asia/Ho_Chi_Minh",
    "iso:country":"VN",
    "wof:name":"Khuoi Man",
    "wof:placetype":"locality"
},
  "geometry": {"coordinates":[105.85961,22.42994],"type":"Point"}
}