{
  "type": "Feature",
  "properties": {
    "gn:admin1_code":"70.0",
    "gn:asciiname":"Lo Mou Kong",
    "gn:country_code":"VN",
    "gn:dem":1231,
    "gn:feature_class":"P",
    "gn:feature_code":"PPL",
    "gn:name":"Lo Mou Kong",
    "gn:population":0,
    "gn:timezone":"Asia/Ho_Chi_Minh",
    "iso:country":"VN",
    "wof:name":"Lo Mou Kong",
    "wof:placetype":"locality"
},
  "geometry": {"coordinates":[104.18333,21.75],"type":"Point"}
}