{
  "type": "Feature",
  "properties": {
    "gn:admin1_code":"84.0",
    "gn:asciiname":"Phu Bao",
    "gn:country_code":"VN",
    "gn:dem":381,
    "gn:feature_class":"P",
    "gn:feature_code":"PPL",
    "gn:name":"Ph\u00f9 Bao",
    "gn:population":0,
    "gn:timezone":"Asia/Ho_Chi_Minh",
    "iso:country":"VN",
    "wof:name":"Phu Bao",
    "wof:placetype":"locality"
},
  "geometry": {"coordinates":[107.90000000000001,15.95],"type":"Point"}
}