{
  "type": "Feature",
  "properties": {
    "gn:admin1_code":"39.0",
    "gn:asciiname":"Khe Luong",
    "gn:country_code":"VN",
    "gn:dem":371,
    "gn:feature_class":"P",
    "gn:feature_code":"PPL",
    "gn:name":"Khe Lu\u1ed3ng",
    "gn:population":0,
    "gn:timezone":"Asia/Ho_Chi_Minh",
    "iso:country":"VN",
    "name:vie_x_preferred":[
        "Khe Lu\u1ed3ng"
    ],
    "wof:name":"Khe Luong",
    "wof:placetype":"locality"
},
  "geometry": {"coordinates":[107.17764,21.51354],"type":"Point"}
}