{
  "type": "Feature",
  "properties": {
    "gn:admin1_code":"32.0",
    "gn:asciiname":"Na Nghiu",
    "gn:country_code":"VN",
    "gn:dem":786,
    "gn:feature_class":"P",
    "gn:feature_code":"PPL",
    "gn:name":"Na Ngh\u1ecbu",
    "gn:population":0,
    "gn:timezone":"Asia/Ho_Chi_Minh",
    "iso:country":"VN",
    "wof:name":"Na Nghiu",
    "wof:placetype":"locality"
},
  "geometry": {"coordinates":[103.96666999999999,21.18333],"type":"Point"}
}