{
  "type": "Feature",
  "properties": {
    "gn:admin1_code":"88.0",
    "gn:asciiname":"Buon Hoai",
    "gn:country_code":"VN",
    "gn:dem":571,
    "gn:feature_class":"P",
    "gn:feature_code":"PPL",
    "gn:name":"Bu\u00f4n Hoai",
    "gn:population":0,
    "gn:timezone":"Asia/Ho_Chi_Minh",
    "iso:country":"VN",
    "name:vie_x_preferred":[
        "Bu\u00f4n Hoai"
    ],
    "wof:name":"Buon Hoai",
    "wof:placetype":"locality"
},
  "geometry": {"coordinates":[108.25941,13.25362],"type":"Point"}
}