{
  "type": "Feature",
  "properties": {
    "gn:admin1_code":"73.0",
    "gn:asciiname":"Xom Hao Cao",
    "gn:country_code":"VN",
    "gn:dem":5,
    "gn:feature_class":"P",
    "gn:feature_code":"PPL",
    "gn:name":"X\u00f3m H\u00e0o C\u00e1o",
    "gn:population":0,
    "gn:timezone":"Asia/Ho_Chi_Minh",
    "iso:country":"VN",
    "wof:name":"Xom Hao Cao",
    "wof:placetype":"locality"
},
  "geometry": {"coordinates":[105.55249999999999,9.44139],"type":"Point"}
}