{
  "type": "Feature",
  "properties": {
    "gn:admin1_code":"63.0",
    "gn:asciiname":"Lam Thuong",
    "gn:country_code":"VN",
    "gn:dem":20,
    "gn:feature_class":"P",
    "gn:feature_code":"PPL",
    "gn:name":"L\u00e2m Th\u01b0\u01a1ng",
    "gn:population":0,
    "gn:timezone":"Asia/Ho_Chi_Minh",
    "iso:country":"VN",
    "name:und_x_variant":[
        "Quat Lam",
        "L\u00e2m Th\u01b0\u01a1ng"
    ],
    "wof:name":"Lam Thuong",
    "wof:placetype":"locality"
},
  "geometry": {"coordinates":[108.91667,14.95],"type":"Point"}
}