{
  "type": "Feature",
  "properties": {
    "gn:admin1_code":"53.0",
    "gn:asciiname":"Xom Tam",
    "gn:country_code":"VN",
    "gn:dem":581,
    "gn:feature_class":"P",
    "gn:feature_code":"PPL",
    "gn:name":"X\u00f3m T\u1ea7m",
    "gn:population":0,
    "gn:timezone":"Asia/Ho_Chi_Minh",
    "iso:country":"VN",
    "name:vie_x_preferred":[
        "X\u00f3m T\u1ea7m"
    ],
    "wof:name":"Xom Tam",
    "wof:placetype":"locality"
},
  "geometry": {"coordinates":[105.09232,20.8761],"type":"Point"}
}