{
  "type": "Feature",
  "properties": {
    "gn:admin1_code":"70.0",
    "gn:asciiname":"Lang Ray",
    "gn:country_code":"VN",
    "gn:dem":69,
    "gn:feature_class":"P",
    "gn:feature_code":"PPL",
    "gn:name":"L\u00e0ng R\u1ea9y",
    "gn:population":0,
    "gn:timezone":"Asia/Ho_Chi_Minh",
    "iso:country":"VN",
    "name:und_x_variant":[
        "L\u00e0ng Gi\u1eaby"
    ],
    "name:vie_x_preferred":[
        "L\u00e0ng R\u1ea9y"
    ],
    "wof:name":"Lang Ray",
    "wof:placetype":"locality"
},
  "geometry": {"coordinates":[104.97501,21.96209],"type":"Point"}
}