{
  "type": "Feature",
  "properties": {
    "gn:admin1_code":"75.0",
    "gn:asciiname":"Ben Tram",
    "gn:country_code":"VN",
    "gn:dem":59,
    "gn:feature_class":"P",
    "gn:feature_code":"PPL",
    "gn:name":"B\u1ebfn Tr\u00e1m",
    "gn:population":0,
    "gn:timezone":"Asia/Ho_Chi_Minh",
    "iso:country":"VN",
    "name:vie_x_preferred":[
        "B\u1ebfn Tr\u00e1m"
    ],
    "wof:name":"Ben Tram",
    "wof:placetype":"locality"
},
  "geometry": {"coordinates":[106.81959999999999,11.20831],"type":"Point"}
}