{
  "type": "Feature",
  "properties": {
    "gn:admin1_code":"71.0",
    "gn:asciiname":"Xom Quat",
    "gn:country_code":"VN",
    "gn:dem":8,
    "gn:feature_class":"P",
    "gn:feature_code":"PPL",
    "gn:name":"X\u00f3m Qu\u1ea5t",
    "gn:population":0,
    "gn:timezone":"Asia/Ho_Chi_Minh",
    "iso:country":"VN",
    "name:vie_x_preferred":[
        "X\u00f3m Qu\u1ea5t"
    ],
    "wof:name":"Xom Quat",
    "wof:placetype":"locality"
},
  "geometry": {"coordinates":[106.15531,21.38495],"type":"Point"}
}