{
  "type": "Feature",
  "properties": {
    "gn:admin1_code":"30.0",
    "gn:asciiname":"Trang Y",
    "gn:cc2":"VN",
    "gn:country_code":"VN",
    "gn:dem":16,
    "gn:feature_class":"P",
    "gn:feature_code":"PPL",
    "gn:name":"Trang Y",
    "gn:population":0,
    "gn:timezone":"Asia/Ho_Chi_Minh",
    "iso:country":"VN",
    "name:und_x_variant":[
        "Trang Yot",
        "Trang Y"
    ],
    "wof:name":"Trang Y",
    "wof:placetype":"locality"
},
  "geometry": {"coordinates":[107.58333,21.33333],"type":"Point"}
}