{
  "type": "Feature",
  "properties": {
    "gn:admin1_code":"87.0",
    "gn:asciiname":"Thoi Hiep Hai",
    "gn:country_code":"VN",
    "gn:dem":3,
    "gn:feature_class":"P",
    "gn:feature_code":"PPL",
    "gn:name":"Th\u1edbi Hi\u1ec7p Hai",
    "gn:population":0,
    "gn:timezone":"Asia/Ho_Chi_Minh",
    "iso:country":"VN",
    "name:vie_x_preferred":[
        "Th\u1edbi Hi\u1ec7p Hai"
    ],
    "name:vie_x_variant":[
        "Th\u1edbi Hi\u1ec7p 2"
    ],
    "wof:name":"Thoi Hiep Hai",
    "wof:placetype":"locality"
},
  "geometry": {"coordinates":[105.45784999999999,10.08888],"type":"Point"}
}