{
  "type": "Feature",
  "properties": {
    "gn:admin1_code":"32.0",
    "gn:asciiname":"Co Dua",
    "gn:country_code":"VN",
    "gn:dem":301,
    "gn:feature_class":"P",
    "gn:feature_code":"PPL",
    "gn:name":"Co \u0110\u1ee9a",
    "gn:population":0,
    "gn:timezone":"Asia/Ho_Chi_Minh",
    "iso:country":"VN",
    "wof:name":"Co Dua",
    "wof:placetype":"locality"
},
  "geometry": {"coordinates":[103.81667,21.55],"type":"Point"}
}