{
  "type": "Feature",
  "properties": {
    "gn:admin1_code":"83.0",
    "gn:asciiname":"Ga Tre",
    "gn:country_code":"VN",
    "gn:dem":170,
    "gn:feature_class":"P",
    "gn:feature_code":"PPL",
    "gn:name":"G\u00e0 Tre",
    "gn:population":0,
    "gn:timezone":"Asia/Ho_Chi_Minh",
    "iso:country":"VN",
    "name:vie_x_preferred":[
        "G\u00e0 Tre"
    ],
    "wof:name":"Ga Tre",
    "wof:placetype":"locality"
},
  "geometry": {"coordinates":[105.19710000000001,21.11904],"type":"Point"}
}