{
  "type": "Feature",
  "properties": {
    "gn:admin1_code":"1.0",
    "gn:asciiname":"Nhon Loi",
    "gn:country_code":"VN",
    "gn:dem":10,
    "gn:feature_class":"P",
    "gn:feature_code":"PPL",
    "gn:name":"Nh\u01a1n L\u1ed9i",
    "gn:population":0,
    "gn:timezone":"Asia/Ho_Chi_Minh",
    "iso:country":"VN",
    "name:und_x_variant":[
        "\u1ea4p Nh\u01a1n L\u1ed9i"
    ],
    "name:vie_x_preferred":[
        "Nh\u01a1n L\u1ed9i"
    ],
    "wof:name":"Nhon Loi",
    "wof:placetype":"locality"
},
  "geometry": {"coordinates":[105.41204999999999,10.45982],"type":"Point"}
}