{
  "type": "Feature",
  "properties": {
    "gn:admin1_code":"64.0",
    "gn:asciiname":"Ba Thach",
    "gn:country_code":"VN",
    "gn:dem":30,
    "gn:feature_class":"P",
    "gn:feature_code":"PPL",
    "gn:name":"Ba Th\u1ea1ch",
    "gn:population":0,
    "gn:timezone":"Asia/Ho_Chi_Minh",
    "iso:country":"VN",
    "name:vie_x_preferred":[
        "Ba Th\u1ea1ch"
    ],
    "wof:name":"Ba Thach",
    "wof:placetype":"locality"
},
  "geometry": {"coordinates":[107.10769000000001,17.04469],"type":"Point"}
}