{
  "type": "Feature",
  "properties": {
    "gn:admin1_code":"65.0",
    "gn:asciiname":"Hoa Loc",
    "gn:country_code":"VN",
    "gn:dem":4,
    "gn:feature_class":"P",
    "gn:feature_code":"PPL",
    "gn:name":"H\u00f2a L\u1ed9c",
    "gn:population":0,
    "gn:timezone":"Asia/Ho_Chi_Minh",
    "iso:country":"VN",
    "name:und_x_variant":[
        "\u1ea4p H\u00f2a L\u1ed9c"
    ],
    "name:vie_x_preferred":[
        "H\u00f2a L\u1ed9c"
    ],
    "wof:name":"Hoa Loc",
    "wof:placetype":"locality"
},
  "geometry": {"coordinates":[105.87220000000001,9.86042],"type":"Point"}
}