{
  "type": "Feature",
  "properties": {
    "gn:admin1_code":"50.0",
    "gn:asciiname":"Ban Nam Am",
    "gn:country_code":"VN",
    "gn:dem":550,
    "gn:feature_class":"P",
    "gn:feature_code":"PPL",
    "gn:name":"B\u1ea3n N\u1eb1m \u1ea4m",
    "gn:population":0,
    "gn:timezone":"Asia/Ho_Chi_Minh",
    "iso:country":"VN",
    "name:vie_x_preferred":[
        "B\u1ea3n N\u1eb1m \u1ea4m"
    ],
    "wof:name":"Ban Nam Am",
    "wof:placetype":"locality"
},
  "geometry": {"coordinates":[105.45865000000001,22.7104],"type":"Point"}
}