{
  "type": "Feature",
  "properties": {
    "gn:admin1_code":"50.0",
    "gn:asciiname":"Ban Ve",
    "gn:country_code":"VN",
    "gn:dem":871,
    "gn:feature_class":"P",
    "gn:feature_code":"PPL",
    "gn:name":"B\u1ea3n V\u1ebd",
    "gn:population":0,
    "gn:timezone":"Asia/Ho_Chi_Minh",
    "iso:country":"VN",
    "name:vie_x_preferred":[
        "B\u1ea3n V\u1ebd"
    ],
    "wof:name":"Ban Ve",
    "wof:placetype":"locality"
},
  "geometry": {"coordinates":[104.46106,22.5038],"type":"Point"}
}