{
  "type": "Feature",
  "properties": {
    "gn:admin1_code":"74.0",
    "gn:asciiname":"Chuc O",
    "gn:country_code":"VN",
    "gn:dem":8,
    "gn:feature_class":"P",
    "gn:feature_code":"PPL",
    "gn:name":"Ch\u00fac \u1ed4",
    "gn:population":0,
    "gn:timezone":"Asia/Ho_Chi_Minh",
    "iso:country":"VN",
    "name:vie_x_preferred":[
        "Ch\u00fac \u1ed4"
    ],
    "wof:name":"Chuc O",
    "wof:placetype":"locality"
},
  "geometry": {"coordinates":[106.1387,21.11893],"type":"Point"}
}