{
  "type": "Feature",
  "properties": {
    "gn:admin1_code":"89.0",
    "gn:asciiname":"Phinh Manh",
    "gn:country_code":"VN",
    "gn:dem":826,
    "gn:feature_class":"P",
    "gn:feature_code":"PPL",
    "gn:name":"Phinh Manh",
    "gn:population":0,
    "gn:timezone":"Asia/Ho_Chi_Minh",
    "iso:country":"VN",
    "name:vie_x_preferred":[
        "Phinh Manh"
    ],
    "wof:name":"Phinh Manh",
    "wof:placetype":"locality"
},
  "geometry": {"coordinates":[102.97593000000001,22.07994],"type":"Point"}
}