{
  "type": "Feature",
  "properties": {
    "gn:admin1_code":"63.0",
    "gn:asciiname":"Nouk Bier",
    "gn:country_code":"VN",
    "gn:dem":238,
    "gn:feature_class":"P",
    "gn:feature_code":"PPL",
    "gn:name":"Nouk Bier",
    "gn:population":0,
    "gn:timezone":"Asia/Ho_Chi_Minh",
    "iso:country":"VN",
    "wof:name":"Nouk Bier",
    "wof:placetype":"locality"
},
  "geometry": {"coordinates":[108.41667,14.83333],"type":"Point"}
}