{
  "type": "Feature",
  "properties": {
    "gn:admin1_code":"58.0",
    "gn:asciiname":"Cha La",
    "gn:country_code":"VN",
    "gn:dem":337,
    "gn:feature_class":"P",
    "gn:feature_code":"PPL",
    "gn:name":"Cha La",
    "gn:population":0,
    "gn:timezone":"Asia/Ho_Chi_Minh",
    "iso:country":"VN",
    "name:vie_x_preferred":[
        "Cha La"
    ],
    "wof:name":"Cha La",
    "wof:placetype":"locality"
},
  "geometry": {"coordinates":[104.64252,19.55588],"type":"Point"}
}