{
  "type": "Feature",
  "properties": {
    "gn:admin1_code":"89.0",
    "gn:asciiname":"Ban Nam Ti",
    "gn:country_code":"VN",
    "gn:dem":355,
    "gn:feature_class":"P",
    "gn:feature_code":"PPL",
    "gn:name":"B\u1ea3n Nam Ti",
    "gn:population":0,
    "gn:timezone":"Asia/Ho_Chi_Minh",
    "iso:country":"VN",
    "wof:name":"Ban Nam Ti",
    "wof:placetype":"locality"
},
  "geometry": {"coordinates":[103.06667,22.13333],"type":"Point"}
}