{
  "type": "Feature",
  "properties": {
    "gn:admin1_code":"89.0",
    "gn:asciiname":"Ban Cao Chai",
    "gn:country_code":"VN",
    "gn:dem":1608,
    "gn:feature_class":"P",
    "gn:feature_code":"PPL",
    "gn:name":"B\u1ea3n Cao Ch\u1ea3i",
    "gn:population":0,
    "gn:timezone":"Asia/Ho_Chi_Minh",
    "iso:country":"VN",
    "wof:name":"Ban Cao Chai",
    "wof:placetype":"locality"
},
  "geometry": {"coordinates":[102.83333,22.58333],"type":"Point"}
}