{
  "type": "Feature",
  "properties": {
    "gn:admin1_code":"78.0",
    "gn:asciiname":"Ba Tung",
    "gn:country_code":"VN",
    "gn:dem":11,
    "gn:feature_class":"P",
    "gn:feature_code":"PPL",
    "gn:name":"B\u00e1 T\u00f9ng",
    "gn:population":0,
    "gn:timezone":"Asia/Ho_Chi_Minh",
    "iso:country":"VN",
    "name:und_x_variant":[
        "B\u00e0 T\u00f9ng",
        "B\u00e1 T\u00f9ng"
    ],
    "wof:name":"Ba Tung",
    "wof:placetype":"locality"
},
  "geometry": {"coordinates":[108.23963999999999,15.99508],"type":"Point"}
}