{
  "type": "Feature",
  "properties": {
    "gn:admin1_code":"5.0",
    "gn:asciiname":"Keng Cu",
    "gn:country_code":"VN",
    "gn:dem":837,
    "gn:feature_class":"P",
    "gn:feature_code":"PPL",
    "gn:name":"Keng C\u1ee7",
    "gn:population":0,
    "gn:timezone":"Asia/Ho_Chi_Minh",
    "iso:country":"VN",
    "wof:name":"Keng Cu",
    "wof:placetype":"locality"
},
  "geometry": {"coordinates":[106.15000000000001,22.88333],"type":"Point"}
}