{
  "type": "Feature",
  "properties": {
    "gn:admin1_code":"72.0",
    "gn:asciiname":"Sack Sai",
    "gn:country_code":"VN",
    "gn:dem":389,
    "gn:feature_class":"P",
    "gn:feature_code":"PPL",
    "gn:name":"Sack Sai",
    "gn:population":0,
    "gn:timezone":"Asia/Ho_Chi_Minh",
    "iso:country":"VN",
    "wof:name":"Sack Sai",
    "wof:placetype":"locality"
},
  "geometry": {"coordinates":[106.15000000000001,22.11667000000001],"type":"Point"}
}