{
  "type": "Feature",
  "properties": {
    "gn:admin1_code":"32.0",
    "gn:asciiname":"Ban Cha Lay",
    "gn:country_code":"VN",
    "gn:dem":939,
    "gn:feature_class":"P",
    "gn:feature_code":"PPL",
    "gn:name":"B\u1ea3n Ch\u1ea3 L\u1eady",
    "gn:population":0,
    "gn:timezone":"Asia/Ho_Chi_Minh",
    "iso:country":"VN",
    "name:vie_x_preferred":[
        "B\u1ea3n Ch\u1ea3 L\u1eady"
    ],
    "wof:name":"Ban Cha Lay",
    "wof:placetype":"locality"
},
  "geometry": {"coordinates":[103.47958,21.10213],"type":"Point"}
}