{
  "type": "Feature",
  "properties": {
    "gn:admin1_code":"67.0",
    "gn:asciiname":"Tham Rom",
    "gn:country_code":"VN",
    "gn:dem":-1,
    "gn:feature_class":"P",
    "gn:feature_code":"PPL",
    "gn:name":"Th\u00e2m Rom",
    "gn:population":0,
    "gn:timezone":"Asia/Ho_Chi_Minh",
    "iso:country":"VN",
    "wof:name":"Tham Rom",
    "wof:placetype":"locality"
},
  "geometry": {"coordinates":[106.44306,9.87917],"type":"Point"}
}