{
  "type": "Feature",
  "properties": {
    "gn:admin1_code":"1.0",
    "gn:asciiname":"Tri Ton",
    "gn:country_code":"VN",
    "gn:dem":9,
    "gn:feature_class":"P",
    "gn:feature_code":"PPLA2",
    "gn:name":"Tri T\u00f4n",
    "gn:population":0,
    "gn:timezone":"Asia/Ho_Chi_Minh",
    "iso:country":"VN",
    "name:und_x_variant":[
        "Tri T\u00f4n"
    ],
    "wof:name":"Tri Ton",
    "wof:placetype":"locality"
},
  "geometry": {"coordinates":[105.00073,10.4202],"type":"Point"}
}