{
  "type": "Feature",
  "properties": {
    "gn:admin1_code":"83.0",
    "gn:asciiname":"Vien Minh",
    "gn:country_code":"VN",
    "gn:dem":25,
    "gn:feature_class":"P",
    "gn:feature_code":"PPL",
    "gn:name":"Vi\u00ean Minh",
    "gn:population":0,
    "gn:timezone":"Asia/Ho_Chi_Minh",
    "iso:country":"VN",
    "name:vie_x_preferred":[
        "Vi\u00ean Minh"
    ],
    "wof:name":"Vien Minh",
    "wof:placetype":"locality"
},
  "geometry": {"coordinates":[105.2877,21.46333],"type":"Point"}
}