{
  "type": "Feature",
  "properties": {
    "gn:admin1_code":"89.0",
    "gn:asciiname":"Tchung Chu Vang",
    "gn:country_code":"VN",
    "gn:dem":1529,
    "gn:feature_class":"P",
    "gn:feature_code":"PPL",
    "gn:name":"Tchung Chu Vang",
    "gn:population":0,
    "gn:timezone":"Asia/Ho_Chi_Minh",
    "iso:country":"VN",
    "wof:name":"Tchung Chu Vang",
    "wof:placetype":"locality"
},
  "geometry": {"coordinates":[103.26667,22.65],"type":"Point"}
}