{
  "type": "Feature",
  "properties": {
    "gn:admin1_code":"63.0",
    "gn:asciiname":"Dong My",
    "gn:country_code":"VN",
    "gn:dem":7,
    "gn:feature_class":"P",
    "gn:feature_code":"PPL",
    "gn:name":"\u0110\u00f4ng M\u1ef9",
    "gn:population":0,
    "gn:timezone":"Asia/Ho_Chi_Minh",
    "iso:country":"VN",
    "wof:name":"Dong My",
    "wof:placetype":"locality"
},
  "geometry": {"coordinates":[108.86667,15.05],"type":"Point"}
}