{
  "type": "Feature",
  "properties": {
    "gn:admin1_code":"49.0",
    "gn:asciiname":"Plei Mil",
    "gn:country_code":"VN",
    "gn:dem":173,
    "gn:feature_class":"P",
    "gn:feature_code":"PPL",
    "gn:name":"Plei Mil",
    "gn:population":0,
    "gn:timezone":"Asia/Ho_Chi_Minh",
    "iso:country":"VN",
    "wof:name":"Plei Mil",
    "wof:placetype":"locality"
},
  "geometry": {"coordinates":[108.34999999999999,13.53333],"type":"Point"}
}