{
  "type": "Feature",
  "properties": {
    "gn:admin1_code":"66.0",
    "gn:asciiname":"Binh Dien",
    "gn:country_code":"VN",
    "gn:dem":34,
    "gn:feature_class":"P",
    "gn:feature_code":"PPL",
    "gn:name":"B\u00ecnh \u0110i\u1ec1n",
    "gn:population":0,
    "gn:timezone":"Asia/Ho_Chi_Minh",
    "iso:country":"VN",
    "name:vie_x_preferred":[
        "B\u00ecnh \u0110i\u1ec1n"
    ],
    "wof:name":"Binh Dien",
    "wof:placetype":"locality"
},
  "geometry": {"coordinates":[107.48926000000002,16.35211],"type":"Point"}
}