{
  "type": "Feature",
  "properties": {
    "gn:admin1_code":"32.0",
    "gn:asciiname":"Ban Giang Lo",
    "gn:country_code":"VN",
    "gn:dem":204,
    "gn:feature_class":"P",
    "gn:feature_code":"PPL",
    "gn:name":"B\u1ea3n Giang L\u00f2",
    "gn:population":0,
    "gn:timezone":"Asia/Ho_Chi_Minh",
    "iso:country":"VN",
    "name:vie_x_preferred":[
        "B\u1ea3n Giang L\u00f2"
    ],
    "wof:name":"Ban Giang Lo",
    "wof:placetype":"locality"
},
  "geometry": {"coordinates":[103.56444,21.89851],"type":"Point"}
}