{
  "type": "Feature",
  "properties": {
    "gn:admin1_code":"68.0",
    "gn:asciiname":"Thon Cong",
    "gn:country_code":"VN",
    "gn:dem":103,
    "gn:feature_class":"P",
    "gn:feature_code":"PPL",
    "gn:name":"Th\u00f4n C\u00f4ng",
    "gn:population":0,
    "gn:timezone":"Asia/Ho_Chi_Minh",
    "iso:country":"VN",
    "name:vie_x_preferred":[
        "Th\u00f4n Cu\u00f4ng"
    ],
    "name:vie_x_variant":[
        "Th\u00f4n C\u00f4ng"
    ],
    "wof:name":"Thon Cong",
    "wof:placetype":"locality"
},
  "geometry": {"coordinates":[105.24997999999999,22.5544],"type":"Point"}
}