{
  "type": "Feature",
  "properties": {
    "gn:admin1_code":"34.0",
    "gn:asciiname":"Dai Dong",
    "gn:country_code":"VN",
    "gn:dem":12,
    "gn:feature_class":"P",
    "gn:feature_code":"PPL",
    "gn:name":"\u0110\u1ea1i \u0110\u1ed3ng",
    "gn:population":0,
    "gn:timezone":"Asia/Ho_Chi_Minh",
    "iso:country":"VN",
    "name:vie_x_preferred":[
        "\u0110\u1ea1i \u0110\u1ed3ng"
    ],
    "wof:name":"Dai Dong",
    "wof:placetype":"locality"
},
  "geometry": {"coordinates":[105.72317,19.41135],"type":"Point"}
}