{
  "type": "Feature",
  "properties": {
    "gn:admin1_code":"52.0",
    "gn:asciiname":"Lang Song",
    "gn:country_code":"VN",
    "gn:dem":7,
    "gn:feature_class":"P",
    "gn:feature_code":"PPL",
    "gn:name":"L\u00e0ng Song",
    "gn:population":0,
    "gn:timezone":"Asia/Ho_Chi_Minh",
    "iso:country":"VN",
    "name:und_x_variant":[
        "L\u00e0ng Sang",
        "L\u00e0ng Song"
    ],
    "wof:name":"Lang Song",
    "wof:placetype":"locality"
},
  "geometry": {"coordinates":[105.78333000000001,18.73333],"type":"Point"}
}