{
  "type": "Feature",
  "properties": {
    "gn:admin1_code":"77.0",
    "gn:asciiname":"Xom Chua",
    "gn:country_code":"VN",
    "gn:dem":6,
    "gn:feature_class":"P",
    "gn:feature_code":"PPL",
    "gn:name":"X\u00f3m Ch\u00f9a",
    "gn:population":0,
    "gn:timezone":"Asia/Ho_Chi_Minh",
    "iso:country":"VN",
    "name:vie_x_preferred":[
        "X\u00f3m Ch\u00f9a"
    ],
    "wof:name":"Xom Chua",
    "wof:placetype":"locality"
},
  "geometry": {"coordinates":[105.20077000000001,9.08502],"type":"Point"}
}