{
  "type": "Feature",
  "properties": {
    "gn:admin1_code":"52.0",
    "gn:asciiname":"Gia Thien",
    "gn:country_code":"VN",
    "gn:dem":3,
    "gn:feature_class":"P",
    "gn:feature_code":"PPL",
    "gn:name":"Gia Thi\u1ec7n",
    "gn:population":0,
    "gn:timezone":"Asia/Ho_Chi_Minh",
    "iso:country":"VN",
    "name:und_x_variant":[
        "Dia Thien",
        "Gia Thi\u1ec7n"
    ],
    "wof:name":"Gia Thien",
    "wof:placetype":"locality"
},
  "geometry": {"coordinates":[105.90000000000001,18.41667],"type":"Point"}
}