{
  "type": "Feature",
  "properties": {
    "gn:admin1_code":"60.0",
    "gn:asciiname":"Thon Hon Thieng",
    "gn:country_code":"VN",
    "gn:dem":0,
    "gn:feature_class":"P",
    "gn:feature_code":"PPL",
    "gn:name":"Th\u00f4n H\u00f2n Thi\u00eang",
    "gn:population":0,
    "gn:timezone":"Asia/Ho_Chi_Minh",
    "iso:country":"VN",
    "wof:name":"Thon Hon Thieng",
    "wof:placetype":"locality"
},
  "geometry": {"coordinates":[109.03333000000001,11.63333],"type":"Point"}
}