{
  "type": "Feature",
  "properties": {
    "gn:admin1_code":"32.0",
    "gn:asciiname":"Suoi Kinh",
    "gn:country_code":"VN",
    "gn:dem":433,
    "gn:feature_class":"P",
    "gn:feature_code":"PPL",
    "gn:name":"Su\u1ed1i Kinh",
    "gn:population":0,
    "gn:timezone":"Asia/Ho_Chi_Minh",
    "iso:country":"VN",
    "wof:name":"Suoi Kinh",
    "wof:placetype":"locality"
},
  "geometry": {"coordinates":[104.73333,21.33333],"type":"Point"}
}