{
  "type": "Feature",
  "properties": {
    "gn:admin1_code":"39.0",
    "gn:asciiname":"Khu Ba",
    "gn:country_code":"VN",
    "gn:dem":184,
    "gn:feature_class":"P",
    "gn:feature_code":"PPL",
    "gn:name":"Khu Ba",
    "gn:population":0,
    "gn:timezone":"Asia/Ho_Chi_Minh",
    "iso:country":"VN",
    "name:vie_x_preferred":[
        "Khu Ba"
    ],
    "name:vie_x_variant":[
        "Khu 3"
    ],
    "wof:name":"Khu Ba",
    "wof:placetype":"locality"
},
  "geometry": {"coordinates":[106.6169,22.05239],"type":"Point"}
}