{
  "type": "Feature",
  "properties": {
    "gn:admin1_code":"84.0",
    "gn:asciiname":"Prehel",
    "gn:country_code":"VN",
    "gn:dem":1151,
    "gn:feature_class":"P",
    "gn:feature_code":"PPL",
    "gn:name":"Pr\u00e9hel",
    "gn:population":0,
    "gn:timezone":"Asia/Ho_Chi_Minh",
    "iso:country":"VN",
    "wof:name":"Prehel",
    "wof:placetype":"locality"
},
  "geometry": {"coordinates":[107.84999999999999,15.23333],"type":"Point"}
}