{
  "type": "Feature",
  "properties": {
    "gn:admin1_code":"87.0",
    "gn:asciiname":"Ap Khanh Hoi",
    "gn:cc2":"VN",
    "gn:country_code":"VN",
    "gn:dem":0,
    "gn:feature_class":"P",
    "gn:feature_code":"PPL",
    "gn:name":"\u1ea4p Kh\u00e1nh H\u1ed9i",
    "gn:population":0,
    "gn:timezone":"Asia/Ho_Chi_Minh",
    "iso:country":"VN",
    "name:und_x_variant":[
        "\u1ea4p An H\u1ed9i",
        "\u1ea4p Kh\u00e1nh H\u1ed9i"
    ],
    "wof:name":"Ap Khanh Hoi",
    "wof:placetype":"locality"
},
  "geometry": {"coordinates":[105.79028,9.94944],"type":"Point"}
}