{
  "type": "Feature",
  "properties": {
    "gn:admin1_code":"49.0",
    "gn:asciiname":"Plei Kep Rinh",
    "gn:country_code":"VN",
    "gn:dem":624,
    "gn:feature_class":"P",
    "gn:feature_code":"PPL",
    "gn:name":"Plei K\u00e9p Rinh",
    "gn:population":0,
    "gn:timezone":"Asia/Ho_Chi_Minh",
    "iso:country":"VN",
    "name:vie_x_preferred":[
        "Plei K\u00e9p Rinh"
    ],
    "wof:name":"Plei Kep Rinh",
    "wof:placetype":"locality"
},
  "geometry": {"coordinates":[107.84903,14.1796],"type":"Point"}
}