{
  "type": "Feature",
  "properties": {
    "gn:admin1_code":"50.0",
    "gn:asciiname":"Ban Phia Manh",
    "gn:country_code":"VN",
    "gn:dem":942,
    "gn:feature_class":"P",
    "gn:feature_code":"PPL",
    "gn:name":"B\u1ea3n Phia M\u1ea1nh",
    "gn:population":0,
    "gn:timezone":"Asia/Ho_Chi_Minh",
    "iso:country":"VN",
    "name:vie_x_preferred":[
        "Phia M\u1ea1nh"
    ],
    "name:vie_x_variant":[
        "B\u1ea3n Phia M\u1ea1nh"
    ],
    "wof:name":"Ban Phia Manh",
    "wof:placetype":"locality"
},
  "geometry": {"coordinates":[105.35159,22.94956],"type":"Point"}
}