{
  "type": "Feature",
  "properties": {
    "gn:admin1_code":"88.0",
    "gn:asciiname":"Dong Tien Mot",
    "gn:country_code":"VN",
    "gn:dem":417,
    "gn:feature_class":"P",
    "gn:feature_code":"PPL",
    "gn:name":"\u0110\u1ed3ng Ti\u1ebfn M\u1ed9t",
    "gn:population":0,
    "gn:timezone":"Asia/Ho_Chi_Minh",
    "iso:country":"VN",
    "name:vie_x_preferred":[
        "\u0110\u1ed3ng Ti\u1ebfn M\u1ed9t"
    ],
    "name:vie_x_variant":[
        "\u0110\u1ed3ng Ti\u1ebfn 1"
    ],
    "wof:name":"Dong Tien Mot",
    "wof:placetype":"locality"
},
  "geometry": {"coordinates":[108.06079,12.39425],"type":"Point"}
}