{
  "type": "Feature",
  "properties": {
    "gn:admin1_code":"78.0",
    "gn:asciiname":"Con Dau",
    "gn:country_code":"VN",
    "gn:dem":5,
    "gn:feature_class":"P",
    "gn:feature_code":"PPL",
    "gn:name":"C\u1ed3n D\u00e2u",
    "gn:population":0,
    "gn:timezone":"Asia/Ho_Chi_Minh",
    "iso:country":"VN",
    "name:vie_x_preferred":[
        "C\u1ed3n D\u00e2u"
    ],
    "wof:name":"Con Dau",
    "wof:placetype":"locality"
},
  "geometry": {"coordinates":[108.22628,16.01665],"type":"Point"}
}