{
  "type": "Feature",
  "properties": {
    "gn:admin1_code":"61.0",
    "gn:asciiname":"Ngoc Son",
    "gn:country_code":"VN",
    "gn:dem":11,
    "gn:feature_class":"P",
    "gn:feature_code":"PPL",
    "gn:name":"Ng\u1ecdc S\u01a1n",
    "gn:population":0,
    "gn:timezone":"Asia/Ho_Chi_Minh",
    "iso:country":"VN",
    "name:und_x_variant":[
        "Ng\u1ecdc S\u1ecfn"
    ],
    "name:vie_x_preferred":[
        "Ng\u1ecdc S\u01a1n"
    ],
    "wof:name":"Ngoc Son",
    "wof:placetype":"locality"
},
  "geometry": {"coordinates":[109.21914,13.081],"type":"Point"}
}