{
  "type": "Feature",
  "properties": {
    "gn:admin1_code":"65.0",
    "gn:asciiname":"Giong Me",
    "gn:country_code":"VN",
    "gn:dem":3,
    "gn:feature_class":"P",
    "gn:feature_code":"PPL",
    "gn:name":"Gi\u1ed3ng M\u00e9",
    "gn:population":0,
    "gn:timezone":"Asia/Ho_Chi_Minh",
    "iso:country":"VN",
    "name:und_x_variant":[
        "Giong Me Bien",
        "Giong Me Me Bien",
        "Gi\u1ed3ng M\u00e9"
    ],
    "wof:name":"Giong Me",
    "wof:placetype":"locality"
},
  "geometry": {"coordinates":[105.93778,9.30778],"type":"Point"}
}