{
  "type": "Feature",
  "properties": {
    "gn:admin1_code":"49.0",
    "gn:asciiname":"Plle Mang",
    "gn:country_code":"VN",
    "gn:dem":162,
    "gn:feature_class":"P",
    "gn:feature_code":"PPL",
    "gn:name":"Plle M\u0103ng",
    "gn:population":0,
    "gn:timezone":"Asia/Ho_Chi_Minh",
    "iso:country":"VN",
    "name:vie_x_preferred":[
        "Plle M\u0103ng"
    ],
    "wof:name":"Plle Mang",
    "wof:placetype":"locality"
},
  "geometry": {"coordinates":[108.44293999999999,13.42752],"type":"Point"}
}