{
  "type": "Feature",
  "properties": {
    "gn:admin1_code":"23.0",
    "gn:asciiname":"Buon Treun",
    "gn:cc2":"VN",
    "gn:country_code":"VN",
    "gn:dem":1135,
    "gn:feature_class":"P",
    "gn:feature_code":"PPL",
    "gn:name":"Bu\u00f4n Treun",
    "gn:population":0,
    "gn:timezone":"Asia/Ho_Chi_Minh",
    "iso:country":"VN",
    "name:und_x_variant":[
        "Buon Treun Bon Tron",
        "Bu\u00f4n Treun"
    ],
    "wof:name":"Buon Treun",
    "wof:placetype":"locality"
},
  "geometry": {"coordinates":[108.31667,12.13333],"type":"Point"}
}