{
  "type": "Feature",
  "properties": {
    "gn:admin1_code":"61.0",
    "gn:asciiname":"Phu Thuan",
    "gn:country_code":"VN",
    "gn:dem":8,
    "gn:feature_class":"P",
    "gn:feature_code":"PPL",
    "gn:name":"Ph\u00fa Thu\u00e2n",
    "gn:population":0,
    "gn:timezone":"Asia/Ho_Chi_Minh",
    "iso:country":"VN",
    "name:und_x_variant":[
        "My Thuan",
        "Ph\u00fa Thu\u00e2n"
    ],
    "wof:name":"Phu Thuan",
    "wof:placetype":"locality"
},
  "geometry": {"coordinates":[109.25,12.96667],"type":"Point"}
}