{
  "type": "Feature",
  "properties": {
    "gn:admin1_code":"58.0",
    "gn:asciiname":"Ban Gie",
    "gn:country_code":"VN",
    "gn:dem":149,
    "gn:feature_class":"P",
    "gn:feature_code":"PPL",
    "gn:name":"B\u1ea3n Gi\u00e9",
    "gn:population":0,
    "gn:timezone":"Asia/Ho_Chi_Minh",
    "iso:country":"VN",
    "name:und_x_variant":[
        "K\u1ebd Nhe",
        "B\u1ea3n Gi\u00e9"
    ],
    "wof:name":"Ban Gie",
    "wof:placetype":"locality"
},
  "geometry": {"coordinates":[105.26667,19.45],"type":"Point"}
}