{
  "type": "Feature",
  "properties": {
    "gn:admin1_code":"81.0",
    "gn:asciiname":"Tra Phuong",
    "gn:country_code":"VN",
    "gn:dem":6,
    "gn:feature_class":"P",
    "gn:feature_code":"PPL",
    "gn:name":"Tr\u00e0 Ph\u01b0\u01a1ng",
    "gn:population":0,
    "gn:timezone":"Asia/Ho_Chi_Minh",
    "iso:country":"VN",
    "name:vie_x_preferred":[
        "Tr\u00e0 Ph\u01b0\u01a1ng"
    ],
    "wof:name":"Tra Phuong",
    "wof:placetype":"locality"
},
  "geometry": {"coordinates":[106.11065000000001,20.75114],"type":"Point"}
}