{
  "type": "Feature",
  "properties": {
    "gn:admin1_code":"75.0",
    "gn:asciiname":"Hoa Lan",
    "gn:country_code":"VN",
    "gn:dem":27,
    "gn:feature_class":"P",
    "gn:feature_code":"PPL",
    "gn:name":"H\u00f2a L\u00e2n",
    "gn:population":0,
    "gn:timezone":"Asia/Ho_Chi_Minh",
    "iso:country":"VN",
    "name:vie_x_preferred":[
        "H\u00f2a L\u00e2n"
    ],
    "wof:name":"Hoa Lan",
    "wof:placetype":"locality"
},
  "geometry": {"coordinates":[106.70422000000001,10.95907],"type":"Point"}
}