{
  "type": "Feature",
  "properties": {
    "gn:admin1_code":"49.0",
    "gn:asciiname":"Plei Chorobo",
    "gn:country_code":"VN",
    "gn:dem":345,
    "gn:feature_class":"P",
    "gn:feature_code":"PPL",
    "gn:name":"Plei Chor\u00f4bo",
    "gn:population":0,
    "gn:timezone":"Asia/Ho_Chi_Minh",
    "iso:country":"VN",
    "wof:name":"Plei Chorobo",
    "wof:placetype":"locality"
},
  "geometry": {"coordinates":[108.11667,13.53333],"type":"Point"}
}