{
  "type": "Feature",
  "properties": {
    "gn:admin1_code":"92.0",
    "gn:asciiname":"Te Lua",
    "gn:country_code":"VN",
    "gn:dem":509,
    "gn:feature_class":"P",
    "gn:feature_code":"PPL",
    "gn:name":"T\u00ea L\u00faa",
    "gn:population":0,
    "gn:timezone":"Asia/Ho_Chi_Minh",
    "iso:country":"VN",
    "wof:name":"Te Lua",
    "wof:placetype":"locality"
},
  "geometry": {"coordinates":[103.05575,21.24818],"type":"Point"}
}