{
  "type": "Feature",
  "properties": {
    "gn:admin1_code":"34.0",
    "gn:asciiname":"Lang Rinh",
    "gn:country_code":"VN",
    "gn:dem":112,
    "gn:feature_class":"P",
    "gn:feature_code":"PPL",
    "gn:name":"L\u00e0ng Rinh",
    "gn:population":0,
    "gn:timezone":"Asia/Ho_Chi_Minh",
    "iso:country":"VN",
    "name:vie_x_preferred":[
        "L\u00e0ng Rinh"
    ],
    "wof:name":"Lang Rinh",
    "wof:placetype":"locality"
},
  "geometry": {"coordinates":[105.20752,20.23615],"type":"Point"}
}