{
  "type": "Feature",
  "properties": {
    "gn:admin1_code":"39.0",
    "gn:asciiname":"Khuoi Cat",
    "gn:country_code":"VN",
    "gn:dem":278,
    "gn:feature_class":"P",
    "gn:feature_code":"PPL",
    "gn:name":"Khu\u1ed5i C\u1eaft",
    "gn:population":0,
    "gn:timezone":"Asia/Ho_Chi_Minh",
    "iso:country":"VN",
    "name:vie_x_preferred":[
        "Khu\u1ed5i C\u1eaft"
    ],
    "wof:name":"Khuoi Cat",
    "wof:placetype":"locality"
},
  "geometry": {"coordinates":[106.18196,21.96422],"type":"Point"}
}