{
  "type": "Feature",
  "properties": {
    "gn:admin1_code":"83.0",
    "gn:asciiname":"Thanh Long",
    "gn:country_code":"VN",
    "gn:dem":51,
    "gn:feature_class":"P",
    "gn:feature_code":"PPL",
    "gn:name":"Thanh Long",
    "gn:population":0,
    "gn:timezone":"Asia/Ho_Chi_Minh",
    "iso:country":"VN",
    "name:vie_x_preferred":[
        "Thanh Long"
    ],
    "wof:name":"Thanh Long",
    "wof:placetype":"locality"
},
  "geometry": {"coordinates":[105.16398999999998,21.49516],"type":"Point"}
}