{
  "type": "Feature",
  "properties": {
    "gn:admin1_code":"58.0",
    "gn:asciiname":"Hung Cuong",
    "gn:country_code":"VN",
    "gn:dem":44,
    "gn:feature_class":"P",
    "gn:feature_code":"PPL",
    "gn:name":"H\u00f9ng C\u01b0\u1eddng",
    "gn:population":0,
    "gn:timezone":"Asia/Ho_Chi_Minh",
    "iso:country":"VN",
    "name:vie_x_preferred":[
        "H\u00f9ng C\u01b0\u1eddng"
    ],
    "wof:name":"Hung Cuong",
    "wof:placetype":"locality"
},
  "geometry": {"coordinates":[105.21816,19.07267],"type":"Point"}
}