{
  "type": "Feature",
  "properties": {
    "gn:admin1_code":"89.0",
    "gn:asciiname":"Co Coc",
    "gn:country_code":"VN",
    "gn:dem":294,
    "gn:feature_class":"P",
    "gn:feature_code":"PPL",
    "gn:name":"Co C\u00f3c",
    "gn:population":0,
    "gn:timezone":"Asia/Ho_Chi_Minh",
    "iso:country":"VN",
    "name:vie_x_preferred":[
        "Co C\u00f3c"
    ],
    "wof:name":"Co Coc",
    "wof:placetype":"locality"
},
  "geometry": {"coordinates":[103.35945,22.3342],"type":"Point"}
}