{
  "type": "Feature",
  "properties": {
    "gn:admin1_code":"4.0",
    "gn:asciiname":"Thon Van Phong",
    "gn:cc2":"VN",
    "gn:country_code":"VN",
    "gn:dem":13,
    "gn:feature_class":"P",
    "gn:feature_code":"PPL",
    "gn:name":"Th\u00f4n V\u0103n Phong",
    "gn:population":0,
    "gn:timezone":"Asia/Ho_Chi_Minh",
    "iso:country":"VN",
    "name:und_x_variant":[
        "V\u0103n Qui Ph\u01b0\u01a1ng",
        "Th\u00f4n V\u0103n Phong"
    ],
    "wof:name":"Thon Van Phong",
    "wof:placetype":"locality"
},
  "geometry": {"coordinates":[107.33333,16.61667000000001],"type":"Point"}
}