{
  "type": "Feature",
  "properties": {
    "gn:admin1_code":"50.0",
    "gn:asciiname":"Pin Sang",
    "gn:country_code":"VN",
    "gn:dem":729,
    "gn:feature_class":"P",
    "gn:feature_code":"PPL",
    "gn:name":"Pin S\u1ea3ng",
    "gn:population":0,
    "gn:timezone":"Asia/Ho_Chi_Minh",
    "iso:country":"VN",
    "name:und_x_variant":[
        "Ping Chan"
    ],
    "name:vie_x_preferred":[
        "Pin S\u1ea3ng"
    ],
    "wof:name":"Pin Sang",
    "wof:placetype":"locality"
},
  "geometry": {"coordinates":[104.88343999999999,22.98595],"type":"Point"}
}