{
  "type": "Feature",
  "properties": {
    "gn:admin1_code":"32.0",
    "gn:asciiname":"Ban Suoi",
    "gn:country_code":"VN",
    "gn:dem":587,
    "gn:feature_class":"P",
    "gn:feature_code":"PPL",
    "gn:name":"B\u1ea3n Su\u1ed1i",
    "gn:population":0,
    "gn:timezone":"Asia/Ho_Chi_Minh",
    "iso:country":"VN",
    "name:und_x_variant":[
        "Ban Suoi Boi Thuong",
        "B\u1ea3n Su\u1ed1i"
    ],
    "wof:name":"Ban Suoi",
    "wof:placetype":"locality"
},
  "geometry": {"coordinates":[104.51667,21.11667000000001],"type":"Point"}
}