{
  "type": "Feature",
  "properties": {
    "gn:admin1_code":"88.0",
    "gn:asciiname":"Ea Thi",
    "gn:country_code":"VN",
    "gn:dem":556,
    "gn:feature_class":"P",
    "gn:feature_code":"PPL",
    "gn:name":"Ea Thi",
    "gn:population":0,
    "gn:timezone":"Asia/Ho_Chi_Minh",
    "iso:country":"VN",
    "name:und_x_variant":[
        "Ban Ai Thi",
        "Buon Aethi",
        "Ban Ei Du",
        "Buon Ei Thi",
        "Buon Ai Thi",
        "Buon Bi Thi",
        "Bu\u00f4n Ea Thi"
    ],
    "name:vie_x_preferred":[
        "Ea Thi"
    ],
    "wof:name":"Ea Thi",
    "wof:placetype":"locality"
},
  "geometry": {"coordinates":[108.86123000000001,12.58481],"type":"Point"}
}