{
  "type": "Feature",
  "properties": {
    "gn:admin1_code":"58.0",
    "gn:asciiname":"Con Dam",
    "gn:country_code":"VN",
    "gn:dem":178,
    "gn:feature_class":"P",
    "gn:feature_code":"PPL",
    "gn:name":"C\u1ed3n \u0110\u00e2m",
    "gn:population":0,
    "gn:timezone":"Asia/Ho_Chi_Minh",
    "iso:country":"VN",
    "wof:name":"Con Dam",
    "wof:placetype":"locality"
},
  "geometry": {"coordinates":[105.34999999999999,19.38333],"type":"Point"}
}