{
  "type": "Feature",
  "properties": {
    "gn:admin1_code":"74.0",
    "gn:asciiname":"Co Me",
    "gn:country_code":"VN",
    "gn:dem":15,
    "gn:feature_class":"P",
    "gn:feature_code":"PPL",
    "gn:name":"C\u1ed5 M\u1ec5",
    "gn:population":0,
    "gn:timezone":"Asia/Ho_Chi_Minh",
    "iso:country":"VN",
    "name:vie_x_preferred":[
        "C\u1ed5 M\u1ec5"
    ],
    "wof:name":"Co Me",
    "wof:placetype":"locality"
},
  "geometry": {"coordinates":[106.08320999999999,21.2023],"type":"Point"}
}