{
  "type": "Feature",
  "properties": {
    "gn:admin1_code":"88.0",
    "gn:asciiname":"Buon Kuop",
    "gn:cc2":"VN",
    "gn:country_code":"VN",
    "gn:dem":356,
    "gn:feature_class":"P",
    "gn:feature_code":"PPL",
    "gn:name":"Bu\u00f4n Kuop",
    "gn:population":0,
    "gn:timezone":"Asia/Ho_Chi_Minh",
    "iso:country":"VN",
    "name:und_x_variant":[
        "Ban Kuop",
        "Buon Koup",
        "Bu\u00f4n Kuop"
    ],
    "wof:name":"Buon Kuop",
    "wof:placetype":"locality"
},
  "geometry": {"coordinates":[107.90000000000001,12.55],"type":"Point"}
}