{
  "type": "Feature",
  "properties": {
    "gn:admin1_code":"32.0",
    "gn:asciiname":"Pa Ma",
    "gn:country_code":"VN",
    "gn:dem":410,
    "gn:feature_class":"P",
    "gn:feature_code":"PPL",
    "gn:name":"P\u00e1 Ma",
    "gn:population":0,
    "gn:timezone":"Asia/Ho_Chi_Minh",
    "iso:country":"VN",
    "name:und_x_variant":[
        "Ban Pa Ma",
        "Pa Mam",
        "Pa Ma"
    ],
    "name:vie_x_preferred":[
        "P\u00e1 Ma"
    ],
    "wof:name":"Pa Ma",
    "wof:placetype":"locality"
},
  "geometry": {"coordinates":[103.4366,21.31352],"type":"Point"}
}