{
  "type": "Feature",
  "properties": {
    "gn:admin1_code":"83.0",
    "gn:asciiname":"Dong Thi",
    "gn:country_code":"VN",
    "gn:dem":25,
    "gn:feature_class":"P",
    "gn:feature_code":"PPL",
    "gn:name":"\u0110\u1ed3ng Th\u1ecb",
    "gn:population":0,
    "gn:timezone":"Asia/Ho_Chi_Minh",
    "iso:country":"VN",
    "name:und_x_variant":[
        "\u0110\u00f4ng Th"
    ],
    "name:vie_x_preferred":[
        "\u0110\u1ed3ng Th\u1ecb"
    ],
    "wof:name":"Dong Thi",
    "wof:placetype":"locality"
},
  "geometry": {"coordinates":[105.31786,21.2061],"type":"Point"}
}