{
  "type": "Feature",
  "properties": {
    "gn:admin1_code":"85.0",
    "gn:asciiname":"Con Vack",
    "gn:country_code":"VN",
    "gn:dem":80,
    "gn:feature_class":"P",
    "gn:feature_code":"PPL",
    "gn:name":"Con Vack",
    "gn:population":0,
    "gn:timezone":"Asia/Ho_Chi_Minh",
    "iso:country":"VN",
    "wof:name":"Con Vack",
    "wof:placetype":"locality"
},
  "geometry": {"coordinates":[105.91667,21.71667],"type":"Point"}
}