{
  "type": "Feature",
  "properties": {
    "gn:admin1_code":"82.0",
    "gn:asciiname":"Khang Cu",
    "gn:country_code":"VN",
    "gn:dem":2,
    "gn:feature_class":"P",
    "gn:feature_code":"PPL",
    "gn:name":"Khang Cu",
    "gn:population":0,
    "gn:timezone":"Asia/Ho_Chi_Minh",
    "iso:country":"VN",
    "name:und_x_variant":[
        "Khang Gu",
        "Khang Cu"
    ],
    "wof:name":"Khang Cu",
    "wof:placetype":"locality"
},
  "geometry": {"coordinates":[106.21666999999999,20.21667],"type":"Point"}
}