{
  "type": "Feature",
  "properties": {
    "gn:admin1_code":"52.0",
    "gn:asciiname":"Trai Cau",
    "gn:country_code":"VN",
    "gn:dem":85,
    "gn:feature_class":"P",
    "gn:feature_code":"PPL",
    "gn:name":"Tr\u1ea1i C\u1ea7u",
    "gn:population":0,
    "gn:timezone":"Asia/Ho_Chi_Minh",
    "iso:country":"VN",
    "wof:name":"Trai Cau",
    "wof:placetype":"locality"
},
  "geometry": {"coordinates":[106.21666999999999,18.05],"type":"Point"}
}