{
  "type": "Feature",
  "properties": {
    "gn:admin1_code":"50.0",
    "gn:asciiname":"Ban Ban Le",
    "gn:country_code":"VN",
    "gn:dem":615,
    "gn:feature_class":"P",
    "gn:feature_code":"PPL",
    "gn:name":"B\u1ea3n B\u1ea3n L\u1ec1",
    "gn:population":0,
    "gn:timezone":"Asia/Ho_Chi_Minh",
    "iso:country":"VN",
    "name:und_x_variant":[
        "B\u1ea3n L\u00ea"
    ],
    "name:vie_x_preferred":[
        "B\u1ea3n L\u1ec1"
    ],
    "name:vie_x_variant":[
        "B\u1ea3n B\u1ea3n L\u1ec1"
    ],
    "wof:name":"Ban Ban Le",
    "wof:placetype":"locality"
},
  "geometry": {"coordinates":[105.30951,22.9296],"type":"Point"}
}