{
  "type": "Feature",
  "properties": {
    "gn:admin1_code":"1.0",
    "gn:asciiname":"Trung Binh Nhi",
    "gn:country_code":"VN",
    "gn:dem":2,
    "gn:feature_class":"P",
    "gn:feature_code":"PPL",
    "gn:name":"Trung B\u00ecnh Nh\u00ec",
    "gn:population":0,
    "gn:timezone":"Asia/Ho_Chi_Minh",
    "iso:country":"VN",
    "name:und_x_variant":[
        "\u1ea4p Trung B\u00ecnh Nh\u00ec"
    ],
    "name:vie_x_preferred":[
        "Trung B\u00ecnh Nh\u00ec"
    ],
    "wof:name":"Trung Binh Nhi",
    "wof:placetype":"locality"
},
  "geometry": {"coordinates":[105.32866,10.34011],"type":"Point"}
}