{
  "type": "Feature",
  "properties": {
    "gn:admin1_code":"32.0",
    "gn:asciiname":"Pha Kanh",
    "gn:country_code":"VN",
    "gn:dem":1079,
    "gn:feature_class":"P",
    "gn:feature_code":"PPL",
    "gn:name":"Pha Kanh",
    "gn:population":0,
    "gn:timezone":"Asia/Ho_Chi_Minh",
    "iso:country":"VN",
    "wof:name":"Pha Kanh",
    "wof:placetype":"locality"
},
  "geometry": {"coordinates":[104.63333,20.91667],"type":"Point"}
}