{
  "type": "Feature",
  "properties": {
    "gn:admin1_code":"32.0",
    "gn:asciiname":"Ban Pha Ha",
    "gn:country_code":"VN",
    "gn:dem":556,
    "gn:feature_class":"P",
    "gn:feature_code":"PPL",
    "gn:name":"B\u1ea3n Pha H\u1ea3",
    "gn:population":0,
    "gn:timezone":"Asia/Ho_Chi_Minh",
    "iso:country":"VN",
    "wof:name":"Ban Pha Ha",
    "wof:placetype":"locality"
},
  "geometry": {"coordinates":[103.73333,21.18333],"type":"Point"}
}