{
  "type": "Feature",
  "properties": {
    "gn:admin1_code":"17.0",
    "gn:asciiname":"Kouei Ma",
    "gn:country_code":"VN",
    "gn:dem":709,
    "gn:feature_class":"P",
    "gn:feature_code":"PPL",
    "gn:name":"Kouei Ma",
    "gn:population":0,
    "gn:timezone":"Asia/Ho_Chi_Minh",
    "iso:country":"VN",
    "wof:name":"Kouei Ma",
    "wof:placetype":"locality"
},
  "geometry": {"coordinates":[105.15000000000001,22.58333],"type":"Point"}
}