{
  "type": "Feature",
  "properties": {
    "gn:admin1_code":"52.0",
    "gn:asciiname":"Hung Thinh",
    "gn:country_code":"VN",
    "gn:dem":24,
    "gn:feature_class":"P",
    "gn:feature_code":"PPL",
    "gn:name":"H\u01b0ng Th\u1ecbnh",
    "gn:population":0,
    "gn:timezone":"Asia/Ho_Chi_Minh",
    "iso:country":"VN",
    "wof:name":"Hung Thinh",
    "wof:placetype":"locality"
},
  "geometry": {"coordinates":[105.66667,18.16667],"type":"Point"}
}