{
  "type": "Feature",
  "properties": {
    "gn:admin1_code":"50.0",
    "gn:asciiname":"Ban Seo Lu Than",
    "gn:country_code":"VN",
    "gn:dem":1354,
    "gn:feature_class":"P",
    "gn:feature_code":"PPL",
    "gn:name":"B\u1ea3n Seo L\u1eed Th\u1eadn",
    "gn:population":0,
    "gn:timezone":"Asia/Ho_Chi_Minh",
    "iso:country":"VN",
    "name:vie_x_preferred":[
        "B\u1ea3n Seo L\u1eed Th\u1eadn"
    ],
    "wof:name":"Ban Seo Lu Than",
    "wof:placetype":"locality"
},
  "geometry": {"coordinates":[104.40039,22.69621],"type":"Point"}
}