{
  "type": "Feature",
  "properties": {
    "gn:admin1_code":"74.0",
    "gn:asciiname":"Cao Duong",
    "gn:country_code":"VN",
    "gn:dem":9,
    "gn:feature_class":"P",
    "gn:feature_code":"PPL",
    "gn:name":"Cao \u0110\u01b0\u1eddng",
    "gn:population":0,
    "gn:timezone":"Asia/Ho_Chi_Minh",
    "iso:country":"VN",
    "name:vie_x_preferred":[
        "Cao \u0110\u01b0\u1eddng"
    ],
    "wof:name":"Cao Duong",
    "wof:placetype":"locality"
},
  "geometry": {"coordinates":[106.01493000000001,21.08462],"type":"Point"}
}