{
  "type": "Feature",
  "properties": {
    "gn:admin1_code":"89.0",
    "gn:asciiname":"Ban Tsa O",
    "gn:cc2":"VN",
    "gn:country_code":"VN",
    "gn:dem":634,
    "gn:feature_class":"P",
    "gn:feature_code":"PPL",
    "gn:name":"B\u1ea3n Tsa \u01a0",
    "gn:population":0,
    "gn:timezone":"Asia/Ho_Chi_Minh",
    "iso:country":"VN",
    "name:und_x_variant":[
        "Ban Isa U",
        "B\u1ea3n Tsa \u01a0"
    ],
    "wof:name":"Ban Tsa O",
    "wof:placetype":"locality"
},
  "geometry": {"coordinates":[103.01667,22.18333],"type":"Point"}
}