{
  "type": "Feature",
  "properties": {
    "gn:admin1_code":"39.0",
    "gn:asciiname":"Ra La",
    "gn:country_code":"VN",
    "gn:dem":425,
    "gn:feature_class":"P",
    "gn:feature_code":"PPL",
    "gn:name":"R\u00e3 L\u00e1",
    "gn:population":0,
    "gn:timezone":"Asia/Ho_Chi_Minh",
    "iso:country":"VN",
    "name:und_x_variant":[
        "Ban Ngoa",
        "Ga La"
    ],
    "name:vie_x_preferred":[
        "R\u00e3 L\u00e1"
    ],
    "wof:name":"Ra La",
    "wof:placetype":"locality"
},
  "geometry": {"coordinates":[106.30862999999999,21.93301],"type":"Point"}
}