{
  "type": "Feature",
  "properties": {
    "gn:admin1_code":"83.0",
    "gn:asciiname":"Go Gai",
    "gn:country_code":"VN",
    "gn:dem":39,
    "gn:feature_class":"P",
    "gn:feature_code":"PPL",
    "gn:name":"G\u01a1 Gai",
    "gn:population":0,
    "gn:timezone":"Asia/Ho_Chi_Minh",
    "iso:country":"VN",
    "name:vie_x_preferred":[
        "G\u01a1 Gai"
    ],
    "wof:name":"Go Gai",
    "wof:placetype":"locality"
},
  "geometry": {"coordinates":[105.25857000000001,21.4301],"type":"Point"}
}