{
  "type": "Feature",
  "properties": {
    "gn:admin1_code":"53.0",
    "gn:asciiname":"Vo Coi",
    "gn:country_code":"VN",
    "gn:dem":219,
    "gn:feature_class":"P",
    "gn:feature_code":"PPL",
    "gn:name":"Vo C\u00f4i",
    "gn:population":0,
    "gn:timezone":"Asia/Ho_Chi_Minh",
    "iso:country":"VN",
    "wof:name":"Vo Coi",
    "wof:placetype":"locality"
},
  "geometry": {"coordinates":[105.48333,20.73333],"type":"Point"}
}