{
  "type": "Feature",
  "properties": {
    "gn:admin1_code":"5.0",
    "gn:asciiname":"Ho Ma",
    "gn:country_code":"VN",
    "gn:dem":281,
    "gn:feature_class":"P",
    "gn:feature_code":"PPL",
    "gn:name":"H\u00f4 M\u1ea3",
    "gn:population":0,
    "gn:timezone":"Asia/Ho_Chi_Minh",
    "iso:country":"VN",
    "wof:name":"Ho Ma",
    "wof:placetype":"locality"
},
  "geometry": {"coordinates":[106.06667,22.83333],"type":"Point"}
}