{
  "type": "Feature",
  "properties": {
    "gn:admin1_code":"30.0",
    "gn:asciiname":"Vang Khay",
    "gn:country_code":"VN",
    "gn:dem":14,
    "gn:feature_class":"P",
    "gn:feature_code":"PPL",
    "gn:name":"V\u00e0ng Kh\u00e1y",
    "gn:population":0,
    "gn:timezone":"Asia/Ho_Chi_Minh",
    "iso:country":"VN",
    "name:vie_x_preferred":[
        "V\u00e0ng Kh\u00e1y"
    ],
    "wof:name":"Vang Khay",
    "wof:placetype":"locality"
},
  "geometry": {"coordinates":[107.81914,21.59344],"type":"Point"}
}