{
  "type": "Feature",
  "properties": {
    "gn:admin1_code":"68.0",
    "gn:asciiname":"Da Tron",
    "gn:country_code":"VN",
    "gn:dem":33,
    "gn:feature_class":"P",
    "gn:feature_code":"PPL",
    "gn:name":"\u0110a Tr\u01a1n",
    "gn:population":0,
    "gn:timezone":"Asia/Ho_Chi_Minh",
    "iso:country":"VN",
    "name:vie_x_preferred":[
        "\u0110a Tr\u01a1n"
    ],
    "wof:name":"Da Tron",
    "wof:placetype":"locality"
},
  "geometry": {"coordinates":[105.27652999999999,21.65504],"type":"Point"}
}