{
  "type": "Feature",
  "properties": {
    "gn:admin1_code":"39.0",
    "gn:asciiname":"Bam Bo",
    "gn:country_code":"VN",
    "gn:dem":405,
    "gn:feature_class":"P",
    "gn:feature_code":"PPL",
    "gn:name":"Bam Bo",
    "gn:population":0,
    "gn:timezone":"Asia/Ho_Chi_Minh",
    "iso:country":"VN",
    "wof:name":"Bam Bo",
    "wof:placetype":"locality"
},
  "geometry": {"coordinates":[106.46666999999999,22.31667],"type":"Point"}
}