{
  "type": "Feature",
  "properties": {
    "gn:admin1_code":"34.0",
    "gn:asciiname":"Cu Ly",
    "gn:country_code":"VN",
    "gn:dem":16,
    "gn:feature_class":"P",
    "gn:feature_code":"PPL",
    "gn:name":"C\u1ef1 L\u00fd",
    "gn:population":0,
    "gn:timezone":"Asia/Ho_Chi_Minh",
    "iso:country":"VN",
    "wof:name":"Cu Ly",
    "wof:placetype":"locality"
},
  "geometry": {"coordinates":[105.61667,20.13333],"type":"Point"}
}