{
  "type": "Feature",
  "properties": {
    "gn:admin1_code":"43.0",
    "gn:asciiname":"Ap Mieu",
    "gn:country_code":"VN",
    "gn:dem":6,
    "gn:feature_class":"P",
    "gn:feature_code":"PPL",
    "gn:name":"\u1ea4p Mi\u1ebfu",
    "gn:population":0,
    "gn:timezone":"Asia/Ho_Chi_Minh",
    "iso:country":"VN",
    "name:vie_x_preferred":[
        "\u1ea4p Mi\u1ebfu"
    ],
    "wof:name":"Ap Mieu",
    "wof:placetype":"locality"
},
  "geometry": {"coordinates":[106.90743999999999,10.88224],"type":"Point"}
}