{
  "type": "Feature",
  "properties": {
    "gn:admin1_code":"89.0",
    "gn:asciiname":"Leang Ho",
    "gn:country_code":"VN",
    "gn:dem":246,
    "gn:feature_class":"P",
    "gn:feature_code":"PPL",
    "gn:name":"L\u00e9ang H\u00f4",
    "gn:population":0,
    "gn:timezone":"Asia/Ho_Chi_Minh",
    "iso:country":"VN",
    "wof:name":"Leang Ho",
    "wof:placetype":"locality"
},
  "geometry": {"coordinates":[103.16667,22.25],"type":"Point"}
}