{
  "type": "Feature",
  "properties": {
    "gn:admin1_code":"49.0",
    "gn:asciiname":"An Phong",
    "gn:country_code":"VN",
    "gn:dem":441,
    "gn:feature_class":"P",
    "gn:feature_code":"PPL",
    "gn:name":"An Phong",
    "gn:population":0,
    "gn:timezone":"Asia/Ho_Chi_Minh",
    "iso:country":"VN",
    "wof:name":"An Phong",
    "wof:placetype":"locality"
},
  "geometry": {"coordinates":[108.66667,13.91667],"type":"Point"}
}