{
  "type": "Feature",
  "properties": {
    "gn:admin1_code":"50.0",
    "gn:asciiname":"Cao Son",
    "gn:country_code":"VN",
    "gn:dem":492,
    "gn:feature_class":"P",
    "gn:feature_code":"PPL",
    "gn:name":"Cao S\u01a1n",
    "gn:population":0,
    "gn:timezone":"Asia/Ho_Chi_Minh",
    "iso:country":"VN",
    "name:vie_x_preferred":[
        "Cao S\u01a1n"
    ],
    "wof:name":"Cao Son",
    "wof:placetype":"locality"
},
  "geometry": {"coordinates":[105.28054,22.67964],"type":"Point"}
}