{
  "type": "Feature",
  "properties": {
    "gn:admin1_code":"1.0",
    "gn:asciiname":"Binh Duc Ba",
    "gn:country_code":"VN",
    "gn:dem":5,
    "gn:feature_class":"P",
    "gn:feature_code":"PPL",
    "gn:name":"B\u00ecnh \u0110\u1ee9c Ba",
    "gn:population":0,
    "gn:timezone":"Asia/Ho_Chi_Minh",
    "iso:country":"VN",
    "name:vie_x_preferred":[
        "B\u00ecnh \u0110\u1ee9c Ba"
    ],
    "name:vie_x_variant":[
        "B\u00ecnh \u0110\u1ee9c 3"
    ],
    "wof:name":"Binh Duc Ba",
    "wof:placetype":"locality"
},
  "geometry": {"coordinates":[105.40958000000001,10.4051],"type":"Point"}
}