{
  "type": "Feature",
  "properties": {
    "gn:admin1_code":"73.0",
    "gn:asciiname":"Vinh Phuoc",
    "gn:country_code":"VN",
    "gn:dem":5,
    "gn:feature_class":"P",
    "gn:feature_code":"PPL",
    "gn:name":"V\u0129nh Ph\u01b0\u1edbc",
    "gn:population":0,
    "gn:timezone":"Asia/Ho_Chi_Minh",
    "iso:country":"VN",
    "name:und_x_variant":[
        "\u1ea4p V\u0129nh Ph\u01b0\u1edbc Hai"
    ],
    "name:vie_x_preferred":[
        "V\u0129nh Ph\u01b0\u1edbc"
    ],
    "wof:name":"Vinh Phuoc",
    "wof:placetype":"locality"
},
  "geometry": {"coordinates":[105.44175,9.41745],"type":"Point"}
}