{
  "type": "Feature",
  "properties": {
    "gn:admin1_code":"39.0",
    "gn:asciiname":"Vinh Lai",
    "gn:country_code":"VN",
    "gn:dem":406,
    "gn:feature_class":"P",
    "gn:feature_code":"PPL",
    "gn:name":"V\u0129nh L\u1ea1i",
    "gn:population":0,
    "gn:timezone":"Asia/Ho_Chi_Minh",
    "iso:country":"VN",
    "wof:name":"Vinh Lai",
    "wof:placetype":"locality"
},
  "geometry": {"coordinates":[106.53333000000001,22.35],"type":"Point"}
}