{
  "type": "Feature",
  "properties": {
    "gn:admin1_code":"76.0",
    "gn:asciiname":"Bu Dop",
    "gn:country_code":"VN",
    "gn:dem":113,
    "gn:feature_class":"P",
    "gn:feature_code":"PPLA2",
    "gn:name":"B\u00f9 \u0110\u1ed1p",
    "gn:population":0,
    "gn:timezone":"Asia/Ho_Chi_Minh",
    "iso:country":"VN",
    "name:und_x_variant":[
        "X\u00e3 Ph\u01b0\u01a1c L\u1ed9c",
        "B\u00f9 \u0110\u1ed1p",
        "Qu\u1eadn B\u00e1 \u0110\u1ee9c",
        "Qu\u1eadn B\u1ed1 \u0110\u1ee9c",
        "B\u00f4 D\u1ee9c"
    ],
    "wof:name":"Bu Dop",
    "wof:placetype":"locality"
},
  "geometry": {"coordinates":[106.80018,11.95486],"type":"Point"}
}