{
  "type": "Feature",
  "properties": {
    "gn:admin1_code":"76.0",
    "gn:asciiname":"Phum Cheam Thoum",
    "gn:country_code":"VN",
    "gn:dem":34,
    "gn:feature_class":"P",
    "gn:feature_code":"PPL",
    "gn:name":"Phum Che\u00e2m Thoum",
    "gn:population":0,
    "gn:timezone":"Asia/Ho_Chi_Minh",
    "iso:country":"VN",
    "wof:name":"Phum Cheam Thoum",
    "wof:placetype":"locality"
},
  "geometry": {"coordinates":[106.48333,11.65],"type":"Point"}
}