{
  "type": "Feature",
  "properties": {
    "gn:admin1_code":"34.0",
    "gn:asciiname":"Muong Lat",
    "gn:country_code":"VN",
    "gn:dem":228,
    "gn:feature_class":"P",
    "gn:feature_code":"PPLA2",
    "gn:name":"M\u01b0\u1eddng L\u00e1t",
    "gn:population":0,
    "gn:timezone":"Asia/Ho_Chi_Minh",
    "iso:country":"VN",
    "name:und_x_variant":[
        "Gian Canh",
        "Muong Lat"
    ],
    "name:vie_x_preferred":[
        "M\u01b0\u1eddng L\u00e1t"
    ],
    "wof:name":"Muong Lat",
    "wof:placetype":"locality"
},
  "geometry": {"coordinates":[104.60138000000001,20.52915],"type":"Point"}
}