{
  "type": "Feature",
  "properties": {
    "gn:admin1_code":"5.0",
    "gn:asciiname":"Lung Khum Dau",
    "gn:country_code":"VN",
    "gn:dem":469,
    "gn:feature_class":"P",
    "gn:feature_code":"PPL",
    "gn:name":"L\u0169ng Khum \u0110\u00e2u",
    "gn:population":0,
    "gn:timezone":"Asia/Ho_Chi_Minh",
    "iso:country":"VN",
    "wof:name":"Lung Khum Dau",
    "wof:placetype":"locality"
},
  "geometry": {"coordinates":[106.58333,22.61667000000001],"type":"Point"}
}