{
  "type": "Feature",
  "properties": {
    "gn:admin1_code":"69.0",
    "gn:asciiname":"Phu Thanh",
    "gn:country_code":"VN",
    "gn:dem":4,
    "gn:feature_class":"P",
    "gn:feature_code":"PPL",
    "gn:name":"Ph\u00fa Th\u00e0nh",
    "gn:population":0,
    "gn:timezone":"Asia/Ho_Chi_Minh",
    "iso:country":"VN",
    "name:und_x_variant":[
        "\u1ea4p Ph\u00fa Th\u00e0nh"
    ],
    "name:vie_x_preferred":[
        "Ph\u00fa Th\u00e0nh"
    ],
    "wof:name":"Phu Thanh",
    "wof:placetype":"locality"
},
  "geometry": {"coordinates":[105.98600999999999,10.1817],"type":"Point"}
}