{
  "type": "Feature",
  "properties": {
    "gn:admin1_code":"44.0",
    "gn:asciiname":"Luu Xa",
    "gn:country_code":"VN",
    "gn:dem":8,
    "gn:feature_class":"P",
    "gn:feature_code":"PPL",
    "gn:name":"L\u01b0u X\u00e1",
    "gn:population":0,
    "gn:timezone":"Asia/Ho_Chi_Minh",
    "iso:country":"VN",
    "name:und_x_variant":[
        "Ch\u00f4i",
        "L\u01b0u X\u00e1"
    ],
    "wof:name":"Luu Xa",
    "wof:placetype":"locality"
},
  "geometry": {"coordinates":[105.71666999999999,21.06667],"type":"Point"}
}