{
  "type": "Feature",
  "properties": {
    "gn:admin1_code":"65.0",
    "gn:asciiname":"Lich Hoi Thuong",
    "gn:country_code":"VN",
    "gn:dem":-1,
    "gn:feature_class":"P",
    "gn:feature_code":"PPL",
    "gn:name":"L\u1ecbch H\u1ed9i Th\u01b0\u1ee3ng",
    "gn:population":0,
    "gn:timezone":"Asia/Ho_Chi_Minh",
    "iso:country":"VN",
    "wof:name":"Lich Hoi Thuong",
    "wof:placetype":"locality"
},
  "geometry": {"coordinates":[106.17028000000001,9.4775],"type":"Point"}
}