{
  "type": "Feature",
  "properties": {
    "gn:admin1_code":"5.0",
    "gn:asciiname":"Sam Luong",
    "gn:country_code":"VN",
    "gn:dem":322,
    "gn:feature_class":"P",
    "gn:feature_code":"PPL",
    "gn:name":"Sam Lu\u1ed3ng",
    "gn:population":0,
    "gn:timezone":"Asia/Ho_Chi_Minh",
    "iso:country":"VN",
    "wof:name":"Sam Luong",
    "wof:placetype":"locality"
},
  "geometry": {"coordinates":[106.06667,22.73333],"type":"Point"}
}