{
  "type": "Feature",
  "properties": {
    "gn:admin1_code":"68.0",
    "gn:asciiname":"Na Phuong",
    "gn:country_code":"VN",
    "gn:dem":116,
    "gn:feature_class":"P",
    "gn:feature_code":"PPL",
    "gn:name":"N\u00e0 Ph\u01b0\u1eddng",
    "gn:population":0,
    "gn:timezone":"Asia/Ho_Chi_Minh",
    "iso:country":"VN",
    "name:vie_x_preferred":[
        "N\u00e0 Ph\u01b0\u1eddng"
    ],
    "wof:name":"Na Phuong",
    "wof:placetype":"locality"
},
  "geometry": {"coordinates":[105.37233000000001,22.47917],"type":"Point"}
}