{
  "type": "Feature",
  "properties": {
    "gn:admin1_code":"90.0",
    "gn:asciiname":"Ban Tan Long",
    "gn:country_code":"VN",
    "gn:dem":174,
    "gn:feature_class":"P",
    "gn:feature_code":"PPL",
    "gn:name":"B\u1ea3n T\u00e2n Long",
    "gn:population":0,
    "gn:timezone":"Asia/Ho_Chi_Minh",
    "iso:country":"VN",
    "name:vie_x_preferred":[
        "B\u1ea3n T\u00e2n Long"
    ],
    "wof:name":"Ban Tan Long",
    "wof:placetype":"locality"
},
  "geometry": {"coordinates":[103.77473000000001,22.65224],"type":"Point"}
}