{
  "type": "Feature",
  "properties": {
    "gn:admin1_code":"82.0",
    "gn:asciiname":"Duong Pham",
    "gn:country_code":"VN",
    "gn:dem":1,
    "gn:feature_class":"P",
    "gn:feature_code":"PPL",
    "gn:name":"D\u01b0\u01a1ng Ph\u1ea1m",
    "gn:population":0,
    "gn:timezone":"Asia/Ho_Chi_Minh",
    "iso:country":"VN",
    "wof:name":"Duong Pham",
    "wof:placetype":"locality"
},
  "geometry": {"coordinates":[106.11667,20.25],"type":"Point"}
}