{
  "type": "Feature",
  "properties": {
    "gn:admin1_code":"72.0",
    "gn:asciiname":"Keo Thay",
    "gn:country_code":"VN",
    "gn:dem":550,
    "gn:feature_class":"P",
    "gn:feature_code":"PPL",
    "gn:name":"K\u00e9o Th\u00e1y",
    "gn:population":0,
    "gn:timezone":"Asia/Ho_Chi_Minh",
    "iso:country":"VN",
    "wof:name":"Keo Thay",
    "wof:placetype":"locality"
},
  "geometry": {"coordinates":[105.75469,22.38984],"type":"Point"}
}