{
  "type": "Feature",
  "properties": {
    "gn:admin1_code":"64.0",
    "gn:asciiname":"Lang Pe Sai",
    "gn:country_code":"VN",
    "gn:dem":238,
    "gn:feature_class":"P",
    "gn:feature_code":"PPL",
    "gn:name":"L\u00e0ng Pe Sai",
    "gn:population":0,
    "gn:timezone":"Asia/Ho_Chi_Minh",
    "iso:country":"VN",
    "name:und_x_variant":[
        "Pe Sai",
        "L\u00e0ng Pe Sai"
    ],
    "wof:name":"Lang Pe Sai",
    "wof:placetype":"locality"
},
  "geometry": {"coordinates":[106.66667,16.53333],"type":"Point"}
}