{
  "type": "Feature",
  "properties": {
    "gn:admin1_code":"72.0",
    "gn:asciiname":"Na Lang",
    "gn:country_code":"VN",
    "gn:dem":374,
    "gn:feature_class":"P",
    "gn:feature_code":"PPL",
    "gn:name":"Na Lang",
    "gn:population":0,
    "gn:timezone":"Asia/Ho_Chi_Minh",
    "iso:country":"VN",
    "name:vie_x_preferred":[
        "Na Lang"
    ],
    "wof:name":"Na Lang",
    "wof:placetype":"locality"
},
  "geometry": {"coordinates":[105.96253,22.00649],"type":"Point"}
}