{
  "type": "Feature",
  "properties": {
    "gn:admin1_code":"50.0",
    "gn:asciiname":"Khao Nia",
    "gn:country_code":"VN",
    "gn:dem":286,
    "gn:feature_class":"P",
    "gn:feature_code":"PPL",
    "gn:name":"Khao Nia",
    "gn:population":0,
    "gn:timezone":"Asia/Ho_Chi_Minh",
    "iso:country":"VN",
    "wof:name":"Khao Nia",
    "wof:placetype":"locality"
},
  "geometry": {"coordinates":[105.28333000000001,22.76667],"type":"Point"}
}