{
  "type": "Feature",
  "properties": {
    "gn:admin1_code":"69.0",
    "gn:asciiname":"Hieu Trung",
    "gn:country_code":"VN",
    "gn:dem":5,
    "gn:feature_class":"P",
    "gn:feature_code":"PPL",
    "gn:name":"Hi\u1ebfu Trung",
    "gn:population":0,
    "gn:timezone":"Asia/Ho_Chi_Minh",
    "iso:country":"VN",
    "name:vie_x_preferred":[
        "Hi\u1ebfu Trung"
    ],
    "wof:name":"Hieu Trung",
    "wof:placetype":"locality"
},
  "geometry": {"coordinates":[106.08459000000001,9.96247],"type":"Point"}
}