{
  "type": "Feature",
  "properties": {
    "gn:admin1_code":"3.0",
    "gn:asciiname":"Tan Phuoc",
    "gn:country_code":"VN",
    "gn:dem":4,
    "gn:feature_class":"P",
    "gn:feature_code":"PPL",
    "gn:name":"T\u00e2n Ph\u01b0\u1edbc",
    "gn:population":0,
    "gn:timezone":"Asia/Ho_Chi_Minh",
    "iso:country":"VN",
    "name:vie_x_preferred":[
        "T\u00e2n Ph\u01b0\u1edbc"
    ],
    "wof:name":"Tan Phuoc",
    "wof:placetype":"locality"
},
  "geometry": {"coordinates":[106.50254,10.12153],"type":"Point"}
}