{
  "type": "Feature",
  "properties": {
    "gn:admin1_code":"39.0",
    "gn:asciiname":"Po Pheo",
    "gn:country_code":"VN",
    "gn:dem":279,
    "gn:feature_class":"P",
    "gn:feature_code":"PPL",
    "gn:name":"P\u00f2 Pheo",
    "gn:population":0,
    "gn:timezone":"Asia/Ho_Chi_Minh",
    "iso:country":"VN",
    "wof:name":"Po Pheo",
    "wof:placetype":"locality"
},
  "geometry": {"coordinates":[106.61901,22.02404],"type":"Point"}
}