{
  "type": "Feature",
  "properties": {
    "gn:admin1_code":"71.0",
    "gn:asciiname":"Ngan Van Trung",
    "gn:country_code":"VN",
    "gn:dem":24,
    "gn:feature_class":"P",
    "gn:feature_code":"PPL",
    "gn:name":"Ng\u00e0n V\u0103n Trung",
    "gn:population":0,
    "gn:timezone":"Asia/Ho_Chi_Minh",
    "iso:country":"VN",
    "name:vie_x_preferred":[
        "Ng\u00e0n V\u0103n Trung"
    ],
    "wof:name":"Ngan Van Trung",
    "wof:placetype":"locality"
},
  "geometry": {"coordinates":[106.07549,21.40629],"type":"Point"}
}