{
  "type": "Feature",
  "properties": {
    "gn:admin1_code":"5.0",
    "gn:asciiname":"Phuc Hoa",
    "gn:country_code":"VN",
    "gn:dem":191,
    "gn:feature_class":"P",
    "gn:feature_code":"PPL",
    "gn:name":"Ph\u1ee5c H\u00f2a",
    "gn:population":0,
    "gn:timezone":"Asia/Ho_Chi_Minh",
    "iso:country":"VN",
    "name:nld_x_preferred":[
        "Ph\u00fac H\u00f2a"
    ],
    "name:und_x_variant":[
        "Ph\u1ee5c H\u00f2a"
    ],
    "name:vie_x_preferred":[
        "Ph\u00fac H\u00f2a"
    ],
    "wof:name":"Phuc Hoa",
    "wof:placetype":"locality"
},
  "geometry": {"coordinates":[106.51667,22.53333],"type":"Point"}
}