{
  "type": "Feature",
  "properties": {
    "gn:admin1_code":"74.0",
    "gn:asciiname":"Ap Trau",
    "gn:country_code":"VN",
    "gn:dem":7,
    "gn:feature_class":"P",
    "gn:feature_code":"PPL",
    "gn:name":"\u1ea4p Tr\u1ea5u",
    "gn:population":0,
    "gn:timezone":"Asia/Ho_Chi_Minh",
    "iso:country":"VN",
    "name:vie_x_preferred":[
        "\u1ea4p Tr\u1ea5u"
    ],
    "wof:name":"Ap Trau",
    "wof:placetype":"locality"
},
  "geometry": {"coordinates":[106.00772000000001,21.22284],"type":"Point"}
}