{
  "type": "Feature",
  "properties": {
    "gn:admin1_code":"65.0",
    "gn:asciiname":"Ap Giai Lang",
    "gn:cc2":"VN",
    "gn:country_code":"VN",
    "gn:dem":1,
    "gn:feature_class":"P",
    "gn:feature_code":"PPL",
    "gn:name":"\u1ea4p Giai Lang",
    "gn:population":0,
    "gn:timezone":"Asia/Ho_Chi_Minh",
    "iso:country":"VN",
    "name:und_x_variant":[
        "Giai Lang",
        "Ap Gia Lang",
        "\u1ea4p Giai Lang"
    ],
    "wof:name":"Ap Giai Lang",
    "wof:placetype":"locality"
},
  "geometry": {"coordinates":[106.065,9.43889],"type":"Point"}
}