{
  "type": "Feature",
  "properties": {
    "gn:admin1_code":"68.0",
    "gn:asciiname":"Ban Na Tau",
    "gn:country_code":"VN",
    "gn:dem":305,
    "gn:feature_class":"P",
    "gn:feature_code":"PPL",
    "gn:name":"B\u1ea3n N\u00e0 T\u1ea5u",
    "gn:population":0,
    "gn:timezone":"Asia/Ho_Chi_Minh",
    "iso:country":"VN",
    "name:und_x_variant":[
        "Na Tou"
    ],
    "name:vie_x_preferred":[
        "N\u00e0 T\u1ea5u"
    ],
    "name:vie_x_variant":[
        "B\u1ea3n N\u00e0 T\u1ea5u"
    ],
    "wof:name":"Ban Na Tau",
    "wof:placetype":"locality"
},
  "geometry": {"coordinates":[105.38079,22.57617],"type":"Point"}
}