{
  "type": "Feature",
  "properties": {
    "gn:admin1_code":"58.0",
    "gn:asciiname":"Hong Linh",
    "gn:country_code":"VN",
    "gn:dem":15,
    "gn:feature_class":"P",
    "gn:feature_code":"PPL",
    "gn:name":"H\u1ed3ng L\u0129nh",
    "gn:population":0,
    "gn:timezone":"Asia/Ho_Chi_Minh",
    "iso:country":"VN",
    "name:vie_x_preferred":[
        "H\u1ed3ng L\u0129nh"
    ],
    "wof:name":"Hong Linh",
    "wof:placetype":"locality"
},
  "geometry": {"coordinates":[105.41701999999999,18.75079],"type":"Point"}
}