{
  "type": "Feature",
  "properties": {
    "gn:admin1_code":"92.0",
    "gn:asciiname":"Lossa",
    "gn:country_code":"VN",
    "gn:dem":671,
    "gn:feature_class":"P",
    "gn:feature_code":"PPL",
    "gn:name":"Lossa",
    "gn:population":0,
    "gn:timezone":"Asia/Ho_Chi_Minh",
    "iso:country":"VN",
    "wof:name":"Lossa",
    "wof:placetype":"locality"
},
  "geometry": {"coordinates":[102.36667,22.38333],"type":"Point"}
}