{
  "type": "Feature",
  "properties": {
    "gn:admin1_code":"89.0",
    "gn:asciiname":"Ban Nam Lo",
    "gn:country_code":"VN",
    "gn:dem":398,
    "gn:feature_class":"P",
    "gn:feature_code":"PPL",
    "gn:name":"B\u1ea3n Nam Lo",
    "gn:population":0,
    "gn:timezone":"Asia/Ho_Chi_Minh",
    "iso:country":"VN",
    "wof:name":"Ban Nam Lo",
    "wof:placetype":"locality"
},
  "geometry": {"coordinates":[103.33333,22.31667],"type":"Point"}
}