{
  "type": "Feature",
  "properties": {
    "gn:admin1_code":"32.0",
    "gn:asciiname":"Houei Tia",
    "gn:cc2":"VN",
    "gn:country_code":"VN",
    "gn:dem":1166,
    "gn:feature_class":"P",
    "gn:feature_code":"PPL",
    "gn:name":"Houei Tia",
    "gn:population":0,
    "gn:timezone":"Asia/Ho_Chi_Minh",
    "iso:country":"VN",
    "name:und_x_variant":[
        "Houie Tia",
        "Houei Tia"
    ],
    "wof:name":"Houei Tia",
    "wof:placetype":"locality"
},
  "geometry": {"coordinates":[103.38333,21.33333],"type":"Point"}
}