{
  "type": "Feature",
  "properties": {
    "gn:admin1_code":"62.0",
    "gn:asciiname":"Xom Cuc",
    "gn:country_code":"VN",
    "gn:dem":242,
    "gn:feature_class":"P",
    "gn:feature_code":"PPL",
    "gn:name":"X\u00f3m C\u00fac",
    "gn:population":0,
    "gn:timezone":"Asia/Ho_Chi_Minh",
    "iso:country":"VN",
    "name:und_x_variant":[
        "Xam Cuc",
        "Xom Cuo",
        "X\u00f3m C\u00fac"
    ],
    "wof:name":"Xom Cuc",
    "wof:placetype":"locality"
},
  "geometry": {"coordinates":[105.78333000000001,17.93332999999999],"type":"Point"}
}