{
  "type": "Feature",
  "properties": {
    "gn:admin1_code":"52.0",
    "gn:asciiname":"Phat Nao",
    "gn:country_code":"VN",
    "gn:dem":8,
    "gn:feature_class":"P",
    "gn:feature_code":"PPL",
    "gn:name":"Ph\u1ea5t N\u00e3o",
    "gn:population":0,
    "gn:timezone":"Asia/Ho_Chi_Minh",
    "iso:country":"VN",
    "wof:name":"Phat Nao",
    "wof:placetype":"locality"
},
  "geometry": {"coordinates":[105.93333,18.31667],"type":"Point"}
}