{
  "type": "Feature",
  "properties": {
    "gn:admin1_code":"60.0",
    "gn:asciiname":"Lang Me",
    "gn:country_code":"VN",
    "gn:dem":21,
    "gn:feature_class":"P",
    "gn:feature_code":"PPL",
    "gn:name":"L\u00e1ng Me",
    "gn:population":0,
    "gn:timezone":"Asia/Ho_Chi_Minh",
    "iso:country":"VN",
    "name:vie_x_preferred":[
        "L\u00e1ng Me"
    ],
    "wof:name":"Lang Me",
    "wof:placetype":"locality"
},
  "geometry": {"coordinates":[109.06332,11.68128],"type":"Point"}
}