{
  "type": "Feature",
  "properties": {
    "gn:admin1_code":"74.0",
    "gn:asciiname":"Ong Lam",
    "gn:country_code":"VN",
    "gn:dem":5,
    "gn:feature_class":"P",
    "gn:feature_code":"PPL",
    "gn:name":"\u00d4ng L\u00e2m",
    "gn:population":0,
    "gn:timezone":"Asia/Ho_Chi_Minh",
    "iso:country":"VN",
    "name:vie_x_preferred":[
        "\u00d4ng L\u00e2m"
    ],
    "wof:name":"Ong Lam",
    "wof:placetype":"locality"
},
  "geometry": {"coordinates":[106.06905,21.0996],"type":"Point"}
}