{
  "type": "Feature",
  "properties": {
    "gn:admin1_code":"32.0",
    "gn:asciiname":"Bo Tao",
    "gn:country_code":"VN",
    "gn:dem":128,
    "gn:feature_class":"P",
    "gn:feature_code":"PPL",
    "gn:name":"B\u00f4 Tao",
    "gn:population":0,
    "gn:timezone":"Asia/Ho_Chi_Minh",
    "iso:country":"VN",
    "wof:name":"Bo Tao",
    "wof:placetype":"locality"
},
  "geometry": {"coordinates":[104.96666999999999,20.91667],"type":"Point"}
}