{
  "type": "Feature",
  "properties": {
    "gn:admin1_code":"50.0",
    "gn:asciiname":"Na Loa",
    "gn:country_code":"VN",
    "gn:dem":398,
    "gn:feature_class":"P",
    "gn:feature_code":"PPL",
    "gn:name":"N\u00e0 L\u00f2a",
    "gn:population":0,
    "gn:timezone":"Asia/Ho_Chi_Minh",
    "iso:country":"VN",
    "name:vie_x_preferred":[
        "N\u00e0 L\u00f2a"
    ],
    "wof:name":"Na Loa",
    "wof:placetype":"locality"
},
  "geometry": {"coordinates":[105.10557,22.84363],"type":"Point"}
}