{
  "type": "Feature",
  "properties": {
    "gn:admin1_code":"45.0",
    "gn:asciiname":"Thon Sau",
    "gn:country_code":"VN",
    "gn:dem":3,
    "gn:feature_class":"P",
    "gn:feature_code":"PPL",
    "gn:name":"Th\u00f4n Sau",
    "gn:population":0,
    "gn:timezone":"Asia/Ho_Chi_Minh",
    "iso:country":"VN",
    "name:vie_x_preferred":[
        "Th\u00f4n Sau"
    ],
    "name:vie_x_variant":[
        "Th\u00f4n 6"
    ],
    "wof:name":"Thon Sau",
    "wof:placetype":"locality"
},
  "geometry": {"coordinates":[107.10451,10.45773],"type":"Point"}
}