{
  "type": "Feature",
  "properties": {
    "gn:admin1_code":"6.0",
    "gn:asciiname":"Ap An Binh",
    "gn:country_code":"VN",
    "gn:dem":9,
    "gn:feature_class":"P",
    "gn:feature_code":"PPL",
    "gn:name":"\u1ea4p An B\u00ecnh",
    "gn:population":0,
    "gn:timezone":"Asia/Ho_Chi_Minh",
    "iso:country":"VN",
    "wof:name":"Ap An Binh",
    "wof:placetype":"locality"
},
  "geometry": {"coordinates":[105.53333000000001,10.38333],"type":"Point"}
}