{
  "type": "Feature",
  "properties": {
    "gn:admin1_code":"62.0",
    "gn:asciiname":"Nhut Mao",
    "gn:country_code":"VN",
    "gn:dem":94,
    "gn:feature_class":"P",
    "gn:feature_code":"PPL",
    "gn:name":"Nh\u1ee9t M\u1ea1o",
    "gn:population":0,
    "gn:timezone":"Asia/Ho_Chi_Minh",
    "iso:country":"VN",
    "wof:name":"Nhut Mao",
    "wof:placetype":"locality"
},
  "geometry": {"coordinates":[105.93333,17.88332999999999],"type":"Point"}
}