{
  "type": "Feature",
  "properties": {
    "gn:admin1_code":"85.0",
    "gn:asciiname":"Ban Giang",
    "gn:country_code":"VN",
    "gn:dem":30,
    "gn:feature_class":"P",
    "gn:feature_code":"PPL",
    "gn:name":"B\u1ea3n Giang",
    "gn:population":0,
    "gn:timezone":"Asia/Ho_Chi_Minh",
    "iso:country":"VN",
    "wof:name":"Ban Giang",
    "wof:placetype":"locality"
},
  "geometry": {"coordinates":[105.84999999999999,21.58333],"type":"Point"}
}