{
  "type": "Feature",
  "properties": {
    "gn:admin1_code":"68.0",
    "gn:asciiname":"Dong Chua",
    "gn:country_code":"VN",
    "gn:dem":42,
    "gn:feature_class":"P",
    "gn:feature_code":"PPL",
    "gn:name":"\u0110\u1ed3ng Ch\u00f9a",
    "gn:population":0,
    "gn:timezone":"Asia/Ho_Chi_Minh",
    "iso:country":"VN",
    "name:vie_x_preferred":[
        "\u0110\u1ed3ng Ch\u00f9a"
    ],
    "wof:name":"Dong Chua",
    "wof:placetype":"locality"
},
  "geometry": {"coordinates":[105.12697,22.06001],"type":"Point"}
}