{
  "type": "Feature",
  "properties": {
    "gn:admin1_code":"75.0",
    "gn:asciiname":"Ap Hai B",
    "gn:country_code":"VN",
    "gn:dem":54,
    "gn:feature_class":"P",
    "gn:feature_code":"PPL",
    "gn:name":"\u1ea4p Hai B",
    "gn:population":0,
    "gn:timezone":"Asia/Ho_Chi_Minh",
    "iso:country":"VN",
    "name:vie_x_preferred":[
        "\u1ea4p Hai B"
    ],
    "name:vie_x_variant":[
        "\u1ea4p 2B"
    ],
    "wof:name":"Ap Hai B",
    "wof:placetype":"locality"
},
  "geometry": {"coordinates":[106.78971,11.28174],"type":"Point"}
}