{
  "type": "Feature",
  "properties": {
    "gn:admin1_code":"58.0",
    "gn:asciiname":"Thai Binh",
    "gn:country_code":"VN",
    "gn:dem":7,
    "gn:feature_class":"P",
    "gn:feature_code":"PPL",
    "gn:name":"Th\u00e1i B\u00ecnh",
    "gn:population":0,
    "gn:timezone":"Asia/Ho_Chi_Minh",
    "iso:country":"VN",
    "name:vie_x_preferred":[
        "Th\u00e1i B\u00ecnh"
    ],
    "wof:name":"Thai Binh",
    "wof:placetype":"locality"
},
  "geometry": {"coordinates":[105.73043,18.70911],"type":"Point"}
}