{
  "type": "Feature",
  "properties": {
    "gn:admin1_code":"64.0",
    "gn:asciiname":"Sa Ve",
    "gn:country_code":"VN",
    "gn:dem":220,
    "gn:feature_class":"P",
    "gn:feature_code":"PPL",
    "gn:name":"Sa V\u00e8",
    "gn:population":0,
    "gn:timezone":"Asia/Ho_Chi_Minh",
    "iso:country":"VN",
    "wof:name":"Sa Ve",
    "wof:placetype":"locality"
},
  "geometry": {"coordinates":[107.06667,16.61667000000001],"type":"Point"}
}