{
  "type": "Feature",
  "properties": {
    "gn:admin1_code":"89.0",
    "gn:asciiname":"Na Da",
    "gn:country_code":"VN",
    "gn:dem":728,
    "gn:feature_class":"P",
    "gn:feature_code":"PPL",
    "gn:name":"Na \u0110a",
    "gn:population":0,
    "gn:timezone":"Asia/Ho_Chi_Minh",
    "iso:country":"VN",
    "wof:name":"Na Da",
    "wof:placetype":"locality"
},
  "geometry": {"coordinates":[103.59999999999999,22.33333],"type":"Point"}
}