{
  "type": "Feature",
  "properties": {
    "gn:admin1_code":"67.0",
    "gn:asciiname":"Vinh Bao",
    "gn:country_code":"VN",
    "gn:dem":4,
    "gn:feature_class":"P",
    "gn:feature_code":"PPL",
    "gn:name":"V\u0129nh B\u1ea3o",
    "gn:population":0,
    "gn:timezone":"Asia/Ho_Chi_Minh",
    "iso:country":"VN",
    "name:vie_x_preferred":[
        "V\u0129nh B\u1ea3o"
    ],
    "wof:name":"Vinh Bao",
    "wof:placetype":"locality"
},
  "geometry": {"coordinates":[106.35406999999999,9.96923],"type":"Point"}
}