{
  "type": "Feature",
  "properties": {
    "gn:admin1_code":"88.0",
    "gn:asciiname":"Thon Muoi Lam",
    "gn:country_code":"VN",
    "gn:dem":515,
    "gn:feature_class":"P",
    "gn:feature_code":"PPL",
    "gn:name":"Th\u00f4n M\u01b0\u1eddi L\u0103m",
    "gn:population":0,
    "gn:timezone":"Asia/Ho_Chi_Minh",
    "iso:country":"VN",
    "name:vie_x_preferred":[
        "Th\u00f4n M\u01b0\u1eddi L\u0103m"
    ],
    "name:vie_x_variant":[
        "Th\u00f4n 15"
    ],
    "wof:name":"Thon Muoi Lam",
    "wof:placetype":"locality"
},
  "geometry": {"coordinates":[108.18592,12.65003],"type":"Point"}
}