{
  "type": "Feature",
  "properties": {
    "gn:admin1_code":"65.0",
    "gn:asciiname":"Huong Tinh",
    "gn:cc2":"VN",
    "gn:country_code":"VN",
    "gn:dem":4,
    "gn:feature_class":"P",
    "gn:feature_code":"PPL",
    "gn:name":"H\u01b0\u01a1ng Tinh",
    "gn:population":0,
    "gn:timezone":"Asia/Ho_Chi_Minh",
    "iso:country":"VN",
    "name:und_x_variant":[
        "Tinh",
        "H\u01b0\u01a1ng Tinh"
    ],
    "wof:name":"Huong Tinh",
    "wof:placetype":"locality"
},
  "geometry": {"coordinates":[106.04722,9.57667],"type":"Point"}
}