{
  "type": "Feature",
  "properties": {
    "gn:admin1_code":"93.0",
    "gn:asciiname":"Xom Tram Troc",
    "gn:country_code":"VN",
    "gn:dem":1,
    "gn:feature_class":"P",
    "gn:feature_code":"PPL",
    "gn:name":"X\u00f3m Tr\u00e0m Tr\u00f3c",
    "gn:population":0,
    "gn:timezone":"Asia/Ho_Chi_Minh",
    "iso:country":"VN",
    "wof:name":"Xom Tram Troc",
    "wof:placetype":"locality"
},
  "geometry": {"coordinates":[105.54555999999999,9.65389],"type":"Point"}
}