{
  "type": "Feature",
  "properties": {
    "gn:admin1_code":"73.0",
    "gn:asciiname":"Cay Gian",
    "gn:country_code":"VN",
    "gn:dem":6,
    "gn:feature_class":"P",
    "gn:feature_code":"PPL",
    "gn:name":"C\u00e2y Gian",
    "gn:population":0,
    "gn:timezone":"Asia/Ho_Chi_Minh",
    "iso:country":"VN",
    "name:und_x_variant":[
        "Cai Giang",
        "Xom Cai Giang",
        "\u1ea4p C\u00e2y Gian"
    ],
    "name:vie_x_preferred":[
        "C\u00e2y Gian"
    ],
    "wof:name":"Cay Gian",
    "wof:placetype":"locality"
},
  "geometry": {"coordinates":[105.48996,9.21288],"type":"Point"}
}