{
  "type": "Feature",
  "properties": {
    "gn:admin1_code":"20.0",
    "gn:asciiname":"Cho Cau",
    "gn:country_code":"VN",
    "gn:dem":6,
    "gn:feature_class":"P",
    "gn:feature_code":"PPL",
    "gn:name":"Ch\u1ee3 C\u00e2u",
    "gn:population":0,
    "gn:timezone":"Asia/Ho_Chi_Minh",
    "iso:country":"VN",
    "name:vie_x_preferred":[
        "Ch\u1ee3 C\u00e2u"
    ],
    "wof:name":"Cho Cau",
    "wof:placetype":"locality"
},
  "geometry": {"coordinates":[106.62973,10.84344],"type":"Point"}
}