{
  "type": "Feature",
  "properties": {
    "gn:admin1_code":"61.0",
    "gn:asciiname":"Chi Than",
    "gn:country_code":"VN",
    "gn:dem":44,
    "gn:feature_class":"P",
    "gn:feature_code":"PPL",
    "gn:name":"Ch\u00ed Th\u00e1n",
    "gn:population":0,
    "gn:timezone":"Asia/Ho_Chi_Minh",
    "iso:country":"VN",
    "name:und_x_variant":[
        "Thi Thang",
        "Ch\u00ed Th\u00e1n"
    ],
    "wof:name":"Chi Than",
    "wof:placetype":"locality"
},
  "geometry": {"coordinates":[108.96253,13.02705],"type":"Point"}
}