{
  "type": "Feature",
  "properties": {
    "gn:admin1_code":"64.0",
    "gn:asciiname":"Thon Luong Chanh",
    "gn:country_code":"VN",
    "gn:dem":4,
    "gn:feature_class":"P",
    "gn:feature_code":"PPL",
    "gn:name":"Th\u00f4n L\u01b0\u01a1ng Ch\u00e1nh",
    "gn:population":0,
    "gn:timezone":"Asia/Ho_Chi_Minh",
    "iso:country":"VN",
    "name:und_x_variant":[
        "Luong Chanh",
        "Th\u00f4n L\u01b0\u01a1ng Ch\u00e1nh"
    ],
    "wof:name":"Thon Luong Chanh",
    "wof:placetype":"locality"
},
  "geometry": {"coordinates":[107.28333000000001,16.73333],"type":"Point"}
}