{
  "type": "Feature",
  "properties": {
    "gn:admin1_code":"72.0",
    "gn:asciiname":"Khuoi Nhinh",
    "gn:country_code":"VN",
    "gn:dem":519,
    "gn:feature_class":"P",
    "gn:feature_code":"PPL",
    "gn:name":"Khu\u1ed5i Nh\u00ecnh",
    "gn:population":0,
    "gn:timezone":"Asia/Ho_Chi_Minh",
    "iso:country":"VN",
    "name:vie_x_preferred":[
        "Khu\u1ed5i Nh\u00ecnh"
    ],
    "wof:name":"Khuoi Nhinh",
    "wof:placetype":"locality"
},
  "geometry": {"coordinates":[105.994,22.31336],"type":"Point"}
}