{
  "type": "Feature",
  "properties": {
    "gn:admin1_code":"81.0",
    "gn:asciiname":"Ngo Xa",
    "gn:country_code":"VN",
    "gn:dem":5,
    "gn:feature_class":"P",
    "gn:feature_code":"PPL",
    "gn:name":"Ng\u00f4 X\u00e1",
    "gn:population":0,
    "gn:timezone":"Asia/Ho_Chi_Minh",
    "iso:country":"VN",
    "wof:name":"Ngo Xa",
    "wof:placetype":"locality"
},
  "geometry": {"coordinates":[106.06667,20.81667],"type":"Point"}
}