{
  "type": "Feature",
  "properties": {
    "gn:admin1_code":"52.0",
    "gn:asciiname":"Do Do",
    "gn:country_code":"VN",
    "gn:dem":35,
    "gn:feature_class":"P",
    "gn:feature_code":"PPL",
    "gn:name":"Do Do",
    "gn:population":0,
    "gn:timezone":"Asia/Ho_Chi_Minh",
    "iso:country":"VN",
    "name:und_x_variant":[
        "D\u00e3 \u0110\u1ed9"
    ],
    "wof:name":"Do Do",
    "wof:placetype":"locality"
},
  "geometry": {"coordinates":[106.18333,18.16667],"type":"Point"}
}