{
  "type": "Feature",
  "properties": {
    "gn:admin1_code":"52.0",
    "gn:asciiname":"Hang Dinh",
    "gn:country_code":"VN",
    "gn:dem":6,
    "gn:feature_class":"P",
    "gn:feature_code":"PPL",
    "gn:name":"H\u00e0ng \u0110\u00ecnh",
    "gn:population":0,
    "gn:timezone":"Asia/Ho_Chi_Minh",
    "iso:country":"VN",
    "name:vie_x_preferred":[
        "H\u00e0ng \u0110\u00ecnh"
    ],
    "wof:name":"Hang Dinh",
    "wof:placetype":"locality"
},
  "geometry": {"coordinates":[105.77686,18.40528],"type":"Point"}
}