{
  "type": "Feature",
  "properties": {
    "gn:admin1_code":"87.0",
    "gn:asciiname":"Ap G Hai B",
    "gn:country_code":"VN",
    "gn:dem":4,
    "gn:feature_class":"P",
    "gn:feature_code":"PPL",
    "gn:name":"\u1ea4p G Hai B",
    "gn:population":0,
    "gn:timezone":"Asia/Ho_Chi_Minh",
    "iso:country":"VN",
    "name:vie_x_preferred":[
        "\u1ea4p G Hai B"
    ],
    "name:vie_x_variant":[
        "\u1ea4p G 2B"
    ],
    "wof:name":"Ap G Hai B",
    "wof:placetype":"locality"
},
  "geometry": {"coordinates":[105.30237,10.26224],"type":"Point"}
}