{
  "type": "Feature",
  "properties": {
    "gn:admin1_code":"90.0",
    "gn:asciiname":"Nam Loun",
    "gn:country_code":"VN",
    "gn:dem":424,
    "gn:feature_class":"P",
    "gn:feature_code":"PPL",
    "gn:name":"N\u1eadm Loun",
    "gn:population":0,
    "gn:timezone":"Asia/Ho_Chi_Minh",
    "iso:country":"VN",
    "wof:name":"Nam Loun",
    "wof:placetype":"locality"
},
  "geometry": {"coordinates":[104.31667,22.35],"type":"Point"}
}