{
  "type": "Feature",
  "properties": {
    "gn:admin1_code":"67.0",
    "gn:asciiname":"Giong Cay Da",
    "gn:country_code":"VN",
    "gn:dem":5,
    "gn:feature_class":"P",
    "gn:feature_code":"PPL",
    "gn:name":"Gi\u1ed3ng C\u00e2y \u0110a",
    "gn:population":0,
    "gn:timezone":"Asia/Ho_Chi_Minh",
    "iso:country":"VN",
    "name:und_x_variant":[
        "C\u00e2y \u0110a",
        "Gi\u1ed3ng C\u00e2y \u0110a"
    ],
    "wof:name":"Giong Cay Da",
    "wof:placetype":"locality"
},
  "geometry": {"coordinates":[106.35527999999999,9.64861],"type":"Point"}
}