{
  "type": "Feature",
  "properties": {
    "gn:admin1_code":"68.0",
    "gn:asciiname":"Thon Xuong",
    "gn:country_code":"VN",
    "gn:dem":72,
    "gn:feature_class":"P",
    "gn:feature_code":"PPL",
    "gn:name":"Th\u00f4n X\u01b0\u01a1ng",
    "gn:population":0,
    "gn:timezone":"Asia/Ho_Chi_Minh",
    "iso:country":"VN",
    "name:vie_x_preferred":[
        "Th\u00f4n X\u01b0\u01a1ng"
    ],
    "wof:name":"Thon Xuong",
    "wof:placetype":"locality"
},
  "geometry": {"coordinates":[105.45085,21.76161],"type":"Point"}
}