{
  "type": "Feature",
  "properties": {
    "gn:admin1_code":"90.0",
    "gn:asciiname":"Ma Quay Ho",
    "gn:country_code":"VN",
    "gn:dem":1046,
    "gn:feature_class":"P",
    "gn:feature_code":"PPL",
    "gn:name":"Ma Quay H\u1ed3",
    "gn:population":0,
    "gn:timezone":"Asia/Ho_Chi_Minh",
    "iso:country":"VN",
    "wof:name":"Ma Quay Ho",
    "wof:placetype":"locality"
},
  "geometry": {"coordinates":[103.95,22.21667],"type":"Point"}
}