{
  "type": "Feature",
  "properties": {
    "gn:admin1_code":"88.0",
    "gn:asciiname":"Buon M'Um",
    "gn:country_code":"VN",
    "gn:dem":419,
    "gn:feature_class":"P",
    "gn:feature_code":"PPL",
    "gn:name":"Bu\u00f4n M\u2019Um",
    "gn:population":0,
    "gn:timezone":"Asia/Ho_Chi_Minh",
    "iso:country":"VN",
    "name:vie_x_preferred":[
        "Bu\u00f4n M\u2019Um"
    ],
    "wof:name":"Buon M'Um",
    "wof:placetype":"locality"
},
  "geometry": {"coordinates":[108.71635000000001,12.74508],"type":"Point"}
}