{
  "type": "Feature",
  "properties": {
    "gn:admin1_code":"71.0",
    "gn:asciiname":"Na Can",
    "gn:country_code":"VN",
    "gn:dem":217,
    "gn:feature_class":"P",
    "gn:feature_code":"PPL",
    "gn:name":"N\u00e0 C\u00e2n",
    "gn:population":0,
    "gn:timezone":"Asia/Ho_Chi_Minh",
    "iso:country":"VN",
    "wof:name":"Na Can",
    "wof:placetype":"locality"
},
  "geometry": {"coordinates":[106.91667,21.35],"type":"Point"}
}