{
  "type": "Feature",
  "properties": {
    "gn:admin1_code":"71.0",
    "gn:asciiname":"Khuc Thieu",
    "gn:country_code":"VN",
    "gn:dem":25,
    "gn:feature_class":"P",
    "gn:feature_code":"PPL",
    "gn:name":"Kh\u00fac Thi\u00eau",
    "gn:population":0,
    "gn:timezone":"Asia/Ho_Chi_Minh",
    "iso:country":"VN",
    "name:vie_x_preferred":[
        "Kh\u00fac Thi\u00eau"
    ],
    "wof:name":"Khuc Thieu",
    "wof:placetype":"locality"
},
  "geometry": {"coordinates":[106.14924000000001,21.45573],"type":"Point"}
}