{
  "type": "Feature",
  "properties": {
    "gn:admin1_code":"68.0",
    "gn:asciiname":"Ban Phung",
    "gn:country_code":"VN",
    "gn:dem":150,
    "gn:feature_class":"P",
    "gn:feature_code":"PPL",
    "gn:name":"B\u1ea3n Ph\u1ee7ng",
    "gn:population":0,
    "gn:timezone":"Asia/Ho_Chi_Minh",
    "iso:country":"VN",
    "name:vie_x_preferred":[
        "B\u1ea3n Ph\u1ee7ng"
    ],
    "wof:name":"Ban Phung",
    "wof:placetype":"locality"
},
  "geometry": {"coordinates":[105.30389,22.53317],"type":"Point"}
}