{
  "type": "Feature",
  "properties": {
    "gn:admin1_code":"84.0",
    "gn:asciiname":"Trung Hiep Ba",
    "gn:country_code":"VN",
    "gn:dem":29,
    "gn:feature_class":"P",
    "gn:feature_code":"PPL",
    "gn:name":"Trung Hi\u1ec7p Ba",
    "gn:population":0,
    "gn:timezone":"Asia/Ho_Chi_Minh",
    "iso:country":"VN",
    "name:und_x_variant":[
        "Tr\u01b0ng Hi\u1ec7p",
        "My An"
    ],
    "name:vie_x_preferred":[
        "Trung Hi\u1ec7p Ba"
    ],
    "name:vie_x_variant":[
        "Trung Hi\u1ec7p 3"
    ],
    "wof:name":"Trung Hiep Ba",
    "wof:placetype":"locality"
},
  "geometry": {"coordinates":[107.86536,15.82659],"type":"Point"}
}