{
  "type": "Feature",
  "properties": {
    "gn:admin1_code":"83.0",
    "gn:asciiname":"Xom Ong",
    "gn:country_code":"VN",
    "gn:dem":244,
    "gn:feature_class":"P",
    "gn:feature_code":"PPL",
    "gn:name":"X\u00f3m Ong",
    "gn:population":0,
    "gn:timezone":"Asia/Ho_Chi_Minh",
    "iso:country":"VN",
    "name:vie_x_preferred":[
        "X\u00f3m Ong"
    ],
    "wof:name":"Xom Ong",
    "wof:placetype":"locality"
},
  "geometry": {"coordinates":[104.95932000000001,21.07759],"type":"Point"}
}