{
  "type": "Feature",
  "properties": {
    "gn:admin1_code":"78.0",
    "gn:asciiname":"Phong Le",
    "gn:country_code":"VN",
    "gn:dem":5,
    "gn:feature_class":"P",
    "gn:feature_code":"PPL",
    "gn:name":"Phong L\u00ea",
    "gn:population":0,
    "gn:timezone":"Asia/Ho_Chi_Minh",
    "iso:country":"VN",
    "name:und_x_variant":[
        "Phong L\u1ec7"
    ],
    "name:vie_x_preferred":[
        "Phong L\u00ea"
    ],
    "wof:name":"Phong Le",
    "wof:placetype":"locality"
},
  "geometry": {"coordinates":[108.19335,15.99644],"type":"Point"}
}