{
  "type": "Feature",
  "properties": {
    "gn:admin1_code":"70.0",
    "gn:asciiname":"Som Dong",
    "gn:country_code":"VN",
    "gn:dem":68,
    "gn:feature_class":"P",
    "gn:feature_code":"PPL",
    "gn:name":"Som Dong",
    "gn:population":0,
    "gn:timezone":"Asia/Ho_Chi_Minh",
    "iso:country":"VN",
    "name:und_x_variant":[
        "X\u00f3m \u0110\u1ed3ng"
    ],
    "wof:name":"Som Dong",
    "wof:placetype":"locality"
},
  "geometry": {"coordinates":[104.73333,21.81667],"type":"Point"}
}