{
  "type": "Feature",
  "properties": {
    "gn:admin1_code":"32.0",
    "gn:asciiname":"Na Che",
    "gn:country_code":"VN",
    "gn:dem":876,
    "gn:feature_class":"P",
    "gn:feature_code":"PPL",
    "gn:name":"Na Che",
    "gn:population":0,
    "gn:timezone":"Asia/Ho_Chi_Minh",
    "iso:country":"VN",
    "wof:name":"Na Che",
    "wof:placetype":"locality"
},
  "geometry": {"coordinates":[103.90000000000001,21.25],"type":"Point"}
}