{
  "type": "Feature",
  "properties": {
    "gn:admin1_code":"53.0",
    "gn:asciiname":"Vinh Dong",
    "gn:country_code":"VN",
    "gn:dem":282,
    "gn:feature_class":"P",
    "gn:feature_code":"PPL",
    "gn:name":"V\u0129nh D\u1ed3ng",
    "gn:population":0,
    "gn:timezone":"Asia/Ho_Chi_Minh",
    "iso:country":"VN",
    "wof:name":"Vinh Dong",
    "wof:placetype":"locality"
},
  "geometry": {"coordinates":[105.45,20.71667],"type":"Point"}
}