{
  "type": "Feature",
  "properties": {
    "gn:admin1_code":"74.0",
    "gn:asciiname":"Xom Ngoai",
    "gn:country_code":"VN",
    "gn:dem":8,
    "gn:feature_class":"P",
    "gn:feature_code":"PPL",
    "gn:name":"X\u00f3m Ngo\u00e0i",
    "gn:population":0,
    "gn:timezone":"Asia/Ho_Chi_Minh",
    "iso:country":"VN",
    "name:vie_x_preferred":[
        "X\u00f3m Ngo\u00e0i"
    ],
    "wof:name":"Xom Ngoai",
    "wof:placetype":"locality"
},
  "geometry": {"coordinates":[106.19483,21.11605],"type":"Point"}
}