{
  "type": "Feature",
  "properties": {
    "gn:admin1_code":"85.0",
    "gn:asciiname":"Ban Nua",
    "gn:country_code":"VN",
    "gn:dem":137,
    "gn:feature_class":"P",
    "gn:feature_code":"PPL",
    "gn:name":"B\u1ea3n N\u01b0a",
    "gn:population":0,
    "gn:timezone":"Asia/Ho_Chi_Minh",
    "iso:country":"VN",
    "name:vie_x_preferred":[
        "B\u1ea3n N\u01b0a"
    ],
    "wof:name":"Ban Nua",
    "wof:placetype":"locality"
},
  "geometry": {"coordinates":[106.05763,21.87381],"type":"Point"}
}