{
  "type": "Feature",
  "properties": {
    "gn:admin1_code":"39.0",
    "gn:asciiname":"Na Khoang",
    "gn:country_code":"VN",
    "gn:dem":301,
    "gn:feature_class":"P",
    "gn:feature_code":"PPL",
    "gn:name":"N\u00e0 Kho\u1ea3ng",
    "gn:population":0,
    "gn:timezone":"Asia/Ho_Chi_Minh",
    "iso:country":"VN",
    "name:vie_x_preferred":[
        "N\u00e0 Kho\u1ea3ng"
    ],
    "wof:name":"Na Khoang",
    "wof:placetype":"locality"
},
  "geometry": {"coordinates":[106.47154999999999,21.91227],"type":"Point"}
}