{
  "type": "Feature",
  "properties": {
    "gn:admin1_code":"58.0",
    "gn:asciiname":"Trung Hau",
    "gn:country_code":"VN",
    "gn:dem":8,
    "gn:feature_class":"P",
    "gn:feature_code":"PPL",
    "gn:name":"Trung Hau",
    "gn:population":0,
    "gn:timezone":"Asia/Ho_Chi_Minh",
    "iso:country":"VN",
    "name:vie_x_preferred":[
        "Trung Hau"
    ],
    "wof:name":"Trung Hau",
    "wof:placetype":"locality"
},
  "geometry": {"coordinates":[105.57532999999999,18.59323],"type":"Point"}
}