{
  "type": "Feature",
  "properties": {
    "gn:admin1_code":"32.0",
    "gn:asciiname":"Ban Hua Muong",
    "gn:country_code":"VN",
    "gn:dem":337,
    "gn:feature_class":"P",
    "gn:feature_code":"PPL",
    "gn:name":"B\u1ea3n H\u01b0a M\u01b0\u1eddng",
    "gn:population":0,
    "gn:timezone":"Asia/Ho_Chi_Minh",
    "iso:country":"VN",
    "name:vie_x_preferred":[
        "B\u1ea3n H\u01b0a M\u01b0\u1eddng"
    ],
    "wof:name":"Ban Hua Muong",
    "wof:placetype":"locality"
},
  "geometry": {"coordinates":[103.69064,21.55599],"type":"Point"}
}