{
  "type": "Feature",
  "properties": {
    "gn:admin1_code":"89.0",
    "gn:asciiname":"Ban Nam Hum",
    "gn:country_code":"VN",
    "gn:dem":1540,
    "gn:feature_class":"P",
    "gn:feature_code":"PPL",
    "gn:name":"B\u1ea3n Nam H\u00f9m",
    "gn:population":0,
    "gn:timezone":"Asia/Ho_Chi_Minh",
    "iso:country":"VN",
    "wof:name":"Ban Nam Hum",
    "wof:placetype":"locality"
},
  "geometry": {"coordinates":[103.03333000000001,22.43333],"type":"Point"}
}