{
  "type": "Feature",
  "properties": {
    "gn:admin1_code":"58.0",
    "gn:asciiname":"Sa Lai",
    "gn:country_code":"VN",
    "gn:dem":1114,
    "gn:feature_class":"P",
    "gn:feature_code":"PPL",
    "gn:name":"Sa L\u00e0i",
    "gn:population":0,
    "gn:timezone":"Asia/Ho_Chi_Minh",
    "iso:country":"VN",
    "name:vie_x_preferred":[
        "Sa L\u00e0i"
    ],
    "wof:name":"Sa Lai",
    "wof:placetype":"locality"
},
  "geometry": {"coordinates":[104.34207000000001,19.51105],"type":"Point"}
}