{
  "type": "Feature",
  "properties": {
    "gn:admin1_code":"3.0",
    "gn:asciiname":"Ap Binh Dong",
    "gn:country_code":"VN",
    "gn:dem":-1,
    "gn:feature_class":"P",
    "gn:feature_code":"PPL",
    "gn:name":"\u1ea4p B\u00ecnh \u0110\u00f4ng",
    "gn:population":0,
    "gn:timezone":"Asia/Ho_Chi_Minh",
    "iso:country":"VN",
    "name:und_x_variant":[
        "B\u00ecnh \u0110\u00f4ng",
        "\u1ea4p B\u00ecnh \u0110\u00f4ng"
    ],
    "wof:name":"Ap Binh Dong",
    "wof:placetype":"locality"
},
  "geometry": {"coordinates":[106.39694,9.99472],"type":"Point"}
}