{
  "type": "Feature",
  "properties": {
    "gn:admin1_code":"85.0",
    "gn:asciiname":"Dong Mo",
    "gn:country_code":"VN",
    "gn:dem":43,
    "gn:feature_class":"P",
    "gn:feature_code":"PPL",
    "gn:name":"\u0110\u1ed3ng M\u1ecf",
    "gn:population":0,
    "gn:timezone":"Asia/Ho_Chi_Minh",
    "iso:country":"VN",
    "name:vie_x_preferred":[
        "\u0110\u1ed3ng M\u1ecf"
    ],
    "wof:name":"Dong Mo",
    "wof:placetype":"locality"
},
  "geometry": {"coordinates":[105.93213,21.61183],"type":"Point"}
}