{
  "type": "Feature",
  "properties": {
    "gn:admin1_code":"49.0",
    "gn:asciiname":"Lang Kla K Hai",
    "gn:country_code":"VN",
    "gn:dem":391,
    "gn:feature_class":"P",
    "gn:feature_code":"PPL",
    "gn:name":"L\u00e0ng Kla K Hai",
    "gn:population":0,
    "gn:timezone":"Asia/Ho_Chi_Minh",
    "iso:country":"VN",
    "name:vie_x_preferred":[
        "L\u00e0ng Kla K Hai"
    ],
    "name:vie_x_variant":[
        "L\u00e0ng Kla K2"
    ],
    "wof:name":"Lang Kla K Hai",
    "wof:placetype":"locality"
},
  "geometry": {"coordinates":[108.55029,13.89833],"type":"Point"}
}