{
  "type": "Feature",
  "properties": {
    "gn:admin1_code":"83.0",
    "gn:asciiname":"Chieng Kit",
    "gn:country_code":"VN",
    "gn:dem":111,
    "gn:feature_class":"P",
    "gn:feature_code":"PPL",
    "gn:name":"Chi\u1ec1ng K\u1ecbt",
    "gn:population":0,
    "gn:timezone":"Asia/Ho_Chi_Minh",
    "iso:country":"VN",
    "name:vie_x_preferred":[
        "Chi\u1ec1ng K\u1ecbt"
    ],
    "wof:name":"Chieng Kit",
    "wof:placetype":"locality"
},
  "geometry": {"coordinates":[104.93692,21.22919],"type":"Point"}
}