{
  "type": "Feature",
  "properties": {
    "gn:admin1_code":"47.0",
    "gn:asciiname":"Thanh My",
    "gn:country_code":"VN",
    "gn:dem":35,
    "gn:feature_class":"P",
    "gn:feature_code":"PPL",
    "gn:name":"Thanh M\u1ef9",
    "gn:population":0,
    "gn:timezone":"Asia/Ho_Chi_Minh",
    "iso:country":"VN",
    "name:und_x_variant":[
        "Th\u1ea1nh M\u1ef9"
    ],
    "name:vie_x_preferred":[
        "Thanh M\u1ef9"
    ],
    "wof:name":"Thanh My",
    "wof:placetype":"locality"
},
  "geometry": {"coordinates":[107.94795000000001,10.74231],"type":"Point"}
}