{
  "type": "Feature",
  "properties": {
    "gn:admin1_code":"70.0",
    "gn:asciiname":"Ban Manh",
    "gn:country_code":"VN",
    "gn:dem":133,
    "gn:feature_class":"P",
    "gn:feature_code":"PPL",
    "gn:name":"B\u1ea3n M\u00e0nh",
    "gn:population":0,
    "gn:timezone":"Asia/Ho_Chi_Minh",
    "iso:country":"VN",
    "name:vie_x_preferred":[
        "B\u1ea3n M\u00e0nh"
    ],
    "wof:name":"Ban Manh",
    "wof:placetype":"locality"
},
  "geometry": {"coordinates":[104.60312999999999,21.68752000000001],"type":"Point"}
}