{
  "type": "Feature",
  "properties": {
    "gn:admin1_code":"5.0",
    "gn:asciiname":"Nam Quet",
    "gn:country_code":"VN",
    "gn:dem":605,
    "gn:feature_class":"P",
    "gn:feature_code":"PPL",
    "gn:name":"Nam Qu\u00e9t",
    "gn:population":0,
    "gn:timezone":"Asia/Ho_Chi_Minh",
    "iso:country":"VN",
    "wof:name":"Nam Quet",
    "wof:placetype":"locality"
},
  "geometry": {"coordinates":[105.75,22.98333],"type":"Point"}
}