{
  "type": "Feature",
  "properties": {
    "gn:admin1_code":"83.0",
    "gn:asciiname":"Tang Nhi",
    "gn:country_code":"VN",
    "gn:dem":25,
    "gn:feature_class":"P",
    "gn:feature_code":"PPL",
    "gn:name":"T\u0103ng Nhi",
    "gn:population":0,
    "gn:timezone":"Asia/Ho_Chi_Minh",
    "iso:country":"VN",
    "name:vie_x_preferred":[
        "T\u0103ng Nhi"
    ],
    "wof:name":"Tang Nhi",
    "wof:placetype":"locality"
},
  "geometry": {"coordinates":[105.18998000000001,21.34459],"type":"Point"}
}