{
  "type": "Feature",
  "properties": {
    "gn:admin1_code":"74.0",
    "gn:asciiname":"Dong Ngoai",
    "gn:country_code":"VN",
    "gn:dem":5,
    "gn:feature_class":"P",
    "gn:feature_code":"PPL",
    "gn:name":"\u0110\u00f4ng Ngo\u1ea1i",
    "gn:population":0,
    "gn:timezone":"Asia/Ho_Chi_Minh",
    "iso:country":"VN",
    "name:vie_x_preferred":[
        "\u0110\u00f4ng Ngo\u1ea1i"
    ],
    "wof:name":"Dong Ngoai",
    "wof:placetype":"locality"
},
  "geometry": {"coordinates":[106.12108000000001,21.00203],"type":"Point"}
}