{
  "type": "Feature",
  "properties": {
    "gn:admin1_code":"39.0",
    "gn:asciiname":"Lan Ruoi",
    "gn:country_code":"VN",
    "gn:dem":445,
    "gn:feature_class":"P",
    "gn:feature_code":"PPL",
    "gn:name":"L\u00e2n R\u01b0\u1ee3i",
    "gn:population":0,
    "gn:timezone":"Asia/Ho_Chi_Minh",
    "iso:country":"VN",
    "name:vie_x_preferred":[
        "L\u00e2n R\u01b0\u1ee3i"
    ],
    "wof:name":"Lan Ruoi",
    "wof:placetype":"locality"
},
  "geometry": {"coordinates":[106.3462,21.75771],"type":"Point"}
}