{
  "type": "Feature",
  "properties": {
    "gn:admin1_code":"71.0",
    "gn:asciiname":"Hop Tien",
    "gn:country_code":"VN",
    "gn:dem":16,
    "gn:feature_class":"P",
    "gn:feature_code":"PPL",
    "gn:name":"H\u1ee3p Ti\u1ebfn",
    "gn:population":0,
    "gn:timezone":"Asia/Ho_Chi_Minh",
    "iso:country":"VN",
    "name:vie_x_preferred":[
        "H\u1ee3p Ti\u1ebfn"
    ],
    "wof:name":"Hop Tien",
    "wof:placetype":"locality"
},
  "geometry": {"coordinates":[106.05373,21.36157],"type":"Point"}
}