{
  "type": "Feature",
  "properties": {
    "gn:admin1_code":"16.0",
    "gn:asciiname":"Dong Vo",
    "gn:country_code":"VN",
    "gn:dem":114,
    "gn:feature_class":"P",
    "gn:feature_code":"PPL",
    "gn:name":"\u0110\u1ed3ng Vo",
    "gn:population":0,
    "gn:timezone":"Asia/Ho_Chi_Minh",
    "iso:country":"VN",
    "wof:name":"Dong Vo",
    "wof:placetype":"locality"
},
  "geometry": {"coordinates":[105.51667,20.93333],"type":"Point"}
}