{
  "type": "Feature",
  "properties": {
    "gn:admin1_code":"63.0",
    "gn:asciiname":"Minh Khanh",
    "gn:country_code":"VN",
    "gn:dem":27,
    "gn:feature_class":"P",
    "gn:feature_code":"PPL",
    "gn:name":"Minh Kh\u00e1nh",
    "gn:population":0,
    "gn:timezone":"Asia/Ho_Chi_Minh",
    "iso:country":"VN",
    "name:und_x_variant":[
        "Minh Kh\u00e1nh",
        "An Phu"
    ],
    "wof:name":"Minh Khanh",
    "wof:placetype":"locality"
},
  "geometry": {"coordinates":[108.66667,15.15],"type":"Point"}
}