{
  "type": "Feature",
  "properties": {
    "gn:admin1_code":"65.0",
    "gn:asciiname":"Tac Gong",
    "gn:country_code":"VN",
    "gn:dem":8,
    "gn:feature_class":"P",
    "gn:feature_code":"PPL",
    "gn:name":"T\u1eafc G\u1ed3ng",
    "gn:population":0,
    "gn:timezone":"Asia/Ho_Chi_Minh",
    "iso:country":"VN",
    "name:und_x_variant":[
        "Ap Tac Dong",
        "\u1ea4p T\u1eafc G\u00f2ng"
    ],
    "name:vie_x_preferred":[
        "T\u1eafc G\u1ed3ng"
    ],
    "wof:name":"Tac Gong",
    "wof:placetype":"locality"
},
  "geometry": {"coordinates":[105.94410000000001,9.51295],"type":"Point"}
}