{
  "type": "Feature",
  "properties": {
    "gn:admin1_code":"61.0",
    "gn:asciiname":"Tan Lap",
    "gn:country_code":"VN",
    "gn:dem":142,
    "gn:feature_class":"P",
    "gn:feature_code":"PPL",
    "gn:name":"T\u00e2n L\u1eadp",
    "gn:population":0,
    "gn:timezone":"Asia/Ho_Chi_Minh",
    "iso:country":"VN",
    "name:vie_x_preferred":[
        "T\u00e2n L\u1eadp"
    ],
    "wof:name":"Tan Lap",
    "wof:placetype":"locality"
},
  "geometry": {"coordinates":[108.94974000000001,13.10075],"type":"Point"}
}