{
  "type": "Feature",
  "properties": {
    "gn:admin1_code":"20.0",
    "gn:asciiname":"Tan Thoi Nhut",
    "gn:cc2":"VN",
    "gn:country_code":"VN",
    "gn:dem":7,
    "gn:feature_class":"P",
    "gn:feature_code":"PPL",
    "gn:name":"T\u00e2n Th\u1edbi Nh\u1ee9t",
    "gn:population":0,
    "gn:timezone":"Asia/Ho_Chi_Minh",
    "iso:country":"VN",
    "name:und_x_variant":[
        "Tan Phoi Nhut Thon",
        "T\u00e2n Th\u1edbi Nh\u1ee9t"
    ],
    "wof:name":"Tan Thoi Nhut",
    "wof:placetype":"locality"
},
  "geometry": {"coordinates":[106.60861,10.83222],"type":"Point"}
}