{
  "type": "Feature",
  "properties": {
    "gn:admin1_code":"68.0",
    "gn:asciiname":"Soi Lam",
    "gn:country_code":"VN",
    "gn:dem":27,
    "gn:feature_class":"P",
    "gn:feature_code":"PPL",
    "gn:name":"Soi L\u00e2m",
    "gn:population":0,
    "gn:timezone":"Asia/Ho_Chi_Minh",
    "iso:country":"VN",
    "name:vie_x_preferred":[
        "Soi L\u00e2m"
    ],
    "wof:name":"Soi Lam",
    "wof:placetype":"locality"
},
  "geometry": {"coordinates":[105.21796999999999,21.8037],"type":"Point"}
}