{
  "type": "Feature",
  "properties": {
    "gn:admin1_code":"58.0",
    "gn:asciiname":"Na Hoc",
    "gn:country_code":"VN",
    "gn:dem":767,
    "gn:feature_class":"P",
    "gn:feature_code":"PPL",
    "gn:name":"Na H\u1ed1c",
    "gn:population":0,
    "gn:timezone":"Asia/Ho_Chi_Minh",
    "iso:country":"VN",
    "name:vie_x_preferred":[
        "Na H\u1ed1c"
    ],
    "wof:name":"Na Hoc",
    "wof:placetype":"locality"
},
  "geometry": {"coordinates":[104.70180000000001,19.53863],"type":"Point"}
}