{
  "type": "Feature",
  "properties": {
    "gn:admin1_code":"46.0",
    "gn:asciiname":"An Nhon",
    "gn:country_code":"VN",
    "gn:dem":13,
    "gn:feature_class":"P",
    "gn:feature_code":"PPLA2",
    "gn:name":"An Nh\u01a1n",
    "gn:population":0,
    "gn:timezone":"Asia/Ho_Chi_Minh",
    "iso:country":"VN",
    "name:fas_x_preferred":[
        "\u0628\u062e\u0634 \u0627\u0646 \u0646\u0647\u0627\u0646"
    ],
    "name:jpn_x_preferred":[
        "\u30a2\u30f3\u30cb\u30e7\u30f3"
    ],
    "name:und_x_variant":[
        "Bhin-Dinh",
        "Binh Dinh",
        "Bin Din",
        "An Nh\u01a1n"
    ],
    "name:urd_x_preferred":[
        "\u0622\u0646 \u0646\u06c1\u0624\u0646 \u0636\u0644\u0639"
    ],
    "name:vie_x_preferred":[
        "An Nh\u01a1n"
    ],
    "name:zho_x_preferred":[
        "\u5b89\u4ec1\u5e02\u793e"
    ],
    "wof:name":"An Nhon",
    "wof:placetype":"locality"
},
  "geometry": {"coordinates":[109.10823000000001,13.88579],"type":"Point"}
}