{
  "type": "Feature",
  "properties": {
    "gn:admin1_code":"46.0",
    "gn:asciiname":"An Nhon",
    "gn:country_code":"VN",
    "gn:dem":13,
    "gn:feature_class":"P",
    "gn:feature_code":"PPLA2",
    "gn:name":"An Nh\u01a1n",
    "gn:population":0,
    "gn:timezone":"Asia/Ho_Chi_Minh",
    "iso:country":"VN",
    "name:und_x_variant":[
        "Bhin-Dinh",
        "Binh Dinh",
        "Bin Din",
        "An Nh\u01a1n"
    ],
    "wof:name":"An Nhon",
    "wof:placetype":"locality"
},
  "geometry": {"coordinates":[109.10823000000001,13.88579],"type":"Point"}
}