{
  "type": "Feature",
  "properties": {
    "gn:admin1_code":"58.0",
    "gn:asciiname":"Thanh Lam",
    "gn:country_code":"VN",
    "gn:dem":16,
    "gn:feature_class":"P",
    "gn:feature_code":"PPL",
    "gn:name":"Thanh L\u00e2m",
    "gn:population":0,
    "gn:timezone":"Asia/Ho_Chi_Minh",
    "iso:country":"VN",
    "name:vie_x_preferred":[
        "Thanh L\u00e2m"
    ],
    "wof:name":"Thanh Lam",
    "wof:placetype":"locality"
},
  "geometry": {"coordinates":[105.39697,18.95017],"type":"Point"}
}