{
  "type": "Feature",
  "properties": {
    "gn:admin1_code":"39.0",
    "gn:asciiname":"Khuoi Luong",
    "gn:country_code":"VN",
    "gn:dem":961,
    "gn:feature_class":"P",
    "gn:feature_code":"PPL",
    "gn:name":"Khu\u00f2i L\u01b0\u01a1ng",
    "gn:population":0,
    "gn:timezone":"Asia/Ho_Chi_Minh",
    "iso:country":"VN",
    "wof:name":"Khuoi Luong",
    "wof:placetype":"locality"
},
  "geometry": {"coordinates":[107.01667,21.86667000000001],"type":"Point"}
}