{
  "type": "Feature",
  "properties": {
    "gn:admin1_code":"58.0",
    "gn:asciiname":"Thuan Nghia",
    "gn:country_code":"VN",
    "gn:dem":10,
    "gn:feature_class":"P",
    "gn:feature_code":"PPL",
    "gn:name":"Thu\u1eadn Ngh\u0129a",
    "gn:population":0,
    "gn:timezone":"Asia/Ho_Chi_Minh",
    "iso:country":"VN",
    "name:vie_x_preferred":[
        "Thu\u1eadn Ngh\u0129a"
    ],
    "wof:name":"Thuan Nghia",
    "wof:placetype":"locality"
},
  "geometry": {"coordinates":[105.62000999999999,19.13878],"type":"Point"}
}