{
  "type": "Feature",
  "properties": {
    "gn:admin1_code":"80.0",
    "gn:asciiname":"Quang Tay",
    "gn:country_code":"VN",
    "gn:dem":10,
    "gn:feature_class":"P",
    "gn:feature_code":"PPL",
    "gn:name":"Qu\u1ea3ng T\u00e2y",
    "gn:population":0,
    "gn:timezone":"Asia/Ho_Chi_Minh",
    "iso:country":"VN",
    "name:vie_x_preferred":[
        "Qu\u1ea3ng T\u00e2y"
    ],
    "wof:name":"Quang Tay",
    "wof:placetype":"locality"
},
  "geometry": {"coordinates":[106.01008,20.60062000000001],"type":"Point"}
}