{
  "type": "Feature",
  "properties": {
    "gn:admin1_code":"33.0",
    "gn:asciiname":"Tapang Prey",
    "gn:country_code":"VN",
    "gn:dem":14,
    "gn:feature_class":"P",
    "gn:feature_code":"PPL",
    "gn:name":"Tapang Prey",
    "gn:population":0,
    "gn:timezone":"Asia/Ho_Chi_Minh",
    "iso:country":"VN",
    "wof:name":"Tapang Prey",
    "wof:placetype":"locality"
},
  "geometry": {"coordinates":[105.95,11.51667],"type":"Point"}
}