{
  "type": "Feature",
  "properties": {
    "gn:admin1_code":"39.0",
    "gn:asciiname":"Phieng Khoang",
    "gn:country_code":"VN",
    "gn:dem":185,
    "gn:feature_class":"P",
    "gn:feature_code":"PPL",
    "gn:name":"Phi\u00eang Khoang",
    "gn:population":0,
    "gn:timezone":"Asia/Ho_Chi_Minh",
    "iso:country":"VN",
    "wof:name":"Phieng Khoang",
    "wof:placetype":"locality"
},
  "geometry": {"coordinates":[106.59462000000001,22.06131],"type":"Point"}
}