{
  "type": "Feature",
  "properties": {
    "gn:admin1_code":"32.0",
    "gn:asciiname":"Ban Suoi Cong",
    "gn:country_code":"VN",
    "gn:dem":557,
    "gn:feature_class":"P",
    "gn:feature_code":"PPL",
    "gn:name":"B\u1ea3n Su\u1ed1i Cong",
    "gn:population":0,
    "gn:timezone":"Asia/Ho_Chi_Minh",
    "iso:country":"VN",
    "wof:name":"Ban Suoi Cong",
    "wof:placetype":"locality"
},
  "geometry": {"coordinates":[104.83333,20.83333],"type":"Point"}
}