{
  "type": "Feature",
  "properties": {
    "gn:admin1_code":"58.0",
    "gn:asciiname":"Ke Me",
    "gn:country_code":"VN",
    "gn:dem":52,
    "gn:feature_class":"P",
    "gn:feature_code":"PPL",
    "gn:name":"K\u1ebb M\u1ebb",
    "gn:population":0,
    "gn:timezone":"Asia/Ho_Chi_Minh",
    "iso:country":"VN",
    "name:vie_x_preferred":[
        "K\u1ebb M\u1ebb"
    ],
    "wof:name":"Ke Me",
    "wof:placetype":"locality"
},
  "geometry": {"coordinates":[104.94364,19.07702],"type":"Point"}
}