{
  "type": "Feature",
  "properties": {
    "gn:admin1_code":"83.0",
    "gn:asciiname":"An Thinh",
    "gn:country_code":"VN",
    "gn:dem":68,
    "gn:feature_class":"P",
    "gn:feature_code":"PPL",
    "gn:name":"An Thinh",
    "gn:population":0,
    "gn:timezone":"Asia/Ho_Chi_Minh",
    "iso:country":"VN",
    "name:vie_x_preferred":[
        "An Thinh"
    ],
    "wof:name":"An Thinh",
    "wof:placetype":"locality"
},
  "geometry": {"coordinates":[105.12560000000001,21.55891],"type":"Point"}
}