{
  "type": "Feature",
  "properties": {
    "gn:admin1_code":"5.0",
    "gn:asciiname":"Ban Khung Khoang",
    "gn:country_code":"VN",
    "gn:dem":913,
    "gn:feature_class":"P",
    "gn:feature_code":"PPL",
    "gn:name":"B\u1ea3n Kh\u00f9ng Kho\u00e0ng",
    "gn:population":0,
    "gn:timezone":"Asia/Ho_Chi_Minh",
    "iso:country":"VN",
    "name:vie_x_preferred":[
        "B\u1ea3n Kh\u00f9ng Kho\u00e0ng"
    ],
    "wof:name":"Ban Khung Khoang",
    "wof:placetype":"locality"
},
  "geometry": {"coordinates":[105.46313000000001,22.9034],"type":"Point"}
}