{
  "type": "Feature",
  "properties": {
    "gn:admin1_code":"39.0",
    "gn:asciiname":"Ban Khuoi Co",
    "gn:country_code":"VN",
    "gn:dem":153,
    "gn:feature_class":"P",
    "gn:feature_code":"PPL",
    "gn:name":"B\u1ea3n Khu\u1ed5i C\u1ecd",
    "gn:population":0,
    "gn:timezone":"Asia/Ho_Chi_Minh",
    "iso:country":"VN",
    "name:und_x_variant":[
        "B\u1ea3n Khu\u1ed5i C\u1ecd",
        "Khu\u00f4i C\u1ed5"
    ],
    "wof:name":"Ban Khuoi Co",
    "wof:placetype":"locality"
},
  "geometry": {"coordinates":[106.63418,22.19611],"type":"Point"}
}