{
  "type": "Feature",
  "properties": {
    "gn:admin1_code":"58.0",
    "gn:asciiname":"Xom Trong",
    "gn:country_code":"VN",
    "gn:dem":9,
    "gn:feature_class":"P",
    "gn:feature_code":"PPL",
    "gn:name":"X\u00f3m Trong",
    "gn:population":0,
    "gn:timezone":"Asia/Ho_Chi_Minh",
    "iso:country":"VN",
    "name:und_x_variant":[
        "X\u00f3m Trung"
    ],
    "name:vie_x_preferred":[
        "X\u00f3m Trong"
    ],
    "wof:name":"Xom Trong",
    "wof:placetype":"locality"
},
  "geometry": {"coordinates":[105.57249,18.98584],"type":"Point"}
}