{
  "type": "Feature",
  "properties": {
    "gn:admin1_code":"74.0",
    "gn:asciiname":"Pho Moi",
    "gn:country_code":"VN",
    "gn:dem":8,
    "gn:feature_class":"P",
    "gn:feature_code":"PPL",
    "gn:name":"Ph\u1ed1 M\u1edbi",
    "gn:population":0,
    "gn:timezone":"Asia/Ho_Chi_Minh",
    "iso:country":"VN",
    "name:vie_x_preferred":[
        "Ph\u1ed1 M\u1edbi"
    ],
    "wof:name":"Pho Moi",
    "wof:placetype":"locality"
},
  "geometry": {"coordinates":[106.0872,21.05461],"type":"Point"}
}