{
  "type": "Feature",
  "properties": {
    "gn:admin1_code":"67.0",
    "gn:asciiname":"Thanh Nguyen",
    "gn:cc2":"VN",
    "gn:country_code":"VN",
    "gn:dem":2,
    "gn:feature_class":"P",
    "gn:feature_code":"PPL",
    "gn:name":"Thanh Nguy\u00ean",
    "gn:population":0,
    "gn:timezone":"Asia/Ho_Chi_Minh",
    "iso:country":"VN",
    "name:und_x_variant":[
        "Nguy\u00ean",
        "Thanh Nguy\u00ean"
    ],
    "wof:name":"Thanh Nguyen",
    "wof:placetype":"locality"
},
  "geometry": {"coordinates":[106.34556000000001,9.84778],"type":"Point"}
}