{
  "type": "Feature",
  "properties": {
    "gn:admin1_code":"58.0",
    "gn:asciiname":"Truong Lung",
    "gn:country_code":"VN",
    "gn:dem":30,
    "gn:feature_class":"P",
    "gn:feature_code":"PPL",
    "gn:name":"Tru\u00f4ng L\u01b0ng",
    "gn:population":0,
    "gn:timezone":"Asia/Ho_Chi_Minh",
    "iso:country":"VN",
    "name:vie_x_preferred":[
        "Tru\u00f4ng L\u01b0ng"
    ],
    "wof:name":"Truong Lung",
    "wof:placetype":"locality"
},
  "geometry": {"coordinates":[105.37899,18.9091],"type":"Point"}
}