{
  "type": "Feature",
  "properties": {
    "gn:admin1_code":"62.0",
    "gn:asciiname":"Cat Dang Sach",
    "gn:country_code":"VN",
    "gn:dem":369,
    "gn:feature_class":"P",
    "gn:feature_code":"PPL",
    "gn:name":"C\u00e1t \u0110\u1eafng S\u00e1ch",
    "gn:population":0,
    "gn:timezone":"Asia/Ho_Chi_Minh",
    "iso:country":"VN",
    "wof:name":"Cat Dang Sach",
    "wof:placetype":"locality"
},
  "geometry": {"coordinates":[105.91667,17.75],"type":"Point"}
}