{
  "type": "Feature",
  "properties": {
    "gn:admin1_code":"30.0",
    "gn:asciiname":"Luc Na",
    "gn:country_code":"VN",
    "gn:dem":246,
    "gn:feature_class":"P",
    "gn:feature_code":"PPL",
    "gn:name":"L\u1ee5c Na",
    "gn:population":0,
    "gn:timezone":"Asia/Ho_Chi_Minh",
    "iso:country":"VN",
    "wof:name":"Luc Na",
    "wof:placetype":"locality"
},
  "geometry": {"coordinates":[107.43333,21.53333],"type":"Point"}
}