{
  "type": "Feature",
  "properties": {
    "gn:admin1_code":"52.0",
    "gn:asciiname":"Vinh Nga",
    "gn:country_code":"VN",
    "gn:dem":6,
    "gn:feature_class":"P",
    "gn:feature_code":"PPL",
    "gn:name":"Vinh Ng\u00e1",
    "gn:population":0,
    "gn:timezone":"Asia/Ho_Chi_Minh",
    "iso:country":"VN",
    "name:und_x_variant":[
        "Vinh Nha",
        "Vinh Ng\u00e1"
    ],
    "wof:name":"Vinh Nga",
    "wof:placetype":"locality"
},
  "geometry": {"coordinates":[105.86667,18.31667],"type":"Point"}
}