{
  "type": "Feature",
  "properties": {
    "gn:admin1_code":"61.0",
    "gn:asciiname":"Le Bach",
    "gn:country_code":"VN",
    "gn:dem":199,
    "gn:feature_class":"P",
    "gn:feature_code":"PPL",
    "gn:name":"L\u00ea B\u00e1ch",
    "gn:population":0,
    "gn:timezone":"Asia/Ho_Chi_Minh",
    "iso:country":"VN",
    "name:vie_x_preferred":[
        "L\u00ea B\u00e1ch"
    ],
    "wof:name":"Le Bach",
    "wof:placetype":"locality"
},
  "geometry": {"coordinates":[108.86933999999999,12.96847],"type":"Point"}
}