{
  "type": "Feature",
  "properties": {
    "gn:admin1_code":"90.0",
    "gn:asciiname":"Chinh Cuong",
    "gn:country_code":"VN",
    "gn:dem":136,
    "gn:feature_class":"P",
    "gn:feature_code":"PPL",
    "gn:name":"Ch\u00ednh C\u01b0\u1eddng",
    "gn:population":0,
    "gn:timezone":"Asia/Ho_Chi_Minh",
    "iso:country":"VN",
    "name:vie_x_preferred":[
        "Ch\u00ednh C\u01b0\u1eddng"
    ],
    "wof:name":"Chinh Cuong",
    "wof:placetype":"locality"
},
  "geometry": {"coordinates":[103.97254,22.47188],"type":"Point"}
}