{
  "type": "Feature",
  "properties": {
    "gn:admin1_code":"46.0",
    "gn:asciiname":"Vinh An",
    "gn:country_code":"VN",
    "gn:dem":15,
    "gn:feature_class":"P",
    "gn:feature_code":"PPL",
    "gn:name":"V\u0129nh An",
    "gn:population":0,
    "gn:timezone":"Asia/Ho_Chi_Minh",
    "iso:country":"VN",
    "name:und_x_variant":[
        "V\u0129nh \u00c2n"
    ],
    "name:vie_x_preferred":[
        "V\u0129nh An"
    ],
    "wof:name":"Vinh An",
    "wof:placetype":"locality"
},
  "geometry": {"coordinates":[109.10796999999999,14.26509],"type":"Point"}
}