{
  "type": "Feature",
  "properties": {
    "gn:admin1_code":"55.0",
    "gn:asciiname":"Dak Mot Kram",
    "gn:country_code":"VN",
    "gn:dem":637,
    "gn:feature_class":"P",
    "gn:feature_code":"PPL",
    "gn:name":"Dak Mot Kram",
    "gn:population":0,
    "gn:timezone":"Asia/Ho_Chi_Minh",
    "iso:country":"VN",
    "name:und_x_variant":[
        "Dak Mor Kram",
        "Dak Mot Kram"
    ],
    "wof:name":"Dak Mot Kram",
    "wof:placetype":"locality"
},
  "geometry": {"coordinates":[107.73333,14.66667],"type":"Point"}
}