{
  "type": "Feature",
  "properties": {
    "gn:admin1_code":"58.0",
    "gn:asciiname":"But Lien",
    "gn:country_code":"VN",
    "gn:dem":6,
    "gn:feature_class":"P",
    "gn:feature_code":"PPL",
    "gn:name":"B\u00fat Li\u1ec5n",
    "gn:population":0,
    "gn:timezone":"Asia/Ho_Chi_Minh",
    "iso:country":"VN",
    "name:und_x_variant":[
        "But Lun",
        "B\u00fat Li\u1ec5n"
    ],
    "wof:name":"But Lien",
    "wof:placetype":"locality"
},
  "geometry": {"coordinates":[105.68333,19.11667000000001],"type":"Point"}
}