{
  "type": "Feature",
  "properties": {
    "gn:admin1_code":"66.0",
    "gn:asciiname":"An Do",
    "gn:country_code":"VN",
    "gn:dem":8,
    "gn:feature_class":"P",
    "gn:feature_code":"PPL",
    "gn:name":"An Do",
    "gn:population":0,
    "gn:timezone":"Asia/Ho_Chi_Minh",
    "iso:country":"VN",
    "name:und_x_variant":[
        "Th\u00f4n An \u0110\u00f4"
    ],
    "name:vie_x_preferred":[
        "An \u0110\u00f4"
    ],
    "wof:name":"An Do",
    "wof:placetype":"locality"
},
  "geometry": {"coordinates":[107.50006,16.48938],"type":"Point"}
}