{
  "type": "Feature",
  "properties": {
    "gn:admin1_code":"68.0",
    "gn:asciiname":"Khau Muon",
    "gn:country_code":"VN",
    "gn:dem":480,
    "gn:feature_class":"P",
    "gn:feature_code":"PPL",
    "gn:name":"Khau Mu\u1ed3n",
    "gn:population":0,
    "gn:timezone":"Asia/Ho_Chi_Minh",
    "iso:country":"VN",
    "name:vie_x_preferred":[
        "Khau Mu\u1ed3n"
    ],
    "wof:name":"Khau Muon",
    "wof:placetype":"locality"
},
  "geometry": {"coordinates":[105.4599,22.48516],"type":"Point"}
}