{
  "type": "Feature",
  "properties": {
    "gn:admin1_code":"5.0",
    "gn:asciiname":"Loung Vai",
    "gn:country_code":"VN",
    "gn:dem":499,
    "gn:feature_class":"P",
    "gn:feature_code":"PPL",
    "gn:name":"Loung Vai",
    "gn:population":0,
    "gn:timezone":"Asia/Ho_Chi_Minh",
    "iso:country":"VN",
    "wof:name":"Loung Vai",
    "wof:placetype":"locality"
},
  "geometry": {"coordinates":[105.59999999999999,22.98333],"type":"Point"}
}