{
  "type": "Feature",
  "properties": {
    "gn:admin1_code":"63.0",
    "gn:asciiname":"Dien Son",
    "gn:country_code":"VN",
    "gn:dem":22,
    "gn:feature_class":"P",
    "gn:feature_code":"PPL",
    "gn:name":"Di\u1ebfn S\u01a1n",
    "gn:population":0,
    "gn:timezone":"Asia/Ho_Chi_Minh",
    "iso:country":"VN",
    "name:vie_x_preferred":[
        "Di\u1ebfn S\u01a1n"
    ],
    "wof:name":"Dien Son",
    "wof:placetype":"locality"
},
  "geometry": {"coordinates":[108.72057,15.00587],"type":"Point"}
}