{
  "type": "Feature",
  "properties": {
    "gn:admin1_code":"47.0",
    "gn:asciiname":"Ke Bou",
    "gn:country_code":"VN",
    "gn:dem":286,
    "gn:feature_class":"P",
    "gn:feature_code":"PPL",
    "gn:name":"K\u00e9 Bou",
    "gn:population":0,
    "gn:timezone":"Asia/Ho_Chi_Minh",
    "iso:country":"VN",
    "wof:name":"Ke Bou",
    "wof:placetype":"locality"
},
  "geometry": {"coordinates":[108.23333,11.31667],"type":"Point"}
}