{
  "type": "Feature",
  "properties": {
    "gn:admin1_code":"32.0",
    "gn:asciiname":"Tsi Ong",
    "gn:country_code":"VN",
    "gn:dem":1007,
    "gn:feature_class":"P",
    "gn:feature_code":"PPL",
    "gn:name":"Tsi Ong",
    "gn:population":0,
    "gn:timezone":"Asia/Ho_Chi_Minh",
    "iso:country":"VN",
    "name:und_x_variant":[
        "Tei Ong",
        "Tsi Ong"
    ],
    "wof:name":"Tsi Ong",
    "wof:placetype":"locality"
},
  "geometry": {"coordinates":[104.63333,21.33333],"type":"Point"}
}