{
  "type": "Feature",
  "properties": {
    "gn:admin1_code":"34.0",
    "gn:asciiname":"Quang Th",
    "gn:cc2":"VN",
    "gn:country_code":"VN",
    "gn:dem":17,
    "gn:feature_class":"P",
    "gn:feature_code":"PPL",
    "gn:name":"Qu\u1ea3ng Th",
    "gn:population":0,
    "gn:timezone":"Asia/Ho_Chi_Minh",
    "iso:country":"VN",
    "name:und_x_variant":[
        "Cho Dam",
        "Chu Dam",
        "Qu\u1ea3ng Th"
    ],
    "wof:name":"Quang Th",
    "wof:placetype":"locality"
},
  "geometry": {"coordinates":[105.43333,19.95],"type":"Point"}
}