{
  "type": "Feature",
  "properties": {
    "gn:admin1_code":"70.0",
    "gn:asciiname":"Thuong Bang La",
    "gn:country_code":"VN",
    "gn:dem":140,
    "gn:feature_class":"P",
    "gn:feature_code":"PPL",
    "gn:name":"Th\u01b0\u1ee3ng B\u1eafng La",
    "gn:population":0,
    "gn:timezone":"Asia/Ho_Chi_Minh",
    "iso:country":"VN",
    "wof:name":"Thuong Bang La",
    "wof:placetype":"locality"
},
  "geometry": {"coordinates":[104.78333000000001,21.41667],"type":"Point"}
}