{
  "type": "Feature",
  "properties": {
    "gn:admin1_code":"84.0",
    "gn:asciiname":"Ap Hai",
    "gn:country_code":"VN",
    "gn:dem":36,
    "gn:feature_class":"P",
    "gn:feature_code":"PPL",
    "gn:name":"\u1ea4p Hai",
    "gn:population":0,
    "gn:timezone":"Asia/Ho_Chi_Minh",
    "iso:country":"VN",
    "name:und_x_variant":[
        "Trung L\u1ed9c",
        "\u1ea4p Hai"
    ],
    "wof:name":"Ap Hai",
    "wof:placetype":"locality"
},
  "geometry": {"coordinates":[108.11667,15.68333],"type":"Point"}
}