{
  "type": "Feature",
  "properties": {
    "gn:admin1_code":"54.0",
    "gn:asciiname":"Thon Tra Long",
    "gn:country_code":"VN",
    "gn:dem":15,
    "gn:feature_class":"P",
    "gn:feature_code":"PPL",
    "gn:name":"Th\u00f4n Tr\u00e0 Long",
    "gn:population":0,
    "gn:timezone":"Asia/Ho_Chi_Minh",
    "iso:country":"VN",
    "wof:name":"Thon Tra Long",
    "wof:placetype":"locality"
},
  "geometry": {"coordinates":[109.13333,11.91667],"type":"Point"}
}