{
  "type": "Feature",
  "properties": {
    "gn:admin1_code":"13.0",
    "gn:asciiname":"My Son",
    "gn:country_code":"VN",
    "gn:dem":8,
    "gn:feature_class":"P",
    "gn:feature_code":"PPL",
    "gn:name":"M\u1ef9 S\u01a1n",
    "gn:population":0,
    "gn:timezone":"Asia/Ho_Chi_Minh",
    "iso:country":"VN",
    "name:und_x_variant":[
        "My S\u01a1n"
    ],
    "name:vie_x_preferred":[
        "M\u1ef9 S\u01a1n"
    ],
    "wof:name":"My Son",
    "wof:placetype":"locality"
},
  "geometry": {"coordinates":[106.73754,20.94256],"type":"Point"}
}