{
  "type": "Feature",
  "properties": {
    "gn:admin1_code":"83.0",
    "gn:asciiname":"Quan Chanh",
    "gn:country_code":"VN",
    "gn:dem":22,
    "gn:feature_class":"P",
    "gn:feature_code":"PPL",
    "gn:name":"Quan Ch\u00e0nh",
    "gn:population":0,
    "gn:timezone":"Asia/Ho_Chi_Minh",
    "iso:country":"VN",
    "name:vie_x_preferred":[
        "Quan Ch\u00e0nh"
    ],
    "wof:name":"Quan Chanh",
    "wof:placetype":"locality"
},
  "geometry": {"coordinates":[105.17744,21.33979],"type":"Point"}
}