{
  "type": "Feature",
  "properties": {
    "gn:admin1_code":"83.0",
    "gn:asciiname":"Xom Chieng",
    "gn:country_code":"VN",
    "gn:dem":80,
    "gn:feature_class":"P",
    "gn:feature_code":"PPL",
    "gn:name":"X\u00f3m Chi\u1ec1ng",
    "gn:population":0,
    "gn:timezone":"Asia/Ho_Chi_Minh",
    "iso:country":"VN",
    "name:und_x_variant":[
        "X\u00f3m Chung"
    ],
    "name:vie_x_preferred":[
        "X\u00f3m Chi\u1ec1ng"
    ],
    "wof:name":"Xom Chieng",
    "wof:placetype":"locality"
},
  "geometry": {"coordinates":[105.10893,21.2554],"type":"Point"}
}