{
  "type": "Feature",
  "properties": {
    "gn:admin1_code":"44.0",
    "gn:asciiname":"Dan The",
    "gn:country_code":"VN",
    "gn:dem":19,
    "gn:feature_class":"P",
    "gn:feature_code":"PPL",
    "gn:name":"\u0110an Th\u00ea",
    "gn:population":0,
    "gn:timezone":"Asia/Ho_Chi_Minh",
    "iso:country":"VN",
    "name:vie_x_preferred":[
        "\u0110an Th\u00ea"
    ],
    "wof:name":"Dan The",
    "wof:placetype":"locality"
},
  "geometry": {"coordinates":[105.30379000000001,21.17433],"type":"Point"}
}