{
  "type": "Feature",
  "properties": {
    "gn:admin1_code":"50.0",
    "gn:asciiname":"Tcha Loung",
    "gn:country_code":"VN",
    "gn:dem":1219,
    "gn:feature_class":"P",
    "gn:feature_code":"PPL",
    "gn:name":"Tcha Loung",
    "gn:population":0,
    "gn:timezone":"Asia/Ho_Chi_Minh",
    "iso:country":"VN",
    "wof:name":"Tcha Loung",
    "wof:placetype":"locality"
},
  "geometry": {"coordinates":[105.45,23.16667],"type":"Point"}
}