{
  "type": "Feature",
  "properties": {
    "gn:admin1_code":"46.0",
    "gn:asciiname":"Nghia Nhon",
    "gn:country_code":"VN",
    "gn:dem":36,
    "gn:feature_class":"P",
    "gn:feature_code":"PPL",
    "gn:name":"Ngh\u0129a Nh\u01a1n",
    "gn:population":0,
    "gn:timezone":"Asia/Ho_Chi_Minh",
    "iso:country":"VN",
    "name:vie_x_preferred":[
        "Ngh\u0129a Nh\u01a1n"
    ],
    "wof:name":"Nghia Nhon",
    "wof:placetype":"locality"
},
  "geometry": {"coordinates":[108.85245,14.29865],"type":"Point"}
}