{
  "type": "Feature",
  "properties": {
    "gn:admin1_code":"90.0",
    "gn:asciiname":"Lang Giou",
    "gn:country_code":"VN",
    "gn:dem":174,
    "gn:feature_class":"P",
    "gn:feature_code":"PPL",
    "gn:name":"L\u00e0ng Giou",
    "gn:population":0,
    "gn:timezone":"Asia/Ho_Chi_Minh",
    "iso:country":"VN",
    "name:und_x_variant":[
        "L\u00e0ng Dau"
    ],
    "name:vie_x_preferred":[
        "L\u00e0ng Giou"
    ],
    "wof:name":"Lang Giou",
    "wof:placetype":"locality"
},
  "geometry": {"coordinates":[104.56243000000001,22.14953],"type":"Point"}
}