{
  "type": "Feature",
  "properties": {
    "gn:admin1_code":"32.0",
    "gn:asciiname":"Ban Khoang",
    "gn:country_code":"VN",
    "gn:dem":137,
    "gn:feature_class":"P",
    "gn:feature_code":"PPL",
    "gn:name":"B\u1ea3n Kho\u00e1ng",
    "gn:population":0,
    "gn:timezone":"Asia/Ho_Chi_Minh",
    "iso:country":"VN",
    "name:vie_x_preferred":[
        "B\u1ea3n Kho\u00e1ng"
    ],
    "wof:name":"Ban Khoang",
    "wof:placetype":"locality"
},
  "geometry": {"coordinates":[104.85294,21.07807],"type":"Point"}
}