{
  "type": "Feature",
  "properties": {
    "gn:admin1_code":"64.0",
    "gn:asciiname":"Lang Tich Tuong",
    "gn:country_code":"VN",
    "gn:dem":16,
    "gn:feature_class":"P",
    "gn:feature_code":"PPL",
    "gn:name":"L\u00e0ng T\u00edch T\u01b0\u1eddng",
    "gn:population":0,
    "gn:timezone":"Asia/Ho_Chi_Minh",
    "iso:country":"VN",
    "name:und_x_variant":[
        "Tich Tuong",
        "L\u00e0ng T\u00edch T\u01b0\u1eddng"
    ],
    "wof:name":"Lang Tich Tuong",
    "wof:placetype":"locality"
},
  "geometry": {"coordinates":[107.18333,16.71667],"type":"Point"}
}