{
  "type": "Feature",
  "properties": {
    "gn:admin1_code":"50.0",
    "gn:asciiname":"Phu Cao",
    "gn:country_code":"VN",
    "gn:dem":1377,
    "gn:feature_class":"P",
    "gn:feature_code":"PPL",
    "gn:name":"Ph\u00fa Cao",
    "gn:population":0,
    "gn:timezone":"Asia/Ho_Chi_Minh",
    "iso:country":"VN",
    "name:und_x_variant":[
        "Pho Cao",
        "Ph\u00fa Cao"
    ],
    "wof:name":"Phu Cao",
    "wof:placetype":"locality"
},
  "geometry": {"coordinates":[105.16667,23.21667],"type":"Point"}
}