{
  "type": "Feature",
  "properties": {
    "gn:admin1_code":"73.0",
    "gn:asciiname":"Trung Hung",
    "gn:country_code":"VN",
    "gn:dem":0,
    "gn:feature_class":"P",
    "gn:feature_code":"PPL",
    "gn:name":"Trung H\u01b0ng",
    "gn:population":0,
    "gn:timezone":"Asia/Ho_Chi_Minh",
    "iso:country":"VN",
    "name:und_x_variant":[
        "\u1ea4p Trung H\u01b0ng"
    ],
    "name:vie_x_preferred":[
        "Trung H\u01b0ng"
    ],
    "wof:name":"Trung Hung",
    "wof:placetype":"locality"
},
  "geometry": {"coordinates":[105.56791,9.38898],"type":"Point"}
}