{
  "type": "Feature",
  "properties": {
    "gn:admin1_code":"47.0",
    "gn:asciiname":"Suoi Da",
    "gn:country_code":"VN",
    "gn:dem":31,
    "gn:feature_class":"P",
    "gn:feature_code":"PPL",
    "gn:name":"Su\u1ed1i Da",
    "gn:population":0,
    "gn:timezone":"Asia/Ho_Chi_Minh",
    "iso:country":"VN",
    "wof:name":"Suoi Da",
    "wof:placetype":"locality"
},
  "geometry": {"coordinates":[108.09999999999999,11.08333],"type":"Point"}
}