{
  "type": "Feature",
  "properties": {
    "gn:admin1_code":"52.0",
    "gn:asciiname":"Dong Tien",
    "gn:country_code":"VN",
    "gn:dem":7,
    "gn:feature_class":"P",
    "gn:feature_code":"PPL",
    "gn:name":"\u0110\u1ed3ng Ti\u1ebfn",
    "gn:population":0,
    "gn:timezone":"Asia/Ho_Chi_Minh",
    "iso:country":"VN",
    "name:vie_x_preferred":[
        "\u0110\u1ed3ng Ti\u1ebfn"
    ],
    "wof:name":"Dong Tien",
    "wof:placetype":"locality"
},
  "geometry": {"coordinates":[106.26508,18.1632],"type":"Point"}
}