{
  "type": "Feature",
  "properties": {
    "gn:admin1_code":"58.0",
    "gn:asciiname":"Hung Nghia",
    "gn:country_code":"VN",
    "gn:dem":110,
    "gn:feature_class":"P",
    "gn:feature_code":"PPL",
    "gn:name":"H\u01b0ng Ngh\u0129a",
    "gn:population":0,
    "gn:timezone":"Asia/Ho_Chi_Minh",
    "iso:country":"VN",
    "name:vie_x_preferred":[
        "H\u01b0ng Ngh\u0129a"
    ],
    "wof:name":"Hung Nghia",
    "wof:placetype":"locality"
},
  "geometry": {"coordinates":[105.51981000000001,19.37698],"type":"Point"}
}