{
  "type": "Feature",
  "properties": {
    "gn:admin1_code":"89.0",
    "gn:asciiname":"Chu Va Muoi Hai",
    "gn:country_code":"VN",
    "gn:dem":952,
    "gn:feature_class":"P",
    "gn:feature_code":"PPL",
    "gn:name":"Chu Va M\u01b0\u1eddi Hai",
    "gn:population":0,
    "gn:timezone":"Asia/Ho_Chi_Minh",
    "iso:country":"VN",
    "name:und_x_variant":[
        "Tcho Va",
        "Tchou Va"
    ],
    "name:vie_x_preferred":[
        "Chu Va M\u01b0\u1eddi Hai"
    ],
    "name:vie_x_variant":[
        "Chu Va 12"
    ],
    "wof:name":"Chu Va Muoi Hai",
    "wof:placetype":"locality"
},
  "geometry": {"coordinates":[103.6913,22.35073],"type":"Point"}
}