{
  "type": "Feature",
  "properties": {
    "gn:admin1_code":"63.0",
    "gn:asciiname":"Mang K Ra",
    "gn:country_code":"VN",
    "gn:dem":220,
    "gn:feature_class":"P",
    "gn:feature_code":"PPL",
    "gn:name":"Mang K R\u00e1",
    "gn:population":0,
    "gn:timezone":"Asia/Ho_Chi_Minh",
    "iso:country":"VN",
    "name:vie_x_preferred":[
        "Mang K R\u00e1"
    ],
    "wof:name":"Mang K Ra",
    "wof:placetype":"locality"
},
  "geometry": {"coordinates":[108.55753,14.65858],"type":"Point"}
}