{
  "type": "Feature",
  "properties": {
    "gn:admin1_code":"33.0",
    "gn:asciiname":"Bau Tram",
    "gn:cc2":"VN",
    "gn:country_code":"VN",
    "gn:dem":43,
    "gn:feature_class":"P",
    "gn:feature_code":"PPL",
    "gn:name":"B\u00e0u Tr\u00e2m",
    "gn:population":0,
    "gn:timezone":"Asia/Ho_Chi_Minh",
    "iso:country":"VN",
    "name:und_x_variant":[
        "Bau Cham",
        "B\u00e0u Tr\u00e2m"
    ],
    "wof:name":"Bau Tram",
    "wof:placetype":"locality"
},
  "geometry": {"coordinates":[106.38333,11.53333],"type":"Point"}
}