{
  "type": "Feature",
  "properties": {
    "gn:admin1_code":"58.0",
    "gn:asciiname":"Xuan Phuc",
    "gn:country_code":"VN",
    "gn:dem":7,
    "gn:feature_class":"P",
    "gn:feature_code":"PPL",
    "gn:name":"Xu\u00e2n Ph\u00fac",
    "gn:population":0,
    "gn:timezone":"Asia/Ho_Chi_Minh",
    "iso:country":"VN",
    "name:vie_x_preferred":[
        "Xu\u00e2n Ph\u00fac"
    ],
    "wof:name":"Xuan Phuc",
    "wof:placetype":"locality"
},
  "geometry": {"coordinates":[105.72087999999999,18.75455],"type":"Point"}
}