{
  "type": "Feature",
  "properties": {
    "gn:admin1_code":"90.0",
    "gn:asciiname":"Diu Co Van",
    "gn:country_code":"VN",
    "gn:dem":1564,
    "gn:feature_class":"P",
    "gn:feature_code":"PPL",
    "gn:name":"D\u00ecu C\u1ed3 V\u00e1n",
    "gn:population":0,
    "gn:timezone":"Asia/Ho_Chi_Minh",
    "iso:country":"VN",
    "name:vie_x_preferred":[
        "D\u00ecu C\u1ed3 V\u00e1n"
    ],
    "wof:name":"Diu Co Van",
    "wof:placetype":"locality"
},
  "geometry": {"coordinates":[104.26643,22.62298],"type":"Point"}
}