{
  "type": "Feature",
  "properties": {
    "gn:admin1_code":"75.0",
    "gn:asciiname":"Phu Loi Hai",
    "gn:country_code":"VN",
    "gn:dem":31,
    "gn:feature_class":"P",
    "gn:feature_code":"PPL",
    "gn:name":"Ph\u00fa L\u1ee3i Hai",
    "gn:population":0,
    "gn:timezone":"Asia/Ho_Chi_Minh",
    "iso:country":"VN",
    "name:und_x_variant":[
        "Ph\u00fa L\u1ee3i"
    ],
    "name:vie_x_preferred":[
        "Ph\u00fa L\u1ee3i Hai"
    ],
    "name:vie_x_variant":[
        "Ph\u00fa L\u1ee3i 2"
    ],
    "wof:name":"Phu Loi Hai",
    "wof:placetype":"locality"
},
  "geometry": {"coordinates":[106.67821000000001,10.98895],"type":"Point"}
}