{
  "type": "Feature",
  "properties": {
    "gn:admin1_code":"5.0",
    "gn:asciiname":"Coc Tram",
    "gn:country_code":"VN",
    "gn:dem":187,
    "gn:feature_class":"P",
    "gn:feature_code":"PPL",
    "gn:name":"C\u1ed1c Tr\u00e2m",
    "gn:population":0,
    "gn:timezone":"Asia/Ho_Chi_Minh",
    "iso:country":"VN",
    "name:vie_x_preferred":[
        "C\u1ed1c Tr\u00e2m"
    ],
    "wof:name":"Coc Tram",
    "wof:placetype":"locality"
},
  "geometry": {"coordinates":[105.59926000000002,22.95824],"type":"Point"}
}