{
  "type": "Feature",
  "properties": {
    "gn:admin1_code":"53.0",
    "gn:asciiname":"Xom Bua",
    "gn:country_code":"VN",
    "gn:dem":151,
    "gn:feature_class":"P",
    "gn:feature_code":"PPL",
    "gn:name":"X\u00f3m Bua",
    "gn:population":0,
    "gn:timezone":"Asia/Ho_Chi_Minh",
    "iso:country":"VN",
    "name:vie_x_preferred":[
        "X\u00f3m Bua"
    ],
    "wof:name":"Xom Bua",
    "wof:placetype":"locality"
},
  "geometry": {"coordinates":[105.22287,20.6418],"type":"Point"}
}