{
  "type": "Feature",
  "properties": {
    "gn:admin1_code":"77.0",
    "gn:asciiname":"Thi Tuong",
    "gn:country_code":"VN",
    "gn:dem":3,
    "gn:feature_class":"P",
    "gn:feature_code":"PPL",
    "gn:name":"Th\u1ecb T\u01b0\u1eddng",
    "gn:population":0,
    "gn:timezone":"Asia/Ho_Chi_Minh",
    "iso:country":"VN",
    "name:und_x_variant":[
        "Xom Thi Tuong",
        "Thi Tuong",
        "\u1ea4p Thi T\u01b0\u1eddng"
    ],
    "name:vie_x_preferred":[
        "Th\u1ecb T\u01b0\u1eddng"
    ],
    "wof:name":"Thi Tuong",
    "wof:placetype":"locality"
},
  "geometry": {"coordinates":[104.96850999999999,9.00799],"type":"Point"}
}