{
  "type": "Feature",
  "properties": {
    "gn:admin1_code":"69.0",
    "gn:asciiname":"Phuoc Loc",
    "gn:country_code":"VN",
    "gn:dem":2,
    "gn:feature_class":"P",
    "gn:feature_code":"PPL",
    "gn:name":"Ph\u01b0\u1edbc L\u1ed9c",
    "gn:population":0,
    "gn:timezone":"Asia/Ho_Chi_Minh",
    "iso:country":"VN",
    "name:und_x_variant":[
        "\u1ea4p Ph\u01b0\u1edbc L\u1ed9c"
    ],
    "name:vie_x_preferred":[
        "Ph\u01b0\u1edbc L\u1ed9c"
    ],
    "wof:name":"Phuoc Loc",
    "wof:placetype":"locality"
},
  "geometry": {"coordinates":[106.02817,10.16943],"type":"Point"}
}