{
  "type": "Feature",
  "properties": {
    "gn:admin1_code":"71.0",
    "gn:asciiname":"Phung Hung",
    "gn:country_code":"VN",
    "gn:dem":6,
    "gn:feature_class":"P",
    "gn:feature_code":"PPL",
    "gn:name":"Ph\u00f9ng H\u01b0ng",
    "gn:population":0,
    "gn:timezone":"Asia/Ho_Chi_Minh",
    "iso:country":"VN",
    "name:vie_x_preferred":[
        "Ph\u00f9ng H\u01b0ng"
    ],
    "wof:name":"Phung Hung",
    "wof:placetype":"locality"
},
  "geometry": {"coordinates":[106.2456,21.18407],"type":"Point"}
}