{
  "type": "Feature",
  "properties": {
    "gn:admin1_code":"34.0",
    "gn:asciiname":"Tao Thon",
    "gn:country_code":"VN",
    "gn:dem":10,
    "gn:feature_class":"P",
    "gn:feature_code":"PPL",
    "gn:name":"T\u00e0o Th\u00f4n",
    "gn:population":0,
    "gn:timezone":"Asia/Ho_Chi_Minh",
    "iso:country":"VN",
    "wof:name":"Tao Thon",
    "wof:placetype":"locality"
},
  "geometry": {"coordinates":[105.76667,19.58333],"type":"Point"}
}