{
  "type": "Feature",
  "properties": {
    "gn:admin1_code":"53.0",
    "gn:asciiname":"Dong Danh",
    "gn:country_code":"VN",
    "gn:dem":620,
    "gn:feature_class":"P",
    "gn:feature_code":"PPL",
    "gn:name":"\u0110ong \u0110anh",
    "gn:population":0,
    "gn:timezone":"Asia/Ho_Chi_Minh",
    "iso:country":"VN",
    "wof:name":"Dong Danh",
    "wof:placetype":"locality"
},
  "geometry": {"coordinates":[105.41667,20.65],"type":"Point"}
}