{
  "type": "Feature",
  "properties": {
    "gn:admin1_code":"75.0",
    "gn:asciiname":"Ap Chin",
    "gn:country_code":"VN",
    "gn:dem":53,
    "gn:feature_class":"P",
    "gn:feature_code":"PPL",
    "gn:name":"\u1ea4p Ch\u00edn",
    "gn:population":0,
    "gn:timezone":"Asia/Ho_Chi_Minh",
    "iso:country":"VN",
    "name:vie_x_preferred":[
        "\u1ea4p Ch\u00edn"
    ],
    "name:vie_x_variant":[
        "\u1ea4p 9"
    ],
    "wof:name":"Ap Chin",
    "wof:placetype":"locality"
},
  "geometry": {"coordinates":[106.72673,11.37354],"type":"Point"}
}