{
  "type": "Feature",
  "properties": {
    "gn:admin1_code":"32.0",
    "gn:asciiname":"Ban Phang",
    "gn:country_code":"VN",
    "gn:dem":745,
    "gn:feature_class":"P",
    "gn:feature_code":"PPL",
    "gn:name":"B\u1ea3n Ph\u1eb7ng",
    "gn:population":0,
    "gn:timezone":"Asia/Ho_Chi_Minh",
    "iso:country":"VN",
    "wof:name":"Ban Phang",
    "wof:placetype":"locality"
},
  "geometry": {"coordinates":[103.76667,21.38333],"type":"Point"}
}