{
  "type": "Feature",
  "properties": {
    "gn:admin1_code":"70.0",
    "gn:asciiname":"Chem",
    "gn:country_code":"VN",
    "gn:dem":53,
    "gn:feature_class":"P",
    "gn:feature_code":"PPL",
    "gn:name":"Ch\u00e8m",
    "gn:population":0,
    "gn:timezone":"Asia/Ho_Chi_Minh",
    "iso:country":"VN",
    "name:vie_x_preferred":[
        "Ch\u00e8m"
    ],
    "wof:name":"Chem",
    "wof:placetype":"locality"
},
  "geometry": {"coordinates":[104.58265,21.94709],"type":"Point"}
}