{
  "type": "Feature",
  "properties": {
    "gn:admin1_code":"72.0",
    "gn:asciiname":"Coc Tao",
    "gn:country_code":"VN",
    "gn:dem":252,
    "gn:feature_class":"P",
    "gn:feature_code":"PPL",
    "gn:name":"C\u1ed1c T\u00e0o",
    "gn:population":0,
    "gn:timezone":"Asia/Ho_Chi_Minh",
    "iso:country":"VN",
    "wof:name":"Coc Tao",
    "wof:placetype":"locality"
},
  "geometry": {"coordinates":[105.89245,22.36111],"type":"Point"}
}