{
  "type": "Feature",
  "properties": {
    "gn:admin1_code":"39.0",
    "gn:asciiname":"La Son",
    "gn:country_code":"VN",
    "gn:dem":332,
    "gn:feature_class":"P",
    "gn:feature_code":"PPL",
    "gn:name":"La S\u1edbn",
    "gn:population":0,
    "gn:timezone":"Asia/Ho_Chi_Minh",
    "iso:country":"VN",
    "wof:name":"La Son",
    "wof:placetype":"locality"
},
  "geometry": {"coordinates":[106.45,22.16667],"type":"Point"}
}