{
  "type": "Feature",
  "properties": {
    "gn:admin1_code":"45.0",
    "gn:asciiname":"Nhu Lam",
    "gn:country_code":"VN",
    "gn:dem":46,
    "gn:feature_class":"P",
    "gn:feature_code":"PPL",
    "gn:name":"Nhu Lam",
    "gn:population":0,
    "gn:timezone":"Asia/Ho_Chi_Minh",
    "iso:country":"VN",
    "name:und_x_variant":[
        "Den",
        "Nhu Lam",
        "\u1ea4p \u0110en"
    ],
    "wof:name":"Nhu Lam",
    "wof:placetype":"locality"
},
  "geometry": {"coordinates":[107.48333,10.63333],"type":"Point"}
}