{
  "type": "Feature",
  "properties": {
    "gn:admin1_code":"74.0",
    "gn:asciiname":"Phuong Quan",
    "gn:country_code":"VN",
    "gn:dem":9,
    "gn:feature_class":"P",
    "gn:feature_code":"PPL",
    "gn:name":"Ph\u01b0\u01a1ng Qu\u1ea7n",
    "gn:population":0,
    "gn:timezone":"Asia/Ho_Chi_Minh",
    "iso:country":"VN",
    "name:vie_x_preferred":[
        "Ph\u01b0\u01a1ng Qu\u1ea7n"
    ],
    "wof:name":"Phuong Quan",
    "wof:placetype":"locality"
},
  "geometry": {"coordinates":[106.03565999999999,21.04353],"type":"Point"}
}