{
  "type": "Feature",
  "properties": {
    "gn:admin1_code":"74.0",
    "gn:asciiname":"Dao Chan",
    "gn:country_code":"VN",
    "gn:dem":10,
    "gn:feature_class":"P",
    "gn:feature_code":"PPL",
    "gn:name":"\u0110\u1ea1o Ch\u00e2n",
    "gn:population":0,
    "gn:timezone":"Asia/Ho_Chi_Minh",
    "iso:country":"VN",
    "name:vie_x_preferred":[
        "\u0110\u1ea1o Ch\u00e2n"
    ],
    "wof:name":"Dao Chan",
    "wof:placetype":"locality"
},
  "geometry": {"coordinates":[106.09784999999999,21.18557],"type":"Point"}
}