{
  "type": "Feature",
  "properties": {
    "gn:admin1_code":"70.0",
    "gn:asciiname":"Lang Vay",
    "gn:country_code":"VN",
    "gn:dem":101,
    "gn:feature_class":"P",
    "gn:feature_code":"PPL",
    "gn:name":"L\u00e0ng V\u00e2y",
    "gn:population":0,
    "gn:timezone":"Asia/Ho_Chi_Minh",
    "iso:country":"VN",
    "name:vie_x_preferred":[
        "L\u00e0ng V\u00e2y"
    ],
    "wof:name":"Lang Vay",
    "wof:placetype":"locality"
},
  "geometry": {"coordinates":[104.61854,21.84614],"type":"Point"}
}