{
  "type": "Feature",
  "properties": {
    "iso:country":"VN",
    "name:eng_x_preferred":[
        "Bong Son"
    ],
    "name:nld_x_preferred":[
        "Bong Son"
    ],
    "name:unk_x_variant":[
        "Ho\u00e0i Nhon"
    ],
    "name:vie_x_preferred":[
        "B\u1ed3ng S\u01a1n"
    ],
    "name:zho_x_preferred":[
        "\u84ec\u5c71\u93ae"
    ],
    "qs:gn_country":"VN",
    "qs:gn_fcode":"PPL",
    "qs:gn_pop":0,
    "qs:name":"B\u1ed3ng S\u01a1n",
    "qs:name_adm0":"Vietnam",
    "qs:name_adm1":"Binh Dinh",
    "qs:photos":12,
    "qs:photos_1k":2,
    "qs:photos_9k":1,
    "qs:photos_9r":1,
    "qs:photos_all":12,
    "qs:photos_sr":1,
    "qs:placetype":"Town",
    "qs:pop_sr":"0",
    "qs:woe_adm0":23424984,
    "wd:wordcount":257,
    "wof:name":"B\u1ed3ng S\u01a1n",
    "wof:placetype":"locality"
},
  "geometry": {"coordinates":[109.01667,14.43333],"type":"Point"}
}