{
  "type": "Feature",
  "properties": {
    "gn:admin1_code":"32.0",
    "gn:asciiname":"Ban Van Pan",
    "gn:country_code":"VN",
    "gn:dem":225,
    "gn:feature_class":"P",
    "gn:feature_code":"PPL",
    "gn:name":"B\u1ea3n V\u00e0n P\u00e1n",
    "gn:population":0,
    "gn:timezone":"Asia/Ho_Chi_Minh",
    "iso:country":"VN",
    "name:vie_x_preferred":[
        "B\u1ea3n V\u00e0n P\u00e1n"
    ],
    "wof:name":"Ban Van Pan",
    "wof:placetype":"locality"
},
  "geometry": {"coordinates":[103.67477,21.67112],"type":"Point"}
}