{
  "type": "Feature",
  "properties": {
    "gn:admin1_code":"90.0",
    "gn:asciiname":"Na Pa",
    "gn:country_code":"VN",
    "gn:dem":983,
    "gn:feature_class":"P",
    "gn:feature_code":"PPL",
    "gn:name":"Na Pa",
    "gn:population":0,
    "gn:timezone":"Asia/Ho_Chi_Minh",
    "iso:country":"VN",
    "wof:name":"Na Pa",
    "wof:placetype":"locality"
},
  "geometry": {"coordinates":[104.23333,22.66667],"type":"Point"}
}