{
  "type": "Feature",
  "properties": {
    "gn:admin1_code":"30.0",
    "gn:asciiname":"Cam Pha Port",
    "gn:cc2":"VN",
    "gn:country_code":"VN",
    "gn:dem":-9999,
    "gn:feature_class":"P",
    "gn:feature_code":"PPL",
    "gn:name":"C\u1ea9m Ph\u1ea3 Port",
    "gn:population":0,
    "gn:timezone":"Asia/Ho_Chi_Minh",
    "iso:country":"VN",
    "name:und_x_variant":[
        "Kamfa Port",
        "Port Campha",
        "Port of Kam Pha",
        "C\u1ea9m Ph\u1ea3 Port"
    ],
    "wof:name":"Cam Pha Port",
    "wof:placetype":"locality"
},
  "geometry": {"coordinates":[107.36667,21.01667],"type":"Point"}
}