{
  "type": "Feature",
  "properties": {
    "gn:admin1_code":"34.0",
    "gn:asciiname":"Muong Ha",
    "gn:country_code":"VN",
    "gn:dem":146,
    "gn:feature_class":"P",
    "gn:feature_code":"PPL",
    "gn:name":"M\u01b0\u01a1ng Ha",
    "gn:population":0,
    "gn:timezone":"Asia/Ho_Chi_Minh",
    "iso:country":"VN",
    "wof:name":"Muong Ha",
    "wof:placetype":"locality"
},
  "geometry": {"coordinates":[104.93333,20.25],"type":"Point"}
}