{
  "type": "Feature",
  "properties": {
    "gn:admin1_code":"43.0",
    "gn:asciiname":"Xa Dau Giay",
    "gn:country_code":"VN",
    "gn:dem":178,
    "gn:feature_class":"P",
    "gn:feature_code":"PPL",
    "gn:name":"Xa Dau Giay",
    "gn:population":0,
    "gn:timezone":"Asia/Ho_Chi_Minh",
    "iso:country":"VN",
    "wof:name":"Xa Dau Giay",
    "wof:placetype":"locality"
},
  "geometry": {"coordinates":[107.14667,10.93833],"type":"Point"}
}