{
  "type": "Feature",
  "properties": {
    "gn:admin1_code":"44.0",
    "gn:asciiname":"Tien Chu",
    "gn:country_code":"VN",
    "gn:dem":16,
    "gn:feature_class":"P",
    "gn:feature_code":"PPL",
    "gn:name":"Ti\u00ean Ch\u1eef",
    "gn:population":0,
    "gn:timezone":"Asia/Ho_Chi_Minh",
    "iso:country":"VN",
    "name:vie_x_preferred":[
        "Ti\u00ean Ch\u1eef"
    ],
    "wof:name":"Tien Chu",
    "wof:placetype":"locality"
},
  "geometry": {"coordinates":[105.8331,21.36111],"type":"Point"}
}