{
  "type": "Feature",
  "properties": {
    "gn:admin1_code":"71.0",
    "gn:asciiname":"Hung Dao",
    "gn:country_code":"VN",
    "gn:dem":12,
    "gn:feature_class":"P",
    "gn:feature_code":"PPL",
    "gn:name":"H\u01b0ng \u0110\u1ea1o",
    "gn:population":0,
    "gn:timezone":"Asia/Ho_Chi_Minh",
    "iso:country":"VN",
    "name:vie_x_preferred":[
        "H\u01b0ng \u0110\u1ea1o"
    ],
    "wof:name":"Hung Dao",
    "wof:placetype":"locality"
},
  "geometry": {"coordinates":[106.00605,21.2826],"type":"Point"}
}