{
  "type": "Feature",
  "properties": {
    "gn:admin1_code":"44.0",
    "gn:asciiname":"Khe Thuong",
    "gn:country_code":"VN",
    "gn:dem":21,
    "gn:feature_class":"P",
    "gn:feature_code":"PPL",
    "gn:name":"Kh\u00ea Th\u01b0\u1ee3ng",
    "gn:population":0,
    "gn:timezone":"Asia/Ho_Chi_Minh",
    "iso:country":"VN",
    "name:vie_x_preferred":[
        "Kh\u00ea Th\u01b0\u1ee3ng"
    ],
    "wof:name":"Khe Thuong",
    "wof:placetype":"locality"
},
  "geometry": {"coordinates":[105.30622,21.18689],"type":"Point"}
}