{
  "type": "Feature",
  "properties": {
    "gn:admin1_code":"1.0",
    "gn:asciiname":"Tay Binh C",
    "gn:country_code":"VN",
    "gn:dem":6,
    "gn:feature_class":"P",
    "gn:feature_code":"PPL",
    "gn:name":"T\u00e2y B\u00ecnh C",
    "gn:population":0,
    "gn:timezone":"Asia/Ho_Chi_Minh",
    "iso:country":"VN",
    "name:vie_x_preferred":[
        "T\u00e2y B\u00ecnh C"
    ],
    "wof:name":"Tay Binh C",
    "wof:placetype":"locality"
},
  "geometry": {"coordinates":[105.35598,10.31527],"type":"Point"}
}