{
  "type": "Feature",
  "properties": {
    "gn:admin1_code":"89.0",
    "gn:asciiname":"Ban Pac Pha",
    "gn:country_code":"VN",
    "gn:dem":458,
    "gn:feature_class":"P",
    "gn:feature_code":"PPL",
    "gn:name":"B\u1ea3n P\u1eafc Pha",
    "gn:population":0,
    "gn:timezone":"Asia/Ho_Chi_Minh",
    "iso:country":"VN",
    "name:vie_x_preferred":[
        "B\u1ea3n P\u1eafc Pha"
    ],
    "wof:name":"Ban Pac Pha",
    "wof:placetype":"locality"
},
  "geometry": {"coordinates":[103.74368,22.06257],"type":"Point"}
}