{
  "type": "Feature",
  "properties": {
    "gn:admin1_code":"63.0",
    "gn:asciiname":"Van Loc",
    "gn:country_code":"VN",
    "gn:dem":17,
    "gn:feature_class":"P",
    "gn:feature_code":"PPL",
    "gn:name":"Van L\u1ed9c",
    "gn:population":0,
    "gn:timezone":"Asia/Ho_Chi_Minh",
    "iso:country":"VN",
    "name:und_x_variant":[
        "Tan Loc",
        "Van L\u1ed9c"
    ],
    "wof:name":"Van Loc",
    "wof:placetype":"locality"
},
  "geometry": {"coordinates":[108.68333,15.18333],"type":"Point"}
}