{
  "type": "Feature",
  "properties": {
    "gn:asciiname":"Huyen Kien Hai",
    "gn:country_code":"VN",
    "gn:dem":18,
    "gn:feature_class":"P",
    "gn:feature_code":"PPL",
    "gn:name":"Huy\u1ec7n Ki\u00ean H\u1ea3i",
    "gn:population":0,
    "gn:timezone":"Asia/Ho_Chi_Minh",
    "iso:country":"VN",
    "wof:name":"Huyen Kien Hai",
    "wof:placetype":"locality"
},
  "geometry": {"coordinates":[104.8475,9.97274],"type":"Point"}
}