{
  "type": "Feature",
  "properties": {
    "gn:admin1_code":"87.0",
    "gn:asciiname":"Truong Khuong A",
    "gn:country_code":"VN",
    "gn:dem":2,
    "gn:feature_class":"P",
    "gn:feature_code":"PPL",
    "gn:name":"Tr\u01b0\u1eddng Kh\u01b0\u01a1ng A",
    "gn:population":0,
    "gn:timezone":"Asia/Ho_Chi_Minh",
    "iso:country":"VN",
    "name:vie_x_preferred":[
        "Tr\u01b0\u1eddng Kh\u01b0\u01a1ng A"
    ],
    "wof:name":"Truong Khuong A",
    "wof:placetype":"locality"
},
  "geometry": {"coordinates":[105.53894,9.98437],"type":"Point"}
}