{
  "type": "Feature",
  "properties": {
    "gn:admin1_code":"61.0",
    "gn:asciiname":"Phu Nhieu",
    "gn:country_code":"VN",
    "gn:dem":15,
    "gn:feature_class":"P",
    "gn:feature_code":"PPL",
    "gn:name":"Ph\u00fa Nhi\u00eau",
    "gn:population":0,
    "gn:timezone":"Asia/Ho_Chi_Minh",
    "iso:country":"VN",
    "name:vie_x_preferred":[
        "Ph\u00fa Nhi\u00eau"
    ],
    "wof:name":"Phu Nhieu",
    "wof:placetype":"locality"
},
  "geometry": {"coordinates":[109.21613000000001,12.96592],"type":"Point"}
}