{
  "type": "Feature",
  "properties": {
    "gn:admin1_code":"39.0",
    "gn:asciiname":"Ban Khuoi",
    "gn:country_code":"VN",
    "gn:dem":490,
    "gn:feature_class":"P",
    "gn:feature_code":"PPL",
    "gn:name":"B\u1ea3n Khu\u00f4i",
    "gn:population":0,
    "gn:timezone":"Asia/Ho_Chi_Minh",
    "iso:country":"VN",
    "wof:name":"Ban Khuoi",
    "wof:placetype":"locality"
},
  "geometry": {"coordinates":[107.26667,21.66667],"type":"Point"}
}