{
  "type": "Feature",
  "properties": {
    "gn:admin1_code":"60.0",
    "gn:asciiname":"Thon Mong Duc",
    "gn:country_code":"VN",
    "gn:dem":13,
    "gn:feature_class":"P",
    "gn:feature_code":"PPL",
    "gn:name":"Th\u00f4n Mong \u0110\u1ee9c",
    "gn:population":0,
    "gn:timezone":"Asia/Ho_Chi_Minh",
    "iso:country":"VN",
    "name:und_x_variant":[
        "Mong Duc",
        "Th\u00f4n Mong \u0110\u1ee9c"
    ],
    "wof:name":"Thon Mong Duc",
    "wof:placetype":"locality"
},
  "geometry": {"coordinates":[108.90000000000001,11.51667],"type":"Point"}
}