{
  "type": "Feature",
  "properties": {
    "gn:admin1_code":"84.0",
    "gn:asciiname":"Que Trung",
    "gn:country_code":"VN",
    "gn:dem":26,
    "gn:feature_class":"P",
    "gn:feature_code":"PPL",
    "gn:name":"Qu\u1ebf Trung",
    "gn:population":0,
    "gn:timezone":"Asia/Ho_Chi_Minh",
    "iso:country":"VN",
    "name:vie_x_preferred":[
        "Qu\u1ebf Trung"
    ],
    "wof:name":"Que Trung",
    "wof:placetype":"locality"
},
  "geometry": {"coordinates":[108.03279000000001,15.70963],"type":"Point"}
}