{
  "type": "Feature",
  "properties": {
    "gn:admin1_code":"88.0",
    "gn:asciiname":"Khu Vuc Ba",
    "gn:country_code":"VN",
    "gn:dem":465,
    "gn:feature_class":"P",
    "gn:feature_code":"PPL",
    "gn:name":"Khu V\u1ef1c Ba",
    "gn:population":0,
    "gn:timezone":"Asia/Ho_Chi_Minh",
    "iso:country":"VN",
    "name:vie_x_preferred":[
        "Khu V\u1ef1c Ba"
    ],
    "name:vie_x_variant":[
        "Khu V\u1ef1c 3"
    ],
    "wof:name":"Khu Vuc Ba",
    "wof:placetype":"locality"
},
  "geometry": {"coordinates":[108.01801,12.51988],"type":"Point"}
}