{
  "type": "Feature",
  "properties": {
    "gn:admin1_code":"58.0",
    "gn:asciiname":"Nha Nghi",
    "gn:country_code":"VN",
    "gn:dem":10,
    "gn:feature_class":"P",
    "gn:feature_code":"PPL",
    "gn:name":"Nha Nghi",
    "gn:population":0,
    "gn:timezone":"Asia/Ho_Chi_Minh",
    "iso:country":"VN",
    "name:vie_x_preferred":[
        "Nha Nghi"
    ],
    "wof:name":"Nha Nghi",
    "wof:placetype":"locality"
},
  "geometry": {"coordinates":[105.60397,19.05215],"type":"Point"}
}