{
  "type": "Feature",
  "properties": {
    "gn:admin1_code":"89.0",
    "gn:asciiname":"Cang Ha",
    "gn:country_code":"VN",
    "gn:dem":1479,
    "gn:feature_class":"P",
    "gn:feature_code":"PPL",
    "gn:name":"C\u0103ng H\u00e1",
    "gn:population":0,
    "gn:timezone":"Asia/Ho_Chi_Minh",
    "iso:country":"VN",
    "name:vie_x_preferred":[
        "C\u0103ng H\u00e1"
    ],
    "wof:name":"Cang Ha",
    "wof:placetype":"locality"
},
  "geometry": {"coordinates":[103.36999,22.69153],"type":"Point"}
}