{
  "type": "Feature",
  "properties": {
    "gn:admin1_code":"58.0",
    "gn:asciiname":"Ban Xop Ti",
    "gn:country_code":"VN",
    "gn:dem":163,
    "gn:feature_class":"P",
    "gn:feature_code":"PPL",
    "gn:name":"B\u1ea3n X\u00f4p Ti",
    "gn:population":0,
    "gn:timezone":"Asia/Ho_Chi_Minh",
    "iso:country":"VN",
    "wof:name":"Ban Xop Ti",
    "wof:placetype":"locality"
},
  "geometry": {"coordinates":[104.18333,19.38333],"type":"Point"}
}