{
  "type": "Feature",
  "properties": {
    "gn:admin1_code":"39.0",
    "gn:asciiname":"Ba Nang",
    "gn:country_code":"VN",
    "gn:dem":37,
    "gn:feature_class":"P",
    "gn:feature_code":"PPL",
    "gn:name":"Ba Nang",
    "gn:population":0,
    "gn:timezone":"Asia/Ho_Chi_Minh",
    "iso:country":"VN",
    "wof:name":"Ba Nang",
    "wof:placetype":"locality"
},
  "geometry": {"coordinates":[106.40000000000001,21.55],"type":"Point"}
}