{
  "type": "Feature",
  "properties": {
    "gn:admin1_code":"85.0",
    "gn:asciiname":"Phuoc Sinh",
    "gn:country_code":"VN",
    "gn:dem":203,
    "gn:feature_class":"P",
    "gn:feature_code":"PPL",
    "gn:name":"Ph\u01b0\u1edbc Sinh",
    "gn:population":0,
    "gn:timezone":"Asia/Ho_Chi_Minh",
    "iso:country":"VN",
    "name:und_x_variant":[
        "Phuc Sinh",
        "Ph\u01b0\u1edbc Sinh"
    ],
    "wof:name":"Phuoc Sinh",
    "wof:placetype":"locality"
},
  "geometry": {"coordinates":[105.59999999999999,21.91667],"type":"Point"}
}