{
  "type": "Feature",
  "properties": {
    "gn:admin1_code":"32.0",
    "gn:asciiname":"Co Si Pan",
    "gn:country_code":"VN",
    "gn:dem":953,
    "gn:feature_class":"P",
    "gn:feature_code":"PPL",
    "gn:name":"Co Si Pan",
    "gn:population":0,
    "gn:timezone":"Asia/Ho_Chi_Minh",
    "iso:country":"VN",
    "wof:name":"Co Si Pan",
    "wof:placetype":"locality"
},
  "geometry": {"coordinates":[104.38333,21.26667],"type":"Point"}
}