{
  "type": "Feature",
  "properties": {
    "gn:admin1_code":"90.0",
    "gn:asciiname":"Na Lang",
    "gn:country_code":"VN",
    "gn:dem":248,
    "gn:feature_class":"P",
    "gn:feature_code":"PPL",
    "gn:name":"Na Lang",
    "gn:population":0,
    "gn:timezone":"Asia/Ho_Chi_Minh",
    "iso:country":"VN",
    "name:und_x_variant":[
        "Na Leng",
        "Na Lang"
    ],
    "wof:name":"Na Lang",
    "wof:placetype":"locality"
},
  "geometry": {"coordinates":[104.08033,22.6162],"type":"Point"}
}