{
  "type": "Feature",
  "properties": {
    "gn:admin1_code":"58.0",
    "gn:asciiname":"Lang Trang",
    "gn:country_code":"VN",
    "gn:dem":56,
    "gn:feature_class":"P",
    "gn:feature_code":"PPL",
    "gn:name":"L\u00e0ng Trang",
    "gn:population":0,
    "gn:timezone":"Asia/Ho_Chi_Minh",
    "iso:country":"VN",
    "name:und_x_variant":[
        "Ap Trang",
        "L\u00e0ng Trang"
    ],
    "wof:name":"Lang Trang",
    "wof:placetype":"locality"
},
  "geometry": {"coordinates":[105.28333000000001,19.18333],"type":"Point"}
}