{
  "type": "Feature",
  "properties": {
    "gn:admin1_code":"52.0",
    "gn:asciiname":"Chien Thang",
    "gn:country_code":"VN",
    "gn:dem":15,
    "gn:feature_class":"P",
    "gn:feature_code":"PPL",
    "gn:name":"Chi\u1ebfn Th\u1eafng",
    "gn:population":0,
    "gn:timezone":"Asia/Ho_Chi_Minh",
    "iso:country":"VN",
    "name:vie_x_preferred":[
        "Chi\u1ebfn Th\u1eafng"
    ],
    "wof:name":"Chien Thang",
    "wof:placetype":"locality"
},
  "geometry": {"coordinates":[105.72024,18.43564],"type":"Point"}
}