{
  "type": "Feature",
  "properties": {
    "gn:admin1_code":"90.0",
    "gn:asciiname":"Lien Hai",
    "gn:country_code":"VN",
    "gn:dem":86,
    "gn:feature_class":"P",
    "gn:feature_code":"PPL",
    "gn:name":"Li\u00ean H\u1ea3i",
    "gn:population":0,
    "gn:timezone":"Asia/Ho_Chi_Minh",
    "iso:country":"VN",
    "name:vie_x_preferred":[
        "Li\u00ean H\u1ea3i"
    ],
    "wof:name":"Lien Hai",
    "wof:placetype":"locality"
},
  "geometry": {"coordinates":[104.32425000000001,22.20128],"type":"Point"}
}