{
  "type": "Feature",
  "properties": {
    "gn:admin1_code":"74.0",
    "gn:asciiname":"Tien Ba",
    "gn:country_code":"VN",
    "gn:dem":7,
    "gn:feature_class":"P",
    "gn:feature_code":"PPL",
    "gn:name":"Ti\u00ean B\u00e1",
    "gn:population":0,
    "gn:timezone":"Asia/Ho_Chi_Minh",
    "iso:country":"VN",
    "name:vie_x_preferred":[
        "Tuy\u00ean B\u00e1"
    ],
    "name:vie_x_variant":[
        "Ti\u00ean B\u00e1"
    ],
    "wof:name":"Tien Ba",
    "wof:placetype":"locality"
},
  "geometry": {"coordinates":[106.16191999999999,21.01197],"type":"Point"}
}