{
  "type": "Feature",
  "properties": {
    "gn:admin1_code":"81.0",
    "gn:asciiname":"Vinh Phuc",
    "gn:country_code":"VN",
    "gn:dem":8,
    "gn:feature_class":"P",
    "gn:feature_code":"PPL",
    "gn:name":"V\u0129nh Ph\u00fac",
    "gn:population":0,
    "gn:timezone":"Asia/Ho_Chi_Minh",
    "iso:country":"VN",
    "name:und_x_variant":[
        "Vinh Phu",
        "V\u0129nh Ph\u00fac"
    ],
    "wof:name":"Vinh Phuc",
    "wof:placetype":"locality"
},
  "geometry": {"coordinates":[106.02262,20.75322],"type":"Point"}
}