{
  "type": "Feature",
  "properties": {
    "gn:admin1_code":"89.0",
    "gn:asciiname":"Mo Chi",
    "gn:country_code":"VN",
    "gn:dem":770,
    "gn:feature_class":"P",
    "gn:feature_code":"PPL",
    "gn:name":"M\u00f4 Chi",
    "gn:population":0,
    "gn:timezone":"Asia/Ho_Chi_Minh",
    "iso:country":"VN",
    "name:vie_x_preferred":[
        "M\u00f4 Chi"
    ],
    "wof:name":"Mo Chi",
    "wof:placetype":"locality"
},
  "geometry": {"coordinates":[102.66305,22.53801],"type":"Point"}
}