{
  "type": "Feature",
  "properties": {
    "gn:admin1_code":"32.0",
    "gn:asciiname":"Co Yao",
    "gn:country_code":"VN",
    "gn:dem":988,
    "gn:feature_class":"P",
    "gn:feature_code":"PPL",
    "gn:name":"Co Yao",
    "gn:population":0,
    "gn:timezone":"Asia/Ho_Chi_Minh",
    "iso:country":"VN",
    "wof:name":"Co Yao",
    "wof:placetype":"locality"
},
  "geometry": {"coordinates":[103.68333,21.25],"type":"Point"}
}