{
  "type": "Feature",
  "properties": {
    "gn:admin1_code":"68.0",
    "gn:asciiname":"Thuc Thuy",
    "gn:country_code":"VN",
    "gn:dem":31,
    "gn:feature_class":"P",
    "gn:feature_code":"PPL",
    "gn:name":"Th\u1ee5c Th\u1ee7y",
    "gn:population":0,
    "gn:timezone":"Asia/Ho_Chi_Minh",
    "iso:country":"VN",
    "wof:name":"Thuc Thuy",
    "wof:placetype":"locality"
},
  "geometry": {"coordinates":[105.26667,21.78333],"type":"Point"}
}