{
  "type": "Feature",
  "properties": {
    "gn:admin1_code":"1.0",
    "gn:asciiname":"Tay Binh",
    "gn:country_code":"VN",
    "gn:dem":3,
    "gn:feature_class":"P",
    "gn:feature_code":"PPL",
    "gn:name":"T\u00e2y B\u00ecnh",
    "gn:population":0,
    "gn:timezone":"Asia/Ho_Chi_Minh",
    "iso:country":"VN",
    "name:und_x_variant":[
        "\u1ea4p T\u00e2y B\u00ecnh"
    ],
    "name:vie_x_preferred":[
        "T\u00e2y B\u00ecnh"
    ],
    "wof:name":"Tay Binh",
    "wof:placetype":"locality"
},
  "geometry": {"coordinates":[105.25552999999999,10.2552],"type":"Point"}
}