{
  "type": "Feature",
  "properties": {
    "gn:admin1_code":"67.0",
    "gn:asciiname":"Xom Hai Ngo",
    "gn:cc2":"VN",
    "gn:country_code":"VN",
    "gn:dem":0,
    "gn:feature_class":"P",
    "gn:feature_code":"PPL",
    "gn:name":"X\u00f3m Hai Ng\u1ecd",
    "gn:population":0,
    "gn:timezone":"Asia/Ho_Chi_Minh",
    "iso:country":"VN",
    "name:und_x_variant":[
        "Hai Ng\u1ecd",
        "X\u00f3m Hai Ng\u1ecd"
    ],
    "wof:name":"Xom Hai Ngo",
    "wof:placetype":"locality"
},
  "geometry": {"coordinates":[106.03806000000002,9.93444],"type":"Point"}
}