{
  "type": "Feature",
  "properties": {
    "gn:admin1_code":"69.0",
    "gn:asciiname":"Vinh Khanh",
    "gn:country_code":"VN",
    "gn:dem":7,
    "gn:feature_class":"P",
    "gn:feature_code":"PPL",
    "gn:name":"V\u0129nh Kh\u00e1nh",
    "gn:population":0,
    "gn:timezone":"Asia/Ho_Chi_Minh",
    "iso:country":"VN",
    "name:und_x_variant":[
        "V\u0129nh Kh\u00e1nh",
        "\u1ea4p V\u0129nh Kh\u00e1nh"
    ],
    "wof:name":"Vinh Khanh",
    "wof:placetype":"locality"
},
  "geometry": {"coordinates":[106.01047,9.94884],"type":"Point"}
}