{
  "type": "Feature",
  "properties": {
    "gn:admin1_code":"58.0",
    "gn:asciiname":"Thai Hoa",
    "gn:country_code":"VN",
    "gn:dem":64,
    "gn:feature_class":"P",
    "gn:feature_code":"PPL",
    "gn:name":"Th\u00e1i H\u00f2a",
    "gn:population":0,
    "gn:timezone":"Asia/Ho_Chi_Minh",
    "iso:country":"VN",
    "name:ceb_x_preferred":[
        "Th\u1ecb X\u00e3 Th\u00e1i H\u00f2a"
    ],
    "name:jpn_x_preferred":[
        "\u30bf\u30a4\u30db\u30a2"
    ],
    "name:vie_x_preferred":[
        "Th\u00e1i H\u00f2a"
    ],
    "name:zho_x_preferred":[
        "\u592a\u548c\u5e02\u793e"
    ],
    "wof:name":"Thai Hoa",
    "wof:placetype":"locality"
},
  "geometry": {"coordinates":[104.97441000000001,18.92031],"type":"Point"}
}