{
  "type": "Feature",
  "properties": {
    "gn:admin1_code":"68.0",
    "gn:asciiname":"Khe Tac",
    "gn:country_code":"VN",
    "gn:dem":41,
    "gn:feature_class":"P",
    "gn:feature_code":"PPL",
    "gn:name":"Khe T\u1ea1c",
    "gn:population":0,
    "gn:timezone":"Asia/Ho_Chi_Minh",
    "iso:country":"VN",
    "name:vie_x_preferred":[
        "Khe T\u1ea1c"
    ],
    "wof:name":"Khe Tac",
    "wof:placetype":"locality"
},
  "geometry": {"coordinates":[105.28834999999999,21.67516],"type":"Point"}
}