{
  "type": "Feature",
  "properties": {
    "gn:admin1_code":"68.0",
    "gn:asciiname":"Tham Hon",
    "gn:country_code":"VN",
    "gn:dem":174,
    "gn:feature_class":"P",
    "gn:feature_code":"PPL",
    "gn:name":"Th\u1eb3m Hon",
    "gn:population":0,
    "gn:timezone":"Asia/Ho_Chi_Minh",
    "iso:country":"VN",
    "name:vie_x_preferred":[
        "Th\u1eb3m Hon"
    ],
    "wof:name":"Tham Hon",
    "wof:placetype":"locality"
},
  "geometry": {"coordinates":[105.10259000000001,22.38671],"type":"Point"}
}