{
  "type": "Feature",
  "properties": {
    "gn:admin1_code":"91.0",
    "gn:asciiname":"Buon Pang So",
    "gn:country_code":"VN",
    "gn:dem":414,
    "gn:feature_class":"P",
    "gn:feature_code":"PPL",
    "gn:name":"Bu\u00f4n Pang S\u00f4",
    "gn:population":0,
    "gn:timezone":"Asia/Ho_Chi_Minh",
    "iso:country":"VN",
    "wof:name":"Buon Pang So",
    "wof:placetype":"locality"
},
  "geometry": {"coordinates":[107.76667,12.61667],"type":"Point"}
}