{
  "type": "Feature",
  "properties": {
    "gn:admin1_code":"92.0",
    "gn:asciiname":"Ban Lai Mot",
    "gn:country_code":"VN",
    "gn:dem":529,
    "gn:feature_class":"P",
    "gn:feature_code":"PPL",
    "gn:name":"B\u1ea3n L\u1ea1i M\u1ed9t",
    "gn:population":0,
    "gn:timezone":"Asia/Ho_Chi_Minh",
    "iso:country":"VN",
    "name:vie_x_preferred":[
        "B\u1ea3n L\u1ea1i M\u1ed9t"
    ],
    "name:vie_x_variant":[
        "B\u1ea3n L\u1ea1i 1"
    ],
    "wof:name":"Ban Lai Mot",
    "wof:placetype":"locality"
},
  "geometry": {"coordinates":[103.40475000000001,21.23335],"type":"Point"}
}