{
  "type": "Feature",
  "properties": {
    "gn:admin1_code":"32.0",
    "gn:asciiname":"Ban Nam Phung",
    "gn:country_code":"VN",
    "gn:dem":155,
    "gn:feature_class":"P",
    "gn:feature_code":"PPL",
    "gn:name":"B\u1ea3n N\u1eadm Phung",
    "gn:population":0,
    "gn:timezone":"Asia/Ho_Chi_Minh",
    "iso:country":"VN",
    "name:vie_x_preferred":[
        "B\u1ea3n N\u1eadm Phung"
    ],
    "wof:name":"Ban Nam Phung",
    "wof:placetype":"locality"
},
  "geometry": {"coordinates":[103.56158000000001,21.84772],"type":"Point"}
}