{
  "type": "Feature",
  "properties": {
    "gn:admin1_code":"81.0",
    "gn:asciiname":"Me So",
    "gn:country_code":"VN",
    "gn:dem":9,
    "gn:feature_class":"P",
    "gn:feature_code":"PPL",
    "gn:name":"M\u1ec5 S\u1edf",
    "gn:population":0,
    "gn:timezone":"Asia/Ho_Chi_Minh",
    "iso:country":"VN",
    "name:vie_x_preferred":[
        "M\u1ec5 S\u1edf"
    ],
    "wof:name":"Me So",
    "wof:placetype":"locality"
},
  "geometry": {"coordinates":[105.92036,20.89316],"type":"Point"}
}