{
  "type": "Feature",
  "properties": {
    "gn:admin1_code":"32.0",
    "gn:asciiname":"Ban Bo Hac",
    "gn:country_code":"VN",
    "gn:dem":745,
    "gn:feature_class":"P",
    "gn:feature_code":"PPL",
    "gn:name":"B\u1ea3n B\u00f3 H\u1ea1c",
    "gn:population":0,
    "gn:timezone":"Asia/Ho_Chi_Minh",
    "iso:country":"VN",
    "name:vie_x_preferred":[
        "B\u1ea3n B\u00f3 H\u1ea1c"
    ],
    "wof:name":"Ban Bo Hac",
    "wof:placetype":"locality"
},
  "geometry": {"coordinates":[104.2012,21.08646],"type":"Point"}
}