{
  "type": "Feature",
  "properties": {
    "gn:admin1_code":"68.0",
    "gn:asciiname":"Ban Chong",
    "gn:country_code":"VN",
    "gn:dem":298,
    "gn:feature_class":"P",
    "gn:feature_code":"PPL",
    "gn:name":"B\u00e1n Chong",
    "gn:population":0,
    "gn:timezone":"Asia/Ho_Chi_Minh",
    "iso:country":"VN",
    "name:vie_x_preferred":[
        "B\u00e1n Chong"
    ],
    "wof:name":"Ban Chong",
    "wof:placetype":"locality"
},
  "geometry": {"coordinates":[105.48927,22.41813],"type":"Point"}
}