{
  "type": "Feature",
  "properties": {
    "gn:admin1_code":"67.0",
    "gn:asciiname":"Bau Cac",
    "gn:country_code":"VN",
    "gn:dem":1,
    "gn:feature_class":"P",
    "gn:feature_code":"PPL",
    "gn:name":"B\u1ea7u C\u00e1c",
    "gn:population":0,
    "gn:timezone":"Asia/Ho_Chi_Minh",
    "iso:country":"VN",
    "wof:name":"Bau Cac",
    "wof:placetype":"locality"
},
  "geometry": {"coordinates":[106.41110999999999,9.805],"type":"Point"}
}