{
  "type": "Feature",
  "properties": {
    "gn:admin1_code":"49.0",
    "gn:asciiname":"De Mang",
    "gn:country_code":"VN",
    "gn:dem":609,
    "gn:feature_class":"P",
    "gn:feature_code":"PPL",
    "gn:name":"De Mang",
    "gn:population":0,
    "gn:timezone":"Asia/Ho_Chi_Minh",
    "iso:country":"VN",
    "wof:name":"De Mang",
    "wof:placetype":"locality"
},
  "geometry": {"coordinates":[108.11667,14.15],"type":"Point"}
}