{
  "type": "Feature",
  "properties": {
    "gn:admin1_code":"1.0",
    "gn:asciiname":"To An",
    "gn:country_code":"VN",
    "gn:dem":14,
    "gn:feature_class":"P",
    "gn:feature_code":"PPL",
    "gn:name":"T\u00f4 An",
    "gn:population":0,
    "gn:timezone":"Asia/Ho_Chi_Minh",
    "iso:country":"VN",
    "name:vie_x_preferred":[
        "T\u00f4 An"
    ],
    "wof:name":"To An",
    "wof:placetype":"locality"
},
  "geometry": {"coordinates":[105.00202,10.35526],"type":"Point"}
}