{
  "type": "Feature",
  "properties": {
    "gn:admin1_code":"90.0",
    "gn:asciiname":"Na An",
    "gn:country_code":"VN",
    "gn:dem":341,
    "gn:feature_class":"P",
    "gn:feature_code":"PPL",
    "gn:name":"N\u00e1 \u1ea2n",
    "gn:population":0,
    "gn:timezone":"Asia/Ho_Chi_Minh",
    "iso:country":"VN",
    "name:vie_x_preferred":[
        "N\u00e1 \u1ea2n"
    ],
    "wof:name":"Na An",
    "wof:placetype":"locality"
},
  "geometry": {"coordinates":[103.81095000000001,22.55713],"type":"Point"}
}