{
  "type": "Feature",
  "properties": {
    "gn:admin1_code":"10.0",
    "gn:asciiname":"Dak Djro",
    "gn:country_code":"VN",
    "gn:dem":643,
    "gn:feature_class":"P",
    "gn:feature_code":"PPL",
    "gn:name":"Dak Djro",
    "gn:population":0,
    "gn:timezone":"Asia/Ho_Chi_Minh",
    "iso:country":"VN",
    "wof:name":"Dak Djro",
    "wof:placetype":"locality"
},
  "geometry": {"coordinates":[108.21666999999999,15.01667],"type":"Point"}
}