{
  "type": "Feature",
  "properties": {
    "gn:admin1_code":"70.0",
    "gn:asciiname":"Hong Lau",
    "gn:country_code":"VN",
    "gn:dem":241,
    "gn:feature_class":"P",
    "gn:feature_code":"PPL",
    "gn:name":"H\u1ed3ng L\u00e2u",
    "gn:population":0,
    "gn:timezone":"Asia/Ho_Chi_Minh",
    "iso:country":"VN",
    "name:vie_x_preferred":[
        "H\u1ed3ng L\u00e2u"
    ],
    "wof:name":"Hong Lau",
    "wof:placetype":"locality"
},
  "geometry": {"coordinates":[104.69649,21.61025],"type":"Point"}
}