{
  "type": "Feature",
  "properties": {
    "gn:admin1_code":"58.0",
    "gn:asciiname":"Ban Huong",
    "gn:country_code":"VN",
    "gn:dem":221,
    "gn:feature_class":"P",
    "gn:feature_code":"PPL",
    "gn:name":"B\u1ea3n Hu\u1ed1ng",
    "gn:population":0,
    "gn:timezone":"Asia/Ho_Chi_Minh",
    "iso:country":"VN",
    "name:vie_x_preferred":[
        "B\u1ea3n Hu\u1ed1ng"
    ],
    "wof:name":"Ban Huong",
    "wof:placetype":"locality"
},
  "geometry": {"coordinates":[105.04086,19.39516],"type":"Point"}
}