{
  "type": "Feature",
  "properties": {
    "gn:admin1_code":"58.0",
    "gn:asciiname":"Dong Coe",
    "gn:country_code":"VN",
    "gn:dem":35,
    "gn:feature_class":"P",
    "gn:feature_code":"PPL",
    "gn:name":"Dong Coe",
    "gn:population":0,
    "gn:timezone":"Asia/Ho_Chi_Minh",
    "iso:country":"VN",
    "name:und_x_variant":[
        "\u0110\u00f4ng C\u1ed1c"
    ],
    "wof:name":"Dong Coe",
    "wof:placetype":"locality"
},
  "geometry": {"coordinates":[105.16667,19.01667],"type":"Point"}
}