{
  "type": "Feature",
  "properties": {
    "gn:admin1_code":"63.0",
    "gn:asciiname":"Thon Trung",
    "gn:country_code":"VN",
    "gn:dem":492,
    "gn:feature_class":"P",
    "gn:feature_code":"PPL",
    "gn:name":"Th\u00f4n Trung",
    "gn:population":0,
    "gn:timezone":"Asia/Ho_Chi_Minh",
    "iso:country":"VN",
    "name:vie_x_preferred":[
        "Th\u00f4n Trung"
    ],
    "wof:name":"Thon Trung",
    "wof:placetype":"locality"
},
  "geometry": {"coordinates":[108.45508,15.14144],"type":"Point"}
}