{
  "type": "Feature",
  "properties": {
    "gn:admin1_code":"13.0",
    "gn:asciiname":"Ho Doan",
    "gn:country_code":"VN",
    "gn:dem":4,
    "gn:feature_class":"P",
    "gn:feature_code":"PPL",
    "gn:name":"Ho Doan",
    "gn:population":0,
    "gn:timezone":"Asia/Ho_Chi_Minh",
    "iso:country":"VN",
    "name:und_x_variant":[
        "H\u1ea1 \u0110o\u1ea1n"
    ],
    "wof:name":"Ho Doan",
    "wof:placetype":"locality"
},
  "geometry": {"coordinates":[106.73333,20.85],"type":"Point"}
}