{
  "type": "Feature",
  "properties": {
    "gn:admin1_code":"74.0",
    "gn:asciiname":"Son Trung",
    "gn:country_code":"VN",
    "gn:dem":18,
    "gn:feature_class":"P",
    "gn:feature_code":"PPL",
    "gn:name":"S\u01a1n Trung",
    "gn:population":0,
    "gn:timezone":"Asia/Ho_Chi_Minh",
    "iso:country":"VN",
    "name:vie_x_preferred":[
        "S\u01a1n Trung"
    ],
    "wof:name":"Son Trung",
    "wof:placetype":"locality"
},
  "geometry": {"coordinates":[106.08737000000001,21.14471],"type":"Point"}
}