{
  "type": "Feature",
  "properties": {
    "gn:admin1_code":"70.0",
    "gn:asciiname":"Khe Giang",
    "gn:country_code":"VN",
    "gn:dem":138,
    "gn:feature_class":"P",
    "gn:feature_code":"PPL",
    "gn:name":"Khe Giang",
    "gn:population":0,
    "gn:timezone":"Asia/Ho_Chi_Minh",
    "iso:country":"VN",
    "name:vie_x_preferred":[
        "Khe Giang"
    ],
    "wof:name":"Khe Giang",
    "wof:placetype":"locality"
},
  "geometry": {"coordinates":[104.62594,21.82885],"type":"Point"}
}