{
  "type": "Feature",
  "properties": {
    "gn:admin1_code":"46.0",
    "gn:asciiname":"Thien Duc",
    "gn:country_code":"VN",
    "gn:dem":22,
    "gn:feature_class":"P",
    "gn:feature_code":"PPL",
    "gn:name":"Thi\u00ean \u0110\u1ee9c",
    "gn:population":0,
    "gn:timezone":"Asia/Ho_Chi_Minh",
    "iso:country":"VN",
    "name:vie_x_preferred":[
        "Thi\u00ean \u0110\u1ee9c"
    ],
    "wof:name":"Thien Duc",
    "wof:placetype":"locality"
},
  "geometry": {"coordinates":[109.07705,14.49288],"type":"Point"}
}