{
  "type": "Feature",
  "properties": {
    "gn:admin1_code":"87.0",
    "gn:asciiname":"Binh Nhat A",
    "gn:country_code":"VN",
    "gn:dem":7,
    "gn:feature_class":"P",
    "gn:feature_code":"PPL",
    "gn:name":"B\u00ecnh Nh\u1eadt A",
    "gn:population":0,
    "gn:timezone":"Asia/Ho_Chi_Minh",
    "iso:country":"VN",
    "name:vie_x_preferred":[
        "B\u00ecnh Nh\u1eadt A"
    ],
    "wof:name":"Binh Nhat A",
    "wof:placetype":"locality"
},
  "geometry": {"coordinates":[105.74122,10.0583],"type":"Point"}
}