{
  "type": "Feature",
  "properties": {
    "gn:admin1_code":"64.0",
    "gn:asciiname":"Tan Dinh",
    "gn:country_code":"VN",
    "gn:dem":6,
    "gn:feature_class":"P",
    "gn:feature_code":"PPL",
    "gn:name":"T\u00e2n \u0110\u1ecbnh",
    "gn:population":0,
    "gn:timezone":"Asia/Ho_Chi_Minh",
    "iso:country":"VN",
    "name:und_x_variant":[
        "T\u00e2n \u0110\u1ecbnh"
    ],
    "wof:name":"Tan Dinh",
    "wof:placetype":"locality"
},
  "geometry": {"coordinates":[107.18333,16.78333],"type":"Point"}
}