{
  "type": "Feature",
  "properties": {
    "gn:admin1_code":"54.0",
    "gn:asciiname":"Thon Hoi Binh",
    "gn:country_code":"VN",
    "gn:dem":3,
    "gn:feature_class":"P",
    "gn:feature_code":"PPL",
    "gn:name":"Th\u00f4n H\u1ed9i B\u00ecnh",
    "gn:population":0,
    "gn:timezone":"Asia/Ho_Chi_Minh",
    "iso:country":"VN",
    "name:und_x_variant":[
        "Hoi Binh",
        "Th\u00f4n H\u1ed9i B\u00ecnh"
    ],
    "wof:name":"Thon Hoi Binh",
    "wof:placetype":"locality"
},
  "geometry": {"coordinates":[109.15000000000001,12.48333],"type":"Point"}
}