{
  "type": "Feature",
  "properties": {
    "gn:admin1_code":"23.0",
    "gn:asciiname":"Klong B",
    "gn:cc2":"VN",
    "gn:country_code":"VN",
    "gn:dem":1075,
    "gn:feature_class":"P",
    "gn:feature_code":"PPL",
    "gn:name":"Klong B",
    "gn:population":0,
    "gn:timezone":"Asia/Ho_Chi_Minh",
    "iso:country":"VN",
    "name:und_x_variant":[
        "Krean",
        "Klong B",
        "Klong"
    ],
    "wof:name":"Klong B",
    "wof:placetype":"locality"
},
  "geometry": {"coordinates":[108.45,11.81667],"type":"Point"}
}