{
  "type": "Feature",
  "properties": {
    "gn:admin1_code":"68.0",
    "gn:asciiname":"Nhu Xuyen",
    "gn:country_code":"VN",
    "gn:dem":52,
    "gn:feature_class":"P",
    "gn:feature_code":"PPL",
    "gn:name":"Nh\u01b0 Xuy\u00ean",
    "gn:population":0,
    "gn:timezone":"Asia/Ho_Chi_Minh",
    "iso:country":"VN",
    "name:und_x_variant":[
        "Nhu Xuy\u00ean"
    ],
    "name:vie_x_preferred":[
        "Nh\u01b0 Xuy\u00ean"
    ],
    "wof:name":"Nhu Xuyen",
    "wof:placetype":"locality"
},
  "geometry": {"coordinates":[105.29452999999999,21.63655],"type":"Point"}
}