{
  "type": "Feature",
  "properties": {
    "gn:admin1_code":"60.0",
    "gn:asciiname":"La Boui",
    "gn:country_code":"VN",
    "gn:dem":398,
    "gn:feature_class":"P",
    "gn:feature_code":"PPL",
    "gn:name":"La Boui",
    "gn:population":0,
    "gn:timezone":"Asia/Ho_Chi_Minh",
    "iso:country":"VN",
    "name:und_x_variant":[
        "La Bou",
        "La Boui"
    ],
    "wof:name":"La Boui",
    "wof:placetype":"locality"
},
  "geometry": {"coordinates":[108.75,11.58333],"type":"Point"}
}