{
  "type": "Feature",
  "properties": {
    "gn:admin1_code":"55.0",
    "gn:asciiname":"Polei Poo",
    "gn:country_code":"VN",
    "gn:dem":591,
    "gn:feature_class":"P",
    "gn:feature_code":"PPL",
    "gn:name":"P\u01a1lei Poo",
    "gn:population":0,
    "gn:timezone":"Asia/Ho_Chi_Minh",
    "iso:country":"VN",
    "name:und_x_variant":[
        "Pele Poo",
        "P\u01a1lei Poo"
    ],
    "wof:name":"Polei Poo",
    "wof:placetype":"locality"
},
  "geometry": {"coordinates":[107.76221,14.34404],"type":"Point"}
}