{
  "type": "Feature",
  "properties": {
    "gn:admin1_code":"75.0",
    "gn:asciiname":"Tong Mach",
    "gn:country_code":"VN",
    "gn:dem":39,
    "gn:feature_class":"P",
    "gn:feature_code":"PPL",
    "gn:name":"T\u1ed5ng M\u1ea1ch",
    "gn:population":0,
    "gn:timezone":"Asia/Ho_Chi_Minh",
    "iso:country":"VN",
    "name:und_x_variant":[
        "S\u00f3c T\u1ed5ng M\u1ea1nh"
    ],
    "name:vie_x_preferred":[
        "T\u1ed5ng M\u1ea1ch"
    ],
    "wof:name":"Tong Mach",
    "wof:placetype":"locality"
},
  "geometry": {"coordinates":[106.44067,11.47384],"type":"Point"}
}