{
  "type": "Feature",
  "properties": {
    "gn:admin1_code":"92.0",
    "gn:asciiname":"Huoi Bon",
    "gn:country_code":"VN",
    "gn:dem":546,
    "gn:feature_class":"P",
    "gn:feature_code":"PPL",
    "gn:name":"Hu\u1ed5i Bon",
    "gn:population":0,
    "gn:timezone":"Asia/Ho_Chi_Minh",
    "iso:country":"VN",
    "name:vie_x_preferred":[
        "Hu\u1ed5i Bon"
    ],
    "wof:name":"Huoi Bon",
    "wof:placetype":"locality"
},
  "geometry": {"coordinates":[103.24079999999999,21.91611],"type":"Point"}
}