{
  "type": "Feature",
  "properties": {
    "gn:admin1_code":"58.0",
    "gn:asciiname":"Yen Phuc",
    "gn:country_code":"VN",
    "gn:dem":28,
    "gn:feature_class":"P",
    "gn:feature_code":"PPL",
    "gn:name":"Y\u00ean Ph\u00fac",
    "gn:population":0,
    "gn:timezone":"Asia/Ho_Chi_Minh",
    "iso:country":"VN",
    "name:und_x_variant":[
        "Yen Phue",
        "Y\u00ean Ph\u00fac"
    ],
    "wof:name":"Yen Phuc",
    "wof:placetype":"locality"
},
  "geometry": {"coordinates":[105.09999999999999,18.93333],"type":"Point"}
}