{
  "type": "Feature",
  "properties": {
    "gn:admin1_code":"70.0",
    "gn:asciiname":"Suoi Co Mot",
    "gn:country_code":"VN",
    "gn:dem":719,
    "gn:feature_class":"P",
    "gn:feature_code":"PPL",
    "gn:name":"Su\u1ed1i C\u00f4 M\u1ed9t",
    "gn:population":0,
    "gn:timezone":"Asia/Ho_Chi_Minh",
    "iso:country":"VN",
    "name:und_x_variant":[
        "B\u1ea3n Su\u1ed1i C\u00f4"
    ],
    "name:vie_x_preferred":[
        "Su\u1ed1i C\u00f4 M\u1ed9t"
    ],
    "name:vie_x_variant":[
        "Su\u1ed1i C\u00f4 1"
    ],
    "wof:name":"Suoi Co Mot",
    "wof:placetype":"locality"
},
  "geometry": {"coordinates":[104.53961,21.65438],"type":"Point"}
}