{
  "type": "Feature",
  "properties": {
    "gn:admin1_code":"32.0",
    "gn:asciiname":"Ban Na Bo",
    "gn:country_code":"VN",
    "gn:dem":753,
    "gn:feature_class":"P",
    "gn:feature_code":"PPL",
    "gn:name":"B\u1ea3n N\u00e0 B\u00f3",
    "gn:population":0,
    "gn:timezone":"Asia/Ho_Chi_Minh",
    "iso:country":"VN",
    "name:vie_x_preferred":[
        "B\u1ea3n N\u00e0 B\u00f3"
    ],
    "wof:name":"Ban Na Bo",
    "wof:placetype":"locality"
},
  "geometry": {"coordinates":[104.14288000000001,21.22545],"type":"Point"}
}