{
  "type": "Feature",
  "properties": {
    "gn:admin1_code":"39.0",
    "gn:asciiname":"Lung Thuong",
    "gn:country_code":"VN",
    "gn:dem":218,
    "gn:feature_class":"P",
    "gn:feature_code":"PPL",
    "gn:name":"L\u0169ng Thu\u00f4ng",
    "gn:population":0,
    "gn:timezone":"Asia/Ho_Chi_Minh",
    "iso:country":"VN",
    "name:und_x_variant":[
        "L\u0169ng Thu\u00f4ng",
        "L\u0169ng Th\u00f4ng"
    ],
    "wof:name":"Lung Thuong",
    "wof:placetype":"locality"
},
  "geometry": {"coordinates":[106.58504000000001,22.11842],"type":"Point"}
}