{
  "type": "Feature",
  "properties": {
    "gn:admin1_code":"21.0",
    "gn:asciiname":"My Phuc",
    "gn:country_code":"VN",
    "gn:dem":5,
    "gn:feature_class":"P",
    "gn:feature_code":"PPL",
    "gn:name":"M\u1ef9 Ph\u00fac",
    "gn:population":0,
    "gn:timezone":"Asia/Ho_Chi_Minh",
    "iso:country":"VN",
    "name:und_x_variant":[
        "Th\u00f4n M\u1ef9 Ph\u00fac"
    ],
    "name:vie_x_preferred":[
        "M\u1ef9 Ph\u00fac"
    ],
    "wof:name":"My Phuc",
    "wof:placetype":"locality"
},
  "geometry": {"coordinates":[105.03033000000001,10.13872],"type":"Point"}
}