{
  "type": "Feature",
  "properties": {
    "gn:admin1_code":"32.0",
    "gn:asciiname":"Ban Lun",
    "gn:cc2":"VN",
    "gn:country_code":"VN",
    "gn:dem":808,
    "gn:feature_class":"P",
    "gn:feature_code":"PPL",
    "gn:name":"B\u1ea3n Lun",
    "gn:population":0,
    "gn:timezone":"Asia/Ho_Chi_Minh",
    "iso:country":"VN",
    "name:und_x_variant":[
        "Ban Lum",
        "B\u1ea3n Lun"
    ],
    "wof:name":"Ban Lun",
    "wof:placetype":"locality"
},
  "geometry": {"coordinates":[104.11667,21.28333],"type":"Point"}
}