{
  "type": "Feature",
  "properties": {
    "gn:admin1_code":"75.0",
    "gn:asciiname":"Xom Xoai",
    "gn:country_code":"VN",
    "gn:dem":26,
    "gn:feature_class":"P",
    "gn:feature_code":"PPL",
    "gn:name":"X\u00f3m Xoai",
    "gn:population":0,
    "gn:timezone":"Asia/Ho_Chi_Minh",
    "iso:country":"VN",
    "wof:name":"Xom Xoai",
    "wof:placetype":"locality"
},
  "geometry": {"coordinates":[106.59999999999999,11.13333],"type":"Point"}
}