{
  "type": "Feature",
  "properties": {
    "gn:admin1_code":"50.0",
    "gn:asciiname":"Na Ngong",
    "gn:country_code":"VN",
    "gn:dem":525,
    "gn:feature_class":"P",
    "gn:feature_code":"PPL",
    "gn:name":"N\u00e0 Ng\u00f2ng",
    "gn:population":0,
    "gn:timezone":"Asia/Ho_Chi_Minh",
    "iso:country":"VN",
    "name:vie_x_preferred":[
        "N\u00e0 Ng\u00f2ng"
    ],
    "wof:name":"Na Ngong",
    "wof:placetype":"locality"
},
  "geometry": {"coordinates":[105.24687,22.85241],"type":"Point"}
}