{
  "type": "Feature",
  "properties": {
    "gn:admin1_code":"89.0",
    "gn:asciiname":"Nam Tan",
    "gn:country_code":"VN",
    "gn:dem":1521,
    "gn:feature_class":"P",
    "gn:feature_code":"PPL",
    "gn:name":"Nam Tan",
    "gn:population":0,
    "gn:timezone":"Asia/Ho_Chi_Minh",
    "iso:country":"VN",
    "wof:name":"Nam Tan",
    "wof:placetype":"locality"
},
  "geometry": {"coordinates":[103.08333,22.46667],"type":"Point"}
}