{
  "type": "Feature",
  "properties": {
    "gn:admin1_code":"58.0",
    "gn:asciiname":"Lang Moi",
    "gn:country_code":"VN",
    "gn:dem":31,
    "gn:feature_class":"P",
    "gn:feature_code":"PPL",
    "gn:name":"L\u00e0ng M\u1edbi",
    "gn:population":0,
    "gn:timezone":"Asia/Ho_Chi_Minh",
    "iso:country":"VN",
    "name:und_x_variant":[
        "Lang Mai",
        "L\u00e0ng M\u1edbi"
    ],
    "wof:name":"Lang Moi",
    "wof:placetype":"locality"
},
  "geometry": {"coordinates":[105.01667,19.06667],"type":"Point"}
}