{
  "type": "Feature",
  "properties": {
    "gn:admin1_code":"69.0",
    "gn:asciiname":"Dap Say",
    "gn:country_code":"VN",
    "gn:dem":6,
    "gn:feature_class":"P",
    "gn:feature_code":"PPL",
    "gn:name":"\u0110\u1eadp S\u1eady",
    "gn:population":0,
    "gn:timezone":"Asia/Ho_Chi_Minh",
    "iso:country":"VN",
    "name:vie_x_preferred":[
        "\u0110\u1eadp S\u1eady"
    ],
    "wof:name":"Dap Say",
    "wof:placetype":"locality"
},
  "geometry": {"coordinates":[106.09098,10.09193],"type":"Point"}
}