{
  "type": "Feature",
  "properties": {
    "gn:admin1_code":"89.0",
    "gn:asciiname":"Chieng La",
    "gn:country_code":"VN",
    "gn:dem":681,
    "gn:feature_class":"P",
    "gn:feature_code":"PPL",
    "gn:name":"Chi\u1ebfng L\u00e0",
    "gn:population":0,
    "gn:timezone":"Asia/Ho_Chi_Minh",
    "iso:country":"VN",
    "name:vie_x_preferred":[
        "Chi\u1ebfng L\u00e0"
    ],
    "wof:name":"Chieng La",
    "wof:placetype":"locality"
},
  "geometry": {"coordinates":[103.54415,22.3399],"type":"Point"}
}