{
  "type": "Feature",
  "properties": {
    "gn:admin1_code":"66.0",
    "gn:asciiname":"Thon Duong Pham",
    "gn:country_code":"VN",
    "gn:dem":46,
    "gn:feature_class":"P",
    "gn:feature_code":"PPL",
    "gn:name":"Th\u00f4n D\u01b0\u01a1ng Ph\u1ea9m",
    "gn:population":0,
    "gn:timezone":"Asia/Ho_Chi_Minh",
    "iso:country":"VN",
    "name:und_x_variant":[
        "Duong Pham",
        "Th\u00f4n D\u01b0\u01a1ng Ph\u1ea9m"
    ],
    "wof:name":"Thon Duong Pham",
    "wof:placetype":"locality"
},
  "geometry": {"coordinates":[107.61667,16.43333],"type":"Point"}
}