{
  "type": "Feature",
  "properties": {
    "gn:admin1_code":"9.0",
    "gn:asciiname":"Ap K Tam",
    "gn:country_code":"VN",
    "gn:dem":7,
    "gn:feature_class":"P",
    "gn:feature_code":"PPL",
    "gn:name":"\u1ea4p K T\u00e1m",
    "gn:population":0,
    "gn:timezone":"Asia/Ho_Chi_Minh",
    "iso:country":"VN",
    "name:vie_x_preferred":[
        "\u1ea4p K T\u00e1m"
    ],
    "name:vie_x_variant":[
        "\u1ea4p K8"
    ],
    "wof:name":"Ap K Tam",
    "wof:placetype":"locality"
},
  "geometry": {"coordinates":[105.54458,10.70405],"type":"Point"}
}