{
  "type": "Feature",
  "properties": {
    "gn:admin1_code":"58.0",
    "gn:asciiname":"Trung Hau",
    "gn:country_code":"VN",
    "gn:dem":9,
    "gn:feature_class":"P",
    "gn:feature_code":"PPL",
    "gn:name":"Trung H\u1eadu",
    "gn:population":0,
    "gn:timezone":"Asia/Ho_Chi_Minh",
    "iso:country":"VN",
    "name:vie_x_preferred":[
        "Trung H\u1eadu"
    ],
    "wof:name":"Trung Hau",
    "wof:placetype":"locality"
},
  "geometry": {"coordinates":[105.60509999999999,19.12943],"type":"Point"}
}