{
  "type": "Feature",
  "properties": {
    "gn:admin1_code":"72.0",
    "gn:asciiname":"Phieng Muong",
    "gn:country_code":"VN",
    "gn:dem":652,
    "gn:feature_class":"P",
    "gn:feature_code":"PPLL",
    "gn:name":"Phi\u00eang Mu\u1ed3ng",
    "gn:population":0,
    "gn:timezone":"Asia/Ho_Chi_Minh",
    "iso:country":"VN",
    "wof:name":"Phieng Muong",
    "wof:placetype":"locality"
},
  "geometry": {"coordinates":[105.76376999999999,22.37572],"type":"Point"}
}