{
  "type": "Feature",
  "properties": {
    "gn:admin1_code":"84.0",
    "gn:asciiname":"Thon Hiep",
    "gn:country_code":"VN",
    "gn:dem":58,
    "gn:feature_class":"P",
    "gn:feature_code":"PPL",
    "gn:name":"Th\u00f4n Hi\u1ec7p",
    "gn:population":0,
    "gn:timezone":"Asia/Ho_Chi_Minh",
    "iso:country":"VN",
    "name:vie_x_preferred":[
        "Th\u00f4n Hi\u1ec7p"
    ],
    "wof:name":"Thon Hiep",
    "wof:placetype":"locality"
},
  "geometry": {"coordinates":[107.81305999999999,15.88275],"type":"Point"}
}