{
  "type": "Feature",
  "properties": {
    "gn:admin1_code":"92.0",
    "gn:asciiname":"Muong Tong",
    "gn:country_code":"VN",
    "gn:dem":344,
    "gn:feature_class":"P",
    "gn:feature_code":"PPL",
    "gn:name":"M\u01b0\u01a1ng Tong",
    "gn:population":0,
    "gn:timezone":"Asia/Ho_Chi_Minh",
    "iso:country":"VN",
    "name:und_x_variant":[
        "Muong Toung",
        "Muong Tung",
        "M\u01b0\u01a1ng Tong"
    ],
    "name:vie_x_preferred":[
        "M\u01b0\u1eddng T\u00f9ng"
    ],
    "wof:name":"Muong Tong",
    "wof:placetype":"locality"
},
  "geometry": {"coordinates":[103.13333,21.96667],"type":"Point"}
}