{
  "type": "Feature",
  "properties": {
    "gn:admin1_code":"23.0",
    "gn:asciiname":"B'sar Lou Sieum",
    "gn:country_code":"VN",
    "gn:dem":499,
    "gn:feature_class":"P",
    "gn:feature_code":"PPL",
    "gn:name":"B\u2019sar Lou Sieum",
    "gn:population":0,
    "gn:timezone":"Asia/Ho_Chi_Minh",
    "iso:country":"VN",
    "name:und_x_variant":[
        "B\u2019Sar Lou Sieun",
        "Bsar Lusieng",
        "B\u2019Sar L\u2019Sieun",
        "B\u2019sar Lou Sieum"
    ],
    "wof:name":"B'sar Lou Sieum",
    "wof:placetype":"locality"
},
  "geometry": {"coordinates":[107.46666999999999,11.73333],"type":"Point"}
}