{
  "type": "Feature",
  "properties": {
    "gn:admin1_code":"89.0",
    "gn:asciiname":"Ban Chom Chang",
    "gn:country_code":"VN",
    "gn:dem":589,
    "gn:feature_class":"P",
    "gn:feature_code":"PPL",
    "gn:name":"B\u1ea3n Chom Ch\u0103ng",
    "gn:population":0,
    "gn:timezone":"Asia/Ho_Chi_Minh",
    "iso:country":"VN",
    "name:und_x_variant":[
        "Chom Chang"
    ],
    "name:vie_x_preferred":[
        "B\u1ea3n Chom Ch\u0103ng"
    ],
    "wof:name":"Ban Chom Chang",
    "wof:placetype":"locality"
},
  "geometry": {"coordinates":[103.77153,22.1579],"type":"Point"}
}