{
  "type": "Feature",
  "properties": {
    "gn:admin1_code":"32.0",
    "gn:asciiname":"Na Sang",
    "gn:country_code":"VN",
    "gn:dem":499,
    "gn:feature_class":"P",
    "gn:feature_code":"PPL",
    "gn:name":"Na Sang",
    "gn:population":0,
    "gn:timezone":"Asia/Ho_Chi_Minh",
    "iso:country":"VN",
    "name:vie_x_preferred":[
        "Na Sang"
    ],
    "wof:name":"Na Sang",
    "wof:placetype":"locality"
},
  "geometry": {"coordinates":[103.73333,21.08333],"type":"Point"}
}