{
  "type": "Feature",
  "properties": {
    "gn:admin1_code":"32.0",
    "gn:asciiname":"Y Chou Phen",
    "gn:country_code":"VN",
    "gn:dem":1161,
    "gn:feature_class":"P",
    "gn:feature_code":"PPL",
    "gn:name":"Y Chou Phen",
    "gn:population":0,
    "gn:timezone":"Asia/Ho_Chi_Minh",
    "iso:country":"VN",
    "wof:name":"Y Chou Phen",
    "wof:placetype":"locality"
},
  "geometry": {"coordinates":[104.16667,21.46667],"type":"Point"}
}