{
  "type": "Feature",
  "properties": {
    "gn:admin1_code":"46.0",
    "gn:asciiname":"Cu Lam Bac",
    "gn:country_code":"VN",
    "gn:dem":17,
    "gn:feature_class":"P",
    "gn:feature_code":"PPL",
    "gn:name":"C\u0169 L\u00e2m B\u1eafc",
    "gn:population":0,
    "gn:timezone":"Asia/Ho_Chi_Minh",
    "iso:country":"VN",
    "name:und_x_variant":[
        "C\u00f9 L\u00e2m",
        "C\u0169 L\u00e2m B\u1eafc"
    ],
    "wof:name":"Cu Lam Bac",
    "wof:placetype":"locality"
},
  "geometry": {"coordinates":[109.03333000000001,13.88333],"type":"Point"}
}