{
  "type": "Feature",
  "properties": {
    "gn:admin1_code":"68.0",
    "gn:asciiname":"Lang Dau",
    "gn:country_code":"VN",
    "gn:dem":114,
    "gn:feature_class":"P",
    "gn:feature_code":"PPL",
    "gn:name":"L\u00e0ng \u0110\u1ea9u",
    "gn:population":0,
    "gn:timezone":"Asia/Ho_Chi_Minh",
    "iso:country":"VN",
    "name:vie_x_preferred":[
        "L\u00e0ng \u0110\u1ea9u"
    ],
    "wof:name":"Lang Dau",
    "wof:placetype":"locality"
},
  "geometry": {"coordinates":[105.19512,22.15342],"type":"Point"}
}