{
  "type": "Feature",
  "properties": {
    "gn:admin1_code":"50.0",
    "gn:asciiname":"Nam Hou Chan",
    "gn:country_code":"VN",
    "gn:dem":468,
    "gn:feature_class":"P",
    "gn:feature_code":"PPL",
    "gn:name":"Nam Hou Chan",
    "gn:population":0,
    "gn:timezone":"Asia/Ho_Chi_Minh",
    "iso:country":"VN",
    "name:und_x_variant":[
        "Nam Hau Chan",
        "Nam Hou Chan"
    ],
    "wof:name":"Nam Hou Chan",
    "wof:placetype":"locality"
},
  "geometry": {"coordinates":[104.45,22.65],"type":"Point"}
}