{
  "type": "Feature",
  "properties": {
    "gn:admin1_code":"39.0",
    "gn:asciiname":"Na Lin",
    "gn:country_code":"VN",
    "gn:dem":278,
    "gn:feature_class":"P",
    "gn:feature_code":"PPL",
    "gn:name":"N\u00e0 Lin",
    "gn:population":0,
    "gn:timezone":"Asia/Ho_Chi_Minh",
    "iso:country":"VN",
    "name:vie_x_preferred":[
        "N\u00e0 Lin"
    ],
    "wof:name":"Na Lin",
    "wof:placetype":"locality"
},
  "geometry": {"coordinates":[106.46065,21.80373],"type":"Point"}
}