{
  "type": "Feature",
  "properties": {
    "gn:admin1_code":"32.0",
    "gn:asciiname":"Ta Liu",
    "gn:country_code":"VN",
    "gn:dem":1081,
    "gn:feature_class":"P",
    "gn:feature_code":"PPL",
    "gn:name":"Ta L\u00edu",
    "gn:population":0,
    "gn:timezone":"Asia/Ho_Chi_Minh",
    "iso:country":"VN",
    "name:vie_x_preferred":[
        "Ta L\u00edu"
    ],
    "wof:name":"Ta Liu",
    "wof:placetype":"locality"
},
  "geometry": {"coordinates":[104.11211,20.98628],"type":"Point"}
}