{
  "type": "Feature",
  "properties": {
    "gn:admin1_code":"88.0",
    "gn:asciiname":"Ban Kdiel",
    "gn:cc2":"VN",
    "gn:country_code":"VN",
    "gn:dem":511,
    "gn:feature_class":"P",
    "gn:feature_code":"PPL",
    "gn:name":"Ban Kdiel",
    "gn:population":0,
    "gn:timezone":"Asia/Ho_Chi_Minh",
    "iso:country":"VN",
    "name:und_x_variant":[
        "Buon Kdiel",
        "Ban Kdiel"
    ],
    "wof:name":"Ban Kdiel",
    "wof:placetype":"locality"
},
  "geometry": {"coordinates":[108.41667,13.21667],"type":"Point"}
}