{
  "type": "Feature",
  "properties": {
    "gn:admin1_code":"82.0",
    "gn:asciiname":"Long Chau",
    "gn:country_code":"VN",
    "gn:dem":3,
    "gn:feature_class":"P",
    "gn:feature_code":"PPL",
    "gn:name":"Long Ch\u00e2u",
    "gn:population":0,
    "gn:timezone":"Asia/Ho_Chi_Minh",
    "iso:country":"VN",
    "name:und_x_variant":[
        "Long Ch\u00e2u"
    ],
    "name:vie_x_preferred":[
        "Long Chao"
    ],
    "wof:name":"Long Chau",
    "wof:placetype":"locality"
},
  "geometry": {"coordinates":[106.21666999999999,20.03333],"type":"Point"}
}