{
  "type": "Feature",
  "properties": {
    "gn:admin1_code":"74.0",
    "gn:asciiname":"Phong Coc",
    "gn:country_code":"VN",
    "gn:dem":8,
    "gn:feature_class":"P",
    "gn:feature_code":"PPL",
    "gn:name":"Phong C\u1ed1c",
    "gn:population":0,
    "gn:timezone":"Asia/Ho_Chi_Minh",
    "iso:country":"VN",
    "name:vie_x_preferred":[
        "Phong C\u1ed1c"
    ],
    "wof:name":"Phong Coc",
    "wof:placetype":"locality"
},
  "geometry": {"coordinates":[106.28982999999999,21.12343],"type":"Point"}
}