{
  "type": "Feature",
  "properties": {
    "gn:admin1_code":"90.0",
    "gn:asciiname":"Nam Sai",
    "gn:country_code":"VN",
    "gn:dem":552,
    "gn:feature_class":"P",
    "gn:feature_code":"PPL",
    "gn:name":"N\u1eadm S\u00e0i",
    "gn:population":0,
    "gn:timezone":"Asia/Ho_Chi_Minh",
    "iso:country":"VN",
    "name:und_x_variant":[
        "N\u00e0m Sang"
    ],
    "name:vie_x_preferred":[
        "N\u1eadm S\u00e0i"
    ],
    "wof:name":"Nam Sai",
    "wof:placetype":"locality"
},
  "geometry": {"coordinates":[104.0001,22.24724],"type":"Point"}
}