{
  "type": "Feature",
  "properties": {
    "gn:admin1_code":"68.0",
    "gn:asciiname":"Phuc Lam",
    "gn:country_code":"VN",
    "gn:dem":141,
    "gn:feature_class":"P",
    "gn:feature_code":"PPL",
    "gn:name":"Ph\u00fac L\u00e2m",
    "gn:population":0,
    "gn:timezone":"Asia/Ho_Chi_Minh",
    "iso:country":"VN",
    "wof:name":"Phuc Lam",
    "wof:placetype":"locality"
},
  "geometry": {"coordinates":[105.46666999999999,21.93333],"type":"Point"}
}