{
  "type": "Feature",
  "properties": {
    "gn:admin1_code":"68.0",
    "gn:asciiname":"Xom Cau Mot",
    "gn:country_code":"VN",
    "gn:dem":98,
    "gn:feature_class":"P",
    "gn:feature_code":"PPL",
    "gn:name":"X\u00f3m C\u1ea7u M\u1ed9t",
    "gn:population":0,
    "gn:timezone":"Asia/Ho_Chi_Minh",
    "iso:country":"VN",
    "name:vie_x_preferred":[
        "X\u00f3m C\u1ea7u 1"
    ],
    "name:vie_x_variant":[
        "X\u00f3m C\u1ea7u M\u1ed9t"
    ],
    "wof:name":"Xom Cau Mot",
    "wof:placetype":"locality"
},
  "geometry": {"coordinates":[105.40031999999999,21.76143],"type":"Point"}
}