{
  "type": "Feature",
  "properties": {
    "gn:admin1_code":"68.0",
    "gn:asciiname":"Pac Van",
    "gn:country_code":"VN",
    "gn:dem":163,
    "gn:feature_class":"P",
    "gn:feature_code":"PPL",
    "gn:name":"Pac Van",
    "gn:population":0,
    "gn:timezone":"Asia/Ho_Chi_Minh",
    "iso:country":"VN",
    "name:und_x_variant":[
        "Pac Ven",
        "Pac Van"
    ],
    "wof:name":"Pac Van",
    "wof:placetype":"locality"
},
  "geometry": {"coordinates":[105.38333,22.46667],"type":"Point"}
}