{
  "type": "Feature",
  "properties": {
    "gn:admin1_code":"49.0",
    "gn:asciiname":"De Panang Groi",
    "gn:country_code":"VN",
    "gn:dem":679,
    "gn:feature_class":"P",
    "gn:feature_code":"PPL",
    "gn:name":"De Panang Groi",
    "gn:population":0,
    "gn:timezone":"Asia/Ho_Chi_Minh",
    "iso:country":"VN",
    "name:und_x_variant":[
        "De Panang Grol",
        "De Panang Groi"
    ],
    "wof:name":"De Panang Groi",
    "wof:placetype":"locality"
},
  "geometry": {"coordinates":[108.25,13.85],"type":"Point"}
}