{
  "type": "Feature",
  "properties": {
    "gn:admin1_code":"81.0",
    "gn:asciiname":"Ta Ha",
    "gn:country_code":"VN",
    "gn:dem":6,
    "gn:feature_class":"P",
    "gn:feature_code":"PPL",
    "gn:name":"Ta H\u1ea1",
    "gn:population":0,
    "gn:timezone":"Asia/Ho_Chi_Minh",
    "iso:country":"VN",
    "name:vie_x_preferred":[
        "Ta H\u1ea1"
    ],
    "wof:name":"Ta Ha",
    "wof:placetype":"locality"
},
  "geometry": {"coordinates":[106.06771999999999,20.75408],"type":"Point"}
}