{
  "type": "Feature",
  "properties": {
    "gn:admin1_code":"53.0",
    "gn:asciiname":"Xom Trao",
    "gn:country_code":"VN",
    "gn:dem":213,
    "gn:feature_class":"P",
    "gn:feature_code":"PPL",
    "gn:name":"X\u00f3m Trao",
    "gn:population":0,
    "gn:timezone":"Asia/Ho_Chi_Minh",
    "iso:country":"VN",
    "name:vie_x_preferred":[
        "X\u00f3m Trao"
    ],
    "wof:name":"Xom Trao",
    "wof:placetype":"locality"
},
  "geometry": {"coordinates":[105.18643,20.6467],"type":"Point"}
}