{
  "type": "Feature",
  "properties": {
    "gn:admin1_code":"83.0",
    "gn:asciiname":"Du Ba",
    "gn:country_code":"VN",
    "gn:dem":31,
    "gn:feature_class":"P",
    "gn:feature_code":"PPL",
    "gn:name":"\u0110\u01b0 Ba",
    "gn:population":0,
    "gn:timezone":"Asia/Ho_Chi_Minh",
    "iso:country":"VN",
    "name:vie_x_preferred":[
        "\u0110\u01b0 Ba"
    ],
    "wof:name":"Du Ba",
    "wof:placetype":"locality"
},
  "geometry": {"coordinates":[105.0714,21.47667],"type":"Point"}
}