{
  "type": "Feature",
  "properties": {
    "gn:admin1_code":"30.0",
    "gn:asciiname":"Tan Oc",
    "gn:country_code":"VN",
    "gn:dem":116,
    "gn:feature_class":"P",
    "gn:feature_code":"PPL",
    "gn:name":"Tan \u1ed0c",
    "gn:population":0,
    "gn:timezone":"Asia/Ho_Chi_Minh",
    "iso:country":"VN",
    "name:und_x_variant":[
        "Tan Co",
        "T\u00e2n \u00d3c"
    ],
    "name:vie_x_preferred":[
        "Tan \u1ed0c"
    ],
    "wof:name":"Tan Oc",
    "wof:placetype":"locality"
},
  "geometry": {"coordinates":[107.02115000000001,21.19349],"type":"Point"}
}