{
  "type": "Feature",
  "properties": {
    "gn:admin1_code":"32.0",
    "gn:asciiname":"Ban Chieng La",
    "gn:country_code":"VN",
    "gn:dem":678,
    "gn:feature_class":"P",
    "gn:feature_code":"PPL",
    "gn:name":"B\u1ea3n Chi\u00eang La",
    "gn:population":0,
    "gn:timezone":"Asia/Ho_Chi_Minh",
    "iso:country":"VN",
    "wof:name":"Ban Chieng La",
    "wof:placetype":"locality"
},
  "geometry": {"coordinates":[103.68333,21.51667],"type":"Point"}
}