{
  "type": "Feature",
  "properties": {
    "gn:admin1_code":"33.0",
    "gn:asciiname":"Xom Ruong",
    "gn:country_code":"VN",
    "gn:dem":9,
    "gn:feature_class":"P",
    "gn:feature_code":"PPL",
    "gn:name":"X\u00f3m Ru\u1ed9ng",
    "gn:population":0,
    "gn:timezone":"Asia/Ho_Chi_Minh",
    "iso:country":"VN",
    "name:vie_x_preferred":[
        "X\u00f3m Ru\u1ed9ng"
    ],
    "wof:name":"Xom Ruong",
    "wof:placetype":"locality"
},
  "geometry": {"coordinates":[106.01729,11.30188],"type":"Point"}
}