{
  "type": "Feature",
  "properties": {
    "gn:admin1_code":"74.0",
    "gn:asciiname":"Phuong Trien",
    "gn:country_code":"VN",
    "gn:dem":4,
    "gn:feature_class":"P",
    "gn:feature_code":"PPL",
    "gn:name":"Ph\u01b0\u01a1ng Tri\u1ec7n",
    "gn:population":0,
    "gn:timezone":"Asia/Ho_Chi_Minh",
    "iso:country":"VN",
    "name:und_x_variant":[
        "Ph\u01b0\u01a1ng Tri\u1ec7n"
    ],
    "name:vie_x_preferred":[
        "Ph\u01b0\u01a1ng Tri\u1ec7t"
    ],
    "wof:name":"Phuong Trien",
    "wof:placetype":"locality"
},
  "geometry": {"coordinates":[106.22311999999999,21.07998],"type":"Point"}
}