{
  "type": "Feature",
  "properties": {
    "gn:admin1_code":"71.0",
    "gn:asciiname":"Toun Mouei",
    "gn:country_code":"VN",
    "gn:dem":89,
    "gn:feature_class":"P",
    "gn:feature_code":"PPL",
    "gn:name":"Toun Mou\u00e9i",
    "gn:population":0,
    "gn:timezone":"Asia/Ho_Chi_Minh",
    "iso:country":"VN",
    "wof:name":"Toun Mouei",
    "wof:placetype":"locality"
},
  "geometry": {"coordinates":[106.73333,21.45],"type":"Point"}
}