{
  "type": "Feature",
  "properties": {
    "gn:admin1_code":"39.0",
    "gn:asciiname":"Khun Dut",
    "gn:country_code":"VN",
    "gn:dem":411,
    "gn:feature_class":"P",
    "gn:feature_code":"PPL",
    "gn:name":"Khun Dut",
    "gn:population":0,
    "gn:timezone":"Asia/Ho_Chi_Minh",
    "iso:country":"VN",
    "wof:name":"Khun Dut",
    "wof:placetype":"locality"
},
  "geometry": {"coordinates":[106.45,21.68333],"type":"Point"}
}