{
  "type": "Feature",
  "properties": {
    "gn:admin1_code":"39.0",
    "gn:asciiname":"Ban Pac Pan",
    "gn:country_code":"VN",
    "gn:dem":158,
    "gn:feature_class":"P",
    "gn:feature_code":"PPL",
    "gn:name":"B\u1ea3n P\u00e1c Pan",
    "gn:population":0,
    "gn:timezone":"Asia/Ho_Chi_Minh",
    "iso:country":"VN",
    "wof:name":"Ban Pac Pan",
    "wof:placetype":"locality"
},
  "geometry": {"coordinates":[106.54125999999999,22.22211],"type":"Point"}
}