{
  "type": "Feature",
  "properties": {
    "gn:admin1_code":"52.0",
    "gn:asciiname":"Trai Tan",
    "gn:country_code":"VN",
    "gn:dem":37,
    "gn:feature_class":"P",
    "gn:feature_code":"PPL",
    "gn:name":"Tr\u1ea1i T\u00e2n",
    "gn:population":0,
    "gn:timezone":"Asia/Ho_Chi_Minh",
    "iso:country":"VN",
    "name:vie_x_preferred":[
        "Tr\u1ea1i T\u00e2n"
    ],
    "wof:name":"Trai Tan",
    "wof:placetype":"locality"
},
  "geometry": {"coordinates":[105.34829000000001,18.56319],"type":"Point"}
}