{
  "type": "Feature",
  "properties": {
    "gn:admin1_code":"53.0",
    "gn:asciiname":"Ban Suoi Gioi",
    "gn:country_code":"VN",
    "gn:dem":118,
    "gn:feature_class":"P",
    "gn:feature_code":"PPL",
    "gn:name":"B\u1ea3n Su\u1ed1i Gioi",
    "gn:population":0,
    "gn:timezone":"Asia/Ho_Chi_Minh",
    "iso:country":"VN",
    "wof:name":"Ban Suoi Gioi",
    "wof:placetype":"locality"
},
  "geometry": {"coordinates":[105.05,20.83333],"type":"Point"}
}