{
  "type": "Feature",
  "properties": {
    "gn:admin1_code":"5.0",
    "gn:asciiname":"Lung Nieo",
    "gn:country_code":"VN",
    "gn:dem":448,
    "gn:feature_class":"P",
    "gn:feature_code":"PPL",
    "gn:name":"L\u0169ng Ni\u00eao",
    "gn:population":0,
    "gn:timezone":"Asia/Ho_Chi_Minh",
    "iso:country":"VN",
    "wof:name":"Lung Nieo",
    "wof:placetype":"locality"
},
  "geometry": {"coordinates":[106.71666999999999,22.85],"type":"Point"}
}