{
  "type": "Feature",
  "properties": {
    "gn:admin1_code":"50.0",
    "gn:asciiname":"Nam Lao",
    "gn:country_code":"VN",
    "gn:dem":1505,
    "gn:feature_class":"P",
    "gn:feature_code":"PPL",
    "gn:name":"Nam Lao",
    "gn:population":0,
    "gn:timezone":"Asia/Ho_Chi_Minh",
    "iso:country":"VN",
    "wof:name":"Nam Lao",
    "wof:placetype":"locality"
},
  "geometry": {"coordinates":[104.76667,22.86667000000001],"type":"Point"}
}