{
  "type": "Feature",
  "properties": {
    "gn:admin1_code":"58.0",
    "gn:asciiname":"Xuan Lieu",
    "gn:country_code":"VN",
    "gn:dem":8,
    "gn:feature_class":"P",
    "gn:feature_code":"PPL",
    "gn:name":"Xu\u00e2n Lieu",
    "gn:population":0,
    "gn:timezone":"Asia/Ho_Chi_Minh",
    "iso:country":"VN",
    "wof:name":"Xuan Lieu",
    "wof:placetype":"locality"
},
  "geometry": {"coordinates":[105.65000000000001,18.71667],"type":"Point"}
}