{
  "type": "Feature",
  "properties": {
    "gn:admin1_code":"84.0",
    "gn:asciiname":"A Hourn",
    "gn:country_code":"VN",
    "gn:dem":533,
    "gn:feature_class":"P",
    "gn:feature_code":"PPL",
    "gn:name":"A Hourn",
    "gn:population":0,
    "gn:timezone":"Asia/Ho_Chi_Minh",
    "iso:country":"VN",
    "wof:name":"A Hourn",
    "wof:placetype":"locality"
},
  "geometry": {"coordinates":[107.48333,15.61667],"type":"Point"}
}