{
  "type": "Feature",
  "properties": {
    "gn:admin1_code":"32.0",
    "gn:asciiname":"Ban Luot",
    "gn:country_code":"VN",
    "gn:dem":1021,
    "gn:feature_class":"P",
    "gn:feature_code":"PPL",
    "gn:name":"B\u1ea3n L\u01b0\u1edbt",
    "gn:population":0,
    "gn:timezone":"Asia/Ho_Chi_Minh",
    "iso:country":"VN",
    "name:vie_x_preferred":[
        "B\u1ea3n L\u01b0\u1edbt"
    ],
    "wof:name":"Ban Luot",
    "wof:placetype":"locality"
},
  "geometry": {"coordinates":[104.23641000000001,21.64714],"type":"Point"}
}