{
  "type": "Feature",
  "properties": {
    "gn:admin1_code":"16.0",
    "gn:asciiname":"Xom Bao",
    "gn:country_code":"VN",
    "gn:dem":333,
    "gn:feature_class":"P",
    "gn:feature_code":"PPL",
    "gn:name":"X\u00f3m Bao",
    "gn:population":0,
    "gn:timezone":"Asia/Ho_Chi_Minh",
    "iso:country":"VN",
    "name:und_x_variant":[
        "B\u1ea3n Su\u1ed1i Bao"
    ],
    "name:vie_x_preferred":[
        "X\u00f3m Bao"
    ],
    "wof:name":"Xom Bao",
    "wof:placetype":"locality"
},
  "geometry": {"coordinates":[104.991,21.01441],"type":"Point"}
}