{
  "type": "Feature",
  "properties": {
    "gn:admin1_code":"58.0",
    "gn:asciiname":"Phuc Am",
    "gn:country_code":"VN",
    "gn:dem":20,
    "gn:feature_class":"P",
    "gn:feature_code":"PPL",
    "gn:name":"Ph\u00fac Am",
    "gn:population":0,
    "gn:timezone":"Asia/Ho_Chi_Minh",
    "iso:country":"VN",
    "name:und_x_variant":[
        "Rh\u00fac Am",
        "Ph\u00fac Am"
    ],
    "wof:name":"Phuc Am",
    "wof:placetype":"locality"
},
  "geometry": {"coordinates":[105.41667,19.03333],"type":"Point"}
}