{
  "type": "Feature",
  "properties": {
    "gn:admin1_code":"89.0",
    "gn:asciiname":"Sin Tiai",
    "gn:cc2":"VN",
    "gn:country_code":"VN",
    "gn:dem":1263,
    "gn:feature_class":"P",
    "gn:feature_code":"PPL",
    "gn:name":"Sin Tiai",
    "gn:population":0,
    "gn:timezone":"Asia/Ho_Chi_Minh",
    "iso:country":"VN",
    "name:und_x_variant":[
        "Sin Tisi",
        "Sin Tiai"
    ],
    "wof:name":"Sin Tiai",
    "wof:placetype":"locality"
},
  "geometry": {"coordinates":[103.41667,22.43333],"type":"Point"}
}