{
  "type": "Feature",
  "properties": {
    "gn:admin1_code":"90.0",
    "gn:asciiname":"Lo Sui Tong",
    "gn:country_code":"VN",
    "gn:dem":1427,
    "gn:feature_class":"P",
    "gn:feature_code":"PPL",
    "gn:name":"Lo Sui Tong",
    "gn:population":0,
    "gn:timezone":"Asia/Ho_Chi_Minh",
    "iso:country":"VN",
    "wof:name":"Lo Sui Tong",
    "wof:placetype":"locality"
},
  "geometry": {"coordinates":[103.83333,22.33333],"type":"Point"}
}