{
  "type": "Feature",
  "properties": {
    "gn:admin1_code":"92.0",
    "gn:asciiname":"Huoi Pan",
    "gn:country_code":"VN",
    "gn:dem":937,
    "gn:feature_class":"P",
    "gn:feature_code":"PPL",
    "gn:name":"Hu\u1ed5i Pan",
    "gn:population":0,
    "gn:timezone":"Asia/Ho_Chi_Minh",
    "iso:country":"VN",
    "name:vie_x_preferred":[
        "Hu\u1ed5i Pan"
    ],
    "wof:name":"Huoi Pan",
    "wof:placetype":"locality"
},
  "geometry": {"coordinates":[103.31411,21.21282],"type":"Point"}
}