{
  "type": "Feature",
  "properties": {
    "gn:admin1_code":"5.0",
    "gn:asciiname":"Nam Din",
    "gn:country_code":"VN",
    "gn:dem":774,
    "gn:feature_class":"P",
    "gn:feature_code":"PPL",
    "gn:name":"N\u1eb7m \u0110in",
    "gn:population":0,
    "gn:timezone":"Asia/Ho_Chi_Minh",
    "iso:country":"VN",
    "wof:name":"Nam Din",
    "wof:placetype":"locality"
},
  "geometry": {"coordinates":[106.15000000000001,22.96667],"type":"Point"}
}