{
  "type": "Feature",
  "properties": {
    "gn:admin1_code":"68.0",
    "gn:asciiname":"Trung Muong",
    "gn:country_code":"VN",
    "gn:dem":135,
    "gn:feature_class":"P",
    "gn:feature_code":"PPL",
    "gn:name":"Trung M\u01b0\u1eddng",
    "gn:population":0,
    "gn:timezone":"Asia/Ho_Chi_Minh",
    "iso:country":"VN",
    "name:und_x_variant":[
        "Tong Muong",
        "Tung Muong"
    ],
    "name:vie_x_preferred":[
        "Trung M\u01b0\u1eddng"
    ],
    "wof:name":"Trung Muong",
    "wof:placetype":"locality"
},
  "geometry": {"coordinates":[105.46172,22.53496],"type":"Point"}
}