{
  "type": "Feature",
  "properties": {
    "gn:admin1_code":"54.0",
    "gn:asciiname":"Trung Dong",
    "gn:country_code":"VN",
    "gn:dem":18,
    "gn:feature_class":"P",
    "gn:feature_code":"PPL",
    "gn:name":"Trung \u0110\u1ecfng",
    "gn:population":0,
    "gn:timezone":"Asia/Ho_Chi_Minh",
    "iso:country":"VN",
    "name:und_x_variant":[
        "Trung Vong",
        "Trung \u0110\u1ecfng"
    ],
    "wof:name":"Trung Dong",
    "wof:placetype":"locality"
},
  "geometry": {"coordinates":[109.23333,12.73333],"type":"Point"}
}