{
  "type": "Feature",
  "properties": {
    "gn:admin1_code":"68.0",
    "gn:asciiname":"Ban Tai",
    "gn:country_code":"VN",
    "gn:dem":93,
    "gn:feature_class":"P",
    "gn:feature_code":"PPL",
    "gn:name":"B\u00e1n Tai",
    "gn:population":0,
    "gn:timezone":"Asia/Ho_Chi_Minh",
    "iso:country":"VN",
    "name:und_x_variant":[
        "B\u00e1n Tai",
        "B\u1ea3n Thai"
    ],
    "wof:name":"Ban Tai",
    "wof:placetype":"locality"
},
  "geometry": {"coordinates":[105.41251,22.13675],"type":"Point"}
}