{
  "type": "Feature",
  "properties": {
    "gn:admin1_code":"88.0",
    "gn:asciiname":"Ban Tri",
    "gn:cc2":"VN",
    "gn:country_code":"VN",
    "gn:dem":677,
    "gn:feature_class":"P",
    "gn:feature_code":"PPL",
    "gn:name":"Ban Tri",
    "gn:population":0,
    "gn:timezone":"Asia/Ho_Chi_Minh",
    "iso:country":"VN",
    "name:und_x_variant":[
        "Boun Tri",
        "Ban Tri"
    ],
    "wof:name":"Ban Tri",
    "wof:placetype":"locality"
},
  "geometry": {"coordinates":[108.25,13.18333],"type":"Point"}
}