{
  "type": "Feature",
  "properties": {
    "gn:admin1_code":"52.0",
    "gn:asciiname":"Nam Thinh",
    "gn:country_code":"VN",
    "gn:dem":7,
    "gn:feature_class":"P",
    "gn:feature_code":"PPL",
    "gn:name":"Nam Th\u1ecbnh",
    "gn:population":0,
    "gn:timezone":"Asia/Ho_Chi_Minh",
    "iso:country":"VN",
    "name:vie_x_preferred":[
        "Nam Th\u1ecbnh"
    ],
    "wof:name":"Nam Thinh",
    "wof:placetype":"locality"
},
  "geometry": {"coordinates":[105.79294,18.44021],"type":"Point"}
}