{
  "type": "Feature",
  "properties": {
    "gn:admin1_code":"72.0",
    "gn:asciiname":"Koi Mo",
    "gn:country_code":"VN",
    "gn:dem":161,
    "gn:feature_class":"P",
    "gn:feature_code":"PPL",
    "gn:name":"Koi M\u00f2",
    "gn:population":0,
    "gn:timezone":"Asia/Ho_Chi_Minh",
    "iso:country":"VN",
    "name:und_x_variant":[
        "Kouei Mo"
    ],
    "name:vie_x_preferred":[
        "Koi M\u00f2"
    ],
    "wof:name":"Koi Mo",
    "wof:placetype":"locality"
},
  "geometry": {"coordinates":[105.87539,22.24697],"type":"Point"}
}