{
  "type": "Feature",
  "properties": {
    "gn:admin1_code":"84.0",
    "gn:asciiname":"Chau Khe",
    "gn:country_code":"VN",
    "gn:dem":5,
    "gn:feature_class":"P",
    "gn:feature_code":"PPL",
    "gn:name":"Ch\u00e2u Kh\u00ea",
    "gn:population":0,
    "gn:timezone":"Asia/Ho_Chi_Minh",
    "iso:country":"VN",
    "name:und_x_variant":[
        "Tien Chau",
        "Ch\u00e2u Kh\u00ea"
    ],
    "wof:name":"Chau Khe",
    "wof:placetype":"locality"
},
  "geometry": {"coordinates":[108.43333,15.71667],"type":"Point"}
}