{
  "type": "Feature",
  "properties": {
    "gn:admin1_code":"5.0",
    "gn:asciiname":"Na Sing",
    "gn:country_code":"VN",
    "gn:dem":362,
    "gn:feature_class":"P",
    "gn:feature_code":"PPL",
    "gn:name":"Na Sing",
    "gn:population":0,
    "gn:timezone":"Asia/Ho_Chi_Minh",
    "iso:country":"VN",
    "wof:name":"Na Sing",
    "wof:placetype":"locality"
},
  "geometry": {"coordinates":[106.55,22.48333],"type":"Point"}
}