{
  "type": "Feature",
  "properties": {
    "gn:admin1_code":"46.0",
    "gn:asciiname":"Dai Son",
    "gn:country_code":"VN",
    "gn:dem":34,
    "gn:feature_class":"P",
    "gn:feature_code":"PPL",
    "gn:name":"\u0110\u1ea1i S\u01a1n",
    "gn:population":0,
    "gn:timezone":"Asia/Ho_Chi_Minh",
    "iso:country":"VN",
    "name:vie_x_preferred":[
        "\u0110\u1ea1i S\u01a1n"
    ],
    "wof:name":"Dai Son",
    "wof:placetype":"locality"
},
  "geometry": {"coordinates":[109.02578,14.14126],"type":"Point"}
}