{
  "type": "Feature",
  "properties": {
    "gn:admin1_code":"85.0",
    "gn:asciiname":"Lang Moi",
    "gn:country_code":"VN",
    "gn:dem":49,
    "gn:feature_class":"P",
    "gn:feature_code":"PPL",
    "gn:name":"L\u00e0ng M\u1edbi",
    "gn:population":0,
    "gn:timezone":"Asia/Ho_Chi_Minh",
    "iso:country":"VN",
    "name:und_x_variant":[
        "L\u00e0ng Moi"
    ],
    "name:vie_x_preferred":[
        "L\u00e0ng M\u1edbi"
    ],
    "wof:name":"Lang Moi",
    "wof:placetype":"locality"
},
  "geometry": {"coordinates":[105.84332000000001,21.72506],"type":"Point"}
}