{
  "type": "Feature",
  "properties": {
    "gn:admin1_code":"39.0",
    "gn:asciiname":"Na Mon",
    "gn:country_code":"VN",
    "gn:dem":360,
    "gn:feature_class":"P",
    "gn:feature_code":"PPL",
    "gn:name":"Na Mon",
    "gn:population":0,
    "gn:timezone":"Asia/Ho_Chi_Minh",
    "iso:country":"VN",
    "wof:name":"Na Mon",
    "wof:placetype":"locality"
},
  "geometry": {"coordinates":[106.18333,22.06667],"type":"Point"}
}