{
  "type": "Feature",
  "properties": {
    "gn:admin1_code":"54.0",
    "gn:asciiname":"Trung Hoa",
    "gn:country_code":"VN",
    "gn:dem":39,
    "gn:feature_class":"P",
    "gn:feature_code":"PPL",
    "gn:name":"Trung H\u00f2a",
    "gn:population":0,
    "gn:timezone":"Asia/Ho_Chi_Minh",
    "iso:country":"VN",
    "name:und_x_variant":[
        "Trung H\u00f2a"
    ],
    "wof:name":"Trung Hoa",
    "wof:placetype":"locality"
},
  "geometry": {"coordinates":[109.15000000000001,12.61667],"type":"Point"}
}