{
  "type": "Feature",
  "properties": {
    "gn:admin1_code":"65.0",
    "gn:asciiname":"Xom Ay Cot",
    "gn:cc2":"VN",
    "gn:country_code":"VN",
    "gn:dem":0,
    "gn:feature_class":"P",
    "gn:feature_code":"PPL",
    "gn:name":"X\u00f3m Ay C\u1ed1t",
    "gn:population":0,
    "gn:timezone":"Asia/Ho_Chi_Minh",
    "iso:country":"VN",
    "name:und_x_variant":[
        "Ay C\u1ed1t",
        "Xom B\u01b0ng Ch\u00f4ng",
        "X\u00f3m Ay C\u1ed1t"
    ],
    "wof:name":"Xom Ay Cot",
    "wof:placetype":"locality"
},
  "geometry": {"coordinates":[106.03528,9.55028],"type":"Point"}
}