{
  "type": "Feature",
  "properties": {
    "gn:admin1_code":"37.0",
    "gn:asciiname":"Ap Muoi Lam",
    "gn:country_code":"VN",
    "gn:dem":2,
    "gn:feature_class":"P",
    "gn:feature_code":"PPL",
    "gn:name":"\u1ea4p M\u01b0\u1eddi L\u0103m",
    "gn:population":0,
    "gn:timezone":"Asia/Ho_Chi_Minh",
    "iso:country":"VN",
    "name:vie_x_preferred":[
        "\u1ea4p M\u01b0\u1eddi L\u0103m"
    ],
    "name:vie_x_variant":[
        "\u1ea4p 15"
    ],
    "wof:name":"Ap Muoi Lam",
    "wof:placetype":"locality"
},
  "geometry": {"coordinates":[106.11297,10.31975],"type":"Point"}
}