{
  "type": "Feature",
  "properties": {
    "gn:admin1_code":"70.0",
    "gn:asciiname":"Nam Gieu",
    "gn:country_code":"VN",
    "gn:dem":797,
    "gn:feature_class":"P",
    "gn:feature_code":"PPL",
    "gn:name":"N\u00e2m Gi\u00e8u",
    "gn:population":0,
    "gn:timezone":"Asia/Ho_Chi_Minh",
    "iso:country":"VN",
    "wof:name":"Nam Gieu",
    "wof:placetype":"locality"
},
  "geometry": {"coordinates":[104.40000000000001,21.76667],"type":"Point"}
}