{
  "type": "Feature",
  "properties": {
    "gn:admin1_code":"68.0",
    "gn:asciiname":"Ao Buc",
    "gn:country_code":"VN",
    "gn:dem":87,
    "gn:feature_class":"P",
    "gn:feature_code":"PPL",
    "gn:name":"Ao B\u00fac",
    "gn:population":0,
    "gn:timezone":"Asia/Ho_Chi_Minh",
    "iso:country":"VN",
    "name:vie_x_preferred":[
        "Ao B\u00fac"
    ],
    "wof:name":"Ao Buc",
    "wof:placetype":"locality"
},
  "geometry": {"coordinates":[105.43434999999999,21.80855],"type":"Point"}
}