{
  "type": "Feature",
  "properties": {
    "gn:admin1_code":"83.0",
    "gn:asciiname":"Do Giong",
    "gn:country_code":"VN",
    "gn:dem":28,
    "gn:feature_class":"P",
    "gn:feature_code":"PPL",
    "gn:name":"\u0110o Gi\u00f4ng",
    "gn:population":0,
    "gn:timezone":"Asia/Ho_Chi_Minh",
    "iso:country":"VN",
    "name:vie_x_preferred":[
        "\u0110o Gi\u00f4ng"
    ],
    "wof:name":"Do Giong",
    "wof:placetype":"locality"
},
  "geometry": {"coordinates":[105.31076000000002,21.45193],"type":"Point"}
}