{
  "type": "Feature",
  "properties": {
    "gn:admin1_code":"52.0",
    "gn:asciiname":"Son Trieu",
    "gn:country_code":"VN",
    "gn:dem":5,
    "gn:feature_class":"P",
    "gn:feature_code":"PPL",
    "gn:name":"S\u01a1n Tri\u1ec1u",
    "gn:population":0,
    "gn:timezone":"Asia/Ho_Chi_Minh",
    "iso:country":"VN",
    "wof:name":"Son Trieu",
    "wof:placetype":"locality"
},
  "geometry": {"coordinates":[106.26667,18.11667000000001],"type":"Point"}
}