{
  "type": "Feature",
  "properties": {
    "gn:admin1_code":"67.0",
    "gn:asciiname":"No Re",
    "gn:country_code":"VN",
    "gn:dem":5,
    "gn:feature_class":"P",
    "gn:feature_code":"PPL",
    "gn:name":"N\u00f4 R\u00e8",
    "gn:population":0,
    "gn:timezone":"Asia/Ho_Chi_Minh",
    "iso:country":"VN",
    "name:vie_x_preferred":[
        "N\u00f4 R\u00e8"
    ],
    "wof:name":"No Re",
    "wof:placetype":"locality"
},
  "geometry": {"coordinates":[106.38132,9.72308],"type":"Point"}
}