{
  "type": "Feature",
  "properties": {
    "gn:admin1_code":"68.0",
    "gn:asciiname":"Xa Noi",
    "gn:country_code":"VN",
    "gn:dem":51,
    "gn:feature_class":"P",
    "gn:feature_code":"PPL",
    "gn:name":"X\u00e1 N\u1ed9i",
    "gn:population":0,
    "gn:timezone":"Asia/Ho_Chi_Minh",
    "iso:country":"VN",
    "name:vie_x_preferred":[
        "X\u00e1 N\u1ed9i"
    ],
    "wof:name":"Xa Noi",
    "wof:placetype":"locality"
},
  "geometry": {"coordinates":[105.24335000000001,21.71711],"type":"Point"}
}