{
  "type": "Feature",
  "properties": {
    "gn:admin1_code":"83.0",
    "gn:asciiname":"Xom Thi",
    "gn:country_code":"VN",
    "gn:dem":65,
    "gn:feature_class":"P",
    "gn:feature_code":"PPL",
    "gn:name":"X\u00f3m Th\u1ecb",
    "gn:population":0,
    "gn:timezone":"Asia/Ho_Chi_Minh",
    "iso:country":"VN",
    "name:vie_x_preferred":[
        "X\u00f3m Th\u1ecb"
    ],
    "wof:name":"Xom Thi",
    "wof:placetype":"locality"
},
  "geometry": {"coordinates":[105.01291999999999,21.38725],"type":"Point"}
}