{
  "type": "Feature",
  "properties": {
    "gn:admin1_code":"6.0",
    "gn:asciiname":"Ap Phu Hoa",
    "gn:cc2":"VN",
    "gn:country_code":"VN",
    "gn:dem":4,
    "gn:feature_class":"P",
    "gn:feature_code":"PPL",
    "gn:name":"\u1ea4p Ph\u00fa H\u00f2a",
    "gn:population":0,
    "gn:timezone":"Asia/Ho_Chi_Minh",
    "iso:country":"VN",
    "name:und_x_variant":[
        "Binh Tien",
        "\u1ea4p Ph\u00fa H\u00f2a"
    ],
    "wof:name":"Ap Phu Hoa",
    "wof:placetype":"locality"
},
  "geometry": {"coordinates":[105.76667,10.25],"type":"Point"}
}