{
  "type": "Feature",
  "properties": {
    "gn:admin1_code":"60.0",
    "gn:asciiname":"Thon My Nghiep",
    "gn:country_code":"VN",
    "gn:dem":12,
    "gn:feature_class":"P",
    "gn:feature_code":"PPL",
    "gn:name":"Th\u00f4n M\u1ef9 Nghi\u1ec7p",
    "gn:population":0,
    "gn:timezone":"Asia/Ho_Chi_Minh",
    "iso:country":"VN",
    "name:und_x_variant":[
        "My Nghiep",
        "Th\u00f4n M\u1ef9 Nghi\u1ec7p"
    ],
    "wof:name":"Thon My Nghiep",
    "wof:placetype":"locality"
},
  "geometry": {"coordinates":[108.95,11.51667],"type":"Point"}
}