{
  "type": "Feature",
  "properties": {
    "gn:admin1_code":"58.0",
    "gn:asciiname":"Quynh Lam",
    "gn:country_code":"VN",
    "gn:dem":19,
    "gn:feature_class":"P",
    "gn:feature_code":"PPL",
    "gn:name":"Qu\u1ef3nh Lam",
    "gn:population":0,
    "gn:timezone":"Asia/Ho_Chi_Minh",
    "iso:country":"VN",
    "name:vie_x_preferred":[
        "Qu\u1ef3nh Lam"
    ],
    "wof:name":"Quynh Lam",
    "wof:placetype":"locality"
},
  "geometry": {"coordinates":[105.56682000000001,19.17194],"type":"Point"}
}