{
  "type": "Feature",
  "properties": {
    "gn:admin1_code":"90.0",
    "gn:asciiname":"Ban Sang Lung San",
    "gn:country_code":"VN",
    "gn:dem":1175,
    "gn:feature_class":"P",
    "gn:feature_code":"PPL",
    "gn:name":"B\u1ea3n S\u1ea3ng L\u00f9ng S\u00e1n",
    "gn:population":0,
    "gn:timezone":"Asia/Ho_Chi_Minh",
    "iso:country":"VN",
    "name:vie_x_preferred":[
        "B\u1ea3n S\u1ea3ng L\u00f9ng S\u00e1n"
    ],
    "wof:name":"Ban Sang Lung San",
    "wof:placetype":"locality"
},
  "geometry": {"coordinates":[104.37291,22.64418],"type":"Point"}
}