{
  "type": "Feature",
  "properties": {
    "gn:admin1_code":"88.0",
    "gn:asciiname":"Thon Nam",
    "gn:country_code":"VN",
    "gn:dem":466,
    "gn:feature_class":"P",
    "gn:feature_code":"PPL",
    "gn:name":"Th\u00f4n N\u0103m",
    "gn:population":0,
    "gn:timezone":"Asia/Ho_Chi_Minh",
    "iso:country":"VN",
    "name:vie_x_preferred":[
        "Th\u00f4n N\u0103m"
    ],
    "name:vie_x_variant":[
        "Th\u00f4n 5"
    ],
    "wof:name":"Thon Nam",
    "wof:placetype":"locality"
},
  "geometry": {"coordinates":[108.53868,12.74181],"type":"Point"}
}