{
  "type": "Feature",
  "properties": {
    "iso:country":"VN",
    "name:und_x_variant":[
        "Lang D\u01b0\u01a1ng"
    ],
    "name:vie_x_preferred":[
        "H\u1ea1 H\u00f2a"
    ],
    "qs:gn_country":"VN",
    "qs:gn_fcode":"PPL",
    "qs:gn_pop":0,
    "qs:name":"\u00d0\u1ed3ng Chu\u1ebf",
    "qs:name_adm0":"Vietnam",
    "qs:name_adm1":"Bac Ninh",
    "qs:photos":33,
    "qs:photos_1k":7,
    "qs:photos_9k":1,
    "qs:photos_9r":2,
    "qs:photos_all":33,
    "qs:photos_sr":2,
    "qs:placetype":"Town",
    "qs:pop_sr":"0",
    "qs:woe_adm0":23424984,
    "wof:name":"\u00d0\u1ed3ng Chu\u1ebf",
    "wof:placetype":"locality"
},
  "geometry": {"coordinates":[106.15000000000001,21.18333],"type":"Point"}
}