{
  "type": "Feature",
  "properties": {
    "gn:admin1_code":"32.0",
    "gn:asciiname":"Ban Lum Cung",
    "gn:country_code":"VN",
    "gn:dem":391,
    "gn:feature_class":"P",
    "gn:feature_code":"PPL",
    "gn:name":"B\u1ea3n L\u1eebm C\u00f9ng",
    "gn:population":0,
    "gn:timezone":"Asia/Ho_Chi_Minh",
    "iso:country":"VN",
    "wof:name":"Ban Lum Cung",
    "wof:placetype":"locality"
},
  "geometry": {"coordinates":[104.18333,21.35],"type":"Point"}
}