{
  "type": "Feature",
  "properties": {
    "gn:admin1_code":"87.0",
    "gn:asciiname":"Binh Thuong",
    "gn:country_code":"VN",
    "gn:dem":2,
    "gn:feature_class":"P",
    "gn:feature_code":"PPL",
    "gn:name":"B\u00ecnh Th\u01b0\u1eddng",
    "gn:population":0,
    "gn:timezone":"Asia/Ho_Chi_Minh",
    "iso:country":"VN",
    "name:und_x_variant":[
        "\u1ea4p B\u00ecnh Th\u01b0\u01a1ng"
    ],
    "name:vie_x_preferred":[
        "B\u00ecnh Th\u01b0\u1eddng"
    ],
    "wof:name":"Binh Thuong",
    "wof:placetype":"locality"
},
  "geometry": {"coordinates":[105.71375999999999,10.01199],"type":"Point"}
}