{
  "type": "Feature",
  "properties": {
    "gn:admin1_code":"88.0",
    "gn:asciiname":"Khoi Ba",
    "gn:country_code":"VN",
    "gn:dem":410,
    "gn:feature_class":"P",
    "gn:feature_code":"PPL",
    "gn:name":"Kh\u1ed1i Ba",
    "gn:population":0,
    "gn:timezone":"Asia/Ho_Chi_Minh",
    "iso:country":"VN",
    "name:vie_x_preferred":[
        "Kh\u1ed1i Ba"
    ],
    "name:vie_x_variant":[
        "Kh\u1ed1i 3"
    ],
    "wof:name":"Khoi Ba",
    "wof:placetype":"locality"
},
  "geometry": {"coordinates":[108.74612999999999,12.75399],"type":"Point"}
}