{
  "type": "Feature",
  "properties": {
    "gn:admin1_code":"67.0",
    "gn:asciiname":"Giong Truong",
    "gn:cc2":"VN",
    "gn:country_code":"VN",
    "gn:dem":0,
    "gn:feature_class":"P",
    "gn:feature_code":"PPL",
    "gn:name":"Gi\u1ed3ng Tr\u01b0\u01a1ng",
    "gn:population":0,
    "gn:timezone":"Asia/Ho_Chi_Minh",
    "iso:country":"VN",
    "name:und_x_variant":[
        "Tr\u01b0\u01a1ng",
        "Gi\u1ed3ng Tr\u01b0\u01a1ng"
    ],
    "wof:name":"Giong Truong",
    "wof:placetype":"locality"
},
  "geometry": {"coordinates":[106.39139,9.89583],"type":"Point"}
}