{
  "type": "Feature",
  "properties": {
    "gn:admin1_code":"70.0",
    "gn:asciiname":"Tien Mich",
    "gn:country_code":"VN",
    "gn:dem":93,
    "gn:feature_class":"P",
    "gn:feature_code":"PPL",
    "gn:name":"Ti\u1ebfn M\u1ecbch",
    "gn:population":0,
    "gn:timezone":"Asia/Ho_Chi_Minh",
    "iso:country":"VN",
    "name:vie_x_preferred":[
        "Ti\u1ebfn M\u1ecbch"
    ],
    "wof:name":"Tien Mich",
    "wof:placetype":"locality"
},
  "geometry": {"coordinates":[104.76913,21.95723],"type":"Point"}
}