{
  "type": "Feature",
  "properties": {
    "gn:admin1_code":"68.0",
    "gn:asciiname":"Yen Linh",
    "gn:country_code":"VN",
    "gn:dem":42,
    "gn:feature_class":"P",
    "gn:feature_code":"PPL",
    "gn:name":"Y\u00ean L\u0129nh",
    "gn:population":0,
    "gn:timezone":"Asia/Ho_Chi_Minh",
    "iso:country":"VN",
    "name:vie_x_preferred":[
        "Y\u00ean L\u0129nh"
    ],
    "wof:name":"Yen Linh",
    "wof:placetype":"locality"
},
  "geometry": {"coordinates":[105.24392,21.871],"type":"Point"}
}