{
  "type": "Feature",
  "properties": {
    "gn:admin1_code":"37.0",
    "gn:asciiname":"Long Thuan A",
    "gn:country_code":"VN",
    "gn:dem":6,
    "gn:feature_class":"P",
    "gn:feature_code":"PPL",
    "gn:name":"Long Thu\u1eadn A",
    "gn:population":0,
    "gn:timezone":"Asia/Ho_Chi_Minh",
    "iso:country":"VN",
    "name:vie_x_preferred":[
        "Long Thu\u1eadn A"
    ],
    "wof:name":"Long Thuan A",
    "wof:placetype":"locality"
},
  "geometry": {"coordinates":[106.27079999999999,10.3645],"type":"Point"}
}