{
  "type": "Feature",
  "properties": {
    "gn:admin1_code":"70.0",
    "gn:asciiname":"Cay Da",
    "gn:country_code":"VN",
    "gn:dem":58,
    "gn:feature_class":"P",
    "gn:feature_code":"PPL",
    "gn:name":"C\u00e2y \u0110a",
    "gn:population":0,
    "gn:timezone":"Asia/Ho_Chi_Minh",
    "iso:country":"VN",
    "name:vie_x_preferred":[
        "C\u00e2y \u0110a"
    ],
    "wof:name":"Cay Da",
    "wof:placetype":"locality"
},
  "geometry": {"coordinates":[104.63985,21.86293],"type":"Point"}
}