{
  "type": "Feature",
  "properties": {
    "gn:admin1_code":"65.0",
    "gn:asciiname":"Sa Bau",
    "gn:country_code":"VN",
    "gn:dem":3,
    "gn:feature_class":"P",
    "gn:feature_code":"PPL",
    "gn:name":"Sa B\u00e2u",
    "gn:population":0,
    "gn:timezone":"Asia/Ho_Chi_Minh",
    "iso:country":"VN",
    "name:vie_x_preferred":[
        "Sa B\u00e2u"
    ],
    "wof:name":"Sa Bau",
    "wof:placetype":"locality"
},
  "geometry": {"coordinates":[105.91486,9.68298],"type":"Point"}
}