{
  "type": "Feature",
  "properties": {
    "gn:admin1_code":"85.0",
    "gn:asciiname":"Quan Trang",
    "gn:country_code":"VN",
    "gn:dem":16,
    "gn:feature_class":"P",
    "gn:feature_code":"PPL",
    "gn:name":"Quan Tr\u00e0ng",
    "gn:population":0,
    "gn:timezone":"Asia/Ho_Chi_Minh",
    "iso:country":"VN",
    "name:und_x_variant":[
        "Thai",
        "Quan Tr\u00e0ng"
    ],
    "wof:name":"Quan Trang",
    "wof:placetype":"locality"
},
  "geometry": {"coordinates":[105.91667,21.48333],"type":"Point"}
}