{
  "type": "Feature",
  "properties": {
    "gn:admin1_code":"84.0",
    "gn:asciiname":"Quy Thuong",
    "gn:country_code":"VN",
    "gn:dem":9,
    "gn:feature_class":"P",
    "gn:feature_code":"PPL",
    "gn:name":"Quy Th\u01b0\u1ee3ng",
    "gn:population":0,
    "gn:timezone":"Asia/Ho_Chi_Minh",
    "iso:country":"VN",
    "wof:name":"Quy Thuong",
    "wof:placetype":"locality"
},
  "geometry": {"coordinates":[108.53333000000001,15.61667],"type":"Point"}
}