{
  "type": "Feature",
  "properties": {
    "gn:admin1_code":"49.0",
    "gn:asciiname":"Plei Holim",
    "gn:country_code":"VN",
    "gn:dem":691,
    "gn:feature_class":"P",
    "gn:feature_code":"PPL",
    "gn:name":"Plei H\u01a1lim",
    "gn:population":0,
    "gn:timezone":"Asia/Ho_Chi_Minh",
    "iso:country":"VN",
    "wof:name":"Plei Holim",
    "wof:placetype":"locality"
},
  "geometry": {"coordinates":[108.26667,13.93333],"type":"Point"}
}