{
  "type": "Feature",
  "properties": {
    "gn:admin1_code":"34.0",
    "gn:asciiname":"But Son",
    "gn:country_code":"VN",
    "gn:dem":8,
    "gn:feature_class":"P",
    "gn:feature_code":"PPLA2",
    "gn:name":"B\u00fat S\u01a1n",
    "gn:population":0,
    "gn:timezone":"Asia/Ho_Chi_Minh",
    "iso:country":"VN",
    "name:vie_x_preferred":[
        "B\u00fat S\u01a1n"
    ],
    "wof:name":"But Son",
    "wof:placetype":"locality"
},
  "geometry": {"coordinates":[105.85482,19.85797],"type":"Point"}
}