{
  "type": "Feature",
  "properties": {
    "gn:admin1_code":"74.0",
    "gn:asciiname":"Khuong Tu",
    "gn:country_code":"VN",
    "gn:dem":9,
    "gn:feature_class":"P",
    "gn:feature_code":"PPL",
    "gn:name":"Kh\u01b0\u01a1ng T\u1ef1",
    "gn:population":0,
    "gn:timezone":"Asia/Ho_Chi_Minh",
    "iso:country":"VN",
    "name:vie_x_preferred":[
        "Kh\u01b0\u01a1ng T\u1ef1"
    ],
    "wof:name":"Khuong Tu",
    "wof:placetype":"locality"
},
  "geometry": {"coordinates":[106.04268,21.03774],"type":"Point"}
}