{
  "type": "Feature",
  "properties": {
    "gn:admin1_code":"61.0",
    "gn:asciiname":"Buon Trinh",
    "gn:country_code":"VN",
    "gn:dem":401,
    "gn:feature_class":"P",
    "gn:feature_code":"PPL",
    "gn:name":"Bu\u00f4n Trinh",
    "gn:population":0,
    "gn:timezone":"Asia/Ho_Chi_Minh",
    "iso:country":"VN",
    "name:vie_x_preferred":[
        "Bu\u00f4n Trinh"
    ],
    "wof:name":"Buon Trinh",
    "wof:placetype":"locality"
},
  "geometry": {"coordinates":[108.81164,12.96722],"type":"Point"}
}