{
  "type": "Feature",
  "properties": {
    "gn:admin1_code":"3.0",
    "gn:asciiname":"An Binh",
    "gn:country_code":"VN",
    "gn:dem":1,
    "gn:feature_class":"P",
    "gn:feature_code":"PPL",
    "gn:name":"An B\u00ecnh",
    "gn:population":0,
    "gn:timezone":"Asia/Ho_Chi_Minh",
    "iso:country":"VN",
    "name:vie_x_preferred":[
        "An B\u00ecnh"
    ],
    "wof:name":"An Binh",
    "wof:placetype":"locality"
},
  "geometry": {"coordinates":[106.62615,9.99799],"type":"Point"}
}