{
  "type": "Feature",
  "properties": {
    "gn:admin1_code":"49.0",
    "gn:asciiname":"Tro Dong",
    "gn:country_code":"VN",
    "gn:dem":439,
    "gn:feature_class":"P",
    "gn:feature_code":"PPL",
    "gn:name":"Tro \u0110\u1ecfng",
    "gn:population":0,
    "gn:timezone":"Asia/Ho_Chi_Minh",
    "iso:country":"VN",
    "name:vie_x_preferred":[
        "Tro \u0110\u1ecfng"
    ],
    "wof:name":"Tro Dong",
    "wof:placetype":"locality"
},
  "geometry": {"coordinates":[108.56337000000001,13.94118],"type":"Point"}
}