{
  "type": "Feature",
  "properties": {
    "gn:admin1_code":"47.0",
    "gn:asciiname":"Hiep An",
    "gn:country_code":"VN",
    "gn:dem":10,
    "gn:feature_class":"P",
    "gn:feature_code":"PPL",
    "gn:name":"Hi\u1ec7p An",
    "gn:population":0,
    "gn:timezone":"Asia/Ho_Chi_Minh",
    "iso:country":"VN",
    "name:vie_x_preferred":[
        "Hi\u1ec7p An"
    ],
    "wof:name":"Hiep An",
    "wof:placetype":"locality"
},
  "geometry": {"coordinates":[107.83499999999999,10.7132],"type":"Point"}
}