{
  "type": "Feature",
  "properties": {
    "gn:admin1_code":"68.0",
    "gn:asciiname":"Khe Ngoai",
    "gn:country_code":"VN",
    "gn:dem":59,
    "gn:feature_class":"P",
    "gn:feature_code":"PPL",
    "gn:name":"Khe Ngo\u00e0i",
    "gn:population":0,
    "gn:timezone":"Asia/Ho_Chi_Minh",
    "iso:country":"VN",
    "name:vie_x_preferred":[
        "Khe Ngo\u00e0i"
    ],
    "wof:name":"Khe Ngoai",
    "wof:placetype":"locality"
},
  "geometry": {"coordinates":[105.14592,21.74051],"type":"Point"}
}