{
  "type": "Feature",
  "properties": {
    "gn:admin1_code":"92.0",
    "gn:asciiname":"Lo Quan Chai",
    "gn:country_code":"VN",
    "gn:dem":1000,
    "gn:feature_class":"P",
    "gn:feature_code":"PPL",
    "gn:name":"L\u00f2 Quan Ch\u1ea3i",
    "gn:population":0,
    "gn:timezone":"Asia/Ho_Chi_Minh",
    "iso:country":"VN",
    "wof:name":"Lo Quan Chai",
    "wof:placetype":"locality"
},
  "geometry": {"coordinates":[102.31667,22.46667],"type":"Point"}
}