{
  "type": "Feature",
  "properties": {
    "gn:admin1_code":"34.0",
    "gn:asciiname":"La Han",
    "gn:country_code":"VN",
    "gn:dem":73,
    "gn:feature_class":"P",
    "gn:feature_code":"PPL",
    "gn:name":"La H\u00e1n",
    "gn:population":0,
    "gn:timezone":"Asia/Ho_Chi_Minh",
    "iso:country":"VN",
    "wof:name":"La Han",
    "wof:placetype":"locality"
},
  "geometry": {"coordinates":[105.21666999999999,20.35],"type":"Point"}
}