{
  "type": "Feature",
  "properties": {
    "gn:admin1_code":"90.0",
    "gn:asciiname":"In Tchang",
    "gn:country_code":"VN",
    "gn:dem":1017,
    "gn:feature_class":"P",
    "gn:feature_code":"PPL",
    "gn:name":"In Tchang",
    "gn:population":0,
    "gn:timezone":"Asia/Ho_Chi_Minh",
    "iso:country":"VN",
    "name:und_x_variant":[
        "Tn Tchang",
        "In Tchong",
        "In Tchang"
    ],
    "wof:name":"In Tchang",
    "wof:placetype":"locality"
},
  "geometry": {"coordinates":[103.66667,22.58333],"type":"Point"}
}