{
  "type": "Feature",
  "properties": {
    "gn:admin1_code":"30.0",
    "gn:asciiname":"Duong Huy",
    "gn:country_code":"VN",
    "gn:dem":159,
    "gn:feature_class":"P",
    "gn:feature_code":"PPL",
    "gn:name":"D\u01b0\u01a1ng Huy",
    "gn:population":0,
    "gn:timezone":"Asia/Ho_Chi_Minh",
    "iso:country":"VN",
    "wof:name":"Duong Huy",
    "wof:placetype":"locality"
},
  "geometry": {"coordinates":[107.25,21.08333],"type":"Point"}
}