{
  "type": "Feature",
  "properties": {
    "gn:admin1_code":"89.0",
    "gn:asciiname":"Ban Nong A",
    "gn:country_code":"VN",
    "gn:dem":563,
    "gn:feature_class":"P",
    "gn:feature_code":"PPL",
    "gn:name":"B\u1ea3n Nong \u00c1",
    "gn:population":0,
    "gn:timezone":"Asia/Ho_Chi_Minh",
    "iso:country":"VN",
    "name:vie_x_preferred":[
        "B\u1ea3n Nong \u00c1"
    ],
    "wof:name":"Ban Nong A",
    "wof:placetype":"locality"
},
  "geometry": {"coordinates":[103.69686,22.21045],"type":"Point"}
}