{
  "type": "Feature",
  "properties": {
    "gn:admin1_code":"39.0",
    "gn:asciiname":"Na Phuong",
    "gn:country_code":"VN",
    "gn:dem":291,
    "gn:feature_class":"P",
    "gn:feature_code":"PPL",
    "gn:name":"N\u00e0 Ph\u01b0\u1ee3ng",
    "gn:population":0,
    "gn:timezone":"Asia/Ho_Chi_Minh",
    "iso:country":"VN",
    "name:vie_x_preferred":[
        "N\u00e0 Ph\u01b0\u1ee3ng"
    ],
    "wof:name":"Na Phuong",
    "wof:placetype":"locality"
},
  "geometry": {"coordinates":[106.54039,22.30567000000001],"type":"Point"}
}