{
  "type": "Feature",
  "properties": {
    "gn:admin1_code":"20.0",
    "gn:asciiname":"Xa Tu Duon",
    "gn:cc2":"VN",
    "gn:country_code":"VN",
    "gn:dem":13,
    "gn:feature_class":"P",
    "gn:feature_code":"PPL",
    "gn:name":"X\u00e1 T\u01b0 D\u01b0\u01a1n",
    "gn:population":0,
    "gn:timezone":"Asia/Ho_Chi_Minh",
    "iso:country":"VN",
    "name:und_x_variant":[
        "Tu Duon",
        "Xom Tu Duon",
        "X\u00e1 T\u01b0 D\u01b0\u01a1n"
    ],
    "wof:name":"Xa Tu Duon",
    "wof:placetype":"locality"
},
  "geometry": {"coordinates":[106.45,11.08333],"type":"Point"}
}