{
  "type": "Feature",
  "properties": {
    "gn:admin1_code":"79.0",
    "gn:asciiname":"Lac Thien",
    "gn:country_code":"VN",
    "gn:dem":4,
    "gn:feature_class":"P",
    "gn:feature_code":"PPL",
    "gn:name":"L\u1ea1c Thi\u1ec7n",
    "gn:population":0,
    "gn:timezone":"Asia/Ho_Chi_Minh",
    "iso:country":"VN",
    "name:vie_x_preferred":[
        "L\u1ea1c Thi\u1ec7n"
    ],
    "wof:name":"Lac Thien",
    "wof:placetype":"locality"
},
  "geometry": {"coordinates":[106.49148999999998,20.87617],"type":"Point"}
}