{
  "type": "Feature",
  "properties": {
    "gn:admin1_code":"90.0",
    "gn:asciiname":"Lao Pan Tchai",
    "gn:country_code":"VN",
    "gn:dem":873,
    "gn:feature_class":"P",
    "gn:feature_code":"PPL",
    "gn:name":"Lao Pan Tchai",
    "gn:population":0,
    "gn:timezone":"Asia/Ho_Chi_Minh",
    "iso:country":"VN",
    "wof:name":"Lao Pan Tchai",
    "wof:placetype":"locality"
},
  "geometry": {"coordinates":[103.81667,22.43333],"type":"Point"}
}