{
  "type": "Feature",
  "properties": {
    "gn:admin1_code":"34.0",
    "gn:asciiname":"Lang Chu",
    "gn:country_code":"VN",
    "gn:dem":150,
    "gn:feature_class":"P",
    "gn:feature_code":"PPL",
    "gn:name":"L\u00e0ng Chu",
    "gn:population":0,
    "gn:timezone":"Asia/Ho_Chi_Minh",
    "iso:country":"VN",
    "name:vie_x_preferred":[
        "L\u00e0ng Chu"
    ],
    "wof:name":"Lang Chu",
    "wof:placetype":"locality"
},
  "geometry": {"coordinates":[105.17057,20.42193],"type":"Point"}
}