{
  "type": "Feature",
  "properties": {
    "gn:admin1_code":"53.0",
    "gn:asciiname":"Sao Ha",
    "gn:country_code":"VN",
    "gn:dem":96,
    "gn:feature_class":"P",
    "gn:feature_code":"PPL",
    "gn:name":"S\u00e0o H\u1ea1",
    "gn:population":0,
    "gn:timezone":"Asia/Ho_Chi_Minh",
    "iso:country":"VN",
    "name:vie_x_preferred":[
        "S\u00e0o H\u1ea1"
    ],
    "wof:name":"Sao Ha",
    "wof:placetype":"locality"
},
  "geometry": {"coordinates":[105.54832,20.5235],"type":"Point"}
}