{
  "type": "Feature",
  "properties": {
    "gn:admin1_code":"83.0",
    "gn:asciiname":"Xom Khe",
    "gn:country_code":"VN",
    "gn:dem":51,
    "gn:feature_class":"P",
    "gn:feature_code":"PPL",
    "gn:name":"X\u00f3m Kh\u00ea",
    "gn:population":0,
    "gn:timezone":"Asia/Ho_Chi_Minh",
    "iso:country":"VN",
    "name:vie_x_preferred":[
        "X\u00f3m Kh\u00ea"
    ],
    "wof:name":"Xom Khe",
    "wof:placetype":"locality"
},
  "geometry": {"coordinates":[105.26387,21.4467],"type":"Point"}
}