{
  "type": "Feature",
  "properties": {
    "gn:admin1_code":"90.0",
    "gn:asciiname":"Ban Gay",
    "gn:country_code":"VN",
    "gn:dem":774,
    "gn:feature_class":"P",
    "gn:feature_code":"PPL",
    "gn:name":"B\u1ea3n Gay",
    "gn:population":0,
    "gn:timezone":"Asia/Ho_Chi_Minh",
    "iso:country":"VN",
    "wof:name":"Ban Gay",
    "wof:placetype":"locality"
},
  "geometry": {"coordinates":[104.40000000000001,22.38333],"type":"Point"}
}