{
  "type": "Feature",
  "properties": {
    "gn:admin1_code":"5.0",
    "gn:asciiname":"Coc Phuong",
    "gn:country_code":"VN",
    "gn:dem":216,
    "gn:feature_class":"P",
    "gn:feature_code":"PPL",
    "gn:name":"C\u1ed1c Ph\u01b0\u1eddng",
    "gn:population":0,
    "gn:timezone":"Asia/Ho_Chi_Minh",
    "iso:country":"VN",
    "wof:name":"Coc Phuong",
    "wof:placetype":"locality"
},
  "geometry": {"coordinates":[106.56667,22.53333],"type":"Point"}
}