{
  "type": "Feature",
  "properties": {
    "gn:admin1_code":"81.0",
    "gn:asciiname":"Hao Xuyen",
    "gn:country_code":"VN",
    "gn:dem":6,
    "gn:feature_class":"P",
    "gn:feature_code":"PPL",
    "gn:name":"H\u00e0o Xuy\u00ean",
    "gn:population":0,
    "gn:timezone":"Asia/Ho_Chi_Minh",
    "iso:country":"VN",
    "name:vie_x_preferred":[
        "H\u00e0o Xuy\u00ean"
    ],
    "wof:name":"Hao Xuyen",
    "wof:placetype":"locality"
},
  "geometry": {"coordinates":[106.04432,20.89551],"type":"Point"}
}