{
  "type": "Feature",
  "properties": {
    "gn:admin1_code":"52.0",
    "gn:asciiname":"Duc Bui",
    "gn:country_code":"VN",
    "gn:dem":16,
    "gn:feature_class":"P",
    "gn:feature_code":"PPL",
    "gn:name":"\u0110\u1ee9c B\u00f9i",
    "gn:population":0,
    "gn:timezone":"Asia/Ho_Chi_Minh",
    "iso:country":"VN",
    "name:vie_x_preferred":[
        "\u0110\u1ee9c B\u00f9i"
    ],
    "wof:name":"Duc Bui",
    "wof:placetype":"locality"
},
  "geometry": {"coordinates":[105.47427999999999,18.40302],"type":"Point"}
}