{
  "type": "Feature",
  "properties": {
    "gn:admin1_code":"61.0",
    "gn:asciiname":"Co Me",
    "gn:country_code":"VN",
    "gn:dem":118,
    "gn:feature_class":"P",
    "gn:feature_code":"PPL",
    "gn:name":"Co Me",
    "gn:population":0,
    "gn:timezone":"Asia/Ho_Chi_Minh",
    "iso:country":"VN",
    "wof:name":"Co Me",
    "wof:placetype":"locality"
},
  "geometry": {"coordinates":[104.8463,20.61304],"type":"Point"}
}