{
  "type": "Feature",
  "properties": {
    "gn:admin1_code":"65.0",
    "gn:asciiname":"Phuoc Thoi",
    "gn:country_code":"VN",
    "gn:dem":6,
    "gn:feature_class":"P",
    "gn:feature_code":"PPL",
    "gn:name":"Ph\u01b0\u1edbc Th\u1edbi",
    "gn:population":0,
    "gn:timezone":"Asia/Ho_Chi_Minh",
    "iso:country":"VN",
    "name:vie_x_preferred":[
        "Ph\u01b0\u1edbc Th\u1edbi"
    ],
    "wof:name":"Phuoc Thoi",
    "wof:placetype":"locality"
},
  "geometry": {"coordinates":[105.69240000000001,9.61133],"type":"Point"}
}