{
  "type": "Feature",
  "properties": {
    "gn:admin1_code":"32.0",
    "gn:asciiname":"Ban Da Do",
    "gn:country_code":"VN",
    "gn:dem":191,
    "gn:feature_class":"P",
    "gn:feature_code":"PPL",
    "gn:name":"B\u1ea3n \u0110\u00e1 \u0110\u1ecf",
    "gn:population":0,
    "gn:timezone":"Asia/Ho_Chi_Minh",
    "iso:country":"VN",
    "name:und_x_variant":[
        "B\u1ea3n D\u00e1 D\u1ed5"
    ],
    "name:vie_x_preferred":[
        "B\u1ea3n \u0110\u00e1 \u0110\u1ecf"
    ],
    "wof:name":"Ban Da Do",
    "wof:placetype":"locality"
},
  "geometry": {"coordinates":[104.56461,21.09525],"type":"Point"}
}