{
  "type": "Feature",
  "properties": {
    "gn:admin1_code":"69.0",
    "gn:asciiname":"Phuoc Yen",
    "gn:country_code":"VN",
    "gn:dem":1,
    "gn:feature_class":"P",
    "gn:feature_code":"PPL",
    "gn:name":"Ph\u01b0\u1edbc Y\u00ean",
    "gn:population":0,
    "gn:timezone":"Asia/Ho_Chi_Minh",
    "iso:country":"VN",
    "name:vie_x_preferred":[
        "Ph\u01b0\u1edbc Y\u00ean"
    ],
    "wof:name":"Phuoc Yen",
    "wof:placetype":"locality"
},
  "geometry": {"coordinates":[105.92379,10.16918],"type":"Point"}
}