{
  "type": "Feature",
  "properties": {
    "gn:admin1_code":"33.0",
    "gn:asciiname":"Go Dau",
    "gn:country_code":"VN",
    "gn:dem":9,
    "gn:feature_class":"P",
    "gn:feature_code":"PPLA2",
    "gn:name":"G\u00f2 D\u1ea7u",
    "gn:population":0,
    "gn:timezone":"Asia/Ho_Chi_Minh",
    "iso:country":"VN",
    "name:vie_x_preferred":[
        "G\u00f2 D\u1ea7u"
    ],
    "wof:name":"Go Dau",
    "wof:placetype":"locality"
},
  "geometry": {"coordinates":[106.26345999999999,11.0885],"type":"Point"}
}