{
  "type": "Feature",
  "properties": {
    "gn:admin1_code":"72.0",
    "gn:asciiname":"Coc Sau",
    "gn:country_code":"VN",
    "gn:dem":284,
    "gn:feature_class":"P",
    "gn:feature_code":"PPL",
    "gn:name":"C\u00f3c S\u1eadu",
    "gn:population":0,
    "gn:timezone":"Asia/Ho_Chi_Minh",
    "iso:country":"VN",
    "wof:name":"Coc Sau",
    "wof:placetype":"locality"
},
  "geometry": {"coordinates":[105.83131000000002,22.34301],"type":"Point"}
}