{
  "type": "Feature",
  "properties": {
    "gn:admin1_code":"58.0",
    "gn:asciiname":"Xom Hai Muoi",
    "gn:country_code":"VN",
    "gn:dem":18,
    "gn:feature_class":"P",
    "gn:feature_code":"PPL",
    "gn:name":"X\u00f3m Hai M\u01b0\u01a1i",
    "gn:population":0,
    "gn:timezone":"Asia/Ho_Chi_Minh",
    "iso:country":"VN",
    "name:vie_x_preferred":[
        "X\u00f3m Hai M\u01b0\u01a1i"
    ],
    "name:vie_x_variant":[
        "X\u00f3m 20"
    ],
    "wof:name":"Xom Hai Muoi",
    "wof:placetype":"locality"
},
  "geometry": {"coordinates":[105.52114,18.80337],"type":"Point"}
}