{
  "type": "Feature",
  "properties": {
    "gn:admin1_code":"76.0",
    "gn:asciiname":"Ap Phuoc Thien",
    "gn:country_code":"VN",
    "gn:dem":154,
    "gn:feature_class":"P",
    "gn:feature_code":"PPL",
    "gn:name":"\u1ea4p Ph\u01b0\u1edbc Thi\u1ec7n",
    "gn:population":0,
    "gn:timezone":"Asia/Ho_Chi_Minh",
    "iso:country":"VN",
    "wof:name":"Ap Phuoc Thien",
    "wof:placetype":"locality"
},
  "geometry": {"coordinates":[106.83333,12.03333],"type":"Point"}
}