{
  "type": "Feature",
  "properties": {
    "gn:admin1_code":"80.0",
    "gn:asciiname":"Lanh Tri",
    "gn:country_code":"VN",
    "gn:dem":5,
    "gn:feature_class":"P",
    "gn:feature_code":"PPL",
    "gn:name":"L\u00e3nh Tr\u00ec",
    "gn:population":0,
    "gn:timezone":"Asia/Ho_Chi_Minh",
    "iso:country":"VN",
    "name:und_x_variant":[
        "L\u1eb7nh Tr\u00ec"
    ],
    "name:vie_x_preferred":[
        "L\u00e3nh Tr\u00ec"
    ],
    "wof:name":"Lanh Tri",
    "wof:placetype":"locality"
},
  "geometry": {"coordinates":[106.02132,20.65969],"type":"Point"}
}