{
  "type": "Feature",
  "properties": {
    "gn:admin1_code":"73.0",
    "gn:asciiname":"Thanh Tri",
    "gn:country_code":"VN",
    "gn:dem":1,
    "gn:feature_class":"P",
    "gn:feature_code":"PPL",
    "gn:name":"Thanh Tr\u1ecb",
    "gn:population":0,
    "gn:timezone":"Asia/Ho_Chi_Minh",
    "iso:country":"VN",
    "name:und_x_variant":[
        "Xom Thanh Tri",
        "\u1ea4p Th\u1ea1nh Tr"
    ],
    "name:vie_x_preferred":[
        "Thanh Tr\u1ecb"
    ],
    "wof:name":"Thanh Tri",
    "wof:placetype":"locality"
},
  "geometry": {"coordinates":[105.45388,9.20069],"type":"Point"}
}