{
  "type": "Feature",
  "properties": {
    "gn:admin1_code":"5.0",
    "gn:asciiname":"Ti Binh",
    "gn:country_code":"VN",
    "gn:dem":500,
    "gn:feature_class":"P",
    "gn:feature_code":"PPL",
    "gn:name":"Ti Binh",
    "gn:population":0,
    "gn:timezone":"Asia/Ho_Chi_Minh",
    "iso:country":"VN",
    "name:und_x_variant":[
        "T\u1ec9 \u0110\u00ednh"
    ],
    "wof:name":"Ti Binh",
    "wof:placetype":"locality"
},
  "geometry": {"coordinates":[106.63333,22.68333],"type":"Point"}
}