{
  "type": "Feature",
  "properties": {
    "gn:admin1_code":"9.0",
    "gn:asciiname":"Ap Hung My Tay",
    "gn:country_code":"VN",
    "gn:dem":5,
    "gn:feature_class":"P",
    "gn:feature_code":"PPL",
    "gn:name":"\u1ea4p H\u01b0ng M\u1ef9 T\u00e2y",
    "gn:population":0,
    "gn:timezone":"Asia/Ho_Chi_Minh",
    "iso:country":"VN",
    "name:und_x_variant":[
        "Hung My Tay",
        "\u1ea4p H\u01b0ng M\u1ef9 T\u00e2y"
    ],
    "wof:name":"Ap Hung My Tay",
    "wof:placetype":"locality"
},
  "geometry": {"coordinates":[105.68333,10.33333],"type":"Point"}
}