{
  "type": "Feature",
  "properties": {
    "gn:admin1_code":"92.0",
    "gn:asciiname":"Huoi Su Mot",
    "gn:country_code":"VN",
    "gn:dem":755,
    "gn:feature_class":"P",
    "gn:feature_code":"PPL",
    "gn:name":"Hu\u1ed5i Su M\u1ed9t",
    "gn:population":0,
    "gn:timezone":"Asia/Ho_Chi_Minh",
    "iso:country":"VN",
    "name:vie_x_preferred":[
        "Hu\u1ed5i Su M\u1ed9t"
    ],
    "name:vie_x_variant":[
        "Hu\u1ed5i Su 1"
    ],
    "wof:name":"Huoi Su Mot",
    "wof:placetype":"locality"
},
  "geometry": {"coordinates":[103.34189000000001,21.11466],"type":"Point"}
}