{
  "type": "Feature",
  "properties": {
    "gn:admin1_code":"30.0",
    "gn:asciiname":"Bac Bin",
    "gn:country_code":"VN",
    "gn:dem":208,
    "gn:feature_class":"P",
    "gn:feature_code":"PPL",
    "gn:name":"B\u1eafc Bin",
    "gn:population":0,
    "gn:timezone":"Asia/Ho_Chi_Minh",
    "iso:country":"VN",
    "wof:name":"Bac Bin",
    "wof:placetype":"locality"
},
  "geometry": {"coordinates":[107.46666999999999,21.58333],"type":"Point"}
}