{
  "type": "Feature",
  "properties": {
    "gn:admin1_code":"63.0",
    "gn:asciiname":"Ngoc Da",
    "gn:country_code":"VN",
    "gn:dem":10,
    "gn:feature_class":"P",
    "gn:feature_code":"PPL",
    "gn:name":"Ngoc \u0110a",
    "gn:population":0,
    "gn:timezone":"Asia/Ho_Chi_Minh",
    "iso:country":"VN",
    "name:und_x_variant":[
        "Ngoc Gia",
        "Ngoc \u0110a"
    ],
    "wof:name":"Ngoc Da",
    "wof:placetype":"locality"
},
  "geometry": {"coordinates":[108.76667,14.95],"type":"Point"}
}