{
  "type": "Feature",
  "properties": {
    "gn:admin1_code":"59.0",
    "gn:asciiname":"Tra Tu",
    "gn:country_code":"VN",
    "gn:dem":2,
    "gn:feature_class":"P",
    "gn:feature_code":"PPL",
    "gn:name":"Tr\u00e0 Tu",
    "gn:population":0,
    "gn:timezone":"Asia/Ho_Chi_Minh",
    "iso:country":"VN",
    "name:und_x_variant":[
        "Ch\u00e1 Tu"
    ],
    "name:vie_x_preferred":[
        "Tr\u00e0 Tu"
    ],
    "wof:name":"Tra Tu",
    "wof:placetype":"locality"
},
  "geometry": {"coordinates":[105.95478,20.16123],"type":"Point"}
}