{
  "type": "Feature",
  "properties": {
    "gn:admin1_code":"33.0",
    "gn:asciiname":"Loc Thanh",
    "gn:country_code":"VN",
    "gn:dem":13,
    "gn:feature_class":"P",
    "gn:feature_code":"PPL",
    "gn:name":"L\u1ed9c Thanh",
    "gn:population":0,
    "gn:timezone":"Asia/Ho_Chi_Minh",
    "iso:country":"VN",
    "name:vie_x_preferred":[
        "L\u1ed9c Thanh"
    ],
    "wof:name":"Loc Thanh",
    "wof:placetype":"locality"
},
  "geometry": {"coordinates":[106.37499,11.08947],"type":"Point"}
}