{
  "type": "Feature",
  "properties": {
    "gn:admin1_code":"61.0",
    "gn:asciiname":"Phu Tien",
    "gn:country_code":"VN",
    "gn:dem":51,
    "gn:feature_class":"P",
    "gn:feature_code":"PPL",
    "gn:name":"Ph\u00fa Ti\u1ebfn",
    "gn:population":0,
    "gn:timezone":"Asia/Ho_Chi_Minh",
    "iso:country":"VN",
    "name:vie_x_preferred":[
        "Ph\u00fa Ti\u1ebfn"
    ],
    "wof:name":"Phu Tien",
    "wof:placetype":"locality"
},
  "geometry": {"coordinates":[108.92355999999999,13.436],"type":"Point"}
}