{
  "type": "Feature",
  "properties": {
    "gn:admin1_code":"14.0",
    "gn:asciiname":"Xuan Hoi",
    "gn:country_code":"VN",
    "gn:dem":2,
    "gn:feature_class":"P",
    "gn:feature_code":"PPL",
    "gn:name":"Xu\u00e2n H\u1ed3i",
    "gn:population":0,
    "gn:timezone":"Asia/Ho_Chi_Minh",
    "iso:country":"VN",
    "wof:name":"Xuan Hoi",
    "wof:placetype":"locality"
},
  "geometry": {"coordinates":[106.15000000000001,20.15],"type":"Point"}
}