{
  "type": "Feature",
  "properties": {
    "gn:admin1_code":"86.0",
    "gn:asciiname":"Than Son",
    "gn:country_code":"VN",
    "gn:dem":46,
    "gn:feature_class":"P",
    "gn:feature_code":"PPL",
    "gn:name":"Th\u00e1n S\u01a1n",
    "gn:population":0,
    "gn:timezone":"Asia/Ho_Chi_Minh",
    "iso:country":"VN",
    "name:vie_x_preferred":[
        "Th\u00e1n S\u01a1n"
    ],
    "wof:name":"Than Son",
    "wof:placetype":"locality"
},
  "geometry": {"coordinates":[105.47478,21.43515],"type":"Point"}
}