{
  "type": "Feature",
  "properties": {
    "gn:admin1_code":"71.0",
    "gn:asciiname":"Na Ngai",
    "gn:country_code":"VN",
    "gn:dem":171,
    "gn:feature_class":"P",
    "gn:feature_code":"PPL",
    "gn:name":"Na Ngai",
    "gn:population":0,
    "gn:timezone":"Asia/Ho_Chi_Minh",
    "iso:country":"VN",
    "wof:name":"Na Ngai",
    "wof:placetype":"locality"
},
  "geometry": {"coordinates":[106.96666999999999,21.35],"type":"Point"}
}