{
  "type": "Feature",
  "properties": {
    "gn:admin1_code":"39.0",
    "gn:asciiname":"Chu Quyen",
    "gn:country_code":"VN",
    "gn:dem":347,
    "gn:feature_class":"P",
    "gn:feature_code":"PPL",
    "gn:name":"Chu Quy\u1ec3n",
    "gn:population":0,
    "gn:timezone":"Asia/Ho_Chi_Minh",
    "iso:country":"VN",
    "wof:name":"Chu Quyen",
    "wof:placetype":"locality"
},
  "geometry": {"coordinates":[106.73333,21.91667],"type":"Point"}
}