{
  "type": "Feature",
  "properties": {
    "gn:admin1_code":"32.0",
    "gn:asciiname":"Ban Suoi Ngang",
    "gn:country_code":"VN",
    "gn:dem":376,
    "gn:feature_class":"P",
    "gn:feature_code":"PPL",
    "gn:name":"B\u1ea3n Su\u1ed1i Ngang",
    "gn:population":0,
    "gn:timezone":"Asia/Ho_Chi_Minh",
    "iso:country":"VN",
    "name:vie_x_preferred":[
        "B\u1ea3n Su\u1ed1i Ngang"
    ],
    "wof:name":"Ban Suoi Ngang",
    "wof:placetype":"locality"
},
  "geometry": {"coordinates":[104.53375,21.03672000000001],"type":"Point"}
}