{
  "type": "Feature",
  "properties": {
    "gn:admin1_code":"83.0",
    "gn:asciiname":"Luong Bang",
    "gn:country_code":"VN",
    "gn:dem":65,
    "gn:feature_class":"P",
    "gn:feature_code":"PPL",
    "gn:name":"L\u01b0\u01a1ng B\u1eb1ng",
    "gn:population":0,
    "gn:timezone":"Asia/Ho_Chi_Minh",
    "iso:country":"VN",
    "name:vie_x_preferred":[
        "L\u01b0\u01a1ng B\u1eb1ng"
    ],
    "wof:name":"Luong Bang",
    "wof:placetype":"locality"
},
  "geometry": {"coordinates":[105.02855,21.64841],"type":"Point"}
}