{
  "type": "Feature",
  "properties": {
    "gn:admin1_code":"86.0",
    "gn:asciiname":"Noi My",
    "gn:country_code":"VN",
    "gn:dem":23,
    "gn:feature_class":"P",
    "gn:feature_code":"PPL",
    "gn:name":"N\u1ed9i M\u1ef9",
    "gn:population":0,
    "gn:timezone":"Asia/Ho_Chi_Minh",
    "iso:country":"VN",
    "name:vie_x_preferred":[
        "N\u1ed9i M\u1ef9"
    ],
    "wof:name":"Noi My",
    "wof:placetype":"locality"
},
  "geometry": {"coordinates":[105.43216,21.40048],"type":"Point"}
}