{
  "type": "Feature",
  "properties": {
    "gn:admin1_code":"84.0",
    "gn:asciiname":"Tu La",
    "gn:country_code":"VN",
    "gn:dem":65,
    "gn:feature_class":"P",
    "gn:feature_code":"PPL",
    "gn:name":"Tu La",
    "gn:population":0,
    "gn:timezone":"Asia/Ho_Chi_Minh",
    "iso:country":"VN",
    "wof:name":"Tu La",
    "wof:placetype":"locality"
},
  "geometry": {"coordinates":[108.11667,15.53333],"type":"Point"}
}