{
  "type": "Feature",
  "properties": {
    "gn:admin1_code":"68.0",
    "gn:asciiname":"Na Hec",
    "gn:country_code":"VN",
    "gn:dem":70,
    "gn:feature_class":"P",
    "gn:feature_code":"PPL",
    "gn:name":"N\u00e0 H\u00e9c",
    "gn:population":0,
    "gn:timezone":"Asia/Ho_Chi_Minh",
    "iso:country":"VN",
    "name:vie_x_preferred":[
        "N\u00e0 H\u00e9c"
    ],
    "wof:name":"Na Hec",
    "wof:placetype":"locality"
},
  "geometry": {"coordinates":[105.21569,22.25065],"type":"Point"}
}