{
  "type": "Feature",
  "properties": {
    "gn:admin1_code":"34.0",
    "gn:asciiname":"Thu Trinh",
    "gn:country_code":"VN",
    "gn:dem":74,
    "gn:feature_class":"P",
    "gn:feature_code":"PPL",
    "gn:name":"Th\u1ee7 Trinh",
    "gn:population":0,
    "gn:timezone":"Asia/Ho_Chi_Minh",
    "iso:country":"VN",
    "wof:name":"Thu Trinh",
    "wof:placetype":"locality"
},
  "geometry": {"coordinates":[105.36667,19.93333],"type":"Point"}
}