{
  "type": "Feature",
  "properties": {
    "gn:admin1_code":"89.0",
    "gn:asciiname":"Lai Chau",
    "gn:cc2":"VN",
    "gn:country_code":"VN",
    "gn:dem":246,
    "gn:feature_class":"P",
    "gn:feature_code":"PPL",
    "gn:name":"Lai Ch\u00e2u",
    "gn:population":0,
    "gn:timezone":"Asia/Ho_Chi_Minh",
    "iso:country":"VN",
    "name:hun_x_preferred":[
        "Lai Chau"
    ],
    "name:rus_x_preferred":[
        "\u041b\u0430\u0439\u0442\u044f\u0443"
    ],
    "name:swe_x_preferred":[
        "Lai Chau"
    ],
    "name:und_x_variant":[
        "Muong Lai",
        "Lai Chou",
        "Lai Chow",
        "Lai Ch\u00e2u"
    ],
    "wof:name":"Lai Chau",
    "wof:placetype":"locality"
},
  "geometry": {"coordinates":[103.1563,22.07021],"type":"Point"}
}