{
  "type": "Feature",
  "properties": {
    "gn:admin1_code":"58.0",
    "gn:asciiname":"Khoi Bay",
    "gn:country_code":"VN",
    "gn:dem":8,
    "gn:feature_class":"P",
    "gn:feature_code":"PPL",
    "gn:name":"Kh\u1ed1i B\u1ea3y",
    "gn:population":0,
    "gn:timezone":"Asia/Ho_Chi_Minh",
    "iso:country":"VN",
    "name:vie_x_preferred":[
        "Kh\u1ed1i B\u1ea3y"
    ],
    "name:vie_x_variant":[
        "Kh\u1ed1i 7"
    ],
    "wof:name":"Khoi Bay",
    "wof:placetype":"locality"
},
  "geometry": {"coordinates":[105.70095999999999,18.82018],"type":"Point"}
}