{
  "type": "Feature",
  "properties": {
    "gn:admin1_code":"49.0",
    "gn:asciiname":"Ban Ni Ko",
    "gn:country_code":"VN",
    "gn:dem":200,
    "gn:feature_class":"P",
    "gn:feature_code":"PPL",
    "gn:name":"Ban Ni K\u00f4",
    "gn:population":0,
    "gn:timezone":"Asia/Ho_Chi_Minh",
    "iso:country":"VN",
    "wof:name":"Ban Ni Ko",
    "wof:placetype":"locality"
},
  "geometry": {"coordinates":[108.84999999999999,13.25],"type":"Point"}
}