{
  "type": "Feature",
  "properties": {
    "gn:admin1_code":"92.0",
    "gn:asciiname":"Cha A",
    "gn:country_code":"VN",
    "gn:dem":780,
    "gn:feature_class":"P",
    "gn:feature_code":"PPL",
    "gn:name":"Ch\u1ea3 A",
    "gn:population":0,
    "gn:timezone":"Asia/Ho_Chi_Minh",
    "iso:country":"VN",
    "wof:name":"Cha A",
    "wof:placetype":"locality"
},
  "geometry": {"coordinates":[103.18035,21.07525],"type":"Point"}
}