{
  "type": "Feature",
  "properties": {
    "gn:admin1_code":"59.0",
    "gn:asciiname":"Kien Phong",
    "gn:country_code":"VN",
    "gn:dem":6,
    "gn:feature_class":"P",
    "gn:feature_code":"PPL",
    "gn:name":"Ki\u00ean Phong",
    "gn:population":0,
    "gn:timezone":"Asia/Ho_Chi_Minh",
    "iso:country":"VN",
    "name:vie_x_preferred":[
        "Ki\u00ean Phong"
    ],
    "wof:name":"Kien Phong",
    "wof:placetype":"locality"
},
  "geometry": {"coordinates":[105.79844,20.35543],"type":"Point"}
}