{
  "type": "Feature",
  "properties": {
    "gn:admin1_code":"32.0",
    "gn:asciiname":"Ban Bo Ngoa",
    "gn:country_code":"VN",
    "gn:dem":767,
    "gn:feature_class":"P",
    "gn:feature_code":"PPL",
    "gn:name":"B\u1ea3n B\u00f3 Ngoa",
    "gn:population":0,
    "gn:timezone":"Asia/Ho_Chi_Minh",
    "iso:country":"VN",
    "name:vie_x_preferred":[
        "B\u1ea3n B\u00f3 Ngoa"
    ],
    "wof:name":"Ban Bo Ngoa",
    "wof:placetype":"locality"
},
  "geometry": {"coordinates":[104.19619,21.12179],"type":"Point"}
}