{
  "type": "Feature",
  "properties": {
    "gn:admin1_code":"32.0",
    "gn:asciiname":"Giac Long",
    "gn:country_code":"VN",
    "gn:dem":272,
    "gn:feature_class":"P",
    "gn:feature_code":"PPL",
    "gn:name":"Gi\u00e1c L\u00f4ng",
    "gn:population":0,
    "gn:timezone":"Asia/Ho_Chi_Minh",
    "iso:country":"VN",
    "name:vie_x_preferred":[
        "Gi\u00e1c L\u00f4ng"
    ],
    "wof:name":"Giac Long",
    "wof:placetype":"locality"
},
  "geometry": {"coordinates":[104.85552,21.04696],"type":"Point"}
}