{
  "type": "Feature",
  "properties": {
    "gn:admin1_code":"32.0",
    "gn:asciiname":"Su Mai",
    "gn:country_code":"VN",
    "gn:dem":1308,
    "gn:feature_class":"P",
    "gn:feature_code":"PPL",
    "gn:name":"Su Mai",
    "gn:population":0,
    "gn:timezone":"Asia/Ho_Chi_Minh",
    "iso:country":"VN",
    "wof:name":"Su Mai",
    "wof:placetype":"locality"
},
  "geometry": {"coordinates":[104.59999999999999,21.33333],"type":"Point"}
}