{
  "type": "Feature",
  "properties": {
    "gn:admin1_code":"58.0",
    "gn:asciiname":"Van Trang",
    "gn:country_code":"VN",
    "gn:dem":5,
    "gn:feature_class":"P",
    "gn:feature_code":"PPL",
    "gn:name":"V\u1ea1n Tr\u00e0ng",
    "gn:population":0,
    "gn:timezone":"Asia/Ho_Chi_Minh",
    "iso:country":"VN",
    "name:vie_x_preferred":[
        "V\u1ea1n Tr\u00e0ng"
    ],
    "wof:name":"Van Trang",
    "wof:placetype":"locality"
},
  "geometry": {"coordinates":[105.49334,18.96728],"type":"Point"}
}