{
  "type": "Feature",
  "properties": {
    "gn:admin1_code":"93.0",
    "gn:asciiname":"Ap Sau",
    "gn:country_code":"VN",
    "gn:dem":3,
    "gn:feature_class":"P",
    "gn:feature_code":"PPL",
    "gn:name":"\u1ea4p S\u00e1u",
    "gn:population":0,
    "gn:timezone":"Asia/Ho_Chi_Minh",
    "iso:country":"VN",
    "name:vie_x_preferred":[
        "\u1ea4p S\u00e1u"
    ],
    "name:vie_x_variant":[
        "\u1ea4p 6"
    ],
    "wof:name":"Ap Sau",
    "wof:placetype":"locality"
},
  "geometry": {"coordinates":[105.61322,9.66358],"type":"Point"}
}