{
  "type": "Feature",
  "properties": {
    "gn:admin1_code":"92.0",
    "gn:asciiname":"Tao Sen",
    "gn:country_code":"VN",
    "gn:dem":242,
    "gn:feature_class":"P",
    "gn:feature_code":"PPL",
    "gn:name":"T\u1ea1o Sen",
    "gn:population":0,
    "gn:timezone":"Asia/Ho_Chi_Minh",
    "iso:country":"VN",
    "name:vie_x_preferred":[
        "T\u1ea1o Sen"
    ],
    "wof:name":"Tao Sen",
    "wof:placetype":"locality"
},
  "geometry": {"coordinates":[103.14543,21.99162],"type":"Point"}
}