{
  "type": "Feature",
  "properties": {
    "gn:admin1_code":"58.0",
    "gn:asciiname":"Dai Bac",
    "gn:country_code":"VN",
    "gn:dem":9,
    "gn:feature_class":"P",
    "gn:feature_code":"PPL",
    "gn:name":"\u0110\u1ea1i B\u1eafc",
    "gn:population":0,
    "gn:timezone":"Asia/Ho_Chi_Minh",
    "iso:country":"VN",
    "name:vie_x_preferred":[
        "\u0110\u1ea1i B\u1eafc"
    ],
    "wof:name":"Dai Bac",
    "wof:placetype":"locality"
},
  "geometry": {"coordinates":[105.69221,19.08828],"type":"Point"}
}