{
  "type": "Feature",
  "properties": {
    "gn:admin1_code":"32.0",
    "gn:asciiname":"Ban Me Lech",
    "gn:country_code":"VN",
    "gn:dem":664,
    "gn:feature_class":"P",
    "gn:feature_code":"PPL",
    "gn:name":"B\u1ea3n Me L\u1ebfch",
    "gn:population":0,
    "gn:timezone":"Asia/Ho_Chi_Minh",
    "iso:country":"VN",
    "name:vie_x_preferred":[
        "B\u1ea3n Me L\u1ebfch"
    ],
    "wof:name":"Ban Me Lech",
    "wof:placetype":"locality"
},
  "geometry": {"coordinates":[104.15188999999999,21.132],"type":"Point"}
}