{
  "type": "Feature",
  "properties": {
    "gn:admin1_code":"91.0",
    "gn:asciiname":"Bu M'bre",
    "gn:country_code":"VN",
    "gn:dem":550,
    "gn:feature_class":"P",
    "gn:feature_code":"PPL",
    "gn:name":"Bu M\u2019br\u00e9",
    "gn:population":0,
    "gn:timezone":"Asia/Ho_Chi_Minh",
    "iso:country":"VN",
    "wof:name":"Bu M'bre",
    "wof:placetype":"locality"
},
  "geometry": {"coordinates":[107.48333,11.98333],"type":"Point"}
}