{
  "type": "Feature",
  "properties": {
    "gn:admin1_code":"46.0",
    "gn:asciiname":"Thuan Phong",
    "gn:country_code":"VN",
    "gn:dem":54,
    "gn:feature_class":"P",
    "gn:feature_code":"PPL",
    "gn:name":"Thu\u1eadn Phong",
    "gn:population":0,
    "gn:timezone":"Asia/Ho_Chi_Minh",
    "iso:country":"VN",
    "name:vie_x_preferred":[
        "Thu\u1eadn Phong"
    ],
    "wof:name":"Thuan Phong",
    "wof:placetype":"locality"
},
  "geometry": {"coordinates":[108.96571000000002,14.05587],"type":"Point"}
}