{
  "type": "Feature",
  "properties": {
    "gn:admin1_code":"24.0",
    "gn:asciiname":"Ca Sao",
    "gn:country_code":"VN",
    "gn:dem":0,
    "gn:feature_class":"P",
    "gn:feature_code":"PPL",
    "gn:name":"C\u1ea3 S\u00e1o",
    "gn:population":0,
    "gn:timezone":"Asia/Ho_Chi_Minh",
    "iso:country":"VN",
    "name:vie_x_preferred":[
        "C\u1ea3 S\u00e1o"
    ],
    "wof:name":"Ca Sao",
    "wof:placetype":"locality"
},
  "geometry": {"coordinates":[105.83038000000001,10.81179],"type":"Point"}
}