{
  "type": "Feature",
  "properties": {
    "gn:admin1_code":"54.0",
    "gn:asciiname":"Khom Ba",
    "gn:country_code":"VN",
    "gn:dem":25,
    "gn:feature_class":"P",
    "gn:feature_code":"PPL",
    "gn:name":"Kh\u00f3m Ba",
    "gn:population":0,
    "gn:timezone":"Asia/Ho_Chi_Minh",
    "iso:country":"VN",
    "name:vie_x_preferred":[
        "Kh\u00f3m Ba"
    ],
    "name:vie_x_variant":[
        "Kh\u00f3m 3"
    ],
    "wof:name":"Khom Ba",
    "wof:placetype":"locality"
},
  "geometry": {"coordinates":[108.93000000000001,12.28158],"type":"Point"}
}