{
  "type": "Feature",
  "properties": {
    "gn:admin1_code":"89.0",
    "gn:asciiname":"Pa La",
    "gn:country_code":"VN",
    "gn:dem":523,
    "gn:feature_class":"P",
    "gn:feature_code":"PPL",
    "gn:name":"Pa La",
    "gn:population":0,
    "gn:timezone":"Asia/Ho_Chi_Minh",
    "iso:country":"VN",
    "wof:name":"Pa La",
    "wof:placetype":"locality"
},
  "geometry": {"coordinates":[103.81667,21.91667],"type":"Point"}
}