{
  "type": "Feature",
  "properties": {
    "gn:admin1_code":"44.0",
    "gn:asciiname":"Tay Dang",
    "gn:country_code":"VN",
    "gn:dem":19,
    "gn:feature_class":"P",
    "gn:feature_code":"PPLA2",
    "gn:name":"T\u00e2y \u0110\u1eb1ng",
    "gn:population":0,
    "gn:timezone":"Asia/Ho_Chi_Minh",
    "iso:country":"VN",
    "name:und_x_variant":[
        "T\u00e2y D\u1eafng"
    ],
    "name:vie_x_preferred":[
        "T\u00e2y D\u1eb1ng"
    ],
    "name:vie_x_variant":[
        "T\u00e2y \u0110\u1eb1ng",
        "Huy\u1ec7n Ba V\u00ec"
    ],
    "wof:name":"Tay Dang",
    "wof:placetype":"locality"
},
  "geometry": {"coordinates":[105.42216999999999,21.19809],"type":"Point"}
}