{
  "type": "Feature",
  "properties": {
    "gn:admin1_code":"39.0",
    "gn:asciiname":"Lap Niu",
    "gn:country_code":"VN",
    "gn:dem":246,
    "gn:feature_class":"P",
    "gn:feature_code":"PPL",
    "gn:name":"L\u1eadp Niu",
    "gn:population":0,
    "gn:timezone":"Asia/Ho_Chi_Minh",
    "iso:country":"VN",
    "name:vie_x_preferred":[
        "L\u1eadp Niu"
    ],
    "wof:name":"Lap Niu",
    "wof:placetype":"locality"
},
  "geometry": {"coordinates":[106.29468,21.75779],"type":"Point"}
}