{
  "type": "Feature",
  "properties": {
    "gn:country":"VN",
    "gn:fcode":"PPLA",
    "gn:pop":40273,
    "iso:country":"VN",
    "name:ara_x_preferred":[
        "\u0647\u0648\u0646\u062c \u064a\u0646"
    ],
    "name:ben_x_preferred":[
        "\u09b9\u09c1\u0982 \u0987\u09af\u09bc\u09c7\u09a8"
    ],
    "name:dan_x_preferred":[
        "Hung Yen"
    ],
    "name:ell_x_preferred":[
        "\u03a7\u03bf\u03cd\u03bd\u03b3\u03ba \u0393\u03b9\u03ad\u03bd"
    ],
    "name:eng_x_preferred":[
        "Hung Yen"
    ],
    "name:fas_x_preferred":[
        "\u0647\u0648\u0646\u06af \u06cc\u0646"
    ],
    "name:fin_x_preferred":[
        "H\u01b0ng Y\u00ean"
    ],
    "name:fra_x_preferred":[
        "H\u01b0ng Y\u00ean"
    ],
    "name:guj_x_preferred":[
        "\u0ab9\u0ac7\u0a82\u0a97 \u0aaf\u0ac7\u0aa8"
    ],
    "name:hak_x_preferred":[
        "H\u00een-\u00f4n-s\u1e73"
    ],
    "name:hin_x_preferred":[
        "\u0939\u0941\u0902\u0917 \u092f\u0947\u0928"
    ],
    "name:ind_x_preferred":[
        "H\u01b0ng Y\u00ean"
    ],
    "name:ita_x_preferred":[
        "H\u01b0ng Y\u00ean"
    ],
    "name:jpn_x_preferred":[
        "\u30d5\u30f3\u30a4\u30a8\u30f3"
    ],
    "name:kan_x_preferred":[
        "\u0cb9\u0c82\u0c97\u0ccd \u0caf\u0cc6\u0ca8\u0ccd"
    ],
    "name:kor_x_preferred":[
        "\ud765\uc60c"
    ],
    "name:lav_x_preferred":[
        "Hinjena"
    ],
    "name:lit_x_preferred":[
        "Hung Jenas"
    ],
    "name:mar_x_preferred":[
        "\u0939\u0945\u0928\u094d\u0917 \u092f\u0947\u0902"
    ],
    "name:msa_x_preferred":[
        "Hung Yen"
    ],
    "name:nld_x_preferred":[
        "H\u01b0ng Y\u00ean"
    ],
    "name:nob_x_preferred":[
        "Hung Yen"
    ],
    "name:pol_x_preferred":[
        "H\u01b0ng Y\u00ean"
    ],
    "name:por_x_preferred":[
        "H\u01b0ng Y\u00ean"
    ],
    "name:rus_x_preferred":[
        "\u0425\u044b\u043d\u0433\u0439\u0435\u043d"
    ],
    "name:sin_x_preferred":[
        "\u0dc4\u0dd0\u0db1\u0dca\u0d9c\u0dca \u0dba\u0dd9\u0db1\u0dca\u0d9c\u0dca"
    ],
    "name:spa_x_preferred":[
        "H\u01b0ng Y\u00ean"
    ],
    "name:srp_x_preferred":[
        "H\u01b0ng Y\u00ean"
    ],
    "name:swe_x_preferred":[
        "Hung Yen"
    ],
    "name:tam_x_preferred":[
        "\u0bb9\u0b99\u0bcd \u0baf\u0bc6\u0ba9\u0bcd"
    ],
    "name:tel_x_preferred":[
        "\u0c39\u0c41\u0c02\u0c17\u0c4d \u0c2f\u0c46\u0c28\u0c4d"
    ],
    "name:tgk_x_preferred":[
        "\u0412\u0438\u043b\u043e\u044f\u0442\u0438 \u0425\u0443\u043d\u0433 \u0415\u043d"
    ],
    "name:tha_x_preferred":[
        "\u0e2e\u0e38\u0e07 \u0e40\u0e22\u0e34\u0e19"
    ],
    "name:tur_x_preferred":[
        "Hung Yen"
    ],
    "name:ukr_x_preferred":[
        "\u0425\u0438\u043d\u0433'\u0454\u043d"
    ],
    "name:unk_x_variant":[
        "Hong-Yen"
    ],
    "name:urd_x_preferred":[
        "\u062d\u0646\u062c \u06cc\u06cc\u0646"
    ],
    "name:vie_x_preferred":[
        "H\u01b0ng Y\u00ean"
    ],
    "name:war_x_preferred":[
        "Hung Yen"
    ],
    "name:zho_x_preferred":[
        "\u8208\u5b89\u5e02"
    ],
    "qs:name":"H\u01b0ng Y\u00ean",
    "qs:photos_9r":0,
    "qs:photos_sr":0,
    "qs:pop_sr":"7",
    "wd:wordcount":235,
    "wof:name":"H\u01b0ng Y\u00ean",
    "wof:placetype":"locality",
    "wof:population":40273
},
  "geometry": {"coordinates":[106.06667,20.65],"type":"Point"}
}