{
  "type": "Feature",
  "properties": {
    "gn:admin1_code":"52.0",
    "gn:asciiname":"Trai Bau Nuoc",
    "gn:country_code":"VN",
    "gn:dem":20,
    "gn:feature_class":"P",
    "gn:feature_code":"PPL",
    "gn:name":"Tr\u1ea1i B\u1ea7u N\u01b0\u1edbc",
    "gn:population":0,
    "gn:timezone":"Asia/Ho_Chi_Minh",
    "iso:country":"VN",
    "name:und_x_variant":[
        "Trai Bau Nvoc",
        "Tr\u1ea1i B\u1ea7u N\u01b0\u1edbc"
    ],
    "wof:name":"Trai Bau Nuoc",
    "wof:placetype":"locality"
},
  "geometry": {"coordinates":[106.15000000000001,18.13333],"type":"Point"}
}