{
  "type": "Feature",
  "properties": {
    "gn:admin1_code":"71.0",
    "gn:asciiname":"Duong Quan Ha",
    "gn:country_code":"VN",
    "gn:dem":13,
    "gn:feature_class":"P",
    "gn:feature_code":"PPL",
    "gn:name":"D\u01b0\u01a1ng Quan H\u1ea1",
    "gn:population":0,
    "gn:timezone":"Asia/Ho_Chi_Minh",
    "iso:country":"VN",
    "name:und_x_variant":[
        "D\u01b0\u01a1ng Quan"
    ],
    "name:vie_x_preferred":[
        "D\u01b0\u01a1ng Quan H\u1ea1"
    ],
    "wof:name":"Duong Quan Ha",
    "wof:placetype":"locality"
},
  "geometry": {"coordinates":[106.184,21.36629],"type":"Point"}
}