{
  "type": "Feature",
  "properties": {
    "gn:admin1_code":"90.0",
    "gn:asciiname":"Nam Dam Dam",
    "gn:country_code":"VN",
    "gn:dem":858,
    "gn:feature_class":"P",
    "gn:feature_code":"PPL",
    "gn:name":"Nam D\u1eadm D\u1ea3m",
    "gn:population":0,
    "gn:timezone":"Asia/Ho_Chi_Minh",
    "iso:country":"VN",
    "wof:name":"Nam Dam Dam",
    "wof:placetype":"locality"
},
  "geometry": {"coordinates":[104.40000000000001,22.45],"type":"Point"}
}