{
  "type": "Feature",
  "properties": {
    "gn:admin1_code":"23.0",
    "gn:asciiname":"Da Loc",
    "gn:country_code":"VN",
    "gn:dem":1371,
    "gn:feature_class":"P",
    "gn:feature_code":"PPL",
    "gn:name":"Da Loc",
    "gn:population":0,
    "gn:timezone":"Asia/Ho_Chi_Minh",
    "iso:country":"VN",
    "name:und_x_variant":[
        "\u1ea4p \u0110a L\u00f4c"
    ],
    "wof:name":"Da Loc",
    "wof:placetype":"locality"
},
  "geometry": {"coordinates":[108.51667,11.93333],"type":"Point"}
}