{
  "type": "Feature",
  "properties": {
    "gn:admin1_code":"62.0",
    "gn:asciiname":"Thanh Lang",
    "gn:country_code":"VN",
    "gn:dem":1,
    "gn:feature_class":"P",
    "gn:feature_code":"PPL",
    "gn:name":"Thanh Lang",
    "gn:population":0,
    "gn:timezone":"Asia/Ho_Chi_Minh",
    "iso:country":"VN",
    "name:und_x_variant":[
        "Thanh Long",
        "Thang Lang",
        "Thanh Lang"
    ],
    "wof:name":"Thanh Lang",
    "wof:placetype":"locality"
},
  "geometry": {"coordinates":[106.36667,17.63332999999999],"type":"Point"}
}