{
  "type": "Feature",
  "properties": {
    "gn:admin1_code":"82.0",
    "gn:asciiname":"Van Chang",
    "gn:country_code":"VN",
    "gn:dem":6,
    "gn:feature_class":"P",
    "gn:feature_code":"PPL",
    "gn:name":"V\u1ea9n Ch\u00e0ng",
    "gn:population":0,
    "gn:timezone":"Asia/Ho_Chi_Minh",
    "iso:country":"VN",
    "name:und_x_variant":[
        "Van Trang",
        "V\u1ea9n Ch\u00e0ng"
    ],
    "wof:name":"Van Chang",
    "wof:placetype":"locality"
},
  "geometry": {"coordinates":[106.18333,20.35],"type":"Point"}
}