{
  "type": "Feature",
  "properties": {
    "gn:admin1_code":"39.0",
    "gn:asciiname":"Po Nhang",
    "gn:country_code":"VN",
    "gn:dem":349,
    "gn:feature_class":"P",
    "gn:feature_code":"PPL",
    "gn:name":"P\u00f2 Nh\u00e0ng",
    "gn:population":0,
    "gn:timezone":"Asia/Ho_Chi_Minh",
    "iso:country":"VN",
    "name:und_x_variant":[
        "P\u00f2 Nhang"
    ],
    "name:vie_x_preferred":[
        "P\u00f2 Nh\u00e0ng"
    ],
    "wof:name":"Po Nhang",
    "wof:placetype":"locality"
},
  "geometry": {"coordinates":[107.05092999999999,21.67925],"type":"Point"}
}