{
  "type": "Feature",
  "properties": {
    "gn:admin1_code":"23.0",
    "gn:asciiname":"Ap R'loum",
    "gn:country_code":"VN",
    "gn:dem":909,
    "gn:feature_class":"P",
    "gn:feature_code":"PPL",
    "gn:name":"\u1ea4p R\u2019loum",
    "gn:population":0,
    "gn:timezone":"Asia/Ho_Chi_Minh",
    "iso:country":"VN",
    "name:und_x_variant":[
        "R\u2019loum",
        "R\u2019Loun",
        "\u1ea4p R\u2019loum"
    ],
    "wof:name":"Ap R'loum",
    "wof:placetype":"locality"
},
  "geometry": {"coordinates":[108.09999999999999,11.38333],"type":"Point"}
}