{
  "type": "Feature",
  "properties": {
    "gn:admin1_code":"20.0",
    "gn:asciiname":"An Nhon Xa",
    "gn:country_code":"VN",
    "gn:dem":12,
    "gn:feature_class":"P",
    "gn:feature_code":"PPL",
    "gn:name":"An Nh\u01a1n X\u00e3",
    "gn:population":0,
    "gn:timezone":"Asia/Ho_Chi_Minh",
    "iso:country":"VN",
    "wof:name":"An Nhon Xa",
    "wof:placetype":"locality"
},
  "geometry": {"coordinates":[106.66667,10.83333],"type":"Point"}
}