{
  "type": "Feature",
  "properties": {
    "gn:admin1_code":"23.0",
    "gn:asciiname":"Tarklette",
    "gn:country_code":"VN",
    "gn:dem":1009,
    "gn:feature_class":"P",
    "gn:feature_code":"PPL",
    "gn:name":"Tarklette",
    "gn:population":0,
    "gn:timezone":"Asia/Ho_Chi_Minh",
    "iso:country":"VN",
    "wof:name":"Tarklette",
    "wof:placetype":"locality"
},
  "geometry": {"coordinates":[108.46666999999999,11.71667],"type":"Point"}
}