{
  "type": "Feature",
  "properties": {
    "gn:admin1_code":"58.0",
    "gn:asciiname":"Xom Cat",
    "gn:country_code":"VN",
    "gn:dem":8,
    "gn:feature_class":"P",
    "gn:feature_code":"PPL",
    "gn:name":"X\u00f3m C\u1eaft",
    "gn:population":0,
    "gn:timezone":"Asia/Ho_Chi_Minh",
    "iso:country":"VN",
    "name:vie_x_preferred":[
        "X\u00f3m C\u1eaft"
    ],
    "wof:name":"Xom Cat",
    "wof:placetype":"locality"
},
  "geometry": {"coordinates":[105.58087999999999,19.10463],"type":"Point"}
}