{
  "type": "Feature",
  "properties": {
    "gn:admin1_code":"45.0",
    "gn:asciiname":"Phuoc Co",
    "gn:country_code":"VN",
    "gn:dem":5,
    "gn:feature_class":"P",
    "gn:feature_code":"PPL",
    "gn:name":"Ph\u01b0\u1edbc C\u01a1",
    "gn:population":0,
    "gn:timezone":"Asia/Ho_Chi_Minh",
    "iso:country":"VN",
    "name:und_x_variant":[
        "Xom Phuoc Co",
        "Phuoc Co",
        "\u1ea4p Ph\u01b0\u1edbc C\u01a1"
    ],
    "name:vie_x_preferred":[
        "Ph\u01b0\u1edbc C\u01a1"
    ],
    "wof:name":"Phuoc Co",
    "wof:placetype":"locality"
},
  "geometry": {"coordinates":[107.17269,10.45672],"type":"Point"}
}