{
  "type": "Feature",
  "properties": {
    "gn:admin1_code":"34.0",
    "gn:asciiname":"Quang Qui",
    "gn:cc2":"VN",
    "gn:country_code":"VN",
    "gn:dem":4,
    "gn:feature_class":"P",
    "gn:feature_code":"PPL",
    "gn:name":"Quang Qu\u00ed",
    "gn:population":0,
    "gn:timezone":"Asia/Ho_Chi_Minh",
    "iso:country":"VN",
    "name:und_x_variant":[
        "Quang Que",
        "Quang Qu\u00ed"
    ],
    "wof:name":"Quang Qui",
    "wof:placetype":"locality"
},
  "geometry": {"coordinates":[105.73333,19.56667],"type":"Point"}
}