{
  "type": "Feature",
  "properties": {
    "gn:admin1_code":"32.0",
    "gn:asciiname":"Ban Xanh",
    "gn:country_code":"VN",
    "gn:dem":891,
    "gn:feature_class":"P",
    "gn:feature_code":"PPL",
    "gn:name":"B\u1ea3n Xanh",
    "gn:population":0,
    "gn:timezone":"Asia/Ho_Chi_Minh",
    "iso:country":"VN",
    "name:vie_x_preferred":[
        "B\u1ea3n Xanh"
    ],
    "wof:name":"Ban Xanh",
    "wof:placetype":"locality"
},
  "geometry": {"coordinates":[103.76246,21.31808],"type":"Point"}
}