{
  "type": "Feature",
  "properties": {
    "gn:admin1_code":"72.0",
    "gn:asciiname":"Loun Ga",
    "gn:country_code":"VN",
    "gn:dem":710,
    "gn:feature_class":"P",
    "gn:feature_code":"PPL",
    "gn:name":"Loun Ga",
    "gn:population":0,
    "gn:timezone":"Asia/Ho_Chi_Minh",
    "iso:country":"VN",
    "wof:name":"Loun Ga",
    "wof:placetype":"locality"
},
  "geometry": {"coordinates":[105.61667,22.35],"type":"Point"}
}