{
  "type": "Feature",
  "properties": {
    "gn:admin1_code":"90.0",
    "gn:asciiname":"Ta Van Meo",
    "gn:country_code":"VN",
    "gn:dem":1127,
    "gn:feature_class":"P",
    "gn:feature_code":"PPL",
    "gn:name":"T\u1ea3 Van M\u00e8o",
    "gn:population":0,
    "gn:timezone":"Asia/Ho_Chi_Minh",
    "iso:country":"VN",
    "name:vie_x_preferred":[
        "T\u1ea3 Van M\u00e8o"
    ],
    "wof:name":"Ta Van Meo",
    "wof:placetype":"locality"
},
  "geometry": {"coordinates":[103.87913,22.30071],"type":"Point"}
}