{
  "type": "Feature",
  "properties": {
    "gn:admin1_code":"20.0",
    "gn:asciiname":"Thanh My Tay",
    "gn:country_code":"VN",
    "gn:dem":1,
    "gn:feature_class":"P",
    "gn:feature_code":"PPL",
    "gn:name":"Thanh M\u1ef9 T\u00e2y",
    "gn:population":0,
    "gn:timezone":"Asia/Ho_Chi_Minh",
    "iso:country":"VN",
    "wof:name":"Thanh My Tay",
    "wof:placetype":"locality"
},
  "geometry": {"coordinates":[106.76667,10.81667],"type":"Point"}
}