{
  "type": "Feature",
  "properties": {
    "gn:admin1_code":"90.0",
    "gn:asciiname":"Ba Nam Tung",
    "gn:country_code":"VN",
    "gn:dem":232,
    "gn:feature_class":"P",
    "gn:feature_code":"PPL",
    "gn:name":"Ba N\u1eadm T\u1ee9ng",
    "gn:population":0,
    "gn:timezone":"Asia/Ho_Chi_Minh",
    "iso:country":"VN",
    "name:vie_x_preferred":[
        "Ba N\u1eadm T\u1ee9ng"
    ],
    "wof:name":"Ba Nam Tung",
    "wof:placetype":"locality"
},
  "geometry": {"coordinates":[103.96886000000001,22.43855],"type":"Point"}
}