{
  "type": "Feature",
  "properties": {
    "gn:admin1_code":"62.0",
    "gn:asciiname":"Hoan Lao",
    "gn:country_code":"VN",
    "gn:dem":10,
    "gn:feature_class":"P",
    "gn:feature_code":"PPLA2",
    "gn:name":"Ho\u00e0n L\u00e3o",
    "gn:population":0,
    "gn:timezone":"Asia/Ho_Chi_Minh",
    "iso:country":"VN",
    "name:bug_x_preferred":[
        "Ho\u00e0n L\u00e3o"
    ],
    "name:nld_x_preferred":[
        "Ho\u00e0n L\u00e3o"
    ],
    "name:spa_x_preferred":[
        "Hoan Lao"
    ],
    "name:und_x_variant":[
        "Ho\u00e0n L\u00e3o",
        "B\u1ed1 Tr\u1ea1ch"
    ],
    "name:vie_x_preferred":[
        "Ho\u00e0n L\u00e3o"
    ],
    "wof:name":"Hoan Lao",
    "wof:placetype":"locality"
},
  "geometry": {"coordinates":[106.53425,17.58436],"type":"Point"}
}