{
  "type": "Feature",
  "properties": {
    "gn:admin1_code":"72.0",
    "gn:asciiname":"Na Nom",
    "gn:country_code":"VN",
    "gn:dem":460,
    "gn:feature_class":"P",
    "gn:feature_code":"PPL",
    "gn:name":"N\u00e0 N\u1ed3m",
    "gn:population":0,
    "gn:timezone":"Asia/Ho_Chi_Minh",
    "iso:country":"VN",
    "name:vie_x_preferred":[
        "N\u00e0 N\u1ed3m"
    ],
    "wof:name":"Na Nom",
    "wof:placetype":"locality"
},
  "geometry": {"coordinates":[105.75891,22.23677],"type":"Point"}
}