{
  "type": "Feature",
  "properties": {
    "gn:admin1_code":"23.0",
    "gn:asciiname":"Ap Da Thanh",
    "gn:country_code":"VN",
    "gn:dem":1494,
    "gn:feature_class":"P",
    "gn:feature_code":"PPL",
    "gn:name":"\u1ea4p \u0110a Th\u00e0nh",
    "gn:population":0,
    "gn:timezone":"Asia/Ho_Chi_Minh",
    "iso:country":"VN",
    "name:und_x_variant":[
        "Da Thanh",
        "\u1ea4p \u0110a Th\u00e0nh"
    ],
    "wof:name":"Ap Da Thanh",
    "wof:placetype":"locality"
},
  "geometry": {"coordinates":[108.43333,11.96667],"type":"Point"}
}