{
  "type": "Feature",
  "properties": {
    "gn:admin1_code":"5.0",
    "gn:asciiname":"Hang Phieng Lau",
    "gn:cc2":"VN",
    "gn:country_code":"VN",
    "gn:dem":189,
    "gn:feature_class":"P",
    "gn:feature_code":"PPL",
    "gn:name":"H\u00e1ng Phi\u00eang L\u00e2u",
    "gn:population":0,
    "gn:timezone":"Asia/Ho_Chi_Minh",
    "iso:country":"VN",
    "name:und_x_variant":[
        "Hang Phieng Lan",
        "H\u00e1ng Phi\u00eang L\u00e2u"
    ],
    "wof:name":"Hang Phieng Lau",
    "wof:placetype":"locality"
},
  "geometry": {"coordinates":[106.43333,22.56667],"type":"Point"}
}