{
  "type": "Feature",
  "properties": {
    "gn:admin1_code":"70.0",
    "gn:asciiname":"Khe Vau",
    "gn:country_code":"VN",
    "gn:dem":74,
    "gn:feature_class":"P",
    "gn:feature_code":"PPL",
    "gn:name":"Khe V\u1ea7u",
    "gn:population":0,
    "gn:timezone":"Asia/Ho_Chi_Minh",
    "iso:country":"VN",
    "name:vie_x_preferred":[
        "Khe V\u1ea7u"
    ],
    "wof:name":"Khe Vau",
    "wof:placetype":"locality"
},
  "geometry": {"coordinates":[104.71638,21.88943],"type":"Point"}
}