{
  "type": "Feature",
  "properties": {
    "gn:admin1_code":"1.0",
    "gn:asciiname":"An Quoi",
    "gn:country_code":"VN",
    "gn:dem":6,
    "gn:feature_class":"P",
    "gn:feature_code":"PPL",
    "gn:name":"An Q\u01b0\u1edbi",
    "gn:population":0,
    "gn:timezone":"Asia/Ho_Chi_Minh",
    "iso:country":"VN",
    "name:vie_x_preferred":[
        "An Q\u01b0\u1edbi"
    ],
    "wof:name":"An Quoi",
    "wof:placetype":"locality"
},
  "geometry": {"coordinates":[105.47185,10.38421],"type":"Point"}
}