{
  "type": "Feature",
  "properties": {
    "gn:admin1_code":"52.0",
    "gn:asciiname":"Nam Hai",
    "gn:country_code":"VN",
    "gn:dem":7,
    "gn:feature_class":"P",
    "gn:feature_code":"PPL",
    "gn:name":"Nam H\u1ea3i",
    "gn:population":0,
    "gn:timezone":"Asia/Ho_Chi_Minh",
    "iso:country":"VN",
    "name:vie_x_preferred":[
        "Nam H\u1ea3i"
    ],
    "wof:name":"Nam Hai",
    "wof:placetype":"locality"
},
  "geometry": {"coordinates":[105.95668000000001,18.42775],"type":"Point"}
}