{
  "type": "Feature",
  "properties": {
    "gn:admin1_code":"78.0",
    "gn:asciiname":"Da Phuoc",
    "gn:country_code":"VN",
    "gn:dem":14,
    "gn:feature_class":"P",
    "gn:feature_code":"PPL",
    "gn:name":"Da Phuoc",
    "gn:population":0,
    "gn:timezone":"Asia/Ho_Chi_Minh",
    "iso:country":"VN",
    "name:und_x_variant":[
        "\u1ea4p \u0110a Ph\u01b0\u1edbc"
    ],
    "name:vie_x_preferred":[
        "\u0110a Ph\u01b0\u1edbc"
    ],
    "wof:name":"Da Phuoc",
    "wof:placetype":"locality"
},
  "geometry": {"coordinates":[108.1421,16.07155],"type":"Point"}
}