{
  "type": "Feature",
  "properties": {
    "gn:admin1_code":"32.0",
    "gn:asciiname":"Co Mon",
    "gn:country_code":"VN",
    "gn:dem":347,
    "gn:feature_class":"P",
    "gn:feature_code":"PPL",
    "gn:name":"Co Mon",
    "gn:population":0,
    "gn:timezone":"Asia/Ho_Chi_Minh",
    "iso:country":"VN",
    "wof:name":"Co Mon",
    "wof:placetype":"locality"
},
  "geometry": {"coordinates":[103.95,21.58333],"type":"Point"}
}