{
  "type": "Feature",
  "properties": {
    "gn:admin1_code":"58.0",
    "gn:asciiname":"Nhan Mai",
    "gn:country_code":"VN",
    "gn:dem":198,
    "gn:feature_class":"P",
    "gn:feature_code":"PPL",
    "gn:name":"Nh\u1ea1n Mai",
    "gn:population":0,
    "gn:timezone":"Asia/Ho_Chi_Minh",
    "iso:country":"VN",
    "name:vie_x_preferred":[
        "Nh\u1ea1n Mai"
    ],
    "wof:name":"Nhan Mai",
    "wof:placetype":"locality"
},
  "geometry": {"coordinates":[104.51891000000001,19.51463],"type":"Point"}
}