{
  "type": "Feature",
  "properties": {
    "gn:admin1_code":"52.0",
    "gn:asciiname":"Trai Duong",
    "gn:country_code":"VN",
    "gn:dem":6,
    "gn:feature_class":"P",
    "gn:feature_code":"PPL",
    "gn:name":"Tr\u1ea1i D\u01b0\u01a1ng",
    "gn:population":0,
    "gn:timezone":"Asia/Ho_Chi_Minh",
    "iso:country":"VN",
    "name:vie_x_preferred":[
        "Tr\u1ea1i D\u01b0\u01a1ng"
    ],
    "wof:name":"Trai Duong",
    "wof:placetype":"locality"
},
  "geometry": {"coordinates":[105.77016,18.39152],"type":"Point"}
}