{
  "type": "Feature",
  "properties": {
    "gn:admin1_code":"32.0",
    "gn:asciiname":"An Pon",
    "gn:country_code":"VN",
    "gn:dem":1026,
    "gn:feature_class":"P",
    "gn:feature_code":"PPL",
    "gn:name":"An Pon",
    "gn:population":0,
    "gn:timezone":"Asia/Ho_Chi_Minh",
    "iso:country":"VN",
    "wof:name":"An Pon",
    "wof:placetype":"locality"
},
  "geometry": {"coordinates":[104.61667,20.91667],"type":"Point"}
}