{
  "type": "Feature",
  "properties": {
    "gn:admin1_code":"30.0",
    "gn:asciiname":"Van Mai",
    "gn:country_code":"VN",
    "gn:dem":111,
    "gn:feature_class":"P",
    "gn:feature_code":"PPL",
    "gn:name":"Van Mai",
    "gn:population":0,
    "gn:timezone":"Asia/Ho_Chi_Minh",
    "iso:country":"VN",
    "wof:name":"Van Mai",
    "wof:placetype":"locality"
},
  "geometry": {"coordinates":[107.38333,21.41667],"type":"Point"}
}