{
  "type": "Feature",
  "properties": {
    "gn:admin1_code":"84.0",
    "gn:asciiname":"Ca La",
    "gn:country_code":"VN",
    "gn:dem":507,
    "gn:feature_class":"P",
    "gn:feature_code":"PPL",
    "gn:name":"C\u00e0 La",
    "gn:population":0,
    "gn:timezone":"Asia/Ho_Chi_Minh",
    "iso:country":"VN",
    "name:vie_x_preferred":[
        "C\u00e0 La"
    ],
    "wof:name":"Ca La",
    "wof:placetype":"locality"
},
  "geometry": {"coordinates":[107.58851,15.8205],"type":"Point"}
}