{
  "type": "Feature",
  "properties": {
    "gn:admin1_code":"34.0",
    "gn:asciiname":"Ngoc Khe",
    "gn:cc2":"VN",
    "gn:country_code":"VN",
    "gn:dem":33,
    "gn:feature_class":"P",
    "gn:feature_code":"PPL",
    "gn:name":"Ng\u1ecdc Kh\u00ea",
    "gn:population":0,
    "gn:timezone":"Asia/Ho_Chi_Minh",
    "iso:country":"VN",
    "name:und_x_variant":[
        "M\u01b0\u01a1ng Ngon",
        "Ng\u1ecdc Kh\u00ea"
    ],
    "wof:name":"Ngoc Khe",
    "wof:placetype":"locality"
},
  "geometry": {"coordinates":[105.38333,20.08333],"type":"Point"}
}