{
  "type": "Feature",
  "properties": {
    "gn:admin1_code":"89.0",
    "gn:asciiname":"Can Cau",
    "gn:country_code":"VN",
    "gn:dem":1198,
    "gn:feature_class":"P",
    "gn:feature_code":"PPL",
    "gn:name":"C\u0103n C\u00e2u",
    "gn:population":0,
    "gn:timezone":"Asia/Ho_Chi_Minh",
    "iso:country":"VN",
    "name:vie_x_preferred":[
        "C\u0103n C\u00e2u"
    ],
    "wof:name":"Can Cau",
    "wof:placetype":"locality"
},
  "geometry": {"coordinates":[103.496,22.48025],"type":"Point"}
}