{
  "type": "Feature",
  "properties": {
    "gn:admin1_code":"61.0",
    "gn:asciiname":"Doi Mot",
    "gn:country_code":"VN",
    "gn:dem":406,
    "gn:feature_class":"P",
    "gn:feature_code":"PPL",
    "gn:name":"\u0110\u1ed9i M\u1ed9t",
    "gn:population":0,
    "gn:timezone":"Asia/Ho_Chi_Minh",
    "iso:country":"VN",
    "name:vie_x_preferred":[
        "\u0110\u1ed9i M\u1ed9t"
    ],
    "name:vie_x_variant":[
        "\u0110\u1ed9i 1"
    ],
    "wof:name":"Doi Mot",
    "wof:placetype":"locality"
},
  "geometry": {"coordinates":[108.80427,12.94106],"type":"Point"}
}