{
  "type": "Feature",
  "properties": {
    "gn:admin1_code":"62.0",
    "gn:asciiname":"Dong Bang Phuong",
    "gn:country_code":"VN",
    "gn:dem":77,
    "gn:feature_class":"P",
    "gn:feature_code":"PPL",
    "gn:name":"\u0110\u1ed3ng Bang Ph\u01b0\u1eddng",
    "gn:population":0,
    "gn:timezone":"Asia/Ho_Chi_Minh",
    "iso:country":"VN",
    "wof:name":"Dong Bang Phuong",
    "wof:placetype":"locality"
},
  "geometry": {"coordinates":[106.06667,17.86667000000001],"type":"Point"}
}