{
  "type": "Feature",
  "properties": {
    "gn:admin1_code":"58.0",
    "gn:asciiname":"Ke Mung",
    "gn:country_code":"VN",
    "gn:dem":57,
    "gn:feature_class":"P",
    "gn:feature_code":"PPL",
    "gn:name":"K\u1ebb M\u00f9ng",
    "gn:population":0,
    "gn:timezone":"Asia/Ho_Chi_Minh",
    "iso:country":"VN",
    "wof:name":"Ke Mung",
    "wof:placetype":"locality"
},
  "geometry": {"coordinates":[105.28333000000001,19.35],"type":"Point"}
}