{
  "type": "Feature",
  "properties": {
    "gn:admin1_code":"87.0",
    "gn:asciiname":"Ap Tan Thanh",
    "gn:country_code":"VN",
    "gn:dem":3,
    "gn:feature_class":"P",
    "gn:feature_code":"PPL",
    "gn:name":"\u1ea4p T\u00e2n Th\u00e0nh",
    "gn:population":0,
    "gn:timezone":"Asia/Ho_Chi_Minh",
    "iso:country":"VN",
    "name:und_x_variant":[
        "Tan Thanh",
        "\u1ea4p T\u00e2n Th\u00e0nh"
    ],
    "wof:name":"Ap Tan Thanh",
    "wof:placetype":"locality"
},
  "geometry": {"coordinates":[105.56667,10.21667],"type":"Point"}
}