{
  "type": "Feature",
  "properties": {
    "gn:admin1_code":"49.0",
    "gn:asciiname":"Po Plei Jrirang",
    "gn:country_code":"VN",
    "gn:dem":262,
    "gn:feature_class":"P",
    "gn:feature_code":"PPL",
    "gn:name":"P\u01a1 Plei Jrirang",
    "gn:population":0,
    "gn:timezone":"Asia/Ho_Chi_Minh",
    "iso:country":"VN",
    "name:und_x_variant":[
        "Plei Jrirang",
        "P\u01a1lei Jrirang",
        "P\u01a1 Plei Jrirang"
    ],
    "wof:name":"Po Plei Jrirang",
    "wof:placetype":"locality"
},
  "geometry": {"coordinates":[107.64059,14.0116],"type":"Point"}
}