{
  "type": "Feature",
  "properties": {
    "gn:admin1_code":"58.0",
    "gn:asciiname":"Tien Son",
    "gn:country_code":"VN",
    "gn:dem":38,
    "gn:feature_class":"P",
    "gn:feature_code":"PPL",
    "gn:name":"Ti\u00ean S\u01a1n",
    "gn:population":0,
    "gn:timezone":"Asia/Ho_Chi_Minh",
    "iso:country":"VN",
    "name:vie_x_preferred":[
        "Ti\u00ean S\u01a1n"
    ],
    "wof:name":"Tien Son",
    "wof:placetype":"locality"
},
  "geometry": {"coordinates":[105.34437,18.95837],"type":"Point"}
}