{
  "type": "Feature",
  "properties": {
    "gn:admin1_code":"82.0",
    "gn:asciiname":"Lai Dai",
    "gn:country_code":"VN",
    "gn:dem":2,
    "gn:feature_class":"P",
    "gn:feature_code":"PPL",
    "gn:name":"Lai Dai",
    "gn:population":0,
    "gn:timezone":"Asia/Ho_Chi_Minh",
    "iso:country":"VN",
    "name:und_x_variant":[
        "\u0110\u1ea1i L\u1ea1i"
    ],
    "wof:name":"Lai Dai",
    "wof:placetype":"locality"
},
  "geometry": {"coordinates":[106.13333,20.31667],"type":"Point"}
}