{
  "type": "Feature",
  "properties": {
    "gn:admin1_code":"32.0",
    "gn:asciiname":"Cha May",
    "gn:country_code":"VN",
    "gn:dem":1151,
    "gn:feature_class":"P",
    "gn:feature_code":"PPL",
    "gn:name":"Ch\u1ea3 May",
    "gn:population":0,
    "gn:timezone":"Asia/Ho_Chi_Minh",
    "iso:country":"VN",
    "name:vie_x_preferred":[
        "Ch\u1ea3 May"
    ],
    "wof:name":"Cha May",
    "wof:placetype":"locality"
},
  "geometry": {"coordinates":[103.53009,21.34095],"type":"Point"}
}