{
  "type": "Feature",
  "properties": {
    "gn:admin1_code":"61.0",
    "gn:asciiname":"Lac Dien",
    "gn:country_code":"VN",
    "gn:dem":54,
    "gn:feature_class":"P",
    "gn:feature_code":"PPL",
    "gn:name":"L\u1ea1c \u0110i\u1ec1n",
    "gn:population":0,
    "gn:timezone":"Asia/Ho_Chi_Minh",
    "iso:country":"VN",
    "name:und_x_variant":[
        "L\u1ea1c \u0110i\u00ean"
    ],
    "name:vie_x_preferred":[
        "L\u1ea1c \u0110i\u1ec1n"
    ],
    "wof:name":"Lac Dien",
    "wof:placetype":"locality"
},
  "geometry": {"coordinates":[109.10448,12.98546],"type":"Point"}
}