{
  "type": "Feature",
  "properties": {
    "gn:admin1_code":"52.0",
    "gn:asciiname":"Minh Quang",
    "gn:country_code":"VN",
    "gn:dem":23,
    "gn:feature_class":"P",
    "gn:feature_code":"PPL",
    "gn:name":"Minh Quang",
    "gn:population":0,
    "gn:timezone":"Asia/Ho_Chi_Minh",
    "iso:country":"VN",
    "name:vie_x_preferred":[
        "Minh Quang"
    ],
    "wof:name":"Minh Quang",
    "wof:placetype":"locality"
},
  "geometry": {"coordinates":[105.58899,18.41911],"type":"Point"}
}