{
  "type": "Feature",
  "properties": {
    "gn:admin1_code":"33.0",
    "gn:asciiname":"Lai Minh",
    "gn:country_code":"VN",
    "gn:dem":23,
    "gn:feature_class":"P",
    "gn:feature_code":"PPL",
    "gn:name":"L\u00e1i Minh",
    "gn:population":0,
    "gn:timezone":"Asia/Ho_Chi_Minh",
    "iso:country":"VN",
    "wof:name":"Lai Minh",
    "wof:placetype":"locality"
},
  "geometry": {"coordinates":[106.43333,11.51667],"type":"Point"}
}