{
  "type": "Feature",
  "properties": {
    "gn:admin1_code":"63.0",
    "gn:asciiname":"Tam Rao",
    "gn:country_code":"VN",
    "gn:dem":36,
    "gn:feature_class":"P",
    "gn:feature_code":"PPL",
    "gn:name":"Tam Rao",
    "gn:population":0,
    "gn:timezone":"Asia/Ho_Chi_Minh",
    "iso:country":"VN",
    "wof:name":"Tam Rao",
    "wof:placetype":"locality"
},
  "geometry": {"coordinates":[108.59999999999999,15.08333],"type":"Point"}
}