{
  "type": "Feature",
  "properties": {
    "gn:admin1_code":"74.0",
    "gn:asciiname":"Thu Phap",
    "gn:country_code":"VN",
    "gn:dem":4,
    "gn:feature_class":"P",
    "gn:feature_code":"PPL",
    "gn:name":"Th\u1ee7 Ph\u00e1p",
    "gn:population":0,
    "gn:timezone":"Asia/Ho_Chi_Minh",
    "iso:country":"VN",
    "name:vie_x_preferred":[
        "Th\u1ee7 Ph\u00e1p"
    ],
    "wof:name":"Thu Phap",
    "wof:placetype":"locality"
},
  "geometry": {"coordinates":[106.18429999999999,21.03949],"type":"Point"}
}