{
  "type": "Feature",
  "properties": {
    "gn:admin1_code":"88.0",
    "gn:asciiname":"Thon Muoi Tam",
    "gn:country_code":"VN",
    "gn:dem":477,
    "gn:feature_class":"P",
    "gn:feature_code":"PPL",
    "gn:name":"Th\u00f4n M\u01b0\u1eddi T\u00e1m",
    "gn:population":0,
    "gn:timezone":"Asia/Ho_Chi_Minh",
    "iso:country":"VN",
    "name:vie_x_preferred":[
        "Th\u00f4n M\u01b0\u1eddi T\u00e1m"
    ],
    "name:vie_x_variant":[
        "Th\u00f4n 18"
    ],
    "wof:name":"Thon Muoi Tam",
    "wof:placetype":"locality"
},
  "geometry": {"coordinates":[108.21747999999999,12.62443],"type":"Point"}
}