{
  "type": "Feature",
  "properties": {
    "gn:admin1_code":"3.0",
    "gn:asciiname":"Binh Phu",
    "gn:country_code":"VN",
    "gn:dem":1,
    "gn:feature_class":"P",
    "gn:feature_code":"PPL",
    "gn:name":"B\u00ecnh Ph\u00fa",
    "gn:population":0,
    "gn:timezone":"Asia/Ho_Chi_Minh",
    "iso:country":"VN",
    "name:vie_x_preferred":[
        "B\u00ecnh Ph\u00fa"
    ],
    "wof:name":"Binh Phu",
    "wof:placetype":"locality"
},
  "geometry": {"coordinates":[106.53489999999999,10.19571],"type":"Point"}
}