{
  "type": "Feature",
  "properties": {
    "gn:admin1_code":"49.0",
    "gn:asciiname":"Buu Tinh Tu",
    "gn:country_code":"VN",
    "gn:dem":162,
    "gn:feature_class":"P",
    "gn:feature_code":"PPL",
    "gn:name":"B\u01b0u Tinh Tu",
    "gn:population":0,
    "gn:timezone":"Asia/Ho_Chi_Minh",
    "iso:country":"VN",
    "name:vie_x_preferred":[
        "B\u01b0u Tinh Tu"
    ],
    "wof:name":"Buu Tinh Tu",
    "wof:placetype":"locality"
},
  "geometry": {"coordinates":[108.45018,13.39463],"type":"Point"}
}