{
  "type": "Feature",
  "properties": {
    "gn:admin1_code":"49.0",
    "gn:asciiname":"Kannack",
    "gn:country_code":"VN",
    "gn:dem":534,
    "gn:feature_class":"P",
    "gn:feature_code":"PPL",
    "gn:name":"Kannack",
    "gn:population":0,
    "gn:timezone":"Asia/Ho_Chi_Minh",
    "iso:country":"VN",
    "name:und_x_variant":[
        "Kan Nak",
        "Kannack"
    ],
    "wof:name":"Kannack",
    "wof:placetype":"locality"
},
  "geometry": {"coordinates":[108.61667,14.15],"type":"Point"}
}