{
  "type": "Feature",
  "properties": {
    "gn:admin1_code":"58.0",
    "gn:asciiname":"Pa Ca",
    "gn:country_code":"VN",
    "gn:dem":733,
    "gn:feature_class":"P",
    "gn:feature_code":"PPL",
    "gn:name":"Pa Ca",
    "gn:population":0,
    "gn:timezone":"Asia/Ho_Chi_Minh",
    "iso:country":"VN",
    "name:vie_x_preferred":[
        "Pa Ca"
    ],
    "wof:name":"Pa Ca",
    "wof:placetype":"locality"
},
  "geometry": {"coordinates":[104.13566,19.43815],"type":"Point"}
}