{
  "type": "Feature",
  "properties": {
    "gn:admin1_code":"89.0",
    "gn:asciiname":"Can Ho",
    "gn:country_code":"VN",
    "gn:dem":311,
    "gn:feature_class":"P",
    "gn:feature_code":"PPL",
    "gn:name":"Can H\u1ed3",
    "gn:population":0,
    "gn:timezone":"Asia/Ho_Chi_Minh",
    "iso:country":"VN",
    "name:vie_x_preferred":[
        "Can H\u1ed3"
    ],
    "wof:name":"Can Ho",
    "wof:placetype":"locality"
},
  "geometry": {"coordinates":[103.32908,22.35844],"type":"Point"}
}