{
  "type": "Feature",
  "properties": {
    "gn:admin1_code":"6.0",
    "gn:asciiname":"Ap Tan Hung",
    "gn:country_code":"VN",
    "gn:dem":8,
    "gn:feature_class":"P",
    "gn:feature_code":"PPL",
    "gn:name":"\u1ea4p T\u00e2n H\u01b0ng",
    "gn:population":0,
    "gn:timezone":"Asia/Ho_Chi_Minh",
    "iso:country":"VN",
    "name:und_x_variant":[
        "Tan Hung",
        "\u1ea4p T\u00e2n H\u01b0ng"
    ],
    "wof:name":"Ap Tan Hung",
    "wof:placetype":"locality"
},
  "geometry": {"coordinates":[105.71666999999999,10.15],"type":"Point"}
}