{
  "type": "Feature",
  "properties": {
    "gn:admin1_code":"16.0",
    "gn:asciiname":"Ao Kenh",
    "gn:country_code":"VN",
    "gn:dem":47,
    "gn:feature_class":"P",
    "gn:feature_code":"PPL",
    "gn:name":"Ao K\u00eanh",
    "gn:population":0,
    "gn:timezone":"Asia/Ho_Chi_Minh",
    "iso:country":"VN",
    "wof:name":"Ao Kenh",
    "wof:placetype":"locality"
},
  "geometry": {"coordinates":[105.63333,20.78333],"type":"Point"}
}