{
  "type": "Feature",
  "properties": {
    "gn:admin1_code":"68.0",
    "gn:asciiname":"Pac Hop",
    "gn:country_code":"VN",
    "gn:dem":189,
    "gn:feature_class":"P",
    "gn:feature_code":"PPL",
    "gn:name":"P\u00e1c H\u00f3p",
    "gn:population":0,
    "gn:timezone":"Asia/Ho_Chi_Minh",
    "iso:country":"VN",
    "name:vie_x_preferred":[
        "P\u00e1c H\u00f3p"
    ],
    "wof:name":"Pac Hop",
    "wof:placetype":"locality"
},
  "geometry": {"coordinates":[105.45961,22.0364],"type":"Point"}
}