{
  "type": "Feature",
  "properties": {
    "gn:admin1_code":"72.0",
    "gn:asciiname":"Ban Giang",
    "gn:country_code":"VN",
    "gn:dem":522,
    "gn:feature_class":"P",
    "gn:feature_code":"PPL",
    "gn:name":"B\u1ea3n Giang",
    "gn:population":0,
    "gn:timezone":"Asia/Ho_Chi_Minh",
    "iso:country":"VN",
    "name:und_x_variant":[
        "B\u1ea3n Dzian"
    ],
    "name:vie_x_preferred":[
        "B\u1ea3n Giang"
    ],
    "wof:name":"Ban Giang",
    "wof:placetype":"locality"
},
  "geometry": {"coordinates":[106.00991999999999,22.35053],"type":"Point"}
}