{
  "type": "Feature",
  "properties": {
    "gn:admin1_code":"34.0",
    "gn:asciiname":"Ben Sung",
    "gn:country_code":"VN",
    "gn:dem":14,
    "gn:feature_class":"P",
    "gn:feature_code":"PPLA2",
    "gn:name":"B\u1ebfn Sung",
    "gn:population":0,
    "gn:timezone":"Asia/Ho_Chi_Minh",
    "iso:country":"VN",
    "name:und_x_variant":[
        "Pho Beu Sung",
        "Ph\u1ed1 B\u1ebfn Sung"
    ],
    "name:vie_x_preferred":[
        "B\u1ebfn Sung"
    ],
    "wof:name":"Ben Sung",
    "wof:placetype":"locality"
},
  "geometry": {"coordinates":[105.57814999999999,19.63141],"type":"Point"}
}