{
  "type": "Feature",
  "properties": {
    "gn:admin1_code":"59.0",
    "gn:asciiname":"Nguyen Ngoai",
    "gn:country_code":"VN",
    "gn:dem":37,
    "gn:feature_class":"P",
    "gn:feature_code":"PPL",
    "gn:name":"Nguy\u00ean Ngo\u1ea1i",
    "gn:population":0,
    "gn:timezone":"Asia/Ho_Chi_Minh",
    "iso:country":"VN",
    "wof:name":"Nguyen Ngoai",
    "wof:placetype":"locality"
},
  "geometry": {"coordinates":[105.93333,20.26667],"type":"Point"}
}