{
  "type": "Feature",
  "properties": {
    "gn:admin1_code":"73.0",
    "gn:asciiname":"Thi Tran Phuoc Long",
    "gn:country_code":"VN",
    "gn:dem":5,
    "gn:feature_class":"P",
    "gn:feature_code":"PPLA2",
    "gn:name":"Th\u1ecb Tr\u1ea5n Ph\u01b0\u1edbc Long",
    "gn:population":0,
    "gn:timezone":"Asia/Ho_Chi_Minh",
    "iso:country":"VN",
    "name:vie_x_preferred":[
        "Th\u1ecb Tr\u1ea5n Ph\u01b0\u1edbc Long"
    ],
    "wof:name":"Thi Tran Phuoc Long",
    "wof:placetype":"locality"
},
  "geometry": {"coordinates":[105.46217,9.43753],"type":"Point"}
}