{
  "type": "Feature",
  "properties": {
    "gn:admin1_code":"90.0",
    "gn:asciiname":"Ban Nam Cay",
    "gn:country_code":"VN",
    "gn:dem":969,
    "gn:feature_class":"P",
    "gn:feature_code":"PPL",
    "gn:name":"B\u1ea3n N\u1eadm C\u1eady",
    "gn:population":0,
    "gn:timezone":"Asia/Ho_Chi_Minh",
    "iso:country":"VN",
    "name:vie_x_preferred":[
        "B\u1ea3n N\u1eadm C\u1eady"
    ],
    "wof:name":"Ban Nam Cay",
    "wof:placetype":"locality"
},
  "geometry": {"coordinates":[104.4264,22.51749],"type":"Point"}
}