{
  "type": "Feature",
  "properties": {
    "gn:admin1_code":"83.0",
    "gn:asciiname":"Xom Han",
    "gn:country_code":"VN",
    "gn:dem":71,
    "gn:feature_class":"P",
    "gn:feature_code":"PPL",
    "gn:name":"X\u00f3m Han",
    "gn:population":0,
    "gn:timezone":"Asia/Ho_Chi_Minh",
    "iso:country":"VN",
    "name:vie_x_preferred":[
        "X\u00f3m Han"
    ],
    "wof:name":"Xom Han",
    "wof:placetype":"locality"
},
  "geometry": {"coordinates":[105.23171000000001,21.04934],"type":"Point"}
}