{
  "type": "Feature",
  "properties": {
    "gn:admin1_code":"50.0",
    "gn:asciiname":"Ngai Sang",
    "gn:country_code":"VN",
    "gn:dem":402,
    "gn:feature_class":"P",
    "gn:feature_code":"PPL",
    "gn:name":"Ng\u00e0i S\u00e1ng",
    "gn:population":0,
    "gn:timezone":"Asia/Ho_Chi_Minh",
    "iso:country":"VN",
    "name:vie_x_preferred":[
        "Ng\u00e0i S\u00e1ng"
    ],
    "wof:name":"Ngai Sang",
    "wof:placetype":"locality"
},
  "geometry": {"coordinates":[105.24366000000001,22.93845],"type":"Point"}
}