{
  "type": "Feature",
  "properties": {
    "gn:admin1_code":"39.0",
    "gn:asciiname":"Cai Lan",
    "gn:country_code":"VN",
    "gn:dem":124,
    "gn:feature_class":"P",
    "gn:feature_code":"PPL",
    "gn:name":"Cai Lan",
    "gn:population":0,
    "gn:timezone":"Asia/Ho_Chi_Minh",
    "iso:country":"VN",
    "wof:name":"Cai Lan",
    "wof:placetype":"locality"
},
  "geometry": {"coordinates":[107.05,21.41667],"type":"Point"}
}