{
  "type": "Feature",
  "properties": {
    "gn:admin1_code":"74.0",
    "gn:asciiname":"Ngo Xa",
    "gn:country_code":"VN",
    "gn:dem":8,
    "gn:feature_class":"P",
    "gn:feature_code":"PPL",
    "gn:name":"Ng\u00f4 X\u00e1",
    "gn:population":0,
    "gn:timezone":"Asia/Ho_Chi_Minh",
    "iso:country":"VN",
    "name:vie_x_preferred":[
        "Ng\u00f4 X\u00e1"
    ],
    "wof:name":"Ngo Xa",
    "wof:placetype":"locality"
},
  "geometry": {"coordinates":[105.99122,21.19283],"type":"Point"}
}