{
  "type": "Feature",
  "properties": {
    "gn:admin1_code":"44.0",
    "gn:asciiname":"Thuong Thuy",
    "gn:country_code":"VN",
    "gn:dem":3,
    "gn:feature_class":"P",
    "gn:feature_code":"PPL",
    "gn:name":"Th\u01b0\u1ee3ng Th\u1ee5y",
    "gn:population":0,
    "gn:timezone":"Asia/Ho_Chi_Minh",
    "iso:country":"VN",
    "wof:name":"Thuong Thuy",
    "wof:placetype":"locality"
},
  "geometry": {"coordinates":[105.81667,20.83333],"type":"Point"}
}