{
  "type": "Feature",
  "properties": {
    "gn:admin1_code":"72.0",
    "gn:asciiname":"Ban Vay",
    "gn:country_code":"VN",
    "gn:dem":178,
    "gn:feature_class":"P",
    "gn:feature_code":"PPL",
    "gn:name":"B\u1ea3n Vay",
    "gn:population":0,
    "gn:timezone":"Asia/Ho_Chi_Minh",
    "iso:country":"VN",
    "name:vie_x_preferred":[
        "B\u1ea3n Vay"
    ],
    "wof:name":"Ban Vay",
    "wof:placetype":"locality"
},
  "geometry": {"coordinates":[105.66938,22.456],"type":"Point"}
}