{
  "type": "Feature",
  "properties": {
    "gn:admin1_code":"23.0",
    "gn:asciiname":"B'sar",
    "gn:country_code":"VN",
    "gn:dem":266,
    "gn:feature_class":"P",
    "gn:feature_code":"PPL",
    "gn:name":"B\u2019sar",
    "gn:population":0,
    "gn:timezone":"Asia/Ho_Chi_Minh",
    "iso:country":"VN",
    "name:und_x_variant":[
        "Saar",
        "Buon Sar",
        "B\u2019sar"
    ],
    "wof:name":"B'sar",
    "wof:placetype":"locality"
},
  "geometry": {"coordinates":[107.65000000000001,11.38333],"type":"Point"}
}