{
  "type": "Feature",
  "properties": {
    "gn:admin1_code":"5.0",
    "gn:asciiname":"Lang Rai",
    "gn:country_code":"VN",
    "gn:dem":887,
    "gn:feature_class":"P",
    "gn:feature_code":"PPL",
    "gn:name":"L\u00e0ng R\u1ea1i",
    "gn:population":0,
    "gn:timezone":"Asia/Ho_Chi_Minh",
    "iso:country":"VN",
    "wof:name":"Lang Rai",
    "wof:placetype":"locality"
},
  "geometry": {"coordinates":[106.18333,22.93333],"type":"Point"}
}