{
  "type": "Feature",
  "properties": {
    "gn:admin1_code":"83.0",
    "gn:asciiname":"Da Can",
    "gn:country_code":"VN",
    "gn:dem":34,
    "gn:feature_class":"P",
    "gn:feature_code":"PPL",
    "gn:name":"\u0110\u00e1 C\u00e1n",
    "gn:population":0,
    "gn:timezone":"Asia/Ho_Chi_Minh",
    "iso:country":"VN",
    "name:und_x_variant":[
        "X\u00f3m \u0110\u1ea5 Coc"
    ],
    "name:vie_x_preferred":[
        "\u0110\u00e1 C\u00e1n"
    ],
    "wof:name":"Da Can",
    "wof:placetype":"locality"
},
  "geometry": {"coordinates":[105.2504,21.0207],"type":"Point"}
}