{
  "type": "Feature",
  "properties": {
    "gn:admin1_code":"44.0",
    "gn:asciiname":"Mai Hien",
    "gn:country_code":"VN",
    "gn:dem":12,
    "gn:feature_class":"P",
    "gn:feature_code":"PPL",
    "gn:name":"Mai Hi\u1ebfn",
    "gn:population":0,
    "gn:timezone":"Asia/Ho_Chi_Minh",
    "iso:country":"VN",
    "name:vie_x_preferred":[
        "Mai Hi\u1ebfn"
    ],
    "wof:name":"Mai Hien",
    "wof:placetype":"locality"
},
  "geometry": {"coordinates":[105.88728,21.08632],"type":"Point"}
}