{
  "type": "Feature",
  "properties": {
    "gn:admin1_code":"1.0",
    "gn:asciiname":"Ap Vinh Phu",
    "gn:country_code":"VN",
    "gn:dem":2,
    "gn:feature_class":"P",
    "gn:feature_code":"PPL",
    "gn:name":"\u1ea4p V\u0129nh Ph\u00fa",
    "gn:population":0,
    "gn:timezone":"Asia/Ho_Chi_Minh",
    "iso:country":"VN",
    "wof:name":"Ap Vinh Phu",
    "wof:placetype":"locality"
},
  "geometry": {"coordinates":[105.06667,10.68333],"type":"Point"}
}