{
  "type": "Feature",
  "properties": {
    "gn:admin1_code":"63.0",
    "gn:asciiname":"Vingao",
    "gn:country_code":"VN",
    "gn:dem":1015,
    "gn:feature_class":"P",
    "gn:feature_code":"PPL",
    "gn:name":"Vingao",
    "gn:population":0,
    "gn:timezone":"Asia/Ho_Chi_Minh",
    "iso:country":"VN",
    "wof:name":"Vingao",
    "wof:placetype":"locality"
},
  "geometry": {"coordinates":[108.34999999999999,15.05],"type":"Point"}
}