{
  "type": "Feature",
  "properties": {
    "gn:admin1_code":"52.0",
    "gn:asciiname":"Nam Trung",
    "gn:country_code":"VN",
    "gn:dem":7,
    "gn:feature_class":"P",
    "gn:feature_code":"PPL",
    "gn:name":"Nam Trung",
    "gn:population":0,
    "gn:timezone":"Asia/Ho_Chi_Minh",
    "iso:country":"VN",
    "name:vie_x_preferred":[
        "Nam Trung"
    ],
    "wof:name":"Nam Trung",
    "wof:placetype":"locality"
},
  "geometry": {"coordinates":[105.97595,18.27054],"type":"Point"}
}