{
  "type": "Feature",
  "properties": {
    "gn:admin1_code":"50.0",
    "gn:asciiname":"Per Ria",
    "gn:country_code":"VN",
    "gn:dem":961,
    "gn:feature_class":"P",
    "gn:feature_code":"PPL",
    "gn:name":"Per R\u1ecba",
    "gn:population":0,
    "gn:timezone":"Asia/Ho_Chi_Minh",
    "iso:country":"VN",
    "name:vie_x_preferred":[
        "Per R\u1ecba"
    ],
    "wof:name":"Per Ria",
    "wof:placetype":"locality"
},
  "geometry": {"coordinates":[105.28923,22.9321],"type":"Point"}
}