{
  "type": "Feature",
  "properties": {
    "gn:admin1_code":"5.0",
    "gn:asciiname":"Pa Khao",
    "gn:cc2":"VN",
    "gn:country_code":"VN",
    "gn:dem":1245,
    "gn:feature_class":"P",
    "gn:feature_code":"PPL",
    "gn:name":"Pa Khao",
    "gn:population":0,
    "gn:timezone":"Asia/Ho_Chi_Minh",
    "iso:country":"VN",
    "name:und_x_variant":[
        "Pa Khau",
        "Pa Khao"
    ],
    "wof:name":"Pa Khao",
    "wof:placetype":"locality"
},
  "geometry": {"coordinates":[105.84999999999999,22.85],"type":"Point"}
}