{
  "type": "Feature",
  "properties": {
    "gn:admin1_code":"62.0",
    "gn:asciiname":"Tay Gat",
    "gn:country_code":"VN",
    "gn:dem":24,
    "gn:feature_class":"P",
    "gn:feature_code":"PPL",
    "gn:name":"T\u00e2y G\u00e1t",
    "gn:population":0,
    "gn:timezone":"Asia/Ho_Chi_Minh",
    "iso:country":"VN",
    "name:und_x_variant":[
        "Khe Ghat",
        "Khe Phat"
    ],
    "name:vie_x_preferred":[
        "T\u00e2y G\u00e1t"
    ],
    "wof:name":"Tay Gat",
    "wof:placetype":"locality"
},
  "geometry": {"coordinates":[106.22667,17.64906000000001],"type":"Point"}
}