{
  "type": "Feature",
  "properties": {
    "gn:admin1_code":"19.0",
    "gn:asciiname":"Doi Muong",
    "gn:country_code":"VN",
    "gn:dem":701,
    "gn:feature_class":"P",
    "gn:feature_code":"PPL",
    "gn:name":"Doi Muong",
    "gn:population":0,
    "gn:timezone":"Asia/Ho_Chi_Minh",
    "iso:country":"VN",
    "wof:name":"Doi Muong",
    "wof:placetype":"locality"
},
  "geometry": {"coordinates":[104.84999999999999,21.13333],"type":"Point"}
}