{
  "type": "Feature",
  "properties": {
    "gn:admin1_code":"16.0",
    "gn:asciiname":"Thuong Ve",
    "gn:country_code":"VN",
    "gn:dem":8,
    "gn:feature_class":"P",
    "gn:feature_code":"PPL",
    "gn:name":"Th\u01b0\u01a1ng V\u1ec7",
    "gn:population":0,
    "gn:timezone":"Asia/Ho_Chi_Minh",
    "iso:country":"VN",
    "wof:name":"Thuong Ve",
    "wof:placetype":"locality"
},
  "geometry": {"coordinates":[105.68333,20.66667],"type":"Point"}
}