{
  "type": "Feature",
  "properties": {
    "gn:admin1_code":"58.0",
    "gn:asciiname":"Ngoc Long Thuong",
    "gn:country_code":"VN",
    "gn:dem":8,
    "gn:feature_class":"P",
    "gn:feature_code":"PPL",
    "gn:name":"Ng\u1ecdc Long Th\u01b0\u1ee3ng",
    "gn:population":0,
    "gn:timezone":"Asia/Ho_Chi_Minh",
    "iso:country":"VN",
    "wof:name":"Ngoc Long Thuong",
    "wof:placetype":"locality"
},
  "geometry": {"coordinates":[105.43333,18.91667],"type":"Point"}
}