{
  "type": "Feature",
  "properties": {
    "gn:admin1_code":"71.0",
    "gn:asciiname":"Ninh Dong",
    "gn:country_code":"VN",
    "gn:dem":10,
    "gn:feature_class":"P",
    "gn:feature_code":"PPL",
    "gn:name":"Ninh \u0110\u1ed9ng",
    "gn:population":0,
    "gn:timezone":"Asia/Ho_Chi_Minh",
    "iso:country":"VN",
    "name:und_x_variant":[
        "Lang N\u00f4i \u0110\u00f4ng",
        "Ninh \u0110\u1ed9ng"
    ],
    "wof:name":"Ninh Dong",
    "wof:placetype":"locality"
},
  "geometry": {"coordinates":[106.07791,21.24082000000001],"type":"Point"}
}