{
  "type": "Feature",
  "properties": {
    "gn:admin1_code":"90.0",
    "gn:asciiname":"Coc Noc",
    "gn:country_code":"VN",
    "gn:dem":429,
    "gn:feature_class":"P",
    "gn:feature_code":"PPL",
    "gn:name":"Coc Noc",
    "gn:population":0,
    "gn:timezone":"Asia/Ho_Chi_Minh",
    "iso:country":"VN",
    "name:und_x_variant":[
        "Coc Non",
        "Coc No",
        "Coc Noc"
    ],
    "wof:name":"Coc Noc",
    "wof:placetype":"locality"
},
  "geometry": {"coordinates":[104.05,22.61667000000001],"type":"Point"}
}