{
  "type": "Feature",
  "properties": {
    "gn:admin1_code":"53.0",
    "gn:asciiname":"Xom Dinh",
    "gn:country_code":"VN",
    "gn:dem":48,
    "gn:feature_class":"P",
    "gn:feature_code":"PPL",
    "gn:name":"X\u00f3m \u0110inh",
    "gn:population":0,
    "gn:timezone":"Asia/Ho_Chi_Minh",
    "iso:country":"VN",
    "wof:name":"Xom Dinh",
    "wof:placetype":"locality"
},
  "geometry": {"coordinates":[105.33333,20.91667],"type":"Point"}
}