{
  "type": "Feature",
  "properties": {
    "gn:admin1_code":"63.0",
    "gn:asciiname":"Ban Muy",
    "gn:country_code":"VN",
    "gn:dem":75,
    "gn:feature_class":"P",
    "gn:feature_code":"PPL",
    "gn:name":"Ban Muy",
    "gn:population":0,
    "gn:timezone":"Asia/Ho_Chi_Minh",
    "iso:country":"VN",
    "name:und_x_variant":[
        "B. Muy",
        "Ban Muy"
    ],
    "wof:name":"Ban Muy",
    "wof:placetype":"locality"
},
  "geometry": {"coordinates":[108.41667,15.06667],"type":"Point"}
}