{
  "type": "Feature",
  "properties": {
    "gn:admin1_code":"55.0",
    "gn:asciiname":"Ngo Trang",
    "gn:country_code":"VN",
    "gn:dem":533,
    "gn:feature_class":"P",
    "gn:feature_code":"PPL",
    "gn:name":"Ng\u00f4 Trang",
    "gn:population":0,
    "gn:timezone":"Asia/Ho_Chi_Minh",
    "iso:country":"VN",
    "name:und_x_variant":[
        "Kon Trang Ho",
        "Ng\u00f4 Trang"
    ],
    "wof:name":"Ngo Trang",
    "wof:placetype":"locality"
},
  "geometry": {"coordinates":[107.95,14.43333],"type":"Point"}
}