{
  "type": "Feature",
  "properties": {
    "gn:admin1_code":"62.0",
    "gn:asciiname":"Bac Trach",
    "gn:country_code":"VN",
    "gn:dem":38,
    "gn:feature_class":"P",
    "gn:feature_code":"PPL",
    "gn:name":"B\u1eafc Tr\u1ea1ch",
    "gn:population":0,
    "gn:timezone":"Asia/Ho_Chi_Minh",
    "iso:country":"VN",
    "name:vie_x_preferred":[
        "B\u1eafc Tr\u1ea1ch"
    ],
    "wof:name":"Bac Trach",
    "wof:placetype":"locality"
},
  "geometry": {"coordinates":[106.39958,17.60729],"type":"Point"}
}