{
  "type": "Feature",
  "properties": {
    "gn:admin1_code":"61.0",
    "gn:asciiname":"Phong Hau",
    "gn:country_code":"VN",
    "gn:dem":439,
    "gn:feature_class":"P",
    "gn:feature_code":"PPL",
    "gn:name":"Phong H\u1eadu",
    "gn:population":0,
    "gn:timezone":"Asia/Ho_Chi_Minh",
    "iso:country":"VN",
    "name:vie_x_preferred":[
        "Phong H\u1eadu"
    ],
    "wof:name":"Phong Hau",
    "wof:placetype":"locality"
},
  "geometry": {"coordinates":[109.10377,13.19282],"type":"Point"}
}