{
  "type": "Feature",
  "properties": {
    "gn:admin1_code":"62.0",
    "gn:asciiname":"Thanh Lam",
    "gn:country_code":"VN",
    "gn:dem":93,
    "gn:feature_class":"P",
    "gn:feature_code":"PPL",
    "gn:name":"Thanh L\u00e2m",
    "gn:population":0,
    "gn:timezone":"Asia/Ho_Chi_Minh",
    "iso:country":"VN",
    "name:deu_x_preferred":[
        "Thanh Lam"
    ],
    "name:est_x_preferred":[
        "Thanh Lam"
    ],
    "name:fra_x_preferred":[
        "Thanh Lam"
    ],
    "name:jpn_x_preferred":[
        "\u30bf\u30f3\u30fb\u30e9\u30e0"
    ],
    "name:kor_x_preferred":[
        "\ud0c0\uc778\ub78c"
    ],
    "name:spa_x_preferred":[
        "Thanh Lam"
    ],
    "name:vie_x_preferred":[
        "Thanh L\u00e2m"
    ],
    "name:vie_x_variant":[
        "Thanh Lam"
    ],
    "wof:name":"Thanh Lam",
    "wof:placetype":"locality"
},
  "geometry": {"coordinates":[105.82996,17.88424],"type":"Point"}
}