{
  "type": "Feature",
  "properties": {
    "gn:admin1_code":"64.0",
    "gn:asciiname":"Thuy Ban",
    "gn:country_code":"VN",
    "gn:dem":11,
    "gn:feature_class":"P",
    "gn:feature_code":"PPL",
    "gn:name":"Th\u1ee7y Ban",
    "gn:population":0,
    "gn:timezone":"Asia/Ho_Chi_Minh",
    "iso:country":"VN",
    "name:vie_x_preferred":[
        "Th\u1ee7y Ban"
    ],
    "wof:name":"Thuy Ban",
    "wof:placetype":"locality"
},
  "geometry": {"coordinates":[107.11018,17.00254],"type":"Point"}
}