{
  "type": "Feature",
  "properties": {
    "gn:admin1_code":"67.0",
    "gn:asciiname":"Bong Ven",
    "gn:country_code":"VN",
    "gn:dem":3,
    "gn:feature_class":"P",
    "gn:feature_code":"PPL",
    "gn:name":"B\u00f4ng Ven",
    "gn:population":0,
    "gn:timezone":"Asia/Ho_Chi_Minh",
    "iso:country":"VN",
    "name:vie_x_preferred":[
        "B\u00f4ng Ven"
    ],
    "wof:name":"Bong Ven",
    "wof:placetype":"locality"
},
  "geometry": {"coordinates":[106.38684000000001,9.77111],"type":"Point"}
}