{
  "type": "Feature",
  "properties": {
    "gn:admin1_code":"52.0",
    "gn:asciiname":"Xom Tranh",
    "gn:country_code":"VN",
    "gn:dem":61,
    "gn:feature_class":"P",
    "gn:feature_code":"PPL",
    "gn:name":"X\u00f3m Tranh",
    "gn:population":0,
    "gn:timezone":"Asia/Ho_Chi_Minh",
    "iso:country":"VN",
    "wof:name":"Xom Tranh",
    "wof:placetype":"locality"
},
  "geometry": {"coordinates":[106.16667,18.01667],"type":"Point"}
}