{
  "type": "Feature",
  "properties": {
    "gn:admin1_code":"72.0",
    "gn:asciiname":"Ban Phieng",
    "gn:country_code":"VN",
    "gn:dem":174,
    "gn:feature_class":"P",
    "gn:feature_code":"PPL",
    "gn:name":"B\u1ea3n Phi\u1ec1ng",
    "gn:population":0,
    "gn:timezone":"Asia/Ho_Chi_Minh",
    "iso:country":"VN",
    "name:und_x_variant":[
        "B\u1ea3n Phi\u1ec1ng",
        "B\u1ea3n Pien"
    ],
    "wof:name":"Ban Phieng",
    "wof:placetype":"locality"
},
  "geometry": {"coordinates":[105.84779,22.24722],"type":"Point"}
}