{
  "type": "Feature",
  "properties": {
    "gn:admin1_code":"66.0",
    "gn:asciiname":"Loa",
    "gn:country_code":"VN",
    "gn:dem":595,
    "gn:feature_class":"P",
    "gn:feature_code":"PPL",
    "gn:name":"Loa",
    "gn:population":0,
    "gn:timezone":"Asia/Ho_Chi_Minh",
    "iso:country":"VN",
    "name:vie_x_preferred":[
        "Loa"
    ],
    "wof:name":"Loa",
    "wof:placetype":"locality"
},
  "geometry": {"coordinates":[107.32541000000001,16.12061],"type":"Point"}
}