{
  "type": "Feature",
  "properties": {
    "gn:admin1_code":"66.0",
    "gn:asciiname":"Loa",
    "gn:country_code":"VN",
    "gn:dem":595,
    "gn:feature_class":"P",
    "gn:feature_code":"PPL",
    "gn:name":"Loa",
    "gn:population":0,
    "gn:timezone":"Asia/Ho_Chi_Minh",
    "iso:country":"VN",
    "name:ast_x_preferred":[
        "Loa"
    ],
    "name:ces_x_preferred":[
        "Loa"
    ],
    "name:deu_x_preferred":[
        "Loa"
    ],
    "name:fra_x_preferred":[
        "Lwa"
    ],
    "name:fry_x_preferred":[
        "Loa"
    ],
    "name:glg_x_preferred":[
        "Loa"
    ],
    "name:hat_x_preferred":[
        "Lwa"
    ],
    "name:ita_x_preferred":[
        "Loa"
    ],
    "name:pol_x_preferred":[
        "Loa"
    ],
    "name:por_x_preferred":[
        "Loa"
    ],
    "name:rus_x_preferred":[
        "\u041b\u043e\u0430"
    ],
    "name:spa_x_preferred":[
        "Loa"
    ],
    "name:srp_x_preferred":[
        "\u041b\u043e\u0430"
    ],
    "name:vie_x_preferred":[
        "Loa"
    ],
    "wof:name":"Loa",
    "wof:placetype":"locality"
},
  "geometry": {"coordinates":[107.32541000000001,16.12061],"type":"Point"}
}