{
  "type": "Feature",
  "properties": {
    "gn:admin1_code":"44.0",
    "gn:asciiname":"Trong Oai",
    "gn:country_code":"VN",
    "gn:dem":16,
    "gn:feature_class":"P",
    "gn:feature_code":"PPL",
    "gn:name":"Trong Oai",
    "gn:population":0,
    "gn:timezone":"Asia/Ho_Chi_Minh",
    "iso:country":"VN",
    "name:und_x_variant":[
        "Trung Oai"
    ],
    "name:vie_x_preferred":[
        "Trong Oai"
    ],
    "wof:name":"Trong Oai",
    "wof:placetype":"locality"
},
  "geometry": {"coordinates":[105.85863999999999,21.13534],"type":"Point"}
}