{
  "type": "Feature",
  "properties": {
    "gn:admin1_code":"71.0",
    "gn:asciiname":"Che Dong",
    "gn:country_code":"VN",
    "gn:dem":19,
    "gn:feature_class":"P",
    "gn:feature_code":"PPL",
    "gn:name":"Ch\u00e8 \u0110\u00f4ng",
    "gn:population":0,
    "gn:timezone":"Asia/Ho_Chi_Minh",
    "iso:country":"VN",
    "name:vie_x_preferred":[
        "Ch\u00e8 \u0110\u00f4ng"
    ],
    "wof:name":"Che Dong",
    "wof:placetype":"locality"
},
  "geometry": {"coordinates":[106.17100000000001,21.44354],"type":"Point"}
}