{
  "type": "Feature",
  "properties": {
    "gn:admin1_code":"39.0",
    "gn:asciiname":"Ta Pang",
    "gn:country_code":"VN",
    "gn:dem":201,
    "gn:feature_class":"P",
    "gn:feature_code":"PPL",
    "gn:name":"T\u00e0 P\u1ea3ng",
    "gn:population":0,
    "gn:timezone":"Asia/Ho_Chi_Minh",
    "iso:country":"VN",
    "wof:name":"Ta Pang",
    "wof:placetype":"locality"
},
  "geometry": {"coordinates":[106.55262,22.03147],"type":"Point"}
}