{
  "type": "Feature",
  "properties": {
    "gn:admin1_code":"58.0",
    "gn:asciiname":"Quy Chau",
    "gn:country_code":"VN",
    "gn:dem":95,
    "gn:feature_class":"P",
    "gn:feature_code":"PPLA2",
    "gn:name":"Qu\u1ef3 Ch\u00e2u",
    "gn:population":0,
    "gn:timezone":"Asia/Ho_Chi_Minh",
    "iso:country":"VN",
    "name:und_x_variant":[
        "Ke Bon",
        "Phu Qui Chau",
        "Q\u00f9y Chau",
        "Qu\u1ef3 Ch\u00e2u",
        "Qu\u00ed Ch\u00e2u"
    ],
    "wof:name":"Quy Chau",
    "wof:placetype":"locality"
},
  "geometry": {"coordinates":[105.09387,19.55206],"type":"Point"}
}