{
  "type": "Feature",
  "properties": {
    "gn:admin1_code":"71.0",
    "gn:asciiname":"Xom Dan",
    "gn:country_code":"VN",
    "gn:dem":116,
    "gn:feature_class":"P",
    "gn:feature_code":"PPL",
    "gn:name":"X\u00f3m D\u1ea7n",
    "gn:population":0,
    "gn:timezone":"Asia/Ho_Chi_Minh",
    "iso:country":"VN",
    "name:und_x_variant":[
        "L\u00e0ng D\u00e2n"
    ],
    "name:vie_x_preferred":[
        "X\u00f3m D\u1ea7n"
    ],
    "wof:name":"Xom Dan",
    "wof:placetype":"locality"
},
  "geometry": {"coordinates":[106.9456,21.3965],"type":"Point"}
}