{
  "type": "Feature",
  "properties": {
    "gn:admin1_code":"74.0",
    "gn:asciiname":"Ty Thanh",
    "gn:country_code":"VN",
    "gn:dem":6,
    "gn:feature_class":"P",
    "gn:feature_code":"PPL",
    "gn:name":"T\u1ef3 Thanh",
    "gn:population":0,
    "gn:timezone":"Asia/Ho_Chi_Minh",
    "iso:country":"VN",
    "name:vie_x_preferred":[
        "T\u1ef3 Thanh"
    ],
    "wof:name":"Ty Thanh",
    "wof:placetype":"locality"
},
  "geometry": {"coordinates":[106.24337,21.04782],"type":"Point"}
}