{
  "type": "Feature",
  "properties": {
    "gn:admin1_code":"71.0",
    "gn:asciiname":"Hoang Long",
    "gn:country_code":"VN",
    "gn:dem":27,
    "gn:feature_class":"P",
    "gn:feature_code":"PPL",
    "gn:name":"Ho\u00e0ng Long",
    "gn:population":0,
    "gn:timezone":"Asia/Ho_Chi_Minh",
    "iso:country":"VN",
    "name:vie_x_preferred":[
        "Ho\u00e0ng Long"
    ],
    "wof:name":"Hoang Long",
    "wof:placetype":"locality"
},
  "geometry": {"coordinates":[106.1099,21.45878],"type":"Point"}
}