{
  "type": "Feature",
  "properties": {
    "gn:admin1_code":"77.0",
    "gn:asciiname":"Ap Bao Cha",
    "gn:country_code":"VN",
    "gn:dem":3,
    "gn:feature_class":"P",
    "gn:feature_code":"PPL",
    "gn:name":"\u1ea4p B\u00e0o Ch\u00e0",
    "gn:population":0,
    "gn:timezone":"Asia/Ho_Chi_Minh",
    "iso:country":"VN",
    "wof:name":"Ap Bao Cha",
    "wof:placetype":"locality"
},
  "geometry": {"coordinates":[105.19056,9.32528],"type":"Point"}
}