{
  "type": "Feature",
  "properties": {
    "gn:admin1_code":"88.0",
    "gn:asciiname":"Khoi Pho Ba",
    "gn:country_code":"VN",
    "gn:dem":477,
    "gn:feature_class":"P",
    "gn:feature_code":"PPL",
    "gn:name":"Kh\u1ed1i Ph\u1ed1 Ba",
    "gn:population":0,
    "gn:timezone":"Asia/Ho_Chi_Minh",
    "iso:country":"VN",
    "name:vie_x_preferred":[
        "Kh\u1ed1i Ph\u1ed1 Ba"
    ],
    "name:vie_x_variant":[
        "Kh\u1ed1i Ph\u1ed1 3"
    ],
    "wof:name":"Khoi Pho Ba",
    "wof:placetype":"locality"
},
  "geometry": {"coordinates":[108.4567,12.81067],"type":"Point"}
}