{
  "type": "Feature",
  "properties": {
    "gn:admin1_code":"21.0",
    "gn:asciiname":"Xom Ta Loc",
    "gn:country_code":"VN",
    "gn:dem":11,
    "gn:feature_class":"P",
    "gn:feature_code":"PPL",
    "gn:name":"X\u00f3m T\u00e0 L\u00f3c",
    "gn:population":0,
    "gn:timezone":"Asia/Ho_Chi_Minh",
    "iso:country":"VN",
    "wof:name":"Xom Ta Loc",
    "wof:placetype":"locality"
},
  "geometry": {"coordinates":[104.98333,10.15],"type":"Point"}
}