{
  "type": "Feature",
  "properties": {
    "gn:admin1_code":"39.0",
    "gn:asciiname":"Na Pung",
    "gn:country_code":"VN",
    "gn:dem":307,
    "gn:feature_class":"P",
    "gn:feature_code":"PPL",
    "gn:name":"N\u00e0 P\u00f9ng",
    "gn:population":0,
    "gn:timezone":"Asia/Ho_Chi_Minh",
    "iso:country":"VN",
    "name:vie_x_preferred":[
        "N\u00e0 P\u00f9ng"
    ],
    "wof:name":"Na Pung",
    "wof:placetype":"locality"
},
  "geometry": {"coordinates":[106.46256,21.90843],"type":"Point"}
}