{
  "type": "Feature",
  "properties": {
    "gn:admin1_code":"65.0",
    "gn:asciiname":"Xom Lung Can Tho",
    "gn:country_code":"VN",
    "gn:dem":1,
    "gn:feature_class":"P",
    "gn:feature_code":"PPL",
    "gn:name":"X\u00f3m Lung C\u1ea7n Th\u01a1",
    "gn:population":0,
    "gn:timezone":"Asia/Ho_Chi_Minh",
    "iso:country":"VN",
    "wof:name":"Xom Lung Can Tho",
    "wof:placetype":"locality"
},
  "geometry": {"coordinates":[105.65917,9.59361],"type":"Point"}
}