{
  "type": "Feature",
  "properties": {
    "gn:admin1_code":"34.0",
    "gn:asciiname":"Lang Pak Pang",
    "gn:country_code":"VN",
    "gn:dem":56,
    "gn:feature_class":"P",
    "gn:feature_code":"PPL",
    "gn:name":"L\u00e0ng Pak Pang",
    "gn:population":0,
    "gn:timezone":"Asia/Ho_Chi_Minh",
    "iso:country":"VN",
    "wof:name":"Lang Pak Pang",
    "wof:placetype":"locality"
},
  "geometry": {"coordinates":[105.26667,19.95],"type":"Point"}
}