{
  "type": "Feature",
  "properties": {
    "gn:admin1_code":"37.0",
    "gn:asciiname":"Binh Tho Dong",
    "gn:country_code":"VN",
    "gn:dem":4,
    "gn:feature_class":"P",
    "gn:feature_code":"PPL",
    "gn:name":"B\u00ecnh Th\u1ecd \u0110\u00f4ng",
    "gn:population":0,
    "gn:timezone":"Asia/Ho_Chi_Minh",
    "iso:country":"VN",
    "name:vie_x_preferred":[
        "B\u00ecnh Th\u1ecd \u0110\u00f4ng"
    ],
    "wof:name":"Binh Tho Dong",
    "wof:placetype":"locality"
},
  "geometry": {"coordinates":[106.48712999999999,10.35432],"type":"Point"}
}