{
  "type": "Feature",
  "properties": {
    "gn:admin1_code":"32.0",
    "gn:asciiname":"Ban Hiem",
    "gn:country_code":"VN",
    "gn:dem":410,
    "gn:feature_class":"P",
    "gn:feature_code":"PPL",
    "gn:name":"B\u1ea3n Hi\u00eam",
    "gn:population":0,
    "gn:timezone":"Asia/Ho_Chi_Minh",
    "iso:country":"VN",
    "wof:name":"Ban Hiem",
    "wof:placetype":"locality"
},
  "geometry": {"coordinates":[104.38333,21.08333],"type":"Point"}
}