{
  "type": "Feature",
  "properties": {
    "gn:admin1_code":"76.0",
    "gn:asciiname":"Vi Thien",
    "gn:country_code":"VN",
    "gn:dem":408,
    "gn:feature_class":"P",
    "gn:feature_code":"PPL",
    "gn:name":"V\u1ecb Thi\u1ec7n",
    "gn:population":0,
    "gn:timezone":"Asia/Ho_Chi_Minh",
    "iso:country":"VN",
    "name:vie_x_preferred":[
        "V\u1ecb Thi\u1ec7n"
    ],
    "wof:name":"Vi Thien",
    "wof:placetype":"locality"
},
  "geometry": {"coordinates":[107.3031,11.8662],"type":"Point"}
}