{
  "type": "Feature",
  "properties": {
    "gn:admin1_code":"58.0",
    "gn:asciiname":"Ban Cha Coong",
    "gn:country_code":"VN",
    "gn:dem":154,
    "gn:feature_class":"P",
    "gn:feature_code":"PPL",
    "gn:name":"B\u1ea3n Ch\u00e0 Coong",
    "gn:population":0,
    "gn:timezone":"Asia/Ho_Chi_Minh",
    "iso:country":"VN",
    "name:vie_x_preferred":[
        "Ch\u00e0 Coong"
    ],
    "name:vie_x_variant":[
        "B\u1ea3n Ch\u00e0 Coong"
    ],
    "wof:name":"Ban Cha Coong",
    "wof:placetype":"locality"
},
  "geometry": {"coordinates":[104.59062,19.51995],"type":"Point"}
}