{
  "type": "Feature",
  "properties": {
    "gn:admin1_code":"39.0",
    "gn:asciiname":"Na Nhi",
    "gn:country_code":"VN",
    "gn:dem":365,
    "gn:feature_class":"P",
    "gn:feature_code":"PPL",
    "gn:name":"Na Nh\u00ec",
    "gn:population":0,
    "gn:timezone":"Asia/Ho_Chi_Minh",
    "iso:country":"VN",
    "wof:name":"Na Nhi",
    "wof:placetype":"locality"
},
  "geometry": {"coordinates":[106.26667,21.81667],"type":"Point"}
}