{
  "type": "Feature",
  "properties": {
    "gn:admin1_code":"39.0",
    "gn:asciiname":"Khon Quan",
    "gn:country_code":"VN",
    "gn:dem":467,
    "gn:feature_class":"P",
    "gn:feature_code":"PPL",
    "gn:name":"Khon Quan",
    "gn:population":0,
    "gn:timezone":"Asia/Ho_Chi_Minh",
    "iso:country":"VN",
    "wof:name":"Khon Quan",
    "wof:placetype":"locality"
},
  "geometry": {"coordinates":[107.06667,21.63333],"type":"Point"}
}