{
  "type": "Feature",
  "properties": {
    "gn:admin1_code":"39.0",
    "gn:asciiname":"Na Khoan",
    "gn:country_code":"VN",
    "gn:dem":268,
    "gn:feature_class":"P",
    "gn:feature_code":"PPL",
    "gn:name":"N\u00e0 Kho\u1ea3n",
    "gn:population":0,
    "gn:timezone":"Asia/Ho_Chi_Minh",
    "iso:country":"VN",
    "name:vie_x_preferred":[
        "N\u00e0 Kho\u1ea3n"
    ],
    "wof:name":"Na Khoan",
    "wof:placetype":"locality"
},
  "geometry": {"coordinates":[106.49039,21.89119],"type":"Point"}
}