{
  "type": "Feature",
  "properties": {
    "gn:admin1_code":"43.0",
    "gn:asciiname":"Song Thao",
    "gn:country_code":"VN",
    "gn:dem":92,
    "gn:feature_class":"P",
    "gn:feature_code":"PPL",
    "gn:name":"S\u00f4ng Thao",
    "gn:population":0,
    "gn:timezone":"Asia/Ho_Chi_Minh",
    "iso:country":"VN",
    "name:vie_x_preferred":[
        "S\u00f4ng Thao"
    ],
    "wof:name":"Song Thao",
    "wof:placetype":"locality"
},
  "geometry": {"coordinates":[107.09352,10.96588],"type":"Point"}
}