{
  "type": "Feature",
  "properties": {
    "gn:admin1_code":"64.0",
    "gn:asciiname":"Hai Lang",
    "gn:country_code":"VN",
    "gn:dem":11,
    "gn:feature_class":"P",
    "gn:feature_code":"PPLA2",
    "gn:name":"H\u1ea3i L\u0103ng",
    "gn:population":0,
    "gn:timezone":"Asia/Ho_Chi_Minh",
    "iso:country":"VN",
    "name:und_x_variant":[
        "Th\u00f4n Di\u00ean Sanh",
        "H\u1ea3i L\u0103ng"
    ],
    "wof:name":"Hai Lang",
    "wof:placetype":"locality"
},
  "geometry": {"coordinates":[107.25124,16.69347],"type":"Point"}
}