{
  "type": "Feature",
  "properties": {
    "gn:admin1_code":"58.0",
    "gn:asciiname":"Ban Huoi Ca Noi",
    "gn:country_code":"VN",
    "gn:dem":1926,
    "gn:feature_class":"P",
    "gn:feature_code":"PPL",
    "gn:name":"B\u1ea3n Hu\u00f4i Ca Noi",
    "gn:population":0,
    "gn:timezone":"Asia/Ho_Chi_Minh",
    "iso:country":"VN",
    "name:und_x_variant":[
        "Ban Houei Ca Noi",
        "B\u1ea3n Hu\u00f4i Ca Noi"
    ],
    "wof:name":"Ban Huoi Ca Noi",
    "wof:placetype":"locality"
},
  "geometry": {"coordinates":[104.18333,19.21667],"type":"Point"}
}