{
  "type": "Feature",
  "properties": {
    "gn:admin1_code":"90.0",
    "gn:asciiname":"Nam Bo Boun",
    "gn:country_code":"VN",
    "gn:dem":579,
    "gn:feature_class":"P",
    "gn:feature_code":"PPL",
    "gn:name":"Nam Bo Boun",
    "gn:population":0,
    "gn:timezone":"Asia/Ho_Chi_Minh",
    "iso:country":"VN",
    "wof:name":"Nam Bo Boun",
    "wof:placetype":"locality"
},
  "geometry": {"coordinates":[104.15000000000001,22.76667],"type":"Point"}
}