{
  "type": "Feature",
  "properties": {
    "gn:admin1_code":"55.0",
    "gn:asciiname":"Dak Tram",
    "gn:country_code":"VN",
    "gn:dem":753,
    "gn:feature_class":"P",
    "gn:feature_code":"PPL",
    "gn:name":"\u0110\u1eafk Tram",
    "gn:population":0,
    "gn:timezone":"Asia/Ho_Chi_Minh",
    "iso:country":"VN",
    "name:vie_x_preferred":[
        "\u0110\u1eafk Tram"
    ],
    "wof:name":"Dak Tram",
    "wof:placetype":"locality"
},
  "geometry": {"coordinates":[107.86199000000001,14.77413],"type":"Point"}
}