{
  "type": "Feature",
  "properties": {
    "gn:admin1_code":"50.0",
    "gn:asciiname":"Giang Chu",
    "gn:country_code":"VN",
    "gn:dem":897,
    "gn:feature_class":"P",
    "gn:feature_code":"PPL",
    "gn:name":"Gi\u00e0ng Ch\u00f9",
    "gn:population":0,
    "gn:timezone":"Asia/Ho_Chi_Minh",
    "iso:country":"VN",
    "name:vie_x_preferred":[
        "Gi\u00e0ng Ch\u00f9"
    ],
    "wof:name":"Giang Chu",
    "wof:placetype":"locality"
},
  "geometry": {"coordinates":[105.16871,22.96017],"type":"Point"}
}