{
  "type": "Feature",
  "properties": {
    "gn:admin1_code":"61.0",
    "gn:asciiname":"Buon Ba",
    "gn:country_code":"VN",
    "gn:dem":114,
    "gn:feature_class":"P",
    "gn:feature_code":"PPL",
    "gn:name":"Bu\u00f4n B\u00e1",
    "gn:population":0,
    "gn:timezone":"Asia/Ho_Chi_Minh",
    "iso:country":"VN",
    "name:und_x_variant":[
        "Ban Bal",
        "Ban Ba"
    ],
    "name:vie_x_preferred":[
        "Bu\u00f4n B\u00e1"
    ],
    "wof:name":"Buon Ba",
    "wof:placetype":"locality"
},
  "geometry": {"coordinates":[108.83956000000001,13.02835],"type":"Point"}
}