{
  "type": "Feature",
  "properties": {
    "gn:admin1_code":"9.0",
    "gn:asciiname":"Tan Quoi",
    "gn:country_code":"VN",
    "gn:dem":6,
    "gn:feature_class":"P",
    "gn:feature_code":"PPL",
    "gn:name":"Tan Quoi",
    "gn:population":0,
    "gn:timezone":"Asia/Ho_Chi_Minh",
    "iso:country":"VN",
    "name:vie_x_preferred":[
        "Tan Quoi"
    ],
    "wof:name":"Tan Quoi",
    "wof:placetype":"locality"
},
  "geometry": {"coordinates":[105.3506,10.63665],"type":"Point"}
}