{
  "type": "Feature",
  "properties": {
    "gn:admin1_code":"32.0",
    "gn:asciiname":"Ban Han",
    "gn:country_code":"VN",
    "gn:dem":693,
    "gn:feature_class":"P",
    "gn:feature_code":"PPL",
    "gn:name":"B\u1ea3n H\u1ea3n",
    "gn:population":0,
    "gn:timezone":"Asia/Ho_Chi_Minh",
    "iso:country":"VN",
    "name:vie_x_preferred":[
        "B\u1ea3n H\u1ea3n"
    ],
    "wof:name":"Ban Han",
    "wof:placetype":"locality"
},
  "geometry": {"coordinates":[104.00512999999999,21.22161],"type":"Point"}
}