{
  "type": "Feature",
  "properties": {
    "gn:admin1_code":"67.0",
    "gn:asciiname":"Ap Tram",
    "gn:cc2":"VN",
    "gn:country_code":"VN",
    "gn:dem":1,
    "gn:feature_class":"P",
    "gn:feature_code":"PPL",
    "gn:name":"\u1ea4p Tr\u1ea1m",
    "gn:population":0,
    "gn:timezone":"Asia/Ho_Chi_Minh",
    "iso:country":"VN",
    "name:und_x_variant":[
        "Tr\u1ea1m",
        "\u1ea4p Tr\u1ea1m"
    ],
    "wof:name":"Ap Tram",
    "wof:placetype":"locality"
},
  "geometry": {"coordinates":[106.32056,9.76306],"type":"Point"}
}