{
  "type": "Feature",
  "properties": {
    "gn:admin1_code":"62.0",
    "gn:asciiname":"Xom Duong Quan",
    "gn:country_code":"VN",
    "gn:dem":119,
    "gn:feature_class":"P",
    "gn:feature_code":"PPL",
    "gn:name":"X\u00f3m D\u01b0\u1eddng Quan",
    "gn:population":0,
    "gn:timezone":"Asia/Ho_Chi_Minh",
    "iso:country":"VN",
    "wof:name":"Xom Duong Quan",
    "wof:placetype":"locality"
},
  "geometry": {"coordinates":[105.83333,17.86667000000001],"type":"Point"}
}