{
  "type": "Feature",
  "properties": {
    "gn:admin1_code":"84.0",
    "gn:asciiname":"Nuoc Kiet",
    "gn:country_code":"VN",
    "gn:dem":249,
    "gn:feature_class":"P",
    "gn:feature_code":"PPL",
    "gn:name":"N\u01b0\u1edbc Ki\u1ebft",
    "gn:population":0,
    "gn:timezone":"Asia/Ho_Chi_Minh",
    "iso:country":"VN",
    "name:vie_x_preferred":[
        "N\u01b0\u1edbc Ki\u1ebft"
    ],
    "wof:name":"Nuoc Kiet",
    "wof:placetype":"locality"
},
  "geometry": {"coordinates":[107.85317000000001,15.35782],"type":"Point"}
}