{
  "type": "Feature",
  "properties": {
    "gn:admin1_code":"90.0",
    "gn:asciiname":"Xom Mot A",
    "gn:country_code":"VN",
    "gn:dem":1491,
    "gn:feature_class":"P",
    "gn:feature_code":"PPL",
    "gn:name":"X\u00f3m M\u1ed9t A",
    "gn:population":0,
    "gn:timezone":"Asia/Ho_Chi_Minh",
    "iso:country":"VN",
    "name:vie_x_preferred":[
        "X\u00f3m M\u1ed9t A"
    ],
    "name:vie_x_variant":[
        "X\u00f3m 1A"
    ],
    "wof:name":"Xom Mot A",
    "wof:placetype":"locality"
},
  "geometry": {"coordinates":[103.85702000000001,22.34285],"type":"Point"}
}