{
  "type": "Feature",
  "properties": {
    "gn:admin1_code":"90.0",
    "gn:asciiname":"Dong Ho",
    "gn:country_code":"VN",
    "gn:dem":153,
    "gn:feature_class":"P",
    "gn:feature_code":"PPL",
    "gn:name":"\u0110\u1ed3ng H\u1ed3",
    "gn:population":0,
    "gn:timezone":"Asia/Ho_Chi_Minh",
    "iso:country":"VN",
    "name:und_x_variant":[
        "D\u1ed3ng H\u1ed3"
    ],
    "name:vie_x_preferred":[
        "\u0110\u1ed3ng H\u1ed3"
    ],
    "wof:name":"Dong Ho",
    "wof:placetype":"locality"
},
  "geometry": {"coordinates":[103.98598,22.43138],"type":"Point"}
}