{
  "type": "Feature",
  "properties": {
    "gn:admin1_code":"5.0",
    "gn:asciiname":"Lung Don",
    "gn:country_code":"VN",
    "gn:dem":382,
    "gn:feature_class":"P",
    "gn:feature_code":"PPL",
    "gn:name":"L\u0169ng \u0110\u1ed1n",
    "gn:population":0,
    "gn:timezone":"Asia/Ho_Chi_Minh",
    "iso:country":"VN",
    "wof:name":"Lung Don",
    "wof:placetype":"locality"
},
  "geometry": {"coordinates":[106.66667,22.68333],"type":"Point"}
}