{
  "type": "Feature",
  "properties": {
    "gn:admin1_code":"68.0",
    "gn:asciiname":"Kim Trang",
    "gn:country_code":"VN",
    "gn:dem":76,
    "gn:feature_class":"P",
    "gn:feature_code":"PPL",
    "gn:name":"Kim Tr\u0103ng",
    "gn:population":0,
    "gn:timezone":"Asia/Ho_Chi_Minh",
    "iso:country":"VN",
    "name:vie_x_preferred":[
        "Kim Tr\u0103ng"
    ],
    "wof:name":"Kim Trang",
    "wof:placetype":"locality"
},
  "geometry": {"coordinates":[105.28524,21.9668],"type":"Point"}
}