{
  "type": "Feature",
  "properties": {
    "gn:admin1_code":"58.0",
    "gn:asciiname":"Minh Triet",
    "gn:country_code":"VN",
    "gn:dem":12,
    "gn:feature_class":"P",
    "gn:feature_code":"PPL",
    "gn:name":"Minh Tri\u1ebft",
    "gn:population":0,
    "gn:timezone":"Asia/Ho_Chi_Minh",
    "iso:country":"VN",
    "name:und_x_variant":[
        "Xom Minh Triet",
        "Minh Chiet",
        "Minh Tri\u1ebft"
    ],
    "wof:name":"Minh Triet",
    "wof:placetype":"locality"
},
  "geometry": {"coordinates":[105.34999999999999,18.75],"type":"Point"}
}