{
  "type": "Feature",
  "properties": {
    "gn:admin1_code":"72.0",
    "gn:asciiname":"Kouei Fan",
    "gn:country_code":"VN",
    "gn:dem":457,
    "gn:feature_class":"P",
    "gn:feature_code":"PPL",
    "gn:name":"Kouei Fan",
    "gn:population":0,
    "gn:timezone":"Asia/Ho_Chi_Minh",
    "iso:country":"VN",
    "name:und_x_variant":[
        "Kuoi Pa",
        "Koue Fan",
        "Kouei Fan"
    ],
    "wof:name":"Kouei Fan",
    "wof:placetype":"locality"
},
  "geometry": {"coordinates":[106.16667,22.15],"type":"Point"}
}