{
  "type": "Feature",
  "properties": {
    "gn:admin1_code":"90.0",
    "gn:asciiname":"Ban Kooc",
    "gn:country_code":"VN",
    "gn:dem":355,
    "gn:feature_class":"P",
    "gn:feature_code":"PPL",
    "gn:name":"B\u1ea3n Ko\u1ecdc",
    "gn:population":0,
    "gn:timezone":"Asia/Ho_Chi_Minh",
    "iso:country":"VN",
    "name:vie_x_preferred":[
        "B\u1ea3n Ko\u1ecdc"
    ],
    "wof:name":"Ban Kooc",
    "wof:placetype":"locality"
},
  "geometry": {"coordinates":[104.2372,22.43035],"type":"Point"}
}