{
  "type": "Feature",
  "properties": {
    "gn:admin1_code":"64.0",
    "gn:asciiname":"Lang Vuc Tang",
    "gn:country_code":"VN",
    "gn:dem":209,
    "gn:feature_class":"P",
    "gn:feature_code":"PPL",
    "gn:name":"L\u00e0ng Vuc Tang",
    "gn:population":0,
    "gn:timezone":"Asia/Ho_Chi_Minh",
    "iso:country":"VN",
    "wof:name":"Lang Vuc Tang",
    "wof:placetype":"locality"
},
  "geometry": {"coordinates":[106.66667,16.56667],"type":"Point"}
}