{
  "type": "Feature",
  "properties": {
    "gn:admin1_code":"39.0",
    "gn:asciiname":"Lan Lin",
    "gn:country_code":"VN",
    "gn:dem":478,
    "gn:feature_class":"P",
    "gn:feature_code":"PPL",
    "gn:name":"L\u00e2n L\u00ecn",
    "gn:population":0,
    "gn:timezone":"Asia/Ho_Chi_Minh",
    "iso:country":"VN",
    "name:vie_x_preferred":[
        "L\u00e2n L\u00ecn"
    ],
    "wof:name":"Lan Lin",
    "wof:placetype":"locality"
},
  "geometry": {"coordinates":[106.38081,21.88595],"type":"Point"}
}