{
  "type": "Feature",
  "properties": {
    "gn:admin1_code":"21.0",
    "gn:asciiname":"Xom Tien My",
    "gn:cc2":"VN",
    "gn:country_code":"VN",
    "gn:dem":3,
    "gn:feature_class":"P",
    "gn:feature_code":"PPL",
    "gn:name":"X\u00f3m Ti\u1ebfn M\u1ef9",
    "gn:population":0,
    "gn:timezone":"Asia/Ho_Chi_Minh",
    "iso:country":"VN",
    "name:und_x_variant":[
        "Ap Tien My",
        "X\u00f3m Ti\u1ebfn M\u1ef9"
    ],
    "wof:name":"Xom Tien My",
    "wof:placetype":"locality"
},
  "geometry": {"coordinates":[104.56667,10.45],"type":"Point"}
}