{
  "type": "Feature",
  "properties": {
    "gn:admin1_code":"88.0",
    "gn:asciiname":"Ea Puor",
    "gn:country_code":"VN",
    "gn:dem":569,
    "gn:feature_class":"P",
    "gn:feature_code":"PPL",
    "gn:name":"Ea Puor",
    "gn:population":0,
    "gn:timezone":"Asia/Ho_Chi_Minh",
    "iso:country":"VN",
    "name:vie_x_preferred":[
        "Ea Puor"
    ],
    "wof:name":"Ea Puor",
    "wof:placetype":"locality"
},
  "geometry": {"coordinates":[108.16029,12.68656],"type":"Point"}
}