{
  "type": "Feature",
  "properties": {
    "gn:admin1_code":"68.0",
    "gn:asciiname":"Soi Dien",
    "gn:country_code":"VN",
    "gn:dem":36,
    "gn:feature_class":"P",
    "gn:feature_code":"PPL",
    "gn:name":"Soi Di\u1ec7n",
    "gn:population":0,
    "gn:timezone":"Asia/Ho_Chi_Minh",
    "iso:country":"VN",
    "name:vie_x_preferred":[
        "Soi Di\u1ec7n"
    ],
    "wof:name":"Soi Dien",
    "wof:placetype":"locality"
},
  "geometry": {"coordinates":[105.10717,22.04273],"type":"Point"}
}