{
  "type": "Feature",
  "properties": {
    "gn:admin1_code":"88.0",
    "gn:asciiname":"Buon Lieng Mot",
    "gn:country_code":"VN",
    "gn:dem":419,
    "gn:feature_class":"P",
    "gn:feature_code":"PPL",
    "gn:name":"Bu\u00f4n Li\u00eang M\u1ed9t",
    "gn:population":0,
    "gn:timezone":"Asia/Ho_Chi_Minh",
    "iso:country":"VN",
    "name:und_x_variant":[
        "Ban M\u2019Lieng",
        "Bu\u00f4n M\u2019li\u00eang"
    ],
    "name:vie_x_preferred":[
        "Bu\u00f4n Li\u00eang M\u1ed9t"
    ],
    "name:vie_x_variant":[
        "Bu\u00f4n Li\u00eang 1"
    ],
    "wof:name":"Buon Lieng Mot",
    "wof:placetype":"locality"
},
  "geometry": {"coordinates":[108.15696,12.4236],"type":"Point"}
}