{
  "type": "Feature",
  "properties": {
    "gn:admin1_code":"58.0",
    "gn:asciiname":"Yen Phu",
    "gn:country_code":"VN",
    "gn:dem":7,
    "gn:feature_class":"P",
    "gn:feature_code":"PPL",
    "gn:name":"Y\u00ean Ph\u00fa",
    "gn:population":0,
    "gn:timezone":"Asia/Ho_Chi_Minh",
    "iso:country":"VN",
    "name:vie_x_preferred":[
        "Y\u00ean Ph\u00fa"
    ],
    "wof:name":"Yen Phu",
    "wof:placetype":"locality"
},
  "geometry": {"coordinates":[105.70607,19.24105],"type":"Point"}
}