{
  "type": "Feature",
  "properties": {
    "gn:admin1_code":"32.0",
    "gn:asciiname":"Ban To Mot",
    "gn:country_code":"VN",
    "gn:dem":196,
    "gn:feature_class":"P",
    "gn:feature_code":"PPL",
    "gn:name":"B\u1ea3n T\u1ecd M\u1ed9t",
    "gn:population":0,
    "gn:timezone":"Asia/Ho_Chi_Minh",
    "iso:country":"VN",
    "name:vie_x_preferred":[
        "B\u1ea3n T\u1ecd M\u1ed9t"
    ],
    "name:vie_x_variant":[
        "B\u1ea3n T\u1ecd 1"
    ],
    "wof:name":"Ban To Mot",
    "wof:placetype":"locality"
},
  "geometry": {"coordinates":[104.62804,21.24724],"type":"Point"}
}