{
  "type": "Feature",
  "properties": {
    "gn:admin1_code":"70.0",
    "gn:asciiname":"Ba Ngoi",
    "gn:country_code":"VN",
    "gn:dem":86,
    "gn:feature_class":"P",
    "gn:feature_code":"PPL",
    "gn:name":"B\u00e0 Ng\u00f4i",
    "gn:population":0,
    "gn:timezone":"Asia/Ho_Chi_Minh",
    "iso:country":"VN",
    "name:vie_x_preferred":[
        "B\u00e0 Ng\u00f4i"
    ],
    "wof:name":"Ba Ngoi",
    "wof:placetype":"locality"
},
  "geometry": {"coordinates":[104.63308000000001,21.96072],"type":"Point"}
}