{
  "type": "Feature",
  "properties": {
    "gn:admin1_code":"23.0",
    "gn:asciiname":"La Hia",
    "gn:cc2":"VN",
    "gn:country_code":"VN",
    "gn:dem":863,
    "gn:feature_class":"P",
    "gn:feature_code":"PPL",
    "gn:name":"La Hia",
    "gn:population":0,
    "gn:timezone":"Asia/Ho_Chi_Minh",
    "iso:country":"VN",
    "name:und_x_variant":[
        "B. L\u01a1 Hir",
        "La Hia"
    ],
    "wof:name":"La Hia",
    "wof:placetype":"locality"
},
  "geometry": {"coordinates":[108.45,12.25],"type":"Point"}
}