{
  "type": "Feature",
  "properties": {
    "gn:admin1_code":"92.0",
    "gn:asciiname":"Ban Pi",
    "gn:country_code":"VN",
    "gn:dem":698,
    "gn:feature_class":"P",
    "gn:feature_code":"PPL",
    "gn:name":"B\u1ea3n Pi",
    "gn:population":0,
    "gn:timezone":"Asia/Ho_Chi_Minh",
    "iso:country":"VN",
    "wof:name":"Ban Pi",
    "wof:placetype":"locality"
},
  "geometry": {"coordinates":[103.34999999999999,21.45],"type":"Point"}
}