{
  "type": "Feature",
  "properties": {
    "gn:admin1_code":"88.0",
    "gn:asciiname":"Buon Dray H'ling",
    "gn:country_code":"VN",
    "gn:dem":351,
    "gn:feature_class":"P",
    "gn:feature_code":"PPL",
    "gn:name":"Bu\u00f4n \u0110ray H\u2019ling",
    "gn:population":0,
    "gn:timezone":"Asia/Ho_Chi_Minh",
    "iso:country":"VN",
    "wof:name":"Buon Dray H'ling",
    "wof:placetype":"locality"
},
  "geometry": {"coordinates":[107.95,12.63333],"type":"Point"}
}