{
  "type": "Feature",
  "properties": {
    "gn:admin1_code":"58.0",
    "gn:asciiname":"Huoi Phong",
    "gn:country_code":"VN",
    "gn:dem":1071,
    "gn:feature_class":"P",
    "gn:feature_code":"PPL",
    "gn:name":"Hu\u1ed5i Phong",
    "gn:population":0,
    "gn:timezone":"Asia/Ho_Chi_Minh",
    "iso:country":"VN",
    "name:vie_x_preferred":[
        "Hu\u1ed5i Phong"
    ],
    "wof:name":"Huoi Phong",
    "wof:placetype":"locality"
},
  "geometry": {"coordinates":[103.93026,19.30126],"type":"Point"}
}