{
  "type": "Feature",
  "properties": {
    "gn:admin1_code":"77.0",
    "gn:asciiname":"Thoi Hau",
    "gn:country_code":"VN",
    "gn:dem":2,
    "gn:feature_class":"P",
    "gn:feature_code":"PPL",
    "gn:name":"Th\u1edbi H\u1eadu",
    "gn:population":0,
    "gn:timezone":"Asia/Ho_Chi_Minh",
    "iso:country":"VN",
    "name:und_x_variant":[
        "\u1ea4p Th\u1edbi H\u1eadu"
    ],
    "name:vie_x_preferred":[
        "Th\u1edbi H\u1eadu"
    ],
    "wof:name":"Thoi Hau",
    "wof:placetype":"locality"
},
  "geometry": {"coordinates":[105.1082,9.35247],"type":"Point"}
}