{
  "type": "Feature",
  "properties": {
    "gn:admin1_code":"58.0",
    "gn:asciiname":"Tan Huu",
    "gn:country_code":"VN",
    "gn:dem":63,
    "gn:feature_class":"P",
    "gn:feature_code":"PPL",
    "gn:name":"T\u00e2n H\u1eefu",
    "gn:population":0,
    "gn:timezone":"Asia/Ho_Chi_Minh",
    "iso:country":"VN",
    "wof:name":"Tan Huu",
    "wof:placetype":"locality"
},
  "geometry": {"coordinates":[105.48333,19.23333],"type":"Point"}
}