{
  "type": "Feature",
  "properties": {
    "gn:admin1_code":"88.0",
    "gn:asciiname":"Ban Hiet",
    "gn:cc2":"VN",
    "gn:country_code":"VN",
    "gn:dem":839,
    "gn:feature_class":"P",
    "gn:feature_code":"PPL",
    "gn:name":"Ban Hiet",
    "gn:population":0,
    "gn:timezone":"Asia/Ho_Chi_Minh",
    "iso:country":"VN",
    "name:und_x_variant":[
        "Ban Hiot",
        "Ban Hiet"
    ],
    "wof:name":"Ban Hiet",
    "wof:placetype":"locality"
},
  "geometry": {"coordinates":[108.36667,13.11667],"type":"Point"}
}