{
  "type": "Feature",
  "properties": {
    "gn:admin1_code":"88.0",
    "gn:asciiname":"Khoi Muoi",
    "gn:country_code":"VN",
    "gn:dem":460,
    "gn:feature_class":"P",
    "gn:feature_code":"PPL",
    "gn:name":"Kh\u1ed1i M\u01b0\u1eddi",
    "gn:population":0,
    "gn:timezone":"Asia/Ho_Chi_Minh",
    "iso:country":"VN",
    "name:vie_x_preferred":[
        "Kh\u1ed1i M\u01b0\u1eddi"
    ],
    "name:vie_x_variant":[
        "Kh\u1ed1i 10"
    ],
    "wof:name":"Khoi Muoi",
    "wof:placetype":"locality"
},
  "geometry": {"coordinates":[108.53667,12.79813],"type":"Point"}
}