{
  "type": "Feature",
  "properties": {
    "gn:admin1_code":"93.0",
    "gn:asciiname":"Phuong Hoa",
    "gn:country_code":"VN",
    "gn:dem":-2,
    "gn:feature_class":"P",
    "gn:feature_code":"PPL",
    "gn:name":"Ph\u01b0\u01a1ng H\u00f2a",
    "gn:population":0,
    "gn:timezone":"Asia/Ho_Chi_Minh",
    "iso:country":"VN",
    "name:vie_x_preferred":[
        "Ph\u01b0\u01a1ng H\u00f2a"
    ],
    "wof:name":"Phuong Hoa",
    "wof:placetype":"locality"
},
  "geometry": {"coordinates":[105.69114,9.75298],"type":"Point"}
}