{
  "type": "Feature",
  "properties": {
    "gn:admin1_code":"88.0",
    "gn:asciiname":"Buon Suoi",
    "gn:country_code":"VN",
    "gn:dem":411,
    "gn:feature_class":"P",
    "gn:feature_code":"PPL",
    "gn:name":"Bu\u00f4n Su\u1ed1i",
    "gn:population":0,
    "gn:timezone":"Asia/Ho_Chi_Minh",
    "iso:country":"VN",
    "name:vie_x_preferred":[
        "Bu\u00f4n Su\u1ed1i"
    ],
    "wof:name":"Buon Suoi",
    "wof:placetype":"locality"
},
  "geometry": {"coordinates":[108.73089,12.76587],"type":"Point"}
}