{
  "type": "Feature",
  "properties": {
    "gn:admin1_code":"92.0",
    "gn:asciiname":"Ta Ma",
    "gn:country_code":"VN",
    "gn:dem":748,
    "gn:feature_class":"P",
    "gn:feature_code":"PPL",
    "gn:name":"Ta Ma",
    "gn:population":0,
    "gn:timezone":"Asia/Ho_Chi_Minh",
    "iso:country":"VN",
    "name:und_x_variant":[
        "Phiang Ta Man"
    ],
    "name:vie_x_preferred":[
        "Ta Ma"
    ],
    "wof:name":"Ta Ma",
    "wof:placetype":"locality"
},
  "geometry": {"coordinates":[103.54967000000001,21.6986],"type":"Point"}
}