{
  "type": "Feature",
  "properties": {
    "gn:admin1_code":"39.0",
    "gn:asciiname":"Con Nua",
    "gn:country_code":"VN",
    "gn:dem":356,
    "gn:feature_class":"P",
    "gn:feature_code":"PPL",
    "gn:name":"C\u00f2n N\u01b0a",
    "gn:population":0,
    "gn:timezone":"Asia/Ho_Chi_Minh",
    "iso:country":"VN",
    "name:vie_x_preferred":[
        "C\u00f2n N\u01b0a"
    ],
    "wof:name":"Con Nua",
    "wof:placetype":"locality"
},
  "geometry": {"coordinates":[106.42287,21.89232],"type":"Point"}
}