{
  "type": "Feature",
  "properties": {
    "gn:admin1_code":"5.0",
    "gn:asciiname":"Na Don",
    "gn:country_code":"VN",
    "gn:dem":153,
    "gn:feature_class":"P",
    "gn:feature_code":"PPL",
    "gn:name":"N\u00e0 \u0110on",
    "gn:population":0,
    "gn:timezone":"Asia/Ho_Chi_Minh",
    "iso:country":"VN",
    "name:vie_x_preferred":[
        "N\u00e0 \u0110on"
    ],
    "wof:name":"Na Don",
    "wof:placetype":"locality"
},
  "geometry": {"coordinates":[105.47099,22.80821],"type":"Point"}
}