{
  "type": "Feature",
  "properties": {
    "gn:admin1_code":"71.0",
    "gn:asciiname":"GJoi Ngo",
    "gn:country_code":"VN",
    "gn:dem":11,
    "gn:feature_class":"P",
    "gn:feature_code":"PPLA2",
    "gn:name":"\u0110\u1ed3i Ng\u00f4",
    "gn:population":0,
    "gn:timezone":"Asia/Ho_Chi_Minh",
    "iso:country":"VN",
    "name:vie_x_preferred":[
        "\u0110\u1ed3i Ng\u00f4"
    ],
    "wof:name":"GJoi Ngo",
    "wof:placetype":"locality"
},
  "geometry": {"coordinates":[106.38673,21.30626],"type":"Point"}
}