{
  "type": "Feature",
  "properties": {
    "gn:admin1_code":"49.0",
    "gn:asciiname":"Kon Gang Yeng",
    "gn:country_code":"VN",
    "gn:dem":701,
    "gn:feature_class":"P",
    "gn:feature_code":"PPL",
    "gn:name":"Kon Gang Yeng",
    "gn:population":0,
    "gn:timezone":"Asia/Ho_Chi_Minh",
    "iso:country":"VN",
    "name:und_x_variant":[
        "Kon Gang Yong",
        "Kon Gang Yeng"
    ],
    "wof:name":"Kon Gang Yeng",
    "wof:placetype":"locality"
},
  "geometry": {"coordinates":[108.15000000000001,14.08333],"type":"Point"}
}