{
  "type": "Feature",
  "properties": {
    "gn:admin1_code":"3.0",
    "gn:asciiname":"Phuoc Hoa",
    "gn:country_code":"VN",
    "gn:dem":5,
    "gn:feature_class":"P",
    "gn:feature_code":"PPL",
    "gn:name":"Ph\u01b0\u1edbc H\u00f2a",
    "gn:population":0,
    "gn:timezone":"Asia/Ho_Chi_Minh",
    "iso:country":"VN",
    "name:vie_x_preferred":[
        "Ph\u01b0\u1edbc H\u00f2a"
    ],
    "wof:name":"Phuoc Hoa",
    "wof:placetype":"locality"
},
  "geometry": {"coordinates":[106.26987,10.29303],"type":"Point"}
}