{
  "type": "Feature",
  "properties": {
    "gn:admin1_code":"72.0",
    "gn:asciiname":"Na Pam",
    "gn:country_code":"VN",
    "gn:dem":157,
    "gn:feature_class":"P",
    "gn:feature_code":"PPL",
    "gn:name":"N\u00e0 Pam",
    "gn:population":0,
    "gn:timezone":"Asia/Ho_Chi_Minh",
    "iso:country":"VN",
    "name:vie_x_preferred":[
        "N\u00e0 Pam"
    ],
    "wof:name":"Na Pam",
    "wof:placetype":"locality"
},
  "geometry": {"coordinates":[105.83526999999999,22.16839],"type":"Point"}
}