{
  "type": "Feature",
  "properties": {
    "gn:admin1_code":"5.0",
    "gn:asciiname":"La Ta",
    "gn:country_code":"VN",
    "gn:dem":318,
    "gn:feature_class":"P",
    "gn:feature_code":"PPL",
    "gn:name":"La Ta",
    "gn:population":0,
    "gn:timezone":"Asia/Ho_Chi_Minh",
    "iso:country":"VN",
    "wof:name":"La Ta",
    "wof:placetype":"locality"
},
  "geometry": {"coordinates":[106.36667,22.36667000000001],"type":"Point"}
}