{
  "type": "Feature",
  "properties": {
    "gn:admin1_code":"39.0",
    "gn:asciiname":"Na Cam",
    "gn:country_code":"VN",
    "gn:dem":272,
    "gn:feature_class":"P",
    "gn:feature_code":"PPL",
    "gn:name":"N\u00e0 Cam",
    "gn:population":0,
    "gn:timezone":"Asia/Ho_Chi_Minh",
    "iso:country":"VN",
    "name:vie_x_preferred":[
        "N\u00e0 Cam"
    ],
    "wof:name":"Na Cam",
    "wof:placetype":"locality"
},
  "geometry": {"coordinates":[106.29418,21.9924],"type":"Point"}
}