{
  "type": "Feature",
  "properties": {
    "gn:admin1_code":"80.0",
    "gn:asciiname":"Lung Xuyen",
    "gn:country_code":"VN",
    "gn:dem":7,
    "gn:feature_class":"P",
    "gn:feature_code":"PPL",
    "gn:name":"L\u0169ng Xuy\u00ean",
    "gn:population":0,
    "gn:timezone":"Asia/Ho_Chi_Minh",
    "iso:country":"VN",
    "name:vie_x_preferred":[
        "L\u0169ng Xuy\u00ean"
    ],
    "wof:name":"Lung Xuyen",
    "wof:placetype":"locality"
},
  "geometry": {"coordinates":[105.97494,20.64527],"type":"Point"}
}