{
  "type": "Feature",
  "properties": {
    "gn:admin1_code":"86.0",
    "gn:asciiname":"Huu Thu",
    "gn:country_code":"VN",
    "gn:dem":35,
    "gn:feature_class":"P",
    "gn:feature_code":"PPL",
    "gn:name":"H\u1eefu Th\u1ee7",
    "gn:population":0,
    "gn:timezone":"Asia/Ho_Chi_Minh",
    "iso:country":"VN",
    "name:vie_x_preferred":[
        "H\u1eefu Th\u1ee7"
    ],
    "wof:name":"Huu Thu",
    "wof:placetype":"locality"
},
  "geometry": {"coordinates":[105.60473,21.35229],"type":"Point"}
}