{
  "type": "Feature",
  "properties": {
    "gn:admin1_code":"88.0",
    "gn:asciiname":"Ho Sing",
    "gn:country_code":"VN",
    "gn:dem":560,
    "gn:feature_class":"P",
    "gn:feature_code":"PPL",
    "gn:name":"H\u1ed3 Sing",
    "gn:population":0,
    "gn:timezone":"Asia/Ho_Chi_Minh",
    "iso:country":"VN",
    "name:und_x_variant":[
        "Ban Sing",
        "Buon Sing",
        "Bu\u00f4n H\u00f4 Sing"
    ],
    "name:vie_x_preferred":[
        "H\u1ed3 Sing"
    ],
    "wof:name":"Ho Sing",
    "wof:placetype":"locality"
},
  "geometry": {"coordinates":[108.38678,12.87778],"type":"Point"}
}