{
  "type": "Feature",
  "properties": {
    "gn:admin1_code":"32.0",
    "gn:asciiname":"Ban Na Mun",
    "gn:country_code":"VN",
    "gn:dem":795,
    "gn:feature_class":"P",
    "gn:feature_code":"PPL",
    "gn:name":"B\u1ea3n N\u00e0 M\u00f9n",
    "gn:population":0,
    "gn:timezone":"Asia/Ho_Chi_Minh",
    "iso:country":"VN",
    "name:vie_x_preferred":[
        "N\u00e0 M\u00f9n"
    ],
    "name:vie_x_variant":[
        "B\u1ea3n N\u00e0 M\u00f9n"
    ],
    "wof:name":"Ban Na Mun",
    "wof:placetype":"locality"
},
  "geometry": {"coordinates":[103.62757999999999,21.94415],"type":"Point"}
}