{
  "type": "Feature",
  "properties": {
    "gn:admin1_code":"58.0",
    "gn:asciiname":"Cua Rao Vang",
    "gn:country_code":"VN",
    "gn:dem":88,
    "gn:feature_class":"P",
    "gn:feature_code":"PPL",
    "gn:name":"C\u1eeda Rao V\u00e0ng",
    "gn:population":0,
    "gn:timezone":"Asia/Ho_Chi_Minh",
    "iso:country":"VN",
    "wof:name":"Cua Rao Vang",
    "wof:placetype":"locality"
},
  "geometry": {"coordinates":[105.25,18.63333],"type":"Point"}
}