{
  "type": "Feature",
  "properties": {
    "gn:admin1_code":"88.0",
    "gn:asciiname":"Buon Emap",
    "gn:cc2":"VN",
    "gn:country_code":"VN",
    "gn:dem":518,
    "gn:feature_class":"P",
    "gn:feature_code":"PPL",
    "gn:name":"Bu\u00f4n Em\u0103p",
    "gn:population":0,
    "gn:timezone":"Asia/Ho_Chi_Minh",
    "iso:country":"VN",
    "name:und_x_variant":[
        "Buon Em\u0103o",
        "Bu\u00f4n Em\u0103p"
    ],
    "wof:name":"Buon Emap",
    "wof:placetype":"locality"
},
  "geometry": {"coordinates":[108.09999999999999,12.78333],"type":"Point"}
}