{
  "type": "Feature",
  "properties": {
    "gn:admin1_code":"34.0",
    "gn:asciiname":"Xom Nom",
    "gn:cc2":"VN",
    "gn:country_code":"VN",
    "gn:dem":140,
    "gn:feature_class":"P",
    "gn:feature_code":"PPL",
    "gn:name":"X\u00f3m N\u00f4m",
    "gn:population":0,
    "gn:timezone":"Asia/Ho_Chi_Minh",
    "iso:country":"VN",
    "name:und_x_variant":[
        "Nom",
        "Xnom",
        "X\u00f3m N\u00f4m"
    ],
    "wof:name":"Xom Nom",
    "wof:placetype":"locality"
},
  "geometry": {"coordinates":[105.38333,20.26667],"type":"Point"}
}