{
  "type": "Feature",
  "properties": {
    "gn:admin1_code":"5.0",
    "gn:asciiname":"Tinh Dong",
    "gn:country_code":"VN",
    "gn:dem":516,
    "gn:feature_class":"P",
    "gn:feature_code":"PPL",
    "gn:name":"T\u00ecnh \u0110\u00f4ng",
    "gn:population":0,
    "gn:timezone":"Asia/Ho_Chi_Minh",
    "iso:country":"VN",
    "wof:name":"Tinh Dong",
    "wof:placetype":"locality"
},
  "geometry": {"coordinates":[106.41667,22.68333],"type":"Point"}
}