{
  "type": "Feature",
  "properties": {
    "gn:admin1_code":"88.0",
    "gn:asciiname":"Dak Tour",
    "gn:country_code":"VN",
    "gn:dem":461,
    "gn:feature_class":"P",
    "gn:feature_code":"PPL",
    "gn:name":"\u0110\u1eafk Tour",
    "gn:population":0,
    "gn:timezone":"Asia/Ho_Chi_Minh",
    "iso:country":"VN",
    "name:vie_x_preferred":[
        "\u0110\u1eafk Tour"
    ],
    "wof:name":"Dak Tour",
    "wof:placetype":"locality"
},
  "geometry": {"coordinates":[108.5003,12.50629],"type":"Point"}
}