{
  "type": "Feature",
  "properties": {
    "gn:admin1_code":"63.0",
    "gn:asciiname":"Viet Day",
    "gn:country_code":"VN",
    "gn:dem":119,
    "gn:feature_class":"P",
    "gn:feature_code":"PPL",
    "gn:name":"Viet Day",
    "gn:population":0,
    "gn:timezone":"Asia/Ho_Chi_Minh",
    "iso:country":"VN",
    "name:und_x_variant":[
        "Badon",
        "Viet Day"
    ],
    "wof:name":"Viet Day",
    "wof:placetype":"locality"
},
  "geometry": {"coordinates":[108.41667,15.08333],"type":"Point"}
}