{
  "type": "Feature",
  "properties": {
    "gn:admin1_code":"68.0",
    "gn:asciiname":"Vinh Quang",
    "gn:country_code":"VN",
    "gn:dem":92,
    "gn:feature_class":"P",
    "gn:feature_code":"PPL",
    "gn:name":"Vinh Quang",
    "gn:population":0,
    "gn:timezone":"Asia/Ho_Chi_Minh",
    "iso:country":"VN",
    "name:vie_x_preferred":[
        "Vinh Quang"
    ],
    "wof:name":"Vinh Quang",
    "wof:placetype":"locality"
},
  "geometry": {"coordinates":[105.30383999999999,22.10733],"type":"Point"}
}