{
  "type": "Feature",
  "properties": {
    "gn:admin1_code":"5.0",
    "gn:asciiname":"Ban Na Ham",
    "gn:country_code":"VN",
    "gn:dem":215,
    "gn:feature_class":"P",
    "gn:feature_code":"PPL",
    "gn:name":"B\u1ea3n N\u00e0 H\u00e2m",
    "gn:population":0,
    "gn:timezone":"Asia/Ho_Chi_Minh",
    "iso:country":"VN",
    "name:vie_x_preferred":[
        "N\u00e0 H\u00f4m"
    ],
    "name:vie_x_variant":[
        "Na H\u00f4m",
        "B\u1ea3n N\u00e0 H\u00e2m"
    ],
    "wof:name":"Ban Na Ham",
    "wof:placetype":"locality"
},
  "geometry": {"coordinates":[105.37575,22.87289],"type":"Point"}
}