{
  "type": "Feature",
  "properties": {
    "gn:admin1_code":"77.0",
    "gn:asciiname":"Bo Dao",
    "gn:country_code":"VN",
    "gn:dem":2,
    "gn:feature_class":"P",
    "gn:feature_code":"PPL",
    "gn:name":"Bo Dao",
    "gn:population":0,
    "gn:timezone":"Asia/Ho_Chi_Minh",
    "iso:country":"VN",
    "name:und_x_variant":[
        "X\u00f3m B\u1edd \u0110\u00e2p"
    ],
    "name:vie_x_preferred":[
        "B\u1edd \u0110\u1eadp"
    ],
    "wof:name":"Bo Dao",
    "wof:placetype":"locality"
},
  "geometry": {"coordinates":[105.11991,8.98735],"type":"Point"}
}