{
  "type": "Feature",
  "properties": {
    "gn:admin1_code":"65.0",
    "gn:asciiname":"Hoa Lac",
    "gn:country_code":"VN",
    "gn:dem":5,
    "gn:elevation":"5.0",
    "gn:feature_class":"P",
    "gn:feature_code":"PPLF",
    "gn:name":"Hoa Lac",
    "gn:population":0,
    "gn:timezone":"Asia/Ho_Chi_Minh",
    "iso:country":"VN",
    "wof:name":"Hoa Lac",
    "wof:placetype":"locality"
},
  "geometry": {"coordinates":[105.93254,20.5486],"type":"Point"}
}