{
  "type": "Feature",
  "properties": {
    "gn:admin1_code":"46.0",
    "gn:asciiname":"Tan Thang",
    "gn:country_code":"VN",
    "gn:dem":14,
    "gn:feature_class":"P",
    "gn:feature_code":"PPL",
    "gn:name":"T\u00e2n Th\u1eafng",
    "gn:population":0,
    "gn:timezone":"Asia/Ho_Chi_Minh",
    "iso:country":"VN",
    "name:vie_x_preferred":[
        "T\u00e2n Th\u1eafng"
    ],
    "wof:name":"Tan Thang",
    "wof:placetype":"locality"
},
  "geometry": {"coordinates":[109.20921,14.05414],"type":"Point"}
}