{
  "type": "Feature",
  "properties": {
    "gn:admin1_code":"86.0",
    "gn:asciiname":"Lien Ho",
    "gn:country_code":"VN",
    "gn:dem":33,
    "gn:feature_class":"P",
    "gn:feature_code":"PPL",
    "gn:name":"Li\u00ean H\u1ed9",
    "gn:population":0,
    "gn:timezone":"Asia/Ho_Chi_Minh",
    "iso:country":"VN",
    "wof:name":"Lien Ho",
    "wof:placetype":"locality"
},
  "geometry": {"coordinates":[105.53333000000001,21.43333],"type":"Point"}
}