{
  "type": "Feature",
  "properties": {
    "gn:admin1_code":"88.0",
    "gn:asciiname":"Nhan Yang",
    "gn:country_code":"VN",
    "gn:dem":465,
    "gn:feature_class":"P",
    "gn:feature_code":"PPL",
    "gn:name":"Nh\u00e2n Yang",
    "gn:population":0,
    "gn:timezone":"Asia/Ho_Chi_Minh",
    "iso:country":"VN",
    "name:vie_x_preferred":[
        "Nh\u00e2n Yang"
    ],
    "wof:name":"Nhan Yang",
    "wof:placetype":"locality"
},
  "geometry": {"coordinates":[108.57998000000001,12.4652],"type":"Point"}
}