{
  "type": "Feature",
  "properties": {
    "gn:admin1_code":"89.0",
    "gn:asciiname":"Pac Pha",
    "gn:country_code":"VN",
    "gn:dem":549,
    "gn:feature_class":"P",
    "gn:feature_code":"PPL",
    "gn:name":"P\u1eafc Pha",
    "gn:population":0,
    "gn:timezone":"Asia/Ho_Chi_Minh",
    "iso:country":"VN",
    "wof:name":"Pac Pha",
    "wof:placetype":"locality"
},
  "geometry": {"coordinates":[103.75,22.01667],"type":"Point"}
}