{
  "type": "Feature",
  "properties": {
    "gn:admin1_code":"32.0",
    "gn:asciiname":"Ban Lai",
    "gn:cc2":"VN",
    "gn:country_code":"VN",
    "gn:dem":496,
    "gn:feature_class":"P",
    "gn:feature_code":"PPL",
    "gn:name":"B\u1ea3n Lai",
    "gn:population":0,
    "gn:timezone":"Asia/Ho_Chi_Minh",
    "iso:country":"VN",
    "name:und_x_variant":[
        "B\u1ea3n La",
        "B\u1ea3n Lai"
    ],
    "wof:name":"Ban Lai",
    "wof:placetype":"locality"
},
  "geometry": {"coordinates":[104.09999999999999,21.53333],"type":"Point"}
}