{
  "type": "Feature",
  "properties": {
    "gn:admin1_code":"32.0",
    "gn:asciiname":"Ban Bac Ban",
    "gn:country_code":"VN",
    "gn:dem":151,
    "gn:feature_class":"P",
    "gn:feature_code":"PPL",
    "gn:name":"B\u1ea3n B\u1eafc B\u0103n",
    "gn:population":0,
    "gn:timezone":"Asia/Ho_Chi_Minh",
    "iso:country":"VN",
    "name:und_x_variant":[
        "B\u1ea3n B\u0103c B\u00e1n"
    ],
    "name:vie_x_preferred":[
        "B\u1ea3n B\u1eafc B\u0103n"
    ],
    "wof:name":"Ban Bac Ban",
    "wof:placetype":"locality"
},
  "geometry": {"coordinates":[104.60424999999999,21.05232],"type":"Point"}
}