{
  "type": "Feature",
  "properties": {
    "gn:admin1_code":"50.0",
    "gn:asciiname":"Lang Cac",
    "gn:country_code":"VN",
    "gn:dem":411,
    "gn:feature_class":"P",
    "gn:feature_code":"PPL",
    "gn:name":"L\u00e0ng Cac",
    "gn:population":0,
    "gn:timezone":"Asia/Ho_Chi_Minh",
    "iso:country":"VN",
    "wof:name":"Lang Cac",
    "wof:placetype":"locality"
},
  "geometry": {"coordinates":[105.21666999999999,22.93333],"type":"Point"}
}