{
  "type": "Feature",
  "properties": {
    "gn:admin1_code":"89.0",
    "gn:asciiname":"Ban Nong Thang",
    "gn:country_code":"VN",
    "gn:dem":449,
    "gn:feature_class":"P",
    "gn:feature_code":"PPL",
    "gn:name":"B\u1ea3n N\u1ed3ng Th\u00e0ng",
    "gn:population":0,
    "gn:timezone":"Asia/Ho_Chi_Minh",
    "iso:country":"VN",
    "name:vie_x_preferred":[
        "B\u1ea3n N\u1ed3ng Th\u00e0ng"
    ],
    "wof:name":"Ban Nong Thang",
    "wof:placetype":"locality"
},
  "geometry": {"coordinates":[103.69513999999999,22.01583],"type":"Point"}
}