{
  "type": "Feature",
  "properties": {
    "gn:admin1_code":"5.0",
    "gn:asciiname":"Ban Sieng Tau",
    "gn:country_code":"VN",
    "gn:dem":294,
    "gn:feature_class":"P",
    "gn:feature_code":"PPL",
    "gn:name":"B\u1ea3n Si\u00eang T\u1ea9u",
    "gn:population":0,
    "gn:timezone":"Asia/Ho_Chi_Minh",
    "iso:country":"VN",
    "wof:name":"Ban Sieng Tau",
    "wof:placetype":"locality"
},
  "geometry": {"coordinates":[106.56667,22.58333],"type":"Point"}
}