{
  "type": "Feature",
  "properties": {
    "gn:admin1_code":"20.0",
    "gn:asciiname":"Xom Dong Tron",
    "gn:country_code":"VN",
    "gn:dem":0,
    "gn:feature_class":"P",
    "gn:feature_code":"PPL",
    "gn:name":"X\u00f3m \u0110\u1ed3ng Tr\u00f2n",
    "gn:population":0,
    "gn:timezone":"Asia/Ho_Chi_Minh",
    "iso:country":"VN",
    "name:und_x_variant":[
        "Dong Tron",
        "X\u00f3m \u0110\u1ed3ng Tr\u00f2n"
    ],
    "wof:name":"Xom Dong Tron",
    "wof:placetype":"locality"
},
  "geometry": {"coordinates":[106.76667,10.48333],"type":"Point"}
}