{
  "type": "Feature",
  "properties": {
    "gn:admin1_code":"74.0",
    "gn:asciiname":"Nghiem Xa",
    "gn:country_code":"VN",
    "gn:dem":9,
    "gn:feature_class":"P",
    "gn:feature_code":"PPL",
    "gn:name":"Nghi\u00eam X\u00e1",
    "gn:population":0,
    "gn:timezone":"Asia/Ho_Chi_Minh",
    "iso:country":"VN",
    "name:und_x_variant":[
        "Nghien Xa",
        "Nghi\u00eam X\u00e1"
    ],
    "wof:name":"Nghiem Xa",
    "wof:placetype":"locality"
},
  "geometry": {"coordinates":[106.1666,21.1519],"type":"Point"}
}