{
  "type": "Feature",
  "properties": {
    "gn:admin1_code":"32.0",
    "gn:asciiname":"Que Me",
    "gn:cc2":"VN",
    "gn:country_code":"VN",
    "gn:dem":637,
    "gn:feature_class":"P",
    "gn:feature_code":"PPL",
    "gn:name":"Que M\u00e9",
    "gn:population":0,
    "gn:timezone":"Asia/Ho_Chi_Minh",
    "iso:country":"VN",
    "name:und_x_variant":[
        "Oue M\u00e9",
        "Que M\u00e9"
    ],
    "wof:name":"Que Me",
    "wof:placetype":"locality"
},
  "geometry": {"coordinates":[104.25,21.23333],"type":"Point"}
}