{
  "type": "Feature",
  "properties": {
    "gn:admin1_code":"81.0",
    "gn:asciiname":"Dong Hong",
    "gn:country_code":"VN",
    "gn:dem":9,
    "gn:feature_class":"P",
    "gn:feature_code":"PPL",
    "gn:name":"\u0110\u00f4ng H\u1ed3ng",
    "gn:population":0,
    "gn:timezone":"Asia/Ho_Chi_Minh",
    "iso:country":"VN",
    "name:vie_x_preferred":[
        "\u0110\u00f4ng H\u1ed3ng"
    ],
    "wof:name":"Dong Hong",
    "wof:placetype":"locality"
},
  "geometry": {"coordinates":[106.04076000000001,20.70238],"type":"Point"}
}