{
  "type": "Feature",
  "properties": {
    "gn:admin1_code":"50.0",
    "gn:asciiname":"Co Tau",
    "gn:country_code":"VN",
    "gn:dem":634,
    "gn:feature_class":"P",
    "gn:feature_code":"PPL",
    "gn:name":"C\u1edd T\u1ea9u",
    "gn:population":0,
    "gn:timezone":"Asia/Ho_Chi_Minh",
    "iso:country":"VN",
    "name:vie_x_preferred":[
        "C\u1edd T\u1ea9u"
    ],
    "wof:name":"Co Tau",
    "wof:placetype":"locality"
},
  "geometry": {"coordinates":[105.20932000000001,22.9864],"type":"Point"}
}