{
  "type": "Feature",
  "properties": {
    "gn:admin1_code":"66.0",
    "gn:asciiname":"Thuong Hoa",
    "gn:country_code":"VN",
    "gn:dem":9,
    "gn:feature_class":"P",
    "gn:feature_code":"PPL",
    "gn:name":"Th\u01b0\u1ee3ng H\u00f2a",
    "gn:population":0,
    "gn:timezone":"Asia/Ho_Chi_Minh",
    "iso:country":"VN",
    "name:und_x_variant":[
        "\u1ea4p Th\u01b0\u1ee3ng H\u00f2a"
    ],
    "name:vie_x_preferred":[
        "Th\u01b0\u1ee3ng H\u00f2a"
    ],
    "wof:name":"Thuong Hoa",
    "wof:placetype":"locality"
},
  "geometry": {"coordinates":[107.39734,16.57384],"type":"Point"}
}