{
  "type": "Feature",
  "properties": {
    "gn:admin1_code":"84.0",
    "gn:asciiname":"Phuoc Duc",
    "gn:country_code":"VN",
    "gn:dem":34,
    "gn:feature_class":"P",
    "gn:feature_code":"PPL",
    "gn:name":"Ph\u01b0\u1edbc \u0110\u00fac",
    "gn:population":0,
    "gn:timezone":"Asia/Ho_Chi_Minh",
    "iso:country":"VN",
    "wof:name":"Phuoc Duc",
    "wof:placetype":"locality"
},
  "geometry": {"coordinates":[108.26667,15.68333],"type":"Point"}
}