{
  "type": "Feature",
  "properties": {
    "gn:admin1_code":"58.0",
    "gn:asciiname":"Khoi Mot",
    "gn:country_code":"VN",
    "gn:dem":11,
    "gn:feature_class":"P",
    "gn:feature_code":"PPL",
    "gn:name":"Kh\u1ed1i M\u1ed9t",
    "gn:population":0,
    "gn:timezone":"Asia/Ho_Chi_Minh",
    "iso:country":"VN",
    "name:vie_x_preferred":[
        "Kh\u1ed1i M\u1ed9t"
    ],
    "name:vie_x_variant":[
        "Kh\u1ed1i 1"
    ],
    "wof:name":"Khoi Mot",
    "wof:placetype":"locality"
},
  "geometry": {"coordinates":[105.72002000000001,18.81051],"type":"Point"}
}