{
  "type": "Feature",
  "properties": {
    "gn:admin1_code":"39.0",
    "gn:asciiname":"Lan Nam",
    "gn:country_code":"VN",
    "gn:dem":325,
    "gn:feature_class":"P",
    "gn:feature_code":"PPL",
    "gn:name":"L\u00e2n N\u1eadm",
    "gn:population":0,
    "gn:timezone":"Asia/Ho_Chi_Minh",
    "iso:country":"VN",
    "name:vie_x_preferred":[
        "L\u00e2n N\u1eadm"
    ],
    "wof:name":"Lan Nam",
    "wof:placetype":"locality"
},
  "geometry": {"coordinates":[106.34842999999999,21.75356],"type":"Point"}
}