{
  "type": "Feature",
  "properties": {
    "gn:admin1_code":"49.0",
    "gn:asciiname":"Khom Hai",
    "gn:country_code":"VN",
    "gn:dem":419,
    "gn:feature_class":"P",
    "gn:feature_code":"PPL",
    "gn:name":"Kh\u00f3m Hai",
    "gn:population":0,
    "gn:timezone":"Asia/Ho_Chi_Minh",
    "iso:country":"VN",
    "name:vie_x_preferred":[
        "Kh\u00f3m Hai"
    ],
    "name:vie_x_variant":[
        "Kh\u00f3m 2"
    ],
    "wof:name":"Khom Hai",
    "wof:placetype":"locality"
},
  "geometry": {"coordinates":[108.67010000000001,13.95999],"type":"Point"}
}