{
  "type": "Feature",
  "properties": {
    "gn:admin1_code":"87.0",
    "gn:asciiname":"Thoi Hoa",
    "gn:country_code":"VN",
    "gn:dem":7,
    "gn:feature_class":"P",
    "gn:feature_code":"PPL",
    "gn:name":"Th\u1edbi H\u00f2a",
    "gn:population":0,
    "gn:timezone":"Asia/Ho_Chi_Minh",
    "iso:country":"VN",
    "name:und_x_variant":[
        "\u1ea4p Th\u1edbi H\u00f2a"
    ],
    "name:vie_x_preferred":[
        "Th\u1edbi H\u00f2a"
    ],
    "wof:name":"Thoi Hoa",
    "wof:placetype":"locality"
},
  "geometry": {"coordinates":[105.58192,10.14214],"type":"Point"}
}