{
  "type": "Feature",
  "properties": {
    "gn:admin1_code":"39.0",
    "gn:asciiname":"Khon Lung Na",
    "gn:cc2":"VN",
    "gn:country_code":"VN",
    "gn:dem":358,
    "gn:feature_class":"P",
    "gn:feature_code":"PPL",
    "gn:name":"Khon Lung Na",
    "gn:population":0,
    "gn:timezone":"Asia/Ho_Chi_Minh",
    "iso:country":"VN",
    "name:und_x_variant":[
        "Khon Lung Ma",
        "Khon Lung Na"
    ],
    "wof:name":"Khon Lung Na",
    "wof:placetype":"locality"
},
  "geometry": {"coordinates":[106.46666999999999,21.66667],"type":"Point"}
}