{
  "type": "Feature",
  "properties": {
    "gn:admin1_code":"72.0",
    "gn:asciiname":"Na Phi",
    "gn:country_code":"VN",
    "gn:dem":354,
    "gn:feature_class":"P",
    "gn:feature_code":"PPL",
    "gn:name":"N\u00e0 Phi",
    "gn:population":0,
    "gn:timezone":"Asia/Ho_Chi_Minh",
    "iso:country":"VN",
    "name:und_x_variant":[
        "Na Pi"
    ],
    "name:vie_x_preferred":[
        "N\u00e0 Phi"
    ],
    "wof:name":"Na Phi",
    "wof:placetype":"locality"
},
  "geometry": {"coordinates":[106.07044999999999,21.97392],"type":"Point"}
}