{
  "type": "Feature",
  "properties": {
    "gn:admin1_code":"63.0",
    "gn:asciiname":"Ta Bien",
    "gn:country_code":"VN",
    "gn:dem":68,
    "gn:feature_class":"P",
    "gn:feature_code":"PPL",
    "gn:name":"T\u00e0 Bi\u00ean",
    "gn:population":0,
    "gn:timezone":"Asia/Ho_Chi_Minh",
    "iso:country":"VN",
    "wof:name":"Ta Bien",
    "wof:placetype":"locality"
},
  "geometry": {"coordinates":[108.53333000000001,14.88333],"type":"Point"}
}