{
  "type": "Feature",
  "properties": {
    "gn:admin1_code":"76.0",
    "gn:asciiname":"Binh Que",
    "gn:country_code":"VN",
    "gn:dem":56,
    "gn:feature_class":"P",
    "gn:feature_code":"PPL",
    "gn:name":"B\u00ecnh Qu\u1ebf",
    "gn:population":0,
    "gn:timezone":"Asia/Ho_Chi_Minh",
    "iso:country":"VN",
    "name:vie_x_preferred":[
        "B\u00ecnh Qu\u1ebf"
    ],
    "wof:name":"Binh Que",
    "wof:placetype":"locality"
},
  "geometry": {"coordinates":[106.52206,11.65467],"type":"Point"}
}