{
  "type": "Feature",
  "properties": {
    "gn:admin1_code":"72.0",
    "gn:asciiname":"Thon Mo",
    "gn:country_code":"VN",
    "gn:dem":176,
    "gn:feature_class":"P",
    "gn:feature_code":"PPL",
    "gn:name":"Th\u00f4n M\u00f2",
    "gn:population":0,
    "gn:timezone":"Asia/Ho_Chi_Minh",
    "iso:country":"VN",
    "name:vie_x_preferred":[
        "Th\u00f4n M\u00f2"
    ],
    "wof:name":"Thon Mo",
    "wof:placetype":"locality"
},
  "geometry": {"coordinates":[105.86893000000001,22.23362],"type":"Point"}
}