{
  "type": "Feature",
  "properties": {
    "gn:admin1_code":"52.0",
    "gn:asciiname":"Xom Muoi Bay",
    "gn:country_code":"VN",
    "gn:dem":7,
    "gn:feature_class":"P",
    "gn:feature_code":"PPL",
    "gn:name":"X\u00f3m M\u01b0\u1eddi B\u1ea3y",
    "gn:population":0,
    "gn:timezone":"Asia/Ho_Chi_Minh",
    "iso:country":"VN",
    "name:vie_x_preferred":[
        "X\u00f3m M\u01b0\u1eddi B\u1ea3y"
    ],
    "name:vie_x_variant":[
        "X\u00f3m 17"
    ],
    "wof:name":"Xom Muoi Bay",
    "wof:placetype":"locality"
},
  "geometry": {"coordinates":[105.89295,18.318],"type":"Point"}
}