{
  "type": "Feature",
  "properties": {
    "gn:admin1_code":"65.0",
    "gn:asciiname":"An Ninh",
    "gn:country_code":"VN",
    "gn:dem":3,
    "gn:feature_class":"P",
    "gn:feature_code":"PPL",
    "gn:name":"An Ninh",
    "gn:population":0,
    "gn:timezone":"Asia/Ho_Chi_Minh",
    "iso:country":"VN",
    "name:fas_x_preferred":[
        "\u0627\u0646 \u0646\u06cc\u0646\u0647"
    ],
    "name:ita_x_preferred":[
        "An Ninh"
    ],
    "name:vie_x_preferred":[
        "An Ninh"
    ],
    "wof:name":"An Ninh",
    "wof:placetype":"locality"
},
  "geometry": {"coordinates":[105.95,9.61667],"type":"Point"}
}