{
  "type": "Feature",
  "properties": {
    "gn:admin1_code":"77.0",
    "gn:asciiname":"Rach Tau",
    "gn:country_code":"VN",
    "gn:dem":-2,
    "gn:feature_class":"P",
    "gn:feature_code":"PPL",
    "gn:name":"R\u1ea1ch T\u00e0u",
    "gn:population":0,
    "gn:timezone":"Asia/Ho_Chi_Minh",
    "iso:country":"VN",
    "name:und_x_variant":[
        "X\u00f3m R\u1ea1ch T\u00e0u",
        "R\u1ea1ch T\u00e0u"
    ],
    "wof:name":"Rach Tau",
    "wof:placetype":"locality"
},
  "geometry": {"coordinates":[104.76494,8.5963],"type":"Point"}
}