{
  "type": "Feature",
  "properties": {
    "gn:admin1_code":"5.0",
    "gn:asciiname":"Thom Tung",
    "gn:country_code":"VN",
    "gn:dem":709,
    "gn:feature_class":"P",
    "gn:feature_code":"PPL",
    "gn:name":"Th\u00f4m T\u1ee7ng",
    "gn:population":0,
    "gn:timezone":"Asia/Ho_Chi_Minh",
    "iso:country":"VN",
    "wof:name":"Thom Tung",
    "wof:placetype":"locality"
},
  "geometry": {"coordinates":[106.34999999999999,22.78333],"type":"Point"}
}