{
  "type": "Feature",
  "properties": {
    "gn:admin1_code":"90.0",
    "gn:asciiname":"Ban Phu La Ngai",
    "gn:country_code":"VN",
    "gn:dem":832,
    "gn:feature_class":"P",
    "gn:feature_code":"PPL",
    "gn:name":"B\u1ea3n Ph\u00f9 L\u00e1 Ng\u00e0i",
    "gn:population":0,
    "gn:timezone":"Asia/Ho_Chi_Minh",
    "iso:country":"VN",
    "name:vie_x_preferred":[
        "B\u1ea3n Ph\u00f9 L\u00e1 Ng\u00e0i"
    ],
    "wof:name":"Ban Phu La Ngai",
    "wof:placetype":"locality"
},
  "geometry": {"coordinates":[104.12867,21.95589],"type":"Point"}
}