{
  "type": "Feature",
  "properties": {
    "gn:admin1_code":"20.0",
    "gn:asciiname":"Binh Dong",
    "gn:country_code":"VN",
    "gn:dem":-1,
    "gn:feature_class":"P",
    "gn:feature_code":"PPL",
    "gn:name":"B\u00ecnh \u0110\u00f4ng",
    "gn:population":0,
    "gn:timezone":"Asia/Ho_Chi_Minh",
    "iso:country":"VN",
    "wof:name":"Binh Dong",
    "wof:placetype":"locality"
},
  "geometry": {"coordinates":[106.66722,10.91389],"type":"Point"}
}