{
  "type": "Feature",
  "properties": {
    "gn:admin1_code":"58.0",
    "gn:asciiname":"Xom Muoi Mot",
    "gn:country_code":"VN",
    "gn:dem":7,
    "gn:feature_class":"P",
    "gn:feature_code":"PPL",
    "gn:name":"X\u00f3m M\u01b0\u1eddi M\u1ed9t",
    "gn:population":0,
    "gn:timezone":"Asia/Ho_Chi_Minh",
    "iso:country":"VN",
    "name:vie_x_preferred":[
        "X\u00f3m M\u01b0\u1eddi M\u1ed9t"
    ],
    "name:vie_x_variant":[
        "X\u00f3m 11"
    ],
    "wof:name":"Xom Muoi Mot",
    "wof:placetype":"locality"
},
  "geometry": {"coordinates":[105.58882,18.79219],"type":"Point"}
}