{
  "type": "Feature",
  "properties": {
    "gn:admin1_code":"23.0",
    "gn:asciiname":"Suoi Thong",
    "gn:country_code":"VN",
    "gn:dem":1053,
    "gn:feature_class":"P",
    "gn:feature_code":"PPL",
    "gn:name":"Su\u1ed1i Th\u00f4ng",
    "gn:population":0,
    "gn:timezone":"Asia/Ho_Chi_Minh",
    "iso:country":"VN",
    "name:vie_x_preferred":[
        "Su\u1ed1i Th\u00f4ng"
    ],
    "wof:name":"Suoi Thong",
    "wof:placetype":"locality"
},
  "geometry": {"coordinates":[108.44692000000001,11.77068],"type":"Point"}
}