{
  "type": "Feature",
  "properties": {
    "gn:admin1_code":"58.0",
    "gn:asciiname":"Huu Nam",
    "gn:country_code":"VN",
    "gn:dem":9,
    "gn:feature_class":"P",
    "gn:feature_code":"PPL",
    "gn:name":"H\u1eefu Nam",
    "gn:population":0,
    "gn:timezone":"Asia/Ho_Chi_Minh",
    "iso:country":"VN",
    "name:vie_x_preferred":[
        "H\u1eefu Nam"
    ],
    "wof:name":"Huu Nam",
    "wof:placetype":"locality"
},
  "geometry": {"coordinates":[105.72654,19.20981],"type":"Point"}
}