{
  "type": "Feature",
  "properties": {
    "gn:admin1_code":"52.0",
    "gn:asciiname":"Dom Thuy",
    "gn:country_code":"VN",
    "gn:dem":5,
    "gn:feature_class":"P",
    "gn:feature_code":"PPL",
    "gn:name":"Dom Thuy",
    "gn:population":0,
    "gn:timezone":"Asia/Ho_Chi_Minh",
    "iso:country":"VN",
    "name:und_x_variant":[
        "\u0110\u00e2m Th\u00f9y"
    ],
    "wof:name":"Dom Thuy",
    "wof:placetype":"locality"
},
  "geometry": {"coordinates":[105.93333,18.41667],"type":"Point"}
}