{
  "type": "Feature",
  "properties": {
    "gn:admin1_code":"71.0",
    "gn:asciiname":"Goc Keo",
    "gn:country_code":"VN",
    "gn:dem":19,
    "gn:feature_class":"P",
    "gn:feature_code":"PPL",
    "gn:name":"G\u1ed1c K\u00e9o",
    "gn:population":0,
    "gn:timezone":"Asia/Ho_Chi_Minh",
    "iso:country":"VN",
    "name:vie_x_preferred":[
        "G\u1ed1c K\u00e9o"
    ],
    "wof:name":"Goc Keo",
    "wof:placetype":"locality"
},
  "geometry": {"coordinates":[106.23278999999999,21.38897],"type":"Point"}
}