{
  "type": "Feature",
  "properties": {
    "gn:admin1_code":"32.0",
    "gn:asciiname":"Kouei Tiao",
    "gn:cc2":"VN",
    "gn:country_code":"VN",
    "gn:dem":821,
    "gn:feature_class":"P",
    "gn:feature_code":"PPL",
    "gn:name":"Kouei Tiao",
    "gn:population":0,
    "gn:timezone":"Asia/Ho_Chi_Minh",
    "iso:country":"VN",
    "name:und_x_variant":[
        "Kouai Tiao",
        "Kouei Tian",
        "Kouei Tiao"
    ],
    "wof:name":"Kouei Tiao",
    "wof:placetype":"locality"
},
  "geometry": {"coordinates":[103.78333000000001,21.68333],"type":"Point"}
}