{
  "type": "Feature",
  "properties": {
    "gn:admin1_code":"83.0",
    "gn:asciiname":"Dong Rao",
    "gn:country_code":"VN",
    "gn:dem":35,
    "gn:feature_class":"P",
    "gn:feature_code":"PPL",
    "gn:name":"D\u1ed3ng R\u00e0o",
    "gn:population":0,
    "gn:timezone":"Asia/Ho_Chi_Minh",
    "iso:country":"VN",
    "name:vie_x_preferred":[
        "D\u1ed3ng R\u00e0o"
    ],
    "wof:name":"Dong Rao",
    "wof:placetype":"locality"
},
  "geometry": {"coordinates":[105.04819999999999,21.44346],"type":"Point"}
}