{
  "type": "Feature",
  "properties": {
    "gn:admin1_code":"39.0",
    "gn:asciiname":"Thach Luong",
    "gn:country_code":"VN",
    "gn:dem":316,
    "gn:feature_class":"P",
    "gn:feature_code":"PPL",
    "gn:name":"Th\u1ea1ch L\u01b0\u01a1ng",
    "gn:population":0,
    "gn:timezone":"Asia/Ho_Chi_Minh",
    "iso:country":"VN",
    "name:vie_x_preferred":[
        "Th\u1ea1ch L\u01b0\u01a1ng"
    ],
    "wof:name":"Thach Luong",
    "wof:placetype":"locality"
},
  "geometry": {"coordinates":[106.50505,21.61941],"type":"Point"}
}