{
  "type": "Feature",
  "properties": {
    "gn:admin1_code":"90.0",
    "gn:asciiname":"In Tchong",
    "gn:country_code":"VN",
    "gn:dem":227,
    "gn:feature_class":"P",
    "gn:feature_code":"PPL",
    "gn:name":"In Tchong",
    "gn:population":0,
    "gn:timezone":"Asia/Ho_Chi_Minh",
    "iso:country":"VN",
    "name:und_x_variant":[
        "La Tchong",
        "In Tchang",
        "In Tchong"
    ],
    "wof:name":"In Tchong",
    "wof:placetype":"locality"
},
  "geometry": {"coordinates":[103.78333000000001,22.61667000000001],"type":"Point"}
}