{
  "type": "Feature",
  "properties": {
    "gn:admin1_code":"58.0",
    "gn:asciiname":"Lang Gien Da",
    "gn:country_code":"VN",
    "gn:dem":83,
    "gn:feature_class":"P",
    "gn:feature_code":"PPL",
    "gn:name":"L\u00e0ng Gi\u00ean \u0110\u00e1",
    "gn:population":0,
    "gn:timezone":"Asia/Ho_Chi_Minh",
    "iso:country":"VN",
    "wof:name":"Lang Gien Da",
    "wof:placetype":"locality"
},
  "geometry": {"coordinates":[105.48333,19.41667],"type":"Point"}
}