{
  "type": "Feature",
  "properties": {
    "gn:admin1_code":"74.0",
    "gn:asciiname":"Ngu Dai",
    "gn:country_code":"VN",
    "gn:dem":9,
    "gn:feature_class":"P",
    "gn:feature_code":"PPL",
    "gn:name":"Ng\u01b0 \u0110\u1ea1i",
    "gn:population":0,
    "gn:timezone":"Asia/Ho_Chi_Minh",
    "iso:country":"VN",
    "name:vie_x_preferred":[
        "Ng\u1ef1 \u0110\u1ea1i"
    ],
    "name:vie_x_variant":[
        "Ng\u01b0 \u0110\u1ea1i"
    ],
    "wof:name":"Ngu Dai",
    "wof:placetype":"locality"
},
  "geometry": {"coordinates":[106.12461999999999,21.19065],"type":"Point"}
}