{
  "type": "Feature",
  "properties": {
    "gn:admin1_code":"39.0",
    "gn:asciiname":"Dinh Lap",
    "gn:country_code":"VN",
    "gn:dem":189,
    "gn:feature_class":"P",
    "gn:feature_code":"PPLA2",
    "gn:name":"\u0110\u00ecnh L\u1eadp",
    "gn:population":0,
    "gn:timezone":"Asia/Ho_Chi_Minh",
    "iso:country":"VN",
    "name:vie_x_preferred":[
        "\u0110\u00ecnh L\u1eadp"
    ],
    "wof:name":"Dinh Lap",
    "wof:placetype":"locality"
},
  "geometry": {"coordinates":[107.09811999999999,21.54633],"type":"Point"}
}