{
  "type": "Feature",
  "properties": {
    "gn:admin1_code":"58.0",
    "gn:asciiname":"Thuong Quan",
    "gn:country_code":"VN",
    "gn:dem":16,
    "gn:feature_class":"P",
    "gn:feature_code":"PPL",
    "gn:name":"Th\u01b0\u1ee3ng Qu\u00e1n",
    "gn:population":0,
    "gn:timezone":"Asia/Ho_Chi_Minh",
    "iso:country":"VN",
    "name:vie_x_preferred":[
        "Th\u01b0\u1ee3ng Qu\u00e1n"
    ],
    "name:vie_x_variant":[
        "Th\u01b0\u1ee3ng Quan"
    ],
    "wof:name":"Thuong Quan",
    "wof:placetype":"locality"
},
  "geometry": {"coordinates":[105.32049000000001,18.75913],"type":"Point"}
}