{
  "type": "Feature",
  "properties": {
    "gn:admin1_code":"5.0",
    "gn:asciiname":"Nam Pieng",
    "gn:country_code":"VN",
    "gn:dem":856,
    "gn:feature_class":"P",
    "gn:feature_code":"PPL",
    "gn:name":"N\u1eb7m Pi\u00eang",
    "gn:population":0,
    "gn:timezone":"Asia/Ho_Chi_Minh",
    "iso:country":"VN",
    "name:und_x_variant":[
        "Nam Pi\u00e9ng"
    ],
    "name:vie_x_preferred":[
        "N\u1eb7m Pi\u00eang"
    ],
    "wof:name":"Nam Pieng",
    "wof:placetype":"locality"
},
  "geometry": {"coordinates":[105.33653,22.85673],"type":"Point"}
}