{
  "type": "Feature",
  "properties": {
    "gn:admin1_code":"32.0",
    "gn:asciiname":"Ban Nong Nghiu",
    "gn:country_code":"VN",
    "gn:dem":824,
    "gn:feature_class":"P",
    "gn:feature_code":"PPL",
    "gn:name":"B\u1ea3n N\u1ecdng Ngh\u1ecbu",
    "gn:population":0,
    "gn:timezone":"Asia/Ho_Chi_Minh",
    "iso:country":"VN",
    "name:vie_x_preferred":[
        "B\u1ea3n N\u1ecdng Ngh\u1ecbu"
    ],
    "wof:name":"Ban Nong Nghiu",
    "wof:placetype":"locality"
},
  "geometry": {"coordinates":[103.86344,21.23604],"type":"Point"}
}