{
  "type": "Feature",
  "properties": {
    "gn:admin1_code":"63.0",
    "gn:asciiname":"On Lanh",
    "gn:country_code":"VN",
    "gn:dem":70,
    "gn:feature_class":"P",
    "gn:feature_code":"PPL",
    "gn:name":"\u00d4n L\u00e3nh",
    "gn:population":0,
    "gn:timezone":"Asia/Ho_Chi_Minh",
    "iso:country":"VN",
    "wof:name":"On Lanh",
    "wof:placetype":"locality"
},
  "geometry": {"coordinates":[108.75,14.83333],"type":"Point"}
}