{
  "type": "Feature",
  "properties": {
    "gn:admin1_code":"30.0",
    "gn:asciiname":"Khe Tu",
    "gn:country_code":"VN",
    "gn:dem":9,
    "gn:feature_class":"P",
    "gn:feature_code":"PPL",
    "gn:name":"Kh\u00ea T\u01b0",
    "gn:population":0,
    "gn:timezone":"Asia/Ho_Chi_Minh",
    "iso:country":"VN",
    "wof:name":"Khe Tu",
    "wof:placetype":"locality"
},
  "geometry": {"coordinates":[107.40000000000001,21.33333],"type":"Point"}
}