{
  "type": "Feature",
  "properties": {
    "gn:admin1_code":"69.0",
    "gn:asciiname":"Phu Hu Yen",
    "gn:country_code":"VN",
    "gn:dem":5,
    "gn:feature_class":"P",
    "gn:feature_code":"PPL",
    "gn:name":"Ph\u00fa H\u1ee7 Y\u00ean",
    "gn:population":0,
    "gn:timezone":"Asia/Ho_Chi_Minh",
    "iso:country":"VN",
    "name:vie_x_preferred":[
        "Ph\u00fa H\u1ee7 Y\u00ean"
    ],
    "wof:name":"Phu Hu Yen",
    "wof:placetype":"locality"
},
  "geometry": {"coordinates":[105.90156,10.11084],"type":"Point"}
}