{
  "type": "Feature",
  "properties": {
    "gn:admin1_code":"44.0",
    "gn:asciiname":"An Thinh",
    "gn:country_code":"VN",
    "gn:dem":37,
    "gn:feature_class":"P",
    "gn:feature_code":"PPL",
    "gn:name":"An Th\u1ecbnh",
    "gn:population":0,
    "gn:timezone":"Asia/Ho_Chi_Minh",
    "iso:country":"VN",
    "name:vie_x_preferred":[
        "An Th\u1ecbnh"
    ],
    "wof:name":"An Thinh",
    "wof:placetype":"locality"
},
  "geometry": {"coordinates":[105.37532,21.18205],"type":"Point"}
}