{
  "type": "Feature",
  "properties": {
    "gn:admin1_code":"88.0",
    "gn:asciiname":"Buon Lung Quang",
    "gn:country_code":"VN",
    "gn:dem":482,
    "gn:feature_class":"P",
    "gn:feature_code":"PPL",
    "gn:name":"Bu\u00f4n L\u0169ng Quang",
    "gn:population":0,
    "gn:timezone":"Asia/Ho_Chi_Minh",
    "iso:country":"VN",
    "name:vie_x_preferred":[
        "Bu\u00f4n L\u0169ng Quang"
    ],
    "wof:name":"Buon Lung Quang",
    "wof:placetype":"locality"
},
  "geometry": {"coordinates":[108.51083,12.95703],"type":"Point"}
}