{
  "type": "Feature",
  "properties": {
    "gn:admin1_code":"5.0",
    "gn:asciiname":"Mou Tiou Tan",
    "gn:country_code":"VN",
    "gn:dem":1244,
    "gn:feature_class":"P",
    "gn:feature_code":"PPL",
    "gn:name":"Mou Tiou Tan",
    "gn:population":0,
    "gn:timezone":"Asia/Ho_Chi_Minh",
    "iso:country":"VN",
    "wof:name":"Mou Tiou Tan",
    "wof:placetype":"locality"
},
  "geometry": {"coordinates":[105.56667,22.81667],"type":"Point"}
}