{
  "type": "Feature",
  "properties": {
    "gn:admin1_code":"32.0",
    "gn:asciiname":"Ban Hon",
    "gn:country_code":"VN",
    "gn:dem":394,
    "gn:feature_class":"P",
    "gn:feature_code":"PPL",
    "gn:name":"B\u1ea3n H\u00f3n",
    "gn:population":0,
    "gn:timezone":"Asia/Ho_Chi_Minh",
    "iso:country":"VN",
    "name:vie_x_preferred":[
        "B\u1ea3n H\u00f3n"
    ],
    "wof:name":"Ban Hon",
    "wof:placetype":"locality"
},
  "geometry": {"coordinates":[103.87736,21.00063],"type":"Point"}
}