{
  "type": "Feature",
  "properties": {
    "gn:admin1_code":"32.0",
    "gn:asciiname":"Ban Cho Cong",
    "gn:country_code":"VN",
    "gn:dem":623,
    "gn:feature_class":"P",
    "gn:feature_code":"PPL",
    "gn:name":"B\u1ea3n Cho C\u00f4ng",
    "gn:population":0,
    "gn:timezone":"Asia/Ho_Chi_Minh",
    "iso:country":"VN",
    "name:und_x_variant":[
        "Cho C\u00f4ng"
    ],
    "name:vie_x_preferred":[
        "B\u1ea3n Cho C\u00f4ng"
    ],
    "wof:name":"Ban Cho Cong",
    "wof:placetype":"locality"
},
  "geometry": {"coordinates":[103.81814,21.15576],"type":"Point"}
}