{
  "type": "Feature",
  "properties": {
    "gn:admin1_code":"19.0",
    "gn:asciiname":"Phay Cau",
    "gn:country_code":"VN",
    "gn:dem":1006,
    "gn:feature_class":"P",
    "gn:feature_code":"PPL",
    "gn:name":"Phay Cau",
    "gn:population":0,
    "gn:timezone":"Asia/Ho_Chi_Minh",
    "iso:country":"VN",
    "wof:name":"Phay Cau",
    "wof:placetype":"locality"
},
  "geometry": {"coordinates":[103.91667,21.73333],"type":"Point"}
}