{
  "type": "Feature",
  "properties": {
    "gn:admin1_code":"64.0",
    "gn:asciiname":"Thu Luat",
    "gn:country_code":"VN",
    "gn:dem":10,
    "gn:feature_class":"P",
    "gn:feature_code":"PPL",
    "gn:name":"Th\u1eed Lu\u1eadt",
    "gn:population":0,
    "gn:timezone":"Asia/Ho_Chi_Minh",
    "iso:country":"VN",
    "name:und_x_variant":[
        "Th\u1eed Lu\u00e2t",
        "Th\u01b0 Lu\u1eadt"
    ],
    "name:vie_x_preferred":[
        "Th\u1eed Lu\u1eadt"
    ],
    "name:vie_x_variant":[
        "Th\u1ee9 Lu\u1eadt"
    ],
    "wof:name":"Thu Luat",
    "wof:placetype":"locality"
},
  "geometry": {"coordinates":[107.03918,17.12262],"type":"Point"}
}