{
  "type": "Feature",
  "properties": {
    "gn:admin1_code":"90.0",
    "gn:asciiname":"Cam Duong",
    "gn:country_code":"VN",
    "gn:dem":109,
    "gn:feature_class":"P",
    "gn:feature_code":"PPL",
    "gn:name":"Cam \u0110\u01b0\u1eddng",
    "gn:population":0,
    "gn:timezone":"Asia/Ho_Chi_Minh",
    "iso:country":"VN",
    "wof:name":"Cam Duong",
    "wof:placetype":"locality"
},
  "geometry": {"coordinates":[104.01667,22.41667],"type":"Point"}
}