{
  "type": "Feature",
  "properties": {
    "gn:admin1_code":"72.0",
    "gn:asciiname":"Ban Lung",
    "gn:country_code":"VN",
    "gn:dem":260,
    "gn:feature_class":"P",
    "gn:feature_code":"PPL",
    "gn:name":"B\u1ea3n L\u00f9ng",
    "gn:population":0,
    "gn:timezone":"Asia/Ho_Chi_Minh",
    "iso:country":"VN",
    "name:und_x_variant":[
        "B\u1ea3n L\u00f9ng",
        "B\u1ea3n Loung"
    ],
    "wof:name":"Ban Lung",
    "wof:placetype":"locality"
},
  "geometry": {"coordinates":[105.82297,22.36178],"type":"Point"}
}