{
  "type": "Feature",
  "properties": {
    "gn:admin1_code":"92.0",
    "gn:asciiname":"Ban Houei Lich",
    "gn:country_code":"VN",
    "gn:dem":979,
    "gn:feature_class":"P",
    "gn:feature_code":"PPL",
    "gn:name":"B\u1ea3n Houei Lich",
    "gn:population":0,
    "gn:timezone":"Asia/Ho_Chi_Minh",
    "iso:country":"VN",
    "wof:name":"Ban Houei Lich",
    "wof:placetype":"locality"
},
  "geometry": {"coordinates":[103.23333,21.41667],"type":"Point"}
}