{
  "type": "Feature",
  "properties": {
    "gn:admin1_code":"9.0",
    "gn:asciiname":"Lap Vo",
    "gn:country_code":"VN",
    "gn:dem":9,
    "gn:feature_class":"P",
    "gn:feature_code":"PPLA2",
    "gn:name":"L\u1ea5p V\u00f2",
    "gn:population":0,
    "gn:timezone":"Asia/Ho_Chi_Minh",
    "iso:country":"VN",
    "name:vie_x_preferred":[
        "L\u1ea5p V\u00f2"
    ],
    "wof:name":"Lap Vo",
    "wof:placetype":"locality"
},
  "geometry": {"coordinates":[105.51924,10.36161],"type":"Point"}
}