{
  "type": "Feature",
  "properties": {
    "gn:admin1_code":"68.0",
    "gn:asciiname":"Kouei Kien",
    "gn:country_code":"VN",
    "gn:dem":726,
    "gn:feature_class":"P",
    "gn:feature_code":"PPL",
    "gn:name":"Kouei Kien",
    "gn:population":0,
    "gn:timezone":"Asia/Ho_Chi_Minh",
    "iso:country":"VN",
    "name:und_x_variant":[
        "Kouni Kran",
        "Kouei Kien"
    ],
    "wof:name":"Kouei Kien",
    "wof:placetype":"locality"
},
  "geometry": {"coordinates":[105.18333,22.51667],"type":"Point"}
}