{
  "type": "Feature",
  "properties": {
    "gn:admin1_code":"83.0",
    "gn:asciiname":"Phong Dang",
    "gn:country_code":"VN",
    "gn:dem":27,
    "gn:feature_class":"P",
    "gn:feature_code":"PPL",
    "gn:name":"Phong \u0110\u0103ng",
    "gn:population":0,
    "gn:timezone":"Asia/Ho_Chi_Minh",
    "iso:country":"VN",
    "name:vie_x_preferred":[
        "Phong \u0110\u0103ng"
    ],
    "wof:name":"Phong Dang",
    "wof:placetype":"locality"
},
  "geometry": {"coordinates":[105.27028,21.42],"type":"Point"}
}