{
  "type": "Feature",
  "properties": {
    "gn:admin1_code":"39.0",
    "gn:asciiname":"Pa Chi",
    "gn:country_code":"VN",
    "gn:dem":393,
    "gn:feature_class":"P",
    "gn:feature_code":"PPL",
    "gn:name":"P\u00e1 Ch\u00ec",
    "gn:population":0,
    "gn:timezone":"Asia/Ho_Chi_Minh",
    "iso:country":"VN",
    "name:vie_x_preferred":[
        "P\u00e1 Ch\u00ec"
    ],
    "wof:name":"Pa Chi",
    "wof:placetype":"locality"
},
  "geometry": {"coordinates":[106.36793,21.80613],"type":"Point"}
}