{
  "type": "Feature",
  "properties": {
    "gn:admin1_code":"89.0",
    "gn:asciiname":"Ban Na Phat",
    "gn:country_code":"VN",
    "gn:dem":541,
    "gn:feature_class":"P",
    "gn:feature_code":"PPL",
    "gn:name":"B\u1ea3n N\u00e0 Ph\u00e1t",
    "gn:population":0,
    "gn:timezone":"Asia/Ho_Chi_Minh",
    "iso:country":"VN",
    "name:vie_x_preferred":[
        "B\u1ea3n N\u00e0 Ph\u00e1t"
    ],
    "wof:name":"Ban Na Phat",
    "wof:placetype":"locality"
},
  "geometry": {"coordinates":[103.90127,22.02087],"type":"Point"}
}