{
  "type": "Feature",
  "properties": {
    "gn:admin1_code":"23.0",
    "gn:admin2_code":"673.0",
    "gn:asciiname":"Bao Loc",
    "gn:country_code":"VN",
    "gn:dem":841,
    "gn:feature_class":"P",
    "gn:feature_code":"PPLA2",
    "gn:name":"B\u1ea3o L\u1ed9c",
    "gn:population":151915,
    "gn:timezone":"Asia/Ho_Chi_Minh",
    "iso:country":"VN",
    "name:rus_x_preferred":[
        "\u0411\u0430\u043e\u043b\u043e\u043a"
    ],
    "name:und_x_variant":[
        "\u1ea4p Th\u00e1nh T\u00e2m",
        "Cong Hinh",
        "Blao",
        "Ban Lao",
        "B\u1ea3o L\u1ed9c"
    ],
    "wof:name":"Bao Loc",
    "wof:placetype":"locality",
    "wof:population":151915
},
  "geometry": {"coordinates":[107.80772,11.54798],"type":"Point"}
}