{
  "type": "Feature",
  "properties": {
    "gn:admin1_code":"23.0",
    "gn:admin2_code":"673.0",
    "gn:asciiname":"Bao Loc",
    "gn:country_code":"VN",
    "gn:dem":841,
    "gn:feature_class":"P",
    "gn:feature_code":"PPLA2",
    "gn:name":"B\u1ea3o L\u1ed9c",
    "gn:population":151915,
    "gn:timezone":"Asia/Ho_Chi_Minh",
    "iso:country":"VN",
    "name:ara_x_preferred":[
        "\u0628\u0627\u0648 \u0644\u0627\u0643"
    ],
    "name:bul_x_preferred":[
        "\u0411\u0430\u043e \u041b\u043e\u043a"
    ],
    "name:ceb_x_preferred":[
        "B\u1ea3o L\u1ed9c"
    ],
    "name:ita_x_preferred":[
        "B\u1ea3o L\u1ed9c"
    ],
    "name:jpn_x_preferred":[
        "\u30d0\u30aa\u30ed\u30af"
    ],
    "name:kor_x_preferred":[
        "\ubc14\uc624\ub85d"
    ],
    "name:nor_x_preferred":[
        "B\u1ea3o L\u1ed9c"
    ],
    "name:pol_x_preferred":[
        "B\u1ea3o L\u1ed9c"
    ],
    "name:rus_x_preferred":[
        "\u0411\u0430\u043e\u043b\u043e\u043a"
    ],
    "name:srp_x_preferred":[
        "B\u1ea3o L\u1ed9c"
    ],
    "name:swe_x_preferred":[
        "Bao Loc"
    ],
    "name:tha_x_preferred":[
        "\u0e1a\u0e4b\u0e32\u0e27\u0e2b\u0e25\u0e01"
    ],
    "name:und_x_variant":[
        "\u1ea4p Th\u00e1nh T\u00e2m",
        "Cong Hinh",
        "Blao",
        "Ban Lao"
    ],
    "name:urd_x_preferred":[
        "\u0628\u0622\u0648 \u0644\u0622\u06a9"
    ],
    "name:vie_x_preferred":[
        "B\u1ea3o L\u1ed9c"
    ],
    "name:zho_x_preferred":[
        "\u4fdd\u7984\u5e02"
    ],
    "wof:name":"Bao Loc",
    "wof:placetype":"locality",
    "wof:population":151915
},
  "geometry": {"coordinates":[107.80772,11.54798],"type":"Point"}
}