{
  "type": "Feature",
  "properties": {
    "gn:admin1_code":"50.0",
    "gn:asciiname":"Kouei Miay",
    "gn:country_code":"VN",
    "gn:dem":312,
    "gn:feature_class":"P",
    "gn:feature_code":"PPL",
    "gn:name":"Kouei Miay",
    "gn:population":0,
    "gn:timezone":"Asia/Ho_Chi_Minh",
    "iso:country":"VN",
    "wof:name":"Kouei Miay",
    "wof:placetype":"locality"
},
  "geometry": {"coordinates":[105.36667,23.05],"type":"Point"}
}