{
  "type": "Feature",
  "properties": {
    "gn:admin1_code":"61.0",
    "gn:asciiname":"Thanh Hoi",
    "gn:country_code":"VN",
    "gn:dem":31,
    "gn:feature_class":"P",
    "gn:feature_code":"PPL",
    "gn:name":"Thanh H\u1ed9i",
    "gn:population":0,
    "gn:timezone":"Asia/Ho_Chi_Minh",
    "iso:country":"VN",
    "name:und_x_variant":[
        "Dong Ly",
        "Thanh H\u1ed9i"
    ],
    "wof:name":"Thanh Hoi",
    "wof:placetype":"locality"
},
  "geometry": {"coordinates":[109.05,13.03333],"type":"Point"}
}