{
  "type": "Feature",
  "properties": {
    "gn:admin1_code":"10.0",
    "gn:asciiname":"Dak Totuong",
    "gn:cc2":"VN",
    "gn:country_code":"VN",
    "gn:dem":1048,
    "gn:feature_class":"P",
    "gn:feature_code":"PPL",
    "gn:name":"Dak Totuong",
    "gn:population":0,
    "gn:timezone":"Asia/Ho_Chi_Minh",
    "iso:country":"VN",
    "name:und_x_variant":[
        "Kon Totuong",
        "Dak Totuong"
    ],
    "wof:name":"Dak Totuong",
    "wof:placetype":"locality"
},
  "geometry": {"coordinates":[108.26667,14.38333],"type":"Point"}
}