{
  "type": "Feature",
  "properties": {
    "gn:admin1_code":"49.0",
    "gn:asciiname":"Lang T'Nung",
    "gn:country_code":"VN",
    "gn:dem":338,
    "gn:feature_class":"P",
    "gn:feature_code":"PPL",
    "gn:name":"L\u00e0ng T\u2019Nung",
    "gn:population":0,
    "gn:timezone":"Asia/Ho_Chi_Minh",
    "iso:country":"VN",
    "name:vie_x_preferred":[
        "L\u00e0ng T\u2019Nung"
    ],
    "wof:name":"Lang T'Nung",
    "wof:placetype":"locality"
},
  "geometry": {"coordinates":[108.50671,13.81175],"type":"Point"}
}