{
  "type": "Feature",
  "properties": {
    "gn:admin1_code":"32.0",
    "gn:asciiname":"Ban Tong Chinh",
    "gn:country_code":"VN",
    "gn:dem":1120,
    "gn:feature_class":"P",
    "gn:feature_code":"PPL",
    "gn:name":"B\u1ea3n Tong Chinh",
    "gn:population":0,
    "gn:timezone":"Asia/Ho_Chi_Minh",
    "iso:country":"VN",
    "name:vie_x_preferred":[
        "B\u1ea3n Tong Chinh"
    ],
    "wof:name":"Ban Tong Chinh",
    "wof:placetype":"locality"
},
  "geometry": {"coordinates":[103.86393,21.06636],"type":"Point"}
}