{
  "type": "Feature",
  "properties": {
    "gn:admin1_code":"90.0",
    "gn:asciiname":"Ban Chu Sang",
    "gn:country_code":"VN",
    "gn:dem":1131,
    "gn:feature_class":"P",
    "gn:feature_code":"PPL",
    "gn:name":"B\u1ea3n Ch\u01b0 Sang",
    "gn:population":0,
    "gn:timezone":"Asia/Ho_Chi_Minh",
    "iso:country":"VN",
    "name:vie_x_preferred":[
        "B\u1ea3n Ch\u01b0 Sang"
    ],
    "wof:name":"Ban Chu Sang",
    "wof:placetype":"locality"
},
  "geometry": {"coordinates":[104.29541999999999,22.64639],"type":"Point"}
}