{
  "type": "Feature",
  "properties": {
    "gn:admin1_code":"89.0",
    "gn:asciiname":"Khoang Chu Tsao",
    "gn:country_code":"VN",
    "gn:dem":935,
    "gn:feature_class":"P",
    "gn:feature_code":"PPL",
    "gn:name":"Khoang Ch\u00f9 Tsao",
    "gn:population":0,
    "gn:timezone":"Asia/Ho_Chi_Minh",
    "iso:country":"VN",
    "wof:name":"Khoang Chu Tsao",
    "wof:placetype":"locality"
},
  "geometry": {"coordinates":[103.21666999999999,22.51667],"type":"Point"}
}