{
  "type": "Feature",
  "properties": {
    "gn:admin1_code":"63.0",
    "gn:asciiname":"Lang Pan",
    "gn:country_code":"VN",
    "gn:dem":572,
    "gn:feature_class":"P",
    "gn:feature_code":"PPL",
    "gn:name":"L\u00e0ng Pan",
    "gn:population":0,
    "gn:timezone":"Asia/Ho_Chi_Minh",
    "iso:country":"VN",
    "wof:name":"Lang Pan",
    "wof:placetype":"locality"
},
  "geometry": {"coordinates":[108.41667,15.13333],"type":"Point"}
}