{
  "type": "Feature",
  "properties": {
    "gn:admin1_code":"5.0",
    "gn:asciiname":"Lung Hoai",
    "gn:country_code":"VN",
    "gn:dem":518,
    "gn:feature_class":"P",
    "gn:feature_code":"PPL",
    "gn:name":"L\u0169ng Hoai",
    "gn:population":0,
    "gn:timezone":"Asia/Ho_Chi_Minh",
    "iso:country":"VN",
    "wof:name":"Lung Hoai",
    "wof:placetype":"locality"
},
  "geometry": {"coordinates":[106.59999999999999,22.81667],"type":"Point"}
}