{
  "type": "Feature",
  "properties": {
    "gn:admin1_code":"49.0",
    "gn:asciiname":"Plei Ya Yang",
    "gn:country_code":"VN",
    "gn:dem":608,
    "gn:feature_class":"P",
    "gn:feature_code":"PPL",
    "gn:name":"Plei Ya Yang",
    "gn:population":0,
    "gn:timezone":"Asia/Ho_Chi_Minh",
    "iso:country":"VN",
    "wof:name":"Plei Ya Yang",
    "wof:placetype":"locality"
},
  "geometry": {"coordinates":[107.90000000000001,14.18333],"type":"Point"}
}