{
  "type": "Feature",
  "properties": {
    "gn:admin1_code":"32.0",
    "gn:asciiname":"Ban Tieng",
    "gn:country_code":"VN",
    "gn:dem":448,
    "gn:feature_class":"P",
    "gn:feature_code":"PPL",
    "gn:name":"B\u1ea3n Tieng",
    "gn:population":0,
    "gn:timezone":"Asia/Ho_Chi_Minh",
    "iso:country":"VN",
    "name:und_x_variant":[
        "Ban Tienu",
        "B\u1ea3n Tieng"
    ],
    "wof:name":"Ban Tieng",
    "wof:placetype":"locality"
},
  "geometry": {"coordinates":[104.78333000000001,21.06667],"type":"Point"}
}