{
  "type": "Feature",
  "properties": {
    "gn:admin1_code":"63.0",
    "gn:asciiname":"O Ka",
    "gn:country_code":"VN",
    "gn:dem":106,
    "gn:feature_class":"P",
    "gn:feature_code":"PPL",
    "gn:name":"\u00d4 Ka",
    "gn:population":0,
    "gn:timezone":"Asia/Ho_Chi_Minh",
    "iso:country":"VN",
    "wof:name":"O Ka",
    "wof:placetype":"locality"
},
  "geometry": {"coordinates":[108.75,14.96667],"type":"Point"}
}