{
  "type": "Feature",
  "properties": {
    "gn:admin1_code":"49.0",
    "gn:asciiname":"Ban Hoang",
    "gn:country_code":"VN",
    "gn:dem":329,
    "gn:feature_class":"P",
    "gn:feature_code":"PPL",
    "gn:name":"Ban Hoang",
    "gn:population":0,
    "gn:timezone":"Asia/Ho_Chi_Minh",
    "iso:country":"VN",
    "name:und_x_variant":[
        "Buon Hoang",
        "Ban Hoang"
    ],
    "wof:name":"Ban Hoang",
    "wof:placetype":"locality"
},
  "geometry": {"coordinates":[108.48333,13.28333],"type":"Point"}
}