{
  "type": "Feature",
  "properties": {
    "gn:admin1_code":"89.0",
    "gn:asciiname":"Ta Phing",
    "gn:country_code":"VN",
    "gn:dem":1700,
    "gn:feature_class":"P",
    "gn:feature_code":"PPL",
    "gn:name":"Ta Phing",
    "gn:population":0,
    "gn:timezone":"Asia/Ho_Chi_Minh",
    "iso:country":"VN",
    "wof:name":"Ta Phing",
    "wof:placetype":"locality"
},
  "geometry": {"coordinates":[103.21666999999999,22.35],"type":"Point"}
}