{
  "type": "Feature",
  "properties": {
    "gn:admin1_code":"62.0",
    "gn:asciiname":"Hung Trung",
    "gn:country_code":"VN",
    "gn:dem":216,
    "gn:feature_class":"P",
    "gn:feature_code":"PPL",
    "gn:name":"H\u01b0ng Trung",
    "gn:population":0,
    "gn:timezone":"Asia/Ho_Chi_Minh",
    "iso:country":"VN",
    "wof:name":"Hung Trung",
    "wof:placetype":"locality"
},
  "geometry": {"coordinates":[105.98333,17.68332999999999],"type":"Point"}
}