{
  "type": "Feature",
  "properties": {
    "gn:admin1_code":"83.0",
    "gn:asciiname":"Chieu Ung",
    "gn:country_code":"VN",
    "gn:dem":35,
    "gn:feature_class":"P",
    "gn:feature_code":"PPL",
    "gn:name":"Chi\u00eau \u01afng",
    "gn:population":0,
    "gn:timezone":"Asia/Ho_Chi_Minh",
    "iso:country":"VN",
    "name:und_x_variant":[
        "Chi\u1ec3u \u1ee8ng"
    ],
    "name:vie_x_preferred":[
        "Chi\u00eau \u01afng"
    ],
    "wof:name":"Chieu Ung",
    "wof:placetype":"locality"
},
  "geometry": {"coordinates":[105.17574999999999,21.41186],"type":"Point"}
}