{
  "type": "Feature",
  "properties": {
    "gn:admin1_code":"71.0",
    "gn:asciiname":"Phuc Lam",
    "gn:country_code":"VN",
    "gn:dem":10,
    "gn:feature_class":"P",
    "gn:feature_code":"PPL",
    "gn:name":"Ph\u00fac L\u00e2m",
    "gn:population":0,
    "gn:timezone":"Asia/Ho_Chi_Minh",
    "iso:country":"VN",
    "name:vie_x_preferred":[
        "Ph\u00fac L\u00e2m"
    ],
    "wof:name":"Phuc Lam",
    "wof:placetype":"locality"
},
  "geometry": {"coordinates":[106.10257,21.24742],"type":"Point"}
}