{
  "type": "Feature",
  "properties": {
    "gn:admin1_code":"74.0",
    "gn:asciiname":"Vang Thon",
    "gn:country_code":"VN",
    "gn:dem":5,
    "gn:feature_class":"P",
    "gn:feature_code":"PPL",
    "gn:name":"V\u00e0ng Th\u00f4n",
    "gn:population":0,
    "gn:timezone":"Asia/Ho_Chi_Minh",
    "iso:country":"VN",
    "name:vie_x_preferred":[
        "V\u00e0ng Th\u00f4n"
    ],
    "wof:name":"Vang Thon",
    "wof:placetype":"locality"
},
  "geometry": {"coordinates":[106.20453000000001,21.05903],"type":"Point"}
}