{
  "type": "Feature",
  "properties": {
    "gn:admin1_code":"58.0",
    "gn:asciiname":"Lang Soi",
    "gn:country_code":"VN",
    "gn:dem":114,
    "gn:feature_class":"P",
    "gn:feature_code":"PPL",
    "gn:name":"L\u00e0ng S\u1ecfi",
    "gn:population":0,
    "gn:timezone":"Asia/Ho_Chi_Minh",
    "iso:country":"VN",
    "name:vie_x_preferred":[
        "L\u00e0ng S\u1ecfi"
    ],
    "wof:name":"Lang Soi",
    "wof:placetype":"locality"
},
  "geometry": {"coordinates":[105.52315,19.38206],"type":"Point"}
}