{
  "type": "Feature",
  "properties": {
    "gn:admin1_code":"43.0",
    "gn:asciiname":"Ap Hoan Quang",
    "gn:country_code":"VN",
    "gn:dem":246,
    "gn:feature_class":"P",
    "gn:feature_code":"PPL",
    "gn:name":"\u1ea4p Ho\u00e1n Quang",
    "gn:population":0,
    "gn:timezone":"Asia/Ho_Chi_Minh",
    "iso:country":"VN",
    "wof:name":"Ap Hoan Quang",
    "wof:placetype":"locality"
},
  "geometry": {"coordinates":[107.23333,10.78333],"type":"Point"}
}