{
  "type": "Feature",
  "properties": {
    "gn:admin1_code":"39.0",
    "gn:asciiname":"Lung Phuc",
    "gn:country_code":"VN",
    "gn:dem":321,
    "gn:feature_class":"P",
    "gn:feature_code":"PPL",
    "gn:name":"L\u0169ng Ph\u00fac",
    "gn:population":0,
    "gn:timezone":"Asia/Ho_Chi_Minh",
    "iso:country":"VN",
    "name:vie_x_preferred":[
        "L\u0169ng Ph\u00fac"
    ],
    "wof:name":"Lung Phuc",
    "wof:placetype":"locality"
},
  "geometry": {"coordinates":[106.44952000000001,21.77427],"type":"Point"}
}