{
  "type": "Feature",
  "properties": {
    "gn:admin1_code":"39.0",
    "gn:asciiname":"Co Cai",
    "gn:country_code":"VN",
    "gn:dem":368,
    "gn:feature_class":"P",
    "gn:feature_code":"PPL",
    "gn:name":"C\u00f4 Cai",
    "gn:population":0,
    "gn:timezone":"Asia/Ho_Chi_Minh",
    "iso:country":"VN",
    "wof:name":"Co Cai",
    "wof:placetype":"locality"
},
  "geometry": {"coordinates":[107.03333000000001,21.71667],"type":"Point"}
}