{
  "type": "Feature",
  "properties": {
    "gn:admin1_code":"1.0",
    "gn:asciiname":"Hoa Tan",
    "gn:country_code":"VN",
    "gn:dem":6,
    "gn:feature_class":"P",
    "gn:feature_code":"PPL",
    "gn:name":"H\u00f2a T\u00e2n",
    "gn:population":0,
    "gn:timezone":"Asia/Ho_Chi_Minh",
    "iso:country":"VN",
    "name:vie_x_preferred":[
        "H\u00f2a T\u00e2n"
    ],
    "wof:name":"Hoa Tan",
    "wof:placetype":"locality"
},
  "geometry": {"coordinates":[105.2958,10.30151],"type":"Point"}
}