{
  "type": "Feature",
  "properties": {
    "gn:admin1_code":"89.0",
    "gn:asciiname":"Ban San Nga",
    "gn:country_code":"VN",
    "gn:dem":529,
    "gn:feature_class":"P",
    "gn:feature_code":"PPL",
    "gn:name":"B\u1ea3n San Ng\u00e0",
    "gn:population":0,
    "gn:timezone":"Asia/Ho_Chi_Minh",
    "iso:country":"VN",
    "name:und_x_variant":[
        "San Nga",
        "Sa Ng\u00e0"
    ],
    "name:vie_x_preferred":[
        "B\u1ea3n San Ng\u00e0"
    ],
    "wof:name":"Ban San Nga",
    "wof:placetype":"locality"
},
  "geometry": {"coordinates":[103.88997999999999,22.03598],"type":"Point"}
}