{
  "type": "Feature",
  "properties": {
    "gn:admin1_code":"39.0",
    "gn:asciiname":"La Ho",
    "gn:country_code":"VN",
    "gn:dem":407,
    "gn:feature_class":"P",
    "gn:feature_code":"PPL",
    "gn:name":"L\u00e0 H\u00f3",
    "gn:population":0,
    "gn:timezone":"Asia/Ho_Chi_Minh",
    "iso:country":"VN",
    "name:vie_x_preferred":[
        "L\u00e0 H\u00f3"
    ],
    "wof:name":"La Ho",
    "wof:placetype":"locality"
},
  "geometry": {"coordinates":[106.30596,21.8986],"type":"Point"}
}