{
  "type": "Feature",
  "properties": {
    "gn:admin1_code":"39.0",
    "gn:asciiname":"Khe Cay",
    "gn:country_code":"VN",
    "gn:dem":81,
    "gn:feature_class":"P",
    "gn:feature_code":"PPL",
    "gn:name":"Khe C\u1ea3y",
    "gn:population":0,
    "gn:timezone":"Asia/Ho_Chi_Minh",
    "iso:country":"VN",
    "name:vie_x_preferred":[
        "Khe C\u1ea3y"
    ],
    "wof:name":"Khe Cay",
    "wof:placetype":"locality"
},
  "geometry": {"coordinates":[107.21505999999999,21.42043],"type":"Point"}
}