{
  "type": "Feature",
  "properties": {
    "gn:admin1_code":"21.0",
    "gn:asciiname":"Ap Vinh Dong",
    "gn:country_code":"VN",
    "gn:dem":4,
    "gn:feature_class":"P",
    "gn:feature_code":"PPL",
    "gn:name":"\u1ea4p V\u0129nh \u0110\u00f4ng",
    "gn:population":0,
    "gn:timezone":"Asia/Ho_Chi_Minh",
    "iso:country":"VN",
    "wof:name":"Ap Vinh Dong",
    "wof:placetype":"locality"
},
  "geometry": {"coordinates":[105.26667,9.51667],"type":"Point"}
}