{
  "type": "Feature",
  "properties": {
    "gn:admin1_code":"46.0",
    "gn:asciiname":"Tien Long",
    "gn:country_code":"VN",
    "gn:dem":56,
    "gn:feature_class":"P",
    "gn:feature_code":"PPL",
    "gn:name":"Ti\u00ean Long",
    "gn:population":0,
    "gn:timezone":"Asia/Ho_Chi_Minh",
    "iso:country":"VN",
    "wof:name":"Tien Long",
    "wof:placetype":"locality"
},
  "geometry": {"coordinates":[108.83333,14.03333],"type":"Point"}
}