{
  "type": "Feature",
  "properties": {
    "gn:admin1_code":"58.0",
    "gn:asciiname":"Ban Xay",
    "gn:country_code":"VN",
    "gn:dem":172,
    "gn:feature_class":"P",
    "gn:feature_code":"PPL",
    "gn:name":"B\u1ea3n X\u00e2y",
    "gn:population":0,
    "gn:timezone":"Asia/Ho_Chi_Minh",
    "iso:country":"VN",
    "name:vie_x_preferred":[
        "B\u1ea3n X\u00e2y"
    ],
    "wof:name":"Ban Xay",
    "wof:placetype":"locality"
},
  "geometry": {"coordinates":[105.14241,19.23092],"type":"Point"}
}