{
  "type": "Feature",
  "properties": {
    "gn:admin1_code":"50.0",
    "gn:asciiname":"Khau Nhoa",
    "gn:country_code":"VN",
    "gn:dem":577,
    "gn:feature_class":"P",
    "gn:feature_code":"PPL",
    "gn:name":"Kh\u00e2u Nh\u00f2a",
    "gn:population":0,
    "gn:timezone":"Asia/Ho_Chi_Minh",
    "iso:country":"VN",
    "name:vie_x_preferred":[
        "Kh\u00e2u Nh\u00f2a"
    ],
    "wof:name":"Khau Nhoa",
    "wof:placetype":"locality"
},
  "geometry": {"coordinates":[105.31328999999999,22.80686],"type":"Point"}
}