{
  "type": "Feature",
  "properties": {
    "gn:admin1_code":"65.0",
    "gn:asciiname":"Xom Chec",
    "gn:cc2":"VN",
    "gn:country_code":"VN",
    "gn:dem":-4,
    "gn:feature_class":"P",
    "gn:feature_code":"PPL",
    "gn:name":"X\u00f3m Ch\u1ec7c",
    "gn:population":0,
    "gn:timezone":"Asia/Ho_Chi_Minh",
    "iso:country":"VN",
    "name:und_x_variant":[
        "Ch\u1ec7c",
        "X\u00f3m Ch\u1ec7c"
    ],
    "wof:name":"Xom Chec",
    "wof:placetype":"locality"
},
  "geometry": {"coordinates":[106.11028,9.495],"type":"Point"}
}