{
  "type": "Feature",
  "properties": {
    "gn:admin1_code":"30.0",
    "gn:asciiname":"Co Gian",
    "gn:cc2":"VN",
    "gn:country_code":"VN",
    "gn:dem":2,
    "gn:feature_class":"P",
    "gn:feature_code":"PPL",
    "gn:name":"C\u1ed5 Gi\u1ea3n",
    "gn:population":0,
    "gn:timezone":"Asia/Ho_Chi_Minh",
    "iso:country":"VN",
    "name:und_x_variant":[
        "Co Gain",
        "C\u1ed5 Gi\u1ea3n"
    ],
    "wof:name":"Co Gian",
    "wof:placetype":"locality"
},
  "geometry": {"coordinates":[106.58333,21.06667],"type":"Point"}
}