{
  "type": "Feature",
  "properties": {
    "gn:admin1_code":"49.0",
    "gn:asciiname":"Plei Potao Kla",
    "gn:country_code":"VN",
    "gn:dem":403,
    "gn:feature_class":"P",
    "gn:feature_code":"PPL",
    "gn:name":"Plei P\u01a1tao Kla",
    "gn:population":0,
    "gn:timezone":"Asia/Ho_Chi_Minh",
    "iso:country":"VN",
    "name:und_x_variant":[
        "Plei P\u2019Tao K\u2019la",
        "Plei P\u2019Tao K\u2019lai",
        "Plei P\u01a1tao Kla"
    ],
    "wof:name":"Plei Potao Kla",
    "wof:placetype":"locality"
},
  "geometry": {"coordinates":[108.11667,13.63333],"type":"Point"}
}