{
  "type": "Feature",
  "properties": {
    "gn:admin1_code":"41.0",
    "gn:asciiname":"Ap Phu Nhon",
    "gn:country_code":"VN",
    "gn:dem":0,
    "gn:feature_class":"P",
    "gn:feature_code":"PPL",
    "gn:name":"\u1ea4p Ph\u00fa Nh\u01a1n",
    "gn:population":0,
    "gn:timezone":"Asia/Ho_Chi_Minh",
    "iso:country":"VN",
    "name:und_x_variant":[
        "Ap Phu Nhou",
        "\u1ea4p Ph\u00fa Nh\u01a1n"
    ],
    "wof:name":"Ap Phu Nhon",
    "wof:placetype":"locality"
},
  "geometry": {"coordinates":[105.81667,9.95],"type":"Point"}
}