{
  "type": "Feature",
  "properties": {
    "gn:admin1_code":"44.0",
    "gn:asciiname":"Xom Rua",
    "gn:country_code":"VN",
    "gn:dem":53,
    "gn:feature_class":"P",
    "gn:feature_code":"PPL",
    "gn:name":"X\u00f3m R\u00f9a",
    "gn:population":0,
    "gn:timezone":"Asia/Ho_Chi_Minh",
    "iso:country":"VN",
    "name:vie_x_preferred":[
        "X\u00f3m R\u00f9a"
    ],
    "wof:name":"Xom Rua",
    "wof:placetype":"locality"
},
  "geometry": {"coordinates":[105.41527000000001,21.07227],"type":"Point"}
}