{
  "type": "Feature",
  "properties": {
    "gn:admin1_code":"89.0",
    "gn:asciiname":"Sin Soui Ho",
    "gn:country_code":"VN",
    "gn:dem":1028,
    "gn:feature_class":"P",
    "gn:feature_code":"PPL",
    "gn:name":"Sin Soui H\u00f4",
    "gn:population":0,
    "gn:timezone":"Asia/Ho_Chi_Minh",
    "iso:country":"VN",
    "wof:name":"Sin Soui Ho",
    "wof:placetype":"locality"
},
  "geometry": {"coordinates":[103.48333,22.48333],"type":"Point"}
}