{
  "type": "Feature",
  "properties": {
    "gn:admin1_code":"55.0",
    "gn:asciiname":"Cha Noi",
    "gn:country_code":"VN",
    "gn:dem":634,
    "gn:feature_class":"P",
    "gn:feature_code":"PPL",
    "gn:name":"Cha N\u1ed9i",
    "gn:population":0,
    "gn:timezone":"Asia/Ho_Chi_Minh",
    "iso:country":"VN",
    "name:vie_x_preferred":[
        "Cha N\u1ed9i"
    ],
    "wof:name":"Cha Noi",
    "wof:placetype":"locality"
},
  "geometry": {"coordinates":[107.69347,14.76466],"type":"Point"}
}