{
  "type": "Feature",
  "properties": {
    "gn:admin1_code":"44.0",
    "gn:asciiname":"Tang Long",
    "gn:country_code":"VN",
    "gn:dem":11,
    "gn:feature_class":"P",
    "gn:feature_code":"PPL",
    "gn:name":"T\u0103ng Long",
    "gn:population":0,
    "gn:timezone":"Asia/Ho_Chi_Minh",
    "iso:country":"VN",
    "name:vie_x_preferred":[
        "T\u0103ng Long"
    ],
    "wof:name":"Tang Long",
    "wof:placetype":"locality"
},
  "geometry": {"coordinates":[105.92731999999999,21.25945],"type":"Point"}
}