{
  "type": "Feature",
  "properties": {
    "gn:admin1_code":"35.0",
    "gn:asciiname":"Huu Tiem",
    "gn:country_code":"VN",
    "gn:dem":2,
    "gn:feature_class":"P",
    "gn:feature_code":"PPL",
    "gn:name":"H\u1eefu Ti\u1ec7m",
    "gn:population":0,
    "gn:timezone":"Asia/Ho_Chi_Minh",
    "iso:country":"VN",
    "wof:name":"Huu Tiem",
    "wof:placetype":"locality"
},
  "geometry": {"coordinates":[106.43333,20.36667000000001],"type":"Point"}
}