{
  "type": "Feature",
  "properties": {
    "gn:admin1_code":"68.0",
    "gn:asciiname":"Ba Nhat",
    "gn:country_code":"VN",
    "gn:dem":76,
    "gn:feature_class":"P",
    "gn:feature_code":"PPL",
    "gn:name":"Ba Nh\u1ea5t",
    "gn:population":0,
    "gn:timezone":"Asia/Ho_Chi_Minh",
    "iso:country":"VN",
    "name:vie_x_preferred":[
        "Ba Nh\u1ea5t"
    ],
    "wof:name":"Ba Nhat",
    "wof:placetype":"locality"
},
  "geometry": {"coordinates":[105.1884,22.08749],"type":"Point"}
}