{
  "type": "Feature",
  "properties": {
    "gn:admin1_code":"21.0",
    "gn:asciiname":"Ap Canh Den",
    "gn:country_code":"VN",
    "gn:dem":1,
    "gn:feature_class":"P",
    "gn:feature_code":"PPL",
    "gn:name":"\u1ea4p C\u1ea1nh \u0110\u00e8n",
    "gn:population":0,
    "gn:timezone":"Asia/Ho_Chi_Minh",
    "iso:country":"VN",
    "name:und_x_variant":[
        "C\u1ea1nh \u0110\u00e8n",
        "\u1ea4p C\u1ea1nh \u0110\u00e8n"
    ],
    "wof:name":"Ap Canh Den",
    "wof:placetype":"locality"
},
  "geometry": {"coordinates":[105.28806000000002,9.46028],"type":"Point"}
}