{
  "type": "Feature",
  "properties": {
    "gn:admin1_code":"58.0",
    "gn:asciiname":"La Van",
    "gn:country_code":"VN",
    "gn:dem":6,
    "gn:feature_class":"P",
    "gn:feature_code":"PPL",
    "gn:name":"La V\u00e2n",
    "gn:population":0,
    "gn:timezone":"Asia/Ho_Chi_Minh",
    "iso:country":"VN",
    "name:und_x_variant":[
        "L\u00f2 V\u00e2n"
    ],
    "name:vie_x_preferred":[
        "La V\u00e2n"
    ],
    "wof:name":"La Van",
    "wof:placetype":"locality"
},
  "geometry": {"coordinates":[105.64700999999999,18.88373],"type":"Point"}
}