{
  "type": "Feature",
  "properties": {
    "gn:admin1_code":"89.0",
    "gn:asciiname":"Sin Chai",
    "gn:country_code":"VN",
    "gn:dem":1401,
    "gn:feature_class":"P",
    "gn:feature_code":"PPL",
    "gn:name":"Sin Ch\u1ea3i",
    "gn:population":0,
    "gn:timezone":"Asia/Ho_Chi_Minh",
    "iso:country":"VN",
    "name:und_x_variant":[
        "Cao Sin Chui",
        "Cao Sin Chai"
    ],
    "name:vie_x_preferred":[
        "Sin Ch\u1ea3i"
    ],
    "wof:name":"Sin Chai",
    "wof:placetype":"locality"
},
  "geometry": {"coordinates":[103.34011,22.67073],"type":"Point"}
}