{
  "type": "Feature",
  "properties": {
    "gn:admin1_code":"92.0",
    "gn:asciiname":"Ban Na Luong",
    "gn:country_code":"VN",
    "gn:dem":697,
    "gn:feature_class":"P",
    "gn:feature_code":"PPL",
    "gn:name":"B\u1ea3n Na Luong",
    "gn:population":0,
    "gn:timezone":"Asia/Ho_Chi_Minh",
    "iso:country":"VN",
    "wof:name":"Ban Na Luong",
    "wof:placetype":"locality"
},
  "geometry": {"coordinates":[103.18333,21.51667],"type":"Point"}
}