{
  "type": "Feature",
  "properties": {
    "gn:admin1_code":"70.0",
    "gn:asciiname":"Khe Nhan",
    "gn:country_code":"VN",
    "gn:dem":102,
    "gn:feature_class":"P",
    "gn:feature_code":"PPL",
    "gn:name":"Khe Nh\u00e0n",
    "gn:population":0,
    "gn:timezone":"Asia/Ho_Chi_Minh",
    "iso:country":"VN",
    "name:und_x_variant":[
        "Khe Nham",
        "Kh\u00ea Nh\u00e0n"
    ],
    "name:vie_x_preferred":[
        "Khe Nh\u00e0n"
    ],
    "wof:name":"Khe Nhan",
    "wof:placetype":"locality"
},
  "geometry": {"coordinates":[104.78143,21.92365],"type":"Point"}
}