{
  "type": "Feature",
  "properties": {
    "gn:admin1_code":"49.0",
    "gn:asciiname":"Plei Hale",
    "gn:country_code":"VN",
    "gn:dem":448,
    "gn:feature_class":"P",
    "gn:feature_code":"PPL",
    "gn:name":"Plei Hal\u00e9",
    "gn:population":0,
    "gn:timezone":"Asia/Ho_Chi_Minh",
    "iso:country":"VN",
    "wof:name":"Plei Hale",
    "wof:placetype":"locality"
},
  "geometry": {"coordinates":[108.48333,13.78333],"type":"Point"}
}