{
  "type": "Feature",
  "properties": {
    "gn:admin1_code":"37.0",
    "gn:asciiname":"Xom Nha Tho",
    "gn:country_code":"VN",
    "gn:dem":0,
    "gn:feature_class":"P",
    "gn:feature_code":"PPL",
    "gn:name":"X\u00f3m Nh\u00e0 Th\u1edd",
    "gn:population":0,
    "gn:timezone":"Asia/Ho_Chi_Minh",
    "iso:country":"VN",
    "wof:name":"Xom Nha Tho",
    "wof:placetype":"locality"
},
  "geometry": {"coordinates":[106.59999999999999,10.25],"type":"Point"}
}