{
  "type": "Feature",
  "properties": {
    "gn:admin1_code":"21.0",
    "gn:asciiname":"Xom Vinh Thanh",
    "gn:cc2":"VN",
    "gn:country_code":"VN",
    "gn:dem":9,
    "gn:feature_class":"P",
    "gn:feature_code":"PPL",
    "gn:name":"X\u00f3m V\u0129nh Thanh",
    "gn:population":0,
    "gn:timezone":"Asia/Ho_Chi_Minh",
    "iso:country":"VN",
    "name:und_x_variant":[
        "Vinh Thanh Van",
        "Vinh Thanh",
        "X\u00f3m V\u0129nh Thanh"
    ],
    "wof:name":"Xom Vinh Thanh",
    "wof:placetype":"locality"
},
  "geometry": {"coordinates":[105.08333,10.01667],"type":"Point"}
}