{
  "type": "Feature",
  "properties": {
    "gn:admin1_code":"21.0",
    "gn:asciiname":"Minh Luong",
    "gn:country_code":"VN",
    "gn:dem":5,
    "gn:feature_class":"P",
    "gn:feature_code":"PPLA2",
    "gn:name":"Minh L\u01b0\u01a1ng",
    "gn:population":0,
    "gn:timezone":"Asia/Ho_Chi_Minh",
    "iso:country":"VN",
    "name:und_x_variant":[
        "Minh H\u00f2a"
    ],
    "name:vie_x_preferred":[
        "Minh L\u01b0\u01a1ng"
    ],
    "wof:name":"Minh Luong",
    "wof:placetype":"locality"
},
  "geometry": {"coordinates":[105.15949999999999,9.90248],"type":"Point"}
}