{
  "type": "Feature",
  "properties": {
    "gn:admin1_code":"33.0",
    "gn:asciiname":"Ap Cau Khoi",
    "gn:country_code":"VN",
    "gn:dem":22,
    "gn:feature_class":"P",
    "gn:feature_code":"PPL",
    "gn:name":"\u1ea4p C\u1ea7u Kh\u1edfi",
    "gn:population":0,
    "gn:timezone":"Asia/Ho_Chi_Minh",
    "iso:country":"VN",
    "wof:name":"Ap Cau Khoi",
    "wof:placetype":"locality"
},
  "geometry": {"coordinates":[106.21666999999999,11.25],"type":"Point"}
}