{
  "type": "Feature",
  "properties": {
    "gn:admin1_code":"82.0",
    "gn:asciiname":"Dong Bieu",
    "gn:country_code":"VN",
    "gn:dem":4,
    "gn:feature_class":"P",
    "gn:feature_code":"PPL",
    "gn:name":"\u0110\u00f4ng Bi\u1ec3u",
    "gn:population":0,
    "gn:timezone":"Asia/Ho_Chi_Minh",
    "iso:country":"VN",
    "name:vie_x_preferred":[
        "\u0110\u00f4ng Bi\u1ec3u"
    ],
    "wof:name":"Dong Bieu",
    "wof:placetype":"locality"
},
  "geometry": {"coordinates":[106.00848000000001,20.26862],"type":"Point"}
}