{
  "type": "Feature",
  "properties": {
    "gn:admin1_code":"5.0",
    "gn:asciiname":"Ban Nhai",
    "gn:cc2":"VN",
    "gn:country_code":"VN",
    "gn:dem":168,
    "gn:feature_class":"P",
    "gn:feature_code":"PPL",
    "gn:name":"B\u1ea3n Nhai",
    "gn:population":0,
    "gn:timezone":"Asia/Ho_Chi_Minh",
    "iso:country":"VN",
    "name:und_x_variant":[
        "Ban Nha",
        "B\u1ea3n Nhai"
    ],
    "wof:name":"Ban Nhai",
    "wof:placetype":"locality"
},
  "geometry": {"coordinates":[106.55,22.51667],"type":"Point"}
}