{
  "type": "Feature",
  "properties": {
    "gn:admin1_code":"46.0",
    "gn:asciiname":"An Don",
    "gn:country_code":"VN",
    "gn:dem":30,
    "gn:feature_class":"P",
    "gn:feature_code":"PPL",
    "gn:name":"An \u0110\u00f4n",
    "gn:population":0,
    "gn:timezone":"Asia/Ho_Chi_Minh",
    "iso:country":"VN",
    "name:und_x_variant":[
        "\u00c2n \u0110\u00f4n"
    ],
    "name:vie_x_preferred":[
        "An \u0110\u00f4n"
    ],
    "wof:name":"An Don",
    "wof:placetype":"locality"
},
  "geometry": {"coordinates":[109.01446,14.34743],"type":"Point"}
}