{
  "type": "Feature",
  "properties": {
    "gn:admin1_code":"1.0",
    "gn:asciiname":"Phu My",
    "gn:country_code":"VN",
    "gn:dem":10,
    "gn:feature_class":"P",
    "gn:feature_code":"PPLA2",
    "gn:name":"Ph\u00fa M\u1ef9",
    "gn:population":0,
    "gn:timezone":"Asia/Ho_Chi_Minh",
    "iso:country":"VN",
    "name:fra_x_preferred":[
        "Ph\u00fa M\u1ef9"
    ],
    "name:nld_x_preferred":[
        "Ph\u00fa M\u1ef9"
    ],
    "name:vie_x_preferred":[
        "Ph\u00fa M\u1ef9"
    ],
    "wof:name":"Phu My",
    "wof:placetype":"locality"
},
  "geometry": {"coordinates":[105.35572999999999,10.59236],"type":"Point"}
}