{
  "type": "Feature",
  "properties": {
    "gn:admin1_code":"1.0",
    "gn:asciiname":"Ap Thi",
    "gn:country_code":"VN",
    "gn:dem":11,
    "gn:feature_class":"P",
    "gn:feature_code":"PPL",
    "gn:name":"\u1ea4p Th\u1ecb",
    "gn:population":0,
    "gn:timezone":"Asia/Ho_Chi_Minh",
    "iso:country":"VN",
    "name:vie_x_preferred":[
        "\u1ea4p Th\u1ecb"
    ],
    "wof:name":"Ap Thi",
    "wof:placetype":"locality"
},
  "geometry": {"coordinates":[105.54795,10.43558],"type":"Point"}
}