{
  "type": "Feature",
  "properties": {
    "gn:admin1_code":"58.0",
    "gn:asciiname":"Hoi Yen",
    "gn:country_code":"VN",
    "gn:dem":44,
    "gn:feature_class":"P",
    "gn:feature_code":"PPL",
    "gn:name":"H\u00f4i Y\u00ean",
    "gn:population":0,
    "gn:timezone":"Asia/Ho_Chi_Minh",
    "iso:country":"VN",
    "wof:name":"Hoi Yen",
    "wof:placetype":"locality"
},
  "geometry": {"coordinates":[105.48333,18.86667000000001],"type":"Point"}
}