{
  "type": "Feature",
  "properties": {
    "gn:admin1_code":"16.0",
    "gn:asciiname":"Xom Nhot",
    "gn:country_code":"VN",
    "gn:dem":58,
    "gn:feature_class":"P",
    "gn:feature_code":"PPL",
    "gn:name":"X\u00f3m Nh\u00f3t",
    "gn:population":0,
    "gn:timezone":"Asia/Ho_Chi_Minh",
    "iso:country":"VN",
    "wof:name":"Xom Nhot",
    "wof:placetype":"locality"
},
  "geometry": {"coordinates":[105.33333,21.11667000000001],"type":"Point"}
}