{
  "type": "Feature",
  "properties": {
    "gn:admin1_code":"58.0",
    "gn:asciiname":"Tan Huong",
    "gn:country_code":"VN",
    "gn:dem":8,
    "gn:feature_class":"P",
    "gn:feature_code":"PPL",
    "gn:name":"T\u00e2n H\u01b0\u01a1ng",
    "gn:population":0,
    "gn:timezone":"Asia/Ho_Chi_Minh",
    "iso:country":"VN",
    "name:vie_x_preferred":[
        "T\u00e2n H\u01b0\u01a1ng"
    ],
    "wof:name":"Tan Huong",
    "wof:placetype":"locality"
},
  "geometry": {"coordinates":[105.55398,18.96094],"type":"Point"}
}