{
  "type": "Feature",
  "properties": {
    "gn:admin1_code":"66.0",
    "gn:asciiname":"Thon Mot",
    "gn:country_code":"VN",
    "gn:dem":152,
    "gn:feature_class":"P",
    "gn:feature_code":"PPL",
    "gn:name":"Th\u00f4n M\u1ed9t",
    "gn:population":0,
    "gn:timezone":"Asia/Ho_Chi_Minh",
    "iso:country":"VN",
    "name:vie_x_preferred":[
        "Th\u00f4n M\u1ed9t"
    ],
    "name:vie_x_variant":[
        "Th\u00f4n 1"
    ],
    "wof:name":"Thon Mot",
    "wof:placetype":"locality"
},
  "geometry": {"coordinates":[107.63392,16.098],"type":"Point"}
}