{
  "type": "Feature",
  "properties": {
    "gn:admin1_code":"50.0",
    "gn:asciiname":"Bac Dung Dong",
    "gn:country_code":"VN",
    "gn:dem":88,
    "gn:feature_class":"P",
    "gn:feature_code":"PPL",
    "gn:name":"B\u0103c Dung D\u1ed9ng",
    "gn:population":0,
    "gn:timezone":"Asia/Ho_Chi_Minh",
    "iso:country":"VN",
    "wof:name":"Bac Dung Dong",
    "wof:placetype":"locality"
},
  "geometry": {"coordinates":[104.71666999999999,22.38333],"type":"Point"}
}