{
  "type": "Feature",
  "properties": {
    "gn:admin1_code":"37.0",
    "gn:asciiname":"Quang Phu",
    "gn:country_code":"VN",
    "gn:dem":3,
    "gn:feature_class":"P",
    "gn:feature_code":"PPL",
    "gn:name":"Quang Ph\u00fa",
    "gn:population":0,
    "gn:timezone":"Asia/Ho_Chi_Minh",
    "iso:country":"VN",
    "name:vie_x_preferred":[
        "Quang Ph\u00fa"
    ],
    "wof:name":"Quang Phu",
    "wof:placetype":"locality"
},
  "geometry": {"coordinates":[106.49558,10.39946],"type":"Point"}
}