{
  "type": "Feature",
  "properties": {
    "gn:admin1_code":"71.0",
    "gn:asciiname":"Quat Du",
    "gn:country_code":"VN",
    "gn:dem":22,
    "gn:feature_class":"P",
    "gn:feature_code":"PPL",
    "gn:name":"Qu\u1ea5t Du",
    "gn:population":0,
    "gn:timezone":"Asia/Ho_Chi_Minh",
    "iso:country":"VN",
    "name:vie_x_preferred":[
        "Qu\u1ea5t Du"
    ],
    "wof:name":"Quat Du",
    "wof:placetype":"locality"
},
  "geometry": {"coordinates":[106.14538,21.41584],"type":"Point"}
}