{
  "type": "Feature",
  "properties": {
    "gn:admin1_code":"80.0",
    "gn:asciiname":"Tram Khe",
    "gn:country_code":"VN",
    "gn:dem":6,
    "gn:feature_class":"P",
    "gn:feature_code":"PPL",
    "gn:name":"Tr\u1ea1m Kh\u00ea",
    "gn:population":0,
    "gn:timezone":"Asia/Ho_Chi_Minh",
    "iso:country":"VN",
    "name:vie_x_preferred":[
        "Tr\u1ea1m Kh\u00ea"
    ],
    "wof:name":"Tram Khe",
    "wof:placetype":"locality"
},
  "geometry": {"coordinates":[106.09806,20.60561],"type":"Point"}
}