{
  "type": "Feature",
  "properties": {
    "gn:admin1_code":"71.0",
    "gn:asciiname":"Duc Thang",
    "gn:country_code":"VN",
    "gn:dem":26,
    "gn:feature_class":"P",
    "gn:feature_code":"PPL",
    "gn:name":"\u0110\u1ee9c Th\u1eafng",
    "gn:population":0,
    "gn:timezone":"Asia/Ho_Chi_Minh",
    "iso:country":"VN",
    "name:nld_x_preferred":[
        "\u0110\u1ee9c Th\u1eafng"
    ],
    "name:und_x_variant":[
        "\u0110\u1ee9c Th\u1eafng"
    ],
    "name:vie_x_preferred":[
        "\u0110\u1ee9c Th\u1eafng"
    ],
    "wof:name":"Duc Thang",
    "wof:placetype":"locality"
},
  "geometry": {"coordinates":[105.97583,21.35639],"type":"Point"}
}