{
  "type": "Feature",
  "properties": {
    "gn:admin1_code":"88.0",
    "gn:asciiname":"Ea Poc",
    "gn:country_code":"VN",
    "gn:dem":456,
    "gn:feature_class":"P",
    "gn:feature_code":"PPL",
    "gn:name":"Ea P\u1ed1c",
    "gn:population":0,
    "gn:timezone":"Asia/Ho_Chi_Minh",
    "iso:country":"VN",
    "name:und_x_variant":[
        "Buon Poch",
        "Bu\u00f4n Ea P\u00f4c"
    ],
    "name:vie_x_preferred":[
        "Ea P\u1ed1c"
    ],
    "wof:name":"Ea Poc",
    "wof:placetype":"locality"
},
  "geometry": {"coordinates":[108.07114,12.77795],"type":"Point"}
}