{
  "type": "Feature",
  "properties": {
    "gn:admin1_code":"85.0",
    "gn:asciiname":"Lai Thanh",
    "gn:country_code":"VN",
    "gn:dem":84,
    "gn:feature_class":"P",
    "gn:feature_code":"PPL",
    "gn:name":"Lai Th\u00e0nh",
    "gn:population":0,
    "gn:timezone":"Asia/Ho_Chi_Minh",
    "iso:country":"VN",
    "name:vie_x_preferred":[
        "Lai Th\u00e0nh"
    ],
    "wof:name":"Lai Thanh",
    "wof:placetype":"locality"
},
  "geometry": {"coordinates":[105.65454,21.77521],"type":"Point"}
}