{
  "type": "Feature",
  "properties": {
    "gn:admin1_code":"87.0",
    "gn:asciiname":"Khu Vuc Hai",
    "gn:country_code":"VN",
    "gn:dem":0,
    "gn:feature_class":"P",
    "gn:feature_code":"PPL",
    "gn:name":"Khu V\u1ef1c Hai",
    "gn:population":0,
    "gn:timezone":"Asia/Ho_Chi_Minh",
    "iso:country":"VN",
    "name:vie_x_preferred":[
        "Khu V\u1ef1c Hai"
    ],
    "name:vie_x_variant":[
        "Khu V\u1ef1c 2"
    ],
    "wof:name":"Khu Vuc Hai",
    "wof:placetype":"locality"
},
  "geometry": {"coordinates":[105.71371000000001,10.09849],"type":"Point"}
}