{
  "type": "Feature",
  "properties": {
    "gn:admin1_code":"67.0",
    "gn:asciiname":"Nguyet Lang A",
    "gn:country_code":"VN",
    "gn:dem":9,
    "gn:feature_class":"P",
    "gn:feature_code":"PPL",
    "gn:name":"Nguy\u1ec7t L\u00e3ng A",
    "gn:population":0,
    "gn:timezone":"Asia/Ho_Chi_Minh",
    "iso:country":"VN",
    "name:vie_x_preferred":[
        "Nguy\u1ec7t L\u00e3ng A"
    ],
    "wof:name":"Nguyet Lang A",
    "wof:placetype":"locality"
},
  "geometry": {"coordinates":[106.24241000000001,9.95862],"type":"Point"}
}