{
  "type": "Feature",
  "properties": {
    "gn:admin1_code":"23.0",
    "gn:asciiname":"M'kar Da Te",
    "gn:country_code":"VN",
    "gn:dem":164,
    "gn:feature_class":"P",
    "gn:feature_code":"PPL",
    "gn:name":"M\u2019kar Da T\u00e9",
    "gn:population":0,
    "gn:timezone":"Asia/Ho_Chi_Minh",
    "iso:country":"VN",
    "wof:name":"M'kar Da Te",
    "wof:placetype":"locality"
},
  "geometry": {"coordinates":[107.53333000000001,11.55],"type":"Point"}
}