{
  "type": "Feature",
  "properties": {
    "gn:admin1_code":"70.0",
    "gn:asciiname":"Khe Long",
    "gn:country_code":"VN",
    "gn:dem":339,
    "gn:feature_class":"P",
    "gn:feature_code":"PPL",
    "gn:name":"Kh\u00e9 Long",
    "gn:population":0,
    "gn:timezone":"Asia/Ho_Chi_Minh",
    "iso:country":"VN",
    "name:und_x_variant":[
        "Khe Loug",
        "Kh\u00e9 Long"
    ],
    "wof:name":"Khe Long",
    "wof:placetype":"locality"
},
  "geometry": {"coordinates":[104.76667,21.48333],"type":"Point"}
}