{
  "type": "Feature",
  "properties": {
    "gn:admin1_code":"5.0",
    "gn:asciiname":"Lenh Cam",
    "gn:country_code":"VN",
    "gn:dem":403,
    "gn:feature_class":"P",
    "gn:feature_code":"PPL",
    "gn:name":"L\u1ec7nh C\u1ea5m",
    "gn:population":0,
    "gn:timezone":"Asia/Ho_Chi_Minh",
    "iso:country":"VN",
    "wof:name":"Lenh Cam",
    "wof:placetype":"locality"
},
  "geometry": {"coordinates":[106.65000000000001,22.63333],"type":"Point"}
}