{
  "type": "Feature",
  "properties": {
    "gn:admin1_code":"50.0",
    "gn:asciiname":"Tan Binh",
    "gn:country_code":"VN",
    "gn:dem":624,
    "gn:feature_class":"P",
    "gn:feature_code":"PPL",
    "gn:name":"T\u00e2n B\u00ecnh",
    "gn:population":0,
    "gn:timezone":"Asia/Ho_Chi_Minh",
    "iso:country":"VN",
    "name:vie_x_preferred":[
        "T\u00e2n B\u00ecnh"
    ],
    "wof:name":"Tan Binh",
    "wof:placetype":"locality"
},
  "geometry": {"coordinates":[104.63076,22.45972],"type":"Point"}
}