{
  "type": "Feature",
  "properties": {
    "gn:admin1_code":"84.0",
    "gn:asciiname":"An Tam",
    "gn:country_code":"VN",
    "gn:dem":16,
    "gn:feature_class":"P",
    "gn:feature_code":"PPL",
    "gn:name":"An T\u00e2m",
    "gn:population":0,
    "gn:timezone":"Asia/Ho_Chi_Minh",
    "iso:country":"VN",
    "name:und_x_variant":[
        "Tan Phong",
        "An T\u00e2m"
    ],
    "wof:name":"An Tam",
    "wof:placetype":"locality"
},
  "geometry": {"coordinates":[108.15000000000001,15.81667],"type":"Point"}
}