{
  "type": "Feature",
  "properties": {
    "gn:admin1_code":"88.0",
    "gn:asciiname":"Thon Sau C",
    "gn:country_code":"VN",
    "gn:dem":468,
    "gn:feature_class":"P",
    "gn:feature_code":"PPL",
    "gn:name":"Th\u00f4n S\u00e1u C",
    "gn:population":0,
    "gn:timezone":"Asia/Ho_Chi_Minh",
    "iso:country":"VN",
    "name:vie_x_preferred":[
        "Th\u00f4n S\u00e1u C"
    ],
    "name:vie_x_variant":[
        "Th\u00f4n 6C"
    ],
    "wof:name":"Thon Sau C",
    "wof:placetype":"locality"
},
  "geometry": {"coordinates":[108.57341,12.7449],"type":"Point"}
}