{
  "type": "Feature",
  "properties": {
    "gn:admin1_code":"90.0",
    "gn:asciiname":"Siao Mon Wan",
    "gn:country_code":"VN",
    "gn:dem":930,
    "gn:feature_class":"P",
    "gn:feature_code":"PPL",
    "gn:name":"Siao Mon Wan",
    "gn:population":0,
    "gn:timezone":"Asia/Ho_Chi_Minh",
    "iso:country":"VN",
    "wof:name":"Siao Mon Wan",
    "wof:placetype":"locality"
},
  "geometry": {"coordinates":[104.18333,22.58333],"type":"Point"}
}