{
  "type": "Feature",
  "properties": {
    "gn:admin1_code":"67.0",
    "gn:asciiname":"Tan Trung Kinh",
    "gn:country_code":"VN",
    "gn:dem":6,
    "gn:feature_class":"P",
    "gn:feature_code":"PPL",
    "gn:name":"T\u00e2n Trung Kinh",
    "gn:population":0,
    "gn:timezone":"Asia/Ho_Chi_Minh",
    "iso:country":"VN",
    "name:vie_x_preferred":[
        "T\u00e2n Trung Kinh"
    ],
    "wof:name":"Tan Trung Kinh",
    "wof:placetype":"locality"
},
  "geometry": {"coordinates":[106.16522000000001,9.88422],"type":"Point"}
}