{
  "type": "Feature",
  "properties": {
    "gn:admin1_code":"37.0",
    "gn:asciiname":"An Hoa Thuong",
    "gn:country_code":"VN",
    "gn:dem":8,
    "gn:feature_class":"P",
    "gn:feature_code":"PPL",
    "gn:name":"An H\u00f2a Th\u01b0\u1ee3ng",
    "gn:population":0,
    "gn:timezone":"Asia/Ho_Chi_Minh",
    "iso:country":"VN",
    "name:vie_x_preferred":[
        "An H\u00f2a Th\u01b0\u1ee3ng"
    ],
    "wof:name":"An Hoa Thuong",
    "wof:placetype":"locality"
},
  "geometry": {"coordinates":[106.41370000000001,10.33461],"type":"Point"}
}