{
  "type": "Feature",
  "properties": {
    "gn:admin1_code":"1.0",
    "gn:asciiname":"Tay Binh B",
    "gn:country_code":"VN",
    "gn:dem":8,
    "gn:feature_class":"P",
    "gn:feature_code":"PPL",
    "gn:name":"T\u00e2y B\u00ecnh B",
    "gn:population":0,
    "gn:timezone":"Asia/Ho_Chi_Minh",
    "iso:country":"VN",
    "name:vie_x_preferred":[
        "T\u00e2y B\u00ecnh B"
    ],
    "wof:name":"Tay Binh B",
    "wof:placetype":"locality"
},
  "geometry": {"coordinates":[105.36811000000002,10.32453],"type":"Point"}
}