{
  "type": "Feature",
  "properties": {
    "gn:admin1_code":"59.0",
    "gn:asciiname":"Trai Rao",
    "gn:country_code":"VN",
    "gn:dem":45,
    "gn:feature_class":"P",
    "gn:feature_code":"PPL",
    "gn:name":"Tr\u1ea1i R\u00e0o",
    "gn:population":0,
    "gn:timezone":"Asia/Ho_Chi_Minh",
    "iso:country":"VN",
    "name:vie_x_preferred":[
        "Tr\u1ea1i R\u00e0o"
    ],
    "wof:name":"Trai Rao",
    "wof:placetype":"locality"
},
  "geometry": {"coordinates":[105.76362,20.25797],"type":"Point"}
}