{
  "type": "Feature",
  "properties": {
    "gn:admin1_code":"75.0",
    "gn:asciiname":"Binh Duc",
    "gn:country_code":"VN",
    "gn:dem":4,
    "gn:feature_class":"P",
    "gn:feature_code":"PPL",
    "gn:name":"B\u00ecnh \u0110\u1ee9c",
    "gn:population":0,
    "gn:timezone":"Asia/Ho_Chi_Minh",
    "iso:country":"VN",
    "name:und_x_variant":[
        "\u1ea4p B\u00ecnh \u0110\u1ee9c"
    ],
    "name:vie_x_preferred":[
        "B\u00ecnh \u0110\u1ee9c"
    ],
    "wof:name":"Binh Duc",
    "wof:placetype":"locality"
},
  "geometry": {"coordinates":[106.68982,10.91829],"type":"Point"}
}