{
  "type": "Feature",
  "properties": {
    "gn:admin1_code":"72.0",
    "gn:asciiname":"Quan Lang",
    "gn:country_code":"VN",
    "gn:dem":176,
    "gn:feature_class":"P",
    "gn:feature_code":"PPL",
    "gn:name":"Quan L\u00e0ng",
    "gn:population":0,
    "gn:timezone":"Asia/Ho_Chi_Minh",
    "iso:country":"VN",
    "wof:name":"Quan Lang",
    "wof:placetype":"locality"
},
  "geometry": {"coordinates":[105.874,22.2604],"type":"Point"}
}