{
  "type": "Feature",
  "properties": {
    "gn:admin1_code":"70.0",
    "gn:asciiname":"Dai Than",
    "gn:country_code":"VN",
    "gn:dem":47,
    "gn:feature_class":"P",
    "gn:feature_code":"PPLL",
    "gn:name":"\u0110\u1ea1i Th\u00e2n",
    "gn:population":0,
    "gn:timezone":"Asia/Ho_Chi_Minh",
    "iso:country":"VN",
    "name:vie_x_preferred":[
        "\u0110\u1ea1i Th\u00e2n"
    ],
    "wof:name":"Dai Than",
    "wof:placetype":"locality"
},
  "geometry": {"coordinates":[105.05305,21.70284],"type":"Point"}
}