{
  "type": "Feature",
  "properties": {
    "gn:admin1_code":"65.0",
    "gn:asciiname":"Kiet Lap",
    "gn:country_code":"VN",
    "gn:dem":2,
    "gn:feature_class":"P",
    "gn:feature_code":"PPL",
    "gn:name":"Ki\u1ebft L\u1eadp",
    "gn:population":0,
    "gn:timezone":"Asia/Ho_Chi_Minh",
    "iso:country":"VN",
    "name:vie_x_preferred":[
        "Ki\u1ebft L\u1eadp"
    ],
    "wof:name":"Kiet Lap",
    "wof:placetype":"locality"
},
  "geometry": {"coordinates":[105.78552999999999,9.50065],"type":"Point"}
}