{
  "type": "Feature",
  "properties": {
    "gn:admin1_code":"30.0",
    "gn:asciiname":"Trang Vinh",
    "gn:country_code":"VN",
    "gn:dem":20,
    "gn:feature_class":"P",
    "gn:feature_code":"PPL",
    "gn:name":"Tr\u00e0ng Vinh",
    "gn:population":0,
    "gn:timezone":"Asia/Ho_Chi_Minh",
    "iso:country":"VN",
    "name:vie_x_preferred":[
        "Tr\u00e0ng Vinh"
    ],
    "wof:name":"Trang Vinh",
    "wof:placetype":"locality"
},
  "geometry": {"coordinates":[107.82687,21.60404],"type":"Point"}
}