{
  "type": "Feature",
  "properties": {
    "gn:admin1_code":"32.0",
    "gn:asciiname":"Ban Hit",
    "gn:country_code":"VN",
    "gn:dem":472,
    "gn:feature_class":"P",
    "gn:feature_code":"PPL",
    "gn:name":"B\u1ea3n Hit",
    "gn:population":0,
    "gn:timezone":"Asia/Ho_Chi_Minh",
    "iso:country":"VN",
    "name:vie_x_preferred":[
        "B\u1ea3n Hit"
    ],
    "wof:name":"Ban Hit",
    "wof:placetype":"locality"
},
  "geometry": {"coordinates":[103.78122999999999,21.16905],"type":"Point"}
}