{
  "type": "Feature",
  "properties": {
    "gn:admin1_code":"1.0",
    "gn:asciiname":"Dong Binh Trach",
    "gn:country_code":"VN",
    "gn:dem":3,
    "gn:feature_class":"P",
    "gn:feature_code":"PPL",
    "gn:name":"\u0110\u00f4ng B\u00ecnh Tr\u1ea1ch",
    "gn:population":0,
    "gn:timezone":"Asia/Ho_Chi_Minh",
    "iso:country":"VN",
    "name:und_x_variant":[
        "\u1ea4p \u0110\u00f4ng B\u00ecnh Tr\u1ea1ch"
    ],
    "name:vie_x_preferred":[
        "\u0110\u00f4ng B\u00ecnh Tr\u1ea1ch"
    ],
    "wof:name":"Dong Binh Trach",
    "wof:placetype":"locality"
},
  "geometry": {"coordinates":[105.34405,10.35046],"type":"Point"}
}