{
  "type": "Feature",
  "properties": {
    "gn:admin1_code":"38.0",
    "gn:asciiname":"Cha La",
    "gn:country_code":"VN",
    "gn:dem":254,
    "gn:feature_class":"P",
    "gn:feature_code":"PPL",
    "gn:name":"Cha La",
    "gn:population":0,
    "gn:timezone":"Asia/Ho_Chi_Minh",
    "iso:country":"VN",
    "wof:name":"Cha La",
    "wof:placetype":"locality"
},
  "geometry": {"coordinates":[105.03333000000001,21.03333],"type":"Point"}
}