{
  "type": "Feature",
  "properties": {
    "gn:admin1_code":"70.0",
    "gn:asciiname":"Nghia Phong",
    "gn:country_code":"VN",
    "gn:dem":60,
    "gn:feature_class":"P",
    "gn:feature_code":"PPL",
    "gn:name":"Ngh\u0129a Phong",
    "gn:population":0,
    "gn:timezone":"Asia/Ho_Chi_Minh",
    "iso:country":"VN",
    "name:vie_x_preferred":[
        "Ngh\u0129a Phong"
    ],
    "wof:name":"Nghia Phong",
    "wof:placetype":"locality"
},
  "geometry": {"coordinates":[104.40142,22.13488],"type":"Point"}
}