{
  "type": "Feature",
  "properties": {
    "gn:admin1_code":"89.0",
    "gn:asciiname":"Ban Kha",
    "gn:country_code":"VN",
    "gn:dem":410,
    "gn:feature_class":"P",
    "gn:feature_code":"PPL",
    "gn:name":"B\u1ea3n Kh\u00e1",
    "gn:population":0,
    "gn:timezone":"Asia/Ho_Chi_Minh",
    "iso:country":"VN",
    "name:und_x_variant":[
        "B\u1ea3n Kha"
    ],
    "name:vie_x_preferred":[
        "B\u1ea3n Kh\u00e1"
    ],
    "wof:name":"Ban Kha",
    "wof:placetype":"locality"
},
  "geometry": {"coordinates":[103.7948,21.95077],"type":"Point"}
}