{
  "type": "Feature",
  "properties": {
    "gn:admin1_code":"88.0",
    "gn:asciiname":"Buon Cham",
    "gn:country_code":"VN",
    "gn:dem":474,
    "gn:feature_class":"P",
    "gn:feature_code":"PPL",
    "gn:name":"Bu\u00f4n Ch\u00e2m",
    "gn:population":0,
    "gn:timezone":"Asia/Ho_Chi_Minh",
    "iso:country":"VN",
    "name:und_x_variant":[
        "Bu\u00f4n Cham"
    ],
    "name:vie_x_preferred":[
        "Bu\u00f4n Ch\u00e2m"
    ],
    "wof:name":"Buon Cham",
    "wof:placetype":"locality"
},
  "geometry": {"coordinates":[108.06416000000002,12.49221],"type":"Point"}
}