{
  "type": "Feature",
  "properties": {
    "gn:admin1_code":"55.0",
    "gn:asciiname":"Dak Cho",
    "gn:country_code":"VN",
    "gn:dem":768,
    "gn:feature_class":"P",
    "gn:feature_code":"PPL",
    "gn:name":"Dak Cho",
    "gn:population":0,
    "gn:timezone":"Asia/Ho_Chi_Minh",
    "iso:country":"VN",
    "name:und_x_variant":[
        "Ong Cho",
        "Dak Cho"
    ],
    "wof:name":"Dak Cho",
    "wof:placetype":"locality"
},
  "geometry": {"coordinates":[108.25,14.86667],"type":"Point"}
}