{
  "type": "Feature",
  "properties": {
    "gn:admin1_code":"24.0",
    "gn:asciiname":"Chanh Hoi",
    "gn:country_code":"VN",
    "gn:dem":6,
    "gn:feature_class":"P",
    "gn:feature_code":"PPL",
    "gn:name":"Ch\u00e1nh H\u1ed9i",
    "gn:population":0,
    "gn:timezone":"Asia/Ho_Chi_Minh",
    "iso:country":"VN",
    "name:vie_x_preferred":[
        "Ch\u00e1nh H\u1ed9i"
    ],
    "wof:name":"Chanh Hoi",
    "wof:placetype":"locality"
},
  "geometry": {"coordinates":[106.36489,10.94378],"type":"Point"}
}