{
  "type": "Feature",
  "properties": {
    "gn:admin1_code":"36.0",
    "gn:asciiname":"Pho La Ha",
    "gn:cc2":"VN",
    "gn:country_code":"VN",
    "gn:dem":556,
    "gn:feature_class":"P",
    "gn:feature_code":"PPL",
    "gn:name":"Pho La Ha",
    "gn:population":0,
    "gn:timezone":"Asia/Ho_Chi_Minh",
    "iso:country":"VN",
    "name:und_x_variant":[
        "P. La Ha",
        "Pho La Ha"
    ],
    "wof:name":"Pho La Ha",
    "wof:placetype":"locality"
},
  "geometry": {"coordinates":[108.68333,11.48333],"type":"Point"}
}