{
  "type": "Feature",
  "properties": {
    "gn:admin1_code":"46.0",
    "gn:asciiname":"Lai Khanh",
    "gn:country_code":"VN",
    "gn:dem":20,
    "gn:feature_class":"P",
    "gn:feature_code":"PPL",
    "gn:name":"L\u1ea1i Kh\u00e1nh",
    "gn:population":0,
    "gn:timezone":"Asia/Ho_Chi_Minh",
    "iso:country":"VN",
    "name:und_x_variant":[
        "Lai Kh\u00e1nh"
    ],
    "name:vie_x_preferred":[
        "L\u1ea1i Kh\u00e1nh"
    ],
    "wof:name":"Lai Khanh",
    "wof:placetype":"locality"
},
  "geometry": {"coordinates":[109.01656,14.40155],"type":"Point"}
}