{
  "type": "Feature",
  "properties": {
    "gn:admin1_code":"53.0",
    "gn:asciiname":"Suoi Sao",
    "gn:country_code":"VN",
    "gn:dem":146,
    "gn:feature_class":"P",
    "gn:feature_code":"PPL",
    "gn:name":"Su\u1ed1i Sao",
    "gn:population":0,
    "gn:timezone":"Asia/Ho_Chi_Minh",
    "iso:country":"VN",
    "wof:name":"Suoi Sao",
    "wof:placetype":"locality"
},
  "geometry": {"coordinates":[105.55,20.83333],"type":"Point"}
}