{
  "type": "Feature",
  "properties": {
    "gn:admin1_code":"65.0",
    "gn:asciiname":"Xom Phu An",
    "gn:cc2":"VN",
    "gn:country_code":"VN",
    "gn:dem":3,
    "gn:feature_class":"P",
    "gn:feature_code":"PPL",
    "gn:name":"X\u00f3m Ph\u00fa An",
    "gn:population":0,
    "gn:timezone":"Asia/Ho_Chi_Minh",
    "iso:country":"VN",
    "name:und_x_variant":[
        "Phu An",
        "X\u00f3m Ph\u00fa An"
    ],
    "wof:name":"Xom Phu An",
    "wof:placetype":"locality"
},
  "geometry": {"coordinates":[106.01639,9.72917],"type":"Point"}
}