{
  "type": "Feature",
  "properties": {
    "gn:admin1_code":"5.0",
    "gn:asciiname":"Lang In Tau",
    "gn:cc2":"VN",
    "gn:country_code":"VN",
    "gn:dem":481,
    "gn:feature_class":"P",
    "gn:feature_code":"PPL",
    "gn:name":"Lang \u1ec8n T\u1ea3u",
    "gn:population":0,
    "gn:timezone":"Asia/Ho_Chi_Minh",
    "iso:country":"VN",
    "name:und_x_variant":[
        "Linh Tao",
        "Lang \u1ec8n T\u1ea3u"
    ],
    "wof:name":"Lang In Tau",
    "wof:placetype":"locality"
},
  "geometry": {"coordinates":[106.08333,22.68333],"type":"Point"}
}