{
  "type": "Feature",
  "properties": {
    "gn:admin1_code":"24.0",
    "gn:asciiname":"Hiep Hoa",
    "gn:country_code":"VN",
    "gn:dem":1,
    "gn:feature_class":"P",
    "gn:feature_code":"PPL",
    "gn:name":"Hi\u1ec7p H\u00f2a",
    "gn:population":0,
    "gn:timezone":"Asia/Ho_Chi_Minh",
    "iso:country":"VN",
    "name:vie_x_preferred":[
        "Hi\u1ec7p H\u00f2a"
    ],
    "wof:name":"Hiep Hoa",
    "wof:placetype":"locality"
},
  "geometry": {"coordinates":[106.31607,10.91115],"type":"Point"}
}