{
  "type": "Feature",
  "properties": {
    "gn:admin1_code":"54.0",
    "gn:asciiname":"Phu Cang",
    "gn:country_code":"VN",
    "gn:dem":11,
    "gn:feature_class":"P",
    "gn:feature_code":"PPL",
    "gn:name":"Ph\u00fa Cang",
    "gn:population":0,
    "gn:timezone":"Asia/Ho_Chi_Minh",
    "iso:country":"VN",
    "name:vie_x_preferred":[
        "Ph\u00fa Cang"
    ],
    "wof:name":"Phu Cang",
    "wof:placetype":"locality"
},
  "geometry": {"coordinates":[109.22444,12.71353],"type":"Point"}
}