{
  "type": "Feature",
  "properties": {
    "gn:admin1_code":"76.0",
    "gn:asciiname":"Bu Nui Choit",
    "gn:country_code":"VN",
    "gn:dem":113,
    "gn:feature_class":"P",
    "gn:feature_code":"PPL",
    "gn:name":"Bu N\u00fai Choit",
    "gn:population":0,
    "gn:timezone":"Asia/Ho_Chi_Minh",
    "iso:country":"VN",
    "wof:name":"Bu Nui Choit",
    "wof:placetype":"locality"
},
  "geometry": {"coordinates":[106.91667,11.96667],"type":"Point"}
}