{
  "type": "Feature",
  "properties": {
    "gn:admin1_code":"61.0",
    "gn:asciiname":"Dan Phu",
    "gn:country_code":"VN",
    "gn:dem":107,
    "gn:feature_class":"P",
    "gn:feature_code":"PPL",
    "gn:name":"D\u00e2n Ph\u00fa",
    "gn:population":0,
    "gn:timezone":"Asia/Ho_Chi_Minh",
    "iso:country":"VN",
    "name:und_x_variant":[
        "V\u0169ng S\u00fa",
        "D\u00e2n Ph\u00fa"
    ],
    "wof:name":"Dan Phu",
    "wof:placetype":"locality"
},
  "geometry": {"coordinates":[109.28333000000001,13.43333],"type":"Point"}
}