{
  "type": "Feature",
  "properties": {
    "gn:admin1_code":"5.0",
    "gn:asciiname":"Ban Sut",
    "gn:country_code":"VN",
    "gn:dem":689,
    "gn:feature_class":"P",
    "gn:feature_code":"PPL",
    "gn:name":"B\u1ea3n S\u00fat",
    "gn:population":0,
    "gn:timezone":"Asia/Ho_Chi_Minh",
    "iso:country":"VN",
    "wof:name":"Ban Sut",
    "wof:placetype":"locality"
},
  "geometry": {"coordinates":[106.38333,22.73333],"type":"Point"}
}