{
  "type": "Feature",
  "properties": {
    "gn:admin1_code":"43.0",
    "gn:asciiname":"Thoai Huong",
    "gn:country_code":"VN",
    "gn:dem":129,
    "gn:feature_class":"P",
    "gn:feature_code":"PPL",
    "gn:name":"Tho\u1ea1i H\u01b0\u01a1ng",
    "gn:population":0,
    "gn:timezone":"Asia/Ho_Chi_Minh",
    "iso:country":"VN",
    "name:und_x_variant":[
        "Toai Huong",
        "Tho\u1ea1i H\u01b0\u01a1ng"
    ],
    "wof:name":"Thoai Huong",
    "wof:placetype":"locality"
},
  "geometry": {"coordinates":[107.39397,10.83364],"type":"Point"}
}