{
  "type": "Feature",
  "properties": {
    "gn:admin1_code":"60.0",
    "gn:asciiname":"Thon No Gia",
    "gn:country_code":"VN",
    "gn:dem":61,
    "gn:feature_class":"P",
    "gn:feature_code":"PPL",
    "gn:name":"Th\u00f4n N\u00f4 Gi\u00e1",
    "gn:population":0,
    "gn:timezone":"Asia/Ho_Chi_Minh",
    "iso:country":"VN",
    "name:und_x_variant":[
        "N\u00f4 Gi\u00e1",
        "Th\u00f4n N\u00f4 Gi\u00e1"
    ],
    "wof:name":"Thon No Gia",
    "wof:placetype":"locality"
},
  "geometry": {"coordinates":[108.81667,11.46667],"type":"Point"}
}