{
  "type": "Feature",
  "properties": {
    "gn:admin1_code":"21.0",
    "gn:asciiname":"Ap Ta Keo",
    "gn:cc2":"VN",
    "gn:country_code":"VN",
    "gn:dem":3,
    "gn:feature_class":"P",
    "gn:feature_code":"PPL",
    "gn:name":"\u1ea4p T\u00e0 Keo",
    "gn:population":0,
    "gn:timezone":"Asia/Ho_Chi_Minh",
    "iso:country":"VN",
    "name:und_x_variant":[
        "Xom Ta Keo",
        "\u1ea4p T\u00e0 Keo"
    ],
    "wof:name":"Ap Ta Keo",
    "wof:placetype":"locality"
},
  "geometry": {"coordinates":[105.11667,10.06667],"type":"Point"}
}