{
  "type": "Feature",
  "properties": {
    "gn:admin1_code":"46.0",
    "gn:asciiname":"Doi Bon",
    "gn:country_code":"VN",
    "gn:dem":10,
    "gn:feature_class":"P",
    "gn:feature_code":"PPL",
    "gn:name":"\u0110\u1ed9i B\u1ed1n",
    "gn:population":0,
    "gn:timezone":"Asia/Ho_Chi_Minh",
    "iso:country":"VN",
    "name:vie_x_preferred":[
        "\u0110\u1ed9i B\u1ed1n"
    ],
    "name:vie_x_variant":[
        "\u0110\u1ed9i 4"
    ],
    "wof:name":"Doi Bon",
    "wof:placetype":"locality"
},
  "geometry": {"coordinates":[109.07776,14.31021],"type":"Point"}
}