{
  "type": "Feature",
  "properties": {
    "gn:admin1_code":"58.0",
    "gn:asciiname":"Ke Ngam",
    "gn:country_code":"VN",
    "gn:dem":50,
    "gn:feature_class":"P",
    "gn:feature_code":"PPL",
    "gn:name":"K\u1ebb Ng\u00e2m",
    "gn:population":0,
    "gn:timezone":"Asia/Ho_Chi_Minh",
    "iso:country":"VN",
    "wof:name":"Ke Ngam",
    "wof:placetype":"locality"
},
  "geometry": {"coordinates":[105.33333,19.23333],"type":"Point"}
}