{
  "type": "Feature",
  "properties": {
    "gn:admin1_code":"69.0",
    "gn:asciiname":"Hung Thanh",
    "gn:country_code":"VN",
    "gn:dem":2,
    "gn:feature_class":"P",
    "gn:feature_code":"PPL",
    "gn:name":"H\u01b0ng Th\u00e0nh",
    "gn:population":0,
    "gn:timezone":"Asia/Ho_Chi_Minh",
    "iso:country":"VN",
    "name:vie_x_preferred":[
        "H\u01b0ng Th\u00e0nh"
    ],
    "wof:name":"Hung Thanh",
    "wof:placetype":"locality"
},
  "geometry": {"coordinates":[105.73605999999999,10.17542],"type":"Point"}
}