{
  "type": "Feature",
  "properties": {
    "gn:admin1_code":"83.0",
    "gn:asciiname":"Lua Thuong",
    "gn:country_code":"VN",
    "gn:dem":97,
    "gn:feature_class":"P",
    "gn:feature_code":"PPL",
    "gn:name":"L\u01b0a Th\u01b0\u1ee3ng",
    "gn:population":0,
    "gn:timezone":"Asia/Ho_Chi_Minh",
    "iso:country":"VN",
    "name:und_x_variant":[
        "X\u00f3m L\u01b0a Th\u01b0\u1ee3ng"
    ],
    "name:vie_x_preferred":[
        "L\u01b0a Th\u01b0\u1ee3ng"
    ],
    "wof:name":"Lua Thuong",
    "wof:placetype":"locality"
},
  "geometry": {"coordinates":[105.18159,21.04667],"type":"Point"}
}