{
  "type": "Feature",
  "properties": {
    "gn:admin1_code":"89.0",
    "gn:asciiname":"Ban Sam",
    "gn:country_code":"VN",
    "gn:dem":1196,
    "gn:feature_class":"P",
    "gn:feature_code":"PPL",
    "gn:name":"B\u1ea3n S\u1ea7m",
    "gn:population":0,
    "gn:timezone":"Asia/Ho_Chi_Minh",
    "iso:country":"VN",
    "wof:name":"Ban Sam",
    "wof:placetype":"locality"
},
  "geometry": {"coordinates":[103.28333000000001,22.23333],"type":"Point"}
}