{
  "type": "Feature",
  "properties": {
    "gn:admin1_code":"49.0",
    "gn:asciiname":"Plei Ya Tong",
    "gn:country_code":"VN",
    "gn:dem":267,
    "gn:feature_class":"P",
    "gn:feature_code":"PPL",
    "gn:name":"Plei Ya Tong",
    "gn:population":0,
    "gn:timezone":"Asia/Ho_Chi_Minh",
    "iso:country":"VN",
    "wof:name":"Plei Ya Tong",
    "wof:placetype":"locality"
},
  "geometry": {"coordinates":[107.65000000000001,13.73333],"type":"Point"}
}