{
  "type": "Feature",
  "properties": {
    "gn:admin1_code":"66.0",
    "gn:asciiname":"Ap Dong Ho",
    "gn:country_code":"VN",
    "gn:dem":11,
    "gn:feature_class":"P",
    "gn:feature_code":"PPL",
    "gn:name":"\u1ea4p \u0110\u1ed3ng H\u00f4",
    "gn:population":0,
    "gn:timezone":"Asia/Ho_Chi_Minh",
    "iso:country":"VN",
    "name:und_x_variant":[
        "\u0110\u00f4ng H\u00f4",
        "\u1ea4p \u0110\u1ed3ng H\u00f4"
    ],
    "wof:name":"Ap Dong Ho",
    "wof:placetype":"locality"
},
  "geometry": {"coordinates":[107.45,16.61667000000001],"type":"Point"}
}