{
  "type": "Feature",
  "properties": {
    "gn:admin1_code":"69.0",
    "gn:asciiname":"Hieu Binh",
    "gn:country_code":"VN",
    "gn:dem":10,
    "gn:feature_class":"P",
    "gn:feature_code":"PPL",
    "gn:name":"Hi\u1ebfu B\u00ecnh",
    "gn:population":0,
    "gn:timezone":"Asia/Ho_Chi_Minh",
    "iso:country":"VN",
    "name:vie_x_preferred":[
        "Hi\u1ebfu B\u00ecnh"
    ],
    "wof:name":"Hieu Binh",
    "wof:placetype":"locality"
},
  "geometry": {"coordinates":[106.13106000000001,9.96209],"type":"Point"}
}