{
  "type": "Feature",
  "properties": {
    "gn:admin1_code":"32.0",
    "gn:asciiname":"Hua Ty",
    "gn:country_code":"VN",
    "gn:dem":1088,
    "gn:feature_class":"P",
    "gn:feature_code":"PPL",
    "gn:name":"Hua Ty",
    "gn:population":0,
    "gn:timezone":"Asia/Ho_Chi_Minh",
    "iso:country":"VN",
    "name:vie_x_preferred":[
        "Hua Ty"
    ],
    "wof:name":"Hua Ty",
    "wof:placetype":"locality"
},
  "geometry": {"coordinates":[103.61257999999999,21.34534],"type":"Point"}
}