{
  "type": "Feature",
  "properties": {
    "gn:admin1_code":"79.0",
    "gn:asciiname":"Phuong Due",
    "gn:country_code":"VN",
    "gn:dem":2,
    "gn:feature_class":"P",
    "gn:feature_code":"PPL",
    "gn:name":"Ph\u01b0\u01a1ng Du\u1ec7",
    "gn:population":0,
    "gn:timezone":"Asia/Ho_Chi_Minh",
    "iso:country":"VN",
    "name:und_x_variant":[
        "Phuong Duc",
        "Ph\u01b0\u01a1ng Du\u1ec7"
    ],
    "wof:name":"Phuong Due",
    "wof:placetype":"locality"
},
  "geometry": {"coordinates":[106.46666999999999,20.96667],"type":"Point"}
}