{
  "type": "Feature",
  "properties": {
    "gn:admin1_code":"55.0",
    "gn:asciiname":"Dak Kosa Peng",
    "gn:country_code":"VN",
    "gn:dem":781,
    "gn:feature_class":"P",
    "gn:feature_code":"PPL",
    "gn:name":"Dak K\u01a1sa Peng",
    "gn:population":0,
    "gn:timezone":"Asia/Ho_Chi_Minh",
    "iso:country":"VN",
    "name:und_x_variant":[
        "Dak Rezia Peng",
        "Dak Rosa Peng",
        "Dak K\u01a1sa Peng"
    ],
    "wof:name":"Dak Kosa Peng",
    "wof:placetype":"locality"
},
  "geometry": {"coordinates":[107.84999999999999,14.75],"type":"Point"}
}