{
  "type": "Feature",
  "properties": {
    "gn:admin1_code":"54.0",
    "gn:asciiname":"Thon Dai Dien Trung",
    "gn:country_code":"VN",
    "gn:dem":6,
    "gn:feature_class":"P",
    "gn:feature_code":"PPL",
    "gn:name":"Th\u00f4n \u0110\u1ea1i \u0110i\u1ec1n Trung",
    "gn:population":0,
    "gn:timezone":"Asia/Ho_Chi_Minh",
    "iso:country":"VN",
    "name:und_x_variant":[
        "Dai Dier Trung",
        "Dai Dien Trung",
        "Th\u00f4n \u0110\u1ea1i \u0110i\u1ec1n Trung"
    ],
    "wof:name":"Thon Dai Dien Trung",
    "wof:placetype":"locality"
},
  "geometry": {"coordinates":[109.09999999999999,12.28333],"type":"Point"}
}