{
  "type": "Feature",
  "properties": {
    "gn:admin1_code":"70.0",
    "gn:asciiname":"Goc Lu",
    "gn:country_code":"VN",
    "gn:dem":93,
    "gn:feature_class":"P",
    "gn:feature_code":"PPL",
    "gn:name":"G\u1ed1c L\u1ee5",
    "gn:population":0,
    "gn:timezone":"Asia/Ho_Chi_Minh",
    "iso:country":"VN",
    "name:vie_x_preferred":[
        "G\u1ed1c L\u1ee5"
    ],
    "wof:name":"Goc Lu",
    "wof:placetype":"locality"
},
  "geometry": {"coordinates":[104.62220000000001,21.86636],"type":"Point"}
}