{
  "type": "Feature",
  "properties": {
    "gn:admin1_code":"70.0",
    "gn:asciiname":"Ban Si Tang",
    "gn:country_code":"VN",
    "gn:dem":714,
    "gn:feature_class":"P",
    "gn:feature_code":"PPL",
    "gn:name":"B\u1ea3n S\u00ed Tang",
    "gn:population":0,
    "gn:timezone":"Asia/Ho_Chi_Minh",
    "iso:country":"VN",
    "name:und_x_variant":[
        "Ban Si Teng",
        "B\u1ea3n S\u00ed Tang"
    ],
    "wof:name":"Ban Si Tang",
    "wof:placetype":"locality"
},
  "geometry": {"coordinates":[104.55,21.46667],"type":"Point"}
}