{
  "type": "Feature",
  "properties": {
    "gn:admin1_code":"81.0",
    "gn:asciiname":"Quang Thi",
    "gn:country_code":"VN",
    "gn:dem":6,
    "gn:feature_class":"P",
    "gn:feature_code":"PPL",
    "gn:name":"Quang Thi",
    "gn:population":0,
    "gn:timezone":"Asia/Ho_Chi_Minh",
    "iso:country":"VN",
    "name:vie_x_preferred":[
        "Quang Thi"
    ],
    "wof:name":"Quang Thi",
    "wof:placetype":"locality"
},
  "geometry": {"coordinates":[106.08596,20.81608],"type":"Point"}
}