{
  "type": "Feature",
  "properties": {
    "gn:admin1_code":"47.0",
    "gn:asciiname":"Thon Ba",
    "gn:country_code":"VN",
    "gn:dem":18,
    "gn:feature_class":"P",
    "gn:feature_code":"PPL",
    "gn:name":"Th\u00f4n Ba",
    "gn:population":0,
    "gn:timezone":"Asia/Ho_Chi_Minh",
    "iso:country":"VN",
    "name:vie_x_preferred":[
        "Th\u00f4n Ba"
    ],
    "name:vie_x_variant":[
        "Th\u00f4n 3"
    ],
    "wof:name":"Thon Ba",
    "wof:placetype":"locality"
},
  "geometry": {"coordinates":[108.51224000000001,11.28054],"type":"Point"}
}