{
  "type": "Feature",
  "properties": {
    "gn:admin1_code":"83.0",
    "gn:asciiname":"Dich Qua",
    "gn:country_code":"VN",
    "gn:dem":64,
    "gn:feature_class":"P",
    "gn:feature_code":"PPL",
    "gn:name":"\u0110\u1ecbch Qu\u1ea3",
    "gn:population":0,
    "gn:timezone":"Asia/Ho_Chi_Minh",
    "iso:country":"VN",
    "wof:name":"Dich Qua",
    "wof:placetype":"locality"
},
  "geometry": {"coordinates":[105.11667,21.16667],"type":"Point"}
}