{
  "type": "Feature",
  "properties": {
    "gn:admin1_code":"53.0",
    "gn:asciiname":"Xom Nui",
    "gn:country_code":"VN",
    "gn:dem":173,
    "gn:feature_class":"P",
    "gn:feature_code":"PPL",
    "gn:name":"X\u00f3m N\u00fai",
    "gn:population":0,
    "gn:timezone":"Asia/Ho_Chi_Minh",
    "iso:country":"VN",
    "wof:name":"Xom Nui",
    "wof:placetype":"locality"
},
  "geometry": {"coordinates":[105.38333,20.88333],"type":"Point"}
}