{
  "type": "Feature",
  "properties": {
    "gn:admin1_code":"5.0",
    "gn:asciiname":"Bo Chienh",
    "gn:country_code":"VN",
    "gn:dem":153,
    "gn:feature_class":"P",
    "gn:feature_code":"PPL",
    "gn:name":"B\u00f4 Chi\u1ec3nh",
    "gn:population":0,
    "gn:timezone":"Asia/Ho_Chi_Minh",
    "iso:country":"VN",
    "wof:name":"Bo Chienh",
    "wof:placetype":"locality"
},
  "geometry": {"coordinates":[106.53333000000001,22.51667],"type":"Point"}
}