{
  "type": "Feature",
  "properties": {
    "gn:admin1_code":"39.0",
    "gn:asciiname":"Koc Co",
    "gn:country_code":"VN",
    "gn:dem":385,
    "gn:feature_class":"P",
    "gn:feature_code":"PPL",
    "gn:name":"K\u1ed1c Co",
    "gn:population":0,
    "gn:timezone":"Asia/Ho_Chi_Minh",
    "iso:country":"VN",
    "name:vie_x_preferred":[
        "K\u1ed1c Co"
    ],
    "wof:name":"Koc Co",
    "wof:placetype":"locality"
},
  "geometry": {"coordinates":[106.25305,21.81876],"type":"Point"}
}