{
  "type": "Feature",
  "properties": {
    "gn:admin1_code":"64.0",
    "gn:asciiname":"Xom Bau",
    "gn:country_code":"VN",
    "gn:dem":22,
    "gn:feature_class":"P",
    "gn:feature_code":"PPL",
    "gn:name":"X\u00f3m B\u00e2u",
    "gn:population":0,
    "gn:timezone":"Asia/Ho_Chi_Minh",
    "iso:country":"VN",
    "name:vie_x_preferred":[
        "X\u00f3m B\u00e2u"
    ],
    "wof:name":"Xom Bau",
    "wof:placetype":"locality"
},
  "geometry": {"coordinates":[107.09713000000001,17.04296],"type":"Point"}
}