{
  "type": "Feature",
  "properties": {
    "gn:admin1_code":"69.0",
    "gn:asciiname":"Long Hung",
    "gn:country_code":"VN",
    "gn:dem":1,
    "gn:feature_class":"P",
    "gn:feature_code":"PPL",
    "gn:name":"Long H\u01b0ng",
    "gn:population":0,
    "gn:timezone":"Asia/Ho_Chi_Minh",
    "iso:country":"VN",
    "name:vie_x_preferred":[
        "Long H\u01b0ng"
    ],
    "wof:name":"Long Hung",
    "wof:placetype":"locality"
},
  "geometry": {"coordinates":[105.99643,10.24057],"type":"Point"}
}