{
  "type": "Feature",
  "properties": {
    "gn:admin1_code":"92.0",
    "gn:asciiname":"Ban Na Pinn",
    "gn:country_code":"VN",
    "gn:dem":638,
    "gn:feature_class":"P",
    "gn:feature_code":"PPL",
    "gn:name":"B\u1ea3n Na Pinn",
    "gn:population":0,
    "gn:timezone":"Asia/Ho_Chi_Minh",
    "iso:country":"VN",
    "wof:name":"Ban Na Pinn",
    "wof:placetype":"locality"
},
  "geometry": {"coordinates":[103.21666999999999,21.48333],"type":"Point"}
}