{
  "type": "Feature",
  "properties": {
    "gn:admin1_code":"3.0",
    "gn:asciiname":"Quy The",
    "gn:country_code":"VN",
    "gn:dem":2,
    "gn:feature_class":"P",
    "gn:feature_code":"PPL",
    "gn:name":"Qu\u00fd Th\u1ebf",
    "gn:population":0,
    "gn:timezone":"Asia/Ho_Chi_Minh",
    "iso:country":"VN",
    "name:vie_x_preferred":[
        "Qu\u00fd Th\u1ebf"
    ],
    "wof:name":"Quy The",
    "wof:placetype":"locality"
},
  "geometry": {"coordinates":[106.4722,10.01745],"type":"Point"}
}