{
  "type": "Feature",
  "properties": {
    "gn:admin1_code":"5.0",
    "gn:asciiname":"Dong Si",
    "gn:country_code":"VN",
    "gn:dem":727,
    "gn:feature_class":"P",
    "gn:feature_code":"PPL",
    "gn:name":"\u0110\u00f4ng S\u00ed",
    "gn:population":0,
    "gn:timezone":"Asia/Ho_Chi_Minh",
    "iso:country":"VN",
    "wof:name":"Dong Si",
    "wof:placetype":"locality"
},
  "geometry": {"coordinates":[106.51667,22.93333],"type":"Point"}
}