{
  "type": "Feature",
  "properties": {
    "gn:admin1_code":"74.0",
    "gn:asciiname":"Van Quan",
    "gn:country_code":"VN",
    "gn:dem":8,
    "gn:feature_class":"P",
    "gn:feature_code":"PPL",
    "gn:name":"V\u0103n Quan",
    "gn:population":0,
    "gn:timezone":"Asia/Ho_Chi_Minh",
    "iso:country":"VN",
    "name:vie_x_preferred":[
        "V\u0103n Quang"
    ],
    "name:vie_x_variant":[
        "V\u0103n Quan"
    ],
    "wof:name":"Van Quan",
    "wof:placetype":"locality"
},
  "geometry": {"coordinates":[106.02549,21.04229],"type":"Point"}
}