{
  "type": "Feature",
  "properties": {
    "gn:admin1_code":"89.0",
    "gn:asciiname":"Nam Ha",
    "gn:country_code":"VN",
    "gn:dem":428,
    "gn:feature_class":"P",
    "gn:feature_code":"PPL",
    "gn:name":"Nam Ha",
    "gn:population":0,
    "gn:timezone":"Asia/Ho_Chi_Minh",
    "iso:country":"VN",
    "wof:name":"Nam Ha",
    "wof:placetype":"locality"
},
  "geometry": {"coordinates":[103.48333,22.18333],"type":"Point"}
}