{
  "type": "Feature",
  "properties": {
    "gn:admin1_code":"53.0",
    "gn:asciiname":"Dong Thuy",
    "gn:country_code":"VN",
    "gn:dem":19,
    "gn:feature_class":"P",
    "gn:feature_code":"PPL",
    "gn:name":"\u0110\u1ed3ng Thuy",
    "gn:population":0,
    "gn:timezone":"Asia/Ho_Chi_Minh",
    "iso:country":"VN",
    "name:und_x_variant":[
        "Bong Thuy",
        "\u0110\u1ed3ng Thuy"
    ],
    "wof:name":"Dong Thuy",
    "wof:placetype":"locality"
},
  "geometry": {"coordinates":[105.51667,20.86667000000001],"type":"Point"}
}