{
  "type": "Feature",
  "properties": {
    "gn:admin1_code":"83.0",
    "gn:asciiname":"Chan Mong",
    "gn:country_code":"VN",
    "gn:dem":65,
    "gn:feature_class":"P",
    "gn:feature_code":"PPL",
    "gn:name":"Ch\u00e2n M\u1ed9ng",
    "gn:population":0,
    "gn:timezone":"Asia/Ho_Chi_Minh",
    "iso:country":"VN",
    "wof:name":"Chan Mong",
    "wof:placetype":"locality"
},
  "geometry": {"coordinates":[105.18333,21.53333],"type":"Point"}
}