{
  "type": "Feature",
  "properties": {
    "gn:admin1_code":"39.0",
    "gn:asciiname":"Lan Khinh",
    "gn:country_code":"VN",
    "gn:dem":430,
    "gn:feature_class":"P",
    "gn:feature_code":"PPL",
    "gn:name":"L\u00e2n Khinh",
    "gn:population":0,
    "gn:timezone":"Asia/Ho_Chi_Minh",
    "iso:country":"VN",
    "name:vie_x_preferred":[
        "L\u00e2n Khinh"
    ],
    "wof:name":"Lan Khinh",
    "wof:placetype":"locality"
},
  "geometry": {"coordinates":[106.39791,21.89007],"type":"Point"}
}