{
  "type": "Feature",
  "properties": {
    "gn:admin1_code":"90.0",
    "gn:asciiname":"Coc Phuc",
    "gn:country_code":"VN",
    "gn:dem":210,
    "gn:feature_class":"P",
    "gn:feature_code":"PPL",
    "gn:name":"C\u1ed1c Phuc",
    "gn:population":0,
    "gn:timezone":"Asia/Ho_Chi_Minh",
    "iso:country":"VN",
    "wof:name":"Coc Phuc",
    "wof:placetype":"locality"
},
  "geometry": {"coordinates":[103.86667,22.55],"type":"Point"}
}