{
  "type": "Feature",
  "properties": {
    "gn:admin1_code":"71.0",
    "gn:asciiname":"Hoa Yen",
    "gn:country_code":"VN",
    "gn:dem":11,
    "gn:feature_class":"P",
    "gn:feature_code":"PPL",
    "gn:name":"H\u00f2a Y\u00ean",
    "gn:population":0,
    "gn:timezone":"Asia/Ho_Chi_Minh",
    "iso:country":"VN",
    "name:und_x_variant":[
        "Hoa Y\u00ean"
    ],
    "name:vie_x_preferred":[
        "H\u00f2a Y\u00ean"
    ],
    "wof:name":"Hoa Yen",
    "wof:placetype":"locality"
},
  "geometry": {"coordinates":[106.19887,21.29745],"type":"Point"}
}