{
  "type": "Feature",
  "properties": {
    "gn:admin1_code":"90.0",
    "gn:asciiname":"Coc Xan",
    "gn:country_code":"VN",
    "gn:dem":173,
    "gn:feature_class":"P",
    "gn:feature_code":"PPL",
    "gn:name":"Coc Xan",
    "gn:population":0,
    "gn:timezone":"Asia/Ho_Chi_Minh",
    "iso:country":"VN",
    "wof:name":"Coc Xan",
    "wof:placetype":"locality"
},
  "geometry": {"coordinates":[103.93333,22.46667],"type":"Point"}
}