{
  "type": "Feature",
  "properties": {
    "gn:admin1_code":"93.0",
    "gn:asciiname":"Xang Moi",
    "gn:country_code":"VN",
    "gn:dem":2,
    "gn:feature_class":"P",
    "gn:feature_code":"PPL",
    "gn:name":"X\u00e1ng M\u1edbi",
    "gn:population":0,
    "gn:timezone":"Asia/Ho_Chi_Minh",
    "iso:country":"VN",
    "name:vie_x_preferred":[
        "X\u00e1ng M\u1edbi"
    ],
    "wof:name":"Xang Moi",
    "wof:placetype":"locality"
},
  "geometry": {"coordinates":[105.64807,9.90185],"type":"Point"}
}