{
  "type": "Feature",
  "properties": {
    "gn:admin1_code":"64.0",
    "gn:asciiname":"Ta Rut",
    "gn:country_code":"VN",
    "gn:dem":231,
    "gn:feature_class":"P",
    "gn:feature_code":"PPL",
    "gn:name":"T\u00e0 R\u1ee5t",
    "gn:population":0,
    "gn:timezone":"Asia/Ho_Chi_Minh",
    "iso:country":"VN",
    "name:und_x_variant":[
        "Tou Rout"
    ],
    "name:vie_x_preferred":[
        "T\u00e0 R\u1ee5t"
    ],
    "wof:name":"Ta Rut",
    "wof:placetype":"locality"
},
  "geometry": {"coordinates":[106.99229,16.40949],"type":"Point"}
}