{
  "type": "Feature",
  "properties": {
    "gn:admin1_code":"52.0",
    "gn:asciiname":"Huong Giang",
    "gn:country_code":"VN",
    "gn:dem":16,
    "gn:feature_class":"P",
    "gn:feature_code":"PPL",
    "gn:name":"H\u01b0\u01a1ng Giang",
    "gn:population":0,
    "gn:timezone":"Asia/Ho_Chi_Minh",
    "iso:country":"VN",
    "name:vie_x_preferred":[
        "H\u01b0\u01a1ng Giang"
    ],
    "wof:name":"Huong Giang",
    "wof:placetype":"locality"
},
  "geometry": {"coordinates":[105.55661000000001,18.3855],"type":"Point"}
}