{
  "type": "Feature",
  "properties": {
    "gn:admin1_code":"30.0",
    "gn:asciiname":"Minh Cam",
    "gn:country_code":"VN",
    "gn:dem":280,
    "gn:feature_class":"P",
    "gn:feature_code":"PPL",
    "gn:name":"Minh C\u1ea7m",
    "gn:population":0,
    "gn:timezone":"Asia/Ho_Chi_Minh",
    "iso:country":"VN",
    "wof:name":"Minh Cam",
    "wof:placetype":"locality"
},
  "geometry": {"coordinates":[107.05,21.23333],"type":"Point"}
}