{
  "type": "Feature",
  "properties": {
    "gn:admin1_code":"17.0",
    "gn:asciiname":"Lo Vien",
    "gn:country_code":"VN",
    "gn:dem":52,
    "gn:feature_class":"P",
    "gn:feature_code":"PPL",
    "gn:name":"L\u1ed9 Vi\u00ean",
    "gn:population":0,
    "gn:timezone":"Asia/Ho_Chi_Minh",
    "iso:country":"VN",
    "wof:name":"Lo Vien",
    "wof:placetype":"locality"
},
  "geometry": {"coordinates":[105.36667,21.53333],"type":"Point"}
}