{
  "type": "Feature",
  "properties": {
    "gn:admin1_code":"32.0",
    "gn:asciiname":"Tieu Khu Bon",
    "gn:country_code":"VN",
    "gn:dem":665,
    "gn:feature_class":"P",
    "gn:feature_code":"PPL",
    "gn:name":"Ti\u1ec3u Khu B\u1ed1n",
    "gn:population":0,
    "gn:timezone":"Asia/Ho_Chi_Minh",
    "iso:country":"VN",
    "name:vie_x_preferred":[
        "Ti\u1ec3u Khu B\u1ed1n"
    ],
    "name:vie_x_variant":[
        "Ti\u1ec3u Khu 4"
    ],
    "wof:name":"Tieu Khu Bon",
    "wof:placetype":"locality"
},
  "geometry": {"coordinates":[104.1557,21.13581],"type":"Point"}
}