{
  "type": "Feature",
  "properties": {
    "gn:admin1_code":"44.0",
    "gn:asciiname":"Quang Huc",
    "gn:country_code":"VN",
    "gn:dem":17,
    "gn:feature_class":"P",
    "gn:feature_code":"PPL",
    "gn:name":"Quang H\u00fac",
    "gn:population":0,
    "gn:timezone":"Asia/Ho_Chi_Minh",
    "iso:country":"VN",
    "name:vie_x_preferred":[
        "Quang H\u00fac"
    ],
    "wof:name":"Quang Huc",
    "wof:placetype":"locality"
},
  "geometry": {"coordinates":[105.44132,21.19071],"type":"Point"}
}