{
  "type": "Feature",
  "properties": {
    "gn:admin1_code":"39.0",
    "gn:asciiname":"Khau Dang",
    "gn:country_code":"VN",
    "gn:dem":314,
    "gn:feature_class":"P",
    "gn:feature_code":"PPL",
    "gn:name":"Khau D\u00e0ng",
    "gn:population":0,
    "gn:timezone":"Asia/Ho_Chi_Minh",
    "iso:country":"VN",
    "name:vie_x_preferred":[
        "Khau D\u00e0ng"
    ],
    "wof:name":"Khau Dang",
    "wof:placetype":"locality"
},
  "geometry": {"coordinates":[106.24448999999998,21.89519],"type":"Point"}
}