{
  "type": "Feature",
  "properties": {
    "gn:admin1_code":"50.0",
    "gn:asciiname":"Yen Binh Xa",
    "gn:country_code":"VN",
    "gn:dem":148,
    "gn:feature_class":"P",
    "gn:feature_code":"PPL",
    "gn:name":"Y\u00ean B\u00ecnh X\u00e3",
    "gn:population":0,
    "gn:timezone":"Asia/Ho_Chi_Minh",
    "iso:country":"VN",
    "wof:name":"Yen Binh Xa",
    "wof:placetype":"locality"
},
  "geometry": {"coordinates":[104.58333,22.41667],"type":"Point"}
}