{
  "type": "Feature",
  "properties": {
    "gn:admin1_code":"74.0",
    "gn:asciiname":"Ngoc Doi",
    "gn:country_code":"VN",
    "gn:dem":9,
    "gn:feature_class":"P",
    "gn:feature_code":"PPL",
    "gn:name":"Ng\u1ecdc \u0110\u00f4i",
    "gn:population":0,
    "gn:timezone":"Asia/Ho_Chi_Minh",
    "iso:country":"VN",
    "name:vie_x_preferred":[
        "Ng\u1ecdc \u0110\u00f4i"
    ],
    "wof:name":"Ngoc Doi",
    "wof:placetype":"locality"
},
  "geometry": {"coordinates":[106.10235,21.20016],"type":"Point"}
}