{
  "type": "Feature",
  "properties": {
    "gn:admin1_code":"37.0",
    "gn:asciiname":"Cai Thia",
    "gn:cc2":"VN",
    "gn:country_code":"VN",
    "gn:dem":5,
    "gn:feature_class":"P",
    "gn:feature_code":"PPL",
    "gn:name":"C\u00e1i Thia",
    "gn:population":0,
    "gn:timezone":"Asia/Ho_Chi_Minh",
    "iso:country":"VN",
    "name:und_x_variant":[
        "Kaitia",
        "C\u00e1i Thia"
    ],
    "wof:name":"Cai Thia",
    "wof:placetype":"locality"
},
  "geometry": {"coordinates":[105.96666999999999,10.33333],"type":"Point"}
}