{
  "type": "Feature",
  "properties": {
    "gn:admin1_code":"88.0",
    "gn:asciiname":"Pandioum",
    "gn:cc2":"VN",
    "gn:country_code":"VN",
    "gn:dem":1015,
    "gn:feature_class":"P",
    "gn:feature_code":"PPL",
    "gn:name":"Pandioum",
    "gn:population":0,
    "gn:timezone":"Asia/Ho_Chi_Minh",
    "iso:country":"VN",
    "name:und_x_variant":[
        "Xom Pandioun",
        "Xom Pandioum",
        "Pandioum"
    ],
    "wof:name":"Pandioum",
    "wof:placetype":"locality"
},
  "geometry": {"coordinates":[108.09999999999999,11.86667],"type":"Point"}
}