{
  "type": "Feature",
  "properties": {
    "gn:admin1_code":"88.0",
    "gn:asciiname":"Thon Chin",
    "gn:country_code":"VN",
    "gn:dem":446,
    "gn:feature_class":"P",
    "gn:feature_code":"PPL",
    "gn:name":"Th\u00f4n Ch\u00edn",
    "gn:population":0,
    "gn:timezone":"Asia/Ho_Chi_Minh",
    "iso:country":"VN",
    "name:vie_x_preferred":[
        "Th\u00f4n Ch\u00edn"
    ],
    "name:vie_x_variant":[
        "Th\u00f4n 9"
    ],
    "wof:name":"Thon Chin",
    "wof:placetype":"locality"
},
  "geometry": {"coordinates":[108.50718999999999,12.84414],"type":"Point"}
}