{
  "type": "Feature",
  "properties": {
    "gn:admin1_code":"65.0",
    "gn:asciiname":"Hoa Duc",
    "gn:country_code":"VN",
    "gn:dem":3,
    "gn:feature_class":"P",
    "gn:feature_code":"PPL",
    "gn:name":"H\u00f2a \u0110\u1ee9c",
    "gn:population":0,
    "gn:timezone":"Asia/Ho_Chi_Minh",
    "iso:country":"VN",
    "name:vie_x_preferred":[
        "H\u00f2a \u0110\u1ee9c"
    ],
    "wof:name":"Hoa Duc",
    "wof:placetype":"locality"
},
  "geometry": {"coordinates":[105.86964,9.47552],"type":"Point"}
}