{
  "type": "Feature",
  "properties": {
    "gn:admin1_code":"32.0",
    "gn:asciiname":"Tieu Khu Huoi Duong",
    "gn:country_code":"VN",
    "gn:dem":793,
    "gn:feature_class":"P",
    "gn:feature_code":"PPL",
    "gn:name":"Ti\u1ec3u Khu Hu\u1ed5i D\u01b0\u01a1ng",
    "gn:population":0,
    "gn:timezone":"Asia/Ho_Chi_Minh",
    "iso:country":"VN",
    "name:vie_x_preferred":[
        "Ti\u1ec3u Khu Hu\u1ed5i D\u01b0\u01a1ng"
    ],
    "wof:name":"Tieu Khu Huoi Duong",
    "wof:placetype":"locality"
},
  "geometry": {"coordinates":[104.19951,21.18208],"type":"Point"}
}