{
  "type": "Feature",
  "properties": {
    "gn:admin1_code":"37.0",
    "gn:asciiname":"My Thach",
    "gn:country_code":"VN",
    "gn:dem":6,
    "gn:feature_class":"P",
    "gn:feature_code":"PPL",
    "gn:name":"M\u1ef9 Th\u1ea1ch",
    "gn:population":0,
    "gn:timezone":"Asia/Ho_Chi_Minh",
    "iso:country":"VN",
    "name:vie_x_preferred":[
        "M\u1ef9 Th\u1ea1ch"
    ],
    "wof:name":"My Thach",
    "wof:placetype":"locality"
},
  "geometry": {"coordinates":[105.86190000000001,10.40243],"type":"Point"}
}