{
  "type": "Feature",
  "properties": {
    "gn:admin1_code":"20.0",
    "gn:asciiname":"Trung My Tay",
    "gn:country_code":"VN",
    "gn:dem":9,
    "gn:feature_class":"P",
    "gn:feature_code":"PPL",
    "gn:name":"Trung M\u1ef9 T\u00e2y",
    "gn:population":0,
    "gn:timezone":"Asia/Ho_Chi_Minh",
    "iso:country":"VN",
    "wof:name":"Trung My Tay",
    "wof:placetype":"locality"
},
  "geometry": {"coordinates":[106.62083,10.8625],"type":"Point"}
}