{
  "type": "Feature",
  "properties": {
    "gn:admin1_code":"70.0",
    "gn:asciiname":"Xom Gua",
    "gn:country_code":"VN",
    "gn:dem":56,
    "gn:feature_class":"P",
    "gn:feature_code":"PPL",
    "gn:name":"X\u00f3m G\u00f9a",
    "gn:population":0,
    "gn:timezone":"Asia/Ho_Chi_Minh",
    "iso:country":"VN",
    "name:und_x_variant":[
        "Sum Gua",
        "S\u00f3m G\u00f9a",
        "X\u00f3m G\u00f9a"
    ],
    "wof:name":"Xom Gua",
    "wof:placetype":"locality"
},
  "geometry": {"coordinates":[104.81667,21.76667],"type":"Point"}
}