{
  "type": "Feature",
  "properties": {
    "gn:admin1_code":"49.0",
    "gn:asciiname":"Buon Hoang",
    "gn:country_code":"VN",
    "gn:dem":158,
    "gn:feature_class":"P",
    "gn:feature_code":"PPL",
    "gn:name":"Bu\u00f4n Hoang",
    "gn:population":0,
    "gn:timezone":"Asia/Ho_Chi_Minh",
    "iso:country":"VN",
    "name:vie_x_preferred":[
        "Bu\u00f4n Hoang"
    ],
    "wof:name":"Buon Hoang",
    "wof:placetype":"locality"
},
  "geometry": {"coordinates":[108.45019000000001,13.37956],"type":"Point"}
}