{
  "type": "Feature",
  "properties": {
    "gn:admin1_code":"72.0",
    "gn:asciiname":"Kim Nhoan",
    "gn:country_code":"VN",
    "gn:dem":271,
    "gn:feature_class":"P",
    "gn:feature_code":"PPL",
    "gn:name":"Kim Nhoan",
    "gn:population":0,
    "gn:timezone":"Asia/Ho_Chi_Minh",
    "iso:country":"VN",
    "wof:name":"Kim Nhoan",
    "wof:placetype":"locality"
},
  "geometry": {"coordinates":[105.81712,22.3549],"type":"Point"}
}