{
  "type": "Feature",
  "properties": {
    "gn:admin1_code":"89.0",
    "gn:asciiname":"Ban Kouei San",
    "gn:country_code":"VN",
    "gn:dem":652,
    "gn:feature_class":"P",
    "gn:feature_code":"PPL",
    "gn:name":"B\u1ea3n Kouei San",
    "gn:population":0,
    "gn:timezone":"Asia/Ho_Chi_Minh",
    "iso:country":"VN",
    "name:und_x_variant":[
        "Ban Koua Ban",
        "B\u1ea3n Kouei San"
    ],
    "wof:name":"Ban Kouei San",
    "wof:placetype":"locality"
},
  "geometry": {"coordinates":[103.86667,21.96667],"type":"Point"}
}