{
  "type": "Feature",
  "properties": {
    "gn:admin1_code":"58.0",
    "gn:asciiname":"Huu Biet",
    "gn:country_code":"VN",
    "gn:dem":6,
    "gn:feature_class":"P",
    "gn:feature_code":"PPL",
    "gn:name":"H\u1eefu Bi\u00eat",
    "gn:population":0,
    "gn:timezone":"Asia/Ho_Chi_Minh",
    "iso:country":"VN",
    "wof:name":"Huu Biet",
    "wof:placetype":"locality"
},
  "geometry": {"coordinates":[105.58333,18.68333],"type":"Point"}
}