{
  "type": "Feature",
  "properties": {
    "gn:admin1_code":"24.0",
    "gn:asciiname":"Ap Phuoc Tuong",
    "gn:country_code":"VN",
    "gn:dem":2,
    "gn:feature_class":"P",
    "gn:feature_code":"PPL",
    "gn:name":"\u1ea4p Ph\u01b0\u1edbc T\u01b0\u1edbng",
    "gn:population":0,
    "gn:timezone":"Asia/Ho_Chi_Minh",
    "iso:country":"VN",
    "wof:name":"Ap Phuoc Tuong",
    "wof:placetype":"locality"
},
  "geometry": {"coordinates":[106.56667,10.53333],"type":"Point"}
}