{
  "type": "Feature",
  "properties": {
    "gn:admin1_code":"52.0",
    "gn:asciiname":"Trung Chau",
    "gn:country_code":"VN",
    "gn:dem":5,
    "gn:feature_class":"P",
    "gn:feature_code":"PPL",
    "gn:name":"Trung Ch\u00e2u",
    "gn:population":0,
    "gn:timezone":"Asia/Ho_Chi_Minh",
    "iso:country":"VN",
    "name:vie_x_preferred":[
        "Trung Ch\u00e2u"
    ],
    "wof:name":"Trung Chau",
    "wof:placetype":"locality"
},
  "geometry": {"coordinates":[105.90021000000002,18.406],"type":"Point"}
}