{
  "type": "Feature",
  "properties": {
    "gn:admin1_code":"5.0",
    "gn:asciiname":"Ban Phieng Phat",
    "gn:country_code":"VN",
    "gn:dem":402,
    "gn:feature_class":"P",
    "gn:feature_code":"PPL",
    "gn:name":"B\u1ea3n Phi\u00eang Ph\u00e1t",
    "gn:population":0,
    "gn:timezone":"Asia/Ho_Chi_Minh",
    "iso:country":"VN",
    "name:und_x_variant":[
        "Phieng Phat"
    ],
    "name:vie_x_preferred":[
        "B\u1ea3n Phi\u00eang Ph\u00e1t"
    ],
    "wof:name":"Ban Phieng Phat",
    "wof:placetype":"locality"
},
  "geometry": {"coordinates":[105.45648,22.87347],"type":"Point"}
}