{
  "type": "Feature",
  "properties": {
    "gn:admin1_code":"63.0",
    "gn:asciiname":"Son Tinh",
    "gn:country_code":"VN",
    "gn:dem":15,
    "gn:feature_class":"P",
    "gn:feature_code":"PPLA2",
    "gn:name":"S\u01a1n T\u1ecbnh",
    "gn:population":0,
    "gn:timezone":"Asia/Ho_Chi_Minh",
    "iso:country":"VN",
    "name:vie_x_preferred":[
        "S\u01a1n T\u1ecbnh"
    ],
    "name:zho_x_preferred":[
        "\u5c71\u975c\u7e23"
    ],
    "wof:name":"Son Tinh",
    "wof:placetype":"locality"
},
  "geometry": {"coordinates":[108.79582000000001,15.15856],"type":"Point"}
}