{
  "type": "Feature",
  "properties": {
    "gn:admin1_code":"52.0",
    "gn:asciiname":"Bac Hai",
    "gn:country_code":"VN",
    "gn:dem":9,
    "gn:feature_class":"P",
    "gn:feature_code":"PPL",
    "gn:name":"B\u1eafc H\u1ea3i",
    "gn:population":0,
    "gn:timezone":"Asia/Ho_Chi_Minh",
    "iso:country":"VN",
    "name:vie_x_preferred":[
        "B\u1eafc H\u1ea3i"
    ],
    "wof:name":"Bac Hai",
    "wof:placetype":"locality"
},
  "geometry": {"coordinates":[106.00105000000001,18.36584],"type":"Point"}
}