{
  "type": "Feature",
  "properties": {
    "gn:admin1_code":"39.0",
    "gn:asciiname":"Na Trung",
    "gn:country_code":"VN",
    "gn:dem":302,
    "gn:feature_class":"P",
    "gn:feature_code":"PPL",
    "gn:name":"N\u00e0 Trung",
    "gn:population":0,
    "gn:timezone":"Asia/Ho_Chi_Minh",
    "iso:country":"VN",
    "name:vie_x_preferred":[
        "N\u00e0 Trung"
    ],
    "wof:name":"Na Trung",
    "wof:placetype":"locality"
},
  "geometry": {"coordinates":[106.53848000000001,21.77863],"type":"Point"}
}