{
  "type": "Feature",
  "properties": {
    "gn:admin1_code":"66.0",
    "gn:asciiname":"Thon Vinh Hoa",
    "gn:country_code":"VN",
    "gn:dem":4,
    "gn:feature_class":"P",
    "gn:feature_code":"PPL",
    "gn:name":"Th\u00f4n Vinh H\u00f2a",
    "gn:population":0,
    "gn:timezone":"Asia/Ho_Chi_Minh",
    "iso:country":"VN",
    "name:und_x_variant":[
        "Vinh Hoa",
        "Th\u00f4n Vinh H\u00f2a"
    ],
    "wof:name":"Thon Vinh Hoa",
    "wof:placetype":"locality"
},
  "geometry": {"coordinates":[107.90000000000001,16.35],"type":"Point"}
}