{
  "type": "Feature",
  "properties": {
    "gn:admin1_code":"92.0",
    "gn:asciiname":"Ban Pa Hon",
    "gn:country_code":"VN",
    "gn:dem":476,
    "gn:feature_class":"P",
    "gn:feature_code":"PPL",
    "gn:name":"B\u1ea3n Pa Hon",
    "gn:population":0,
    "gn:timezone":"Asia/Ho_Chi_Minh",
    "iso:country":"VN",
    "wof:name":"Ban Pa Hon",
    "wof:placetype":"locality"
},
  "geometry": {"coordinates":[103.31667,21.78333],"type":"Point"}
}