{
  "type": "Feature",
  "properties": {
    "gn:admin1_code":"23.0",
    "gn:asciiname":"B'kor",
    "gn:country_code":"VN",
    "gn:dem":687,
    "gn:feature_class":"P",
    "gn:feature_code":"PPL",
    "gn:name":"B\u2019k\u00f2r",
    "gn:population":0,
    "gn:timezone":"Asia/Ho_Chi_Minh",
    "iso:country":"VN",
    "name:und_x_variant":[
        "B\u2019Kour",
        "B\u2019k\u00f2r"
    ],
    "wof:name":"B'kor",
    "wof:placetype":"locality"
},
  "geometry": {"coordinates":[107.91667,11.76667],"type":"Point"}
}