{
  "type": "Feature",
  "properties": {
    "gn:admin1_code":"71.0",
    "gn:asciiname":"Xom Ke",
    "gn:country_code":"VN",
    "gn:dem":17,
    "gn:feature_class":"P",
    "gn:feature_code":"PPL",
    "gn:name":"X\u00f3m K\u1ebb",
    "gn:population":0,
    "gn:timezone":"Asia/Ho_Chi_Minh",
    "iso:country":"VN",
    "name:vie_x_preferred":[
        "X\u00f3m K\u1ebb"
    ],
    "wof:name":"Xom Ke",
    "wof:placetype":"locality"
},
  "geometry": {"coordinates":[106.08403,21.22846],"type":"Point"}
}