{
  "type": "Feature",
  "properties": {
    "gn:admin1_code":"66.0",
    "gn:asciiname":"Pa Du",
    "gn:country_code":"VN",
    "gn:dem":555,
    "gn:feature_class":"P",
    "gn:feature_code":"PPL",
    "gn:name":"Pa Du",
    "gn:population":0,
    "gn:timezone":"Asia/Ho_Chi_Minh",
    "iso:country":"VN",
    "wof:name":"Pa Du",
    "wof:placetype":"locality"
},
  "geometry": {"coordinates":[107.23333,16.23333],"type":"Point"}
}