{
  "type": "Feature",
  "properties": {
    "gn:admin1_code":"66.0",
    "gn:asciiname":"Ap Trach Pho",
    "gn:country_code":"VN",
    "gn:dem":4,
    "gn:feature_class":"P",
    "gn:feature_code":"PPL",
    "gn:name":"\u1ea4p Tr\u1ea1ch Ph\u1ed5",
    "gn:population":0,
    "gn:timezone":"Asia/Ho_Chi_Minh",
    "iso:country":"VN",
    "name:und_x_variant":[
        "Uu Diem",
        "\u1ea4p Tr\u1ea1ch Ph\u1ed5"
    ],
    "wof:name":"Ap Trach Pho",
    "wof:placetype":"locality"
},
  "geometry": {"coordinates":[107.36667,16.63332999999999],"type":"Point"}
}