{
  "type": "Feature",
  "properties": {
    "gn:admin1_code":"50.0",
    "gn:asciiname":"Lao Va Chai",
    "gn:country_code":"VN",
    "gn:dem":1043,
    "gn:feature_class":"P",
    "gn:feature_code":"PPL",
    "gn:name":"Lao V\u00e0 Ch\u1ea3i",
    "gn:population":0,
    "gn:timezone":"Asia/Ho_Chi_Minh",
    "iso:country":"VN",
    "name:und_x_variant":[
        "Lao Du Tchai",
        "Lao Ou Tchai"
    ],
    "name:vie_x_preferred":[
        "Lao V\u00e0 Ch\u1ea3i"
    ],
    "wof:name":"Lao Va Chai",
    "wof:placetype":"locality"
},
  "geometry": {"coordinates":[105.08159000000001,23.11687],"type":"Point"}
}