{
  "type": "Feature",
  "properties": {
    "gn:admin1_code":"66.0",
    "gn:asciiname":"Nam Duong",
    "gn:country_code":"VN",
    "gn:dem":7,
    "gn:feature_class":"P",
    "gn:feature_code":"PPL",
    "gn:name":"Nam D\u01b0\u01a1ng",
    "gn:population":0,
    "gn:timezone":"Asia/Ho_Chi_Minh",
    "iso:country":"VN",
    "name:vie_x_preferred":[
        "Nam D\u01b0\u01a1ng"
    ],
    "wof:name":"Nam Duong",
    "wof:placetype":"locality"
},
  "geometry": {"coordinates":[107.46602,16.57722],"type":"Point"}
}