{
  "type": "Feature",
  "properties": {
    "gn:admin1_code":"11.0",
    "gn:asciiname":"Gia Thon",
    "gn:cc2":"VN",
    "gn:country_code":"VN",
    "gn:dem":7,
    "gn:feature_class":"P",
    "gn:feature_code":"PPL",
    "gn:name":"Gia Th\u1ed1n",
    "gn:population":0,
    "gn:timezone":"Asia/Ho_Chi_Minh",
    "iso:country":"VN",
    "name:und_x_variant":[
        "Lang N\u00f4i Dat",
        "Gia Th\u1ed1n"
    ],
    "wof:name":"Gia Thon",
    "wof:placetype":"locality"
},
  "geometry": {"coordinates":[106.08333,21.21667],"type":"Point"}
}