{
  "type": "Feature",
  "properties": {
    "gn:admin1_code":"86.0",
    "gn:asciiname":"Phuc Yen",
    "gn:country_code":"VN",
    "gn:dem":20,
    "gn:feature_class":"P",
    "gn:feature_code":"PPLA2",
    "gn:name":"Ph\u00fac Y\u00ean",
    "gn:population":0,
    "gn:timezone":"Asia/Ho_Chi_Minh",
    "iso:country":"VN",
    "name:und_x_variant":[
        "Ph\u00fac Y\u00ean"
    ],
    "wof:name":"Phuc Yen",
    "wof:placetype":"locality"
},
  "geometry": {"coordinates":[105.70483,21.23695],"type":"Point"}
}