{
  "type": "Feature",
  "properties": {
    "gn:admin1_code":"83.0",
    "gn:asciiname":"Chung Ngai",
    "gn:country_code":"VN",
    "gn:dem":70,
    "gn:feature_class":"P",
    "gn:feature_code":"PPL",
    "gn:name":"Chung Ng\u00e3i",
    "gn:population":0,
    "gn:timezone":"Asia/Ho_Chi_Minh",
    "iso:country":"VN",
    "name:vie_x_preferred":[
        "Chung Ng\u00e3i"
    ],
    "wof:name":"Chung Ngai",
    "wof:placetype":"locality"
},
  "geometry": {"coordinates":[105.04552,21.34435],"type":"Point"}
}