{
  "type": "Feature",
  "properties": {
    "gn:admin1_code":"32.0",
    "gn:asciiname":"Ban Chanh",
    "gn:country_code":"VN",
    "gn:dem":813,
    "gn:feature_class":"P",
    "gn:feature_code":"PPL",
    "gn:name":"B\u1ea3n Chanh",
    "gn:population":0,
    "gn:timezone":"Asia/Ho_Chi_Minh",
    "iso:country":"VN",
    "wof:name":"Ban Chanh",
    "wof:placetype":"locality"
},
  "geometry": {"coordinates":[104.78333000000001,21.08333],"type":"Point"}
}