{
  "type": "Feature",
  "properties": {
    "gn:admin1_code":"58.0",
    "gn:asciiname":"Nguyet Lang",
    "gn:country_code":"VN",
    "gn:dem":38,
    "gn:feature_class":"P",
    "gn:feature_code":"PPL",
    "gn:name":"Nguy\u1ec7t L\u1ea1ng",
    "gn:population":0,
    "gn:timezone":"Asia/Ho_Chi_Minh",
    "iso:country":"VN",
    "name:und_x_variant":[
        "Nyuget Lang",
        "Nguy\u1ec7t L\u1ea1ng"
    ],
    "wof:name":"Nguyet Lang",
    "wof:placetype":"locality"
},
  "geometry": {"coordinates":[105.33333,19.01667],"type":"Point"}
}