{
  "type": "Feature",
  "properties": {
    "gn:admin1_code":"5.0",
    "gn:asciiname":"Thi Tran Ta Lung",
    "gn:country_code":"VN",
    "gn:dem":157,
    "gn:feature_class":"P",
    "gn:feature_code":"PPLA2",
    "gn:name":"Th\u1ecb Tr\u1ea5n T\u00e0 L\u00f9ng",
    "gn:population":0,
    "gn:timezone":"Asia/Ho_Chi_Minh",
    "iso:country":"VN",
    "name:und_x_variant":[
        "T\u00e0 L\u00f9ng"
    ],
    "name:vie_x_preferred":[
        "Th\u1ecb Tr\u1ea5n T\u00e0 L\u00f9ng"
    ],
    "wof:name":"Thi Tran Ta Lung",
    "wof:placetype":"locality"
},
  "geometry": {"coordinates":[106.5669,22.4979],"type":"Point"}
}