{
  "type": "Feature",
  "properties": {
    "gn:admin1_code":"58.0",
    "gn:asciiname":"Lam Son",
    "gn:country_code":"VN",
    "gn:dem":32,
    "gn:feature_class":"P",
    "gn:feature_code":"PPL",
    "gn:name":"Lam S\u01a1n",
    "gn:population":0,
    "gn:timezone":"Asia/Ho_Chi_Minh",
    "iso:country":"VN",
    "name:vie_x_preferred":[
        "Lam S\u01a1n"
    ],
    "wof:name":"Lam Son",
    "wof:placetype":"locality"
},
  "geometry": {"coordinates":[105.42700000000001,18.77628],"type":"Point"}
}