{
  "type": "Feature",
  "properties": {
    "gn:admin1_code":"71.0",
    "gn:asciiname":"Thang Cuong",
    "gn:country_code":"VN",
    "gn:dem":7,
    "gn:feature_class":"P",
    "gn:feature_code":"PPL",
    "gn:name":"Th\u1eafng C\u01b0\u01a1ng",
    "gn:population":0,
    "gn:timezone":"Asia/Ho_Chi_Minh",
    "iso:country":"VN",
    "name:vie_x_preferred":[
        "Th\u1eafng C\u01b0\u01a1ng"
    ],
    "wof:name":"Thang Cuong",
    "wof:placetype":"locality"
},
  "geometry": {"coordinates":[106.22582,21.15808],"type":"Point"}
}