{
  "type": "Feature",
  "properties": {
    "gn:admin1_code":"54.0",
    "gn:asciiname":"Buon Tuong",
    "gn:country_code":"VN",
    "gn:dem":75,
    "gn:feature_class":"P",
    "gn:feature_code":"PPL",
    "gn:name":"Bu\u00f4n T\u01b0\u01a1ng",
    "gn:population":0,
    "gn:timezone":"Asia/Ho_Chi_Minh",
    "iso:country":"VN",
    "name:und_x_variant":[
        "Ban Teun",
        "Buon Teun",
        "Ban Toun",
        "Bu\u00f4n T\u01b0\u01a1ng"
    ],
    "wof:name":"Buon Tuong",
    "wof:placetype":"locality"
},
  "geometry": {"coordinates":[108.93704,12.55029],"type":"Point"}
}