{
  "type": "Feature",
  "properties": {
    "gn:admin1_code":"49.0",
    "gn:asciiname":"Lang Kong",
    "gn:country_code":"VN",
    "gn:dem":304,
    "gn:feature_class":"P",
    "gn:feature_code":"PPL",
    "gn:name":"L\u00e0ng K\u00f4ng",
    "gn:population":0,
    "gn:timezone":"Asia/Ho_Chi_Minh",
    "iso:country":"VN",
    "name:vie_x_preferred":[
        "L\u00e0ng K\u00f4ng"
    ],
    "wof:name":"Lang Kong",
    "wof:placetype":"locality"
},
  "geometry": {"coordinates":[108.59443,13.83203],"type":"Point"}
}