{
  "type": "Feature",
  "properties": {
    "gn:admin1_code":"67.0",
    "gn:asciiname":"Long Hoi",
    "gn:country_code":"VN",
    "gn:dem":7,
    "gn:feature_class":"P",
    "gn:feature_code":"PPL",
    "gn:name":"Long H\u1ed9i",
    "gn:population":0,
    "gn:timezone":"Asia/Ho_Chi_Minh",
    "iso:country":"VN",
    "name:vie_x_preferred":[
        "Long H\u1ed9i"
    ],
    "name:vie_x_variant":[
        "\u1ea4p Long H\u1ed9i"
    ],
    "wof:name":"Long Hoi",
    "wof:placetype":"locality"
},
  "geometry": {"coordinates":[106.16419,9.87788],"type":"Point"}
}