{
  "type": "Feature",
  "properties": {
    "gn:admin1_code":"39.0",
    "gn:asciiname":"Khuoi Luong",
    "gn:country_code":"VN",
    "gn:dem":296,
    "gn:feature_class":"P",
    "gn:feature_code":"PPL",
    "gn:name":"Khu\u1ed5i L\u01b0\u01a1ng",
    "gn:population":0,
    "gn:timezone":"Asia/Ho_Chi_Minh",
    "iso:country":"VN",
    "name:vie_x_preferred":[
        "Khu\u1ed5i L\u01b0\u01a1ng"
    ],
    "wof:name":"Khuoi Luong",
    "wof:placetype":"locality"
},
  "geometry": {"coordinates":[106.48309999999999,21.95258],"type":"Point"}
}