{
  "type": "Feature",
  "properties": {
    "gn:admin1_code":"83.0",
    "gn:asciiname":"Thuy Tram",
    "gn:country_code":"VN",
    "gn:dem":40,
    "gn:feature_class":"P",
    "gn:feature_code":"PPL",
    "gn:name":"Thuy Tram",
    "gn:population":0,
    "gn:timezone":"Asia/Ho_Chi_Minh",
    "iso:country":"VN",
    "name:vie_x_preferred":[
        "Thuy Tram"
    ],
    "wof:name":"Thuy Tram",
    "wof:placetype":"locality"
},
  "geometry": {"coordinates":[105.05301,21.46716],"type":"Point"}
}