{
  "type": "Feature",
  "properties": {
    "gn:admin1_code":"21.0",
    "gn:asciiname":"Cu La",
    "gn:cc2":"VN",
    "gn:country_code":"VN",
    "gn:dem":5,
    "gn:feature_class":"P",
    "gn:feature_code":"PPL",
    "gn:name":"C\u00f9 L\u00e0",
    "gn:population":0,
    "gn:timezone":"Asia/Ho_Chi_Minh",
    "iso:country":"VN",
    "name:und_x_variant":[
        "Cu Hoa",
        "C\u00f9 L\u00e0"
    ],
    "wof:name":"Cu La",
    "wof:placetype":"locality"
},
  "geometry": {"coordinates":[105.15611,9.91806],"type":"Point"}
}