{
  "type": "Feature",
  "properties": {
    "gn:admin1_code":"46.0",
    "gn:asciiname":"Loc Khanh",
    "gn:country_code":"VN",
    "gn:dem":10,
    "gn:feature_class":"P",
    "gn:feature_code":"PPL",
    "gn:name":"L\u1ed9c Kh\u00e1nh",
    "gn:population":0,
    "gn:timezone":"Asia/Ho_Chi_Minh",
    "iso:country":"VN",
    "name:und_x_variant":[
        "Khanh Hau",
        "L\u1ed9c Kh\u00e1nk",
        "L\u1ed9c Kh\u00e1nh",
        "Chanh Loc"
    ],
    "wof:name":"Loc Khanh",
    "wof:placetype":"locality"
},
  "geometry": {"coordinates":[109.19410000000001,13.9643],"type":"Point"}
}