{
  "type": "Feature",
  "properties": {
    "gn:admin1_code":"34.0",
    "gn:asciiname":"Xom Bai",
    "gn:country_code":"VN",
    "gn:dem":43,
    "gn:feature_class":"P",
    "gn:feature_code":"PPL",
    "gn:name":"X\u00f3m B\u00e1i",
    "gn:population":0,
    "gn:timezone":"Asia/Ho_Chi_Minh",
    "iso:country":"VN",
    "name:und_x_variant":[
        "X\u00f3m Bai"
    ],
    "name:vie_x_preferred":[
        "X\u00f3m B\u00e1i"
    ],
    "wof:name":"Xom Bai",
    "wof:placetype":"locality"
},
  "geometry": {"coordinates":[105.45077000000001,20.26759],"type":"Point"}
}