{
  "type": "Feature",
  "properties": {
    "gn:admin1_code":"50.0",
    "gn:asciiname":"Bong Ha",
    "gn:country_code":"VN",
    "gn:dem":646,
    "gn:feature_class":"P",
    "gn:feature_code":"PPL",
    "gn:name":"Bong Ha",
    "gn:population":0,
    "gn:timezone":"Asia/Ho_Chi_Minh",
    "iso:country":"VN",
    "name:und_x_variant":[
        "Hong Ha",
        "Bong Ha"
    ],
    "wof:name":"Bong Ha",
    "wof:placetype":"locality"
},
  "geometry": {"coordinates":[105.03333000000001,23.03333],"type":"Point"}
}