{
  "type": "Feature",
  "properties": {
    "gn:admin1_code":"90.0",
    "gn:asciiname":"Kim Tien",
    "gn:country_code":"VN",
    "gn:dem":142,
    "gn:feature_class":"P",
    "gn:feature_code":"PPL",
    "gn:name":"Kim Ti\u1ebfn",
    "gn:population":0,
    "gn:timezone":"Asia/Ho_Chi_Minh",
    "iso:country":"VN",
    "name:vie_x_preferred":[
        "Kim Ti\u1ebfn"
    ],
    "wof:name":"Kim Tien",
    "wof:placetype":"locality"
},
  "geometry": {"coordinates":[103.93626999999999,22.51902],"type":"Point"}
}