{
  "type": "Feature",
  "properties": {
    "gn:admin1_code":"49.0",
    "gn:asciiname":"Plei Herel",
    "gn:country_code":"VN",
    "gn:dem":707,
    "gn:feature_class":"P",
    "gn:feature_code":"PPL",
    "gn:name":"Plei Her\u00eal",
    "gn:population":0,
    "gn:timezone":"Asia/Ho_Chi_Minh",
    "iso:country":"VN",
    "wof:name":"Plei Herel",
    "wof:placetype":"locality"
},
  "geometry": {"coordinates":[108.23333,14.03333],"type":"Point"}
}