{
  "type": "Feature",
  "properties": {
    "gn:admin1_code":"52.0",
    "gn:asciiname":"Dong Con",
    "gn:country_code":"VN",
    "gn:dem":20,
    "gn:feature_class":"P",
    "gn:feature_code":"PPL",
    "gn:name":"\u0110\u1ed9ng C\u1ed3n",
    "gn:population":0,
    "gn:timezone":"Asia/Ho_Chi_Minh",
    "iso:country":"VN",
    "name:vie_x_preferred":[
        "\u0110\u1ed9ng C\u1ed3n"
    ],
    "wof:name":"Dong Con",
    "wof:placetype":"locality"
},
  "geometry": {"coordinates":[105.67547999999999,18.25209],"type":"Point"}
}