{
  "type": "Feature",
  "properties": {
    "gn:admin1_code":"60.0",
    "gn:asciiname":"Cau Gay",
    "gn:country_code":"VN",
    "gn:dem":44,
    "gn:feature_class":"P",
    "gn:feature_code":"PPL",
    "gn:name":"C\u1ea7u G\u00e3y",
    "gn:population":0,
    "gn:timezone":"Asia/Ho_Chi_Minh",
    "iso:country":"VN",
    "name:vie_x_preferred":[
        "C\u1ea7u G\u00e3y"
    ],
    "wof:name":"Cau Gay",
    "wof:placetype":"locality"
},
  "geometry": {"coordinates":[109.19122,11.72926],"type":"Point"}
}