{
  "type": "Feature",
  "properties": {
    "gn:admin1_code":"21.0",
    "gn:asciiname":"Xom Xeo Gia",
    "gn:cc2":"VN",
    "gn:country_code":"VN",
    "gn:dem":0,
    "gn:feature_class":"P",
    "gn:feature_code":"PPL",
    "gn:name":"X\u00f3m X\u00e8o Gia",
    "gn:population":0,
    "gn:timezone":"Asia/Ho_Chi_Minh",
    "iso:country":"VN",
    "name:und_x_variant":[
        "Xom Keo Gia",
        "X\u00f3m X\u00e8o Gia"
    ],
    "wof:name":"Xom Xeo Gia",
    "wof:placetype":"locality"
},
  "geometry": {"coordinates":[105.26667,9.68333],"type":"Point"}
}