{
  "type": "Feature",
  "properties": {
    "gn:admin1_code":"5.0",
    "gn:asciiname":"Po Bau",
    "gn:country_code":"VN",
    "gn:dem":296,
    "gn:feature_class":"P",
    "gn:feature_code":"PPL",
    "gn:name":"P\u00f3 B\u1ea9u",
    "gn:population":0,
    "gn:timezone":"Asia/Ho_Chi_Minh",
    "iso:country":"VN",
    "name:und_x_variant":[
        "Pao Boc",
        "Pac Boc"
    ],
    "name:vie_x_preferred":[
        "P\u00f3 B\u1ea9u"
    ],
    "wof:name":"Po Bau",
    "wof:placetype":"locality"
},
  "geometry": {"coordinates":[106.16985,22.46097],"type":"Point"}
}