{
  "type": "Feature",
  "properties": {
    "gn:admin1_code":"32.0",
    "gn:asciiname":"Ban Nong Trang",
    "gn:country_code":"VN",
    "gn:dem":845,
    "gn:feature_class":"P",
    "gn:feature_code":"PPL",
    "gn:name":"B\u1ea3n N\u1ecdng Tr\u1ea1ng",
    "gn:population":0,
    "gn:timezone":"Asia/Ho_Chi_Minh",
    "iso:country":"VN",
    "name:vie_x_preferred":[
        "B\u1ea3n N\u1ecdng Tr\u1ea1ng"
    ],
    "wof:name":"Ban Nong Trang",
    "wof:placetype":"locality"
},
  "geometry": {"coordinates":[103.85029,21.24674],"type":"Point"}
}