{
  "type": "Feature",
  "properties": {
    "gn:admin1_code":"5.0",
    "gn:asciiname":"Ban Na Vi",
    "gn:country_code":"VN",
    "gn:dem":358,
    "gn:feature_class":"P",
    "gn:feature_code":"PPL",
    "gn:name":"B\u1ea3n N\u00e0 V\u1ecb",
    "gn:population":0,
    "gn:timezone":"Asia/Ho_Chi_Minh",
    "iso:country":"VN",
    "name:vie_x_preferred":[
        "B\u1ea3n N\u00e0 V\u1ecb"
    ],
    "wof:name":"Ban Na Vi",
    "wof:placetype":"locality"
},
  "geometry": {"coordinates":[106.75731,22.79323],"type":"Point"}
}