{
  "type": "Feature",
  "properties": {
    "gn:admin1_code":"39.0",
    "gn:asciiname":"Bo Day",
    "gn:country_code":"VN",
    "gn:dem":319,
    "gn:feature_class":"P",
    "gn:feature_code":"PPL",
    "gn:name":"B\u00f3 \u0110\u1ea5y",
    "gn:population":0,
    "gn:timezone":"Asia/Ho_Chi_Minh",
    "iso:country":"VN",
    "name:vie_x_preferred":[
        "B\u00f3 \u0110\u1ea5y"
    ],
    "wof:name":"Bo Day",
    "wof:placetype":"locality"
},
  "geometry": {"coordinates":[106.25203999999999,21.89658],"type":"Point"}
}