{
  "type": "Feature",
  "properties": {
    "gn:admin1_code":"19.0",
    "gn:asciiname":"Lang Khieng",
    "gn:country_code":"VN",
    "gn:dem":317,
    "gn:feature_class":"P",
    "gn:feature_code":"PPL",
    "gn:name":"L\u00e0ng Khi\u00eang",
    "gn:population":0,
    "gn:timezone":"Asia/Ho_Chi_Minh",
    "iso:country":"VN",
    "wof:name":"Lang Khieng",
    "wof:placetype":"locality"
},
  "geometry": {"coordinates":[104.56667,22.11667000000001],"type":"Point"}
}