{
  "type": "Feature",
  "properties": {
    "gn:admin1_code":"75.0",
    "gn:asciiname":"Thang Hien",
    "gn:country_code":"VN",
    "gn:dem":36,
    "gn:feature_class":"P",
    "gn:feature_code":"PPL",
    "gn:name":"Th\u00e0ng Hi\u00ean",
    "gn:population":0,
    "gn:timezone":"Asia/Ho_Chi_Minh",
    "iso:country":"VN",
    "name:und_x_variant":[
        "X\u00f3m Th\u0103ng H\u00e8n"
    ],
    "name:vie_x_preferred":[
        "Th\u00e0ng Hi\u00ean"
    ],
    "wof:name":"Thang Hien",
    "wof:placetype":"locality"
},
  "geometry": {"coordinates":[106.9015,11.14108],"type":"Point"}
}