{
  "type": "Feature",
  "properties": {
    "gn:admin1_code":"20.0",
    "gn:asciiname":"Tam Ha",
    "gn:country_code":"VN",
    "gn:dem":6,
    "gn:feature_class":"P",
    "gn:feature_code":"PPL",
    "gn:name":"Tam H\u00e0",
    "gn:population":0,
    "gn:timezone":"Asia/Ho_Chi_Minh",
    "iso:country":"VN",
    "name:vie_x_preferred":[
        "Tam H\u00e0"
    ],
    "wof:name":"Tam Ha",
    "wof:placetype":"locality"
},
  "geometry": {"coordinates":[106.74088999999999,10.85994],"type":"Point"}
}