{
  "type": "Feature",
  "properties": {
    "gn:admin1_code":"38.0",
    "gn:asciiname":"Xom Chau",
    "gn:cc2":"VN",
    "gn:country_code":"VN",
    "gn:dem":154,
    "gn:feature_class":"P",
    "gn:feature_code":"PPL",
    "gn:name":"X\u00f3m Chau",
    "gn:population":0,
    "gn:timezone":"Asia/Ho_Chi_Minh",
    "iso:country":"VN",
    "name:und_x_variant":[
        "X\u00f3m Ch\u01a1u",
        "X\u00f3m Chau"
    ],
    "wof:name":"Xom Chau",
    "wof:placetype":"locality"
},
  "geometry": {"coordinates":[105.25,20.95],"type":"Point"}
}