{
  "type": "Feature",
  "properties": {
    "gn:admin1_code":"53.0",
    "gn:asciiname":"Lang Chieng",
    "gn:country_code":"VN",
    "gn:dem":113,
    "gn:feature_class":"P",
    "gn:feature_code":"PPL",
    "gn:name":"L\u00e0ng Chi\u1ec1ng",
    "gn:population":0,
    "gn:timezone":"Asia/Ho_Chi_Minh",
    "iso:country":"VN",
    "name:vie_x_preferred":[
        "L\u00e0ng Chi\u1ec1ng"
    ],
    "wof:name":"Lang Chieng",
    "wof:placetype":"locality"
},
  "geometry": {"coordinates":[105.59908,20.47631],"type":"Point"}
}