{
  "type": "Feature",
  "properties": {
    "gn:admin1_code":"3.0",
    "gn:asciiname":"Thanh Phu",
    "gn:country_code":"VN",
    "gn:dem":4,
    "gn:feature_class":"P",
    "gn:feature_code":"PPLA2",
    "gn:name":"Th\u1ea1nh Ph\u00fa",
    "gn:population":0,
    "gn:timezone":"Asia/Ho_Chi_Minh",
    "iso:country":"VN",
    "name:nld_x_preferred":[
        "Th\u1ea1nh Ph\u00fa"
    ],
    "name:und_x_variant":[
        "H\u01b0\u01a1ng Th\u1ea1nh Ph\u00fa",
        "Ph\u00fa",
        "Th\u1ea1nh Ph\u00fa"
    ],
    "name:vie_x_preferred":[
        "Th\u1ea1nh Ph\u00fa"
    ],
    "wof:name":"Thanh Phu",
    "wof:placetype":"locality"
},
  "geometry": {"coordinates":[106.51628999999998,9.94827],"type":"Point"}
}