{
  "type": "Feature",
  "properties": {
    "gn:admin1_code":"49.0",
    "gn:asciiname":"Khom Tam",
    "gn:country_code":"VN",
    "gn:dem":428,
    "gn:feature_class":"P",
    "gn:feature_code":"PPL",
    "gn:name":"Kh\u00f3m T\u00e1m",
    "gn:population":0,
    "gn:timezone":"Asia/Ho_Chi_Minh",
    "iso:country":"VN",
    "name:vie_x_preferred":[
        "Kh\u00f3m T\u00e1m"
    ],
    "name:vie_x_variant":[
        "Kh\u00f3m 8"
    ],
    "wof:name":"Khom Tam",
    "wof:placetype":"locality"
},
  "geometry": {"coordinates":[108.64704999999999,13.97284],"type":"Point"}
}