{
  "type": "Feature",
  "properties": {
    "gn:admin1_code":"32.0",
    "gn:asciiname":"Ban Dong Luong",
    "gn:country_code":"VN",
    "gn:dem":188,
    "gn:feature_class":"P",
    "gn:feature_code":"PPL",
    "gn:name":"B\u1ea3n \u0110\u1ed3ng L\u01b0\u01a1ng",
    "gn:population":0,
    "gn:timezone":"Asia/Ho_Chi_Minh",
    "iso:country":"VN",
    "name:vie_x_preferred":[
        "B\u1ea3n \u0110\u1ed3ng L\u01b0\u01a1ng"
    ],
    "wof:name":"Ban Dong Luong",
    "wof:placetype":"locality"
},
  "geometry": {"coordinates":[104.62634,21.24102],"type":"Point"}
}