{
  "type": "Feature",
  "properties": {
    "gn:admin1_code":"70.0",
    "gn:asciiname":"Lang Lom",
    "gn:country_code":"VN",
    "gn:dem":113,
    "gn:feature_class":"P",
    "gn:feature_code":"PPL",
    "gn:name":"L\u00e0ng Lom",
    "gn:population":0,
    "gn:timezone":"Asia/Ho_Chi_Minh",
    "iso:country":"VN",
    "name:vie_x_preferred":[
        "L\u00e0ng Lom"
    ],
    "wof:name":"Lang Lom",
    "wof:placetype":"locality"
},
  "geometry": {"coordinates":[104.47441999999999,21.92784],"type":"Point"}
}