{
  "type": "Feature",
  "properties": {
    "gn:admin1_code":"39.0",
    "gn:asciiname":"Lan Ca",
    "gn:country_code":"VN",
    "gn:dem":469,
    "gn:feature_class":"P",
    "gn:feature_code":"PPL",
    "gn:name":"L\u00e2n C\u00e1",
    "gn:population":0,
    "gn:timezone":"Asia/Ho_Chi_Minh",
    "iso:country":"VN",
    "name:und_x_variant":[
        "Lung Ca"
    ],
    "name:vie_x_preferred":[
        "L\u00e2n C\u00e1"
    ],
    "wof:name":"Lan Ca",
    "wof:placetype":"locality"
},
  "geometry": {"coordinates":[106.38055,21.77178],"type":"Point"}
}