{
  "type": "Feature",
  "properties": {
    "gn:admin1_code":"54.0",
    "gn:asciiname":"Thac Da",
    "gn:country_code":"VN",
    "gn:dem":19,
    "gn:feature_class":"P",
    "gn:feature_code":"PPL",
    "gn:name":"Th\u00e1c Da",
    "gn:population":0,
    "gn:timezone":"Asia/Ho_Chi_Minh",
    "iso:country":"VN",
    "wof:name":"Thac Da",
    "wof:placetype":"locality"
},
  "geometry": {"coordinates":[108.98333,12.35],"type":"Point"}
}