{
  "type": "Feature",
  "properties": {
    "gn:admin1_code":"50.0",
    "gn:asciiname":"Dong Khoui Dam",
    "gn:country_code":"VN",
    "gn:dem":93,
    "gn:feature_class":"P",
    "gn:feature_code":"PPL",
    "gn:name":"D\u00f4ng Khoui Dam",
    "gn:population":0,
    "gn:timezone":"Asia/Ho_Chi_Minh",
    "iso:country":"VN",
    "name:und_x_variant":[
        "Dong Khoie Dam",
        "D\u00f4ng Khoui Dam"
    ],
    "wof:name":"Dong Khoui Dam",
    "wof:placetype":"locality"
},
  "geometry": {"coordinates":[104.75,22.35],"type":"Point"}
}