{
  "type": "Feature",
  "properties": {
    "gn:admin1_code":"75.0",
    "gn:asciiname":"Ap 107",
    "gn:country_code":"VN",
    "gn:dem":88,
    "gn:feature_class":"P",
    "gn:feature_code":"PPL",
    "gn:name":"Ap 107",
    "gn:population":0,
    "gn:timezone":"Asia/Ho_Chi_Minh",
    "iso:country":"VN",
    "name:vie_x_preferred":[
        "Ap M\u1ed9t Tr\u0103m Kh\u00f4ng B\u1ea3y"
    ],
    "name:vie_x_variant":[
        "Ap 107"
    ],
    "wof:name":"Ap 107",
    "wof:placetype":"locality"
},
  "geometry": {"coordinates":[107.30725,11.16621],"type":"Point"}
}