{
  "type": "Feature",
  "properties": {
    "gn:admin1_code":"39.0",
    "gn:asciiname":"Len Rom",
    "gn:country_code":"VN",
    "gn:dem":307,
    "gn:feature_class":"P",
    "gn:feature_code":"PPL",
    "gn:name":"Len Rom",
    "gn:population":0,
    "gn:timezone":"Asia/Ho_Chi_Minh",
    "iso:country":"VN",
    "wof:name":"Len Rom",
    "wof:placetype":"locality"
},
  "geometry": {"coordinates":[106.38333,21.73333],"type":"Point"}
}