{
  "type": "Feature",
  "properties": {
    "gn:admin1_code":"72.0",
    "gn:asciiname":"Na Lon",
    "gn:country_code":"VN",
    "gn:dem":186,
    "gn:feature_class":"P",
    "gn:feature_code":"PPL",
    "gn:name":"N\u00e0 L\u00f2n",
    "gn:population":0,
    "gn:timezone":"Asia/Ho_Chi_Minh",
    "iso:country":"VN",
    "name:und_x_variant":[
        "N\u00e0 L\u00f2n",
        "Na Lan"
    ],
    "wof:name":"Na Lon",
    "wof:placetype":"locality"
},
  "geometry": {"coordinates":[105.75976,22.42891],"type":"Point"}
}