{
  "type": "Feature",
  "properties": {
    "gn:admin1_code":"39.0",
    "gn:asciiname":"Sien Chang",
    "gn:country_code":"VN",
    "gn:dem":198,
    "gn:feature_class":"P",
    "gn:feature_code":"PPL",
    "gn:name":"Si\u00ean Ch\u0103ng",
    "gn:population":0,
    "gn:timezone":"Asia/Ho_Chi_Minh",
    "iso:country":"VN",
    "wof:name":"Sien Chang",
    "wof:placetype":"locality"
},
  "geometry": {"coordinates":[106.57975999999999,22.25554],"type":"Point"}
}