{
  "type": "Feature",
  "properties": {
    "gn:admin1_code":"62.0",
    "gn:asciiname":"Rau Xa",
    "gn:country_code":"VN",
    "gn:dem":247,
    "gn:feature_class":"P",
    "gn:feature_code":"PPL",
    "gn:name":"Rau Xa",
    "gn:population":0,
    "gn:timezone":"Asia/Ho_Chi_Minh",
    "iso:country":"VN",
    "wof:name":"Rau Xa",
    "wof:placetype":"locality"
},
  "geometry": {"coordinates":[106.05,17.71667],"type":"Point"}
}