{
  "type": "Feature",
  "properties": {
    "gn:admin1_code":"44.0",
    "gn:asciiname":"Trung Quan",
    "gn:country_code":"VN",
    "gn:dem":14,
    "gn:feature_class":"P",
    "gn:feature_code":"PPL",
    "gn:name":"Trung Quan",
    "gn:population":0,
    "gn:timezone":"Asia/Ho_Chi_Minh",
    "iso:country":"VN",
    "name:vie_x_preferred":[
        "Trung Quan"
    ],
    "wof:name":"Trung Quan",
    "wof:placetype":"locality"
},
  "geometry": {"coordinates":[105.89738,20.94763],"type":"Point"}
}