{
  "type": "Feature",
  "properties": {
    "gn:admin1_code":"81.0",
    "gn:asciiname":"Xuan Dinh",
    "gn:country_code":"VN",
    "gn:dem":8,
    "gn:feature_class":"P",
    "gn:feature_code":"PPL",
    "gn:name":"Xu\u00e2n \u0110\u00ecnh",
    "gn:population":0,
    "gn:timezone":"Asia/Ho_Chi_Minh",
    "iso:country":"VN",
    "name:vie_x_preferred":[
        "Xu\u00e2n \u0110\u00ecnh"
    ],
    "wof:name":"Xuan Dinh",
    "wof:placetype":"locality"
},
  "geometry": {"coordinates":[105.94238,20.85578],"type":"Point"}
}