{
  "type": "Feature",
  "properties": {
    "gn:admin1_code":"3.0",
    "gn:asciiname":"Giong Ong Ho",
    "gn:country_code":"VN",
    "gn:dem":1,
    "gn:feature_class":"P",
    "gn:feature_code":"PPL",
    "gn:name":"Gi\u00f2ng \u00d4ng H\u1ed5",
    "gn:population":0,
    "gn:timezone":"Asia/Ho_Chi_Minh",
    "iso:country":"VN",
    "wof:name":"Giong Ong Ho",
    "wof:placetype":"locality"
},
  "geometry": {"coordinates":[106.55,10.21667],"type":"Point"}
}