{
  "type": "Feature",
  "properties": {
    "gn:admin1_code":"70.0",
    "gn:asciiname":"Khe Not",
    "gn:country_code":"VN",
    "gn:dem":311,
    "gn:feature_class":"P",
    "gn:feature_code":"PPL",
    "gn:name":"Khe N\u1ecdt",
    "gn:population":0,
    "gn:timezone":"Asia/Ho_Chi_Minh",
    "iso:country":"VN",
    "name:vie_x_preferred":[
        "Khe N\u1ecdt"
    ],
    "wof:name":"Khe Not",
    "wof:placetype":"locality"
},
  "geometry": {"coordinates":[104.45793999999999,21.95212],"type":"Point"}
}