{
  "type": "Feature",
  "properties": {
    "gn:admin1_code":"32.0",
    "gn:asciiname":"Na Man",
    "gn:country_code":"VN",
    "gn:dem":837,
    "gn:feature_class":"P",
    "gn:feature_code":"PPL",
    "gn:name":"N\u00e0 M\u1eb7n",
    "gn:population":0,
    "gn:timezone":"Asia/Ho_Chi_Minh",
    "iso:country":"VN",
    "name:vie_x_preferred":[
        "N\u00e0 M\u1eb7n"
    ],
    "wof:name":"Na Man",
    "wof:placetype":"locality"
},
  "geometry": {"coordinates":[103.93131,21.24182],"type":"Point"}
}