{
  "type": "Feature",
  "properties": {
    "gn:admin1_code":"75.0",
    "gn:asciiname":"Ap Hai",
    "gn:country_code":"VN",
    "gn:dem":50,
    "gn:feature_class":"P",
    "gn:feature_code":"PPL",
    "gn:name":"\u1ea4p Hai",
    "gn:population":0,
    "gn:timezone":"Asia/Ho_Chi_Minh",
    "iso:country":"VN",
    "name:vie_x_preferred":[
        "\u1ea4p Hai"
    ],
    "name:vie_x_variant":[
        "\u1ea4p 2"
    ],
    "wof:name":"Ap Hai",
    "wof:placetype":"locality"
},
  "geometry": {"coordinates":[106.63455,11.35324],"type":"Point"}
}