{
  "type": "Feature",
  "properties": {
    "gn:admin1_code":"84.0",
    "gn:asciiname":"Dich An Tay",
    "gn:country_code":"VN",
    "gn:dem":135,
    "gn:feature_class":"P",
    "gn:feature_code":"PPL",
    "gn:name":"\u0110\u1ecbch An T\u00e2y",
    "gn:population":0,
    "gn:timezone":"Asia/Ho_Chi_Minh",
    "iso:country":"VN",
    "wof:name":"Dich An Tay",
    "wof:placetype":"locality"
},
  "geometry": {"coordinates":[108.34999999999999,15.53333],"type":"Point"}
}