{
  "type": "Feature",
  "properties": {
    "gn:admin1_code":"55.0",
    "gn:asciiname":"Kon Cun",
    "gn:country_code":"VN",
    "gn:dem":1029,
    "gn:feature_class":"P",
    "gn:feature_code":"PPL",
    "gn:name":"Kon Cun",
    "gn:population":0,
    "gn:timezone":"Asia/Ho_Chi_Minh",
    "iso:country":"VN",
    "wof:name":"Kon Cun",
    "wof:placetype":"locality"
},
  "geometry": {"coordinates":[108.08333,14.58333],"type":"Point"}
}