{
  "type": "Feature",
  "properties": {
    "gn:admin1_code":"70.0",
    "gn:asciiname":"Thuong Thanh",
    "gn:country_code":"VN",
    "gn:dem":188,
    "gn:feature_class":"P",
    "gn:feature_code":"PPL",
    "gn:name":"Th\u01b0\u1ee3ng Th\u00e0nh",
    "gn:population":0,
    "gn:timezone":"Asia/Ho_Chi_Minh",
    "iso:country":"VN",
    "name:vie_x_preferred":[
        "Th\u01b0\u1ee3ng Th\u00e0nh"
    ],
    "wof:name":"Thuong Thanh",
    "wof:placetype":"locality"
},
  "geometry": {"coordinates":[104.78091999999999,21.5819],"type":"Point"}
}