{
  "type": "Feature",
  "properties": {
    "gn:admin1_code":"55.0",
    "gn:asciiname":"Touto",
    "gn:country_code":"VN",
    "gn:dem":1511,
    "gn:feature_class":"P",
    "gn:feature_code":"PPL",
    "gn:name":"Touto",
    "gn:population":0,
    "gn:timezone":"Asia/Ho_Chi_Minh",
    "iso:country":"VN",
    "wof:name":"Touto",
    "wof:placetype":"locality"
},
  "geometry": {"coordinates":[107.95,14.95],"type":"Point"}
}