{
  "type": "Feature",
  "properties": {
    "gn:admin1_code":"58.0",
    "gn:asciiname":"Gia Lac",
    "gn:country_code":"VN",
    "gn:dem":5,
    "gn:feature_class":"P",
    "gn:feature_code":"PPL",
    "gn:name":"Gia L\u1ea1c",
    "gn:population":0,
    "gn:timezone":"Asia/Ho_Chi_Minh",
    "iso:country":"VN",
    "name:und_x_variant":[
        "Lang Da Lac",
        "Gia L\u1ea1c"
    ],
    "wof:name":"Gia Lac",
    "wof:placetype":"locality"
},
  "geometry": {"coordinates":[105.55,18.68333],"type":"Point"}
}