{
  "type": "Feature",
  "properties": {
    "gn:admin1_code":"43.0",
    "gn:asciiname":"Xa Tan Lap",
    "gn:country_code":"VN",
    "gn:dem":179,
    "gn:feature_class":"P",
    "gn:feature_code":"PPL",
    "gn:name":"X\u00e3 T\u00e2n L\u1eadp",
    "gn:population":0,
    "gn:timezone":"Asia/Ho_Chi_Minh",
    "iso:country":"VN",
    "name:und_x_variant":[
        "Tan Lap",
        "X\u00e3 T\u00e2n L\u1eadp"
    ],
    "wof:name":"Xa Tan Lap",
    "wof:placetype":"locality"
},
  "geometry": {"coordinates":[107.18333,10.91667],"type":"Point"}
}