{
  "type": "Feature",
  "properties": {
    "gn:admin1_code":"50.0",
    "gn:asciiname":"Hiep Thuan",
    "gn:country_code":"VN",
    "gn:dem":420,
    "gn:feature_class":"P",
    "gn:feature_code":"PPL",
    "gn:name":"Hi\u1ec7p Thu\u1eadn",
    "gn:population":0,
    "gn:timezone":"Asia/Ho_Chi_Minh",
    "iso:country":"VN",
    "name:vie_x_preferred":[
        "Hi\u1ec7p Thu\u1eadn"
    ],
    "wof:name":"Hiep Thuan",
    "wof:placetype":"locality"
},
  "geometry": {"coordinates":[105.033,22.81929],"type":"Point"}
}