{
  "type": "Feature",
  "properties": {
    "gn:admin1_code":"92.0",
    "gn:asciiname":"Hua Sat",
    "gn:country_code":"VN",
    "gn:dem":1024,
    "gn:feature_class":"P",
    "gn:feature_code":"PPL",
    "gn:name":"Hua S\u00e1t",
    "gn:population":0,
    "gn:timezone":"Asia/Ho_Chi_Minh",
    "iso:country":"VN",
    "name:vie_x_preferred":[
        "Hua S\u00e1t"
    ],
    "wof:name":"Hua Sat",
    "wof:placetype":"locality"
},
  "geometry": {"coordinates":[103.23161,21.6414],"type":"Point"}
}