{
  "type": "Feature",
  "properties": {
    "gn:admin1_code":"68.0",
    "gn:asciiname":"Xom Ngoi Lau",
    "gn:country_code":"VN",
    "gn:dem":70,
    "gn:feature_class":"P",
    "gn:feature_code":"PPL",
    "gn:name":"X\u00f3m Ngoi Lau",
    "gn:population":0,
    "gn:timezone":"Asia/Ho_Chi_Minh",
    "iso:country":"VN",
    "wof:name":"Xom Ngoi Lau",
    "wof:placetype":"locality"
},
  "geometry": {"coordinates":[105.33333,21.71667],"type":"Point"}
}