{
  "type": "Feature",
  "properties": {
    "gn:admin1_code":"39.0",
    "gn:asciiname":"Phieng Mo",
    "gn:country_code":"VN",
    "gn:dem":171,
    "gn:feature_class":"P",
    "gn:feature_code":"PPL",
    "gn:name":"Phi\u00eang M\u00f2",
    "gn:population":0,
    "gn:timezone":"Asia/Ho_Chi_Minh",
    "iso:country":"VN",
    "name:und_x_variant":[
        "Phi\u00eang M\u00f2",
        "Phi\u00eang Mo"
    ],
    "wof:name":"Phieng Mo",
    "wof:placetype":"locality"
},
  "geometry": {"coordinates":[106.6198,22.17489],"type":"Point"}
}