{
  "type": "Feature",
  "properties": {
    "gn:admin1_code":"68.0",
    "gn:asciiname":"Lang Dong",
    "gn:country_code":"VN",
    "gn:dem":94,
    "gn:feature_class":"P",
    "gn:feature_code":"PPL",
    "gn:name":"L\u00e0ng \u0110\u00f3ng",
    "gn:population":0,
    "gn:timezone":"Asia/Ho_Chi_Minh",
    "iso:country":"VN",
    "name:vie_x_preferred":[
        "L\u00e0ng \u0110\u00f3ng"
    ],
    "wof:name":"Lang Dong",
    "wof:placetype":"locality"
},
  "geometry": {"coordinates":[105.27373,22.20835],"type":"Point"}
}