{
  "type": "Feature",
  "properties": {
    "gn:admin1_code":"88.0",
    "gn:asciiname":"Buon Dja",
    "gn:cc2":"VN",
    "gn:country_code":"VN",
    "gn:dem":557,
    "gn:feature_class":"P",
    "gn:feature_code":"PPL",
    "gn:name":"Bu\u00f4n Dj\u0103",
    "gn:population":0,
    "gn:timezone":"Asia/Ho_Chi_Minh",
    "iso:country":"VN",
    "name:und_x_variant":[
        "Buon Ung Dak",
        "Bu\u00f4n Dj\u0103"
    ],
    "wof:name":"Buon Dja",
    "wof:placetype":"locality"
},
  "geometry": {"coordinates":[108.40000000000001,12.85],"type":"Point"}
}