{
  "type": "Feature",
  "properties": {
    "gn:admin1_code":"63.0",
    "gn:asciiname":"An Thach",
    "gn:country_code":"VN",
    "gn:dem":10,
    "gn:feature_class":"P",
    "gn:feature_code":"PPL",
    "gn:name":"An Th\u1ea1ch",
    "gn:population":0,
    "gn:timezone":"Asia/Ho_Chi_Minh",
    "iso:country":"VN",
    "name:und_x_variant":[
        "An Thach Thach Nan",
        "An Th\u1ea1ch"
    ],
    "wof:name":"An Thach",
    "wof:placetype":"locality"
},
  "geometry": {"coordinates":[108.95341999999999,14.884],"type":"Point"}
}