{
  "type": "Feature",
  "properties": {
    "gn:admin1_code":"17.0",
    "gn:asciiname":"Co Tiai",
    "gn:cc2":"VN",
    "gn:country_code":"VN",
    "gn:dem":637,
    "gn:feature_class":"P",
    "gn:feature_code":"PPL",
    "gn:name":"Co Tiai",
    "gn:population":0,
    "gn:timezone":"Asia/Ho_Chi_Minh",
    "iso:country":"VN",
    "name:und_x_variant":[
        "Coc Tiai",
        "Co Tiai"
    ],
    "wof:name":"Co Tiai",
    "wof:placetype":"locality"
},
  "geometry": {"coordinates":[105.34999999999999,22.96667],"type":"Point"}
}