{
  "type": "Feature",
  "properties": {
    "gn:admin1_code":"66.0",
    "gn:asciiname":"Thon Phu O",
    "gn:country_code":"VN",
    "gn:dem":7,
    "gn:feature_class":"P",
    "gn:feature_code":"PPL",
    "gn:name":"Th\u00f4n Ph\u1ee5 \u1ed4",
    "gn:population":0,
    "gn:timezone":"Asia/Ho_Chi_Minh",
    "iso:country":"VN",
    "name:und_x_variant":[
        "Ph\u1ee5 \u1ed2",
        "Th\u00f4n Ph\u1ee5 \u1ed4"
    ],
    "wof:name":"Thon Phu O",
    "wof:placetype":"locality"
},
  "geometry": {"coordinates":[107.51667,16.48333],"type":"Point"}
}