{
  "type": "Feature",
  "properties": {
    "gn:admin1_code":"83.0",
    "gn:asciiname":"Xom Go",
    "gn:country_code":"VN",
    "gn:dem":50,
    "gn:feature_class":"P",
    "gn:feature_code":"PPL",
    "gn:name":"X\u00f3m G\u00f2",
    "gn:population":0,
    "gn:timezone":"Asia/Ho_Chi_Minh",
    "iso:country":"VN",
    "name:vie_x_preferred":[
        "X\u00f3m G\u00f2"
    ],
    "wof:name":"Xom Go",
    "wof:placetype":"locality"
},
  "geometry": {"coordinates":[105.12497,21.15906],"type":"Point"}
}