{
  "type": "Feature",
  "properties": {
    "gn:admin1_code":"80.0",
    "gn:asciiname":"Nhu Trac",
    "gn:country_code":"VN",
    "gn:dem":5,
    "gn:feature_class":"P",
    "gn:feature_code":"PPL",
    "gn:name":"Nh\u01b0 Tr\u00e1c",
    "gn:population":0,
    "gn:timezone":"Asia/Ho_Chi_Minh",
    "iso:country":"VN",
    "wof:name":"Nhu Trac",
    "wof:placetype":"locality"
},
  "geometry": {"coordinates":[106.09999999999999,20.58333],"type":"Point"}
}