{
  "type": "Feature",
  "properties": {
    "gn:admin1_code":"68.0",
    "gn:asciiname":"Lang Nang",
    "gn:country_code":"VN",
    "gn:dem":64,
    "gn:feature_class":"P",
    "gn:feature_code":"PPL",
    "gn:name":"L\u00e0ng N\u00e0ng",
    "gn:population":0,
    "gn:timezone":"Asia/Ho_Chi_Minh",
    "iso:country":"VN",
    "name:vie_x_preferred":[
        "L\u00e0ng N\u00e0ng"
    ],
    "wof:name":"Lang Nang",
    "wof:placetype":"locality"
},
  "geometry": {"coordinates":[105.44766,21.5267],"type":"Point"}
}