{
  "type": "Feature",
  "properties": {
    "gn:admin1_code":"58.0",
    "gn:asciiname":"Dieu Le",
    "gn:country_code":"VN",
    "gn:dem":6,
    "gn:feature_class":"P",
    "gn:feature_code":"PPL",
    "gn:name":"Dieu Le",
    "gn:population":0,
    "gn:timezone":"Asia/Ho_Chi_Minh",
    "iso:country":"VN",
    "name:und_x_variant":[
        "\u0110i\u1ec3n L\u1ec7"
    ],
    "wof:name":"Dieu Le",
    "wof:placetype":"locality"
},
  "geometry": {"coordinates":[105.58333,19.03333],"type":"Point"}
}