{
  "type": "Feature",
  "properties": {
    "gn:admin1_code":"34.0",
    "gn:asciiname":"My Ha",
    "gn:country_code":"VN",
    "gn:dem":5,
    "gn:feature_class":"P",
    "gn:feature_code":"PPL",
    "gn:name":"M\u1ef9 H\u00e0",
    "gn:population":0,
    "gn:timezone":"Asia/Ho_Chi_Minh",
    "iso:country":"VN",
    "name:und_x_variant":[
        "M\u1ef9 H\u00e0"
    ],
    "wof:name":"My Ha",
    "wof:placetype":"locality"
},
  "geometry": {"coordinates":[105.78333000000001,19.58333],"type":"Point"}
}