{
  "type": "Feature",
  "properties": {
    "gn:admin1_code":"32.0",
    "gn:asciiname":"Me Tren",
    "gn:country_code":"VN",
    "gn:dem":714,
    "gn:feature_class":"P",
    "gn:feature_code":"PPL",
    "gn:name":"M\u00e8 Tr\u00ean",
    "gn:population":0,
    "gn:timezone":"Asia/Ho_Chi_Minh",
    "iso:country":"VN",
    "name:vie_x_preferred":[
        "M\u00e8 Tr\u00ean"
    ],
    "wof:name":"Me Tren",
    "wof:placetype":"locality"
},
  "geometry": {"coordinates":[104.00922,21.15493],"type":"Point"}
}