{
  "type": "Feature",
  "properties": {
    "gn:admin1_code":"88.0",
    "gn:asciiname":"Buon Nam",
    "gn:country_code":"VN",
    "gn:dem":479,
    "gn:feature_class":"P",
    "gn:feature_code":"PPL",
    "gn:name":"Bu\u00f4n N\u0103m",
    "gn:population":0,
    "gn:timezone":"Asia/Ho_Chi_Minh",
    "iso:country":"VN",
    "name:vie_x_preferred":[
        "Bu\u00f4n N\u0103m"
    ],
    "wof:name":"Buon Nam",
    "wof:placetype":"locality"
},
  "geometry": {"coordinates":[108.20623999999999,12.34477],"type":"Point"}
}