{
  "type": "Feature",
  "properties": {
    "gn:admin1_code":"92.0",
    "gn:asciiname":"Tang Do",
    "gn:country_code":"VN",
    "gn:dem":502,
    "gn:feature_class":"P",
    "gn:feature_code":"PPL",
    "gn:name":"Tang Do",
    "gn:population":0,
    "gn:timezone":"Asia/Ho_Chi_Minh",
    "iso:country":"VN",
    "name:ara_x_preferred":[
        "\u062a\u0646\u063a \u062f\u0648"
    ],
    "name:azb_x_preferred":[
        "\u062a\u0646\u06af \u062f\u0648(\u0627\u0646\u062f\u06cc\u0645\u0634\u06a9)"
    ],
    "name:fas_x_preferred":[
        "\u062a\u0646\u06af \u062f\u0648"
    ],
    "name:vie_x_preferred":[
        "Tang Do"
    ],
    "wof:name":"Tang Do",
    "wof:placetype":"locality"
},
  "geometry": {"coordinates":[102.74202,21.92709],"type":"Point"}
}