{
  "type": "Feature",
  "properties": {
    "gn:admin1_code":"92.0",
    "gn:asciiname":"Tang Do",
    "gn:country_code":"VN",
    "gn:dem":502,
    "gn:feature_class":"P",
    "gn:feature_code":"PPL",
    "gn:name":"Tang Do",
    "gn:population":0,
    "gn:timezone":"Asia/Ho_Chi_Minh",
    "iso:country":"VN",
    "name:vie_x_preferred":[
        "Tang Do"
    ],
    "wof:name":"Tang Do",
    "wof:placetype":"locality"
},
  "geometry": {"coordinates":[102.74202,21.92709],"type":"Point"}
}