{
  "type": "Feature",
  "properties": {
    "gn:admin1_code":"88.0",
    "gn:asciiname":"Thon Bon A",
    "gn:country_code":"VN",
    "gn:dem":470,
    "gn:feature_class":"P",
    "gn:feature_code":"PPL",
    "gn:name":"Th\u00f4n B\u1ed1n A",
    "gn:population":0,
    "gn:timezone":"Asia/Ho_Chi_Minh",
    "iso:country":"VN",
    "name:vie_x_preferred":[
        "Th\u00f4n B\u1ed1n A"
    ],
    "name:vie_x_variant":[
        "Th\u00f4n 4A"
    ],
    "wof:name":"Thon Bon A",
    "wof:placetype":"locality"
},
  "geometry": {"coordinates":[108.65446,12.65221],"type":"Point"}
}