{
  "type": "Feature",
  "properties": {
    "gn:admin1_code":"32.0",
    "gn:asciiname":"Bon Phang",
    "gn:country_code":"VN",
    "gn:dem":931,
    "gn:feature_class":"P",
    "gn:feature_code":"PPL",
    "gn:name":"Bon Ph\u1eb7ng",
    "gn:population":0,
    "gn:timezone":"Asia/Ho_Chi_Minh",
    "iso:country":"VN",
    "wof:name":"Bon Phang",
    "wof:placetype":"locality"
},
  "geometry": {"coordinates":[103.75,21.36667000000001],"type":"Point"}
}