{
  "type": "Feature",
  "properties": {
    "gn:admin1_code":"32.0",
    "gn:asciiname":"Ban Nguy",
    "gn:cc2":"VN",
    "gn:country_code":"VN",
    "gn:dem":254,
    "gn:feature_class":"P",
    "gn:feature_code":"PPL",
    "gn:name":"B\u1ea3n Nguy",
    "gn:population":0,
    "gn:timezone":"Asia/Ho_Chi_Minh",
    "iso:country":"VN",
    "name:und_x_variant":[
        "Tu Ngui",
        "B\u1ea3n Nguy"
    ],
    "wof:name":"Ban Nguy",
    "wof:placetype":"locality"
},
  "geometry": {"coordinates":[104.95,20.86667000000001],"type":"Point"}
}