{
  "type": "Feature",
  "properties": {
    "gn:admin1_code":"52.0",
    "gn:asciiname":"Ru Ga",
    "gn:country_code":"VN",
    "gn:dem":15,
    "gn:feature_class":"P",
    "gn:feature_code":"PPL",
    "gn:name":"R\u00fa Ga",
    "gn:population":0,
    "gn:timezone":"Asia/Ho_Chi_Minh",
    "iso:country":"VN",
    "name:vie_x_preferred":[
        "R\u00fa Ga"
    ],
    "wof:name":"Ru Ga",
    "wof:placetype":"locality"
},
  "geometry": {"coordinates":[105.50942000000001,18.57961],"type":"Point"}
}