{
  "type": "Feature",
  "properties": {
    "gn:admin1_code":"34.0",
    "gn:asciiname":"Na Leng",
    "gn:cc2":"VN",
    "gn:country_code":"VN",
    "gn:dem":307,
    "gn:feature_class":"P",
    "gn:feature_code":"PPL",
    "gn:name":"Na Leng",
    "gn:population":0,
    "gn:timezone":"Asia/Ho_Chi_Minh",
    "iso:country":"VN",
    "name:und_x_variant":[
        "Na Lang",
        "Na Leng"
    ],
    "wof:name":"Na Leng",
    "wof:placetype":"locality"
},
  "geometry": {"coordinates":[105.05,20.16667],"type":"Point"}
}