{
  "type": "Feature",
  "properties": {
    "gn:admin1_code":"52.0",
    "gn:asciiname":"My Giang",
    "gn:country_code":"VN",
    "gn:dem":3,
    "gn:feature_class":"P",
    "gn:feature_code":"PPL",
    "gn:name":"My Giang",
    "gn:population":0,
    "gn:timezone":"Asia/Ho_Chi_Minh",
    "iso:country":"VN",
    "name:vie_x_preferred":[
        "My Giang"
    ],
    "wof:name":"My Giang",
    "wof:placetype":"locality"
},
  "geometry": {"coordinates":[105.85697999999999,18.45603],"type":"Point"}
}