{
  "type": "Feature",
  "properties": {
    "gn:admin1_code":"88.0",
    "gn:asciiname":"Khoi Chin",
    "gn:country_code":"VN",
    "gn:dem":548,
    "gn:feature_class":"P",
    "gn:feature_code":"PPL",
    "gn:name":"Kh\u1ed1i Ch\u00edn",
    "gn:population":0,
    "gn:timezone":"Asia/Ho_Chi_Minh",
    "iso:country":"VN",
    "name:vie_x_preferred":[
        "Kh\u1ed1i Ch\u00edn"
    ],
    "name:vie_x_variant":[
        "Kh\u1ed1i 9"
    ],
    "wof:name":"Khoi Chin",
    "wof:placetype":"locality"
},
  "geometry": {"coordinates":[108.08111,12.71064],"type":"Point"}
}