{
  "type": "Feature",
  "properties": {
    "gn:admin1_code":"92.0",
    "gn:asciiname":"Bung Buoi",
    "gn:country_code":"VN",
    "gn:dem":672,
    "gn:feature_class":"P",
    "gn:feature_code":"PPL",
    "gn:name":"B\u00fang B\u01b0\u1edfi",
    "gn:population":0,
    "gn:timezone":"Asia/Ho_Chi_Minh",
    "iso:country":"VN",
    "name:vie_x_preferred":[
        "B\u00fang B\u01b0\u1edfi"
    ],
    "wof:name":"Bung Buoi",
    "wof:placetype":"locality"
},
  "geometry": {"coordinates":[102.98754,21.14674],"type":"Point"}
}