{
  "type": "Feature",
  "properties": {
    "gn:admin1_code":"66.0",
    "gn:asciiname":"Thon Xuan Thien Thuong",
    "gn:country_code":"VN",
    "gn:dem":12,
    "gn:feature_class":"P",
    "gn:feature_code":"PPL",
    "gn:name":"Th\u00f4n Xu\u00e2n Thi\u00ean Th\u01b0\u1ee3ng",
    "gn:population":0,
    "gn:timezone":"Asia/Ho_Chi_Minh",
    "iso:country":"VN",
    "name:und_x_variant":[
        "Xuan Thien",
        "Th\u00f4n Xu\u00e2n Thi\u00ean Th\u01b0\u1ee3ng"
    ],
    "wof:name":"Thon Xuan Thien Thuong",
    "wof:placetype":"locality"
},
  "geometry": {"coordinates":[107.78333000000001,16.46667],"type":"Point"}
}