{
  "type": "Feature",
  "properties": {
    "gn:admin1_code":"50.0",
    "gn:asciiname":"Hoang Su Phi",
    "gn:cc2":"VN",
    "gn:country_code":"VN",
    "gn:dem":536,
    "gn:feature_class":"P",
    "gn:feature_code":"PPL",
    "gn:name":"Ho\u00e0ng Su Ph\u00ec",
    "gn:population":0,
    "gn:timezone":"Asia/Ho_Chi_Minh",
    "iso:country":"VN",
    "name:und_x_variant":[
        "Hoang-Tchou-Pi",
        "Ho\u00e0ng Su Ph\u00ec"
    ],
    "wof:name":"Hoang Su Phi",
    "wof:placetype":"locality"
},
  "geometry": {"coordinates":[104.66667,22.75],"type":"Point"}
}