{
  "type": "Feature",
  "properties": {
    "gn:admin1_code":"82.0",
    "gn:asciiname":"Thach Bi",
    "gn:country_code":"VN",
    "gn:dem":5,
    "gn:feature_class":"P",
    "gn:feature_code":"PPL",
    "gn:name":"Th\u1ea1ch Bi",
    "gn:population":0,
    "gn:timezone":"Asia/Ho_Chi_Minh",
    "iso:country":"VN",
    "name:vie_x_preferred":[
        "Th\u1ea1ch Bi"
    ],
    "wof:name":"Thach Bi",
    "wof:placetype":"locality"
},
  "geometry": {"coordinates":[106.17643,20.26036],"type":"Point"}
}