{
  "type": "Feature",
  "properties": {
    "gn:admin1_code":"88.0",
    "gn:asciiname":"Bon Kanour",
    "gn:country_code":"VN",
    "gn:dem":593,
    "gn:feature_class":"P",
    "gn:feature_code":"PPL",
    "gn:name":"Bon Kanour",
    "gn:population":0,
    "gn:timezone":"Asia/Ho_Chi_Minh",
    "iso:country":"VN",
    "wof:name":"Bon Kanour",
    "wof:placetype":"locality"
},
  "geometry": {"coordinates":[107.75,11.88333],"type":"Point"}
}