{
  "type": "Feature",
  "properties": {
    "gn:admin1_code":"72.0",
    "gn:asciiname":"Pac Chi",
    "gn:country_code":"VN",
    "gn:dem":264,
    "gn:feature_class":"P",
    "gn:feature_code":"PPL",
    "gn:name":"P\u00e1c Chi",
    "gn:population":0,
    "gn:timezone":"Asia/Ho_Chi_Minh",
    "iso:country":"VN",
    "wof:name":"Pac Chi",
    "wof:placetype":"locality"
},
  "geometry": {"coordinates":[105.82765000000001,22.38661],"type":"Point"}
}