{
  "type": "Feature",
  "properties": {
    "gn:admin1_code":"89.0",
    "gn:asciiname":"Ban He Noi",
    "gn:country_code":"VN",
    "gn:dem":654,
    "gn:feature_class":"P",
    "gn:feature_code":"PPL",
    "gn:name":"B\u1ea3n He Noi",
    "gn:population":0,
    "gn:timezone":"Asia/Ho_Chi_Minh",
    "iso:country":"VN",
    "wof:name":"Ban He Noi",
    "wof:placetype":"locality"
},
  "geometry": {"coordinates":[103.90000000000001,21.96667],"type":"Point"}
}