{
  "type": "Feature",
  "properties": {
    "gn:admin1_code":"88.0",
    "gn:asciiname":"Xuan Truong",
    "gn:country_code":"VN",
    "gn:dem":583,
    "gn:feature_class":"P",
    "gn:feature_code":"PPL",
    "gn:name":"Xu\u00e2n Tr\u01b0\u1eddng",
    "gn:population":0,
    "gn:timezone":"Asia/Ho_Chi_Minh",
    "iso:country":"VN",
    "name:vie_x_preferred":[
        "Xu\u00e2n Tr\u01b0\u1eddng"
    ],
    "wof:name":"Xuan Truong",
    "wof:placetype":"locality"
},
  "geometry": {"coordinates":[108.39171,12.91125],"type":"Point"}
}