{
  "type": "Feature",
  "properties": {
    "gn:admin1_code":"93.0",
    "gn:asciiname":"Ap Tan Qui",
    "gn:country_code":"VN",
    "gn:dem":-1,
    "gn:feature_class":"P",
    "gn:feature_code":"PPL",
    "gn:name":"\u1ea4p T\u00e2n Q\u1ee9i",
    "gn:population":0,
    "gn:timezone":"Asia/Ho_Chi_Minh",
    "iso:country":"VN",
    "wof:name":"Ap Tan Qui",
    "wof:placetype":"locality"
},
  "geometry": {"coordinates":[105.59860999999999,9.86444],"type":"Point"}
}