{
  "type": "Feature",
  "properties": {
    "gn:admin1_code":"54.0",
    "gn:asciiname":"Thon Thai Thong",
    "gn:country_code":"VN",
    "gn:dem":3,
    "gn:feature_class":"P",
    "gn:feature_code":"PPL",
    "gn:name":"Th\u00f4n Th\u00e1i Th\u00f4ng",
    "gn:population":0,
    "gn:timezone":"Asia/Ho_Chi_Minh",
    "iso:country":"VN",
    "name:und_x_variant":[
        "Thai Thong",
        "Th\u00f4n Th\u00e1i Th\u00f4ng"
    ],
    "wof:name":"Thon Thai Thong",
    "wof:placetype":"locality"
},
  "geometry": {"coordinates":[109.16667,12.25],"type":"Point"}
}