{
  "type": "Feature",
  "properties": {
    "gn:admin1_code":"93.0",
    "gn:asciiname":"Nga Sau",
    "gn:country_code":"VN",
    "gn:dem":4,
    "gn:feature_class":"P",
    "gn:feature_code":"PPLA2",
    "gn:name":"Ng\u00e3 S\u00e1u",
    "gn:population":0,
    "gn:timezone":"Asia/Ho_Chi_Minh",
    "iso:country":"VN",
    "name:vie_x_preferred":[
        "Ng\u00e3 S\u00e1u"
    ],
    "wof:name":"Nga Sau",
    "wof:placetype":"locality"
},
  "geometry": {"coordinates":[105.80542,9.92303],"type":"Point"}
}