{
  "type": "Feature",
  "properties": {
    "gn:admin1_code":"55.0",
    "gn:asciiname":"Dak Den",
    "gn:country_code":"VN",
    "gn:dem":884,
    "gn:feature_class":"P",
    "gn:feature_code":"PPL",
    "gn:name":"\u0110\u1eafk D\u00ean",
    "gn:population":0,
    "gn:timezone":"Asia/Ho_Chi_Minh",
    "iso:country":"VN",
    "name:vie_x_preferred":[
        "\u0110\u1eafk D\u00ean"
    ],
    "wof:name":"Dak Den",
    "wof:placetype":"locality"
},
  "geometry": {"coordinates":[107.72333999999999,15.11227],"type":"Point"}
}