{
  "type": "Feature",
  "properties": {
    "gn:admin1_code":"83.0",
    "gn:asciiname":"Chu Mat",
    "gn:country_code":"VN",
    "gn:dem":21,
    "gn:feature_class":"P",
    "gn:feature_code":"PPL",
    "gn:name":"Chu M\u1eadt",
    "gn:population":0,
    "gn:timezone":"Asia/Ho_Chi_Minh",
    "iso:country":"VN",
    "name:und_x_variant":[
        "Ch\u00fa M\u1eadt"
    ],
    "name:vie_x_preferred":[
        "Chu M\u1eadt"
    ],
    "wof:name":"Chu Mat",
    "wof:placetype":"locality"
},
  "geometry": {"coordinates":[105.22641000000002,21.41016],"type":"Point"}
}