{
  "type": "Feature",
  "properties": {
    "gn:admin1_code":"39.0",
    "gn:asciiname":"On",
    "gn:country_code":"VN",
    "gn:dem":222,
    "gn:feature_class":"P",
    "gn:feature_code":"PPL",
    "gn:name":"\u00d4n",
    "gn:population":0,
    "gn:timezone":"Asia/Ho_Chi_Minh",
    "iso:country":"VN",
    "name:heb_x_preferred":[
        "\u05d0\u05d5\u05df"
    ],
    "name:ukr_x_preferred":[
        "\u041e\u043d"
    ],
    "wof:name":"On",
    "wof:placetype":"locality"
},
  "geometry": {"coordinates":[106.58333,21.66667],"type":"Point"}
}