{
  "type": "Feature",
  "properties": {
    "gn:admin1_code":"53.0",
    "gn:asciiname":"Bo Men",
    "gn:country_code":"VN",
    "gn:dem":742,
    "gn:feature_class":"P",
    "gn:feature_code":"PPL",
    "gn:name":"Bo Men",
    "gn:population":0,
    "gn:timezone":"Asia/Ho_Chi_Minh",
    "iso:country":"VN",
    "wof:name":"Bo Men",
    "wof:placetype":"locality"
},
  "geometry": {"coordinates":[105.05,20.88333],"type":"Point"}
}