{
  "type": "Feature",
  "properties": {
    "gn:admin1_code":"70.0",
    "gn:asciiname":"Trai Hut",
    "gn:country_code":"VN",
    "gn:dem":53,
    "gn:feature_class":"P",
    "gn:feature_code":"PPL",
    "gn:name":"Tr\u00e1i H\u00fat",
    "gn:population":0,
    "gn:timezone":"Asia/Ho_Chi_Minh",
    "iso:country":"VN",
    "name:und_x_variant":[
        "Tr\u1ea1i H\u00fat"
    ],
    "name:vie_x_preferred":[
        "Tr\u00e1i H\u00fat"
    ],
    "wof:name":"Trai Hut",
    "wof:placetype":"locality"
},
  "geometry": {"coordinates":[104.59238000000001,21.97071],"type":"Point"}
}