{
  "type": "Feature",
  "properties": {
    "gn:admin1_code":"58.0",
    "gn:asciiname":"Xom Chin",
    "gn:country_code":"VN",
    "gn:dem":23,
    "gn:feature_class":"P",
    "gn:feature_code":"PPL",
    "gn:name":"X\u00f3m Ch\u00edn",
    "gn:population":0,
    "gn:timezone":"Asia/Ho_Chi_Minh",
    "iso:country":"VN",
    "name:vie_x_preferred":[
        "X\u00f3m Ch\u00edn"
    ],
    "name:vie_x_variant":[
        "X\u00f3m 9"
    ],
    "wof:name":"Xom Chin",
    "wof:placetype":"locality"
},
  "geometry": {"coordinates":[105.48826,18.85762],"type":"Point"}
}