{
  "type": "Feature",
  "properties": {
    "gn:admin1_code":"81.0",
    "gn:asciiname":"Yen My",
    "gn:country_code":"VN",
    "gn:dem":8,
    "gn:feature_class":"P",
    "gn:feature_code":"PPLA2",
    "gn:name":"Y\u00ean M\u1ef9",
    "gn:population":0,
    "gn:timezone":"Asia/Ho_Chi_Minh",
    "iso:country":"VN",
    "name:vie_x_preferred":[
        "Y\u00ean M\u1ef9"
    ],
    "wof:name":"Yen My",
    "wof:placetype":"locality"
},
  "geometry": {"coordinates":[106.0356,20.88557],"type":"Point"}
}