{
  "type": "Feature",
  "properties": {
    "gn:admin1_code":"61.0",
    "gn:asciiname":"Thach Ban",
    "gn:country_code":"VN",
    "gn:dem":33,
    "gn:feature_class":"P",
    "gn:feature_code":"PPL",
    "gn:name":"Th\u1ea1ch B\u00e0n",
    "gn:population":0,
    "gn:timezone":"Asia/Ho_Chi_Minh",
    "iso:country":"VN",
    "name:und_x_variant":[
        "Van Loe",
        "Van Hoa",
        "Th\u1ea1ch B\u00e0n"
    ],
    "wof:name":"Thach Ban",
    "wof:placetype":"locality"
},
  "geometry": {"coordinates":[109.11667,12.98333],"type":"Point"}
}