{
  "type": "Feature",
  "properties": {
    "gn:admin1_code":"72.0",
    "gn:asciiname":"Pia Meo",
    "gn:country_code":"VN",
    "gn:dem":169,
    "gn:feature_class":"P",
    "gn:feature_code":"PPL",
    "gn:name":"Pia Meo",
    "gn:population":0,
    "gn:timezone":"Asia/Ho_Chi_Minh",
    "iso:country":"VN",
    "name:vie_x_preferred":[
        "Pia Meo"
    ],
    "wof:name":"Pia Meo",
    "wof:placetype":"locality"
},
  "geometry": {"coordinates":[105.73305999999999,22.46487],"type":"Point"}
}