{
  "type": "Feature",
  "properties": {
    "gn:admin1_code":"5.0",
    "gn:asciiname":"Loung Xeo",
    "gn:country_code":"VN",
    "gn:dem":1424,
    "gn:feature_class":"P",
    "gn:feature_code":"PPL",
    "gn:name":"Loung Xeo",
    "gn:population":0,
    "gn:timezone":"Asia/Ho_Chi_Minh",
    "iso:country":"VN",
    "wof:name":"Loung Xeo",
    "wof:placetype":"locality"
},
  "geometry": {"coordinates":[105.84999999999999,22.86667000000001],"type":"Point"}
}