{
  "type": "Feature",
  "properties": {
    "gn:admin1_code":"89.0",
    "gn:asciiname":"Can Ti",
    "gn:country_code":"VN",
    "gn:dem":1480,
    "gn:feature_class":"P",
    "gn:feature_code":"PPL",
    "gn:name":"Can Ti",
    "gn:population":0,
    "gn:timezone":"Asia/Ho_Chi_Minh",
    "iso:country":"VN",
    "wof:name":"Can Ti",
    "wof:placetype":"locality"
},
  "geometry": {"coordinates":[103.34999999999999,22.45],"type":"Point"}
}