{
  "type": "Feature",
  "properties": {
    "gn:admin1_code":"32.0",
    "gn:asciiname":"Ban Phu Mao",
    "gn:cc2":"VN",
    "gn:country_code":"VN",
    "gn:dem":486,
    "gn:feature_class":"P",
    "gn:feature_code":"PPL",
    "gn:name":"B\u1ea3n Phu Mao",
    "gn:population":0,
    "gn:timezone":"Asia/Ho_Chi_Minh",
    "iso:country":"VN",
    "name:und_x_variant":[
        "B\u1ea3n Pho Mao",
        "B\u1ea3n Phu Mao"
    ],
    "wof:name":"Ban Phu Mao",
    "wof:placetype":"locality"
},
  "geometry": {"coordinates":[104.96666999999999,20.75],"type":"Point"}
}