{
  "type": "Feature",
  "properties": {
    "gn:admin1_code":"87.0",
    "gn:asciiname":"Lan Quoi Hai",
    "gn:country_code":"VN",
    "gn:dem":8,
    "gn:feature_class":"P",
    "gn:feature_code":"PPL",
    "gn:name":"L\u00e2n Qu\u1edbi Hai",
    "gn:population":0,
    "gn:timezone":"Asia/Ho_Chi_Minh",
    "iso:country":"VN",
    "name:vie_x_preferred":[
        "L\u00e2n Qu\u1edbi Hai"
    ],
    "name:vie_x_variant":[
        "L\u00e2n Qu\u1edbi 2"
    ],
    "wof:name":"Lan Quoi Hai",
    "wof:placetype":"locality"
},
  "geometry": {"coordinates":[105.40975,10.18426],"type":"Point"}
}