{
  "type": "Feature",
  "properties": {
    "gn:admin1_code":"24.0",
    "gn:asciiname":"Ap Hoa An",
    "gn:country_code":"VN",
    "gn:dem":2,
    "gn:feature_class":"P",
    "gn:feature_code":"PPL",
    "gn:name":"\u1ea4p H\u00f2a An",
    "gn:population":0,
    "gn:timezone":"Asia/Ho_Chi_Minh",
    "iso:country":"VN",
    "wof:name":"Ap Hoa An",
    "wof:placetype":"locality"
},
  "geometry": {"coordinates":[106.33333,10.56667],"type":"Point"}
}