{
  "type": "Feature",
  "properties": {
    "gn:admin1_code":"35.0",
    "gn:asciiname":"Phu Chu",
    "gn:country_code":"VN",
    "gn:dem":6,
    "gn:feature_class":"P",
    "gn:feature_code":"PPL",
    "gn:name":"Ph\u00fa Ch\u1eed",
    "gn:population":0,
    "gn:timezone":"Asia/Ho_Chi_Minh",
    "iso:country":"VN",
    "name:und_x_variant":[
        "Ph\u00fac Ch\u01b0"
    ],
    "name:vie_x_preferred":[
        "Ph\u00fa Ch\u1eed"
    ],
    "wof:name":"Phu Chu",
    "wof:placetype":"locality"
},
  "geometry": {"coordinates":[106.2158,20.48452],"type":"Point"}
}