{
  "type": "Feature",
  "properties": {
    "gn:admin1_code":"50.0",
    "gn:asciiname":"Ban Na Sa",
    "gn:country_code":"VN",
    "gn:dem":822,
    "gn:feature_class":"P",
    "gn:feature_code":"PPL",
    "gn:name":"B\u1ea3n N\u00e0 Sa",
    "gn:population":0,
    "gn:timezone":"Asia/Ho_Chi_Minh",
    "iso:country":"VN",
    "name:vie_x_preferred":[
        "B\u1ea3n N\u00e0 Sa"
    ],
    "wof:name":"Ban Na Sa",
    "wof:placetype":"locality"
},
  "geometry": {"coordinates":[105.32259999999999,22.95796],"type":"Point"}
}