{
  "type": "Feature",
  "properties": {
    "gn:admin1_code":"58.0",
    "gn:asciiname":"Phu Huu",
    "gn:country_code":"VN",
    "gn:dem":3,
    "gn:feature_class":"P",
    "gn:feature_code":"PPL",
    "gn:name":"Ph\u00fa H\u1eefu",
    "gn:population":0,
    "gn:timezone":"Asia/Ho_Chi_Minh",
    "iso:country":"VN",
    "name:und_x_variant":[
        "Phu Dien",
        "Ph\u00fa H\u1eefu"
    ],
    "wof:name":"Phu Huu",
    "wof:placetype":"locality"
},
  "geometry": {"coordinates":[105.51667,18.96667],"type":"Point"}
}