{
  "type": "Feature",
  "properties": {
    "gn:admin1_code":"69.0",
    "gn:asciiname":"Dong Hung Ba",
    "gn:country_code":"VN",
    "gn:dem":3,
    "gn:feature_class":"P",
    "gn:feature_code":"PPL",
    "gn:name":"\u0110\u00f4ng H\u01b0ng Ba",
    "gn:population":0,
    "gn:timezone":"Asia/Ho_Chi_Minh",
    "iso:country":"VN",
    "name:und_x_variant":[
        "\u1ea4p \u0110\u00f4ng H\u01b0ng"
    ],
    "name:vie_x_preferred":[
        "\u0110\u00f4ng H\u01b0ng"
    ],
    "name:vie_x_variant":[
        "\u0110\u00f4ng H\u01b0ng Ba",
        "\u0110\u00f4ng H\u01b0ng 3"
    ],
    "wof:name":"Dong Hung Ba",
    "wof:placetype":"locality"
},
  "geometry": {"coordinates":[105.85962000000001,10.00752],"type":"Point"}
}