{
  "type": "Feature",
  "properties": {
    "gn:admin1_code":"87.0",
    "gn:asciiname":"Thanh Hung Mot",
    "gn:country_code":"VN",
    "gn:dem":7,
    "gn:feature_class":"P",
    "gn:feature_code":"PPL",
    "gn:name":"Th\u1ea1nh H\u01b0ng M\u1ed9t",
    "gn:population":0,
    "gn:timezone":"Asia/Ho_Chi_Minh",
    "iso:country":"VN",
    "name:vie_x_preferred":[
        "Th\u1ea1nh H\u01b0ng M\u1ed9t"
    ],
    "name:vie_x_variant":[
        "Th\u1ea1nh H\u01b0ng 1"
    ],
    "wof:name":"Thanh Hung Mot",
    "wof:placetype":"locality"
},
  "geometry": {"coordinates":[105.46888,10.16419],"type":"Point"}
}