{
  "type": "Feature",
  "properties": {
    "gn:admin1_code":"92.0",
    "gn:asciiname":"Na Pen Hai",
    "gn:country_code":"VN",
    "gn:dem":956,
    "gn:feature_class":"P",
    "gn:feature_code":"PPL",
    "gn:name":"N\u00e0 P\u00e8n Hai",
    "gn:population":0,
    "gn:timezone":"Asia/Ho_Chi_Minh",
    "iso:country":"VN",
    "name:vie_x_preferred":[
        "N\u00e0 P\u00e8n Hai"
    ],
    "name:vie_x_variant":[
        "N\u00e0 P\u00e8n 2"
    ],
    "wof:name":"Na Pen Hai",
    "wof:placetype":"locality"
},
  "geometry": {"coordinates":[103.04564999999999,21.5041],"type":"Point"}
}