{
  "type": "Feature",
  "properties": {
    "gn:admin1_code":"71.0",
    "gn:asciiname":"Cau Thay",
    "gn:country_code":"VN",
    "gn:dem":27,
    "gn:feature_class":"P",
    "gn:feature_code":"PPL",
    "gn:name":"C\u1ea7u Th\u1ea7y",
    "gn:population":0,
    "gn:timezone":"Asia/Ho_Chi_Minh",
    "iso:country":"VN",
    "name:vie_x_preferred":[
        "C\u1ea7u Th\u1ea7y"
    ],
    "wof:name":"Cau Thay",
    "wof:placetype":"locality"
},
  "geometry": {"coordinates":[106.06686000000001,21.45956],"type":"Point"}
}