{
  "type": "Feature",
  "properties": {
    "gn:admin1_code":"58.0",
    "gn:asciiname":"Khanh Nghia",
    "gn:country_code":"VN",
    "gn:dem":8,
    "gn:feature_class":"P",
    "gn:feature_code":"PPL",
    "gn:name":"Kh\u00e1nh Ngh\u0129a",
    "gn:population":0,
    "gn:timezone":"Asia/Ho_Chi_Minh",
    "iso:country":"VN",
    "name:vie_x_preferred":[
        "Kh\u00e1nh Ngh\u0129a"
    ],
    "wof:name":"Khanh Nghia",
    "wof:placetype":"locality"
},
  "geometry": {"coordinates":[105.70048,18.80618],"type":"Point"}
}