{
  "type": "Feature",
  "properties": {
    "gn:admin1_code":"1.0",
    "gn:asciiname":"Dong Thinh A",
    "gn:country_code":"VN",
    "gn:dem":7,
    "gn:feature_class":"P",
    "gn:feature_code":"PPL",
    "gn:name":"\u0110\u00f4ng Th\u1ecbnh A",
    "gn:population":0,
    "gn:timezone":"Asia/Ho_Chi_Minh",
    "iso:country":"VN",
    "name:vie_x_preferred":[
        "\u0110\u00f4ng Th\u1ecbnh A"
    ],
    "wof:name":"Dong Thinh A",
    "wof:placetype":"locality"
},
  "geometry": {"coordinates":[105.4483,10.38163],"type":"Point"}
}