{
  "type": "Feature",
  "properties": {
    "gn:admin1_code":"21.0",
    "gn:asciiname":"Ba Bien B",
    "gn:country_code":"VN",
    "gn:dem":5,
    "gn:feature_class":"P",
    "gn:feature_code":"PPL",
    "gn:name":"Ba Bi\u1ec3n B",
    "gn:population":0,
    "gn:timezone":"Asia/Ho_Chi_Minh",
    "iso:country":"VN",
    "name:vie_x_preferred":[
        "Ba Bi\u1ec3n B"
    ],
    "wof:name":"Ba Bien B",
    "wof:placetype":"locality"
},
  "geometry": {"coordinates":[105.01518,9.86727],"type":"Point"}
}