{
  "type": "Feature",
  "properties": {
    "gn:admin1_code":"55.0",
    "gn:asciiname":"Nang Lon Ba",
    "gn:country_code":"VN",
    "gn:dem":801,
    "gn:feature_class":"P",
    "gn:feature_code":"PPL",
    "gn:name":"N\u0103ng L\u1edbn Ba",
    "gn:population":0,
    "gn:timezone":"Asia/Ho_Chi_Minh",
    "iso:country":"VN",
    "name:vie_x_preferred":[
        "N\u0103ng L\u1edbn Ba"
    ],
    "name:vie_x_variant":[
        "N\u0103ng L\u1edbn 3"
    ],
    "wof:name":"Nang Lon Ba",
    "wof:placetype":"locality"
},
  "geometry": {"coordinates":[107.82548,14.92416],"type":"Point"}
}