{
  "type": "Feature",
  "properties": {
    "gn:admin1_code":"49.0",
    "gn:asciiname":"Plei Kadjang",
    "gn:country_code":"VN",
    "gn:dem":524,
    "gn:feature_class":"P",
    "gn:feature_code":"PPL",
    "gn:name":"Plei Kadjang",
    "gn:population":0,
    "gn:timezone":"Asia/Ho_Chi_Minh",
    "iso:country":"VN",
    "wof:name":"Plei Kadjang",
    "wof:placetype":"locality"
},
  "geometry": {"coordinates":[108.58333,14.01667],"type":"Point"}
}