{
  "type": "Feature",
  "properties": {
    "gn:admin1_code":"5.0",
    "gn:asciiname":"Phai Chang",
    "gn:country_code":"VN",
    "gn:dem":192,
    "gn:feature_class":"P",
    "gn:feature_code":"PPL",
    "gn:name":"Phai Chang",
    "gn:population":0,
    "gn:timezone":"Asia/Ho_Chi_Minh",
    "iso:country":"VN",
    "wof:name":"Phai Chang",
    "wof:placetype":"locality"
},
  "geometry": {"coordinates":[106.15000000000001,22.73333],"type":"Point"}
}