{
  "type": "Feature",
  "properties": {
    "gn:admin1_code":"43.0",
    "gn:asciiname":"Cay Dau",
    "gn:country_code":"VN",
    "gn:dem":127,
    "gn:feature_class":"P",
    "gn:feature_code":"PPL",
    "gn:name":"C\u00e2y D\u1ea7u",
    "gn:population":0,
    "gn:timezone":"Asia/Ho_Chi_Minh",
    "iso:country":"VN",
    "name:vie_x_preferred":[
        "C\u00e2y D\u1ea7u"
    ],
    "wof:name":"Cay Dau",
    "wof:placetype":"locality"
},
  "geometry": {"coordinates":[107.48086000000001,11.30691],"type":"Point"}
}