{
  "type": "Feature",
  "properties": {
    "gn:admin1_code":"32.0",
    "gn:asciiname":"Lang Khey So",
    "gn:country_code":"VN",
    "gn:dem":507,
    "gn:feature_class":"P",
    "gn:feature_code":"PPL",
    "gn:name":"L\u00e0ng Khey So",
    "gn:population":0,
    "gn:timezone":"Asia/Ho_Chi_Minh",
    "iso:country":"VN",
    "wof:name":"Lang Khey So",
    "wof:placetype":"locality"
},
  "geometry": {"coordinates":[104.78333000000001,21.28333],"type":"Point"}
}