{
  "type": "Feature",
  "properties": {
    "gn:admin1_code":"84.0",
    "gn:asciiname":"Ninh Long",
    "gn:country_code":"VN",
    "gn:dem":84,
    "gn:feature_class":"P",
    "gn:feature_code":"PPL",
    "gn:name":"Ninh Long",
    "gn:population":0,
    "gn:timezone":"Asia/Ho_Chi_Minh",
    "iso:country":"VN",
    "wof:name":"Ninh Long",
    "wof:placetype":"locality"
},
  "geometry": {"coordinates":[108.03333000000001,15.65],"type":"Point"}
}