{
  "type": "Feature",
  "properties": {
    "gn:admin1_code":"86.0",
    "gn:asciiname":"Long Thanh",
    "gn:country_code":"VN",
    "gn:dem":21,
    "gn:feature_class":"P",
    "gn:feature_code":"PPL",
    "gn:name":"Long Th\u00e0nh",
    "gn:population":0,
    "gn:timezone":"Asia/Ho_Chi_Minh",
    "iso:country":"VN",
    "name:vie_x_preferred":[
        "Long Th\u00e0nh"
    ],
    "wof:name":"Long Thanh",
    "wof:placetype":"locality"
},
  "geometry": {"coordinates":[105.39597999999999,21.37691],"type":"Point"}
}