{
  "type": "Feature",
  "properties": {
    "gn:admin1_code":"32.0",
    "gn:asciiname":"Pa Tche",
    "gn:country_code":"VN",
    "gn:dem":1399,
    "gn:feature_class":"P",
    "gn:feature_code":"PPL",
    "gn:name":"Pa Tch\u00e9",
    "gn:population":0,
    "gn:timezone":"Asia/Ho_Chi_Minh",
    "iso:country":"VN",
    "wof:name":"Pa Tche",
    "wof:placetype":"locality"
},
  "geometry": {"coordinates":[104.83333,20.76667],"type":"Point"}
}