{
  "type": "Feature",
  "properties": {
    "gn:admin1_code":"50.0",
    "gn:asciiname":"Ban Na Ly",
    "gn:country_code":"VN",
    "gn:dem":513,
    "gn:feature_class":"P",
    "gn:feature_code":"PPL",
    "gn:name":"B\u1ea3n N\u00e0 L\u1ef3",
    "gn:population":0,
    "gn:timezone":"Asia/Ho_Chi_Minh",
    "iso:country":"VN",
    "name:vie_x_preferred":[
        "B\u1ea3n N\u00e0 L\u1ef3"
    ],
    "wof:name":"Ban Na Ly",
    "wof:placetype":"locality"
},
  "geometry": {"coordinates":[105.42561000000001,22.68035],"type":"Point"}
}