{
  "type": "Feature",
  "properties": {
    "gn:admin1_code":"89.0",
    "gn:asciiname":"Nieu Tao Phung",
    "gn:country_code":"VN",
    "gn:dem":876,
    "gn:feature_class":"P",
    "gn:feature_code":"PPL",
    "gn:name":"Nieu Tao Phung",
    "gn:population":0,
    "gn:timezone":"Asia/Ho_Chi_Minh",
    "iso:country":"VN",
    "wof:name":"Nieu Tao Phung",
    "wof:placetype":"locality"
},
  "geometry": {"coordinates":[103.40000000000001,22.41667],"type":"Point"}
}