{
  "type": "Feature",
  "properties": {
    "gn:admin1_code":"88.0",
    "gn:asciiname":"Buon Ho",
    "gn:country_code":"VN",
    "gn:dem":706,
    "gn:feature_class":"P",
    "gn:feature_code":"PPL",
    "gn:name":"Bu\u00f4n H\u1ed3",
    "gn:population":0,
    "gn:timezone":"Asia/Ho_Chi_Minh",
    "iso:country":"VN",
    "name:jpn_x_preferred":[
        "\u30d6\u30aa\u30f3\u30db\u30fc"
    ],
    "name:und_x_variant":[
        "Ban Ho",
        "Bu\u00f4n H\u00f4"
    ],
    "name:vie_x_preferred":[
        "Bu\u00f4n H\u1ed3"
    ],
    "name:zho_x_preferred":[
        "\u5954\u80e1\u5e02\u793e"
    ],
    "wof:name":"Buon Ho",
    "wof:placetype":"locality"
},
  "geometry": {"coordinates":[108.2962,12.95226],"type":"Point"}
}