{
  "type": "Feature",
  "properties": {
    "gn:admin1_code":"88.0",
    "gn:asciiname":"Buon Ho",
    "gn:country_code":"VN",
    "gn:dem":706,
    "gn:feature_class":"P",
    "gn:feature_code":"PPL",
    "gn:name":"Bu\u00f4n H\u1ed3",
    "gn:population":0,
    "gn:timezone":"Asia/Ho_Chi_Minh",
    "iso:country":"VN",
    "name:und_x_variant":[
        "Ban Ho",
        "Bu\u00f4n H\u00f4",
        "Bu\u00f4n H\u1ed3"
    ],
    "wof:name":"Buon Ho",
    "wof:placetype":"locality"
},
  "geometry": {"coordinates":[108.2962,12.95226],"type":"Point"}
}