{
  "type": "Feature",
  "properties": {
    "gn:admin1_code":"87.0",
    "gn:asciiname":"Khu Nam",
    "gn:country_code":"VN",
    "gn:dem":4,
    "gn:feature_class":"P",
    "gn:feature_code":"PPL",
    "gn:name":"Khu N\u0103m",
    "gn:population":0,
    "gn:timezone":"Asia/Ho_Chi_Minh",
    "iso:country":"VN",
    "name:vie_x_preferred":[
        "Khu N\u0103m"
    ],
    "name:vie_x_variant":[
        "Khu 5"
    ],
    "wof:name":"Khu Nam",
    "wof:placetype":"locality"
},
  "geometry": {"coordinates":[105.51859,10.15057],"type":"Point"}
}