{
  "type": "Feature",
  "properties": {
    "gn:admin1_code":"92.0",
    "gn:asciiname":"Nam He Hai",
    "gn:country_code":"VN",
    "gn:dem":540,
    "gn:feature_class":"P",
    "gn:feature_code":"PPL",
    "gn:name":"N\u1eadm H\u1eb9 Hai",
    "gn:population":0,
    "gn:timezone":"Asia/Ho_Chi_Minh",
    "iso:country":"VN",
    "wof:name":"Nam He Hai",
    "wof:placetype":"locality"
},
  "geometry": {"coordinates":[103.02715000000001,21.20884],"type":"Point"}
}