{
  "type": "Feature",
  "properties": {
    "gn:admin1_code":"71.0",
    "gn:asciiname":"Lieu De",
    "gn:country_code":"VN",
    "gn:dem":8,
    "gn:feature_class":"P",
    "gn:feature_code":"PPL",
    "gn:name":"Li\u1ec5u \u0110\u00ea",
    "gn:population":0,
    "gn:timezone":"Asia/Ho_Chi_Minh",
    "iso:country":"VN",
    "name:vie_x_preferred":[
        "Li\u1ec5u \u0110\u00ea"
    ],
    "wof:name":"Lieu De",
    "wof:placetype":"locality"
},
  "geometry": {"coordinates":[106.23438,21.24462],"type":"Point"}
}