{
  "type": "Feature",
  "properties": {
    "gn:admin1_code":"5.0",
    "gn:asciiname":"Ban Thin",
    "gn:country_code":"VN",
    "gn:dem":442,
    "gn:feature_class":"P",
    "gn:feature_code":"PPL",
    "gn:name":"B\u00e2n Th\u00ecn",
    "gn:population":0,
    "gn:timezone":"Asia/Ho_Chi_Minh",
    "iso:country":"VN",
    "wof:name":"Ban Thin",
    "wof:placetype":"locality"
},
  "geometry": {"coordinates":[106.68333,22.65],"type":"Point"}
}