{
  "type": "Feature",
  "properties": {
    "gn:admin1_code":"89.0",
    "gn:asciiname":"Ban Pac La",
    "gn:country_code":"VN",
    "gn:dem":605,
    "gn:feature_class":"P",
    "gn:feature_code":"PPL",
    "gn:name":"B\u1ea3n P\u1eafc La",
    "gn:population":0,
    "gn:timezone":"Asia/Ho_Chi_Minh",
    "iso:country":"VN",
    "name:vie_x_preferred":[
        "B\u1ea3n P\u1eafc La"
    ],
    "wof:name":"Ban Pac La",
    "wof:placetype":"locality"
},
  "geometry": {"coordinates":[103.84336999999999,22.08031],"type":"Point"}
}