{
  "type": "Feature",
  "properties": {
    "gn:admin1_code":"5.0",
    "gn:asciiname":"Phieng Con Xac Lao",
    "gn:cc2":"VN",
    "gn:country_code":"VN",
    "gn:dem":181,
    "gn:feature_class":"P",
    "gn:feature_code":"PPL",
    "gn:name":"Phi\u00eang Con X\u00e1c Lao",
    "gn:population":0,
    "gn:timezone":"Asia/Ho_Chi_Minh",
    "iso:country":"VN",
    "name:und_x_variant":[
        "Phi\u00eang Con",
        "Phi\u00eang Con X\u00e1c Lao"
    ],
    "wof:name":"Phieng Con Xac Lao",
    "wof:placetype":"locality"
},
  "geometry": {"coordinates":[106.41667,22.55],"type":"Point"}
}