{
  "type": "Feature",
  "properties": {
    "gn:admin1_code":"54.0",
    "gn:asciiname":"Pa Kang",
    "gn:country_code":"VN",
    "gn:dem":152,
    "gn:feature_class":"P",
    "gn:feature_code":"PPL",
    "gn:name":"Pa K\u00e2ng",
    "gn:population":0,
    "gn:timezone":"Asia/Ho_Chi_Minh",
    "iso:country":"VN",
    "wof:name":"Pa Kang",
    "wof:placetype":"locality"
},
  "geometry": {"coordinates":[108.88333,12.41667],"type":"Point"}
}