{
  "type": "Feature",
  "properties": {
    "gn:admin1_code":"13.0",
    "gn:asciiname":"Dong Nghia",
    "gn:country_code":"VN",
    "gn:dem":3,
    "gn:feature_class":"P",
    "gn:feature_code":"PPL",
    "gn:name":"Dong Nghia",
    "gn:population":0,
    "gn:timezone":"Asia/Ho_Chi_Minh",
    "iso:country":"VN",
    "name:und_x_variant":[
        "\u0110\u00f4n Ngh\u0129a"
    ],
    "wof:name":"Dong Nghia",
    "wof:placetype":"locality"
},
  "geometry": {"coordinates":[106.66667,20.81667],"type":"Point"}
}