{
  "type": "Feature",
  "properties": {
    "gn:admin1_code":"39.0",
    "gn:asciiname":"Minh Quang",
    "gn:country_code":"VN",
    "gn:dem":393,
    "gn:feature_class":"P",
    "gn:feature_code":"PPL",
    "gn:name":"Minh Quang",
    "gn:population":0,
    "gn:timezone":"Asia/Ho_Chi_Minh",
    "iso:country":"VN",
    "name:vie_x_preferred":[
        "Minh Quang"
    ],
    "wof:name":"Minh Quang",
    "wof:placetype":"locality"
},
  "geometry": {"coordinates":[106.32714,21.94042],"type":"Point"}
}