{
  "type": "Feature",
  "properties": {
    "gn:admin1_code":"32.0",
    "gn:asciiname":"Nong Phu",
    "gn:country_code":"VN",
    "gn:dem":614,
    "gn:feature_class":"P",
    "gn:feature_code":"PPL",
    "gn:name":"Nong Ph\u00fa",
    "gn:population":0,
    "gn:timezone":"Asia/Ho_Chi_Minh",
    "iso:country":"VN",
    "name:vie_x_preferred":[
        "Nong Ph\u00fa"
    ],
    "wof:name":"Nong Phu",
    "wof:placetype":"locality"
},
  "geometry": {"coordinates":[104.03668999999999,21.22294],"type":"Point"}
}