{
  "type": "Feature",
  "properties": {
    "gn:admin1_code":"81.0",
    "gn:asciiname":"An Trang",
    "gn:country_code":"VN",
    "gn:dem":5,
    "gn:feature_class":"P",
    "gn:feature_code":"PPL",
    "gn:name":"An Tr\u00e0ng",
    "gn:population":0,
    "gn:timezone":"Asia/Ho_Chi_Minh",
    "iso:country":"VN",
    "name:vie_x_preferred":[
        "An Tr\u00e0ng"
    ],
    "wof:name":"An Trang",
    "wof:placetype":"locality"
},
  "geometry": {"coordinates":[106.16392999999999,20.68588],"type":"Point"}
}