{
  "type": "Feature",
  "properties": {
    "gn:admin1_code":"5.0",
    "gn:asciiname":"Dong Phen",
    "gn:country_code":"VN",
    "gn:dem":612,
    "gn:feature_class":"P",
    "gn:feature_code":"PPL",
    "gn:name":"\u0110\u00f4ng Ph\u00e9n",
    "gn:population":0,
    "gn:timezone":"Asia/Ho_Chi_Minh",
    "iso:country":"VN",
    "wof:name":"Dong Phen",
    "wof:placetype":"locality"
},
  "geometry": {"coordinates":[106.59999999999999,22.75],"type":"Point"}
}