{
  "type": "Feature",
  "properties": {
    "gn:admin1_code":"70.0",
    "gn:asciiname":"Nam Tuc",
    "gn:country_code":"VN",
    "gn:dem":350,
    "gn:feature_class":"P",
    "gn:feature_code":"PPL",
    "gn:name":"N\u1eadm T\u1ee5c",
    "gn:population":0,
    "gn:timezone":"Asia/Ho_Chi_Minh",
    "iso:country":"VN",
    "wof:name":"Nam Tuc",
    "wof:placetype":"locality"
},
  "geometry": {"coordinates":[104.46666999999999,21.61667000000001],"type":"Point"}
}