{
  "type": "Feature",
  "properties": {
    "gn:admin1_code":"87.0",
    "gn:asciiname":"Thanh Xuan",
    "gn:country_code":"VN",
    "gn:dem":4,
    "gn:feature_class":"P",
    "gn:feature_code":"PPL",
    "gn:name":"Th\u1ea1nh Xu\u00e2n",
    "gn:population":0,
    "gn:timezone":"Asia/Ho_Chi_Minh",
    "iso:country":"VN",
    "name:vie_x_preferred":[
        "Th\u1ea1nh Xu\u00e2n"
    ],
    "wof:name":"Thanh Xuan",
    "wof:placetype":"locality"
},
  "geometry": {"coordinates":[105.4405,10.14814],"type":"Point"}
}