{
  "type": "Feature",
  "properties": {
    "gn:admin1_code":"49.0",
    "gn:asciiname":"An Binh",
    "gn:country_code":"VN",
    "gn:dem":449,
    "gn:feature_class":"P",
    "gn:feature_code":"PPL",
    "gn:name":"An B\u00ecnh",
    "gn:population":0,
    "gn:timezone":"Asia/Ho_Chi_Minh",
    "iso:country":"VN",
    "wof:name":"An Binh",
    "wof:placetype":"locality"
},
  "geometry": {"coordinates":[108.71666999999999,14.03333],"type":"Point"}
}