{
  "type": "Feature",
  "properties": {
    "gn:admin1_code":"89.0",
    "gn:asciiname":"La Cuoi",
    "gn:country_code":"VN",
    "gn:dem":200,
    "gn:feature_class":"P",
    "gn:feature_code":"PPL",
    "gn:name":"L\u00e0 Cu\u1ed5i",
    "gn:population":0,
    "gn:timezone":"Asia/Ho_Chi_Minh",
    "iso:country":"VN",
    "name:vie_x_preferred":[
        "L\u00e0 Cu\u1ed5i"
    ],
    "wof:name":"La Cuoi",
    "wof:placetype":"locality"
},
  "geometry": {"coordinates":[103.43768,22.18972],"type":"Point"}
}