{
  "type": "Feature",
  "properties": {
    "gn:admin1_code":"66.0",
    "gn:asciiname":"Doi Chin",
    "gn:country_code":"VN",
    "gn:dem":29,
    "gn:feature_class":"P",
    "gn:feature_code":"PPL",
    "gn:name":"\u0110\u1ed9i Ch\u00edn",
    "gn:population":0,
    "gn:timezone":"Asia/Ho_Chi_Minh",
    "iso:country":"VN",
    "name:vie_x_preferred":[
        "\u0110\u1ed9i Ch\u00edn"
    ],
    "name:vie_x_variant":[
        "\u0110\u1ed9i 9"
    ],
    "wof:name":"Doi Chin",
    "wof:placetype":"locality"
},
  "geometry": {"coordinates":[107.4927,16.37821],"type":"Point"}
}