{
  "type": "Feature",
  "properties": {
    "gn:admin1_code":"58.0",
    "gn:asciiname":"Lang Ke Se",
    "gn:country_code":"VN",
    "gn:dem":84,
    "gn:feature_class":"P",
    "gn:feature_code":"PPL",
    "gn:name":"L\u00e0ng K\u1ebd Se",
    "gn:population":0,
    "gn:timezone":"Asia/Ho_Chi_Minh",
    "iso:country":"VN",
    "wof:name":"Lang Ke Se",
    "wof:placetype":"locality"
},
  "geometry": {"coordinates":[105.34999999999999,19.43333],"type":"Point"}
}