{
  "type": "Feature",
  "properties": {
    "gn:admin1_code":"32.0",
    "gn:asciiname":"Co Quen",
    "gn:cc2":"VN",
    "gn:country_code":"VN",
    "gn:dem":809,
    "gn:feature_class":"P",
    "gn:feature_code":"PPL",
    "gn:name":"Co Quen",
    "gn:population":0,
    "gn:timezone":"Asia/Ho_Chi_Minh",
    "iso:country":"VN",
    "name:und_x_variant":[
        "Cao Quan",
        "Co Quen"
    ],
    "wof:name":"Co Quen",
    "wof:placetype":"locality"
},
  "geometry": {"coordinates":[104.83333,20.93333],"type":"Point"}
}