{
  "type": "Feature",
  "properties": {
    "gn:admin1_code":"44.0",
    "gn:asciiname":"Van Khe",
    "gn:country_code":"VN",
    "gn:dem":25,
    "gn:feature_class":"P",
    "gn:feature_code":"PPL",
    "gn:name":"V\u0103n Kh\u00ea",
    "gn:population":0,
    "gn:timezone":"Asia/Ho_Chi_Minh",
    "iso:country":"VN",
    "name:vie_x_preferred":[
        "V\u0103n Kh\u00ea"
    ],
    "wof:name":"Van Khe",
    "wof:placetype":"locality"
},
  "geometry": {"coordinates":[105.45474,21.1319],"type":"Point"}
}