{
  "type": "Feature",
  "properties": {
    "gn:admin1_code":"39.0",
    "gn:asciiname":"Pac Cap",
    "gn:country_code":"VN",
    "gn:dem":266,
    "gn:feature_class":"P",
    "gn:feature_code":"PPL",
    "gn:name":"Pac C\u00e1p",
    "gn:population":0,
    "gn:timezone":"Asia/Ho_Chi_Minh",
    "iso:country":"VN",
    "wof:name":"Pac Cap",
    "wof:placetype":"locality"
},
  "geometry": {"coordinates":[106.83333,21.88333],"type":"Point"}
}