{
  "type": "Feature",
  "properties": {
    "gn:admin1_code":"89.0",
    "gn:asciiname":"Nong Hom",
    "gn:country_code":"VN",
    "gn:dem":289,
    "gn:feature_class":"P",
    "gn:feature_code":"PPL",
    "gn:name":"Nong Hom",
    "gn:population":0,
    "gn:timezone":"Asia/Ho_Chi_Minh",
    "iso:country":"VN",
    "wof:name":"Nong Hom",
    "wof:placetype":"locality"
},
  "geometry": {"coordinates":[103.46666999999999,22.21667],"type":"Point"}
}