{
  "type": "Feature",
  "properties": {
    "gn:admin1_code":"39.0",
    "gn:asciiname":"Po Cu",
    "gn:country_code":"VN",
    "gn:dem":445,
    "gn:feature_class":"P",
    "gn:feature_code":"PPL",
    "gn:name":"P\u00f2 Cu",
    "gn:population":0,
    "gn:timezone":"Asia/Ho_Chi_Minh",
    "iso:country":"VN",
    "name:und_x_variant":[
        "P\u00f2 C\u0169"
    ],
    "name:vie_x_preferred":[
        "P\u00f2 Cu"
    ],
    "wof:name":"Po Cu",
    "wof:placetype":"locality"
},
  "geometry": {"coordinates":[106.80168,21.65607],"type":"Point"}
}