{
  "type": "Feature",
  "properties": {
    "gn:admin1_code":"90.0",
    "gn:asciiname":"Ta Giang Phinh",
    "gn:country_code":"VN",
    "gn:dem":1792,
    "gn:feature_class":"P",
    "gn:feature_code":"PPL",
    "gn:name":"T\u1ea3 Giang Ph\u00ecnh",
    "gn:population":0,
    "gn:timezone":"Asia/Ho_Chi_Minh",
    "iso:country":"VN",
    "wof:name":"Ta Giang Phinh",
    "wof:placetype":"locality"
},
  "geometry": {"coordinates":[103.76667,22.41667],"type":"Point"}
}