{
  "type": "Feature",
  "properties": {
    "gn:admin1_code":"21.0",
    "gn:asciiname":"Ap Hoa Phau",
    "gn:cc2":"VN",
    "gn:country_code":"VN",
    "gn:dem":-9999,
    "gn:feature_class":"P",
    "gn:feature_code":"PPL",
    "gn:name":"\u1ea4p H\u00f2a Ph\u1ea7u",
    "gn:population":0,
    "gn:timezone":"Asia/Ho_Chi_Minh",
    "iso:country":"VN",
    "name:und_x_variant":[
        "Duong Hoa",
        "\u1ea4p H\u00f2a Ph\u1ea7u"
    ],
    "wof:name":"Ap Hoa Phau",
    "wof:placetype":"locality"
},
  "geometry": {"coordinates":[104.51667,10.33333],"type":"Point"}
}