{
  "type": "Feature",
  "properties": {
    "gn:admin1_code":"50.0",
    "gn:asciiname":"Nam Luong",
    "gn:country_code":"VN",
    "gn:dem":616,
    "gn:feature_class":"P",
    "gn:feature_code":"PPL",
    "gn:name":"Nam Luong",
    "gn:population":0,
    "gn:timezone":"Asia/Ho_Chi_Minh",
    "iso:country":"VN",
    "wof:name":"Nam Luong",
    "wof:placetype":"locality"
},
  "geometry": {"coordinates":[105.08333,22.98333],"type":"Point"}
}