{
  "type": "Feature",
  "properties": {
    "gn:admin1_code":"34.0",
    "gn:asciiname":"Mau Lam",
    "gn:country_code":"VN",
    "gn:dem":36,
    "gn:feature_class":"P",
    "gn:feature_code":"PPL",
    "gn:name":"M\u1eadu L\u00e2m",
    "gn:population":0,
    "gn:timezone":"Asia/Ho_Chi_Minh",
    "iso:country":"VN",
    "wof:name":"Mau Lam",
    "wof:placetype":"locality"
},
  "geometry": {"coordinates":[105.58333,19.68333],"type":"Point"}
}