{
  "type": "Feature",
  "properties": {
    "gn:admin1_code":"72.0",
    "gn:asciiname":"Cam Ha",
    "gn:country_code":"VN",
    "gn:dem":527,
    "gn:feature_class":"P",
    "gn:feature_code":"PPL",
    "gn:name":"C\u00e1m H\u1ea1",
    "gn:population":0,
    "gn:timezone":"Asia/Ho_Chi_Minh",
    "iso:country":"VN",
    "wof:name":"Cam Ha",
    "wof:placetype":"locality"
},
  "geometry": {"coordinates":[105.60854,22.45582000000001],"type":"Point"}
}