{
  "type": "Feature",
  "properties": {
    "gn:admin1_code":"32.0",
    "gn:asciiname":"Hoa Son Hai",
    "gn:country_code":"VN",
    "gn:dem":709,
    "gn:feature_class":"P",
    "gn:feature_code":"PPL",
    "gn:name":"Hoa S\u01a1n Hai",
    "gn:population":0,
    "gn:timezone":"Asia/Ho_Chi_Minh",
    "iso:country":"VN",
    "name:vie_x_preferred":[
        "Hoa S\u01a1n Hai"
    ],
    "name:vie_x_variant":[
        "Hoa S\u01a1n 2"
    ],
    "wof:name":"Hoa Son Hai",
    "wof:placetype":"locality"
},
  "geometry": {"coordinates":[103.9992,21.19377],"type":"Point"}
}