{
  "type": "Feature",
  "properties": {
    "gn:admin1_code":"70.0",
    "gn:asciiname":"Ban Che Tao",
    "gn:country_code":"VN",
    "gn:dem":1249,
    "gn:feature_class":"P",
    "gn:feature_code":"PPL",
    "gn:name":"B\u1ea3n Ch\u1ebf T\u1ea1o",
    "gn:population":0,
    "gn:timezone":"Asia/Ho_Chi_Minh",
    "iso:country":"VN",
    "name:vie_x_preferred":[
        "Ch\u1ebf T\u1ea1o"
    ],
    "name:vie_x_variant":[
        "B\u1ea3n Ch\u1ebf T\u1ea1o"
    ],
    "wof:name":"Ban Che Tao",
    "wof:placetype":"locality"
},
  "geometry": {"coordinates":[104.03196,21.72206],"type":"Point"}
}