{
  "type": "Feature",
  "properties": {
    "gn:admin1_code":"13.0",
    "gn:asciiname":"Phu Lien",
    "gn:cc2":"VN",
    "gn:country_code":"VN",
    "gn:dem":18,
    "gn:feature_class":"P",
    "gn:feature_code":"PPL",
    "gn:name":"Ph\u00f9 Li\u1ec5n",
    "gn:population":0,
    "gn:timezone":"Asia/Ho_Chi_Minh",
    "iso:country":"VN",
    "name:und_x_variant":[
        "Observatoire de Phu Lien",
        "Ph\u00f9 Li\u1ec5n"
    ],
    "wof:name":"Phu Lien",
    "wof:placetype":"locality"
},
  "geometry": {"coordinates":[106.63333,20.81667],"type":"Point"}
}