{
  "type": "Feature",
  "properties": {
    "gn:admin1_code":"90.0",
    "gn:asciiname":"Ban Ngai Pan",
    "gn:country_code":"VN",
    "gn:dem":1271,
    "gn:feature_class":"P",
    "gn:feature_code":"PPL",
    "gn:name":"B\u1ea3n Ng\u00e0i P\u1ea3n",
    "gn:population":0,
    "gn:timezone":"Asia/Ho_Chi_Minh",
    "iso:country":"VN",
    "name:vie_x_preferred":[
        "B\u1ea3n Ng\u00e0i P\u1ea3n"
    ],
    "wof:name":"Ban Ngai Pan",
    "wof:placetype":"locality"
},
  "geometry": {"coordinates":[104.28834000000001,22.69372000000001],"type":"Point"}
}