{
  "type": "Feature",
  "properties": {
    "gn:admin1_code":"65.0",
    "gn:asciiname":"Le Minh Chau",
    "gn:country_code":"VN",
    "gn:dem":1,
    "gn:feature_class":"P",
    "gn:feature_code":"PPL",
    "gn:name":"L\u00ea Minh Ch\u00e2u",
    "gn:population":0,
    "gn:timezone":"Asia/Ho_Chi_Minh",
    "iso:country":"VN",
    "name:vie_x_preferred":[
        "L\u00ea Minh Ch\u00e2u"
    ],
    "wof:name":"Le Minh Chau",
    "wof:placetype":"locality"
},
  "geometry": {"coordinates":[106.21053999999999,9.62195],"type":"Point"}
}