{
  "type": "Feature",
  "properties": {
    "gn:admin1_code":"39.0",
    "gn:asciiname":"Ban Na Phan",
    "gn:country_code":"VN",
    "gn:dem":275,
    "gn:feature_class":"P",
    "gn:feature_code":"PPL",
    "gn:name":"B\u1ea3n N\u00e0 Ph\u1ea7n",
    "gn:population":0,
    "gn:timezone":"Asia/Ho_Chi_Minh",
    "iso:country":"VN",
    "name:und_x_variant":[
        "B\u1ea3n N\u00e0 Ph\u1ea7n",
        "N\u00e0 Ph\u00e2n"
    ],
    "wof:name":"Ban Na Phan",
    "wof:placetype":"locality"
},
  "geometry": {"coordinates":[106.68778,22.07026],"type":"Point"}
}