{
  "type": "Feature",
  "properties": {
    "gn:admin1_code":"2.0",
    "gn:asciiname":"Coun Pi",
    "gn:country_code":"VN",
    "gn:dem":425,
    "gn:feature_class":"P",
    "gn:feature_code":"PPL",
    "gn:name":"Coun Pi",
    "gn:population":0,
    "gn:timezone":"Asia/Ho_Chi_Minh",
    "iso:country":"VN",
    "wof:name":"Coun Pi",
    "wof:placetype":"locality"
},
  "geometry": {"coordinates":[106.01667,22.38333],"type":"Point"}
}