{
  "type": "Feature",
  "properties": {
    "gn:admin1_code":"83.0",
    "gn:asciiname":"Dong Sen",
    "gn:country_code":"VN",
    "gn:dem":50,
    "gn:feature_class":"P",
    "gn:feature_code":"PPL",
    "gn:name":"\u0110\u1ed3ng Sen",
    "gn:population":0,
    "gn:timezone":"Asia/Ho_Chi_Minh",
    "iso:country":"VN",
    "name:und_x_variant":[
        "\u0110ong Sen"
    ],
    "name:vie_x_preferred":[
        "\u0110\u1ed3ng Sen"
    ],
    "wof:name":"Dong Sen",
    "wof:placetype":"locality"
},
  "geometry": {"coordinates":[105.2351,21.10518],"type":"Point"}
}