{
  "type": "Feature",
  "properties": {
    "gn:admin1_code":"67.0",
    "gn:asciiname":"Xom O Dung",
    "gn:country_code":"VN",
    "gn:dem":7,
    "gn:feature_class":"P",
    "gn:feature_code":"PPL",
    "gn:name":"X\u00f3m \u00d4 \u0110ung",
    "gn:population":0,
    "gn:timezone":"Asia/Ho_Chi_Minh",
    "iso:country":"VN",
    "name:und_x_variant":[
        "Xom Ong Dung",
        "X\u00f3m \u00d4 \u0110ung"
    ],
    "wof:name":"Xom O Dung",
    "wof:placetype":"locality"
},
  "geometry": {"coordinates":[106.21666999999999,9.86667],"type":"Point"}
}