{
  "type": "Feature",
  "properties": {
    "gn:admin1_code":"47.0",
    "gn:asciiname":"Cay Tung",
    "gn:country_code":"VN",
    "gn:dem":71,
    "gn:feature_class":"P",
    "gn:feature_code":"PPL",
    "gn:name":"C\u00e2y Tung",
    "gn:population":0,
    "gn:timezone":"Asia/Ho_Chi_Minh",
    "iso:country":"VN",
    "wof:name":"Cay Tung",
    "wof:placetype":"locality"
},
  "geometry": {"coordinates":[107.76667,10.75],"type":"Point"}
}