{
  "type": "Feature",
  "properties": {
    "gn:admin1_code":"70.0",
    "gn:asciiname":"Ngoc Chan",
    "gn:country_code":"VN",
    "gn:dem":203,
    "gn:feature_class":"P",
    "gn:feature_code":"PPL",
    "gn:name":"Ng\u1ecdc Ch\u1ea5n",
    "gn:population":0,
    "gn:timezone":"Asia/Ho_Chi_Minh",
    "iso:country":"VN",
    "name:und_x_variant":[
        "L\u00e0ng B\u00ea",
        "Ng\u1ecdc Ch\u1ea5n"
    ],
    "wof:name":"Ngoc Chan",
    "wof:placetype":"locality"
},
  "geometry": {"coordinates":[104.90000000000001,21.96667],"type":"Point"}
}