{
  "type": "Feature",
  "properties": {
    "gn:admin1_code":"88.0",
    "gn:asciiname":"Buon Don",
    "gn:country_code":"VN",
    "gn:dem":456,
    "gn:feature_class":"P",
    "gn:feature_code":"PPL",
    "gn:name":"Bu\u00f4n D\u01a1n",
    "gn:population":0,
    "gn:timezone":"Asia/Ho_Chi_Minh",
    "iso:country":"VN",
    "name:und_x_variant":[
        "Buon G\u2019D\u00e9",
        "Bu\u00f4n Dham"
    ],
    "name:vie_x_preferred":[
        "Bu\u00f4n D\u01a1n"
    ],
    "wof:name":"Buon Don",
    "wof:placetype":"locality"
},
  "geometry": {"coordinates":[108.14563,12.34033],"type":"Point"}
}