{
  "type": "Feature",
  "properties": {
    "gn:admin1_code":"50.0",
    "gn:asciiname":"Ban Kieng",
    "gn:country_code":"VN",
    "gn:dem":225,
    "gn:feature_class":"P",
    "gn:feature_code":"PPL",
    "gn:name":"B\u1ea3n Ki\u1ebfng",
    "gn:population":0,
    "gn:timezone":"Asia/Ho_Chi_Minh",
    "iso:country":"VN",
    "name:vie_x_preferred":[
        "B\u1ea3n Ki\u1ebfng"
    ],
    "wof:name":"Ban Kieng",
    "wof:placetype":"locality"
},
  "geometry": {"coordinates":[105.12603,22.86488],"type":"Point"}
}