{
  "type": "Feature",
  "properties": {
    "gn:admin1_code":"86.0",
    "gn:asciiname":"Bac Ai",
    "gn:country_code":"VN",
    "gn:dem":55,
    "gn:feature_class":"P",
    "gn:feature_code":"PPL",
    "gn:name":"B\u1eafc \u00c1i",
    "gn:population":0,
    "gn:timezone":"Asia/Ho_Chi_Minh",
    "iso:country":"VN",
    "name:vie_x_preferred":[
        "B\u1eafc \u00c1i"
    ],
    "wof:name":"Bac Ai",
    "wof:placetype":"locality"
},
  "geometry": {"coordinates":[105.73511000000001,21.38632],"type":"Point"}
}