{
  "type": "Feature",
  "properties": {
    "gn:admin1_code":"47.0",
    "gn:asciiname":"Ninh Thuan",
    "gn:country_code":"VN",
    "gn:dem":21,
    "gn:feature_class":"P",
    "gn:feature_code":"PPL",
    "gn:name":"Ninh Thu\u1eadn",
    "gn:population":0,
    "gn:timezone":"Asia/Ho_Chi_Minh",
    "iso:country":"VN",
    "name:und_x_variant":[
        "Ninh Thu\u00e2n",
        "Ninh Thu\u00e2n Th\u00f4n",
        "\u1ea4p Ninh Thu\u1eadn"
    ],
    "name:vie_x_preferred":[
        "Ninh Thu\u1eadn"
    ],
    "wof:name":"Ninh Thuan",
    "wof:placetype":"locality"
},
  "geometry": {"coordinates":[108.11873,11.01353],"type":"Point"}
}