{
  "type": "Feature",
  "properties": {
    "gn:admin1_code":"44.0",
    "gn:asciiname":"Co Nhue",
    "gn:country_code":"VN",
    "gn:dem":11,
    "gn:feature_class":"P",
    "gn:feature_code":"PPL",
    "gn:name":"C\u1ed5 Nhu\u1ebf",
    "gn:population":0,
    "gn:timezone":"Asia/Ho_Chi_Minh",
    "iso:country":"VN",
    "name:und_x_variant":[
        "C\u1ed5 Nhu\u1ebf Vi\u00ean"
    ],
    "name:vie_x_preferred":[
        "C\u1ed5 Nhu\u1ebf"
    ],
    "wof:name":"Co Nhue",
    "wof:placetype":"locality"
},
  "geometry": {"coordinates":[105.78125,21.05846],"type":"Point"}
}