{
  "type": "Feature",
  "properties": {
    "gn:admin1_code":"88.0",
    "gn:asciiname":"Buon Wik",
    "gn:country_code":"VN",
    "gn:dem":732,
    "gn:feature_class":"P",
    "gn:feature_code":"PPL",
    "gn:name":"Bu\u00f4n Wik",
    "gn:population":0,
    "gn:timezone":"Asia/Ho_Chi_Minh",
    "iso:country":"VN",
    "name:vie_x_preferred":[
        "Bu\u00f4n Wik"
    ],
    "wof:name":"Buon Wik",
    "wof:placetype":"locality"
},
  "geometry": {"coordinates":[108.29474,12.97484],"type":"Point"}
}