{
  "type": "Feature",
  "properties": {
    "gn:admin1_code":"54.0",
    "gn:asciiname":"Thon Truong Tay",
    "gn:country_code":"VN",
    "gn:dem":-9999,
    "gn:feature_class":"P",
    "gn:feature_code":"PPL",
    "gn:name":"Th\u00f4n Tr\u01b0\u1eddng T\u00e2y",
    "gn:population":0,
    "gn:timezone":"Asia/Ho_Chi_Minh",
    "iso:country":"VN",
    "name:und_x_variant":[
        "Truong Tay",
        "Th\u00f4n Tr\u01b0\u1eddng T\u00e2y"
    ],
    "wof:name":"Thon Truong Tay",
    "wof:placetype":"locality"
},
  "geometry": {"coordinates":[109.21666999999999,12.21667],"type":"Point"}
}