{
  "type": "Feature",
  "properties": {
    "gn:admin1_code":"71.0",
    "gn:asciiname":"Xom Cuong",
    "gn:country_code":"VN",
    "gn:dem":83,
    "gn:feature_class":"P",
    "gn:feature_code":"PPL",
    "gn:name":"X\u00f3m Cuong",
    "gn:population":0,
    "gn:timezone":"Asia/Ho_Chi_Minh",
    "iso:country":"VN",
    "wof:name":"Xom Cuong",
    "wof:placetype":"locality"
},
  "geometry": {"coordinates":[106.73333,21.43333],"type":"Point"}
}