{
  "type": "Feature",
  "properties": {
    "gn:admin1_code":"39.0",
    "gn:asciiname":"Soong Bai",
    "gn:country_code":"VN",
    "gn:dem":279,
    "gn:feature_class":"P",
    "gn:feature_code":"PPL",
    "gn:name":"Soong B\u00e1i",
    "gn:population":0,
    "gn:timezone":"Asia/Ho_Chi_Minh",
    "iso:country":"VN",
    "name:vie_x_preferred":[
        "Soong B\u00e1i"
    ],
    "wof:name":"Soong Bai",
    "wof:placetype":"locality"
},
  "geometry": {"coordinates":[106.45950999999999,21.84298],"type":"Point"}
}