{
  "type": "Feature",
  "properties": {
    "gn:admin1_code":"67.0",
    "gn:asciiname":"Ap Tu",
    "gn:country_code":"VN",
    "gn:dem":0,
    "gn:feature_class":"P",
    "gn:feature_code":"PPL",
    "gn:name":"\u1ea4p T\u01b0",
    "gn:population":0,
    "gn:timezone":"Asia/Ho_Chi_Minh",
    "iso:country":"VN",
    "name:und_x_variant":[
        "T\u01b0",
        "\u1ea4p T\u01b0"
    ],
    "wof:name":"Ap Tu",
    "wof:placetype":"locality"
},
  "geometry": {"coordinates":[106.22528,9.77472],"type":"Point"}
}