{
  "type": "Feature",
  "properties": {
    "gn:admin1_code":"85.0",
    "gn:asciiname":"Cau Ve",
    "gn:country_code":"VN",
    "gn:dem":90,
    "gn:feature_class":"P",
    "gn:feature_code":"PPL",
    "gn:name":"C\u1ea7u V\u1ebd",
    "gn:population":0,
    "gn:timezone":"Asia/Ho_Chi_Minh",
    "iso:country":"VN",
    "name:und_x_variant":[
        "Cao Ve"
    ],
    "name:vie_x_preferred":[
        "C\u1ea7u V\u1ebd"
    ],
    "wof:name":"Cau Ve",
    "wof:placetype":"locality"
},
  "geometry": {"coordinates":[106.08579,21.75924],"type":"Point"}
}