{
  "type": "Feature",
  "properties": {
    "gn:admin1_code":"70.0",
    "gn:asciiname":"Ban Tong Duon",
    "gn:country_code":"VN",
    "gn:dem":310,
    "gn:feature_class":"P",
    "gn:feature_code":"PPL",
    "gn:name":"B\u1ea3n T\u00f4ng Du\u00f4n",
    "gn:population":0,
    "gn:timezone":"Asia/Ho_Chi_Minh",
    "iso:country":"VN",
    "wof:name":"Ban Tong Duon",
    "wof:placetype":"locality"
},
  "geometry": {"coordinates":[104.53333000000001,21.56667],"type":"Point"}
}