{
  "type": "Feature",
  "properties": {
    "gn:admin1_code":"44.0",
    "gn:asciiname":"Vu Chu",
    "gn:country_code":"VN",
    "gn:dem":17,
    "gn:feature_class":"P",
    "gn:feature_code":"PPL",
    "gn:name":"Vu Chu",
    "gn:population":0,
    "gn:timezone":"Asia/Ho_Chi_Minh",
    "iso:country":"VN",
    "name:vie_x_preferred":[
        "Vu Chu"
    ],
    "wof:name":"Vu Chu",
    "wof:placetype":"locality"
},
  "geometry": {"coordinates":[105.37253,21.28568],"type":"Point"}
}