{
  "type": "Feature",
  "properties": {
    "gn:admin1_code":"72.0",
    "gn:asciiname":"Tong Tang",
    "gn:country_code":"VN",
    "gn:dem":81,
    "gn:feature_class":"P",
    "gn:feature_code":"PPL",
    "gn:name":"T\u1ed5ng T\u00e0ng",
    "gn:population":0,
    "gn:timezone":"Asia/Ho_Chi_Minh",
    "iso:country":"VN",
    "name:vie_x_preferred":[
        "T\u1ed5ng T\u00e0ng"
    ],
    "wof:name":"Tong Tang",
    "wof:placetype":"locality"
},
  "geometry": {"coordinates":[105.83241,22.01094],"type":"Point"}
}