{
  "type": "Feature",
  "properties": {
    "gn:admin1_code":"63.0",
    "gn:asciiname":"Tan Khanh",
    "gn:country_code":"VN",
    "gn:dem":35,
    "gn:feature_class":"P",
    "gn:feature_code":"PPL",
    "gn:name":"T\u00e2n Khanh",
    "gn:population":0,
    "gn:timezone":"Asia/Ho_Chi_Minh",
    "iso:country":"VN",
    "name:und_x_variant":[
        "Tan An Ap",
        "T\u00e2n Khanh"
    ],
    "wof:name":"Tan Khanh",
    "wof:placetype":"locality"
},
  "geometry": {"coordinates":[108.59999999999999,15.18333],"type":"Point"}
}