{
  "type": "Feature",
  "properties": {
    "gn:admin1_code":"83.0",
    "gn:asciiname":"Hoa Binh",
    "gn:country_code":"VN",
    "gn:dem":31,
    "gn:feature_class":"P",
    "gn:feature_code":"PPL",
    "gn:name":"Hoa B\u00ecnh",
    "gn:population":0,
    "gn:timezone":"Asia/Ho_Chi_Minh",
    "iso:country":"VN",
    "name:heb_x_preferred":[
        "\u05d4\u05d5\u05d0\u05d4 \u05d1\u05d9\u05df"
    ],
    "name:hun_x_preferred":[
        "Hoa Binh"
    ],
    "name:spa_x_preferred":[
        "Hoa Binh"
    ],
    "name:vie_x_preferred":[
        "Hoa B\u00ecnh"
    ],
    "wof:name":"Hoa Binh",
    "wof:placetype":"locality"
},
  "geometry": {"coordinates":[105.21463,21.42189],"type":"Point"}
}