{
  "type": "Feature",
  "properties": {
    "gn:admin1_code":"9.0",
    "gn:asciiname":"Go Bay Chau Giang",
    "gn:country_code":"VN",
    "gn:dem":4,
    "gn:feature_class":"P",
    "gn:feature_code":"PPL",
    "gn:name":"G\u00f2 B\u1ea9y Ch\u00e2u Giang",
    "gn:population":0,
    "gn:timezone":"Asia/Ho_Chi_Minh",
    "iso:country":"VN",
    "name:vie_x_preferred":[
        "G\u00f2 B\u1ea9y Ch\u00e2u Giang"
    ],
    "wof:name":"Go Bay Chau Giang",
    "wof:placetype":"locality"
},
  "geometry": {"coordinates":[105.51102,10.89587],"type":"Point"}
}