{
  "type": "Feature",
  "properties": {
    "gn:admin1_code":"76.0",
    "gn:asciiname":"Bu Nho",
    "gn:country_code":"VN",
    "gn:dem":118,
    "gn:feature_class":"P",
    "gn:feature_code":"PPL",
    "gn:name":"B\u00f9 Nho",
    "gn:population":0,
    "gn:timezone":"Asia/Ho_Chi_Minh",
    "iso:country":"VN",
    "name:und_x_variant":[
        "Ap Bu Nho",
        "B\u00f9 Nho"
    ],
    "wof:name":"Bu Nho",
    "wof:placetype":"locality"
},
  "geometry": {"coordinates":[106.84999999999999,11.73333],"type":"Point"}
}