{
  "type": "Feature",
  "properties": {
    "gn:admin1_code":"39.0",
    "gn:asciiname":"Ban Bo Ban",
    "gn:country_code":"VN",
    "gn:dem":263,
    "gn:feature_class":"P",
    "gn:feature_code":"PPL",
    "gn:name":"B\u1ea3n B\u00f3 B\u1ea9n",
    "gn:population":0,
    "gn:timezone":"Asia/Ho_Chi_Minh",
    "iso:country":"VN",
    "name:und_x_variant":[
        "B\u1ea3n B\u00f3 B\u1ea9n",
        "B\u00f3 B\u1ee7n"
    ],
    "wof:name":"Ban Bo Ban",
    "wof:placetype":"locality"
},
  "geometry": {"coordinates":[106.69902999999999,22.09203],"type":"Point"}
}