{
  "type": "Feature",
  "properties": {
    "gn:admin1_code":"63.0",
    "gn:asciiname":"Va Nheng",
    "gn:country_code":"VN",
    "gn:dem":67,
    "gn:feature_class":"P",
    "gn:feature_code":"PPL",
    "gn:name":"V\u1ea3 Nheng",
    "gn:population":0,
    "gn:timezone":"Asia/Ho_Chi_Minh",
    "iso:country":"VN",
    "name:vie_x_preferred":[
        "V\u1ea3 Nheng"
    ],
    "wof:name":"Va Nheng",
    "wof:placetype":"locality"
},
  "geometry": {"coordinates":[108.73062,14.75682],"type":"Point"}
}