{
  "type": "Feature",
  "properties": {
    "gn:admin1_code":"44.0",
    "gn:asciiname":"Chuc Son",
    "gn:country_code":"VN",
    "gn:dem":16,
    "gn:feature_class":"P",
    "gn:feature_code":"PPLA2",
    "gn:name":"Ch\u00fac S\u01a1n",
    "gn:population":0,
    "gn:timezone":"Asia/Ho_Chi_Minh",
    "iso:country":"VN",
    "name:vie_x_preferred":[
        "Ch\u00fac S\u01a1n"
    ],
    "wof:name":"Chuc Son",
    "wof:placetype":"locality"
},
  "geometry": {"coordinates":[105.70155,20.92375],"type":"Point"}
}