{
  "type": "Feature",
  "properties": {
    "gn:admin1_code":"54.0",
    "gn:asciiname":"Xom Tan Hung",
    "gn:country_code":"VN",
    "gn:dem":16,
    "gn:feature_class":"P",
    "gn:feature_code":"PPL",
    "gn:name":"X\u00f3m T\u00e2n H\u01b0ng",
    "gn:population":0,
    "gn:timezone":"Asia/Ho_Chi_Minh",
    "iso:country":"VN",
    "name:und_x_variant":[
        "\u0110\u1ed3ng Chu\u00f4i",
        "Tan Hung",
        "X\u00f3m T\u00e2n H\u01b0ng"
    ],
    "wof:name":"Xom Tan Hung",
    "wof:placetype":"locality"
},
  "geometry": {"coordinates":[109.09999999999999,12.45],"type":"Point"}
}