{
  "type": "Feature",
  "properties": {
    "gn:admin1_code":"59.0",
    "gn:asciiname":"Yen Duong",
    "gn:country_code":"VN",
    "gn:dem":6,
    "gn:feature_class":"P",
    "gn:feature_code":"PPL",
    "gn:name":"Y\u00ean D\u01b0\u01a1ng",
    "gn:population":0,
    "gn:timezone":"Asia/Ho_Chi_Minh",
    "iso:country":"VN",
    "wof:name":"Yen Duong",
    "wof:placetype":"locality"
},
  "geometry": {"coordinates":[106.01667,20.18333],"type":"Point"}
}