{
  "type": "Feature",
  "properties": {
    "gn:admin1_code":"72.0",
    "gn:asciiname":"Na Ca",
    "gn:country_code":"VN",
    "gn:dem":299,
    "gn:feature_class":"P",
    "gn:feature_code":"PPL",
    "gn:name":"Na Ca",
    "gn:population":0,
    "gn:timezone":"Asia/Ho_Chi_Minh",
    "iso:country":"VN",
    "wof:name":"Na Ca",
    "wof:placetype":"locality"
},
  "geometry": {"coordinates":[105.55,22.08333],"type":"Point"}
}