{
  "type": "Feature",
  "properties": {
    "gn:admin1_code":"58.0",
    "gn:asciiname":"Hoa Nam",
    "gn:country_code":"VN",
    "gn:dem":10,
    "gn:feature_class":"P",
    "gn:feature_code":"PPL",
    "gn:name":"Hoa Nam",
    "gn:population":0,
    "gn:timezone":"Asia/Ho_Chi_Minh",
    "iso:country":"VN",
    "name:vie_x_preferred":[
        "Hoa Nam"
    ],
    "wof:name":"Hoa Nam",
    "wof:placetype":"locality"
},
  "geometry": {"coordinates":[105.64310999999999,18.79875],"type":"Point"}
}