{
  "type": "Feature",
  "properties": {
    "gn:admin1_code":"45.0",
    "gn:asciiname":"Doi Hai",
    "gn:country_code":"VN",
    "gn:dem":52,
    "gn:feature_class":"P",
    "gn:feature_code":"PPL",
    "gn:name":"\u0110\u1ed9i Hai",
    "gn:population":0,
    "gn:timezone":"Asia/Ho_Chi_Minh",
    "iso:country":"VN",
    "name:vie_x_preferred":[
        "\u0110\u1ed9i Hai"
    ],
    "name:vie_x_variant":[
        "\u0110\u1ed9i 2"
    ],
    "wof:name":"Doi Hai",
    "wof:placetype":"locality"
},
  "geometry": {"coordinates":[107.43228000000001,10.62649],"type":"Point"}
}