{
  "type": "Feature",
  "properties": {
    "gn:admin1_code":"34.0",
    "gn:asciiname":"Chieng",
    "gn:country_code":"VN",
    "gn:dem":205,
    "gn:feature_class":"P",
    "gn:feature_code":"PPL",
    "gn:name":"Chi\u1ec1ng",
    "gn:population":0,
    "gn:timezone":"Asia/Ho_Chi_Minh",
    "iso:country":"VN",
    "name:und_x_variant":[
        "Chi\u00e9ng",
        "L\u00e0ng Chi\u00e9ng"
    ],
    "name:vie_x_preferred":[
        "Chi\u1ec1ng"
    ],
    "wof:name":"Chieng",
    "wof:placetype":"locality"
},
  "geometry": {"coordinates":[105.0877,20.23921],"type":"Point"}
}