{
  "type": "Feature",
  "properties": {
    "gn:admin1_code":"72.0",
    "gn:asciiname":"Na ken",
    "gn:country_code":"VN",
    "gn:dem":575,
    "gn:feature_class":"P",
    "gn:feature_code":"PPL",
    "gn:name":"N\u00e0 k\u00e9n",
    "gn:population":0,
    "gn:timezone":"Asia/Ho_Chi_Minh",
    "iso:country":"VN",
    "name:vie_x_preferred":[
        "N\u00e0 k\u00e9n"
    ],
    "wof:name":"Na ken",
    "wof:placetype":"locality"
},
  "geometry": {"coordinates":[105.95891,22.24998],"type":"Point"}
}