{
  "type": "Feature",
  "properties": {
    "gn:admin1_code":"50.0",
    "gn:asciiname":"Lo Lo Thang",
    "gn:country_code":"VN",
    "gn:dem":959,
    "gn:feature_class":"P",
    "gn:feature_code":"PPL",
    "gn:name":"L\u1ed3 L\u1ed1 Th\u00e0ng",
    "gn:population":0,
    "gn:timezone":"Asia/Ho_Chi_Minh",
    "iso:country":"VN",
    "name:vie_x_preferred":[
        "L\u1ed3 L\u1ed1 Th\u00e0ng"
    ],
    "wof:name":"Lo Lo Thang",
    "wof:placetype":"locality"
},
  "geometry": {"coordinates":[105.08634000000001,22.99662],"type":"Point"}
}