{
  "type": "Feature",
  "properties": {
    "gn:admin1_code":"83.0",
    "gn:asciiname":"Tan Tien",
    "gn:country_code":"VN",
    "gn:dem":62,
    "gn:feature_class":"P",
    "gn:feature_code":"PPL",
    "gn:name":"T\u00e2n Ti\u00ean",
    "gn:population":0,
    "gn:timezone":"Asia/Ho_Chi_Minh",
    "iso:country":"VN",
    "name:vie_x_preferred":[
        "T\u00e2n Ti\u00ean"
    ],
    "wof:name":"Tan Tien",
    "wof:placetype":"locality"
},
  "geometry": {"coordinates":[105.10038,21.57842],"type":"Point"}
}