{
  "type": "Feature",
  "properties": {
    "gn:admin1_code":"39.0",
    "gn:asciiname":"Ban Hau",
    "gn:country_code":"VN",
    "gn:dem":360,
    "gn:feature_class":"P",
    "gn:feature_code":"PPL",
    "gn:name":"B\u1ea3n H\u1eadu",
    "gn:population":0,
    "gn:timezone":"Asia/Ho_Chi_Minh",
    "iso:country":"VN",
    "name:vie_x_preferred":[
        "B\u1ea3n H\u1eadu"
    ],
    "wof:name":"Ban Hau",
    "wof:placetype":"locality"
},
  "geometry": {"coordinates":[106.41961999999999,21.93698],"type":"Point"}
}