{
  "type": "Feature",
  "properties": {
    "gn:admin1_code":"68.0",
    "gn:asciiname":"Lang Ngoang",
    "gn:country_code":"VN",
    "gn:dem":106,
    "gn:feature_class":"P",
    "gn:feature_code":"PPL",
    "gn:name":"L\u00e0ng Ngo\u1eb5ng",
    "gn:population":0,
    "gn:timezone":"Asia/Ho_Chi_Minh",
    "iso:country":"VN",
    "name:vie_x_preferred":[
        "L\u00e0ng Ngo\u1eb5ng"
    ],
    "wof:name":"Lang Ngoang",
    "wof:placetype":"locality"
},
  "geometry": {"coordinates":[105.21124,22.31747],"type":"Point"}
}