{
  "type": "Feature",
  "properties": {
    "gn:admin1_code":"52.0",
    "gn:asciiname":"Vinh Long",
    "gn:country_code":"VN",
    "gn:dem":9,
    "gn:feature_class":"P",
    "gn:feature_code":"PPL",
    "gn:name":"Vinh Long",
    "gn:population":0,
    "gn:timezone":"Asia/Ho_Chi_Minh",
    "iso:country":"VN",
    "name:vie_x_preferred":[
        "Vinh Long"
    ],
    "wof:name":"Vinh Long",
    "wof:placetype":"locality"
},
  "geometry": {"coordinates":[105.77181000000002,18.41069],"type":"Point"}
}