{
  "type": "Feature",
  "properties": {
    "gn:admin1_code":"60.0",
    "gn:asciiname":"Gia Hoa",
    "gn:country_code":"VN",
    "gn:dem":168,
    "gn:feature_class":"P",
    "gn:feature_code":"PPL",
    "gn:name":"Gia Hoa",
    "gn:population":0,
    "gn:timezone":"Asia/Ho_Chi_Minh",
    "iso:country":"VN",
    "name:vie_x_preferred":[
        "Gia Hoa"
    ],
    "wof:name":"Gia Hoa",
    "wof:placetype":"locality"
},
  "geometry": {"coordinates":[108.69723999999999,11.65061],"type":"Point"}
}