{
  "type": "Feature",
  "properties": {
    "gn:admin1_code":"92.0",
    "gn:asciiname":"Chong Su",
    "gn:country_code":"VN",
    "gn:dem":611,
    "gn:feature_class":"P",
    "gn:feature_code":"PPL",
    "gn:name":"Ch\u1ed1ng S\u01b0",
    "gn:population":0,
    "gn:timezone":"Asia/Ho_Chi_Minh",
    "iso:country":"VN",
    "name:vie_x_preferred":[
        "Ch\u1ed1ng S\u01b0"
    ],
    "wof:name":"Chong Su",
    "wof:placetype":"locality"
},
  "geometry": {"coordinates":[103.26448000000001,21.20714],"type":"Point"}
}