{
  "type": "Feature",
  "properties": {
    "gn:admin1_code":"5.0",
    "gn:asciiname":"Quang Dau",
    "gn:country_code":"VN",
    "gn:dem":731,
    "gn:feature_class":"P",
    "gn:feature_code":"PPL",
    "gn:name":"Quang \u0110\u00e2u",
    "gn:population":0,
    "gn:timezone":"Asia/Ho_Chi_Minh",
    "iso:country":"VN",
    "wof:name":"Quang Dau",
    "wof:placetype":"locality"
},
  "geometry": {"coordinates":[106.33333,22.76667],"type":"Point"}
}