{
  "type": "Feature",
  "properties": {
    "gn:admin1_code":"74.0",
    "gn:asciiname":"Dinh Ca",
    "gn:country_code":"VN",
    "gn:dem":11,
    "gn:feature_class":"P",
    "gn:feature_code":"PPL",
    "gn:name":"\u0110\u00ecnh C\u1ea3",
    "gn:population":0,
    "gn:timezone":"Asia/Ho_Chi_Minh",
    "iso:country":"VN",
    "name:vie_x_preferred":[
        "\u0110\u00ecnh C\u1ea3"
    ],
    "wof:name":"Dinh Ca",
    "wof:placetype":"locality"
},
  "geometry": {"coordinates":[106.00337,21.13578],"type":"Point"}
}