{
  "type": "Feature",
  "properties": {
    "gn:admin1_code":"71.0",
    "gn:asciiname":"Xom Mac",
    "gn:country_code":"VN",
    "gn:dem":28,
    "gn:feature_class":"P",
    "gn:feature_code":"PPL",
    "gn:name":"X\u00f3m M\u1ea1c",
    "gn:population":0,
    "gn:timezone":"Asia/Ho_Chi_Minh",
    "iso:country":"VN",
    "name:vie_x_preferred":[
        "X\u00f3m M\u1ea1c"
    ],
    "wof:name":"Xom Mac",
    "wof:placetype":"locality"
},
  "geometry": {"coordinates":[106.11230999999999,21.43917],"type":"Point"}
}