{
  "type": "Feature",
  "properties": {
    "gn:admin1_code":"58.0",
    "gn:asciiname":"Cam Truong",
    "gn:country_code":"VN",
    "gn:dem":7,
    "gn:feature_class":"P",
    "gn:feature_code":"PPL",
    "gn:name":"C\u1ea9m Tr\u01b0\u1eddng",
    "gn:population":0,
    "gn:timezone":"Asia/Ho_Chi_Minh",
    "iso:country":"VN",
    "name:und_x_variant":[
        "C\u1ea7m Tr\u01b0\u1eddng"
    ],
    "name:vie_x_preferred":[
        "C\u1ea9m Tr\u01b0\u1eddng"
    ],
    "wof:name":"Cam Truong",
    "wof:placetype":"locality"
},
  "geometry": {"coordinates":[105.67025,19.13255],"type":"Point"}
}