{
  "type": "Feature",
  "properties": {
    "gn:admin1_code":"45.0",
    "gn:asciiname":"Phuoc Loi",
    "gn:country_code":"VN",
    "gn:dem":10,
    "gn:feature_class":"P",
    "gn:feature_code":"PPL",
    "gn:name":"Ph\u01b0\u1edbc L\u1ee3i",
    "gn:population":0,
    "gn:timezone":"Asia/Ho_Chi_Minh",
    "iso:country":"VN",
    "name:und_x_variant":[
        "X\u00e3 Ph\u01b0\u1edbc L\u1ee3i"
    ],
    "name:vie_x_preferred":[
        "Ph\u01b0\u1edbc L\u1ee3i"
    ],
    "wof:name":"Phuoc Loi",
    "wof:placetype":"locality"
},
  "geometry": {"coordinates":[107.27766,10.46093],"type":"Point"}
}