{
  "type": "Feature",
  "properties": {
    "gn:admin1_code":"5.0",
    "gn:asciiname":"Keo Suong",
    "gn:country_code":"VN",
    "gn:dem":469,
    "gn:feature_class":"P",
    "gn:feature_code":"PPL",
    "gn:name":"K\u00e9o S\u01b0\u1eddng",
    "gn:population":0,
    "gn:timezone":"Asia/Ho_Chi_Minh",
    "iso:country":"VN",
    "wof:name":"Keo Suong",
    "wof:placetype":"locality"
},
  "geometry": {"coordinates":[106.58333,22.61667000000001],"type":"Point"}
}