{
  "type": "Feature",
  "properties": {
    "gn:admin1_code":"53.0",
    "gn:asciiname":"Nhuong Lao",
    "gn:country_code":"VN",
    "gn:dem":14,
    "gn:feature_class":"P",
    "gn:feature_code":"PPL",
    "gn:name":"Nh\u01b0\u1ee3ng L\u00e3o",
    "gn:population":0,
    "gn:timezone":"Asia/Ho_Chi_Minh",
    "iso:country":"VN",
    "wof:name":"Nhuong Lao",
    "wof:placetype":"locality"
},
  "geometry": {"coordinates":[105.73333,20.56667],"type":"Point"}
}