{
  "type": "Feature",
  "properties": {
    "gn:admin1_code":"88.0",
    "gn:asciiname":"Buon Tur",
    "gn:country_code":"VN",
    "gn:dem":458,
    "gn:feature_class":"P",
    "gn:feature_code":"PPL",
    "gn:name":"Bu\u00f4n Tur",
    "gn:population":0,
    "gn:timezone":"Asia/Ho_Chi_Minh",
    "iso:country":"VN",
    "name:und_x_variant":[
        "Bad Tld",
        "Ban Tla",
        "Ban Tlo",
        "Bu\u00f4n Tur"
    ],
    "wof:name":"Buon Tur",
    "wof:placetype":"locality"
},
  "geometry": {"coordinates":[108.01667,12.51667],"type":"Point"}
}