{
  "type": "Feature",
  "properties": {
    "gn:admin1_code":"64.0",
    "gn:asciiname":"Hoan Thanh",
    "gn:country_code":"VN",
    "gn:dem":4,
    "gn:feature_class":"P",
    "gn:feature_code":"PPL",
    "gn:name":"Hoan Thanh",
    "gn:population":0,
    "gn:timezone":"Asia/Ho_Chi_Minh",
    "iso:country":"VN",
    "name:und_x_variant":[
        "Th\u00f4n \u0110\u00f4ng H\u00e0"
    ],
    "wof:name":"Hoan Thanh",
    "wof:placetype":"locality"
},
  "geometry": {"coordinates":[107.13333,16.81667],"type":"Point"}
}