{
  "type": "Feature",
  "properties": {
    "gn:admin1_code":"89.0",
    "gn:asciiname":"Teu Tao Ho",
    "gn:country_code":"VN",
    "gn:dem":600,
    "gn:feature_class":"P",
    "gn:feature_code":"PPL",
    "gn:name":"Teu Tao H\u00f2",
    "gn:population":0,
    "gn:timezone":"Asia/Ho_Chi_Minh",
    "iso:country":"VN",
    "wof:name":"Teu Tao Ho",
    "wof:placetype":"locality"
},
  "geometry": {"coordinates":[103.45,22.46667],"type":"Point"}
}