{
  "type": "Feature",
  "properties": {
    "gn:admin1_code":"89.0",
    "gn:asciiname":"Ban Nan Than",
    "gn:country_code":"VN",
    "gn:dem":528,
    "gn:feature_class":"P",
    "gn:feature_code":"PPL",
    "gn:name":"B\u1ea3n N\u00e1n Than",
    "gn:population":0,
    "gn:timezone":"Asia/Ho_Chi_Minh",
    "iso:country":"VN",
    "name:vie_x_preferred":[
        "B\u1ea3n N\u00e1n Than"
    ],
    "wof:name":"Ban Nan Than",
    "wof:placetype":"locality"
},
  "geometry": {"coordinates":[103.6276,22.0393],"type":"Point"}
}