{
  "type": "Feature",
  "properties": {
    "gn:admin1_code":"90.0",
    "gn:asciiname":"Na Cap",
    "gn:country_code":"VN",
    "gn:dem":739,
    "gn:feature_class":"P",
    "gn:feature_code":"PPL",
    "gn:name":"Na C\u1ea1p",
    "gn:population":0,
    "gn:timezone":"Asia/Ho_Chi_Minh",
    "iso:country":"VN",
    "name:vie_x_preferred":[
        "Na C\u1ea1p"
    ],
    "wof:name":"Na Cap",
    "wof:placetype":"locality"
},
  "geometry": {"coordinates":[104.16151000000001,22.72125],"type":"Point"}
}