{
  "type": "Feature",
  "properties": {
    "gn:admin1_code":"93.0",
    "gn:asciiname":"Ap Mot A",
    "gn:country_code":"VN",
    "gn:dem":3,
    "gn:feature_class":"P",
    "gn:feature_code":"PPL",
    "gn:name":"\u1ea4p M\u1ed9t A",
    "gn:population":0,
    "gn:timezone":"Asia/Ho_Chi_Minh",
    "iso:country":"VN",
    "name:vie_x_preferred":[
        "\u1ea4p M\u1ed9t A"
    ],
    "name:vie_x_variant":[
        "\u1ea4p 1A"
    ],
    "wof:name":"Ap Mot A",
    "wof:placetype":"locality"
},
  "geometry": {"coordinates":[105.42807000000001,9.76197],"type":"Point"}
}