{
  "type": "Feature",
  "properties": {
    "gn:admin1_code":"89.0",
    "gn:asciiname":"Ban Phieng Khon",
    "gn:country_code":"VN",
    "gn:dem":506,
    "gn:feature_class":"P",
    "gn:feature_code":"PPL",
    "gn:name":"B\u1ea3n Phi\u00eang Khon",
    "gn:population":0,
    "gn:timezone":"Asia/Ho_Chi_Minh",
    "iso:country":"VN",
    "name:und_x_variant":[
        "Ping Koum"
    ],
    "name:vie_x_preferred":[
        "B\u1ea3n Phi\u00eang Khon"
    ],
    "wof:name":"Ban Phieng Khon",
    "wof:placetype":"locality"
},
  "geometry": {"coordinates":[103.70497,22.17781],"type":"Point"}
}