{
  "type": "Feature",
  "properties": {
    "gn:admin1_code":"63.0",
    "gn:asciiname":"Mantay",
    "gn:country_code":"VN",
    "gn:dem":114,
    "gn:feature_class":"P",
    "gn:feature_code":"PPL",
    "gn:name":"Mantay",
    "gn:population":0,
    "gn:timezone":"Asia/Ho_Chi_Minh",
    "iso:country":"VN",
    "wof:name":"Mantay",
    "wof:placetype":"locality"
},
  "geometry": {"coordinates":[108.48333,14.91667],"type":"Point"}
}