{
  "type": "Feature",
  "properties": {
    "gn:admin1_code":"32.0",
    "gn:asciiname":"Suoi Chang",
    "gn:country_code":"VN",
    "gn:dem":973,
    "gn:feature_class":"P",
    "gn:feature_code":"PPL",
    "gn:name":"Su\u1ed1i Ch\u1ea1ng",
    "gn:population":0,
    "gn:timezone":"Asia/Ho_Chi_Minh",
    "iso:country":"VN",
    "name:vie_x_preferred":[
        "Su\u1ed1i Ch\u1ea1ng"
    ],
    "wof:name":"Suoi Chang",
    "wof:placetype":"locality"
},
  "geometry": {"coordinates":[104.47190999999999,21.16829],"type":"Point"}
}