{
  "type": "Feature",
  "properties": {
    "gn:admin1_code":"13.0",
    "gn:asciiname":"Ang Duong",
    "gn:country_code":"VN",
    "gn:dem":5,
    "gn:feature_class":"P",
    "gn:feature_code":"PPL",
    "gn:name":"Ang D\u01b0\u01a1ng",
    "gn:population":0,
    "gn:timezone":"Asia/Ho_Chi_Minh",
    "iso:country":"VN",
    "name:deu_x_preferred":[
        "Ang Duong"
    ],
    "name:fra_x_preferred":[
        "Ang Duong"
    ],
    "name:hin_x_preferred":[
        "\u0913\u0902\u0917 \u0926\u0941\u0913\u0902\u0917"
    ],
    "name:ind_x_preferred":[
        "Ang Duong"
    ],
    "name:ita_x_preferred":[
        "Ang Duong"
    ],
    "name:jpn_x_preferred":[
        "\u30a2\u30f3\u30fb\u30c9\u30a5\u30aa\u30f3"
    ],
    "name:khm_x_preferred":[
        "\u17a2\u1784\u17d2\u1782\u178a\u17bd\u1784"
    ],
    "name:msa_x_preferred":[
        "Ang Duong"
    ],
    "name:rus_x_preferred":[
        "\u0410\u043d\u0433 \u0414\u0443\u043e\u043d\u0433"
    ],
    "name:spa_x_preferred":[
        "Ang Duong"
    ],
    "name:swe_x_preferred":[
        "Ang Duong"
    ],
    "name:tha_x_preferred":[
        "\u0e2a\u0e21\u0e40\u0e14\u0e47\u0e08\u0e1e\u0e23\u0e30\u0e2b\u0e23\u0e34\u0e23\u0e31\u0e01\u0e29\u0e4c\u0e23\u0e32\u0e21\u0e21\u0e2b\u0e32\u0e2d\u0e34\u0e28\u0e23\u0e32\u0e18\u0e34\u0e1a\u0e14\u0e35"
    ],
    "name:ukr_x_preferred":[
        "\u0410\u043d\u0433 \u0414\u0443\u043e\u043d\u0433"
    ],
    "name:vie_x_preferred":[
        "Ang Duong"
    ],
    "wof:name":"Ang Duong",
    "wof:placetype":"locality"
},
  "geometry": {"coordinates":[106.46666999999999,20.71667],"type":"Point"}
}