{
  "type": "Feature",
  "properties": {
    "gn:admin1_code":"39.0",
    "gn:asciiname":"Tham Sam",
    "gn:country_code":"VN",
    "gn:dem":220,
    "gn:feature_class":"P",
    "gn:feature_code":"PPL",
    "gn:name":"Th\u00e2m Sam",
    "gn:population":0,
    "gn:timezone":"Asia/Ho_Chi_Minh",
    "iso:country":"VN",
    "wof:name":"Tham Sam",
    "wof:placetype":"locality"
},
  "geometry": {"coordinates":[106.62581000000002,22.04456],"type":"Point"}
}