{
  "type": "Feature",
  "properties": {
    "gn:admin1_code":"55.0",
    "gn:asciiname":"Dak Phai",
    "gn:country_code":"VN",
    "gn:dem":638,
    "gn:feature_class":"P",
    "gn:feature_code":"PPL",
    "gn:name":"\u0110\u1eafk Ph\u00e1i",
    "gn:population":0,
    "gn:timezone":"Asia/Ho_Chi_Minh",
    "iso:country":"VN",
    "name:vie_x_preferred":[
        "\u0110\u1eafk Ph\u00e1i"
    ],
    "wof:name":"Dak Phai",
    "wof:placetype":"locality"
},
  "geometry": {"coordinates":[107.70908,14.84033],"type":"Point"}
}