{
  "type": "Feature",
  "properties": {
    "gn:admin1_code":"14.0",
    "gn:asciiname":"An Dao",
    "gn:country_code":"VN",
    "gn:dem":0,
    "gn:feature_class":"P",
    "gn:feature_code":"PPL",
    "gn:name":"An \u0110\u1ea1o",
    "gn:population":0,
    "gn:timezone":"Asia/Ho_Chi_Minh",
    "iso:country":"VN",
    "name:vie_x_preferred":[
        "An \u0110\u1ea1o"
    ],
    "wof:name":"An Dao",
    "wof:placetype":"locality"
},
  "geometry": {"coordinates":[106.38336,20.33008],"type":"Point"}
}