{
  "type": "Feature",
  "properties": {
    "gn:admin1_code":"39.0",
    "gn:asciiname":"Ban Con Sung",
    "gn:country_code":"VN",
    "gn:dem":375,
    "gn:feature_class":"P",
    "gn:feature_code":"PPL",
    "gn:name":"B\u1ea3n C\u00f2n Sung",
    "gn:population":0,
    "gn:timezone":"Asia/Ho_Chi_Minh",
    "iso:country":"VN",
    "name:und_x_variant":[
        "Khon Sung",
        "Kh\u00f4n Khu",
        "B\u1ea3n C\u00f2n Sung"
    ],
    "wof:name":"Ban Con Sung",
    "wof:placetype":"locality"
},
  "geometry": {"coordinates":[106.66807,22.0654],"type":"Point"}
}