{
  "type": "Feature",
  "properties": {
    "gn:country":"VN",
    "gn:fcode":"PPL",
    "gn:pop":152200,
    "iso:country":"VN",
    "name:ceb_x_preferred":[
        "Huy\u1ec7n C\u1ea7n \u0110\u01b0\u1edbc"
    ],
    "name:eng_x_preferred":[
        "Can Giuoc"
    ],
    "name:eng_x_variant":[
        "C\u1ea7n \u0110\u01b0\u1edbc"
    ],
    "name:unk_x_variant":[
        "C\u1ea7n Giu\u1ed9c"
    ],
    "name:vie_x_preferred":[
        "C\u1ea7n \u0110\u01b0\u1edbc"
    ],
    "name:zho_x_preferred":[
        "\u82b9\u5fb7\u7e23"
    ],
    "qs:name":"C\u1ea7n Du\u1ed9c",
    "qs:photos_9r":0,
    "qs:photos_sr":0,
    "qs:pop_sr":"9",
    "wd:wordcount":554,
    "wof:name":"C\u1ea7n Du\u1ed9c",
    "wof:placetype":"locality",
    "wof:population":152200
},
  "geometry": {"coordinates":[106.66667,10.61667],"type":"Point"}
}