{
  "type": "Feature",
  "properties": {
    "gn:admin1_code":"50.0",
    "gn:asciiname":"Khuon Pa",
    "gn:country_code":"VN",
    "gn:dem":208,
    "gn:feature_class":"P",
    "gn:feature_code":"PPL",
    "gn:name":"Khu\u00f4n P\u00e0",
    "gn:population":0,
    "gn:timezone":"Asia/Ho_Chi_Minh",
    "iso:country":"VN",
    "name:und_x_variant":[
        "Khouan Pha",
        "Kouen Pha",
        "Kouan Pha"
    ],
    "name:vie_x_preferred":[
        "Khu\u00f4n P\u00e0"
    ],
    "wof:name":"Khuon Pa",
    "wof:placetype":"locality"
},
  "geometry": {"coordinates":[105.12195,22.86121],"type":"Point"}
}