{
  "type": "Feature",
  "properties": {
    "gn:admin1_code":"73.0",
    "gn:asciiname":"Ben Bao",
    "gn:country_code":"VN",
    "gn:dem":7,
    "gn:feature_class":"P",
    "gn:feature_code":"PPL",
    "gn:name":"B\u1ebfn B\u00e0o",
    "gn:population":0,
    "gn:timezone":"Asia/Ho_Chi_Minh",
    "iso:country":"VN",
    "name:und_x_variant":[
        "X\u00f3m B\u1ebfn B\u00e0o"
    ],
    "name:vie_x_preferred":[
        "B\u1ebfn B\u00e0o"
    ],
    "wof:name":"Ben Bao",
    "wof:placetype":"locality"
},
  "geometry": {"coordinates":[105.31789000000001,9.60393],"type":"Point"}
}