{
  "type": "Feature",
  "properties": {
    "gn:admin1_code":"58.0",
    "gn:asciiname":"Co Nhau",
    "gn:country_code":"VN",
    "gn:dem":648,
    "gn:feature_class":"P",
    "gn:feature_code":"PPL",
    "gn:name":"C\u1ecf Nhau",
    "gn:population":0,
    "gn:timezone":"Asia/Ho_Chi_Minh",
    "iso:country":"VN",
    "name:vie_x_preferred":[
        "C\u1ecf Nhau"
    ],
    "wof:name":"Co Nhau",
    "wof:placetype":"locality"
},
  "geometry": {"coordinates":[104.68237000000001,19.58387],"type":"Point"}
}