{
  "type": "Feature",
  "properties": {
    "gn:admin1_code":"50.0",
    "gn:asciiname":"Xin Cai",
    "gn:country_code":"VN",
    "gn:dem":1500,
    "gn:feature_class":"P",
    "gn:feature_code":"PPL",
    "gn:name":"Xin Cai",
    "gn:population":0,
    "gn:timezone":"Asia/Ho_Chi_Minh",
    "iso:country":"VN",
    "name:und_x_variant":[
        "Xin Ca",
        "Xin Cai"
    ],
    "wof:name":"Xin Cai",
    "wof:placetype":"locality"
},
  "geometry": {"coordinates":[105.45,23.26667],"type":"Point"}
}