{
  "type": "Feature",
  "properties": {
    "gn:admin1_code":"74.0",
    "gn:asciiname":"Trai Dao",
    "gn:country_code":"VN",
    "gn:dem":5,
    "gn:feature_class":"P",
    "gn:feature_code":"PPL",
    "gn:name":"Tr\u1ea1i \u0110\u00e0o",
    "gn:population":0,
    "gn:timezone":"Asia/Ho_Chi_Minh",
    "iso:country":"VN",
    "name:vie_x_preferred":[
        "Tr\u1ea1i \u0110\u00e0o"
    ],
    "wof:name":"Trai Dao",
    "wof:placetype":"locality"
},
  "geometry": {"coordinates":[106.23663000000001,21.07269],"type":"Point"}
}