{
  "type": "Feature",
  "properties": {
    "gn:admin1_code":"21.0",
    "gn:asciiname":"Tra Tien",
    "gn:cc2":"VN",
    "gn:country_code":"VN",
    "gn:dem":4,
    "gn:feature_class":"P",
    "gn:feature_code":"PPL",
    "gn:name":"Tr\u00e0 Ti\u00ean",
    "gn:population":0,
    "gn:timezone":"Asia/Ho_Chi_Minh",
    "iso:country":"VN",
    "name:und_x_variant":[
        "Ap Tra Tien",
        "Tr\u00e0 Ti\u00ean"
    ],
    "wof:name":"Tra Tien",
    "wof:placetype":"locality"
},
  "geometry": {"coordinates":[104.63333,10.43333],"type":"Point"}
}