{
  "type": "Feature",
  "properties": {
    "gn:admin1_code":"58.0",
    "gn:asciiname":"Khe Gao",
    "gn:country_code":"VN",
    "gn:dem":17,
    "gn:feature_class":"P",
    "gn:feature_code":"PPL",
    "gn:name":"Khe G\u1ea1o",
    "gn:population":0,
    "gn:timezone":"Asia/Ho_Chi_Minh",
    "iso:country":"VN",
    "name:vie_x_preferred":[
        "Khe G\u1ea1o"
    ],
    "wof:name":"Khe Gao",
    "wof:placetype":"locality"
},
  "geometry": {"coordinates":[105.44394,18.98296],"type":"Point"}
}