{
  "type": "Feature",
  "properties": {
    "gn:admin1_code":"32.0",
    "gn:asciiname":"Ban Bon",
    "gn:country_code":"VN",
    "gn:dem":887,
    "gn:feature_class":"P",
    "gn:feature_code":"PPL",
    "gn:name":"B\u1ea3n B\u00f4n",
    "gn:population":0,
    "gn:timezone":"Asia/Ho_Chi_Minh",
    "iso:country":"VN",
    "wof:name":"Ban Bon",
    "wof:placetype":"locality"
},
  "geometry": {"coordinates":[103.76667,21.36667000000001],"type":"Point"}
}