{
  "type": "Feature",
  "properties": {
    "gn:admin1_code":"49.0",
    "gn:asciiname":"Buon Bir",
    "gn:country_code":"VN",
    "gn:dem":181,
    "gn:feature_class":"P",
    "gn:feature_code":"PPL",
    "gn:name":"Bu\u00f4n Bir",
    "gn:population":0,
    "gn:timezone":"Asia/Ho_Chi_Minh",
    "iso:country":"VN",
    "name:vie_x_preferred":[
        "Bu\u00f4n Bir"
    ],
    "wof:name":"Buon Bir",
    "wof:placetype":"locality"
},
  "geometry": {"coordinates":[108.41464000000001,13.3916],"type":"Point"}
}