{
  "type": "Feature",
  "properties": {
    "gn:admin1_code":"45.0",
    "gn:asciiname":"Ap Cho Ben",
    "gn:country_code":"VN",
    "gn:dem":22,
    "gn:feature_class":"P",
    "gn:feature_code":"PPL",
    "gn:name":"\u1ea4p Ch\u00f4 B\u00ean",
    "gn:population":0,
    "gn:timezone":"Asia/Ho_Chi_Minh",
    "iso:country":"VN",
    "name:und_x_variant":[
        "Cho Ben",
        "\u1ea4p Ch\u00f4 B\u00ean"
    ],
    "wof:name":"Ap Cho Ben",
    "wof:placetype":"locality"
},
  "geometry": {"coordinates":[107.21666999999999,10.46667],"type":"Point"}
}