{
  "type": "Feature",
  "properties": {
    "gn:admin1_code":"30.0",
    "gn:asciiname":"Thi Tran Cai Rong",
    "gn:country_code":"VN",
    "gn:dem":15,
    "gn:feature_class":"P",
    "gn:feature_code":"PPL",
    "gn:name":"Th\u1ecb Tr\u1ea5n C\u00e1i R\u1ed3ng",
    "gn:population":0,
    "gn:timezone":"Asia/Ho_Chi_Minh",
    "iso:country":"VN",
    "name:und_x_variant":[
        "C\u00e1i R\u1ed3ng"
    ],
    "name:vie_x_preferred":[
        "Th\u1ecb Tr\u1ea5n C\u00e1i R\u1ed3ng"
    ],
    "wof:name":"Thi Tran Cai Rong",
    "wof:placetype":"locality"
},
  "geometry": {"coordinates":[107.42074,21.07124],"type":"Point"}
}