{
  "type": "Feature",
  "properties": {
    "gn:admin1_code":"58.0",
    "gn:asciiname":"Eo Da",
    "gn:country_code":"VN",
    "gn:dem":33,
    "gn:feature_class":"P",
    "gn:feature_code":"PPL",
    "gn:name":"Eo \u0110\u00e1",
    "gn:population":0,
    "gn:timezone":"Asia/Ho_Chi_Minh",
    "iso:country":"VN",
    "name:vie_x_preferred":[
        "Eo \u0110\u00e1"
    ],
    "wof:name":"Eo Da",
    "wof:placetype":"locality"
},
  "geometry": {"coordinates":[105.63166,19.28788],"type":"Point"}
}