{
  "type": "Feature",
  "properties": {
    "gn:admin1_code":"89.0",
    "gn:asciiname":"Ban Fan Hom",
    "gn:country_code":"VN",
    "gn:dem":743,
    "gn:feature_class":"P",
    "gn:feature_code":"PPL",
    "gn:name":"B\u1ea3n Fan Hom",
    "gn:population":0,
    "gn:timezone":"Asia/Ho_Chi_Minh",
    "iso:country":"VN",
    "wof:name":"Ban Fan Hom",
    "wof:placetype":"locality"
},
  "geometry": {"coordinates":[103.73333,21.88333],"type":"Point"}
}