{
  "type": "Feature",
  "properties": {
    "gn:admin1_code":"52.0",
    "gn:asciiname":"Vinh Thanh",
    "gn:country_code":"VN",
    "gn:dem":10,
    "gn:feature_class":"P",
    "gn:feature_code":"PPL",
    "gn:name":"V\u0129nh Th\u00e0nh",
    "gn:population":0,
    "gn:timezone":"Asia/Ho_Chi_Minh",
    "iso:country":"VN",
    "name:vie_x_preferred":[
        "V\u0129nh Th\u00e0nh"
    ],
    "wof:name":"Vinh Thanh",
    "wof:placetype":"locality"
},
  "geometry": {"coordinates":[105.64744,18.29323],"type":"Point"}
}