{
  "type": "Feature",
  "properties": {
    "gn:admin1_code":"60.0",
    "gn:asciiname":"My Tan",
    "gn:country_code":"VN",
    "gn:dem":5,
    "gn:feature_class":"P",
    "gn:feature_code":"PPL",
    "gn:name":"M\u1ef9 T\u00e2n",
    "gn:population":0,
    "gn:timezone":"Asia/Ho_Chi_Minh",
    "iso:country":"VN",
    "name:vie_x_preferred":[
        "M\u1ef9 T\u00e2n"
    ],
    "wof:name":"My Tan",
    "wof:placetype":"locality"
},
  "geometry": {"coordinates":[109.13042,11.58136],"type":"Point"}
}