{
  "type": "Feature",
  "properties": {
    "gn:admin1_code":"59.0",
    "gn:asciiname":"Xom Dang",
    "gn:country_code":"VN",
    "gn:dem":219,
    "gn:feature_class":"P",
    "gn:feature_code":"PPL",
    "gn:name":"X\u00f3m \u0110ang",
    "gn:population":0,
    "gn:timezone":"Asia/Ho_Chi_Minh",
    "iso:country":"VN",
    "name:vie_x_preferred":[
        "X\u00f3m \u0110ang"
    ],
    "wof:name":"Xom Dang",
    "wof:placetype":"locality"
},
  "geometry": {"coordinates":[105.68546000000001,20.27281],"type":"Point"}
}