{
  "type": "Feature",
  "properties": {
    "gn:admin1_code":"16.0",
    "gn:asciiname":"Duyen Yet",
    "gn:country_code":"VN",
    "gn:dem":5,
    "gn:feature_class":"P",
    "gn:feature_code":"PPL",
    "gn:name":"Duy\u00ean Y\u1ebft",
    "gn:population":0,
    "gn:timezone":"Asia/Ho_Chi_Minh",
    "iso:country":"VN",
    "wof:name":"Duyen Yet",
    "wof:placetype":"locality"
},
  "geometry": {"coordinates":[105.95,20.76667],"type":"Point"}
}