{
  "type": "Feature",
  "properties": {
    "gn:admin1_code":"80.0",
    "gn:asciiname":"Than Nu",
    "gn:country_code":"VN",
    "gn:dem":6,
    "gn:feature_class":"P",
    "gn:feature_code":"PPL",
    "gn:name":"Th\u1ea7n N\u1eef",
    "gn:population":0,
    "gn:timezone":"Asia/Ho_Chi_Minh",
    "iso:country":"VN",
    "name:vie_x_preferred":[
        "Th\u1ea7n N\u1eef"
    ],
    "wof:name":"Than Nu",
    "wof:placetype":"locality"
},
  "geometry": {"coordinates":[105.93031999999999,20.65186],"type":"Point"}
}