{
  "type": "Feature",
  "properties": {
    "gn:admin1_code":"70.0",
    "gn:asciiname":"Doi Tam",
    "gn:country_code":"VN",
    "gn:dem":62,
    "gn:feature_class":"P",
    "gn:feature_code":"PPL",
    "gn:name":"\u0110\u1ed9i T\u00e1m",
    "gn:population":0,
    "gn:timezone":"Asia/Ho_Chi_Minh",
    "iso:country":"VN",
    "name:vie_x_preferred":[
        "\u0110\u1ed9i T\u00e1m"
    ],
    "name:vie_x_variant":[
        "\u0110\u1ed9i 8"
    ],
    "wof:name":"Doi Tam",
    "wof:placetype":"locality"
},
  "geometry": {"coordinates":[104.88890000000001,21.86337],"type":"Point"}
}