{
  "type": "Feature",
  "properties": {
    "gn:admin1_code":"65.0",
    "gn:asciiname":"Ap Vinh Binh",
    "gn:country_code":"VN",
    "gn:dem":2,
    "gn:feature_class":"P",
    "gn:feature_code":"PPL",
    "gn:name":"\u1ea4p V\u0129nh B\u00ecnh",
    "gn:population":0,
    "gn:timezone":"Asia/Ho_Chi_Minh",
    "iso:country":"VN",
    "name:und_x_variant":[
        "V\u0129nh B\u00ecnh",
        "\u1ea4p V\u0129nh B\u00ecnh"
    ],
    "wof:name":"Ap Vinh Binh",
    "wof:placetype":"locality"
},
  "geometry": {"coordinates":[105.64472000000001,9.49889],"type":"Point"}
}