{
  "type": "Feature",
  "properties": {
    "gn:admin1_code":"13.0",
    "gn:asciiname":"Don Luong",
    "gn:country_code":"VN",
    "gn:dem":6,
    "gn:feature_class":"P",
    "gn:feature_code":"PPL",
    "gn:name":"D\u1ed3n L\u01b0\u1ed1ng",
    "gn:population":0,
    "gn:timezone":"Asia/Ho_Chi_Minh",
    "iso:country":"VN",
    "wof:name":"Don Luong",
    "wof:placetype":"locality"
},
  "geometry": {"coordinates":[106.89888999999999,20.80028],"type":"Point"}
}