{
  "type": "Feature",
  "properties": {
    "gn:admin1_code":"67.0",
    "gn:asciiname":"Xoai Lo",
    "gn:country_code":"VN",
    "gn:dem":4,
    "gn:feature_class":"P",
    "gn:feature_code":"PPL",
    "gn:name":"Xo\u00e0i L\u01a1",
    "gn:population":0,
    "gn:timezone":"Asia/Ho_Chi_Minh",
    "iso:country":"VN",
    "name:vie_x_preferred":[
        "Xo\u00e0i L\u01a1"
    ],
    "wof:name":"Xoai Lo",
    "wof:placetype":"locality"
},
  "geometry": {"coordinates":[106.17834999999999,9.69556],"type":"Point"}
}