{
  "type": "Feature",
  "properties": {
    "gn:admin1_code":"91.0",
    "gn:asciiname":"Bon R'kop",
    "gn:country_code":"VN",
    "gn:dem":564,
    "gn:feature_class":"P",
    "gn:feature_code":"PPL",
    "gn:name":"Bon R\u2019kop",
    "gn:population":0,
    "gn:timezone":"Asia/Ho_Chi_Minh",
    "iso:country":"VN",
    "wof:name":"Bon R'kop",
    "wof:placetype":"locality"
},
  "geometry": {"coordinates":[107.76667,12.36667],"type":"Point"}
}