{
  "type": "Feature",
  "properties": {
    "gn:admin1_code":"70.0",
    "gn:asciiname":"Xom Giua",
    "gn:country_code":"VN",
    "gn:dem":32,
    "gn:feature_class":"P",
    "gn:feature_code":"PPL",
    "gn:name":"X\u00f3m Gi\u1eefa",
    "gn:population":0,
    "gn:timezone":"Asia/Ho_Chi_Minh",
    "iso:country":"VN",
    "name:und_x_variant":[
        "Som Giu",
        "X\u00f3m Gi\u1eefa"
    ],
    "wof:name":"Xom Giua",
    "wof:placetype":"locality"
},
  "geometry": {"coordinates":[104.84999999999999,21.71667],"type":"Point"}
}