{
  "type": "Feature",
  "properties": {
    "gn:admin1_code":"5.0",
    "gn:asciiname":"Thua Uc",
    "gn:country_code":"VN",
    "gn:dem":670,
    "gn:feature_class":"P",
    "gn:feature_code":"PPL",
    "gn:name":"Th\u1ee5a \u00dac",
    "gn:population":0,
    "gn:timezone":"Asia/Ho_Chi_Minh",
    "iso:country":"VN",
    "wof:name":"Thua Uc",
    "wof:placetype":"locality"
},
  "geometry": {"coordinates":[106.36667,22.75],"type":"Point"}
}