{
  "type": "Feature",
  "properties": {
    "gn:admin1_code":"55.0",
    "gn:asciiname":"Kon Trang Kla",
    "gn:country_code":"VN",
    "gn:dem":562,
    "gn:feature_class":"P",
    "gn:feature_code":"PPL",
    "gn:name":"Kon Trang Kla",
    "gn:population":0,
    "gn:timezone":"Asia/Ho_Chi_Minh",
    "iso:country":"VN",
    "name:und_x_variant":[
        "Kon Trang Klaa",
        "Kon Trang Kla"
    ],
    "wof:name":"Kon Trang Kla",
    "wof:placetype":"locality"
},
  "geometry": {"coordinates":[107.96666999999999,14.46667],"type":"Point"}
}