{
  "type": "Feature",
  "properties": {
    "gn:admin1_code":"58.0",
    "gn:asciiname":"Tan Son",
    "gn:country_code":"VN",
    "gn:dem":47,
    "gn:feature_class":"P",
    "gn:feature_code":"PPL",
    "gn:name":"T\u00e2n S\u01a1n",
    "gn:population":0,
    "gn:timezone":"Asia/Ho_Chi_Minh",
    "iso:country":"VN",
    "name:vie_x_preferred":[
        "T\u00e2n S\u01a1n"
    ],
    "wof:name":"Tan Son",
    "wof:placetype":"locality"
},
  "geometry": {"coordinates":[105.15564000000001,19.06041],"type":"Point"}
}