{
  "type": "Feature",
  "properties": {
    "gn:admin1_code":"82.0",
    "gn:asciiname":"Bac Cuong",
    "gn:country_code":"VN",
    "gn:dem":3,
    "gn:feature_class":"P",
    "gn:feature_code":"PPL",
    "gn:name":"B\u1eafc C\u01b0\u1eddng",
    "gn:population":0,
    "gn:timezone":"Asia/Ho_Chi_Minh",
    "iso:country":"VN",
    "name:vie_x_preferred":[
        "B\u1eafc C\u01b0\u1eddng"
    ],
    "wof:name":"Bac Cuong",
    "wof:placetype":"locality"
},
  "geometry": {"coordinates":[106.46519000000001,20.23001],"type":"Point"}
}