{
  "type": "Feature",
  "properties": {
    "gn:admin1_code":"92.0",
    "gn:asciiname":"Pu Tiu",
    "gn:country_code":"VN",
    "gn:dem":999,
    "gn:feature_class":"P",
    "gn:feature_code":"PPL",
    "gn:name":"P\u00fa T\u1ec9u",
    "gn:population":0,
    "gn:timezone":"Asia/Ho_Chi_Minh",
    "iso:country":"VN",
    "name:vie_x_preferred":[
        "P\u00fa T\u1ec9u"
    ],
    "wof:name":"Pu Tiu",
    "wof:placetype":"locality"
},
  "geometry": {"coordinates":[103.22589000000001,21.55507],"type":"Point"}
}