{
  "type": "Feature",
  "properties": {
    "gn:admin1_code":"21.0",
    "gn:asciiname":"Thu Muoi",
    "gn:country_code":"VN",
    "gn:dem":5,
    "gn:feature_class":"P",
    "gn:feature_code":"PPL",
    "gn:name":"Th\u1ee9 M\u01b0\u1eddi",
    "gn:population":0,
    "gn:timezone":"Asia/Ho_Chi_Minh",
    "iso:country":"VN",
    "name:und_x_variant":[
        "Xom Thu Mudi",
        "X\u00f3m Th\u1ee9 M\u01b0\u1eddi"
    ],
    "name:vie_x_preferred":[
        "Th\u1ee9 M\u01b0\u1eddi"
    ],
    "wof:name":"Thu Muoi",
    "wof:placetype":"locality"
},
  "geometry": {"coordinates":[104.90124,9.75749],"type":"Point"}
}