{
  "type": "Feature",
  "properties": {
    "gn:admin1_code":"92.0",
    "gn:asciiname":"Tua Thang",
    "gn:country_code":"VN",
    "gn:dem":854,
    "gn:feature_class":"P",
    "gn:feature_code":"PPL",
    "gn:name":"T\u1ee7a Th\u00e0ng",
    "gn:population":0,
    "gn:timezone":"Asia/Ho_Chi_Minh",
    "iso:country":"VN",
    "name:fas_x_preferred":[
        "\u062a\u0648\u0627 \u062a\u0627\u0646\u06af"
    ],
    "name:urd_x_preferred":[
        "\u062a\u0648\u0627 \u062a\u0627\u0646\u06af"
    ],
    "name:vie_x_preferred":[
        "T\u1ee7a Th\u00e0ng"
    ],
    "wof:name":"Tua Thang",
    "wof:placetype":"locality"
},
  "geometry": {"coordinates":[103.441,21.94468],"type":"Point"}
}