{
  "type": "Feature",
  "properties": {
    "gn:admin1_code":"39.0",
    "gn:asciiname":"Po Tung",
    "gn:country_code":"VN",
    "gn:dem":223,
    "gn:feature_class":"P",
    "gn:feature_code":"PPL",
    "gn:name":"Po Tung",
    "gn:population":0,
    "gn:timezone":"Asia/Ho_Chi_Minh",
    "iso:country":"VN",
    "wof:name":"Po Tung",
    "wof:placetype":"locality"
},
  "geometry": {"coordinates":[106.61667,22.21667],"type":"Point"}
}