{
  "type": "Feature",
  "properties": {
    "gn:admin1_code":"83.0",
    "gn:asciiname":"Phuong Vien",
    "gn:country_code":"VN",
    "gn:dem":70,
    "gn:feature_class":"P",
    "gn:feature_code":"PPL",
    "gn:name":"Ph\u01b0\u01a1ng Vi\u00ean",
    "gn:population":0,
    "gn:timezone":"Asia/Ho_Chi_Minh",
    "iso:country":"VN",
    "name:und_x_variant":[
        "Phuong Vieu"
    ],
    "name:vie_x_preferred":[
        "Ph\u01b0\u01a1ng Vi\u00ean"
    ],
    "wof:name":"Phuong Vien",
    "wof:placetype":"locality"
},
  "geometry": {"coordinates":[105.08503,21.59105],"type":"Point"}
}