{
  "type": "Feature",
  "properties": {
    "gn:admin1_code":"83.0",
    "gn:asciiname":"Vinh Thinh",
    "gn:country_code":"VN",
    "gn:dem":26,
    "gn:feature_class":"P",
    "gn:feature_code":"PPL",
    "gn:name":"V\u0129nh Thinh",
    "gn:population":0,
    "gn:timezone":"Asia/Ho_Chi_Minh",
    "iso:country":"VN",
    "name:vie_x_preferred":[
        "V\u0129nh Thinh"
    ],
    "wof:name":"Vinh Thinh",
    "wof:placetype":"locality"
},
  "geometry": {"coordinates":[105.28033000000001,21.37862],"type":"Point"}
}