{
  "type": "Feature",
  "properties": {
    "gn:admin1_code":"87.0",
    "gn:asciiname":"Dong Phuoc",
    "gn:country_code":"VN",
    "gn:dem":4,
    "gn:feature_class":"P",
    "gn:feature_code":"PPL",
    "gn:name":"\u0110\u00f4ng Ph\u01b0\u1edbc",
    "gn:population":0,
    "gn:timezone":"Asia/Ho_Chi_Minh",
    "iso:country":"VN",
    "name:vie_x_preferred":[
        "\u0110\u00f4ng Ph\u01b0\u1edbc"
    ],
    "wof:name":"Dong Phuoc",
    "wof:placetype":"locality"
},
  "geometry": {"coordinates":[105.42965,10.0317],"type":"Point"}
}