{
  "type": "Feature",
  "properties": {
    "gn:admin1_code":"90.0",
    "gn:asciiname":"U Xi Xung",
    "gn:country_code":"VN",
    "gn:dem":731,
    "gn:feature_class":"P",
    "gn:feature_code":"PPL",
    "gn:name":"U X\u0129 Xung",
    "gn:population":0,
    "gn:timezone":"Asia/Ho_Chi_Minh",
    "iso:country":"VN",
    "name:vie_x_preferred":[
        "U X\u0129 Xung"
    ],
    "wof:name":"U Xi Xung",
    "wof:placetype":"locality"
},
  "geometry": {"coordinates":[103.95325,22.36612],"type":"Point"}
}