{
  "type": "Feature",
  "properties": {
    "gn:admin1_code":"2.0",
    "gn:asciiname":"Na Tom",
    "gn:country_code":"VN",
    "gn:dem":193,
    "gn:feature_class":"P",
    "gn:feature_code":"PPL",
    "gn:name":"Na Tom",
    "gn:population":0,
    "gn:timezone":"Asia/Ho_Chi_Minh",
    "iso:country":"VN",
    "wof:name":"Na Tom",
    "wof:placetype":"locality"
},
  "geometry": {"coordinates":[105.76667,22.41667],"type":"Point"}
}