{
  "type": "Feature",
  "properties": {
    "gn:admin1_code":"24.0",
    "gn:asciiname":"Cai Sach",
    "gn:country_code":"VN",
    "gn:dem":2,
    "gn:feature_class":"P",
    "gn:feature_code":"PPL",
    "gn:name":"C\u00e1i S\u00e1ch",
    "gn:population":0,
    "gn:timezone":"Asia/Ho_Chi_Minh",
    "iso:country":"VN",
    "name:und_x_variant":[
        "\u1ea4p C\u00e1i S\u00e1ch"
    ],
    "name:vie_x_preferred":[
        "C\u00e1i S\u00e1ch"
    ],
    "wof:name":"Cai Sach",
    "wof:placetype":"locality"
},
  "geometry": {"coordinates":[105.76967,10.80045],"type":"Point"}
}