{
  "type": "Feature",
  "properties": {
    "gn:admin1_code":"58.0",
    "gn:asciiname":"Thon Gam",
    "gn:country_code":"VN",
    "gn:dem":16,
    "gn:feature_class":"P",
    "gn:feature_code":"PPL",
    "gn:name":"Th\u00f4n G\u00e1m",
    "gn:population":0,
    "gn:timezone":"Asia/Ho_Chi_Minh",
    "iso:country":"VN",
    "name:vie_x_preferred":[
        "Th\u00f4n G\u00e1m"
    ],
    "wof:name":"Thon Gam",
    "wof:placetype":"locality"
},
  "geometry": {"coordinates":[105.44856,18.99617000000001],"type":"Point"}
}