{
  "type": "Feature",
  "properties": {
    "gn:admin1_code":"90.0",
    "gn:asciiname":"Lao Chai Sang Mot",
    "gn:country_code":"VN",
    "gn:dem":1206,
    "gn:feature_class":"P",
    "gn:feature_code":"PPL",
    "gn:name":"Lao Ch\u1ea3i Sang M\u1ed9t",
    "gn:population":0,
    "gn:timezone":"Asia/Ho_Chi_Minh",
    "iso:country":"VN",
    "name:vie_x_preferred":[
        "Lao Ch\u1ea3i Sang M\u1ed9t"
    ],
    "name:vie_x_variant":[
        "Lao Ch\u1ea3i Sang 1"
    ],
    "wof:name":"Lao Chai Sang Mot",
    "wof:placetype":"locality"
},
  "geometry": {"coordinates":[103.85554999999999,22.30297],"type":"Point"}
}