{
  "type": "Feature",
  "properties": {
    "gn:admin1_code":"83.0",
    "gn:asciiname":"Suoi Sin",
    "gn:country_code":"VN",
    "gn:dem":188,
    "gn:feature_class":"P",
    "gn:feature_code":"PPL",
    "gn:name":"Su\u1ed1i Sin",
    "gn:population":0,
    "gn:timezone":"Asia/Ho_Chi_Minh",
    "iso:country":"VN",
    "wof:name":"Suoi Sin",
    "wof:placetype":"locality"
},
  "geometry": {"coordinates":[105.16667,21.01667],"type":"Point"}
}