{
  "type": "Feature",
  "properties": {
    "gn:admin1_code":"70.0",
    "gn:asciiname":"Xom Trai",
    "gn:country_code":"VN",
    "gn:dem":51,
    "gn:feature_class":"P",
    "gn:feature_code":"PPL",
    "gn:name":"X\u00f3m Tr\u1ea1i",
    "gn:population":0,
    "gn:timezone":"Asia/Ho_Chi_Minh",
    "iso:country":"VN",
    "name:vie_x_preferred":[
        "X\u00f3m Tr\u1ea1i"
    ],
    "wof:name":"Xom Trai",
    "wof:placetype":"locality"
},
  "geometry": {"coordinates":[104.6896,21.8725],"type":"Point"}
}