{
  "type": "Feature",
  "properties": {
    "gn:admin1_code":"90.0",
    "gn:asciiname":"Phin Ho",
    "gn:country_code":"VN",
    "gn:dem":1302,
    "gn:feature_class":"P",
    "gn:feature_code":"PPL",
    "gn:name":"Ph\u00ecn H\u1ed3",
    "gn:population":0,
    "gn:timezone":"Asia/Ho_Chi_Minh",
    "iso:country":"VN",
    "name:und_x_variant":[
        "Ph\u00ecn H\u1ed3"
    ],
    "wof:name":"Phin Ho",
    "wof:placetype":"locality"
},
  "geometry": {"coordinates":[103.80410000000001,22.40909],"type":"Point"}
}