{
  "type": "Feature",
  "properties": {
    "gn:admin1_code":"62.0",
    "gn:asciiname":"Y Leng",
    "gn:country_code":"VN",
    "gn:dem":141,
    "gn:feature_class":"P",
    "gn:feature_code":"PPL",
    "gn:name":"Y Leng",
    "gn:population":0,
    "gn:timezone":"Asia/Ho_Chi_Minh",
    "iso:country":"VN",
    "name:und_x_variant":[
        "X\u00f3m Y L\u00e0nh"
    ],
    "name:vie_x_preferred":[
        "Y Leng"
    ],
    "wof:name":"Y Leng",
    "wof:placetype":"locality"
},
  "geometry": {"coordinates":[105.78234999999999,17.79342],"type":"Point"}
}