{
  "type": "Feature",
  "properties": {
    "gn:admin1_code":"50.0",
    "gn:asciiname":"Ban Bac Le",
    "gn:country_code":"VN",
    "gn:dem":345,
    "gn:feature_class":"P",
    "gn:feature_code":"PPL",
    "gn:name":"B\u1ea3n B\u1eafc L\u1ebd",
    "gn:population":0,
    "gn:timezone":"Asia/Ho_Chi_Minh",
    "iso:country":"VN",
    "name:vie_x_preferred":[
        "B\u1ea3n B\u1eafc L\u1ebd"
    ],
    "wof:name":"Ban Bac Le",
    "wof:placetype":"locality"
},
  "geometry": {"coordinates":[105.45711,22.63576],"type":"Point"}
}