{
  "type": "Feature",
  "properties": {
    "gn:admin1_code":"32.0",
    "gn:asciiname":"Ban Giang",
    "gn:country_code":"VN",
    "gn:dem":417,
    "gn:feature_class":"P",
    "gn:feature_code":"PPL",
    "gn:name":"B\u1ea3n Gi\u00e0ng",
    "gn:population":0,
    "gn:timezone":"Asia/Ho_Chi_Minh",
    "iso:country":"VN",
    "name:und_x_variant":[
        "Muong Giang",
        "B\u1ea3n Giang"
    ],
    "name:vie_x_preferred":[
        "B\u1ea3n Gi\u00e0ng"
    ],
    "wof:name":"Ban Giang",
    "wof:placetype":"locality"
},
  "geometry": {"coordinates":[103.59166,21.65809],"type":"Point"}
}