{
  "type": "Feature",
  "properties": {
    "gn:admin1_code":"32.0",
    "gn:asciiname":"Ban Tin Toc Nua",
    "gn:country_code":"VN",
    "gn:dem":859,
    "gn:feature_class":"P",
    "gn:feature_code":"PPL",
    "gn:name":"B\u1ea3n Tin T\u1ed1c N\u01b0a",
    "gn:population":0,
    "gn:timezone":"Asia/Ho_Chi_Minh",
    "iso:country":"VN",
    "name:vie_x_preferred":[
        "B\u1ea3n Tin T\u1ed1c N\u01b0a"
    ],
    "wof:name":"Ban Tin Toc Nua",
    "wof:placetype":"locality"
},
  "geometry": {"coordinates":[103.54689,21.53825],"type":"Point"}
}