{
  "type": "Feature",
  "properties": {
    "gn:admin1_code":"49.0",
    "gn:asciiname":"Plei Ngoi Yo",
    "gn:country_code":"VN",
    "gn:dem":624,
    "gn:feature_class":"P",
    "gn:feature_code":"PPL",
    "gn:name":"Plei Ngoi Y\u1ed5",
    "gn:population":0,
    "gn:timezone":"Asia/Ho_Chi_Minh",
    "iso:country":"VN",
    "name:vie_x_preferred":[
        "Plei Ngoi Y\u1ed5"
    ],
    "wof:name":"Plei Ngoi Yo",
    "wof:placetype":"locality"
},
  "geometry": {"coordinates":[107.87260000000001,14.04712],"type":"Point"}
}