{
  "type": "Feature",
  "properties": {
    "gn:admin1_code":"53.0",
    "gn:asciiname":"Dam Hong",
    "gn:country_code":"VN",
    "gn:dem":122,
    "gn:feature_class":"P",
    "gn:feature_code":"PPL",
    "gn:name":"D\u00e2m H\u00f4ng",
    "gn:population":0,
    "gn:timezone":"Asia/Ho_Chi_Minh",
    "iso:country":"VN",
    "wof:name":"Dam Hong",
    "wof:placetype":"locality"
},
  "geometry": {"coordinates":[105.58333,20.43333],"type":"Point"}
}