{
  "type": "Feature",
  "properties": {
    "gn:admin1_code":"49.0",
    "gn:asciiname":"Buon Chu Bah",
    "gn:country_code":"VN",
    "gn:dem":183,
    "gn:feature_class":"P",
    "gn:feature_code":"PPL",
    "gn:name":"Bu\u00f4n Ch\u01b0 Bah",
    "gn:population":0,
    "gn:timezone":"Asia/Ho_Chi_Minh",
    "iso:country":"VN",
    "name:vie_x_preferred":[
        "Bu\u00f4n Ch\u01b0 Bah"
    ],
    "wof:name":"Buon Chu Bah",
    "wof:placetype":"locality"
},
  "geometry": {"coordinates":[108.41513999999999,13.38518],"type":"Point"}
}