{
  "type": "Feature",
  "properties": {
    "gn:admin1_code":"76.0",
    "gn:asciiname":"Bu Lon",
    "gn:country_code":"VN",
    "gn:dem":330,
    "gn:feature_class":"P",
    "gn:feature_code":"PPL",
    "gn:name":"Bu Lon",
    "gn:population":0,
    "gn:timezone":"Asia/Ho_Chi_Minh",
    "iso:country":"VN",
    "name:vie_x_preferred":[
        "Bu Lon"
    ],
    "wof:name":"Bu Lon",
    "wof:placetype":"locality"
},
  "geometry": {"coordinates":[107.27956,11.79674],"type":"Point"}
}