{
  "type": "Feature",
  "properties": {
    "gn:admin1_code":"88.0",
    "gn:asciiname":"Ea Knop",
    "gn:country_code":"VN",
    "gn:dem":464,
    "gn:feature_class":"P",
    "gn:feature_code":"PPL",
    "gn:name":"Ea Kn\u1ed1p",
    "gn:population":0,
    "gn:timezone":"Asia/Ho_Chi_Minh",
    "iso:country":"VN",
    "wof:name":"Ea Knop",
    "wof:placetype":"locality"
},
  "geometry": {"coordinates":[108.53964000000001,12.80473],"type":"Point"}
}