{
  "type": "Feature",
  "properties": {
    "gn:admin1_code":"32.0",
    "gn:asciiname":"Ban Phieng Xim",
    "gn:country_code":"VN",
    "gn:dem":367,
    "gn:feature_class":"P",
    "gn:feature_code":"PPL",
    "gn:name":"B\u1ea3n Phi\u00eang Xim",
    "gn:population":0,
    "gn:timezone":"Asia/Ho_Chi_Minh",
    "iso:country":"VN",
    "name:vie_x_preferred":[
        "B\u1ea3n Phi\u00eang Xim"
    ],
    "wof:name":"Ban Phieng Xim",
    "wof:placetype":"locality"
},
  "geometry": {"coordinates":[103.80526999999999,21.02242],"type":"Point"}
}