{
  "type": "Feature",
  "properties": {
    "gn:admin1_code":"49.0",
    "gn:asciiname":"Lang Hup",
    "gn:country_code":"VN",
    "gn:dem":402,
    "gn:feature_class":"P",
    "gn:feature_code":"PPL",
    "gn:name":"L\u00e0ng H\u00fap",
    "gn:population":0,
    "gn:timezone":"Asia/Ho_Chi_Minh",
    "iso:country":"VN",
    "name:und_x_variant":[
        "Plei Hup"
    ],
    "name:vie_x_preferred":[
        "L\u00e0ng H\u00fap"
    ],
    "wof:name":"Lang Hup",
    "wof:placetype":"locality"
},
  "geometry": {"coordinates":[108.54443999999999,13.89915],"type":"Point"}
}