{
  "type": "Feature",
  "properties": {
    "gn:admin1_code":"76.0",
    "gn:asciiname":"Bu Ceman",
    "gn:country_code":"VN",
    "gn:dem":126,
    "gn:feature_class":"P",
    "gn:feature_code":"PPL",
    "gn:name":"Bu C\u00eaman",
    "gn:population":0,
    "gn:timezone":"Asia/Ho_Chi_Minh",
    "iso:country":"VN",
    "wof:name":"Bu Ceman",
    "wof:placetype":"locality"
},
  "geometry": {"coordinates":[106.84999999999999,12.06667],"type":"Point"}
}