{
  "type": "Feature",
  "properties": {
    "gn:admin1_code":"32.0",
    "gn:asciiname":"Ban Lung Khieu A",
    "gn:country_code":"VN",
    "gn:dem":656,
    "gn:feature_class":"P",
    "gn:feature_code":"PPL",
    "gn:name":"B\u1ea3n L\u0169ng Khi\u00eau A",
    "gn:population":0,
    "gn:timezone":"Asia/Ho_Chi_Minh",
    "iso:country":"VN",
    "name:vie_x_preferred":[
        "B\u1ea3n L\u0169ng Khi\u00eau A"
    ],
    "wof:name":"Ban Lung Khieu A",
    "wof:placetype":"locality"
},
  "geometry": {"coordinates":[103.56683,21.66415],"type":"Point"}
}