{
  "type": "Feature",
  "properties": {
    "gn:admin1_code":"1.0",
    "gn:asciiname":"Phu Hung",
    "gn:country_code":"VN",
    "gn:dem":6,
    "gn:feature_class":"P",
    "gn:feature_code":"PPL",
    "gn:name":"Ph\u00fa H\u01b0ng",
    "gn:population":0,
    "gn:timezone":"Asia/Ho_Chi_Minh",
    "iso:country":"VN",
    "name:und_x_variant":[
        "\u1ea4p Ph\u00fa H\u01b0ng"
    ],
    "name:vie_x_preferred":[
        "Ph\u00fa H\u01b0ng"
    ],
    "wof:name":"Phu Hung",
    "wof:placetype":"locality"
},
  "geometry": {"coordinates":[105.19114,10.75611],"type":"Point"}
}