{
  "type": "Feature",
  "properties": {
    "gn:admin1_code":"75.0",
    "gn:asciiname":"Tan Phuoc Khanh",
    "gn:country_code":"VN",
    "gn:dem":22,
    "gn:feature_class":"P",
    "gn:feature_code":"PPL",
    "gn:name":"T\u00e2n Ph\u01b0\u1edbc Kh\u00e1nh",
    "gn:population":0,
    "gn:timezone":"Asia/Ho_Chi_Minh",
    "iso:country":"VN",
    "name:und_x_variant":[
        "Tan Khanh",
        "T\u00e2n Ph\u01b0\u1edbc Kh\u00e1nh"
    ],
    "wof:name":"Tan Phuoc Khanh",
    "wof:placetype":"locality"
},
  "geometry": {"coordinates":[106.72046,11.00558],"type":"Point"}
}