{
  "type": "Feature",
  "properties": {
    "gn:admin1_code":"65.0",
    "gn:asciiname":"Xom Song Chat",
    "gn:cc2":"VN",
    "gn:country_code":"VN",
    "gn:dem":3,
    "gn:feature_class":"P",
    "gn:feature_code":"PPL",
    "gn:name":"X\u00f3m Song Ch\u00e1t",
    "gn:population":0,
    "gn:timezone":"Asia/Ho_Chi_Minh",
    "iso:country":"VN",
    "name:und_x_variant":[
        "Song Ch\u00e1t",
        "X\u00f3m Song Ch\u00e1t"
    ],
    "wof:name":"Xom Song Chat",
    "wof:placetype":"locality"
},
  "geometry": {"coordinates":[106.02278,9.63972],"type":"Point"}
}