{
  "type": "Feature",
  "properties": {
    "gn:admin1_code":"58.0",
    "gn:asciiname":"Qua Cu Hai",
    "gn:country_code":"VN",
    "gn:dem":30,
    "gn:feature_class":"P",
    "gn:feature_code":"PPL",
    "gn:name":"Qu\u00e1 C\u01b0 Hai",
    "gn:population":0,
    "gn:timezone":"Asia/Ho_Chi_Minh",
    "iso:country":"VN",
    "name:vie_x_preferred":[
        "Qu\u00e1 C\u01b0 Hai"
    ],
    "name:vie_x_variant":[
        "Qu\u00e1 C\u01b0 2"
    ],
    "wof:name":"Qua Cu Hai",
    "wof:placetype":"locality"
},
  "geometry": {"coordinates":[105.38948000000001,18.91573],"type":"Point"}
}