{
  "type": "Feature",
  "properties": {
    "gn:admin1_code":"32.0",
    "gn:asciiname":"Ban Lut",
    "gn:country_code":"VN",
    "gn:dem":247,
    "gn:feature_class":"P",
    "gn:feature_code":"PPL",
    "gn:name":"B\u1ea3n L\u00fat",
    "gn:population":0,
    "gn:timezone":"Asia/Ho_Chi_Minh",
    "iso:country":"VN",
    "name:vie_x_preferred":[
        "B\u1ea3n L\u00fat"
    ],
    "wof:name":"Ban Lut",
    "wof:placetype":"locality"
},
  "geometry": {"coordinates":[103.70843000000001,21.5725],"type":"Point"}
}