{
  "type": "Feature",
  "properties": {
    "gn:admin1_code":"88.0",
    "gn:asciiname":"Buon Bung",
    "gn:country_code":"VN",
    "gn:dem":554,
    "gn:feature_class":"P",
    "gn:feature_code":"PPL",
    "gn:name":"Bu\u00f4n Bung",
    "gn:population":0,
    "gn:timezone":"Asia/Ho_Chi_Minh",
    "iso:country":"VN",
    "name:vie_x_preferred":[
        "Bu\u00f4n Bung"
    ],
    "wof:name":"Buon Bung",
    "wof:placetype":"locality"
},
  "geometry": {"coordinates":[108.28779,13.28221],"type":"Point"}
}