{
  "type": "Feature",
  "properties": {
    "gn:admin1_code":"84.0",
    "gn:asciiname":"Giao Young",
    "gn:country_code":"VN",
    "gn:dem":414,
    "gn:feature_class":"P",
    "gn:feature_code":"PPL",
    "gn:name":"Gia\u00f4 Young",
    "gn:population":0,
    "gn:timezone":"Asia/Ho_Chi_Minh",
    "iso:country":"VN",
    "wof:name":"Giao Young",
    "wof:placetype":"locality"
},
  "geometry": {"coordinates":[107.68333,15.78333],"type":"Point"}
}