{
  "type": "Feature",
  "properties": {
    "gn:admin1_code":"30.0",
    "gn:asciiname":"Quynh Lau",
    "gn:cc2":"VN",
    "gn:country_code":"VN",
    "gn:dem":14,
    "gn:feature_class":"P",
    "gn:feature_code":"PPL",
    "gn:name":"Qu\u1ef3nh L\u00e2u",
    "gn:population":0,
    "gn:timezone":"Asia/Ho_Chi_Minh",
    "iso:country":"VN",
    "name:und_x_variant":[
        "Quinh Lau",
        "Qu\u1ef3nh L\u00e2u"
    ],
    "wof:name":"Quynh Lau",
    "wof:placetype":"locality"
},
  "geometry": {"coordinates":[106.83333,20.95],"type":"Point"}
}