{
  "type": "Feature",
  "properties": {
    "gn:admin1_code":"20.0",
    "gn:asciiname":"Vinh Loc",
    "gn:cc2":"VN",
    "gn:country_code":"VN",
    "gn:dem":2,
    "gn:feature_class":"P",
    "gn:feature_code":"PPL",
    "gn:name":"V\u0129nh L\u1ed9c",
    "gn:population":0,
    "gn:timezone":"Asia/Ho_Chi_Minh",
    "iso:country":"VN",
    "name:und_x_variant":[
        "Vinh Loc Thon",
        "V\u0129nh L\u1ed9c"
    ],
    "wof:name":"Vinh Loc",
    "wof:placetype":"locality"
},
  "geometry": {"coordinates":[106.56667,10.81667],"type":"Point"}
}