{
  "type": "Feature",
  "properties": {
    "gn:admin1_code":"70.0",
    "gn:asciiname":"Nam Kip",
    "gn:country_code":"VN",
    "gn:dem":396,
    "gn:feature_class":"P",
    "gn:feature_code":"PPL",
    "gn:name":"N\u1eadm K\u00edp",
    "gn:population":0,
    "gn:timezone":"Asia/Ho_Chi_Minh",
    "iso:country":"VN",
    "name:und_x_variant":[
        "Nam Kie",
        "N\u00e2m Ki\u1ec7t"
    ],
    "name:vie_x_preferred":[
        "N\u1eadm K\u00edp"
    ],
    "wof:name":"Nam Kip",
    "wof:placetype":"locality"
},
  "geometry": {"coordinates":[104.44311999999999,21.69803],"type":"Point"}
}