{
  "type": "Feature",
  "properties": {
    "gn:admin1_code":"72.0",
    "gn:asciiname":"Ban Siang",
    "gn:country_code":"VN",
    "gn:dem":296,
    "gn:feature_class":"P",
    "gn:feature_code":"PPL",
    "gn:name":"B\u1ea3n Siang",
    "gn:population":0,
    "gn:timezone":"Asia/Ho_Chi_Minh",
    "iso:country":"VN",
    "name:und_x_variant":[
        "Ban Giang",
        "B\u1ea3n Siang"
    ],
    "wof:name":"Ban Siang",
    "wof:placetype":"locality"
},
  "geometry": {"coordinates":[106.08333,22.26667],"type":"Point"}
}