{
  "type": "Feature",
  "properties": {
    "gn:admin1_code":"50.0",
    "gn:asciiname":"Lang Khen",
    "gn:country_code":"VN",
    "gn:dem":111,
    "gn:feature_class":"P",
    "gn:feature_code":"PPL",
    "gn:name":"L\u00e0ng Kh\u1ebbn",
    "gn:population":0,
    "gn:timezone":"Asia/Ho_Chi_Minh",
    "iso:country":"VN",
    "name:vie_x_preferred":[
        "L\u00e0ng Kh\u1ebbn"
    ],
    "wof:name":"Lang Khen",
    "wof:placetype":"locality"
},
  "geometry": {"coordinates":[104.96641,22.69369],"type":"Point"}
}