{
  "type": "Feature",
  "properties": {
    "gn:admin1_code":"90.0",
    "gn:asciiname":"Minh Luong",
    "gn:country_code":"VN",
    "gn:dem":622,
    "gn:feature_class":"P",
    "gn:feature_code":"PPL",
    "gn:name":"Minh L\u01b0\u01a1ng",
    "gn:population":0,
    "gn:timezone":"Asia/Ho_Chi_Minh",
    "iso:country":"VN",
    "name:und_x_variant":[
        "M\u01b0\u1eddng Khaa",
        "Minh L\u01b0\u01a1ng"
    ],
    "wof:name":"Minh Luong",
    "wof:placetype":"locality"
},
  "geometry": {"coordinates":[104.03333000000001,22.01667],"type":"Point"}
}