{
  "type": "Feature",
  "properties": {
    "gn:admin1_code":"32.0",
    "gn:asciiname":"Ban Gioi",
    "gn:country_code":"VN",
    "gn:dem":735,
    "gn:feature_class":"P",
    "gn:feature_code":"PPL",
    "gn:name":"B\u1ea3n Gi\u1ed5i",
    "gn:population":0,
    "gn:timezone":"Asia/Ho_Chi_Minh",
    "iso:country":"VN",
    "wof:name":"Ban Gioi",
    "wof:placetype":"locality"
},
  "geometry": {"coordinates":[104.63333,20.95],"type":"Point"}
}