{
  "type": "Feature",
  "properties": {
    "gn:admin1_code":"58.0",
    "gn:asciiname":"Tri Thuy",
    "gn:country_code":"VN",
    "gn:dem":4,
    "gn:feature_class":"P",
    "gn:feature_code":"PPL",
    "gn:name":"Tr\u1ecb Th\u1ee7y",
    "gn:population":0,
    "gn:timezone":"Asia/Ho_Chi_Minh",
    "iso:country":"VN",
    "name:und_x_variant":[
        "Iri Thuy",
        "Tr\u1ecb Th\u1ee7y"
    ],
    "wof:name":"Tri Thuy",
    "wof:placetype":"locality"
},
  "geometry": {"coordinates":[105.68333,18.85],"type":"Point"}
}