{
  "type": "Feature",
  "properties": {
    "gn:admin1_code":"21.0",
    "gn:asciiname":"Xom Ngoc Hoa",
    "gn:country_code":"VN",
    "gn:dem":-3,
    "gn:feature_class":"P",
    "gn:feature_code":"PPL",
    "gn:name":"X\u00f3m Ng\u1ecdc H\u00f2a",
    "gn:population":0,
    "gn:timezone":"Asia/Ho_Chi_Minh",
    "iso:country":"VN",
    "wof:name":"Xom Ngoc Hoa",
    "wof:placetype":"locality"
},
  "geometry": {"coordinates":[105.41472,9.93028],"type":"Point"}
}