{
  "type": "Feature",
  "properties": {
    "gn:admin1_code":"23.0",
    "gn:asciiname":"Pho Lang Bah",
    "gn:cc2":"VN",
    "gn:country_code":"VN",
    "gn:dem":386,
    "gn:feature_class":"P",
    "gn:feature_code":"PPL",
    "gn:name":"Pho Lang Bah",
    "gn:population":0,
    "gn:timezone":"Asia/Ho_Chi_Minh",
    "iso:country":"VN",
    "name:und_x_variant":[
        "Plei Lang Bah",
        "Pho Lang Ban",
        "Pho Lang Bah"
    ],
    "wof:name":"Pho Lang Bah",
    "wof:placetype":"locality"
},
  "geometry": {"coordinates":[108.63333,11.73333],"type":"Point"}
}