{
  "type": "Feature",
  "properties": {
    "gn:admin1_code":"58.0",
    "gn:asciiname":"Yen Thang",
    "gn:country_code":"VN",
    "gn:dem":7,
    "gn:feature_class":"P",
    "gn:feature_code":"PPL",
    "gn:name":"Y\u00ean Th\u1eafng",
    "gn:population":0,
    "gn:timezone":"Asia/Ho_Chi_Minh",
    "iso:country":"VN",
    "name:vie_x_preferred":[
        "Y\u00ean Th\u1eafng"
    ],
    "wof:name":"Yen Thang",
    "wof:placetype":"locality"
},
  "geometry": {"coordinates":[105.59881,19.0996],"type":"Point"}
}