{
  "type": "Feature",
  "properties": {
    "gn:admin1_code":"49.0",
    "gn:asciiname":"An Thuong Bon",
    "gn:country_code":"VN",
    "gn:dem":435,
    "gn:feature_class":"P",
    "gn:feature_code":"PPL",
    "gn:name":"An Th\u01b0\u1ee3ng B\u1ed1n",
    "gn:population":0,
    "gn:timezone":"Asia/Ho_Chi_Minh",
    "iso:country":"VN",
    "name:vie_x_preferred":[
        "An Th\u01b0\u1ee3ng B\u1ed1n"
    ],
    "name:vie_x_variant":[
        "An Th\u01b0\u1ee3ng 4"
    ],
    "wof:name":"An Thuong Bon",
    "wof:placetype":"locality"
},
  "geometry": {"coordinates":[108.70578,13.97683],"type":"Point"}
}