{
  "type": "Feature",
  "properties": {
    "gn:admin1_code":"83.0",
    "gn:asciiname":"Doan Ket",
    "gn:country_code":"VN",
    "gn:dem":31,
    "gn:feature_class":"P",
    "gn:feature_code":"PPL",
    "gn:name":"\u0110o\u00e0n K\u1ebft",
    "gn:population":0,
    "gn:timezone":"Asia/Ho_Chi_Minh",
    "iso:country":"VN",
    "name:vie_x_preferred":[
        "\u0110o\u00e0n K\u1ebft"
    ],
    "wof:name":"Doan Ket",
    "wof:placetype":"locality"
},
  "geometry": {"coordinates":[105.08174,21.43629],"type":"Point"}
}