{
  "type": "Feature",
  "properties": {
    "gn:admin1_code":"70.0",
    "gn:asciiname":"Lang Than Mot",
    "gn:country_code":"VN",
    "gn:dem":158,
    "gn:feature_class":"P",
    "gn:feature_code":"PPL",
    "gn:name":"L\u00e0ng Than M\u1ed9t",
    "gn:population":0,
    "gn:timezone":"Asia/Ho_Chi_Minh",
    "iso:country":"VN",
    "name:und_x_variant":[
        "L\u00e0ng Than"
    ],
    "name:vie_x_preferred":[
        "L\u00e0ng Than M\u1ed9t"
    ],
    "name:vie_x_variant":[
        "L\u00e0ng Than 1"
    ],
    "wof:name":"Lang Than Mot",
    "wof:placetype":"locality"
},
  "geometry": {"coordinates":[104.43925,21.88257],"type":"Point"}
}