{
  "type": "Feature",
  "properties": {
    "gn:admin1_code":"92.0",
    "gn:asciiname":"Ban Sam Giong",
    "gn:country_code":"VN",
    "gn:dem":939,
    "gn:feature_class":"P",
    "gn:feature_code":"PPL",
    "gn:name":"B\u1ea3n Sam Giong",
    "gn:population":0,
    "gn:timezone":"Asia/Ho_Chi_Minh",
    "iso:country":"VN",
    "wof:name":"Ban Sam Giong",
    "wof:placetype":"locality"
},
  "geometry": {"coordinates":[103.25,21.41667],"type":"Point"}
}