{
  "type": "Feature",
  "properties": {
    "gn:admin1_code":"50.0",
    "gn:asciiname":"Sang Pa",
    "gn:country_code":"VN",
    "gn:dem":697,
    "gn:feature_class":"P",
    "gn:feature_code":"PPL",
    "gn:name":"S\u00e1ng P\u00e1",
    "gn:population":0,
    "gn:timezone":"Asia/Ho_Chi_Minh",
    "iso:country":"VN",
    "name:vie_x_preferred":[
        "S\u1ea3ng P\u1ea3"
    ],
    "name:vie_x_variant":[
        "S\u00e1ng P\u00e1"
    ],
    "wof:name":"Sang Pa",
    "wof:placetype":"locality"
},
  "geometry": {"coordinates":[105.16083,22.97413],"type":"Point"}
}