{
  "type": "Feature",
  "properties": {
    "gn:admin1_code":"34.0",
    "gn:asciiname":"Bong Thuong",
    "gn:country_code":"VN",
    "gn:dem":7,
    "gn:feature_class":"P",
    "gn:feature_code":"PPL",
    "gn:name":"B\u1ed3ng Th\u01b0\u1ee3ng",
    "gn:population":0,
    "gn:timezone":"Asia/Ho_Chi_Minh",
    "iso:country":"VN",
    "name:vie_x_preferred":[
        "B\u1ed3ng Th\u01b0\u1ee3ng"
    ],
    "wof:name":"Bong Thuong",
    "wof:placetype":"locality"
},
  "geometry": {"coordinates":[105.77478000000001,20.00568],"type":"Point"}
}