{
  "type": "Feature",
  "properties": {
    "gn:admin1_code":"39.0",
    "gn:asciiname":"Mo Cay",
    "gn:country_code":"VN",
    "gn:dem":402,
    "gn:feature_class":"P",
    "gn:feature_code":"PPL",
    "gn:name":"Mo C\u00e2y",
    "gn:population":0,
    "gn:timezone":"Asia/Ho_Chi_Minh",
    "iso:country":"VN",
    "wof:name":"Mo Cay",
    "wof:placetype":"locality"
},
  "geometry": {"coordinates":[106.45,21.66667],"type":"Point"}
}