{
  "type": "Feature",
  "properties": {
    "gn:admin1_code":"72.0",
    "gn:asciiname":"Bo Lin",
    "gn:country_code":"VN",
    "gn:dem":223,
    "gn:feature_class":"P",
    "gn:feature_code":"PPL",
    "gn:name":"B\u00f3 L\u1ecbn",
    "gn:population":0,
    "gn:timezone":"Asia/Ho_Chi_Minh",
    "iso:country":"VN",
    "wof:name":"Bo Lin",
    "wof:placetype":"locality"
},
  "geometry": {"coordinates":[105.84522,22.28814],"type":"Point"}
}