{
  "type": "Feature",
  "properties": {
    "gn:admin1_code":"32.0",
    "gn:asciiname":"Ban Tom",
    "gn:cc2":"VN",
    "gn:country_code":"VN",
    "gn:dem":557,
    "gn:feature_class":"P",
    "gn:feature_code":"PPL",
    "gn:name":"B\u1ea3n T\u00f4m",
    "gn:population":0,
    "gn:timezone":"Asia/Ho_Chi_Minh",
    "iso:country":"VN",
    "name:und_x_variant":[
        "Ban Lom",
        "B\u1ea3n T\u00f4m"
    ],
    "wof:name":"Ban Tom",
    "wof:placetype":"locality"
},
  "geometry": {"coordinates":[103.86667,21.46667],"type":"Point"}
}