{
  "type": "Feature",
  "properties": {
    "gn:admin1_code":"69.0",
    "gn:asciiname":"Tuong Tri B",
    "gn:country_code":"VN",
    "gn:dem":-1,
    "gn:feature_class":"P",
    "gn:feature_code":"PPL",
    "gn:name":"T\u01b0\u1eddng Tr\u00ed B",
    "gn:population":0,
    "gn:timezone":"Asia/Ho_Chi_Minh",
    "iso:country":"VN",
    "name:vie_x_preferred":[
        "T\u01b0\u1eddng Tr\u00ed B"
    ],
    "wof:name":"Tuong Tri B",
    "wof:placetype":"locality"
},
  "geometry": {"coordinates":[105.99583,10.03621],"type":"Point"}
}