{
  "type": "Feature",
  "properties": {
    "gn:admin1_code":"72.0",
    "gn:asciiname":"Ban Ven",
    "gn:country_code":"VN",
    "gn:dem":225,
    "gn:feature_class":"P",
    "gn:feature_code":"PPL",
    "gn:name":"B\u1ea3n V\u00e9n",
    "gn:population":0,
    "gn:timezone":"Asia/Ho_Chi_Minh",
    "iso:country":"VN",
    "name:vie_x_preferred":[
        "B\u1ea3n V\u00e9n"
    ],
    "wof:name":"Ban Ven",
    "wof:placetype":"locality"
},
  "geometry": {"coordinates":[105.76948,22.16],"type":"Point"}
}