{
  "type": "Feature",
  "properties": {
    "gn:admin1_code":"66.0",
    "gn:asciiname":"Huong Tra",
    "gn:country_code":"VN",
    "gn:dem":11,
    "gn:feature_class":"P",
    "gn:feature_code":"PPLA2",
    "gn:name":"H\u01b0\u01a1ng Tr\u00e0",
    "gn:population":0,
    "gn:timezone":"Asia/Ho_Chi_Minh",
    "iso:country":"VN",
    "name:jpn_x_preferred":[
        "\u30d5\u30aa\u30f3\u30c1\u30e3\u30fc"
    ],
    "name:vie_x_preferred":[
        "H\u01b0\u01a1ng Tr\u00e0"
    ],
    "name:zho_x_preferred":[
        "\u9999\u8336\u5e02\u793e"
    ],
    "wof:name":"Huong Tra",
    "wof:placetype":"locality"
},
  "geometry": {"coordinates":[107.4755,16.52539],"type":"Point"}
}