{
  "type": "Feature",
  "properties": {
    "gn:admin1_code":"32.0",
    "gn:asciiname":"Ban Lom",
    "gn:cc2":"VN",
    "gn:country_code":"VN",
    "gn:dem":258,
    "gn:feature_class":"P",
    "gn:feature_code":"PPL",
    "gn:name":"B\u1ea3n L\u1ed1m",
    "gn:population":0,
    "gn:timezone":"Asia/Ho_Chi_Minh",
    "iso:country":"VN",
    "name:und_x_variant":[
        "Ban Kom",
        "B\u1ea3n L\u1ed1m"
    ],
    "wof:name":"Ban Lom",
    "wof:placetype":"locality"
},
  "geometry": {"coordinates":[103.91667,21.55],"type":"Point"}
}