{
  "type": "Feature",
  "properties": {
    "gn:admin1_code":"5.0",
    "gn:asciiname":"Quan Vang",
    "gn:country_code":"VN",
    "gn:dem":178,
    "gn:feature_class":"P",
    "gn:feature_code":"PPL",
    "gn:name":"Qu\u1ea3n V\u00e0ng",
    "gn:population":0,
    "gn:timezone":"Asia/Ho_Chi_Minh",
    "iso:country":"VN",
    "name:vie_x_preferred":[
        "Qu\u1ea3n V\u00e0ng"
    ],
    "wof:name":"Quan Vang",
    "wof:placetype":"locality"
},
  "geometry": {"coordinates":[105.42570000000001,22.80533],"type":"Point"}
}