{
  "type": "Feature",
  "properties": {
    "gn:admin1_code":"68.0",
    "gn:asciiname":"Lang Hoac",
    "gn:country_code":"VN",
    "gn:dem":106,
    "gn:feature_class":"P",
    "gn:feature_code":"PPL",
    "gn:name":"L\u00e0ng Ho\u1eb7c",
    "gn:population":0,
    "gn:timezone":"Asia/Ho_Chi_Minh",
    "iso:country":"VN",
    "name:und_x_variant":[
        "L\u00e0ng Hoac"
    ],
    "name:vie_x_preferred":[
        "L\u00e0ng Ho\u1eb7c"
    ],
    "wof:name":"Lang Hoac",
    "wof:placetype":"locality"
},
  "geometry": {"coordinates":[105.31645,21.81093],"type":"Point"}
}