{
  "type": "Feature",
  "properties": {
    "gn:admin1_code":"49.0",
    "gn:asciiname":"Plei Khun",
    "gn:country_code":"VN",
    "gn:dem":728,
    "gn:feature_class":"P",
    "gn:feature_code":"PPL",
    "gn:name":"Plei Kh\u01b0n",
    "gn:population":0,
    "gn:timezone":"Asia/Ho_Chi_Minh",
    "iso:country":"VN",
    "wof:name":"Plei Khun",
    "wof:placetype":"locality"
},
  "geometry": {"coordinates":[108.03333000000001,13.95],"type":"Point"}
}