{
  "type": "Feature",
  "properties": {
    "gn:admin1_code":"89.0",
    "gn:asciiname":"Hoi Bao",
    "gn:country_code":"VN",
    "gn:dem":348,
    "gn:feature_class":"P",
    "gn:feature_code":"PPL",
    "gn:name":"H\u1ed5i B\u1ea3o",
    "gn:population":0,
    "gn:timezone":"Asia/Ho_Chi_Minh",
    "iso:country":"VN",
    "name:vie_x_preferred":[
        "H\u1ed5i B\u1ea3o"
    ],
    "wof:name":"Hoi Bao",
    "wof:placetype":"locality"
},
  "geometry": {"coordinates":[103.37251999999999,22.52969],"type":"Point"}
}