{
  "type": "Feature",
  "properties": {
    "gn:admin1_code":"88.0",
    "gn:asciiname":"Hoa Binh Hai",
    "gn:country_code":"VN",
    "gn:dem":419,
    "gn:feature_class":"P",
    "gn:feature_code":"PPL",
    "gn:name":"H\u00f2a B\u00ecnh Hai",
    "gn:population":0,
    "gn:timezone":"Asia/Ho_Chi_Minh",
    "iso:country":"VN",
    "name:vie_x_preferred":[
        "H\u00f2a B\u00ecnh Hai"
    ],
    "name:vie_x_variant":[
        "H\u00f2a B\u00ecnh 2"
    ],
    "wof:name":"Hoa Binh Hai",
    "wof:placetype":"locality"
},
  "geometry": {"coordinates":[108.13697000000001,12.40695],"type":"Point"}
}