{
  "type": "Feature",
  "properties": {
    "gn:admin1_code":"58.0",
    "gn:asciiname":"Dinh Long Mot",
    "gn:country_code":"VN",
    "gn:dem":43,
    "gn:feature_class":"P",
    "gn:feature_code":"PPL",
    "gn:name":"\u0110\u00ecnh Long M\u1ed9t",
    "gn:population":0,
    "gn:timezone":"Asia/Ho_Chi_Minh",
    "iso:country":"VN",
    "name:vie_x_preferred":[
        "\u0110\u00ecnh Long M\u1ed9t"
    ],
    "name:vie_x_variant":[
        "\u0110\u00ecnh Long 1"
    ],
    "wof:name":"Dinh Long Mot",
    "wof:placetype":"locality"
},
  "geometry": {"coordinates":[105.41992,18.76923],"type":"Point"}
}