{
  "type": "Feature",
  "properties": {
    "gn:admin1_code":"23.0",
    "gn:asciiname":"Ban Gle Dih",
    "gn:cc2":"VN",
    "gn:country_code":"VN",
    "gn:dem":908,
    "gn:feature_class":"P",
    "gn:feature_code":"PPL",
    "gn:name":"Ban Gl\u00e9 Dih",
    "gn:population":0,
    "gn:timezone":"Asia/Ho_Chi_Minh",
    "iso:country":"VN",
    "name:und_x_variant":[
        "Ban Tl\u00ea",
        "Ban Gl\u00e9 Dih"
    ],
    "wof:name":"Ban Gle Dih",
    "wof:placetype":"locality"
},
  "geometry": {"coordinates":[108.45,12.26667],"type":"Point"}
}