{
  "type": "Feature",
  "properties": {
    "gn:admin1_code":"68.0",
    "gn:asciiname":"Binh Dien",
    "gn:country_code":"VN",
    "gn:dem":32,
    "gn:feature_class":"P",
    "gn:feature_code":"PPL",
    "gn:name":"B\u00ecnh \u0110i\u00ean",
    "gn:population":0,
    "gn:timezone":"Asia/Ho_Chi_Minh",
    "iso:country":"VN",
    "name:vie_x_preferred":[
        "B\u00ecnh \u0110i\u00ean"
    ],
    "wof:name":"Binh Dien",
    "wof:placetype":"locality"
},
  "geometry": {"coordinates":[105.22837,21.77487],"type":"Point"}
}