{
  "type": "Feature",
  "properties": {
    "gn:admin1_code":"58.0",
    "gn:asciiname":"Xieng Lam",
    "gn:country_code":"VN",
    "gn:dem":131,
    "gn:feature_class":"P",
    "gn:feature_code":"PPL",
    "gn:name":"Xi\u1ec1ng L\u1eb1m",
    "gn:population":0,
    "gn:timezone":"Asia/Ho_Chi_Minh",
    "iso:country":"VN",
    "name:und_x_variant":[
        "M\u01b0\u1eddng Lam"
    ],
    "name:vie_x_preferred":[
        "Xi\u1ec1ng L\u1eb1m"
    ],
    "wof:name":"Xieng Lam",
    "wof:placetype":"locality"
},
  "geometry": {"coordinates":[104.62824999999999,19.50887],"type":"Point"}
}