{
  "type": "Feature",
  "properties": {
    "gn:admin1_code":"47.0",
    "gn:asciiname":"Ap An Lam",
    "gn:country_code":"VN",
    "gn:dem":46,
    "gn:feature_class":"P",
    "gn:feature_code":"PPL",
    "gn:name":"\u1ea4p An L\u00e2m",
    "gn:population":0,
    "gn:timezone":"Asia/Ho_Chi_Minh",
    "iso:country":"VN",
    "name:und_x_variant":[
        "An Lam",
        "An Lan",
        "\u1ea4p An L\u00e2m"
    ],
    "wof:name":"Ap An Lam",
    "wof:placetype":"locality"
},
  "geometry": {"coordinates":[108.15000000000001,11.13333],"type":"Point"}
}