{
  "type": "Feature",
  "properties": {
    "gn:admin1_code":"50.0",
    "gn:asciiname":"Khau Hen",
    "gn:country_code":"VN",
    "gn:dem":824,
    "gn:feature_class":"P",
    "gn:feature_code":"PPL",
    "gn:name":"Kh\u00e2u H\u00ean",
    "gn:population":0,
    "gn:timezone":"Asia/Ho_Chi_Minh",
    "iso:country":"VN",
    "name:vie_x_preferred":[
        "Kh\u00e2u H\u00ean"
    ],
    "wof:name":"Khau Hen",
    "wof:placetype":"locality"
},
  "geometry": {"coordinates":[105.28053,22.93478],"type":"Point"}
}