{
  "type": "Feature",
  "properties": {
    "gn:admin1_code":"5.0",
    "gn:asciiname":"Chang Vac",
    "gn:country_code":"VN",
    "gn:dem":914,
    "gn:feature_class":"P",
    "gn:feature_code":"PPL",
    "gn:name":"Chang V\u1eb7c",
    "gn:population":0,
    "gn:timezone":"Asia/Ho_Chi_Minh",
    "iso:country":"VN",
    "wof:name":"Chang Vac",
    "wof:placetype":"locality"
},
  "geometry": {"coordinates":[106.16667,22.96667],"type":"Point"}
}