{
  "type": "Feature",
  "properties": {
    "gn:admin1_code":"39.0",
    "gn:asciiname":"Bo Min",
    "gn:country_code":"VN",
    "gn:dem":250,
    "gn:feature_class":"P",
    "gn:feature_code":"PPL",
    "gn:name":"B\u00f3 M\u1ecbn",
    "gn:population":0,
    "gn:timezone":"Asia/Ho_Chi_Minh",
    "iso:country":"VN",
    "wof:name":"Bo Min",
    "wof:placetype":"locality"
},
  "geometry": {"coordinates":[106.58450999999999,22.1454],"type":"Point"}
}