{
  "type": "Feature",
  "properties": {
    "gn:admin1_code":"1.0",
    "gn:asciiname":"Ap Binh Trung",
    "gn:cc2":"VN",
    "gn:country_code":"VN",
    "gn:dem":7,
    "gn:feature_class":"P",
    "gn:feature_code":"PPL",
    "gn:name":"\u1ea4p B\u00ecnh Trung",
    "gn:population":0,
    "gn:timezone":"Asia/Ho_Chi_Minh",
    "iso:country":"VN",
    "name:und_x_variant":[
        "Binh Trung",
        "\u1ea4p B\u00ecnh Trung"
    ],
    "wof:name":"Ap Binh Trung",
    "wof:placetype":"locality"
},
  "geometry": {"coordinates":[105.25,10.56667],"type":"Point"}
}