{
  "type": "Feature",
  "properties": {
    "gn:admin1_code":"23.0",
    "gn:asciiname":"Lam Bieng",
    "gn:country_code":"VN",
    "gn:dem":1470,
    "gn:feature_class":"P",
    "gn:feature_code":"PPL",
    "gn:name":"L\u00e2m Bi\u00eang",
    "gn:population":0,
    "gn:timezone":"Asia/Ho_Chi_Minh",
    "iso:country":"VN",
    "name:vie_x_preferred":[
        "L\u00e2m Bi\u00eang"
    ],
    "wof:name":"Lam Bieng",
    "wof:placetype":"locality"
},
  "geometry": {"coordinates":[108.42655000000001,12.01621],"type":"Point"}
}