{
  "type": "Feature",
  "properties": {
    "gn:admin1_code":"68.0",
    "gn:asciiname":"Na Kheng",
    "gn:country_code":"VN",
    "gn:dem":67,
    "gn:feature_class":"P",
    "gn:feature_code":"PPL",
    "gn:name":"N\u00e0 Kh\u00e8ng",
    "gn:population":0,
    "gn:timezone":"Asia/Ho_Chi_Minh",
    "iso:country":"VN",
    "name:vie_x_preferred":[
        "N\u00e0 Kh\u00e8ng"
    ],
    "wof:name":"Na Kheng",
    "wof:placetype":"locality"
},
  "geometry": {"coordinates":[105.36586,22.36053],"type":"Point"}
}