{
  "type": "Feature",
  "properties": {
    "gn:admin1_code":"91.0",
    "gn:asciiname":"Buon Bupah",
    "gn:country_code":"VN",
    "gn:dem":753,
    "gn:feature_class":"P",
    "gn:feature_code":"PPL",
    "gn:name":"Bu\u00f4n Bupah",
    "gn:population":0,
    "gn:timezone":"Asia/Ho_Chi_Minh",
    "iso:country":"VN",
    "wof:name":"Buon Bupah",
    "wof:placetype":"locality"
},
  "geometry": {"coordinates":[107.66667,12.11667],"type":"Point"}
}