{
  "type": "Feature",
  "properties": {
    "gn:admin1_code":"24.0",
    "gn:asciiname":"Xom Giong",
    "gn:country_code":"VN",
    "gn:dem":1,
    "gn:feature_class":"P",
    "gn:feature_code":"PPL",
    "gn:name":"X\u00f3m Gi\u1ed3ng",
    "gn:population":0,
    "gn:timezone":"Asia/Ho_Chi_Minh",
    "iso:country":"VN",
    "name:und_x_variant":[
        "\u1ea4p Nhi",
        "X\u00f3m Gi\u1ed3ng"
    ],
    "wof:name":"Xom Giong",
    "wof:placetype":"locality"
},
  "geometry": {"coordinates":[106.58333,10.48333],"type":"Point"}
}