{
  "type": "Feature",
  "properties": {
    "gn:admin1_code":"55.0",
    "gn:asciiname":"Kon Kolok",
    "gn:country_code":"VN",
    "gn:dem":678,
    "gn:feature_class":"P",
    "gn:feature_code":"PPL",
    "gn:name":"Kon K\u01a1lok",
    "gn:population":0,
    "gn:timezone":"Asia/Ho_Chi_Minh",
    "iso:country":"VN",
    "wof:name":"Kon Kolok",
    "wof:placetype":"locality"
},
  "geometry": {"coordinates":[107.95,14.56667],"type":"Point"}
}