{
  "type": "Feature",
  "properties": {
    "gn:admin1_code":"52.0",
    "gn:asciiname":"Yen Khanh",
    "gn:country_code":"VN",
    "gn:dem":7,
    "gn:feature_class":"P",
    "gn:feature_code":"PPL",
    "gn:name":"Y\u1ebfn Kh\u00e1nh",
    "gn:population":0,
    "gn:timezone":"Asia/Ho_Chi_Minh",
    "iso:country":"VN",
    "name:vie_x_preferred":[
        "Y\u1ebfn Kh\u00e1nh"
    ],
    "wof:name":"Yen Khanh",
    "wof:placetype":"locality"
},
  "geometry": {"coordinates":[105.92268,18.2977],"type":"Point"}
}