{
  "type": "Feature",
  "properties": {
    "gn:admin1_code":"87.0",
    "gn:asciiname":"Truong Quoi",
    "gn:country_code":"VN",
    "gn:dem":3,
    "gn:feature_class":"P",
    "gn:feature_code":"PPL",
    "gn:name":"Tr\u01b0\u1eddng Qu\u1edbi",
    "gn:population":0,
    "gn:timezone":"Asia/Ho_Chi_Minh",
    "iso:country":"VN",
    "name:vie_x_preferred":[
        "Tr\u01b0\u1eddng Qu\u1edbi"
    ],
    "wof:name":"Truong Quoi",
    "wof:placetype":"locality"
},
  "geometry": {"coordinates":[105.64413999999999,10.01257],"type":"Point"}
}