{
  "type": "Feature",
  "properties": {
    "gn:admin1_code":"32.0",
    "gn:asciiname":"Tieu Khu Chin",
    "gn:country_code":"VN",
    "gn:dem":559,
    "gn:feature_class":"P",
    "gn:feature_code":"PPL",
    "gn:name":"Ti\u1ec3u Khu Ch\u00edn",
    "gn:population":0,
    "gn:timezone":"Asia/Ho_Chi_Minh",
    "iso:country":"VN",
    "name:vie_x_preferred":[
        "Ti\u1ec3u Khu Ch\u00edn"
    ],
    "name:vie_x_variant":[
        "Ti\u1ec3u Khu 9"
    ],
    "wof:name":"Tieu Khu Chin",
    "wof:placetype":"locality"
},
  "geometry": {"coordinates":[104.09575,21.20057000000001],"type":"Point"}
}