{
  "type": "Feature",
  "properties": {
    "gn:admin1_code":"50.0",
    "gn:asciiname":"Sua Pa",
    "gn:country_code":"VN",
    "gn:dem":1130,
    "gn:feature_class":"P",
    "gn:feature_code":"PPL",
    "gn:name":"S\u1ee7a P\u00e1",
    "gn:population":0,
    "gn:timezone":"Asia/Ho_Chi_Minh",
    "iso:country":"VN",
    "name:vie_x_preferred":[
        "S\u1ee7a P\u00e1"
    ],
    "wof:name":"Sua Pa",
    "wof:placetype":"locality"
},
  "geometry": {"coordinates":[105.19069,23.19591],"type":"Point"}
}