{
  "type": "Feature",
  "properties": {
    "gn:admin1_code":"49.0",
    "gn:asciiname":"Plei Tower",
    "gn:country_code":"VN",
    "gn:dem":604,
    "gn:feature_class":"P",
    "gn:feature_code":"PPL",
    "gn:name":"Plei Tower",
    "gn:population":0,
    "gn:timezone":"Asia/Ho_Chi_Minh",
    "iso:country":"VN",
    "wof:name":"Plei Tower",
    "wof:placetype":"locality"
},
  "geometry": {"coordinates":[108.03333000000001,14.21667],"type":"Point"}
}