{
  "type": "Feature",
  "properties": {
    "gn:admin1_code":"78.0",
    "gn:asciiname":"Dong Tham",
    "gn:country_code":"VN",
    "gn:dem":97,
    "gn:feature_class":"P",
    "gn:feature_code":"PPL",
    "gn:name":"\u0110\u1ed9ng Tham",
    "gn:population":0,
    "gn:timezone":"Asia/Ho_Chi_Minh",
    "iso:country":"VN",
    "wof:name":"Dong Tham",
    "wof:placetype":"locality"
},
  "geometry": {"coordinates":[107.96666999999999,16.13332999999999],"type":"Point"}
}