{
  "type": "Feature",
  "properties": {
    "gn:admin1_code":"32.0",
    "gn:asciiname":"Ban Hoi Tat",
    "gn:country_code":"VN",
    "gn:dem":900,
    "gn:feature_class":"P",
    "gn:feature_code":"PPL",
    "gn:name":"B\u1ea3n H\u1ed9i T\u00e1t",
    "gn:population":0,
    "gn:timezone":"Asia/Ho_Chi_Minh",
    "iso:country":"VN",
    "name:vie_x_preferred":[
        "B\u1ea3n H\u1ed9i T\u00e1t"
    ],
    "wof:name":"Ban Hoi Tat",
    "wof:placetype":"locality"
},
  "geometry": {"coordinates":[103.61324,21.52035],"type":"Point"}
}