{
  "type": "Feature",
  "properties": {
    "gn:admin1_code":"88.0",
    "gn:asciiname":"Ban Kha",
    "gn:cc2":"VN",
    "gn:country_code":"VN",
    "gn:dem":628,
    "gn:feature_class":"P",
    "gn:feature_code":"PPL",
    "gn:name":"Ban Kh\u00e1",
    "gn:population":0,
    "gn:timezone":"Asia/Ho_Chi_Minh",
    "iso:country":"VN",
    "name:und_x_variant":[
        "Buon Kha",
        "Ban Kh\u00e1"
    ],
    "wof:name":"Ban Kha",
    "wof:placetype":"locality"
},
  "geometry": {"coordinates":[108.25,13.21667],"type":"Point"}
}