{
  "type": "Feature",
  "properties": {
    "gn:admin1_code":"92.0",
    "gn:asciiname":"Ban Tra",
    "gn:country_code":"VN",
    "gn:dem":563,
    "gn:feature_class":"P",
    "gn:feature_code":"PPL",
    "gn:name":"B\u1ea3n Tr\u00e1",
    "gn:population":0,
    "gn:timezone":"Asia/Ho_Chi_Minh",
    "iso:country":"VN",
    "name:vie_x_preferred":[
        "B\u1ea3n Tr\u00e1"
    ],
    "wof:name":"Ban Tra",
    "wof:placetype":"locality"
},
  "geometry": {"coordinates":[103.24043,21.52936],"type":"Point"}
}