{
  "type": "Feature",
  "properties": {
    "gn:admin1_code":"1.0",
    "gn:asciiname":"Binh Khanh",
    "gn:country_code":"VN",
    "gn:dem":1,
    "gn:feature_class":"P",
    "gn:feature_code":"PPL",
    "gn:name":"B\u00ecnh Kh\u00e1nh",
    "gn:population":0,
    "gn:timezone":"Asia/Ho_Chi_Minh",
    "iso:country":"VN",
    "name:und_x_variant":[
        "\u1ea4p B\u00ecnh Kh\u00e1nh"
    ],
    "name:vie_x_preferred":[
        "B\u00ecnh Kh\u00e1nh"
    ],
    "wof:name":"Binh Khanh",
    "wof:placetype":"locality"
},
  "geometry": {"coordinates":[105.41798,10.3933],"type":"Point"}
}