{
  "type": "Feature",
  "properties": {
    "gn:admin1_code":"70.0",
    "gn:asciiname":"Cay Tho",
    "gn:country_code":"VN",
    "gn:dem":82,
    "gn:feature_class":"P",
    "gn:feature_code":"PPL",
    "gn:name":"C\u00e2y Th\u1ecd",
    "gn:population":0,
    "gn:timezone":"Asia/Ho_Chi_Minh",
    "iso:country":"VN",
    "name:vie_x_preferred":[
        "C\u00e2y Th\u1ecd"
    ],
    "wof:name":"Cay Tho",
    "wof:placetype":"locality"
},
  "geometry": {"coordinates":[104.93545,21.75875],"type":"Point"}
}