{
  "type": "Feature",
  "properties": {
    "gn:admin1_code":"52.0",
    "gn:asciiname":"Mai Long",
    "gn:country_code":"VN",
    "gn:dem":29,
    "gn:feature_class":"P",
    "gn:feature_code":"PPL",
    "gn:name":"Mai Long",
    "gn:population":0,
    "gn:timezone":"Asia/Ho_Chi_Minh",
    "iso:country":"VN",
    "name:vie_x_preferred":[
        "Mai Long"
    ],
    "wof:name":"Mai Long",
    "wof:placetype":"locality"
},
  "geometry": {"coordinates":[105.75471,18.40327000000001],"type":"Point"}
}