{
  "type": "Feature",
  "properties": {
    "gn:admin1_code":"37.0",
    "gn:asciiname":"Tan Binh Hai",
    "gn:country_code":"VN",
    "gn:dem":2,
    "gn:feature_class":"P",
    "gn:feature_code":"PPL",
    "gn:name":"T\u00e2n B\u00ecnh Hai",
    "gn:population":0,
    "gn:timezone":"Asia/Ho_Chi_Minh",
    "iso:country":"VN",
    "name:vie_x_preferred":[
        "T\u00e2n B\u00ecnh Hai"
    ],
    "name:vie_x_variant":[
        "T\u00e2n B\u00ecnh 2"
    ],
    "wof:name":"Tan Binh Hai",
    "wof:placetype":"locality"
},
  "geometry": {"coordinates":[106.47242,10.37646],"type":"Point"}
}