{
  "type": "Feature",
  "properties": {
    "gn:admin1_code":"58.0",
    "gn:asciiname":"Lien Tri",
    "gn:country_code":"VN",
    "gn:dem":8,
    "gn:feature_class":"P",
    "gn:feature_code":"PPL",
    "gn:name":"Li\u00ean Tr\u00ec",
    "gn:population":0,
    "gn:timezone":"Asia/Ho_Chi_Minh",
    "iso:country":"VN",
    "name:vie_x_preferred":[
        "Li\u00ean Tr\u00ec"
    ],
    "wof:name":"Lien Tri",
    "wof:placetype":"locality"
},
  "geometry": {"coordinates":[105.45361,18.93463],"type":"Point"}
}