{
  "type": "Feature",
  "properties": {
    "gn:admin1_code":"83.0",
    "gn:asciiname":"Giai Ha",
    "gn:country_code":"VN",
    "gn:dem":36,
    "gn:feature_class":"P",
    "gn:feature_code":"PPL",
    "gn:name":"Giai H\u1ea1",
    "gn:population":0,
    "gn:timezone":"Asia/Ho_Chi_Minh",
    "iso:country":"VN",
    "name:vie_x_preferred":[
        "Giai H\u1ea1"
    ],
    "wof:name":"Giai Ha",
    "wof:placetype":"locality"
},
  "geometry": {"coordinates":[105.27273,21.09739],"type":"Point"}
}