{
  "type": "Feature",
  "properties": {
    "gn:admin1_code":"5.0",
    "gn:asciiname":"Ban Dong Ke",
    "gn:country_code":"VN",
    "gn:dem":322,
    "gn:feature_class":"P",
    "gn:feature_code":"PPL",
    "gn:name":"B\u1ea3n \u0110\u00f4ng K\u00e9",
    "gn:population":0,
    "gn:timezone":"Asia/Ho_Chi_Minh",
    "iso:country":"VN",
    "name:vie_x_preferred":[
        "B\u1ea3n \u0110\u00f4ng K\u00e9"
    ],
    "wof:name":"Ban Dong Ke",
    "wof:placetype":"locality"
},
  "geometry": {"coordinates":[106.80938,22.77931],"type":"Point"}
}