{
  "type": "Feature",
  "properties": {
    "gn:admin1_code":"34.0",
    "gn:asciiname":"Ban Son",
    "gn:country_code":"VN",
    "gn:dem":720,
    "gn:feature_class":"P",
    "gn:feature_code":"PPL",
    "gn:name":"B\u1ea3n Son",
    "gn:population":0,
    "gn:timezone":"Asia/Ho_Chi_Minh",
    "iso:country":"VN",
    "name:vie_x_preferred":[
        "B\u1ea3n Son"
    ],
    "wof:name":"Ban Son",
    "wof:placetype":"locality"
},
  "geometry": {"coordinates":[104.64490000000001,20.3229],"type":"Point"}
}