{
  "type": "Feature",
  "properties": {
    "gn:admin1_code":"47.0",
    "gn:asciiname":"Soung Trao",
    "gn:country_code":"VN",
    "gn:dem":483,
    "gn:feature_class":"P",
    "gn:feature_code":"PPL",
    "gn:name":"Soung Trao",
    "gn:population":0,
    "gn:timezone":"Asia/Ho_Chi_Minh",
    "iso:country":"VN",
    "name:und_x_variant":[
        "S\u00f4ng Trao",
        "Soung Trao"
    ],
    "wof:name":"Soung Trao",
    "wof:placetype":"locality"
},
  "geometry": {"coordinates":[107.99028,11.08831],"type":"Point"}
}