{
  "type": "Feature",
  "properties": {
    "gn:admin1_code":"88.0",
    "gn:asciiname":"Khoi Tam",
    "gn:country_code":"VN",
    "gn:dem":445,
    "gn:feature_class":"P",
    "gn:feature_code":"PPL",
    "gn:name":"Kh\u1ed1i T\u00e1m",
    "gn:population":0,
    "gn:timezone":"Asia/Ho_Chi_Minh",
    "iso:country":"VN",
    "name:vie_x_preferred":[
        "Kh\u1ed1i T\u00e1m"
    ],
    "name:vie_x_variant":[
        "Kh\u1ed1i 8"
    ],
    "wof:name":"Khoi Tam",
    "wof:placetype":"locality"
},
  "geometry": {"coordinates":[108.54564000000001,12.80755],"type":"Point"}
}