{
  "type": "Feature",
  "properties": {
    "gn:admin1_code":"65.0",
    "gn:asciiname":"Tra Ong",
    "gn:country_code":"VN",
    "gn:dem":3,
    "gn:feature_class":"P",
    "gn:feature_code":"PPL",
    "gn:name":"Tr\u00e0 Ong",
    "gn:population":0,
    "gn:timezone":"Asia/Ho_Chi_Minh",
    "iso:country":"VN",
    "name:und_x_variant":[
        "Tr\u00e0 \u00d4ng",
        "\u1ea4p Tr\u00e0 \u00d4ng"
    ],
    "name:vie_x_preferred":[
        "Tr\u00e0 Ong"
    ],
    "wof:name":"Tra Ong",
    "wof:placetype":"locality"
},
  "geometry": {"coordinates":[106.07756999999999,9.48358],"type":"Point"}
}