{
  "type": "Feature",
  "properties": {
    "gn:admin1_code":"34.0",
    "gn:asciiname":"Chom Ta",
    "gn:country_code":"VN",
    "gn:dem":101,
    "gn:feature_class":"P",
    "gn:feature_code":"PPL",
    "gn:name":"Ch\u00f2m Ta",
    "gn:population":0,
    "gn:timezone":"Asia/Ho_Chi_Minh",
    "iso:country":"VN",
    "wof:name":"Chom Ta",
    "wof:placetype":"locality"
},
  "geometry": {"coordinates":[105.31667,20.23333],"type":"Point"}
}