{
  "type": "Feature",
  "properties": {
    "gn:admin1_code":"58.0",
    "gn:asciiname":"Mau Nghia",
    "gn:country_code":"VN",
    "gn:dem":131,
    "gn:feature_class":"P",
    "gn:feature_code":"PPL",
    "gn:name":"M\u1eadu Ngh\u0129a",
    "gn:population":0,
    "gn:timezone":"Asia/Ho_Chi_Minh",
    "iso:country":"VN",
    "wof:name":"Mau Nghia",
    "wof:placetype":"locality"
},
  "geometry": {"coordinates":[105.53333000000001,19.35],"type":"Point"}
}