{
  "type": "Feature",
  "properties": {
    "gn:admin1_code":"74.0",
    "gn:asciiname":"Lam Cau",
    "gn:country_code":"VN",
    "gn:dem":12,
    "gn:feature_class":"P",
    "gn:feature_code":"PPL",
    "gn:name":"Lam C\u1ea7u",
    "gn:population":0,
    "gn:timezone":"Asia/Ho_Chi_Minh",
    "iso:country":"VN",
    "name:vie_x_preferred":[
        "Lam C\u1ea7u"
    ],
    "wof:name":"Lam Cau",
    "wof:placetype":"locality"
},
  "geometry": {"coordinates":[106.11591,21.09023],"type":"Point"}
}