{
  "type": "Feature",
  "properties": {
    "gn:admin1_code":"23.0",
    "gn:asciiname":"Ap An Kroet",
    "gn:cc2":"VN",
    "gn:country_code":"VN",
    "gn:dem":1531,
    "gn:feature_class":"P",
    "gn:feature_code":"PPL",
    "gn:name":"\u1ea4p An Kro\u00ebt",
    "gn:population":0,
    "gn:timezone":"Asia/Ho_Chi_Minh",
    "iso:country":"VN",
    "name:und_x_variant":[
        "Ankroet",
        "\u1ea4p An Kro\u00ebt"
    ],
    "wof:name":"Ap An Kroet",
    "wof:placetype":"locality"
},
  "geometry": {"coordinates":[108.34999999999999,11.98333],"type":"Point"}
}