{
  "type": "Feature",
  "properties": {
    "gn:admin1_code":"61.0",
    "gn:asciiname":"Hoa Thanh",
    "gn:country_code":"VN",
    "gn:dem":93,
    "gn:feature_class":"P",
    "gn:feature_code":"PPL",
    "gn:name":"H\u00f2a Th\u1ea1nh",
    "gn:population":0,
    "gn:timezone":"Asia/Ho_Chi_Minh",
    "iso:country":"VN",
    "name:vie_x_preferred":[
        "H\u00f2a Th\u1ea1nh"
    ],
    "wof:name":"Hoa Thanh",
    "wof:placetype":"locality"
},
  "geometry": {"coordinates":[109.23497999999999,13.2743],"type":"Point"}
}