{
  "type": "Feature",
  "properties": {
    "gn:admin1_code":"69.0",
    "gn:asciiname":"Hoi Phuoc",
    "gn:country_code":"VN",
    "gn:dem":8,
    "gn:feature_class":"P",
    "gn:feature_code":"PPL",
    "gn:name":"H\u1ed3i Ph\u01b0\u1edbc",
    "gn:population":0,
    "gn:timezone":"Asia/Ho_Chi_Minh",
    "iso:country":"VN",
    "name:vie_x_preferred":[
        "H\u1ed3i Ph\u01b0\u1edbc"
    ],
    "wof:name":"Hoi Phuoc",
    "wof:placetype":"locality"
},
  "geometry": {"coordinates":[106.07785,10.06937],"type":"Point"}
}