{
  "type": "Feature",
  "properties": {
    "gn:admin1_code":"58.0",
    "gn:asciiname":"Na Dam",
    "gn:country_code":"VN",
    "gn:dem":146,
    "gn:feature_class":"P",
    "gn:feature_code":"PPL",
    "gn:name":"Na \u0110\u0103m",
    "gn:population":0,
    "gn:timezone":"Asia/Ho_Chi_Minh",
    "iso:country":"VN",
    "name:vie_x_preferred":[
        "Na \u0110\u0103m"
    ],
    "wof:name":"Na Dam",
    "wof:placetype":"locality"
},
  "geometry": {"coordinates":[105.07617999999999,19.37483],"type":"Point"}
}