{
  "type": "Feature",
  "properties": {
    "gn:admin1_code":"49.0",
    "gn:asciiname":"Thanh Binh",
    "gn:country_code":"VN",
    "gn:dem":547,
    "gn:feature_class":"P",
    "gn:feature_code":"PPL",
    "gn:name":"Thanh B\u00ecnh",
    "gn:population":0,
    "gn:timezone":"Asia/Ho_Chi_Minh",
    "iso:country":"VN",
    "name:und_x_variant":[
        "Thanh B\u00ecnh"
    ],
    "wof:name":"Thanh Binh",
    "wof:placetype":"locality"
},
  "geometry": {"coordinates":[107.87483,13.81787],"type":"Point"}
}