{
  "type": "Feature",
  "properties": {
    "gn:admin1_code":"87.0",
    "gn:asciiname":"Thoi Binh Mot",
    "gn:country_code":"VN",
    "gn:dem":5,
    "gn:feature_class":"P",
    "gn:feature_code":"PPL",
    "gn:name":"Th\u1edbi B\u00ecnh M\u1ed9t",
    "gn:population":0,
    "gn:timezone":"Asia/Ho_Chi_Minh",
    "iso:country":"VN",
    "name:vie_x_preferred":[
        "Th\u1edbi B\u00ecnh M\u1ed9t"
    ],
    "name:vie_x_variant":[
        "Th\u1edbi B\u00ecnh 1"
    ],
    "wof:name":"Thoi Binh Mot",
    "wof:placetype":"locality"
},
  "geometry": {"coordinates":[105.42083,10.07962],"type":"Point"}
}