{
  "type": "Feature",
  "properties": {
    "gn:admin1_code":"67.0",
    "gn:asciiname":"Kenh Xang",
    "gn:country_code":"VN",
    "gn:dem":6,
    "gn:feature_class":"P",
    "gn:feature_code":"PPL",
    "gn:name":"K\u00eanh X\u00e1ng",
    "gn:population":0,
    "gn:timezone":"Asia/Ho_Chi_Minh",
    "iso:country":"VN",
    "name:vie_x_preferred":[
        "K\u00eanh X\u00e1ng"
    ],
    "wof:name":"Kenh Xang",
    "wof:placetype":"locality"
},
  "geometry": {"coordinates":[106.09334,9.84875],"type":"Point"}
}