{
  "type": "Feature",
  "properties": {
    "gn:admin1_code":"32.0",
    "gn:asciiname":"Ban Co Loi",
    "gn:country_code":"VN",
    "gn:dem":817,
    "gn:feature_class":"P",
    "gn:feature_code":"PPL",
    "gn:name":"B\u1ea3n C\u00f3 L\u1ecdi",
    "gn:population":0,
    "gn:timezone":"Asia/Ho_Chi_Minh",
    "iso:country":"VN",
    "name:vie_x_preferred":[
        "B\u1ea3n C\u00f3 L\u1ecdi"
    ],
    "wof:name":"Ban Co Loi",
    "wof:placetype":"locality"
},
  "geometry": {"coordinates":[103.65921,21.83694],"type":"Point"}
}