{
  "type": "Feature",
  "properties": {
    "gn:admin1_code":"43.0",
    "gn:asciiname":"Xa Gia Kiem",
    "gn:country_code":"VN",
    "gn:dem":108,
    "gn:feature_class":"P",
    "gn:feature_code":"PPL",
    "gn:name":"X\u00e3 Gia Ki\u00eam",
    "gn:population":0,
    "gn:timezone":"Asia/Ho_Chi_Minh",
    "iso:country":"VN",
    "name:und_x_variant":[
        "Gia Kiem",
        "New Phat Diem",
        "X\u00e3 Gia Kiam",
        "X\u00e3 Gia Ki\u00eam"
    ],
    "wof:name":"Xa Gia Kiem",
    "wof:placetype":"locality"
},
  "geometry": {"coordinates":[107.18333,11.03333],"type":"Point"}
}