{
  "type": "Feature",
  "properties": {
    "gn:admin1_code":"32.0",
    "gn:asciiname":"Ban Ai",
    "gn:country_code":"VN",
    "gn:dem":496,
    "gn:feature_class":"P",
    "gn:feature_code":"PPL",
    "gn:name":"B\u1ea3n \u00c1i",
    "gn:population":0,
    "gn:timezone":"Asia/Ho_Chi_Minh",
    "iso:country":"VN",
    "name:vie_x_preferred":[
        "B\u1ea3n \u00c1i"
    ],
    "wof:name":"Ban Ai",
    "wof:placetype":"locality"
},
  "geometry": {"coordinates":[103.58087,21.67364],"type":"Point"}
}