{
  "type": "Feature",
  "properties": {
    "gn:admin1_code":"64.0",
    "gn:asciiname":"Giem Ha Trung",
    "gn:country_code":"VN",
    "gn:dem":7,
    "gn:feature_class":"P",
    "gn:feature_code":"PPL",
    "gn:name":"Gi\u00eam H\u00e0 Trung",
    "gn:population":0,
    "gn:timezone":"Asia/Ho_Chi_Minh",
    "iso:country":"VN",
    "wof:name":"Giem Ha Trung",
    "wof:placetype":"locality"
},
  "geometry": {"coordinates":[107.15000000000001,16.95],"type":"Point"}
}