{
  "type": "Feature",
  "properties": {
    "gn:admin1_code":"50.0",
    "gn:asciiname":"Ban Ha Son II",
    "gn:country_code":"VN",
    "gn:dem":380,
    "gn:feature_class":"P",
    "gn:feature_code":"PPL",
    "gn:name":"B\u1ea3n H\u00e0 S\u01a1n II",
    "gn:population":0,
    "gn:timezone":"Asia/Ho_Chi_Minh",
    "iso:country":"VN",
    "name:vie_x_preferred":[
        "B\u1ea3n H\u00e0 S\u01a1n II"
    ],
    "wof:name":"Ban Ha Son II",
    "wof:placetype":"locality"
},
  "geometry": {"coordinates":[105.28440000000001,22.7324],"type":"Point"}
}