{
  "type": "Feature",
  "properties": {
    "gn:admin1_code":"68.0",
    "gn:asciiname":"Dong Ho",
    "gn:country_code":"VN",
    "gn:dem":52,
    "gn:feature_class":"P",
    "gn:feature_code":"PPLL",
    "gn:name":"\u0110\u00f4ng H\u1ed9",
    "gn:population":0,
    "gn:timezone":"Asia/Ho_Chi_Minh",
    "iso:country":"VN",
    "name:und_x_variant":[
        "\u0110ong He"
    ],
    "name:vie_x_preferred":[
        "\u0110\u00f4ng H\u1ed9"
    ],
    "wof:name":"Dong Ho",
    "wof:placetype":"locality"
},
  "geometry": {"coordinates":[105.34128,21.72907],"type":"Point"}
}