{
  "type": "Feature",
  "properties": {
    "gn:admin1_code":"50.0",
    "gn:asciiname":"Ten Sao Phin",
    "gn:country_code":"VN",
    "gn:dem":829,
    "gn:feature_class":"P",
    "gn:feature_code":"PPL",
    "gn:name":"Ten Sao Phin",
    "gn:population":0,
    "gn:timezone":"Asia/Ho_Chi_Minh",
    "iso:country":"VN",
    "wof:name":"Ten Sao Phin",
    "wof:placetype":"locality"
},
  "geometry": {"coordinates":[104.73333,22.61667000000001],"type":"Point"}
}