{
  "type": "Feature",
  "properties": {
    "gn:admin1_code":"72.0",
    "gn:asciiname":"Ban Cao",
    "gn:country_code":"VN",
    "gn:dem":443,
    "gn:feature_class":"P",
    "gn:feature_code":"PPL",
    "gn:name":"B\u1ea3n C\u00e0o",
    "gn:population":0,
    "gn:timezone":"Asia/Ho_Chi_Minh",
    "iso:country":"VN",
    "name:und_x_variant":[
        "B\u1ea3n Cao"
    ],
    "name:vie_x_preferred":[
        "B\u1ea3n C\u00e0o"
    ],
    "wof:name":"Ban Cao",
    "wof:placetype":"locality"
},
  "geometry": {"coordinates":[106.00144,22.14536],"type":"Point"}
}