{
  "type": "Feature",
  "properties": {
    "gn:admin1_code":"74.0",
    "gn:asciiname":"Phu Cam",
    "gn:country_code":"VN",
    "gn:dem":10,
    "gn:feature_class":"P",
    "gn:feature_code":"PPL",
    "gn:name":"Ph\u1ee5 C\u1ea7m",
    "gn:population":0,
    "gn:timezone":"Asia/Ho_Chi_Minh",
    "iso:country":"VN",
    "name:vie_x_preferred":[
        "Ph\u00f9 C\u1ea7m"
    ],
    "name:vie_x_variant":[
        "Ph\u1ee5 C\u1ea7m"
    ],
    "wof:name":"Phu Cam",
    "wof:placetype":"locality"
},
  "geometry": {"coordinates":[106.00870999999999,21.25674],"type":"Point"}
}