{
  "type": "Feature",
  "properties": {
    "gn:admin1_code":"74.0",
    "gn:asciiname":"Yen Dinh",
    "gn:country_code":"VN",
    "gn:dem":7,
    "gn:feature_class":"P",
    "gn:feature_code":"PPL",
    "gn:name":"Y\u00ean \u0110\u00ecnh",
    "gn:population":0,
    "gn:timezone":"Asia/Ho_Chi_Minh",
    "iso:country":"VN",
    "name:vie_x_preferred":[
        "Y\u00ean \u0110\u1ecbnh"
    ],
    "name:vie_x_variant":[
        "Y\u00ean \u0110\u00ecnh"
    ],
    "wof:name":"Yen Dinh",
    "wof:placetype":"locality"
},
  "geometry": {"coordinates":[106.20458000000001,21.16222],"type":"Point"}
}