{
  "type": "Feature",
  "properties": {
    "gn:admin1_code":"76.0",
    "gn:asciiname":"Bu R'lieng",
    "gn:country_code":"VN",
    "gn:dem":353,
    "gn:feature_class":"P",
    "gn:feature_code":"PPL",
    "gn:name":"Bu R\u2019li\u00eang",
    "gn:population":0,
    "gn:timezone":"Asia/Ho_Chi_Minh",
    "iso:country":"VN",
    "name:und_x_variant":[
        "Lieng",
        "Bu R\u2019li\u00eang"
    ],
    "wof:name":"Bu R'lieng",
    "wof:placetype":"locality"
},
  "geometry": {"coordinates":[107.18333,11.95],"type":"Point"}
}