{
  "type": "Feature",
  "properties": {
    "gn:admin1_code":"52.0",
    "gn:asciiname":"Phu Thuong",
    "gn:country_code":"VN",
    "gn:dem":12,
    "gn:feature_class":"P",
    "gn:feature_code":"PPL",
    "gn:name":"Ph\u00fa Th\u01b0\u1ee3ng",
    "gn:population":0,
    "gn:timezone":"Asia/Ho_Chi_Minh",
    "iso:country":"VN",
    "name:vie_x_preferred":[
        "Ph\u00fa Th\u01b0\u1ee3ng"
    ],
    "wof:name":"Phu Thuong",
    "wof:placetype":"locality"
},
  "geometry": {"coordinates":[106.26924,18.18298],"type":"Point"}
}