{
  "type": "Feature",
  "properties": {
    "gn:admin1_code":"50.0",
    "gn:asciiname":"Na Cha",
    "gn:country_code":"VN",
    "gn:dem":96,
    "gn:feature_class":"P",
    "gn:feature_code":"PPL",
    "gn:name":"N\u00e0 Ch\u00e0",
    "gn:population":0,
    "gn:timezone":"Asia/Ho_Chi_Minh",
    "iso:country":"VN",
    "name:vie_x_preferred":[
        "N\u00e0 Ch\u00e0"
    ],
    "wof:name":"Na Cha",
    "wof:placetype":"locality"
},
  "geometry": {"coordinates":[105.05776000000002,22.69045],"type":"Point"}
}