{
  "type": "Feature",
  "properties": {
    "gn:admin1_code":"52.0",
    "gn:asciiname":"Pho Chau",
    "gn:country_code":"VN",
    "gn:dem":17,
    "gn:feature_class":"P",
    "gn:feature_code":"PPLA2",
    "gn:name":"Ph\u1ed1 Ch\u00e2u",
    "gn:population":0,
    "gn:timezone":"Asia/Ho_Chi_Minh",
    "iso:country":"VN",
    "name:und_x_variant":[
        "Cho Pho",
        "Ph\u1ed1 Ch\u00e2u"
    ],
    "wof:name":"Pho Chau",
    "wof:placetype":"locality"
},
  "geometry": {"coordinates":[105.42411,18.51335],"type":"Point"}
}