{
  "type": "Feature",
  "properties": {
    "gn:admin1_code":"72.0",
    "gn:asciiname":"Bo Lung",
    "gn:country_code":"VN",
    "gn:dem":811,
    "gn:feature_class":"P",
    "gn:feature_code":"PPL",
    "gn:name":"Bo Lung",
    "gn:population":0,
    "gn:timezone":"Asia/Ho_Chi_Minh",
    "iso:country":"VN",
    "wof:name":"Bo Lung",
    "wof:placetype":"locality"
},
  "geometry": {"coordinates":[105.53333000000001,22.26667],"type":"Point"}
}