{
  "type": "Feature",
  "properties": {
    "gn:admin1_code":"90.0",
    "gn:asciiname":"Tinh Tia Tong",
    "gn:country_code":"VN",
    "gn:dem":609,
    "gn:feature_class":"P",
    "gn:feature_code":"PPL",
    "gn:name":"Tinh Tia Tong",
    "gn:population":0,
    "gn:timezone":"Asia/Ho_Chi_Minh",
    "iso:country":"VN",
    "name:und_x_variant":[
        "Tinh Tia",
        "Tinh Tia Tong"
    ],
    "wof:name":"Tinh Tia Tong",
    "wof:placetype":"locality"
},
  "geometry": {"coordinates":[104.16667,22.51667],"type":"Point"}
}