{
  "type": "Feature",
  "properties": {
    "gn:admin1_code":"67.0",
    "gn:asciiname":"Ap Long Thanh",
    "gn:cc2":"VN",
    "gn:country_code":"VN",
    "gn:dem":1,
    "gn:feature_class":"P",
    "gn:feature_code":"PPL",
    "gn:name":"\u1ea4p Long Th\u1ea1nh",
    "gn:population":0,
    "gn:timezone":"Asia/Ho_Chi_Minh",
    "iso:country":"VN",
    "name:und_x_variant":[
        "Long Th\u1ea1nh",
        "\u1ea4p Long Th\u1ea1nh"
    ],
    "wof:name":"Ap Long Thanh",
    "wof:placetype":"locality"
},
  "geometry": {"coordinates":[106.44889000000001,9.9125],"type":"Point"}
}