{
  "type": "Feature",
  "properties": {
    "gn:admin1_code":"79.0",
    "gn:asciiname":"Chuc Khe",
    "gn:country_code":"VN",
    "gn:dem":4,
    "gn:feature_class":"P",
    "gn:feature_code":"PPL",
    "gn:name":"Ch\u00fac Kh\u00ea",
    "gn:population":0,
    "gn:timezone":"Asia/Ho_Chi_Minh",
    "iso:country":"VN",
    "name:und_x_variant":[
        "Chue Khe",
        "Ch\u00fac Kh\u00ea"
    ],
    "wof:name":"Chuc Khe",
    "wof:placetype":"locality"
},
  "geometry": {"coordinates":[106.28333000000001,20.85],"type":"Point"}
}