{
  "type": "Feature",
  "properties": {
    "gn:admin1_code":"44.0",
    "gn:asciiname":"Tan My",
    "gn:country_code":"VN",
    "gn:dem":37,
    "gn:feature_class":"P",
    "gn:feature_code":"PPL",
    "gn:name":"T\u00e2n M\u1ef9",
    "gn:population":0,
    "gn:timezone":"Asia/Ho_Chi_Minh",
    "iso:country":"VN",
    "name:und_x_variant":[
        "T\u00e2n My",
        "\u1ea4p T\u00e2n My"
    ],
    "name:vie_x_preferred":[
        "T\u00e2n M\u1ef9"
    ],
    "wof:name":"Tan My",
    "wof:placetype":"locality"
},
  "geometry": {"coordinates":[105.31023999999999,21.05731],"type":"Point"}
}