{
  "type": "Feature",
  "properties": {
    "gn:admin1_code":"80.0",
    "gn:asciiname":"Minh Giang",
    "gn:country_code":"VN",
    "gn:dem":8,
    "gn:feature_class":"P",
    "gn:feature_code":"PPL",
    "gn:name":"Minh Giang",
    "gn:population":0,
    "gn:timezone":"Asia/Ho_Chi_Minh",
    "iso:country":"VN",
    "name:vie_x_preferred":[
        "Minh Giang"
    ],
    "wof:name":"Minh Giang",
    "wof:placetype":"locality"
},
  "geometry": {"coordinates":[106.01049999999999,20.6167],"type":"Point"}
}