{
  "type": "Feature",
  "properties": {
    "gn:admin1_code":"63.0",
    "gn:asciiname":"Tap An Nam",
    "gn:country_code":"VN",
    "gn:dem":8,
    "gn:feature_class":"P",
    "gn:feature_code":"PPL",
    "gn:name":"T\u1eadp An Nam",
    "gn:population":0,
    "gn:timezone":"Asia/Ho_Chi_Minh",
    "iso:country":"VN",
    "name:und_x_variant":[
        "Tinh Quang",
        "Tinh Qang",
        "T\u1eadp An Nam"
    ],
    "wof:name":"Tap An Nam",
    "wof:placetype":"locality"
},
  "geometry": {"coordinates":[108.93333,14.85],"type":"Point"}
}