{
  "type": "Feature",
  "properties": {
    "gn:admin1_code":"60.0",
    "gn:asciiname":"Pho Maa Lam",
    "gn:country_code":"VN",
    "gn:dem":498,
    "gn:feature_class":"P",
    "gn:feature_code":"PPL",
    "gn:name":"Pho Maa Lam",
    "gn:population":0,
    "gn:timezone":"Asia/Ho_Chi_Minh",
    "iso:country":"VN",
    "name:und_x_variant":[
        "Plei Maalam",
        "Maa Lam",
        "Pho Maa Lam"
    ],
    "wof:name":"Pho Maa Lam",
    "wof:placetype":"locality"
},
  "geometry": {"coordinates":[108.59999999999999,11.58333],"type":"Point"}
}