{
  "type": "Feature",
  "properties": {
    "gn:admin1_code":"23.0",
    "gn:asciiname":"Rhan Plang",
    "gn:country_code":"VN",
    "gn:dem":925,
    "gn:feature_class":"P",
    "gn:feature_code":"PPL",
    "gn:name":"Rhan Plang",
    "gn:population":0,
    "gn:timezone":"Asia/Ho_Chi_Minh",
    "iso:country":"VN",
    "wof:name":"Rhan Plang",
    "wof:placetype":"locality"
},
  "geometry": {"coordinates":[108.23333,11.58333],"type":"Point"}
}