{
  "type": "Feature",
  "properties": {
    "gn:admin1_code":"68.0",
    "gn:asciiname":"Na Ta",
    "gn:country_code":"VN",
    "gn:dem":615,
    "gn:feature_class":"P",
    "gn:feature_code":"PPL",
    "gn:name":"Na Ta",
    "gn:population":0,
    "gn:timezone":"Asia/Ho_Chi_Minh",
    "iso:country":"VN",
    "wof:name":"Na Ta",
    "wof:placetype":"locality"
},
  "geometry": {"coordinates":[105.51667,22.56667],"type":"Point"}
}