{
  "type": "Feature",
  "properties": {
    "gn:admin1_code":"32.0",
    "gn:asciiname":"Ban Na Doc",
    "gn:country_code":"VN",
    "gn:dem":781,
    "gn:feature_class":"P",
    "gn:feature_code":"PPL",
    "gn:name":"B\u1ea3n N\u00e0 \u0110\u1ed1c",
    "gn:population":0,
    "gn:timezone":"Asia/Ho_Chi_Minh",
    "iso:country":"VN",
    "name:vie_x_preferred":[
        "B\u1ea3n N\u00e0 \u0110\u1ed1c"
    ],
    "wof:name":"Ban Na Doc",
    "wof:placetype":"locality"
},
  "geometry": {"coordinates":[103.58243,21.50476],"type":"Point"}
}