{
  "type": "Feature",
  "properties": {
    "gn:admin1_code":"66.0",
    "gn:asciiname":"Phong Dien",
    "gn:country_code":"VN",
    "gn:dem":14,
    "gn:feature_class":"P",
    "gn:feature_code":"PPLA2",
    "gn:name":"Phong \u0110i\u1ec1n",
    "gn:population":0,
    "gn:timezone":"Asia/Ho_Chi_Minh",
    "iso:country":"VN",
    "name:vie_x_preferred":[
        "Phong \u0110i\u1ec1n"
    ],
    "wof:name":"Phong Dien",
    "wof:placetype":"locality"
},
  "geometry": {"coordinates":[107.36438,16.58321],"type":"Point"}
}