{
  "type": "Feature",
  "properties": {
    "gn:admin1_code":"67.0",
    "gn:asciiname":"Ap Nhi",
    "gn:country_code":"VN",
    "gn:dem":4,
    "gn:feature_class":"P",
    "gn:feature_code":"PPL",
    "gn:name":"\u1ea4p Nh\u00ec",
    "gn:population":0,
    "gn:timezone":"Asia/Ho_Chi_Minh",
    "iso:country":"VN",
    "name:und_x_variant":[
        "Nhi",
        "\u1ea4p Nhi"
    ],
    "name:vie_x_preferred":[
        "\u1ea4p Nh\u00ec"
    ],
    "wof:name":"Ap Nhi",
    "wof:placetype":"locality"
},
  "geometry": {"coordinates":[106.22996000000001,9.79502],"type":"Point"}
}