{
  "type": "Feature",
  "properties": {
    "gn:admin1_code":"26.0",
    "gn:asciiname":"Kieu Linh",
    "gn:country_code":"VN",
    "gn:dem":0,
    "gn:feature_class":"P",
    "gn:feature_code":"PPL",
    "gn:name":"Kieu Linh",
    "gn:population":0,
    "gn:timezone":"Asia/Ho_Chi_Minh",
    "iso:country":"VN",
    "name:und_x_variant":[
        "\u0110an Ph\u00f4"
    ],
    "wof:name":"Kieu Linh",
    "wof:placetype":"locality"
},
  "geometry": {"coordinates":[105.76667,18.68333],"type":"Point"}
}