{
  "type": "Feature",
  "properties": {
    "gn:admin1_code":"88.0",
    "gn:asciiname":"Doan Ket",
    "gn:country_code":"VN",
    "gn:dem":426,
    "gn:feature_class":"P",
    "gn:feature_code":"PPL",
    "gn:name":"\u0110o\u00e0n K\u1ebft",
    "gn:population":0,
    "gn:timezone":"Asia/Ho_Chi_Minh",
    "iso:country":"VN",
    "name:vie_x_preferred":[
        "\u0110o\u00e0n K\u1ebft"
    ],
    "wof:name":"Doan Ket",
    "wof:placetype":"locality"
},
  "geometry": {"coordinates":[108.17467000000001,12.39768],"type":"Point"}
}