{
  "type": "Feature",
  "properties": {
    "gn:admin1_code":"59.0",
    "gn:asciiname":"Giai Co",
    "gn:country_code":"VN",
    "gn:dem":7,
    "gn:feature_class":"P",
    "gn:feature_code":"PPL",
    "gn:name":"Gi\u1ea3i C\u1edd",
    "gn:population":0,
    "gn:timezone":"Asia/Ho_Chi_Minh",
    "iso:country":"VN",
    "name:vie_x_preferred":[
        "Gi\u1ea3i C\u1edd"
    ],
    "wof:name":"Giai Co",
    "wof:placetype":"locality"
},
  "geometry": {"coordinates":[105.95131000000001,20.10924],"type":"Point"}
}