{
  "type": "Feature",
  "properties": {
    "gn:admin1_code":"92.0",
    "gn:asciiname":"Na Ngua",
    "gn:country_code":"VN",
    "gn:dem":533,
    "gn:feature_class":"P",
    "gn:feature_code":"PPL",
    "gn:name":"Na Ngua",
    "gn:population":0,
    "gn:timezone":"Asia/Ho_Chi_Minh",
    "iso:country":"VN",
    "name:und_x_variant":[
        "Ban Na Ngua",
        "Na Ngua"
    ],
    "wof:name":"Na Ngua",
    "wof:placetype":"locality"
},
  "geometry": {"coordinates":[103.40000000000001,21.23333],"type":"Point"}
}