{
  "type": "Feature",
  "properties": {
    "gn:admin1_code":"83.0",
    "gn:asciiname":"Cong Hoa",
    "gn:country_code":"VN",
    "gn:dem":35,
    "gn:feature_class":"P",
    "gn:feature_code":"PPLL",
    "gn:name":"C\u00f4ng Hoa",
    "gn:population":0,
    "gn:timezone":"Asia/Ho_Chi_Minh",
    "iso:country":"VN",
    "name:vie_x_preferred":[
        "C\u00f4ng Hoa"
    ],
    "wof:name":"Cong Hoa",
    "wof:placetype":"locality"
},
  "geometry": {"coordinates":[105.01076999999999,21.56954],"type":"Point"}
}