{
  "type": "Feature",
  "properties": {
    "gn:admin1_code":"20.0",
    "gn:asciiname":"Khom Bay",
    "gn:country_code":"VN",
    "gn:dem":6,
    "gn:feature_class":"P",
    "gn:feature_code":"PPL",
    "gn:name":"Kh\u00f3m B\u1ea3y",
    "gn:population":0,
    "gn:timezone":"Asia/Ho_Chi_Minh",
    "iso:country":"VN",
    "name:vie_x_preferred":[
        "Kh\u00f3m B\u1ea3y"
    ],
    "name:vie_x_variant":[
        "Kh\u00f3m 7"
    ],
    "wof:name":"Khom Bay",
    "wof:placetype":"locality"
},
  "geometry": {"coordinates":[106.62108000000001,10.7796],"type":"Point"}
}