{
  "type": "Feature",
  "properties": {
    "gn:admin1_code":"71.0",
    "gn:asciiname":"Ap Sau",
    "gn:country_code":"VN",
    "gn:dem":21,
    "gn:feature_class":"P",
    "gn:feature_code":"PPL",
    "gn:name":"\u1ea4p S\u1eadu",
    "gn:population":0,
    "gn:timezone":"Asia/Ho_Chi_Minh",
    "iso:country":"VN",
    "name:vie_x_preferred":[
        "\u1ea4p S\u1eadu"
    ],
    "wof:name":"Ap Sau",
    "wof:placetype":"locality"
},
  "geometry": {"coordinates":[106.06220999999999,21.43583],"type":"Point"}
}