{
  "type": "Feature",
  "properties": {
    "gn:admin1_code":"78.0",
    "gn:asciiname":"Son Tra",
    "gn:country_code":"VN",
    "gn:dem":8,
    "gn:feature_class":"P",
    "gn:feature_code":"PPLA2",
    "gn:name":"S\u01a1n Tr\u00e0",
    "gn:population":0,
    "gn:timezone":"Asia/Ho_Chi_Minh",
    "iso:country":"VN",
    "name:vie_x_preferred":[
        "S\u01a1n Tr\u00e0"
    ],
    "wof:name":"Son Tra",
    "wof:placetype":"locality"
},
  "geometry": {"coordinates":[108.23256000000001,16.06068],"type":"Point"}
}