{
  "type": "Feature",
  "properties": {
    "gn:admin1_code":"32.0",
    "gn:asciiname":"Tieu Khu Nam",
    "gn:country_code":"VN",
    "gn:dem":528,
    "gn:feature_class":"P",
    "gn:feature_code":"PPL",
    "gn:name":"Ti\u1ec3u Khu N\u0103m",
    "gn:population":0,
    "gn:timezone":"Asia/Ho_Chi_Minh",
    "iso:country":"VN",
    "name:vie_x_preferred":[
        "Ti\u1ec3u Khu N\u0103m"
    ],
    "name:vie_x_variant":[
        "Ti\u1ec3u Khu 5"
    ],
    "wof:name":"Tieu Khu Nam",
    "wof:placetype":"locality"
},
  "geometry": {"coordinates":[104.10084000000001,21.19913],"type":"Point"}
}