{
  "type": "Feature",
  "properties": {
    "gn:admin1_code":"1.0",
    "gn:asciiname":"Hoa Phu Mot",
    "gn:country_code":"VN",
    "gn:dem":2,
    "gn:feature_class":"P",
    "gn:feature_code":"PPL",
    "gn:name":"H\u00f2a Ph\u00fa M\u1ed9t",
    "gn:population":0,
    "gn:timezone":"Asia/Ho_Chi_Minh",
    "iso:country":"VN",
    "name:vie_x_preferred":[
        "H\u00f2a Ph\u00fa M\u1ed9t"
    ],
    "name:vie_x_variant":[
        "H\u00f2a Ph\u00fa 1"
    ],
    "wof:name":"Hoa Phu Mot",
    "wof:placetype":"locality"
},
  "geometry": {"coordinates":[105.39949,10.43611],"type":"Point"}
}