{
  "type": "Feature",
  "properties": {
    "gn:admin1_code":"88.0",
    "gn:asciiname":"Dia Diem Dinh Dien Buon Kuang",
    "gn:country_code":"VN",
    "gn:dem":666,
    "gn:feature_class":"P",
    "gn:feature_code":"PPL",
    "gn:name":"\u0110\u1ecba \u0110i\u1ec3m Dinh \u0110i\u1ec1n Bu\u00f4n Ku\u0103ng",
    "gn:population":0,
    "gn:timezone":"Asia/Ho_Chi_Minh",
    "iso:country":"VN",
    "wof:name":"Dia Diem Dinh Dien Buon Kuang",
    "wof:placetype":"locality"
},
  "geometry": {"coordinates":[108.23333,12.78333],"type":"Point"}
}