{
  "type": "Feature",
  "properties": {
    "gn:admin1_code":"74.0",
    "gn:asciiname":"Nghia La",
    "gn:country_code":"VN",
    "gn:dem":5,
    "gn:feature_class":"P",
    "gn:feature_code":"PPL",
    "gn:name":"Ngh\u0129a L\u1ea1",
    "gn:population":0,
    "gn:timezone":"Asia/Ho_Chi_Minh",
    "iso:country":"VN",
    "name:vie_x_preferred":[
        "Ngh\u0129a L\u1ea1"
    ],
    "wof:name":"Nghia La",
    "wof:placetype":"locality"
},
  "geometry": {"coordinates":[106.23777,21.00487],"type":"Point"}
}