{
  "type": "Feature",
  "properties": {
    "gn:admin1_code":"88.0",
    "gn:asciiname":"Thon Muoi Sau",
    "gn:country_code":"VN",
    "gn:dem":475,
    "gn:feature_class":"P",
    "gn:feature_code":"PPL",
    "gn:name":"Th\u00f4n M\u01b0\u1eddi S\u00e1u",
    "gn:population":0,
    "gn:timezone":"Asia/Ho_Chi_Minh",
    "iso:country":"VN",
    "name:vie_x_preferred":[
        "Th\u00f4n M\u01b0\u1eddi S\u00e1u"
    ],
    "name:vie_x_variant":[
        "Th\u00f4n 16"
    ],
    "wof:name":"Thon Muoi Sau",
    "wof:placetype":"locality"
},
  "geometry": {"coordinates":[108.60841000000001,12.74611],"type":"Point"}
}