{
  "type": "Feature",
  "properties": {
    "gn:admin1_code":"88.0",
    "gn:asciiname":"Buon Gam",
    "gn:country_code":"VN",
    "gn:dem":417,
    "gn:feature_class":"P",
    "gn:feature_code":"PPL",
    "gn:name":"Bu\u00f4n G\u0103m",
    "gn:population":0,
    "gn:timezone":"Asia/Ho_Chi_Minh",
    "iso:country":"VN",
    "name:vie_x_preferred":[
        "Bu\u00f4n G\u0103m"
    ],
    "wof:name":"Buon Gam",
    "wof:placetype":"locality"
},
  "geometry": {"coordinates":[108.72933999999999,12.76027],"type":"Point"}
}