{
  "type": "Feature",
  "properties": {
    "gn:admin1_code":"71.0",
    "gn:asciiname":"Kim Son",
    "gn:country_code":"VN",
    "gn:dem":21,
    "gn:feature_class":"P",
    "gn:feature_code":"PPL",
    "gn:name":"Kim S\u01a1n",
    "gn:population":0,
    "gn:timezone":"Asia/Ho_Chi_Minh",
    "iso:country":"VN",
    "name:vie_x_preferred":[
        "Kim S\u01a1n"
    ],
    "wof:name":"Kim Son",
    "wof:placetype":"locality"
},
  "geometry": {"coordinates":[106.24908000000001,21.35814],"type":"Point"}
}