{
  "type": "Feature",
  "properties": {
    "gn:admin1_code":"81.0",
    "gn:asciiname":"Phuc Mieu",
    "gn:country_code":"VN",
    "gn:dem":5,
    "gn:feature_class":"P",
    "gn:feature_code":"PPL",
    "gn:name":"Ph\u00fac Mi\u1ebfu",
    "gn:population":0,
    "gn:timezone":"Asia/Ho_Chi_Minh",
    "iso:country":"VN",
    "name:vie_x_preferred":[
        "Ph\u00fac Mi\u1ebfu"
    ],
    "wof:name":"Phuc Mieu",
    "wof:placetype":"locality"
},
  "geometry": {"coordinates":[106.14695,20.93932],"type":"Point"}
}