{
  "type": "Feature",
  "properties": {
    "gn:admin1_code":"74.0",
    "gn:asciiname":"Ba Khe",
    "gn:country_code":"VN",
    "gn:dem":6,
    "gn:feature_class":"P",
    "gn:feature_code":"PPL",
    "gn:name":"B\u00e0 Kh\u00ea",
    "gn:population":0,
    "gn:timezone":"Asia/Ho_Chi_Minh",
    "iso:country":"VN",
    "name:und_x_variant":[
        "B\u00e1 Kh\u1ec1"
    ],
    "name:vie_x_preferred":[
        "B\u00e0 Kh\u00ea"
    ],
    "wof:name":"Ba Khe",
    "wof:placetype":"locality"
},
  "geometry": {"coordinates":[106.2441,21.05731],"type":"Point"}
}