{
  "type": "Feature",
  "properties": {
    "gn:admin1_code":"90.0",
    "gn:asciiname":"Khu Chu Din",
    "gn:country_code":"VN",
    "gn:dem":1078,
    "gn:feature_class":"P",
    "gn:feature_code":"PPL",
    "gn:name":"Khu Chu D\u00ecn",
    "gn:population":0,
    "gn:timezone":"Asia/Ho_Chi_Minh",
    "iso:country":"VN",
    "name:vie_x_preferred":[
        "Khu Chu D\u00ecn"
    ],
    "wof:name":"Khu Chu Din",
    "wof:placetype":"locality"
},
  "geometry": {"coordinates":[103.65644,22.56504],"type":"Point"}
}