{
  "type": "Feature",
  "properties": {
    "gn:admin1_code":"34.0",
    "gn:asciiname":"Dong Lam",
    "gn:country_code":"VN",
    "gn:dem":50,
    "gn:feature_class":"P",
    "gn:feature_code":"PPL",
    "gn:name":"\u0110\u1ed3ng L\u1ea9m",
    "gn:population":0,
    "gn:timezone":"Asia/Ho_Chi_Minh",
    "iso:country":"VN",
    "name:vie_x_preferred":[
        "\u0110\u1ed3ng L\u1ea9m"
    ],
    "wof:name":"Dong Lam",
    "wof:placetype":"locality"
},
  "geometry": {"coordinates":[105.60742999999999,19.49282],"type":"Point"}
}