{
  "type": "Feature",
  "properties": {
    "gn:admin1_code":"34.0",
    "gn:asciiname":"Nghi Son",
    "gn:cc2":"VN",
    "gn:country_code":"VN",
    "gn:dem":-9999,
    "gn:feature_class":"P",
    "gn:feature_code":"PPL",
    "gn:name":"Nghi S\u01a1n",
    "gn:population":0,
    "gn:timezone":"Asia/Ho_Chi_Minh",
    "iso:country":"VN",
    "name:und_x_variant":[
        "Bien Son",
        "Nghi S\u01a1n"
    ],
    "wof:name":"Nghi Son",
    "wof:placetype":"locality"
},
  "geometry": {"coordinates":[105.83333,19.33333],"type":"Point"}
}