{
  "type": "Feature",
  "properties": {
    "gn:admin1_code":"68.0",
    "gn:asciiname":"Ban Na Dua",
    "gn:country_code":"VN",
    "gn:dem":215,
    "gn:feature_class":"P",
    "gn:feature_code":"PPL",
    "gn:name":"B\u1ea3n N\u00e0 \u0110\u1ee9a",
    "gn:population":0,
    "gn:timezone":"Asia/Ho_Chi_Minh",
    "iso:country":"VN",
    "name:vie_x_preferred":[
        "N\u00e0 \u0110\u1ee9a"
    ],
    "name:vie_x_variant":[
        "B\u1ea3n N\u00e0 \u0110\u1ee9a"
    ],
    "wof:name":"Ban Na Dua",
    "wof:placetype":"locality"
},
  "geometry": {"coordinates":[105.33709,22.52093],"type":"Point"}
}