{
  "type": "Feature",
  "properties": {
    "gn:admin1_code":"77.0",
    "gn:asciiname":"Xom Cai Muoi",
    "gn:country_code":"VN",
    "gn:dem":4,
    "gn:feature_class":"P",
    "gn:feature_code":"PPL",
    "gn:name":"X\u00f3m C\u00e1i Mu\u00f4i",
    "gn:population":0,
    "gn:timezone":"Asia/Ho_Chi_Minh",
    "iso:country":"VN",
    "name:und_x_variant":[
        "Cai Muoi",
        "X\u00f3m C\u00e1i Mu\u00f4i"
    ],
    "wof:name":"Xom Cai Muoi",
    "wof:placetype":"locality"
},
  "geometry": {"coordinates":[105.03333000000001,8.88333],"type":"Point"}
}