{
  "type": "Feature",
  "properties": {
    "gn:admin1_code":"23.0",
    "gn:asciiname":"Dinh An",
    "gn:country_code":"VN",
    "gn:dem":1116,
    "gn:feature_class":"P",
    "gn:feature_code":"PPL",
    "gn:name":"\u0110inh An",
    "gn:population":0,
    "gn:timezone":"Asia/Ho_Chi_Minh",
    "iso:country":"VN",
    "wof:name":"Dinh An",
    "wof:placetype":"locality"
},
  "geometry": {"coordinates":[108.46666999999999,11.83333],"type":"Point"}
}