{
  "type": "Feature",
  "properties": {
    "gn:admin1_code":"70.0",
    "gn:asciiname":"Khe Dong",
    "gn:country_code":"VN",
    "gn:dem":459,
    "gn:feature_class":"P",
    "gn:feature_code":"PPL",
    "gn:name":"Khe \u0110\u1ecfng",
    "gn:population":0,
    "gn:timezone":"Asia/Ho_Chi_Minh",
    "iso:country":"VN",
    "name:und_x_variant":[
        "Kh\u00ea D\u00f3m"
    ],
    "name:vie_x_preferred":[
        "Khe \u0110\u1ecfng"
    ],
    "wof:name":"Khe Dong",
    "wof:placetype":"locality"
},
  "geometry": {"coordinates":[104.49065,21.86678],"type":"Point"}
}