{
  "type": "Feature",
  "properties": {
    "gn:admin1_code":"44.0",
    "gn:asciiname":"Ngoc Lam",
    "gn:country_code":"VN",
    "gn:dem":4,
    "gn:feature_class":"P",
    "gn:feature_code":"PPL",
    "gn:name":"Ng\u1ecdc L\u00e2m",
    "gn:population":0,
    "gn:timezone":"Asia/Ho_Chi_Minh",
    "iso:country":"VN",
    "name:und_x_variant":[
        "Cau Ca",
        "Ng\u1ecdc L\u00e2m"
    ],
    "wof:name":"Ngoc Lam",
    "wof:placetype":"locality"
},
  "geometry": {"coordinates":[105.86667,21.03333],"type":"Point"}
}