{
  "type": "Feature",
  "properties": {
    "gn:admin1_code":"93.0",
    "gn:asciiname":"Phu Tri B Mot",
    "gn:country_code":"VN",
    "gn:dem":3,
    "gn:feature_class":"P",
    "gn:feature_code":"PPL",
    "gn:name":"Ph\u00fa Tr\u00ed B M\u1ed9t",
    "gn:population":0,
    "gn:timezone":"Asia/Ho_Chi_Minh",
    "iso:country":"VN",
    "name:vie_x_preferred":[
        "Ph\u00fa Tr\u00ed B M\u1ed9t"
    ],
    "name:vie_x_variant":[
        "Ph\u00fa Tr\u00ed B1"
    ],
    "wof:name":"Phu Tri B Mot",
    "wof:placetype":"locality"
},
  "geometry": {"coordinates":[105.82639,9.89862],"type":"Point"}
}