{
  "type": "Feature",
  "properties": {
    "gn:admin1_code":"73.0",
    "gn:asciiname":"Gia Rai",
    "gn:cc2":"VN",
    "gn:country_code":"VN",
    "gn:dem":4,
    "gn:feature_class":"P",
    "gn:feature_code":"PPL",
    "gn:name":"Gi\u00e1 Rai",
    "gn:population":0,
    "gn:timezone":"Asia/Ho_Chi_Minh",
    "iso:country":"VN",
    "name:und_x_variant":[
        "Xom Gia Rai",
        "Gi\u00e1 Rai"
    ],
    "wof:name":"Gia Rai",
    "wof:placetype":"locality"
},
  "geometry": {"coordinates":[105.45833,9.23444],"type":"Point"}
}