{
  "type": "Feature",
  "properties": {
    "gn:admin1_code":"23.0",
    "gn:asciiname":"Buon Pi Ko",
    "gn:country_code":"VN",
    "gn:dem":498,
    "gn:feature_class":"P",
    "gn:feature_code":"PPL",
    "gn:name":"Bu\u00f4n Pi K\u00f4",
    "gn:population":0,
    "gn:timezone":"Asia/Ho_Chi_Minh",
    "iso:country":"VN",
    "name:und_x_variant":[
        "Bon Phi Ko",
        "Ban Peco",
        "Ban Phi Ko",
        "Bon Pi Ko"
    ],
    "name:vie_x_preferred":[
        "Pi K\u00f3"
    ],
    "name:vie_x_variant":[
        "Bu\u00f4n Pi K\u00f4"
    ],
    "wof:name":"Buon Pi Ko",
    "wof:placetype":"locality"
},
  "geometry": {"coordinates":[108.12585,12.17225],"type":"Point"}
}