{
  "type": "Feature",
  "properties": {
    "gn:admin1_code":"70.0",
    "gn:asciiname":"Dong Det",
    "gn:country_code":"VN",
    "gn:dem":49,
    "gn:feature_class":"P",
    "gn:feature_code":"PPL",
    "gn:name":"\u0110\u1ed3ng Det",
    "gn:population":0,
    "gn:timezone":"Asia/Ho_Chi_Minh",
    "iso:country":"VN",
    "name:vie_x_preferred":[
        "\u0110\u1ed3ng Det"
    ],
    "wof:name":"Dong Det",
    "wof:placetype":"locality"
},
  "geometry": {"coordinates":[104.60044000000001,21.94564],"type":"Point"}
}