{
  "type": "Feature",
  "properties": {
    "gn:admin1_code":"53.0",
    "gn:asciiname":"Lam Liu",
    "gn:country_code":"VN",
    "gn:dem":712,
    "gn:feature_class":"P",
    "gn:feature_code":"PPL",
    "gn:name":"L\u00e0m Liu",
    "gn:population":0,
    "gn:timezone":"Asia/Ho_Chi_Minh",
    "iso:country":"VN",
    "wof:name":"Lam Liu",
    "wof:placetype":"locality"
},
  "geometry": {"coordinates":[105.15000000000001,20.65],"type":"Point"}
}