{
  "type": "Feature",
  "properties": {
    "gn:admin1_code":"20.0",
    "gn:asciiname":"Xom Rach Da",
    "gn:country_code":"VN",
    "gn:dem":3,
    "gn:feature_class":"P",
    "gn:feature_code":"PPL",
    "gn:name":"X\u00f3m R\u1ea1ch \u0110\u00e1",
    "gn:population":0,
    "gn:timezone":"Asia/Ho_Chi_Minh",
    "iso:country":"VN",
    "wof:name":"Xom Rach Da",
    "wof:placetype":"locality"
},
  "geometry": {"coordinates":[106.71666999999999,10.83333],"type":"Point"}
}