{
  "type": "Feature",
  "properties": {
    "gn:admin1_code":"6.0",
    "gn:asciiname":"Ap Dong Thanh Thuong",
    "gn:country_code":"VN",
    "gn:dem":0,
    "gn:feature_class":"P",
    "gn:feature_code":"PPL",
    "gn:name":"\u1ea4p \u0110\u00f4ng Th\u00e0nh Th\u01b0\u1ee3ng",
    "gn:population":0,
    "gn:timezone":"Asia/Ho_Chi_Minh",
    "iso:country":"VN",
    "wof:name":"Ap Dong Thanh Thuong",
    "wof:placetype":"locality"
},
  "geometry": {"coordinates":[106.03333000000001,10.25],"type":"Point"}
}