{
  "type": "Feature",
  "properties": {
    "gn:admin1_code":"32.0",
    "gn:asciiname":"Na Nga",
    "gn:country_code":"VN",
    "gn:dem":266,
    "gn:feature_class":"P",
    "gn:feature_code":"PPL",
    "gn:name":"N\u00e0 Nga",
    "gn:population":0,
    "gn:timezone":"Asia/Ho_Chi_Minh",
    "iso:country":"VN",
    "name:vie_x_preferred":[
        "N\u00e0 Nga"
    ],
    "name:vie_x_variant":[
        "B\u1ea3n Na Nga"
    ],
    "wof:name":"Na Nga",
    "wof:placetype":"locality"
},
  "geometry": {"coordinates":[104.38052,21.01655],"type":"Point"}
}