{
  "type": "Feature",
  "properties": {
    "gn:admin1_code":"67.0",
    "gn:asciiname":"Ap Lac Hoa",
    "gn:cc2":"VN",
    "gn:country_code":"VN",
    "gn:dem":1,
    "gn:feature_class":"P",
    "gn:feature_code":"PPL",
    "gn:name":"\u1ea4p L\u1ea1c H\u00f2a",
    "gn:population":0,
    "gn:timezone":"Asia/Ho_Chi_Minh",
    "iso:country":"VN",
    "name:und_x_variant":[
        "L\u1ea1c H\u00f2a",
        "\u1ea4p L\u1ea1c H\u00f2a"
    ],
    "wof:name":"Ap Lac Hoa",
    "wof:placetype":"locality"
},
  "geometry": {"coordinates":[106.46972,9.70556],"type":"Point"}
}