{
  "type": "Feature",
  "properties": {
    "gn:admin1_code":"70.0",
    "gn:asciiname":"Tan An",
    "gn:country_code":"VN",
    "gn:dem":55,
    "gn:feature_class":"P",
    "gn:feature_code":"PPL",
    "gn:name":"T\u00e2n An",
    "gn:population":0,
    "gn:timezone":"Asia/Ho_Chi_Minh",
    "iso:country":"VN",
    "name:vie_x_preferred":[
        "T\u00e2n An"
    ],
    "wof:name":"Tan An",
    "wof:placetype":"locality"
},
  "geometry": {"coordinates":[104.64382000000001,21.85887],"type":"Point"}
}