{
  "type": "Feature",
  "properties": {
    "gn:admin1_code":"61.0",
    "gn:asciiname":"Tuy Luat Hoa",
    "gn:country_code":"VN",
    "gn:dem":30,
    "gn:feature_class":"P",
    "gn:feature_code":"PPL",
    "gn:name":"Tuy Lu\u1eadt H\u00f2a",
    "gn:population":0,
    "gn:timezone":"Asia/Ho_Chi_Minh",
    "iso:country":"VN",
    "name:und_x_variant":[
        "Gia Ngoi",
        "Tuy Lu\u1eadt H\u00f2a"
    ],
    "wof:name":"Tuy Luat Hoa",
    "wof:placetype":"locality"
},
  "geometry": {"coordinates":[109.25,13.51667],"type":"Point"}
}