{
  "type": "Feature",
  "properties": {
    "gn:admin1_code":"23.0",
    "gn:asciiname":"Noseri",
    "gn:country_code":"VN",
    "gn:dem":749,
    "gn:feature_class":"P",
    "gn:feature_code":"PPL",
    "gn:name":"Noseri",
    "gn:population":0,
    "gn:timezone":"Asia/Ho_Chi_Minh",
    "iso:country":"VN",
    "wof:name":"Noseri",
    "wof:placetype":"locality"
},
  "geometry": {"coordinates":[107.86667,11.51667],"type":"Point"}
}