{
  "type": "Feature",
  "properties": {
    "gn:admin1_code":"50.0",
    "gn:asciiname":"Sin Soi Ho",
    "gn:country_code":"VN",
    "gn:dem":447,
    "gn:feature_class":"P",
    "gn:feature_code":"PPL",
    "gn:name":"S\u00edn S\u1ecfi H\u1ed3",
    "gn:population":0,
    "gn:timezone":"Asia/Ho_Chi_Minh",
    "iso:country":"VN",
    "name:vie_x_preferred":[
        "S\u00edn S\u1ecfi H\u1ed3"
    ],
    "wof:name":"Sin Soi Ho",
    "wof:placetype":"locality"
},
  "geometry": {"coordinates":[105.02434,23.11636],"type":"Point"}
}