{
  "type": "Feature",
  "properties": {
    "gn:admin1_code":"90.0",
    "gn:asciiname":"Ban Phinh Dong",
    "gn:country_code":"VN",
    "gn:dem":552,
    "gn:feature_class":"P",
    "gn:feature_code":"PPL",
    "gn:name":"B\u1ea3n Phinh \u0110\u00f3ng",
    "gn:population":0,
    "gn:timezone":"Asia/Ho_Chi_Minh",
    "iso:country":"VN",
    "name:vie_x_preferred":[
        "B\u1ea3n Phinh \u0110\u00f3ng"
    ],
    "wof:name":"Ban Phinh Dong",
    "wof:placetype":"locality"
},
  "geometry": {"coordinates":[104.08257,21.97432],"type":"Point"}
}