{
  "type": "Feature",
  "properties": {
    "gn:admin1_code":"83.0",
    "gn:asciiname":"Minh Tan",
    "gn:country_code":"VN",
    "gn:dem":109,
    "gn:feature_class":"P",
    "gn:feature_code":"PPL",
    "gn:name":"Minh T\u00e2n",
    "gn:population":0,
    "gn:timezone":"Asia/Ho_Chi_Minh",
    "iso:country":"VN",
    "name:vie_x_preferred":[
        "Minh T\u00e2n"
    ],
    "wof:name":"Minh Tan",
    "wof:placetype":"locality"
},
  "geometry": {"coordinates":[105.06279000000001,21.2815],"type":"Point"}
}