{
  "type": "Feature",
  "properties": {
    "gn:admin1_code":"58.0",
    "gn:asciiname":"Kim Nguyen",
    "gn:country_code":"VN",
    "gn:dem":6,
    "gn:feature_class":"P",
    "gn:feature_code":"PPL",
    "gn:name":"Kim Nguy\u00ean",
    "gn:population":0,
    "gn:timezone":"Asia/Ho_Chi_Minh",
    "iso:country":"VN",
    "name:ara_x_preferred":[
        "\u0643\u064a\u0645 \u0646\u062c\u0648\u064a\u0646"
    ],
    "name:deu_x_preferred":[
        "Kim Nguyen"
    ],
    "name:fas_x_preferred":[
        "\u06a9\u06cc\u0645 \u0646\u06af\u0648\u06cc\u0646"
    ],
    "name:fra_x_preferred":[
        "Kim Nguyen"
    ],
    "name:ind_x_preferred":[
        "Kim Nguyen"
    ],
    "name:ita_x_preferred":[
        "Kim Nguyen"
    ],
    "name:jpn_x_preferred":[
        "\u30ad\u30e0\u30fb\u30b0\u30a8\u30f3"
    ],
    "name:por_x_preferred":[
        "Kim Nguyen"
    ],
    "name:spa_x_preferred":[
        "Kim Nguyen"
    ],
    "wof:name":"Kim Nguyen",
    "wof:placetype":"locality"
},
  "geometry": {"coordinates":[105.65000000000001,18.75],"type":"Point"}
}