{
  "type": "Feature",
  "properties": {
    "gn:admin1_code":"68.0",
    "gn:asciiname":"Minh Tan",
    "gn:country_code":"VN",
    "gn:dem":84,
    "gn:feature_class":"P",
    "gn:feature_code":"PPL",
    "gn:name":"Minh T\u00e2n",
    "gn:population":0,
    "gn:timezone":"Asia/Ho_Chi_Minh",
    "iso:country":"VN",
    "name:vie_x_preferred":[
        "Minh T\u00e2n"
    ],
    "wof:name":"Minh Tan",
    "wof:placetype":"locality"
},
  "geometry": {"coordinates":[105.21382,22.18603],"type":"Point"}
}