{
  "type": "Feature",
  "properties": {
    "gn:admin1_code":"5.0",
    "gn:asciiname":"Cay Tac",
    "gn:country_code":"VN",
    "gn:dem":938,
    "gn:feature_class":"P",
    "gn:feature_code":"PPL",
    "gn:name":"C\u00e1y T\u1eafc",
    "gn:population":0,
    "gn:timezone":"Asia/Ho_Chi_Minh",
    "iso:country":"VN",
    "wof:name":"Cay Tac",
    "wof:placetype":"locality"
},
  "geometry": {"coordinates":[106.08333,22.98333],"type":"Point"}
}