{
  "type": "Feature",
  "properties": {
    "gn:admin1_code":"2.0",
    "gn:asciiname":"Tam Pong",
    "gn:cc2":"VN",
    "gn:country_code":"VN",
    "gn:dem":636,
    "gn:feature_class":"P",
    "gn:feature_code":"PPL",
    "gn:name":"Tam Pong",
    "gn:population":0,
    "gn:timezone":"Asia/Ho_Chi_Minh",
    "iso:country":"VN",
    "name:und_x_variant":[
        "Tam Pon",
        "Tam Pong"
    ],
    "wof:name":"Tam Pong",
    "wof:placetype":"locality"
},
  "geometry": {"coordinates":[105.76667,22.23333],"type":"Point"}
}