{
  "type": "Feature",
  "properties": {
    "gn:admin1_code":"52.0",
    "gn:asciiname":"Xom Bay",
    "gn:country_code":"VN",
    "gn:dem":11,
    "gn:feature_class":"P",
    "gn:feature_code":"PPL",
    "gn:name":"X\u00f3m B\u1ea3y",
    "gn:population":0,
    "gn:timezone":"Asia/Ho_Chi_Minh",
    "iso:country":"VN",
    "name:vie_x_preferred":[
        "X\u00f3m B\u1ea3y"
    ],
    "name:vie_x_variant":[
        "X\u00f3m 7"
    ],
    "wof:name":"Xom Bay",
    "wof:placetype":"locality"
},
  "geometry": {"coordinates":[105.81679,18.37241],"type":"Point"}
}