{
  "type": "Feature",
  "properties": {
    "gn:admin1_code":"68.0",
    "gn:asciiname":"Lang Chua",
    "gn:country_code":"VN",
    "gn:dem":144,
    "gn:feature_class":"P",
    "gn:feature_code":"PPL",
    "gn:name":"L\u00e0ng Ch\u00faa",
    "gn:population":0,
    "gn:timezone":"Asia/Ho_Chi_Minh",
    "iso:country":"VN",
    "name:vie_x_preferred":[
        "L\u00e0ng Ch\u00faa"
    ],
    "wof:name":"Lang Chua",
    "wof:placetype":"locality"
},
  "geometry": {"coordinates":[105.11506,22.34552],"type":"Point"}
}