{
  "type": "Feature",
  "properties": {
    "gn:admin1_code":"84.0",
    "gn:asciiname":"Vieu",
    "gn:country_code":"VN",
    "gn:dem":395,
    "gn:feature_class":"P",
    "gn:feature_code":"PPL",
    "gn:name":"Vi\u00eau",
    "gn:population":0,
    "gn:timezone":"Asia/Ho_Chi_Minh",
    "iso:country":"VN",
    "name:ara_x_preferred":[
        "\u0641\u064a\u0648"
    ],
    "name:bug_x_preferred":[
        "Vieu"
    ],
    "name:cat_x_preferred":[
        "Vieu"
    ],
    "name:ceb_x_preferred":[
        "Vieu"
    ],
    "name:deu_x_preferred":[
        "Vieu"
    ],
    "name:eus_x_preferred":[
        "Vieu"
    ],
    "name:fas_x_preferred":[
        "\u0648\u06cc\u0648"
    ],
    "name:fra_x_preferred":[
        "Vieu"
    ],
    "name:frp_x_preferred":[
        "Viu"
    ],
    "name:glg_x_preferred":[
        "Vieu"
    ],
    "name:hun_x_preferred":[
        "Vieu"
    ],
    "name:hye_x_preferred":[
        "\u054e\u0575\u0578"
    ],
    "name:ind_x_preferred":[
        "Vieu"
    ],
    "name:ita_x_preferred":[
        "Vieu"
    ],
    "name:lat_x_preferred":[
        "Vieu"
    ],
    "name:lmo_x_preferred":[
        "Vieu"
    ],
    "name:ltz_x_preferred":[
        "Vieu"
    ],
    "name:msa_x_preferred":[
        "Vieu"
    ],
    "name:nld_x_preferred":[
        "Vieu"
    ],
    "name:oci_x_preferred":[
        "Vieu"
    ],
    "name:pol_x_preferred":[
        "Vieu"
    ],
    "name:por_x_preferred":[
        "Vieu"
    ],
    "name:ron_x_preferred":[
        "Vieu"
    ],
    "name:rus_x_preferred":[
        "\u0412\u044c\u0451"
    ],
    "name:slk_x_preferred":[
        "Vieu"
    ],
    "name:spa_x_preferred":[
        "Vieu"
    ],
    "name:swe_x_preferred":[
        "Vieu"
    ],
    "name:tgl_x_preferred":[
        "Vieu"
    ],
    "name:ukr_x_preferred":[
        "\u0412'\u0454"
    ],
    "name:uzb_x_preferred":[
        "Vieu"
    ],
    "name:vie_x_preferred":[
        "Vieu"
    ],
    "name:vol_x_preferred":[
        "Vieu"
    ],
    "name:war_x_preferred":[
        "Vieu"
    ],
    "name:zea_x_preferred":[
        "Vieu"
    ],
    "wof:name":"Vieu",
    "wof:placetype":"locality"
},
  "geometry": {"coordinates":[107.83333,15.91667],"type":"Point"}
}