{
  "type": "Feature",
  "properties": {
    "gn:admin1_code":"43.0",
    "gn:asciiname":"Khu Muoi Bon",
    "gn:country_code":"VN",
    "gn:dem":18,
    "gn:feature_class":"P",
    "gn:feature_code":"PPL",
    "gn:name":"Khu M\u01b0\u1eddi B\u1ed1n",
    "gn:population":0,
    "gn:timezone":"Asia/Ho_Chi_Minh",
    "iso:country":"VN",
    "name:vie_x_preferred":[
        "Khu M\u01b0\u1eddi B\u1ed1n"
    ],
    "name:vie_x_variant":[
        "Khu 14"
    ],
    "wof:name":"Khu Muoi Bon",
    "wof:placetype":"locality"
},
  "geometry": {"coordinates":[106.95645,10.81096],"type":"Point"}
}