{
  "type": "Feature",
  "properties": {
    "gn:admin1_code":"32.0",
    "gn:asciiname":"Ban Hoc",
    "gn:country_code":"VN",
    "gn:dem":451,
    "gn:feature_class":"P",
    "gn:feature_code":"PPL",
    "gn:name":"B\u1ea3n H\u1ed1c",
    "gn:population":0,
    "gn:timezone":"Asia/Ho_Chi_Minh",
    "iso:country":"VN",
    "name:vie_x_preferred":[
        "B\u1ea3n H\u1ed1c"
    ],
    "wof:name":"Ban Hoc",
    "wof:placetype":"locality"
},
  "geometry": {"coordinates":[104.06372,21.56355],"type":"Point"}
}