{
  "type": "Feature",
  "properties": {
    "gn:admin1_code":"47.0",
    "gn:asciiname":"Tan Long",
    "gn:country_code":"VN",
    "gn:dem":14,
    "gn:feature_class":"P",
    "gn:feature_code":"PPL",
    "gn:name":"T\u00e2n Long",
    "gn:population":0,
    "gn:timezone":"Asia/Ho_Chi_Minh",
    "iso:country":"VN",
    "name:ara_x_preferred":[
        "\u062a\u0627\u0646 \u0644\u0648\u0646\u063a"
    ],
    "name:cat_x_preferred":[
        "Tan Long"
    ],
    "name:spa_x_preferred":[
        "Tan Long"
    ],
    "name:vie_x_preferred":[
        "T\u00e2n Long"
    ],
    "wof:name":"Tan Long",
    "wof:placetype":"locality"
},
  "geometry": {"coordinates":[107.78107,10.66183],"type":"Point"}
}