{
  "type": "Feature",
  "properties": {
    "gn:admin1_code":"68.0",
    "gn:asciiname":"An Thach",
    "gn:country_code":"VN",
    "gn:dem":64,
    "gn:feature_class":"P",
    "gn:feature_code":"PPL",
    "gn:name":"An Th\u1ea1ch",
    "gn:population":0,
    "gn:timezone":"Asia/Ho_Chi_Minh",
    "iso:country":"VN",
    "name:vie_x_preferred":[
        "An Th\u1ea1ch"
    ],
    "wof:name":"An Thach",
    "wof:placetype":"locality"
},
  "geometry": {"coordinates":[105.11178999999998,22.02737],"type":"Point"}
}