{
  "type": "Feature",
  "properties": {
    "gn:admin1_code":"70.0",
    "gn:asciiname":"Hoi Dau",
    "gn:country_code":"VN",
    "gn:dem":68,
    "gn:feature_class":"P",
    "gn:feature_code":"PPL",
    "gn:name":"H\u1ed9i D\u00e2u",
    "gn:population":0,
    "gn:timezone":"Asia/Ho_Chi_Minh",
    "iso:country":"VN",
    "name:und_x_variant":[
        "\u0110oi Hoi",
        "Hoi \u0110\u00e2u"
    ],
    "name:vie_x_preferred":[
        "H\u1ed9i D\u00e2u"
    ],
    "wof:name":"Hoi Dau",
    "wof:placetype":"locality"
},
  "geometry": {"coordinates":[104.87822,21.86361],"type":"Point"}
}