{
  "type": "Feature",
  "properties": {
    "gn:admin1_code":"50.0",
    "gn:asciiname":"Nam Hin",
    "gn:country_code":"VN",
    "gn:dem":530,
    "gn:feature_class":"P",
    "gn:feature_code":"PPL",
    "gn:name":"Nam Hin",
    "gn:population":0,
    "gn:timezone":"Asia/Ho_Chi_Minh",
    "iso:country":"VN",
    "name:vie_x_preferred":[
        "Nam Hin"
    ],
    "wof:name":"Nam Hin",
    "wof:placetype":"locality"
},
  "geometry": {"coordinates":[105.37264,22.64842],"type":"Point"}
}