{
  "type": "Feature",
  "properties": {
    "gn:admin1_code":"58.0",
    "gn:asciiname":"Ban Dom",
    "gn:country_code":"VN",
    "gn:dem":298,
    "gn:feature_class":"P",
    "gn:feature_code":"PPL",
    "gn:name":"B\u1ea3n \u0110\u00f4m",
    "gn:population":0,
    "gn:timezone":"Asia/Ho_Chi_Minh",
    "iso:country":"VN",
    "name:vie_x_preferred":[
        "B\u1ea3n \u0110\u00f4m"
    ],
    "wof:name":"Ban Dom",
    "wof:placetype":"locality"
},
  "geometry": {"coordinates":[105.05298999999999,19.46712],"type":"Point"}
}