{
  "type": "Feature",
  "properties": {
    "gn:admin1_code":"35.0",
    "gn:asciiname":"Dong Hoang",
    "gn:country_code":"VN",
    "gn:dem":-9999,
    "gn:feature_class":"P",
    "gn:feature_code":"PPL",
    "gn:name":"\u0110\u00f4ng Hoang",
    "gn:population":0,
    "gn:timezone":"Asia/Ho_Chi_Minh",
    "iso:country":"VN",
    "wof:name":"Dong Hoang",
    "wof:placetype":"locality"
},
  "geometry": {"coordinates":[106.59999999999999,20.41667],"type":"Point"}
}