{
  "type": "Feature",
  "properties": {
    "gn:admin1_code":"50.0",
    "gn:asciiname":"Ban Phinh Rao",
    "gn:country_code":"VN",
    "gn:dem":740,
    "gn:feature_class":"P",
    "gn:feature_code":"PPL",
    "gn:name":"B\u1ea3n Phinh Rao",
    "gn:population":0,
    "gn:timezone":"Asia/Ho_Chi_Minh",
    "iso:country":"VN",
    "name:vie_x_preferred":[
        "B\u1ea3n Phinh Rao"
    ],
    "wof:name":"Ban Phinh Rao",
    "wof:placetype":"locality"
},
  "geometry": {"coordinates":[105.3252,22.94944],"type":"Point"}
}