{
  "type": "Feature",
  "properties": {
    "gn:admin1_code":"88.0",
    "gn:asciiname":"Buon Cam",
    "gn:country_code":"VN",
    "gn:dem":424,
    "gn:feature_class":"P",
    "gn:feature_code":"PPL",
    "gn:name":"Bu\u00f4n Cam",
    "gn:population":0,
    "gn:timezone":"Asia/Ho_Chi_Minh",
    "iso:country":"VN",
    "name:vie_x_preferred":[
        "Bu\u00f4n Cam"
    ],
    "wof:name":"Buon Cam",
    "wof:placetype":"locality"
},
  "geometry": {"coordinates":[108.14116,12.40087],"type":"Point"}
}