{
  "type": "Feature",
  "properties": {
    "gn:admin1_code":"50.0",
    "gn:asciiname":"Vo Lang",
    "gn:country_code":"VN",
    "gn:dem":132,
    "gn:feature_class":"P",
    "gn:feature_code":"PPL",
    "gn:name":"V\u00f4 Lang",
    "gn:population":0,
    "gn:timezone":"Asia/Ho_Chi_Minh",
    "iso:country":"VN",
    "wof:name":"Vo Lang",
    "wof:placetype":"locality"
},
  "geometry": {"coordinates":[104.63333,22.36667000000001],"type":"Point"}
}