{
  "type": "Feature",
  "properties": {
    "gn:admin1_code":"89.0",
    "gn:asciiname":"Ban Khang Kha",
    "gn:country_code":"VN",
    "gn:dem":1164,
    "gn:feature_class":"P",
    "gn:feature_code":"PPL",
    "gn:name":"B\u1ea3n Kh\u1eb1ng Kh\u00e0",
    "gn:population":0,
    "gn:timezone":"Asia/Ho_Chi_Minh",
    "iso:country":"VN",
    "wof:name":"Ban Khang Kha",
    "wof:placetype":"locality"
},
  "geometry": {"coordinates":[102.48333,22.73333],"type":"Point"}
}