{
  "type": "Feature",
  "properties": {
    "gn:admin1_code":"65.0",
    "gn:asciiname":"Ap Ta Bien B",
    "gn:country_code":"VN",
    "gn:dem":2,
    "gn:feature_class":"P",
    "gn:feature_code":"PPL",
    "gn:name":"\u1ea4p T\u1ea3 Bi\u00ean B",
    "gn:population":0,
    "gn:timezone":"Asia/Ho_Chi_Minh",
    "iso:country":"VN",
    "name:und_x_variant":[
        "Dai Sour",
        "\u1ea4p T\u1ea3 Bi\u00ean B"
    ],
    "wof:name":"Ap Ta Bien B",
    "wof:placetype":"locality"
},
  "geometry": {"coordinates":[105.86667,9.53333],"type":"Point"}
}