{
  "type": "Feature",
  "properties": {
    "gn:admin1_code":"65.0",
    "gn:asciiname":"Ta Diep C Mot",
    "gn:country_code":"VN",
    "gn:dem":4,
    "gn:feature_class":"P",
    "gn:feature_code":"PPL",
    "gn:name":"T\u00e0 Di\u1ebfp C M\u1ed9t",
    "gn:population":0,
    "gn:timezone":"Asia/Ho_Chi_Minh",
    "iso:country":"VN",
    "name:vie_x_preferred":[
        "T\u00e0 Di\u1ebfp C M\u1ed9t"
    ],
    "name:vie_x_variant":[
        "T\u00e0 Di\u1ebfp C1"
    ],
    "wof:name":"Ta Diep C Mot",
    "wof:placetype":"locality"
},
  "geometry": {"coordinates":[105.71827,9.46331],"type":"Point"}
}