{
  "type": "Feature",
  "properties": {
    "gn:admin1_code":"84.0",
    "gn:asciiname":"Phu Son",
    "gn:country_code":"VN",
    "gn:dem":67,
    "gn:feature_class":"P",
    "gn:feature_code":"PPL",
    "gn:name":"Ph\u00fa S\u01a1n",
    "gn:population":0,
    "gn:timezone":"Asia/Ho_Chi_Minh",
    "iso:country":"VN",
    "name:vie_x_preferred":[
        "Ph\u00fa S\u01a1n"
    ],
    "name:vie_x_variant":[
        "Ph\u00fa Nh\u01a1n"
    ],
    "wof:name":"Phu Son",
    "wof:placetype":"locality"
},
  "geometry": {"coordinates":[108.11628,15.52138],"type":"Point"}
}