{
  "type": "Feature",
  "properties": {
    "gn:admin1_code":"32.0",
    "gn:asciiname":"Ban Co Phat",
    "gn:country_code":"VN",
    "gn:dem":765,
    "gn:feature_class":"P",
    "gn:feature_code":"PPL",
    "gn:name":"B\u1ea3n Co Ph\u00e1t",
    "gn:population":0,
    "gn:timezone":"Asia/Ho_Chi_Minh",
    "iso:country":"VN",
    "name:vie_x_preferred":[
        "B\u1ea3n Co Ph\u00e1t"
    ],
    "wof:name":"Ban Co Phat",
    "wof:placetype":"locality"
},
  "geometry": {"coordinates":[103.82536,21.05232],"type":"Point"}
}