{
  "type": "Feature",
  "properties": {
    "gn:admin1_code":"74.0",
    "gn:asciiname":"An Phu",
    "gn:country_code":"VN",
    "gn:dem":10,
    "gn:feature_class":"P",
    "gn:feature_code":"PPL",
    "gn:name":"\u00c2n Ph\u00fa",
    "gn:population":0,
    "gn:timezone":"Asia/Ho_Chi_Minh",
    "iso:country":"VN",
    "name:vie_x_preferred":[
        "\u00c2n Ph\u00fa"
    ],
    "wof:name":"An Phu",
    "wof:placetype":"locality"
},
  "geometry": {"coordinates":[105.98071000000002,21.16921],"type":"Point"}
}