{
  "type": "Feature",
  "properties": {
    "gn:admin1_code":"76.0",
    "gn:asciiname":"Taptak",
    "gn:country_code":"VN",
    "gn:dem":216,
    "gn:feature_class":"P",
    "gn:feature_code":"PPL",
    "gn:name":"Taptak",
    "gn:population":0,
    "gn:timezone":"Asia/Ho_Chi_Minh",
    "iso:country":"VN",
    "name:und_x_variant":[
        "Tapak",
        "Taptak"
    ],
    "wof:name":"Taptak",
    "wof:placetype":"locality"
},
  "geometry": {"coordinates":[107.11667,11.76667],"type":"Point"}
}