{
  "type": "Feature",
  "properties": {
    "gn:admin1_code":"89.0",
    "gn:asciiname":"Ban Lo Ma",
    "gn:country_code":"VN",
    "gn:dem":810,
    "gn:feature_class":"P",
    "gn:feature_code":"PPL",
    "gn:name":"B\u1ea3n L\u00f3 Ma",
    "gn:population":0,
    "gn:timezone":"Asia/Ho_Chi_Minh",
    "iso:country":"VN",
    "wof:name":"Ban Lo Ma",
    "wof:placetype":"locality"
},
  "geometry": {"coordinates":[102.45,22.65],"type":"Point"}
}