{
  "type": "Feature",
  "properties": {
    "gn:admin1_code":"92.0",
    "gn:asciiname":"Khua Tra",
    "gn:country_code":"VN",
    "gn:dem":758,
    "gn:feature_class":"P",
    "gn:feature_code":"PPL",
    "gn:name":"Khua Tra",
    "gn:population":0,
    "gn:timezone":"Asia/Ho_Chi_Minh",
    "iso:country":"VN",
    "name:vie_x_preferred":[
        "Khua Tra"
    ],
    "wof:name":"Khua Tra",
    "wof:placetype":"locality"
},
  "geometry": {"coordinates":[103.48884,21.8315],"type":"Point"}
}