{
  "type": "Feature",
  "properties": {
    "gn:admin1_code":"72.0",
    "gn:asciiname":"Thom An",
    "gn:country_code":"VN",
    "gn:dem":812,
    "gn:feature_class":"P",
    "gn:feature_code":"PPL",
    "gn:name":"Th\u00f4m \u00c1n",
    "gn:population":0,
    "gn:timezone":"Asia/Ho_Chi_Minh",
    "iso:country":"VN",
    "wof:name":"Thom An",
    "wof:placetype":"locality"
},
  "geometry": {"coordinates":[105.94573,22.34166],"type":"Point"}
}