{
  "type": "Feature",
  "properties": {
    "gn:admin1_code":"52.0",
    "gn:asciiname":"Xuan Phuong",
    "gn:country_code":"VN",
    "gn:dem":7,
    "gn:feature_class":"P",
    "gn:feature_code":"PPL",
    "gn:name":"Xu\u00e2n Ph\u01b0\u1ee3ng",
    "gn:population":0,
    "gn:timezone":"Asia/Ho_Chi_Minh",
    "iso:country":"VN",
    "name:vie_x_preferred":[
        "Xu\u00e2n Ph\u01b0\u1ee3ng"
    ],
    "wof:name":"Xuan Phuong",
    "wof:placetype":"locality"
},
  "geometry": {"coordinates":[105.91732,18.45779],"type":"Point"}
}