{
  "type": "Feature",
  "properties": {
    "gn:admin1_code":"58.0",
    "gn:asciiname":"Xom Dinh",
    "gn:country_code":"VN",
    "gn:dem":8,
    "gn:feature_class":"P",
    "gn:feature_code":"PPL",
    "gn:name":"X\u00f3m \u0110\u00ecnh",
    "gn:population":0,
    "gn:timezone":"Asia/Ho_Chi_Minh",
    "iso:country":"VN",
    "name:vie_x_preferred":[
        "X\u00f3m \u0110\u00ecnh"
    ],
    "wof:name":"Xom Dinh",
    "wof:placetype":"locality"
},
  "geometry": {"coordinates":[105.55504999999999,19.02425],"type":"Point"}
}