{
  "type": "Feature",
  "properties": {
    "gn:admin1_code":"45.0",
    "gn:asciiname":"Xa An Ngai",
    "gn:country_code":"VN",
    "gn:dem":5,
    "gn:feature_class":"P",
    "gn:feature_code":"PPL",
    "gn:name":"X\u00e3 An Ng\u00e3i",
    "gn:population":0,
    "gn:timezone":"Asia/Ho_Chi_Minh",
    "iso:country":"VN",
    "name:und_x_variant":[
        "An Ngai",
        "X\u00e3 An Ng\u00e3i"
    ],
    "wof:name":"Xa An Ngai",
    "wof:placetype":"locality"
},
  "geometry": {"coordinates":[107.23333,10.48333],"type":"Point"}
}