{
  "type": "Feature",
  "properties": {
    "gn:admin1_code":"88.0",
    "gn:asciiname":"Chu Ka Nao",
    "gn:country_code":"VN",
    "gn:dem":426,
    "gn:feature_class":"P",
    "gn:feature_code":"PPL",
    "gn:name":"Ch\u01b0 Ka Nao",
    "gn:population":0,
    "gn:timezone":"Asia/Ho_Chi_Minh",
    "iso:country":"VN",
    "name:vie_x_preferred":[
        "Ch\u01b0 Ka Nao"
    ],
    "wof:name":"Chu Ka Nao",
    "wof:placetype":"locality"
},
  "geometry": {"coordinates":[108.23932000000001,12.54086],"type":"Point"}
}