{
  "type": "Feature",
  "properties": {
    "gn:admin1_code":"88.0",
    "gn:asciiname":"Ban Tir",
    "gn:country_code":"VN",
    "gn:dem":575,
    "gn:feature_class":"P",
    "gn:feature_code":"PPL",
    "gn:name":"Ban Tir",
    "gn:population":0,
    "gn:timezone":"Asia/Ho_Chi_Minh",
    "iso:country":"VN",
    "name:und_x_variant":[
        "Buon Tir",
        "Ban Tir"
    ],
    "wof:name":"Ban Tir",
    "wof:placetype":"locality"
},
  "geometry": {"coordinates":[108.25,13.25],"type":"Point"}
}