{
  "type": "Feature",
  "properties": {
    "gn:admin1_code":"60.0",
    "gn:asciiname":"Da Mai Tren",
    "gn:country_code":"VN",
    "gn:dem":87,
    "gn:feature_class":"P",
    "gn:feature_code":"PPL",
    "gn:name":"\u0110\u00e1 M\u00e0i Tr\u00ean",
    "gn:population":0,
    "gn:timezone":"Asia/Ho_Chi_Minh",
    "iso:country":"VN",
    "name:vie_x_preferred":[
        "\u0110\u00e1 M\u00e0i Tr\u00ean"
    ],
    "wof:name":"Da Mai Tren",
    "wof:placetype":"locality"
},
  "geometry": {"coordinates":[109.02127,11.73193],"type":"Point"}
}