{
  "type": "Feature",
  "properties": {
    "gn:admin1_code":"32.0",
    "gn:asciiname":"Pou Houk",
    "gn:country_code":"VN",
    "gn:dem":1097,
    "gn:feature_class":"P",
    "gn:feature_code":"PPL",
    "gn:name":"Pou Houk",
    "gn:population":0,
    "gn:timezone":"Asia/Ho_Chi_Minh",
    "iso:country":"VN",
    "wof:name":"Pou Houk",
    "wof:placetype":"locality"
},
  "geometry": {"coordinates":[104.28333000000001,21.65],"type":"Point"}
}