{
  "type": "Feature",
  "properties": {
    "gn:admin1_code":"13.0",
    "gn:asciiname":"Minh Chau",
    "gn:country_code":"VN",
    "gn:dem":121,
    "gn:feature_class":"P",
    "gn:feature_code":"PPL",
    "gn:name":"Minh Ch\u00e2u",
    "gn:population":0,
    "gn:timezone":"Asia/Ho_Chi_Minh",
    "iso:country":"VN",
    "name:vie_x_preferred":[
        "Minh Ch\u00e2u"
    ],
    "wof:name":"Minh Chau",
    "wof:placetype":"locality"
},
  "geometry": {"coordinates":[107.00894,20.76167],"type":"Point"}
}