{
  "type": "Feature",
  "properties": {
    "gn:admin1_code":"93.0",
    "gn:asciiname":"Xom Tra Ban Nho",
    "gn:country_code":"VN",
    "gn:dem":5,
    "gn:feature_class":"P",
    "gn:feature_code":"PPL",
    "gn:name":"X\u00f3m Tr\u00e0 Ban Nh\u1ecf",
    "gn:population":0,
    "gn:timezone":"Asia/Ho_Chi_Minh",
    "iso:country":"VN",
    "wof:name":"Xom Tra Ban Nho",
    "wof:placetype":"locality"
},
  "geometry": {"coordinates":[105.58278,9.6175],"type":"Point"}
}