{
  "type": "Feature",
  "properties": {
    "gn:admin1_code":"46.0",
    "gn:asciiname":"Tai Luong",
    "gn:country_code":"VN",
    "gn:dem":13,
    "gn:feature_class":"P",
    "gn:feature_code":"PPL",
    "gn:name":"T\u00e0i L\u01b0\u01a1ng",
    "gn:population":0,
    "gn:timezone":"Asia/Ho_Chi_Minh",
    "iso:country":"VN",
    "name:und_x_variant":[
        "T\u00e1i L\u01b0\u01a1ng"
    ],
    "name:vie_x_preferred":[
        "T\u00e0i L\u01b0\u01a1ng"
    ],
    "wof:name":"Tai Luong",
    "wof:placetype":"locality"
},
  "geometry": {"coordinates":[109.03807999999999,14.4978],"type":"Point"}
}