{
  "type": "Feature",
  "properties": {
    "gn:admin1_code":"83.0",
    "gn:asciiname":"A Mai",
    "gn:country_code":"VN",
    "gn:dem":79,
    "gn:feature_class":"P",
    "gn:feature_code":"PPL",
    "gn:name":"A Mai",
    "gn:population":0,
    "gn:timezone":"Asia/Ho_Chi_Minh",
    "iso:country":"VN",
    "name:und_x_variant":[
        "\u1ea4p Mai",
        "A Mai"
    ],
    "wof:name":"A Mai",
    "wof:placetype":"locality"
},
  "geometry": {"coordinates":[104.95,21.55],"type":"Point"}
}