{
  "type": "Feature",
  "properties": {
    "gn:admin1_code":"79.0",
    "gn:asciiname":"Co Menh",
    "gn:country_code":"VN",
    "gn:dem":21,
    "gn:feature_class":"P",
    "gn:feature_code":"PPL",
    "gn:name":"C\u1ed5 M\u1ec7nh",
    "gn:population":0,
    "gn:timezone":"Asia/Ho_Chi_Minh",
    "iso:country":"VN",
    "name:und_x_variant":[
        "Co Nlanh",
        "C\u1ed5 Manh"
    ],
    "name:vie_x_preferred":[
        "C\u1ed5 M\u1ec7nh"
    ],
    "wof:name":"Co Menh",
    "wof:placetype":"locality"
},
  "geometry": {"coordinates":[106.42613,21.19147],"type":"Point"}
}