{
  "type": "Feature",
  "properties": {
    "gn:admin1_code":"72.0",
    "gn:asciiname":"Khau Chu",
    "gn:country_code":"VN",
    "gn:dem":324,
    "gn:feature_class":"P",
    "gn:feature_code":"PPL",
    "gn:name":"Khau Chu",
    "gn:population":0,
    "gn:timezone":"Asia/Ho_Chi_Minh",
    "iso:country":"VN",
    "name:und_x_variant":[
        "Khao Tiou"
    ],
    "name:vie_x_preferred":[
        "Khau Chu"
    ],
    "wof:name":"Khau Chu",
    "wof:placetype":"locality"
},
  "geometry": {"coordinates":[105.66779,22.14243],"type":"Point"}
}