{
  "type": "Feature",
  "properties": {
    "gn:admin1_code":"32.0",
    "gn:asciiname":"Ban Hat Do",
    "gn:country_code":"VN",
    "gn:dem":315,
    "gn:feature_class":"P",
    "gn:feature_code":"PPL",
    "gn:name":"B\u1ea3n H\u00e1t D\u1ecd",
    "gn:population":0,
    "gn:timezone":"Asia/Ho_Chi_Minh",
    "iso:country":"VN",
    "name:vie_x_preferred":[
        "B\u1ea3n H\u00e1t D\u1ecd"
    ],
    "wof:name":"Ban Hat Do",
    "wof:placetype":"locality"
},
  "geometry": {"coordinates":[103.71727,21.65766],"type":"Point"}
}