{
  "type": "Feature",
  "properties": {
    "gn:admin1_code":"39.0",
    "gn:asciiname":"Po Som",
    "gn:country_code":"VN",
    "gn:dem":406,
    "gn:feature_class":"P",
    "gn:feature_code":"PPL",
    "gn:name":"Po Som",
    "gn:population":0,
    "gn:timezone":"Asia/Ho_Chi_Minh",
    "iso:country":"VN",
    "wof:name":"Po Som",
    "wof:placetype":"locality"
},
  "geometry": {"coordinates":[106.56667,22.31667],"type":"Point"}
}