{
  "type": "Feature",
  "properties": {
    "gn:admin1_code":"46.0",
    "gn:asciiname":"Phu Ninh",
    "gn:country_code":"VN",
    "gn:dem":30,
    "gn:feature_class":"P",
    "gn:feature_code":"PPL",
    "gn:name":"Ph\u00fa Ninh",
    "gn:population":0,
    "gn:timezone":"Asia/Ho_Chi_Minh",
    "iso:country":"VN",
    "name:vie_x_preferred":[
        "Ph\u00fa Ninh"
    ],
    "wof:name":"Phu Ninh",
    "wof:placetype":"locality"
},
  "geometry": {"coordinates":[108.89588000000001,14.25943],"type":"Point"}
}