{
  "type": "Feature",
  "properties": {
    "gn:admin1_code":"80.0",
    "gn:asciiname":"Mau Chu",
    "gn:country_code":"VN",
    "gn:dem":6,
    "gn:feature_class":"P",
    "gn:feature_code":"PPL",
    "gn:name":"M\u1eadu Ch\u1eed",
    "gn:population":0,
    "gn:timezone":"Asia/Ho_Chi_Minh",
    "iso:country":"VN",
    "name:und_x_variant":[
        "M\u1ea1o Ch\u1eed"
    ],
    "name:vie_x_preferred":[
        "M\u1eadu Ch\u1eed"
    ],
    "wof:name":"Mau Chu",
    "wof:placetype":"locality"
},
  "geometry": {"coordinates":[105.91849999999999,20.51155],"type":"Point"}
}