{
  "type": "Feature",
  "properties": {
    "gn:admin1_code":"39.0",
    "gn:asciiname":"Ban Can",
    "gn:country_code":"VN",
    "gn:dem":188,
    "gn:feature_class":"P",
    "gn:feature_code":"PPL",
    "gn:name":"B\u1ea3n C\u1ea5n",
    "gn:population":0,
    "gn:timezone":"Asia/Ho_Chi_Minh",
    "iso:country":"VN",
    "name:und_x_variant":[
        "B\u1ea3n C\u1ea5n",
        "B\u1ea3n Keun"
    ],
    "wof:name":"Ban Can",
    "wof:placetype":"locality"
},
  "geometry": {"coordinates":[106.55594000000001,22.07252],"type":"Point"}
}