{
  "type": "Feature",
  "properties": {
    "gn:admin1_code":"71.0",
    "gn:asciiname":"Doi Chua",
    "gn:country_code":"VN",
    "gn:dem":19,
    "gn:feature_class":"P",
    "gn:feature_code":"PPL",
    "gn:name":"\u0110\u1ed3i Ch\u00f9a",
    "gn:population":0,
    "gn:timezone":"Asia/Ho_Chi_Minh",
    "iso:country":"VN",
    "name:vie_x_preferred":[
        "\u0110\u1ed3i Ch\u00f9a"
    ],
    "wof:name":"Doi Chua",
    "wof:placetype":"locality"
},
  "geometry": {"coordinates":[106.10133999999999,21.34175],"type":"Point"}
}