{
  "type": "Feature",
  "properties": {
    "gn:admin1_code":"50.0",
    "gn:asciiname":"Lung Vai",
    "gn:country_code":"VN",
    "gn:dem":151,
    "gn:feature_class":"P",
    "gn:feature_code":"PPL",
    "gn:name":"L\u0169ng Vai",
    "gn:population":0,
    "gn:timezone":"Asia/Ho_Chi_Minh",
    "iso:country":"VN",
    "name:vie_x_preferred":[
        "L\u0169ng Vai"
    ],
    "wof:name":"Lung Vai",
    "wof:placetype":"locality"
},
  "geometry": {"coordinates":[105.04723,22.58809],"type":"Point"}
}