{
  "type": "Feature",
  "properties": {
    "gn:admin1_code":"90.0",
    "gn:asciiname":"Su Man Khang",
    "gn:country_code":"VN",
    "gn:dem":1473,
    "gn:feature_class":"P",
    "gn:feature_code":"PPL",
    "gn:name":"S\u1ee9 M\u1ea7n Khang",
    "gn:population":0,
    "gn:timezone":"Asia/Ho_Chi_Minh",
    "iso:country":"VN",
    "name:vie_x_preferred":[
        "S\u1ee9 M\u1ea7n Khang"
    ],
    "wof:name":"Su Man Khang",
    "wof:placetype":"locality"
},
  "geometry": {"coordinates":[104.26560000000001,22.58564],"type":"Point"}
}