{
  "type": "Feature",
  "properties": {
    "gn:admin1_code":"72.0",
    "gn:asciiname":"Coi Sieu",
    "gn:country_code":"VN",
    "gn:dem":169,
    "gn:feature_class":"P",
    "gn:feature_code":"PPL",
    "gn:name":"C\u00f2i Si\u1ec3u",
    "gn:population":0,
    "gn:timezone":"Asia/Ho_Chi_Minh",
    "iso:country":"VN",
    "wof:name":"Coi Sieu",
    "wof:placetype":"locality"
},
  "geometry": {"coordinates":[105.77755000000001,22.46104],"type":"Point"}
}