{
  "type": "Feature",
  "properties": {
    "gn:admin1_code":"58.0",
    "gn:asciiname":"Ban Mai",
    "gn:country_code":"VN",
    "gn:dem":113,
    "gn:feature_class":"P",
    "gn:feature_code":"PPL",
    "gn:name":"B\u1ea3n Mai",
    "gn:population":0,
    "gn:timezone":"Asia/Ho_Chi_Minh",
    "iso:country":"VN",
    "name:und_x_variant":[
        "Lang Noi",
        "B\u1ea3n Mai"
    ],
    "wof:name":"Ban Mai",
    "wof:placetype":"locality"
},
  "geometry": {"coordinates":[105.15000000000001,19.56667],"type":"Point"}
}