{
  "type": "Feature",
  "properties": {
    "gn:admin1_code":"68.0",
    "gn:asciiname":"Dung Vi",
    "gn:country_code":"VN",
    "gn:dem":67,
    "gn:feature_class":"P",
    "gn:feature_code":"PPL",
    "gn:name":"D\u0169ng Vi",
    "gn:population":0,
    "gn:timezone":"Asia/Ho_Chi_Minh",
    "iso:country":"VN",
    "wof:name":"Dung Vi",
    "wof:placetype":"locality"
},
  "geometry": {"coordinates":[105.43333,21.53333],"type":"Point"}
}