{
  "type": "Feature",
  "properties": {
    "gn:admin1_code":"54.0",
    "gn:asciiname":"Khanh Xuan",
    "gn:country_code":"VN",
    "gn:dem":16,
    "gn:feature_class":"P",
    "gn:feature_code":"PPL",
    "gn:name":"Kh\u00e1nh Xu\u00e2n",
    "gn:population":0,
    "gn:timezone":"Asia/Ho_Chi_Minh",
    "iso:country":"VN",
    "name:und_x_variant":[
        "Th\u00f4n Kh\u00e1nh Xu\u00e2n"
    ],
    "name:vie_x_preferred":[
        "Kh\u00e1nh Xu\u00e2n"
    ],
    "wof:name":"Khanh Xuan",
    "wof:placetype":"locality"
},
  "geometry": {"coordinates":[109.00422,12.30199],"type":"Point"}
}