{
  "type": "Feature",
  "properties": {
    "gn:admin1_code":"23.0",
    "gn:asciiname":"Da Krone",
    "gn:cc2":"VN",
    "gn:country_code":"VN",
    "gn:dem":920,
    "gn:feature_class":"P",
    "gn:feature_code":"PPL",
    "gn:name":"Da Krone",
    "gn:population":0,
    "gn:timezone":"Asia/Ho_Chi_Minh",
    "iso:country":"VN",
    "name:und_x_variant":[
        "Tia Kreum",
        "Da Krone"
    ],
    "wof:name":"Da Krone",
    "wof:placetype":"locality"
},
  "geometry": {"coordinates":[108.45,11.56667],"type":"Point"}
}