{
  "type": "Feature",
  "properties": {
    "gn:admin1_code":"32.0",
    "gn:asciiname":"Ban Bac Uon",
    "gn:country_code":"VN",
    "gn:dem":276,
    "gn:feature_class":"P",
    "gn:feature_code":"PPL",
    "gn:name":"B\u1ea3n B\u1eafc U\u00f4n",
    "gn:population":0,
    "gn:timezone":"Asia/Ho_Chi_Minh",
    "iso:country":"VN",
    "name:vie_x_preferred":[
        "B\u1eafc U\u00f4n"
    ],
    "name:vie_x_variant":[
        "B\u1ea3n B\u1eafc U\u00f4n"
    ],
    "wof:name":"Ban Bac Uon",
    "wof:placetype":"locality"
},
  "geometry": {"coordinates":[103.62209,21.68101],"type":"Point"}
}