{
  "type": "Feature",
  "properties": {
    "gn:admin1_code":"89.0",
    "gn:asciiname":"Ban Chung Ban",
    "gn:country_code":"VN",
    "gn:dem":460,
    "gn:feature_class":"P",
    "gn:feature_code":"PPL",
    "gn:name":"B\u1ea3n Chung Ban",
    "gn:population":0,
    "gn:timezone":"Asia/Ho_Chi_Minh",
    "iso:country":"VN",
    "wof:name":"Ban Chung Ban",
    "wof:placetype":"locality"
},
  "geometry": {"coordinates":[103.86667,21.86667000000001],"type":"Point"}
}