{
  "type": "Feature",
  "properties": {
    "gn:admin1_code":"53.0",
    "gn:asciiname":"Que Cu",
    "gn:country_code":"VN",
    "gn:dem":97,
    "gn:feature_class":"P",
    "gn:feature_code":"PPL",
    "gn:name":"Qu\u00e8 C\u00f9",
    "gn:population":0,
    "gn:timezone":"Asia/Ho_Chi_Minh",
    "iso:country":"VN",
    "wof:name":"Que Cu",
    "wof:placetype":"locality"
},
  "geometry": {"coordinates":[105.45,20.56667],"type":"Point"}
}