{
  "type": "Feature",
  "properties": {
    "gn:admin1_code":"82.0",
    "gn:asciiname":"Xuong Dien",
    "gn:country_code":"VN",
    "gn:dem":2,
    "gn:feature_class":"P",
    "gn:feature_code":"PPL",
    "gn:name":"X\u01b0\u01a1ng \u0110i\u1ec1n",
    "gn:population":0,
    "gn:timezone":"Asia/Ho_Chi_Minh",
    "iso:country":"VN",
    "wof:name":"Xuong Dien",
    "wof:placetype":"locality"
},
  "geometry": {"coordinates":[106.31667,20.13333],"type":"Point"}
}