{
  "type": "Feature",
  "properties": {
    "gn:admin1_code":"23.0",
    "gn:asciiname":"Buon Bedeur",
    "gn:country_code":"VN",
    "gn:dem":832,
    "gn:feature_class":"P",
    "gn:feature_code":"PPL",
    "gn:name":"Bu\u00f4n Bedeur",
    "gn:population":0,
    "gn:timezone":"Asia/Ho_Chi_Minh",
    "iso:country":"VN",
    "wof:name":"Buon Bedeur",
    "wof:placetype":"locality"
},
  "geometry": {"coordinates":[107.75,11.65],"type":"Point"}
}