{
  "type": "Feature",
  "properties": {
    "gn:admin1_code":"20.0",
    "gn:asciiname":"Trung Lap",
    "gn:cc2":"VN",
    "gn:country_code":"VN",
    "gn:dem":17,
    "gn:feature_class":"P",
    "gn:feature_code":"PPL",
    "gn:name":"Trung L\u1eadp",
    "gn:population":0,
    "gn:timezone":"Asia/Ho_Chi_Minh",
    "iso:country":"VN",
    "name:und_x_variant":[
        "Thruong Lap",
        "Trung L\u1eadp"
    ],
    "wof:name":"Trung Lap",
    "wof:placetype":"locality"
},
  "geometry": {"coordinates":[106.45,11.05],"type":"Point"}
}