{
  "type": "Feature",
  "properties": {
    "gn:admin1_code":"39.0",
    "gn:asciiname":"Con Phieng",
    "gn:country_code":"VN",
    "gn:dem":349,
    "gn:feature_class":"P",
    "gn:feature_code":"PPL",
    "gn:name":"C\u00f2n Phi\u00eang",
    "gn:population":0,
    "gn:timezone":"Asia/Ho_Chi_Minh",
    "iso:country":"VN",
    "name:vie_x_preferred":[
        "C\u00f2n Phi\u00eang"
    ],
    "wof:name":"Con Phieng",
    "wof:placetype":"locality"
},
  "geometry": {"coordinates":[107.11483,21.64223],"type":"Point"}
}