{
  "type": "Feature",
  "properties": {
    "gn:admin1_code":"73.0",
    "gn:asciiname":"Tram Mot",
    "gn:country_code":"VN",
    "gn:dem":1,
    "gn:feature_class":"P",
    "gn:feature_code":"PPL",
    "gn:name":"Tr\u00e0m M\u1ed9t",
    "gn:population":0,
    "gn:timezone":"Asia/Ho_Chi_Minh",
    "iso:country":"VN",
    "name:und_x_variant":[
        "Nh\u00e0 M\u00e1y Gao",
        "\u1ea4p Tr\u00e0m M\u1ed9t"
    ],
    "name:vie_x_preferred":[
        "Tr\u00e0m M\u1ed9t"
    ],
    "wof:name":"Tram Mot",
    "wof:placetype":"locality"
},
  "geometry": {"coordinates":[105.64407,9.34473],"type":"Point"}
}