{
  "type": "Feature",
  "properties": {
    "gn:admin1_code":"72.0",
    "gn:asciiname":"Khuoi Khau",
    "gn:country_code":"VN",
    "gn:dem":233,
    "gn:feature_class":"P",
    "gn:feature_code":"PPL",
    "gn:name":"Khu\u1ed5i Kh\u1ea5u",
    "gn:population":0,
    "gn:timezone":"Asia/Ho_Chi_Minh",
    "iso:country":"VN",
    "wof:name":"Khuoi Khau",
    "wof:placetype":"locality"
},
  "geometry": {"coordinates":[105.78848000000001,22.40327000000001],"type":"Point"}
}