{
  "type": "Feature",
  "properties": {
    "gn:admin1_code":"61.0",
    "gn:asciiname":"Phuoc Ly",
    "gn:country_code":"VN",
    "gn:dem":12,
    "gn:feature_class":"P",
    "gn:feature_code":"PPL",
    "gn:name":"Ph\u01b0\u1edbc L\u00fd",
    "gn:population":0,
    "gn:timezone":"Asia/Ho_Chi_Minh",
    "iso:country":"VN",
    "name:und_x_variant":[
        "Truon Cam Dang",
        "Ph\u01b0\u1edbc L\u1ef9"
    ],
    "name:vie_x_preferred":[
        "Ph\u01b0\u1edbc L\u00fd"
    ],
    "wof:name":"Phuoc Ly",
    "wof:placetype":"locality"
},
  "geometry": {"coordinates":[109.23258,13.47438],"type":"Point"}
}