{
  "type": "Feature",
  "properties": {
    "gn:admin1_code":"87.0",
    "gn:asciiname":"Ap Truong Phu",
    "gn:country_code":"VN",
    "gn:dem":-1,
    "gn:feature_class":"P",
    "gn:feature_code":"PPL",
    "gn:name":"\u1ea4p Tr\u01b0\u1eddng Ph\u00fa",
    "gn:population":0,
    "gn:timezone":"Asia/Ho_Chi_Minh",
    "iso:country":"VN",
    "wof:name":"Ap Truong Phu",
    "wof:placetype":"locality"
},
  "geometry": {"coordinates":[105.61722,10.00056],"type":"Point"}
}