{
  "type": "Feature",
  "properties": {
    "gn:admin1_code":"88.0",
    "gn:asciiname":"Buon Krong Pach",
    "gn:country_code":"VN",
    "gn:dem":482,
    "gn:feature_class":"P",
    "gn:feature_code":"PPL",
    "gn:name":"Bu\u00f4n Kr\u00f4ng P\u00e1ch",
    "gn:population":0,
    "gn:timezone":"Asia/Ho_Chi_Minh",
    "iso:country":"VN",
    "name:vie_x_preferred":[
        "Bu\u00f4n Kr\u00f4ng P\u00e1ch"
    ],
    "wof:name":"Buon Krong Pach",
    "wof:placetype":"locality"
},
  "geometry": {"coordinates":[108.41073,12.78211],"type":"Point"}
}