{
  "type": "Feature",
  "properties": {
    "gn:admin1_code":"58.0",
    "gn:asciiname":"Xuan Kieu",
    "gn:country_code":"VN",
    "gn:dem":12,
    "gn:feature_class":"P",
    "gn:feature_code":"PPL",
    "gn:name":"Xuan Kieu",
    "gn:population":0,
    "gn:timezone":"Asia/Ho_Chi_Minh",
    "iso:country":"VN",
    "name:und_x_variant":[
        "Dom Kieu",
        "\u0110on Ki\u1ec1u"
    ],
    "name:vie_x_preferred":[
        "\u0110\u1ed3n Ki\u1ec1u"
    ],
    "wof:name":"Xuan Kieu",
    "wof:placetype":"locality"
},
  "geometry": {"coordinates":[105.49299000000001,18.82254],"type":"Point"}
}