{
  "type": "Feature",
  "properties": {
    "gn:admin1_code":"70.0",
    "gn:asciiname":"Khe Cha",
    "gn:country_code":"VN",
    "gn:dem":112,
    "gn:feature_class":"P",
    "gn:feature_code":"PPL",
    "gn:name":"Khe Ch\u00e0",
    "gn:population":0,
    "gn:timezone":"Asia/Ho_Chi_Minh",
    "iso:country":"VN",
    "name:vie_x_preferred":[
        "Khe Ch\u00e0"
    ],
    "wof:name":"Khe Cha",
    "wof:placetype":"locality"
},
  "geometry": {"coordinates":[104.61077,21.84374],"type":"Point"}
}