{
  "type": "Feature",
  "properties": {
    "gn:admin1_code":"68.0",
    "gn:asciiname":"Song Linh",
    "gn:country_code":"VN",
    "gn:dem":33,
    "gn:feature_class":"P",
    "gn:feature_code":"PPL",
    "gn:name":"S\u00f4ng Linh",
    "gn:population":0,
    "gn:timezone":"Asia/Ho_Chi_Minh",
    "iso:country":"VN",
    "name:vie_x_preferred":[
        "S\u00f4ng Linh"
    ],
    "wof:name":"Song Linh",
    "wof:placetype":"locality"
},
  "geometry": {"coordinates":[105.28830000000001,21.77547],"type":"Point"}
}