{
  "type": "Feature",
  "properties": {
    "gn:admin1_code":"34.0",
    "gn:asciiname":"Lang Than",
    "gn:country_code":"VN",
    "gn:dem":67,
    "gn:feature_class":"P",
    "gn:feature_code":"PPL",
    "gn:name":"L\u00e0ng Than",
    "gn:population":0,
    "gn:timezone":"Asia/Ho_Chi_Minh",
    "iso:country":"VN",
    "name:und_x_variant":[
        "Lang Tha",
        "L\u00e0ng Than"
    ],
    "wof:name":"Lang Than",
    "wof:placetype":"locality"
},
  "geometry": {"coordinates":[105.43299,19.77333],"type":"Point"}
}