{
  "type": "Feature",
  "properties": {
    "gn:admin1_code":"54.0",
    "gn:asciiname":"Ta Gop",
    "gn:country_code":"VN",
    "gn:dem":602,
    "gn:feature_class":"P",
    "gn:feature_code":"PPL",
    "gn:name":"Ta G\u00f3p",
    "gn:population":0,
    "gn:timezone":"Asia/Ho_Chi_Minh",
    "iso:country":"VN",
    "name:und_x_variant":[
        "Ten Li\u00eang"
    ],
    "name:vie_x_preferred":[
        "Ta G\u00f3p"
    ],
    "wof:name":"Ta Gop",
    "wof:placetype":"locality"
},
  "geometry": {"coordinates":[108.80240999999999,12.39821],"type":"Point"}
}