{
  "type": "Feature",
  "properties": {
    "gn:admin1_code":"52.0",
    "gn:asciiname":"Son Bang",
    "gn:country_code":"VN",
    "gn:dem":6,
    "gn:feature_class":"P",
    "gn:feature_code":"PPL",
    "gn:name":"S\u01a1n B\u1eb1ng",
    "gn:population":0,
    "gn:timezone":"Asia/Ho_Chi_Minh",
    "iso:country":"VN",
    "name:vie_x_preferred":[
        "S\u01a1n B\u1eb1ng"
    ],
    "wof:name":"Son Bang",
    "wof:placetype":"locality"
},
  "geometry": {"coordinates":[105.91407,18.45773],"type":"Point"}
}