{
  "type": "Feature",
  "properties": {
    "gn:admin1_code":"32.0",
    "gn:asciiname":"Mua Tuoi",
    "gn:country_code":"VN",
    "gn:dem":1026,
    "gn:feature_class":"P",
    "gn:feature_code":"PPL",
    "gn:name":"M\u01b0a T\u01b0\u01a1i",
    "gn:population":0,
    "gn:timezone":"Asia/Ho_Chi_Minh",
    "iso:country":"VN",
    "name:und_x_variant":[
        "Mu Tui"
    ],
    "name:vie_x_preferred":[
        "M\u01b0a T\u01b0\u01a1i"
    ],
    "wof:name":"Mua Tuoi",
    "wof:placetype":"locality"
},
  "geometry": {"coordinates":[104.38844,20.888],"type":"Point"}
}