{
  "type": "Feature",
  "properties": {
    "gn:admin1_code":"34.0",
    "gn:asciiname":"Hoang Trung",
    "gn:cc2":"VN",
    "gn:country_code":"VN",
    "gn:dem":6,
    "gn:feature_class":"P",
    "gn:feature_code":"PPL",
    "gn:name":"Hoang Trung",
    "gn:population":0,
    "gn:timezone":"Asia/Ho_Chi_Minh",
    "iso:country":"VN",
    "name:und_x_variant":[
        "Hoanh Trung",
        "Hoang Trung"
    ],
    "wof:name":"Hoang Trung",
    "wof:placetype":"locality"
},
  "geometry": {"coordinates":[105.90000000000001,19.93333],"type":"Point"}
}