{
  "type": "Feature",
  "properties": {
    "gn:admin1_code":"92.0",
    "gn:asciiname":"Nam Pong",
    "gn:country_code":"VN",
    "gn:dem":775,
    "gn:feature_class":"P",
    "gn:feature_code":"PPL",
    "gn:name":"N\u1eadm P\u1ecdng",
    "gn:population":0,
    "gn:timezone":"Asia/Ho_Chi_Minh",
    "iso:country":"VN",
    "name:vie_x_preferred":[
        "N\u1eadm P\u1ecdng"
    ],
    "wof:name":"Nam Pong",
    "wof:placetype":"locality"
},
  "geometry": {"coordinates":[103.15306,21.56925],"type":"Point"}
}