{
  "type": "Feature",
  "properties": {
    "gn:admin1_code":"72.0",
    "gn:asciiname":"Ban Nhai",
    "gn:country_code":"VN",
    "gn:dem":495,
    "gn:feature_class":"P",
    "gn:feature_code":"PPL",
    "gn:name":"B\u1ea3n Nhai",
    "gn:population":0,
    "gn:timezone":"Asia/Ho_Chi_Minh",
    "iso:country":"VN",
    "name:vie_x_preferred":[
        "B\u1ea3n Nhai"
    ],
    "wof:name":"Ban Nhai",
    "wof:placetype":"locality"
},
  "geometry": {"coordinates":[105.53538,22.22227],"type":"Point"}
}