{
  "type": "Feature",
  "properties": {
    "gn:admin1_code":"77.0",
    "gn:asciiname":"Ong Trang",
    "gn:country_code":"VN",
    "gn:dem":2,
    "gn:feature_class":"P",
    "gn:feature_code":"PPL",
    "gn:name":"\u00d4ng Trang",
    "gn:population":0,
    "gn:timezone":"Asia/Ho_Chi_Minh",
    "iso:country":"VN",
    "name:und_x_variant":[
        "X\u00f3m \u00d4ng Trang",
        "\u00d4ng Trang"
    ],
    "wof:name":"Ong Trang",
    "wof:placetype":"locality"
},
  "geometry": {"coordinates":[104.86193,8.6886],"type":"Point"}
}