{
  "type": "Feature",
  "properties": {
    "gn:admin1_code":"73.0",
    "gn:asciiname":"Ap Thong Luu",
    "gn:country_code":"VN",
    "gn:dem":-5,
    "gn:feature_class":"P",
    "gn:feature_code":"PPL",
    "gn:name":"\u1ea4p Th\u00f4ng L\u01b0u",
    "gn:population":0,
    "gn:timezone":"Asia/Ho_Chi_Minh",
    "iso:country":"VN",
    "wof:name":"Ap Thong Luu",
    "wof:placetype":"locality"
},
  "geometry": {"coordinates":[105.72806,9.35139],"type":"Point"}
}