{
  "type": "Feature",
  "properties": {
    "gn:admin1_code":"92.0",
    "gn:asciiname":"Ban Dua",
    "gn:country_code":"VN",
    "gn:dem":707,
    "gn:feature_class":"P",
    "gn:feature_code":"PPL",
    "gn:name":"B\u1ea3n Dua",
    "gn:population":0,
    "gn:timezone":"Asia/Ho_Chi_Minh",
    "iso:country":"VN",
    "wof:name":"Ban Dua",
    "wof:placetype":"locality"
},
  "geometry": {"coordinates":[103.40000000000001,21.56667],"type":"Point"}
}