{
  "type": "Feature",
  "properties": {
    "gn:admin1_code":"74.0",
    "gn:asciiname":"Mai Thon",
    "gn:country_code":"VN",
    "gn:dem":7,
    "gn:feature_class":"P",
    "gn:feature_code":"PPL",
    "gn:name":"Mai Th\u00f4n",
    "gn:population":0,
    "gn:timezone":"Asia/Ho_Chi_Minh",
    "iso:country":"VN",
    "name:vie_x_preferred":[
        "Mai Th\u00f4n"
    ],
    "wof:name":"Mai Thon",
    "wof:placetype":"locality"
},
  "geometry": {"coordinates":[106.13703,21.09215],"type":"Point"}
}