{
  "type": "Feature",
  "properties": {
    "gn:admin1_code":"33.0",
    "gn:asciiname":"Gia Binh",
    "gn:cc2":"VN",
    "gn:country_code":"VN",
    "gn:dem":6,
    "gn:feature_class":"P",
    "gn:feature_code":"PPL",
    "gn:name":"Gia B\u00ecnh",
    "gn:population":0,
    "gn:timezone":"Asia/Ho_Chi_Minh",
    "iso:country":"VN",
    "name:und_x_variant":[
        "Ap Gia Binh",
        "Gia B\u00ecnh"
    ],
    "wof:name":"Gia Binh",
    "wof:placetype":"locality"
},
  "geometry": {"coordinates":[106.31667,11.05],"type":"Point"}
}