{
  "type": "Feature",
  "properties": {
    "gn:admin1_code":"68.0",
    "gn:asciiname":"Khong May",
    "gn:country_code":"VN",
    "gn:dem":98,
    "gn:feature_class":"P",
    "gn:feature_code":"PPL",
    "gn:name":"Kh\u00f4ng M\u00e2y",
    "gn:population":0,
    "gn:timezone":"Asia/Ho_Chi_Minh",
    "iso:country":"VN",
    "name:vie_x_preferred":[
        "Kh\u00f4ng M\u00e2y"
    ],
    "wof:name":"Khong May",
    "wof:placetype":"locality"
},
  "geometry": {"coordinates":[105.3432,22.3901],"type":"Point"}
}