{
  "type": "Feature",
  "properties": {
    "gn:admin1_code":"58.0",
    "gn:asciiname":"Ban Tuc",
    "gn:country_code":"VN",
    "gn:dem":101,
    "gn:feature_class":"P",
    "gn:feature_code":"PPL",
    "gn:name":"B\u1ea3n T\u1ee5c",
    "gn:population":0,
    "gn:timezone":"Asia/Ho_Chi_Minh",
    "iso:country":"VN",
    "wof:name":"Ban Tuc",
    "wof:placetype":"locality"
},
  "geometry": {"coordinates":[105.12307,19.91742],"type":"Point"}
}