{
  "type": "Feature",
  "properties": {
    "gn:admin1_code":"33.0",
    "gn:asciiname":"Chams",
    "gn:cc2":"VN",
    "gn:country_code":"VN",
    "gn:dem":11,
    "gn:feature_class":"P",
    "gn:feature_code":"PPL",
    "gn:name":"Chams",
    "gn:population":0,
    "gn:timezone":"Asia/Ho_Chi_Minh",
    "iso:country":"VN",
    "name:ace_x_preferred":[
        "Bansa Cham"
    ],
    "name:ara_x_preferred":[
        "\u062a\u0634\u0627\u0645"
    ],
    "name:arz_x_preferred":[
        "\u062a\u0634\u0627\u0645"
    ],
    "name:ast_x_preferred":[
        "Pueblu cham"
    ],
    "name:azb_x_preferred":[
        "\u0686\u0627\u0645\u0644\u0627\u0631"
    ],
    "name:bel_x_preferred":[
        "\u0427\u0430\u043c\u044b"
    ],
    "name:cat_x_preferred":[
        "Txams"
    ],
    "name:deu_x_preferred":[
        "Cham"
    ],
    "name:ell_x_preferred":[
        "\u03a4\u03c3\u03b1\u03bc"
    ],
    "name:epo_x_preferred":[
        "\u0108amoj"
    ],
    "name:eus_x_preferred":[
        "Cham"
    ],
    "name:fas_x_preferred":[
        "\u0645\u0631\u062f\u0645 \u0686\u0627\u0645"
    ],
    "name:fin_x_preferred":[
        "Chamit"
    ],
    "name:fra_x_preferred":[
        "Cham"
    ],
    "name:hin_x_preferred":[
        "\u091a\u093e\u092e \u0932\u094b\u0917"
    ],
    "name:ind_x_preferred":[
        "Suku Cham"
    ],
    "name:ita_x_preferred":[
        "Ch\u0103m"
    ],
    "name:jpn_x_preferred":[
        "\u30c1\u30e3\u30e0\u65cf"
    ],
    "name:lit_x_preferred":[
        "\u010camai"
    ],
    "name:msa_x_preferred":[
        "Orang Cham"
    ],
    "name:nld_x_preferred":[
        "Cham"
    ],
    "name:nor_x_preferred":[
        "Chamfolket"
    ],
    "name:pnb_x_preferred":[
        "\u0686\u0627\u0645 \u0644\u0648\u06a9"
    ],
    "name:pol_x_preferred":[
        "Czamowie"
    ],
    "name:por_x_preferred":[
        "Cham"
    ],
    "name:rus_x_preferred":[
        "\u0422\u044f\u043c\u044b"
    ],
    "name:spa_x_preferred":[
        "Pueblo cham"
    ],
    "name:srp_x_preferred":[
        "\u0427\u0430\u043c"
    ],
    "name:swe_x_preferred":[
        "Chamfolket"
    ],
    "name:tam_x_preferred":[
        "\u0b9a\u0bbe\u0bae\u0bcd \u0bae\u0b95\u0bcd\u0b95\u0bb3\u0bcd"
    ],
    "name:tha_x_preferred":[
        "\u0e0a\u0e32\u0e27\u0e08\u0e32\u0e21"
    ],
    "name:tur_x_preferred":[
        "\u00c7amlar"
    ],
    "name:ukr_x_preferred":[
        "\u0422\u044f\u043c\u0438"
    ],
    "name:und_x_variant":[
        "Chama",
        "Chams"
    ],
    "name:vie_x_preferred":[
        "Ng\u01b0\u1eddi Ch\u0103m"
    ],
    "wof:name":"Chams",
    "wof:placetype":"locality"
},
  "geometry": {"coordinates":[106.08333,11.45],"type":"Point"}
}