{
  "type": "Feature",
  "properties": {
    "gn:admin1_code":"72.0",
    "gn:asciiname":"An Ma",
    "gn:country_code":"VN",
    "gn:dem":469,
    "gn:feature_class":"P",
    "gn:feature_code":"PPL",
    "gn:name":"An Ma",
    "gn:population":0,
    "gn:timezone":"Asia/Ho_Chi_Minh",
    "iso:country":"VN",
    "wof:name":"An Ma",
    "wof:placetype":"locality"
},
  "geometry": {"coordinates":[105.59999999999999,22.41667],"type":"Point"}
}