{
  "type": "Feature",
  "properties": {
    "gn:admin1_code":"49.0",
    "gn:asciiname":"Khu Pho Mot",
    "gn:country_code":"VN",
    "gn:dem":166,
    "gn:feature_class":"P",
    "gn:feature_code":"PPL",
    "gn:name":"Khu Ph\u1ed1 M\u1ed9t",
    "gn:population":0,
    "gn:timezone":"Asia/Ho_Chi_Minh",
    "iso:country":"VN",
    "name:vie_x_preferred":[
        "Khu Ph\u1ed1 M\u1ed9t"
    ],
    "name:vie_x_variant":[
        "Khu Ph\u1ed1 1"
    ],
    "wof:name":"Khu Pho Mot",
    "wof:placetype":"locality"
},
  "geometry": {"coordinates":[108.42668999999999,13.41769],"type":"Point"}
}