{
  "type": "Feature",
  "properties": {
    "gn:admin1_code":"39.0",
    "gn:asciiname":"Binh Ha",
    "gn:country_code":"VN",
    "gn:dem":430,
    "gn:feature_class":"P",
    "gn:feature_code":"PPL",
    "gn:name":"B\u00ecnh H\u1ea1",
    "gn:population":0,
    "gn:timezone":"Asia/Ho_Chi_Minh",
    "iso:country":"VN",
    "name:vie_x_preferred":[
        "B\u00ecnh H\u1ea1"
    ],
    "wof:name":"Binh Ha",
    "wof:placetype":"locality"
},
  "geometry": {"coordinates":[106.33156,21.86528],"type":"Point"}
}