{
  "type": "Feature",
  "properties": {
    "gn:admin1_code":"34.0",
    "gn:asciiname":"Cam Bua",
    "gn:cc2":"VN",
    "gn:country_code":"VN",
    "gn:dem":277,
    "gn:feature_class":"P",
    "gn:feature_code":"PPL",
    "gn:name":"Cam B\u00faa",
    "gn:population":0,
    "gn:timezone":"Asia/Ho_Chi_Minh",
    "iso:country":"VN",
    "name:und_x_variant":[
        "Ch\u00f2m B\u00faa",
        "Cam B\u00faa"
    ],
    "wof:name":"Cam Bua",
    "wof:placetype":"locality"
},
  "geometry": {"coordinates":[105.36667,20.21667],"type":"Point"}
}