{
  "type": "Feature",
  "properties": {
    "gn:admin1_code":"13.0",
    "gn:asciiname":"Hop Le",
    "gn:country_code":"VN",
    "gn:dem":4,
    "gn:feature_class":"P",
    "gn:feature_code":"PPL",
    "gn:name":"H\u1ee3p L\u1ec5",
    "gn:population":0,
    "gn:timezone":"Asia/Ho_Chi_Minh",
    "iso:country":"VN",
    "name:vie_x_preferred":[
        "H\u1ee3p L\u1ec5"
    ],
    "wof:name":"Hop Le",
    "wof:placetype":"locality"
},
  "geometry": {"coordinates":[106.72183,20.75837000000001],"type":"Point"}
}