{
  "type": "Feature",
  "properties": {
    "gn:admin1_code":"50.0",
    "gn:asciiname":"Ma Phan",
    "gn:country_code":"VN",
    "gn:dem":1504,
    "gn:feature_class":"P",
    "gn:feature_code":"PPL",
    "gn:name":"Ma Phan",
    "gn:population":0,
    "gn:timezone":"Asia/Ho_Chi_Minh",
    "iso:country":"VN",
    "wof:name":"Ma Phan",
    "wof:placetype":"locality"
},
  "geometry": {"coordinates":[105.31667,23.25],"type":"Point"}
}