{
  "type": "Feature",
  "properties": {
    "gn:admin1_code":"32.0",
    "gn:asciiname":"Bang Nho",
    "gn:country_code":"VN",
    "gn:dem":1212,
    "gn:feature_class":"P",
    "gn:feature_code":"PPL",
    "gn:name":"Bang Nho",
    "gn:population":0,
    "gn:timezone":"Asia/Ho_Chi_Minh",
    "iso:country":"VN",
    "wof:name":"Bang Nho",
    "wof:placetype":"locality"
},
  "geometry": {"coordinates":[104.76667,20.78333],"type":"Point"}
}