{
  "type": "Feature",
  "properties": {
    "gn:admin1_code":"9.0",
    "gn:asciiname":"Binh Dinh",
    "gn:country_code":"VN",
    "gn:dem":3,
    "gn:feature_class":"P",
    "gn:feature_code":"PPL",
    "gn:name":"B\u00ecnh \u0110\u1ecbnh",
    "gn:population":0,
    "gn:timezone":"Asia/Ho_Chi_Minh",
    "iso:country":"VN",
    "name:vie_x_preferred":[
        "B\u00ecnh \u0110\u1ecbnh"
    ],
    "wof:name":"Binh Dinh",
    "wof:placetype":"locality"
},
  "geometry": {"coordinates":[105.52291,10.55562],"type":"Point"}
}