{
  "type": "Feature",
  "properties": {
    "gn:admin1_code":"12.0",
    "gn:asciiname":"Tan Ap",
    "gn:country_code":"VN",
    "gn:dem":18,
    "gn:feature_class":"P",
    "gn:feature_code":"PPL",
    "gn:name":"T\u00e2n \u00c1p",
    "gn:population":0,
    "gn:timezone":"Asia/Ho_Chi_Minh",
    "iso:country":"VN",
    "wof:name":"Tan Ap",
    "wof:placetype":"locality"
},
  "geometry": {"coordinates":[106.43333,21.08333],"type":"Point"}
}