{
  "type": "Feature",
  "properties": {
    "gn:admin1_code":"39.0",
    "gn:asciiname":"Tham Cai",
    "gn:country_code":"VN",
    "gn:dem":476,
    "gn:feature_class":"P",
    "gn:feature_code":"PPL",
    "gn:name":"Th\u00e2m C\u00e1i",
    "gn:population":0,
    "gn:timezone":"Asia/Ho_Chi_Minh",
    "iso:country":"VN",
    "name:vie_x_preferred":[
        "Th\u00e2m C\u00e1i"
    ],
    "wof:name":"Tham Cai",
    "wof:placetype":"locality"
},
  "geometry": {"coordinates":[106.28413999999999,21.8806],"type":"Point"}
}