{
  "type": "Feature",
  "properties": {
    "gn:admin1_code":"23.0",
    "gn:asciiname":"B Kr'Chia",
    "gn:country_code":"VN",
    "gn:dem":156,
    "gn:feature_class":"P",
    "gn:feature_code":"PPL",
    "gn:name":"B Kr\u2019Chia",
    "gn:population":0,
    "gn:timezone":"Asia/Ho_Chi_Minh",
    "iso:country":"VN",
    "wof:name":"B Kr'Chia",
    "wof:placetype":"locality"
},
  "geometry": {"coordinates":[107.56541,11.5379],"type":"Point"}
}