{
  "type": "Feature",
  "properties": {
    "gn:admin1_code":"39.0",
    "gn:asciiname":"Minh Dan",
    "gn:country_code":"VN",
    "gn:dem":417,
    "gn:feature_class":"P",
    "gn:feature_code":"PPL",
    "gn:name":"Minh \u0110\u00e1n",
    "gn:population":0,
    "gn:timezone":"Asia/Ho_Chi_Minh",
    "iso:country":"VN",
    "name:vie_x_preferred":[
        "Minh \u0110\u00e1n"
    ],
    "wof:name":"Minh Dan",
    "wof:placetype":"locality"
},
  "geometry": {"coordinates":[106.35961,21.84887],"type":"Point"}
}