{
  "type": "Feature",
  "properties": {
    "gn:admin1_code":"32.0",
    "gn:asciiname":"Ban Huoi Duong",
    "gn:country_code":"VN",
    "gn:dem":752,
    "gn:feature_class":"P",
    "gn:feature_code":"PPL",
    "gn:name":"B\u1ea3n Hu\u1ed5i D\u01b0\u1edbng",
    "gn:population":0,
    "gn:timezone":"Asia/Ho_Chi_Minh",
    "iso:country":"VN",
    "name:vie_x_preferred":[
        "B\u1ea3n Hu\u1ed5i D\u01b0\u1edbng"
    ],
    "wof:name":"Ban Huoi Duong",
    "wof:placetype":"locality"
},
  "geometry": {"coordinates":[103.63039000000001,21.59062],"type":"Point"}
}