{
  "type": "Feature",
  "properties": {
    "gn:admin1_code":"74.0",
    "gn:asciiname":"Tu Chi",
    "gn:country_code":"VN",
    "gn:dem":7,
    "gn:feature_class":"P",
    "gn:feature_code":"PPL",
    "gn:name":"T\u01b0 Chi",
    "gn:population":0,
    "gn:timezone":"Asia/Ho_Chi_Minh",
    "iso:country":"VN",
    "name:und_x_variant":[
        "Tu Vi"
    ],
    "name:vie_x_preferred":[
        "T\u1ef1 Ch\u00ed"
    ],
    "name:vie_x_variant":[
        "T\u01b0 Chi"
    ],
    "wof:name":"Tu Chi",
    "wof:placetype":"locality"
},
  "geometry": {"coordinates":[106.08459000000001,21.09323],"type":"Point"}
}