{
  "type": "Feature",
  "properties": {
    "gn:admin1_code":"92.0",
    "gn:asciiname":"Tin Toc",
    "gn:country_code":"VN",
    "gn:dem":644,
    "gn:feature_class":"P",
    "gn:feature_code":"PPL",
    "gn:name":"Tin T\u1ed1c",
    "gn:population":0,
    "gn:timezone":"Asia/Ho_Chi_Minh",
    "iso:country":"VN",
    "name:und_x_variant":[
        "B\u1ea3n Tin Toc"
    ],
    "name:vie_x_preferred":[
        "Tin T\u1ed1c"
    ],
    "wof:name":"Tin Toc",
    "wof:placetype":"locality"
},
  "geometry": {"coordinates":[103.18962000000001,21.51326],"type":"Point"}
}