{
  "type": "Feature",
  "properties": {
    "gn:admin1_code":"5.0",
    "gn:asciiname":"Ban Thung",
    "gn:country_code":"VN",
    "gn:dem":355,
    "gn:feature_class":"P",
    "gn:feature_code":"PPL",
    "gn:name":"B\u1ea3n Th\u1eebng",
    "gn:population":0,
    "gn:timezone":"Asia/Ho_Chi_Minh",
    "iso:country":"VN",
    "name:vie_x_preferred":[
        "B\u1ea3n Th\u1eebng"
    ],
    "wof:name":"Ban Thung",
    "wof:placetype":"locality"
},
  "geometry": {"coordinates":[106.76018000000001,22.79859],"type":"Point"}
}