{
  "type": "Feature",
  "properties": {
    "gn:admin1_code":"85.0",
    "gn:asciiname":"Phu Khuon",
    "gn:country_code":"VN",
    "gn:dem":75,
    "gn:feature_class":"P",
    "gn:feature_code":"PPL",
    "gn:name":"Ph\u00fa Khu\u00f4n",
    "gn:population":0,
    "gn:timezone":"Asia/Ho_Chi_Minh",
    "iso:country":"VN",
    "wof:name":"Phu Khuon",
    "wof:placetype":"locality"
},
  "geometry": {"coordinates":[105.65000000000001,21.76667],"type":"Point"}
}