{
  "type": "Feature",
  "properties": {
    "gn:admin1_code":"52.0",
    "gn:asciiname":"Vinh Hoa",
    "gn:country_code":"VN",
    "gn:dem":7,
    "gn:feature_class":"P",
    "gn:feature_code":"PPL",
    "gn:name":"V\u0129nh H\u00f2a",
    "gn:population":0,
    "gn:timezone":"Asia/Ho_Chi_Minh",
    "iso:country":"VN",
    "name:vie_x_preferred":[
        "V\u0129nh H\u00f2a"
    ],
    "wof:name":"Vinh Hoa",
    "wof:placetype":"locality"
},
  "geometry": {"coordinates":[105.9318,18.40312],"type":"Point"}
}