{
  "type": "Feature",
  "properties": {
    "gn:admin1_code":"32.0",
    "gn:asciiname":"Ban Tuong",
    "gn:cc2":"VN",
    "gn:country_code":"VN",
    "gn:dem":531,
    "gn:feature_class":"P",
    "gn:feature_code":"PPL",
    "gn:name":"B\u1ea3n T\u01b0\u01a1ng",
    "gn:population":0,
    "gn:timezone":"Asia/Ho_Chi_Minh",
    "iso:country":"VN",
    "name:und_x_variant":[
        "Ban Tdong",
        "B\u1ea3n T\u01b0\u01a1ng"
    ],
    "wof:name":"Ban Tuong",
    "wof:placetype":"locality"
},
  "geometry": {"coordinates":[104.36667,21.05],"type":"Point"}
}