{
  "type": "Feature",
  "properties": {
    "gn:admin1_code":"84.0",
    "gn:asciiname":"Duy Dong",
    "gn:country_code":"VN",
    "gn:dem":14,
    "gn:feature_class":"P",
    "gn:feature_code":"PPL",
    "gn:name":"Duy \u0110\u00f4ng",
    "gn:population":0,
    "gn:timezone":"Asia/Ho_Chi_Minh",
    "iso:country":"VN",
    "wof:name":"Duy Dong",
    "wof:placetype":"locality"
},
  "geometry": {"coordinates":[108.25,15.85],"type":"Point"}
}