{
  "type": "Feature",
  "properties": {
    "gn:admin1_code":"89.0",
    "gn:asciiname":"Kam Ho",
    "gn:country_code":"VN",
    "gn:dem":1509,
    "gn:feature_class":"P",
    "gn:feature_code":"PPL",
    "gn:name":"Kam Ho",
    "gn:population":0,
    "gn:timezone":"Asia/Ho_Chi_Minh",
    "iso:country":"VN",
    "name:und_x_variant":[
        "Kan Ho",
        "Kam Ho"
    ],
    "wof:name":"Kam Ho",
    "wof:placetype":"locality"
},
  "geometry": {"coordinates":[103.83333,22.13333],"type":"Point"}
}