{
  "type": "Feature",
  "properties": {
    "gn:admin1_code":"33.0",
    "gn:asciiname":"Ben Cau",
    "gn:country_code":"VN",
    "gn:dem":7,
    "gn:feature_class":"P",
    "gn:feature_code":"PPLA2",
    "gn:name":"B\u1ebfn C\u1ea7u",
    "gn:population":0,
    "gn:timezone":"Asia/Ho_Chi_Minh",
    "iso:country":"VN",
    "name:und_x_variant":[
        "Ap Ben Cau",
        "Hieu Thien",
        "B\u1ebfn C\u1ea7u"
    ],
    "wof:name":"Ben Cau",
    "wof:placetype":"locality"
},
  "geometry": {"coordinates":[106.17923999999999,11.11051],"type":"Point"}
}