{
  "type": "Feature",
  "properties": {
    "gn:admin1_code":"1.0",
    "gn:asciiname":"Binh Phu",
    "gn:country_code":"VN",
    "gn:dem":7,
    "gn:feature_class":"P",
    "gn:feature_code":"PPL",
    "gn:name":"B\u00ecnh Ph\u00fa",
    "gn:population":0,
    "gn:timezone":"Asia/Ho_Chi_Minh",
    "iso:country":"VN",
    "name:und_x_variant":[
        "\u1ea4p B\u00ecnh Ph\u00fa"
    ],
    "name:vie_x_preferred":[
        "B\u00ecnh Ph\u00fa"
    ],
    "wof:name":"Binh Phu",
    "wof:placetype":"locality"
},
  "geometry": {"coordinates":[105.21832000000001,10.61722],"type":"Point"}
}