{
  "type": "Feature",
  "properties": {
    "gn:admin1_code":"65.0",
    "gn:asciiname":"Ap Rat",
    "gn:cc2":"VN",
    "gn:country_code":"VN",
    "gn:dem":4,
    "gn:feature_class":"P",
    "gn:feature_code":"PPL",
    "gn:name":"\u1ea4p R\u1ea5t",
    "gn:population":0,
    "gn:timezone":"Asia/Ho_Chi_Minh",
    "iso:country":"VN",
    "name:und_x_variant":[
        "R\u1ea5t",
        "\u1ea4p R\u1ea5t"
    ],
    "wof:name":"Ap Rat",
    "wof:placetype":"locality"
},
  "geometry": {"coordinates":[106.02333,9.38194],"type":"Point"}
}