{
  "type": "Feature",
  "properties": {
    "gn:admin1_code":"59.0",
    "gn:asciiname":"Dong Trao",
    "gn:country_code":"VN",
    "gn:dem":62,
    "gn:feature_class":"P",
    "gn:feature_code":"PPL",
    "gn:name":"\u0110\u1ed3ng Trao",
    "gn:population":0,
    "gn:timezone":"Asia/Ho_Chi_Minh",
    "iso:country":"VN",
    "name:vie_x_preferred":[
        "\u0110\u1ed3ng Trao"
    ],
    "wof:name":"Dong Trao",
    "wof:placetype":"locality"
},
  "geometry": {"coordinates":[105.74856,20.24356],"type":"Point"}
}