{
  "type": "Feature",
  "properties": {
    "gn:admin1_code":"89.0",
    "gn:asciiname":"Ban Na Nhien",
    "gn:country_code":"VN",
    "gn:dem":503,
    "gn:feature_class":"P",
    "gn:feature_code":"PPL",
    "gn:name":"B\u1ea3n Na Nhi\u1ec1n",
    "gn:population":0,
    "gn:timezone":"Asia/Ho_Chi_Minh",
    "iso:country":"VN",
    "wof:name":"Ban Na Nhien",
    "wof:placetype":"locality"
},
  "geometry": {"coordinates":[103.83333,21.81667],"type":"Point"}
}