{
  "type": "Feature",
  "properties": {
    "gn:admin1_code":"35.0",
    "gn:asciiname":"Bach Tinh",
    "gn:country_code":"VN",
    "gn:dem":6,
    "gn:feature_class":"P",
    "gn:feature_code":"PPL",
    "gn:name":"B\u00e1ch T\u00ednh",
    "gn:population":0,
    "gn:timezone":"Asia/Ho_Chi_Minh",
    "iso:country":"VN",
    "name:vie_x_preferred":[
        "B\u00e1ch T\u00ednh"
    ],
    "wof:name":"Bach Tinh",
    "wof:placetype":"locality"
},
  "geometry": {"coordinates":[106.22607000000001,20.41271],"type":"Point"}
}