{
  "type": "Feature",
  "properties": {
    "iso:country":"VN",
    "oa:elevation_ft":"39",
    "oa:type":"large_airport",
    "woe:hierarchy":{
        "country_id":23424984,
        "planet_id":1,
        "state_id":20070090
    },
    "wof:name":"Noi Bai Airport",
    "wof:placetype":"campus"
},
  "geometry": {"coordinates":[105.80722222222001,21.221111111111],"type":"Point"}
}