{
  "type": "Feature",
  "properties": {
    "iso:country":"VN",
    "name:ara_x_preferred":[
        "\u0645\u0637\u0627\u0631 \u0646\u0648\u064a \u0628\u0627\u064a \u0627\u0644\u062f\u0648\u0644\u064a"
    ],
    "name:bel_x_preferred":[
        "\u041c\u0456\u0436\u043d\u0430\u0440\u043e\u0434\u043d\u044b \u0430\u044d\u0440\u0430\u043f\u043e\u0440\u0442 \u041d\u0430\u0439\u0431\u0430\u0439"
    ],
    "name:ces_x_preferred":[
        "Leti\u0161t\u011b N\u1ed9i B\u00e0i"
    ],
    "name:deu_x_preferred":[
        "Flughafen Hanoi"
    ],
    "name:est_x_preferred":[
        "Noi Bai rahvusvaheline lennujaam"
    ],
    "name:fas_x_preferred":[
        "\u0641\u0631\u0648\u062f\u06af\u0627\u0647 \u0628\u06cc\u0646\u200c\u0627\u0644\u0645\u0644\u0644\u06cc \u0646\u0648\u0627 \u0628\u0647"
    ],
    "name:fin_x_preferred":[
        "Noi Bain kansainv\u00e4linen lentoasema"
    ],
    "name:ind_x_preferred":[
        "Bandar Udara Internasional Noi Bai"
    ],
    "name:ita_x_preferred":[
        "Aeroporto Internazionale Noi Bai"
    ],
    "name:jpn_x_preferred":[
        "\u30ce\u30a4\u30d0\u30a4\u56fd\u969b\u7a7a\u6e2f"
    ],
    "name:kor_x_preferred":[
        "\ub178\uc774\ubc14\uc774 \uad6d\uc81c\uacf5\ud56d"
    ],
    "name:msa_x_preferred":[
        "Lapangan Terbang Antarabangsa Noibai"
    ],
    "name:mya_x_preferred":[
        "\u1014\u103d\u102d\u102f\u1004\u103a\u1018\u102d\u102f\u1004\u103a \u1021\u1015\u103c\u100a\u103a\u1015\u103c\u100a\u103a\u1006\u102d\u102f\u1004\u103a\u101b\u102c \u101c\u1031\u1006\u102d\u1015\u103a"
    ],
    "name:ron_x_preferred":[
        "Aeroportul Interna\u021bional Noi Bai"
    ],
    "name:rus_x_preferred":[
        "\u0425\u0430\u043d\u043e\u0439"
    ],
    "name:sco_x_preferred":[
        "Noi Bai Internaitional Airport"
    ],
    "name:swe_x_preferred":[
        "Noi Bai Internationell flygplats"
    ],
    "name:tha_x_preferred":[
        "\u0e17\u0e48\u0e32\u0e2d\u0e32\u0e01\u0e32\u0e28\u0e22\u0e32\u0e19\u0e19\u0e32\u0e19\u0e32\u0e0a\u0e32\u0e15\u0e34\u0e42\u0e2b\u0e19\u0e48\u0e22\u0e1a\u0e48\u0e32\u0e22"
    ],
    "name:ukr_x_preferred":[
        "\u0425\u0430\u043d\u043e\u0439"
    ],
    "name:wuu_x_preferred":[
        "\u5167\u6392\u56fd\u9645\u673a\u573a"
    ],
    "name:yue_x_preferred":[
        "\u5167\u6392\u570b\u969b\u6a5f\u5834"
    ],
    "name:zho_x_preferred":[
        "\u5167\u6392\u570b\u969b\u6a5f\u5834"
    ],
    "oa:elevation_ft":"39",
    "oa:type":"large_airport",
    "woe:hierarchy":{
        "country_id":23424984,
        "planet_id":1,
        "state_id":20070090
    },
    "wof:name":"Noi Bai Airport",
    "wof:placetype":"campus"
},
  "geometry": {"coordinates":[105.80722222222001,21.221111111111],"type":"Point"}
}