{
  "type": "Feature",
  "properties": {
    "date:inception_lower": "1978-01-02",
    "date:inception_upper": "1978-01-02",
    "iso:country": "VN",
    "name:ara_x_preferred": [
      "مطار نوي باي الدولي"
    ],
    "name:bel_x_preferred": [
      "Міжнародны аэрапорт Найбай"
    ],
    "name:ces_x_preferred": [
      "Letiště Nội Bài"
    ],
    "name:deu_x_preferred": [
      "Flughafen Hanoi"
    ],
    "name:eng_x_variant": [
      "HAN",
      "VVNB"
    ],
    "name:est_x_preferred": [
      "Noi Bai rahvusvaheline lennujaam"
    ],
    "name:fas_x_preferred": [
      "فرودگاه بین‌المللی نوا به"
    ],
    "name:fin_x_preferred": [
      "Noi Bain kansainvälinen lentoasema"
    ],
    "name:ind_x_preferred": [
      "Bandar Udara Internasional Noi Bai"
    ],
    "name:ita_x_preferred": [
      "Aeroporto Internazionale Noi Bai"
    ],
    "name:jpn_x_preferred": [
      "ノイバイ国際空港"
    ],
    "name:kor_x_preferred": [
      "노이바이 국제공항"
    ],
    "name:msa_x_preferred": [
      "Lapangan Terbang Antarabangsa Noibai"
    ],
    "name:mya_x_preferred": [
      "နွိုင်ဘိုင် အပြည်ပြည်ဆိုင်ရာ လေဆိပ်"
    ],
    "name:ron_x_preferred": [
      "Aeroportul Internațional Noi Bai"
    ],
    "name:rus_x_preferred": [
      "Ханой"
    ],
    "name:sco_x_preferred": [
      "Noi Bai Internaitional Airport"
    ],
    "name:swe_x_preferred": [
      "Noi Bai Internationell flygplats"
    ],
    "name:tha_x_preferred": [
      "ท่าอากาศยานนานาชาติโหน่ยบ่าย"
    ],
    "name:ukr_x_preferred": [
      "Ханой"
    ],
    "name:wuu_x_preferred": [
      "內排国际机场"
    ],
    "name:yue_x_preferred": [
      "內排國際機場"
    ],
    "name:zho_x_preferred": [
      "內排國際機場"
    ],
    "oa:elevation_ft": "39",
    "oa:type": "large_airport",
    "woe:hierarchy": {
      "country_id": 23424984,
      "planet_id": 1,
      "state_id": 20070090
    },
    "wof:name": "Noi Bai Airport",
    "wof:placetype": "campus"
  },
  "geometry": {"coordinates":[105.807222,21.221111],"type":"Point"}
}
