{
  "type": "Feature",
  "properties": {
    "gn:admin1_code":"32.0",
    "gn:asciiname":"Ta Sinh",
    "gn:country_code":"VN",
    "gn:dem":599,
    "gn:feature_class":"P",
    "gn:feature_code":"PPL",
    "gn:name":"Ta Sinh",
    "gn:population":0,
    "gn:timezone":"Asia/Ho_Chi_Minh",
    "iso:country":"VN",
    "name:vie_x_preferred":[
        "Ta Sinh"
    ],
    "wof:name":"Ta Sinh",
    "wof:placetype":"locality"
},
  "geometry": {"coordinates":[104.04510999999999,21.23323],"type":"Point"}
}