{
  "type": "Feature",
  "properties": {
    "gn:admin1_code":"83.0",
    "gn:asciiname":"Na Dong",
    "gn:country_code":"VN",
    "gn:dem":96,
    "gn:feature_class":"P",
    "gn:feature_code":"PPL",
    "gn:name":"N\u00e0 \u0110\u1ed3ng",
    "gn:population":0,
    "gn:timezone":"Asia/Ho_Chi_Minh",
    "iso:country":"VN",
    "name:vie_x_preferred":[
        "N\u00e0 \u0110\u1ed3ng"
    ],
    "wof:name":"Na Dong",
    "wof:placetype":"locality"
},
  "geometry": {"coordinates":[105.01327000000001,21.21792],"type":"Point"}
}