{
  "type": "Feature",
  "properties": {
    "gn:admin1_code":"65.0",
    "gn:asciiname":"Pray Chop",
    "gn:country_code":"VN",
    "gn:dem":3,
    "gn:feature_class":"P",
    "gn:feature_code":"PPL",
    "gn:name":"Pr\u00e2y Ch\u00f3p",
    "gn:population":0,
    "gn:timezone":"Asia/Ho_Chi_Minh",
    "iso:country":"VN",
    "name:vie_x_preferred":[
        "Pr\u00e2y Ch\u00f3p"
    ],
    "wof:name":"Pray Chop",
    "wof:placetype":"locality"
},
  "geometry": {"coordinates":[105.83958,9.28089],"type":"Point"}
}