{
  "type": "Feature",
  "properties": {
    "gn:admin1_code":"58.0",
    "gn:asciiname":"Ban Chieng",
    "gn:country_code":"VN",
    "gn:dem":118,
    "gn:feature_class":"P",
    "gn:feature_code":"PPL",
    "gn:name":"B\u1ea3n Chi\u00eang",
    "gn:population":0,
    "gn:timezone":"Asia/Ho_Chi_Minh",
    "iso:country":"VN",
    "wof:name":"Ban Chieng",
    "wof:placetype":"locality"
},
  "geometry": {"coordinates":[105.18333,19.56667],"type":"Point"}
}