{
  "type": "Feature",
  "properties": {
    "gn:admin1_code":"58.0",
    "gn:asciiname":"Mu Si",
    "gn:country_code":"VN",
    "gn:dem":25,
    "gn:feature_class":"P",
    "gn:feature_code":"PPL",
    "gn:name":"M\u1ee5 S\u0129",
    "gn:population":0,
    "gn:timezone":"Asia/Ho_Chi_Minh",
    "iso:country":"VN",
    "wof:name":"Mu Si",
    "wof:placetype":"locality"
},
  "geometry": {"coordinates":[105.40000000000001,18.63333],"type":"Point"}
}