{
  "type": "Feature",
  "properties": {
    "gn:admin1_code":"68.0",
    "gn:asciiname":"Ban Dong Da",
    "gn:country_code":"VN",
    "gn:dem":237,
    "gn:feature_class":"P",
    "gn:feature_code":"PPL",
    "gn:name":"B\u1ea3n \u0110\u1ed1ng \u0110a",
    "gn:population":0,
    "gn:timezone":"Asia/Ho_Chi_Minh",
    "iso:country":"VN",
    "name:vie_x_preferred":[
        "B\u1ea3n \u0110\u1ed1ng \u0110a"
    ],
    "wof:name":"Ban Dong Da",
    "wof:placetype":"locality"
},
  "geometry": {"coordinates":[105.49363,22.57329],"type":"Point"}
}