{
  "type": "Feature",
  "properties": {
    "gn:admin1_code":"44.0",
    "gn:asciiname":"Thuong Tri",
    "gn:country_code":"VN",
    "gn:dem":7,
    "gn:feature_class":"P",
    "gn:feature_code":"PPL",
    "gn:name":"Th\u01b0\u1ee3ng Tr\u00ec",
    "gn:population":0,
    "gn:timezone":"Asia/Ho_Chi_Minh",
    "iso:country":"VN",
    "wof:name":"Thuong Tri",
    "wof:placetype":"locality"
},
  "geometry": {"coordinates":[105.71666999999999,21.11667000000001],"type":"Point"}
}