{
  "type": "Feature",
  "properties": {
    "gn:admin1_code":"32.0",
    "gn:asciiname":"Ban Cun",
    "gn:country_code":"VN",
    "gn:dem":168,
    "gn:feature_class":"P",
    "gn:feature_code":"PPL",
    "gn:name":"B\u1ea3n Cun",
    "gn:population":0,
    "gn:timezone":"Asia/Ho_Chi_Minh",
    "iso:country":"VN",
    "name:vie_x_preferred":[
        "B\u1ea3n Cun"
    ],
    "wof:name":"Ban Cun",
    "wof:placetype":"locality"
},
  "geometry": {"coordinates":[103.92009,21.63066],"type":"Point"}
}