{
  "type": "Feature",
  "properties": {
    "gn:admin1_code":"50.0",
    "gn:asciiname":"Ban Phin Ty",
    "gn:country_code":"VN",
    "gn:dem":347,
    "gn:feature_class":"P",
    "gn:feature_code":"PPL",
    "gn:name":"B\u1ea3n Ph\u00ecn T\u1ef7",
    "gn:population":0,
    "gn:timezone":"Asia/Ho_Chi_Minh",
    "iso:country":"VN",
    "name:vie_x_preferred":[
        "B\u1ea3n Ph\u00ecn T\u1ef7"
    ],
    "wof:name":"Ban Phin Ty",
    "wof:placetype":"locality"
},
  "geometry": {"coordinates":[105.26814,22.97685],"type":"Point"}
}