{
  "type": "Feature",
  "properties": {
    "gn:admin1_code":"85.0",
    "gn:asciiname":"Xom Hoan",
    "gn:country_code":"VN",
    "gn:dem":94,
    "gn:feature_class":"P",
    "gn:feature_code":"PPL",
    "gn:name":"X\u00f3m Hoan",
    "gn:population":0,
    "gn:timezone":"Asia/Ho_Chi_Minh",
    "iso:country":"VN",
    "name:vie_x_preferred":[
        "X\u00f3m Hoan"
    ],
    "wof:name":"Xom Hoan",
    "wof:placetype":"locality"
},
  "geometry": {"coordinates":[105.99285,21.65922],"type":"Point"}
}