{
  "type": "Feature",
  "properties": {
    "gn:admin1_code":"46.0",
    "gn:asciiname":"Kon Djirang Tih",
    "gn:country_code":"VN",
    "gn:dem":99,
    "gn:feature_class":"P",
    "gn:feature_code":"PPL",
    "gn:name":"Kon Djirang Tih",
    "gn:population":0,
    "gn:timezone":"Asia/Ho_Chi_Minh",
    "iso:country":"VN",
    "name:und_x_variant":[
        "Kon Djirang",
        "Kon Djirang Tih"
    ],
    "wof:name":"Kon Djirang Tih",
    "wof:placetype":"locality"
},
  "geometry": {"coordinates":[108.76667,14.28333],"type":"Point"}
}