{
  "type": "Feature",
  "properties": {
    "gn:admin1_code":"52.0",
    "gn:asciiname":"Xom Nay",
    "gn:country_code":"VN",
    "gn:dem":10,
    "gn:feature_class":"P",
    "gn:feature_code":"PPL",
    "gn:name":"X\u00f3m N\u1eady",
    "gn:population":0,
    "gn:timezone":"Asia/Ho_Chi_Minh",
    "iso:country":"VN",
    "name:vie_x_preferred":[
        "X\u00f3m N\u1eady"
    ],
    "wof:name":"Xom Nay",
    "wof:placetype":"locality"
},
  "geometry": {"coordinates":[105.89315000000001,18.28497],"type":"Point"}
}