{
  "type": "Feature",
  "properties": {
    "gn:admin1_code":"78.0",
    "gn:asciiname":"Co Man",
    "gn:country_code":"VN",
    "gn:dem":0,
    "gn:feature_class":"P",
    "gn:feature_code":"PPL",
    "gn:name":"C\u1ed5 M\u00e2n",
    "gn:population":0,
    "gn:timezone":"Asia/Ho_Chi_Minh",
    "iso:country":"VN",
    "wof:name":"Co Man",
    "wof:placetype":"locality"
},
  "geometry": {"coordinates":[108.21666999999999,15.98333],"type":"Point"}
}