{
  "type": "Feature",
  "properties": {
    "gn:admin1_code":"54.0",
    "gn:asciiname":"Suoi Hoa Hai",
    "gn:country_code":"VN",
    "gn:dem":15,
    "gn:feature_class":"P",
    "gn:feature_code":"PPL",
    "gn:name":"Su\u1ed1i H\u00f2a Hai",
    "gn:population":0,
    "gn:timezone":"Asia/Ho_Chi_Minh",
    "iso:country":"VN",
    "name:vie_x_preferred":[
        "Su\u1ed1i H\u00f2a Hai"
    ],
    "name:vie_x_variant":[
        "Su\u1ed1i H\u00f2a",
        "Su\u1ed1i H\u00f2a 2"
    ],
    "wof:name":"Suoi Hoa Hai",
    "wof:placetype":"locality"
},
  "geometry": {"coordinates":[109.16561000000002,12.04874],"type":"Point"}
}