{
  "type": "Feature",
  "properties": {
    "gn:admin1_code":"44.0",
    "gn:asciiname":"Phu Lo",
    "gn:country_code":"VN",
    "gn:dem":15,
    "gn:feature_class":"P",
    "gn:feature_code":"PPL",
    "gn:name":"Ph\u00f9 L\u1ed7",
    "gn:population":0,
    "gn:timezone":"Asia/Ho_Chi_Minh",
    "iso:country":"VN",
    "name:und_x_variant":[
        "Phu Lo Dong",
        "Ph\u00f9 L\u1ed7"
    ],
    "wof:name":"Phu Lo",
    "wof:placetype":"locality"
},
  "geometry": {"coordinates":[105.84889,21.19942],"type":"Point"}
}