{
  "type": "Feature",
  "properties": {
    "gn:admin1_code":"88.0",
    "gn:asciiname":"Ninh Thanh Hai",
    "gn:country_code":"VN",
    "gn:dem":473,
    "gn:feature_class":"P",
    "gn:feature_code":"PPL",
    "gn:name":"Ninh Thanh Hai",
    "gn:population":0,
    "gn:timezone":"Asia/Ho_Chi_Minh",
    "iso:country":"VN",
    "name:vie_x_preferred":[
        "Ninh Thanh Hai"
    ],
    "name:vie_x_variant":[
        "Ninh Thanh 2"
    ],
    "wof:name":"Ninh Thanh Hai",
    "wof:placetype":"locality"
},
  "geometry": {"coordinates":[108.45289,12.78314],"type":"Point"}
}