{
  "type": "Feature",
  "properties": {
    "gn:admin1_code":"70.0",
    "gn:asciiname":"Tchen Kien",
    "gn:country_code":"VN",
    "gn:dem":396,
    "gn:feature_class":"P",
    "gn:feature_code":"PPL",
    "gn:name":"Tchen Kien",
    "gn:population":0,
    "gn:timezone":"Asia/Ho_Chi_Minh",
    "iso:country":"VN",
    "wof:name":"Tchen Kien",
    "wof:placetype":"locality"
},
  "geometry": {"coordinates":[104.46666999999999,21.66667],"type":"Point"}
}