{
  "type": "Feature",
  "properties": {
    "gn:admin1_code":"58.0",
    "gn:asciiname":"Dat Thit",
    "gn:country_code":"VN",
    "gn:dem":29,
    "gn:feature_class":"P",
    "gn:feature_code":"PPL",
    "gn:name":"\u0110\u1ea5t Th\u1ecbt",
    "gn:population":0,
    "gn:timezone":"Asia/Ho_Chi_Minh",
    "iso:country":"VN",
    "wof:name":"Dat Thit",
    "wof:placetype":"locality"
},
  "geometry": {"coordinates":[105.58333,19.26667],"type":"Point"}
}