{
  "type": "Feature",
  "properties": {
    "gn:admin1_code":"19.0",
    "gn:asciiname":"Nam Lao",
    "gn:country_code":"VN",
    "gn:dem":818,
    "gn:feature_class":"P",
    "gn:feature_code":"PPL",
    "gn:name":"Nam Lao",
    "gn:population":0,
    "gn:timezone":"Asia/Ho_Chi_Minh",
    "iso:country":"VN",
    "wof:name":"Nam Lao",
    "wof:placetype":"locality"
},
  "geometry": {"coordinates":[103.71666999999999,21.88333],"type":"Point"}
}