{
  "type": "Feature",
  "properties": {
    "gn:admin1_code":"32.0",
    "gn:asciiname":"Ban Po",
    "gn:country_code":"VN",
    "gn:dem":646,
    "gn:feature_class":"P",
    "gn:feature_code":"PPL",
    "gn:name":"B\u1ea3n P\u00f3",
    "gn:population":0,
    "gn:timezone":"Asia/Ho_Chi_Minh",
    "iso:country":"VN",
    "name:und_x_variant":[
        "B\u1ea3n Po"
    ],
    "name:vie_x_preferred":[
        "B\u1ea3n P\u00f3"
    ],
    "wof:name":"Ban Po",
    "wof:placetype":"locality"
},
  "geometry": {"coordinates":[104.11895,21.11928],"type":"Point"}
}