{
  "type": "Feature",
  "properties": {
    "gn:admin1_code":"80.0",
    "gn:asciiname":"An Tap",
    "gn:country_code":"VN",
    "gn:dem":6,
    "gn:feature_class":"P",
    "gn:feature_code":"PPL",
    "gn:name":"An T\u1eadp",
    "gn:population":0,
    "gn:timezone":"Asia/Ho_Chi_Minh",
    "iso:country":"VN",
    "name:vie_x_preferred":[
        "An T\u1eadp"
    ],
    "wof:name":"An Tap",
    "wof:placetype":"locality"
},
  "geometry": {"coordinates":[106.02461,20.49185],"type":"Point"}
}