{
  "type": "Feature",
  "properties": {
    "gn:admin1_code":"43.0",
    "gn:asciiname":"Binh Loc",
    "gn:country_code":"VN",
    "gn:dem":150,
    "gn:feature_class":"P",
    "gn:feature_code":"PPL",
    "gn:name":"B\u00ecnh L\u1ed9c",
    "gn:population":0,
    "gn:timezone":"Asia/Ho_Chi_Minh",
    "iso:country":"VN",
    "name:und_x_variant":[
        "\u0110\u0129nh B\u0129nh L\u1ed9c"
    ],
    "name:vie_x_preferred":[
        "B\u00ecnh L\u1ed9c"
    ],
    "wof:name":"Binh Loc",
    "wof:placetype":"locality"
},
  "geometry": {"coordinates":[107.23833999999999,10.97165],"type":"Point"}
}