{
  "type": "Feature",
  "properties": {
    "gn:admin1_code":"30.0",
    "gn:asciiname":"Vinh Thuc Nung",
    "gn:country_code":"VN",
    "gn:dem":0,
    "gn:feature_class":"P",
    "gn:feature_code":"PPL",
    "gn:name":"V\u0129nh Th\u1ef1c N\u00f9ng",
    "gn:population":0,
    "gn:timezone":"Asia/Ho_Chi_Minh",
    "iso:country":"VN",
    "wof:name":"Vinh Thuc Nung",
    "wof:placetype":"locality"
},
  "geometry": {"coordinates":[107.86667,21.36667000000001],"type":"Point"}
}