{
  "type": "Feature",
  "properties": {
    "gn:admin1_code":"71.0",
    "gn:asciiname":"Khuon Dong",
    "gn:country_code":"VN",
    "gn:dem":49,
    "gn:feature_class":"P",
    "gn:feature_code":"PPL",
    "gn:name":"Khu\u00f4n \u0110\u1ed1ng",
    "gn:population":0,
    "gn:timezone":"Asia/Ho_Chi_Minh",
    "iso:country":"VN",
    "name:vie_x_preferred":[
        "Khu\u00f4n \u0110\u1ed1ng"
    ],
    "wof:name":"Khuon Dong",
    "wof:placetype":"locality"
},
  "geometry": {"coordinates":[106.10375999999999,21.58403],"type":"Point"}
}