{
  "type": "Feature",
  "properties": {
    "gn:admin1_code":"68.0",
    "gn:asciiname":"Cay Vai",
    "gn:country_code":"VN",
    "gn:dem":50,
    "gn:feature_class":"P",
    "gn:feature_code":"PPL",
    "gn:name":"C\u00e2y V\u1ea3i",
    "gn:population":0,
    "gn:timezone":"Asia/Ho_Chi_Minh",
    "iso:country":"VN",
    "name:vie_x_preferred":[
        "C\u00e2y V\u1ea3i"
    ],
    "wof:name":"Cay Vai",
    "wof:placetype":"locality"
},
  "geometry": {"coordinates":[105.11487,21.97998],"type":"Point"}
}