{
  "type": "Feature",
  "properties": {
    "gn:admin1_code":"23.0",
    "gn:asciiname":"Ap Lam Lac",
    "gn:country_code":"VN",
    "gn:dem":755,
    "gn:feature_class":"P",
    "gn:feature_code":"PPL",
    "gn:name":"\u1ea4p L\u00e2m L\u1ea1c",
    "gn:population":0,
    "gn:timezone":"Asia/Ho_Chi_Minh",
    "iso:country":"VN",
    "wof:name":"Ap Lam Lac",
    "wof:placetype":"locality"
},
  "geometry": {"coordinates":[107.91667,11.51667],"type":"Point"}
}