{
  "type": "Feature",
  "properties": {
    "gn:admin1_code":"5.0",
    "gn:asciiname":"Coc Sau",
    "gn:country_code":"VN",
    "gn:dem":395,
    "gn:feature_class":"P",
    "gn:feature_code":"PPL",
    "gn:name":"C\u1ed1c S\u00e2u",
    "gn:population":0,
    "gn:timezone":"Asia/Ho_Chi_Minh",
    "iso:country":"VN",
    "name:vie_x_preferred":[
        "C\u1ed1c S\u00e2u"
    ],
    "wof:name":"Coc Sau",
    "wof:placetype":"locality"
},
  "geometry": {"coordinates":[105.57632,23.03788],"type":"Point"}
}