{
  "type": "Feature",
  "properties": {
    "gn:admin1_code":"93.0",
    "gn:asciiname":"Vinh Thuan Dong",
    "gn:country_code":"VN",
    "gn:dem":1,
    "gn:feature_class":"P",
    "gn:feature_code":"PPL",
    "gn:name":"V\u0129nh Thu\u1eadn \u0110\u00f4ng",
    "gn:population":0,
    "gn:timezone":"Asia/Ho_Chi_Minh",
    "iso:country":"VN",
    "name:und_x_variant":[
        "Vinh Thuanh Dong",
        "V\u0129nh Thu\u1eadn \u0110\u00f4ng"
    ],
    "wof:name":"Vinh Thuan Dong",
    "wof:placetype":"locality"
},
  "geometry": {"coordinates":[105.45638999999998,9.72111],"type":"Point"}
}