{
  "type": "Feature",
  "properties": {
    "gn:admin1_code":"68.0",
    "gn:asciiname":"Tien Thanh",
    "gn:country_code":"VN",
    "gn:dem":290,
    "gn:feature_class":"P",
    "gn:feature_code":"PPL",
    "gn:name":"Ti\u1ebfn Th\u00e0nh",
    "gn:population":0,
    "gn:timezone":"Asia/Ho_Chi_Minh",
    "iso:country":"VN",
    "name:vie_x_preferred":[
        "Ti\u1ebfn Th\u00e0nh"
    ],
    "wof:name":"Tien Thanh",
    "wof:placetype":"locality"
},
  "geometry": {"coordinates":[105.26112000000001,21.9891],"type":"Point"}
}