{
  "type": "Feature",
  "properties": {
    "gn:admin1_code":"5.0",
    "gn:asciiname":"Na Giu",
    "gn:cc2":"VN",
    "gn:country_code":"VN",
    "gn:dem":512,
    "gn:feature_class":"P",
    "gn:feature_code":"PPL",
    "gn:name":"N\u00e0 Giu",
    "gn:population":0,
    "gn:timezone":"Asia/Ho_Chi_Minh",
    "iso:country":"VN",
    "name:und_x_variant":[
        "Na Ciu",
        "N\u00e0 Giu"
    ],
    "wof:name":"Na Giu",
    "wof:placetype":"locality"
},
  "geometry": {"coordinates":[106.41667,22.63333],"type":"Point"}
}