{
  "type": "Feature",
  "properties": {
    "gn:admin1_code":"52.0",
    "gn:asciiname":"Xom Dau Xa",
    "gn:country_code":"VN",
    "gn:dem":228,
    "gn:feature_class":"P",
    "gn:feature_code":"PPL",
    "gn:name":"Xom Dau Xa",
    "gn:population":0,
    "gn:timezone":"Asia/Ho_Chi_Minh",
    "iso:country":"VN",
    "name:und_x_variant":[
        "\u0110\u1eadu X\u00e1"
    ],
    "wof:name":"Xom Dau Xa",
    "wof:placetype":"locality"
},
  "geometry": {"coordinates":[106.28333000000001,18.15],"type":"Point"}
}