{
  "type": "Feature",
  "properties": {
    "gn:admin1_code":"30.0",
    "gn:asciiname":"Thi Tran Dong Trieu",
    "gn:country_code":"VN",
    "gn:dem":5,
    "gn:feature_class":"P",
    "gn:feature_code":"PPL",
    "gn:name":"Th\u1ecb Tr\u1ea5n \u0110\u00f4ng Tri\u1ec1u",
    "gn:population":0,
    "gn:timezone":"Asia/Ho_Chi_Minh",
    "iso:country":"VN",
    "name:und_x_variant":[
        "\u0110\u00f4ng Tri\u1ec1u"
    ],
    "name:vie_x_preferred":[
        "Th\u1ecb Tr\u1ea5n \u0110\u00f4ng Tri\u1ec1u"
    ],
    "wof:name":"Thi Tran Dong Trieu",
    "wof:placetype":"locality"
},
  "geometry": {"coordinates":[106.5138,21.08242000000001],"type":"Point"}
}