{
  "type": "Feature",
  "properties": {
    "gn:admin1_code":"3.0",
    "gn:asciiname":"Ap Giao Thanh",
    "gn:cc2":"VN",
    "gn:country_code":"VN",
    "gn:dem":3,
    "gn:feature_class":"P",
    "gn:feature_code":"PPL",
    "gn:name":"\u1ea4p Giao Th\u1ea1nh",
    "gn:population":0,
    "gn:timezone":"Asia/Ho_Chi_Minh",
    "iso:country":"VN",
    "name:und_x_variant":[
        "Giao Th\u1ea1nh",
        "\u1ea4p Giao Th\u1ea1nh"
    ],
    "wof:name":"Ap Giao Thanh",
    "wof:placetype":"locality"
},
  "geometry": {"coordinates":[106.61417,9.8925],"type":"Point"}
}