{
  "type": "Feature",
  "properties": {
    "gn:admin1_code":"65.0",
    "gn:asciiname":"Xom Phu Huu",
    "gn:country_code":"VN",
    "gn:dem":3,
    "gn:feature_class":"P",
    "gn:feature_code":"PPL",
    "gn:name":"X\u00f3m Ph\u00fa H\u1eefu",
    "gn:population":0,
    "gn:timezone":"Asia/Ho_Chi_Minh",
    "iso:country":"VN",
    "name:und_x_variant":[
        "Phu Huu",
        "X\u00f3m Ph\u00fa H\u1eefu"
    ],
    "wof:name":"Xom Phu Huu",
    "wof:placetype":"locality"
},
  "geometry": {"coordinates":[106.06667,9.66667],"type":"Point"}
}