{
  "type": "Feature",
  "properties": {
    "gn:admin1_code":"89.0",
    "gn:asciiname":"Phi Chi A",
    "gn:country_code":"VN",
    "gn:dem":655,
    "gn:feature_class":"P",
    "gn:feature_code":"PPL",
    "gn:name":"Ph\u00ed Chi A",
    "gn:population":0,
    "gn:timezone":"Asia/Ho_Chi_Minh",
    "iso:country":"VN",
    "name:vie_x_preferred":[
        "Ph\u00ed Chi A"
    ],
    "wof:name":"Phi Chi A",
    "wof:placetype":"locality"
},
  "geometry": {"coordinates":[102.84389,22.44981],"type":"Point"}
}