{
  "type": "Feature",
  "properties": {
    "gn:admin1_code":"72.0",
    "gn:asciiname":"Na Lai",
    "gn:country_code":"VN",
    "gn:dem":456,
    "gn:feature_class":"P",
    "gn:feature_code":"PPL",
    "gn:name":"Na Lai",
    "gn:population":0,
    "gn:timezone":"Asia/Ho_Chi_Minh",
    "iso:country":"VN",
    "name:und_x_variant":[
        "Na La",
        "Na Lai"
    ],
    "wof:name":"Na Lai",
    "wof:placetype":"locality"
},
  "geometry": {"coordinates":[105.63333,22.13333],"type":"Point"}
}