{
  "type": "Feature",
  "properties": {
    "gn:admin1_code":"67.0",
    "gn:asciiname":"Rach Giong",
    "gn:country_code":"VN",
    "gn:dem":3,
    "gn:feature_class":"P",
    "gn:feature_code":"PPL",
    "gn:name":"R\u1ea1ch Gi\u00f2ng",
    "gn:population":0,
    "gn:timezone":"Asia/Ho_Chi_Minh",
    "iso:country":"VN",
    "name:vie_x_preferred":[
        "R\u1ea1ch Gi\u00f2ng"
    ],
    "wof:name":"Rach Giong",
    "wof:placetype":"locality"
},
  "geometry": {"coordinates":[106.52093000000001,9.86359],"type":"Point"}
}