{
  "type": "Feature",
  "properties": {
    "gn:admin1_code":"50.0",
    "gn:asciiname":"Ban Tham Li",
    "gn:country_code":"VN",
    "gn:dem":816,
    "gn:feature_class":"P",
    "gn:feature_code":"PPL",
    "gn:name":"B\u1ea3n Th\u00e2m L\u0129",
    "gn:population":0,
    "gn:timezone":"Asia/Ho_Chi_Minh",
    "iso:country":"VN",
    "name:vie_x_preferred":[
        "B\u1ea3n Th\u00e2m L\u0129"
    ],
    "wof:name":"Ban Tham Li",
    "wof:placetype":"locality"
},
  "geometry": {"coordinates":[105.2925,22.8016],"type":"Point"}
}