{
  "type": "Feature",
  "properties": {
    "gn:admin1_code":"33.0",
    "gn:asciiname":"Chom Dua",
    "gn:country_code":"VN",
    "gn:dem":14,
    "gn:feature_class":"P",
    "gn:feature_code":"PPL",
    "gn:name":"Ch\u00f2m D\u1eeba",
    "gn:population":0,
    "gn:timezone":"Asia/Ho_Chi_Minh",
    "iso:country":"VN",
    "name:vie_x_preferred":[
        "Ch\u00f2m D\u1eeba"
    ],
    "wof:name":"Chom Dua",
    "wof:placetype":"locality"
},
  "geometry": {"coordinates":[106.02518999999999,11.39321],"type":"Point"}
}