{
  "type": "Feature",
  "properties": {
    "gn:admin1_code":"32.0",
    "gn:asciiname":"Ban Pu Tau",
    "gn:country_code":"VN",
    "gn:dem":1055,
    "gn:feature_class":"P",
    "gn:feature_code":"PPL",
    "gn:name":"B\u1ea3n P\u00fa T\u1ea1u",
    "gn:population":0,
    "gn:timezone":"Asia/Ho_Chi_Minh",
    "iso:country":"VN",
    "name:vie_x_preferred":[
        "B\u1ea3n P\u00fa T\u1ea1u"
    ],
    "wof:name":"Ban Pu Tau",
    "wof:placetype":"locality"
},
  "geometry": {"coordinates":[103.90645000000001,21.13726],"type":"Point"}
}