{
  "type": "Feature",
  "properties": {
    "gn:admin1_code":"92.0",
    "gn:asciiname":"Huoi Van",
    "gn:country_code":"VN",
    "gn:dem":869,
    "gn:feature_class":"P",
    "gn:feature_code":"PPL",
    "gn:name":"Hu\u1ed5i Van",
    "gn:population":0,
    "gn:timezone":"Asia/Ho_Chi_Minh",
    "iso:country":"VN",
    "name:vie_x_preferred":[
        "Hu\u1ed5i Van"
    ],
    "wof:name":"Huoi Van",
    "wof:placetype":"locality"
},
  "geometry": {"coordinates":[103.05012000000001,21.97733],"type":"Point"}
}