{
  "type": "Feature",
  "properties": {
    "gn:admin1_code":"39.0",
    "gn:asciiname":"Na Tat",
    "gn:country_code":"VN",
    "gn:dem":487,
    "gn:feature_class":"P",
    "gn:feature_code":"PPL",
    "gn:name":"N\u00e0 T\u00e1t",
    "gn:population":0,
    "gn:timezone":"Asia/Ho_Chi_Minh",
    "iso:country":"VN",
    "name:vie_x_preferred":[
        "N\u00e0 T\u00e1t"
    ],
    "wof:name":"Na Tat",
    "wof:placetype":"locality"
},
  "geometry": {"coordinates":[106.35663,21.99948],"type":"Point"}
}