{
  "type": "Feature",
  "properties": {
    "gn:admin1_code":"32.0",
    "gn:asciiname":"Suoi Ke",
    "gn:country_code":"VN",
    "gn:dem":603,
    "gn:feature_class":"P",
    "gn:feature_code":"PPL",
    "gn:name":"Su\u1ed1i K\u00ea",
    "gn:population":0,
    "gn:timezone":"Asia/Ho_Chi_Minh",
    "iso:country":"VN",
    "name:vie_x_preferred":[
        "Su\u1ed1i K\u00ea"
    ],
    "wof:name":"Suoi Ke",
    "wof:placetype":"locality"
},
  "geometry": {"coordinates":[104.76676999999999,21.08512],"type":"Point"}
}