{
  "type": "Feature",
  "properties": {
    "gn:admin1_code":"68.0",
    "gn:asciiname":"Na Heng",
    "gn:country_code":"VN",
    "gn:dem":238,
    "gn:feature_class":"P",
    "gn:feature_code":"PPL",
    "gn:name":"N\u00e0 Heng",
    "gn:population":0,
    "gn:timezone":"Asia/Ho_Chi_Minh",
    "iso:country":"VN",
    "name:und_x_variant":[
        "N\u00e0 Heng",
        "Na Hang"
    ],
    "wof:name":"Na Heng",
    "wof:placetype":"locality"
},
  "geometry": {"coordinates":[105.30938,22.33532],"type":"Point"}
}