{
  "type": "Feature",
  "properties": {
    "gn:admin1_code":"64.0",
    "gn:asciiname":"Khe Ba",
    "gn:country_code":"VN",
    "gn:dem":61,
    "gn:feature_class":"P",
    "gn:feature_code":"PPL",
    "gn:name":"Khe Ba",
    "gn:population":0,
    "gn:timezone":"Asia/Ho_Chi_Minh",
    "iso:country":"VN",
    "name:vie_x_preferred":[
        "Khe Ba"
    ],
    "wof:name":"Khe Ba",
    "wof:placetype":"locality"
},
  "geometry": {"coordinates":[107.09289,17.06429],"type":"Point"}
}