{
  "type": "Feature",
  "properties": {
    "gn:admin1_code":"88.0",
    "gn:asciiname":"Thon Hai Muoi Sau",
    "gn:country_code":"VN",
    "gn:dem":478,
    "gn:feature_class":"P",
    "gn:feature_code":"PPL",
    "gn:name":"Th\u00f4n Hai M\u01b0\u01a1i S\u00e1u",
    "gn:population":0,
    "gn:timezone":"Asia/Ho_Chi_Minh",
    "iso:country":"VN",
    "name:vie_x_preferred":[
        "Th\u00f4n Hai M\u01b0\u01a1i S\u00e1u"
    ],
    "name:vie_x_variant":[
        "Th\u00f4n 26"
    ],
    "wof:name":"Thon Hai Muoi Sau",
    "wof:placetype":"locality"
},
  "geometry": {"coordinates":[108.18874,12.615],"type":"Point"}
}