{
  "type": "Feature",
  "properties": {
    "gn:admin1_code":"34.0",
    "gn:asciiname":"Ban Chao",
    "gn:country_code":"VN",
    "gn:dem":247,
    "gn:feature_class":"P",
    "gn:feature_code":"PPL",
    "gn:name":"B\u1ea3n Ch\u00e1o",
    "gn:population":0,
    "gn:timezone":"Asia/Ho_Chi_Minh",
    "iso:country":"VN",
    "name:azb_x_preferred":[
        "\u0628\u0627\u0646 \u0686\u0627\u0626\u0648"
    ],
    "name:bul_x_preferred":[
        "\u0411\u0430\u043d \u0427\u0430\u043e"
    ],
    "name:cat_x_preferred":[
        "Ban Chao"
    ],
    "name:ces_x_preferred":[
        "Pan \u010cchao"
    ],
    "name:dan_x_preferred":[
        "Ban Chao"
    ],
    "name:deu_x_preferred":[
        "Ban Chao"
    ],
    "name:fra_x_preferred":[
        "Ban Chao"
    ],
    "name:ind_x_preferred":[
        "Ban Chao"
    ],
    "name:ita_x_preferred":[
        "Ban Chao"
    ],
    "name:kaz_x_preferred":[
        "\u0411\u0430\u043d\u044c \u0427\u0430\u043e"
    ],
    "name:nld_x_preferred":[
        "Ban Chao"
    ],
    "name:nor_x_preferred":[
        "Ban Chao"
    ],
    "name:oci_x_preferred":[
        "Ban Chao"
    ],
    "name:pol_x_preferred":[
        "Ban Chao"
    ],
    "name:rus_x_preferred":[
        "\u0411\u0430\u043d\u044c \u0427\u0430\u043e"
    ],
    "name:slv_x_preferred":[
        "Ban Chao"
    ],
    "name:spa_x_preferred":[
        "Ban Chao"
    ],
    "name:swe_x_preferred":[
        "Ban Chao"
    ],
    "name:tur_x_preferred":[
        "Ban Chao"
    ],
    "name:vie_x_preferred":[
        "B\u1ea3n Ch\u00e1o"
    ],
    "name:vie_x_variant":[
        "Ban Si\u00eau"
    ],
    "wof:name":"Ban Chao",
    "wof:placetype":"locality"
},
  "geometry": {"coordinates":[105.03249,20.27685],"type":"Point"}
}