{
  "type": "Feature",
  "properties": {
    "gn:admin1_code":"34.0",
    "gn:asciiname":"Ban Chao",
    "gn:country_code":"VN",
    "gn:dem":247,
    "gn:feature_class":"P",
    "gn:feature_code":"PPL",
    "gn:name":"B\u1ea3n Ch\u00e1o",
    "gn:population":0,
    "gn:timezone":"Asia/Ho_Chi_Minh",
    "iso:country":"VN",
    "name:vie_x_preferred":[
        "B\u1ea3n Ch\u00e1o"
    ],
    "wof:name":"Ban Chao",
    "wof:placetype":"locality"
},
  "geometry": {"coordinates":[105.03249,20.27685],"type":"Point"}
}