{
  "type": "Feature",
  "properties": {
    "gn:admin1_code":"20.0",
    "gn:asciiname":"Khu Pho Ba",
    "gn:country_code":"VN",
    "gn:dem":3,
    "gn:feature_class":"P",
    "gn:feature_code":"PPL",
    "gn:name":"Khu Ph\u1ed1 Ba",
    "gn:population":0,
    "gn:timezone":"Asia/Ho_Chi_Minh",
    "iso:country":"VN",
    "name:vie_x_preferred":[
        "Khu Ph\u1ed1 Ba"
    ],
    "name:vie_x_variant":[
        "Khu Ph\u1ed1 3"
    ],
    "wof:name":"Khu Pho Ba",
    "wof:placetype":"locality"
},
  "geometry": {"coordinates":[106.74751000000001,10.81855],"type":"Point"}
}