{
  "type": "Feature",
  "properties": {
    "gn:admin1_code":"34.0",
    "gn:asciiname":"Phu Ban",
    "gn:country_code":"VN",
    "gn:dem":59,
    "gn:feature_class":"P",
    "gn:feature_code":"PPL",
    "gn:name":"Ph\u00f9 B\u1ea3n",
    "gn:population":0,
    "gn:timezone":"Asia/Ho_Chi_Minh",
    "iso:country":"VN",
    "wof:name":"Phu Ban",
    "wof:placetype":"locality"
},
  "geometry": {"coordinates":[105.71666999999999,20.16667],"type":"Point"}
}