{
  "type": "Feature",
  "properties": {
    "gn:admin1_code":"71.0",
    "gn:asciiname":"Xom Bi",
    "gn:country_code":"VN",
    "gn:dem":13,
    "gn:feature_class":"P",
    "gn:feature_code":"PPL",
    "gn:name":"X\u00f3m Bi",
    "gn:population":0,
    "gn:timezone":"Asia/Ho_Chi_Minh",
    "iso:country":"VN",
    "name:und_x_variant":[
        "Th\u00f4n B\u1ec9"
    ],
    "name:vie_x_preferred":[
        "X\u00f3m Bi"
    ],
    "wof:name":"Xom Bi",
    "wof:placetype":"locality"
},
  "geometry": {"coordinates":[106.07623,21.35438],"type":"Point"}
}