{
  "type": "Feature",
  "properties": {
    "gn:admin1_code":"5.0",
    "gn:asciiname":"Gia Cung",
    "gn:country_code":"VN",
    "gn:dem":200,
    "gn:feature_class":"P",
    "gn:feature_code":"PPL",
    "gn:name":"Gia Cung",
    "gn:population":0,
    "gn:timezone":"Asia/Ho_Chi_Minh",
    "iso:country":"VN",
    "wof:name":"Gia Cung",
    "wof:placetype":"locality"
},
  "geometry": {"coordinates":[106.25,22.68333],"type":"Point"}
}