{
  "type": "Feature",
  "properties": {
    "gn:admin1_code":"84.0",
    "gn:asciiname":"Tien Phuoc",
    "gn:country_code":"VN",
    "gn:dem":54,
    "gn:feature_class":"P",
    "gn:feature_code":"PPLA2",
    "gn:name":"Ti\u00ean Ph\u01b0\u1edbc",
    "gn:population":0,
    "gn:timezone":"Asia/Ho_Chi_Minh",
    "iso:country":"VN",
    "name:und_x_variant":[
        "Ph\u01b0\u1edbc An",
        "Ti\u00ean Ph\u01b0\u1edbc"
    ],
    "name:vie_x_preferred":[
        "Ti\u00ean K\u1ef3"
    ],
    "wof:name":"Tien Phuoc",
    "wof:placetype":"locality"
},
  "geometry": {"coordinates":[108.30736,15.48819],"type":"Point"}
}