{
  "type": "Feature",
  "properties": {
    "gn:admin1_code":"70.0",
    "gn:asciiname":"Dong Ly",
    "gn:country_code":"VN",
    "gn:dem":62,
    "gn:feature_class":"P",
    "gn:feature_code":"PPL",
    "gn:name":"\u0110\u00f4ng L\u00fd",
    "gn:population":0,
    "gn:timezone":"Asia/Ho_Chi_Minh",
    "iso:country":"VN",
    "name:vie_x_preferred":[
        "\u0110\u00f4ng L\u00fd"
    ],
    "wof:name":"Dong Ly",
    "wof:placetype":"locality"
},
  "geometry": {"coordinates":[104.55145,21.98678],"type":"Point"}
}