{
  "type": "Feature",
  "properties": {
    "gn:admin1_code":"53.0",
    "gn:asciiname":"Da Bac",
    "gn:country_code":"VN",
    "gn:dem":280,
    "gn:feature_class":"P",
    "gn:feature_code":"PPLA2",
    "gn:name":"\u0110\u00e0 B\u1eafc",
    "gn:population":0,
    "gn:timezone":"Asia/Ho_Chi_Minh",
    "iso:country":"VN",
    "name:vie_x_preferred":[
        "\u0110\u00e0 B\u1eafc"
    ],
    "wof:name":"Da Bac",
    "wof:placetype":"locality"
},
  "geometry": {"coordinates":[105.25417,20.87714],"type":"Point"}
}