{
  "type": "Feature",
  "properties": {
    "gn:admin1_code":"72.0",
    "gn:asciiname":"Na Ta",
    "gn:country_code":"VN",
    "gn:dem":227,
    "gn:feature_class":"P",
    "gn:feature_code":"PPL",
    "gn:name":"N\u00e0 T\u00e0",
    "gn:population":0,
    "gn:timezone":"Asia/Ho_Chi_Minh",
    "iso:country":"VN",
    "name:und_x_variant":[
        "N\u00e0 T\u00e0",
        "Na Ta"
    ],
    "wof:name":"Na Ta",
    "wof:placetype":"locality"
},
  "geometry": {"coordinates":[105.84535,22.26716],"type":"Point"}
}