{
  "type": "Feature",
  "properties": {
    "gn:admin1_code":"62.0",
    "gn:asciiname":"Thuong Luat",
    "gn:country_code":"VN",
    "gn:dem":-9999,
    "gn:feature_class":"P",
    "gn:feature_code":"PPL",
    "gn:name":"Th\u01b0\u1ee3ng Lu\u00e2t",
    "gn:population":0,
    "gn:timezone":"Asia/Ho_Chi_Minh",
    "iso:country":"VN",
    "wof:name":"Thuong Luat",
    "wof:placetype":"locality"
},
  "geometry": {"coordinates":[106.91667,17.28333],"type":"Point"}
}