{
  "type": "Feature",
  "properties": {
    "gn:admin1_code":"50.0",
    "gn:asciiname":"Dong Rom",
    "gn:country_code":"VN",
    "gn:dem":84,
    "gn:feature_class":"P",
    "gn:feature_code":"PPL",
    "gn:name":"\u0110\u1ed3ng R\u00f4m",
    "gn:population":0,
    "gn:timezone":"Asia/Ho_Chi_Minh",
    "iso:country":"VN",
    "name:vie_x_preferred":[
        "\u0110\u1ed3ng R\u00f4m"
    ],
    "wof:name":"Dong Rom",
    "wof:placetype":"locality"
},
  "geometry": {"coordinates":[104.93404,22.41817],"type":"Point"}
}