{
  "type": "Feature",
  "properties": {
    "gn:admin1_code":"39.0",
    "gn:asciiname":"La Gieo",
    "gn:country_code":"VN",
    "gn:dem":407,
    "gn:feature_class":"P",
    "gn:feature_code":"PPL",
    "gn:name":"La Gieo",
    "gn:population":0,
    "gn:timezone":"Asia/Ho_Chi_Minh",
    "iso:country":"VN",
    "wof:name":"La Gieo",
    "wof:placetype":"locality"
},
  "geometry": {"coordinates":[106.21666999999999,21.88333],"type":"Point"}
}