{
  "type": "Feature",
  "properties": {
    "gn:admin1_code":"63.0",
    "gn:asciiname":"Phuoc Son",
    "gn:country_code":"VN",
    "gn:dem":11,
    "gn:feature_class":"P",
    "gn:feature_code":"PPL",
    "gn:name":"Ph\u01b0\u1edbc S\u01a1n",
    "gn:population":0,
    "gn:timezone":"Asia/Ho_Chi_Minh",
    "iso:country":"VN",
    "name:und_x_variant":[
        "Van Phuoc Hung",
        "Ph\u01b0\u1edbc S\u01a1n"
    ],
    "wof:name":"Phuoc Son",
    "wof:placetype":"locality"
},
  "geometry": {"coordinates":[108.85303999999999,14.99318],"type":"Point"}
}