{
  "type": "Feature",
  "properties": {
    "gn:admin1_code":"49.0",
    "gn:asciiname":"Lang Buc",
    "gn:country_code":"VN",
    "gn:dem":431,
    "gn:feature_class":"P",
    "gn:feature_code":"PPL",
    "gn:name":"L\u00e0ng B\u00fac",
    "gn:population":0,
    "gn:timezone":"Asia/Ho_Chi_Minh",
    "iso:country":"VN",
    "name:und_x_variant":[
        "Plei But"
    ],
    "name:vie_x_preferred":[
        "L\u00e0ng B\u00fac"
    ],
    "wof:name":"Lang Buc",
    "wof:placetype":"locality"
},
  "geometry": {"coordinates":[108.49634,13.96712],"type":"Point"}
}