{
  "type": "Feature",
  "properties": {
    "gn:admin1_code":"49.0",
    "gn:asciiname":"Plei Thaie Namra",
    "gn:country_code":"VN",
    "gn:dem":378,
    "gn:feature_class":"P",
    "gn:feature_code":"PPL",
    "gn:name":"Plei Thaie Namra",
    "gn:population":0,
    "gn:timezone":"Asia/Ho_Chi_Minh",
    "iso:country":"VN",
    "name:und_x_variant":[
        "Plei Thaie Namta",
        "Plei Thaie Namra"
    ],
    "wof:name":"Plei Thaie Namra",
    "wof:placetype":"locality"
},
  "geometry": {"coordinates":[107.98333,13.58333],"type":"Point"}
}