{
  "type": "Feature",
  "properties": {
    "gn:admin1_code":"71.0",
    "gn:asciiname":"Doi Hong",
    "gn:country_code":"VN",
    "gn:dem":78,
    "gn:feature_class":"P",
    "gn:feature_code":"PPL",
    "gn:name":"\u0110\u1ed3i Hong",
    "gn:population":0,
    "gn:timezone":"Asia/Ho_Chi_Minh",
    "iso:country":"VN",
    "wof:name":"Doi Hong",
    "wof:placetype":"locality"
},
  "geometry": {"coordinates":[106.25,21.46667],"type":"Point"}
}