{
  "type": "Feature",
  "properties": {
    "gn:admin1_code":"5.0",
    "gn:asciiname":"Dong Da",
    "gn:country_code":"VN",
    "gn:dem":415,
    "gn:feature_class":"P",
    "gn:feature_code":"PPL",
    "gn:name":"\u0110\u1ed3ng \u0110a",
    "gn:population":0,
    "gn:timezone":"Asia/Ho_Chi_Minh",
    "iso:country":"VN",
    "name:und_x_variant":[
        "\u0110\u1ed3ng \u0110a"
    ],
    "wof:name":"Dong Da",
    "wof:placetype":"locality"
},
  "geometry": {"coordinates":[106.40000000000001,22.63333],"type":"Point"}
}