{
  "type": "Feature",
  "properties": {
    "gn:admin1_code":"69.0",
    "gn:asciiname":"Nga Tu",
    "gn:country_code":"VN",
    "gn:dem":0,
    "gn:feature_class":"P",
    "gn:feature_code":"PPL",
    "gn:name":"Ng\u00e3 T\u01b0",
    "gn:population":0,
    "gn:timezone":"Asia/Ho_Chi_Minh",
    "iso:country":"VN",
    "wof:name":"Nga Tu",
    "wof:placetype":"locality"
},
  "geometry": {"coordinates":[106.01667,10.18333],"type":"Point"}
}