{
  "type": "Feature",
  "properties": {
    "gn:admin1_code":"83.0",
    "gn:asciiname":"Da Tho",
    "gn:country_code":"VN",
    "gn:dem":43,
    "gn:feature_class":"P",
    "gn:feature_code":"PPL",
    "gn:name":"\u0110\u00e1 Th\u01a1",
    "gn:population":0,
    "gn:timezone":"Asia/Ho_Chi_Minh",
    "iso:country":"VN",
    "name:vie_x_preferred":[
        "\u0110\u00e1 Th\u01a1"
    ],
    "wof:name":"Da Tho",
    "wof:placetype":"locality"
},
  "geometry": {"coordinates":[105.08843,21.36513],"type":"Point"}
}