{
  "type": "Feature",
  "properties": {
    "gn:admin1_code":"63.0",
    "gn:asciiname":"Dong Phuoc",
    "gn:country_code":"VN",
    "gn:dem":15,
    "gn:feature_class":"P",
    "gn:feature_code":"PPL",
    "gn:name":"\u0110\u00f4ng Ph\u01b0\u1edbc",
    "gn:population":0,
    "gn:timezone":"Asia/Ho_Chi_Minh",
    "iso:country":"VN",
    "wof:name":"Dong Phuoc",
    "wof:placetype":"locality"
},
  "geometry": {"coordinates":[108.81667,15.25],"type":"Point"}
}