{
  "type": "Feature",
  "properties": {
    "gn:admin1_code":"37.0",
    "gn:asciiname":"Xom Huong Luu",
    "gn:country_code":"VN",
    "gn:dem":3,
    "gn:feature_class":"P",
    "gn:feature_code":"PPL",
    "gn:name":"X\u00f3m H\u01b0\u01a1ng L\u01b0u",
    "gn:population":0,
    "gn:timezone":"Asia/Ho_Chi_Minh",
    "iso:country":"VN",
    "wof:name":"Xom Huong Luu",
    "wof:placetype":"locality"
},
  "geometry": {"coordinates":[106.66667,10.43333],"type":"Point"}
}