{
  "type": "Feature",
  "properties": {
    "gn:admin1_code":"39.0",
    "gn:asciiname":"Keng Nong",
    "gn:country_code":"VN",
    "gn:dem":220,
    "gn:feature_class":"P",
    "gn:feature_code":"PPL",
    "gn:name":"Keng Nong",
    "gn:population":0,
    "gn:timezone":"Asia/Ho_Chi_Minh",
    "iso:country":"VN",
    "wof:name":"Keng Nong",
    "wof:placetype":"locality"
},
  "geometry": {"coordinates":[106.59999999999999,22.06667],"type":"Point"}
}