{
  "type": "Feature",
  "properties": {
    "gn:admin1_code":"93.0",
    "gn:asciiname":"Ap Vinh Thanh",
    "gn:country_code":"VN",
    "gn:dem":2,
    "gn:feature_class":"P",
    "gn:feature_code":"PPL",
    "gn:name":"\u1ea4p V\u0129nh Thanh",
    "gn:population":0,
    "gn:timezone":"Asia/Ho_Chi_Minh",
    "iso:country":"VN",
    "name:und_x_variant":[
        "\u1ea4p V\u0129nh Thanh"
    ],
    "name:vie_x_preferred":[
        "V\u0129nh Thanh"
    ],
    "wof:name":"Ap Vinh Thanh",
    "wof:placetype":"locality"
},
  "geometry": {"coordinates":[105.55889000000001,9.76889],"type":"Point"}
}