{
  "type": "Feature",
  "properties": {
    "gn:admin1_code":"52.0",
    "gn:asciiname":"Lien Hop",
    "gn:country_code":"VN",
    "gn:dem":6,
    "gn:feature_class":"P",
    "gn:feature_code":"PPL",
    "gn:name":"Li\u00ean H\u1ee3p",
    "gn:population":0,
    "gn:timezone":"Asia/Ho_Chi_Minh",
    "iso:country":"VN",
    "name:vie_x_preferred":[
        "Li\u00ean H\u1ee3p"
    ],
    "wof:name":"Lien Hop",
    "wof:placetype":"locality"
},
  "geometry": {"coordinates":[105.87332000000001,18.34938],"type":"Point"}
}