{
  "type": "Feature",
  "properties": {
    "gn:admin1_code":"90.0",
    "gn:asciiname":"Can Ho Mong",
    "gn:country_code":"VN",
    "gn:dem":1288,
    "gn:feature_class":"P",
    "gn:feature_code":"PPL",
    "gn:name":"Can H\u1ed3 M\u00f4ng",
    "gn:population":0,
    "gn:timezone":"Asia/Ho_Chi_Minh",
    "iso:country":"VN",
    "name:und_x_variant":[
        "Can H\u1ed3 M\u00e8o",
        "Can H\u1ed3 M\u00e1n"
    ],
    "name:vie_x_preferred":[
        "Can H\u1ed3 M\u00f4ng"
    ],
    "wof:name":"Can Ho Mong",
    "wof:placetype":"locality"
},
  "geometry": {"coordinates":[103.79374,22.39913],"type":"Point"}
}