{
  "type": "Feature",
  "properties": {
    "gn:admin1_code":"69.0",
    "gn:asciiname":"Phu Hung",
    "gn:country_code":"VN",
    "gn:dem":2,
    "gn:feature_class":"P",
    "gn:feature_code":"PPL",
    "gn:name":"Ph\u00fa H\u01b0ng",
    "gn:population":0,
    "gn:timezone":"Asia/Ho_Chi_Minh",
    "iso:country":"VN",
    "name:vie_x_preferred":[
        "Ph\u00fa H\u01b0ng"
    ],
    "wof:name":"Phu Hung",
    "wof:placetype":"locality"
},
  "geometry": {"coordinates":[105.85804,10.11704],"type":"Point"}
}