{
  "type": "Feature",
  "properties": {
    "gn:admin1_code":"79.0",
    "gn:asciiname":"Trai Phong",
    "gn:country_code":"VN",
    "gn:dem":15,
    "gn:feature_class":"P",
    "gn:feature_code":"PPL",
    "gn:name":"Tr\u1ea1i Phong",
    "gn:population":0,
    "gn:timezone":"Asia/Ho_Chi_Minh",
    "iso:country":"VN",
    "name:vie_x_preferred":[
        "Tr\u1ea1i Phong"
    ],
    "wof:name":"Trai Phong",
    "wof:placetype":"locality"
},
  "geometry": {"coordinates":[106.47778999999998,21.13192],"type":"Point"}
}