{
  "type": "Feature",
  "properties": {
    "gn:admin1_code":"32.0",
    "gn:asciiname":"Huoi Hin",
    "gn:country_code":"VN",
    "gn:dem":991,
    "gn:feature_class":"P",
    "gn:feature_code":"PPL",
    "gn:name":"Hu\u1ed5i Hin",
    "gn:population":0,
    "gn:timezone":"Asia/Ho_Chi_Minh",
    "iso:country":"VN",
    "name:vie_x_preferred":[
        "Hu\u1ed5i Hin"
    ],
    "wof:name":"Huoi Hin",
    "wof:placetype":"locality"
},
  "geometry": {"coordinates":[103.85943,20.8777],"type":"Point"}
}