{
  "type": "Feature",
  "properties": {
    "gn:admin1_code":"74.0",
    "gn:asciiname":"Chua Duoi",
    "gn:country_code":"VN",
    "gn:dem":7,
    "gn:feature_class":"P",
    "gn:feature_code":"PPL",
    "gn:name":"Ch\u00f9a Du\u1ed1i",
    "gn:population":0,
    "gn:timezone":"Asia/Ho_Chi_Minh",
    "iso:country":"VN",
    "name:vie_x_preferred":[
        "Ch\u00f9a Du\u1ed1i"
    ],
    "wof:name":"Chua Duoi",
    "wof:placetype":"locality"
},
  "geometry": {"coordinates":[106.20095000000001,21.17255],"type":"Point"}
}