{
  "type": "Feature",
  "properties": {
    "gn:admin1_code":"55.0",
    "gn:asciiname":"Kon Brap",
    "gn:country_code":"VN",
    "gn:dem":832,
    "gn:feature_class":"P",
    "gn:feature_code":"PPL",
    "gn:name":"Kon Brap",
    "gn:population":0,
    "gn:timezone":"Asia/Ho_Chi_Minh",
    "iso:country":"VN",
    "wof:name":"Kon Brap",
    "wof:placetype":"locality"
},
  "geometry": {"coordinates":[108.25,14.46667],"type":"Point"}
}