{
  "type": "Feature",
  "properties": {
    "gn:admin1_code":"50.0",
    "gn:asciiname":"Lang Di",
    "gn:country_code":"VN",
    "gn:dem":102,
    "gn:feature_class":"P",
    "gn:feature_code":"PPL",
    "gn:name":"L\u00e0ng \u0110i",
    "gn:population":0,
    "gn:timezone":"Asia/Ho_Chi_Minh",
    "iso:country":"VN",
    "name:vie_x_preferred":[
        "L\u00e0ng \u0110i"
    ],
    "wof:name":"Lang Di",
    "wof:placetype":"locality"
},
  "geometry": {"coordinates":[105.01989,22.40242000000001],"type":"Point"}
}