{
  "type": "Feature",
  "properties": {
    "gn:admin1_code":"67.0",
    "gn:asciiname":"Soc Chuoc",
    "gn:country_code":"VN",
    "gn:dem":2,
    "gn:feature_class":"P",
    "gn:feature_code":"PPL",
    "gn:name":"S\u00f3c Chu\u1ed1c",
    "gn:population":0,
    "gn:timezone":"Asia/Ho_Chi_Minh",
    "iso:country":"VN",
    "name:vie_x_preferred":[
        "S\u00f3c Chu\u1ed1c"
    ],
    "wof:name":"Soc Chuoc",
    "wof:placetype":"locality"
},
  "geometry": {"coordinates":[106.4066,9.68232],"type":"Point"}
}