{
  "type": "Feature",
  "properties": {
    "gn:admin1_code":"58.0",
    "gn:asciiname":"Muong Xen",
    "gn:country_code":"VN",
    "gn:dem":147,
    "gn:feature_class":"P",
    "gn:feature_code":"PPLA2",
    "gn:name":"M\u01b0\u1eddng X\u00e9n",
    "gn:population":0,
    "gn:timezone":"Asia/Ho_Chi_Minh",
    "iso:country":"VN",
    "name:und_x_variant":[
        "Muong X\u00e9n",
        "Muong Sen",
        "K\u1ef3 S\u01a1n"
    ],
    "name:vie_x_preferred":[
        "M\u01b0\u1eddng X\u00e9n"
    ],
    "wof:name":"Muong Xen",
    "wof:placetype":"locality"
},
  "geometry": {"coordinates":[104.15239,19.39795],"type":"Point"}
}