{
  "type": "Feature",
  "properties": {
    "gn:admin1_code":"63.0",
    "gn:asciiname":"Van An",
    "gn:country_code":"VN",
    "gn:dem":3,
    "gn:feature_class":"P",
    "gn:feature_code":"PPL",
    "gn:name":"Van An",
    "gn:population":0,
    "gn:timezone":"Asia/Ho_Chi_Minh",
    "iso:country":"VN",
    "name:und_x_variant":[
        "Nang Dong",
        "Van An"
    ],
    "wof:name":"Van An",
    "wof:placetype":"locality"
},
  "geometry": {"coordinates":[108.86667,15.06667],"type":"Point"}
}