{
  "type": "Feature",
  "properties": {
    "gn:admin1_code":"49.0",
    "gn:asciiname":"Mit Kom",
    "gn:country_code":"VN",
    "gn:dem":265,
    "gn:feature_class":"P",
    "gn:feature_code":"PPL",
    "gn:name":"M\u00edt Kom",
    "gn:population":0,
    "gn:timezone":"Asia/Ho_Chi_Minh",
    "iso:country":"VN",
    "name:vie_x_preferred":[
        "M\u00edt Kom"
    ],
    "wof:name":"Mit Kom",
    "wof:placetype":"locality"
},
  "geometry": {"coordinates":[107.56614999999999,13.98757],"type":"Point"}
}