{
  "type": "Feature",
  "properties": {
    "gn:admin1_code":"34.0",
    "gn:asciiname":"Loc Trach",
    "gn:country_code":"VN",
    "gn:dem":6,
    "gn:feature_class":"P",
    "gn:feature_code":"PPL",
    "gn:name":"L\u1ed9c Tr\u1ea1ch",
    "gn:population":0,
    "gn:timezone":"Asia/Ho_Chi_Minh",
    "iso:country":"VN",
    "wof:name":"Loc Trach",
    "wof:placetype":"locality"
},
  "geometry": {"coordinates":[105.65000000000001,19.76667],"type":"Point"}
}