{
  "type": "Feature",
  "properties": {
    "gn:admin1_code":"74.0",
    "gn:asciiname":"Ich Phu",
    "gn:country_code":"VN",
    "gn:dem":7,
    "gn:feature_class":"P",
    "gn:feature_code":"PPL",
    "gn:name":"\u00cdch Ph\u00fa",
    "gn:population":0,
    "gn:timezone":"Asia/Ho_Chi_Minh",
    "iso:country":"VN",
    "name:vie_x_preferred":[
        "\u00cdch Ph\u00fa"
    ],
    "wof:name":"Ich Phu",
    "wof:placetype":"locality"
},
  "geometry": {"coordinates":[106.17827,21.08406],"type":"Point"}
}