{
  "type": "Feature",
  "properties": {
    "gn:admin1_code":"90.0",
    "gn:asciiname":"Thin Thung",
    "gn:country_code":"VN",
    "gn:dem":76,
    "gn:feature_class":"P",
    "gn:feature_code":"PPL",
    "gn:name":"Th\u00ecn Th\u1ee7ng",
    "gn:population":0,
    "gn:timezone":"Asia/Ho_Chi_Minh",
    "iso:country":"VN",
    "name:vie_x_preferred":[
        "Th\u00ecn Th\u1ee7ng"
    ],
    "wof:name":"Thin Thung",
    "wof:placetype":"locality"
},
  "geometry": {"coordinates":[104.34432,22.15114],"type":"Point"}
}