{
  "type": "Feature",
  "properties": {
    "gn:admin1_code":"37.0",
    "gn:asciiname":"Tan Hoa",
    "gn:country_code":"VN",
    "gn:dem":4,
    "gn:feature_class":"P",
    "gn:feature_code":"PPLA2",
    "gn:name":"T\u00e2n H\u00f2a",
    "gn:population":0,
    "gn:timezone":"Asia/Ho_Chi_Minh",
    "iso:country":"VN",
    "name:vie_x_preferred":[
        "T\u00e2n H\u00f2a"
    ],
    "wof:name":"Tan Hoa",
    "wof:placetype":"locality"
},
  "geometry": {"coordinates":[106.71128,10.31906],"type":"Point"}
}