{
  "type": "Feature",
  "properties": {
    "gn:admin1_code":"47.0",
    "gn:asciiname":"Tan Tao",
    "gn:country_code":"VN",
    "gn:dem":34,
    "gn:feature_class":"P",
    "gn:feature_code":"PPL",
    "gn:name":"T\u00e2n T\u1ea1o",
    "gn:population":0,
    "gn:timezone":"Asia/Ho_Chi_Minh",
    "iso:country":"VN",
    "wof:name":"Tan Tao",
    "wof:placetype":"locality"
},
  "geometry": {"coordinates":[107.75,10.68333],"type":"Point"}
}