{
  "type": "Feature",
  "properties": {
    "gn:admin1_code":"74.0",
    "gn:asciiname":"Lieu Ngan",
    "gn:country_code":"VN",
    "gn:dem":6,
    "gn:feature_class":"P",
    "gn:feature_code":"PPL",
    "gn:name":"Li\u1ec5u Ng\u1ea1n",
    "gn:population":0,
    "gn:timezone":"Asia/Ho_Chi_Minh",
    "iso:country":"VN",
    "name:vie_x_preferred":[
        "Li\u1ec5u Ng\u1ea1n"
    ],
    "wof:name":"Lieu Ngan",
    "wof:placetype":"locality"
},
  "geometry": {"coordinates":[106.02828,21.00776],"type":"Point"}
}