{
  "type": "Feature",
  "properties": {
    "gn:admin1_code":"23.0",
    "gn:asciiname":"Buon Dong Trang",
    "gn:country_code":"VN",
    "gn:dem":791,
    "gn:feature_class":"P",
    "gn:feature_code":"PPL",
    "gn:name":"Bu\u00f4n D\u01a1ng Trang",
    "gn:population":0,
    "gn:timezone":"Asia/Ho_Chi_Minh",
    "iso:country":"VN",
    "name:und_x_variant":[
        "Buon Ya Tran",
        "Ban Ya Tran",
        "Bon Deung Trang"
    ],
    "name:vie_x_preferred":[
        "Bu\u00f4n D\u01a1ng Trang"
    ],
    "wof:name":"Buon Dong Trang",
    "wof:placetype":"locality"
},
  "geometry": {"coordinates":[108.32888,12.17821],"type":"Point"}
}