{
  "type": "Feature",
  "properties": {
    "gn:admin1_code":"55.0",
    "gn:asciiname":"Bon Du",
    "gn:country_code":"VN",
    "gn:dem":680,
    "gn:feature_class":"P",
    "gn:feature_code":"PPL",
    "gn:name":"Bon Du",
    "gn:population":0,
    "gn:timezone":"Asia/Ho_Chi_Minh",
    "iso:country":"VN",
    "wof:name":"Bon Du",
    "wof:placetype":"locality"
},
  "geometry": {"coordinates":[107.86667,14.71667],"type":"Point"}
}