{
  "type": "Feature",
  "properties": {
    "gn:admin1_code":"52.0",
    "gn:asciiname":"Thanh Long",
    "gn:country_code":"VN",
    "gn:dem":8,
    "gn:feature_class":"P",
    "gn:feature_code":"PPL",
    "gn:name":"Th\u00e0nh Long",
    "gn:population":0,
    "gn:timezone":"Asia/Ho_Chi_Minh",
    "iso:country":"VN",
    "name:vie_x_preferred":[
        "Th\u00e0nh Long"
    ],
    "wof:name":"Thanh Long",
    "wof:placetype":"locality"
},
  "geometry": {"coordinates":[105.93649000000001,18.41986],"type":"Point"}
}