{
  "type": "Feature",
  "properties": {
    "gn:admin1_code":"71.0",
    "gn:asciiname":"Xom Nguoi",
    "gn:country_code":"VN",
    "gn:dem":10,
    "gn:feature_class":"P",
    "gn:feature_code":"PPL",
    "gn:name":"X\u00f3m Ng\u01b0\u01a1i",
    "gn:population":0,
    "gn:timezone":"Asia/Ho_Chi_Minh",
    "iso:country":"VN",
    "name:vie_x_preferred":[
        "X\u00f3m Ng\u01b0\u01a1i"
    ],
    "wof:name":"Xom Nguoi",
    "wof:placetype":"locality"
},
  "geometry": {"coordinates":[106.21352,21.28254],"type":"Point"}
}