{
  "type": "Feature",
  "properties": {
    "gn:admin1_code":"87.0",
    "gn:asciiname":"Nhon Binh",
    "gn:country_code":"VN",
    "gn:dem":2,
    "gn:feature_class":"P",
    "gn:feature_code":"PPL",
    "gn:name":"Nh\u01a1n B\u00ecnh",
    "gn:population":0,
    "gn:timezone":"Asia/Ho_Chi_Minh",
    "iso:country":"VN",
    "name:und_x_variant":[
        "\u1ea4p Nh\u01a1n B\u00ecnh"
    ],
    "name:vie_x_preferred":[
        "Nh\u01a1n B\u00ecnh"
    ],
    "wof:name":"Nhon Binh",
    "wof:placetype":"locality"
},
  "geometry": {"coordinates":[105.66337,9.96832],"type":"Point"}
}