{
  "type": "Feature",
  "properties": {
    "gn:admin1_code":"54.0",
    "gn:asciiname":"Nu Lan",
    "gn:country_code":"VN",
    "gn:dem":158,
    "gn:feature_class":"P",
    "gn:feature_code":"PPL",
    "gn:name":"Nu Lan",
    "gn:population":0,
    "gn:timezone":"Asia/Ho_Chi_Minh",
    "iso:country":"VN",
    "name:und_x_variant":[
        "Nui Lao",
        "Nu Lan"
    ],
    "wof:name":"Nu Lan",
    "wof:placetype":"locality"
},
  "geometry": {"coordinates":[108.78333000000001,12.31667],"type":"Point"}
}