{
  "type": "Feature",
  "properties": {
    "gn:admin1_code":"83.0",
    "gn:asciiname":"Xom Mit",
    "gn:country_code":"VN",
    "gn:dem":64,
    "gn:feature_class":"P",
    "gn:feature_code":"PPL",
    "gn:name":"X\u00f3m M\u00edt",
    "gn:population":0,
    "gn:timezone":"Asia/Ho_Chi_Minh",
    "iso:country":"VN",
    "name:vie_x_preferred":[
        "X\u00f3m M\u00edt"
    ],
    "wof:name":"Xom Mit",
    "wof:placetype":"locality"
},
  "geometry": {"coordinates":[105.20484,21.01682000000001],"type":"Point"}
}