{
  "type": "Feature",
  "properties": {
    "gn:admin1_code":"46.0",
    "gn:asciiname":"Binh Chuong",
    "gn:country_code":"VN",
    "gn:dem":12,
    "gn:feature_class":"P",
    "gn:feature_code":"PPL",
    "gn:name":"B\u00ecnh Ch\u01b0\u01a1ng",
    "gn:population":0,
    "gn:timezone":"Asia/Ho_Chi_Minh",
    "iso:country":"VN",
    "name:vie_x_preferred":[
        "B\u00ecnh Ch\u01b0\u01a1ng"
    ],
    "wof:name":"Binh Chuong",
    "wof:placetype":"locality"
},
  "geometry": {"coordinates":[109.01716,14.41997],"type":"Point"}
}