{
  "type": "Feature",
  "properties": {
    "gn:admin1_code":"89.0",
    "gn:asciiname":"Ban Chua Kheo Thap",
    "gn:country_code":"VN",
    "gn:dem":807,
    "gn:feature_class":"P",
    "gn:feature_code":"PPL",
    "gn:name":"B\u1ea3n Ch\u00f9a Kh\u00e8o Th\u1ea5p",
    "gn:population":0,
    "gn:timezone":"Asia/Ho_Chi_Minh",
    "iso:country":"VN",
    "name:vie_x_preferred":[
        "B\u1ea3n Ch\u00f9a Kh\u00e8o Th\u1ea5p"
    ],
    "wof:name":"Ban Chua Kheo Thap",
    "wof:placetype":"locality"
},
  "geometry": {"coordinates":[103.61532,22.24297],"type":"Point"}
}