{
  "type": "Feature",
  "properties": {
    "gn:admin1_code":"83.0",
    "gn:asciiname":"Bach Duong",
    "gn:country_code":"VN",
    "gn:dem":54,
    "gn:feature_class":"P",
    "gn:feature_code":"PPL",
    "gn:name":"B\u00e1ch D\u01b0\u01a1ng",
    "gn:population":0,
    "gn:timezone":"Asia/Ho_Chi_Minh",
    "iso:country":"VN",
    "name:und_x_variant":[
        "B\u1ea1ch D\u01b0\u01a1ng"
    ],
    "name:vie_x_preferred":[
        "B\u00e1ch D\u01b0\u01a1ng"
    ],
    "wof:name":"Bach Duong",
    "wof:placetype":"locality"
},
  "geometry": {"coordinates":[105.03582,21.60932],"type":"Point"}
}