{
  "type": "Feature",
  "properties": {
    "gn:admin1_code":"72.0",
    "gn:asciiname":"Pou Ton",
    "gn:country_code":"VN",
    "gn:dem":745,
    "gn:feature_class":"P",
    "gn:feature_code":"PPL",
    "gn:name":"Pou Ton",
    "gn:population":0,
    "gn:timezone":"Asia/Ho_Chi_Minh",
    "iso:country":"VN",
    "wof:name":"Pou Ton",
    "wof:placetype":"locality"
},
  "geometry": {"coordinates":[105.63333,22.33333],"type":"Point"}
}