{
  "type": "Feature",
  "properties": {
    "gn:admin1_code":"49.0",
    "gn:asciiname":"Plei Ring Do",
    "gn:country_code":"VN",
    "gn:dem":712,
    "gn:feature_class":"P",
    "gn:feature_code":"PPL",
    "gn:name":"Plei Ring D\u00f4",
    "gn:population":0,
    "gn:timezone":"Asia/Ho_Chi_Minh",
    "iso:country":"VN",
    "name:und_x_variant":[
        "Plei Ia Puch",
        "Plei Ring D\u00f4"
    ],
    "wof:name":"Plei Ring Do",
    "wof:placetype":"locality"
},
  "geometry": {"coordinates":[107.98333,13.85],"type":"Point"}
}