{
  "type": "Feature",
  "properties": {
    "gn:admin1_code":"75.0",
    "gn:asciiname":"Nuoc Trong",
    "gn:country_code":"VN",
    "gn:dem":43,
    "gn:feature_class":"P",
    "gn:feature_code":"PPL",
    "gn:name":"N\u01b0\u1edbc Trong",
    "gn:population":0,
    "gn:timezone":"Asia/Ho_Chi_Minh",
    "iso:country":"VN",
    "name:vie_x_preferred":[
        "N\u01b0\u1edbc Trong"
    ],
    "wof:name":"Nuoc Trong",
    "wof:placetype":"locality"
},
  "geometry": {"coordinates":[106.79955,11.19084],"type":"Point"}
}