{
  "type": "Feature",
  "properties": {
    "gn:admin1_code":"32.0",
    "gn:asciiname":"Ban Suoi Cay B",
    "gn:country_code":"VN",
    "gn:dem":679,
    "gn:feature_class":"P",
    "gn:feature_code":"PPL",
    "gn:name":"B\u1ea3n Su\u1ed1i C\u00e1y B",
    "gn:population":0,
    "gn:timezone":"Asia/Ho_Chi_Minh",
    "iso:country":"VN",
    "name:vie_x_preferred":[
        "B\u1ea3n Su\u1ed1i C\u00e1y B"
    ],
    "wof:name":"Ban Suoi Cay B",
    "wof:placetype":"locality"
},
  "geometry": {"coordinates":[104.52019,21.21788],"type":"Point"}
}