{
  "type": "Feature",
  "properties": {
    "gn:admin1_code":"32.0",
    "gn:asciiname":"Khong To",
    "gn:country_code":"VN",
    "gn:dem":337,
    "gn:feature_class":"P",
    "gn:feature_code":"PPL",
    "gn:name":"Khong T\u1ee3",
    "gn:population":0,
    "gn:timezone":"Asia/Ho_Chi_Minh",
    "iso:country":"VN",
    "name:und_x_variant":[
        "Khoong T\u1ee3"
    ],
    "name:vie_x_preferred":[
        "Khong T\u1ee3"
    ],
    "wof:name":"Khong To",
    "wof:placetype":"locality"
},
  "geometry": {"coordinates":[103.78660000000001,21.02598],"type":"Point"}
}