{
  "type": "Feature",
  "properties": {
    "gn:admin1_code":"92.0",
    "gn:asciiname":"Long Dao",
    "gn:country_code":"VN",
    "gn:dem":941,
    "gn:feature_class":"P",
    "gn:feature_code":"PPL",
    "gn:name":"Long D\u1ea1o",
    "gn:population":0,
    "gn:timezone":"Asia/Ho_Chi_Minh",
    "iso:country":"VN",
    "name:vie_x_preferred":[
        "Long D\u1ea1o"
    ],
    "wof:name":"Long Dao",
    "wof:placetype":"locality"
},
  "geometry": {"coordinates":[102.9179,21.78422],"type":"Point"}
}