{
  "type": "Feature",
  "properties": {
    "gn:admin1_code":"33.0",
    "gn:asciiname":"Xa Cau Loi",
    "gn:cc2":"VN",
    "gn:country_code":"VN",
    "gn:dem":7,
    "gn:feature_class":"P",
    "gn:feature_code":"PPL",
    "gn:name":"X\u00e1 C\u1ea7u L\u1ecfi",
    "gn:population":0,
    "gn:timezone":"Asia/Ho_Chi_Minh",
    "iso:country":"VN",
    "name:und_x_variant":[
        "Cau Loi",
        "Xom Cau Loi",
        "X\u00e1 C\u1ea7u L\u1ecfi"
    ],
    "wof:name":"Xa Cau Loi",
    "wof:placetype":"locality"
},
  "geometry": {"coordinates":[106.31667,11.11667],"type":"Point"}
}