{
  "type": "Feature",
  "properties": {
    "gn:admin1_code":"87.0",
    "gn:asciiname":"Ap Truong Phuoc",
    "gn:country_code":"VN",
    "gn:dem":1,
    "gn:feature_class":"P",
    "gn:feature_code":"PPL",
    "gn:name":"\u1ea4p Tr\u01b0\u1eddng Ph\u01b0\u1edbc",
    "gn:population":0,
    "gn:timezone":"Asia/Ho_Chi_Minh",
    "iso:country":"VN",
    "wof:name":"Ap Truong Phuoc",
    "wof:placetype":"locality"
},
  "geometry": {"coordinates":[105.59139,9.94972],"type":"Point"}
}