{
  "type": "Feature",
  "properties": {
    "gn:admin1_code":"76.0",
    "gn:asciiname":"Bu Korla Tiudul",
    "gn:country_code":"VN",
    "gn:dem":170,
    "gn:feature_class":"P",
    "gn:feature_code":"PPL",
    "gn:name":"Bu Korla Tiudul",
    "gn:population":0,
    "gn:timezone":"Asia/Ho_Chi_Minh",
    "iso:country":"VN",
    "wof:name":"Bu Korla Tiudul",
    "wof:placetype":"locality"
},
  "geometry": {"coordinates":[106.90000000000001,11.91667],"type":"Point"}
}