{
  "type": "Feature",
  "properties": {
    "gn:admin1_code":"89.0",
    "gn:asciiname":"Gia Khau",
    "gn:country_code":"VN",
    "gn:dem":1219,
    "gn:feature_class":"P",
    "gn:feature_code":"PPL",
    "gn:name":"Gia Kh\u1eabu",
    "gn:population":0,
    "gn:timezone":"Asia/Ho_Chi_Minh",
    "iso:country":"VN",
    "name:vie_x_preferred":[
        "Gia Kh\u1eabu"
    ],
    "wof:name":"Gia Khau",
    "wof:placetype":"locality"
},
  "geometry": {"coordinates":[103.5603,22.35287000000001],"type":"Point"}
}