{
  "type": "Feature",
  "properties": {
    "gn:admin1_code":"53.0",
    "gn:asciiname":"Lang Dam",
    "gn:country_code":"VN",
    "gn:dem":474,
    "gn:feature_class":"P",
    "gn:feature_code":"PPL",
    "gn:name":"L\u00e0ng \u0110am",
    "gn:population":0,
    "gn:timezone":"Asia/Ho_Chi_Minh",
    "iso:country":"VN",
    "wof:name":"Lang Dam",
    "wof:placetype":"locality"
},
  "geometry": {"coordinates":[105.40000000000001,20.43333],"type":"Point"}
}