{
  "type": "Feature",
  "properties": {
    "gn:admin1_code":"2.0",
    "gn:asciiname":"Me Hai",
    "gn:country_code":"VN",
    "gn:dem":586,
    "gn:feature_class":"P",
    "gn:feature_code":"PPL",
    "gn:name":"Me Hai",
    "gn:population":0,
    "gn:timezone":"Asia/Ho_Chi_Minh",
    "iso:country":"VN",
    "wof:name":"Me Hai",
    "wof:placetype":"locality"
},
  "geometry": {"coordinates":[106.09999999999999,21.81667],"type":"Point"}
}