{
  "type": "Feature",
  "properties": {
    "gn:admin1_code":"32.0",
    "gn:asciiname":"Huoi Nha",
    "gn:country_code":"VN",
    "gn:dem":1048,
    "gn:feature_class":"P",
    "gn:feature_code":"PPL",
    "gn:name":"Hu\u1ed5i Nh\u1ea3",
    "gn:population":0,
    "gn:timezone":"Asia/Ho_Chi_Minh",
    "iso:country":"VN",
    "wof:name":"Huoi Nha",
    "wof:placetype":"locality"
},
  "geometry": {"coordinates":[103.76667,21.11667000000001],"type":"Point"}
}