{
  "type": "Feature",
  "properties": {
    "gn:admin1_code":"88.0",
    "gn:asciiname":"Ban Cho Ah",
    "gn:country_code":"VN",
    "gn:dem":739,
    "gn:feature_class":"P",
    "gn:feature_code":"PPL",
    "gn:name":"Ban Cho Ah",
    "gn:population":0,
    "gn:timezone":"Asia/Ho_Chi_Minh",
    "iso:country":"VN",
    "wof:name":"Ban Cho Ah",
    "wof:placetype":"locality"
},
  "geometry": {"coordinates":[108.28333000000001,13.18333],"type":"Point"}
}