{
  "type": "Feature",
  "properties": {
    "gn:admin1_code":"65.0",
    "gn:asciiname":"Phuong Binh",
    "gn:country_code":"VN",
    "gn:dem":5,
    "gn:feature_class":"P",
    "gn:feature_code":"PPL",
    "gn:name":"Ph\u01b0\u01a1ng B\u00ecnh",
    "gn:population":0,
    "gn:timezone":"Asia/Ho_Chi_Minh",
    "iso:country":"VN",
    "name:vie_x_preferred":[
        "Ph\u01b0\u01a1ng B\u00ecnh"
    ],
    "wof:name":"Phuong Binh",
    "wof:placetype":"locality"
},
  "geometry": {"coordinates":[105.73766000000001,9.65833],"type":"Point"}
}