{
  "type": "Feature",
  "properties": {
    "gn:admin1_code":"84.0",
    "gn:asciiname":"Mang May",
    "gn:country_code":"VN",
    "gn:dem":683,
    "gn:feature_class":"P",
    "gn:feature_code":"PPL",
    "gn:name":"Mang May",
    "gn:population":0,
    "gn:timezone":"Asia/Ho_Chi_Minh",
    "iso:country":"VN",
    "name:und_x_variant":[
        "Mong May",
        "Mang May"
    ],
    "wof:name":"Mang May",
    "wof:placetype":"locality"
},
  "geometry": {"coordinates":[107.91667,15.95],"type":"Point"}
}