{
  "type": "Feature",
  "properties": {
    "gn:admin1_code":"83.0",
    "gn:asciiname":"Xom Manh",
    "gn:country_code":"VN",
    "gn:dem":54,
    "gn:feature_class":"P",
    "gn:feature_code":"PPL",
    "gn:name":"X\u00f3m M\u00e0nh",
    "gn:population":0,
    "gn:timezone":"Asia/Ho_Chi_Minh",
    "iso:country":"VN",
    "name:und_x_variant":[
        "X\u00f3m Manh"
    ],
    "name:vie_x_preferred":[
        "X\u00f3m M\u00e0nh"
    ],
    "wof:name":"Xom Manh",
    "wof:placetype":"locality"
},
  "geometry": {"coordinates":[105.06997,21.15604],"type":"Point"}
}