{
  "type": "Feature",
  "properties": {
    "gn:admin1_code":"34.0",
    "gn:asciiname":"Phu Son",
    "gn:country_code":"VN",
    "gn:dem":17,
    "gn:feature_class":"P",
    "gn:feature_code":"PPL",
    "gn:name":"Ph\u00fa S\u01a1n",
    "gn:population":0,
    "gn:timezone":"Asia/Ho_Chi_Minh",
    "iso:country":"VN",
    "wof:name":"Phu Son",
    "wof:placetype":"locality"
},
  "geometry": {"coordinates":[105.59999999999999,20.06667],"type":"Point"}
}