{
  "type": "Feature",
  "properties": {
    "gn:admin1_code":"39.0",
    "gn:asciiname":"Po Don",
    "gn:country_code":"VN",
    "gn:dem":333,
    "gn:feature_class":"P",
    "gn:feature_code":"PPL",
    "gn:name":"P\u00f2 \u0110\u1ed3n",
    "gn:population":0,
    "gn:timezone":"Asia/Ho_Chi_Minh",
    "iso:country":"VN",
    "name:und_x_variant":[
        "Pho \u0110on"
    ],
    "name:vie_x_preferred":[
        "P\u00f2 \u0110\u1ed3n"
    ],
    "wof:name":"Po Don",
    "wof:placetype":"locality"
},
  "geometry": {"coordinates":[106.15151000000002,21.85086],"type":"Point"}
}