{
  "type": "Feature",
  "properties": {
    "gn:admin1_code":"78.0",
    "gn:asciiname":"Phuoc Dong",
    "gn:country_code":"VN",
    "gn:dem":45,
    "gn:feature_class":"P",
    "gn:feature_code":"PPL",
    "gn:name":"Ph\u01b0\u1edbc \u0110\u00f4ng",
    "gn:population":0,
    "gn:timezone":"Asia/Ho_Chi_Minh",
    "iso:country":"VN",
    "name:und_x_variant":[
        "Th\u00f4n Ph\u01b0\u1edbc \u0110\u00f4ng"
    ],
    "name:vie_x_preferred":[
        "Ph\u01b0\u1edbc \u0110\u00f4ng"
    ],
    "wof:name":"Phuoc Dong",
    "wof:placetype":"locality"
},
  "geometry": {"coordinates":[108.08238,16.0548],"type":"Point"}
}