{
  "type": "Feature",
  "properties": {
    "gn:admin1_code":"74.0",
    "gn:asciiname":"Chi Chung",
    "gn:country_code":"VN",
    "gn:dem":9,
    "gn:feature_class":"P",
    "gn:feature_code":"PPL",
    "gn:name":"Chi Chung",
    "gn:population":0,
    "gn:timezone":"Asia/Ho_Chi_Minh",
    "iso:country":"VN",
    "name:vie_x_preferred":[
        "Chi Chung"
    ],
    "wof:name":"Chi Chung",
    "wof:placetype":"locality"
},
  "geometry": {"coordinates":[106.09117000000001,21.07547000000001],"type":"Point"}
}