{
  "type": "Feature",
  "properties": {
    "gn:admin1_code":"90.0",
    "gn:asciiname":"Ngai Cho",
    "gn:country_code":"VN",
    "gn:dem":1282,
    "gn:feature_class":"P",
    "gn:feature_code":"PPL",
    "gn:name":"Ng\u00e0i Ch\u00f4",
    "gn:population":0,
    "gn:timezone":"Asia/Ho_Chi_Minh",
    "iso:country":"VN",
    "name:vie_x_preferred":[
        "Ng\u00e0i Ch\u00f4"
    ],
    "wof:name":"Ngai Cho",
    "wof:placetype":"locality"
},
  "geometry": {"coordinates":[104.25143,22.61154],"type":"Point"}
}