{
  "type": "Feature",
  "properties": {
    "gn:admin1_code":"58.0",
    "gn:asciiname":"Ban Nong Bua",
    "gn:country_code":"VN",
    "gn:dem":283,
    "gn:feature_class":"P",
    "gn:feature_code":"PPL",
    "gn:name":"B\u1ea3n Nong B\u00f9a",
    "gn:population":0,
    "gn:timezone":"Asia/Ho_Chi_Minh",
    "iso:country":"VN",
    "wof:name":"Ban Nong Bua",
    "wof:placetype":"locality"
},
  "geometry": {"coordinates":[104.95,18.91667],"type":"Point"}
}