{
  "type": "Feature",
  "properties": {
    "gn:admin1_code":"90.0",
    "gn:asciiname":"Xin Chai",
    "gn:country_code":"VN",
    "gn:dem":802,
    "gn:feature_class":"P",
    "gn:feature_code":"PPL",
    "gn:name":"Xin Ch\u1ea3i",
    "gn:population":0,
    "gn:timezone":"Asia/Ho_Chi_Minh",
    "iso:country":"VN",
    "name:vie_x_preferred":[
        "Xin Ch\u1ea3i"
    ],
    "wof:name":"Xin Chai",
    "wof:placetype":"locality"
},
  "geometry": {"coordinates":[103.91661000000001,22.4148],"type":"Point"}
}