{
  "type": "Feature",
  "properties": {
    "gn:admin1_code":"23.0",
    "gn:asciiname":"Bon Da Xi",
    "gn:cc2":"VN",
    "gn:country_code":"VN",
    "gn:dem":545,
    "gn:feature_class":"P",
    "gn:feature_code":"PPL",
    "gn:name":"Bon Da Xi",
    "gn:population":0,
    "gn:timezone":"Asia/Ho_Chi_Minh",
    "iso:country":"VN",
    "name:und_x_variant":[
        "Ban Da Xi",
        "Bon Da Si",
        "Bon Da Xi"
    ],
    "wof:name":"Bon Da Xi",
    "wof:placetype":"locality"
},
  "geometry": {"coordinates":[108.21666999999999,12.15],"type":"Point"}
}