{
  "type": "Feature",
  "properties": {
    "gn:admin1_code":"43.0",
    "gn:asciiname":"Phan Tuong Nam",
    "gn:country_code":"VN",
    "gn:dem":35,
    "gn:feature_class":"P",
    "gn:feature_code":"PPL",
    "gn:name":"Ph\u00e2n T\u01b0\u1eddng N\u0103m",
    "gn:population":0,
    "gn:timezone":"Asia/Ho_Chi_Minh",
    "iso:country":"VN",
    "name:vie_x_preferred":[
        "Ph\u00e2n T\u01b0\u1eddng N\u0103m"
    ],
    "name:vie_x_variant":[
        "Ph\u00e2n T\u01b0\u1eddng 5"
    ],
    "wof:name":"Phan Tuong Nam",
    "wof:placetype":"locality"
},
  "geometry": {"coordinates":[106.93391,11.25288],"type":"Point"}
}