{
  "type": "Feature",
  "properties": {
    "gn:admin1_code":"32.0",
    "gn:asciiname":"Ban Chieng",
    "gn:country_code":"VN",
    "gn:dem":256,
    "gn:feature_class":"P",
    "gn:feature_code":"PPL",
    "gn:name":"B\u1ea3n Chi\u1ec1ng",
    "gn:population":0,
    "gn:timezone":"Asia/Ho_Chi_Minh",
    "iso:country":"VN",
    "name:vie_x_preferred":[
        "B\u1ea3n Chi\u1ec1ng"
    ],
    "wof:name":"Ban Chieng",
    "wof:placetype":"locality"
},
  "geometry": {"coordinates":[104.78006999999999,21.24783],"type":"Point"}
}