{
  "type": "Feature",
  "properties": {
    "gn:admin1_code":"44.0",
    "gn:asciiname":"Chi Nam",
    "gn:country_code":"VN",
    "gn:dem":14,
    "gn:feature_class":"P",
    "gn:feature_code":"PPL",
    "gn:name":"Chi Nam",
    "gn:population":0,
    "gn:timezone":"Asia/Ho_Chi_Minh",
    "iso:country":"VN",
    "name:vie_x_preferred":[
        "Chi Nam"
    ],
    "wof:name":"Chi Nam",
    "wof:placetype":"locality"
},
  "geometry": {"coordinates":[105.99988999999999,21.05312],"type":"Point"}
}