{
  "type": "Feature",
  "properties": {
    "gn:admin1_code":"74.0",
    "gn:asciiname":"Dong Xa",
    "gn:country_code":"VN",
    "gn:dem":12,
    "gn:feature_class":"P",
    "gn:feature_code":"PPL",
    "gn:name":"\u0110\u00f4ng X\u00e1",
    "gn:population":0,
    "gn:timezone":"Asia/Ho_Chi_Minh",
    "iso:country":"VN",
    "name:vie_x_preferred":[
        "\u0110\u00f4ng X\u00e1"
    ],
    "wof:name":"Dong Xa",
    "wof:placetype":"locality"
},
  "geometry": {"coordinates":[106.02289,21.19598],"type":"Point"}
}