{
  "type": "Feature",
  "properties": {
    "gn:admin1_code":"1.0",
    "gn:asciiname":"My Hiep",
    "gn:country_code":"VN",
    "gn:dem":4,
    "gn:feature_class":"P",
    "gn:feature_code":"PPL",
    "gn:name":"M\u1ef9 Hi\u1ec7p",
    "gn:population":0,
    "gn:timezone":"Asia/Ho_Chi_Minh",
    "iso:country":"VN",
    "name:und_x_variant":[
        "\u1ea4p M\u1ef9 Hi\u1ec7p"
    ],
    "name:vie_x_preferred":[
        "M\u1ef9 Hi\u1ec7p"
    ],
    "wof:name":"My Hiep",
    "wof:placetype":"locality"
},
  "geometry": {"coordinates":[105.43941,10.42839],"type":"Point"}
}