{
  "type": "Feature",
  "properties": {
    "gn:admin1_code":"61.0",
    "gn:asciiname":"Trung Thanh",
    "gn:country_code":"VN",
    "gn:dem":75,
    "gn:feature_class":"P",
    "gn:feature_code":"PPL",
    "gn:name":"Trung Th\u00e0nh",
    "gn:population":0,
    "gn:timezone":"Asia/Ho_Chi_Minh",
    "iso:country":"VN",
    "wof:name":"Trung Thanh",
    "wof:placetype":"locality"
},
  "geometry": {"coordinates":[109.13333,13.28333],"type":"Point"}
}