{
  "type": "Feature",
  "properties": {
    "gn:admin1_code":"49.0",
    "gn:asciiname":"Kon Rong Nak",
    "gn:country_code":"VN",
    "gn:dem":867,
    "gn:feature_class":"P",
    "gn:feature_code":"PPL",
    "gn:name":"Kon Rong Nak",
    "gn:population":0,
    "gn:timezone":"Asia/Ho_Chi_Minh",
    "iso:country":"VN",
    "wof:name":"Kon Rong Nak",
    "wof:placetype":"locality"
},
  "geometry": {"coordinates":[108.28333000000001,14.35],"type":"Point"}
}