{
  "type": "Feature",
  "properties": {
    "gn:admin1_code":"71.0",
    "gn:asciiname":"Xom Thiem",
    "gn:country_code":"VN",
    "gn:dem":16,
    "gn:feature_class":"P",
    "gn:feature_code":"PPL",
    "gn:name":"X\u00f3m Thi\u00eam",
    "gn:population":0,
    "gn:timezone":"Asia/Ho_Chi_Minh",
    "iso:country":"VN",
    "name:vie_x_preferred":[
        "X\u00f3m Thi\u00eam"
    ],
    "wof:name":"Xom Thiem",
    "wof:placetype":"locality"
},
  "geometry": {"coordinates":[106.12014000000001,21.39332000000001],"type":"Point"}
}