{
  "type": "Feature",
  "properties": {
    "gn:admin1_code":"59.0",
    "gn:asciiname":"Dong Con",
    "gn:country_code":"VN",
    "gn:dem":291,
    "gn:feature_class":"P",
    "gn:feature_code":"PPL",
    "gn:name":"\u0110\u1ed3ng Con",
    "gn:population":0,
    "gn:timezone":"Asia/Ho_Chi_Minh",
    "iso:country":"VN",
    "name:vie_x_preferred":[
        "\u0110\u1ed3ng Con"
    ],
    "wof:name":"Dong Con",
    "wof:placetype":"locality"
},
  "geometry": {"coordinates":[105.64428999999998,20.31194],"type":"Point"}
}