{
  "type": "Feature",
  "properties": {
    "gn:admin1_code":"39.0",
    "gn:asciiname":"Kouei Youye",
    "gn:country_code":"VN",
    "gn:dem":351,
    "gn:feature_class":"P",
    "gn:feature_code":"PPL",
    "gn:name":"Kouei Youye",
    "gn:population":0,
    "gn:timezone":"Asia/Ho_Chi_Minh",
    "iso:country":"VN",
    "wof:name":"Kouei Youye",
    "wof:placetype":"locality"
},
  "geometry": {"coordinates":[106.25,22.18333],"type":"Point"}
}