{
  "type": "Feature",
  "properties": {
    "gn:admin1_code":"72.0",
    "gn:asciiname":"Na Ca Trong",
    "gn:country_code":"VN",
    "gn:dem":522,
    "gn:feature_class":"P",
    "gn:feature_code":"PPL",
    "gn:name":"N\u00e0 C\u00e0 Trong",
    "gn:population":0,
    "gn:timezone":"Asia/Ho_Chi_Minh",
    "iso:country":"VN",
    "wof:name":"Na Ca Trong",
    "wof:placetype":"locality"
},
  "geometry": {"coordinates":[105.93415,22.30746],"type":"Point"}
}