{
  "type": "Feature",
  "properties": {
    "gn:admin1_code":"72.0",
    "gn:asciiname":"Coc Tiou",
    "gn:country_code":"VN",
    "gn:dem":210,
    "gn:feature_class":"P",
    "gn:feature_code":"PPL",
    "gn:name":"Coc Tiou",
    "gn:population":0,
    "gn:timezone":"Asia/Ho_Chi_Minh",
    "iso:country":"VN",
    "name:und_x_variant":[
        "Coc Tio",
        "Coc Tiou"
    ],
    "wof:name":"Coc Tiou",
    "wof:placetype":"locality"
},
  "geometry": {"coordinates":[105.84999999999999,22.21667],"type":"Point"}
}