{
  "type": "Feature",
  "properties": {
    "gn:admin1_code":"64.0",
    "gn:asciiname":"Tam Boai",
    "gn:country_code":"VN",
    "gn:dem":420,
    "gn:feature_class":"P",
    "gn:feature_code":"PPL",
    "gn:name":"Tam Boai",
    "gn:population":0,
    "gn:timezone":"Asia/Ho_Chi_Minh",
    "iso:country":"VN",
    "wof:name":"Tam Boai",
    "wof:placetype":"locality"
},
  "geometry": {"coordinates":[106.95,16.38332999999999],"type":"Point"}
}