{
  "type": "Feature",
  "properties": {
    "gn:admin1_code":"88.0",
    "gn:asciiname":"Dong Giang",
    "gn:country_code":"VN",
    "gn:dem":683,
    "gn:feature_class":"P",
    "gn:feature_code":"PPL",
    "gn:name":"\u0110\u00f4ng Giang",
    "gn:population":0,
    "gn:timezone":"Asia/Ho_Chi_Minh",
    "iso:country":"VN",
    "name:vie_x_preferred":[
        "\u0110\u00f4ng Giang"
    ],
    "wof:name":"Dong Giang",
    "wof:placetype":"locality"
},
  "geometry": {"coordinates":[108.34963,12.95511],"type":"Point"}
}