{
  "type": "Feature",
  "properties": {
    "gn:admin1_code":"32.0",
    "gn:asciiname":"Ban Xuan Quay",
    "gn:country_code":"VN",
    "gn:dem":966,
    "gn:feature_class":"P",
    "gn:feature_code":"PPL",
    "gn:name":"B\u1ea3n Xu\u00e2n Qu\u1ea9y",
    "gn:population":0,
    "gn:timezone":"Asia/Ho_Chi_Minh",
    "iso:country":"VN",
    "name:vie_x_preferred":[
        "B\u1ea3n Xu\u00e2n Qu\u1ea9y"
    ],
    "wof:name":"Ban Xuan Quay",
    "wof:placetype":"locality"
},
  "geometry": {"coordinates":[104.01121999999999,21.58047],"type":"Point"}
}