{
  "type": "Feature",
  "properties": {
    "gn:admin1_code":"68.0",
    "gn:asciiname":"Lang Duoc",
    "gn:country_code":"VN",
    "gn:dem":28,
    "gn:feature_class":"P",
    "gn:feature_code":"PPL",
    "gn:name":"L\u00e0ng \u0110\u01b0\u01a1c",
    "gn:population":0,
    "gn:timezone":"Asia/Ho_Chi_Minh",
    "iso:country":"VN",
    "name:vie_x_preferred":[
        "L\u00e0ng \u0110\u01b0\u01a1c"
    ],
    "wof:name":"Lang Duoc",
    "wof:placetype":"locality"
},
  "geometry": {"coordinates":[105.25408,21.76054],"type":"Point"}
}