{
  "type": "Feature",
  "properties": {
    "gn:admin1_code":"72.0",
    "gn:asciiname":"Na Rao",
    "gn:country_code":"VN",
    "gn:dem":146,
    "gn:feature_class":"P",
    "gn:feature_code":"PPL",
    "gn:name":"N\u00e0 R\u00e0o",
    "gn:population":0,
    "gn:timezone":"Asia/Ho_Chi_Minh",
    "iso:country":"VN",
    "name:vie_x_preferred":[
        "N\u00e0 R\u00e0o"
    ],
    "wof:name":"Na Rao",
    "wof:placetype":"locality"
},
  "geometry": {"coordinates":[105.81177,22.15494],"type":"Point"}
}