{
  "type": "Feature",
  "properties": {
    "gn:admin1_code":"13.0",
    "gn:asciiname":"Duc Lien",
    "gn:country_code":"VN",
    "gn:dem":3,
    "gn:feature_class":"P",
    "gn:feature_code":"PPL",
    "gn:name":"D\u1ef1c Li\u1ec5n",
    "gn:population":0,
    "gn:timezone":"Asia/Ho_Chi_Minh",
    "iso:country":"VN",
    "wof:name":"Duc Lien",
    "wof:placetype":"locality"
},
  "geometry": {"coordinates":[106.66667,20.91667],"type":"Point"}
}