{
  "type": "Feature",
  "properties": {
    "gn:admin1_code":"72.0",
    "gn:asciiname":"Phieng An Hai",
    "gn:country_code":"VN",
    "gn:dem":164,
    "gn:feature_class":"P",
    "gn:feature_code":"PPL",
    "gn:name":"Phi\u00eang An Hai",
    "gn:population":0,
    "gn:timezone":"Asia/Ho_Chi_Minh",
    "iso:country":"VN",
    "name:vie_x_preferred":[
        "Phi\u00eang An Hai"
    ],
    "name:vie_x_variant":[
        "Phi\u00eang An 2"
    ],
    "wof:name":"Phieng An Hai",
    "wof:placetype":"locality"
},
  "geometry": {"coordinates":[105.79225,22.13538],"type":"Point"}
}