{
  "type": "Feature",
  "properties": {
    "gn:admin1_code":"44.0",
    "gn:asciiname":"Cham Me",
    "gn:country_code":"VN",
    "gn:dem":43,
    "gn:feature_class":"P",
    "gn:feature_code":"PPL",
    "gn:name":"Ch\u1ea7m Me",
    "gn:population":0,
    "gn:timezone":"Asia/Ho_Chi_Minh",
    "iso:country":"VN",
    "name:vie_x_preferred":[
        "Ch\u1ea7m Me"
    ],
    "wof:name":"Cham Me",
    "wof:placetype":"locality"
},
  "geometry": {"coordinates":[105.3719,21.12329],"type":"Point"}
}