{
  "type": "Feature",
  "properties": {
    "gn:admin1_code":"88.0",
    "gn:asciiname":"Khoi Bon",
    "gn:country_code":"VN",
    "gn:dem":527,
    "gn:feature_class":"P",
    "gn:feature_code":"PPL",
    "gn:name":"Kh\u1ed1i B\u1ed1n",
    "gn:population":0,
    "gn:timezone":"Asia/Ho_Chi_Minh",
    "iso:country":"VN",
    "name:vie_x_preferred":[
        "Kh\u1ed1i B\u1ed1n"
    ],
    "name:vie_x_variant":[
        "Kh\u1ed1i 4"
    ],
    "wof:name":"Khoi Bon",
    "wof:placetype":"locality"
},
  "geometry": {"coordinates":[108.05655,12.70011],"type":"Point"}
}