{
  "type": "Feature",
  "properties": {
    "gn:admin1_code":"89.0",
    "gn:asciiname":"Nam Ma",
    "gn:country_code":"VN",
    "gn:dem":191,
    "gn:feature_class":"P",
    "gn:feature_code":"PPL",
    "gn:name":"N\u1eadm M\u1ea1",
    "gn:population":0,
    "gn:timezone":"Asia/Ho_Chi_Minh",
    "iso:country":"VN",
    "name:und_x_variant":[
        "N\u1eadm Ma"
    ],
    "name:vie_x_preferred":[
        "N\u1eadm M\u1ea1"
    ],
    "wof:name":"Nam Ma",
    "wof:placetype":"locality"
},
  "geometry": {"coordinates":[103.37985999999999,22.16023],"type":"Point"}
}