{
  "type": "Feature",
  "properties": {
    "gn:admin1_code":"91.0",
    "gn:asciiname":"B'rong",
    "gn:country_code":"VN",
    "gn:dem":618,
    "gn:feature_class":"P",
    "gn:feature_code":"PPL",
    "gn:name":"B\u2019rong",
    "gn:population":0,
    "gn:timezone":"Asia/Ho_Chi_Minh",
    "iso:country":"VN",
    "wof:name":"B'rong",
    "wof:placetype":"locality"
},
  "geometry": {"coordinates":[107.96666999999999,11.83333],"type":"Point"}
}