{
  "type": "Feature",
  "properties": {
    "gn:admin1_code":"30.0",
    "gn:asciiname":"Dong Giang",
    "gn:country_code":"VN",
    "gn:dem":104,
    "gn:feature_class":"P",
    "gn:feature_code":"PPL",
    "gn:name":"\u0110\u1ed3ng Giang",
    "gn:population":0,
    "gn:timezone":"Asia/Ho_Chi_Minh",
    "iso:country":"VN",
    "name:vie_x_preferred":[
        "\u0110\u1ed3ng Giang"
    ],
    "wof:name":"Dong Giang",
    "wof:placetype":"locality"
},
  "geometry": {"coordinates":[107.02176,21.25546],"type":"Point"}
}