{
  "type": "Feature",
  "properties": {
    "gn:admin1_code":"54.0",
    "gn:asciiname":"Dien Khanh",
    "gn:country_code":"VN",
    "gn:dem":12,
    "gn:feature_class":"P",
    "gn:feature_code":"PPLA2",
    "gn:name":"Di\u00ean Kh\u00e1nh",
    "gn:population":0,
    "gn:timezone":"Asia/Ho_Chi_Minh",
    "iso:country":"VN",
    "name:und_x_variant":[
        "Kanh-Hoa",
        "Khan\u2019 Hoa",
        "Khanh Hoa",
        "Kank Hoa",
        "Di\u00ean Kh\u00e1nh"
    ],
    "wof:name":"Dien Khanh",
    "wof:placetype":"locality"
},
  "geometry": {"coordinates":[109.09332000000001,12.2549],"type":"Point"}
}