{
  "type": "Feature",
  "properties": {
    "gn:admin1_code":"89.0",
    "gn:asciiname":"Ouei Leup",
    "gn:country_code":"VN",
    "gn:dem":548,
    "gn:feature_class":"P",
    "gn:feature_code":"PPL",
    "gn:name":"Ouei Leup",
    "gn:population":0,
    "gn:timezone":"Asia/Ho_Chi_Minh",
    "iso:country":"VN",
    "name:und_x_variant":[
        "Quei Leup",
        "Ouei Leup"
    ],
    "wof:name":"Ouei Leup",
    "wof:placetype":"locality"
},
  "geometry": {"coordinates":[103.81667,21.98333],"type":"Point"}
}