{
  "type": "Feature",
  "properties": {
    "gn:admin1_code":"16.0",
    "gn:asciiname":"Nhuan Trach",
    "gn:country_code":"VN",
    "gn:dem":16,
    "gn:feature_class":"P",
    "gn:feature_code":"PPL",
    "gn:name":"Nhu\u1eadn Tr\u1ea1ch",
    "gn:population":0,
    "gn:timezone":"Asia/Ho_Chi_Minh",
    "iso:country":"VN",
    "wof:name":"Nhuan Trach",
    "wof:placetype":"locality"
},
  "geometry": {"coordinates":[105.55,20.86667000000001],"type":"Point"}
}