{
  "type": "Feature",
  "properties": {
    "gn:admin1_code":"92.0",
    "gn:asciiname":"Ban Lich Neua",
    "gn:country_code":"VN",
    "gn:dem":612,
    "gn:feature_class":"P",
    "gn:feature_code":"PPL",
    "gn:name":"B\u1ea3n Lich Neua",
    "gn:population":0,
    "gn:timezone":"Asia/Ho_Chi_Minh",
    "iso:country":"VN",
    "wof:name":"Ban Lich Neua",
    "wof:placetype":"locality"
},
  "geometry": {"coordinates":[103.25,21.46667],"type":"Point"}
}