{
  "type": "Feature",
  "properties": {
    "gn:admin1_code":"32.0",
    "gn:asciiname":"Ban Le",
    "gn:country_code":"VN",
    "gn:dem":343,
    "gn:feature_class":"P",
    "gn:feature_code":"PPL",
    "gn:name":"B\u1ea3n L\u00e8",
    "gn:population":0,
    "gn:timezone":"Asia/Ho_Chi_Minh",
    "iso:country":"VN",
    "name:und_x_variant":[
        "B\u1ea3n L\u1ec1"
    ],
    "name:vie_x_preferred":[
        "B\u1ea3n L\u00e8"
    ],
    "wof:name":"Ban Le",
    "wof:placetype":"locality"
},
  "geometry": {"coordinates":[103.80421,21.01352],"type":"Point"}
}