{
  "type": "Feature",
  "properties": {
    "gn:admin1_code":"45.0",
    "gn:asciiname":"Tan Giao",
    "gn:country_code":"VN",
    "gn:dem":95,
    "gn:feature_class":"P",
    "gn:feature_code":"PPL",
    "gn:name":"T\u00e2n Giao",
    "gn:population":0,
    "gn:timezone":"Asia/Ho_Chi_Minh",
    "iso:country":"VN",
    "name:vie_x_preferred":[
        "T\u00e2n Giao"
    ],
    "wof:name":"Tan Giao",
    "wof:placetype":"locality"
},
  "geometry": {"coordinates":[107.19371,10.65836],"type":"Point"}
}