{
  "type": "Feature",
  "properties": {
    "gn:admin1_code":"59.0",
    "gn:asciiname":"Moc Hoan",
    "gn:country_code":"VN",
    "gn:dem":110,
    "gn:feature_class":"P",
    "gn:feature_code":"PPL",
    "gn:name":"M\u00f4c Ho\u00e0n",
    "gn:population":0,
    "gn:timezone":"Asia/Ho_Chi_Minh",
    "iso:country":"VN",
    "wof:name":"Moc Hoan",
    "wof:placetype":"locality"
},
  "geometry": {"coordinates":[105.88333,20.25],"type":"Point"}
}