{
  "type": "Feature",
  "properties": {
    "gn:admin1_code":"50.0",
    "gn:asciiname":"Ban Coc Phat",
    "gn:country_code":"VN",
    "gn:dem":207,
    "gn:feature_class":"P",
    "gn:feature_code":"PPL",
    "gn:name":"B\u1ea3n C\u1ed1c Ph\u00e1t",
    "gn:population":0,
    "gn:timezone":"Asia/Ho_Chi_Minh",
    "iso:country":"VN",
    "name:vie_x_preferred":[
        "C\u1ed1c Ph\u00e1t"
    ],
    "name:vie_x_variant":[
        "B\u1ea3n C\u1ed1c Ph\u00e1t"
    ],
    "wof:name":"Ban Coc Phat",
    "wof:placetype":"locality"
},
  "geometry": {"coordinates":[105.37654000000001,22.71731],"type":"Point"}
}