{
  "type": "Feature",
  "properties": {
    "gn:admin1_code":"88.0",
    "gn:asciiname":"Buon Ko Emong",
    "gn:country_code":"VN",
    "gn:dem":434,
    "gn:feature_class":"P",
    "gn:feature_code":"PPL",
    "gn:name":"Bu\u00f4n K\u00f4 Em\u00f4ng",
    "gn:population":0,
    "gn:timezone":"Asia/Ho_Chi_Minh",
    "iso:country":"VN",
    "name:und_x_variant":[
        "Buon M\u2019Prenh",
        "Bu\u00f4n K\u00f4 Em\u00f4ng"
    ],
    "wof:name":"Buon Ko Emong",
    "wof:placetype":"locality"
},
  "geometry": {"coordinates":[108.23333,12.58333],"type":"Point"}
}