{
  "type": "Feature",
  "properties": {
    "gn:admin1_code":"68.0",
    "gn:asciiname":"Lang Ca",
    "gn:country_code":"VN",
    "gn:dem":64,
    "gn:feature_class":"P",
    "gn:feature_code":"PPL",
    "gn:name":"L\u00e0ng C\u00e1",
    "gn:population":0,
    "gn:timezone":"Asia/Ho_Chi_Minh",
    "iso:country":"VN",
    "name:und_x_variant":[
        "L\u00e0ng Ca"
    ],
    "name:vie_x_preferred":[
        "L\u00e0ng C\u00e1"
    ],
    "wof:name":"Lang Ca",
    "wof:placetype":"locality"
},
  "geometry": {"coordinates":[105.38206,21.69351],"type":"Point"}
}