{
  "type": "Feature",
  "properties": {
    "gn:admin1_code":"5.0",
    "gn:asciiname":"Khu Mot",
    "gn:country_code":"VN",
    "gn:dem":154,
    "gn:feature_class":"P",
    "gn:feature_code":"PPL",
    "gn:name":"Khu M\u1ed9t",
    "gn:population":0,
    "gn:timezone":"Asia/Ho_Chi_Minh",
    "iso:country":"VN",
    "name:vie_x_preferred":[
        "Khu M\u1ed9t"
    ],
    "name:vie_x_variant":[
        "Khu 1"
    ],
    "wof:name":"Khu Mot",
    "wof:placetype":"locality"
},
  "geometry": {"coordinates":[105.49821,22.81869],"type":"Point"}
}