{
  "type": "Feature",
  "properties": {
    "gn:admin1_code":"71.0",
    "gn:asciiname":"Cao Thuong",
    "gn:country_code":"VN",
    "gn:dem":15,
    "gn:feature_class":"P",
    "gn:feature_code":"PPLA2",
    "gn:name":"Cao Th\u01b0\u1ee3ng",
    "gn:population":0,
    "gn:timezone":"Asia/Ho_Chi_Minh",
    "iso:country":"VN",
    "name:nld_x_preferred":[
        "Cao Th\u01b0\u1ee3ng"
    ],
    "name:vie_x_preferred":[
        "Cao Th\u01b0\u1ee3ng"
    ],
    "wof:name":"Cao Thuong",
    "wof:placetype":"locality"
},
  "geometry": {"coordinates":[106.12931,21.38707],"type":"Point"}
}