{
  "type": "Feature",
  "properties": {
    "gn:admin1_code":"88.0",
    "gn:asciiname":"Ban Ay Jao",
    "gn:cc2":"VN",
    "gn:country_code":"VN",
    "gn:dem":466,
    "gn:feature_class":"P",
    "gn:feature_code":"PPL",
    "gn:name":"Ban Ay Jao",
    "gn:population":0,
    "gn:timezone":"Asia/Ho_Chi_Minh",
    "iso:country":"VN",
    "name:und_x_variant":[
        "Buon Ay Jao",
        "Ban Ay Jao"
    ],
    "wof:name":"Ban Ay Jao",
    "wof:placetype":"locality"
},
  "geometry": {"coordinates":[108.59999999999999,12.65],"type":"Point"}
}