{
  "type": "Feature",
  "properties": {
    "gn:admin1_code":"55.0",
    "gn:asciiname":"Kong Tri",
    "gn:country_code":"VN",
    "gn:dem":950,
    "gn:feature_class":"P",
    "gn:feature_code":"PPL",
    "gn:name":"Kong Tri",
    "gn:population":0,
    "gn:timezone":"Asia/Ho_Chi_Minh",
    "iso:country":"VN",
    "name:und_x_variant":[
        "Kon Tri",
        "Kong Try",
        "Kong Tri"
    ],
    "wof:name":"Kong Tri",
    "wof:placetype":"locality"
},
  "geometry": {"coordinates":[108.03333000000001,14.53333],"type":"Point"}
}