{
  "type": "Feature",
  "properties": {
    "gn:admin1_code":"58.0",
    "gn:asciiname":"Lang Cay",
    "gn:country_code":"VN",
    "gn:dem":100,
    "gn:feature_class":"P",
    "gn:feature_code":"PPL",
    "gn:name":"L\u00e0ng Cay",
    "gn:population":0,
    "gn:timezone":"Asia/Ho_Chi_Minh",
    "iso:country":"VN",
    "name:vie_x_preferred":[
        "L\u00e0ng Cay"
    ],
    "wof:name":"Lang Cay",
    "wof:placetype":"locality"
},
  "geometry": {"coordinates":[105.57023999999998,19.39081],"type":"Point"}
}