{
  "type": "Feature",
  "properties": {
    "gn:admin1_code":"69.0",
    "gn:asciiname":"Tan Quoi",
    "gn:country_code":"VN",
    "gn:dem":0,
    "gn:feature_class":"P",
    "gn:feature_code":"PPL",
    "gn:name":"T\u00e2n Q\u01b0\u1edbi",
    "gn:population":0,
    "gn:timezone":"Asia/Ho_Chi_Minh",
    "iso:country":"VN",
    "name:vie_x_preferred":[
        "T\u00e2n Q\u01b0\u1edbi"
    ],
    "wof:name":"Tan Quoi",
    "wof:placetype":"locality"
},
  "geometry": {"coordinates":[105.9114,10.24883],"type":"Point"}
}