{
  "type": "Feature",
  "properties": {
    "gn:admin1_code":"88.0",
    "gn:asciiname":"Pu Hien",
    "gn:country_code":"VN",
    "gn:dem":548,
    "gn:feature_class":"P",
    "gn:feature_code":"PPL",
    "gn:name":"Pu Hi\u00ean",
    "gn:population":0,
    "gn:timezone":"Asia/Ho_Chi_Minh",
    "iso:country":"VN",
    "name:und_x_variant":[
        "Buon Pu Y Hueh",
        "Bu\u00f4n Pu Hu\u00e8h"
    ],
    "name:vie_x_preferred":[
        "Pu Hi\u00ean"
    ],
    "wof:name":"Pu Hien",
    "wof:placetype":"locality"
},
  "geometry": {"coordinates":[108.21633,12.67605],"type":"Point"}
}