{
  "type": "Feature",
  "properties": {
    "gn:admin1_code":"13.0",
    "gn:asciiname":"Dong Bai",
    "gn:country_code":"VN",
    "gn:dem":0,
    "gn:feature_class":"P",
    "gn:feature_code":"PPL",
    "gn:name":"\u0110\u1ed3ng B\u00e0i",
    "gn:population":0,
    "gn:timezone":"Asia/Ho_Chi_Minh",
    "iso:country":"VN",
    "wof:name":"Dong Bai",
    "wof:placetype":"locality"
},
  "geometry": {"coordinates":[106.86667,20.81667],"type":"Point"}
}