{
  "type": "Feature",
  "properties": {
    "gn:admin1_code":"89.0",
    "gn:asciiname":"Ta Phin Ba",
    "gn:country_code":"VN",
    "gn:dem":1620,
    "gn:feature_class":"P",
    "gn:feature_code":"PPL",
    "gn:name":"T\u1ea3 Ph\u00ecn Ba",
    "gn:population":0,
    "gn:timezone":"Asia/Ho_Chi_Minh",
    "iso:country":"VN",
    "name:vie_x_preferred":[
        "T\u1ea3 Ph\u00ecn Ba"
    ],
    "name:vie_x_variant":[
        "T\u1ea3 Ph\u00ecn 3"
    ],
    "wof:name":"Ta Phin Ba",
    "wof:placetype":"locality"
},
  "geometry": {"coordinates":[103.2165,22.35598],"type":"Point"}
}