{
  "type": "Feature",
  "properties": {
    "gn:admin1_code":"89.0",
    "gn:asciiname":"Nam No Hai",
    "gn:country_code":"VN",
    "gn:dem":511,
    "gn:feature_class":"P",
    "gn:feature_code":"PPL",
    "gn:name":"N\u1eadm No Hai",
    "gn:population":0,
    "gn:timezone":"Asia/Ho_Chi_Minh",
    "iso:country":"VN",
    "name:vie_x_preferred":[
        "N\u1eadm No Hai"
    ],
    "name:vie_x_variant":[
        "N\u1eadm No 2"
    ],
    "wof:name":"Nam No Hai",
    "wof:placetype":"locality"
},
  "geometry": {"coordinates":[103.14104,22.36733],"type":"Point"}
}