{
  "type": "Feature",
  "properties": {
    "gn:admin1_code":"32.0",
    "gn:asciiname":"Noong Lay",
    "gn:country_code":"VN",
    "gn:dem":586,
    "gn:feature_class":"P",
    "gn:feature_code":"PPL",
    "gn:name":"No\u1ecdng Lay",
    "gn:population":0,
    "gn:timezone":"Asia/Ho_Chi_Minh",
    "iso:country":"VN",
    "wof:name":"Noong Lay",
    "wof:placetype":"locality"
},
  "geometry": {"coordinates":[103.75,21.46667],"type":"Point"}
}