{
  "type": "Feature",
  "properties": {
    "gn:admin1_code":"66.0",
    "gn:asciiname":"Ta Vai",
    "gn:country_code":"VN",
    "gn:dem":300,
    "gn:feature_class":"P",
    "gn:feature_code":"PPL",
    "gn:name":"T\u00e0 Vai",
    "gn:population":0,
    "gn:timezone":"Asia/Ho_Chi_Minh",
    "iso:country":"VN",
    "name:und_x_variant":[
        "Te Ney"
    ],
    "name:vie_x_preferred":[
        "T\u00e0 Vai"
    ],
    "wof:name":"Ta Vai",
    "wof:placetype":"locality"
},
  "geometry": {"coordinates":[107.04582000000001,16.37577000000001],"type":"Point"}
}