{
  "type": "Feature",
  "properties": {
    "gn:admin1_code":"67.0",
    "gn:asciiname":"Giong Ba Nhi",
    "gn:cc2":"VN",
    "gn:country_code":"VN",
    "gn:dem":2,
    "gn:feature_class":"P",
    "gn:feature_code":"PPL",
    "gn:name":"Gi\u1ed3ng Ba Nhi",
    "gn:population":0,
    "gn:timezone":"Asia/Ho_Chi_Minh",
    "iso:country":"VN",
    "name:und_x_variant":[
        "Ba Nhi",
        "Gi\u1ed3ng Ba Nhi"
    ],
    "wof:name":"Giong Ba Nhi",
    "wof:placetype":"locality"
},
  "geometry": {"coordinates":[106.37667,9.65167],"type":"Point"}
}