{
  "type": "Feature",
  "properties": {
    "gn:admin1_code":"72.0",
    "gn:asciiname":"Ban Dan",
    "gn:country_code":"VN",
    "gn:dem":236,
    "gn:feature_class":"P",
    "gn:feature_code":"PPL",
    "gn:name":"B\u1ea3n \u0110\u00e1n",
    "gn:population":0,
    "gn:timezone":"Asia/Ho_Chi_Minh",
    "iso:country":"VN",
    "name:und_x_variant":[
        "B\u1ea3n Dan"
    ],
    "name:vie_x_preferred":[
        "B\u1ea3n \u0110\u00e1n"
    ],
    "wof:name":"Ban Dan",
    "wof:placetype":"locality"
},
  "geometry": {"coordinates":[105.76442,22.17744],"type":"Point"}
}