{
  "type": "Feature",
  "properties": {
    "gn:admin1_code":"91.0",
    "gn:asciiname":"B'tong",
    "gn:country_code":"VN",
    "gn:dem":719,
    "gn:feature_class":"P",
    "gn:feature_code":"PPL",
    "gn:name":"B\u2019tong",
    "gn:population":0,
    "gn:timezone":"Asia/Ho_Chi_Minh",
    "iso:country":"VN",
    "wof:name":"B'tong",
    "wof:placetype":"locality"
},
  "geometry": {"coordinates":[107.98333,11.83333],"type":"Point"}
}