{
  "type": "Feature",
  "properties": {
    "gn:admin1_code":"32.0",
    "gn:asciiname":"Phieng Kuan",
    "gn:country_code":"VN",
    "gn:dem":920,
    "gn:feature_class":"P",
    "gn:feature_code":"PPL",
    "gn:name":"Phieng Kuan",
    "gn:population":0,
    "gn:timezone":"Asia/Ho_Chi_Minh",
    "iso:country":"VN",
    "wof:name":"Phieng Kuan",
    "wof:placetype":"locality"
},
  "geometry": {"coordinates":[104.65000000000001,20.91667],"type":"Point"}
}