{
  "type": "Feature",
  "properties": {
    "gn:admin1_code":"88.0",
    "gn:asciiname":"Buon Dung",
    "gn:country_code":"VN",
    "gn:dem":509,
    "gn:feature_class":"P",
    "gn:feature_code":"PPL",
    "gn:name":"Bu\u00f4n Dung",
    "gn:population":0,
    "gn:timezone":"Asia/Ho_Chi_Minh",
    "iso:country":"VN",
    "name:und_x_variant":[
        "Buon Jung Yu",
        "Buon Yung",
        "Bu\u00f4n Jung",
        "Ban Jung"
    ],
    "name:vie_x_preferred":[
        "Bu\u00f4n Dung"
    ],
    "wof:name":"Buon Dung",
    "wof:placetype":"locality"
},
  "geometry": {"coordinates":[108.15446,12.64261],"type":"Point"}
}