{
  "type": "Feature",
  "properties": {
    "gn:admin1_code":"30.0",
    "gn:asciiname":"Kenh Trao",
    "gn:country_code":"VN",
    "gn:dem":227,
    "gn:feature_class":"P",
    "gn:feature_code":"PPL",
    "gn:name":"K\u00eanh Tr\u1ea1o",
    "gn:population":0,
    "gn:timezone":"Asia/Ho_Chi_Minh",
    "iso:country":"VN",
    "wof:name":"Kenh Trao",
    "wof:placetype":"locality"
},
  "geometry": {"coordinates":[106.90000000000001,21.15],"type":"Point"}
}