{
  "type": "Feature",
  "properties": {
    "gn:admin1_code":"49.0",
    "gn:asciiname":"Plei Bra",
    "gn:country_code":"VN",
    "gn:dem":268,
    "gn:feature_class":"P",
    "gn:feature_code":"PPL",
    "gn:name":"Plei Bra",
    "gn:population":0,
    "gn:timezone":"Asia/Ho_Chi_Minh",
    "iso:country":"VN",
    "name:vie_x_preferred":[
        "Plei Bra"
    ],
    "wof:name":"Plei Bra",
    "wof:placetype":"locality"
},
  "geometry": {"coordinates":[107.54956,13.92924],"type":"Point"}
}