{
  "type": "Feature",
  "properties": {
    "gn:admin1_code":"73.0",
    "gn:asciiname":"Ap Rach Ran",
    "gn:country_code":"VN",
    "gn:dem":4,
    "gn:feature_class":"P",
    "gn:feature_code":"PPL",
    "gn:name":"\u1ea4p R\u1ea1ch R\u1eafn",
    "gn:population":0,
    "gn:timezone":"Asia/Ho_Chi_Minh",
    "iso:country":"VN",
    "name:und_x_variant":[
        "Xom Rach Rang",
        "\u1ea4p R\u1ea1ch R\u1eafn"
    ],
    "wof:name":"Ap Rach Ran",
    "wof:placetype":"locality"
},
  "geometry": {"coordinates":[105.46666999999999,9.21667],"type":"Point"}
}