{
  "type": "Feature",
  "properties": {
    "gn:admin1_code":"5.0",
    "gn:asciiname":"Ban Khi Chao",
    "gn:country_code":"VN",
    "gn:dem":303,
    "gn:feature_class":"P",
    "gn:feature_code":"PPL",
    "gn:name":"B\u1ea3n Kh\u1ec9 Ch\u00e1o",
    "gn:population":0,
    "gn:timezone":"Asia/Ho_Chi_Minh",
    "iso:country":"VN",
    "name:und_x_variant":[
        "L\u0169ng Khi Ch\u00e1o"
    ],
    "name:vie_x_preferred":[
        "B\u1ea3n Kh\u1ec9 Ch\u00e1o"
    ],
    "wof:name":"Ban Khi Chao",
    "wof:placetype":"locality"
},
  "geometry": {"coordinates":[106.82234,22.8017],"type":"Point"}
}