{
  "type": "Feature",
  "properties": {
    "gn:admin1_code":"72.0",
    "gn:asciiname":"Doi Khai Chi",
    "gn:country_code":"VN",
    "gn:dem":910,
    "gn:feature_class":"P",
    "gn:feature_code":"PPL",
    "gn:name":"\u0110\u1ed9i Khai Ch\u1ec9",
    "gn:population":0,
    "gn:timezone":"Asia/Ho_Chi_Minh",
    "iso:country":"VN",
    "name:vie_x_preferred":[
        "\u0110\u1ed9i Khai Ch\u1ec9"
    ],
    "wof:name":"Doi Khai Chi",
    "wof:placetype":"locality"
},
  "geometry": {"coordinates":[105.52822,22.26241],"type":"Point"}
}