{
  "type": "Feature",
  "properties": {
    "gn:admin1_code":"49.0",
    "gn:asciiname":"Plei Poo Jal",
    "gn:country_code":"VN",
    "gn:dem":687,
    "gn:feature_class":"P",
    "gn:feature_code":"PPL",
    "gn:name":"Plei Po\u00f4 Jal",
    "gn:population":0,
    "gn:timezone":"Asia/Ho_Chi_Minh",
    "iso:country":"VN",
    "name:und_x_variant":[
        "Plei Poo Jial",
        "Plei Po\u00f4 Jal"
    ],
    "wof:name":"Plei Poo Jal",
    "wof:placetype":"locality"
},
  "geometry": {"coordinates":[107.91667,13.91667],"type":"Point"}
}