{
  "type": "Feature",
  "properties": {
    "gn:admin1_code":"75.0",
    "gn:asciiname":"Ap Ba",
    "gn:country_code":"VN",
    "gn:dem":13,
    "gn:feature_class":"P",
    "gn:feature_code":"PPL",
    "gn:name":"\u1ea4p Ba",
    "gn:population":0,
    "gn:timezone":"Asia/Ho_Chi_Minh",
    "iso:country":"VN",
    "name:vie_x_preferred":[
        "\u1ea4p Ba"
    ],
    "name:vie_x_variant":[
        "\u1ea4p 3"
    ],
    "wof:name":"Ap Ba",
    "wof:placetype":"locality"
},
  "geometry": {"coordinates":[106.41070000000001,11.19461],"type":"Point"}
}