{
  "type": "Feature",
  "properties": {
    "gn:admin1_code":"83.0",
    "gn:asciiname":"Thach Khoan",
    "gn:country_code":"VN",
    "gn:dem":28,
    "gn:feature_class":"P",
    "gn:feature_code":"PPL",
    "gn:name":"Th\u1ea1ch Kho\u00e1n",
    "gn:population":0,
    "gn:timezone":"Asia/Ho_Chi_Minh",
    "iso:country":"VN",
    "wof:name":"Thach Khoan",
    "wof:placetype":"locality"
},
  "geometry": {"coordinates":[105.25,21.18333],"type":"Point"}
}