{
  "type": "Feature",
  "properties": {
    "gn:admin1_code":"44.0",
    "gn:asciiname":"Yen Vien",
    "gn:country_code":"VN",
    "gn:dem":14,
    "gn:feature_class":"P",
    "gn:feature_code":"PPL",
    "gn:name":"Y\u00ean Vi\u00ean",
    "gn:population":0,
    "gn:timezone":"Asia/Ho_Chi_Minh",
    "iso:country":"VN",
    "name:und_x_variant":[
        "Y\u00ean Vi\u00ean"
    ],
    "wof:name":"Yen Vien",
    "wof:placetype":"locality"
},
  "geometry": {"coordinates":[105.91667,21.08333],"type":"Point"}
}