{
  "type": "Feature",
  "properties": {
    "gn:admin1_code":"62.0",
    "gn:asciiname":"Phu Qui",
    "gn:country_code":"VN",
    "gn:dem":19,
    "gn:feature_class":"P",
    "gn:feature_code":"PPL",
    "gn:name":"Ph\u00fa Qu\u00ed",
    "gn:population":0,
    "gn:timezone":"Asia/Ho_Chi_Minh",
    "iso:country":"VN",
    "name:und_x_variant":[
        "Ph\u00fa L\u00e2m",
        "Ph\u00fa Qu\u00ed"
    ],
    "wof:name":"Phu Qui",
    "wof:placetype":"locality"
},
  "geometry": {"coordinates":[106.51667,17.48333],"type":"Point"}
}