{
  "type": "Feature",
  "properties": {
    "gn:admin1_code":"39.0",
    "gn:asciiname":"Na Puc",
    "gn:cc2":"VN",
    "gn:country_code":"VN",
    "gn:dem":203,
    "gn:feature_class":"P",
    "gn:feature_code":"PPL",
    "gn:name":"Na Puc",
    "gn:population":0,
    "gn:timezone":"Asia/Ho_Chi_Minh",
    "iso:country":"VN",
    "name:und_x_variant":[
        "Na Pun",
        "Na Puo",
        "Na Puc"
    ],
    "wof:name":"Na Puc",
    "wof:placetype":"locality"
},
  "geometry": {"coordinates":[106.58333,22.23333],"type":"Point"}
}