{
  "type": "Feature",
  "properties": {
    "gn:admin1_code":"90.0",
    "gn:asciiname":"Sao Ko Ti",
    "gn:country_code":"VN",
    "gn:dem":1175,
    "gn:feature_class":"P",
    "gn:feature_code":"PPL",
    "gn:name":"Sao Ko Ti",
    "gn:population":0,
    "gn:timezone":"Asia/Ho_Chi_Minh",
    "iso:country":"VN",
    "wof:name":"Sao Ko Ti",
    "wof:placetype":"locality"
},
  "geometry": {"coordinates":[104.36667,22.63333],"type":"Point"}
}