{
  "type": "Feature",
  "properties": {
    "gn:admin1_code":"68.0",
    "gn:asciiname":"Lang Dong",
    "gn:country_code":"VN",
    "gn:dem":27,
    "gn:feature_class":"P",
    "gn:feature_code":"PPL",
    "gn:name":"L\u00e0ng D\u00f4ng",
    "gn:population":0,
    "gn:timezone":"Asia/Ho_Chi_Minh",
    "iso:country":"VN",
    "name:vie_x_preferred":[
        "L\u00e0ng D\u00f4ng"
    ],
    "wof:name":"Lang Dong",
    "wof:placetype":"locality"
},
  "geometry": {"coordinates":[105.19119999999999,21.81859],"type":"Point"}
}