{
  "type": "Feature",
  "properties": {
    "gn:admin1_code":"43.0",
    "gn:asciiname":"Suoi Cat",
    "gn:country_code":"VN",
    "gn:dem":129,
    "gn:feature_class":"P",
    "gn:feature_code":"PPL",
    "gn:name":"Su\u1ed1i C\u00e1t",
    "gn:population":0,
    "gn:timezone":"Asia/Ho_Chi_Minh",
    "iso:country":"VN",
    "name:und_x_variant":[
        "\u1ea4p Su\u1ed1i C\u00e1t"
    ],
    "name:vie_x_preferred":[
        "Su\u1ed1i C\u00e1t"
    ],
    "wof:name":"Suoi Cat",
    "wof:placetype":"locality"
},
  "geometry": {"coordinates":[107.36552,10.90839],"type":"Point"}
}