{
  "type": "Feature",
  "properties": {
    "gn:admin1_code":"91.0",
    "gn:asciiname":"Nghia Binh",
    "gn:country_code":"VN",
    "gn:dem":668,
    "gn:feature_class":"P",
    "gn:feature_code":"PPL",
    "gn:name":"Ngh\u0129a B\u00ecnh",
    "gn:population":0,
    "gn:timezone":"Asia/Ho_Chi_Minh",
    "iso:country":"VN",
    "name:vie_x_preferred":[
        "Ngh\u0129a B\u00ecnh"
    ],
    "wof:name":"Nghia Binh",
    "wof:placetype":"locality"
},
  "geometry": {"coordinates":[107.68747,12.03116],"type":"Point"}
}