{
  "type": "Feature",
  "properties": {
    "gn:admin1_code":"58.0",
    "gn:asciiname":"Son Thanh",
    "gn:country_code":"VN",
    "gn:dem":18,
    "gn:feature_class":"P",
    "gn:feature_code":"PPL",
    "gn:name":"S\u01a1n Th\u00e0nh",
    "gn:population":0,
    "gn:timezone":"Asia/Ho_Chi_Minh",
    "iso:country":"VN",
    "name:vie_x_preferred":[
        "S\u01a1n Th\u00e0nh"
    ],
    "wof:name":"Son Thanh",
    "wof:placetype":"locality"
},
  "geometry": {"coordinates":[105.31255,18.7877],"type":"Point"}
}