{
  "type": "Feature",
  "properties": {
    "gn:admin1_code":"33.0",
    "gn:asciiname":"Tan Tien",
    "gn:country_code":"VN",
    "gn:dem":29,
    "gn:feature_class":"P",
    "gn:feature_code":"PPL",
    "gn:name":"T\u00e2n Ti\u1ebfn",
    "gn:population":0,
    "gn:timezone":"Asia/Ho_Chi_Minh",
    "iso:country":"VN",
    "name:vie_x_preferred":[
        "T\u00e2n Ti\u1ebfn"
    ],
    "wof:name":"Tan Tien",
    "wof:placetype":"locality"
},
  "geometry": {"coordinates":[106.16198,11.51335],"type":"Point"}
}