{
  "type": "Feature",
  "properties": {
    "gn:admin1_code":"67.0",
    "gn:asciiname":"Giong Cao",
    "gn:country_code":"VN",
    "gn:dem":3,
    "gn:feature_class":"P",
    "gn:feature_code":"PPL",
    "gn:name":"Gi\u1ed3ng Cao",
    "gn:population":0,
    "gn:timezone":"Asia/Ho_Chi_Minh",
    "iso:country":"VN",
    "name:vie_x_preferred":[
        "Gi\u1ed3ng Cao"
    ],
    "wof:name":"Giong Cao",
    "wof:placetype":"locality"
},
  "geometry": {"coordinates":[106.36999,9.70288],"type":"Point"}
}