{
  "type": "Feature",
  "properties": {
    "gn:admin1_code":"32.0",
    "gn:asciiname":"Ban Pac Ngan",
    "gn:country_code":"VN",
    "gn:dem":1321,
    "gn:feature_class":"P",
    "gn:feature_code":"PPL",
    "gn:name":"B\u1ea3n P\u1eb7c Ng\u1ea7n",
    "gn:population":0,
    "gn:timezone":"Asia/Ho_Chi_Minh",
    "iso:country":"VN",
    "name:vie_x_preferred":[
        "B\u1ea3n P\u1eb7c Ng\u1ea7n"
    ],
    "wof:name":"Ban Pac Ngan",
    "wof:placetype":"locality"
},
  "geometry": {"coordinates":[103.92739,21.16349],"type":"Point"}
}