{
  "type": "Feature",
  "properties": {
    "gn:admin1_code":"58.0",
    "gn:asciiname":"Ngoc Thai",
    "gn:country_code":"VN",
    "gn:dem":27,
    "gn:feature_class":"P",
    "gn:feature_code":"PPL",
    "gn:name":"Ng\u1ecdc Th\u00e1i",
    "gn:population":0,
    "gn:timezone":"Asia/Ho_Chi_Minh",
    "iso:country":"VN",
    "name:vie_x_preferred":[
        "Ng\u1ecdc Th\u00e1i"
    ],
    "wof:name":"Ngoc Thai",
    "wof:placetype":"locality"
},
  "geometry": {"coordinates":[105.39296000000002,18.92937],"type":"Point"}
}