{
  "type": "Feature",
  "properties": {
    "gn:admin1_code":"74.0",
    "gn:asciiname":"Man Xa",
    "gn:country_code":"VN",
    "gn:dem":11,
    "gn:feature_class":"P",
    "gn:feature_code":"PPL",
    "gn:name":"M\u1eabn X\u00e1",
    "gn:population":0,
    "gn:timezone":"Asia/Ho_Chi_Minh",
    "iso:country":"VN",
    "name:vie_x_preferred":[
        "M\u1eabn X\u00e1"
    ],
    "wof:name":"Man Xa",
    "wof:placetype":"locality"
},
  "geometry": {"coordinates":[105.93255000000001,21.1712],"type":"Point"}
}