{
  "type": "Feature",
  "properties": {
    "gn:admin1_code":"92.0",
    "gn:asciiname":"Na Tong",
    "gn:country_code":"VN",
    "gn:dem":946,
    "gn:feature_class":"P",
    "gn:feature_code":"PPL",
    "gn:name":"N\u00e0 T\u00f2ng",
    "gn:population":0,
    "gn:timezone":"Asia/Ho_Chi_Minh",
    "iso:country":"VN",
    "name:vie_x_preferred":[
        "N\u00e0 T\u00f2ng"
    ],
    "wof:name":"Na Tong",
    "wof:placetype":"locality"
},
  "geometry": {"coordinates":[103.37251000000001,21.80035],"type":"Point"}
}