{
  "type": "Feature",
  "properties": {
    "gn:admin1_code":"74.0",
    "gn:asciiname":"Thon Doai",
    "gn:country_code":"VN",
    "gn:dem":9,
    "gn:feature_class":"P",
    "gn:feature_code":"PPL",
    "gn:name":"Th\u00f4n \u0110o\u00e0i",
    "gn:population":0,
    "gn:timezone":"Asia/Ho_Chi_Minh",
    "iso:country":"VN",
    "name:vie_x_preferred":[
        "Th\u00f4n \u0110o\u00e0i"
    ],
    "wof:name":"Thon Doai",
    "wof:placetype":"locality"
},
  "geometry": {"coordinates":[106.06131999999999,21.13913],"type":"Point"}
}