{
  "type": "Feature",
  "properties": {
    "gn:admin1_code":"90.0",
    "gn:asciiname":"Lang Qua",
    "gn:country_code":"VN",
    "gn:dem":278,
    "gn:feature_class":"P",
    "gn:feature_code":"PPL",
    "gn:name":"L\u00e0ng Qua",
    "gn:population":0,
    "gn:timezone":"Asia/Ho_Chi_Minh",
    "iso:country":"VN",
    "name:und_x_variant":[
        "B\u1ea3n T\u00e2 Qua",
        "L\u00e0ng Qua"
    ],
    "wof:name":"Lang Qua",
    "wof:placetype":"locality"
},
  "geometry": {"coordinates":[104.33333,22.01667],"type":"Point"}
}