{
  "type": "Feature",
  "properties": {
    "gn:admin1_code":"90.0",
    "gn:asciiname":"Ta Trung Ho",
    "gn:country_code":"VN",
    "gn:dem":1382,
    "gn:feature_class":"P",
    "gn:feature_code":"PPL",
    "gn:name":"T\u1ea3 Trung H\u1ed3",
    "gn:population":0,
    "gn:timezone":"Asia/Ho_Chi_Minh",
    "iso:country":"VN",
    "name:und_x_variant":[
        "Ta Tchuong H\u1ed3",
        "T\u1ea3 Chung H\u1ed3"
    ],
    "name:vie_x_preferred":[
        "T\u1ea3 Trung H\u1ed3"
    ],
    "wof:name":"Ta Trung Ho",
    "wof:placetype":"locality"
},
  "geometry": {"coordinates":[103.9671,22.20326],"type":"Point"}
}