{
  "type": "Feature",
  "properties": {
    "gn:admin1_code":"70.0",
    "gn:asciiname":"Khe Tchat",
    "gn:country_code":"VN",
    "gn:dem":541,
    "gn:feature_class":"P",
    "gn:feature_code":"PPL",
    "gn:name":"Kh\u00ea Tchat",
    "gn:population":0,
    "gn:timezone":"Asia/Ho_Chi_Minh",
    "iso:country":"VN",
    "wof:name":"Khe Tchat",
    "wof:placetype":"locality"
},
  "geometry": {"coordinates":[104.48333,21.96667],"type":"Point"}
}