{
  "type": "Feature",
  "properties": {
    "gn:admin1_code":"89.0",
    "gn:asciiname":"Ban Sa Phi",
    "gn:country_code":"VN",
    "gn:dem":1854,
    "gn:feature_class":"P",
    "gn:feature_code":"PPL",
    "gn:name":"B\u1ea3n S\u00e0 Ph\u00ec",
    "gn:population":0,
    "gn:timezone":"Asia/Ho_Chi_Minh",
    "iso:country":"VN",
    "wof:name":"Ban Sa Phi",
    "wof:placetype":"locality"
},
  "geometry": {"coordinates":[102.86667,22.56667],"type":"Point"}
}