{
  "type": "Feature",
  "properties": {
    "gn:admin1_code":"90.0",
    "gn:asciiname":"Ban Nan Ho",
    "gn:country_code":"VN",
    "gn:dem":1177,
    "gn:feature_class":"P",
    "gn:feature_code":"PPL",
    "gn:name":"B\u1ea3n N\u00e0n H\u1ed3",
    "gn:population":0,
    "gn:timezone":"Asia/Ho_Chi_Minh",
    "iso:country":"VN",
    "name:vie_x_preferred":[
        "B\u1ea3n N\u00e0n H\u1ed3"
    ],
    "wof:name":"Ban Nan Ho",
    "wof:placetype":"locality"
},
  "geometry": {"coordinates":[104.35392,22.57772000000001],"type":"Point"}
}