{
  "type": "Feature",
  "properties": {
    "gn:admin1_code":"34.0",
    "gn:asciiname":"Lang Chiom",
    "gn:cc2":"VN",
    "gn:country_code":"VN",
    "gn:dem":147,
    "gn:feature_class":"P",
    "gn:feature_code":"PPL",
    "gn:name":"L\u00e0ng Chiom",
    "gn:population":0,
    "gn:timezone":"Asia/Ho_Chi_Minh",
    "iso:country":"VN",
    "name:und_x_variant":[
        "L\u00e0ng Chiam",
        "L\u00e0ng Chiom"
    ],
    "wof:name":"Lang Chiom",
    "wof:placetype":"locality"
},
  "geometry": {"coordinates":[105.21666999999999,19.83333],"type":"Point"}
}