{
  "type": "Feature",
  "properties": {
    "gn:admin1_code":"76.0",
    "gn:asciiname":"Bu Da Gro",
    "gn:country_code":"VN",
    "gn:dem":157,
    "gn:feature_class":"P",
    "gn:feature_code":"PPL",
    "gn:name":"Bu Da Gro",
    "gn:population":0,
    "gn:timezone":"Asia/Ho_Chi_Minh",
    "iso:country":"VN",
    "wof:name":"Bu Da Gro",
    "wof:placetype":"locality"
},
  "geometry": {"coordinates":[106.90000000000001,11.88333],"type":"Point"}
}