{
  "type": "Feature",
  "properties": {
    "gn:admin1_code":"72.0",
    "gn:asciiname":"Ban Cau",
    "gn:country_code":"VN",
    "gn:dem":337,
    "gn:feature_class":"P",
    "gn:feature_code":"PPL",
    "gn:name":"B\u1ea3n C\u1eadu",
    "gn:population":0,
    "gn:timezone":"Asia/Ho_Chi_Minh",
    "iso:country":"VN",
    "name:und_x_variant":[
        "B\u00e1n C\u1eadu",
        "B\u1ea3n Kao"
    ],
    "name:vie_x_preferred":[
        "B\u1ea3n C\u1eadu"
    ],
    "wof:name":"Ban Cau",
    "wof:placetype":"locality"
},
  "geometry": {"coordinates":[105.47750000000001,22.2076],"type":"Point"}
}