{
  "type": "Feature",
  "properties": {
    "gn:admin1_code":"65.0",
    "gn:asciiname":"Tra Quit",
    "gn:country_code":"VN",
    "gn:dem":4,
    "gn:feature_class":"P",
    "gn:feature_code":"PPL",
    "gn:name":"Tr\u00e0 Qu\u00edt",
    "gn:population":0,
    "gn:timezone":"Asia/Ho_Chi_Minh",
    "iso:country":"VN",
    "name:und_x_variant":[
        "X\u00f3m Tr\u00e0 Qu\u00edt"
    ],
    "name:vie_x_preferred":[
        "Tr\u00e0 Qu\u00edt"
    ],
    "wof:name":"Tra Quit",
    "wof:placetype":"locality"
},
  "geometry": {"coordinates":[105.89827,9.70576],"type":"Point"}
}