{
  "type": "Feature",
  "properties": {
    "gn:admin1_code":"1.0",
    "gn:asciiname":"Ap Dong Co Ki",
    "gn:cc2":"VN",
    "gn:country_code":"VN",
    "gn:dem":7,
    "gn:feature_class":"P",
    "gn:feature_code":"PPL",
    "gn:name":"\u1ea4p D\u1ed3ng C\u00f4 Ki",
    "gn:population":0,
    "gn:timezone":"Asia/Ho_Chi_Minh",
    "iso:country":"VN",
    "name:und_x_variant":[
        "Dong Co Ki",
        "Dong Duc",
        "\u1ea4p D\u1ed3ng C\u00f4 Ki"
    ],
    "wof:name":"Ap Dong Co Ki",
    "wof:placetype":"locality"
},
  "geometry": {"coordinates":[105.08333,10.91667],"type":"Point"}
}