{
  "type": "Feature",
  "properties": {
    "gn:admin1_code":"20.0",
    "gn:asciiname":"Cu Xa Phu Lam A",
    "gn:country_code":"VN",
    "gn:dem":4,
    "gn:feature_class":"P",
    "gn:feature_code":"PPLL",
    "gn:name":"C\u01b0 X\u00e1 Ph\u00fa L\u00e2m A",
    "gn:population":0,
    "gn:timezone":"Asia/Ho_Chi_Minh",
    "iso:country":"VN",
    "wof:name":"Cu Xa Phu Lam A",
    "wof:placetype":"locality"
},
  "geometry": {"coordinates":[106.63068,10.75062],"type":"Point"}
}