{
  "type": "Feature",
  "properties": {
    "gn:admin1_code":"92.0",
    "gn:asciiname":"Ma Thi Ho",
    "gn:country_code":"VN",
    "gn:dem":696,
    "gn:feature_class":"P",
    "gn:feature_code":"PPL",
    "gn:name":"Ma Th\u00ec H\u1ed3",
    "gn:population":0,
    "gn:timezone":"Asia/Ho_Chi_Minh",
    "iso:country":"VN",
    "name:vie_x_preferred":[
        "Ma Th\u00ec H\u1ed3"
    ],
    "wof:name":"Ma Thi Ho",
    "wof:placetype":"locality"
},
  "geometry": {"coordinates":[103.03321,21.8207],"type":"Point"}
}