{
  "type": "Feature",
  "properties": {
    "gn:admin1_code":"90.0",
    "gn:asciiname":"Ngoi Luc",
    "gn:country_code":"VN",
    "gn:dem":81,
    "gn:feature_class":"P",
    "gn:feature_code":"PPL",
    "gn:name":"Ng\u00f2i L\u00fac",
    "gn:population":0,
    "gn:timezone":"Asia/Ho_Chi_Minh",
    "iso:country":"VN",
    "name:und_x_variant":[
        "Ngai Luc",
        "Ng\u00f2i L\u00fac"
    ],
    "wof:name":"Ngoi Luc",
    "wof:placetype":"locality"
},
  "geometry": {"coordinates":[104.36667,22.18333],"type":"Point"}
}