{
  "type": "Feature",
  "properties": {
    "gn:admin1_code":"89.0",
    "gn:asciiname":"Ban Sai Luong",
    "gn:country_code":"VN",
    "gn:dem":455,
    "gn:feature_class":"P",
    "gn:feature_code":"PPL",
    "gn:name":"B\u1ea3n S\u00e0i L\u01b0\u01a1ng",
    "gn:population":0,
    "gn:timezone":"Asia/Ho_Chi_Minh",
    "iso:country":"VN",
    "name:vie_x_preferred":[
        "B\u1ea3n S\u00e0i L\u01b0\u01a1ng"
    ],
    "wof:name":"Ban Sai Luong",
    "wof:placetype":"locality"
},
  "geometry": {"coordinates":[103.72745,22.06995],"type":"Point"}
}