{
  "type": "Feature",
  "properties": {
    "gn:admin1_code":"49.0",
    "gn:asciiname":"Plei Doi",
    "gn:country_code":"VN",
    "gn:dem":657,
    "gn:feature_class":"P",
    "gn:feature_code":"PPL",
    "gn:name":"Plei Doi",
    "gn:population":0,
    "gn:timezone":"Asia/Ho_Chi_Minh",
    "iso:country":"VN",
    "wof:name":"Plei Doi",
    "wof:placetype":"locality"
},
  "geometry": {"coordinates":[107.78333000000001,14.18333],"type":"Point"}
}