{
  "type": "Feature",
  "properties": {
    "gn:admin1_code":"52.0",
    "gn:asciiname":"Sung Oc",
    "gn:country_code":"VN",
    "gn:dem":15,
    "gn:feature_class":"P",
    "gn:feature_code":"PPL",
    "gn:name":"S\u1ee7ng \u00d4c",
    "gn:population":0,
    "gn:timezone":"Asia/Ho_Chi_Minh",
    "iso:country":"VN",
    "name:und_x_variant":[
        "Song Oc",
        "S\u1ee7ng \u00d4c"
    ],
    "wof:name":"Sung Oc",
    "wof:placetype":"locality"
},
  "geometry": {"coordinates":[105.56667,18.51667],"type":"Point"}
}