{
  "type": "Feature",
  "properties": {
    "gn:admin1_code":"53.0",
    "gn:asciiname":"Lang Chum",
    "gn:country_code":"VN",
    "gn:dem":428,
    "gn:feature_class":"P",
    "gn:feature_code":"PPL",
    "gn:name":"L\u00e0ng Chum",
    "gn:population":0,
    "gn:timezone":"Asia/Ho_Chi_Minh",
    "iso:country":"VN",
    "name:vie_x_preferred":[
        "L\u00e0ng Chum"
    ],
    "wof:name":"Lang Chum",
    "wof:placetype":"locality"
},
  "geometry": {"coordinates":[104.96272999999999,20.96859],"type":"Point"}
}