{
  "type": "Feature",
  "properties": {
    "gn:admin1_code":"68.0",
    "gn:asciiname":"Na Va",
    "gn:country_code":"VN",
    "gn:dem":244,
    "gn:feature_class":"P",
    "gn:feature_code":"PPL",
    "gn:name":"N\u00e0 Va",
    "gn:population":0,
    "gn:timezone":"Asia/Ho_Chi_Minh",
    "iso:country":"VN",
    "name:vie_x_preferred":[
        "N\u00e0 Va"
    ],
    "wof:name":"Na Va",
    "wof:placetype":"locality"
},
  "geometry": {"coordinates":[105.31211,22.46377],"type":"Point"}
}