{
  "type": "Feature",
  "properties": {
    "gn:admin1_code":"71.0",
    "gn:asciiname":"Xom Giua",
    "gn:country_code":"VN",
    "gn:dem":23,
    "gn:feature_class":"P",
    "gn:feature_code":"PPL",
    "gn:name":"X\u00f3m Gi\u1eefa",
    "gn:population":0,
    "gn:timezone":"Asia/Ho_Chi_Minh",
    "iso:country":"VN",
    "name:und_x_variant":[
        "Lang Gi\u1eefa",
        "M\u1ef9 H\u00f2a"
    ],
    "name:vie_x_preferred":[
        "X\u00f3m Gi\u1eefa"
    ],
    "wof:name":"Xom Giua",
    "wof:placetype":"locality"
},
  "geometry": {"coordinates":[106.23797,21.43683],"type":"Point"}
}