{
  "type": "Feature",
  "properties": {
    "gn:admin1_code":"70.0",
    "gn:asciiname":"Tho Thon",
    "gn:country_code":"VN",
    "gn:dem":63,
    "gn:feature_class":"P",
    "gn:feature_code":"PPL",
    "gn:name":"Th\u1ecd Th\u00f4n",
    "gn:population":0,
    "gn:timezone":"Asia/Ho_Chi_Minh",
    "iso:country":"VN",
    "wof:name":"Tho Thon",
    "wof:placetype":"locality"
},
  "geometry": {"coordinates":[104.96666999999999,21.71667],"type":"Point"}
}