{
  "type": "Feature",
  "properties": {
    "gn:admin1_code":"71.0",
    "gn:asciiname":"Xom Soi",
    "gn:country_code":"VN",
    "gn:dem":6,
    "gn:feature_class":"P",
    "gn:feature_code":"PPL",
    "gn:name":"X\u00f3m S\u00f2i",
    "gn:population":0,
    "gn:timezone":"Asia/Ho_Chi_Minh",
    "iso:country":"VN",
    "name:vie_x_preferred":[
        "X\u00f3m S\u00f2i"
    ],
    "wof:name":"Xom Soi",
    "wof:placetype":"locality"
},
  "geometry": {"coordinates":[106.20189000000001,21.25204],"type":"Point"}
}