{
  "type": "Feature",
  "properties": {
    "gn:admin1_code":"72.0",
    "gn:asciiname":"Khuoi Phai",
    "gn:country_code":"VN",
    "gn:dem":146,
    "gn:feature_class":"P",
    "gn:feature_code":"PPL",
    "gn:name":"Khu\u1ed5i Ph\u00e1i",
    "gn:population":0,
    "gn:timezone":"Asia/Ho_Chi_Minh",
    "iso:country":"VN",
    "name:vie_x_preferred":[
        "Khu\u1ed5i Ph\u00e1i"
    ],
    "wof:name":"Khuoi Phai",
    "wof:placetype":"locality"
},
  "geometry": {"coordinates":[105.87712999999999,22.14565],"type":"Point"}
}