{
  "type": "Feature",
  "properties": {
    "gn:admin1_code":"5.0",
    "gn:asciiname":"Na Nghiong",
    "gn:country_code":"VN",
    "gn:dem":576,
    "gn:feature_class":"P",
    "gn:feature_code":"PPL",
    "gn:name":"N\u00e0 Nghi\u1ed1ng",
    "gn:population":0,
    "gn:timezone":"Asia/Ho_Chi_Minh",
    "iso:country":"VN",
    "wof:name":"Na Nghiong",
    "wof:placetype":"locality"
},
  "geometry": {"coordinates":[105.95,22.55],"type":"Point"}
}