{
  "type": "Feature",
  "properties": {
    "gn:admin1_code":"70.0",
    "gn:asciiname":"Nuoc Nong",
    "gn:country_code":"VN",
    "gn:dem":61,
    "gn:feature_class":"P",
    "gn:feature_code":"PPL",
    "gn:name":"N\u01b0\u1edbc N\u00f3ng",
    "gn:population":0,
    "gn:timezone":"Asia/Ho_Chi_Minh",
    "iso:country":"VN",
    "name:und_x_variant":[
        "X\u00f3m N\u01b0\u1edbc N\u00f3ng"
    ],
    "name:vie_x_preferred":[
        "N\u01b0\u1edbc N\u00f3ng"
    ],
    "wof:name":"Nuoc Nong",
    "wof:placetype":"locality"
},
  "geometry": {"coordinates":[104.62358999999999,21.91475],"type":"Point"}
}