{
  "type": "Feature",
  "properties": {
    "gn:admin1_code":"32.0",
    "gn:asciiname":"Loung Xa",
    "gn:country_code":"VN",
    "gn:dem":1171,
    "gn:feature_class":"P",
    "gn:feature_code":"PPL",
    "gn:name":"Loung Xa",
    "gn:population":0,
    "gn:timezone":"Asia/Ho_Chi_Minh",
    "iso:country":"VN",
    "wof:name":"Loung Xa",
    "wof:placetype":"locality"
},
  "geometry": {"coordinates":[104.83333,20.75],"type":"Point"}
}