{
  "type": "Feature",
  "properties": {
    "gn:admin1_code":"58.0",
    "gn:asciiname":"Thanh Da",
    "gn:country_code":"VN",
    "gn:dem":19,
    "gn:feature_class":"P",
    "gn:feature_code":"PPL",
    "gn:name":"Thanh \u0110a",
    "gn:population":0,
    "gn:timezone":"Asia/Ho_Chi_Minh",
    "iso:country":"VN",
    "name:vie_x_preferred":[
        "Thanh \u0110a"
    ],
    "wof:name":"Thanh Da",
    "wof:placetype":"locality"
},
  "geometry": {"coordinates":[105.50715,19.09304],"type":"Point"}
}