{
  "type": "Feature",
  "properties": {
    "gn:admin1_code":"68.0",
    "gn:asciiname":"Ban Bung",
    "gn:country_code":"VN",
    "gn:dem":384,
    "gn:feature_class":"P",
    "gn:feature_code":"PPL",
    "gn:name":"B\u00e1n B\u1ee5ng",
    "gn:population":0,
    "gn:timezone":"Asia/Ho_Chi_Minh",
    "iso:country":"VN",
    "name:vie_x_preferred":[
        "B\u00e1n B\u1ee5ng"
    ],
    "wof:name":"Ban Bung",
    "wof:placetype":"locality"
},
  "geometry": {"coordinates":[105.43022000000001,22.27997],"type":"Point"}
}