{
  "type": "Feature",
  "properties": {
    "gn:admin1_code":"53.0",
    "gn:asciiname":"Lang Giuom",
    "gn:country_code":"VN",
    "gn:dem":885,
    "gn:feature_class":"P",
    "gn:feature_code":"PPL",
    "gn:name":"L\u00e0ng Giu\u1ed9m",
    "gn:population":0,
    "gn:timezone":"Asia/Ho_Chi_Minh",
    "iso:country":"VN",
    "wof:name":"Lang Giuom",
    "wof:placetype":"locality"
},
  "geometry": {"coordinates":[105.41667,20.66667],"type":"Point"}
}