{
  "type": "Feature",
  "properties": {
    "gn:admin1_code":"65.0",
    "gn:asciiname":"Tan Thanh A",
    "gn:country_code":"VN",
    "gn:dem":-2,
    "gn:feature_class":"P",
    "gn:feature_code":"PPL",
    "gn:name":"T\u00e2n Th\u00e0nh A",
    "gn:population":0,
    "gn:timezone":"Asia/Ho_Chi_Minh",
    "iso:country":"VN",
    "name:vie_x_preferred":[
        "T\u00e2n Th\u00e0nh A"
    ],
    "wof:name":"Tan Thanh A",
    "wof:placetype":"locality"
},
  "geometry": {"coordinates":[105.94425,9.3452],"type":"Point"}
}