{
  "type": "Feature",
  "properties": {
    "gn:admin1_code":"3.0",
    "gn:asciiname":"Tien Dong Vam",
    "gn:country_code":"VN",
    "gn:dem":7,
    "gn:feature_class":"P",
    "gn:feature_code":"PPL",
    "gn:name":"Ti\u00ean \u0110\u00f4ng V\u1ea3m",
    "gn:population":0,
    "gn:timezone":"Asia/Ho_Chi_Minh",
    "iso:country":"VN",
    "name:vie_x_preferred":[
        "Ti\u00ean \u0110\u00f4ng V\u1ea3m"
    ],
    "wof:name":"Tien Dong Vam",
    "wof:placetype":"locality"
},
  "geometry": {"coordinates":[106.26409,10.26747],"type":"Point"}
}