{
  "type": "Feature",
  "properties": {
    "gn:admin1_code":"39.0",
    "gn:asciiname":"Coc Man",
    "gn:country_code":"VN",
    "gn:dem":319,
    "gn:feature_class":"P",
    "gn:feature_code":"PPL",
    "gn:name":"C\u1ed1c M\u1eb7n",
    "gn:population":0,
    "gn:timezone":"Asia/Ho_Chi_Minh",
    "iso:country":"VN",
    "name:vie_x_preferred":[
        "C\u1ed1c M\u1eb7n"
    ],
    "wof:name":"Coc Man",
    "wof:placetype":"locality"
},
  "geometry": {"coordinates":[106.31399,21.97732],"type":"Point"}
}