{
  "type": "Feature",
  "properties": {
    "gn:admin1_code":"93.0",
    "gn:asciiname":"Vi Thanh",
    "gn:country_code":"VN",
    "gn:dem":3,
    "gn:feature_class":"P",
    "gn:feature_code":"PPLA",
    "gn:name":"V\u1ecb Thanh",
    "gn:population":24477,
    "gn:timezone":"Asia/Ho_Chi_Minh",
    "iso:country":"VN",
    "name:und_x_variant":[
        "\u0110\u1ee9c Long",
        "Vi Tanh",
        "V\u1ecb Thanh"
    ],
    "wof:name":"Vi Thanh",
    "wof:placetype":"locality",
    "wof:population":24477
},
  "geometry": {"coordinates":[105.47011999999999,9.78449],"type":"Point"}
}