{
  "type": "Feature",
  "properties": {
    "gn:admin1_code":"93.0",
    "gn:asciiname":"Vi Thanh",
    "gn:country_code":"VN",
    "gn:dem":3,
    "gn:feature_class":"P",
    "gn:feature_code":"PPLA",
    "gn:name":"V\u1ecb Thanh",
    "gn:population":24477,
    "gn:timezone":"Asia/Ho_Chi_Minh",
    "iso:country":"VN",
    "name:ceb_x_preferred":[
        "V\u1ecb Thanh"
    ],
    "name:dan_x_preferred":[
        "Vi Thanh"
    ],
    "name:fas_x_preferred":[
        "\u0648\u06cc \u062a\u0627\u0646"
    ],
    "name:fra_x_preferred":[
        "Vi Thanh"
    ],
    "name:jpn_x_preferred":[
        "\u30f4\u30a3\u30fc\u30bf\u30a4\u30f3"
    ],
    "name:kor_x_preferred":[
        "\ube44\ud0c0\uc778"
    ],
    "name:msa_x_preferred":[
        "Vi Thanh"
    ],
    "name:nld_x_preferred":[
        "V\u1ecb Thanh"
    ],
    "name:pol_x_preferred":[
        "V\u1ecb Thanh"
    ],
    "name:rus_x_preferred":[
        "\u0412\u0438\u0442\u0445\u0430\u043d\u044c"
    ],
    "name:spa_x_preferred":[
        "V\u1ecb Thanh"
    ],
    "name:srp_x_preferred":[
        "\u0412\u0438 \u0422\u0430\u043d"
    ],
    "name:swe_x_preferred":[
        "Vi Thanh"
    ],
    "name:ukr_x_preferred":[
        "\u0412\u0456\u0442\u0445\u0430\u043d\u044c"
    ],
    "name:und_x_variant":[
        "\u0110\u1ee9c Long",
        "Vi Tanh",
        "V\u1ecb Thanh"
    ],
    "name:urd_x_preferred":[
        "\u0648\u06cc \u062a\u06be\u0627\u0646"
    ],
    "name:vie_x_preferred":[
        "V\u1ecb Thanh"
    ],
    "name:war_x_preferred":[
        "Vi Thanh"
    ],
    "name:zho_x_preferred":[
        "\u6e2d\u6e05\u5e02"
    ],
    "wof:name":"Vi Thanh",
    "wof:placetype":"locality",
    "wof:population":24477
},
  "geometry": {"coordinates":[105.47011999999999,9.78449],"type":"Point"}
}