{
  "type": "Feature",
  "properties": {
    "gn:admin1_code":"89.0",
    "gn:asciiname":"Sang Cai",
    "gn:country_code":"VN",
    "gn:dem":926,
    "gn:feature_class":"P",
    "gn:feature_code":"PPL",
    "gn:name":"S\u1ea3ng C\u1ea3i",
    "gn:population":0,
    "gn:timezone":"Asia/Ho_Chi_Minh",
    "iso:country":"VN",
    "name:vie_x_preferred":[
        "S\u1ea3ng C\u1ea3i"
    ],
    "wof:name":"Sang Cai",
    "wof:placetype":"locality"
},
  "geometry": {"coordinates":[103.30349,22.63399],"type":"Point"}
}