{
  "type": "Feature",
  "properties": {
    "gn:admin1_code":"24.0",
    "gn:asciiname":"Duc Hanh",
    "gn:country_code":"VN",
    "gn:dem":4,
    "gn:feature_class":"P",
    "gn:feature_code":"PPL",
    "gn:name":"Duc Hanh",
    "gn:population":0,
    "gn:timezone":"Asia/Ho_Chi_Minh",
    "iso:country":"VN",
    "name:und_x_variant":[
        "X\u00f3m \u0110\u1ee9c H\u1ea1nh"
    ],
    "wof:name":"Duc Hanh",
    "wof:placetype":"locality"
},
  "geometry": {"coordinates":[106.43333,10.91667],"type":"Point"}
}