{
  "type": "Feature",
  "properties": {
    "gn:admin1_code":"93.0",
    "gn:asciiname":"My Thuan Hai",
    "gn:country_code":"VN",
    "gn:dem":5,
    "gn:feature_class":"P",
    "gn:feature_code":"PPL",
    "gn:name":"M\u1ef9 Thu\u1eadn Hai",
    "gn:population":0,
    "gn:timezone":"Asia/Ho_Chi_Minh",
    "iso:country":"VN",
    "name:und_x_variant":[
        "\u1ea4p M\u1ef9 Thu\u1eadn"
    ],
    "name:vie_x_preferred":[
        "M\u1ef9 Thu\u1eadn Hai"
    ],
    "name:vie_x_variant":[
        "M\u1ef9 Thu\u1eadn 2"
    ],
    "wof:name":"My Thuan Hai",
    "wof:placetype":"locality"
},
  "geometry": {"coordinates":[105.74869,9.82209],"type":"Point"}
}