{
  "type": "Feature",
  "properties": {
    "gn:admin1_code":"52.0",
    "gn:asciiname":"Bac Pho",
    "gn:country_code":"VN",
    "gn:dem":7,
    "gn:feature_class":"P",
    "gn:feature_code":"PPL",
    "gn:name":"B\u1eafc Ph\u1ed1",
    "gn:population":0,
    "gn:timezone":"Asia/Ho_Chi_Minh",
    "iso:country":"VN",
    "name:vie_x_preferred":[
        "B\u1eafc Ph\u1ed1"
    ],
    "wof:name":"Bac Pho",
    "wof:placetype":"locality"
},
  "geometry": {"coordinates":[105.97534,18.32186],"type":"Point"}
}