{
  "type": "Feature",
  "properties": {
    "gn:admin1_code":"16.0",
    "gn:asciiname":"Dao Lang",
    "gn:country_code":"VN",
    "gn:dem":85,
    "gn:feature_class":"P",
    "gn:feature_code":"PPL",
    "gn:name":"\u0110\u00e0o L\u00e3ng",
    "gn:population":0,
    "gn:timezone":"Asia/Ho_Chi_Minh",
    "iso:country":"VN",
    "name:und_x_variant":[
        "\u0110\u00e8o L\u00e3ng",
        "\u0110\u00e0o L\u00e3ng"
    ],
    "wof:name":"Dao Lang",
    "wof:placetype":"locality"
},
  "geometry": {"coordinates":[105.46666999999999,20.98333],"type":"Point"}
}