{
  "type": "Feature",
  "properties": {
    "gn:admin1_code":"61.0",
    "gn:asciiname":"Phu Hoi",
    "gn:country_code":"VN",
    "gn:dem":1,
    "gn:feature_class":"P",
    "gn:feature_code":"PPL",
    "gn:name":"Ph\u00fa H\u1ed9i",
    "gn:population":0,
    "gn:timezone":"Asia/Ho_Chi_Minh",
    "iso:country":"VN",
    "wof:name":"Phu Hoi",
    "wof:placetype":"locality"
},
  "geometry": {"coordinates":[109.26667,13.55],"type":"Point"}
}