{
  "type": "Feature",
  "properties": {
    "gn:admin1_code":"74.0",
    "gn:asciiname":"Duong Mong",
    "gn:country_code":"VN",
    "gn:dem":36,
    "gn:feature_class":"P",
    "gn:feature_code":"PPL",
    "gn:name":"D\u01b0\u1ee1ng M\u00f4ng",
    "gn:population":0,
    "gn:timezone":"Asia/Ho_Chi_Minh",
    "iso:country":"VN",
    "name:vie_x_preferred":[
        "D\u01b0\u1ee1ng M\u00f4ng"
    ],
    "wof:name":"Duong Mong",
    "wof:placetype":"locality"
},
  "geometry": {"coordinates":[106.00266999999999,21.12526],"type":"Point"}
}