{
  "type": "Feature",
  "properties": {
    "gn:admin1_code":"39.0",
    "gn:asciiname":"Lang Chang",
    "gn:country_code":"VN",
    "gn:dem":357,
    "gn:feature_class":"P",
    "gn:feature_code":"PPL",
    "gn:name":"L\u00e0ng Chang",
    "gn:population":0,
    "gn:timezone":"Asia/Ho_Chi_Minh",
    "iso:country":"VN",
    "name:vie_x_preferred":[
        "L\u00e0ng Chang"
    ],
    "wof:name":"Lang Chang",
    "wof:placetype":"locality"
},
  "geometry": {"coordinates":[106.44492,21.66409],"type":"Point"}
}