{
  "type": "Feature",
  "properties": {
    "gn:admin1_code":"61.0",
    "gn:asciiname":"Lanh Van",
    "gn:country_code":"VN",
    "gn:dem":42,
    "gn:feature_class":"P",
    "gn:feature_code":"PPL",
    "gn:name":"L\u00e3nh V\u00e2n",
    "gn:population":0,
    "gn:timezone":"Asia/Ho_Chi_Minh",
    "iso:country":"VN",
    "name:vie_x_preferred":[
        "L\u00e3nh V\u00e2n"
    ],
    "wof:name":"Lanh Van",
    "wof:placetype":"locality"
},
  "geometry": {"coordinates":[109.03188,13.49142],"type":"Point"}
}