{
  "type": "Feature",
  "properties": {
    "gn:admin1_code":"58.0",
    "gn:asciiname":"Phu Loi",
    "gn:country_code":"VN",
    "gn:dem":134,
    "gn:feature_class":"P",
    "gn:feature_code":"PPL",
    "gn:name":"Ph\u00fa L\u1ee3i",
    "gn:population":0,
    "gn:timezone":"Asia/Ho_Chi_Minh",
    "iso:country":"VN",
    "name:vie_x_preferred":[
        "Ph\u00fa L\u1ee3i"
    ],
    "wof:name":"Phu Loi",
    "wof:placetype":"locality"
},
  "geometry": {"coordinates":[105.5437,19.38888],"type":"Point"}
}