{
  "type": "Feature",
  "properties": {
    "gn:admin1_code":"58.0",
    "gn:asciiname":"Huoi Dun",
    "gn:country_code":"VN",
    "gn:dem":1131,
    "gn:feature_class":"P",
    "gn:feature_code":"PPL",
    "gn:name":"Hu\u1ed3i \u0110un",
    "gn:population":0,
    "gn:timezone":"Asia/Ho_Chi_Minh",
    "iso:country":"VN",
    "name:vie_x_preferred":[
        "Hu\u1ed3i \u0110un"
    ],
    "wof:name":"Huoi Dun",
    "wof:placetype":"locality"
},
  "geometry": {"coordinates":[104.25512999999999,19.52731],"type":"Point"}
}