{
  "type": "Feature",
  "properties": {
    "gn:admin1_code":"93.0",
    "gn:asciiname":"Phuoc Thuan",
    "gn:country_code":"VN",
    "gn:dem":6,
    "gn:feature_class":"P",
    "gn:feature_code":"PPL",
    "gn:name":"Ph\u01b0\u1edbc Thu\u1eadn",
    "gn:population":0,
    "gn:timezone":"Asia/Ho_Chi_Minh",
    "iso:country":"VN",
    "name:nld_x_preferred":[
        "Ph\u01b0\u1edbc Thu\u1eadn"
    ],
    "name:und_x_variant":[
        "Ph\u01b0\u1edbc Thu\u1eadn",
        "\u1ea4p Ph\u01b0\u1edbc Thu\u1eadn"
    ],
    "name:vie_x_preferred":[
        "Ph\u01b0\u1edbc Thu\u1eadn"
    ],
    "wof:name":"Phuoc Thuan",
    "wof:placetype":"locality"
},
  "geometry": {"coordinates":[105.79458,9.92456],"type":"Point"}
}