{
  "type": "Feature",
  "properties": {
    "gn:admin1_code":"44.0",
    "gn:asciiname":"An Thai",
    "gn:country_code":"VN",
    "gn:dem":19,
    "gn:feature_class":"P",
    "gn:feature_code":"PPL",
    "gn:name":"An Thai",
    "gn:population":0,
    "gn:timezone":"Asia/Ho_Chi_Minh",
    "iso:country":"VN",
    "name:vie_x_preferred":[
        "An Thai"
    ],
    "wof:name":"An Thai",
    "wof:placetype":"locality"
},
  "geometry": {"coordinates":[105.36935,21.15883],"type":"Point"}
}