{
  "type": "Feature",
  "properties": {
    "gn:admin1_code":"50.0",
    "gn:asciiname":"Binh Son",
    "gn:country_code":"VN",
    "gn:dem":276,
    "gn:feature_class":"P",
    "gn:feature_code":"PPL",
    "gn:name":"B\u00ecnh S\u01a1n",
    "gn:population":0,
    "gn:timezone":"Asia/Ho_Chi_Minh",
    "iso:country":"VN",
    "name:vie_x_preferred":[
        "B\u00ecnh S\u01a1n"
    ],
    "wof:name":"Binh Son",
    "wof:placetype":"locality"
},
  "geometry": {"coordinates":[105.05242,22.47095],"type":"Point"}
}