{
  "type": "Feature",
  "properties": {
    "gn:admin1_code":"79.0",
    "gn:asciiname":"Thon Quan",
    "gn:country_code":"VN",
    "gn:dem":6,
    "gn:feature_class":"P",
    "gn:feature_code":"PPL",
    "gn:name":"Th\u00f4n Qu\u1ea7n",
    "gn:population":0,
    "gn:timezone":"Asia/Ho_Chi_Minh",
    "iso:country":"VN",
    "name:vie_x_preferred":[
        "Th\u00f4n Qu\u1ea7n"
    ],
    "wof:name":"Thon Quan",
    "wof:placetype":"locality"
},
  "geometry": {"coordinates":[106.18376000000001,20.83475],"type":"Point"}
}