{
  "type": "Feature",
  "properties": {
    "gn:admin1_code":"46.0",
    "gn:asciiname":"Chanh Thang",
    "gn:country_code":"VN",
    "gn:dem":144,
    "gn:feature_class":"P",
    "gn:feature_code":"PPL",
    "gn:name":"Ch\u00e1nh Th\u1eafng",
    "gn:population":0,
    "gn:timezone":"Asia/Ho_Chi_Minh",
    "iso:country":"VN",
    "wof:name":"Chanh Thang",
    "wof:placetype":"locality"
},
  "geometry": {"coordinates":[109.16667,14.06667],"type":"Point"}
}