{
  "type": "Feature",
  "properties": {
    "gn:admin1_code":"39.0",
    "gn:asciiname":"Vang Thuy",
    "gn:country_code":"VN",
    "gn:dem":381,
    "gn:feature_class":"P",
    "gn:feature_code":"PPL",
    "gn:name":"V\u00e0ng Thu\u1ef7",
    "gn:population":0,
    "gn:timezone":"Asia/Ho_Chi_Minh",
    "iso:country":"VN",
    "name:vie_x_preferred":[
        "V\u00e0ng Thu\u1ef7"
    ],
    "wof:name":"Vang Thuy",
    "wof:placetype":"locality"
},
  "geometry": {"coordinates":[106.41898,21.94633],"type":"Point"}
}