{
  "type": "Feature",
  "properties": {
    "gn:admin1_code":"50.0",
    "gn:asciiname":"Thon Luong",
    "gn:country_code":"VN",
    "gn:dem":85,
    "gn:feature_class":"P",
    "gn:feature_code":"PPL",
    "gn:name":"Th\u00f4n Lu\u00f4ng",
    "gn:population":0,
    "gn:timezone":"Asia/Ho_Chi_Minh",
    "iso:country":"VN",
    "name:vie_x_preferred":[
        "Th\u00f4n Lu\u00f4ng"
    ],
    "wof:name":"Thon Luong",
    "wof:placetype":"locality"
},
  "geometry": {"coordinates":[104.98402,22.64168],"type":"Point"}
}