{
  "type": "Feature",
  "properties": {
    "gn:admin1_code":"55.0",
    "gn:asciiname":"Dak Trap",
    "gn:country_code":"VN",
    "gn:dem":922,
    "gn:feature_class":"P",
    "gn:feature_code":"PPL",
    "gn:name":"Dak Trap",
    "gn:population":0,
    "gn:timezone":"Asia/Ho_Chi_Minh",
    "iso:country":"VN",
    "wof:name":"Dak Trap",
    "wof:placetype":"locality"
},
  "geometry": {"coordinates":[107.71666999999999,15.15],"type":"Point"}
}