{
  "type": "Feature",
  "properties": {
    "gn:admin1_code":"71.0",
    "gn:asciiname":"Dong Muoi",
    "gn:country_code":"VN",
    "gn:dem":36,
    "gn:feature_class":"P",
    "gn:feature_code":"PPL",
    "gn:name":"\u0110\u1ed3ng M\u01b0\u1eddi",
    "gn:population":0,
    "gn:timezone":"Asia/Ho_Chi_Minh",
    "iso:country":"VN",
    "name:vie_x_preferred":[
        "\u0110\u1ed3ng M\u01b0\u1eddi"
    ],
    "wof:name":"Dong Muoi",
    "wof:placetype":"locality"
},
  "geometry": {"coordinates":[106.10473,21.50205],"type":"Point"}
}