{
  "type": "Feature",
  "properties": {
    "gn:admin1_code":"83.0",
    "gn:asciiname":"Phu Thinh",
    "gn:country_code":"VN",
    "gn:dem":47,
    "gn:feature_class":"P",
    "gn:feature_code":"PPL",
    "gn:name":"Ph\u00fa Thinh",
    "gn:population":0,
    "gn:timezone":"Asia/Ho_Chi_Minh",
    "iso:country":"VN",
    "name:vie_x_preferred":[
        "Ph\u00fa Thinh"
    ],
    "wof:name":"Phu Thinh",
    "wof:placetype":"locality"
},
  "geometry": {"coordinates":[105.28816,21.43184],"type":"Point"}
}