{
  "type": "Feature",
  "properties": {
    "gn:admin1_code":"64.0",
    "gn:asciiname":"Tan Di",
    "gn:country_code":"VN",
    "gn:dem":316,
    "gn:feature_class":"P",
    "gn:feature_code":"PPL",
    "gn:name":"T\u00e2n \u0110i",
    "gn:population":0,
    "gn:timezone":"Asia/Ho_Chi_Minh",
    "iso:country":"VN",
    "name:vie_x_preferred":[
        "T\u00e2n \u0110i"
    ],
    "wof:name":"Tan Di",
    "wof:placetype":"locality"
},
  "geometry": {"coordinates":[106.94926,16.39231],"type":"Point"}
}