{
  "type": "Feature",
  "properties": {
    "gn:admin1_code":"49.0",
    "gn:asciiname":"GJak Ru",
    "gn:country_code":"VN",
    "gn:dem":540,
    "gn:feature_class":"P",
    "gn:feature_code":"PPL",
    "gn:name":"\u0110\u1eafk Ru",
    "gn:population":0,
    "gn:timezone":"Asia/Ho_Chi_Minh",
    "iso:country":"VN",
    "wof:name":"GJak Ru",
    "wof:placetype":"locality"
},
  "geometry": {"coordinates":[107.40115,11.91697],"type":"Point"}
}