{
  "type": "Feature",
  "properties": {
    "iso:country":"VN",
    "ne:ADM0CAP":0.0,
    "ne:ADM0NAME":"Vietnam",
    "ne:ADM0_A3":"VNM",
    "ne:ADM1NAME":"BNnh Phu?c",
    "ne:ADMIN1_COD":0,
    "ne:CAPALT":0,
    "ne:CHANGED":4,
    "ne:CHECKME":0,
    "ne:COMPARE":0,
    "ne:DIFFASCII":0,
    "ne:DIFFNOTE":"Changed scale rank.",
    "ne:ELEVATION":0.0,
    "ne:FEATURECLA":"Populated place",
    "ne:GEONAMEID":-1,
    "ne:GEONAMESNO":"No GeoNames match due to small population, not in GeoNames, or poor NEV placement.",
    "ne:GN_POP":0,
    "ne:GTOPO30":0.0,
    "ne:ISO_A2":"VN",
    "ne:LABELRANK":5,
    "ne:LATITUDE":11.650386,
    "ne:LONGITUDE":106.600046,
    "ne:LS_MATCH":1,
    "ne:LS_NAME":"Hon Quan",
    "ne:MAX_AREAKM":10.0,
    "ne:MAX_AREAMI":4.0,
    "ne:MAX_BBXMAX":106.633333,
    "ne:MAX_BBXMIN":106.591667,
    "ne:MAX_BBYMAX":11.666667,
    "ne:MAX_BBYMIN":11.633333,
    "ne:MAX_NATSCA":10.0,
    "ne:MAX_PERKM":17.0,
    "ne:MAX_PERMI":10.0,
    "ne:MAX_POP10":40279,
    "ne:MAX_POP20":0,
    "ne:MAX_POP300":0,
    "ne:MAX_POP310":0,
    "ne:MAX_POP50":0,
    "ne:MEAN_BBXC":106.611806,
    "ne:MEAN_BBYC":11.647917,
    "ne:MEGACITY":0,
    "ne:MIN_AREAKM":10.0,
    "ne:MIN_AREAMI":4.0,
    "ne:MIN_BBXMAX":106.633333,
    "ne:MIN_BBXMIN":106.591667,
    "ne:MIN_BBYMAX":11.666667,
    "ne:MIN_BBYMIN":11.633333,
    "ne:MIN_PERKM":17.0,
    "ne:MIN_PERMI":10.0,
    "ne:NAME":"Hon Quan",
    "ne:NAMEASCII":"Hon Quan",
    "ne:NAMEDIFF":0,
    "ne:NATSCALE":20,
    "ne:POP1950":0,
    "ne:POP1955":0,
    "ne:POP1960":0,
    "ne:POP1965":0,
    "ne:POP1970":0,
    "ne:POP1975":0,
    "ne:POP1980":0,
    "ne:POP1985":0,
    "ne:POP1990":0,
    "ne:POP1995":0,
    "ne:POP2000":0,
    "ne:POP2005":0,
    "ne:POP2010":0,
    "ne:POP2015":0,
    "ne:POP2020":0,
    "ne:POP2025":0,
    "ne:POP2050":0,
    "ne:POP_MAX":40279,
    "ne:POP_MIN":40279,
    "ne:POP_OTHER":40279,
    "ne:RANK_MAX":7,
    "ne:RANK_MIN":7,
    "ne:SCALERANK":7,
    "ne:SOV0NAME":"Vietnam",
    "ne:SOV_A3":"VNM",
    "ne:UN_FID":0,
    "ne:UN_LAT":0.0,
    "ne:UN_LONG":0.0,
    "ne:WORLDCITY":0,
    "ne:min_zoom":6.7,
    "wof:name":"Hon Quan",
    "wof:placetype":"locality"
},
  "geometry": {"coordinates":[106.60004593813932,11.65038576145633],"type":"Point"}
}