{
  "type": "Feature",
  "properties": {
    "gn:admin1_code":"39.0",
    "gn:asciiname":"Ro Rieng",
    "gn:country_code":"VN",
    "gn:dem":271,
    "gn:feature_class":"P",
    "gn:feature_code":"PPL",
    "gn:name":"R\u1ecd Ri\u1ec1ng",
    "gn:population":0,
    "gn:timezone":"Asia/Ho_Chi_Minh",
    "iso:country":"VN",
    "name:vie_x_preferred":[
        "R\u1ecd Ri\u1ec1ng"
    ],
    "wof:name":"Ro Rieng",
    "wof:placetype":"locality"
},
  "geometry": {"coordinates":[106.22235999999999,21.9307],"type":"Point"}
}