{
  "type": "Feature",
  "properties": {
    "gn:admin1_code":"90.0",
    "gn:asciiname":"Ly Ta",
    "gn:country_code":"VN",
    "gn:dem":457,
    "gn:feature_class":"P",
    "gn:feature_code":"PPL",
    "gn:name":"Ly Ta",
    "gn:population":0,
    "gn:timezone":"Asia/Ho_Chi_Minh",
    "iso:country":"VN",
    "wof:name":"Ly Ta",
    "wof:placetype":"locality"
},
  "geometry": {"coordinates":[103.84999999999999,22.45],"type":"Point"}
}