{
  "type": "Feature",
  "properties": {
    "gn:admin1_code":"72.0",
    "gn:asciiname":"Ban Chang",
    "gn:country_code":"VN",
    "gn:dem":119,
    "gn:feature_class":"P",
    "gn:feature_code":"PPL",
    "gn:name":"B\u1ea3n Chang",
    "gn:population":0,
    "gn:timezone":"Asia/Ho_Chi_Minh",
    "iso:country":"VN",
    "name:ceb_x_preferred":[
        "Ban Chang"
    ],
    "name:vie_x_preferred":[
        "B\u1ea3n Chang"
    ],
    "wof:name":"Ban Chang",
    "wof:placetype":"locality"
},
  "geometry": {"coordinates":[105.84282,22.04903],"type":"Point"}
}