{
  "type": "Feature",
  "properties": {
    "gn:admin1_code":"9.0",
    "gn:asciiname":"Sa Rai",
    "gn:country_code":"VN",
    "gn:dem":6,
    "gn:feature_class":"P",
    "gn:feature_code":"PPLA2",
    "gn:name":"Sa R\u00e0i",
    "gn:population":0,
    "gn:timezone":"Asia/Ho_Chi_Minh",
    "iso:country":"VN",
    "name:vie_x_preferred":[
        "Sa R\u00e0i"
    ],
    "wof:name":"Sa Rai",
    "wof:placetype":"locality"
},
  "geometry": {"coordinates":[105.46583,10.87016],"type":"Point"}
}