{
  "type": "Feature",
  "properties": {
    "gn:admin1_code":"39.0",
    "gn:asciiname":"Khon Sao",
    "gn:country_code":"VN",
    "gn:dem":228,
    "gn:feature_class":"P",
    "gn:feature_code":"PPL",
    "gn:name":"Kh\u00f2n Sao",
    "gn:population":0,
    "gn:timezone":"Asia/Ho_Chi_Minh",
    "iso:country":"VN",
    "name:und_x_variant":[
        "Kh\u00f2n Sao",
        "Khon Sao"
    ],
    "wof:name":"Khon Sao",
    "wof:placetype":"locality"
},
  "geometry": {"coordinates":[106.55773000000001,22.09096],"type":"Point"}
}