{
  "type": "Feature",
  "properties": {
    "gn:admin1_code":"72.0",
    "gn:asciiname":"Nam Pen",
    "gn:country_code":"VN",
    "gn:dem":794,
    "gn:feature_class":"P",
    "gn:feature_code":"PPL",
    "gn:name":"N\u1eb7m P\u1ebbn",
    "gn:population":0,
    "gn:timezone":"Asia/Ho_Chi_Minh",
    "iso:country":"VN",
    "wof:name":"Nam Pen",
    "wof:placetype":"locality"
},
  "geometry": {"coordinates":[105.86445999999999,22.48966],"type":"Point"}
}