{
  "type": "Feature",
  "properties": {
    "gn:admin1_code":"88.0",
    "gn:asciiname":"Buon Cham A",
    "gn:country_code":"VN",
    "gn:dem":465,
    "gn:feature_class":"P",
    "gn:feature_code":"PPL",
    "gn:name":"Bu\u00f4n Ch\u1ea3m A",
    "gn:population":0,
    "gn:timezone":"Asia/Ho_Chi_Minh",
    "iso:country":"VN",
    "name:und_x_variant":[
        "Ban Tiam",
        "Bu\u00f4n Tiam"
    ],
    "name:vie_x_preferred":[
        "Bu\u00f4n Ch\u1ea3m A"
    ],
    "wof:name":"Buon Cham A",
    "wof:placetype":"locality"
},
  "geometry": {"coordinates":[108.56001000000001,12.48645],"type":"Point"}
}