{
  "type": "Feature",
  "properties": {
    "gn:admin1_code":"85.0",
    "gn:asciiname":"Na Hang",
    "gn:country_code":"VN",
    "gn:dem":121,
    "gn:feature_class":"P",
    "gn:feature_code":"PPL",
    "gn:name":"Na Hang",
    "gn:population":0,
    "gn:timezone":"Asia/Ho_Chi_Minh",
    "iso:country":"VN",
    "name:vie_x_preferred":[
        "Na Hang"
    ],
    "wof:name":"Na Hang",
    "wof:placetype":"locality"
},
  "geometry": {"coordinates":[105.59639,21.58951],"type":"Point"}
}