{
  "type": "Feature",
  "properties": {
    "gn:admin1_code":"23.0",
    "gn:asciiname":"Bon Tiang Wir",
    "gn:cc2":"VN",
    "gn:country_code":"VN",
    "gn:dem":656,
    "gn:feature_class":"P",
    "gn:feature_code":"PPL",
    "gn:name":"Bon Tiang Wir",
    "gn:population":0,
    "gn:timezone":"Asia/Ho_Chi_Minh",
    "iso:country":"VN",
    "name:und_x_variant":[
        "Bon Tchieum Houiih",
        "Ban Tchieum Houiih",
        "Bon Tiang Wir"
    ],
    "wof:name":"Bon Tiang Wir",
    "wof:placetype":"locality"
},
  "geometry": {"coordinates":[108.33333,12.25],"type":"Point"}
}