{
  "type": "Feature",
  "properties": {
    "gn:admin1_code":"58.0",
    "gn:asciiname":"Ban Tong",
    "gn:country_code":"VN",
    "gn:dem":440,
    "gn:feature_class":"P",
    "gn:feature_code":"PPL",
    "gn:name":"B\u1ea3n T\u00f3ng",
    "gn:population":0,
    "gn:timezone":"Asia/Ho_Chi_Minh",
    "iso:country":"VN",
    "name:vie_x_preferred":[
        "B\u1ea3n T\u00f3ng"
    ],
    "wof:name":"Ban Tong",
    "wof:placetype":"locality"
},
  "geometry": {"coordinates":[104.83351999999999,19.62807],"type":"Point"}
}