{
  "type": "Feature",
  "properties": {
    "gn:admin1_code":"70.0",
    "gn:asciiname":"Doi Bay",
    "gn:country_code":"VN",
    "gn:dem":58,
    "gn:feature_class":"P",
    "gn:feature_code":"PPL",
    "gn:name":"\u0110\u1ed9i B\u1ea3y",
    "gn:population":0,
    "gn:timezone":"Asia/Ho_Chi_Minh",
    "iso:country":"VN",
    "name:vie_x_preferred":[
        "\u0110\u1ed9i B\u1ea3y"
    ],
    "name:vie_x_variant":[
        "\u0110\u1ed9i 7"
    ],
    "wof:name":"Doi Bay",
    "wof:placetype":"locality"
},
  "geometry": {"coordinates":[104.67195,21.89178],"type":"Point"}
}