{
  "type": "Feature",
  "properties": {
    "gn:admin1_code":"45.0",
    "gn:asciiname":"Nam Binh",
    "gn:country_code":"VN",
    "gn:dem":8,
    "gn:feature_class":"P",
    "gn:feature_code":"PPL",
    "gn:name":"Nam B\u00ecnh",
    "gn:population":0,
    "gn:timezone":"Asia/Ho_Chi_Minh",
    "iso:country":"VN",
    "name:vie_x_preferred":[
        "Nam B\u00ecnh"
    ],
    "wof:name":"Nam Binh",
    "wof:placetype":"locality"
},
  "geometry": {"coordinates":[107.1618,10.41643],"type":"Point"}
}