{
  "type": "Feature",
  "properties": {
    "gn:admin1_code":"5.0",
    "gn:asciiname":"Lang Oan",
    "gn:country_code":"VN",
    "gn:dem":345,
    "gn:feature_class":"P",
    "gn:feature_code":"PPL",
    "gn:name":"L\u00e0ng Oan",
    "gn:population":0,
    "gn:timezone":"Asia/Ho_Chi_Minh",
    "iso:country":"VN",
    "wof:name":"Lang Oan",
    "wof:placetype":"locality"
},
  "geometry": {"coordinates":[106.03333000000001,22.71667],"type":"Point"}
}