{
  "type": "Feature",
  "properties": {
    "gn:admin1_code":"78.0",
    "gn:asciiname":"Khu Pho Tan Thai",
    "gn:country_code":"VN",
    "gn:dem":3,
    "gn:feature_class":"P",
    "gn:feature_code":"PPL",
    "gn:name":"Khu Ph\u1ed1 T\u00e2n Th\u00e1i",
    "gn:population":0,
    "gn:timezone":"Asia/Ho_Chi_Minh",
    "iso:country":"VN",
    "name:und_x_variant":[
        "Phong T\u00e2n Th\u00e1i",
        "Khu Ph\u1ed1 T\u00e2n Th\u00e1i"
    ],
    "wof:name":"Khu Pho Tan Thai",
    "wof:placetype":"locality"
},
  "geometry": {"coordinates":[108.24944000000001,16.08694],"type":"Point"}
}