{
  "type": "Feature",
  "properties": {
    "gn:admin1_code":"13.0",
    "gn:asciiname":"Thiem Khe",
    "gn:country_code":"VN",
    "gn:dem":10,
    "gn:feature_class":"P",
    "gn:feature_code":"PPL",
    "gn:name":"Thi\u00eam Kh\u00ea",
    "gn:population":0,
    "gn:timezone":"Asia/Ho_Chi_Minh",
    "iso:country":"VN",
    "name:vie_x_preferred":[
        "Thi\u00eam Kh\u00ea"
    ],
    "wof:name":"Thiem Khe",
    "wof:placetype":"locality"
},
  "geometry": {"coordinates":[106.63797,20.99303],"type":"Point"}
}